{"2010":"","2016":"","Department":"Харківський окружний адміністративний суд","Region":"Харківська область","Position":"Суддя Харківського окружного адміністративного суду","Name":"Біленський Олег Олексійович","Link":"https://drive.google.com/open?id=0BygiyWAl79DMUWtmSVZMYmRvRXM","Note":"У меня","AdditionalNote":"","field8":"","field9":"","field10":"","Кількість справ":"","Оскаржені":"","Кількість скарг":2,"Кількість дисциплінарних стягнень":"","Клейма":"","Фото":"","Як живе":"","key":"bilenskiy_oleg_oleksiyovich","allDeclarations":[{"provider":"declarations.com.ua","document":{"income":{"5":{"family_comment":"","family_unclear":false,"value":"159831.26","family":"24275.76","comment":""},"6":{"value":"159831.26","family_comment":"","value_unclear":false,"family_unclear":false,"family":"12493.48","comment":""},"7":{"source_name_unclear":false,"value":"","family_comment":"","source_name":"","family":"","comment":"","source_name_hidden":false},"8":{"family_comment":"","value":"","family":"","comment":""},"9":{"family_comment":"","family_unclear":false,"value":"","family":"","comment":""},"10":{"family_comment":"","value":"","family":"","comment":""},"11":{"family_comment":"","value":"","family":"","comment":""},"12":{"family_comment":"","value":"","family":"","comment":""},"13":{"family_comment":"","value":"","family":"","comment":""},"14":{"family_comment":"","value":"","family":"","comment":""},"15":{"family_comment":"","value":"","family":"","comment":""},"16":{"family_comment":"","family_unclear":false,"value":"","family":"","comment":""},"17":{"family_comment":"","family_unclear":false,"value":"","family":"","comment":""},"18":{"family_comment":"","value":"","family":"","comment":""},"19":{"family_comment":"","value":"","family":"","comment":""},"20":{"family_comment":"","value":"","comment_unclear":false,"family":"11782.28","comment":""}},"vehicle":{"35":[{"brand_info":"1781 куб. см. 438 см","sum":"","brand":"Volkswagen Vento","sum_comment":"","brand_unclear":false,"year":"1994","brand_hidden":false,"brand_info_hidden":false,"brand_info_unclear":true,"sum_rent_comment":"","sum_rent":""}],"36":[{"brand_info":"55.2 кВт 436 см","sum_rent_comment":"","brand":"УАЗ 452 Д","sum_comment":"","brand_unclear":true,"year":"1978","sum":"","sum_rent":""}],"40":[{"brand_info":"1997 куб. см.","sum":"","brand":"Mitsubishi Outlander","sum_comment":"","brand_unclear":false,"year":"2003","brand_hidden":false,"brand_info_hidden":false,"brand_info_unclear":false,"sum_rent_comment":"","sum_rent":""}]},"id":"vulyk_95_27","declaration":{"additional_info_text":"","notfull_lostpages":"","date":"2016-03-14T00:00:00","notfull":"","additional_info":"","url":"http://static.declarations.com.ua/declarations/chosen_ones/judges_batch/28_bilenskyi_oleh_oleksiiovych.pdf"},"liabilities":{"54":{"sum_foreign_comment":"","sum":"","sum_comment":"","sum_hidden":false,"sum_comment_hidden":false,"sum_unclear":false,"sum_foreign":""},"55":{"sum_foreign_comment":"","sum":"","sum_comment":"","sum_foreign":""},"56":{"sum_foreign_comment":"","sum":"","sum_comment":"","sum_foreign":""},"57":{"sum_foreign_comment":"","sum":"","sum_comment":"","sum_hidden":false,"sum_comment_hidden":false,"sum_unclear":false,"sum_foreign":""},"58":{"sum_foreign_comment":"","sum":"","sum_comment":"","sum_hidden":false,"sum_comment_hidden":false,"sum_unclear":false,"sum_foreign":""},"59":{"sum_foreign_comment":"","sum":"","sum_comment":"","sum_foreign":""},"60":{"sum_foreign_comment":"","sum":"","sum_comment":"","sum_hidden":false,"sum_comment_hidden":false,"sum_foreign":""},"61":{"sum_foreign_comment":"","sum":"","sum_comment":"","sum_foreign":""},"62":{"sum_foreign_comment":"","sum":"","sum_comment":"","sum_unclear":false,"sum_foreign":""},"63":{"sum_foreign_comment":"","sum":"","sum_comment":"","sum_unclear":false,"sum_foreign":""},"64":{"sum_foreign_comment":"","sum":"","sum_comment":"","sum_foreign":""}},"ft_src":"Південне\nХарківська область\nБіленський Олег Олексійович\nсуддя харківського окружного адміністративного суду\nХарківська область\nАдміністративний місцевий суд\nОлег\nКононова Юлія В'ячеславівна\nПодружжя\nБіленська Єлизавета Олегівна\nДитина\nБіленська Евеліна Олегівна\nДитина\nБіленський Олег Олексійович\nОлег Олексійович Біленський\nОлег Біленський\nБіленський Олег Олексійович\nБіленський\nОлексійович\n1978\n55.2 кВт 436 см\nУАЗ 452 Д\nVolkswagen Vento\n1781 куб. см. 438 см\n1994\nMitsubishi Outlander\n1997 куб. см.\n2003\nм. Південне\n1554\nХарківська область\n45.65\nХарківська область\nХарківська область\nм. Харків\n68.7\nХарківська область\nм. Харків\n66.4\nХарківська область\nХарківська область\nм. Південне\n41.3\nХарківська область\nм. Південне\n45.65\n2015\n12493.48\n159831.26\n24275.76\n159831.26\n11782.28\nVolkswagen Vento\n1781 куб. см. 438 см\n1994\nMitsubishi Outlander\n1997 куб. см.\n2003\n55.2 кВт 436 см\nУАЗ 452 Д\n1978\n1554\nм. Південне\nХарківська область\n45.65\nХарківська область\n41.3\nм. Південне\nХарківська область\n45.65\nм. Південне\nХарківська область\nм. Харків\nХарківська область\n68.7\nм. Харків\nХарківська область\n66.4\nХарківська область\nОлексійович\nПодружжя\nКононова Юлія В'ячеславівна\nДитина\nБіленська Єлизавета Олегівна\nДитина\nБіленська Евеліна Олегівна\nБіленський Олег Олексійович\nОлег Олексійович Біленський\nОлег Біленський\nБіленський Олег Олексійович\nОлег\nПівденне\nХарківська область\nБіленський Олег Олексійович\nБіленський\nАдміністративний місцевий суд\nсуддя харківського окружного адміністративного суду\nХарківська область\n159831.26\n12493.48\n11782.28\n159831.26\n24275.76\n2015\nКононова Юлія В'ячеславівна\nПодружжя\nБіленська Єлизавета Олегівна\nДитина\nБіленська Евеліна Олегівна\nДитина\nХарківська область\nПівденне\nОлексійович\nБіленський\nХарківська область\nАдміністративний місцевий суд\nсуддя харківського окружного адміністративного суду\nБіленський Олег Олексійович\nБіленський Олег Олексійович\nОлег Олексійович Біленський\nОлег Біленський\nБіленський Олег Олексійович\nОлег\nMitsubishi Outlander\n1997 куб. см.\n2003\nVolkswagen Vento\n1781 куб. см. 438 см\n1994\n1978\n55.2 кВт 436 см\nУАЗ 452 Д\n11782.28\n24275.76\n159831.26\n159831.26\n12493.48\nм. Харків\nХарківська область\n68.7\nм. Харків\nХарківська область\n66.4\nм. Південне\nХарківська область\n1554\nХарківська область\n45.65\nм. Південне\nХарківська область\n41.3\nм. Південне\nХарківська область\n45.65\nХарківська область\n2015","general":{"inn":"","inn_hidden":true,"last_name":"Біленський","post":{"post":"суддя харківського окружного адміністративного суду","region":"Харківська область","candidate":"","office_hidden":false,"office":"Адміністративний місцевий суд","office_unclear":false},"name":"Олег","full_name":"Біленський Олег Олексійович","family_raw":"","addresses":[{"place_address":"","place_district_hidden":false,"place_city_type":"","place_city_hidden":false,"place_address_unclear":false,"place_city_type_hidden":false,"place_city":"Південне","place":"Харківська область","place_district":"","place_address_hidden":false,"place_hidden":true,"place_city_unclear":true}],"family":[{"inn":"","inn_hidden":true,"inn_unclear":false,"relations_hidden":false,"relations_other":"","relations":"Подружжя","name_hidden":false,"family_name":"Кононова Юлія В'ячеславівна","name_unclear":true},{"inn":"","inn_hidden":false,"inn_unclear":false,"relations_hidden":false,"relations_other":"","relations":"Дитина","name_hidden":false,"family_name":"Біленська Єлизавета Олегівна","name_unclear":false},{"inn":"","inn_hidden":false,"inn_unclear":false,"relations_hidden":false,"relations_other":"","relations":"Дитина","name_hidden":false,"family_name":"Біленська Евеліна Олегівна","name_unclear":false}],"full_name_suggest":{"output":"Біленський Олег Олексійович","input":["Біленський Олег Олексійович","Олег Олексійович Біленський","Олег Біленський"]},"patronymic":"Олексійович"},"source":"VULYK","estate":{"23":[{"region_unclear":false,"space_unclear":false,"costs":"","costs_comment":"","address_hidden":true,"region_hidden":false,"space_comment":"","space":"1554","address":"м. Південне","region":"Харківська область","address_unclear":true,"costs_rent_comment":"","costs_comment_hidden":false,"space_units":"м²","costs_rent":""},{"costs":"","costs_comment":"","address_hidden":false,"region_hidden":false,"space_units_unclear":false,"space":"45.65","address":"","region":"Харківська область","costs_rent_comment":"","space_units":"м²","space_units_hidden":false,"space_comment":"","costs_rent":""}],"24":[{"costs":"","costs_comment":"","address_hidden":true,"region_hidden":false,"space_comment":"","space":"41.3","address":"м. Південне","region":"Харківська область","address_unclear":true,"costs_rent_comment":"","space_units":"м²","costs_rent":""},{"costs":"","costs_comment":"","address_hidden":false,"region_hidden":false,"space_comment":"","space":"45.65","address":"м. Південне","region":"Харківська область","address_unclear":true,"costs_rent_comment":"","space_units":"м²","costs_rent":""}],"31":[{"space_unclear":false,"address_hidden":true,"region_hidden":false,"space_comment":"","space":"68.7","address":"м. Харків","region":"Харківська область","costs_property":"","costs_rent_comment":"","space_comment_unclear":false,"space_units":"м²","costs_property_comment":"","costs_rent":""},{"address_hidden":false,"region_hidden":false,"space_comment":"","space":"66.4","address":"м. Харків","region":"Харківська область","costs_property":"","costs_rent_comment":"","space_comment_unclear":false,"space_units":"м²","costs_property_comment":"","costs_rent":""}],"32":[{"address_hidden":false,"region_hidden":false,"space_comment":"","space":"","address":"","region":"Харківська область","costs_property":"","costs_rent_comment":"","address_unclear":false,"space_units":"м²","costs_property_comment":"","costs_rent":""}]},"intro":{"declaration_year":"2015","isnotdeclaration":""}}},{"provider":"declarations.com.ua","document":{"income":{"5":{"family_comment":"","value":"206049","family":"14345","comment":""},"6":{"value":"206014","family_comment":"","value_unclear":false,"comment_hidden":false,"family_unclear":false,"family":"10908","comment":""},"7":{"family_comment":"","value":"","source_name":"","family":"","comment":""},"8":{"family_comment":"","value":"","family":"","comment":""},"9":{"family_comment":"","family_unclear":false,"value":"","family":"","comment":""},"10":{"family_comment":"","value":"","value_unclear":false,"family":"","comment":""},"11":{"family_comment":"","value":"35","family":"","comment":""},"12":{"family_comment":"","value":"","family":"","comment":""},"13":{"family_comment":"","value":"","family":"","comment":""},"14":{"family_comment":"","value":"","family":"","comment":""},"15":{"family_comment":"","value":"","family":"","comment":""},"16":{"family_comment":"","value":"","family":"","comment":""},"17":{"family_comment":"","value":"","family":"","comment":""},"18":{"family_comment":"","value":"","family":"","comment":""},"19":{"family_comment":"","value":"","family":"","comment":""},"20":{"value":"","family":"3437","value_unclear":false,"family_hidden":false,"family_comment":"","comment_unclear":false,"comment":"","family_comment_unclear":false}},"vehicle":{"35":[{"year_hidden":false,"brand_info":"1781 куб. см., 438 см","sum_rent_comment":"","year":"1994","brand_info_hidden":false,"brand_info_unclear":false,"sum_rent":"","sum":"","brand":"Volkswagen Vento","sum_comment":"","brand_unclear":false,"brand_hidden":false}],"36":[{"brand_info":"2440 куб. см., 55.2 кВт , 436 см","sum_rent_comment":"","brand":"УАЗ 452 Д","sum_comment":"","year":"1978","brand_info_unclear":true,"sum":"","sum_rent":""}],"40":[{"brand_info":"1997 куб. см., 454.5 см","sum_rent_comment":"","brand":"Mitsubishi Outlander","sum_comment":"","brand_unclear":false,"year":"2003","brand_info_unclear":false,"year_unclear":false,"sum":"","sum_rent":""}]},"id":"vulyk_97_99","declaration":{"additional_info_text":"","notfull_lostpages":"","date":"2015-03-24T00:00:00","notfull":"","additional_info":"","url":"http://static.declarations.com.ua/declarations/chosen_ones/judges_batch/4000_bilenskyi_oleh_oleksiiovych.pdf"},"liabilities":{"54":{"sum_foreign_comment":"","sum":"","sum_comment":"","sum_comment_unclear":false,"sum_hidden":false,"sum_comment_hidden":false,"sum_unclear":false,"sum_foreign":""},"55":{"sum_foreign_comment":"","sum":"","sum_comment":"","sum_foreign":""},"56":{"sum_foreign_comment":"","sum":"","sum_comment":"","sum_foreign":""},"57":{"sum_foreign_comment":"","sum":"","sum_comment":"","sum_comment_unclear":false,"sum_hidden":false,"sum_comment_hidden":false,"sum_unclear":false,"sum_foreign":""},"58":{"sum_foreign_comment":"","sum":"","sum_comment":"","sum_comment_unclear":false,"sum_hidden":false,"sum_comment_hidden":false,"sum_unclear":false,"sum_foreign":""},"59":{"sum_foreign_comment":"","sum":"","sum_comment":"","sum_foreign":""},"60":{"sum_foreign_comment":"","sum":"","sum_comment":"","sum_comment_unclear":false,"sum_hidden":false,"sum_comment_hidden":false,"sum_foreign":""},"61":{"sum_foreign_comment":"","sum":"","sum_comment":"","sum_foreign":""},"62":{"sum_foreign_comment":"","sum":"","sum_comment":"","sum_unclear":false,"sum_foreign":""},"63":{"sum_foreign_comment":"","sum":"","sum_hidden":false,"sum_comment":"","sum_foreign":""},"64":{"sum_foreign_comment":"","sum":"","sum_comment":"","sum_foreign":""}},"ft_src":"Південне\nХарківський\nХарківська область\nсуддя харківського окружного адміністративного суду\nХарківська область\nАдміністративний місцевий суд\nОлег\nКононова Юлія Вячеславівна\nПодружжя\nБіленська Єлізавета Олегівна\nДитина\nБіленська Евеліна Олегівна\nДитина\nОлексійович\nБіленський Олег Олексійович\nОлег Олексійович Біленський\nОлег Біленський\nБіленський Олег Олексійович\nБіленський Олег Олексійович\nБіленський\n2440 куб. см., 55.2 кВт , 436 см\n1978\nУАЗ 452 Д\n1781 куб. см., 438 см\nVolkswagen Vento\n1994\nMitsubishi Outlander\n1997 куб. см., 454.5 см\n2003\nХарківський р-н, м. Південне\n1554\nХарківська область\nХарківський р-н, м. Південне\n45.65\nХарківська область\n68.7\nХарківська область\nм. Харків\nХарківська область\nм. Харків\n66.4\nХарківський р-н, м. Південне\n41.3\nХарківська область\nХарківська область\nХарківський р-н, м. Південне\n45.65\n2014\n10908\n206014\n35\n14345\n206049\n3437\n1781 куб. см., 438 см\nVolkswagen Vento\n1994\n1997 куб. см., 454.5 см\nMitsubishi Outlander\n2003\n2440 куб. см., 55.2 кВт , 436 см\n1978\nУАЗ 452 Д\n2014\nБіленський Олег Олексійович\nОлег Олексійович Біленський\nОлег Біленський\nБіленський Олег Олексійович\nОлег\nПодружжя\nКононова Юлія Вячеславівна\nДитина\nБіленська Єлізавета Олегівна\nДитина\nБіленська Евеліна Олегівна\nБіленський Олег Олексійович\nБіленський\nАдміністративний місцевий суд\nХарківська область\nсуддя харківського окружного адміністративного суду\nОлексійович\nХарківська область\nПівденне\nХарківський\n206014\n10908\n3437\n206049\n14345\n35\n1554\nХарківський р-н, м. Південне\nХарківська область\n45.65\nХарківський р-н, м. Південне\nХарківська область\n41.3\nХарківська область\nХарківський р-н, м. Південне\n45.65\nХарківська область\nХарківський р-н, м. Південне\n68.7\nХарківська область\nм. Харків\n66.4\nХарківська область\nм. Харків\nПодружжя\nКононова Юлія Вячеславівна\nБіленська Єлізавета Олегівна\nДитина\nДитина\nБіленська Евеліна Олегівна\nОлексійович\nБіленський\nОлег\nБіленський Олег Олексійович\nОлег Олексійович Біленський\nОлег Біленський\nБіленський Олег Олексійович\nПівденне\nХарківська область\nХарківський\nХарківська область\nАдміністративний місцевий суд\nсуддя харківського окружного адміністративного суду\nБіленський Олег Олексійович\n2003\n1997 куб. см., 454.5 см\nMitsubishi Outlander\n1994\nVolkswagen Vento\n1781 куб. см., 438 см\n1978\n2440 куб. см., 55.2 кВт , 436 см\nУАЗ 452 Д\n35\n3437\n14345\n206049\n206014\n10908\nм. Харків\nХарківська область\n68.7\nм. Харків\nХарківська область\n66.4\nХарківський р-н, м. Південне\nХарківська область\n1554\nХарківський р-н, м. Південне\nХарківська область\n45.65\nХарківський р-н, м. Південне\nХарківська область\n41.3\nХарківський р-н, м. Південне\nХарківська область\n45.65\n2014","general":{"name_hidden":false,"name":"Олег","last_name_hidden":false,"inn":"","family":[{"inn":"","relations":"Подружжя","relations_other":"","inn_hidden":true,"family_name":"Кононова Юлія Вячеславівна","name_hidden":false,"name_unclear":false},{"inn_hidden":false,"inn":"","name_hidden":false,"family_name":"Біленська Єлізавета Олегівна","relations":"Дитина","name_unclear":false},{"inn":"","relations":"Дитина","relations_other":"","inn_hidden":false,"family_name":"Біленська Евеліна Олегівна","name_hidden":false,"name_unclear":false}],"patronymic":"Олексійович","inn_hidden":true,"family_raw":"","inn_unclear":false,"post":{"region_unclear":false,"region":"Харківська область","post":"суддя харківського окружного адміністративного суду","office":"Адміністративний місцевий суд","office_unclear":false,"post_hidden":false},"full_name":"Біленський Олег Олексійович","addresses":[{"place_district":"Харківський","place_city_hidden":false,"place_city":"Південне","place_city_unclear":false,"place_district_hidden":false,"place_city_type":"Місто","place_address_hidden":true,"place_city_type_hidden":false,"place_address":"","place_hidden":false,"place":"Харківська область"}],"last_name":"Біленський","patronymic_hidden":false,"full_name_suggest":{"output":"Біленський Олег Олексійович","input":["Біленський Олег Олексійович","Олег Олексійович Біленський","Олег Біленський"]}},"source":"VULYK","estate":{"23":[{"region_unclear":false,"space_unclear":false,"costs":"","costs_rent_unclear":false,"costs_comment":"","address_hidden":false,"region_hidden":false,"space_comment":"","space":"1554","address":"Харківський р-н, м. Південне","region":"Харківська область","address_unclear":false,"costs_rent_comment":"","space_units":"м²","costs_rent":""},{"region_unclear":false,"costs":"","costs_rent_unclear":false,"costs_comment":"","region_hidden":false,"space_comment":"","space":"45.65","address":"Харківський р-н, м. Південне","region":"Харківська область","address_unclear":false,"costs_rent_comment":"","space_units":"м²","costs_rent":""}],"24":[{"region_unclear":false,"space_unclear":false,"costs":"","costs_comment":"","address_hidden":false,"region_hidden":false,"space_comment":"","space_hidden":false,"space":"41.3","address":"Харківський р-н, м. Південне","region":"Харківська область","address_unclear":false,"costs_rent_comment":"","space_comment_unclear":false,"space_units":"м²","costs_rent":""},{"costs_rent":"","space_unclear":false,"region":"Харківська область","costs":"","costs_rent_comment":"","costs_comment":"","region_hidden":false,"space_comment":"","space_units":"м²","space":"45.65","address":"Харківський р-н, м. Південне"}],"31":[{"space_unclear":false,"address_hidden":false,"region_hidden":false,"space_comment":"","space_hidden":false,"space":"68.7","address":"м. Харків","region":"Харківська область","costs_property":"","costs_rent_comment":"","space_comment_hidden":false,"space_units":"м²","costs_property_comment":"","costs_rent":""},{"costs_rent":"","region":"Харківська область","costs_property":"","costs_rent_comment":"","address_hidden":false,"space_comment":"","costs_property_comment":"","space_units":"м²","space":"66.4","address":"м. Харків"}]},"intro":{"declaration_year":"2014","isnotdeclaration":""}}},{"provider":"public-api.nazk.gov.ua","document":{"step_0":{"declarationType":"1","declarationYear1":"2015"},"step_1":{"city":"[Конфіденційна інформація]","region":"[Конфіденційна інформація]","street":"[Конфіденційна інформація]","country":"1","cityPath":"[Конфіденційна інформація]","cityType":"[Конфіденційна інформація]","district":"[Конфіденційна інформація]","lastname":"Біленський","postCode":"[Конфіденційна інформація]","postType":"","workPost":"суддя","firstname":"Олег","workPlace":"Харківський окружний адміністративний суд","middlename":"Олексійович","streetType":"[Конфіденційна інформація]","changedName":false,"countryPath":"","eng_postCode":"","postCategory":"","actual_street":"[Конфіденційна інформація]","actual_cityPath":"[Конфіденційна інформація]","actual_cityType":"[Конфіденційна інформація]","actual_postCode":"[Конфіденційна інформація]","actual_streetType":"[Конфіденційна інформація]","previous_lastname":"","corruptionAffected":"Ні","eng_actualPostCode":"[Конфіденційна інформація]","previous_firstname":"","previous_middlename":"","responsiblePosition":"Суддя суду загальної юрисдикції, суддя Конституційного Суду України","sameRegLivingAddress":"[Конфіденційна інформація]","postType_extendedstatus":"1","eng_sameRegLivingAddress":"[Конфіденційна інформація]","housePartNum_extendedstatus":"1","postCategory_extendedstatus":"1","apartmentsNum_extendedstatus":"1"},"step_2":{"1476786764887":{"lastname":"Кононова","firstname":"Юлія","middlename":"Вячеславівна","changedName":false,"citizenship":"1","eng_lastname":"","eng_firstname":"","eng_middlename":"","isNotApplicable":"","subjectRelation":"дружина","previous_lastname":"","previous_firstname":"","previous_middlename":"","previous_eng_lastname":"","previous_eng_firstname":"","previous_eng_middlename":""},"1476787624613":{"lastname":"Біленська ","firstname":"Єлизавета","middlename":"Олегівна","changedName":false,"citizenship":"1","eng_lastname":"","eng_firstname":"","eng_middlename":"","isNotApplicable":"","subjectRelation":"дочка","previous_lastname":"","previous_firstname":"","previous_middlename":"","previous_eng_lastname":"","previous_eng_firstname":"","previous_eng_middlename":""},"1476787822071":{"lastname":"Біленська","firstname":"Евеліна","middlename":"Олегівна","changedName":false,"citizenship":"1","eng_lastname":"","eng_firstname":"","eng_middlename":"","isNotApplicable":"","subjectRelation":"дочка","previous_lastname":"","previous_firstname":"","previous_middlename":"","previous_eng_lastname":"","previous_eng_firstname":"","previous_eng_middlename":""}},"step_3":{"1476788354519":{"city":"[Конфіденційна інформація]","person":"1","region":"[Конфіденційна інформація]","rights":{"1":{"citizen":"","ua_city":"","ua_street":"[Конфіденційна інформація]","ua_lastname":"","ua_postCode":"","eng_lastname":"","eng_postCode":"","rightBelongs":"1","ua_firstname":"","ukr_lastname":"","eng_firstname":"","ownershipType":"Власність","ua_middlename":"","ua_streetType":"[Конфіденційна інформація]","ukr_firstname":"","eng_middlename":"","otherOwnership":"","ukr_middlename":"","rights_cityPath":"","ua_company_name":"","eng_company_name":"","ukr_company_name":"","percent-ownership":"100","ua_street_extendedstatus":"","ua_houseNum_extendedstatus":"","ua_postCode_extendedstatus":"","eng_postCode_extendedstatus":"","ua_middlename_extendedstatus":"","eng_middlename_extendedstatus":"","ukr_middlename_extendedstatus":"","ua_housePartNum_extendedstatus":"","ua_apartmentsNum_extendedstatus":""}},"country":"1","cityPath":"[Конфіденційна інформація]","costDate":"","district":"[Конфіденційна інформація]","postCode":"[Конфіденційна інформація]","totalArea":"41,30","ua_street":"[Конфіденційна інформація]","objectType":"Житловий будинок","owningDate":"23.06.1990","ua_cityType":"Південне / Харківський Район / Харківська Область / Україна","ua_postCode":"62461","ua_streetType":"[Конфіденційна інформація]","costAssessment":"","otherObjectType":"","costDate_extendedstatus":"2","regNumber_extendedstatus":"0","costAssessment_extendedstatus":"2","ua_housePartNum_extendedstatus":"1","ua_apartmentsNum_extendedstatus":"1"},"1476789438356":{"city":"[Конфіденційна інформація]","person":"1","region":"[Конфіденційна інформація]","rights":{"1":{"citizen":"","ua_city":"","ua_street":"[Конфіденційна інформація]","ua_lastname":"","ua_postCode":"","eng_lastname":"","eng_postCode":"","rightBelongs":"1","ua_firstname":"","ukr_lastname":"","eng_firstname":"","ownershipType":"Спільна власність","ua_middlename":"","ua_streetType":"[Конфіденційна інформація]","ukr_firstname":"","eng_middlename":"","otherOwnership":"","ukr_middlename":"","rights_cityPath":"","ua_company_name":"","eng_company_name":"","ukr_company_name":"","percent-ownership":"50","ua_street_extendedstatus":"","ua_houseNum_extendedstatus":"","ua_postCode_extendedstatus":"","eng_postCode_extendedstatus":"","ua_middlename_extendedstatus":"","eng_middlename_extendedstatus":"","ukr_middlename_extendedstatus":"","ua_housePartNum_extendedstatus":"","ua_apartmentsNum_extendedstatus":""},"1476793240145":{"citizen":"Громадянин України","ua_city":"Південне / Харківський Район / Харківська Область / Україна","ua_street":"[Конфіденційна інформація]","ua_lastname":"Біленська","ua_postCode":"62461","eng_lastname":"","eng_postCode":"","rightBelongs":"j","ua_firstname":"Ірина","ukr_lastname":"","eng_firstname":"","ownershipType":"Спільна власність","ua_middlename":"Олексіївна","ua_streetType":"[Конфіденційна інформація]","ukr_firstname":"","eng_middlename":"","otherOwnership":"","ukr_middlename":"","rights_cityPath":"1.2.63.2.51.1.10","ua_company_name":"","eng_company_name":"","ukr_company_name":"","percent-ownership":"50","ua_street_extendedstatus":"","ua_houseNum_extendedstatus":"","ua_postCode_extendedstatus":"","eng_postCode_extendedstatus":"","ua_taxNumber_extendedstatus":"2","ua_middlename_extendedstatus":"","eng_middlename_extendedstatus":"","ukr_middlename_extendedstatus":"","ua_housePartNum_extendedstatus":"1","ua_apartmentsNum_extendedstatus":"1"}},"country":"1","cityPath":"[Конфіденційна інформація]","costDate":"28779","district":"[Конфіденційна інформація]","postCode":"[Конфіденційна інформація]","totalArea":"91,30","ua_street":"[Конфіденційна інформація]","objectType":"Житловий будинок","owningDate":"09.08.2012","ua_cityType":"Південне / Харківський Район / Харківська Область / Україна","ua_postCode":"62461","ua_streetType":"[Конфіденційна інформація]","costAssessment":"","otherObjectType":"","costAssessment_extendedstatus":"2","ua_housePartNum_extendedstatus":"1","ua_apartmentsNum_extendedstatus":"1"},"1476794339766":{"city":"[Конфіденційна інформація]","person":"1476786764887","region":"[Конфіденційна інформація]","rights":{"1476786764887":{"citizen":"","ua_city":"","ua_street":"[Конфіденційна інформація]","ua_lastname":"","ua_postCode":"","eng_lastname":"","eng_postCode":"","rightBelongs":"1476786764887","ua_firstname":"","ukr_lastname":"","eng_firstname":"","ownershipType":"Власність","ua_middlename":"","ua_streetType":"[Конфіденційна інформація]","ukr_firstname":"","eng_middlename":"","otherOwnership":"","ukr_middlename":"","rights_cityPath":"","ua_company_name":"","eng_company_name":"","ukr_company_name":"","percent-ownership":"100","ua_street_extendedstatus":"","ua_houseNum_extendedstatus":"","ua_postCode_extendedstatus":"","eng_postCode_extendedstatus":"","ua_middlename_extendedstatus":"","eng_middlename_extendedstatus":"","ukr_middlename_extendedstatus":"","ua_housePartNum_extendedstatus":"","ua_apartmentsNum_extendedstatus":""}},"country":"1","cityPath":"[Конфіденційна інформація]","costDate":"296881","district":"[Конфіденційна інформація]","postCode":"[Конфіденційна інформація]","totalArea":"68,70","ua_street":"[Конфіденційна інформація]","objectType":"Квартира","owningDate":"28.04.2010","ua_cityType":"Харків / Харківська Область / Україна","ua_postCode":"61204","ua_streetType":"[Конфіденційна інформація]","costAssessment":"","otherObjectType":"","costAssessment_extendedstatus":"2","ua_housePartNum_extendedstatus":"1"},"1476795024265":{"city":"[Конфіденційна інформація]","person":"1476786764887","region":"[Конфіденційна інформація]","rights":{"1476786764887":{"citizen":"","ua_city":"","ua_street":"[Конфіденційна інформація]","ua_lastname":"","ua_postCode":"","eng_lastname":"","eng_postCode":"","rightBelongs":"1476786764887","ua_firstname":"","ukr_lastname":"","eng_firstname":"","ownershipType":"Власність","ua_middlename":"","ua_streetType":"[Конфіденційна інформація]","ukr_firstname":"","eng_middlename":"","otherOwnership":"","ukr_middlename":"","rights_cityPath":"","ua_company_name":"","eng_company_name":"","ukr_company_name":"","percent-ownership":"100","ua_street_extendedstatus":"","ua_houseNum_extendedstatus":"","ua_postCode_extendedstatus":"","eng_postCode_extendedstatus":"","ua_middlename_extendedstatus":"","eng_middlename_extendedstatus":"","ukr_middlename_extendedstatus":"","ua_housePartNum_extendedstatus":"","ua_apartmentsNum_extendedstatus":""}},"country":"1","cityPath":"[Конфіденційна інформація]","costDate":"21028","district":"[Конфіденційна інформація]","postCode":"[Конфіденційна інформація]","totalArea":"66,40","ua_street":"[Конфіденційна інформація]","objectType":"Квартира","owningDate":"06.04.2002","ua_cityType":"Харків / Харківська Область / Україна","ua_postCode":"61024","ua_streetType":"[Конфіденційна інформація]","costAssessment":"","otherObjectType":"","regNumber_extendedstatus":"1","costAssessment_extendedstatus":"2","ua_housePartNum_extendedstatus":"1"},"1476878073766":{"city":"[Конфіденційна інформація]","person":"1","region":"[Конфіденційна інформація]","rights":{"1":{"citizen":"","ua_city":"","ua_street":"[Конфіденційна інформація]","ua_lastname":"","ua_postCode":"","eng_lastname":"","eng_postCode":"","rightBelongs":"1","ua_firstname":"","ukr_lastname":"","eng_firstname":"","ownershipType":"Власність","ua_middlename":"","ua_streetType":"[Конфіденційна інформація]","ukr_firstname":"","eng_middlename":"","otherOwnership":"","ukr_middlename":"","rights_cityPath":"","ua_company_name":"","eng_company_name":"","ukr_company_name":"","percent-ownership":"100","ua_street_extendedstatus":"","ua_houseNum_extendedstatus":"","ua_postCode_extendedstatus":"","eng_postCode_extendedstatus":"","ua_middlename_extendedstatus":"","eng_middlename_extendedstatus":"","ukr_middlename_extendedstatus":"","ua_housePartNum_extendedstatus":"","ua_apartmentsNum_extendedstatus":""}},"country":"1","cityPath":"[Конфіденційна інформація]","costDate":"","district":"[Конфіденційна інформація]","postCode":"[Конфіденційна інформація]","totalArea":"554","ua_street":"[Конфіденційна інформація]","objectType":"Земельна ділянка","owningDate":"25.07.2014","ua_cityType":"Південне / Харківський Район / Харківська Область / Україна","ua_postCode":"62461","ua_streetType":"[Конфіденційна інформація]","costAssessment":"","otherObjectType":"","costDate_extendedstatus":"2","costAssessment_extendedstatus":"2","ua_housePartNum_extendedstatus":"1","ua_apartmentsNum_extendedstatus":"1"},"1476878703146":{"city":"[Конфіденційна інформація]","person":"1","region":"[Конфіденційна інформація]","rights":{"1":{"citizen":"","ua_city":"","ua_street":"[Конфіденційна інформація]","ua_lastname":"","ua_postCode":"","eng_lastname":"","eng_postCode":"","rightBelongs":"1","ua_firstname":"","ukr_lastname":"","eng_firstname":"","ownershipType":"Власність","ua_middlename":"","ua_streetType":"[Конфіденційна інформація]","ukr_firstname":"","eng_middlename":"","otherOwnership":"","ukr_middlename":"","rights_cityPath":"","ua_company_name":"","eng_company_name":"","ukr_company_name":"","percent-ownership":"100","ua_street_extendedstatus":"","ua_houseNum_extendedstatus":"","ua_postCode_extendedstatus":"","eng_postCode_extendedstatus":"","ua_middlename_extendedstatus":"","eng_middlename_extendedstatus":"","ukr_middlename_extendedstatus":"","ua_housePartNum_extendedstatus":"","ua_apartmentsNum_extendedstatus":""}},"country":"1","cityPath":"[Конфіденційна інформація]","costDate":"","district":"[Конфіденційна інформація]","postCode":"[Конфіденційна інформація]","totalArea":"1000","ua_street":"[Конфіденційна інформація]","objectType":"Земельна ділянка","owningDate":"25.07.2014","ua_cityType":"Південне / Харківський Район / Харківська Область / Україна","ua_postCode":"62461","ua_streetType":"[Конфіденційна інформація]","costAssessment":"","otherObjectType":"","costDate_extendedstatus":"2","costAssessment_extendedstatus":"2","ua_housePartNum_extendedstatus":"1","ua_apartmentsNum_extendedstatus":"1"}},"step_4":[],"step_5":[],"step_6":{"1476963846971":{"brand":"MITSUBISHI","model":"OUTLANDER","person":"1476786764887","rights":{"1":{"citizen":"","ua_city":"","ua_street":"[Конфіденційна інформація]","ua_lastname":"","ua_postCode":"","eng_lastname":"","eng_postCode":"","rightBelongs":"1","ua_firstname":"","ukr_lastname":"","eng_firstname":"","ownershipType":"Інше право користування","ua_middlename":"","ua_streetType":"[Конфіденційна інформація]","ukr_firstname":"","eng_middlename":"","otherOwnership":"ПРАВО КОРИСТУВАННЯ ","ukr_middlename":"","rights_cityPath":"","ua_company_name":"","eng_company_name":"","ukr_company_name":"","percent-ownership":"","ua_street_extendedstatus":"","ua_houseNum_extendedstatus":"","ua_postCode_extendedstatus":"","eng_postCode_extendedstatus":"","ua_middlename_extendedstatus":"","eng_middlename_extendedstatus":"","ukr_middlename_extendedstatus":"","ua_housePartNum_extendedstatus":"","ua_apartmentsNum_extendedstatus":""},"1476786764887":{"citizen":"","ua_city":"","ua_street":"[Конфіденційна інформація]","ua_lastname":"","ua_postCode":"","eng_lastname":"","eng_postCode":"","rightBelongs":"1476786764887","ua_firstname":"","ukr_lastname":"","eng_firstname":"","ownershipType":"Власність","ua_middlename":"","ua_streetType":"[Конфіденційна інформація]","ukr_firstname":"","eng_middlename":"","otherOwnership":"","ukr_middlename":"","rights_cityPath":"","ua_company_name":"","eng_company_name":"","ukr_company_name":"","percent-ownership":"","ua_street_extendedstatus":"","ua_houseNum_extendedstatus":"","ua_postCode_extendedstatus":"","eng_postCode_extendedstatus":"","ua_middlename_extendedstatus":"","eng_middlename_extendedstatus":"","ukr_middlename_extendedstatus":"","ua_housePartNum_extendedstatus":"","ua_apartmentsNum_extendedstatus":""}},"costDate":"64897","objectType":"Автомобіль легковий","owningDate":"31.10.2006","graduationYear":"2003","otherObjectType":""},"1477477162369":{"brand":"УАЗ","model":"452Д","person":"1","rights":{"1":{"citizen":"","ua_city":"","ua_street":"[Конфіденційна інформація]","ua_lastname":"","ua_postCode":"","eng_fullname":"","eng_lastname":"","eng_postCode":"","rightBelongs":"1","ua_firstname":"","ukr_fullname":"","ukr_lastname":"","eng_firstname":"","ownershipType":"Власність","ua_middlename":"","ua_streetType":"[Конфіденційна інформація]","ukr_firstname":"","eng_middlename":"","otherOwnership":"","ukr_middlename":"","rights_cityPath":"","ua_company_name":"","eng_company_name":"","ukr_company_name":"","percent-ownership":"","ua_street_extendedstatus":"","ua_houseNum_extendedstatus":"","ua_postCode_extendedstatus":"","eng_postCode_extendedstatus":"","ua_middlename_extendedstatus":"","eng_middlename_extendedstatus":"","ukr_middlename_extendedstatus":"","ua_housePartNum_extendedstatus":"","ua_apartmentsNum_extendedstatus":""}},"costDate":"","objectType":"Автомобіль легковий","owningDate":"07.12.1991","graduationYear":"1979","otherObjectType":"","costDate_extendedstatus":"2"},"1477477321005":{"brand":"VOLKSWAGEN","model":"VENTO","person":"1","rights":{"1":{"citizen":"","ua_city":"","ua_street":"[Конфіденційна інформація]","ua_lastname":"","ua_postCode":"","eng_fullname":"","eng_lastname":"","eng_postCode":"","rightBelongs":"1","ua_firstname":"","ukr_fullname":"","ukr_lastname":"","eng_firstname":"","ownershipType":"Власність","ua_middlename":"","ua_streetType":"[Конфіденційна інформація]","ukr_firstname":"","eng_middlename":"","otherOwnership":"","ukr_middlename":"","rights_cityPath":"","ua_company_name":"","eng_company_name":"","ukr_company_name":"","percent-ownership":"","ua_street_extendedstatus":"","ua_houseNum_extendedstatus":"","ua_postCode_extendedstatus":"","eng_postCode_extendedstatus":"","ua_middlename_extendedstatus":"","eng_middlename_extendedstatus":"","ukr_middlename_extendedstatus":"","ua_housePartNum_extendedstatus":"","ua_apartmentsNum_extendedstatus":""}},"costDate":"15926","objectType":"Автомобіль легковий","owningDate":"27.12.1997","graduationYear":"1994","otherObjectType":""}},"step_7":[],"step_8":[],"step_9":[],"step_10":[],"step_11":{"1476797968593":{"person":"1","rights":{"1":{"citizen":"","ua_city":"","ua_street":"[Конфіденційна інформація]","ua_lastname":"","ua_postCode":"","eng_lastname":"","eng_postCode":"","rightBelongs":"1","ua_firstname":"","ukr_lastname":"","eng_firstname":"","ownershipType":"Власність","ua_middlename":"","ua_streetType":"[Конфіденційна інформація]","ukr_firstname":"","eng_middlename":"","otherOwnership":"","ukr_middlename":"","rights_cityPath":"","ua_company_name":"","eng_company_name":"","ukr_company_name":"","percent-ownership":"","ua_street_extendedstatus":"","ua_houseNum_extendedstatus":"","ua_postCode_extendedstatus":"","eng_postCode_extendedstatus":"","ua_middlename_extendedstatus":"","eng_middlename_extendedstatus":"","ukr_middlename_extendedstatus":"","ua_housePartNum_extendedstatus":"","ua_apartmentsNum_extendedstatus":""}},"objectType":"Заробітна плата отримана за основним місцем роботи","sizeIncome":"159831","incomeSource":"j","source_citizen":"Юридична особа, зареєстрована в Україні","otherObjectType":"","source_ua_lastname":"","source_eng_lastname":"","source_ua_firstname":"","source_ukr_lastname":"","source_eng_firstname":"","source_ua_middlename":"","source_ukr_firstname":"","source_eng_middlename":"","source_ukr_middlename":"","source_ua_company_name":"Харківський окружний адміністративний суд","source_eng_company_name":"","source_ukr_company_name":"","source_ua_sameRegLivingAddress":"","source_eng_sameRegLivingAddress":""},"1476799109601":{"person":"1476786764887","rights":{"1476786764887":{"citizen":"","ua_city":"","ua_street":"[Конфіденційна інформація]","ua_lastname":"","ua_postCode":"","eng_lastname":"","eng_postCode":"","rightBelongs":"1476786764887","ua_firstname":"","ukr_lastname":"","eng_firstname":"","ownershipType":"Власність","ua_middlename":"","ua_streetType":"[Конфіденційна інформація]","ukr_firstname":"","eng_middlename":"","otherOwnership":"","ukr_middlename":"","rights_cityPath":"","ua_company_name":"","eng_company_name":"","ukr_company_name":"","percent-ownership":"","ua_street_extendedstatus":"","ua_houseNum_extendedstatus":"","ua_postCode_extendedstatus":"","eng_postCode_extendedstatus":"","ua_middlename_extendedstatus":"","eng_middlename_extendedstatus":"","ukr_middlename_extendedstatus":"","ua_housePartNum_extendedstatus":"","ua_apartmentsNum_extendedstatus":""}},"objectType":"Заробітна плата отримана за основним місцем роботи","sizeIncome":"12493","incomeSource":"j","source_citizen":"Юридична особа, зареєстрована в Україні","otherObjectType":"","source_ua_lastname":"","source_eng_lastname":"","source_ua_firstname":"","source_ukr_lastname":"","source_eng_firstname":"","source_ua_middlename":"","source_ukr_firstname":"","source_eng_middlename":"","source_ukr_middlename":"","source_ua_company_name":"Харківський національний педагогічний університет імені Г. С. Сковороди","source_eng_company_name":"","source_ukr_company_name":"","source_ua_sameRegLivingAddress":"","source_eng_sameRegLivingAddress":""},"1476799312421":{"person":"1476787624613","rights":{"1476787624613":{"citizen":"","ua_city":"","ua_street":"[Конфіденційна інформація]","ua_lastname":"","ua_postCode":"","eng_lastname":"","eng_postCode":"","rightBelongs":"1476787624613","ua_firstname":"","ukr_lastname":"","eng_firstname":"","ownershipType":"Власність","ua_middlename":"","ua_streetType":"[Конфіденційна інформація]","ukr_firstname":"","eng_middlename":"","otherOwnership":"","ukr_middlename":"","rights_cityPath":"","ua_company_name":"","eng_company_name":"","ukr_company_name":"","percent-ownership":"","ua_street_extendedstatus":"","ua_houseNum_extendedstatus":"","ua_postCode_extendedstatus":"","eng_postCode_extendedstatus":"","ua_middlename_extendedstatus":"","eng_middlename_extendedstatus":"","ukr_middlename_extendedstatus":"","ua_housePartNum_extendedstatus":"","ua_apartmentsNum_extendedstatus":""}},"objectType":"Інше","sizeIncome":"11782","incomeSource":"j","source_citizen":"Юридична особа, зареєстрована в Україні","otherObjectType":"стипендія","source_ua_lastname":"","source_eng_lastname":"","source_ua_firstname":"","source_ukr_lastname":"","source_eng_firstname":"","source_ua_middlename":"","source_ukr_firstname":"","source_eng_middlename":"","source_ukr_middlename":"","source_ua_company_name":"Національний юридичний університет імені Ярослава Мудрого","source_eng_company_name":"","source_ukr_company_name":"","source_ua_sameRegLivingAddress":"","source_eng_sameRegLivingAddress":""}},"step_12":[],"step_13":[],"step_14":[],"step_15":[],"step_16":[],"id":"c0af5c6e-a06d-47f6-8a21-bbd000ef3f61"}}],"declarations":[{"income":{"5":{"family_comment":"","family_unclear":false,"value":"159831.26","family":"24275.76","comment":""},"6":{"value":"159831.26","family_comment":"","value_unclear":false,"family_unclear":false,"family":"12493.48","comment":""},"7":{"source_name_unclear":false,"value":"","family_comment":"","source_name":"","family":"","comment":"","source_name_hidden":false},"8":{"family_comment":"","value":"","family":"","comment":""},"9":{"family_comment":"","family_unclear":false,"value":"","family":"","comment":""},"10":{"family_comment":"","value":"","family":"","comment":""},"11":{"family_comment":"","value":"","family":"","comment":""},"12":{"family_comment":"","value":"","family":"","comment":""},"13":{"family_comment":"","value":"","family":"","comment":""},"14":{"family_comment":"","value":"","family":"","comment":""},"15":{"family_comment":"","value":"","family":"","comment":""},"16":{"family_comment":"","family_unclear":false,"value":"","family":"","comment":""},"17":{"family_comment":"","family_unclear":false,"value":"","family":"","comment":""},"18":{"family_comment":"","value":"","family":"","comment":""},"19":{"family_comment":"","value":"","family":"","comment":""},"20":{"family_comment":"","value":"","comment_unclear":false,"family":"11782.28","comment":""}},"vehicle":{"35":[{"brand_info":"1781 куб. см. 438 см","sum":"","brand":"Volkswagen Vento","sum_comment":"","brand_unclear":false,"year":"1994","brand_hidden":false,"brand_info_hidden":false,"brand_info_unclear":true,"sum_rent_comment":"","sum_rent":""}],"36":[{"brand_info":"55.2 кВт 436 см","sum_rent_comment":"","brand":"УАЗ 452 Д","sum_comment":"","brand_unclear":true,"year":"1978","sum":"","sum_rent":""}],"40":[{"brand_info":"1997 куб. см.","sum":"","brand":"Mitsubishi Outlander","sum_comment":"","brand_unclear":false,"year":"2003","brand_hidden":false,"brand_info_hidden":false,"brand_info_unclear":false,"sum_rent_comment":"","sum_rent":""}]},"id":"vulyk_95_27","declaration":{"additional_info_text":"","notfull_lostpages":"","date":"2016-03-14T00:00:00","notfull":"","additional_info":"","url":"http://static.declarations.com.ua/declarations/chosen_ones/judges_batch/28_bilenskyi_oleh_oleksiiovych.pdf"},"liabilities":{"54":{"sum_foreign_comment":"","sum":"","sum_comment":"","sum_hidden":false,"sum_comment_hidden":false,"sum_unclear":false,"sum_foreign":""},"55":{"sum_foreign_comment":"","sum":"","sum_comment":"","sum_foreign":""},"56":{"sum_foreign_comment":"","sum":"","sum_comment":"","sum_foreign":""},"57":{"sum_foreign_comment":"","sum":"","sum_comment":"","sum_hidden":false,"sum_comment_hidden":false,"sum_unclear":false,"sum_foreign":""},"58":{"sum_foreign_comment":"","sum":"","sum_comment":"","sum_hidden":false,"sum_comment_hidden":false,"sum_unclear":false,"sum_foreign":""},"59":{"sum_foreign_comment":"","sum":"","sum_comment":"","sum_foreign":""},"60":{"sum_foreign_comment":"","sum":"","sum_comment":"","sum_hidden":false,"sum_comment_hidden":false,"sum_foreign":""},"61":{"sum_foreign_comment":"","sum":"","sum_comment":"","sum_foreign":""},"62":{"sum_foreign_comment":"","sum":"","sum_comment":"","sum_unclear":false,"sum_foreign":""},"63":{"sum_foreign_comment":"","sum":"","sum_comment":"","sum_unclear":false,"sum_foreign":""},"64":{"sum_foreign_comment":"","sum":"","sum_comment":"","sum_foreign":""}},"ft_src":"Південне\nХарківська область\nБіленський Олег Олексійович\nсуддя харківського окружного адміністративного суду\nХарківська область\nАдміністративний місцевий суд\nОлег\nКононова Юлія В'ячеславівна\nПодружжя\nБіленська Єлизавета Олегівна\nДитина\nБіленська Евеліна Олегівна\nДитина\nБіленський Олег Олексійович\nОлег Олексійович Біленський\nОлег Біленський\nБіленський Олег Олексійович\nБіленський\nОлексійович\n1978\n55.2 кВт 436 см\nУАЗ 452 Д\nVolkswagen Vento\n1781 куб. см. 438 см\n1994\nMitsubishi Outlander\n1997 куб. см.\n2003\nм. Південне\n1554\nХарківська область\n45.65\nХарківська область\nХарківська область\nм. Харків\n68.7\nХарківська область\nм. Харків\n66.4\nХарківська область\nХарківська область\nм. Південне\n41.3\nХарківська область\nм. Південне\n45.65\n2015\n12493.48\n159831.26\n24275.76\n159831.26\n11782.28\nVolkswagen Vento\n1781 куб. см. 438 см\n1994\nMitsubishi Outlander\n1997 куб. см.\n2003\n55.2 кВт 436 см\nУАЗ 452 Д\n1978\n1554\nм. Південне\nХарківська область\n45.65\nХарківська область\n41.3\nм. Південне\nХарківська область\n45.65\nм. Південне\nХарківська область\nм. Харків\nХарківська область\n68.7\nм. Харків\nХарківська область\n66.4\nХарківська область\nОлексійович\nПодружжя\nКононова Юлія В'ячеславівна\nДитина\nБіленська Єлизавета Олегівна\nДитина\nБіленська Евеліна Олегівна\nБіленський Олег Олексійович\nОлег Олексійович Біленський\nОлег Біленський\nБіленський Олег Олексійович\nОлег\nПівденне\nХарківська область\nБіленський Олег Олексійович\nБіленський\nАдміністративний місцевий суд\nсуддя харківського окружного адміністративного суду\nХарківська область\n159831.26\n12493.48\n11782.28\n159831.26\n24275.76\n2015\nКононова Юлія В'ячеславівна\nПодружжя\nБіленська Єлизавета Олегівна\nДитина\nБіленська Евеліна Олегівна\nДитина\nХарківська область\nПівденне\nОлексійович\nБіленський\nХарківська область\nАдміністративний місцевий суд\nсуддя харківського окружного адміністративного суду\nБіленський Олег Олексійович\nБіленський Олег Олексійович\nОлег Олексійович Біленський\nОлег Біленський\nБіленський Олег Олексійович\nОлег\nMitsubishi Outlander\n1997 куб. см.\n2003\nVolkswagen Vento\n1781 куб. см. 438 см\n1994\n1978\n55.2 кВт 436 см\nУАЗ 452 Д\n11782.28\n24275.76\n159831.26\n159831.26\n12493.48\nм. Харків\nХарківська область\n68.7\nм. Харків\nХарківська область\n66.4\nм. Південне\nХарківська область\n1554\nХарківська область\n45.65\nм. Південне\nХарківська область\n41.3\nм. Південне\nХарківська область\n45.65\nХарківська область\n2015","general":{"inn":"","inn_hidden":true,"last_name":"Біленський","post":{"post":"суддя харківського окружного адміністративного суду","region":"Харківська область","candidate":"","office_hidden":false,"office":"Адміністративний місцевий суд","office_unclear":false},"name":"Олег","full_name":"Біленський Олег Олексійович","family_raw":"","addresses":[{"place_address":"","place_district_hidden":false,"place_city_type":"","place_city_hidden":false,"place_address_unclear":false,"place_city_type_hidden":false,"place_city":"Південне","place":"Харківська область","place_district":"","place_address_hidden":false,"place_hidden":true,"place_city_unclear":true}],"family":[{"inn":"","inn_hidden":true,"inn_unclear":false,"relations_hidden":false,"relations_other":"","relations":"Подружжя","name_hidden":false,"family_name":"Кононова Юлія В'ячеславівна","name_unclear":true},{"inn":"","inn_hidden":false,"inn_unclear":false,"relations_hidden":false,"relations_other":"","relations":"Дитина","name_hidden":false,"family_name":"Біленська Єлизавета Олегівна","name_unclear":false},{"inn":"","inn_hidden":false,"inn_unclear":false,"relations_hidden":false,"relations_other":"","relations":"Дитина","name_hidden":false,"family_name":"Біленська Евеліна Олегівна","name_unclear":false}],"full_name_suggest":{"output":"Біленський Олег Олексійович","input":["Біленський Олег Олексійович","Олег Олексійович Біленський","Олег Біленський"]},"patronymic":"Олексійович"},"source":"VULYK","estate":{"23":[{"region_unclear":false,"space_unclear":false,"costs":"","costs_comment":"","address_hidden":true,"region_hidden":false,"space_comment":"","space":"1554","address":"м. Південне","region":"Харківська область","address_unclear":true,"costs_rent_comment":"","costs_comment_hidden":false,"space_units":"м²","costs_rent":""},{"costs":"","costs_comment":"","address_hidden":false,"region_hidden":false,"space_units_unclear":false,"space":"45.65","address":"","region":"Харківська область","costs_rent_comment":"","space_units":"м²","space_units_hidden":false,"space_comment":"","costs_rent":""}],"24":[{"costs":"","costs_comment":"","address_hidden":true,"region_hidden":false,"space_comment":"","space":"41.3","address":"м. Південне","region":"Харківська область","address_unclear":true,"costs_rent_comment":"","space_units":"м²","costs_rent":""},{"costs":"","costs_comment":"","address_hidden":false,"region_hidden":false,"space_comment":"","space":"45.65","address":"м. Південне","region":"Харківська область","address_unclear":true,"costs_rent_comment":"","space_units":"м²","costs_rent":""}],"31":[{"space_unclear":false,"address_hidden":true,"region_hidden":false,"space_comment":"","space":"68.7","address":"м. Харків","region":"Харківська область","costs_property":"","costs_rent_comment":"","space_comment_unclear":false,"space_units":"м²","costs_property_comment":"","costs_rent":""},{"address_hidden":false,"region_hidden":false,"space_comment":"","space":"66.4","address":"м. Харків","region":"Харківська область","costs_property":"","costs_rent_comment":"","space_comment_unclear":false,"space_units":"м²","costs_property_comment":"","costs_rent":""}],"32":[{"address_hidden":false,"region_hidden":false,"space_comment":"","space":"","address":"","region":"Харківська область","costs_property":"","costs_rent_comment":"","address_unclear":false,"space_units":"м²","costs_property_comment":"","costs_rent":""}]},"intro":{"declaration_year":"2015","isnotdeclaration":""}},{"income":{"5":{"family_comment":"","value":"206049","family":"14345","comment":""},"6":{"value":"206014","family_comment":"","value_unclear":false,"comment_hidden":false,"family_unclear":false,"family":"10908","comment":""},"7":{"family_comment":"","value":"","source_name":"","family":"","comment":""},"8":{"family_comment":"","value":"","family":"","comment":""},"9":{"family_comment":"","family_unclear":false,"value":"","family":"","comment":""},"10":{"family_comment":"","value":"","value_unclear":false,"family":"","comment":""},"11":{"family_comment":"","value":"35","family":"","comment":""},"12":{"family_comment":"","value":"","family":"","comment":""},"13":{"family_comment":"","value":"","family":"","comment":""},"14":{"family_comment":"","value":"","family":"","comment":""},"15":{"family_comment":"","value":"","family":"","comment":""},"16":{"family_comment":"","value":"","family":"","comment":""},"17":{"family_comment":"","value":"","family":"","comment":""},"18":{"family_comment":"","value":"","family":"","comment":""},"19":{"family_comment":"","value":"","family":"","comment":""},"20":{"value":"","family":"3437","value_unclear":false,"family_hidden":false,"family_comment":"","comment_unclear":false,"comment":"","family_comment_unclear":false}},"vehicle":{"35":[{"year_hidden":false,"brand_info":"1781 куб. см., 438 см","sum_rent_comment":"","year":"1994","brand_info_hidden":false,"brand_info_unclear":false,"sum_rent":"","sum":"","brand":"Volkswagen Vento","sum_comment":"","brand_unclear":false,"brand_hidden":false}],"36":[{"brand_info":"2440 куб. см., 55.2 кВт , 436 см","sum_rent_comment":"","brand":"УАЗ 452 Д","sum_comment":"","year":"1978","brand_info_unclear":true,"sum":"","sum_rent":""}],"40":[{"brand_info":"1997 куб. см., 454.5 см","sum_rent_comment":"","brand":"Mitsubishi Outlander","sum_comment":"","brand_unclear":false,"year":"2003","brand_info_unclear":false,"year_unclear":false,"sum":"","sum_rent":""}]},"id":"vulyk_97_99","declaration":{"additional_info_text":"","notfull_lostpages":"","date":"2015-03-24T00:00:00","notfull":"","additional_info":"","url":"http://static.declarations.com.ua/declarations/chosen_ones/judges_batch/4000_bilenskyi_oleh_oleksiiovych.pdf"},"liabilities":{"54":{"sum_foreign_comment":"","sum":"","sum_comment":"","sum_comment_unclear":false,"sum_hidden":false,"sum_comment_hidden":false,"sum_unclear":false,"sum_foreign":""},"55":{"sum_foreign_comment":"","sum":"","sum_comment":"","sum_foreign":""},"56":{"sum_foreign_comment":"","sum":"","sum_comment":"","sum_foreign":""},"57":{"sum_foreign_comment":"","sum":"","sum_comment":"","sum_comment_unclear":false,"sum_hidden":false,"sum_comment_hidden":false,"sum_unclear":false,"sum_foreign":""},"58":{"sum_foreign_comment":"","sum":"","sum_comment":"","sum_comment_unclear":false,"sum_hidden":false,"sum_comment_hidden":false,"sum_unclear":false,"sum_foreign":""},"59":{"sum_foreign_comment":"","sum":"","sum_comment":"","sum_foreign":""},"60":{"sum_foreign_comment":"","sum":"","sum_comment":"","sum_comment_unclear":false,"sum_hidden":false,"sum_comment_hidden":false,"sum_foreign":""},"61":{"sum_foreign_comment":"","sum":"","sum_comment":"","sum_foreign":""},"62":{"sum_foreign_comment":"","sum":"","sum_comment":"","sum_unclear":false,"sum_foreign":""},"63":{"sum_foreign_comment":"","sum":"","sum_hidden":false,"sum_comment":"","sum_foreign":""},"64":{"sum_foreign_comment":"","sum":"","sum_comment":"","sum_foreign":""}},"ft_src":"Південне\nХарківський\nХарківська область\nсуддя харківського окружного адміністративного суду\nХарківська область\nАдміністративний місцевий суд\nОлег\nКононова Юлія Вячеславівна\nПодружжя\nБіленська Єлізавета Олегівна\nДитина\nБіленська Евеліна Олегівна\nДитина\nОлексійович\nБіленський Олег Олексійович\nОлег Олексійович Біленський\nОлег Біленський\nБіленський Олег Олексійович\nБіленський Олег Олексійович\nБіленський\n2440 куб. см., 55.2 кВт , 436 см\n1978\nУАЗ 452 Д\n1781 куб. см., 438 см\nVolkswagen Vento\n1994\nMitsubishi Outlander\n1997 куб. см., 454.5 см\n2003\nХарківський р-н, м. Південне\n1554\nХарківська область\nХарківський р-н, м. Південне\n45.65\nХарківська область\n68.7\nХарківська область\nм. Харків\nХарківська область\nм. Харків\n66.4\nХарківський р-н, м. Південне\n41.3\nХарківська область\nХарківська область\nХарківський р-н, м. Південне\n45.65\n2014\n10908\n206014\n35\n14345\n206049\n3437\n1781 куб. см., 438 см\nVolkswagen Vento\n1994\n1997 куб. см., 454.5 см\nMitsubishi Outlander\n2003\n2440 куб. см., 55.2 кВт , 436 см\n1978\nУАЗ 452 Д\n2014\nБіленський Олег Олексійович\nОлег Олексійович Біленський\nОлег Біленський\nБіленський Олег Олексійович\nОлег\nПодружжя\nКононова Юлія Вячеславівна\nДитина\nБіленська Єлізавета Олегівна\nДитина\nБіленська Евеліна Олегівна\nБіленський Олег Олексійович\nБіленський\nАдміністративний місцевий суд\nХарківська область\nсуддя харківського окружного адміністративного суду\nОлексійович\nХарківська область\nПівденне\nХарківський\n206014\n10908\n3437\n206049\n14345\n35\n1554\nХарківський р-н, м. Південне\nХарківська область\n45.65\nХарківський р-н, м. Південне\nХарківська область\n41.3\nХарківська область\nХарківський р-н, м. Південне\n45.65\nХарківська область\nХарківський р-н, м. Південне\n68.7\nХарківська область\nм. Харків\n66.4\nХарківська область\nм. Харків\nПодружжя\nКононова Юлія Вячеславівна\nБіленська Єлізавета Олегівна\nДитина\nДитина\nБіленська Евеліна Олегівна\nОлексійович\nБіленський\nОлег\nБіленський Олег Олексійович\nОлег Олексійович Біленський\nОлег Біленський\nБіленський Олег Олексійович\nПівденне\nХарківська область\nХарківський\nХарківська область\nАдміністративний місцевий суд\nсуддя харківського окружного адміністративного суду\nБіленський Олег Олексійович\n2003\n1997 куб. см., 454.5 см\nMitsubishi Outlander\n1994\nVolkswagen Vento\n1781 куб. см., 438 см\n1978\n2440 куб. см., 55.2 кВт , 436 см\nУАЗ 452 Д\n35\n3437\n14345\n206049\n206014\n10908\nм. Харків\nХарківська область\n68.7\nм. Харків\nХарківська область\n66.4\nХарківський р-н, м. Південне\nХарківська область\n1554\nХарківський р-н, м. Південне\nХарківська область\n45.65\nХарківський р-н, м. Південне\nХарківська область\n41.3\nХарківський р-н, м. Південне\nХарківська область\n45.65\n2014","general":{"name_hidden":false,"name":"Олег","last_name_hidden":false,"inn":"","family":[{"inn":"","relations":"Подружжя","relations_other":"","inn_hidden":true,"family_name":"Кононова Юлія Вячеславівна","name_hidden":false,"name_unclear":false},{"inn_hidden":false,"inn":"","name_hidden":false,"family_name":"Біленська Єлізавета Олегівна","relations":"Дитина","name_unclear":false},{"inn":"","relations":"Дитина","relations_other":"","inn_hidden":false,"family_name":"Біленська Евеліна Олегівна","name_hidden":false,"name_unclear":false}],"patronymic":"Олексійович","inn_hidden":true,"family_raw":"","inn_unclear":false,"post":{"region_unclear":false,"region":"Харківська область","post":"суддя харківського окружного адміністративного суду","office":"Адміністративний місцевий суд","office_unclear":false,"post_hidden":false},"full_name":"Біленський Олег Олексійович","addresses":[{"place_district":"Харківський","place_city_hidden":false,"place_city":"Південне","place_city_unclear":false,"place_district_hidden":false,"place_city_type":"Місто","place_address_hidden":true,"place_city_type_hidden":false,"place_address":"","place_hidden":false,"place":"Харківська область"}],"last_name":"Біленський","patronymic_hidden":false,"full_name_suggest":{"output":"Біленський Олег Олексійович","input":["Біленський Олег Олексійович","Олег Олексійович Біленський","Олег Біленський"]}},"source":"VULYK","estate":{"23":[{"region_unclear":false,"space_unclear":false,"costs":"","costs_rent_unclear":false,"costs_comment":"","address_hidden":false,"region_hidden":false,"space_comment":"","space":"1554","address":"Харківський р-н, м. Південне","region":"Харківська область","address_unclear":false,"costs_rent_comment":"","space_units":"м²","costs_rent":""},{"region_unclear":false,"costs":"","costs_rent_unclear":false,"costs_comment":"","region_hidden":false,"space_comment":"","space":"45.65","address":"Харківський р-н, м. Південне","region":"Харківська область","address_unclear":false,"costs_rent_comment":"","space_units":"м²","costs_rent":""}],"24":[{"region_unclear":false,"space_unclear":false,"costs":"","costs_comment":"","address_hidden":false,"region_hidden":false,"space_comment":"","space_hidden":false,"space":"41.3","address":"Харківський р-н, м. Південне","region":"Харківська область","address_unclear":false,"costs_rent_comment":"","space_comment_unclear":false,"space_units":"м²","costs_rent":""},{"costs_rent":"","space_unclear":false,"region":"Харківська область","costs":"","costs_rent_comment":"","costs_comment":"","region_hidden":false,"space_comment":"","space_units":"м²","space":"45.65","address":"Харківський р-н, м. Південне"}],"31":[{"space_unclear":false,"address_hidden":false,"region_hidden":false,"space_comment":"","space_hidden":false,"space":"68.7","address":"м. Харків","region":"Харківська область","costs_property":"","costs_rent_comment":"","space_comment_hidden":false,"space_units":"м²","costs_property_comment":"","costs_rent":""},{"costs_rent":"","region":"Харківська область","costs_property":"","costs_rent_comment":"","address_hidden":false,"space_comment":"","costs_property_comment":"","space_units":"м²","space":"66.4","address":"м. Харків"}]},"intro":{"declaration_year":"2014","isnotdeclaration":""}}],"declarationsLength":2,"analytics":[{"y":2015,"i":159831.26,"c":1,"h":86.95,"ha":2,"l":1599.65,"la":2,"fi":24275.76,"ff":135.1,"ffa":2,"j":2},{"y":2014,"i":206049,"c":1,"h":86.95,"ha":2,"l":1599.65,"la":2,"fi":14345,"ff":135.1,"ffa":2}]}