{"2010":"","2016":"","Department":"Коломийський міськрайонний суд Івано-Франківської області","Region":"Івано-Франківська область","Position":"Суддя Коломийського міськрайонного суду Івано-Франківської області","Name":"Бирич Наталія Володимирівна","Link":"https://drive.google.com/open?id=0BygiyWAl79DMRnlBdUF1X0loanc","Note":"У меня","AdditionalNote":"","field8":"","field9":"","field10":"","Кількість справ":"","Оскаржені":"","Кількість скарг":0,"Кількість дисциплінарних стягнень":"","Клейма":"","Фото":"","Як живе":"","key":"birich_nataliya_volodimirivna","allDeclarations":[{"provider":"declarations.com.ua","document":{"income":{"5":{"value":"173710","family_hidden":false,"value_hidden":false,"family_comment":"","family":"7813","comment":""},"6":{"family_comment":"","value":"167710","family":"","comment":""},"7":{"family_comment":"","value":"","source_name":"","family":"","comment":""},"8":{"family_comment":"","value":"","family":"","comment":""},"9":{"family_comment":"","value":"","family":"","comment":""},"10":{"family_comment":"","value":"","family":"","comment":""},"11":{"family_comment":"","value":"","family":"","comment":""},"12":{"family_comment":"","value":"","family":"","comment":""},"13":{"family_comment":"","value":"6000","family":"","comment":""},"14":{"family_comment":"","value":"","family":"","comment":""},"15":{"family_comment":"","value":"","family":"","comment":""},"16":{"family_comment":"","value":"","family":"","comment":""},"17":{"family_comment":"","value":"","family":"","comment":""},"18":{"family_comment":"","value":"","family":"","comment":""},"19":{"family_comment":"","value":"","family":"","comment":""},"20":{"family_comment":"","value":"","family":"7813","comment":""}},"vehicle":{"40":[{"brand_info":"1600 куб. см.","sum":"","brand":"ВАЗ 211004","sum_comment":"","year":"2009","sum_rent_comment":"","sum_rent":""}]},"id":"vulyk_89_18","declaration":{"date":"2015-03-26T00:00:00","notfull":"","notfull_lostpages":"","url":"http://static.declarations.com.ua/declarations/chosen_ones/judges_batch/3021_byrych_nataliia_volodymyrivna.pdf"},"liabilities":{"54":{"sum_foreign_comment":"","sum":"","sum_comment":"","sum_foreign":""},"55":{"sum_foreign_comment":"","sum":"","sum_comment":"","sum_foreign":""},"56":{"sum_foreign_comment":"","sum":"","sum_comment":"","sum_unclear":false,"sum_foreign":""},"57":{"sum_foreign_comment":"","sum":"43032","sum_comment":"","sum_foreign":""},"58":{"sum_foreign_comment":"","sum":"24","sum_comment":"","sum_foreign":""},"59":{"sum_foreign_comment":"","sum":"","sum_comment":"","sum_foreign":""},"60":{"sum_foreign_comment":"","sum":"","sum_comment":"","sum_foreign":""},"61":{"sum_foreign_comment":"","sum":"","sum_comment":"","sum_foreign":""},"62":{"sum_foreign_comment":"","sum":"","sum_comment":"","sum_unclear":false,"sum_foreign":""},"63":{"sum_foreign_comment":"","sum":"","sum_comment":"","sum_foreign":""},"64":{"sum_foreign_comment":"","sum":"","sum_comment":"","sum_foreign":""}},"ft_src":"1600 куб. см.\n2009\nВАЗ 211004\nТисменицький р-н, с. Угринів\nІвано-Франківська область\n56.9\nІвано-Франківська область\nТисменицький р-н, с. Угринів\n150\nІвано-Франківська область\n1/3\nТлумацький р-н, село Королівка\n93.2\nІвано-Франківська область\nТисменицький р-н, с. Угринів\n2500\n2014\n167710\n6000\n7813\n173710\n7813\n1600 куб. см.\nВАЗ 211004\n2009\n2014\nВолодимирівна\nЧапюк Є. В. 23. 10. 1957\nБатьки\nБрат/Сестра\nЧапюк І. В. 01. 09. 1988\nБирич Т. В., 19. 04. 2005\nДитина\nБирич Наталія Володимирівна\nНаталія Володимирівна Бирич\nНаталія Бирич\nБирич Наталія Володимирівна\nБирич Наталія Володимирівна\nСело\nІвано-Франківська область\nУгринів\nТисменицький\nНаталія\nБирич\nІвано-Франківська область\nсуддя коломийського міськрайонного суду івано-франківської області\nЗагальний місцевий суд\n24\n43032\n167710\n7813\n6000\n173710\n7813\n2500\nІвано-Франківська область\nТисменицький р-н, с. Угринів\n150\nІвано-Франківська область\nТисменицький р-н, с. Угринів\n93.2\n1/3\nТлумацький р-н, село Королівка\nІвано-Франківська область\n56.9\nТисменицький р-н, с. Угринів\nІвано-Франківська область\n24\n43032\nЧапюк Є. В. 23. 10. 1957\nБатьки\nЧапюк І. В. 01. 09. 1988\nБрат/Сестра\nДитина\nБирич Т. В., 19. 04. 2005\nСело\nІвано-Франківська область\nУгринів\nТисменицький\nВолодимирівна\nБирич\nсуддя коломийського міськрайонного суду івано-франківської області\nІвано-Франківська область\nЗагальний місцевий суд\nБирич Наталія Володимирівна\nБирич Наталія Володимирівна\nНаталія Володимирівна Бирич\nНаталія Бирич\nБирич Наталія Володимирівна\nНаталія","general":{"inn":"","inn_hidden":true,"last_name":"Бирич","post":{"office":"Загальний місцевий суд","region":"Івано-Франківська область","post":"суддя коломийського міськрайонного суду івано-франківської області"},"name":"Наталія","full_name":"Бирич Наталія Володимирівна","family_raw":"","addresses":[{"place_district":"Тисменицький","place_address_hidden":true,"place_city":"Угринів","place_address":"","place_district_hidden":false,"place_city_type":"Село","place_city_hidden":false,"place_city_type_hidden":false,"place_hidden":false,"place":"Івано-Франківська область"}],"family":[{"inn":"","inn_hidden":true,"relations":"Батьки","family_name":"Чапюк Є. В. 23. 10. 1957","name_hidden":false},{"inn":"","inn_hidden":false,"family_name":"Чапюк І. В. 01. 09. 1988","relations_other":"","relations":"Брат/Сестра","name_hidden":false,"name_unclear":false},{"inn":"","inn_hidden":true,"relations":"Дитина","name_unclear":false,"family_name":"Бирич Т. В., 19. 04. 2005"}],"full_name_suggest":{"output":"Бирич Наталія Володимирівна","input":["Бирич Наталія Володимирівна","Наталія Володимирівна Бирич","Наталія Бирич"]},"patronymic":"Володимирівна"},"source":"VULYK","estate":{"29":[{"costs_rent":"","region":"Івано-Франківська область","costs_property":"","costs_rent_comment":"","address_hidden":true,"region_hidden":false,"space_comment":"","costs_property_comment":"","space_units":"м²","space":"2500","address":"Тисменицький р-н, с. Угринів"}],"30":[{"costs_rent":"","region":"Івано-Франківська область","costs_property":"","costs_rent_comment":"","address_hidden":true,"region_hidden":false,"space_comment":"","costs_property_comment":"","space_units":"м²","space":"150","address":"Тисменицький р-н, с. Угринів"},{"costs_rent":"","region":"Івано-Франківська область","costs_property":"","costs_rent_comment":"","space_comment":"1/3","costs_property_comment":"","space_units":"м²","space":"93.2","address":"Тлумацький р-н, село Королівка"}],"31":[{"space_hidden":false,"address_hidden":true,"region_hidden":false,"space_comment":"","space":"56.9","address":"Тисменицький р-н, с. Угринів","region":"Івано-Франківська область","costs_property":"","costs_rent_comment":"","space_units":"м²","costs_property_comment":"","costs_rent":""}]},"intro":{"declaration_year":"2014"}}},{"provider":"public-api.nazk.gov.ua","document":{"step_0":{"declarationType":"1","declarationYear1":"2015"},"step_1":{"city":"[Конфіденційна інформація]","region":"[Конфіденційна інформація]","street":"[Конфіденційна інформація]","country":"1","cityPath":"[Конфіденційна інформація]","cityType":"[Конфіденційна інформація]","district":"[Конфіденційна інформація]","lastname":"Бирич","postCode":"[Конфіденційна інформація]","postType":"","workPost":"Суддя","firstname":"Наталія","workPlace":"Коломийський міськрайонний суд Івано-Франківської області","middlename":"Володимирівна","streetType":"[Конфіденційна інформація]","changedName":false,"countryPath":"","eng_postCode":"","postCategory":"","actual_street":"[Конфіденційна інформація]","actual_cityPath":"[Конфіденційна інформація]","actual_cityType":"[Конфіденційна інформація]","actual_postCode":"[Конфіденційна інформація]","actual_streetType":"[Конфіденційна інформація]","previous_lastname":"","corruptionAffected":"Ні","eng_actualPostCode":"[Конфіденційна інформація]","previous_firstname":"","previous_middlename":"","responsiblePosition":"Суддя суду загальної юрисдикції, суддя Конституційного Суду України","sameRegLivingAddress":"[Конфіденційна інформація]","postType_extendedstatus":"1","eng_sameRegLivingAddress":"[Конфіденційна інформація]","housePartNum_extendedstatus":"1","postCategory_extendedstatus":"1"},"step_2":{"1477304404411":{"lastname":"Бирич","firstname":"Тарас","middlename":"Володимирович","changedName":false,"citizenship":"1","eng_lastname":"","eng_firstname":"","eng_middlename":"","isNotApplicable":"","subjectRelation":"син","previous_lastname":"","previous_firstname":"","previous_middlename":"","previous_eng_lastname":"","previous_eng_firstname":"","previous_eng_middlename":""}},"step_3":[],"step_4":[],"step_5":[],"step_6":[],"step_7":[],"step_8":[],"step_9":[],"step_10":[],"step_11":{"1477304814405":{"person":"1","rights":{"1":{"citizen":"","ua_city":"","ua_street":"[Конфіденційна інформація]","ua_lastname":"","ua_postCode":"","eng_fullname":"","eng_lastname":"","eng_postCode":"","rightBelongs":"1","ua_firstname":"","ukr_fullname":"","ukr_lastname":"","eng_firstname":"","ownershipType":"Власність","ua_middlename":"","ua_streetType":"[Конфіденційна інформація]","ukr_firstname":"","eng_middlename":"","otherOwnership":"","ukr_middlename":"","rights_cityPath":"","ua_company_name":"","eng_company_name":"","ukr_company_name":"","percent-ownership":"","ua_street_extendedstatus":"","ua_houseNum_extendedstatus":"","ua_postCode_extendedstatus":"","eng_postCode_extendedstatus":"","ua_middlename_extendedstatus":"","eng_middlename_extendedstatus":"","ukr_middlename_extendedstatus":"","ua_housePartNum_extendedstatus":"","ua_apartmentsNum_extendedstatus":""}},"objectType":"Заробітна плата отримана за основним місцем роботи","sizeIncome":"172621","incomeSource":"j","source_citizen":"Юридична особа, зареєстрована в Україні","otherObjectType":"","source_ua_lastname":"","source_eng_fullname":"","source_ua_firstname":"","source_ukr_fullname":"","source_ua_middlename":"","source_ua_company_name":"Територіальне управління Державної судової адміністрації України в Івано-Франківській області","source_eng_company_name":"","source_ukr_company_name":"","source_ua_sameRegLivingAddress":""},"1477306297963":{"person":"1","rights":{"1":{"citizen":"","ua_city":"","ua_street":"[Конфіденційна інформація]","ua_lastname":"","ua_postCode":"","eng_fullname":"","eng_lastname":"","eng_postCode":"","rightBelongs":"1","ua_firstname":"","ukr_fullname":"","ukr_lastname":"","eng_firstname":"","ownershipType":"Власність","ua_middlename":"","ua_streetType":"[Конфіденційна інформація]","ukr_firstname":"","eng_middlename":"","otherOwnership":"","ukr_middlename":"","rights_cityPath":"","ua_company_name":"","eng_company_name":"","ukr_company_name":"","percent-ownership":"","ua_street_extendedstatus":"","ua_houseNum_extendedstatus":"","ua_postCode_extendedstatus":"","eng_postCode_extendedstatus":"","ua_middlename_extendedstatus":"","eng_middlename_extendedstatus":"","ukr_middlename_extendedstatus":"","ua_housePartNum_extendedstatus":"","ua_apartmentsNum_extendedstatus":""}},"objectType":"Інше","sizeIncome":"6000","incomeSource":"j","source_citizen":"Громадянин України","otherObjectType":"Аліменти","source_ua_lastname":"Бирич","source_eng_fullname":"","source_ua_firstname":"Володимир","source_ukr_fullname":"","source_ua_middlename":"Іванович","source_ua_company_name":"","source_eng_company_name":"","source_ukr_company_name":"","source_ua_sameRegLivingAddress":false,"source_ua_birthday_extendedstatus":"0","source_ua_taxNumber_extendedstatus":"0","source_ua_regAddress_extendedstatus":"2"}},"step_12":[],"step_13":{"1477306903148":{"person":"1","currency":"UAH","guarantor":[],"dateOrigin":"14.06.2012","objectType":"Розмір сплачених коштів в рахунок основної суми позики (кредиту)","margin-emitent":"j","sizeObligation":"15873","emitent_citizen":"Юридична особа, зареєстрована в Україні","otherObjectType":"","guarantor_exist_":false,"guarantor_realty":[],"ownerThirdPerson":"","emitent_ua_lastname":"","emitent_eng_fullname":"","emitent_ua_firstname":"","emitent_ukr_fullname":"","emitent_ua_middlename":"","ownerThirdPersonThing":"","emitent_ua_company_name":"Публічне акціонерне товариство Комерційний банк \" ПриватБанк \"","guarantor_realty_exist_":false,"emitent_eng_company_name":"","emitent_ukr_company_name":"","emitent_ua_sameRegLivingAddress":"","emitent_ua_company_code_extendedstatus":"0"}},"step_14":[],"step_15":[],"step_16":[],"id":"4653f1d7-e823-4709-999b-e4d7ec1d6c4c"}}],"declarations":[{"income":{"5":{"value":"173710","family_hidden":false,"value_hidden":false,"family_comment":"","family":"7813","comment":""},"6":{"family_comment":"","value":"167710","family":"","comment":""},"7":{"family_comment":"","value":"","source_name":"","family":"","comment":""},"8":{"family_comment":"","value":"","family":"","comment":""},"9":{"family_comment":"","value":"","family":"","comment":""},"10":{"family_comment":"","value":"","family":"","comment":""},"11":{"family_comment":"","value":"","family":"","comment":""},"12":{"family_comment":"","value":"","family":"","comment":""},"13":{"family_comment":"","value":"6000","family":"","comment":""},"14":{"family_comment":"","value":"","family":"","comment":""},"15":{"family_comment":"","value":"","family":"","comment":""},"16":{"family_comment":"","value":"","family":"","comment":""},"17":{"family_comment":"","value":"","family":"","comment":""},"18":{"family_comment":"","value":"","family":"","comment":""},"19":{"family_comment":"","value":"","family":"","comment":""},"20":{"family_comment":"","value":"","family":"7813","comment":""}},"vehicle":{"40":[{"brand_info":"1600 куб. см.","sum":"","brand":"ВАЗ 211004","sum_comment":"","year":"2009","sum_rent_comment":"","sum_rent":""}]},"id":"vulyk_89_18","declaration":{"date":"2015-03-26T00:00:00","notfull":"","notfull_lostpages":"","url":"http://static.declarations.com.ua/declarations/chosen_ones/judges_batch/3021_byrych_nataliia_volodymyrivna.pdf"},"liabilities":{"54":{"sum_foreign_comment":"","sum":"","sum_comment":"","sum_foreign":""},"55":{"sum_foreign_comment":"","sum":"","sum_comment":"","sum_foreign":""},"56":{"sum_foreign_comment":"","sum":"","sum_comment":"","sum_unclear":false,"sum_foreign":""},"57":{"sum_foreign_comment":"","sum":"43032","sum_comment":"","sum_foreign":""},"58":{"sum_foreign_comment":"","sum":"24","sum_comment":"","sum_foreign":""},"59":{"sum_foreign_comment":"","sum":"","sum_comment":"","sum_foreign":""},"60":{"sum_foreign_comment":"","sum":"","sum_comment":"","sum_foreign":""},"61":{"sum_foreign_comment":"","sum":"","sum_comment":"","sum_foreign":""},"62":{"sum_foreign_comment":"","sum":"","sum_comment":"","sum_unclear":false,"sum_foreign":""},"63":{"sum_foreign_comment":"","sum":"","sum_comment":"","sum_foreign":""},"64":{"sum_foreign_comment":"","sum":"","sum_comment":"","sum_foreign":""}},"ft_src":"1600 куб. см.\n2009\nВАЗ 211004\nТисменицький р-н, с. Угринів\nІвано-Франківська область\n56.9\nІвано-Франківська область\nТисменицький р-н, с. Угринів\n150\nІвано-Франківська область\n1/3\nТлумацький р-н, село Королівка\n93.2\nІвано-Франківська область\nТисменицький р-н, с. Угринів\n2500\n2014\n167710\n6000\n7813\n173710\n7813\n1600 куб. см.\nВАЗ 211004\n2009\n2014\nВолодимирівна\nЧапюк Є. В. 23. 10. 1957\nБатьки\nБрат/Сестра\nЧапюк І. В. 01. 09. 1988\nБирич Т. В., 19. 04. 2005\nДитина\nБирич Наталія Володимирівна\nНаталія Володимирівна Бирич\nНаталія Бирич\nБирич Наталія Володимирівна\nБирич Наталія Володимирівна\nСело\nІвано-Франківська область\nУгринів\nТисменицький\nНаталія\nБирич\nІвано-Франківська область\nсуддя коломийського міськрайонного суду івано-франківської області\nЗагальний місцевий суд\n24\n43032\n167710\n7813\n6000\n173710\n7813\n2500\nІвано-Франківська область\nТисменицький р-н, с. Угринів\n150\nІвано-Франківська область\nТисменицький р-н, с. Угринів\n93.2\n1/3\nТлумацький р-н, село Королівка\nІвано-Франківська область\n56.9\nТисменицький р-н, с. Угринів\nІвано-Франківська область\n24\n43032\nЧапюк Є. В. 23. 10. 1957\nБатьки\nЧапюк І. В. 01. 09. 1988\nБрат/Сестра\nДитина\nБирич Т. В., 19. 04. 2005\nСело\nІвано-Франківська область\nУгринів\nТисменицький\nВолодимирівна\nБирич\nсуддя коломийського міськрайонного суду івано-франківської області\nІвано-Франківська область\nЗагальний місцевий суд\nБирич Наталія Володимирівна\nБирич Наталія Володимирівна\nНаталія Володимирівна Бирич\nНаталія Бирич\nБирич Наталія Володимирівна\nНаталія","general":{"inn":"","inn_hidden":true,"last_name":"Бирич","post":{"office":"Загальний місцевий суд","region":"Івано-Франківська область","post":"суддя коломийського міськрайонного суду івано-франківської області"},"name":"Наталія","full_name":"Бирич Наталія Володимирівна","family_raw":"","addresses":[{"place_district":"Тисменицький","place_address_hidden":true,"place_city":"Угринів","place_address":"","place_district_hidden":false,"place_city_type":"Село","place_city_hidden":false,"place_city_type_hidden":false,"place_hidden":false,"place":"Івано-Франківська область"}],"family":[{"inn":"","inn_hidden":true,"relations":"Батьки","family_name":"Чапюк Є. В. 23. 10. 1957","name_hidden":false},{"inn":"","inn_hidden":false,"family_name":"Чапюк І. В. 01. 09. 1988","relations_other":"","relations":"Брат/Сестра","name_hidden":false,"name_unclear":false},{"inn":"","inn_hidden":true,"relations":"Дитина","name_unclear":false,"family_name":"Бирич Т. В., 19. 04. 2005"}],"full_name_suggest":{"output":"Бирич Наталія Володимирівна","input":["Бирич Наталія Володимирівна","Наталія Володимирівна Бирич","Наталія Бирич"]},"patronymic":"Володимирівна"},"source":"VULYK","estate":{"29":[{"costs_rent":"","region":"Івано-Франківська область","costs_property":"","costs_rent_comment":"","address_hidden":true,"region_hidden":false,"space_comment":"","costs_property_comment":"","space_units":"м²","space":"2500","address":"Тисменицький р-н, с. Угринів"}],"30":[{"costs_rent":"","region":"Івано-Франківська область","costs_property":"","costs_rent_comment":"","address_hidden":true,"region_hidden":false,"space_comment":"","costs_property_comment":"","space_units":"м²","space":"150","address":"Тисменицький р-н, с. Угринів"},{"costs_rent":"","region":"Івано-Франківська область","costs_property":"","costs_rent_comment":"","space_comment":"1/3","costs_property_comment":"","space_units":"м²","space":"93.2","address":"Тлумацький р-н, село Королівка"}],"31":[{"space_hidden":false,"address_hidden":true,"region_hidden":false,"space_comment":"","space":"56.9","address":"Тисменицький р-н, с. Угринів","region":"Івано-Франківська область","costs_property":"","costs_rent_comment":"","space_units":"м²","costs_property_comment":"","costs_rent":""}]},"intro":{"declaration_year":"2014"}}],"declarationsLength":1,"analytics":[{"y":2014,"i":173710,"fi":7813,"ff":56.9,"ffa":1,"fh":243.2,"fha":2,"fl":2500,"fla":1},{"y":2015,"i":178621}]}