{"2010":"Синято Людмила Іванівна","2016":1,"Department":"Долинський районний суд Кіровоградської області","Region":"Кіровоградська область","Position":"Голова Долинського районного суду Кіровоградської області","Name":"Бойко Павло Миколайович","Link":"https://drive.google.com/open?id=0BygiyWAl79DMajBuTG1PUXpBMmM","Note":"У меня","AdditionalNote":"","field8":"","field9":"","field10":"","Кількість справ":"","Оскаржені":"","Кількість скарг":0,"Кількість дисциплінарних стягнень":"","Клейма":3,"Фото":"","Як живе":"","key":"boyko_pavlo_mikolayovich","allDeclarations":[{"provider":"declarations.com.ua","document":{"income":{"5":{"family_comment":"","value":"258731","family":"24076","comment":""},"6":{"value":"246551","comment_hidden":false,"family_comment":"","family":"24076","comment":"","family_comment_hidden":false},"7":{"value":"","comment_unclear":false,"family_comment":"","source_name":"","family":"","comment":""},"8":{"family_comment":"","value":"","family":"","comment":""},"9":{"family_comment":"","value":"","family":"","comment":""},"10":{"family_comment":"","value":"12180","family":"","comment":"","family_hidden":false},"11":{"family_comment":"","value":"","family":"","comment":""},"12":{"family_comment":"","value":"","family":"","comment":""},"13":{"family_comment":"","value":"","family":"","comment":""},"14":{"family_comment":"","value":"","family":"","comment":""},"15":{"family_comment":"","value":"","family":"","comment":""},"16":{"family_comment":"","value":"","family":"","comment":""},"17":{"family_comment":"","value":"","family":"","comment":""},"18":{"family_comment":"","value":"","family":"","comment":""},"19":{"family_comment":"","value":"","family":"","comment":""},"20":{"value":"","value_unclear":false,"family_hidden":false,"family_comment":"","family":"","comment":""}},"vehicle":{"35":[{"brand_info":"1600 куб. см.","sum_rent_comment":"","brand":"Renault Fluence","sum_comment":"","year":"2010","brand_info_unclear":false,"sum":"","sum_rent":""}]},"id":"vulyk_83_17","declaration":{"additional_info_text":"","notfull_lostpages":"","date":"2015-03-10T00:00:00","notfull":"","additional_info":"","url":"http://static.declarations.com.ua/declarations/chosen_ones/judges_batch/2287_boiko_pavlo_mykolaiovych.pdf"},"liabilities":{"54":{"sum_foreign_comment":"","sum":"","sum_comment":"","sum_foreign":""},"55":{"sum_foreign_comment":"","sum":"","sum_comment":"","sum_foreign":""},"56":{"sum_foreign_comment":"","sum":"12000","sum_comment":"","sum_foreign":""},"57":{"sum_foreign_comment":"","sum":"12862","sum_comment":"","sum_foreign":""},"58":{"sum_foreign_comment":"","sum":"","sum_comment":"","sum_foreign":""},"59":{"sum_foreign_comment":"","sum":"","sum_comment":"","sum_foreign":""},"60":{"sum_foreign_comment":"","sum":"","sum_comment":"","sum_foreign":""},"61":{"sum_foreign_comment":"","sum":"","sum_comment":"","sum_foreign":""},"62":{"sum_foreign_comment":"","sum":"","sum_comment":"","sum_foreign":""},"63":{"sum_foreign_comment":"","sum":"","sum_comment":"","sum_foreign":""},"64":{"sum_foreign_comment":"","sum":"","sum_comment":"","sum_foreign":""}},"ft_src":"1600 куб. см.\n2010\nRenault Fluence\n55\nКіровоградська область\n1900\nКіровоградська область\nм. Долинське\n2014\n24076\n246551\n12180\n24076\n258731\n1600 куб. см.\nRenault Fluence\n2010\nКіровоградська область\n1900\n55\nКіровоградська область\nм. Долинське\nПодружжя\nБойко І. Ю. 1962 р. н\nДитина\nБойко В. П. 1989 р. н\nБойко Павло Миколайович\nПавло Миколайович Бойко\nПавло Бойко\nБойко Павло Миколайович\nБойко Павло Миколайович\nПавло\nМиколайович\nЗагальний місцевий суд\nКіровоградська область\nголова долинського районного суду кіровоградської області\nБойко\nДолинська\nКіровоградська область\n12862\n12000\n246551\n24076\n258731\n24076\n12180\n2014\n12862\n12000\nБойко І. Ю. 1962 р. н\nПодружжя\nБойко В. П. 1989 р. н\nДитина\nМиколайович\nБойко\nПавло\nБойко Павло Миколайович\nПавло Миколайович Бойко\nПавло Бойко\nБойко Павло Миколайович\nКіровоградська область\nДолинська\nКіровоградська область\nЗагальний місцевий суд\nголова долинського районного суду кіровоградської області\nБойко Павло Миколайович","general":{"inn":"","name":"Павло","last_name":"Бойко","family":[{"inn":"","inn_hidden":true,"relations_hidden":false,"family_name":"Бойко І. Ю. 1962 р. н","relations_other":"","relations":"Подружжя","name_hidden":false,"name_unclear":false},{"inn":"","inn_hidden":false,"family_name":"Бойко В. П. 1989 р. н","relations_other":"","relations":"Дитина","name_hidden":false,"name_unclear":false}],"inn_hidden":true,"family_raw":"","inn_unclear":false,"post":{"post_unclear":false,"post":"голова долинського районного суду кіровоградської області","candidate":"","region":"Кіровоградська область","office":"Загальний місцевий суд","office_unclear":false},"full_name_suggest":{"output":"Бойко Павло Миколайович","input":["Бойко Павло Миколайович","Павло Миколайович Бойко","Павло Бойко"]},"full_name":"Бойко Павло Миколайович","addresses":[{"place_city_type_unclear":false,"place_city_type_hidden":false,"place_district_hidden":false,"place_city_type":"Місто","place_city_hidden":false,"place_address_unclear":false,"place_address":"","place":"Кіровоградська область","place_district":"","place_address_hidden":true,"place_hidden":false,"place_city_unclear":false,"place_city":"Долинська"}],"patronymic":"Миколайович","last_name_unclear":false},"source":"VULYK","estate":{"24":[{"space_hidden":true,"costs":"","costs_comment":"","address_hidden":false,"region_hidden":false,"space_comment":"","space":"","address":"","region":"","costs_rent_comment":"","space_units":"м²","costs_rent":""}],"25":[{"region_unclear":false,"space_hidden":true,"costs":"","costs_comment":"","address_hidden":true,"region_hidden":false,"space_comment":"","space_unclear":true,"space":"","address":"м. Долинське","region":"Кіровоградська область","costs_rent_comment":"","space_comment_unclear":false,"space_units":"м²","costs_rent":""}],"29":[{"address_hidden":true,"region_hidden":false,"space_comment":"","space":"1900","address":"","region":"Кіровоградська область","costs_property":"","costs_rent_comment":"","space_comment_unclear":false,"space_units":"м²","costs_property_comment":"","costs_rent":""}],"30":[{"address_hidden":false,"region_hidden":true,"space_comment":"","space":"55","address":"","region":"","costs_property":"","costs_rent_comment":"","space_comment_unclear":false,"space_units":"м²","costs_property_comment":"","costs_rent":""}]},"intro":{"declaration_year":"2014"}}}],"declarations":[{"income":{"5":{"family_comment":"","value":"258731","family":"24076","comment":""},"6":{"value":"246551","comment_hidden":false,"family_comment":"","family":"24076","comment":"","family_comment_hidden":false},"7":{"value":"","comment_unclear":false,"family_comment":"","source_name":"","family":"","comment":""},"8":{"family_comment":"","value":"","family":"","comment":""},"9":{"family_comment":"","value":"","family":"","comment":""},"10":{"family_comment":"","value":"12180","family":"","comment":"","family_hidden":false},"11":{"family_comment":"","value":"","family":"","comment":""},"12":{"family_comment":"","value":"","family":"","comment":""},"13":{"family_comment":"","value":"","family":"","comment":""},"14":{"family_comment":"","value":"","family":"","comment":""},"15":{"family_comment":"","value":"","family":"","comment":""},"16":{"family_comment":"","value":"","family":"","comment":""},"17":{"family_comment":"","value":"","family":"","comment":""},"18":{"family_comment":"","value":"","family":"","comment":""},"19":{"family_comment":"","value":"","family":"","comment":""},"20":{"value":"","value_unclear":false,"family_hidden":false,"family_comment":"","family":"","comment":""}},"vehicle":{"35":[{"brand_info":"1600 куб. см.","sum_rent_comment":"","brand":"Renault Fluence","sum_comment":"","year":"2010","brand_info_unclear":false,"sum":"","sum_rent":""}]},"id":"vulyk_83_17","declaration":{"additional_info_text":"","notfull_lostpages":"","date":"2015-03-10T00:00:00","notfull":"","additional_info":"","url":"http://static.declarations.com.ua/declarations/chosen_ones/judges_batch/2287_boiko_pavlo_mykolaiovych.pdf"},"liabilities":{"54":{"sum_foreign_comment":"","sum":"","sum_comment":"","sum_foreign":""},"55":{"sum_foreign_comment":"","sum":"","sum_comment":"","sum_foreign":""},"56":{"sum_foreign_comment":"","sum":"12000","sum_comment":"","sum_foreign":""},"57":{"sum_foreign_comment":"","sum":"12862","sum_comment":"","sum_foreign":""},"58":{"sum_foreign_comment":"","sum":"","sum_comment":"","sum_foreign":""},"59":{"sum_foreign_comment":"","sum":"","sum_comment":"","sum_foreign":""},"60":{"sum_foreign_comment":"","sum":"","sum_comment":"","sum_foreign":""},"61":{"sum_foreign_comment":"","sum":"","sum_comment":"","sum_foreign":""},"62":{"sum_foreign_comment":"","sum":"","sum_comment":"","sum_foreign":""},"63":{"sum_foreign_comment":"","sum":"","sum_comment":"","sum_foreign":""},"64":{"sum_foreign_comment":"","sum":"","sum_comment":"","sum_foreign":""}},"ft_src":"1600 куб. см.\n2010\nRenault Fluence\n55\nКіровоградська область\n1900\nКіровоградська область\nм. Долинське\n2014\n24076\n246551\n12180\n24076\n258731\n1600 куб. см.\nRenault Fluence\n2010\nКіровоградська область\n1900\n55\nКіровоградська область\nм. Долинське\nПодружжя\nБойко І. Ю. 1962 р. н\nДитина\nБойко В. П. 1989 р. н\nБойко Павло Миколайович\nПавло Миколайович Бойко\nПавло Бойко\nБойко Павло Миколайович\nБойко Павло Миколайович\nПавло\nМиколайович\nЗагальний місцевий суд\nКіровоградська область\nголова долинського районного суду кіровоградської області\nБойко\nДолинська\nКіровоградська область\n12862\n12000\n246551\n24076\n258731\n24076\n12180\n2014\n12862\n12000\nБойко І. Ю. 1962 р. н\nПодружжя\nБойко В. П. 1989 р. н\nДитина\nМиколайович\nБойко\nПавло\nБойко Павло Миколайович\nПавло Миколайович Бойко\nПавло Бойко\nБойко Павло Миколайович\nКіровоградська область\nДолинська\nКіровоградська область\nЗагальний місцевий суд\nголова долинського районного суду кіровоградської області\nБойко Павло Миколайович","general":{"inn":"","name":"Павло","last_name":"Бойко","family":[{"inn":"","inn_hidden":true,"relations_hidden":false,"family_name":"Бойко І. Ю. 1962 р. н","relations_other":"","relations":"Подружжя","name_hidden":false,"name_unclear":false},{"inn":"","inn_hidden":false,"family_name":"Бойко В. П. 1989 р. н","relations_other":"","relations":"Дитина","name_hidden":false,"name_unclear":false}],"inn_hidden":true,"family_raw":"","inn_unclear":false,"post":{"post_unclear":false,"post":"голова долинського районного суду кіровоградської області","candidate":"","region":"Кіровоградська область","office":"Загальний місцевий суд","office_unclear":false},"full_name_suggest":{"output":"Бойко Павло Миколайович","input":["Бойко Павло Миколайович","Павло Миколайович Бойко","Павло Бойко"]},"full_name":"Бойко Павло Миколайович","addresses":[{"place_city_type_unclear":false,"place_city_type_hidden":false,"place_district_hidden":false,"place_city_type":"Місто","place_city_hidden":false,"place_address_unclear":false,"place_address":"","place":"Кіровоградська область","place_district":"","place_address_hidden":true,"place_hidden":false,"place_city_unclear":false,"place_city":"Долинська"}],"patronymic":"Миколайович","last_name_unclear":false},"source":"VULYK","estate":{"24":[{"space_hidden":true,"costs":"","costs_comment":"","address_hidden":false,"region_hidden":false,"space_comment":"","space":"","address":"","region":"","costs_rent_comment":"","space_units":"м²","costs_rent":""}],"25":[{"region_unclear":false,"space_hidden":true,"costs":"","costs_comment":"","address_hidden":true,"region_hidden":false,"space_comment":"","space_unclear":true,"space":"","address":"м. Долинське","region":"Кіровоградська область","costs_rent_comment":"","space_comment_unclear":false,"space_units":"м²","costs_rent":""}],"29":[{"address_hidden":true,"region_hidden":false,"space_comment":"","space":"1900","address":"","region":"Кіровоградська область","costs_property":"","costs_rent_comment":"","space_comment_unclear":false,"space_units":"м²","costs_property_comment":"","costs_rent":""}],"30":[{"address_hidden":false,"region_hidden":true,"space_comment":"","space":"55","address":"","region":"","costs_property":"","costs_rent_comment":"","space_comment_unclear":false,"space_units":"м²","costs_property_comment":"","costs_rent":""}]},"intro":{"declaration_year":"2014"}}],"declarationsLength":1,"analytics":[{"y":2014,"i":258731,"c":1,"ka":1,"ha":1,"fi":24076,"fh":55,"fha":1,"fl":1900,"fla":1}]}