{"2010":"","2016":"","Department":"Малиновський районний суд м. Одеси","Region":"Одеська область","Position":"Суддя Малиновського районного суду м. Одеси","Name":"Буран Олексій Миколайович","Link":"https://drive.google.com/open?id=0BygiyWAl79DMU3cxSk5CRGxyNFk","Note":"У меня","AdditionalNote":"","field8":"","field9":"","field10":"","Кількість справ":"","Оскаржені":"","Кількість скарг":6,"Кількість дисциплінарних стягнень":"","Клейма":"","Фото":"http://picua.org/img/2016-10/24/08z3noknzvkifrbvuzpt4n8dr.jpg","Як живе":"","key":"buran_oleksiy_mikolayovich","allDeclarations":[{"provider":"declarations.com.ua","document":{"income":{"5":{"value":"230771.05","family_comment":"","value_unclear":false,"comment_hidden":false,"family_hidden":false,"value_hidden":false,"family_unclear":false,"family":"","comment":""},"6":{"value":"230771.05","family_comment":"","value_unclear":false,"family_hidden":false,"family_unclear":false,"comment_unclear":false,"comment":"","family":""},"7":{"source_name_unclear":false,"value":"","value_hidden":false,"family_comment":"","source_name":"","family":"","comment":"","source_name_hidden":false},"8":{"value":"","family_hidden":false,"value_hidden":false,"family_comment":"","family":"","comment":""},"9":{"value":"","family_comment":"","value_unclear":false,"family_hidden":false,"value_hidden":false,"family_unclear":false,"family":"","comment":""},"10":{"family_comment":"","value":"","family":"","comment":""},"11":{"family_comment":"","value":"","family":"","comment":""},"12":{"family_comment":"","value":"","family":"","comment":""},"13":{"family_comment":"","value":"","family":"","comment":""},"14":{"family_comment":"","value":"","family":"","comment":""},"15":{"family_comment":"","value":"","family":"","comment":""},"16":{"value":"","family_comment":"","value_unclear":false,"family_unclear":false,"family":"","comment":""},"17":{"family_comment":"","value":"","family":"","comment":""},"18":{"family_comment":"","value":"","family":"","comment":""},"19":{"family_comment":"","value":"","comment_unclear":false,"family":"","comment":""},"20":{"value":"","family_comment":"","value_unclear":false,"comment_hidden":false,"family_hidden":false,"family":"","value_hidden":false,"family_unclear":false,"comment_unclear":false,"comment":"","family_comment_unclear":false}},"vehicle":{"35":[{"brand_info":"2800 куб. см., 3876 мм","sum_rent_comment":"","brand":"Nissan Patrol","sum_comment":"","brand_unclear":false,"year":"1994","brand_info_unclear":false,"sum":"","sum_rent":""}],"39":[{"brand_info":"650 куб. см., мотоцикл","sum":"","brand":"Suzuki V-Strom","sum_comment":"","brand_unclear":false,"year":"2009","brand_hidden":false,"brand_info_hidden":false,"brand_info_unclear":true,"sum_rent_comment":"","sum_rent":""},{"brand_info":"","sum_rent_comment":"","brand":"Прицеп Вестфалия","sum_comment":"","year":"1990","sum":"","sum_rent":""},{"brand_info":"","sum_rent_comment":"","brand":"Прицеп Одиссей","sum_comment":"","year":"1994","sum":"","sum_rent":""}]},"id":"vulyk_63_80","declaration":{"additional_info_text":"","notfull_lostpages":"","date":"2015-03-30T00:00:00","notfull":"","additional_info":"","url":"http://static.declarations.com.ua/declarations/chosen_ones/mega_batch/buran_oleksii_mykolaiovych.pdf"},"liabilities":{"54":{"sum_foreign_comment":"","sum":"","sum_comment":"","sum_unclear":false,"sum_foreign":""},"55":{"sum_foreign_comment":"","sum":"","sum_comment":"","sum_foreign":""},"56":{"sum_foreign_comment":"","sum":"12500","sum_comment":"","sum_unclear":false,"sum_foreign":""},"57":{"sum_foreign_comment":"","sum":"","sum_comment":"","sum_comment_hidden":false,"sum_unclear":false,"sum_foreign":""},"58":{"sum_foreign_comment":"","sum_comment_hidden":false,"sum":"","sum_comment":"","sum_foreign":""},"59":{"sum_foreign_comment":"","sum":"","sum_comment":"","sum_foreign":""},"60":{"sum_foreign_comment":"","sum":"","sum_comment":"","sum_comment_unclear":false,"sum_foreign":""},"61":{"sum_foreign_comment":"","sum":"","sum_comment":"","sum_unclear":false,"sum_foreign":""},"62":{"sum_foreign_comment":"","sum":"","sum_comment":"","sum_unclear":false,"sum_foreign":""},"63":{"sum_foreign_comment":"","sum":"","sum_comment":"","sum_hidden":false,"sum_comment_hidden":false,"sum_unclear":false,"sum_foreign":""},"64":{"sum_foreign_comment":"","sum_comment_hidden":false,"sum":"","sum_comment":"","sum_foreign":""}},"ft_src":"12500\nсуддя малиновського районного суду м. одеса\nОдеська область\nЗагальний місцевий суд\nОлексій\nБуран Катерина Олексіївна\nДитина\nБуран Марія Олексіївна\nДитина\nМиколайович\nБуран\nБуран Олексій Миколайович\nБуран Олексій Миколайович\nОлексій Миколайович Буран\nОлексій Буран\nБуран Олексій Миколайович\nSuzuki V-Strom\n650 куб. см., мотоцикл\n2009\n1990\nПрицеп Вестфалия\n1994\nПрицеп Одиссей\n1994\nNissan Patrol\n2800 куб. см., 3876 мм\n25\n61\n2014\n230771.05\n230771.05\n2800 куб. см., 3876 мм\n1994\nNissan Patrol\n650 куб. см., мотоцикл\n2009\nSuzuki V-Strom\nПрицеп Вестфалия\n1990\nПрицеп Одиссей\n1994\n25\n61\nБуран Олексій Миколайович\nОлексій Миколайович Буран\nОлексій Буран\nБуран Олексій Миколайович\nОлексій\nДитина\nБуран Катерина Олексіївна\nДитина\nБуран Марія Олексіївна\nБуран Олексій Миколайович\nБуран\nЗагальний місцевий суд\nОдеська область\nсуддя малиновського районного суду м. одеса\nМиколайович\n12500\n230771.05\n230771.05\n2014\n12500\nДитина\nБуран Катерина Олексіївна\nДитина\nБуран Марія Олексіївна\nМиколайович\nБуран\nБуран Олексій Миколайович\nОлексій Миколайович Буран\nОлексій Буран\nБуран Олексій Миколайович\nОлексій\nОдеська область\nсуддя малиновського районного суду м. одеса\nЗагальний місцевий суд\nБуран Олексій Миколайович\nSuzuki V-Strom\n650 куб. см., мотоцикл\n2009\nПрицеп Вестфалия\n1990\nПрицеп Одиссей\n1994\n1994\n2800 куб. см., 3876 мм\nNissan Patrol\n230771.05\n230771.05\n61\n25\n2014","general":{"name_hidden":false,"name":"Олексій","patronymic_unclear":false,"last_name_hidden":false,"inn":"","family":[{"inn":"","inn_hidden":true,"relations_unclear":false,"relations_hidden":false,"relations_other":"","relations":"Дитина","name_hidden":false,"inn_unclear":false,"family_name":"Буран Катерина Олексіївна","name_unclear":false},{"inn":"","relations":"Дитина","relations_unclear":false,"family_name":"Буран Марія Олексіївна","inn_hidden":true,"relations_other":"","name_hidden":false,"inn_unclear":false,"name_unclear":false}],"patronymic":"Миколайович","inn_hidden":true,"family_raw":"","inn_unclear":false,"post":{"post_unclear":false,"region_unclear":false,"region":"Одеська область","office_hidden":false,"region_hidden":false,"post":"суддя малиновського районного суду м. одеса","office_unclear":false,"office":"Загальний місцевий суд"},"last_name_unclear":false,"full_name":"Буран Олексій Миколайович","last_name":"Буран","full_name_suggest":{"output":"Буран Олексій Миколайович","input":["Буран Олексій Миколайович","Олексій Миколайович Буран","Олексій Буран"]},"name_unclear":false},"source":"VULYK","estate":{"25":[{"region_unclear":false,"space_unclear":false,"costs":"","costs_comment":"","costs_hidden":false,"address_hidden":true,"region_hidden":true,"space_comment":"","space_hidden":false,"space":"61","space_units_hidden":false,"region":"","address_unclear":false,"costs_rent_comment":"","costs_rent_hidden":false,"space_comment_unclear":false,"costs_rent_comment_hidden":false,"space_units":"м²","address":"","costs_comment_hidden":false,"costs_rent":""}],"26":[{"costs":"","costs_comment":"","costs_hidden":false,"address_hidden":true,"region_hidden":true,"space_comment":"","space":"25","address":"","region":"","costs_rent_comment":"","costs_rent_hidden":false,"costs_rent_comment_hidden":false,"space_units":"м²","costs_comment_hidden":false,"costs_rent":""}]},"intro":{"declaration_year":"2014","isnotdeclaration":"","declaration_year_unclear":false}}}],"declarations":[{"income":{"5":{"value":"230771.05","family_comment":"","value_unclear":false,"comment_hidden":false,"family_hidden":false,"value_hidden":false,"family_unclear":false,"family":"","comment":""},"6":{"value":"230771.05","family_comment":"","value_unclear":false,"family_hidden":false,"family_unclear":false,"comment_unclear":false,"comment":"","family":""},"7":{"source_name_unclear":false,"value":"","value_hidden":false,"family_comment":"","source_name":"","family":"","comment":"","source_name_hidden":false},"8":{"value":"","family_hidden":false,"value_hidden":false,"family_comment":"","family":"","comment":""},"9":{"value":"","family_comment":"","value_unclear":false,"family_hidden":false,"value_hidden":false,"family_unclear":false,"family":"","comment":""},"10":{"family_comment":"","value":"","family":"","comment":""},"11":{"family_comment":"","value":"","family":"","comment":""},"12":{"family_comment":"","value":"","family":"","comment":""},"13":{"family_comment":"","value":"","family":"","comment":""},"14":{"family_comment":"","value":"","family":"","comment":""},"15":{"family_comment":"","value":"","family":"","comment":""},"16":{"value":"","family_comment":"","value_unclear":false,"family_unclear":false,"family":"","comment":""},"17":{"family_comment":"","value":"","family":"","comment":""},"18":{"family_comment":"","value":"","family":"","comment":""},"19":{"family_comment":"","value":"","comment_unclear":false,"family":"","comment":""},"20":{"value":"","family_comment":"","value_unclear":false,"comment_hidden":false,"family_hidden":false,"family":"","value_hidden":false,"family_unclear":false,"comment_unclear":false,"comment":"","family_comment_unclear":false}},"vehicle":{"35":[{"brand_info":"2800 куб. см., 3876 мм","sum_rent_comment":"","brand":"Nissan Patrol","sum_comment":"","brand_unclear":false,"year":"1994","brand_info_unclear":false,"sum":"","sum_rent":""}],"39":[{"brand_info":"650 куб. см., мотоцикл","sum":"","brand":"Suzuki V-Strom","sum_comment":"","brand_unclear":false,"year":"2009","brand_hidden":false,"brand_info_hidden":false,"brand_info_unclear":true,"sum_rent_comment":"","sum_rent":""},{"brand_info":"","sum_rent_comment":"","brand":"Прицеп Вестфалия","sum_comment":"","year":"1990","sum":"","sum_rent":""},{"brand_info":"","sum_rent_comment":"","brand":"Прицеп Одиссей","sum_comment":"","year":"1994","sum":"","sum_rent":""}]},"id":"vulyk_63_80","declaration":{"additional_info_text":"","notfull_lostpages":"","date":"2015-03-30T00:00:00","notfull":"","additional_info":"","url":"http://static.declarations.com.ua/declarations/chosen_ones/mega_batch/buran_oleksii_mykolaiovych.pdf"},"liabilities":{"54":{"sum_foreign_comment":"","sum":"","sum_comment":"","sum_unclear":false,"sum_foreign":""},"55":{"sum_foreign_comment":"","sum":"","sum_comment":"","sum_foreign":""},"56":{"sum_foreign_comment":"","sum":"12500","sum_comment":"","sum_unclear":false,"sum_foreign":""},"57":{"sum_foreign_comment":"","sum":"","sum_comment":"","sum_comment_hidden":false,"sum_unclear":false,"sum_foreign":""},"58":{"sum_foreign_comment":"","sum_comment_hidden":false,"sum":"","sum_comment":"","sum_foreign":""},"59":{"sum_foreign_comment":"","sum":"","sum_comment":"","sum_foreign":""},"60":{"sum_foreign_comment":"","sum":"","sum_comment":"","sum_comment_unclear":false,"sum_foreign":""},"61":{"sum_foreign_comment":"","sum":"","sum_comment":"","sum_unclear":false,"sum_foreign":""},"62":{"sum_foreign_comment":"","sum":"","sum_comment":"","sum_unclear":false,"sum_foreign":""},"63":{"sum_foreign_comment":"","sum":"","sum_comment":"","sum_hidden":false,"sum_comment_hidden":false,"sum_unclear":false,"sum_foreign":""},"64":{"sum_foreign_comment":"","sum_comment_hidden":false,"sum":"","sum_comment":"","sum_foreign":""}},"ft_src":"12500\nсуддя малиновського районного суду м. одеса\nОдеська область\nЗагальний місцевий суд\nОлексій\nБуран Катерина Олексіївна\nДитина\nБуран Марія Олексіївна\nДитина\nМиколайович\nБуран\nБуран Олексій Миколайович\nБуран Олексій Миколайович\nОлексій Миколайович Буран\nОлексій Буран\nБуран Олексій Миколайович\nSuzuki V-Strom\n650 куб. см., мотоцикл\n2009\n1990\nПрицеп Вестфалия\n1994\nПрицеп Одиссей\n1994\nNissan Patrol\n2800 куб. см., 3876 мм\n25\n61\n2014\n230771.05\n230771.05\n2800 куб. см., 3876 мм\n1994\nNissan Patrol\n650 куб. см., мотоцикл\n2009\nSuzuki V-Strom\nПрицеп Вестфалия\n1990\nПрицеп Одиссей\n1994\n25\n61\nБуран Олексій Миколайович\nОлексій Миколайович Буран\nОлексій Буран\nБуран Олексій Миколайович\nОлексій\nДитина\nБуран Катерина Олексіївна\nДитина\nБуран Марія Олексіївна\nБуран Олексій Миколайович\nБуран\nЗагальний місцевий суд\nОдеська область\nсуддя малиновського районного суду м. одеса\nМиколайович\n12500\n230771.05\n230771.05\n2014\n12500\nДитина\nБуран Катерина Олексіївна\nДитина\nБуран Марія Олексіївна\nМиколайович\nБуран\nБуран Олексій Миколайович\nОлексій Миколайович Буран\nОлексій Буран\nБуран Олексій Миколайович\nОлексій\nОдеська область\nсуддя малиновського районного суду м. одеса\nЗагальний місцевий суд\nБуран Олексій Миколайович\nSuzuki V-Strom\n650 куб. см., мотоцикл\n2009\nПрицеп Вестфалия\n1990\nПрицеп Одиссей\n1994\n1994\n2800 куб. см., 3876 мм\nNissan Patrol\n230771.05\n230771.05\n61\n25\n2014","general":{"name_hidden":false,"name":"Олексій","patronymic_unclear":false,"last_name_hidden":false,"inn":"","family":[{"inn":"","inn_hidden":true,"relations_unclear":false,"relations_hidden":false,"relations_other":"","relations":"Дитина","name_hidden":false,"inn_unclear":false,"family_name":"Буран Катерина Олексіївна","name_unclear":false},{"inn":"","relations":"Дитина","relations_unclear":false,"family_name":"Буран Марія Олексіївна","inn_hidden":true,"relations_other":"","name_hidden":false,"inn_unclear":false,"name_unclear":false}],"patronymic":"Миколайович","inn_hidden":true,"family_raw":"","inn_unclear":false,"post":{"post_unclear":false,"region_unclear":false,"region":"Одеська область","office_hidden":false,"region_hidden":false,"post":"суддя малиновського районного суду м. одеса","office_unclear":false,"office":"Загальний місцевий суд"},"last_name_unclear":false,"full_name":"Буран Олексій Миколайович","last_name":"Буран","full_name_suggest":{"output":"Буран Олексій Миколайович","input":["Буран Олексій Миколайович","Олексій Миколайович Буран","Олексій Буран"]},"name_unclear":false},"source":"VULYK","estate":{"25":[{"region_unclear":false,"space_unclear":false,"costs":"","costs_comment":"","costs_hidden":false,"address_hidden":true,"region_hidden":true,"space_comment":"","space_hidden":false,"space":"61","space_units_hidden":false,"region":"","address_unclear":false,"costs_rent_comment":"","costs_rent_hidden":false,"space_comment_unclear":false,"costs_rent_comment_hidden":false,"space_units":"м²","address":"","costs_comment_hidden":false,"costs_rent":""}],"26":[{"costs":"","costs_comment":"","costs_hidden":false,"address_hidden":true,"region_hidden":true,"space_comment":"","space":"25","address":"","region":"","costs_rent_comment":"","costs_rent_hidden":false,"costs_rent_comment_hidden":false,"space_units":"м²","costs_comment_hidden":false,"costs_rent":""}]},"intro":{"declaration_year":"2014","isnotdeclaration":"","declaration_year_unclear":false}}],"declarationsLength":1,"analytics":[{"y":2014,"i":230771.05,"c":1,"k":61,"ka":1}]}