{"2010":"","2016":"","Department":"Костянтинівський міськрайонний суд Донецької області","Region":"Донецька область","Position":"Суддя Костянтинівського міськрайонного суду Донецької області","Name":"Чернецький Володимир Анатолійович","Link":"","Note":9,"AdditionalNote":13,"field8":"","field9":"","field10":"","Кількість справ":"","Оскаржені":"","Кількість скарг":0,"Кількість дисциплінарних стягнень":"","Клейма":3,"Фото":"","Як живе":"","key":"cherneckiy_volodimir_anatoliyovich","allDeclarations":[{"provider":"declarations.com.ua","document":{"income":{"5":{"family_comment":"","value":"225003","value_unclear":false,"family":"","comment":""},"6":{"value":"219096","value_unclear":false,"family_hidden":false,"family_comment":"","family":"","comment":""},"7":{"source_name_unclear":false,"value":"","family_comment":"","source_name":"","family":"","comment":""},"8":{"family_comment":"","value":"","family":"","comment":""},"9":{"family_comment":"","value":"","family":"","comment":""},"10":{"family_comment":"","value":"12180","family":"","comment":""},"11":{"family_comment":"","value":"","comment_unclear":false,"family":"","comment":""},"12":{"family_comment":"","value":"","family":"","comment":""},"13":{"family_comment":"","value":"","family":"","comment":""},"14":{"family_comment":"","value":"","family":"","comment":""},"15":{"family_comment":"","value":"","family":"","comment":""},"16":{"family_comment":"","value":"","family":"","comment":""},"17":{"family_comment":"","value":"","family":"","comment":""},"18":{"family_comment":"","value":"","family":"","comment":""},"19":{"family_comment":"","value":"","family":"","comment":""},"20":{"value":"5907","family_comment":"","value_unclear":false,"family_unclear":false,"comment_unclear":false,"comment":"","family":""}},"vehicle":{"35":[{"brand_info":"ЗАЗ, Т13110, 1299 , оренда чи інше право користування","sum_rent_comment":"","brand":"Daewoo","sum_comment":"","brand_unclear":false,"year":"2006","sum_rent_unclear":false,"brand_info_hidden":false,"brand_info_unclear":false,"sum":"","sum_rent":""}]},"id":"vulyk_101_138","declaration":{"additional_info_text":"","notfull_lostpages":"","date":"2016-03-18T00:00:00","notfull":"","additional_info":"","url":"http://static.declarations.com.ua/declarations/chosen_ones/judges_batch/853_chernetskyi_volodymyr_anatoliiovych_2015.pdf"},"liabilities":{"54":{"sum_foreign_comment":"","sum":"","sum_comment":"","sum_comment_unclear":false,"sum_hidden":false,"sum_comment_hidden":false,"sum_unclear":false,"sum_foreign":""},"55":{"sum_foreign_comment":"","sum":"","sum_comment":"","sum_foreign":""},"56":{"sum_foreign_comment":"","sum":"","sum_comment":"","sum_comment_hidden":false,"sum_unclear":false,"sum_foreign":""},"57":{"sum_foreign_comment":"","sum":"","sum_comment":"","sum_hidden":false,"sum_comment_hidden":false,"sum_unclear":false,"sum_foreign":""},"58":{"sum_foreign_comment":"","sum":"","sum_comment":"","sum_comment_unclear":false,"sum_hidden":false,"sum_comment_hidden":false,"sum_unclear":false,"sum_foreign":""},"59":{"sum_foreign_comment":"","sum":"","sum_comment":"","sum_foreign":""},"60":{"sum_foreign_comment":"","sum":"","sum_comment":"","sum_hidden":false,"sum_comment_hidden":false,"sum_unclear":false,"sum_foreign":""},"61":{"sum_foreign_comment":"","sum":"","sum_comment":"","sum_foreign":""},"62":{"sum_foreign_comment":"","sum":"","sum_comment":"","sum_comment_unclear":false,"sum_foreign":""},"63":{"sum_foreign_comment":"","sum_comment_hidden":false,"sum":"","sum_comment":"","sum_foreign":""},"64":{"sum_foreign_comment":"","sum_comment_hidden":false,"sum":"","sum_comment":"","sum_foreign":""}},"ft_src":"суддя костянтинівського міськрайонного суду донецької області\nДонецька область\nЗагальний місцевий суд\nВолодимир\nАнатолійович\nЧернецький Володимир Анатолійович\nЧернецький\nЧернецький Володимир Анатолійович\nВолодимир Анатолійович Чернецький\nВолодимир Чернецький\nЧернецький Володимир Анатолійович\nDaewoo\nЗАЗ, Т13110, 1299 , оренда чи інше право користування\n2006\nм. Костянтинівка\nДонецька область\n24\nм. Костянтинівка\n24\nДонецька область\nм. Костянтинівка\nДонецька область\n68.3\n2015\n219096\n12180\n225003\n5907\nDaewoo\nЗАЗ, Т13110, 1299 , оренда чи інше право користування\n2006\n2015\nЧернецький Володимир Анатолійович\nВолодимир Анатолійович Чернецький\nВолодимир Чернецький\nЧернецький Володимир Анатолійович\nВолодимир\nЧернецький Володимир Анатолійович\nЧернецький\nЗагальний місцевий суд\nсуддя костянтинівського міськрайонного суду донецької області\nДонецька область\nАнатолійович\n219096\n5907\n225003\n12180\n24\nДонецька область\nм. Костянтинівка\n24\nДонецька область\nм. Костянтинівка\n68.3\nм. Костянтинівка\nДонецька область\nАнатолійович\nЧернецький\nВолодимир\nЧернецький Володимир Анатолійович\nВолодимир Анатолійович Чернецький\nВолодимир Чернецький\nЧернецький Володимир Анатолійович\nсуддя костянтинівського міськрайонного суду донецької області\nЗагальний місцевий суд\nДонецька область\nЧернецький Володимир Анатолійович\n2006\nDaewoo\nЗАЗ, Т13110, 1299 , оренда чи інше право користування\n12180\n5907\n225003\n219096\nм. Костянтинівка\nДонецька область\n68.3\nм. Костянтинівка\nДонецька область\n24\nм. Костянтинівка\nДонецька область\n24\n2015","general":{"inn":"","name":"Володимир","inn_unclear":false,"patronymic":"Анатолійович","inn_hidden":true,"family_raw":"","last_name":"Чернецький","post":{"region":"Донецька область","region_unclear":false,"post":"суддя костянтинівського міськрайонного суду донецької області","office_unclear":false,"office":"Загальний місцевий суд"},"full_name":"Чернецький Володимир Анатолійович","addresses":[{"place_district":"","place_city_hidden":true,"place_city":"","place_city_type_hidden":false,"place_district_hidden":false,"place_city_type":"","place_address_hidden":true,"place_address":"","place_hidden":true,"place":""}],"patronymic_hidden":false,"full_name_suggest":{"output":"Чернецький Володимир Анатолійович","input":["Чернецький Володимир Анатолійович","Володимир Анатолійович Чернецький","Володимир Чернецький"]}},"source":"VULYK","estate":{"23":[{"space_unclear":false,"costs":"","costs_comment":"","address_hidden":true,"region_hidden":false,"space_comment":"","space_hidden":false,"space":"24","address":"м. Костянтинівка","costs_comment_unclear":false,"region":"Донецька область","space_units_unclear":false,"space_units":"м²","costs_rent":"","costs_rent_comment":""}],"25":[{"space_unclear":false,"costs":"","costs_comment":"","address_hidden":true,"region_hidden":false,"space_comment":"","space_hidden":false,"space":"68.3","address":"м. Костянтинівка","region":"Донецька область","costs_rent_comment":"","space_comment_unclear":false,"space_units":"м²","costs_rent":""}],"27":[{"space_hidden":false,"costs":"","costs_comment":"","address_hidden":true,"region_hidden":false,"space_comment":"","space":"24","address":"м. Костянтинівка","region":"Донецька область","costs_rent_comment":"","space_units":"м²","costs_rent":""}]},"intro":{"declaration_year":"2015"}}},{"provider":"declarations.com.ua","document":{"income":{"5":{"value":"254943","family_comment":"","value_unclear":false,"family_unclear":false,"family":"","comment":""},"6":{"family_comment":"","value":"231327","value_unclear":false,"family":"","comment":""},"7":{"family_comment":"","value":"","source_name":"","family":"","comment":""},"8":{"family_comment":"","value":"","family":"","comment":""},"9":{"family_comment":"","value":"","value_unclear":false,"family":"","comment":""},"10":{"family_comment":"","value":"","family":"","comment":""},"11":{"family_comment":"","value":"","family":"","comment":""},"12":{"family_comment":"","value":"","family":"","comment":""},"13":{"family_comment":"","value":"","family":"","comment":""},"14":{"family_comment":"","value":"","family":"","comment":""},"15":{"family_comment":"","value":"","family":"","comment":""},"16":{"family_comment":"","value":"","family":"","comment":""},"17":{"family_comment":"","value":"","family":"","comment":""},"18":{"family_comment":"","value":"","family":"","comment":""},"19":{"family_comment":"","value":"","family":"","comment":""},"20":{"family_comment":"","value":"23616","value_unclear":false,"family":"","comment":""}},"vehicle":{"35":[{"brand_info":"1299 куб. см.","sum_rent_comment":"","brand":"Daewoo 13110","sum_comment":"","brand_unclear":false,"year":"2006","brand_info_unclear":false,"sum":"","sum_rent":""}]},"id":"vulyk_98_35","declaration":{"date":"2015-03-26T00:00:00","url":"http://static.declarations.com.ua/declarations/chosen_ones/judges_batch/4532_chernetskyi_volodymyr_anatoliiovych.pdf"},"liabilities":{"54":{"sum_foreign_comment":"","sum":"","sum_comment":"","sum_comment_unclear":false,"sum_hidden":false,"sum_comment_hidden":false,"sum_unclear":false,"sum_foreign":""},"55":{"sum_foreign_comment":"","sum":"","sum_comment":"","sum_foreign":""},"56":{"sum_foreign_comment":"","sum":"","sum_comment":"","sum_unclear":false,"sum_foreign":""},"57":{"sum_foreign_comment":"","sum":"","sum_comment":"","sum_comment_unclear":false,"sum_hidden":false,"sum_comment_hidden":false,"sum_unclear":false,"sum_foreign":""},"58":{"sum_foreign_comment":"","sum":"","sum_comment":"","sum_hidden":false,"sum_comment_hidden":false,"sum_unclear":false,"sum_foreign":""},"59":{"sum_foreign_comment":"","sum":"","sum_comment":"","sum_comment_unclear":false,"sum_foreign":""},"60":{"sum_foreign_comment":"","sum":"","sum_comment":"","sum_hidden":false,"sum_comment_hidden":false,"sum_foreign":""},"61":{"sum_foreign_comment":"","sum":"","sum_comment":"","sum_foreign":""},"62":{"sum_foreign_comment":"","sum":"","sum_comment":"","sum_comment_hidden":false,"sum_unclear":false,"sum_foreign":""},"63":{"sum_foreign_comment":"","sum":"","sum_comment":"","sum_comment_unclear":false,"sum_comment_hidden":false,"sum_foreign":""},"64":{"sum_foreign_comment":"","sum_comment_hidden":false,"sum":"","sum_comment":"","sum_foreign":""}},"ft_src":"суддя костянтинівського міськрайонного суду донецької області\nДонецька область\nЗагальний місцевий суд\nВолодимир\nАнатолійович\nЧернецький Володимир Анатолійович\nВолодимир Анатолійович Чернецький\nВолодимир Чернецький\nЧернецький Володимир Анатолійович\nЧернецький Володимир Анатолійович\nЧернецький\n2006\nDaewoo 13110\n1299 куб. см.\nм. Костянтинівка\n24\nДонецька область\nм. Костянтинівка\n24\nДонецька область\nм. Костянтинівка\n68.3\nДонецька область\n2014\n231327\n254943\n23616\n1299 куб. см.\n2006\nDaewoo 13110\n2014\nЗагальний місцевий суд\nсуддя костянтинівського міськрайонного суду донецької області\nДонецька область\nЧернецький Володимир Анатолійович\nВолодимир Анатолійович Чернецький\nВолодимир Чернецький\nЧернецький Володимир Анатолійович\nЧернецький Володимир Анатолійович\nВолодимир\nЧернецький\nАнатолійович\n231327\n23616\n254943\n24\nДонецька область\nм. Костянтинівка\n24\nДонецька область\nм. Костянтинівка\n68.3\nДонецька область\nм. Костянтинівка\nАнатолійович\nЧернецький\nВолодимир\nЧернецький Володимир Анатолійович\nВолодимир Анатолійович Чернецький\nВолодимир Чернецький\nЧернецький Володимир Анатолійович\nсуддя костянтинівського міськрайонного суду донецької області\nДонецька область\nЗагальний місцевий суд\nЧернецький Володимир Анатолійович\n2006\n1299 куб. см.\nDaewoo 13110\n23616\n254943\n231327\nм. Костянтинівка\nДонецька область\n68.3\nм. Костянтинівка\nДонецька область\n24\nм. Костянтинівка\nДонецька область\n24\n2014","general":{"inn":"","name":"Володимир","last_name_hidden":false,"last_name":"Чернецький","patronymic":"Анатолійович","inn_hidden":true,"family_raw":"","inn_unclear":false,"post":{"post_unclear":false,"office":"Загальний місцевий суд","post":"суддя костянтинівського міськрайонного суду донецької області","region":"Донецька область"},"full_name_suggest":{"output":"Чернецький Володимир Анатолійович","input":["Чернецький Володимир Анатолійович","Володимир Анатолійович Чернецький","Володимир Чернецький"]},"full_name":"Чернецький Володимир Анатолійович","addresses":[{"place_district":"","place_city_hidden":true,"place_city":"","place_city_type_hidden":false,"place_district_hidden":false,"place_city_type":"","place_address_hidden":true,"place_address":"","place_hidden":true,"place":""}],"patronymic_hidden":false,"last_name_unclear":false},"source":"VULYK","estate":{"23":[{"space_unclear":false,"costs":"","costs_comment":"","address_hidden":true,"region_hidden":false,"space_comment":"","space":"24","address":"м. Костянтинівка","region":"Донецька область","costs_rent_comment":"","space_units":"м²","costs_rent":""}],"25":[{"space_unclear":false,"costs":"","costs_comment":"","address_hidden":true,"region_hidden":false,"space_comment":"","space":"68.3","address":"м. Костянтинівка","region":"Донецька область","address_unclear":false,"costs_rent_comment":"","space_units":"м²","costs_rent":""}],"27":[{"space_unclear":false,"costs":"","costs_comment":"","address_hidden":true,"region_hidden":false,"space_comment":"","space":"24","address":"м. Костянтинівка","region":"Донецька область","costs_rent_comment":"","space_units":"м²","costs_rent":""}]},"intro":{"declaration_year":"2014"}}},{"provider":"public-api.nazk.gov.ua","document":{"step_0":{"declarationType":"1","declarationYear1":"2015"},"step_1":{"street":"[Конфіденційна інформація]","country":"1","cityPath":"[Конфіденційна інформація]","cityType":"[Конфіденційна інформація]","lastname":"Чернецький","postCode":"[Конфіденційна інформація]","postType":"","workPost":"суддя","buildType":"багатоквартирний будинок","firstname":"Володимир","workPlace":"Костянтинівський міськрайонний суд Донецької області","middlename":"Анатолійович","streetType":"[Конфіденційна інформація]","changedName":false,"countryPath":"","eng_postCode":"","postCategory":"","actual_street":"[Конфіденційна інформація]","actual_cityType":"[Конфіденційна інформація]","actual_postCode":"[Конфіденційна інформація]","actual_buildType":"","actual_streetType":"[Конфіденційна інформація]","previous_lastname":"","corruptionAffected":"Ні","eng_actualPostCode":"[Конфіденційна інформація]","previous_firstname":"","previous_middlename":"","responsiblePosition":"Суддя суду загальної юрисдикції, суддя Конституційного Суду України","sameRegLivingAddress":"[Конфіденційна інформація]","postType_extendedstatus":"1","eng_sameRegLivingAddress":"[Конфіденційна інформація]","housePartNum_extendedstatus":"1","postCategory_extendedstatus":"1"},"step_2":{"empty":"У суб'єкта декларування відсутні об'єкти для декларування в цьому розділі."},"step_3":{"1474884265424":{"person":"1","rights":{"1":{"citizen":"","ua_lastname":"","eng_lastname":"","rightBelongs":"1","ua_firstname":"","eng_firstname":"","ownershipType":"Власність","ua_middlename":"","eng_middlename":"","otherOwnership":"","ua_company_name":"","eng_company_name":"","ukr_company_name":"","percent-ownership":""}},"country":"1","cityPath":"[Конфіденційна інформація]","costDate":"","postCode":"[Конфіденційна інформація]","totalArea":"68,30","ua_street":"[Конфіденційна інформація]","objectType":"Квартира","owningDate":"26.03.2007","ua_cityType":"Костянтинівка / Донецька Область/м.Донецьк / Україна","ua_postCode":"85102","ua_buildType":"багатоквартирний будинок","ua_streetType":"[Конфіденційна інформація]","costAssessment":"","otherObjectType":"","costDate_extendedstatus":"2","costAssessment_extendedstatus":"1","ua_housePartNum_extendedstatus":"1"},"1474885431900":{"person":"1","rights":{"1":{"citizen":"","ua_lastname":"","eng_lastname":"","rightBelongs":"1","ua_firstname":"","eng_firstname":"","ownershipType":"Власність","ua_middlename":"","eng_middlename":"","otherOwnership":"","ua_company_name":"","eng_company_name":"","ukr_company_name":"","percent-ownership":""}},"country":"1","cityPath":"[Конфіденційна інформація]","costDate":"7899","postCode":"[Конфіденційна інформація]","totalArea":"20,40","ua_street":"[Конфіденційна інформація]","objectType":"Гараж","owningDate":"29.11.2012","ua_cityType":"Костянтинівка / Донецька Область/м.Донецьк / Україна","ua_postCode":"85102","ua_buildType":"заклад соціального обслуговування","ua_streetType":"[Конфіденційна інформація]","costAssessment":"","otherObjectType":"","costAssessment_extendedstatus":"1","ua_housePartNum_extendedstatus":"1","ua_apartmentsNum_extendedstatus":"1"},"1474885803217":{"person":"1","rights":{"1":{"citizen":"","ua_lastname":"","eng_lastname":"","rightBelongs":"1","ua_firstname":"","eng_firstname":"","ownershipType":"Власність","ua_middlename":"","eng_middlename":"","otherOwnership":"","ua_company_name":"","eng_company_name":"","ukr_company_name":"","percent-ownership":""}},"country":"1","cityPath":"[Конфіденційна інформація]","costDate":"4917","postCode":"[Конфіденційна інформація]","totalArea":"24","ua_street":"[Конфіденційна інформація]","objectType":"Земельна ділянка","owningDate":"29.11.2012","ua_cityType":"Костянтинівка / Донецька Область/м.Донецьк / Україна","ua_postCode":"85102","ua_buildType":"","ua_streetType":"[Конфіденційна інформація]","costAssessment":"","otherObjectType":"","costAssessment_extendedstatus":"1","ua_housePartNum_extendedstatus":"1","ua_apartmentsNum_extendedstatus":"1"}},"step_4":[],"step_5":[],"step_6":[],"step_7":[],"step_8":[],"step_9":[],"step_10":[],"step_11":{"1474884991142":{"person":"1","rights":{"1":{"citizen":"","ua_lastname":"","eng_lastname":"","rightBelongs":"1","ua_firstname":"","eng_firstname":"","ownershipType":"Власність","ua_middlename":"","eng_middlename":"","otherOwnership":"","ua_company_name":"","eng_company_name":"","ukr_company_name":"","percent-ownership":""}},"objectType":"Заробітна плата отримана за основним місцем роботи","sizeIncome":"219096","incomeSource":"1","source_citizen":"","otherObjectType":"","source_ua_lastname":"","source_eng_lastname":"","source_ua_firstname":"","source_ukr_lastname":"","source_eng_firstname":"","source_ua_middlename":"","source_ukr_firstname":"","source_eng_middlename":"","source_ukr_middlename":"","source_ua_company_name":"","source_eng_company_name":"","source_ukr_company_name":"","source_ua_sameRegLivingAddress":"","source_eng_sameRegLivingAddress":""},"1474885255898":{"person":"1","rights":{"1":{"citizen":"","ua_lastname":"","eng_lastname":"","rightBelongs":"1","ua_firstname":"","eng_firstname":"","ownershipType":"Власність","ua_middlename":"","eng_middlename":"","otherOwnership":"","ua_company_name":"","eng_company_name":"","ukr_company_name":"","percent-ownership":""}},"objectType":"Пенсія","sizeIncome":"5907","incomeSource":"1","source_citizen":"","otherObjectType":"","source_ua_lastname":"","source_eng_lastname":"","source_ua_firstname":"","source_ukr_lastname":"","source_eng_firstname":"","source_ua_middlename":"","source_ukr_firstname":"","source_eng_middlename":"","source_ukr_middlename":"","source_ua_company_name":"","source_eng_company_name":"","source_ukr_company_name":"","source_ua_sameRegLivingAddress":"","source_eng_sameRegLivingAddress":""}},"step_12":[],"step_13":[],"step_14":[],"step_15":[],"step_16":{"org":[],"part_org":[]},"id":"1f320c68-192a-4e58-8d44-87289ede0f29"}}],"declarations":[{"income":{"5":{"family_comment":"","value":"225003","value_unclear":false,"family":"","comment":""},"6":{"value":"219096","value_unclear":false,"family_hidden":false,"family_comment":"","family":"","comment":""},"7":{"source_name_unclear":false,"value":"","family_comment":"","source_name":"","family":"","comment":""},"8":{"family_comment":"","value":"","family":"","comment":""},"9":{"family_comment":"","value":"","family":"","comment":""},"10":{"family_comment":"","value":"12180","family":"","comment":""},"11":{"family_comment":"","value":"","comment_unclear":false,"family":"","comment":""},"12":{"family_comment":"","value":"","family":"","comment":""},"13":{"family_comment":"","value":"","family":"","comment":""},"14":{"family_comment":"","value":"","family":"","comment":""},"15":{"family_comment":"","value":"","family":"","comment":""},"16":{"family_comment":"","value":"","family":"","comment":""},"17":{"family_comment":"","value":"","family":"","comment":""},"18":{"family_comment":"","value":"","family":"","comment":""},"19":{"family_comment":"","value":"","family":"","comment":""},"20":{"value":"5907","family_comment":"","value_unclear":false,"family_unclear":false,"comment_unclear":false,"comment":"","family":""}},"vehicle":{"35":[{"brand_info":"ЗАЗ, Т13110, 1299 , оренда чи інше право користування","sum_rent_comment":"","brand":"Daewoo","sum_comment":"","brand_unclear":false,"year":"2006","sum_rent_unclear":false,"brand_info_hidden":false,"brand_info_unclear":false,"sum":"","sum_rent":""}]},"id":"vulyk_101_138","declaration":{"additional_info_text":"","notfull_lostpages":"","date":"2016-03-18T00:00:00","notfull":"","additional_info":"","url":"http://static.declarations.com.ua/declarations/chosen_ones/judges_batch/853_chernetskyi_volodymyr_anatoliiovych_2015.pdf"},"liabilities":{"54":{"sum_foreign_comment":"","sum":"","sum_comment":"","sum_comment_unclear":false,"sum_hidden":false,"sum_comment_hidden":false,"sum_unclear":false,"sum_foreign":""},"55":{"sum_foreign_comment":"","sum":"","sum_comment":"","sum_foreign":""},"56":{"sum_foreign_comment":"","sum":"","sum_comment":"","sum_comment_hidden":false,"sum_unclear":false,"sum_foreign":""},"57":{"sum_foreign_comment":"","sum":"","sum_comment":"","sum_hidden":false,"sum_comment_hidden":false,"sum_unclear":false,"sum_foreign":""},"58":{"sum_foreign_comment":"","sum":"","sum_comment":"","sum_comment_unclear":false,"sum_hidden":false,"sum_comment_hidden":false,"sum_unclear":false,"sum_foreign":""},"59":{"sum_foreign_comment":"","sum":"","sum_comment":"","sum_foreign":""},"60":{"sum_foreign_comment":"","sum":"","sum_comment":"","sum_hidden":false,"sum_comment_hidden":false,"sum_unclear":false,"sum_foreign":""},"61":{"sum_foreign_comment":"","sum":"","sum_comment":"","sum_foreign":""},"62":{"sum_foreign_comment":"","sum":"","sum_comment":"","sum_comment_unclear":false,"sum_foreign":""},"63":{"sum_foreign_comment":"","sum_comment_hidden":false,"sum":"","sum_comment":"","sum_foreign":""},"64":{"sum_foreign_comment":"","sum_comment_hidden":false,"sum":"","sum_comment":"","sum_foreign":""}},"ft_src":"суддя костянтинівського міськрайонного суду донецької області\nДонецька область\nЗагальний місцевий суд\nВолодимир\nАнатолійович\nЧернецький Володимир Анатолійович\nЧернецький\nЧернецький Володимир Анатолійович\nВолодимир Анатолійович Чернецький\nВолодимир Чернецький\nЧернецький Володимир Анатолійович\nDaewoo\nЗАЗ, Т13110, 1299 , оренда чи інше право користування\n2006\nм. Костянтинівка\nДонецька область\n24\nм. Костянтинівка\n24\nДонецька область\nм. Костянтинівка\nДонецька область\n68.3\n2015\n219096\n12180\n225003\n5907\nDaewoo\nЗАЗ, Т13110, 1299 , оренда чи інше право користування\n2006\n2015\nЧернецький Володимир Анатолійович\nВолодимир Анатолійович Чернецький\nВолодимир Чернецький\nЧернецький Володимир Анатолійович\nВолодимир\nЧернецький Володимир Анатолійович\nЧернецький\nЗагальний місцевий суд\nсуддя костянтинівського міськрайонного суду донецької області\nДонецька область\nАнатолійович\n219096\n5907\n225003\n12180\n24\nДонецька область\nм. Костянтинівка\n24\nДонецька область\nм. Костянтинівка\n68.3\nм. Костянтинівка\nДонецька область\nАнатолійович\nЧернецький\nВолодимир\nЧернецький Володимир Анатолійович\nВолодимир Анатолійович Чернецький\nВолодимир Чернецький\nЧернецький Володимир Анатолійович\nсуддя костянтинівського міськрайонного суду донецької області\nЗагальний місцевий суд\nДонецька область\nЧернецький Володимир Анатолійович\n2006\nDaewoo\nЗАЗ, Т13110, 1299 , оренда чи інше право користування\n12180\n5907\n225003\n219096\nм. Костянтинівка\nДонецька область\n68.3\nм. Костянтинівка\nДонецька область\n24\nм. Костянтинівка\nДонецька область\n24\n2015","general":{"inn":"","name":"Володимир","inn_unclear":false,"patronymic":"Анатолійович","inn_hidden":true,"family_raw":"","last_name":"Чернецький","post":{"region":"Донецька область","region_unclear":false,"post":"суддя костянтинівського міськрайонного суду донецької області","office_unclear":false,"office":"Загальний місцевий суд"},"full_name":"Чернецький Володимир Анатолійович","addresses":[{"place_district":"","place_city_hidden":true,"place_city":"","place_city_type_hidden":false,"place_district_hidden":false,"place_city_type":"","place_address_hidden":true,"place_address":"","place_hidden":true,"place":""}],"patronymic_hidden":false,"full_name_suggest":{"output":"Чернецький Володимир Анатолійович","input":["Чернецький Володимир Анатолійович","Володимир Анатолійович Чернецький","Володимир Чернецький"]}},"source":"VULYK","estate":{"23":[{"space_unclear":false,"costs":"","costs_comment":"","address_hidden":true,"region_hidden":false,"space_comment":"","space_hidden":false,"space":"24","address":"м. Костянтинівка","costs_comment_unclear":false,"region":"Донецька область","space_units_unclear":false,"space_units":"м²","costs_rent":"","costs_rent_comment":""}],"25":[{"space_unclear":false,"costs":"","costs_comment":"","address_hidden":true,"region_hidden":false,"space_comment":"","space_hidden":false,"space":"68.3","address":"м. Костянтинівка","region":"Донецька область","costs_rent_comment":"","space_comment_unclear":false,"space_units":"м²","costs_rent":""}],"27":[{"space_hidden":false,"costs":"","costs_comment":"","address_hidden":true,"region_hidden":false,"space_comment":"","space":"24","address":"м. Костянтинівка","region":"Донецька область","costs_rent_comment":"","space_units":"м²","costs_rent":""}]},"intro":{"declaration_year":"2015"}},{"income":{"5":{"value":"254943","family_comment":"","value_unclear":false,"family_unclear":false,"family":"","comment":""},"6":{"family_comment":"","value":"231327","value_unclear":false,"family":"","comment":""},"7":{"family_comment":"","value":"","source_name":"","family":"","comment":""},"8":{"family_comment":"","value":"","family":"","comment":""},"9":{"family_comment":"","value":"","value_unclear":false,"family":"","comment":""},"10":{"family_comment":"","value":"","family":"","comment":""},"11":{"family_comment":"","value":"","family":"","comment":""},"12":{"family_comment":"","value":"","family":"","comment":""},"13":{"family_comment":"","value":"","family":"","comment":""},"14":{"family_comment":"","value":"","family":"","comment":""},"15":{"family_comment":"","value":"","family":"","comment":""},"16":{"family_comment":"","value":"","family":"","comment":""},"17":{"family_comment":"","value":"","family":"","comment":""},"18":{"family_comment":"","value":"","family":"","comment":""},"19":{"family_comment":"","value":"","family":"","comment":""},"20":{"family_comment":"","value":"23616","value_unclear":false,"family":"","comment":""}},"vehicle":{"35":[{"brand_info":"1299 куб. см.","sum_rent_comment":"","brand":"Daewoo 13110","sum_comment":"","brand_unclear":false,"year":"2006","brand_info_unclear":false,"sum":"","sum_rent":""}]},"id":"vulyk_98_35","declaration":{"date":"2015-03-26T00:00:00","url":"http://static.declarations.com.ua/declarations/chosen_ones/judges_batch/4532_chernetskyi_volodymyr_anatoliiovych.pdf"},"liabilities":{"54":{"sum_foreign_comment":"","sum":"","sum_comment":"","sum_comment_unclear":false,"sum_hidden":false,"sum_comment_hidden":false,"sum_unclear":false,"sum_foreign":""},"55":{"sum_foreign_comment":"","sum":"","sum_comment":"","sum_foreign":""},"56":{"sum_foreign_comment":"","sum":"","sum_comment":"","sum_unclear":false,"sum_foreign":""},"57":{"sum_foreign_comment":"","sum":"","sum_comment":"","sum_comment_unclear":false,"sum_hidden":false,"sum_comment_hidden":false,"sum_unclear":false,"sum_foreign":""},"58":{"sum_foreign_comment":"","sum":"","sum_comment":"","sum_hidden":false,"sum_comment_hidden":false,"sum_unclear":false,"sum_foreign":""},"59":{"sum_foreign_comment":"","sum":"","sum_comment":"","sum_comment_unclear":false,"sum_foreign":""},"60":{"sum_foreign_comment":"","sum":"","sum_comment":"","sum_hidden":false,"sum_comment_hidden":false,"sum_foreign":""},"61":{"sum_foreign_comment":"","sum":"","sum_comment":"","sum_foreign":""},"62":{"sum_foreign_comment":"","sum":"","sum_comment":"","sum_comment_hidden":false,"sum_unclear":false,"sum_foreign":""},"63":{"sum_foreign_comment":"","sum":"","sum_comment":"","sum_comment_unclear":false,"sum_comment_hidden":false,"sum_foreign":""},"64":{"sum_foreign_comment":"","sum_comment_hidden":false,"sum":"","sum_comment":"","sum_foreign":""}},"ft_src":"суддя костянтинівського міськрайонного суду донецької області\nДонецька область\nЗагальний місцевий суд\nВолодимир\nАнатолійович\nЧернецький Володимир Анатолійович\nВолодимир Анатолійович Чернецький\nВолодимир Чернецький\nЧернецький Володимир Анатолійович\nЧернецький Володимир Анатолійович\nЧернецький\n2006\nDaewoo 13110\n1299 куб. см.\nм. Костянтинівка\n24\nДонецька область\nм. Костянтинівка\n24\nДонецька область\nм. Костянтинівка\n68.3\nДонецька область\n2014\n231327\n254943\n23616\n1299 куб. см.\n2006\nDaewoo 13110\n2014\nЗагальний місцевий суд\nсуддя костянтинівського міськрайонного суду донецької області\nДонецька область\nЧернецький Володимир Анатолійович\nВолодимир Анатолійович Чернецький\nВолодимир Чернецький\nЧернецький Володимир Анатолійович\nЧернецький Володимир Анатолійович\nВолодимир\nЧернецький\nАнатолійович\n231327\n23616\n254943\n24\nДонецька область\nм. Костянтинівка\n24\nДонецька область\nм. Костянтинівка\n68.3\nДонецька область\nм. Костянтинівка\nАнатолійович\nЧернецький\nВолодимир\nЧернецький Володимир Анатолійович\nВолодимир Анатолійович Чернецький\nВолодимир Чернецький\nЧернецький Володимир Анатолійович\nсуддя костянтинівського міськрайонного суду донецької області\nДонецька область\nЗагальний місцевий суд\nЧернецький Володимир Анатолійович\n2006\n1299 куб. см.\nDaewoo 13110\n23616\n254943\n231327\nм. Костянтинівка\nДонецька область\n68.3\nм. Костянтинівка\nДонецька область\n24\nм. Костянтинівка\nДонецька область\n24\n2014","general":{"inn":"","name":"Володимир","last_name_hidden":false,"last_name":"Чернецький","patronymic":"Анатолійович","inn_hidden":true,"family_raw":"","inn_unclear":false,"post":{"post_unclear":false,"office":"Загальний місцевий суд","post":"суддя костянтинівського міськрайонного суду донецької області","region":"Донецька область"},"full_name_suggest":{"output":"Чернецький Володимир Анатолійович","input":["Чернецький Володимир Анатолійович","Володимир Анатолійович Чернецький","Володимир Чернецький"]},"full_name":"Чернецький Володимир Анатолійович","addresses":[{"place_district":"","place_city_hidden":true,"place_city":"","place_city_type_hidden":false,"place_district_hidden":false,"place_city_type":"","place_address_hidden":true,"place_address":"","place_hidden":true,"place":""}],"patronymic_hidden":false,"last_name_unclear":false},"source":"VULYK","estate":{"23":[{"space_unclear":false,"costs":"","costs_comment":"","address_hidden":true,"region_hidden":false,"space_comment":"","space":"24","address":"м. Костянтинівка","region":"Донецька область","costs_rent_comment":"","space_units":"м²","costs_rent":""}],"25":[{"space_unclear":false,"costs":"","costs_comment":"","address_hidden":true,"region_hidden":false,"space_comment":"","space":"68.3","address":"м. Костянтинівка","region":"Донецька область","address_unclear":false,"costs_rent_comment":"","space_units":"м²","costs_rent":""}],"27":[{"space_unclear":false,"costs":"","costs_comment":"","address_hidden":true,"region_hidden":false,"space_comment":"","space":"24","address":"м. Костянтинівка","region":"Донецька область","costs_rent_comment":"","space_units":"м²","costs_rent":""}]},"intro":{"declaration_year":"2014"}}],"declarationsLength":2,"analytics":[{"y":2015,"i":225003,"c":1,"k":68.3,"ka":1,"l":24,"la":1},{"y":2014,"i":254943,"c":1,"k":68.3,"ka":1,"l":24,"la":1}]}