{"2010":"","2016":"","Department":"Господарський суд Хмельницької області","Region":"Хмельницька область","Position":"Суддя Господарського суду Хмельницької області","Name":"Димбовський В'ячеслав Вікторович","Link":"https://drive.google.com/open?id=0BygiyWAl79DMYWwyRmo4bkRsN2s","Note":"У меня","AdditionalNote":"","field8":"","field9":"","field10":"","Кількість справ":"","Оскаржені":"","Кількість скарг":1,"Кількість дисциплінарних стягнень":"","Клейма":"","Фото":"","Як живе":"","key":"dimbovskiy_vyacheslav_viktorovich","allDeclarations":[{"provider":"declarations.com.ua","document":{"income":{"5":{"family_comment":"","value":"230374.9","family":"35270","comment":""},"6":{"family_comment":"","value":"230374.9","family":"35270","comment":""},"7":{"value":"","comment_hidden":false,"family_comment":"","source_name":"","family":"","comment":"","source_name_hidden":false},"8":{"family_comment":"","value":"","family":"","comment":"","family_hidden":false},"9":{"value":"","family_comment":"","value_unclear":false,"family_unclear":false,"family":"","comment":""},"10":{"family_comment":"","value":"","family":"","comment":""},"11":{"family_comment":"","value":"","family":"","comment":""},"12":{"family_comment":"","value":"","family":"","comment":""},"13":{"family_comment":"","value":"","family":"","comment":""},"14":{"family_comment":"","value":"","family":"","comment":""},"15":{"family_comment":"","value":"","family":"","comment":""},"16":{"family_comment":"","value":"","family":"","comment":""},"17":{"family_comment":"","value":"","family":"","comment":""},"18":{"family_comment":"","value":"","family":"","comment":""},"19":{"family_comment":"","value":"","family":"","comment":""},"20":{"value":"","value_unclear":false,"family_hidden":false,"family_comment":"","family":"","comment":""}},"id":"vulyk_109_117","declaration":{"additional_info_text":"","notfull_lostpages":"","date":"2016-03-23T00:00:00","notfull":"","additional_info":"","url":"http://static.declarations.com.ua/declarations/chosen_ones/judges_batch/2574_dymbovskyi_v_iacheslav_viktorovych_2015.pdf"},"liabilities":{"54":{"sum_foreign_comment":"","sum":"","sum_comment":"","sum_hidden":false,"sum_comment_hidden":false,"sum_unclear":false,"sum_foreign":""},"55":{"sum_foreign_comment":"","sum":"","sum_comment":"","sum_comment_unclear":false,"sum_foreign":""},"56":{"sum_foreign_comment":"","sum":"","sum_comment":"","sum_foreign":""},"57":{"sum_foreign_comment":"","sum_comment":"","sum":"","sum_comment_hidden":false,"sum_foreign":""},"58":{"sum_foreign_comment":"","sum_comment":"","sum":"","sum_comment_hidden":false,"sum_foreign":""},"59":{"sum_foreign_comment":"","sum":"","sum_comment":"","sum_foreign":""},"60":{"sum_foreign_comment":"","sum":"","sum_comment":"","sum_foreign":""},"61":{"sum_foreign_comment":"","sum":"","sum_comment":"","sum_foreign":""},"62":{"sum_foreign_comment":"","sum":"","sum_comment":"","sum_foreign":""},"63":{"sum_foreign_comment":"","sum":"","sum_comment":"","sum_foreign":""},"64":{"sum_foreign_comment":"","sum":"","sum_comment":"","sum_foreign":""}},"ft_src":"68.2\n2015\n35270\n230374.9\n35270\n230374.9\n230374.9\n35270\n230374.9\n35270\nДимбовський В'ячеслав Вікторович\nВ'ячеслав Вікторович Димбовський\nВ'ячеслав Димбовський\nДимбовський В'ячеслав Вікторович\nВ'ячеслав\nПодружжя\nДимбовська Ія Андріївна\nДитина\nДимбовський Максим Вячеславович\nДитина\nДимбовський Герман Вячеславович\nДимбовський В'ячеслав Вікторович\nВікторович\nГосподарський місцевий суд\nХмельницька область\nсуддя господарського суду хмельницької області\nДимбовський\n68.2\n2015\nПодружжя\nДимбовська Ія Андріївна\nДитина\nДимбовський Максим Вячеславович\nДитина\nДимбовський Герман Вячеславович\nВікторович\nДимбовський\nВ'ячеслав\nДимбовський В'ячеслав Вікторович\nВ'ячеслав Вікторович Димбовський\nВ'ячеслав Димбовський\nДимбовський В'ячеслав Вікторович\nХмельницька область\nГосподарський місцевий суд\nсуддя господарського суду хмельницької області\nДимбовський В'ячеслав Вікторович","general":{"name_hidden":false,"name":"В'ячеслав","inn":"","last_name":"Димбовський","family":[{"inn":"","relations":"Подружжя","relations_hidden":false,"inn_hidden":true,"family_name":"Димбовська Ія Андріївна","relations_other":"","name_hidden":true,"name_unclear":false},{"inn":"","relations":"Дитина","relations_other":"","inn_hidden":false,"family_name":"Димбовський Максим Вячеславович","name_hidden":false,"name_unclear":false},{"inn":"","relations":"Дитина","relations_other":"","inn_hidden":false,"family_name":"Димбовський Герман Вячеславович","name_hidden":false,"name_unclear":false}],"inn_hidden":true,"family_raw":"","inn_unclear":false,"post":{"region_unclear":false,"region":"Хмельницька область","post":"суддя господарського суду хмельницької області","region_hidden":false,"office":"Господарський місцевий суд","office_hidden":false,"office_unclear":false},"full_name":"Димбовський В'ячеслав Вікторович","addresses":[{"place_district":"","place_address_hidden":true,"place_city":"","place_address":"","place_district_hidden":true,"place_city_type":"","place_city_hidden":true,"place_city_type_hidden":true,"place_hidden":true,"place":""}],"patronymic":"Вікторович","full_name_suggest":{"output":"Димбовський В'ячеслав Вікторович","input":["Димбовський В'ячеслав Вікторович","В'ячеслав Вікторович Димбовський","В'ячеслав Димбовський"]}},"source":"VULYK","estate":{"31":[{"space_hidden":false,"address_hidden":true,"region_hidden":true,"space_comment":"","space":"68.2","space_units_hidden":false,"region":"","costs_property":"","costs_rent_comment":"","space_units":"м²","costs_property_comment":"","costs_rent":"","address":""}]},"intro":{"declaration_year":"2015","isnotdeclaration":""}}}],"declarations":[{"income":{"5":{"family_comment":"","value":"230374.9","family":"35270","comment":""},"6":{"family_comment":"","value":"230374.9","family":"35270","comment":""},"7":{"value":"","comment_hidden":false,"family_comment":"","source_name":"","family":"","comment":"","source_name_hidden":false},"8":{"family_comment":"","value":"","family":"","comment":"","family_hidden":false},"9":{"value":"","family_comment":"","value_unclear":false,"family_unclear":false,"family":"","comment":""},"10":{"family_comment":"","value":"","family":"","comment":""},"11":{"family_comment":"","value":"","family":"","comment":""},"12":{"family_comment":"","value":"","family":"","comment":""},"13":{"family_comment":"","value":"","family":"","comment":""},"14":{"family_comment":"","value":"","family":"","comment":""},"15":{"family_comment":"","value":"","family":"","comment":""},"16":{"family_comment":"","value":"","family":"","comment":""},"17":{"family_comment":"","value":"","family":"","comment":""},"18":{"family_comment":"","value":"","family":"","comment":""},"19":{"family_comment":"","value":"","family":"","comment":""},"20":{"value":"","value_unclear":false,"family_hidden":false,"family_comment":"","family":"","comment":""}},"id":"vulyk_109_117","declaration":{"additional_info_text":"","notfull_lostpages":"","date":"2016-03-23T00:00:00","notfull":"","additional_info":"","url":"http://static.declarations.com.ua/declarations/chosen_ones/judges_batch/2574_dymbovskyi_v_iacheslav_viktorovych_2015.pdf"},"liabilities":{"54":{"sum_foreign_comment":"","sum":"","sum_comment":"","sum_hidden":false,"sum_comment_hidden":false,"sum_unclear":false,"sum_foreign":""},"55":{"sum_foreign_comment":"","sum":"","sum_comment":"","sum_comment_unclear":false,"sum_foreign":""},"56":{"sum_foreign_comment":"","sum":"","sum_comment":"","sum_foreign":""},"57":{"sum_foreign_comment":"","sum_comment":"","sum":"","sum_comment_hidden":false,"sum_foreign":""},"58":{"sum_foreign_comment":"","sum_comment":"","sum":"","sum_comment_hidden":false,"sum_foreign":""},"59":{"sum_foreign_comment":"","sum":"","sum_comment":"","sum_foreign":""},"60":{"sum_foreign_comment":"","sum":"","sum_comment":"","sum_foreign":""},"61":{"sum_foreign_comment":"","sum":"","sum_comment":"","sum_foreign":""},"62":{"sum_foreign_comment":"","sum":"","sum_comment":"","sum_foreign":""},"63":{"sum_foreign_comment":"","sum":"","sum_comment":"","sum_foreign":""},"64":{"sum_foreign_comment":"","sum":"","sum_comment":"","sum_foreign":""}},"ft_src":"68.2\n2015\n35270\n230374.9\n35270\n230374.9\n230374.9\n35270\n230374.9\n35270\nДимбовський В'ячеслав Вікторович\nВ'ячеслав Вікторович Димбовський\nВ'ячеслав Димбовський\nДимбовський В'ячеслав Вікторович\nВ'ячеслав\nПодружжя\nДимбовська Ія Андріївна\nДитина\nДимбовський Максим Вячеславович\nДитина\nДимбовський Герман Вячеславович\nДимбовський В'ячеслав Вікторович\nВікторович\nГосподарський місцевий суд\nХмельницька область\nсуддя господарського суду хмельницької області\nДимбовський\n68.2\n2015\nПодружжя\nДимбовська Ія Андріївна\nДитина\nДимбовський Максим Вячеславович\nДитина\nДимбовський Герман Вячеславович\nВікторович\nДимбовський\nВ'ячеслав\nДимбовський В'ячеслав Вікторович\nВ'ячеслав Вікторович Димбовський\nВ'ячеслав Димбовський\nДимбовський В'ячеслав Вікторович\nХмельницька область\nГосподарський місцевий суд\nсуддя господарського суду хмельницької області\nДимбовський В'ячеслав Вікторович","general":{"name_hidden":false,"name":"В'ячеслав","inn":"","last_name":"Димбовський","family":[{"inn":"","relations":"Подружжя","relations_hidden":false,"inn_hidden":true,"family_name":"Димбовська Ія Андріївна","relations_other":"","name_hidden":true,"name_unclear":false},{"inn":"","relations":"Дитина","relations_other":"","inn_hidden":false,"family_name":"Димбовський Максим Вячеславович","name_hidden":false,"name_unclear":false},{"inn":"","relations":"Дитина","relations_other":"","inn_hidden":false,"family_name":"Димбовський Герман Вячеславович","name_hidden":false,"name_unclear":false}],"inn_hidden":true,"family_raw":"","inn_unclear":false,"post":{"region_unclear":false,"region":"Хмельницька область","post":"суддя господарського суду хмельницької області","region_hidden":false,"office":"Господарський місцевий суд","office_hidden":false,"office_unclear":false},"full_name":"Димбовський В'ячеслав Вікторович","addresses":[{"place_district":"","place_address_hidden":true,"place_city":"","place_address":"","place_district_hidden":true,"place_city_type":"","place_city_hidden":true,"place_city_type_hidden":true,"place_hidden":true,"place":""}],"patronymic":"Вікторович","full_name_suggest":{"output":"Димбовський В'ячеслав Вікторович","input":["Димбовський В'ячеслав Вікторович","В'ячеслав Вікторович Димбовський","В'ячеслав Димбовський"]}},"source":"VULYK","estate":{"31":[{"space_hidden":false,"address_hidden":true,"region_hidden":true,"space_comment":"","space":"68.2","space_units_hidden":false,"region":"","costs_property":"","costs_rent_comment":"","space_units":"м²","costs_property_comment":"","costs_rent":"","address":""}]},"intro":{"declaration_year":"2015","isnotdeclaration":""}}],"declarationsLength":1,"analytics":[{"y":2015,"i":230374.9,"fi":35270,"ff":68.2,"ffa":1,"j":1}]}