{"2010":"","2016":"","Department":"Жовтневий районний суд м. Дніпропетровська","Region":"Дніпропетровська область","Position":"Суддя Жовтневого районного суду м. Дніпропетровська","Name":"Федоріщев Сергій Сергійович","Link":"https://drive.google.com/open?id=0B9adEr6qDus4YlVGZzZXSEQwY3M&authuser=0","Note":"У меня","AdditionalNote":"","field8":"","field9":"","Link 2015":"","Кількість справ":"","Оскаржені":"","Кількість скарг":1,"Кількість дисциплінарних стягнень":"","Клейма":"","Фото":"","Як живе":"","key":"fedorishchev_sergiy_sergiyovich","allDeclarations":[{"provider":"declarations.com.ua","document":{"income":{"5":{"value":"301220","family_comment":"","value_unclear":false,"family_unclear":false,"family":"24242","comment":""},"6":{"family_comment":"","family_unclear":false,"value":"153368","family":"22768","comment":""},"7":{"source_name_unclear":true,"value":"1788","family_comment":"","source_name":"Національна школа суддів України","family":"","comment":"Національна школа суддів України"},"8":{"family_comment":"","value":"","family":"","comment":""},"9":{"value":"","family_comment":"","comment_hidden":false,"family_unclear":false,"family":"","comment":"","family_comment_hidden":false},"10":{"family_comment":"","value":"12180","family":"1474","comment":""},"11":{"family_comment":"","value":"","family":"","comment":""},"12":{"family_comment":"","value":"","family":"","comment":""},"13":{"family_comment":"","value":"","family":"","comment":""},"14":{"family_comment":"","value":"","family":"","comment":""},"15":{"family_comment":"","value":"","family":"","comment":""},"16":{"family_comment":"","value":"","family":"","comment":""},"17":{"family_comment":"","value":"","family":"","comment":""},"18":{"family_comment":"","value":"","family":"","comment":""},"19":{"family_comment":"","value":"","family":"","comment":""},"20":{"value":"133884","value_unclear":false,"comment_hidden":false,"family_comment":"","comment_unclear":false,"comment":"133878 - кредитна картка Приватбанк, 6 - % Приватбанк","family":""}},"vehicle":{"35":[{"brand_info":"2461 куб. см, у власності","sum_rent_comment":"","brand":"Volkswagen Transporter","sum_comment":"","year":"2007","brand_info_unclear":false,"sum":"","sum_rent":""}],"36":[{"brand_info":"вантажопасажирський 2148 куб. см, маю право керувати на підставі довіреності","sum_rent_comment":"","brand":"Mercedes-Benz Sprinter 313","sum_comment":"","year":"2007","sum":"","sum_rent":""}],"39":[{"brand_info":"легковий причіп, у власності","sum_rent_comment":"","brand":"Креон","sum_comment":"","year":"2014","sum":"","sum_rent":""}]},"id":"vulyk_108_150","declaration":{"additional_info_text":"","notfull_lostpages":"","date":"2016-03-31T00:00:00","notfull":"","additional_info":"","url":"http://static.declarations.com.ua/declarations/chosen_ones/judges_batch/2449_fedorishchev_serhii_serhiiovych_2015.pdf"},"liabilities":{"54":{"sum_foreign_comment":"","sum":"120","sum_hidden":false,"sum_comment":"Приватбанк - страхування здоров'я","sum_foreign":""},"55":{"sum_foreign_comment":"","sum":"","sum_comment":"","sum_foreign":""},"56":{"sum_foreign_comment":"","sum":"","sum_comment":"","sum_unclear":false,"sum_foreign":""},"57":{"sum_foreign_comment":"","sum":"133878","sum_comment":"Кредитна карта Приватбанк","sum_hidden":false,"sum_comment_hidden":false,"sum_foreign":""},"58":{"sum_foreign_comment":"","sum_comment_hidden":false,"sum":"","sum_comment":"","sum_foreign":""},"59":{"sum_foreign_comment":"","sum":"","sum_comment":"","sum_unclear":false,"sum_foreign":""},"60":{"sum_foreign_comment":"","sum_comment_hidden":false,"sum":"","sum_comment":"","sum_foreign":""},"61":{"sum_foreign_comment":"","sum_comment_hidden":false,"sum":"","sum_comment":"","sum_foreign":""},"62":{"sum_foreign_comment":"","sum":"","sum_comment":"","sum_foreign":""},"63":{"sum_foreign_comment":"","sum":"","sum_comment":"","sum_hidden":false,"sum_comment_hidden":false,"sum_unclear":false,"sum_foreign":""},"64":{"sum_foreign_comment":"","sum":"","sum_comment":"","sum_comment_hidden":false,"sum_unclear":false,"sum_foreign":""}},"ft_src":"Кредитна карта Приватбанк\n133878\nПриватбанк - страхування здоров'я\n120\nДніпропетровськ\nДніпропетровська область\nсуддя жовтневого районного суду м. дніпропетровська\nДніпропетровська область\nЗагальний місцевий суд\nСергій\nФедоріщева К. А\nПодружжя\nФедоріщева Д. С\nДитина\nСергійович\nФедоріщев Сергій Сергійович\nСергій Сергійович Федоріщев\nСергій Федоріщев\nФедоріщев Сергій Сергійович\nФедоріщев Сергій Сергійович\nФедоріщев\nлегковий причіп, у власності\n2014\nКреон\n2461 куб. см, у власності\n2007\nVolkswagen Transporter\nвантажопасажирський 2148 куб. см, маю право керувати на підставі довіреності\n2007\nMercedes-Benz Sprinter 313\nДніпропетровська область\n454\nм. Дніпродзержинськ\nДніпропетровська область\n41\nм. Дніпропетровськ\n16.4\nДніпропетровська область\n2015\n22768\n153368\n1474\n12180\nНаціональна школа суддів України\nНаціональна школа суддів України\n1788\n24242\n301220\n133878 - кредитна картка Приватбанк, 6 - % Приватбанк\n133884\n2461 куб. см, у власності\n2007\nVolkswagen Transporter\nлегковий причіп, у власності\n2014\nКреон\nвантажопасажирський 2148 куб. см, маю право керувати на підставі довіреності\n2007\nMercedes-Benz Sprinter 313\n2015\nФедоріщев Сергій Сергійович\nСергій Сергійович Федоріщев\nСергій Федоріщев\nФедоріщев Сергій Сергійович\nСергій\nПодружжя\nФедоріщева К. А\nДитина\nФедоріщева Д. С\nФедоріщев Сергій Сергійович\nСергійович\nЗагальний місцевий суд\nДніпропетровська область\nсуддя жовтневого районного суду м. дніпропетровська\nФедоріщев\nДніпропетровськ\nДніпропетровська область\n133878\nКредитна карта Приватбанк\n120\nПриватбанк - страхування здоров'я\n1788\nНаціональна школа суддів України\nНаціональна школа суддів України\n153368\n22768\n133884\n133878 - кредитна картка Приватбанк, 6 - % Приватбанк\n301220\n24242\n12180\n1474\n454\nДніпропетровська область\n16.4\nм. Дніпропетровськ\nДніпропетровська область\n41\nм. Дніпродзержинськ\nДніпропетровська область\nКредитна карта Приватбанк\n133878\nПриватбанк - страхування здоров'я\n120\nПодружжя\nФедоріщева К. А\nДитина\nФедоріщева Д. С\nСергійович\nФедоріщев\nСергій\nФедоріщев Сергій Сергійович\nСергій Сергійович Федоріщев\nСергій Федоріщев\nФедоріщев Сергій Сергійович\nДніпропетровська область\nДніпропетровськ\nДніпропетровська область\nсуддя жовтневого районного суду м. дніпропетровська\nЗагальний місцевий суд\nФедоріщев Сергій Сергійович\nКреон\nлегковий причіп, у власності\n2014\n2007\n2461 куб. см, у власності\nVolkswagen Transporter\nMercedes-Benz Sprinter 313\nвантажопасажирський 2148 куб. см, маю право керувати на підставі довіреності\n2007\n1474\n12180\n133884\n133878 - кредитна картка Приватбанк, 6 - % Приватбанк\n301220\n24242\n1788\nНаціональна школа суддів України\nНаціональна школа суддів України\n22768\n153368\nм. Дніпропетровськ\nДніпропетровська область\n16.4\nДніпропетровська область\n454\nм. Дніпродзержинськ\nДніпропетровська область\n41\n2015","general":{"inn":"","name":"Сергій","inn_unclear":true,"family":[{"inn":"","relations":"Подружжя","inn_unclear":true,"relations_hidden":false,"inn_hidden":true,"relations_other":"","name_hidden":false,"family_name":"Федоріщева К. А","name_unclear":false},{"inn":"","relations":"Дитина","relations_other":"","inn_hidden":false,"family_name":"Федоріщева Д. С","name_hidden":false,"name_unclear":false}],"inn_hidden":true,"family_raw":"","last_name":"Федоріщев","post":{"post_unclear":false,"post":"суддя жовтневого районного суду м. дніпропетровська","office_hidden":false,"region":"Дніпропетровська область","office":"Загальний місцевий суд","office_unclear":false},"full_name":"Федоріщев Сергій Сергійович","addresses":[{"place_city_type_hidden":false,"place_district_hidden":false,"place_city_type":"Місто","place_city_hidden":false,"place_address_unclear":true,"place_address":"","place_hidden":false,"place":"Дніпропетровська область","place_district":"","place_unclear":false,"place_city":"Дніпропетровськ","place_address_hidden":true}],"patronymic":"Сергійович","full_name_suggest":{"output":"Федоріщев Сергій Сергійович","input":["Федоріщев Сергій Сергійович","Сергій Сергійович Федоріщев","Сергій Федоріщев"]}},"source":"VULYK","estate":{"25":[{"space_unclear":false,"costs":"","costs_comment":"","address_hidden":true,"region_hidden":false,"space_comment":"","space":"16.4","address":"м. Дніпропетровськ","region":"Дніпропетровська область","costs_rent_comment":"","space_comment_unclear":false,"space_units":"м²","space_units_unclear":false,"costs_rent":""}],"29":[{"space_unclear":false,"address_hidden":true,"region_hidden":false,"space_comment":"","space":"454","address":"","region":"Дніпропетровська область","costs_property":"","costs_rent_comment":"","space_units":"м²","costs_property_comment":"","costs_rent":""}],"32":[{"space_unclear":false,"address_hidden":true,"region_hidden":false,"space_comment":"","space":"41","address":"м. Дніпродзержинськ","region":"Дніпропетровська область","costs_property":"","costs_rent_comment":"","space_units":"м²","costs_property_comment":"","costs_rent":""}]},"intro":{"declaration_year":"2015","isnotdeclaration":"","declaration_year_hidden":false}}},{"provider":"declarations.com.ua","document":{"income":{"5":{"value":"240058","family_comment":"","value_unclear":false,"family_hidden":false,"family_unclear":false,"family":"28338","comment":""},"6":{"value":"226059","value_unclear":false,"comment_hidden":false,"family_hidden":false,"value_hidden":false,"family_comment":"","family":"28192","comment":""},"7":{"value":"","family_comment":"","source_name":"","family":"","comment":"","source_name_hidden":false},"8":{"family_comment":"","value":"","family":"","comment":""},"9":{"family_comment":"","value":"569","family":"146","comment":"","value_hidden":false},"10":{"value":"12180","value_unclear":false,"family_hidden":false,"value_hidden":false,"family_comment":"","family":"","comment":""},"11":{"family_comment":"","value":"","family":"","comment":""},"12":{"family_comment":"","value":"","family":"","comment":""},"13":{"family_comment":"","value":"","comment_hidden":false,"family":"","comment":""},"14":{"value":"","comment_hidden":false,"value_hidden":false,"family_comment":"","family":"","comment":""},"15":{"family_comment":"","value":"1250","family":"","comment":""},"16":{"family_comment":"","value":"","family":"","comment":"","value_hidden":false},"17":{"family_comment":"","value":"","family":"","comment":""},"18":{"family_comment":"","value":"","family":"","comment":""},"19":{"family_comment":"","value":"","family":"","comment":"","value_hidden":false},"20":{"value":"","family_comment":"","comment_unclear":false,"family_unclear":false,"family":"","comment":""}},"vehicle":{"35":[{"brand_info":"2461 куб. см.","sum_rent_comment":"","sum_rent_hidden":false,"year":"2007","sum_hidden":false,"brand_info_hidden":false,"brand_info_unclear":false,"sum_rent":"","sum":"","brand":"Volkswagen T2 (Transporter","sum_comment":"","sum_rent_comment_hidden":false}]},"id":"vulyk_12_69","banks":{"45":[{"sum_foreign_comment":"","sum":"","sum_comment":"","sum_hidden":false,"sum_foreign_units":"UAH","sum_foreign_hidden":false,"sum_units":"UAH","sum_comment_hidden":false,"sum_unclear":false,"sum_foreign":"","sum_units_hidden":false},{"sum_foreign_comment":"","sum_units":"","sum_comment":"","sum_foreign_units":"","sum":"","sum_foreign":""}],"46":[{"sum_foreign_comment":"","sum_units":"UAH","sum_comment":"","sum_hidden":false,"sum_foreign_units":"UAH","sum":"","sum_foreign_hidden":false,"sum_foreign":""}],"47":[{"sum_foreign_comment":"","sum_units":"UAH","sum_comment":"","sum_comment_unclear":false,"sum_foreign_units":"UAH","sum":"","sum_foreign":""},{"sum_foreign_comment":"","sum_units":"","sum_comment":"","sum_foreign_units":"","sum":"","sum_foreign":""}],"48":[{"sum_foreign_comment":"","sum_units":"UAH","sum_comment":"","sum_foreign_units":"UAH","sum":"","sum_foreign":""}],"49":[{"sum_foreign_comment":"","sum_units":"UAH","sum_comment":"","sum_foreign_units":"UAH","sum":"","sum_foreign":""}],"50":[{"sum_foreign_comment":"","sum_units":"UAH","sum_comment":"","sum_foreign_units":"UAH","sum":"","sum_foreign":""}],"51":[{"sum_foreign_comment":"","sum_units":"UAH","sum_comment":"","sum_hidden":false,"sum_foreign_units":"UAH","sum_comment_hidden":false,"sum_units_hidden":false,"sum":"","sum_foreign":""}],"52":[{"sum_foreign_comment":"","sum_units":"UAH","sum_comment":"","sum_comment_unclear":false,"sum_foreign_units":"UAH","sum":"","sum_foreign":""},{"sum_foreign_comment":"","sum_units":"","sum_comment":"","sum_foreign_units":"","sum":"","sum_foreign":""},{"sum_foreign_comment":"","sum_units":"","sum_comment":"","sum_foreign_units":"","sum":"","sum_foreign":""},{"sum_foreign_comment":"","sum_units":"","sum_comment":"","sum_foreign_units":"","sum":"","sum_foreign":""}],"53":[{"sum_foreign_comment":"","sum_units":"UAH","sum_comment":"","sum_foreign_units":"UAH","sum":"","sum_foreign":""}]},"declaration":{"additional_info_text":"","notfull_lostpages":"","date":"2015-03-25T00:00:00","notfull":"","additional_info":"","url":"http://static.declarations.com.ua/declarations/chosen_ones/mega_batch/fedorishchev_serhii_serhiiovych.pdf"},"liabilities":{"54":{"sum_foreign_comment":"","sum":"","sum_comment":"","sum_hidden":false,"sum_comment_hidden":false,"sum_foreign":""},"55":{"sum_foreign_comment":"","sum":"","sum_comment":"","sum_foreign":""},"56":{"sum_foreign_comment":"","sum":"","sum_comment":"","sum_foreign":""},"57":{"sum_foreign_comment":"","sum":"","sum_comment":"","sum_comment_unclear":false,"sum_hidden":false,"sum_comment_hidden":false,"sum_unclear":false,"sum_foreign":""},"58":{"sum_foreign_comment":"","sum":"","sum_comment":"","sum_comment_unclear":false,"sum_hidden":false,"sum_foreign":""},"59":{"sum_foreign_comment":"","sum":"","sum_hidden":false,"sum_comment":"","sum_foreign":""},"60":{"sum_foreign_comment":"","sum":"","sum_comment":"","sum_hidden":false,"sum_comment_hidden":false,"sum_foreign":""},"61":{"sum_foreign_comment":"","sum":"","sum_comment":"","sum_foreign":""},"62":{"sum_foreign_comment":"","sum":"","sum_comment":"","sum_comment_unclear":false,"sum_unclear":false,"sum_foreign":""},"63":{"sum_foreign_comment":"","sum":"","sum_comment":"","sum_comment_unclear":false,"sum_foreign":""},"64":{"sum_foreign_comment":"","sum":"","sum_comment":"","sum_comment_unclear":false,"sum_foreign":""}},"ft_src":"суддя жовтневого районного суду м. дніпропетровська\nДніпропетровська область\nЗагальний місцевий суд\nСергій\nФедоріщева К. А\nПодружжя\nФедоріщева Д. С\nДитина\nСергійович\nФедоріщев\nФедоріщев Сергій Сергійович\nФедоріщев Сергій Сергійович\nСергій Сергійович Федоріщев\nСергій Федоріщев\nФедоріщев Сергій Сергійович\n2461 куб. см.\nVolkswagen T2 (Transporter\n2007\n2014\n2461 куб. см.\nVolkswagen T2 (Transporter\n2007\n454\nДніпропетровська область\n12\nДніпропетровська область\nм. Дніпропетровськ\n41\nДніпропетровська область\nЗагальний місцевий суд\nсуддя жовтневого районного суду м. дніпропетровська\nДніпропетровська область\nПодружжя\nФедоріщева К. А\nДитина\nФедоріщева Д. С\nФедоріщев Сергій Сергійович\nСергій Сергійович Федоріщев\nСергій Федоріщев\nФедоріщев Сергій Сергійович\nСергій\nФедоріщев Сергій Сергійович\nФедоріщев\nСергійович\n226059\n28192\n1250\n28338\n240058\n12180\n569\n146\n2014\nДніпропетровська область\n454\nДніпропетровська область\n41\nм. Дніпропетровськ\n12\nДніпропетровська область\nПодружжя\nФедоріщева К. А\nФедоріщева Д. С\nДитина\nСергійович\nФедоріщев\nСергій\nФедоріщев Сергій Сергійович\nСергій Сергійович Федоріщев\nСергій Федоріщев\nФедоріщев Сергій Сергійович\nДніпропетровська область\nЗагальний місцевий суд\nсуддя жовтневого районного суду м. дніпропетровська\nФедоріщев Сергій Сергійович\n28192\n226059\n1250\n12180\n28338\n240058\n146\n569\nVolkswagen T2 (Transporter\n2461 куб. см.\n2007\n1250\n12180\n240058\n28338\n146\n569\n226059\n28192\nм. Дніпропетровськ\nДніпропетровська область\n12\nДніпропетровська область\n454\nДніпропетровська область\n41\n2014","general":{"inn":"","name":"Сергій","patronymic_unclear":false,"last_name_hidden":false,"family":[{"inn":"","inn_hidden":true,"relations_unclear":false,"relations_hidden":false,"relations_other":"","relations":"Подружжя","name_hidden":false,"inn_unclear":false,"family_name":"Федоріщева К. А","name_unclear":false},{"inn":"","relations":"Дитина","inn_unclear":false,"family_name":"Федоріщева Д. С","inn_hidden":true,"relations_other":"","name_hidden":false,"name_unclear":false}],"patronymic":"Сергійович","inn_hidden":true,"family_raw":"","inn_unclear":false,"post":{"post_unclear":false,"post":"суддя жовтневого районного суду м. дніпропетровська","candidate":"","office_hidden":false,"region":"Дніпропетровська область","post_hidden":false,"office":"Загальний місцевий суд","office_unclear":false},"last_name_unclear":false,"full_name":"Федоріщев Сергій Сергійович","addresses":[{"place_district":"","place_city_hidden":false,"place_city":"","place_city_type_hidden":false,"place_district_hidden":false,"place_city_type":"","place_address_hidden":false,"place_address":"","place_hidden":true,"place":""}],"last_name":"Федоріщев","patronymic_hidden":false,"full_name_suggest":{"output":"Федоріщев Сергій Сергійович","input":["Федоріщев Сергій Сергійович","Сергій Сергійович Федоріщев","Сергій Федоріщев"]}},"source":"VULYK","estate":{"23":[{"space_unclear":false,"costs":"","costs_comment":"","address_hidden":false,"region_hidden":false,"space_comment":"","space_hidden":false,"space":"","address":"","costs_comment_unclear":false,"region":"","address_unclear":false,"costs_rent_comment":"","space_units":"м²","costs_rent":""},{"space_unclear":false,"costs":"","costs_comment":"","address_hidden":false,"region_hidden":false,"space_comment":"","space":"","address":"","region":"","costs_rent_comment":"","space_units":"","costs_rent":""},{"space_hidden":false,"costs":"","costs_comment":"","address_hidden":false,"region_hidden":false,"space_comment":"","space":"","address":"","region":"","costs_rent_comment":"","space_units":"","costs_rent":""},{"costs_rent":"","region":"","costs":"","costs_rent_comment":"","costs_comment":"","space_comment":"","space_units":"","space":"","address":""}],"25":[{"region_unclear":false,"space_hidden":false,"costs":"","costs_comment":"","costs_hidden":false,"address_hidden":false,"region_hidden":false,"space_comment":"","space_unclear":false,"space":"12","address":"м. Дніпропетровськ","region":"Дніпропетровська область","address_unclear":false,"costs_rent_comment":"","costs_rent_hidden":false,"space_comment_unclear":false,"space_units":"м²","costs_rent":""}],"29":[{"region_unclear":false,"space_unclear":false,"address_hidden":true,"region_hidden":false,"space_comment":"","space":"454","address":"","region":"Дніпропетровська область","costs_property":"","costs_rent_comment":"","space_comment_unclear":false,"address_unclear":false,"space_units":"м²","costs_property_comment":"","costs_rent":""}],"32":[{"space_unclear":false,"address_hidden":false,"region_hidden":false,"space_comment":"","space":"41","address":"","region":"Дніпропетровська область","costs_property":"","costs_rent_comment":"","space_units":"м²","costs_property_comment":"","costs_rent":""}]},"intro":{"declaration_year":"2014","isnotdeclaration":""}}},{"provider":"public-api.nazk.gov.ua","document":{"step_0":{"declarationType":"1","declarationYear1":"2015"},"step_1":{"region":"[Конфіденційна інформація]","street":"[Конфіденційна інформація]","country":"1","cityPath":"[Конфіденційна інформація]","cityType":"[Конфіденційна інформація]","lastname":"Федоріщев","postCode":"[Конфіденційна інформація]","postType":"","workPost":"суддя","firstname":"Сергій","workPlace":"Жовтневий районний суд міста Дніпропетровська","middlename":"Сергійович","streetType":"[Конфіденційна інформація]","changedName":false,"countryPath":"","eng_postCode":"","postCategory":"","actual_street":"[Конфіденційна інформація]","actual_cityPath":"[Конфіденційна інформація]","actual_cityType":"[Конфіденційна інформація]","actual_postCode":"[Конфіденційна інформація]","actual_streetType":"[Конфіденційна інформація]","previous_lastname":"","corruptionAffected":"Ні","eng_actualPostCode":"[Конфіденційна інформація]","previous_firstname":"","previous_middlename":"","responsiblePosition":"Суддя суду загальної юрисдикції, суддя Конституційного Суду України","sameRegLivingAddress":"[Конфіденційна інформація]","eng_sameRegLivingAddress":"[Конфіденційна інформація]"},"step_2":{"1476340198597":{"lastname":"Федоріщева","firstname":"Катерина","middlename":"Арнольдівна","changedName":false,"citizenship":"1","eng_lastname":"","no_taxNumber":false,"eng_firstname":"","eng_middlename":"","isNotApplicable":"","subjectRelation":"дружина","previous_lastname":"","previous_firstname":"","previous_middlename":"","previous_eng_lastname":"","previous_eng_firstname":"","previous_eng_middlename":""},"1476340350196":{"lastname":"Федоріщева","firstname":"Дар'я","middlename":"Сергіївна","changedName":false,"citizenship":"1","eng_lastname":"","no_taxNumber":false,"eng_firstname":"","eng_middlename":"","isNotApplicable":"","subjectRelation":"дочка","previous_lastname":"","previous_firstname":"","previous_middlename":"","previous_eng_lastname":"","previous_eng_firstname":"","previous_eng_middlename":""}},"step_3":{"1476470783347":{"person":"1","region":"[Конфіденційна інформація]","rights":{"1476775616106":{"citizen":"Юридична особа, зареєстрована в Україні","ua_city":"","ua_street":"[Конфіденційна інформація]","ua_lastname":"","ua_postCode":"","eng_lastname":"","eng_postCode":"","rightBelongs":"j","ua_firstname":"","ukr_lastname":"","eng_firstname":"","ownershipType":"Інше право користування","ua_middlename":"","ua_streetType":"[Конфіденційна інформація]","ukr_firstname":"","eng_middlename":"","otherOwnership":"маю право на проживання з сім'єю на підставі ордеру","ukr_middlename":"","rights_cityPath":"","ua_company_name":" \"ЖИЛСЕРВІС-5\" ДНІПРОПЕТРОВСЬКОЇ МІСЬКОЇ РАДИ","eng_company_name":"","ukr_company_name":"","percent-ownership":"0","ua_street_extendedstatus":"","ua_houseNum_extendedstatus":"","ua_postCode_extendedstatus":"","eng_postCode_extendedstatus":"","ua_middlename_extendedstatus":"","eng_middlename_extendedstatus":"","ukr_middlename_extendedstatus":"","ua_housePartNum_extendedstatus":"","ua_apartmentsNum_extendedstatus":""}},"country":"1","cityPath":"[Конфіденційна інформація]","costDate":"","postCode":"[Конфіденційна інформація]","totalArea":"16.40","ua_street":"[Конфіденційна інформація]","objectType":"Квартира","owningDate":"14.11.2000","ua_cityType":"Дніпропетровська Область / Україна","ua_postCode":"49081","ua_streetType":"[Конфіденційна інформація]","costAssessment":"","otherObjectType":"","costDate_extendedstatus":"2","regNumber_extendedstatus":"2","costAssessment_extendedstatus":"2"},"1476472521854":{"person":"1476340198597","region":"[Конфіденційна інформація]","rights":{"1476340198597":{"citizen":"","ua_city":"","ua_street":"[Конфіденційна інформація]","ua_lastname":"","ua_postCode":"","eng_lastname":"","eng_postCode":"","rightBelongs":"1476340198597","ua_firstname":"","ukr_lastname":"","eng_firstname":"","ownershipType":"Власність","ua_middlename":"","ua_streetType":"[Конфіденційна інформація]","ukr_firstname":"","eng_middlename":"","otherOwnership":"","ukr_middlename":"","rights_cityPath":"","ua_company_name":"","eng_company_name":"","ukr_company_name":"","percent-ownership":"100","ua_street_extendedstatus":"","ua_houseNum_extendedstatus":"","ua_postCode_extendedstatus":"","eng_postCode_extendedstatus":"","ua_middlename_extendedstatus":"","eng_middlename_extendedstatus":"","ukr_middlename_extendedstatus":"","ua_housePartNum_extendedstatus":"","ua_apartmentsNum_extendedstatus":""}},"country":"1","cityPath":"[Конфіденційна інформація]","costDate":"","district":"[Конфіденційна інформація]","postCode":"[Конфіденційна інформація]","totalArea":"454","ua_street":"[Конфіденційна інформація]","objectType":"Земельна ділянка","owningDate":"17.09.2015","ua_cityType":"Кам'янське / Дніпропетровська Область / Україна","ua_postCode":"51900","ua_streetType":"[Конфіденційна інформація]","costAssessment":"","otherObjectType":"","costDate_extendedstatus":"2","costAssessment_extendedstatus":"2"}},"step_4":{"1476775906605":{"person":"1476340198597","region":"[Конфіденційна інформація]","rights":{"1476340198597":{"citizen":"","ua_city":"","ua_street":"[Конфіденційна інформація]","ua_lastname":"","ua_postCode":"","eng_lastname":"","eng_postCode":"","rightBelongs":"1476340198597","ua_firstname":"","ukr_lastname":"","eng_firstname":"","ownershipType":"Власність","ua_middlename":"","ua_streetType":"[Конфіденційна інформація]","ukr_firstname":"","eng_middlename":"","otherOwnership":"","ukr_middlename":"","rights_cityPath":"","ua_company_name":"","eng_company_name":"","ukr_company_name":"","percent-ownership":"","ua_street_extendedstatus":"","ua_houseNum_extendedstatus":"","ua_postCode_extendedstatus":"","eng_postCode_extendedstatus":"","ua_middlename_extendedstatus":"","eng_middlename_extendedstatus":"","ukr_middlename_extendedstatus":"","ua_housePartNum_extendedstatus":"","ua_apartmentsNum_extendedstatus":""}},"country":"1","ua_area":"","cityPath":"[Конфіденційна інформація]","district":"[Конфіденційна інформація]","postCode":"[Конфіденційна інформація]","totalArea":"","ua_region":"","ua_street":"[Конфіденційна інформація]","objectType":"Садовий (дачний) будинок","ua_cityType":"Кам'янське / Дніпропетровська Область / Україна","ua_postCode":"51937","exploitation":false,"isThirdOwner":false,"ua_city_full":"","ua_streetType":"[Конфіденційна інформація]","dontRegistered":false,"otherObjectType":"","unfinishConstruct":true,"builtMaterialsOrFunds":true,"regNumber_extendedstatus":"2","totalArea_extendedstatus":"2","ua_street_extendedstatus":"1","belongsSubjectOfDeclaration":false,"ua_streetType_extendedstatus":"1"}},"step_5":[],"step_6":{"1476515456076":{"brand":"Volkswagen","model":"TRANSPORTER","person":"1","rights":{"1":{"citizen":"","ua_city":"","ua_street":"[Конфіденційна інформація]","ua_lastname":"","ua_postCode":"","eng_lastname":"","eng_postCode":"","rightBelongs":"1","ua_firstname":"","ukr_lastname":"","eng_firstname":"","ownershipType":"Власність","ua_middlename":"","ua_streetType":"[Конфіденційна інформація]","ukr_firstname":"","eng_middlename":"","otherOwnership":"","ukr_middlename":"","rights_cityPath":"","ua_company_name":"","eng_company_name":"","ukr_company_name":"","percent-ownership":"","ua_street_extendedstatus":"","ua_houseNum_extendedstatus":"","ua_postCode_extendedstatus":"","eng_postCode_extendedstatus":"","ua_middlename_extendedstatus":"","eng_middlename_extendedstatus":"","ukr_middlename_extendedstatus":"","ua_housePartNum_extendedstatus":"","ua_apartmentsNum_extendedstatus":""}},"costDate":"69700","objectType":"Автомобіль легковий","owningDate":"06.04.2013","typeProperty":"","graduationYear":"2007","otherTypeProperty":""},"1476515864301":{"brand":"КРЕОН","model":"ПУ-ТД-2000","person":"1","rights":{"1":{"citizen":"","ua_city":"","ua_street":"[Конфіденційна інформація]","ua_lastname":"","ua_postCode":"","eng_lastname":"","eng_postCode":"","rightBelongs":"1","ua_firstname":"","ukr_lastname":"","eng_firstname":"","ownershipType":"Власність","ua_middlename":"","ua_streetType":"[Конфіденційна інформація]","ukr_firstname":"","eng_middlename":"","otherOwnership":"","ukr_middlename":"","rights_cityPath":"","ua_company_name":"","eng_company_name":"","ukr_company_name":"","percent-ownership":"","ua_street_extendedstatus":"","ua_houseNum_extendedstatus":"","ua_postCode_extendedstatus":"","eng_postCode_extendedstatus":"","ua_middlename_extendedstatus":"","eng_middlename_extendedstatus":"","ukr_middlename_extendedstatus":"","ua_housePartNum_extendedstatus":"","ua_apartmentsNum_extendedstatus":""}},"costDate":"4950","objectType":"Інше","owningDate":"28.03.2014","typeProperty":"","graduationYear":"2014","otherObjectType":"причеп легковий","otherTypeProperty":""},"1476728074265":{"brand":"MERCEDES-BENZ","model":"SPRINTER 313 CDI","person":"1","rights":{"1476772687225":{"citizen":"Громадянин України","ua_city":"Кам'янське / Дніпропетровська Область / Україна","ua_street":"[Конфіденційна інформація]","ua_lastname":"Федоріщева","ua_postCode":"51937","eng_lastname":"","eng_postCode":"","rightBelongs":"j","ua_firstname":"Валентина","ukr_lastname":"","eng_firstname":"","ownershipType":"Інше право користування","ua_middlename":"Іванівна","ua_streetType":"[Конфіденційна інформація]","ukr_firstname":"","eng_middlename":"","otherOwnership":"маю право керувати за довіреністю","ukr_middlename":"","rights_cityPath":"1.2.12.1.4","ua_company_name":"","eng_company_name":"","ukr_company_name":"","percent-ownership":"","ua_street_extendedstatus":"","ua_houseNum_extendedstatus":"","ua_postCode_extendedstatus":"","eng_postCode_extendedstatus":"","ua_middlename_extendedstatus":"","eng_middlename_extendedstatus":"","ukr_middlename_extendedstatus":"","ua_housePartNum_extendedstatus":"","ua_apartmentsNum_extendedstatus":""}},"costDate":"179520","objectType":"Інше","owningDate":"10.07.2014","typeProperty":"","graduationYear":"2007","otherObjectType":"автомобіль вантажопасажирський-В ","otherTypeProperty":""}},"step_7":[],"step_8":[],"step_9":[],"step_10":[],"step_11":{"1476731291363":{"person":"1","rights":{"1":{"citizen":"","ua_city":"","ua_street":"[Конфіденційна інформація]","ua_lastname":"","ua_postCode":"","eng_lastname":"","eng_postCode":"","rightBelongs":"1","ua_firstname":"","ukr_lastname":"","eng_firstname":"","ownershipType":"Власність","ua_middlename":"","ua_streetType":"[Конфіденційна інформація]","ukr_firstname":"","eng_middlename":"","otherOwnership":"","ukr_middlename":"","rights_cityPath":"","ua_company_name":"","eng_company_name":"","ukr_company_name":"","percent-ownership":"","ua_street_extendedstatus":"","ua_houseNum_extendedstatus":"","ua_postCode_extendedstatus":"","eng_postCode_extendedstatus":"","ua_middlename_extendedstatus":"","eng_middlename_extendedstatus":"","ukr_middlename_extendedstatus":"","ua_housePartNum_extendedstatus":"","ua_apartmentsNum_extendedstatus":""}},"objectType":"Заробітна плата отримана за основним місцем роботи","sizeIncome":"165548","incomeSource":"j","source_citizen":"Юридична особа, зареєстрована в Україні","otherObjectType":"","source_ua_lastname":"","source_eng_lastname":"","source_ua_firstname":"","source_ukr_lastname":"","source_eng_firstname":"","source_ua_middlename":"","source_ukr_firstname":"","source_eng_middlename":"","source_ukr_middlename":"","source_ua_company_name":"ТУ ДСА України в Дніпропетровській області","source_eng_company_name":"","source_ukr_company_name":"","source_ua_sameRegLivingAddress":"","source_eng_sameRegLivingAddress":""},"1476731831589":{"person":"1","rights":{"1":{"citizen":"","ua_city":"","ua_street":"[Конфіденційна інформація]","ua_lastname":"","ua_postCode":"","eng_lastname":"","eng_postCode":"","rightBelongs":"1","ua_firstname":"","ukr_lastname":"","eng_firstname":"","ownershipType":"Власність","ua_middlename":"","ua_streetType":"[Конфіденційна інформація]","ukr_firstname":"","eng_middlename":"","otherOwnership":"","ukr_middlename":"","rights_cityPath":"","ua_company_name":"","eng_company_name":"","ukr_company_name":"","percent-ownership":"","ua_street_extendedstatus":"","ua_houseNum_extendedstatus":"","ua_postCode_extendedstatus":"","eng_postCode_extendedstatus":"","ua_middlename_extendedstatus":"","eng_middlename_extendedstatus":"","ukr_middlename_extendedstatus":"","ua_housePartNum_extendedstatus":"","ua_apartmentsNum_extendedstatus":""}},"objectType":"Гонорари та інші виплати згідно з цивільно-правовим правочинами","sizeIncome":"1788","incomeSource":"j","source_citizen":"Юридична особа, зареєстрована в Україні","otherObjectType":"","source_ua_lastname":"","source_eng_lastname":"","source_ua_firstname":"","source_ukr_lastname":"","source_eng_firstname":"","source_ua_middlename":"","source_ukr_firstname":"","source_eng_middlename":"","source_ukr_middlename":"","source_ua_company_name":"Національна школа суддів України","source_eng_company_name":"","source_ukr_company_name":"","source_ua_sameRegLivingAddress":"","source_eng_sameRegLivingAddress":""},"1476732991777":{"person":"1","rights":{"1":{"citizen":"","ua_city":"","ua_street":"[Конфіденційна інформація]","ua_lastname":"","ua_postCode":"","eng_lastname":"","eng_postCode":"","rightBelongs":"1","ua_firstname":"","ukr_lastname":"","eng_firstname":"","ownershipType":"Власність","ua_middlename":"","ua_streetType":"[Конфіденційна інформація]","ukr_firstname":"","eng_middlename":"","otherOwnership":"","ukr_middlename":"","rights_cityPath":"","ua_company_name":"","eng_company_name":"","ukr_company_name":"","percent-ownership":"","ua_street_extendedstatus":"","ua_houseNum_extendedstatus":"","ua_postCode_extendedstatus":"","eng_postCode_extendedstatus":"","ua_middlename_extendedstatus":"","eng_middlename_extendedstatus":"","ukr_middlename_extendedstatus":"","ua_housePartNum_extendedstatus":"","ua_apartmentsNum_extendedstatus":""}},"objectType":"Проценти","sizeIncome":"6","incomeSource":"j","source_citizen":"Юридична особа, зареєстрована в Україні","otherObjectType":"","source_ua_lastname":"","source_eng_lastname":"","source_ua_firstname":"","source_ukr_lastname":"","source_eng_firstname":"","source_ua_middlename":"","source_ukr_firstname":"","source_eng_middlename":"","source_ukr_middlename":"","source_ua_company_name":"ПАТ КБ ПРИВАТБАНК","source_eng_company_name":"","source_ukr_company_name":"","source_ua_sameRegLivingAddress":"","source_eng_sameRegLivingAddress":""},"1476734558693":{"person":"1476340198597","rights":{"1476340198597":{"citizen":"","ua_city":"","ua_street":"[Конфіденційна інформація]","ua_lastname":"","ua_postCode":"","eng_lastname":"","eng_postCode":"","rightBelongs":"1476340198597","ua_firstname":"","ukr_lastname":"","eng_firstname":"","ownershipType":"Власність","ua_middlename":"","ua_streetType":"[Конфіденційна інформація]","ukr_firstname":"","eng_middlename":"","otherOwnership":"","ukr_middlename":"","rights_cityPath":"","ua_company_name":"","eng_company_name":"","ukr_company_name":"","percent-ownership":"","ua_street_extendedstatus":"","ua_houseNum_extendedstatus":"","ua_postCode_extendedstatus":"","eng_postCode_extendedstatus":"","ua_middlename_extendedstatus":"","eng_middlename_extendedstatus":"","ukr_middlename_extendedstatus":"","ua_housePartNum_extendedstatus":"","ua_apartmentsNum_extendedstatus":""}},"objectType":"Заробітна плата отримана за основним місцем роботи","sizeIncome":"24242","incomeSource":"j","source_citizen":"Юридична особа, зареєстрована в Україні","otherObjectType":"","source_ua_lastname":"","source_eng_lastname":"","source_ua_firstname":"","source_ukr_lastname":"","source_eng_firstname":"","source_ua_middlename":"","source_ukr_firstname":"","source_eng_middlename":"","source_ukr_middlename":"","source_ua_company_name":"Комунальний заклад \"Навчально-виховне об'єднання \"Дошкільний навчальний заклад - загальноосвітній навчальний заклад I - II ступенів - ліцей нових інформаційних технологій м. Дніпродзержинська\" Дніпродзержинської міської ради","source_eng_company_name":"","source_ukr_company_name":"","source_ua_sameRegLivingAddress":"","source_eng_sameRegLivingAddress":""},"1476945124809":{"person":"1","rights":{"1":{"citizen":"","ua_city":"","ua_street":"[Конфіденційна інформація]","ua_lastname":"","ua_postCode":"","eng_lastname":"","eng_postCode":"","rightBelongs":"1","ua_firstname":"","ukr_lastname":"","eng_firstname":"","ownershipType":"Власність","ua_middlename":"","ua_streetType":"[Конфіденційна інформація]","ukr_firstname":"","eng_middlename":"","otherOwnership":"","ukr_middlename":"","rights_cityPath":"","ua_company_name":"","eng_company_name":"","ukr_company_name":"","percent-ownership":"","ua_street_extendedstatus":"","ua_houseNum_extendedstatus":"","ua_postCode_extendedstatus":"","eng_postCode_extendedstatus":"","ua_middlename_extendedstatus":"","eng_middlename_extendedstatus":"","ukr_middlename_extendedstatus":"","ua_housePartNum_extendedstatus":"","ua_apartmentsNum_extendedstatus":""}},"objectType":"Інше","sizeIncome":"133878","incomeSource":"j","source_citizen":"Юридична особа, зареєстрована в Україні","otherObjectType":"грошові кошти з банківської кредитної картки","source_ua_lastname":"","source_eng_lastname":"","source_ua_firstname":"","source_ukr_lastname":"","source_eng_firstname":"","source_ua_middlename":"","source_ukr_firstname":"","source_eng_middlename":"","source_ukr_middlename":"","source_ua_company_name":"ПАТ КБ \"ПРИВАТБАНК\"","source_eng_company_name":"","source_ukr_company_name":"","source_ua_sameRegLivingAddress":"","source_eng_sameRegLivingAddress":""}},"step_12":[],"step_13":[],"step_14":{"1476989657110":{"type":1,"person":"","country":"1","costAmount":"133878","costsAmount":"","specExpenses":"Інше","specOtherExpenses":"повернення коштів на кредитну картку","specExpensesSubject":"Рухоме майно","specExpensesOtherSubject":"","specExpensesAssetsSubject":"","specExpensesRealtySubject":"","specExpensesMovableSubject":"Грошові кошти","specExpensesOtherRealtySubject":"","specExpensesOtherMovableSubject":""}},"step_15":[],"step_16":[],"id":"3c97aefe-c1a6-4a40-8e78-a0ac9c94d167"}}],"declarations":[{"income":{"5":{"value":"301220","family_comment":"","value_unclear":false,"family_unclear":false,"family":"24242","comment":""},"6":{"family_comment":"","family_unclear":false,"value":"153368","family":"22768","comment":""},"7":{"source_name_unclear":true,"value":"1788","family_comment":"","source_name":"Національна школа суддів України","family":"","comment":"Національна школа суддів України"},"8":{"family_comment":"","value":"","family":"","comment":""},"9":{"value":"","family_comment":"","comment_hidden":false,"family_unclear":false,"family":"","comment":"","family_comment_hidden":false},"10":{"family_comment":"","value":"12180","family":"1474","comment":""},"11":{"family_comment":"","value":"","family":"","comment":""},"12":{"family_comment":"","value":"","family":"","comment":""},"13":{"family_comment":"","value":"","family":"","comment":""},"14":{"family_comment":"","value":"","family":"","comment":""},"15":{"family_comment":"","value":"","family":"","comment":""},"16":{"family_comment":"","value":"","family":"","comment":""},"17":{"family_comment":"","value":"","family":"","comment":""},"18":{"family_comment":"","value":"","family":"","comment":""},"19":{"family_comment":"","value":"","family":"","comment":""},"20":{"value":"133884","value_unclear":false,"comment_hidden":false,"family_comment":"","comment_unclear":false,"comment":"133878 - кредитна картка Приватбанк, 6 - % Приватбанк","family":""}},"vehicle":{"35":[{"brand_info":"2461 куб. см, у власності","sum_rent_comment":"","brand":"Volkswagen Transporter","sum_comment":"","year":"2007","brand_info_unclear":false,"sum":"","sum_rent":""}],"36":[{"brand_info":"вантажопасажирський 2148 куб. см, маю право керувати на підставі довіреності","sum_rent_comment":"","brand":"Mercedes-Benz Sprinter 313","sum_comment":"","year":"2007","sum":"","sum_rent":""}],"39":[{"brand_info":"легковий причіп, у власності","sum_rent_comment":"","brand":"Креон","sum_comment":"","year":"2014","sum":"","sum_rent":""}]},"id":"vulyk_108_150","declaration":{"additional_info_text":"","notfull_lostpages":"","date":"2016-03-31T00:00:00","notfull":"","additional_info":"","url":"http://static.declarations.com.ua/declarations/chosen_ones/judges_batch/2449_fedorishchev_serhii_serhiiovych_2015.pdf"},"liabilities":{"54":{"sum_foreign_comment":"","sum":"120","sum_hidden":false,"sum_comment":"Приватбанк - страхування здоров'я","sum_foreign":""},"55":{"sum_foreign_comment":"","sum":"","sum_comment":"","sum_foreign":""},"56":{"sum_foreign_comment":"","sum":"","sum_comment":"","sum_unclear":false,"sum_foreign":""},"57":{"sum_foreign_comment":"","sum":"133878","sum_comment":"Кредитна карта Приватбанк","sum_hidden":false,"sum_comment_hidden":false,"sum_foreign":""},"58":{"sum_foreign_comment":"","sum_comment_hidden":false,"sum":"","sum_comment":"","sum_foreign":""},"59":{"sum_foreign_comment":"","sum":"","sum_comment":"","sum_unclear":false,"sum_foreign":""},"60":{"sum_foreign_comment":"","sum_comment_hidden":false,"sum":"","sum_comment":"","sum_foreign":""},"61":{"sum_foreign_comment":"","sum_comment_hidden":false,"sum":"","sum_comment":"","sum_foreign":""},"62":{"sum_foreign_comment":"","sum":"","sum_comment":"","sum_foreign":""},"63":{"sum_foreign_comment":"","sum":"","sum_comment":"","sum_hidden":false,"sum_comment_hidden":false,"sum_unclear":false,"sum_foreign":""},"64":{"sum_foreign_comment":"","sum":"","sum_comment":"","sum_comment_hidden":false,"sum_unclear":false,"sum_foreign":""}},"ft_src":"Кредитна карта Приватбанк\n133878\nПриватбанк - страхування здоров'я\n120\nДніпропетровськ\nДніпропетровська область\nсуддя жовтневого районного суду м. дніпропетровська\nДніпропетровська область\nЗагальний місцевий суд\nСергій\nФедоріщева К. А\nПодружжя\nФедоріщева Д. С\nДитина\nСергійович\nФедоріщев Сергій Сергійович\nСергій Сергійович Федоріщев\nСергій Федоріщев\nФедоріщев Сергій Сергійович\nФедоріщев Сергій Сергійович\nФедоріщев\nлегковий причіп, у власності\n2014\nКреон\n2461 куб. см, у власності\n2007\nVolkswagen Transporter\nвантажопасажирський 2148 куб. см, маю право керувати на підставі довіреності\n2007\nMercedes-Benz Sprinter 313\nДніпропетровська область\n454\nм. Дніпродзержинськ\nДніпропетровська область\n41\nм. Дніпропетровськ\n16.4\nДніпропетровська область\n2015\n22768\n153368\n1474\n12180\nНаціональна школа суддів України\nНаціональна школа суддів України\n1788\n24242\n301220\n133878 - кредитна картка Приватбанк, 6 - % Приватбанк\n133884\n2461 куб. см, у власності\n2007\nVolkswagen Transporter\nлегковий причіп, у власності\n2014\nКреон\nвантажопасажирський 2148 куб. см, маю право керувати на підставі довіреності\n2007\nMercedes-Benz Sprinter 313\n2015\nФедоріщев Сергій Сергійович\nСергій Сергійович Федоріщев\nСергій Федоріщев\nФедоріщев Сергій Сергійович\nСергій\nПодружжя\nФедоріщева К. А\nДитина\nФедоріщева Д. С\nФедоріщев Сергій Сергійович\nСергійович\nЗагальний місцевий суд\nДніпропетровська область\nсуддя жовтневого районного суду м. дніпропетровська\nФедоріщев\nДніпропетровськ\nДніпропетровська область\n133878\nКредитна карта Приватбанк\n120\nПриватбанк - страхування здоров'я\n1788\nНаціональна школа суддів України\nНаціональна школа суддів України\n153368\n22768\n133884\n133878 - кредитна картка Приватбанк, 6 - % Приватбанк\n301220\n24242\n12180\n1474\n454\nДніпропетровська область\n16.4\nм. Дніпропетровськ\nДніпропетровська область\n41\nм. Дніпродзержинськ\nДніпропетровська область\nКредитна карта Приватбанк\n133878\nПриватбанк - страхування здоров'я\n120\nПодружжя\nФедоріщева К. А\nДитина\nФедоріщева Д. С\nСергійович\nФедоріщев\nСергій\nФедоріщев Сергій Сергійович\nСергій Сергійович Федоріщев\nСергій Федоріщев\nФедоріщев Сергій Сергійович\nДніпропетровська область\nДніпропетровськ\nДніпропетровська область\nсуддя жовтневого районного суду м. дніпропетровська\nЗагальний місцевий суд\nФедоріщев Сергій Сергійович\nКреон\nлегковий причіп, у власності\n2014\n2007\n2461 куб. см, у власності\nVolkswagen Transporter\nMercedes-Benz Sprinter 313\nвантажопасажирський 2148 куб. см, маю право керувати на підставі довіреності\n2007\n1474\n12180\n133884\n133878 - кредитна картка Приватбанк, 6 - % Приватбанк\n301220\n24242\n1788\nНаціональна школа суддів України\nНаціональна школа суддів України\n22768\n153368\nм. Дніпропетровськ\nДніпропетровська область\n16.4\nДніпропетровська область\n454\nм. Дніпродзержинськ\nДніпропетровська область\n41\n2015","general":{"inn":"","name":"Сергій","inn_unclear":true,"family":[{"inn":"","relations":"Подружжя","inn_unclear":true,"relations_hidden":false,"inn_hidden":true,"relations_other":"","name_hidden":false,"family_name":"Федоріщева К. А","name_unclear":false},{"inn":"","relations":"Дитина","relations_other":"","inn_hidden":false,"family_name":"Федоріщева Д. С","name_hidden":false,"name_unclear":false}],"inn_hidden":true,"family_raw":"","last_name":"Федоріщев","post":{"post_unclear":false,"post":"суддя жовтневого районного суду м. дніпропетровська","office_hidden":false,"region":"Дніпропетровська область","office":"Загальний місцевий суд","office_unclear":false},"full_name":"Федоріщев Сергій Сергійович","addresses":[{"place_city_type_hidden":false,"place_district_hidden":false,"place_city_type":"Місто","place_city_hidden":false,"place_address_unclear":true,"place_address":"","place_hidden":false,"place":"Дніпропетровська область","place_district":"","place_unclear":false,"place_city":"Дніпропетровськ","place_address_hidden":true}],"patronymic":"Сергійович","full_name_suggest":{"output":"Федоріщев Сергій Сергійович","input":["Федоріщев Сергій Сергійович","Сергій Сергійович Федоріщев","Сергій Федоріщев"]}},"source":"VULYK","estate":{"25":[{"space_unclear":false,"costs":"","costs_comment":"","address_hidden":true,"region_hidden":false,"space_comment":"","space":"16.4","address":"м. Дніпропетровськ","region":"Дніпропетровська область","costs_rent_comment":"","space_comment_unclear":false,"space_units":"м²","space_units_unclear":false,"costs_rent":""}],"29":[{"space_unclear":false,"address_hidden":true,"region_hidden":false,"space_comment":"","space":"454","address":"","region":"Дніпропетровська область","costs_property":"","costs_rent_comment":"","space_units":"м²","costs_property_comment":"","costs_rent":""}],"32":[{"space_unclear":false,"address_hidden":true,"region_hidden":false,"space_comment":"","space":"41","address":"м. Дніпродзержинськ","region":"Дніпропетровська область","costs_property":"","costs_rent_comment":"","space_units":"м²","costs_property_comment":"","costs_rent":""}]},"intro":{"declaration_year":"2015","isnotdeclaration":"","declaration_year_hidden":false}},{"income":{"5":{"value":"240058","family_comment":"","value_unclear":false,"family_hidden":false,"family_unclear":false,"family":"28338","comment":""},"6":{"value":"226059","value_unclear":false,"comment_hidden":false,"family_hidden":false,"value_hidden":false,"family_comment":"","family":"28192","comment":""},"7":{"value":"","family_comment":"","source_name":"","family":"","comment":"","source_name_hidden":false},"8":{"family_comment":"","value":"","family":"","comment":""},"9":{"family_comment":"","value":"569","family":"146","comment":"","value_hidden":false},"10":{"value":"12180","value_unclear":false,"family_hidden":false,"value_hidden":false,"family_comment":"","family":"","comment":""},"11":{"family_comment":"","value":"","family":"","comment":""},"12":{"family_comment":"","value":"","family":"","comment":""},"13":{"family_comment":"","value":"","comment_hidden":false,"family":"","comment":""},"14":{"value":"","comment_hidden":false,"value_hidden":false,"family_comment":"","family":"","comment":""},"15":{"family_comment":"","value":"1250","family":"","comment":""},"16":{"family_comment":"","value":"","family":"","comment":"","value_hidden":false},"17":{"family_comment":"","value":"","family":"","comment":""},"18":{"family_comment":"","value":"","family":"","comment":""},"19":{"family_comment":"","value":"","family":"","comment":"","value_hidden":false},"20":{"value":"","family_comment":"","comment_unclear":false,"family_unclear":false,"family":"","comment":""}},"vehicle":{"35":[{"brand_info":"2461 куб. см.","sum_rent_comment":"","sum_rent_hidden":false,"year":"2007","sum_hidden":false,"brand_info_hidden":false,"brand_info_unclear":false,"sum_rent":"","sum":"","brand":"Volkswagen T2 (Transporter","sum_comment":"","sum_rent_comment_hidden":false}]},"id":"vulyk_12_69","banks":{"45":[{"sum_foreign_comment":"","sum":"","sum_comment":"","sum_hidden":false,"sum_foreign_units":"UAH","sum_foreign_hidden":false,"sum_units":"UAH","sum_comment_hidden":false,"sum_unclear":false,"sum_foreign":"","sum_units_hidden":false},{"sum_foreign_comment":"","sum_units":"","sum_comment":"","sum_foreign_units":"","sum":"","sum_foreign":""}],"46":[{"sum_foreign_comment":"","sum_units":"UAH","sum_comment":"","sum_hidden":false,"sum_foreign_units":"UAH","sum":"","sum_foreign_hidden":false,"sum_foreign":""}],"47":[{"sum_foreign_comment":"","sum_units":"UAH","sum_comment":"","sum_comment_unclear":false,"sum_foreign_units":"UAH","sum":"","sum_foreign":""},{"sum_foreign_comment":"","sum_units":"","sum_comment":"","sum_foreign_units":"","sum":"","sum_foreign":""}],"48":[{"sum_foreign_comment":"","sum_units":"UAH","sum_comment":"","sum_foreign_units":"UAH","sum":"","sum_foreign":""}],"49":[{"sum_foreign_comment":"","sum_units":"UAH","sum_comment":"","sum_foreign_units":"UAH","sum":"","sum_foreign":""}],"50":[{"sum_foreign_comment":"","sum_units":"UAH","sum_comment":"","sum_foreign_units":"UAH","sum":"","sum_foreign":""}],"51":[{"sum_foreign_comment":"","sum_units":"UAH","sum_comment":"","sum_hidden":false,"sum_foreign_units":"UAH","sum_comment_hidden":false,"sum_units_hidden":false,"sum":"","sum_foreign":""}],"52":[{"sum_foreign_comment":"","sum_units":"UAH","sum_comment":"","sum_comment_unclear":false,"sum_foreign_units":"UAH","sum":"","sum_foreign":""},{"sum_foreign_comment":"","sum_units":"","sum_comment":"","sum_foreign_units":"","sum":"","sum_foreign":""},{"sum_foreign_comment":"","sum_units":"","sum_comment":"","sum_foreign_units":"","sum":"","sum_foreign":""},{"sum_foreign_comment":"","sum_units":"","sum_comment":"","sum_foreign_units":"","sum":"","sum_foreign":""}],"53":[{"sum_foreign_comment":"","sum_units":"UAH","sum_comment":"","sum_foreign_units":"UAH","sum":"","sum_foreign":""}]},"declaration":{"additional_info_text":"","notfull_lostpages":"","date":"2015-03-25T00:00:00","notfull":"","additional_info":"","url":"http://static.declarations.com.ua/declarations/chosen_ones/mega_batch/fedorishchev_serhii_serhiiovych.pdf"},"liabilities":{"54":{"sum_foreign_comment":"","sum":"","sum_comment":"","sum_hidden":false,"sum_comment_hidden":false,"sum_foreign":""},"55":{"sum_foreign_comment":"","sum":"","sum_comment":"","sum_foreign":""},"56":{"sum_foreign_comment":"","sum":"","sum_comment":"","sum_foreign":""},"57":{"sum_foreign_comment":"","sum":"","sum_comment":"","sum_comment_unclear":false,"sum_hidden":false,"sum_comment_hidden":false,"sum_unclear":false,"sum_foreign":""},"58":{"sum_foreign_comment":"","sum":"","sum_comment":"","sum_comment_unclear":false,"sum_hidden":false,"sum_foreign":""},"59":{"sum_foreign_comment":"","sum":"","sum_hidden":false,"sum_comment":"","sum_foreign":""},"60":{"sum_foreign_comment":"","sum":"","sum_comment":"","sum_hidden":false,"sum_comment_hidden":false,"sum_foreign":""},"61":{"sum_foreign_comment":"","sum":"","sum_comment":"","sum_foreign":""},"62":{"sum_foreign_comment":"","sum":"","sum_comment":"","sum_comment_unclear":false,"sum_unclear":false,"sum_foreign":""},"63":{"sum_foreign_comment":"","sum":"","sum_comment":"","sum_comment_unclear":false,"sum_foreign":""},"64":{"sum_foreign_comment":"","sum":"","sum_comment":"","sum_comment_unclear":false,"sum_foreign":""}},"ft_src":"суддя жовтневого районного суду м. дніпропетровська\nДніпропетровська область\nЗагальний місцевий суд\nСергій\nФедоріщева К. А\nПодружжя\nФедоріщева Д. С\nДитина\nСергійович\nФедоріщев\nФедоріщев Сергій Сергійович\nФедоріщев Сергій Сергійович\nСергій Сергійович Федоріщев\nСергій Федоріщев\nФедоріщев Сергій Сергійович\n2461 куб. см.\nVolkswagen T2 (Transporter\n2007\n2014\n2461 куб. см.\nVolkswagen T2 (Transporter\n2007\n454\nДніпропетровська область\n12\nДніпропетровська область\nм. Дніпропетровськ\n41\nДніпропетровська область\nЗагальний місцевий суд\nсуддя жовтневого районного суду м. дніпропетровська\nДніпропетровська область\nПодружжя\nФедоріщева К. А\nДитина\nФедоріщева Д. С\nФедоріщев Сергій Сергійович\nСергій Сергійович Федоріщев\nСергій Федоріщев\nФедоріщев Сергій Сергійович\nСергій\nФедоріщев Сергій Сергійович\nФедоріщев\nСергійович\n226059\n28192\n1250\n28338\n240058\n12180\n569\n146\n2014\nДніпропетровська область\n454\nДніпропетровська область\n41\nм. Дніпропетровськ\n12\nДніпропетровська область\nПодружжя\nФедоріщева К. А\nФедоріщева Д. С\nДитина\nСергійович\nФедоріщев\nСергій\nФедоріщев Сергій Сергійович\nСергій Сергійович Федоріщев\nСергій Федоріщев\nФедоріщев Сергій Сергійович\nДніпропетровська область\nЗагальний місцевий суд\nсуддя жовтневого районного суду м. дніпропетровська\nФедоріщев Сергій Сергійович\n28192\n226059\n1250\n12180\n28338\n240058\n146\n569\nVolkswagen T2 (Transporter\n2461 куб. см.\n2007\n1250\n12180\n240058\n28338\n146\n569\n226059\n28192\nм. Дніпропетровськ\nДніпропетровська область\n12\nДніпропетровська область\n454\nДніпропетровська область\n41\n2014","general":{"inn":"","name":"Сергій","patronymic_unclear":false,"last_name_hidden":false,"family":[{"inn":"","inn_hidden":true,"relations_unclear":false,"relations_hidden":false,"relations_other":"","relations":"Подружжя","name_hidden":false,"inn_unclear":false,"family_name":"Федоріщева К. А","name_unclear":false},{"inn":"","relations":"Дитина","inn_unclear":false,"family_name":"Федоріщева Д. С","inn_hidden":true,"relations_other":"","name_hidden":false,"name_unclear":false}],"patronymic":"Сергійович","inn_hidden":true,"family_raw":"","inn_unclear":false,"post":{"post_unclear":false,"post":"суддя жовтневого районного суду м. дніпропетровська","candidate":"","office_hidden":false,"region":"Дніпропетровська область","post_hidden":false,"office":"Загальний місцевий суд","office_unclear":false},"last_name_unclear":false,"full_name":"Федоріщев Сергій Сергійович","addresses":[{"place_district":"","place_city_hidden":false,"place_city":"","place_city_type_hidden":false,"place_district_hidden":false,"place_city_type":"","place_address_hidden":false,"place_address":"","place_hidden":true,"place":""}],"last_name":"Федоріщев","patronymic_hidden":false,"full_name_suggest":{"output":"Федоріщев Сергій Сергійович","input":["Федоріщев Сергій Сергійович","Сергій Сергійович Федоріщев","Сергій Федоріщев"]}},"source":"VULYK","estate":{"23":[{"space_unclear":false,"costs":"","costs_comment":"","address_hidden":false,"region_hidden":false,"space_comment":"","space_hidden":false,"space":"","address":"","costs_comment_unclear":false,"region":"","address_unclear":false,"costs_rent_comment":"","space_units":"м²","costs_rent":""},{"space_unclear":false,"costs":"","costs_comment":"","address_hidden":false,"region_hidden":false,"space_comment":"","space":"","address":"","region":"","costs_rent_comment":"","space_units":"","costs_rent":""},{"space_hidden":false,"costs":"","costs_comment":"","address_hidden":false,"region_hidden":false,"space_comment":"","space":"","address":"","region":"","costs_rent_comment":"","space_units":"","costs_rent":""},{"costs_rent":"","region":"","costs":"","costs_rent_comment":"","costs_comment":"","space_comment":"","space_units":"","space":"","address":""}],"25":[{"region_unclear":false,"space_hidden":false,"costs":"","costs_comment":"","costs_hidden":false,"address_hidden":false,"region_hidden":false,"space_comment":"","space_unclear":false,"space":"12","address":"м. Дніпропетровськ","region":"Дніпропетровська область","address_unclear":false,"costs_rent_comment":"","costs_rent_hidden":false,"space_comment_unclear":false,"space_units":"м²","costs_rent":""}],"29":[{"region_unclear":false,"space_unclear":false,"address_hidden":true,"region_hidden":false,"space_comment":"","space":"454","address":"","region":"Дніпропетровська область","costs_property":"","costs_rent_comment":"","space_comment_unclear":false,"address_unclear":false,"space_units":"м²","costs_property_comment":"","costs_rent":""}],"32":[{"space_unclear":false,"address_hidden":false,"region_hidden":false,"space_comment":"","space":"41","address":"","region":"Дніпропетровська область","costs_property":"","costs_rent_comment":"","space_units":"м²","costs_property_comment":"","costs_rent":""}]},"intro":{"declaration_year":"2014","isnotdeclaration":""}}],"declarationsLength":2,"analytics":[{"y":2015,"i":301220,"c":1,"k":16.4,"ka":1,"fi":24242,"fl":454,"fla":1,"j":1},{"y":2014,"i":240058,"c":1,"k":12,"ka":1,"la":4,"fi":28338,"fl":454,"fla":1}]}