{"2010":"","2016":"","Department":"Білгород-Дністровський міськрайонний суд Одеської області","Region":"Одеська область","Position":"Суддя Білгород-Дністровського міськрайонного суду Одеської області","Name":"Гайда-Герасименко Олена Дмитрівна","Link":"https://drive.google.com/open?id=0BygiyWAl79DMUHJuWlgtbXQyRDA","Note":"У меня","AdditionalNote":"","field8":"","field9":"","field10":"","Кількість справ":"","Оскаржені":"","Кількість скарг":6,"Кількість дисциплінарних стягнень":"","Клейма":"","Фото":"","Як живе":"","key":"gayda_gerasimenko_olena_dmitrivna","allDeclarations":[{"provider":"declarations.com.ua","document":{"income":{"5":{"family_comment":"","value":"180905","family":"3239","comment":""},"6":{"family_comment":"","value":"173705","family_hidden":false,"comment":"","family":"3239"},"7":{"family_comment":"","value":"","source_name":"","family":"","comment":""},"8":{"family_comment":"","value":"","family":"","comment":""},"9":{"value":"","value_unclear":false,"family_hidden":false,"family_comment":"","family":"","comment":""},"10":{"value":"","family_comment":"","family_hidden":false,"value_hidden":false,"family_unclear":false,"family":"","comment":""},"11":{"family_comment":"","value":"","family":"","comment":""},"12":{"family_comment":"","value":"","family":"","comment":""},"13":{"family_comment":"","value":"7200","family":"","comment":""},"14":{"family_comment":"","value":"","family":"","comment":""},"15":{"family_comment":"","value":"","family":"","comment":""},"16":{"family_comment":"","value":"","family":"","comment":""},"17":{"family_comment":"","value":"","family":"","comment":""},"18":{"family_comment":"","value":"","family":"","comment":""},"19":{"family_comment":"","value":"","family":"","comment":""},"20":{"value":"","comment_unclear":false,"family_comment":"","family":"","comment":"","family_comment_unclear":false}},"id":"vulyk_75_113","declaration":{"additional_info_text":"","notfull_lostpages":"","date":"2015-03-24T00:00:00","notfull":"","additional_info":"","url":"http://static.declarations.com.ua/declarations/chosen_ones/judges_batch/1822_haida-herasymenko_olena_dmytrivna.pdf"},"liabilities":{"54":{"sum_foreign_comment":"","sum":"","sum_comment":"","sum_foreign":""},"55":{"sum_foreign_comment":"","sum":"","sum_comment":"","sum_foreign":""},"56":{"sum_foreign_comment":"","sum":"","sum_comment":"","sum_foreign":""},"57":{"sum_foreign_comment":"","sum":"","sum_comment":"","sum_foreign":""},"58":{"sum_foreign_comment":"","sum":"","sum_comment":"","sum_foreign":""},"59":{"sum_foreign_comment":"","sum":"","sum_comment":"","sum_comment_unclear":false,"sum_unclear":false,"sum_foreign":""},"60":{"sum_foreign_comment":"","sum":"","sum_comment":"","sum_foreign":""},"61":{"sum_foreign_comment":"","sum":"","sum_comment":"","sum_foreign":""},"62":{"sum_foreign_comment":"","sum":"","sum_comment":"","sum_unclear":false,"sum_foreign":""},"63":{"sum_foreign_comment":"","sum":"","sum_comment":"","sum_foreign":""},"64":{"sum_foreign_comment":"","sum":"","sum_comment":"","sum_foreign":""}},"ft_src":"Гайда-Герасименко Олена Дмитрівна\nсуддя білгород-дністровського міськрайонного суду одеської області\nОдеська область\nЗагальний місцевий суд\nОлена\nГайда Анастасія Сергіївна\nДитина\nГерасименко Катерина Олександрівна\nДитина\nГайда-Герасименко Олена Дмитрівна\nОлена Дмитрівна Гайда-Герасименко\nОлена Гайда-Герасименко\nГайда-Герасименко Олена Дмитрівна\nГайда-Герасименко\nДмитрівна\n3239\n180905\n3239\n173705\n7200\n2014\n3239\n173705\n7200\n3239\n180905\n2014\nГайда-Герасименко\nДмитрівна\nДитина\nГайда Анастасія Сергіївна\nДитина\nГерасименко Катерина Олександрівна\nГайда-Герасименко Олена Дмитрівна\nОлена Дмитрівна Гайда-Герасименко\nОлена Гайда-Герасименко\nГайда-Герасименко Олена Дмитрівна\nОлена\nГайда-Герасименко Олена Дмитрівна\nЗагальний місцевий суд\nсуддя білгород-дністровського міськрайонного суду одеської області\nОдеська область\n173705\n3239\n7200\n180905\n3239\nГайда Анастасія Сергіївна\nДитина\nГерасименко Катерина Олександрівна\nДитина\nГайда-Герасименко\nДмитрівна\nсуддя білгород-дністровського міськрайонного суду одеської області\nОдеська область\nЗагальний місцевий суд\nГайда-Герасименко Олена Дмитрівна\nГайда-Герасименко Олена Дмитрівна\nОлена Дмитрівна Гайда-Герасименко\nОлена Гайда-Герасименко\nГайда-Герасименко Олена Дмитрівна\nОлена\n2014","general":{"inn":"","inn_hidden":true,"last_name":"Гайда-Герасименко","post":{"office":"Загальний місцевий суд","region":"Одеська область","post":"суддя білгород-дністровського міськрайонного суду одеської області"},"name":"Олена","full_name":"Гайда-Герасименко Олена Дмитрівна","family_raw":"","addresses":[{"place_district":"","place_address_hidden":false,"place_city":"","place_city_type_hidden":false,"place_district_hidden":false,"place_city_type":"","place_city_hidden":false,"place_address":"","place_hidden":true,"place":""}],"family":[{"inn":"","inn_hidden":false,"relations_hidden":false,"family_name":"Гайда Анастасія Сергіївна","relations_other":"","relations":"Дитина","name_hidden":false,"name_unclear":false},{"inn":"","relations":"Дитина","relations_other":"","inn_hidden":false,"family_name":"Герасименко Катерина Олександрівна","name_hidden":false,"name_unclear":false}],"full_name_suggest":{"output":"Гайда-Герасименко Олена Дмитрівна","input":["Гайда-Герасименко Олена Дмитрівна","Олена Дмитрівна Гайда-Герасименко","Олена Гайда-Герасименко"]},"patronymic":"Дмитрівна"},"source":"VULYK","intro":{"declaration_year":"2014","isnotdeclaration":""}}},{"provider":"public-api.nazk.gov.ua","document":{"step_0":{"declarationType":"1","declarationYear1":"2015"},"step_1":{"city":"[Конфіденційна інформація]","region":"[Конфіденційна інформація]","street":"[Конфіденційна інформація]","country":"1","cityPath":"[Конфіденційна інформація]","cityType":"[Конфіденційна інформація]","district":"[Конфіденційна інформація]","lastname":"Гайда-Герасименко","postCode":"[Конфіденційна інформація]","postType":"","workPost":"суддя","firstname":"Олена","workPlace":"Білгород-Дністровський міськрайонний суд Одеської області","middlename":"Дмитрівна","streetType":"[Конфіденційна інформація]","actual_city":"1.2.51.2.10.8.42.1.1","changedName":false,"countryPath":"","eng_postCode":"","postCategory":"","actual_region":"1.2.51","actual_street":"[Конфіденційна інформація]","actual_country":"1","actual_cityPath":"[Конфіденційна інформація]","actual_cityType":"[Конфіденційна інформація]","actual_district":"1.2.51.2.10","actual_postCode":"[Конфіденційна інформація]","actual_streetType":"[Конфіденційна інформація]","previous_lastname":"","corruptionAffected":"Ні","eng_actualPostCode":"[Конфіденційна інформація]","previous_firstname":"","previous_middlename":"","responsiblePosition":"Суддя суду загальної юрисдикції, суддя Конституційного Суду України","sameRegLivingAddress":"[Конфіденційна інформація]","postType_extendedstatus":"1","eng_sameRegLivingAddress":"[Конфіденційна інформація]","housePartNum_extendedstatus":"1","postCategory_extendedstatus":"1","apartmentsNum_extendedstatus":"1","actual_housePartNum_extendedstatus":"1","actual_apartmentsNum_extendedstatus":"1"},"step_2":{"1477471696099":{"lastname":"Гайда ","firstname":"Анастасія","middlename":"Сергіївна","changedName":false,"citizenship":"1","eng_lastname":"","eng_firstname":"","eng_middlename":"","isNotApplicable":"","subjectRelation":"дочка","previous_lastname":"","previous_firstname":"","previous_middlename":"","previous_eng_lastname":"","previous_eng_firstname":"","previous_eng_middlename":""},"1477471801209":{"lastname":"Герасименко","firstname":"Катерина","middlename":"Олександрівна","changedName":false,"citizenship":"1","eng_lastname":"","eng_firstname":"","eng_middlename":"","isNotApplicable":"","subjectRelation":"дочка","previous_lastname":"","previous_firstname":"","previous_middlename":"","previous_eng_lastname":"","previous_eng_firstname":"","previous_eng_middlename":""}},"step_3":[],"step_4":[],"step_5":[],"step_6":[],"step_7":[],"step_8":[],"step_9":[],"step_10":[],"step_11":{"1477485842888":{"person":"1","rights":[],"objectType":"Заробітна плата отримана за основним місцем роботи","sizeIncome":"16599","incomeSource":"j","source_citizen":"Юридична особа, зареєстрована в Україні","otherObjectType":"","source_ua_lastname":"","source_eng_fullname":"","source_ua_firstname":"","source_ukr_fullname":"","source_ua_middlename":"","source_ua_company_name":"Територіальне управління Державної судової адміністрації України в Одеській області","source_eng_company_name":"","source_ukr_company_name":"","source_ua_sameRegLivingAddress":""},"1477486025879":{"person":"1","rights":[],"objectType":"Інше","sizeIncome":"7200","incomeSource":"j","source_citizen":"Громадянин України","otherObjectType":"аліменти на утримання неповнолітньої дитини","source_ua_lastname":"Герасименко ","source_eng_fullname":"","source_ua_firstname":"Олександр","source_ukr_fullname":"","source_ua_middlename":"Сергійович","source_ua_company_name":"","source_eng_company_name":"","source_ukr_company_name":"","source_ua_sameRegLivingAddress":false,"source_ua_taxNumber_extendedstatus":"2"}},"step_12":[],"step_13":[],"step_14":[],"step_15":[],"step_16":[],"id":"1c9a62c5-0048-466d-aa8d-abb1533c450c"}}],"declarations":[{"income":{"5":{"family_comment":"","value":"180905","family":"3239","comment":""},"6":{"family_comment":"","value":"173705","family_hidden":false,"comment":"","family":"3239"},"7":{"family_comment":"","value":"","source_name":"","family":"","comment":""},"8":{"family_comment":"","value":"","family":"","comment":""},"9":{"value":"","value_unclear":false,"family_hidden":false,"family_comment":"","family":"","comment":""},"10":{"value":"","family_comment":"","family_hidden":false,"value_hidden":false,"family_unclear":false,"family":"","comment":""},"11":{"family_comment":"","value":"","family":"","comment":""},"12":{"family_comment":"","value":"","family":"","comment":""},"13":{"family_comment":"","value":"7200","family":"","comment":""},"14":{"family_comment":"","value":"","family":"","comment":""},"15":{"family_comment":"","value":"","family":"","comment":""},"16":{"family_comment":"","value":"","family":"","comment":""},"17":{"family_comment":"","value":"","family":"","comment":""},"18":{"family_comment":"","value":"","family":"","comment":""},"19":{"family_comment":"","value":"","family":"","comment":""},"20":{"value":"","comment_unclear":false,"family_comment":"","family":"","comment":"","family_comment_unclear":false}},"id":"vulyk_75_113","declaration":{"additional_info_text":"","notfull_lostpages":"","date":"2015-03-24T00:00:00","notfull":"","additional_info":"","url":"http://static.declarations.com.ua/declarations/chosen_ones/judges_batch/1822_haida-herasymenko_olena_dmytrivna.pdf"},"liabilities":{"54":{"sum_foreign_comment":"","sum":"","sum_comment":"","sum_foreign":""},"55":{"sum_foreign_comment":"","sum":"","sum_comment":"","sum_foreign":""},"56":{"sum_foreign_comment":"","sum":"","sum_comment":"","sum_foreign":""},"57":{"sum_foreign_comment":"","sum":"","sum_comment":"","sum_foreign":""},"58":{"sum_foreign_comment":"","sum":"","sum_comment":"","sum_foreign":""},"59":{"sum_foreign_comment":"","sum":"","sum_comment":"","sum_comment_unclear":false,"sum_unclear":false,"sum_foreign":""},"60":{"sum_foreign_comment":"","sum":"","sum_comment":"","sum_foreign":""},"61":{"sum_foreign_comment":"","sum":"","sum_comment":"","sum_foreign":""},"62":{"sum_foreign_comment":"","sum":"","sum_comment":"","sum_unclear":false,"sum_foreign":""},"63":{"sum_foreign_comment":"","sum":"","sum_comment":"","sum_foreign":""},"64":{"sum_foreign_comment":"","sum":"","sum_comment":"","sum_foreign":""}},"ft_src":"Гайда-Герасименко Олена Дмитрівна\nсуддя білгород-дністровського міськрайонного суду одеської області\nОдеська область\nЗагальний місцевий суд\nОлена\nГайда Анастасія Сергіївна\nДитина\nГерасименко Катерина Олександрівна\nДитина\nГайда-Герасименко Олена Дмитрівна\nОлена Дмитрівна Гайда-Герасименко\nОлена Гайда-Герасименко\nГайда-Герасименко Олена Дмитрівна\nГайда-Герасименко\nДмитрівна\n3239\n180905\n3239\n173705\n7200\n2014\n3239\n173705\n7200\n3239\n180905\n2014\nГайда-Герасименко\nДмитрівна\nДитина\nГайда Анастасія Сергіївна\nДитина\nГерасименко Катерина Олександрівна\nГайда-Герасименко Олена Дмитрівна\nОлена Дмитрівна Гайда-Герасименко\nОлена Гайда-Герасименко\nГайда-Герасименко Олена Дмитрівна\nОлена\nГайда-Герасименко Олена Дмитрівна\nЗагальний місцевий суд\nсуддя білгород-дністровського міськрайонного суду одеської області\nОдеська область\n173705\n3239\n7200\n180905\n3239\nГайда Анастасія Сергіївна\nДитина\nГерасименко Катерина Олександрівна\nДитина\nГайда-Герасименко\nДмитрівна\nсуддя білгород-дністровського міськрайонного суду одеської області\nОдеська область\nЗагальний місцевий суд\nГайда-Герасименко Олена Дмитрівна\nГайда-Герасименко Олена Дмитрівна\nОлена Дмитрівна Гайда-Герасименко\nОлена Гайда-Герасименко\nГайда-Герасименко Олена Дмитрівна\nОлена\n2014","general":{"inn":"","inn_hidden":true,"last_name":"Гайда-Герасименко","post":{"office":"Загальний місцевий суд","region":"Одеська область","post":"суддя білгород-дністровського міськрайонного суду одеської області"},"name":"Олена","full_name":"Гайда-Герасименко Олена Дмитрівна","family_raw":"","addresses":[{"place_district":"","place_address_hidden":false,"place_city":"","place_city_type_hidden":false,"place_district_hidden":false,"place_city_type":"","place_city_hidden":false,"place_address":"","place_hidden":true,"place":""}],"family":[{"inn":"","inn_hidden":false,"relations_hidden":false,"family_name":"Гайда Анастасія Сергіївна","relations_other":"","relations":"Дитина","name_hidden":false,"name_unclear":false},{"inn":"","relations":"Дитина","relations_other":"","inn_hidden":false,"family_name":"Герасименко Катерина Олександрівна","name_hidden":false,"name_unclear":false}],"full_name_suggest":{"output":"Гайда-Герасименко Олена Дмитрівна","input":["Гайда-Герасименко Олена Дмитрівна","Олена Дмитрівна Гайда-Герасименко","Олена Гайда-Герасименко"]},"patronymic":"Дмитрівна"},"source":"VULYK","intro":{"declaration_year":"2014","isnotdeclaration":""}}],"declarationsLength":1,"analytics":[{"y":2014,"i":180905,"fi":3239},{"y":2015,"i":23799,"j":6}]}