{"2010":"","2016":"","Department":"Верховний Суд України","Region":"Загальнодержавний","Position":"Суддя Верховного Суду України - виведений з персонального складу судової палати в частині здійснення судочинства","Name":"Гусак Микола Борисович","Link":"","Note":"","AdditionalNote":"","декларації 2015":"","Youtube":"","field10":"","Кількість справ":"","Оскаржені":"","Кількість скарг":"","Кількість дисциплінарних стягнень":"","Клейма":3,"Фото":"http://i.piccy.info/i9/56902efe613e365b5bc55d7cbbffdffa/1473770953/26268/1069643/Gusak_Mykola_Borysovych.jpg","Як живе":"","key":"gusak_mikola_borisovich","allDeclarations":[{"provider":"declarations.com.ua","document":{"income":{"5":{"value":"315931","value_unclear":false,"family_hidden":false,"family_comment":"","family":"21015","comment":""},"6":{"family_comment":"","value":"284139","family":"21015","comment":""},"7":{"family_comment":"","value":"367","source_name":"НШСУ","family":"","comment":""},"8":{"family_comment":"","value":"","family":"","comment":""},"9":{"family_comment":"","value":"","family":"","comment":""},"10":{"family_comment":"","value":"","family":"","comment":""},"11":{"family_comment":"","value":"","family_hidden":false,"comment":"","family":""},"12":{"family_comment":"","value":"","family":"","comment":""},"13":{"family_comment":"","value":"","family":"","comment":""},"14":{"family_comment":"","value":"","family":"","comment":""},"15":{"family_comment":"","value":"31425","family":"","comment":""},"16":{"family_comment":"","value":"","family":"","comment":""},"17":{"family_comment":"","value":"","family":"","comment":"","family_comment_unclear":false},"18":{"family_comment":"","value":"","family":"","comment":""},"19":{"family_comment":"","value":"","family":"","comment":""},"20":{"value":"","family_unclear":false,"family_hidden":false,"family_comment":"","family":"","comment":""}},"vehicle":{"35":[{"brand_info":"1997 куб. см.","sum":"","brand":"Nissan X-Trail","sum_comment":"","brand_unclear":false,"year":"2012","brand_hidden":false,"brand_info_hidden":false,"brand_info_unclear":false,"sum_rent_comment":"","sum_rent":""}]},"id":"vulyk_103_118","declaration":{"date":"2016-03-30T00:00:00","additional_info_text":"","additional_info":"","url":"http://static.declarations.com.ua/declarations/chosen_ones/judges_batch/1073_husak_mykola_borysovych.pdf"},"liabilities":{"54":{"sum_foreign_comment":"","sum_foreign_hidden":false,"sum_comment":"","sum_foreign_comment_hidden":false,"sum_hidden":false,"sum_foreign_comment_unclear":false,"sum_comment_hidden":false,"sum_unclear":false,"sum":"","sum_foreign":""},"55":{"sum_foreign_comment":"","sum":"","sum_comment":"","sum_foreign":""},"56":{"sum_foreign_comment":"","sum":"","sum_comment":"","sum_foreign":""},"57":{"sum_foreign_comment":"","sum_foreign_hidden":false,"sum_comment":"","sum_foreign_comment_hidden":false,"sum_hidden":false,"sum_comment_hidden":false,"sum":"","sum_foreign":""},"58":{"sum_foreign_comment":"","sum_foreign_hidden":false,"sum_comment":"","sum_foreign_comment_hidden":false,"sum_hidden":false,"sum_comment_hidden":false,"sum":"","sum_foreign":""},"59":{"sum_foreign_comment":"","sum_foreign_hidden":false,"sum_comment":"","sum_foreign_comment_hidden":false,"sum_hidden":false,"sum_comment_hidden":false,"sum":"","sum_foreign":""},"60":{"sum_foreign_comment":"","sum":"","sum_comment":"","sum_hidden":false,"sum_comment_hidden":false,"sum_foreign":""},"61":{"sum_foreign_comment":"","sum":"","sum_comment":"","sum_foreign":""},"62":{"sum_foreign_comment":"","sum_comment_hidden":false,"sum":"","sum_comment":"","sum_foreign":""},"63":{"sum_foreign_comment":"","sum":"","sum_comment":"","sum_foreign":""},"64":{"sum_foreign_comment":"","sum":"","sum_comment":"","sum_foreign":""}},"ft_src":"Гусак Микола Борисович\nчлен врю\nЗагальнодержавний регіон\nВерховний суд\nМикола\nГусак С. В\nПодружжя\nГусак Микола Борисович\nМикола Борисович Гусак\nМикола Гусак\nГусак Микола Борисович\nГусак\nБорисович\nNissan X-Trail\n1997 куб. см.\n2012\n1700\n40.5\n90\n2015\n21015\n284139\n31425\n367\nНШСУ\n21015\n315931\n1997 куб. см.\n2012\nNissan X-Trail\n1700\n40.5\n90\nГусак\nГусак Микола Борисович\nМикола Борисович Гусак\nМикола Гусак\nГусак Микола Борисович\nГусак Микола Борисович\nБорисович\nПодружжя\nГусак С. В\nМикола\nВерховний суд\nчлен врю\nЗагальнодержавний регіон\nНШСУ\n367\n284139\n21015\n31425\n315931\n21015\n2015\nПодружжя\nГусак С. В\nГусак\nБорисович\nчлен врю\nВерховний суд\nЗагальнодержавний регіон\nГусак Микола Борисович\nГусак Микола Борисович\nМикола Борисович Гусак\nМикола Гусак\nГусак Микола Борисович\nМикола\nNissan X-Trail\n1997 куб. см.\n2012\n31425\n315931\n21015\nНШСУ\n367\n21015\n284139\n90\n1700\n40.5\n2015","general":{"inn":"","inn_hidden":true,"last_name":"Гусак","post":{"region":"Загальнодержавний регіон","region_unclear":false,"post":"член врю","office_unclear":false,"office":"Верховний суд"},"name":"Микола","full_name":"Гусак Микола Борисович","family_raw":"","addresses":[{"place_district":"","place_city_hidden":true,"place_city":"","place_city_type_hidden":false,"place_district_hidden":false,"place_city_type":"","place_address_hidden":true,"place_address":"","place_hidden":true,"place":""}],"family":[{"inn":"","relations":"Подружжя","relations_hidden":false,"inn_hidden":true,"relations_other":"","name_hidden":true,"family_name":"Гусак С. В","name_unclear":false}],"full_name_suggest":{"output":"Гусак Микола Борисович","input":["Гусак Микола Борисович","Микола Борисович Гусак","Микола Гусак"]},"patronymic":"Борисович"},"source":"VULYK","estate":{"23":[{"costs_rent":"","region":"","costs":"","costs_rent_comment":"","costs_comment":"","address_hidden":false,"region_hidden":true,"space_comment":"","space_units":"м²","space":"1700","address":""}],"25":[{"costs":"","costs_comment":"","address_hidden":false,"region_hidden":true,"space_comment":"","space":"90","address":"","region":"","costs_rent_comment":"","space_comment_unclear":false,"space_comment_hidden":false,"space_units":"м²","costs_rent":""}],"27":[{"costs_rent":"","region":"","costs":"","costs_rent_comment":"","costs_comment":"","address_hidden":false,"region_hidden":true,"space_comment":"","space_units":"м²","space":"40.5","address":""}]},"intro":{"declaration_year":"2015"}}},{"provider":"declarations.com.ua","document":{"income":{"5":{"family_comment":"","value":"396643","value_unclear":false,"family":"21905","comment":""},"6":{"family_comment":"","value":"380643","value_unclear":false,"family":"21905","comment":""},"7":{"source_name_unclear":false,"value":"1089","family_hidden":false,"value_hidden":false,"family_comment":"","source_name":"ТОВ 'ДК 'Управління знаннями', Національна школа суддів України","family":"","comment":"","source_name_hidden":false},"8":{"value":"","family_hidden":false,"value_hidden":false,"family_comment":"","family":"","comment":""},"9":{"value":"","value_unclear":false,"value_hidden":false,"family_comment":"","comment_unclear":false,"comment":"","family":""},"10":{"value":"14911","family_hidden":false,"value_hidden":false,"family_comment":"","family":"","comment":""},"11":{"value":"","family_hidden":false,"value_hidden":false,"family_comment":"","family":"","comment":""},"12":{"value":"","family_hidden":false,"value_hidden":false,"family_comment":"","family":"","comment":""},"13":{"value":"","family_hidden":false,"value_hidden":false,"family_comment":"","family":"","comment":""},"14":{"value":"","family_hidden":false,"value_hidden":false,"family_comment":"","family":"","comment":""},"15":{"value":"","family_hidden":false,"value_hidden":false,"family_comment":"","family":"","comment":""},"16":{"value":"","family_hidden":false,"value_hidden":false,"family_comment":"","family":"","comment":""},"17":{"value":"","family_hidden":false,"value_hidden":false,"family_comment":"","family":"","comment":""},"18":{"value":"","comment_unclear":false,"family_hidden":false,"value_hidden":false,"family_comment":"","family":"","comment":""},"19":{"value":"","family_hidden":false,"value_hidden":false,"family_comment":"","family":"","comment":""},"20":{"value":"","value_unclear":false,"family_hidden":false,"value_hidden":false,"family_comment":"","comment_unclear":false,"comment":"","family":""}},"id":"193","declaration":{"additional_info_text":"","notfull_lostpages":"","date":"2014-03-31T00:00:00","notfull":"","additional_info":"","url":"http://static.declarations.com.ua/declarations/chosen_ones/judges_batch/20_husak_mykola_borysovych.pdf"},"liabilities":{"54":{"sum_foreign_comment":"","sum_foreign_hidden":false,"sum_comment":"","sum_hidden":false,"sum_foreign_comment_unclear":false,"sum_comment_hidden":false,"sum":"","sum_foreign":""},"55":{"sum_foreign_comment":"","sum":"","sum_hidden":false,"sum_comment":"","sum_foreign":""},"56":{"sum_foreign_comment":"","sum":"9800","sum_comment":"","sum_foreign":""},"57":{"sum_foreign_comment":"","sum_foreign_hidden":false,"sum_comment":"","sum_hidden":false,"sum_comment_hidden":false,"sum":"","sum_foreign":""},"58":{"sum_foreign_comment":"","sum":"","sum_comment":"","sum_hidden":false,"sum_comment_hidden":false,"sum_foreign":""},"59":{"sum_foreign_comment":"","sum_foreign_hidden":false,"sum_comment":"","sum_hidden":false,"sum":"","sum_foreign":""},"60":{"sum_foreign_comment":"","sum":"","sum_comment":"","sum_comment_unclear":false,"sum_hidden":false,"sum_comment_hidden":false,"sum_foreign":""},"61":{"sum_foreign_comment":"","sum":"","sum_hidden":false,"sum_comment":"","sum_foreign":""},"62":{"sum_foreign_comment":"","sum_foreign_hidden":false,"sum_comment":"","sum_comment_hidden":false,"sum_unclear":false,"sum":"3100","sum_foreign":""},"63":{"sum_foreign_comment":"","sum_foreign_hidden":false,"sum_comment":"","sum_hidden":false,"sum_comment_hidden":false,"sum":"","sum_foreign":""},"64":{"sum_foreign_comment":"","sum":"","sum_comment":"","sum_hidden":false,"sum_comment_hidden":false,"sum_foreign":""}},"ft_src":"3100\n9800\nсуддя верховного суду україни\nЗагальнодержавний регіон\nВерховний суд\nМикола\nГусак С. В\nПодружжя\nБорисович\nГусак Микола Борисович\nМикола Борисович Гусак\nМикола Гусак\nГусак Микола Борисович\nГусак Микола Борисович\nГусак\n14911\n21905\n396643\n1089\nТОВ 'ДК 'Управління знаннями', Національна школа суддів України\n21905\n380643\nприватизована\n1700\n42\nприватизована\n90\n2013\n21905\n380643\n14911\nТОВ 'ДК 'Управління знаннями', Національна школа суддів України\n1089\n21905\n396643\n1089\nТОВ 'ДК 'Управління знаннями', Національна школа суддів України\n380643\n21905\n396643\n21905\n14911\nГусак Микола Борисович\nМикола Борисович Гусак\nМикола Гусак\nГусак Микола Борисович\nГусак Микола Борисович\nПодружжя\nГусак С. В\nМикола\nБорисович\nсуддя верховного суду україни\nВерховний суд\nЗагальнодержавний регіон\nГусак\n9800\n3100\n1700\nприватизована\n42\n90\nприватизована\n2013\n9800\n3100\nПодружжя\nГусак С. В\nБорисович\nГусак\nМикола\nГусак Микола Борисович\nМикола Борисович Гусак\nМикола Гусак\nГусак Микола Борисович\nЗагальнодержавний регіон\nВерховний суд\nсуддя верховного суду україни\nГусак Микола Борисович\nприватизована\n90\n1700\nприватизована\n42\n2013","general":{"inn":"","name":"Микола","inn_unclear":false,"family":[{"inn":"","relations":"Подружжя","inn_unclear":false,"relations_hidden":false,"inn_hidden":false,"relations_other":"","name_hidden":false,"family_name":"Гусак С. В","name_unclear":false}],"inn_hidden":false,"family_raw":"","last_name":"Гусак","post":{"post":"суддя верховного суду україни","region":"Загальнодержавний регіон","candidate":"","office_hidden":false,"post_hidden":false,"office":"Верховний суд","region_hidden":false},"full_name_suggest":{"output":"Гусак Микола Борисович","input":["Гусак Микола Борисович","Микола Борисович Гусак","Микола Гусак"]},"full_name":"Гусак Микола Борисович","patronymic":"Борисович","last_name_unclear":false,"name_unclear":false},"source":"VULYK","estate":{"23":[{"region_unclear":false,"space_unclear":false,"costs":"","costs_comment":"приватизована","costs_hidden":false,"address_hidden":false,"region_hidden":false,"space_comment":"","space_hidden":false,"space_units_unclear":false,"address":"","costs_comment_unclear":false,"region":"","address_unclear":false,"space":"1700","costs_rent_hidden":false,"costs_rent_comment_hidden":false,"space_units":"м²","costs_comment_hidden":false,"costs_rent":"","costs_rent_comment":""}],"25":[{"region_unclear":false,"space_unclear":false,"costs":"","costs_comment":"приватизована","costs_hidden":false,"address_hidden":false,"region_hidden":false,"space_comment":"","space":"90","address":"","costs_rent_comment_unclear":false,"region":"","costs_rent_comment":"","costs_rent_hidden":false,"space_comment_unclear":false,"costs_rent_comment_hidden":false,"space_units":"м²","costs_comment_hidden":false,"costs_rent":"","costs_unclear":false}],"27":[{"space_hidden":false,"costs":"","costs_comment":"","costs_hidden":false,"address_hidden":false,"region_hidden":false,"space_comment":"","space_unclear":false,"space":"42","address":"","region":"","costs_rent_comment":"","costs_rent_hidden":false,"costs_rent_comment_hidden":false,"space_units":"м²","costs_comment_hidden":false,"costs_rent":""}]},"intro":{"declaration_year":"2013","isnotdeclaration":"","declaration_year_unclear":false,"declaration_year_hidden":false}}}],"declarations":[{"income":{"5":{"value":"315931","value_unclear":false,"family_hidden":false,"family_comment":"","family":"21015","comment":""},"6":{"family_comment":"","value":"284139","family":"21015","comment":""},"7":{"family_comment":"","value":"367","source_name":"НШСУ","family":"","comment":""},"8":{"family_comment":"","value":"","family":"","comment":""},"9":{"family_comment":"","value":"","family":"","comment":""},"10":{"family_comment":"","value":"","family":"","comment":""},"11":{"family_comment":"","value":"","family_hidden":false,"comment":"","family":""},"12":{"family_comment":"","value":"","family":"","comment":""},"13":{"family_comment":"","value":"","family":"","comment":""},"14":{"family_comment":"","value":"","family":"","comment":""},"15":{"family_comment":"","value":"31425","family":"","comment":""},"16":{"family_comment":"","value":"","family":"","comment":""},"17":{"family_comment":"","value":"","family":"","comment":"","family_comment_unclear":false},"18":{"family_comment":"","value":"","family":"","comment":""},"19":{"family_comment":"","value":"","family":"","comment":""},"20":{"value":"","family_unclear":false,"family_hidden":false,"family_comment":"","family":"","comment":""}},"vehicle":{"35":[{"brand_info":"1997 куб. см.","sum":"","brand":"Nissan X-Trail","sum_comment":"","brand_unclear":false,"year":"2012","brand_hidden":false,"brand_info_hidden":false,"brand_info_unclear":false,"sum_rent_comment":"","sum_rent":""}]},"id":"vulyk_103_118","declaration":{"date":"2016-03-30T00:00:00","additional_info_text":"","additional_info":"","url":"http://static.declarations.com.ua/declarations/chosen_ones/judges_batch/1073_husak_mykola_borysovych.pdf"},"liabilities":{"54":{"sum_foreign_comment":"","sum_foreign_hidden":false,"sum_comment":"","sum_foreign_comment_hidden":false,"sum_hidden":false,"sum_foreign_comment_unclear":false,"sum_comment_hidden":false,"sum_unclear":false,"sum":"","sum_foreign":""},"55":{"sum_foreign_comment":"","sum":"","sum_comment":"","sum_foreign":""},"56":{"sum_foreign_comment":"","sum":"","sum_comment":"","sum_foreign":""},"57":{"sum_foreign_comment":"","sum_foreign_hidden":false,"sum_comment":"","sum_foreign_comment_hidden":false,"sum_hidden":false,"sum_comment_hidden":false,"sum":"","sum_foreign":""},"58":{"sum_foreign_comment":"","sum_foreign_hidden":false,"sum_comment":"","sum_foreign_comment_hidden":false,"sum_hidden":false,"sum_comment_hidden":false,"sum":"","sum_foreign":""},"59":{"sum_foreign_comment":"","sum_foreign_hidden":false,"sum_comment":"","sum_foreign_comment_hidden":false,"sum_hidden":false,"sum_comment_hidden":false,"sum":"","sum_foreign":""},"60":{"sum_foreign_comment":"","sum":"","sum_comment":"","sum_hidden":false,"sum_comment_hidden":false,"sum_foreign":""},"61":{"sum_foreign_comment":"","sum":"","sum_comment":"","sum_foreign":""},"62":{"sum_foreign_comment":"","sum_comment_hidden":false,"sum":"","sum_comment":"","sum_foreign":""},"63":{"sum_foreign_comment":"","sum":"","sum_comment":"","sum_foreign":""},"64":{"sum_foreign_comment":"","sum":"","sum_comment":"","sum_foreign":""}},"ft_src":"Гусак Микола Борисович\nчлен врю\nЗагальнодержавний регіон\nВерховний суд\nМикола\nГусак С. В\nПодружжя\nГусак Микола Борисович\nМикола Борисович Гусак\nМикола Гусак\nГусак Микола Борисович\nГусак\nБорисович\nNissan X-Trail\n1997 куб. см.\n2012\n1700\n40.5\n90\n2015\n21015\n284139\n31425\n367\nНШСУ\n21015\n315931\n1997 куб. см.\n2012\nNissan X-Trail\n1700\n40.5\n90\nГусак\nГусак Микола Борисович\nМикола Борисович Гусак\nМикола Гусак\nГусак Микола Борисович\nГусак Микола Борисович\nБорисович\nПодружжя\nГусак С. В\nМикола\nВерховний суд\nчлен врю\nЗагальнодержавний регіон\nНШСУ\n367\n284139\n21015\n31425\n315931\n21015\n2015\nПодружжя\nГусак С. В\nГусак\nБорисович\nчлен врю\nВерховний суд\nЗагальнодержавний регіон\nГусак Микола Борисович\nГусак Микола Борисович\nМикола Борисович Гусак\nМикола Гусак\nГусак Микола Борисович\nМикола\nNissan X-Trail\n1997 куб. см.\n2012\n31425\n315931\n21015\nНШСУ\n367\n21015\n284139\n90\n1700\n40.5\n2015","general":{"inn":"","inn_hidden":true,"last_name":"Гусак","post":{"region":"Загальнодержавний регіон","region_unclear":false,"post":"член врю","office_unclear":false,"office":"Верховний суд"},"name":"Микола","full_name":"Гусак Микола Борисович","family_raw":"","addresses":[{"place_district":"","place_city_hidden":true,"place_city":"","place_city_type_hidden":false,"place_district_hidden":false,"place_city_type":"","place_address_hidden":true,"place_address":"","place_hidden":true,"place":""}],"family":[{"inn":"","relations":"Подружжя","relations_hidden":false,"inn_hidden":true,"relations_other":"","name_hidden":true,"family_name":"Гусак С. В","name_unclear":false}],"full_name_suggest":{"output":"Гусак Микола Борисович","input":["Гусак Микола Борисович","Микола Борисович Гусак","Микола Гусак"]},"patronymic":"Борисович"},"source":"VULYK","estate":{"23":[{"costs_rent":"","region":"","costs":"","costs_rent_comment":"","costs_comment":"","address_hidden":false,"region_hidden":true,"space_comment":"","space_units":"м²","space":"1700","address":""}],"25":[{"costs":"","costs_comment":"","address_hidden":false,"region_hidden":true,"space_comment":"","space":"90","address":"","region":"","costs_rent_comment":"","space_comment_unclear":false,"space_comment_hidden":false,"space_units":"м²","costs_rent":""}],"27":[{"costs_rent":"","region":"","costs":"","costs_rent_comment":"","costs_comment":"","address_hidden":false,"region_hidden":true,"space_comment":"","space_units":"м²","space":"40.5","address":""}]},"intro":{"declaration_year":"2015"}},{"income":{"5":{"family_comment":"","value":"396643","value_unclear":false,"family":"21905","comment":""},"6":{"family_comment":"","value":"380643","value_unclear":false,"family":"21905","comment":""},"7":{"source_name_unclear":false,"value":"1089","family_hidden":false,"value_hidden":false,"family_comment":"","source_name":"ТОВ 'ДК 'Управління знаннями', Національна школа суддів України","family":"","comment":"","source_name_hidden":false},"8":{"value":"","family_hidden":false,"value_hidden":false,"family_comment":"","family":"","comment":""},"9":{"value":"","value_unclear":false,"value_hidden":false,"family_comment":"","comment_unclear":false,"comment":"","family":""},"10":{"value":"14911","family_hidden":false,"value_hidden":false,"family_comment":"","family":"","comment":""},"11":{"value":"","family_hidden":false,"value_hidden":false,"family_comment":"","family":"","comment":""},"12":{"value":"","family_hidden":false,"value_hidden":false,"family_comment":"","family":"","comment":""},"13":{"value":"","family_hidden":false,"value_hidden":false,"family_comment":"","family":"","comment":""},"14":{"value":"","family_hidden":false,"value_hidden":false,"family_comment":"","family":"","comment":""},"15":{"value":"","family_hidden":false,"value_hidden":false,"family_comment":"","family":"","comment":""},"16":{"value":"","family_hidden":false,"value_hidden":false,"family_comment":"","family":"","comment":""},"17":{"value":"","family_hidden":false,"value_hidden":false,"family_comment":"","family":"","comment":""},"18":{"value":"","comment_unclear":false,"family_hidden":false,"value_hidden":false,"family_comment":"","family":"","comment":""},"19":{"value":"","family_hidden":false,"value_hidden":false,"family_comment":"","family":"","comment":""},"20":{"value":"","value_unclear":false,"family_hidden":false,"value_hidden":false,"family_comment":"","comment_unclear":false,"comment":"","family":""}},"id":"193","declaration":{"additional_info_text":"","notfull_lostpages":"","date":"2014-03-31T00:00:00","notfull":"","additional_info":"","url":"http://static.declarations.com.ua/declarations/chosen_ones/judges_batch/20_husak_mykola_borysovych.pdf"},"liabilities":{"54":{"sum_foreign_comment":"","sum_foreign_hidden":false,"sum_comment":"","sum_hidden":false,"sum_foreign_comment_unclear":false,"sum_comment_hidden":false,"sum":"","sum_foreign":""},"55":{"sum_foreign_comment":"","sum":"","sum_hidden":false,"sum_comment":"","sum_foreign":""},"56":{"sum_foreign_comment":"","sum":"9800","sum_comment":"","sum_foreign":""},"57":{"sum_foreign_comment":"","sum_foreign_hidden":false,"sum_comment":"","sum_hidden":false,"sum_comment_hidden":false,"sum":"","sum_foreign":""},"58":{"sum_foreign_comment":"","sum":"","sum_comment":"","sum_hidden":false,"sum_comment_hidden":false,"sum_foreign":""},"59":{"sum_foreign_comment":"","sum_foreign_hidden":false,"sum_comment":"","sum_hidden":false,"sum":"","sum_foreign":""},"60":{"sum_foreign_comment":"","sum":"","sum_comment":"","sum_comment_unclear":false,"sum_hidden":false,"sum_comment_hidden":false,"sum_foreign":""},"61":{"sum_foreign_comment":"","sum":"","sum_hidden":false,"sum_comment":"","sum_foreign":""},"62":{"sum_foreign_comment":"","sum_foreign_hidden":false,"sum_comment":"","sum_comment_hidden":false,"sum_unclear":false,"sum":"3100","sum_foreign":""},"63":{"sum_foreign_comment":"","sum_foreign_hidden":false,"sum_comment":"","sum_hidden":false,"sum_comment_hidden":false,"sum":"","sum_foreign":""},"64":{"sum_foreign_comment":"","sum":"","sum_comment":"","sum_hidden":false,"sum_comment_hidden":false,"sum_foreign":""}},"ft_src":"3100\n9800\nсуддя верховного суду україни\nЗагальнодержавний регіон\nВерховний суд\nМикола\nГусак С. В\nПодружжя\nБорисович\nГусак Микола Борисович\nМикола Борисович Гусак\nМикола Гусак\nГусак Микола Борисович\nГусак Микола Борисович\nГусак\n14911\n21905\n396643\n1089\nТОВ 'ДК 'Управління знаннями', Національна школа суддів України\n21905\n380643\nприватизована\n1700\n42\nприватизована\n90\n2013\n21905\n380643\n14911\nТОВ 'ДК 'Управління знаннями', Національна школа суддів України\n1089\n21905\n396643\n1089\nТОВ 'ДК 'Управління знаннями', Національна школа суддів України\n380643\n21905\n396643\n21905\n14911\nГусак Микола Борисович\nМикола Борисович Гусак\nМикола Гусак\nГусак Микола Борисович\nГусак Микола Борисович\nПодружжя\nГусак С. В\nМикола\nБорисович\nсуддя верховного суду україни\nВерховний суд\nЗагальнодержавний регіон\nГусак\n9800\n3100\n1700\nприватизована\n42\n90\nприватизована\n2013\n9800\n3100\nПодружжя\nГусак С. В\nБорисович\nГусак\nМикола\nГусак Микола Борисович\nМикола Борисович Гусак\nМикола Гусак\nГусак Микола Борисович\nЗагальнодержавний регіон\nВерховний суд\nсуддя верховного суду україни\nГусак Микола Борисович\nприватизована\n90\n1700\nприватизована\n42\n2013","general":{"inn":"","name":"Микола","inn_unclear":false,"family":[{"inn":"","relations":"Подружжя","inn_unclear":false,"relations_hidden":false,"inn_hidden":false,"relations_other":"","name_hidden":false,"family_name":"Гусак С. В","name_unclear":false}],"inn_hidden":false,"family_raw":"","last_name":"Гусак","post":{"post":"суддя верховного суду україни","region":"Загальнодержавний регіон","candidate":"","office_hidden":false,"post_hidden":false,"office":"Верховний суд","region_hidden":false},"full_name_suggest":{"output":"Гусак Микола Борисович","input":["Гусак Микола Борисович","Микола Борисович Гусак","Микола Гусак"]},"full_name":"Гусак Микола Борисович","patronymic":"Борисович","last_name_unclear":false,"name_unclear":false},"source":"VULYK","estate":{"23":[{"region_unclear":false,"space_unclear":false,"costs":"","costs_comment":"приватизована","costs_hidden":false,"address_hidden":false,"region_hidden":false,"space_comment":"","space_hidden":false,"space_units_unclear":false,"address":"","costs_comment_unclear":false,"region":"","address_unclear":false,"space":"1700","costs_rent_hidden":false,"costs_rent_comment_hidden":false,"space_units":"м²","costs_comment_hidden":false,"costs_rent":"","costs_rent_comment":""}],"25":[{"region_unclear":false,"space_unclear":false,"costs":"","costs_comment":"приватизована","costs_hidden":false,"address_hidden":false,"region_hidden":false,"space_comment":"","space":"90","address":"","costs_rent_comment_unclear":false,"region":"","costs_rent_comment":"","costs_rent_hidden":false,"space_comment_unclear":false,"costs_rent_comment_hidden":false,"space_units":"м²","costs_comment_hidden":false,"costs_rent":"","costs_unclear":false}],"27":[{"space_hidden":false,"costs":"","costs_comment":"","costs_hidden":false,"address_hidden":false,"region_hidden":false,"space_comment":"","space_unclear":false,"space":"42","address":"","region":"","costs_rent_comment":"","costs_rent_hidden":false,"costs_rent_comment_hidden":false,"space_units":"м²","costs_comment_hidden":false,"costs_rent":""}]},"intro":{"declaration_year":"2013","isnotdeclaration":"","declaration_year_unclear":false,"declaration_year_hidden":false}}],"declarationsLength":2,"analytics":[{"y":2015,"i":315931,"c":1,"k":90,"ka":1,"l":1700,"la":1,"fi":21015},{"y":2013,"i":396643,"k":90,"ka":1,"l":1700,"la":1,"fi":21905}]}