{"2010":"","2016":"","Department":"Господарський суд м. Києв","Region":"м. Київ","Position":"Суддя Господарського суду м. Києва","Name":"Гусєва Тетяна Олексіївна","Link":"https://drive.google.com/open?id=0BygiyWAl79DMZV9LYUg3bEo5d28","Note":"У меня","AdditionalNote":"","field8":"","field9":"","field10":"","Кількість справ":"","Оскаржені":"","Кількість скарг":0,"Кількість дисциплінарних стягнень":"","Клейма":4,"Фото":"","Як живе":"","key":"gusieva_tetyana_oleksiyivna","allDeclarations":[{"provider":"declarations.com.ua","document":{"id":"vulyk_66_82","ft_src":"2987 куб. см., 190 кВт , 48.4 см\nMercedes-Benz 350\n2012\n2359 куб. см., 131008 кВт , 482.0 см\nHyundai Sonata\n2011\nм. Сімферополь\n434\nКримська Автономна Республіка\n65\nКримська Автономна Республіка\nЛенінський район\nм. Сімферополь\n60.4\nКримська Автономна Республіка\nм. Сімферополь\n122.6\nКримська Автономна Республіка\nм. Сімферополь\n90.8\nКримська Автономна Республіка\n2014\n32022\n9485\n41507\n2987 куб. см., 190 кВт , 48.4 см\nMercedes-Benz 350\n2012\n2359 куб. см., 131008 кВт , 482.0 см\n2011\nHyundai Sonata\n434\nКримська Автономна Республіка\nм. Сімферополь\n60.4\nм. Сімферополь\nКримська Автономна Республіка\n65\nКримська Автономна Республіка\nЛенінський район\n122.6\nКримська Автономна Республіка\nм. Сімферополь\n90.8\nКримська Автономна Республіка\nм. Сімферополь\nГосподарський місцевий суд\nсуддя господарського суду м. києва\nм. Київ\nПодружжя\nГусєв О. П\nДитина\nГусєва М. О\nГусєва Тетяна Олексіївна\nТетяна Олексіївна Гусєва\nТетяна Гусєва\nГусєва Тетяна Олексіївна\nГусєва Тетяна Олексіївна\nТетяна\nГусєва\nОлексіївна\nКиїв\nм. Київ\nКримська Автономна Республіка\nСімферополь\n24030\n36527\n1403\n32022\n9485\n41507\n2014\n36527\n1403\n24030\nГусєв О. П\nПодружжя\nГусєва М. О\nДитина\nОлексіївна\nГусєва\nТетяна\nГусєва Тетяна Олексіївна\nТетяна Олексіївна Гусєва\nТетяна Гусєва\nГусєва Тетяна Олексіївна\nм. Київ\nКиїв\nСімферополь\nКримська Автономна Республіка\nм. Київ\nсуддя господарського суду м. києва\nГосподарський місцевий суд\nГусєва Тетяна Олексіївна","estate":{"23":[{"address":"м. Сімферополь","space_units":"м²","costs_hidden":false,"space_hidden":false,"space_unclear":false,"region_hidden":false,"space_units_unclear":false,"costs_comment":"","address_hidden":true,"costs":"","address_unclear":false,"space_comment":"","costs_rent_comment":"","space":"434","region":"Кримська Автономна Республіка","space_units_hidden":false,"costs_rent":""}],"24":[{"costs":"","address":"м. Сімферополь","space_units":"м²","costs_hidden":false,"costs_rent_hidden":false,"space_comment":"","region_hidden":false,"costs_rent_comment":"","costs_comment":"","space_comment_unclear":false,"space_hidden":false,"address_unclear":false,"address_hidden":true,"space_unclear":false,"space":"60.4","region":"Кримська Автономна Республіка","costs_rent":""}],"25":[{"address":"м. Сімферополь","space_units":"м²","costs_hidden":false,"space_hidden":false,"space_unclear":false,"region_hidden":false,"costs_rent_comment":"","space_comment":"","space_comment_unclear":false,"costs":"","address_unclear":false,"address_hidden":true,"costs_comment":"","space":"122.6","region_unclear":false,"region":"Кримська Автономна Республіка","space_units_hidden":false,"costs_rent":""},{"address":"м. Сімферополь","space_units":"м²","costs_hidden":false,"space_hidden":false,"space_unclear":false,"region_hidden":false,"costs_rent_comment":"","space_comment":"","address_hidden":false,"costs":"","costs_comment_unclear":false,"costs_comment":"","space":"90.8","region":"Кримська Автономна Республіка","costs_rent":""}],"31":[{"costs_property_comment":"","address":"Ленінський район","space_units":"м²","space_hidden":false,"space_unclear":false,"region_hidden":false,"costs_property":"","space_comment":"","address_hidden":true,"space_comment_hidden":false,"space_comment_unclear":false,"costs_rent_comment":"","space":"65","region":"Кримська Автономна Республіка","costs_rent":""}]},"vehicle":{"35":[{"year_hidden":false,"brand_info":"2987 куб. см., 190 кВт , 48.4 см","sum_rent_comment":"","brand_unclear":false,"brand_hidden":false,"year":"2012","sum_comment":"","sum_rent":"","brand":"Mercedes-Benz 350","year_unclear":false,"brand_info_unclear":false,"sum":""}],"40":[{"sum_comment":"","brand_info":"2359 куб. см., 131008 кВт , 482.0 см","brand_unclear":false,"sum_rent_comment":"","year":"2011","brand":"Hyundai Sonata","sum_rent":"","brand_info_unclear":false,"year_unclear":false,"sum":""}]},"source":"VULYK","income":{"5":{"family_comment":"","family":"","value_hidden":false,"comment":"","value":"41507","comment_unclear":false,"value_unclear":false,"family_unclear":false,"family_hidden":false},"6":{"family":"","family_comment":"","comment":"","value_hidden":false,"value_unclear":false,"value":"32022","comment_unclear":false,"family_unclear":false,"family_hidden":false},"7":{"family_comment":"","comment":"","family":"","source_name_unclear":false,"value":"","source_name":""},"8":{"family_comment":"","value":"","family":"","comment":""},"9":{"family_comment":"","comment":"","family":"","value_unclear":false,"comment_hidden":false,"comment_unclear":false,"value":""},"10":{"family_comment":"","family":"","value_hidden":false,"comment":"","comment_unclear":false,"value":""},"11":{"family_comment":"","value":"","family":"","comment":""},"12":{"family_comment":"","value":"","family":"","comment":""},"13":{"family_comment":"","value":"","family":"","comment":""},"14":{"family_comment":"","value":"","family":"","comment":""},"15":{"family_comment":"","value":"9485","family":"","comment":""},"16":{"family_comment":"","value":"","family":"","comment":""},"17":{"family_comment":"","value":"","family":"","comment":""},"18":{"family":"","family_comment":"","comment":"","value_hidden":false,"family_hidden":false,"value":""},"19":{"family_comment":"","value":"","family":"","comment":""},"20":{"family":"","family_comment":"","comment":"","value_hidden":false,"value_unclear":false,"value":"","family_hidden":false,"family_unclear":false}},"general":{"family":[{"inn":"","family_name":"Гусєв О. П","relations_other":"","relations_hidden":false,"name_unclear":false,"inn_hidden":true,"name_hidden":true,"relations":"Подружжя"},{"inn":"","family_name":"Гусєва М. О","relations_other":"","relations_hidden":false,"relations_unclear":false,"name_unclear":false,"inn_hidden":true,"name_hidden":false,"relations":"Дитина"}],"family_raw":"","name":"Тетяна","full_name_suggest":{"input":["Гусєва Тетяна Олексіївна","Тетяна Олексіївна Гусєва","Тетяна Гусєва"],"output":"Гусєва Тетяна Олексіївна"},"patronymic":"Олексіївна","inn_hidden":true,"addresses":[{"place_city_type_hidden":false,"place_district_hidden":true,"place_address_unclear":false,"place":"м. Київ","place_city":"Київ","place_unclear":false,"place_city_type_unclear":false,"place_city_type":"Місто","place_city_hidden":true,"place_city_unclear":false,"place_district":"","place_district_unclear":false,"place_address":"","place_address_hidden":true,"place_hidden":false},{"place_district":"Сімферополь","place":"Кримська Автономна Республіка","place_city_type":"","place_address":"","place_city":""}],"last_name_hidden":false,"inn":"","inn_unclear":false,"last_name":"Гусєва","full_name":"Гусєва Тетяна Олексіївна","post":{"office":"Господарський місцевий суд","post":"суддя господарського суду м. києва","candidate":"","office_hidden":false,"region":"м. Київ","post_unclear":false,"office_unclear":false},"last_name_unclear":false},"liabilities":{"54":{"sum_comment_unclear":false,"sum_comment":"","sum":"1403","sum_foreign_comment":"","sum_foreign":"","sum_unclear":false,"sum_comment_hidden":false},"55":{"sum_comment":"","sum_foreign_comment":"","sum_foreign":"","sum":""},"56":{"sum_comment":"","sum_hidden":false,"sum":"","sum_foreign_comment":"","sum_foreign":"","sum_foreign_hidden":false,"sum_comment_hidden":false},"57":{"sum_comment_unclear":false,"sum_comment":"","sum_hidden":false,"sum":"","sum_foreign_comment":"","sum_foreign":"","sum_unclear":false,"sum_comment_hidden":false},"58":{"sum_comment_unclear":false,"sum_comment":"","sum":"","sum_foreign_comment":"","sum_foreign":"","sum_unclear":false},"59":{"sum_comment_unclear":false,"sum_comment":"","sum_hidden":false,"sum":"","sum_foreign_comment":"","sum_foreign":"","sum_foreign_hidden":false},"60":{"sum_comment":"","sum_comment_unclear":false,"sum_foreign_comment":"","sum":"","sum_foreign":""},"61":{"sum_comment":"","sum_foreign_comment":"","sum_foreign":"","sum":""},"62":{"sum_comment":"","sum_hidden":false,"sum":"","sum_foreign_comment":"","sum_foreign":"","sum_unclear":false,"sum_foreign_hidden":false},"63":{"sum_comment_unclear":false,"sum_comment":"","sum":"24030","sum_foreign_comment":"","sum_foreign":"","sum_unclear":false,"sum_comment_hidden":false},"64":{"sum_comment":"","sum_comment_unclear":false,"sum_foreign_comment":"","sum":"36527","sum_foreign":""}},"declaration":{"notfull_lostpages":"","additional_info_text":"","additional_info":"","date":"2015-03-31T00:00:00","notfull":"","url":"http://static.declarations.com.ua/declarations/chosen_ones/mega_batch/husieva_tetiana_oleksiivna.pdf"},"intro":{"isnotdeclaration":"","declaration_year_unclear":false,"declaration_year":"2014"}}}],"declarations":[{"id":"vulyk_66_82","ft_src":"2987 куб. см., 190 кВт , 48.4 см\nMercedes-Benz 350\n2012\n2359 куб. см., 131008 кВт , 482.0 см\nHyundai Sonata\n2011\nм. Сімферополь\n434\nКримська Автономна Республіка\n65\nКримська Автономна Республіка\nЛенінський район\nм. Сімферополь\n60.4\nКримська Автономна Республіка\nм. Сімферополь\n122.6\nКримська Автономна Республіка\nм. Сімферополь\n90.8\nКримська Автономна Республіка\n2014\n32022\n9485\n41507\n2987 куб. см., 190 кВт , 48.4 см\nMercedes-Benz 350\n2012\n2359 куб. см., 131008 кВт , 482.0 см\n2011\nHyundai Sonata\n434\nКримська Автономна Республіка\nм. Сімферополь\n60.4\nм. Сімферополь\nКримська Автономна Республіка\n65\nКримська Автономна Республіка\nЛенінський район\n122.6\nКримська Автономна Республіка\nм. Сімферополь\n90.8\nКримська Автономна Республіка\nм. Сімферополь\nГосподарський місцевий суд\nсуддя господарського суду м. києва\nм. Київ\nПодружжя\nГусєв О. П\nДитина\nГусєва М. О\nГусєва Тетяна Олексіївна\nТетяна Олексіївна Гусєва\nТетяна Гусєва\nГусєва Тетяна Олексіївна\nГусєва Тетяна Олексіївна\nТетяна\nГусєва\nОлексіївна\nКиїв\nм. Київ\nКримська Автономна Республіка\nСімферополь\n24030\n36527\n1403\n32022\n9485\n41507\n2014\n36527\n1403\n24030\nГусєв О. П\nПодружжя\nГусєва М. О\nДитина\nОлексіївна\nГусєва\nТетяна\nГусєва Тетяна Олексіївна\nТетяна Олексіївна Гусєва\nТетяна Гусєва\nГусєва Тетяна Олексіївна\nм. Київ\nКиїв\nСімферополь\nКримська Автономна Республіка\nм. Київ\nсуддя господарського суду м. києва\nГосподарський місцевий суд\nГусєва Тетяна Олексіївна","estate":{"23":[{"address":"м. Сімферополь","space_units":"м²","costs_hidden":false,"space_hidden":false,"space_unclear":false,"region_hidden":false,"space_units_unclear":false,"costs_comment":"","address_hidden":true,"costs":"","address_unclear":false,"space_comment":"","costs_rent_comment":"","space":"434","region":"Кримська Автономна Республіка","space_units_hidden":false,"costs_rent":""}],"24":[{"costs":"","address":"м. Сімферополь","space_units":"м²","costs_hidden":false,"costs_rent_hidden":false,"space_comment":"","region_hidden":false,"costs_rent_comment":"","costs_comment":"","space_comment_unclear":false,"space_hidden":false,"address_unclear":false,"address_hidden":true,"space_unclear":false,"space":"60.4","region":"Кримська Автономна Республіка","costs_rent":""}],"25":[{"address":"м. Сімферополь","space_units":"м²","costs_hidden":false,"space_hidden":false,"space_unclear":false,"region_hidden":false,"costs_rent_comment":"","space_comment":"","space_comment_unclear":false,"costs":"","address_unclear":false,"address_hidden":true,"costs_comment":"","space":"122.6","region_unclear":false,"region":"Кримська Автономна Республіка","space_units_hidden":false,"costs_rent":""},{"address":"м. Сімферополь","space_units":"м²","costs_hidden":false,"space_hidden":false,"space_unclear":false,"region_hidden":false,"costs_rent_comment":"","space_comment":"","address_hidden":false,"costs":"","costs_comment_unclear":false,"costs_comment":"","space":"90.8","region":"Кримська Автономна Республіка","costs_rent":""}],"31":[{"costs_property_comment":"","address":"Ленінський район","space_units":"м²","space_hidden":false,"space_unclear":false,"region_hidden":false,"costs_property":"","space_comment":"","address_hidden":true,"space_comment_hidden":false,"space_comment_unclear":false,"costs_rent_comment":"","space":"65","region":"Кримська Автономна Республіка","costs_rent":""}]},"vehicle":{"35":[{"year_hidden":false,"brand_info":"2987 куб. см., 190 кВт , 48.4 см","sum_rent_comment":"","brand_unclear":false,"brand_hidden":false,"year":"2012","sum_comment":"","sum_rent":"","brand":"Mercedes-Benz 350","year_unclear":false,"brand_info_unclear":false,"sum":""}],"40":[{"sum_comment":"","brand_info":"2359 куб. см., 131008 кВт , 482.0 см","brand_unclear":false,"sum_rent_comment":"","year":"2011","brand":"Hyundai Sonata","sum_rent":"","brand_info_unclear":false,"year_unclear":false,"sum":""}]},"source":"VULYK","income":{"5":{"family_comment":"","family":"","value_hidden":false,"comment":"","value":"41507","comment_unclear":false,"value_unclear":false,"family_unclear":false,"family_hidden":false},"6":{"family":"","family_comment":"","comment":"","value_hidden":false,"value_unclear":false,"value":"32022","comment_unclear":false,"family_unclear":false,"family_hidden":false},"7":{"family_comment":"","comment":"","family":"","source_name_unclear":false,"value":"","source_name":""},"8":{"family_comment":"","value":"","family":"","comment":""},"9":{"family_comment":"","comment":"","family":"","value_unclear":false,"comment_hidden":false,"comment_unclear":false,"value":""},"10":{"family_comment":"","family":"","value_hidden":false,"comment":"","comment_unclear":false,"value":""},"11":{"family_comment":"","value":"","family":"","comment":""},"12":{"family_comment":"","value":"","family":"","comment":""},"13":{"family_comment":"","value":"","family":"","comment":""},"14":{"family_comment":"","value":"","family":"","comment":""},"15":{"family_comment":"","value":"9485","family":"","comment":""},"16":{"family_comment":"","value":"","family":"","comment":""},"17":{"family_comment":"","value":"","family":"","comment":""},"18":{"family":"","family_comment":"","comment":"","value_hidden":false,"family_hidden":false,"value":""},"19":{"family_comment":"","value":"","family":"","comment":""},"20":{"family":"","family_comment":"","comment":"","value_hidden":false,"value_unclear":false,"value":"","family_hidden":false,"family_unclear":false}},"general":{"family":[{"inn":"","family_name":"Гусєв О. П","relations_other":"","relations_hidden":false,"name_unclear":false,"inn_hidden":true,"name_hidden":true,"relations":"Подружжя"},{"inn":"","family_name":"Гусєва М. О","relations_other":"","relations_hidden":false,"relations_unclear":false,"name_unclear":false,"inn_hidden":true,"name_hidden":false,"relations":"Дитина"}],"family_raw":"","name":"Тетяна","full_name_suggest":{"input":["Гусєва Тетяна Олексіївна","Тетяна Олексіївна Гусєва","Тетяна Гусєва"],"output":"Гусєва Тетяна Олексіївна"},"patronymic":"Олексіївна","inn_hidden":true,"addresses":[{"place_city_type_hidden":false,"place_district_hidden":true,"place_address_unclear":false,"place":"м. Київ","place_city":"Київ","place_unclear":false,"place_city_type_unclear":false,"place_city_type":"Місто","place_city_hidden":true,"place_city_unclear":false,"place_district":"","place_district_unclear":false,"place_address":"","place_address_hidden":true,"place_hidden":false},{"place_district":"Сімферополь","place":"Кримська Автономна Республіка","place_city_type":"","place_address":"","place_city":""}],"last_name_hidden":false,"inn":"","inn_unclear":false,"last_name":"Гусєва","full_name":"Гусєва Тетяна Олексіївна","post":{"office":"Господарський місцевий суд","post":"суддя господарського суду м. києва","candidate":"","office_hidden":false,"region":"м. Київ","post_unclear":false,"office_unclear":false},"last_name_unclear":false},"liabilities":{"54":{"sum_comment_unclear":false,"sum_comment":"","sum":"1403","sum_foreign_comment":"","sum_foreign":"","sum_unclear":false,"sum_comment_hidden":false},"55":{"sum_comment":"","sum_foreign_comment":"","sum_foreign":"","sum":""},"56":{"sum_comment":"","sum_hidden":false,"sum":"","sum_foreign_comment":"","sum_foreign":"","sum_foreign_hidden":false,"sum_comment_hidden":false},"57":{"sum_comment_unclear":false,"sum_comment":"","sum_hidden":false,"sum":"","sum_foreign_comment":"","sum_foreign":"","sum_unclear":false,"sum_comment_hidden":false},"58":{"sum_comment_unclear":false,"sum_comment":"","sum":"","sum_foreign_comment":"","sum_foreign":"","sum_unclear":false},"59":{"sum_comment_unclear":false,"sum_comment":"","sum_hidden":false,"sum":"","sum_foreign_comment":"","sum_foreign":"","sum_foreign_hidden":false},"60":{"sum_comment":"","sum_comment_unclear":false,"sum_foreign_comment":"","sum":"","sum_foreign":""},"61":{"sum_comment":"","sum_foreign_comment":"","sum_foreign":"","sum":""},"62":{"sum_comment":"","sum_hidden":false,"sum":"","sum_foreign_comment":"","sum_foreign":"","sum_unclear":false,"sum_foreign_hidden":false},"63":{"sum_comment_unclear":false,"sum_comment":"","sum":"24030","sum_foreign_comment":"","sum_foreign":"","sum_unclear":false,"sum_comment_hidden":false},"64":{"sum_comment":"","sum_comment_unclear":false,"sum_foreign_comment":"","sum":"36527","sum_foreign":""}},"declaration":{"notfull_lostpages":"","additional_info_text":"","additional_info":"","date":"2015-03-31T00:00:00","notfull":"","url":"http://static.declarations.com.ua/declarations/chosen_ones/mega_batch/husieva_tetiana_oleksiivna.pdf"},"intro":{"isnotdeclaration":"","declaration_year_unclear":false,"declaration_year":"2014"}}],"declarationsLength":1,"analytics":[{"y":2014,"i":41507,"c":1,"k":213.4,"ka":2,"h":60.4,"ha":1,"l":434,"la":1,"ff":65,"ffa":1}]}