{"2010":"","2016":"","Department":"Господарський суд Дніпропетровської області","Region":"Дніпропетровська область","Position":"Суддя Господарського суду Дніпропетровської області","Name":"Євстигнеєва Надія Михайлівна","Link":"http://dp.arbitr.gov.ua/userfiles/file/sud5005/deklarazii%202014/evstegneeva.pdf","Note":"","AdditionalNote":"","field8":"","field9":"","Link 2015":"","Кількість справ":"","Оскаржені":"","Кількість скарг":0,"Кількість дисциплінарних стягнень":"","Клейма":"","Фото":"","Як живе":"","key":"ievstigneieva_nadiya_mihaylivna","allDeclarations":[{"provider":"declarations.com.ua","document":{"income":{"5":{"family_comment":"","value":"228746","family":"81180","comment":""},"6":{"family_comment":"","value":"214149","family":"77497","comment":""},"7":{"value":"","comment_hidden":false,"family_comment":"","source_name":"","family":"","comment":"","source_name_hidden":false},"8":{"family_comment":"","value":"","family_hidden":false,"comment":"","family":""},"9":{"value":"14597","family_comment":"","value_unclear":false,"family_unclear":false,"family":"182","comment":""},"10":{"family_comment":"","value":"","family":"","comment":""},"11":{"family_comment":"","value":"","family":"","comment":""},"12":{"family_comment":"","value":"","family":"","comment":""},"13":{"family_comment":"","value":"","family":"","comment":""},"14":{"family_comment":"","value":"","family":"","comment":""},"15":{"family_comment":"","value":"","family":"","comment":""},"16":{"family_comment":"","value":"","family":"","comment":""},"17":{"family_comment":"","value":"","family":"","comment":""},"18":{"family_comment":"","value":"","family":"","comment":""},"19":{"family_comment":"","value":"","family":"","comment":""},"20":{"value":"","value_unclear":false,"family_hidden":false,"family_comment":"","family":"3501","comment":""}},"vehicle":{"35":[{"brand_info":"1548, 454.0","sum_rent_comment":"","year":"2012","brand_info_hidden":false,"brand_info_unclear":false,"year_unclear":false,"sum_rent":"","sum":"","brand":"Toyota Corolla","sum_comment":"","sum_comment_unclear":false,"brand_hidden":false,"brand_unclear":false}],"40":[{"brand_info":"1.5","sum_rent_comment":"","brand":"Jac S4","sum_comment":"","year":"2015","brand_info_unclear":false,"sum":"","sum_rent":""}]},"id":"vulyk_109_40","banks":{"45":[{"sum_foreign_comment":"","sum_unclear":false,"sum_units":"UAH","sum_comment":"Райффайзен Банк Аваль","sum_foreign_units":"UAH","sum_comment_hidden":false,"sum_units_hidden":false,"sum":"33400","sum_foreign":""},{"sum_foreign_comment":"","sum_units":"UAH","sum_comment":"Кредит Дніпро","sum_comment_unclear":false,"sum":"68946","sum_foreign":""}]},"declaration":{"additional_info_text":"","notfull_lostpages":"","date":"2016-03-31T00:00:00","notfull":"","additional_info":"","url":"http://static.declarations.com.ua/declarations/chosen_ones/judges_batch/2497_ievstyhneieva_nadiia_mykhailivna_2015.pdf"},"liabilities":{"54":{"sum_foreign_comment":"","sum":"","sum_comment":"","sum_hidden":false,"sum_comment_hidden":false,"sum_unclear":false,"sum_foreign":""},"55":{"sum_foreign_comment":"","sum":"","sum_comment":"","sum_comment_unclear":false,"sum_foreign":""},"56":{"sum_foreign_comment":"","sum":"","sum_comment":"","sum_foreign":""},"57":{"sum_foreign_comment":"","sum_comment_hidden":false,"sum":"","sum_comment":"","sum_foreign":""},"58":{"sum_foreign_comment":"","sum_comment_hidden":false,"sum":"","sum_comment":"","sum_foreign":""},"59":{"sum_foreign_comment":"","sum":"","sum_comment":"","sum_foreign":""},"60":{"sum_foreign_comment":"","sum":"120","sum_comment":"","sum_foreign":""},"61":{"sum_foreign_comment":"","sum":"","sum_comment":"","sum_foreign":""},"62":{"sum_foreign_comment":"","sum":"","sum_comment":"","sum_foreign":""},"63":{"sum_foreign_comment":"","sum":"","sum_comment":"","sum_foreign":""},"64":{"sum_foreign_comment":"","sum":"","sum_comment":"","sum_foreign":""}},"ft_src":"120\nДніпропетровська область\nсуддя господарського суду дніпропетровської області\nДніпропетровська область\nГосподарський місцевий суд\nНадія\nГерун Т. О\nДитина\nГерун Є. О\nЗять\nІнше\nГерун М\nМихайлівна\nЄвстигнеєва Надія Михайлівна\nНадія Михайлівна Євстигнеєва\nНадія Євстигнеєва\nЄвстигнеєва Надія Михайлівна\nЄвстигнеєва Надія Михайлівна\nЄвстигнеєва\n1548, 454.0\nToyota Corolla\n2012\n1.5\n2015\nJac S4\n14.72\n162.8\nРайффайзен Банк Аваль\n33400\nКредит Дніпро\n68946\n2015\n1548, 454.0\nToyota Corolla\n2012\n1.5\n2015\nJac S4\n2015\nЄвстигнеєва Надія Михайлівна\nНадія Михайлівна Євстигнеєва\nНадія Євстигнеєва\nЄвстигнеєва Надія Михайлівна\nНадія\nДитина\nГерун Т. О\nІнше\nГерун Є. О\nЗять\nГерун М\nЄвстигнеєва Надія Михайлівна\nМихайлівна\nГосподарський місцевий суд\nДніпропетровська область\nсуддя господарського суду дніпропетровської області\nЄвстигнеєва\nДніпропетровська область\n120\n214149\n77497\n3501\n228746\n81180\n14597\n182\n14.72\n162.8\n33400\nРайффайзен Банк Аваль\n68946\nКредит Дніпро\n120\n77497\n214149\n81180\n228746\n182\n14597\n3501\nДитина\nГерун Т. О\nІнше\nГерун Є. О\nЗять\nГерун М\nМихайлівна\nЄвстигнеєва\nНадія\nЄвстигнеєва Надія Михайлівна\nНадія Михайлівна Євстигнеєва\nНадія Євстигнеєва\nЄвстигнеєва Надія Михайлівна\nДніпропетровська область\nДніпропетровська область\nГосподарський місцевий суд\nсуддя господарського суду дніпропетровської області\nЄвстигнеєва Надія Михайлівна\n2012\nToyota Corolla\n1548, 454.0\n2015\n1.5\nJac S4\n3501\n81180\n228746\n14597\n182\n77497\n214149\n14.72\n162.8\nРайффайзен Банк Аваль\n33400\nКредит Дніпро\n68946\n2015","general":{"name_hidden":false,"name":"Надія","inn":"","family":[{"inn":"","relations":"Дитина","relations_hidden":false,"inn_hidden":false,"relations_other":"","name_hidden":false,"family_name":"Герун Т. О","name_unclear":false},{"inn":"","relations":"Інше","relations_other":"Зять","inn_hidden":false,"family_name":"Герун Є. О","name_hidden":false,"name_unclear":false},{"inn":"","relations":"","relations_other":"","inn_hidden":false,"family_name":"Герун М","name_hidden":false,"name_unclear":false}],"patronymic":"Михайлівна","inn_hidden":false,"family_raw":"","inn_unclear":false,"post":{"region_unclear":false,"region":"Дніпропетровська область","post":"суддя господарського суду дніпропетровської області","region_hidden":false,"office":"Господарський місцевий суд","office_hidden":false,"office_unclear":false},"full_name":"Євстигнеєва Надія Михайлівна","addresses":[{"place_district":"","place_city_hidden":false,"place_city":"","place_city_type_hidden":false,"place_district_hidden":false,"place_city_type":"","place_address_hidden":false,"place_address":"","place_hidden":false,"place":"Дніпропетровська область"}],"last_name":"Євстигнеєва","full_name_suggest":{"output":"Євстигнеєва Надія Михайлівна","input":["Євстигнеєва Надія Михайлівна","Надія Михайлівна Євстигнеєва","Надія Євстигнеєва"]}},"source":"VULYK","estate":{"25":[{"space_unclear":false,"costs":"","costs_comment":"","address_hidden":false,"region_hidden":false,"space_comment":"","space_hidden":false,"space":"162.8","address":"","region":"","costs_rent_comment":"","space_units":"м²","space_units_hidden":false,"costs_rent":""}],"31":[{"space_hidden":false,"costs_property_comment":"","address_hidden":true,"region_hidden":false,"space_comment":"","space":"14.72","address":"","region":"","costs_property":"","costs_rent_comment":"","space_units":"м²","space_units_hidden":false,"costs_rent":""}]},"intro":{"declaration_year":"2015","isnotdeclaration":""}}},{"provider":"declarations.com.ua","document":{"income":{"5":{"value":"225714","family_unclear":false,"family_hidden":false,"family_comment":"","family":"","comment":""},"6":{"family_comment":"","value":"217700","family_hidden":false,"comment":"","family":""},"7":{"family_comment":"","value":"","source_name":"","family":"","comment":""},"8":{"family_comment":"","value":"","family":"","comment":""},"9":{"value":"8014","comment_unclear":false,"family_hidden":false,"family_comment":"","family":"","comment":""},"10":{"family_comment":"","value":"","family":"","comment":""},"11":{"family_comment":"","value":"","family":"","comment":""},"12":{"family_comment":"","value":"","family":"","comment":""},"13":{"family_comment":"","value":"","family":"","comment":""},"14":{"family_comment":"","value":"","family":"","comment":""},"15":{"family_comment":"","value":"","value_unclear":false,"family":"","comment":""},"16":{"family_comment":"","value":"","family":"","comment":""},"17":{"family_comment":"","value":"","family":"","comment":""},"18":{"family_comment":"","value":"","family":"","comment":""},"19":{"family_comment":"","value":"","family":"","comment":""},"20":{"value":"","comment_unclear":false,"comment_hidden":false,"family_hidden":false,"value_hidden":false,"family_comment":"","value_unclear":false,"family":"","comment":"","family_comment_hidden":false}},"vehicle":{"35":[{"brand_info":"1598, 4540","sum_rent_comment":"","brand":"Toyota Corolla","sum_comment":"","year":"2012","brand_info_hidden":false,"sum":"","sum_rent":""}]},"id":"vulyk_41_6","banks":{"45":[{"sum_foreign_comment":"","sum_units":"UAH","sum_comment":"","sum_foreign_unclear":false,"sum_foreign_units":"UAH","sum_hidden":false,"sum_comment_hidden":false,"sum":"19652","sum_foreign":""},{"sum_foreign_comment":"","sum_units":"UAH","sum_comment":"","sum_foreign_unclear":false,"sum_foreign_units":"","sum":"53071","sum_foreign":""}],"46":[{"sum_foreign_comment":"","sum_units":"UAH","sum_comment":"","sum_foreign_units":"UAH","sum_comment_hidden":false,"sum_unclear":false,"sum":"","sum_foreign":""},{"sum_foreign_comment":"","sum_units":"","sum_comment":"","sum_foreign_units":"","sum":"","sum_unclear":false,"sum_foreign":""}],"47":[{"sum_foreign_comment":"","sum_units":"UAH","sum_comment":"","sum_foreign_units":"UAH","sum":"","sum_foreign":""},{"sum_foreign_comment":"","sum_units":"","sum_comment":"","sum_foreign_units":"","sum":"","sum_foreign":""}],"48":[{"sum_foreign_comment":"","sum_units":"UAH","sum_comment":"","sum_foreign_units":"UAH","sum":"","sum_foreign":""}],"49":[{"sum_foreign_comment":"","sum_units":"UAH","sum_comment":"","sum_foreign_units":"UAH","sum":"","sum_foreign":""}],"50":[{"sum_foreign_comment":"","sum_units":"UAH","sum_comment":"","sum_foreign_units":"UAH","sum":"","sum_foreign":""}],"51":[{"sum_foreign_comment":"","sum_units":"UAH","sum_comment":"","sum_hidden":false,"sum_foreign_units":"UAH","sum_comment_hidden":false,"sum_unclear":false,"sum":"","sum_foreign":""},{"sum_foreign_comment":"","sum_units":"","sum_comment":"","sum_foreign_units":"","sum":"","sum_foreign":""}],"52":[{"sum_foreign_comment":"","sum_units":"UAH","sum_comment":"","sum_foreign_units":"UAH","sum_comment_hidden":false,"sum_unclear":false,"sum":"","sum_foreign":""}],"53":[{"sum_foreign_comment":"","sum_units":"UAH","sum_comment":"","sum_foreign_units":"UAH","sum_comment_hidden":false,"sum":"","sum_foreign":""},{"sum_foreign_comment":"","sum_units":"","sum_comment":"","sum_foreign_units":"","sum":"","sum_foreign":""},{"sum_foreign_comment":"","sum_units":"","sum_comment":"","sum_foreign_units":"","sum":"","sum_foreign":""}]},"declaration":{"date":"2015-03-31T00:00:00","additional_info_text":"","additional_info":"","url":"http://static.declarations.com.ua/declarations/chosen_ones/mega_batch/yevstyhneieva_nadiia_mykhailivna.pdf"},"liabilities":{"54":{"sum_foreign_comment":"","sum_comment_hidden":false,"sum":"11718","sum_comment":"","sum_foreign":""},"55":{"sum_foreign_comment":"","sum":"","sum_comment":"","sum_foreign":""},"56":{"sum_foreign_comment":"","sum":"11716","sum_hidden":false,"sum_comment":"","sum_foreign":""},"57":{"sum_foreign_comment":"","sum":"7693","sum_comment":"","sum_comment_hidden":false,"sum_unclear":false,"sum_foreign":""},"58":{"sum_foreign_comment":"","sum_comment_hidden":false,"sum":"","sum_comment":"","sum_foreign":""},"59":{"sum_foreign_comment":"","sum":"","sum_comment":"","sum_foreign":""},"60":{"sum_foreign_comment":"","sum_comment_hidden":false,"sum":"","sum_comment":"","sum_foreign":""},"61":{"sum_foreign_comment":"","sum":"","sum_comment":"","sum_foreign":""},"62":{"sum_foreign_comment":"","sum":"","sum_comment":"","sum_foreign":""},"63":{"sum_foreign_comment":"","sum":"","sum_comment":"","sum_comment_hidden":false,"sum_unclear":false,"sum_foreign":""},"64":{"sum_foreign_comment":"","sum_comment_hidden":false,"sum":"","sum_comment":"","sum_foreign":""}},"ft_src":"7693\n11718\n11716\nсуддя господарського суду дніпропетровської області\nДніпропетровська область\nГосподарський місцевий суд\nНадія\nГерун Т. О\nДитина\nМихайлівна\nЄвстигнеєва Надія Михайлівна\nНадія Михайлівна Євстигнеєва\nНадія Євстигнеєва\nЄвстигнеєва Надія Михайлівна\nЄвстигнеєва\nЄвстигнеєва Надія Михайлівна\n1598, 4540\n2012\nToyota Corolla\n19652\n53071\n2014\nToyota Corolla\n1598, 4540\n2012\n19652\n53071\n162.8\nДитина\nГерун Т. О\nЄвстигнеєва Надія Михайлівна\nНадія Михайлівна Євстигнеєва\nНадія Євстигнеєва\nЄвстигнеєва Надія Михайлівна\nЄвстигнеєва Надія Михайлівна\nНадія\nМихайлівна\nГосподарський місцевий суд\nсуддя господарського суду дніпропетровської області\nДніпропетровська область\nЄвстигнеєва\n7693\n11716\n11718\n217700\n225714\n8014\n2014\n7693\n11716\n11718\n162.8\nГерун Т. О\nДитина\nМихайлівна\nЄвстигнеєва\nНадія\nЄвстигнеєва Надія Михайлівна\nНадія Михайлівна Євстигнеєва\nНадія Євстигнеєва\nЄвстигнеєва Надія Михайлівна\nДніпропетровська область\nсуддя господарського суду дніпропетровської області\nГосподарський місцевий суд\nЄвстигнеєва Надія Михайлівна\n217700\n225714\n8014\nToyota Corolla\n1598, 4540\n2012\n225714\n8014\n217700\n162.8\n19652\n53071\n2014","general":{"inn":"","name":"Надія","family":[{"inn":"","relations":"Дитина","relations_hidden":false,"inn_hidden":true,"family_name":"Герун Т. О","name_hidden":false,"name_unclear":false}],"patronymic":"Михайлівна","inn_hidden":true,"family_raw":"","last_name":"Євстигнеєва","post":{"post_unclear":false,"post":"суддя господарського суду дніпропетровської області","post_hidden":false,"region":"Дніпропетровська область","region_hidden":false,"office":"Господарський місцевий суд","office_hidden":false},"last_name_unclear":false,"full_name":"Євстигнеєва Надія Михайлівна","addresses":[{"place_district":"","place_city_hidden":true,"place_city":"","place_city_type_hidden":false,"place_district_hidden":true,"place_city_type":"","place_address_hidden":false,"place_address":"","place_hidden":true,"place":""}],"patronymic_hidden":false,"full_name_suggest":{"output":"Євстигнеєва Надія Михайлівна","input":["Євстигнеєва Надія Михайлівна","Надія Михайлівна Євстигнеєва","Надія Євстигнеєва"]},"name_unclear":false},"source":"VULYK","estate":{"23":[{"region_unclear":false,"space_unclear":false,"costs":"","costs_comment":"","address_hidden":false,"region_hidden":false,"space_comment":"","space":"","address":"","costs_comment_unclear":false,"region":"","space_units_unclear":false,"space_comment_hidden":false,"space_units":"м²","costs_rent":"","costs_rent_comment":""},{"costs_rent":"","space_unclear":false,"region":"","costs":"","costs_rent_comment":"","costs_comment":"","space_comment":"","space_units":"","space":"","address":""},{"costs_rent":"","region":"","costs":"","costs_rent_comment":"","costs_comment":"","space_comment":"","space_units":"","space":"","address":""}],"25":[{"region_unclear":false,"space_hidden":false,"costs":"","costs_comment":"","address_hidden":false,"region_hidden":true,"space_comment":"","space_unclear":false,"space":"162.8","address":"","costs_comment_unclear":false,"region":"","costs_rent_comment":"","costs_unclear":false,"space_units":"м²","costs_rent":""}]},"intro":{"declaration_year":"2014"}}},{"provider":"declarations.com.ua","document":{"income":{"5":{"family_comment":"","value":"213973","family":"26172","comment":""},"6":{"family_comment":"","value":"193690","family":"26172","comment":""},"7":{"family_comment":"","value":"0","source_name":"0","family":"0","comment":""},"8":{"family_comment":"","value":"0","family":"0","comment":""},"9":{"family_comment":"","value":"2359","family":"0","comment":""},"10":{"family_comment":"","value":"11470","family":"0","comment":""},"11":{"family_comment":"","value":"0","family":"0","comment":""},"12":{"family_comment":"","value":"0","family":"0","comment":""},"13":{"family_comment":"","value":"0","family":"0","comment":""},"14":{"family_comment":"","value":"0","family":"0","comment":""},"15":{"family_comment":"","value":"6454","family":"0","comment":""},"16":{"family_comment":"","value":"0","family":"0","comment":""},"17":{"family_comment":"","value":"0","family":"0","comment":""},"18":{"family_comment":"","value":"0","family":"0","comment":""},"19":{"family_comment":"","value":"0","family":"0","comment":""},"20":{"family_comment":"","value":"0","family":"0","comment":""},"21":[{"cur":"0","country":"0","uah_equal":"0","country_comment":""},{"cur":"0","country":"0","uah_equal":"0","country_comment":""},{"cur":"0","country":"0","uah_equal":"0","country_comment":""},{"cur":"0","country":"0","uah_equal":"0","country_comment":""},{"cur":"0","country":"0","uah_equal":"0","country_comment":""}],"22":[{"cur":"0","country":"0","uah_equal":"0","country_comment":""},{"cur":"0","country":"0","uah_equal":"0","country_comment":""},{"cur":"0","country":"0","uah_equal":"0","country_comment":""},{"cur":"0","country":"0","uah_equal":"0","country_comment":""},{"cur":"0","country":"0","uah_equal":"0","country_comment":""}]},"vehicle":{"35":[{"brand_info":"","sum_rent_comment":"","brand":"Toyota,Corolla","sum_comment":"","year":"2012","brand_hidden":false,"sum":"","sum_rent":""}]},"id":"177","banks":{"45":[{"sum_foreign_comment":"","sum_units":"UAH","sum_comment":"","sum_foreign_units":"","sum":"36640","sum_foreign":""},{"sum_foreign_comment":"","sum_units":"USD","sum_comment":"","sum_foreign_units":"","sum":"","sum_foreign":""},{"sum_foreign_comment":"","sum_units":"EUR","sum_comment":"","sum_foreign_units":"","sum":"","sum_foreign":""}],"46":[{"sum_foreign_comment":"","sum_units":"UAH","sum_comment":"","sum_foreign_units":"","sum":"30993","sum_foreign":""},{"sum_foreign_comment":"","sum_units":"USD","sum_comment":"","sum_foreign_units":"","sum":"","sum_foreign":""},{"sum_foreign_comment":"","sum_units":"EUR","sum_comment":"","sum_foreign_units":"","sum":"","sum_foreign":""}],"47":[{"sum_foreign_comment":"","sum_units":"","sum_comment":"","sum_foreign_units":"","sum":"","sum_foreign":""}],"48":[{"sum_foreign_comment":"","sum_units":"","sum_comment":"","sum_foreign_units":"","sum":"","sum_foreign":""}],"49":[{"sum_foreign_comment":"","sum_units":"","sum_comment":"","sum_foreign_units":"","sum":"","sum_foreign":""}],"50":[{"sum_foreign_comment":"","sum_units":"","sum_comment":"","sum_foreign_units":"","sum":"","sum_foreign":""}],"51":[{"sum_foreign_comment":"","sum_units":"UAH","sum_comment":"","sum_foreign_units":"","sum":"","sum_foreign":""},{"sum_foreign_comment":"","sum_units":"USD","sum_comment":"","sum_foreign_units":"","sum":"","sum_foreign":""},{"sum_foreign_comment":"","sum_units":"EUR","sum_comment":"","sum_foreign_units":"","sum":"","sum_foreign":""}],"52":[{"sum_foreign_comment":"","sum_units":"","sum_comment":"","sum_foreign_units":"","sum":"","sum_foreign":""}],"53":[{"sum_foreign_comment":"","sum_units":"","sum_comment":"","sum_foreign_units":"","sum":"","sum_foreign":""}]},"declaration":{"needs_scancopy_check":false,"additional_info_text":"в этих пунктах я вносила только цифры, а доп.информация (в каких банках) написала здесь ниже.;Була інформація по пунктам;;45. Сума коштів на рахунках у банках усього; 9961 ПАТ РАЙФАЙЗЕН БАНК АВАЛЬ;26679  ПАТ БАНК КРЕДИТ ДНІПРО;;46. вкладених у звітному році Усього;7993   ПАТ РАЙФАЙЗЕН БАНК АВАЛЬ;23000  ПАТ БАНК КРЕДИТ ДНІПРО;;54. Добровільне страхування Усього;9218 Дніпропетровська філія СК «АХА»;;57. Погашення основної суми позики. Усього. ;50000 ПАТ КредіАгріколь, філія у Дніпропетровській обл;","notfull_lostpages":"","notfull":"FALSE","additional_info":"TRUE","url":"http://static.declarations.com.ua/declarations/sudy/hospodarski_mistsevi_sudy/dnipropetrovska_oblast/evsegneeva.pdf"},"liabilities":{"54":{"sum_foreign_comment":"","sum":"9218","sum_comment":"","sum_foreign":""},"55":{"sum_foreign_comment":"","sum_units":"","sum_comment":"","sum_foreign_units":"","sum":"","sum_foreign":""},"56":{"sum_foreign_comment":"","sum":"12269","sum_comment":"","sum_foreign":""},"57":{"sum_foreign_comment":"","sum":"50000","sum_comment":"","sum_foreign":""},"58":{"sum_foreign_comment":"","sum":"","sum_comment":"","sum_foreign":""},"59":{"sum_foreign_comment":"","sum":"","sum_comment":"","sum_foreign":""},"60":{"sum_foreign_comment":"","sum":"","sum_comment":"","sum_foreign":""},"61":{"sum_foreign_comment":"","sum_units":"","sum_comment":"","sum_foreign_units":"","sum":"","sum_foreign":""},"62":{"sum_foreign_comment":"","sum":"","sum_comment":"","sum_foreign":""},"63":{"sum_foreign_comment":"","sum_units":"","sum_comment":"","sum":"","sum_foreign":""},"64":{"sum_foreign_comment":"","sum_units":"","sum_comment":"","sum":"","sum_foreign":""}},"estate":{"23":[{"costs_rent":"","location_raw":"","region":"","costs":"","costs_rent_comment":"","costs_comment":"","space_comment":"","space_units":"","space":"","address":""},{"costs_rent":"","location_raw":"","region":"","costs":"","costs_rent_comment":"","costs_comment":"","space_comment":"","space_units":"","space":"","address":""},{"costs_rent":"","location_raw":"","region":"","costs":"","costs_rent_comment":"","costs_comment":"","space_comment":"","space_units":"","space":"","address":""}],"25":[{"costs_rent":"","location_raw":"приховано","region":"","costs":"","costs_rent_comment":"","costs_comment":"","space_comment":"","space_units":"","space":"162,8","address":""}]},"general":{"name_hidden":false,"name":"Надія","patronymic_unclear":false,"last_name_hidden":false,"addresses_raw":"приховано","post_raw":"Суддя господарського суду Дніпропетровської області","patronymic":"Михайлівна","inn":"","family_raw":"Донька, Євстигнеєва Т.О.","last_name":"Євстигнеєва","post":{"office":"Господарський місцевий суд","region":"Дніпропетровська область","post":"Суддя"},"addresses_raw_hidden":true,"last_name_unclear":false,"full_name":"Євстигнеєва Надія Михайлівна","patronymic_hidden":false,"full_name_suggest":{"output":"Євстигнеєва Надія Михайлівна","input":["Євстигнеєва Надія Михайлівна","Надія Михайлівна Євстигнеєва","Надія Євстигнеєва"]},"name_unclear":false},"ft_src":"50000\n9218\n12269\nFALSE\nв этих пунктах я вносила только цифры, а доп.информация (в каких банках) написала здесь ниже.;Була інформація по пунктам;;45. Сума коштів на рахунках у банках усього; 9961 ПАТ РАЙФАЙЗЕН БАНК АВАЛЬ;26679  ПАТ БАНК КРЕДИТ ДНІПРО;;46. вкладених у звітному році Усього;7993   ПАТ РАЙФАЙЗЕН БАНК АВАЛЬ;23000  ПАТ БАНК КРЕДИТ ДНІПРО;;54. Добровільне страхування Усього;9218 Дніпропетровська філія СК «АХА»;;57. Погашення основної суми позики. Усього. ;50000 ПАТ КредіАгріколь, філія у Дніпропетровській обл;\nTRUE\n6454\n11470\n26172\n213973\n2359\n26172\n193690\nToyota,Corolla\n2012\nToyota,Corolla\n2012\n162,8\n30993\n36640\nTRUE\nв этих пунктах я вносила только цифры, а доп.информация (в каких банках) написала здесь ниже.;Була інформація по пунктам;;45. Сума коштів на рахунках у банках усього; 9961 ПАТ РАЙФАЙЗЕН БАНК АВАЛЬ;26679  ПАТ БАНК КРЕДИТ ДНІПРО;;46. вкладених у звітному році Усього;7993   ПАТ РАЙФАЙЗЕН БАНК АВАЛЬ;23000  ПАТ БАНК КРЕДИТ ДНІПРО;;54. Добровільне страхування Усього;9218 Дніпропетровська філія СК «АХА»;;57. Погашення основної суми позики. Усього. ;50000 ПАТ КредіАгріколь, філія у Дніпропетровській обл;\nFALSE\nFALSE\n2013\n26172\n193690\n6454\n11470\n26172\n213973\n2359\nToyota,Corolla\n2012\nв этих пунктах я вносила только цифры, а доп.информация (в каких банках) написала здесь ниже.;Була інформація по пунктам;;45. Сума коштів на рахунках у банках усього; 9961 ПАТ РАЙФАЙЗЕН БАНК АВАЛЬ;26679  ПАТ БАНК КРЕДИТ ДНІПРО;;46. вкладених у звітному році Усього;7993   ПАТ РАЙФАЙЗЕН БАНК АВАЛЬ;23000  ПАТ БАНК КРЕДИТ ДНІПРО;;54. Добровільне страхування Усього;9218 Дніпропетровська філія СК «АХА»;;57. Погашення основної суми позики. Усього. ;50000 ПАТ КредіАгріколь, філія у Дніпропетровській обл;\nFALSE\nTRUE\n162,8\nСуддя господарського суду Дніпропетровської області\nДонька, Євстигнеєва Т.О.\nЄвстигнеєва\nЄвстигнеєва Надія Михайлівна\nНадія Михайлівна Євстигнеєва\nНадія Євстигнеєва\nЄвстигнеєва Надія Михайлівна\nНадія\nЄвстигнеєва Надія Михайлівна\nГосподарський місцевий суд\nСуддя\nДніпропетровська область\nМихайлівна\n50000\n12269\n9218\n193690\n26172\n6454\n213973\n26172\n11470\n2359\n36640\n30993\n2013\nFALSE\n50000\n12269\n9218\nЄвстигнеєва\nМихайлівна\nДонька, Євстигнеєва Т.О.\nЄвстигнеєва Надія Михайлівна\nНадія Михайлівна Євстигнеєва\nНадія Євстигнеєва\nЄвстигнеєва Надія Михайлівна\nНадія\nСуддя господарського суду Дніпропетровської області\nСуддя\nДніпропетровська область\nГосподарський місцевий суд\nЄвстигнеєва Надія Михайлівна\n162,8\nСуддя\nДніпропетровська область\nГосподарський місцевий суд\nСуддя господарського суду Дніпропетровської області\nНадія\nМихайлівна\nДонька, Євстигнеєва Т.О.\nЄвстигнеєва\nЄвстигнеєва Надія Михайлівна\nЄвстигнеєва Надія Михайлівна\nНадія Михайлівна Євстигнеєва\nНадія Євстигнеєва\nЄвстигнеєва Надія Михайлівна\n30993\n36640\nFALSE\n2013","intro":{"declaration_year":"2013","isnotdeclaration":"FALSE"}}},{"provider":"public-api.nazk.gov.ua","document":{"step_0":{"declarationType":"1","declarationYear1":"2015"},"step_1":{"city":"[Конфіденційна інформація]","region":"[Конфіденційна інформація]","street":"[Конфіденційна інформація]","country":"1","cityPath":"[Конфіденційна інформація]","cityType":"[Конфіденційна інформація]","district":"[Конфіденційна інформація]","lastname":"Євстигнеєва","postCode":"[Конфіденційна інформація]","postType":"","workPost":"суддя господарського суду Дніпропетровської області","firstname":"Надія","workPlace":"господарський суд Дніпропетровської області","middlename":"Михайлівна","streetType":"[Конфіденційна інформація]","changedName":false,"countryPath":"","eng_postCode":"","postCategory":"","actual_street":"[Конфіденційна інформація]","actual_cityPath":"[Конфіденційна інформація]","actual_cityType":"[Конфіденційна інформація]","actual_postCode":"[Конфіденційна інформація]","actual_streetType":"[Конфіденційна інформація]","previous_lastname":"","corruptionAffected":"Ні","eng_actualPostCode":"[Конфіденційна інформація]","previous_firstname":"","city_extendedstatus":"1","previous_middlename":"","responsiblePosition":"Суддя суду загальної юрисдикції, суддя Конституційного Суду України","sameRegLivingAddress":"[Конфіденційна інформація]","postType_extendedstatus":"1","eng_sameRegLivingAddress":"[Конфіденційна інформація]","housePartNum_extendedstatus":"1","postCategory_extendedstatus":"1"},"step_2":{"1475742805177":{"lastname":"Герун ","firstname":"Тетяна","middlename":"Олександрівна","changedName":false,"citizenship":"1","eng_lastname":"","eng_firstname":"","eng_middlename":"","isNotApplicable":"","subjectRelation":"дочка","previous_lastname":"","previous_firstname":"","previous_middlename":"","previous_eng_lastname":"","previous_eng_firstname":"","previous_eng_middlename":""},"1475750608825":{"lastname":"Герун","firstname":"Євген","middlename":"Олександрович","changedName":false,"citizenship":"1","eng_lastname":"","eng_firstname":"","eng_middlename":"","isNotApplicable":"","subjectRelation":"зять","previous_lastname":"","previous_firstname":"","previous_middlename":"","previous_eng_lastname":"","previous_eng_firstname":"","previous_eng_middlename":""},"1475750968234":{"lastname":"Герун","firstname":"Максим","middlename":"Євгенович","changedName":false,"citizenship":"1","eng_lastname":"","eng_firstname":"","eng_middlename":"","isNotApplicable":"","subjectRelation":"онук","previous_lastname":"","previous_firstname":"","previous_middlename":"","previous_eng_lastname":"","previous_eng_firstname":"","previous_eng_middlename":""}},"step_3":{"1475752175042":{"city":"[Конфіденційна інформація]","person":"1","region":"[Конфіденційна інформація]","rights":{"1":{"citizen":"","ua_city":"","ua_street":"[Конфіденційна інформація]","ua_lastname":"","ua_postCode":"","eng_lastname":"","eng_postCode":"","rightBelongs":"1","ua_firstname":"","ukr_lastname":"","eng_firstname":"","ownershipType":"Власність","ua_middlename":"","ua_streetType":"[Конфіденційна інформація]","ukr_firstname":"","eng_middlename":"","otherOwnership":"","ukr_middlename":"","rights_cityPath":"","ua_company_name":"","eng_company_name":"","ukr_company_name":"","percent-ownership":"100,00","ua_street_extendedstatus":"","ua_houseNum_extendedstatus":"","ua_postCode_extendedstatus":"","eng_postCode_extendedstatus":"","ua_middlename_extendedstatus":"","eng_middlename_extendedstatus":"","ukr_middlename_extendedstatus":"","ua_housePartNum_extendedstatus":"","ua_apartmentsNum_extendedstatus":"","percent-ownership_extendedstatus":"0"}},"country":"1","cityPath":"[Конфіденційна інформація]","costDate":"","district":"[Конфіденційна інформація]","postCode":"[Конфіденційна інформація]","totalArea":"162,8","ua_street":"[Конфіденційна інформація]","objectType":"Квартира","owningDate":"11.09.2009","ua_cityType":"Дніпро / Дніпропетровська Область / Україна","ua_postCode":"49054","ua_streetType":"[Конфіденційна інформація]","costAssessment":"2799834","otherObjectType":"","costDate_extendedstatus":"2","regNumber_extendedstatus":"0","costAssessment_extendedstatus":"0","ua_housePartNum_extendedstatus":"1"},"1476873633877":{"city":"[Конфіденційна інформація]","person":"1475750608825","region":"[Конфіденційна інформація]","rights":{"1475750608825":{"citizen":"","ua_city":"","ua_street":"[Конфіденційна інформація]","ua_lastname":"","ua_postCode":"","eng_lastname":"","eng_postCode":"","rightBelongs":"1475750608825","ua_firstname":"","ukr_lastname":"","eng_firstname":"","ownershipType":"Спільна власність","ua_middlename":"","ua_streetType":"[Конфіденційна інформація]","ukr_firstname":"","eng_middlename":"","otherOwnership":"","ukr_middlename":"","rights_cityPath":"","ua_company_name":"","eng_company_name":"","ukr_company_name":"","percent-ownership":"14,72","ua_street_extendedstatus":"","ua_houseNum_extendedstatus":"","ua_postCode_extendedstatus":"","eng_postCode_extendedstatus":"","ua_middlename_extendedstatus":"","eng_middlename_extendedstatus":"","ukr_middlename_extendedstatus":"","ua_housePartNum_extendedstatus":"","ua_apartmentsNum_extendedstatus":""}},"country":"1","cityPath":"[Конфіденційна інформація]","costDate":"8","district":"[Конфіденційна інформація]","postCode":"[Конфіденційна інформація]","totalArea":"44,15","ua_street":"[Конфіденційна інформація]","objectType":"Квартира","owningDate":"28.09.2006","ua_cityType":"Гайворон / Гайворонський Район / Кіровоградська Область / Україна","ua_postCode":"26300","ua_streetType":"[Конфіденційна інформація]","costAssessment":"","otherObjectType":"","costDate_extendedstatus":"0","ua_houseNum_extendedstatus":"0","costAssessment_extendedstatus":"2","ua_housePartNum_extendedstatus":"1"}},"step_4":[],"step_5":[],"step_6":{"1476359696459":{"brand":"Toyota","model":"Corolla","person":"1","rights":{"1":{"citizen":"","ua_city":"","ua_street":"[Конфіденційна інформація]","ua_lastname":"","ua_postCode":"","eng_fullname":"","eng_lastname":"","eng_postCode":"","rightBelongs":"1","ua_firstname":"","ukr_fullname":"","ukr_lastname":"","eng_firstname":"","ownershipType":"Власність","ua_middlename":"","ua_streetType":"[Конфіденційна інформація]","ukr_firstname":"","eng_middlename":"","otherOwnership":"","ukr_middlename":"","rights_cityPath":"","ua_company_name":"","eng_company_name":"","ukr_company_name":"","percent-ownership":"","ua_street_extendedstatus":"","ua_houseNum_extendedstatus":"","ua_postCode_extendedstatus":"","eng_postCode_extendedstatus":"","ua_middlename_extendedstatus":"","eng_middlename_extendedstatus":"","ukr_middlename_extendedstatus":"","ua_housePartNum_extendedstatus":"","ua_apartmentsNum_extendedstatus":""}},"costDate":"204234","objectType":"Автомобіль легковий","owningDate":"31.05.2012","graduationYear":"2012","otherObjectType":""},"1476359986294":{"brand":"JAC","model":"J4","person":"1475742805177","rights":{"1475742805177":{"citizen":"","ua_city":"","ua_street":"[Конфіденційна інформація]","ua_lastname":"","ua_postCode":"","eng_fullname":"","eng_lastname":"","eng_postCode":"","rightBelongs":"1475742805177","ua_firstname":"","ukr_fullname":"","ukr_lastname":"","eng_firstname":"","ownershipType":"Власність","ua_middlename":"","ua_streetType":"[Конфіденційна інформація]","ukr_firstname":"","eng_middlename":"","otherOwnership":"","ukr_middlename":"","rights_cityPath":"","ua_company_name":"","eng_company_name":"","ukr_company_name":"","percent-ownership":"","ua_street_extendedstatus":"","ua_houseNum_extendedstatus":"","ua_postCode_extendedstatus":"","eng_postCode_extendedstatus":"","ua_middlename_extendedstatus":"","eng_middlename_extendedstatus":"","ukr_middlename_extendedstatus":"","ua_housePartNum_extendedstatus":"","ua_apartmentsNum_extendedstatus":""}},"costDate":"246100","objectType":"Автомобіль легковий","owningDate":"28.04.2015","graduationYear":"2014","otherObjectType":""}},"step_7":[],"step_8":[],"step_9":[],"step_10":[],"step_11":{"1476788025062":{"person":"1","rights":{"1":{"citizen":"","ua_city":"","ua_street":"[Конфіденційна інформація]","ua_lastname":"","ua_postCode":"","eng_lastname":"","eng_postCode":"","rightBelongs":"1","ua_firstname":"","ukr_lastname":"","eng_firstname":"","ownershipType":"Власність","ua_middlename":"","ua_streetType":"[Конфіденційна інформація]","ukr_firstname":"","eng_middlename":"","otherOwnership":"","ukr_middlename":"","rights_cityPath":"","ua_company_name":"","eng_company_name":"","ukr_company_name":"","percent-ownership":"","ua_street_extendedstatus":"","ua_houseNum_extendedstatus":"","ua_postCode_extendedstatus":"","eng_postCode_extendedstatus":"","ua_middlename_extendedstatus":"","eng_middlename_extendedstatus":"","ukr_middlename_extendedstatus":"","ua_housePartNum_extendedstatus":"","ua_apartmentsNum_extendedstatus":""}},"objectType":"Заробітна плата отримана за основним місцем роботи","sizeIncome":"214149","incomeSource":"j","source_citizen":"Юридична особа, зареєстрована в Україні","otherObjectType":"","source_ua_lastname":"","source_eng_fullname":"","source_ua_firstname":"","source_ukr_fullname":"","source_ua_middlename":"","source_ua_company_name":"господарський суд Дніпропетровської області","source_eng_company_name":"","source_ukr_company_name":"","source_ua_sameRegLivingAddress":""},"1476876152162":{"person":"1","rights":{"1":{"citizen":"","ua_city":"","ua_street":"[Конфіденційна інформація]","ua_lastname":"","ua_postCode":"","eng_lastname":"","eng_postCode":"","rightBelongs":"1","ua_firstname":"","ukr_lastname":"","eng_firstname":"","ownershipType":"Власність","ua_middlename":"","ua_streetType":"[Конфіденційна інформація]","ukr_firstname":"","eng_middlename":"","otherOwnership":"","ukr_middlename":"","rights_cityPath":"","ua_company_name":"","eng_company_name":"","ukr_company_name":"","percent-ownership":"","ua_street_extendedstatus":"","ua_houseNum_extendedstatus":"","ua_postCode_extendedstatus":"","eng_postCode_extendedstatus":"","ua_middlename_extendedstatus":"","eng_middlename_extendedstatus":"","ukr_middlename_extendedstatus":"","ua_housePartNum_extendedstatus":"","ua_apartmentsNum_extendedstatus":""}},"objectType":"Проценти","sizeIncome":"14597","incomeSource":"j","source_citizen":"Юридична особа, зареєстрована в Україні","otherObjectType":"","source_ua_lastname":"","source_eng_fullname":"","source_ua_firstname":"","source_ukr_fullname":"","source_ua_middlename":"","source_ua_company_name":"ПАТ \"Банк Кредит Дніпро\"","source_eng_company_name":"","source_ukr_company_name":"","source_ua_sameRegLivingAddress":""},"1476876225074":{"person":"1475742805177","rights":{"1475742805177":{"citizen":"","ua_city":"","ua_street":"[Конфіденційна інформація]","ua_lastname":"","ua_postCode":"","eng_lastname":"","eng_postCode":"","rightBelongs":"1475742805177","ua_firstname":"","ukr_lastname":"","eng_firstname":"","ownershipType":"Власність","ua_middlename":"","ua_streetType":"[Конфіденційна інформація]","ukr_firstname":"","eng_middlename":"","otherOwnership":"","ukr_middlename":"","rights_cityPath":"","ua_company_name":"","eng_company_name":"","ukr_company_name":"","percent-ownership":"","ua_street_extendedstatus":"","ua_houseNum_extendedstatus":"","ua_postCode_extendedstatus":"","eng_postCode_extendedstatus":"","ua_middlename_extendedstatus":"","eng_middlename_extendedstatus":"","ukr_middlename_extendedstatus":"","ua_housePartNum_extendedstatus":"","ua_apartmentsNum_extendedstatus":""}},"objectType":"Заробітна плата отримана за основним місцем роботи","sizeIncome":"46416","incomeSource":"j","source_citizen":"Юридична особа, зареєстрована в Україні","otherObjectType":"","source_ua_lastname":"","source_eng_fullname":"","source_ua_firstname":"","source_ukr_fullname":"","source_ua_middlename":"","source_ua_company_name":"Дніпропетровський апеляційний господарський суд","source_eng_company_name":"","source_ukr_company_name":"","source_ua_sameRegLivingAddress":""},"1476876468634":{"person":"1475742805177","rights":{"1475742805177":{"citizen":"","ua_city":"","ua_street":"[Конфіденційна інформація]","ua_lastname":"","ua_postCode":"","eng_fullname":"","eng_lastname":"","eng_postCode":"","rightBelongs":"1475742805177","ua_firstname":"","ukr_fullname":"","ukr_lastname":"","eng_firstname":"","ownershipType":"Власність","ua_middlename":"","ua_streetType":"[Конфіденційна інформація]","ukr_firstname":"","eng_middlename":"","otherOwnership":"","ukr_middlename":"","rights_cityPath":"","ua_company_name":"","eng_company_name":"","ukr_company_name":"","percent-ownership":"","ua_street_extendedstatus":"","ua_houseNum_extendedstatus":"","ua_postCode_extendedstatus":"","eng_postCode_extendedstatus":"","ua_middlename_extendedstatus":"","eng_middlename_extendedstatus":"","ukr_middlename_extendedstatus":"","ua_housePartNum_extendedstatus":"","ua_apartmentsNum_extendedstatus":""}},"objectType":"Проценти","sizeIncome":"182","incomeSource":"j","source_citizen":"Юридична особа, зареєстрована в Україні","otherObjectType":"","source_ua_lastname":"","source_eng_fullname":"","source_ua_firstname":"","source_ukr_fullname":"","source_ua_middlename":"","source_ua_company_name":"ПАТ \"Банк Кредит Дніпро\" ","source_eng_company_name":"","source_ukr_company_name":"","source_ua_sameRegLivingAddress":""},"1476876518682":{"person":"1475750608825","rights":{"1475750608825":{"citizen":"","ua_city":"","ua_street":"[Конфіденційна інформація]","ua_lastname":"","ua_postCode":"","eng_fullname":"","eng_lastname":"","eng_postCode":"","rightBelongs":"1475750608825","ua_firstname":"","ukr_fullname":"","ukr_lastname":"","eng_firstname":"","ownershipType":"Власність","ua_middlename":"","ua_streetType":"[Конфіденційна інформація]","ukr_firstname":"","eng_middlename":"","otherOwnership":"","ukr_middlename":"","rights_cityPath":"","ua_company_name":"","eng_company_name":"","ukr_company_name":"","percent-ownership":"","ua_street_extendedstatus":"","ua_houseNum_extendedstatus":"","ua_postCode_extendedstatus":"","eng_postCode_extendedstatus":"","ua_middlename_extendedstatus":"","eng_middlename_extendedstatus":"","ukr_middlename_extendedstatus":"","ua_housePartNum_extendedstatus":"","ua_apartmentsNum_extendedstatus":""}},"objectType":"Заробітна плата отримана за основним місцем роботи","sizeIncome":"31081","incomeSource":"j","source_citizen":"Юридична особа, зареєстрована в Україні","otherObjectType":"","source_ua_lastname":"","source_eng_fullname":"","source_ua_firstname":"","source_ukr_fullname":"","source_ua_middlename":"","source_ua_company_name":"Дніпропетровський Національний університет залізничного транспорту ім. Академіка В.Лазаряна","source_eng_company_name":"","source_ukr_company_name":"","source_ua_sameRegLivingAddress":""},"1477459762892":{"person":"1475750608825","rights":{"1475750608825":{"citizen":"","ua_city":"","ua_street":"[Конфіденційна інформація]","ua_lastname":"","ua_postCode":"","eng_fullname":"","eng_lastname":"","eng_postCode":"","rightBelongs":"1475750608825","ua_firstname":"","ukr_fullname":"","ukr_lastname":"","eng_firstname":"","ownershipType":"Власність","ua_middlename":"","ua_streetType":"[Конфіденційна інформація]","ukr_firstname":"","eng_middlename":"","otherOwnership":"","ukr_middlename":"","rights_cityPath":"","ua_company_name":"","eng_company_name":"","ukr_company_name":"","percent-ownership":"","ua_street_extendedstatus":"","ua_houseNum_extendedstatus":"","ua_postCode_extendedstatus":"","eng_postCode_extendedstatus":"","ua_middlename_extendedstatus":"","eng_middlename_extendedstatus":"","ukr_middlename_extendedstatus":"","ua_housePartNum_extendedstatus":"","ua_apartmentsNum_extendedstatus":""}},"objectType":"Інше","sizeIncome":"3501","incomeSource":"j","source_citizen":"Юридична особа, зареєстрована в Україні","otherObjectType":"кредитний ліміт","source_ua_lastname":"","source_eng_fullname":"","source_ua_firstname":"","source_ukr_fullname":"","source_ua_middlename":"","source_ua_company_name":"ПАТ КБ\"Приватбанк\"","source_eng_company_name":"","source_ukr_company_name":"","source_ua_sameRegLivingAddress":""}},"step_12":{"1476879083851":{"person":"1","rights":{"1":{"citizen":"","ua_city":"","ua_street":"[Конфіденційна інформація]","ua_lastname":"","ua_postCode":"","eng_fullname":"","eng_lastname":"","eng_postCode":"","rightBelongs":"1","ua_firstname":"","ukr_fullname":"","ukr_lastname":"","eng_firstname":"","ownershipType":"Власність","ua_middlename":"","ua_streetType":"[Конфіденційна інформація]","ukr_firstname":"","eng_middlename":"","otherOwnership":"","ukr_middlename":"","rights_cityPath":"","ua_company_name":"","eng_company_name":"","ukr_company_name":"","percent-ownership":"","ua_street_extendedstatus":"","ua_houseNum_extendedstatus":"","ua_postCode_extendedstatus":"","eng_postCode_extendedstatus":"","ua_middlename_extendedstatus":"","eng_middlename_extendedstatus":"","ukr_middlename_extendedstatus":"","ua_housePartNum_extendedstatus":"","ua_apartmentsNum_extendedstatus":""}},"objectType":"Кошти, розміщені на банківських рахунках","sizeAssets":"68946","organization":"j","assetsCurrency":"UAH","otherObjectType":"","organization_type":"Юридична особа, зареєстрована в Україні","debtor_ua_lastname":"","debtor_eng_lastname":"","debtor_ua_firstname":"","debtor_ukr_lastname":"","debtor_eng_firstname":"","debtor_ua_middlename":"","debtor_ukr_firstname":"","debtor_eng_middlename":"","debtor_ukr_middlename":"","organization_ua_company_name":"ПАТ \"Банк Кредит Дніпро\"","organization_eng_company_name":"","organization_ukr_company_name":"","debtor_ua_sameRegLivingAddress":"","debtor_eng_sameRegLivingAddress":""},"1477041286773":{"person":"1","rights":{"1":{"citizen":"","ua_city":"","ua_street":"[Конфіденційна інформація]","ua_lastname":"","ua_postCode":"","eng_fullname":"","eng_lastname":"","eng_postCode":"","rightBelongs":"1","ua_firstname":"","ukr_fullname":"","ukr_lastname":"","eng_firstname":"","ownershipType":"Власність","ua_middlename":"","ua_streetType":"[Конфіденційна інформація]","ukr_firstname":"","eng_middlename":"","otherOwnership":"","ukr_middlename":"","rights_cityPath":"","ua_company_name":"","eng_company_name":"","ukr_company_name":"","percent-ownership":"","ua_street_extendedstatus":"","ua_houseNum_extendedstatus":"","ua_postCode_extendedstatus":"","eng_postCode_extendedstatus":"","ua_middlename_extendedstatus":"","eng_middlename_extendedstatus":"","ukr_middlename_extendedstatus":"","ua_housePartNum_extendedstatus":"","ua_apartmentsNum_extendedstatus":""}},"objectType":"Кошти, розміщені на банківських рахунках","sizeAssets":"1246","organization":"j","assetsCurrency":"USD","otherObjectType":"","organization_type":"Юридична особа, зареєстрована в Україні","debtor_ua_lastname":"","debtor_eng_lastname":"","debtor_ua_firstname":"","debtor_ukr_lastname":"","debtor_eng_firstname":"","debtor_ua_middlename":"","debtor_ukr_firstname":"","debtor_eng_middlename":"","debtor_ukr_middlename":"","organization_ua_company_name":"ПАТ \"Райффайзен Банк Аваль\"","organization_eng_company_name":"","organization_ukr_company_name":"","debtor_ua_sameRegLivingAddress":"","debtor_eng_sameRegLivingAddress":""}},"step_13":{"1477058111720":{"person":"1475750608825","currency":"UAH","guarantor":[],"dateOrigin":"27.07.2015","objectType":"Зобов'язання за договорами страхування","margin-emitent":"1475750608825","sizeObligation":"120","emitent_citizen":"","otherObjectType":"","guarantor_exist_":false,"guarantor_realty":[],"ownerThirdPerson":"","emitent_ua_lastname":"","emitent_eng_fullname":"","emitent_ua_firstname":"","emitent_ukr_fullname":"","emitent_ua_middlename":"","ownerThirdPersonThing":"","emitent_ua_company_name":"","guarantor_realty_exist_":false,"emitent_eng_company_name":"","emitent_ukr_company_name":"","emitent_ua_sameRegLivingAddress":""}},"step_14":[],"step_15":[],"step_16":[],"id":"e9981cc8-4bf2-4ed1-baed-5d64009f1159"}}],"declarations":[{"income":{"5":{"family_comment":"","value":"228746","family":"81180","comment":""},"6":{"family_comment":"","value":"214149","family":"77497","comment":""},"7":{"value":"","comment_hidden":false,"family_comment":"","source_name":"","family":"","comment":"","source_name_hidden":false},"8":{"family_comment":"","value":"","family_hidden":false,"comment":"","family":""},"9":{"value":"14597","family_comment":"","value_unclear":false,"family_unclear":false,"family":"182","comment":""},"10":{"family_comment":"","value":"","family":"","comment":""},"11":{"family_comment":"","value":"","family":"","comment":""},"12":{"family_comment":"","value":"","family":"","comment":""},"13":{"family_comment":"","value":"","family":"","comment":""},"14":{"family_comment":"","value":"","family":"","comment":""},"15":{"family_comment":"","value":"","family":"","comment":""},"16":{"family_comment":"","value":"","family":"","comment":""},"17":{"family_comment":"","value":"","family":"","comment":""},"18":{"family_comment":"","value":"","family":"","comment":""},"19":{"family_comment":"","value":"","family":"","comment":""},"20":{"value":"","value_unclear":false,"family_hidden":false,"family_comment":"","family":"3501","comment":""}},"vehicle":{"35":[{"brand_info":"1548, 454.0","sum_rent_comment":"","year":"2012","brand_info_hidden":false,"brand_info_unclear":false,"year_unclear":false,"sum_rent":"","sum":"","brand":"Toyota Corolla","sum_comment":"","sum_comment_unclear":false,"brand_hidden":false,"brand_unclear":false}],"40":[{"brand_info":"1.5","sum_rent_comment":"","brand":"Jac S4","sum_comment":"","year":"2015","brand_info_unclear":false,"sum":"","sum_rent":""}]},"id":"vulyk_109_40","banks":{"45":[{"sum_foreign_comment":"","sum_unclear":false,"sum_units":"UAH","sum_comment":"Райффайзен Банк Аваль","sum_foreign_units":"UAH","sum_comment_hidden":false,"sum_units_hidden":false,"sum":"33400","sum_foreign":""},{"sum_foreign_comment":"","sum_units":"UAH","sum_comment":"Кредит Дніпро","sum_comment_unclear":false,"sum":"68946","sum_foreign":""}]},"declaration":{"additional_info_text":"","notfull_lostpages":"","date":"2016-03-31T00:00:00","notfull":"","additional_info":"","url":"http://static.declarations.com.ua/declarations/chosen_ones/judges_batch/2497_ievstyhneieva_nadiia_mykhailivna_2015.pdf"},"liabilities":{"54":{"sum_foreign_comment":"","sum":"","sum_comment":"","sum_hidden":false,"sum_comment_hidden":false,"sum_unclear":false,"sum_foreign":""},"55":{"sum_foreign_comment":"","sum":"","sum_comment":"","sum_comment_unclear":false,"sum_foreign":""},"56":{"sum_foreign_comment":"","sum":"","sum_comment":"","sum_foreign":""},"57":{"sum_foreign_comment":"","sum_comment_hidden":false,"sum":"","sum_comment":"","sum_foreign":""},"58":{"sum_foreign_comment":"","sum_comment_hidden":false,"sum":"","sum_comment":"","sum_foreign":""},"59":{"sum_foreign_comment":"","sum":"","sum_comment":"","sum_foreign":""},"60":{"sum_foreign_comment":"","sum":"120","sum_comment":"","sum_foreign":""},"61":{"sum_foreign_comment":"","sum":"","sum_comment":"","sum_foreign":""},"62":{"sum_foreign_comment":"","sum":"","sum_comment":"","sum_foreign":""},"63":{"sum_foreign_comment":"","sum":"","sum_comment":"","sum_foreign":""},"64":{"sum_foreign_comment":"","sum":"","sum_comment":"","sum_foreign":""}},"ft_src":"120\nДніпропетровська область\nсуддя господарського суду дніпропетровської області\nДніпропетровська область\nГосподарський місцевий суд\nНадія\nГерун Т. О\nДитина\nГерун Є. О\nЗять\nІнше\nГерун М\nМихайлівна\nЄвстигнеєва Надія Михайлівна\nНадія Михайлівна Євстигнеєва\nНадія Євстигнеєва\nЄвстигнеєва Надія Михайлівна\nЄвстигнеєва Надія Михайлівна\nЄвстигнеєва\n1548, 454.0\nToyota Corolla\n2012\n1.5\n2015\nJac S4\n14.72\n162.8\nРайффайзен Банк Аваль\n33400\nКредит Дніпро\n68946\n2015\n1548, 454.0\nToyota Corolla\n2012\n1.5\n2015\nJac S4\n2015\nЄвстигнеєва Надія Михайлівна\nНадія Михайлівна Євстигнеєва\nНадія Євстигнеєва\nЄвстигнеєва Надія Михайлівна\nНадія\nДитина\nГерун Т. О\nІнше\nГерун Є. О\nЗять\nГерун М\nЄвстигнеєва Надія Михайлівна\nМихайлівна\nГосподарський місцевий суд\nДніпропетровська область\nсуддя господарського суду дніпропетровської області\nЄвстигнеєва\nДніпропетровська область\n120\n214149\n77497\n3501\n228746\n81180\n14597\n182\n14.72\n162.8\n33400\nРайффайзен Банк Аваль\n68946\nКредит Дніпро\n120\n77497\n214149\n81180\n228746\n182\n14597\n3501\nДитина\nГерун Т. О\nІнше\nГерун Є. О\nЗять\nГерун М\nМихайлівна\nЄвстигнеєва\nНадія\nЄвстигнеєва Надія Михайлівна\nНадія Михайлівна Євстигнеєва\nНадія Євстигнеєва\nЄвстигнеєва Надія Михайлівна\nДніпропетровська область\nДніпропетровська область\nГосподарський місцевий суд\nсуддя господарського суду дніпропетровської області\nЄвстигнеєва Надія Михайлівна\n2012\nToyota Corolla\n1548, 454.0\n2015\n1.5\nJac S4\n3501\n81180\n228746\n14597\n182\n77497\n214149\n14.72\n162.8\nРайффайзен Банк Аваль\n33400\nКредит Дніпро\n68946\n2015","general":{"name_hidden":false,"name":"Надія","inn":"","family":[{"inn":"","relations":"Дитина","relations_hidden":false,"inn_hidden":false,"relations_other":"","name_hidden":false,"family_name":"Герун Т. О","name_unclear":false},{"inn":"","relations":"Інше","relations_other":"Зять","inn_hidden":false,"family_name":"Герун Є. О","name_hidden":false,"name_unclear":false},{"inn":"","relations":"","relations_other":"","inn_hidden":false,"family_name":"Герун М","name_hidden":false,"name_unclear":false}],"patronymic":"Михайлівна","inn_hidden":false,"family_raw":"","inn_unclear":false,"post":{"region_unclear":false,"region":"Дніпропетровська область","post":"суддя господарського суду дніпропетровської області","region_hidden":false,"office":"Господарський місцевий суд","office_hidden":false,"office_unclear":false},"full_name":"Євстигнеєва Надія Михайлівна","addresses":[{"place_district":"","place_city_hidden":false,"place_city":"","place_city_type_hidden":false,"place_district_hidden":false,"place_city_type":"","place_address_hidden":false,"place_address":"","place_hidden":false,"place":"Дніпропетровська область"}],"last_name":"Євстигнеєва","full_name_suggest":{"output":"Євстигнеєва Надія Михайлівна","input":["Євстигнеєва Надія Михайлівна","Надія Михайлівна Євстигнеєва","Надія Євстигнеєва"]}},"source":"VULYK","estate":{"25":[{"space_unclear":false,"costs":"","costs_comment":"","address_hidden":false,"region_hidden":false,"space_comment":"","space_hidden":false,"space":"162.8","address":"","region":"","costs_rent_comment":"","space_units":"м²","space_units_hidden":false,"costs_rent":""}],"31":[{"space_hidden":false,"costs_property_comment":"","address_hidden":true,"region_hidden":false,"space_comment":"","space":"14.72","address":"","region":"","costs_property":"","costs_rent_comment":"","space_units":"м²","space_units_hidden":false,"costs_rent":""}]},"intro":{"declaration_year":"2015","isnotdeclaration":""}},{"income":{"5":{"value":"225714","family_unclear":false,"family_hidden":false,"family_comment":"","family":"","comment":""},"6":{"family_comment":"","value":"217700","family_hidden":false,"comment":"","family":""},"7":{"family_comment":"","value":"","source_name":"","family":"","comment":""},"8":{"family_comment":"","value":"","family":"","comment":""},"9":{"value":"8014","comment_unclear":false,"family_hidden":false,"family_comment":"","family":"","comment":""},"10":{"family_comment":"","value":"","family":"","comment":""},"11":{"family_comment":"","value":"","family":"","comment":""},"12":{"family_comment":"","value":"","family":"","comment":""},"13":{"family_comment":"","value":"","family":"","comment":""},"14":{"family_comment":"","value":"","family":"","comment":""},"15":{"family_comment":"","value":"","value_unclear":false,"family":"","comment":""},"16":{"family_comment":"","value":"","family":"","comment":""},"17":{"family_comment":"","value":"","family":"","comment":""},"18":{"family_comment":"","value":"","family":"","comment":""},"19":{"family_comment":"","value":"","family":"","comment":""},"20":{"value":"","comment_unclear":false,"comment_hidden":false,"family_hidden":false,"value_hidden":false,"family_comment":"","value_unclear":false,"family":"","comment":"","family_comment_hidden":false}},"vehicle":{"35":[{"brand_info":"1598, 4540","sum_rent_comment":"","brand":"Toyota Corolla","sum_comment":"","year":"2012","brand_info_hidden":false,"sum":"","sum_rent":""}]},"id":"vulyk_41_6","banks":{"45":[{"sum_foreign_comment":"","sum_units":"UAH","sum_comment":"","sum_foreign_unclear":false,"sum_foreign_units":"UAH","sum_hidden":false,"sum_comment_hidden":false,"sum":"19652","sum_foreign":""},{"sum_foreign_comment":"","sum_units":"UAH","sum_comment":"","sum_foreign_unclear":false,"sum_foreign_units":"","sum":"53071","sum_foreign":""}],"46":[{"sum_foreign_comment":"","sum_units":"UAH","sum_comment":"","sum_foreign_units":"UAH","sum_comment_hidden":false,"sum_unclear":false,"sum":"","sum_foreign":""},{"sum_foreign_comment":"","sum_units":"","sum_comment":"","sum_foreign_units":"","sum":"","sum_unclear":false,"sum_foreign":""}],"47":[{"sum_foreign_comment":"","sum_units":"UAH","sum_comment":"","sum_foreign_units":"UAH","sum":"","sum_foreign":""},{"sum_foreign_comment":"","sum_units":"","sum_comment":"","sum_foreign_units":"","sum":"","sum_foreign":""}],"48":[{"sum_foreign_comment":"","sum_units":"UAH","sum_comment":"","sum_foreign_units":"UAH","sum":"","sum_foreign":""}],"49":[{"sum_foreign_comment":"","sum_units":"UAH","sum_comment":"","sum_foreign_units":"UAH","sum":"","sum_foreign":""}],"50":[{"sum_foreign_comment":"","sum_units":"UAH","sum_comment":"","sum_foreign_units":"UAH","sum":"","sum_foreign":""}],"51":[{"sum_foreign_comment":"","sum_units":"UAH","sum_comment":"","sum_hidden":false,"sum_foreign_units":"UAH","sum_comment_hidden":false,"sum_unclear":false,"sum":"","sum_foreign":""},{"sum_foreign_comment":"","sum_units":"","sum_comment":"","sum_foreign_units":"","sum":"","sum_foreign":""}],"52":[{"sum_foreign_comment":"","sum_units":"UAH","sum_comment":"","sum_foreign_units":"UAH","sum_comment_hidden":false,"sum_unclear":false,"sum":"","sum_foreign":""}],"53":[{"sum_foreign_comment":"","sum_units":"UAH","sum_comment":"","sum_foreign_units":"UAH","sum_comment_hidden":false,"sum":"","sum_foreign":""},{"sum_foreign_comment":"","sum_units":"","sum_comment":"","sum_foreign_units":"","sum":"","sum_foreign":""},{"sum_foreign_comment":"","sum_units":"","sum_comment":"","sum_foreign_units":"","sum":"","sum_foreign":""}]},"declaration":{"date":"2015-03-31T00:00:00","additional_info_text":"","additional_info":"","url":"http://static.declarations.com.ua/declarations/chosen_ones/mega_batch/yevstyhneieva_nadiia_mykhailivna.pdf"},"liabilities":{"54":{"sum_foreign_comment":"","sum_comment_hidden":false,"sum":"11718","sum_comment":"","sum_foreign":""},"55":{"sum_foreign_comment":"","sum":"","sum_comment":"","sum_foreign":""},"56":{"sum_foreign_comment":"","sum":"11716","sum_hidden":false,"sum_comment":"","sum_foreign":""},"57":{"sum_foreign_comment":"","sum":"7693","sum_comment":"","sum_comment_hidden":false,"sum_unclear":false,"sum_foreign":""},"58":{"sum_foreign_comment":"","sum_comment_hidden":false,"sum":"","sum_comment":"","sum_foreign":""},"59":{"sum_foreign_comment":"","sum":"","sum_comment":"","sum_foreign":""},"60":{"sum_foreign_comment":"","sum_comment_hidden":false,"sum":"","sum_comment":"","sum_foreign":""},"61":{"sum_foreign_comment":"","sum":"","sum_comment":"","sum_foreign":""},"62":{"sum_foreign_comment":"","sum":"","sum_comment":"","sum_foreign":""},"63":{"sum_foreign_comment":"","sum":"","sum_comment":"","sum_comment_hidden":false,"sum_unclear":false,"sum_foreign":""},"64":{"sum_foreign_comment":"","sum_comment_hidden":false,"sum":"","sum_comment":"","sum_foreign":""}},"ft_src":"7693\n11718\n11716\nсуддя господарського суду дніпропетровської області\nДніпропетровська область\nГосподарський місцевий суд\nНадія\nГерун Т. О\nДитина\nМихайлівна\nЄвстигнеєва Надія Михайлівна\nНадія Михайлівна Євстигнеєва\nНадія Євстигнеєва\nЄвстигнеєва Надія Михайлівна\nЄвстигнеєва\nЄвстигнеєва Надія Михайлівна\n1598, 4540\n2012\nToyota Corolla\n19652\n53071\n2014\nToyota Corolla\n1598, 4540\n2012\n19652\n53071\n162.8\nДитина\nГерун Т. О\nЄвстигнеєва Надія Михайлівна\nНадія Михайлівна Євстигнеєва\nНадія Євстигнеєва\nЄвстигнеєва Надія Михайлівна\nЄвстигнеєва Надія Михайлівна\nНадія\nМихайлівна\nГосподарський місцевий суд\nсуддя господарського суду дніпропетровської області\nДніпропетровська область\nЄвстигнеєва\n7693\n11716\n11718\n217700\n225714\n8014\n2014\n7693\n11716\n11718\n162.8\nГерун Т. О\nДитина\nМихайлівна\nЄвстигнеєва\nНадія\nЄвстигнеєва Надія Михайлівна\nНадія Михайлівна Євстигнеєва\nНадія Євстигнеєва\nЄвстигнеєва Надія Михайлівна\nДніпропетровська область\nсуддя господарського суду дніпропетровської області\nГосподарський місцевий суд\nЄвстигнеєва Надія Михайлівна\n217700\n225714\n8014\nToyota Corolla\n1598, 4540\n2012\n225714\n8014\n217700\n162.8\n19652\n53071\n2014","general":{"inn":"","name":"Надія","family":[{"inn":"","relations":"Дитина","relations_hidden":false,"inn_hidden":true,"family_name":"Герун Т. О","name_hidden":false,"name_unclear":false}],"patronymic":"Михайлівна","inn_hidden":true,"family_raw":"","last_name":"Євстигнеєва","post":{"post_unclear":false,"post":"суддя господарського суду дніпропетровської області","post_hidden":false,"region":"Дніпропетровська область","region_hidden":false,"office":"Господарський місцевий суд","office_hidden":false},"last_name_unclear":false,"full_name":"Євстигнеєва Надія Михайлівна","addresses":[{"place_district":"","place_city_hidden":true,"place_city":"","place_city_type_hidden":false,"place_district_hidden":true,"place_city_type":"","place_address_hidden":false,"place_address":"","place_hidden":true,"place":""}],"patronymic_hidden":false,"full_name_suggest":{"output":"Євстигнеєва Надія Михайлівна","input":["Євстигнеєва Надія Михайлівна","Надія Михайлівна Євстигнеєва","Надія Євстигнеєва"]},"name_unclear":false},"source":"VULYK","estate":{"23":[{"region_unclear":false,"space_unclear":false,"costs":"","costs_comment":"","address_hidden":false,"region_hidden":false,"space_comment":"","space":"","address":"","costs_comment_unclear":false,"region":"","space_units_unclear":false,"space_comment_hidden":false,"space_units":"м²","costs_rent":"","costs_rent_comment":""},{"costs_rent":"","space_unclear":false,"region":"","costs":"","costs_rent_comment":"","costs_comment":"","space_comment":"","space_units":"","space":"","address":""},{"costs_rent":"","region":"","costs":"","costs_rent_comment":"","costs_comment":"","space_comment":"","space_units":"","space":"","address":""}],"25":[{"region_unclear":false,"space_hidden":false,"costs":"","costs_comment":"","address_hidden":false,"region_hidden":true,"space_comment":"","space_unclear":false,"space":"162.8","address":"","costs_comment_unclear":false,"region":"","costs_rent_comment":"","costs_unclear":false,"space_units":"м²","costs_rent":""}]},"intro":{"declaration_year":"2014"}},{"income":{"5":{"family_comment":"","value":"213973","family":"26172","comment":""},"6":{"family_comment":"","value":"193690","family":"26172","comment":""},"7":{"family_comment":"","value":"0","source_name":"0","family":"0","comment":""},"8":{"family_comment":"","value":"0","family":"0","comment":""},"9":{"family_comment":"","value":"2359","family":"0","comment":""},"10":{"family_comment":"","value":"11470","family":"0","comment":""},"11":{"family_comment":"","value":"0","family":"0","comment":""},"12":{"family_comment":"","value":"0","family":"0","comment":""},"13":{"family_comment":"","value":"0","family":"0","comment":""},"14":{"family_comment":"","value":"0","family":"0","comment":""},"15":{"family_comment":"","value":"6454","family":"0","comment":""},"16":{"family_comment":"","value":"0","family":"0","comment":""},"17":{"family_comment":"","value":"0","family":"0","comment":""},"18":{"family_comment":"","value":"0","family":"0","comment":""},"19":{"family_comment":"","value":"0","family":"0","comment":""},"20":{"family_comment":"","value":"0","family":"0","comment":""},"21":[{"cur":"0","country":"0","uah_equal":"0","country_comment":""},{"cur":"0","country":"0","uah_equal":"0","country_comment":""},{"cur":"0","country":"0","uah_equal":"0","country_comment":""},{"cur":"0","country":"0","uah_equal":"0","country_comment":""},{"cur":"0","country":"0","uah_equal":"0","country_comment":""}],"22":[{"cur":"0","country":"0","uah_equal":"0","country_comment":""},{"cur":"0","country":"0","uah_equal":"0","country_comment":""},{"cur":"0","country":"0","uah_equal":"0","country_comment":""},{"cur":"0","country":"0","uah_equal":"0","country_comment":""},{"cur":"0","country":"0","uah_equal":"0","country_comment":""}]},"vehicle":{"35":[{"brand_info":"","sum_rent_comment":"","brand":"Toyota,Corolla","sum_comment":"","year":"2012","brand_hidden":false,"sum":"","sum_rent":""}]},"id":"177","banks":{"45":[{"sum_foreign_comment":"","sum_units":"UAH","sum_comment":"","sum_foreign_units":"","sum":"36640","sum_foreign":""},{"sum_foreign_comment":"","sum_units":"USD","sum_comment":"","sum_foreign_units":"","sum":"","sum_foreign":""},{"sum_foreign_comment":"","sum_units":"EUR","sum_comment":"","sum_foreign_units":"","sum":"","sum_foreign":""}],"46":[{"sum_foreign_comment":"","sum_units":"UAH","sum_comment":"","sum_foreign_units":"","sum":"30993","sum_foreign":""},{"sum_foreign_comment":"","sum_units":"USD","sum_comment":"","sum_foreign_units":"","sum":"","sum_foreign":""},{"sum_foreign_comment":"","sum_units":"EUR","sum_comment":"","sum_foreign_units":"","sum":"","sum_foreign":""}],"47":[{"sum_foreign_comment":"","sum_units":"","sum_comment":"","sum_foreign_units":"","sum":"","sum_foreign":""}],"48":[{"sum_foreign_comment":"","sum_units":"","sum_comment":"","sum_foreign_units":"","sum":"","sum_foreign":""}],"49":[{"sum_foreign_comment":"","sum_units":"","sum_comment":"","sum_foreign_units":"","sum":"","sum_foreign":""}],"50":[{"sum_foreign_comment":"","sum_units":"","sum_comment":"","sum_foreign_units":"","sum":"","sum_foreign":""}],"51":[{"sum_foreign_comment":"","sum_units":"UAH","sum_comment":"","sum_foreign_units":"","sum":"","sum_foreign":""},{"sum_foreign_comment":"","sum_units":"USD","sum_comment":"","sum_foreign_units":"","sum":"","sum_foreign":""},{"sum_foreign_comment":"","sum_units":"EUR","sum_comment":"","sum_foreign_units":"","sum":"","sum_foreign":""}],"52":[{"sum_foreign_comment":"","sum_units":"","sum_comment":"","sum_foreign_units":"","sum":"","sum_foreign":""}],"53":[{"sum_foreign_comment":"","sum_units":"","sum_comment":"","sum_foreign_units":"","sum":"","sum_foreign":""}]},"declaration":{"needs_scancopy_check":false,"additional_info_text":"в этих пунктах я вносила только цифры, а доп.информация (в каких банках) написала здесь ниже.;Була інформація по пунктам;;45. Сума коштів на рахунках у банках усього; 9961 ПАТ РАЙФАЙЗЕН БАНК АВАЛЬ;26679  ПАТ БАНК КРЕДИТ ДНІПРО;;46. вкладених у звітному році Усього;7993   ПАТ РАЙФАЙЗЕН БАНК АВАЛЬ;23000  ПАТ БАНК КРЕДИТ ДНІПРО;;54. Добровільне страхування Усього;9218 Дніпропетровська філія СК «АХА»;;57. Погашення основної суми позики. Усього. ;50000 ПАТ КредіАгріколь, філія у Дніпропетровській обл;","notfull_lostpages":"","notfull":"FALSE","additional_info":"TRUE","url":"http://static.declarations.com.ua/declarations/sudy/hospodarski_mistsevi_sudy/dnipropetrovska_oblast/evsegneeva.pdf"},"liabilities":{"54":{"sum_foreign_comment":"","sum":"9218","sum_comment":"","sum_foreign":""},"55":{"sum_foreign_comment":"","sum_units":"","sum_comment":"","sum_foreign_units":"","sum":"","sum_foreign":""},"56":{"sum_foreign_comment":"","sum":"12269","sum_comment":"","sum_foreign":""},"57":{"sum_foreign_comment":"","sum":"50000","sum_comment":"","sum_foreign":""},"58":{"sum_foreign_comment":"","sum":"","sum_comment":"","sum_foreign":""},"59":{"sum_foreign_comment":"","sum":"","sum_comment":"","sum_foreign":""},"60":{"sum_foreign_comment":"","sum":"","sum_comment":"","sum_foreign":""},"61":{"sum_foreign_comment":"","sum_units":"","sum_comment":"","sum_foreign_units":"","sum":"","sum_foreign":""},"62":{"sum_foreign_comment":"","sum":"","sum_comment":"","sum_foreign":""},"63":{"sum_foreign_comment":"","sum_units":"","sum_comment":"","sum":"","sum_foreign":""},"64":{"sum_foreign_comment":"","sum_units":"","sum_comment":"","sum":"","sum_foreign":""}},"estate":{"23":[{"costs_rent":"","location_raw":"","region":"","costs":"","costs_rent_comment":"","costs_comment":"","space_comment":"","space_units":"","space":"","address":""},{"costs_rent":"","location_raw":"","region":"","costs":"","costs_rent_comment":"","costs_comment":"","space_comment":"","space_units":"","space":"","address":""},{"costs_rent":"","location_raw":"","region":"","costs":"","costs_rent_comment":"","costs_comment":"","space_comment":"","space_units":"","space":"","address":""}],"25":[{"costs_rent":"","location_raw":"приховано","region":"","costs":"","costs_rent_comment":"","costs_comment":"","space_comment":"","space_units":"","space":"162,8","address":""}]},"general":{"name_hidden":false,"name":"Надія","patronymic_unclear":false,"last_name_hidden":false,"addresses_raw":"приховано","post_raw":"Суддя господарського суду Дніпропетровської області","patronymic":"Михайлівна","inn":"","family_raw":"Донька, Євстигнеєва Т.О.","last_name":"Євстигнеєва","post":{"office":"Господарський місцевий суд","region":"Дніпропетровська область","post":"Суддя"},"addresses_raw_hidden":true,"last_name_unclear":false,"full_name":"Євстигнеєва Надія Михайлівна","patronymic_hidden":false,"full_name_suggest":{"output":"Євстигнеєва Надія Михайлівна","input":["Євстигнеєва Надія Михайлівна","Надія Михайлівна Євстигнеєва","Надія Євстигнеєва"]},"name_unclear":false},"ft_src":"50000\n9218\n12269\nFALSE\nв этих пунктах я вносила только цифры, а доп.информация (в каких банках) написала здесь ниже.;Була інформація по пунктам;;45. Сума коштів на рахунках у банках усього; 9961 ПАТ РАЙФАЙЗЕН БАНК АВАЛЬ;26679  ПАТ БАНК КРЕДИТ ДНІПРО;;46. вкладених у звітному році Усього;7993   ПАТ РАЙФАЙЗЕН БАНК АВАЛЬ;23000  ПАТ БАНК КРЕДИТ ДНІПРО;;54. Добровільне страхування Усього;9218 Дніпропетровська філія СК «АХА»;;57. Погашення основної суми позики. Усього. ;50000 ПАТ КредіАгріколь, філія у Дніпропетровській обл;\nTRUE\n6454\n11470\n26172\n213973\n2359\n26172\n193690\nToyota,Corolla\n2012\nToyota,Corolla\n2012\n162,8\n30993\n36640\nTRUE\nв этих пунктах я вносила только цифры, а доп.информация (в каких банках) написала здесь ниже.;Була інформація по пунктам;;45. Сума коштів на рахунках у банках усього; 9961 ПАТ РАЙФАЙЗЕН БАНК АВАЛЬ;26679  ПАТ БАНК КРЕДИТ ДНІПРО;;46. вкладених у звітному році Усього;7993   ПАТ РАЙФАЙЗЕН БАНК АВАЛЬ;23000  ПАТ БАНК КРЕДИТ ДНІПРО;;54. Добровільне страхування Усього;9218 Дніпропетровська філія СК «АХА»;;57. Погашення основної суми позики. Усього. ;50000 ПАТ КредіАгріколь, філія у Дніпропетровській обл;\nFALSE\nFALSE\n2013\n26172\n193690\n6454\n11470\n26172\n213973\n2359\nToyota,Corolla\n2012\nв этих пунктах я вносила только цифры, а доп.информация (в каких банках) написала здесь ниже.;Була інформація по пунктам;;45. Сума коштів на рахунках у банках усього; 9961 ПАТ РАЙФАЙЗЕН БАНК АВАЛЬ;26679  ПАТ БАНК КРЕДИТ ДНІПРО;;46. вкладених у звітному році Усього;7993   ПАТ РАЙФАЙЗЕН БАНК АВАЛЬ;23000  ПАТ БАНК КРЕДИТ ДНІПРО;;54. Добровільне страхування Усього;9218 Дніпропетровська філія СК «АХА»;;57. Погашення основної суми позики. Усього. ;50000 ПАТ КредіАгріколь, філія у Дніпропетровській обл;\nFALSE\nTRUE\n162,8\nСуддя господарського суду Дніпропетровської області\nДонька, Євстигнеєва Т.О.\nЄвстигнеєва\nЄвстигнеєва Надія Михайлівна\nНадія Михайлівна Євстигнеєва\nНадія Євстигнеєва\nЄвстигнеєва Надія Михайлівна\nНадія\nЄвстигнеєва Надія Михайлівна\nГосподарський місцевий суд\nСуддя\nДніпропетровська область\nМихайлівна\n50000\n12269\n9218\n193690\n26172\n6454\n213973\n26172\n11470\n2359\n36640\n30993\n2013\nFALSE\n50000\n12269\n9218\nЄвстигнеєва\nМихайлівна\nДонька, Євстигнеєва Т.О.\nЄвстигнеєва Надія Михайлівна\nНадія Михайлівна Євстигнеєва\nНадія Євстигнеєва\nЄвстигнеєва Надія Михайлівна\nНадія\nСуддя господарського суду Дніпропетровської області\nСуддя\nДніпропетровська область\nГосподарський місцевий суд\nЄвстигнеєва Надія Михайлівна\n162,8\nСуддя\nДніпропетровська область\nГосподарський місцевий суд\nСуддя господарського суду Дніпропетровської області\nНадія\nМихайлівна\nДонька, Євстигнеєва Т.О.\nЄвстигнеєва\nЄвстигнеєва Надія Михайлівна\nЄвстигнеєва Надія Михайлівна\nНадія Михайлівна Євстигнеєва\nНадія Євстигнеєва\nЄвстигнеєва Надія Михайлівна\n30993\n36640\nFALSE\n2013","intro":{"declaration_year":"2013","isnotdeclaration":"FALSE"}}],"declarationsLength":3,"analytics":[{"y":2015,"b":102346,"i":228746,"c":1,"k":162.8,"ka":1,"fi":81180,"ff":14.72,"ffa":1},{"y":2014,"b":72723,"i":225714,"c":1,"k":162.8,"ka":1,"la":3},{"y":2013,"b":36640,"i":213973,"c":1,"k":162.8,"ka":1,"la":3,"fi":26172}]}