{"2010":"","2016":"","Department":"Уманський міськрайонний суд Черкаської області","Region":"Черкаська область","Position":"Суддя Уманського міськрайонного суду Черкаської області","Name":"Іванов Анатолій Анатолійович","Link":"http://um.ck.court.gov.ua/userfiles/ivanov%281%29.pdf","Note":"","AdditionalNote":"","field8":"","field9":"","field10":"","Кількість справ":"","Оскаржені":"","Кількість скарг":2,"Кількість дисциплінарних стягнень":"","Клейма":4,"Фото":"","Як живе":"","key":"ivanov_anatoliy_anatoliyovich","allDeclarations":[{"provider":"declarations.com.ua","document":{"income":{"5":{"family_comment":"","value":"164091","value_unclear":false,"family":"180000","comment":""},"6":{"value":"164091","value_unclear":false,"family_hidden":false,"family_comment":"","family":"180000","comment":""},"7":{"source_name_unclear":false,"value":"","family_comment":"","source_name":"","family":"","comment":""},"8":{"family_comment":"","value":"","family":"","comment":""},"9":{"family_comment":"","value":"","family":"","comment":""},"10":{"family_comment":"","value":"","family":"","comment":""},"11":{"family_comment":"","value":"","comment_unclear":false,"family":"","comment":""},"12":{"family_comment":"","value":"","family":"","comment":""},"13":{"family_comment":"","value":"","family":"","comment":""},"14":{"family_comment":"","value":"","family":"","comment":""},"15":{"family_comment":"","value":"","family":"","comment":""},"16":{"family_comment":"","value":"","family":"","comment":""},"17":{"family_comment":"","value":"","family":"","comment":""},"18":{"family_comment":"","value":"","family":"","comment":""},"19":{"family_comment":"","value":"","family":"","comment":""},"20":{"value":"","family_comment":"","value_unclear":false,"family_unclear":false,"comment_unclear":false,"comment":"","family":""}},"id":"vulyk_101_150","declaration":{"additional_info_text":"","notfull_lostpages":"","date":"2016-03-17T00:00:00","notfull":"","additional_info":"","url":"http://static.declarations.com.ua/declarations/chosen_ones/judges_batch/865_ivanov_anatolii_anatoliiovych_2015.pdf"},"liabilities":{"54":{"sum_foreign_comment":"","sum":"","sum_comment":"","sum_comment_unclear":false,"sum_hidden":false,"sum_comment_hidden":false,"sum_unclear":false,"sum_foreign":""},"55":{"sum_foreign_comment":"","sum":"","sum_comment":"","sum_foreign":""},"56":{"sum_foreign_comment":"","sum":"","sum_comment":"","sum_comment_hidden":false,"sum_unclear":false,"sum_foreign":""},"57":{"sum_foreign_comment":"","sum":"","sum_comment":"","sum_hidden":false,"sum_comment_hidden":false,"sum_unclear":false,"sum_foreign":""},"58":{"sum_foreign_comment":"","sum":"","sum_comment":"","sum_comment_unclear":false,"sum_hidden":false,"sum_comment_hidden":false,"sum_unclear":false,"sum_foreign":""},"59":{"sum_foreign_comment":"","sum":"","sum_comment":"","sum_foreign":""},"60":{"sum_foreign_comment":"","sum":"","sum_comment":"","sum_hidden":false,"sum_comment_hidden":false,"sum_unclear":false,"sum_foreign":""},"61":{"sum_foreign_comment":"","sum":"","sum_comment":"","sum_foreign":""},"62":{"sum_foreign_comment":"","sum":"","sum_comment":"","sum_comment_unclear":false,"sum_foreign":""},"63":{"sum_foreign_comment":"","sum_comment_hidden":false,"sum":"","sum_comment":"","sum_foreign":""},"64":{"sum_foreign_comment":"","sum_comment_hidden":false,"sum":"","sum_comment":"","sum_foreign":""}},"ft_src":"суддя\nЧеркаська область\nЗагальний місцевий суд\nАнатолій\nТкач В. В\nПодружжя\nАнатолійович\nІванов Анатолій Анатолійович\nІванов\nІванов Анатолій Анатолійович\nАнатолій Анатолійович Іванов\nАнатолій Іванов\nІванов Анатолій Анатолійович\n180000\n164091\n164091\n180000\n30.1\n.295\n2015\n180000\n164091\n180000\n164091\n.295\n30.1\nПодружжя\nТкач В. В\nІванов Анатолій Анатолійович\nАнатолій Анатолійович Іванов\nАнатолій Іванов\nІванов Анатолій Анатолійович\nАнатолій\nІванов Анатолій Анатолійович\nАнатолійович\nЗагальний місцевий суд\nсуддя\nЧеркаська область\nІванов\n164091\n180000\n164091\n180000\n2015\nТкач В. В\nПодружжя\nАнатолій\nАнатолійович\nІванов\nІванов Анатолій Анатолійович\nАнатолій Анатолійович Іванов\nАнатолій Іванов\nІванов Анатолій Анатолійович\nсуддя\nЗагальний місцевий суд\nЧеркаська область\nІванов Анатолій Анатолійович\n30.1\n.295\n2015","general":{"inn":"","name":"Анатолій","inn_unclear":false,"family":[{"inn":"","relations":"Подружжя","relations_other":"","inn_hidden":true,"family_name":"Ткач В. В","name_hidden":true,"name_unclear":false}],"inn_hidden":true,"family_raw":"","last_name":"Іванов","post":{"region":"Черкаська область","region_unclear":false,"post":"суддя","office_unclear":false,"office":"Загальний місцевий суд"},"full_name":"Іванов Анатолій Анатолійович","addresses":[{"place_district":"","place_city_hidden":true,"place_city":"","place_city_type_hidden":false,"place_district_hidden":false,"place_city_type":"","place_address_hidden":true,"place_address":"","place_hidden":true,"place":""}],"patronymic":"Анатолійович","patronymic_hidden":false,"full_name_suggest":{"output":"Іванов Анатолій Анатолійович","input":["Іванов Анатолій Анатолійович","Анатолій Анатолійович Іванов","Анатолій Іванов"]}},"source":"VULYK","estate":{"29":[{"costs_rent":"","region":"","costs_property":"","costs_rent_comment":"","address_hidden":false,"region_hidden":true,"space_comment":"","costs_property_comment":"","space_units":"га","space":".295","address":""}],"30":[{"costs_rent":"","region":"","costs_property":"","costs_rent_comment":"","address_hidden":false,"region_hidden":true,"space_comment":"","costs_property_comment":"","space_units":"м²","space":"30.1","address":""}]},"intro":{"declaration_year":"2015"}}},{"provider":"declarations.com.ua","document":{"income":{"5":{"value":"186738","value_unclear":false,"family_hidden":false,"family_comment":"","family":"180000","comment":""},"6":{"family_comment":"","value":"186738","value_unclear":false,"family":"180000","comment":""},"7":{"source_name_unclear":false,"value":"","family_comment":"","source_name":"","family":"","comment":"","source_name_hidden":false},"8":{"family_comment":"","value":"","family":"","comment":""},"9":{"family_comment":"","value":"","comment_unclear":false,"family":"","comment":""},"10":{"family_comment":"","value":"","family":"","comment":""},"11":{"family_comment":"","family_unclear":false,"value":"","family":"","comment":""},"12":{"family_comment":"","value":"","family":"","comment":""},"13":{"family_comment":"","value":"","family":"","comment":""},"14":{"family_comment":"","value":"","family":"","comment":""},"15":{"family_comment":"","value":"","family":"","comment":""},"16":{"family_comment":"","value":"","family":"","comment":""},"17":{"family_comment":"","value":"","family":"","comment":""},"18":{"family_comment":"","value":"","family":"","comment":""},"19":{"family_comment":"","value":"","family":"","comment":""},"20":{"value":"","value_unclear":false,"family_comment":"","comment_unclear":false,"comment":"","family":""}},"id":"vulyk_94_90","declaration":{"additional_info_text":"","notfull_lostpages":"","date":"2015-03-24T00:00:00","notfull":"","additional_info":"","url":"http://static.declarations.com.ua/declarations/chosen_ones/judges_batch/3736_ivanov_anatolii_anatoliiovych.pdf"},"liabilities":{"54":{"sum_foreign_comment":"","sum":"","sum_comment":"","sum_comment_unclear":false,"sum_comment_hidden":false,"sum_unclear":false,"sum_foreign":""},"55":{"sum_foreign_comment":"","sum":"","sum_comment":"","sum_foreign":""},"56":{"sum_foreign_comment":"","sum":"","sum_comment":"","sum_unclear":false,"sum_foreign":""},"57":{"sum_foreign_comment":"","sum":"","sum_comment":"","sum_hidden":false,"sum_unclear":false,"sum_foreign":""},"58":{"sum_foreign_comment":"","sum":"","sum_comment":"","sum_hidden":false,"sum_unclear":false,"sum_foreign":""},"59":{"sum_foreign_comment":"","sum":"","sum_comment":"","sum_foreign":""},"60":{"sum_foreign_comment":"","sum_comment_hidden":false,"sum":"","sum_comment":"","sum_foreign":""},"61":{"sum_foreign_comment":"","sum":"","sum_comment":"","sum_foreign":""},"62":{"sum_foreign_comment":"","sum":"","sum_hidden":false,"sum_comment":"","sum_foreign":""},"63":{"sum_foreign_comment":"","sum_comment_hidden":false,"sum":"","sum_comment":"","sum_foreign":""},"64":{"sum_foreign_comment":"","sum":"","sum_comment":"","sum_unclear":false,"sum_foreign":""}},"ft_src":"суддя уманського міськрайонного суду черкаської області\nЧеркаська область\nЗагальний місцевий суд\nАнатолій\nТкач В. В\nПодружжя\nАнатолійович\nІванов Анатолій Анатолійович\nАнатолій Анатолійович Іванов\nАнатолій Іванов\nІванов Анатолій Анатолійович\nІванов Анатолій Анатолійович\nІванов\n186738\n180000\n180000\n186738\n30.1\n.296\n2014\n180000\n186738\n180000\n186738\n.296\n30.1\nІванов Анатолій Анатолійович\nАнатолій Анатолійович Іванов\nАнатолій Іванов\nІванов Анатолій Анатолійович\nІванов Анатолій Анатолійович\nПодружжя\nТкач В. В\nАнатолій\nІванов\nЗагальний місцевий суд\nЧеркаська область\nсуддя уманського міськрайонного суду черкаської області\nАнатолійович\n186738\n180000\n186738\n180000\n2014\nТкач В. В\nПодружжя\nАнатолійович\nІванов\nАнатолій\nІванов Анатолій Анатолійович\nАнатолій Анатолійович Іванов\nАнатолій Іванов\nІванов Анатолій Анатолійович\nЧеркаська область\nЗагальний місцевий суд\nсуддя уманського міськрайонного суду черкаської області\nІванов Анатолій Анатолійович\n30.1\n.296\n2014","general":{"inn":"","name":"Анатолій","last_name":"Іванов","family":[{"inn":"","relations":"Подружжя","relations_hidden":false,"inn_hidden":true,"family_name":"Ткач В. В","name_hidden":false,"name_unclear":false}],"inn_hidden":true,"family_raw":"","inn_unclear":false,"post":{"post_unclear":false,"region_unclear":false,"post":"суддя уманського міськрайонного суду черкаської області","candidate":"","post_hidden":false,"region":"Черкаська область","office":"Загальний місцевий суд","office_unclear":false},"full_name":"Іванов Анатолій Анатолійович","addresses":[{"place_district":"","place_city_hidden":false,"place_city":"","place_city_type_hidden":false,"place_district_hidden":false,"place_city_type":"","place_address_hidden":false,"place_address":"","place_hidden":true,"place":""}],"patronymic":"Анатолійович","patronymic_hidden":false,"full_name_suggest":{"output":"Іванов Анатолій Анатолійович","input":["Іванов Анатолій Анатолійович","Анатолій Анатолійович Іванов","Анатолій Іванов"]}},"source":"VULYK","estate":{"29":[{"costs_rent":"","region":"","costs_property":"","costs_rent_comment":"","address_hidden":false,"region_hidden":true,"space_comment":"","costs_property_comment":"","space_units":"га","space":".296","address":""}],"30":[{"space_hidden":false,"address_hidden":false,"region_hidden":true,"space_comment":"","space":"30.1","address":"","region":"","costs_property":"","costs_rent_comment":"","space_units":"м²","costs_property_comment":"","costs_rent":""}]},"intro":{"declaration_year":"2014","isnotdeclaration":""}}}],"declarations":[{"income":{"5":{"family_comment":"","value":"164091","value_unclear":false,"family":"180000","comment":""},"6":{"value":"164091","value_unclear":false,"family_hidden":false,"family_comment":"","family":"180000","comment":""},"7":{"source_name_unclear":false,"value":"","family_comment":"","source_name":"","family":"","comment":""},"8":{"family_comment":"","value":"","family":"","comment":""},"9":{"family_comment":"","value":"","family":"","comment":""},"10":{"family_comment":"","value":"","family":"","comment":""},"11":{"family_comment":"","value":"","comment_unclear":false,"family":"","comment":""},"12":{"family_comment":"","value":"","family":"","comment":""},"13":{"family_comment":"","value":"","family":"","comment":""},"14":{"family_comment":"","value":"","family":"","comment":""},"15":{"family_comment":"","value":"","family":"","comment":""},"16":{"family_comment":"","value":"","family":"","comment":""},"17":{"family_comment":"","value":"","family":"","comment":""},"18":{"family_comment":"","value":"","family":"","comment":""},"19":{"family_comment":"","value":"","family":"","comment":""},"20":{"value":"","family_comment":"","value_unclear":false,"family_unclear":false,"comment_unclear":false,"comment":"","family":""}},"id":"vulyk_101_150","declaration":{"additional_info_text":"","notfull_lostpages":"","date":"2016-03-17T00:00:00","notfull":"","additional_info":"","url":"http://static.declarations.com.ua/declarations/chosen_ones/judges_batch/865_ivanov_anatolii_anatoliiovych_2015.pdf"},"liabilities":{"54":{"sum_foreign_comment":"","sum":"","sum_comment":"","sum_comment_unclear":false,"sum_hidden":false,"sum_comment_hidden":false,"sum_unclear":false,"sum_foreign":""},"55":{"sum_foreign_comment":"","sum":"","sum_comment":"","sum_foreign":""},"56":{"sum_foreign_comment":"","sum":"","sum_comment":"","sum_comment_hidden":false,"sum_unclear":false,"sum_foreign":""},"57":{"sum_foreign_comment":"","sum":"","sum_comment":"","sum_hidden":false,"sum_comment_hidden":false,"sum_unclear":false,"sum_foreign":""},"58":{"sum_foreign_comment":"","sum":"","sum_comment":"","sum_comment_unclear":false,"sum_hidden":false,"sum_comment_hidden":false,"sum_unclear":false,"sum_foreign":""},"59":{"sum_foreign_comment":"","sum":"","sum_comment":"","sum_foreign":""},"60":{"sum_foreign_comment":"","sum":"","sum_comment":"","sum_hidden":false,"sum_comment_hidden":false,"sum_unclear":false,"sum_foreign":""},"61":{"sum_foreign_comment":"","sum":"","sum_comment":"","sum_foreign":""},"62":{"sum_foreign_comment":"","sum":"","sum_comment":"","sum_comment_unclear":false,"sum_foreign":""},"63":{"sum_foreign_comment":"","sum_comment_hidden":false,"sum":"","sum_comment":"","sum_foreign":""},"64":{"sum_foreign_comment":"","sum_comment_hidden":false,"sum":"","sum_comment":"","sum_foreign":""}},"ft_src":"суддя\nЧеркаська область\nЗагальний місцевий суд\nАнатолій\nТкач В. В\nПодружжя\nАнатолійович\nІванов Анатолій Анатолійович\nІванов\nІванов Анатолій Анатолійович\nАнатолій Анатолійович Іванов\nАнатолій Іванов\nІванов Анатолій Анатолійович\n180000\n164091\n164091\n180000\n30.1\n.295\n2015\n180000\n164091\n180000\n164091\n.295\n30.1\nПодружжя\nТкач В. В\nІванов Анатолій Анатолійович\nАнатолій Анатолійович Іванов\nАнатолій Іванов\nІванов Анатолій Анатолійович\nАнатолій\nІванов Анатолій Анатолійович\nАнатолійович\nЗагальний місцевий суд\nсуддя\nЧеркаська область\nІванов\n164091\n180000\n164091\n180000\n2015\nТкач В. В\nПодружжя\nАнатолій\nАнатолійович\nІванов\nІванов Анатолій Анатолійович\nАнатолій Анатолійович Іванов\nАнатолій Іванов\nІванов Анатолій Анатолійович\nсуддя\nЗагальний місцевий суд\nЧеркаська область\nІванов Анатолій Анатолійович\n30.1\n.295\n2015","general":{"inn":"","name":"Анатолій","inn_unclear":false,"family":[{"inn":"","relations":"Подружжя","relations_other":"","inn_hidden":true,"family_name":"Ткач В. В","name_hidden":true,"name_unclear":false}],"inn_hidden":true,"family_raw":"","last_name":"Іванов","post":{"region":"Черкаська область","region_unclear":false,"post":"суддя","office_unclear":false,"office":"Загальний місцевий суд"},"full_name":"Іванов Анатолій Анатолійович","addresses":[{"place_district":"","place_city_hidden":true,"place_city":"","place_city_type_hidden":false,"place_district_hidden":false,"place_city_type":"","place_address_hidden":true,"place_address":"","place_hidden":true,"place":""}],"patronymic":"Анатолійович","patronymic_hidden":false,"full_name_suggest":{"output":"Іванов Анатолій Анатолійович","input":["Іванов Анатолій Анатолійович","Анатолій Анатолійович Іванов","Анатолій Іванов"]}},"source":"VULYK","estate":{"29":[{"costs_rent":"","region":"","costs_property":"","costs_rent_comment":"","address_hidden":false,"region_hidden":true,"space_comment":"","costs_property_comment":"","space_units":"га","space":".295","address":""}],"30":[{"costs_rent":"","region":"","costs_property":"","costs_rent_comment":"","address_hidden":false,"region_hidden":true,"space_comment":"","costs_property_comment":"","space_units":"м²","space":"30.1","address":""}]},"intro":{"declaration_year":"2015"}},{"income":{"5":{"value":"186738","value_unclear":false,"family_hidden":false,"family_comment":"","family":"180000","comment":""},"6":{"family_comment":"","value":"186738","value_unclear":false,"family":"180000","comment":""},"7":{"source_name_unclear":false,"value":"","family_comment":"","source_name":"","family":"","comment":"","source_name_hidden":false},"8":{"family_comment":"","value":"","family":"","comment":""},"9":{"family_comment":"","value":"","comment_unclear":false,"family":"","comment":""},"10":{"family_comment":"","value":"","family":"","comment":""},"11":{"family_comment":"","family_unclear":false,"value":"","family":"","comment":""},"12":{"family_comment":"","value":"","family":"","comment":""},"13":{"family_comment":"","value":"","family":"","comment":""},"14":{"family_comment":"","value":"","family":"","comment":""},"15":{"family_comment":"","value":"","family":"","comment":""},"16":{"family_comment":"","value":"","family":"","comment":""},"17":{"family_comment":"","value":"","family":"","comment":""},"18":{"family_comment":"","value":"","family":"","comment":""},"19":{"family_comment":"","value":"","family":"","comment":""},"20":{"value":"","value_unclear":false,"family_comment":"","comment_unclear":false,"comment":"","family":""}},"id":"vulyk_94_90","declaration":{"additional_info_text":"","notfull_lostpages":"","date":"2015-03-24T00:00:00","notfull":"","additional_info":"","url":"http://static.declarations.com.ua/declarations/chosen_ones/judges_batch/3736_ivanov_anatolii_anatoliiovych.pdf"},"liabilities":{"54":{"sum_foreign_comment":"","sum":"","sum_comment":"","sum_comment_unclear":false,"sum_comment_hidden":false,"sum_unclear":false,"sum_foreign":""},"55":{"sum_foreign_comment":"","sum":"","sum_comment":"","sum_foreign":""},"56":{"sum_foreign_comment":"","sum":"","sum_comment":"","sum_unclear":false,"sum_foreign":""},"57":{"sum_foreign_comment":"","sum":"","sum_comment":"","sum_hidden":false,"sum_unclear":false,"sum_foreign":""},"58":{"sum_foreign_comment":"","sum":"","sum_comment":"","sum_hidden":false,"sum_unclear":false,"sum_foreign":""},"59":{"sum_foreign_comment":"","sum":"","sum_comment":"","sum_foreign":""},"60":{"sum_foreign_comment":"","sum_comment_hidden":false,"sum":"","sum_comment":"","sum_foreign":""},"61":{"sum_foreign_comment":"","sum":"","sum_comment":"","sum_foreign":""},"62":{"sum_foreign_comment":"","sum":"","sum_hidden":false,"sum_comment":"","sum_foreign":""},"63":{"sum_foreign_comment":"","sum_comment_hidden":false,"sum":"","sum_comment":"","sum_foreign":""},"64":{"sum_foreign_comment":"","sum":"","sum_comment":"","sum_unclear":false,"sum_foreign":""}},"ft_src":"суддя уманського міськрайонного суду черкаської області\nЧеркаська область\nЗагальний місцевий суд\nАнатолій\nТкач В. В\nПодружжя\nАнатолійович\nІванов Анатолій Анатолійович\nАнатолій Анатолійович Іванов\nАнатолій Іванов\nІванов Анатолій Анатолійович\nІванов Анатолій Анатолійович\nІванов\n186738\n180000\n180000\n186738\n30.1\n.296\n2014\n180000\n186738\n180000\n186738\n.296\n30.1\nІванов Анатолій Анатолійович\nАнатолій Анатолійович Іванов\nАнатолій Іванов\nІванов Анатолій Анатолійович\nІванов Анатолій Анатолійович\nПодружжя\nТкач В. В\nАнатолій\nІванов\nЗагальний місцевий суд\nЧеркаська область\nсуддя уманського міськрайонного суду черкаської області\nАнатолійович\n186738\n180000\n186738\n180000\n2014\nТкач В. В\nПодружжя\nАнатолійович\nІванов\nАнатолій\nІванов Анатолій Анатолійович\nАнатолій Анатолійович Іванов\nАнатолій Іванов\nІванов Анатолій Анатолійович\nЧеркаська область\nЗагальний місцевий суд\nсуддя уманського міськрайонного суду черкаської області\nІванов Анатолій Анатолійович\n30.1\n.296\n2014","general":{"inn":"","name":"Анатолій","last_name":"Іванов","family":[{"inn":"","relations":"Подружжя","relations_hidden":false,"inn_hidden":true,"family_name":"Ткач В. В","name_hidden":false,"name_unclear":false}],"inn_hidden":true,"family_raw":"","inn_unclear":false,"post":{"post_unclear":false,"region_unclear":false,"post":"суддя уманського міськрайонного суду черкаської області","candidate":"","post_hidden":false,"region":"Черкаська область","office":"Загальний місцевий суд","office_unclear":false},"full_name":"Іванов Анатолій Анатолійович","addresses":[{"place_district":"","place_city_hidden":false,"place_city":"","place_city_type_hidden":false,"place_district_hidden":false,"place_city_type":"","place_address_hidden":false,"place_address":"","place_hidden":true,"place":""}],"patronymic":"Анатолійович","patronymic_hidden":false,"full_name_suggest":{"output":"Іванов Анатолій Анатолійович","input":["Іванов Анатолій Анатолійович","Анатолій Анатолійович Іванов","Анатолій Іванов"]}},"source":"VULYK","estate":{"29":[{"costs_rent":"","region":"","costs_property":"","costs_rent_comment":"","address_hidden":false,"region_hidden":true,"space_comment":"","costs_property_comment":"","space_units":"га","space":".296","address":""}],"30":[{"space_hidden":false,"address_hidden":false,"region_hidden":true,"space_comment":"","space":"30.1","address":"","region":"","costs_property":"","costs_rent_comment":"","space_units":"м²","costs_property_comment":"","costs_rent":""}]},"intro":{"declaration_year":"2014","isnotdeclaration":""}}],"declarationsLength":2,"analytics":[{"y":2015,"i":164091,"fi":180000,"fh":30.1,"fha":1,"fl":2950,"fla":1,"j":2},{"y":2014,"i":186738,"fi":180000,"fh":30.1,"fha":1,"fl":2960,"fla":1}]}