{"2010":"","2016":"","Department":"Хустській районний суд Закарпатської області","Region":"Закарпатська область","Position":"Суддя Хустського районного суду Закарпатської області","Name":"Кемінь Володимир Дмитрович","Link":"http://hs.zk.court.gov.ua/userfiles/file/Xycm_sud/deklaracija/Deklaracija%20Kemin.pdf","Note":"","AdditionalNote":"","field8":"","field9":"","field10":"","Кількість справ":"","Оскаржені":"","Кількість скарг":1,"Кількість дисциплінарних стягнень":"","Клейма":"","Фото":"http://picua.org/img/2016-10/04/k06jdnicd3rd0y72j62z9ak3o.jpg","Як живе":"","key":"kemin_volodimir_dmitrovich","allDeclarations":[{"provider":"declarations.com.ua","document":{"income":{"5":{"value":"234061","value_unclear":false,"comment_hidden":false,"family_comment":"","family":"27526","comment":""},"6":{"family_comment":"","value":"234061","family":"","comment":"","value_hidden":false},"7":{"family_comment":"","value":"","source_name":"","family":"","comment":""},"8":{"family_comment":"","value":"","family":"","comment":""},"9":{"family_comment":"","value":"","comment_hidden":false,"family":"","comment":""},"10":{"family_comment":"","value":"","family":"","comment":""},"11":{"family_comment":"","value":"","family":"","comment":""},"12":{"family_comment":"","value":"","family":"","comment":""},"13":{"family_comment":"","value":"","family":"","comment":""},"14":{"family_comment":"","value":"","family":"","comment":""},"15":{"family_comment":"","value":"","family":"","comment":"","family_comment_hidden":false},"16":{"family_comment":"","value":"","family":"","comment":""},"17":{"family_comment":"","value":"","family":"","comment":""},"18":{"family_comment":"","value":"","family":"","comment":"","value_hidden":false},"19":{"family_comment":"","value":"","family":"","comment":""},"20":{"family_comment":"","value":"","family":"","comment":"","family_comment_unclear":false}},"vehicle":{"35":[{"brand_info":"2.4 куб. см.","sum_rent_comment":"","brand":"Toyota Camry","sum_comment":"на підставі свідоцтва про спадщину за заповітом","year":"2008","sum":"","sum_rent":""}]},"id":"vulyk_78_3","declaration":{"additional_info_text":"","notfull_lostpages":"","date":"2015-03-27T00:00:00","notfull":"","additional_info":"","url":"http://static.declarations.com.ua/declarations/chosen_ones/judges_batch/2070_kemin_volodymyr_dmytrovych.pdf"},"liabilities":{"54":{"sum_foreign_comment":"","sum_foreign_hidden":false,"sum_comment":"","sum_comment_unclear":false,"sum_hidden":false,"sum_comment_hidden":false,"sum":"","sum_foreign":""},"55":{"sum_foreign_comment":"","sum":"","sum_comment":"","sum_foreign":""},"56":{"sum_foreign_comment":"","sum":"","sum_comment":"","sum_foreign":""},"57":{"sum_foreign_comment":"","sum":"","sum_comment":"","sum_foreign":""},"58":{"sum_foreign_comment":"","sum":"","sum_comment":"","sum_unclear":false,"sum_foreign":""},"59":{"sum_foreign_comment":"","sum":"","sum_comment":"","sum_foreign":""},"60":{"sum_foreign_comment":"","sum":"","sum_comment":"","sum_comment_unclear":false,"sum_comment_hidden":false,"sum_foreign":""},"61":{"sum_foreign_comment":"","sum":"","sum_comment":"","sum_foreign":""},"62":{"sum_foreign_comment":"","sum":"","sum_hidden":false,"sum_comment":"","sum_foreign":""},"63":{"sum_foreign_comment":"","sum_foreign_hidden":false,"sum_comment":"","sum":"","sum_unclear":false,"sum_foreign":""},"64":{"sum_foreign_comment":"","sum_foreign_hidden":false,"sum_comment":"","sum_hidden":false,"sum":"","sum_foreign":""}},"ft_src":"заступник голови хустського районного суду закарпатської області\nЗакарпатська область\nЗагальний місцевий суд\n2520344512\nВолодимир\n2912800983\nКемінь Світлана Степанівна\nПодружжя\nКемінь Владислава Володимирівна\nДитина\nКемінь Ростислав Володимирович\nДитина\nДмитрович\nКемінь Володимир Дмитрович\nВолодимир Дмитрович Кемінь\nВолодимир Кемінь\nКемінь Володимир Дмитрович\nКемінь\nКемінь Володимир Дмитрович\nІза\nСело\nвул. Терешкової,19, 90436\nЗакарпатська область\nХустський\nна підставі свідоцтва про спадщину за заповітом\n2.4 куб. см.\n2008\nToyota Camry\nЗакарпатська область\nХустський р-н,с. Іза, вул. Терешкової,19\n230\nс. Іза, вул. Терешкової,19\nЗакарпатська область\n95\nЗакарпатська область\nс. Іза, вул. Терешкової,19\n163\n2014\n234061\n27526\n234061\n2.4 куб. см.\nна підставі свідоцтва про спадщину за заповітом\n2008\nToyota Camry\n2014\nПодружжя\nКемінь Світлана Степанівна\n2912800983\nДитина\nКемінь Владислава Володимирівна\nДитина\nКемінь Ростислав Володимирович\nКемінь Володимир Дмитрович\nВолодимир Дмитрович Кемінь\nВолодимир Кемінь\nКемінь Володимир Дмитрович\nКемінь Володимир Дмитрович\n2520344512\nВолодимир\nДмитрович\nЗагальний місцевий суд\nзаступник голови хустського районного суду закарпатської області\nЗакарпатська область\nКемінь\nСело\nвул. Терешкової,19, 90436\nЗакарпатська область\nІза\nХустський\n234061\n234061\n27526\n95\nЗакарпатська область\nс. Іза, вул. Терешкової,19\n163\nЗакарпатська область\nс. Іза, вул. Терешкової,19\nХустський р-н,с. Іза, вул. Терешкової,19\nЗакарпатська область\n230\n2912800983\nПодружжя\nКемінь Світлана Степанівна\nДитина\nКемінь Владислава Володимирівна\nДитина\nКемінь Ростислав Володимирович\n2520344512\nДмитрович\nКемінь\nВолодимир\nКемінь Володимир Дмитрович\nВолодимир Дмитрович Кемінь\nВолодимир Кемінь\nКемінь Володимир Дмитрович\nСело\nЗакарпатська область\nІза\nвул. Терешкової,19, 90436\nХустський\nЗакарпатська область\nзаступник голови хустського районного суду закарпатської області\nЗагальний місцевий суд\nКемінь Володимир Дмитрович\nна підставі свідоцтва про спадщину за заповітом\nToyota Camry\n2.4 куб. см.\n2008\n234061\n27526\n234061\nХустський р-н,с. Іза, вул. Терешкової,19\nЗакарпатська область\n230\nс. Іза, вул. Терешкової,19\nЗакарпатська область\n95\nс. Іза, вул. Терешкової,19\nЗакарпатська область\n163\n2014","general":{"inn":"2520344512","name":"Володимир","family":[{"inn":"2912800983","relations":"Подружжя","relations_other":"","inn_hidden":true,"family_name":"Кемінь Світлана Степанівна","name_hidden":false,"name_unclear":true},{"inn":"","relations":"Дитина","relations_other":"","inn_hidden":true,"family_name":"Кемінь Владислава Володимирівна","name_hidden":false,"name_unclear":true},{"inn":"","relations":"Дитина","relations_other":"","inn_hidden":true,"family_name":"Кемінь Ростислав Володимирович","name_unclear":false}],"patronymic":"Дмитрович","inn_hidden":false,"family_raw":"","last_name":"Кемінь","post":{"post_unclear":false,"post":"заступник голови хустського районного суду закарпатської області","post_hidden":false,"region":"Закарпатська область","region_hidden":false,"office":"Загальний місцевий суд","office_hidden":false},"last_name_unclear":true,"full_name":"Кемінь Володимир Дмитрович","addresses":[{"place_district":"Хустський","place_city_hidden":false,"place_city":"Іза","place_city_type_hidden":false,"place_district_hidden":false,"place_city_type":"Село","place_address_hidden":false,"place_address":"вул. Терешкової,19, 90436","place_hidden":false,"place":"Закарпатська область"}],"full_name_suggest":{"output":"Кемінь Володимир Дмитрович","input":["Кемінь Володимир Дмитрович","Володимир Дмитрович Кемінь","Володимир Кемінь"]},"name_unclear":false},"source":"VULYK","estate":{"29":[{"space_unclear":true,"address_hidden":false,"region_hidden":false,"space_comment":"","space":"95","address":"с. Іза, вул. Терешкової,19","region":"Закарпатська область","costs_property":"","costs_rent_comment":"","space_units":"м²","costs_property_comment":"","costs_rent":""},{"costs_rent":"","region":"Закарпатська область","costs_property":"","costs_rent_comment":"","address_hidden":false,"space_comment":"","costs_property_comment":"","space_units":"м²","space":"163","address":"с. Іза, вул. Терешкової,19"}],"30":[{"space_hidden":false,"address_hidden":false,"region_hidden":false,"space_comment":"","space":"230","address":"Хустський р-н,с. Іза, вул. Терешкової,19","region":"Закарпатська область","costs_property":"","costs_rent_comment":"","space_units":"м²","costs_property_comment":"","costs_rent":""}]},"intro":{"declaration_year":"2014"}}},{"provider":"public-api.nazk.gov.ua","document":{"step_0":{"declarationType":"1","declarationYear1":"2015"},"step_1":{"city":"[Конфіденційна інформація]","region":"[Конфіденційна інформація]","street":"[Конфіденційна інформація]","country":"1","cityPath":"[Конфіденційна інформація]","cityType":"[Конфіденційна інформація]","district":"[Конфіденційна інформація]","lastname":"Кемінь","postCode":"[Конфіденційна інформація]","postType":"Посада державної служби","workPost":"суддя","firstname":"Володимир","workPlace":"Хустський районний суд Закарпатської області","middlename":"Дмитрович","streetType":"[Конфіденційна інформація]","changedName":false,"countryPath":"","eng_postCode":"","postCategory":"","actual_street":"[Конфіденційна інформація]","actual_cityPath":"[Конфіденційна інформація]","actual_cityType":"[Конфіденційна інформація]","actual_postCode":"[Конфіденційна інформація]","actual_streetType":"[Конфіденційна інформація]","previous_lastname":"","corruptionAffected":"Так","eng_actualPostCode":"[Конфіденційна інформація]","previous_firstname":"","previous_middlename":"","responsiblePosition":"Суддя суду загальної юрисдикції, суддя Конституційного Суду України","sameRegLivingAddress":"[Конфіденційна інформація]","eng_sameRegLivingAddress":"[Конфіденційна інформація]","housePartNum_extendedstatus":"1","postCategory_extendedstatus":"1","apartmentsNum_extendedstatus":"1"},"step_2":{"1480310316554":{"lastname":"Кемінь","firstname":"Світлана","middlename":"Степанівна","changedName":false,"citizenship":"1","eng_lastname":"","eng_firstname":"","eng_middlename":"","isNotApplicable":"","subjectRelation":"дружина","previous_lastname":"","previous_firstname":"","previous_middlename":"","previous_eng_lastname":"","previous_eng_firstname":"","previous_eng_middlename":""},"1480310386132":{"lastname":"Кемінь","firstname":"Владислава","middlename":"Володимирівна","changedName":false,"citizenship":"1","eng_lastname":"","eng_firstname":"","eng_middlename":"","isNotApplicable":"","subjectRelation":"дочка","previous_lastname":"","previous_firstname":"","previous_middlename":"","previous_eng_lastname":"","previous_eng_firstname":"","previous_eng_middlename":""},"1480310449434":{"lastname":"Кемінь","firstname":"Ростислав","middlename":"Володимирович","changedName":false,"citizenship":"1","eng_lastname":"","eng_firstname":"","eng_middlename":"","isNotApplicable":"","subjectRelation":"син","previous_lastname":"","previous_firstname":"","previous_middlename":"","previous_eng_lastname":"","previous_eng_firstname":"","previous_eng_middlename":""}},"step_3":{"1480310511510":{"city":"[Конфіденційна інформація]","person":"1","region":"[Конфіденційна інформація]","rights":{"1":{"citizen":"","ua_city":"","ua_street":"[Конфіденційна інформація]","ua_lastname":"","ua_postCode":"","eng_fullname":"","eng_lastname":"","eng_postCode":"","rightBelongs":"1","ua_firstname":"","ukr_fullname":"","ukr_lastname":"","eng_firstname":"","ownershipType":"Власність","ua_middlename":"","ua_streetType":"[Конфіденційна інформація]","ukr_firstname":"","eng_middlename":"","otherOwnership":"","ukr_middlename":"","rights_cityPath":"","ua_company_name":"","eng_company_name":"","ukr_company_name":"","percent-ownership":"100","ua_street_extendedstatus":"","ua_houseNum_extendedstatus":"","ua_postCode_extendedstatus":"","eng_postCode_extendedstatus":"","ua_middlename_extendedstatus":"","eng_middlename_extendedstatus":"","ukr_middlename_extendedstatus":"","ua_housePartNum_extendedstatus":"","ua_apartmentsNum_extendedstatus":""}},"country":"1","cityPath":"[Конфіденційна інформація]","costDate":"110821","district":"[Конфіденційна інформація]","postCode":"[Конфіденційна інформація]","iteration":"1480310511510","totalArea":"90,10","ua_street":"[Конфіденційна інформація]","objectType":"Житловий будинок","owningDate":"17.03.2015","ua_cityType":"Іза / Хустський Район / Закарпатська Область / Україна","ua_postCode":"90436","ua_streetType":"[Конфіденційна інформація]","costAssessment":"1100821","otherObjectType":"","ua_housePartNum_extendedstatus":"1","ua_apartmentsNum_extendedstatus":"1"},"1480312955962":{"city":"[Конфіденційна інформація]","person":"1","region":"[Конфіденційна інформація]","rights":{"1480310316554":{"citizen":"","ua_city":"","ua_street":"[Конфіденційна інформація]","ua_lastname":"","ua_postCode":"","eng_fullname":"","eng_lastname":"","eng_postCode":"","rightBelongs":"1480310316554","ua_firstname":"","ukr_fullname":"","ukr_lastname":"","eng_firstname":"","ownershipType":"Власність","ua_middlename":"","ua_streetType":"[Конфіденційна інформація]","ukr_firstname":"","eng_middlename":"","otherOwnership":"","ukr_middlename":"","rights_cityPath":"","ua_company_name":"","eng_company_name":"","ukr_company_name":"","percent-ownership":"100","ua_street_extendedstatus":"","ua_houseNum_extendedstatus":"","ua_postCode_extendedstatus":"","eng_postCode_extendedstatus":"","ua_middlename_extendedstatus":"","eng_middlename_extendedstatus":"","ukr_middlename_extendedstatus":"","ua_housePartNum_extendedstatus":"","ua_apartmentsNum_extendedstatus":""}},"country":"1","cityPath":"[Конфіденційна інформація]","costDate":"","district":"[Конфіденційна інформація]","postCode":"[Конфіденційна інформація]","iteration":"1480312955962","totalArea":"1600","ua_street":"[Конфіденційна інформація]","objectType":"Земельна ділянка","owningDate":"26.06.2003","ua_cityType":"Іза / Хустський Район / Закарпатська Область / Україна","ua_postCode":"90436","ua_streetType":"[Конфіденційна інформація]","costAssessment":"","otherObjectType":"","costDate_extendedstatus":"2","regNumber_extendedstatus":"2","costAssessment_extendedstatus":"2","ua_housePartNum_extendedstatus":"1","ua_apartmentsNum_extendedstatus":"1"},"1480313170942":{"city":"[Конфіденційна інформація]","person":"1","region":"[Конфіденційна інформація]","rights":{"1480310316554":{"citizen":"","ua_city":"","ua_street":"[Конфіденційна інформація]","ua_lastname":"","ua_postCode":"","eng_fullname":"","eng_lastname":"","eng_postCode":"","rightBelongs":"1480310316554","ua_firstname":"","ukr_fullname":"","ukr_lastname":"","eng_firstname":"","ownershipType":"Власність","ua_middlename":"","ua_streetType":"[Конфіденційна інформація]","ukr_firstname":"","eng_middlename":"","otherOwnership":"","ukr_middlename":"","rights_cityPath":"","ua_company_name":"","eng_company_name":"","ukr_company_name":"","percent-ownership":"100","ua_street_extendedstatus":"","ua_houseNum_extendedstatus":"","ua_postCode_extendedstatus":"","eng_postCode_extendedstatus":"","ua_middlename_extendedstatus":"","eng_middlename_extendedstatus":"","ukr_middlename_extendedstatus":"","ua_housePartNum_extendedstatus":"","ua_apartmentsNum_extendedstatus":""}},"country":"1","cityPath":"[Конфіденційна інформація]","costDate":"","district":"[Конфіденційна інформація]","postCode":"[Конфіденційна інформація]","iteration":"1480313170942","totalArea":"955","ua_street":"[Конфіденційна інформація]","objectType":"Земельна ділянка","owningDate":"17.09.2007","ua_cityType":"Іза / Хустський Район / Закарпатська область / Україна","ua_postCode":"90436","ua_streetType":"[Конфіденційна інформація]","costAssessment":"","otherObjectType":"","costDate_extendedstatus":"2","costAssessment_extendedstatus":"2","ua_housePartNum_extendedstatus":"1","ua_apartmentsNum_extendedstatus":"1"}},"step_4":{"1480311639152":{"city":"[Конфіденційна інформація]","person":"1","region":"[Конфіденційна інформація]","rights":{"1480310316554":{"citizen":"","ua_city":"","ua_street":"[Конфіденційна інформація]","ua_lastname":"","ua_postCode":"","eng_fullname":"","eng_lastname":"","eng_postCode":"","rightBelongs":"1480310316554","ua_firstname":"","ukr_fullname":"","ukr_lastname":"","eng_firstname":"","ownershipType":"Власність","ua_middlename":"","ua_streetType":"[Конфіденційна інформація]","ukr_firstname":"","eng_middlename":"","otherOwnership":"","ukr_middlename":"","rights_cityPath":"","ua_company_name":"","eng_company_name":"","ukr_company_name":"","percent-ownership":"","ua_street_extendedstatus":"","ua_houseNum_extendedstatus":"","ua_postCode_extendedstatus":"","eng_postCode_extendedstatus":"","ua_middlename_extendedstatus":"","eng_middlename_extendedstatus":"","ukr_middlename_extendedstatus":"","ua_housePartNum_extendedstatus":"","ua_apartmentsNum_extendedstatus":""}},"country":"1","cityPath":"[Конфіденційна інформація]","district":"[Конфіденційна інформація]","postCode":"[Конфіденційна інформація]","iteration":"1480311639152","totalArea":"132,8","ua_street":"[Конфіденційна інформація]","objectType":"Житловий будинок","ua_cityType":"Іза / Хустський Район / Закарпатська Область / Україна","ua_postCode":"90436","exploitation":true,"isThirdOwner":false,"ua_city_full":"","eng_regNumber":"","ua_streetType":"[Конфіденційна інформація]","dontRegistered":false,"flag_thirdOwner":1,"otherObjectType":"","addition_lastname":"","unfinishConstruct":false,"addition_firstname":"","thirdOwner_citizen":"","addition_middlename":"","addition_ua_fullName":"","addition_company_name":"","addition_eng_fullName":"","builtMaterialsOrFunds":false,"addition_ua_company_name":"","addition_eng_company_name":"","belongsSubjectOfDeclaration":true,"actualAddressEqualRegAddress":"","ua_housePartNum_extendedstatus":"1","ua_apartmentsNum_extendedstatus":"1"}},"step_5":[],"step_6":{"1480310935179":{"brand":"Тойота","model":"Кемрі","person":"1","rights":{"1":{"citizen":"","ua_city":"","ua_street":"[Конфіденційна інформація]","ua_lastname":"","ua_postCode":"","eng_fullname":"","eng_lastname":"","eng_postCode":"","rightBelongs":"1","ua_firstname":"","ukr_fullname":"","ukr_lastname":"","eng_firstname":"","ownershipType":"Власність","ua_middlename":"","ua_streetType":"[Конфіденційна інформація]","ukr_firstname":"","eng_middlename":"","otherOwnership":"","ukr_middlename":"","rights_cityPath":"","ua_company_name":"","eng_company_name":"","ukr_company_name":"","percent-ownership":"","ua_street_extendedstatus":"","ua_houseNum_extendedstatus":"","ua_postCode_extendedstatus":"","eng_postCode_extendedstatus":"","ua_middlename_extendedstatus":"","eng_middlename_extendedstatus":"","ukr_middlename_extendedstatus":"","ua_housePartNum_extendedstatus":"","ua_apartmentsNum_extendedstatus":""}},"costDate":"140507","iteration":"1480310935179","objectType":"Автомобіль легковий","owningDate":"15.07.2013","graduationYear":"2008","otherObjectType":""}},"step_7":[],"step_8":[],"step_9":[],"step_10":[],"step_11":{"1480313428898":{"person":"1","rights":{"1":{"citizen":"","ua_city":"","ua_street":"[Конфіденційна інформація]","ua_lastname":"","ua_postCode":"","eng_fullname":"","eng_lastname":"","eng_postCode":"","rightBelongs":"1","ua_firstname":"","ukr_fullname":"","ukr_lastname":"","eng_firstname":"","ownershipType":"Власність","ua_middlename":"","ua_streetType":"[Конфіденційна інформація]","ukr_firstname":"","eng_middlename":"","otherOwnership":"","ukr_middlename":"","rights_cityPath":"","ua_company_name":"","eng_company_name":"","ukr_company_name":"","percent-ownership":"","ua_street_extendedstatus":"","ua_houseNum_extendedstatus":"","ua_postCode_extendedstatus":"","eng_postCode_extendedstatus":"","ua_middlename_extendedstatus":"","eng_middlename_extendedstatus":"","ukr_middlename_extendedstatus":"","ua_housePartNum_extendedstatus":"","ua_apartmentsNum_extendedstatus":""}},"iteration":"1480313428898","objectType":"Заробітна плата отримана за основним місцем роботи","sizeIncome":"222855","incomeSource":"j","source_citizen":"Юридична особа, зареєстрована в Україні","otherObjectType":"","source_ua_lastname":"","source_eng_fullname":"","source_ua_firstname":"","source_ukr_fullname":"","source_ua_middlename":"","source_ua_company_name":"Територіальне управління державної судової адміністрації України в Закарпатській області","source_eng_company_name":"","source_ukr_company_name":"","source_ua_sameRegLivingAddress":""},"1480313609207":{"person":"1","rights":{"1480310316554":{"citizen":"","ua_city":"","ua_street":"[Конфіденційна інформація]","ua_lastname":"","ua_postCode":"","eng_fullname":"","eng_lastname":"","eng_postCode":"","rightBelongs":"1480310316554","ua_firstname":"","ukr_fullname":"","ukr_lastname":"","eng_firstname":"","ownershipType":"Власність","ua_middlename":"","ua_streetType":"[Конфіденційна інформація]","ukr_firstname":"","eng_middlename":"","otherOwnership":"","ukr_middlename":"","rights_cityPath":"","ua_company_name":"","eng_company_name":"","ukr_company_name":"","percent-ownership":"","ua_street_extendedstatus":"","ua_houseNum_extendedstatus":"","ua_postCode_extendedstatus":"","eng_postCode_extendedstatus":"","ua_middlename_extendedstatus":"","eng_middlename_extendedstatus":"","ukr_middlename_extendedstatus":"","ua_housePartNum_extendedstatus":"","ua_apartmentsNum_extendedstatus":""}},"iteration":"1480313609207","objectType":"Заробітна плата отримана за основним місцем роботи","sizeIncome":"31994","incomeSource":"j","source_citizen":"Юридична особа, зареєстрована в Україні","otherObjectType":"","source_ua_lastname":"","source_eng_fullname":"","source_ua_firstname":"","source_ukr_fullname":"","source_ua_middlename":"","source_ua_company_name":"Відділ освіти Хустської Державної Адміністрації","source_eng_company_name":"","source_ukr_company_name":"","source_ua_sameRegLivingAddress":""}},"step_12":[],"step_13":[],"step_14":[],"step_15":[],"step_16":[],"id":"e688eea3-627a-450c-8535-7f75f42d2136"}}],"declarations":[{"income":{"5":{"value":"234061","value_unclear":false,"comment_hidden":false,"family_comment":"","family":"27526","comment":""},"6":{"family_comment":"","value":"234061","family":"","comment":"","value_hidden":false},"7":{"family_comment":"","value":"","source_name":"","family":"","comment":""},"8":{"family_comment":"","value":"","family":"","comment":""},"9":{"family_comment":"","value":"","comment_hidden":false,"family":"","comment":""},"10":{"family_comment":"","value":"","family":"","comment":""},"11":{"family_comment":"","value":"","family":"","comment":""},"12":{"family_comment":"","value":"","family":"","comment":""},"13":{"family_comment":"","value":"","family":"","comment":""},"14":{"family_comment":"","value":"","family":"","comment":""},"15":{"family_comment":"","value":"","family":"","comment":"","family_comment_hidden":false},"16":{"family_comment":"","value":"","family":"","comment":""},"17":{"family_comment":"","value":"","family":"","comment":""},"18":{"family_comment":"","value":"","family":"","comment":"","value_hidden":false},"19":{"family_comment":"","value":"","family":"","comment":""},"20":{"family_comment":"","value":"","family":"","comment":"","family_comment_unclear":false}},"vehicle":{"35":[{"brand_info":"2.4 куб. см.","sum_rent_comment":"","brand":"Toyota Camry","sum_comment":"на підставі свідоцтва про спадщину за заповітом","year":"2008","sum":"","sum_rent":""}]},"id":"vulyk_78_3","declaration":{"additional_info_text":"","notfull_lostpages":"","date":"2015-03-27T00:00:00","notfull":"","additional_info":"","url":"http://static.declarations.com.ua/declarations/chosen_ones/judges_batch/2070_kemin_volodymyr_dmytrovych.pdf"},"liabilities":{"54":{"sum_foreign_comment":"","sum_foreign_hidden":false,"sum_comment":"","sum_comment_unclear":false,"sum_hidden":false,"sum_comment_hidden":false,"sum":"","sum_foreign":""},"55":{"sum_foreign_comment":"","sum":"","sum_comment":"","sum_foreign":""},"56":{"sum_foreign_comment":"","sum":"","sum_comment":"","sum_foreign":""},"57":{"sum_foreign_comment":"","sum":"","sum_comment":"","sum_foreign":""},"58":{"sum_foreign_comment":"","sum":"","sum_comment":"","sum_unclear":false,"sum_foreign":""},"59":{"sum_foreign_comment":"","sum":"","sum_comment":"","sum_foreign":""},"60":{"sum_foreign_comment":"","sum":"","sum_comment":"","sum_comment_unclear":false,"sum_comment_hidden":false,"sum_foreign":""},"61":{"sum_foreign_comment":"","sum":"","sum_comment":"","sum_foreign":""},"62":{"sum_foreign_comment":"","sum":"","sum_hidden":false,"sum_comment":"","sum_foreign":""},"63":{"sum_foreign_comment":"","sum_foreign_hidden":false,"sum_comment":"","sum":"","sum_unclear":false,"sum_foreign":""},"64":{"sum_foreign_comment":"","sum_foreign_hidden":false,"sum_comment":"","sum_hidden":false,"sum":"","sum_foreign":""}},"ft_src":"заступник голови хустського районного суду закарпатської області\nЗакарпатська область\nЗагальний місцевий суд\n2520344512\nВолодимир\n2912800983\nКемінь Світлана Степанівна\nПодружжя\nКемінь Владислава Володимирівна\nДитина\nКемінь Ростислав Володимирович\nДитина\nДмитрович\nКемінь Володимир Дмитрович\nВолодимир Дмитрович Кемінь\nВолодимир Кемінь\nКемінь Володимир Дмитрович\nКемінь\nКемінь Володимир Дмитрович\nІза\nСело\nвул. Терешкової,19, 90436\nЗакарпатська область\nХустський\nна підставі свідоцтва про спадщину за заповітом\n2.4 куб. см.\n2008\nToyota Camry\nЗакарпатська область\nХустський р-н,с. Іза, вул. Терешкової,19\n230\nс. Іза, вул. Терешкової,19\nЗакарпатська область\n95\nЗакарпатська область\nс. Іза, вул. Терешкової,19\n163\n2014\n234061\n27526\n234061\n2.4 куб. см.\nна підставі свідоцтва про спадщину за заповітом\n2008\nToyota Camry\n2014\nПодружжя\nКемінь Світлана Степанівна\n2912800983\nДитина\nКемінь Владислава Володимирівна\nДитина\nКемінь Ростислав Володимирович\nКемінь Володимир Дмитрович\nВолодимир Дмитрович Кемінь\nВолодимир Кемінь\nКемінь Володимир Дмитрович\nКемінь Володимир Дмитрович\n2520344512\nВолодимир\nДмитрович\nЗагальний місцевий суд\nзаступник голови хустського районного суду закарпатської області\nЗакарпатська область\nКемінь\nСело\nвул. Терешкової,19, 90436\nЗакарпатська область\nІза\nХустський\n234061\n234061\n27526\n95\nЗакарпатська область\nс. Іза, вул. Терешкової,19\n163\nЗакарпатська область\nс. Іза, вул. Терешкової,19\nХустський р-н,с. Іза, вул. Терешкової,19\nЗакарпатська область\n230\n2912800983\nПодружжя\nКемінь Світлана Степанівна\nДитина\nКемінь Владислава Володимирівна\nДитина\nКемінь Ростислав Володимирович\n2520344512\nДмитрович\nКемінь\nВолодимир\nКемінь Володимир Дмитрович\nВолодимир Дмитрович Кемінь\nВолодимир Кемінь\nКемінь Володимир Дмитрович\nСело\nЗакарпатська область\nІза\nвул. Терешкової,19, 90436\nХустський\nЗакарпатська область\nзаступник голови хустського районного суду закарпатської області\nЗагальний місцевий суд\nКемінь Володимир Дмитрович\nна підставі свідоцтва про спадщину за заповітом\nToyota Camry\n2.4 куб. см.\n2008\n234061\n27526\n234061\nХустський р-н,с. Іза, вул. Терешкової,19\nЗакарпатська область\n230\nс. Іза, вул. Терешкової,19\nЗакарпатська область\n95\nс. Іза, вул. Терешкової,19\nЗакарпатська область\n163\n2014","general":{"inn":"2520344512","name":"Володимир","family":[{"inn":"2912800983","relations":"Подружжя","relations_other":"","inn_hidden":true,"family_name":"Кемінь Світлана Степанівна","name_hidden":false,"name_unclear":true},{"inn":"","relations":"Дитина","relations_other":"","inn_hidden":true,"family_name":"Кемінь Владислава Володимирівна","name_hidden":false,"name_unclear":true},{"inn":"","relations":"Дитина","relations_other":"","inn_hidden":true,"family_name":"Кемінь Ростислав Володимирович","name_unclear":false}],"patronymic":"Дмитрович","inn_hidden":false,"family_raw":"","last_name":"Кемінь","post":{"post_unclear":false,"post":"заступник голови хустського районного суду закарпатської області","post_hidden":false,"region":"Закарпатська область","region_hidden":false,"office":"Загальний місцевий суд","office_hidden":false},"last_name_unclear":true,"full_name":"Кемінь Володимир Дмитрович","addresses":[{"place_district":"Хустський","place_city_hidden":false,"place_city":"Іза","place_city_type_hidden":false,"place_district_hidden":false,"place_city_type":"Село","place_address_hidden":false,"place_address":"вул. Терешкової,19, 90436","place_hidden":false,"place":"Закарпатська область"}],"full_name_suggest":{"output":"Кемінь Володимир Дмитрович","input":["Кемінь Володимир Дмитрович","Володимир Дмитрович Кемінь","Володимир Кемінь"]},"name_unclear":false},"source":"VULYK","estate":{"29":[{"space_unclear":true,"address_hidden":false,"region_hidden":false,"space_comment":"","space":"95","address":"с. Іза, вул. Терешкової,19","region":"Закарпатська область","costs_property":"","costs_rent_comment":"","space_units":"м²","costs_property_comment":"","costs_rent":""},{"costs_rent":"","region":"Закарпатська область","costs_property":"","costs_rent_comment":"","address_hidden":false,"space_comment":"","costs_property_comment":"","space_units":"м²","space":"163","address":"с. Іза, вул. Терешкової,19"}],"30":[{"space_hidden":false,"address_hidden":false,"region_hidden":false,"space_comment":"","space":"230","address":"Хустський р-н,с. Іза, вул. Терешкової,19","region":"Закарпатська область","costs_property":"","costs_rent_comment":"","space_units":"м²","costs_property_comment":"","costs_rent":""}]},"intro":{"declaration_year":"2014"}}],"declarationsLength":1,"analytics":[{"y":2014,"i":234061,"c":1,"fi":27526,"fh":230,"fha":1,"fl":258,"fla":2},{"y":2015,"i":254849,"c":1,"h":90.1,"ha":1,"l":2555,"la":2,"j":1}]}