{"2010":"","2016":"","Department":"Богуславський районний суд Київської області","Region":"Київська область","Position":"Суддя Богуславського районного суду Київської області","Name":"Кіхтенко Сергій Олександрович","Link":"https://drive.google.com/open?id=0BygiyWAl79DMc2tid3VKa0pRaW8","Note":"У меня","AdditionalNote":"","field8":"","field9":"","field10":"","Кількість справ":"","Оскаржені":"","Кількість скарг":0,"Кількість дисциплінарних стягнень":"","Клейма":"","Фото":"","Як живе":"","key":"kihtenko_sergiy_oleksandrovich","allDeclarations":[{"provider":"declarations.com.ua","document":{"income":{"5":{"family_comment":"","family_unclear":false,"value":"162467","family":"1266","comment":""},"6":{"value":"162467","family_comment":"","value_unclear":false,"family_unclear":false,"family":"1266","comment":""},"7":{"value":"","family_comment":"","value_unclear":false,"family_unclear":false,"source_name":"","family":"","comment":"","source_name_hidden":false},"8":{"family_comment":"","value":"","family":"","comment":""},"9":{"family_comment":"","value":"","family":"","comment":""},"10":{"family_comment":"","value":"","value_unclear":false,"family":"","comment":""},"11":{"family_comment":"","value":"","family":"","comment":""},"12":{"family_comment":"","value":"","family":"","comment":""},"13":{"family_comment":"","value":"","family":"","comment":""},"14":{"family_comment":"","value":"","family":"","comment":""},"15":{"family_comment":"","value":"","family":"","comment":""},"16":{"family_comment":"","value":"","family":"","comment":""},"17":{"family_comment":"","value":"","family":"","comment":""},"18":{"family_comment":"","value":"","family":"","comment":""},"19":{"family_comment":"","value":"","family":"","comment":""},"20":{"value":"","value_unclear":false,"comment_hidden":false,"family_comment":"","comment_unclear":false,"comment":"","family":""}},"vehicle":{"35":[{"year_hidden":false,"brand_info":"2.4 л., 160 к.с.","sum_rent_comment":"","year":"2008","brand_info_hidden":false,"year_unclear":false,"sum_rent":"","sum":"","brand":"Mitsubishi","sum_comment":"","brand_unclear":false,"brand_hidden":false,"sum_unclear":false}]},"id":"vulyk_96_31","declaration":{"additional_info_text":"","notfull_lostpages":"","date":"2016-03-29T00:00:00","notfull":"","additional_info":"","url":"http://static.declarations.com.ua/declarations/chosen_ones/judges_batch/245_kikhtenko_serhii_oleksandrovych_2015.pdf"},"liabilities":{"54":{"sum_foreign_comment":"","sum":"","sum_comment":"","sum_hidden":false,"sum_comment_hidden":false,"sum_foreign":""},"55":{"sum_foreign_comment":"","sum":"","sum_comment":"","sum_foreign":""},"56":{"sum_foreign_comment":"","sum":"","sum_comment":"","sum_unclear":false,"sum_foreign":""},"57":{"sum_foreign_comment":"","sum_comment_hidden":false,"sum":"","sum_comment":"","sum_foreign":""},"58":{"sum_foreign_comment":"","sum":"","sum_comment":"","sum_comment_hidden":false,"sum_unclear":false,"sum_foreign":""},"59":{"sum_foreign_comment":"","sum":"","sum_comment":"","sum_foreign":""},"60":{"sum_foreign_comment":"","sum_comment_hidden":false,"sum":"","sum_comment":"","sum_foreign":""},"61":{"sum_foreign_comment":"","sum":"","sum_comment":"","sum_foreign":""},"62":{"sum_foreign_comment":"","sum":"","sum_comment":"","sum_foreign":""},"63":{"sum_foreign_comment":"","sum_comment_hidden":false,"sum":"","sum_comment":"","sum_foreign":""},"64":{"sum_foreign_comment":"","sum_comment_hidden":false,"sum":"","sum_comment":"","sum_foreign":""}},"ft_src":"Богуслав\n09700\nКиївська область\nсуддя богуславського районного суду київської області\nКиївська область\nЗагальний місцевий суд\nСергій\nКіхтенко Тетяна Олександрівна\nПодружжя\nКіхтенко Кирило Сергійович\nДитина\nОлександрович\nКіхтенко Сергій Олександрович\nКіхтенко\nКіхтенко Сергій Олександрович\nСергій Олександрович Кіхтенко\nСергій Кіхтенко\nКіхтенко Сергій Олександрович\n2.4 л., 160 к.с.\nMitsubishi\n2008\nЧеркаська область\nм. Черкаси\n17.5\nм. Корсунь-Шевченківський\n65\nЧеркаська область\n2015\n1266\n162467\n1266\n162467\n2.4 л., 160 к.с.\nMitsubishi\n2008\n2015\nКіхтенко Сергій Олександрович\nСергій Олександрович Кіхтенко\nСергій Кіхтенко\nКіхтенко Сергій Олександрович\nКіхтенко Сергій Олександрович\nСергій\nКіхтенко\nКиївська область\nсуддя богуславського районного суду київської області\nЗагальний місцевий суд\nОлександрович\n09700\nКиївська область\nБогуслав\nПодружжя\nКіхтенко Тетяна Олександрівна\nДитина\nКіхтенко Кирило Сергійович\n1266\n162467\n162467\n1266\nм. Черкаси\nЧеркаська область\n17.5\n65\nм. Корсунь-Шевченківський\nЧеркаська область\nКіхтенко Тетяна Олександрівна\nПодружжя\nДитина\nКіхтенко Кирило Сергійович\nСергій\nОлександрович\nКіхтенко\nКіхтенко Сергій Олександрович\nСергій Олександрович Кіхтенко\nСергій Кіхтенко\nКіхтенко Сергій Олександрович\nКиївська область\nБогуслав\n09700\nсуддя богуславського районного суду київської області\nКиївська область\nЗагальний місцевий суд\nКіхтенко Сергій Олександрович\nMitsubishi\n2.4 л., 160 к.с.\n2008\n1266\n162467\n162467\n1266\nм. Черкаси\nЧеркаська область\n17.5\n65\nм. Корсунь-Шевченківський\nЧеркаська область\n2015","general":{"inn":"","name":"Сергій","family":[{"inn":"","inn_hidden":true,"inn_unclear":false,"relations_hidden":false,"relations_other":"","relations":"Подружжя","name_hidden":true,"family_name":"Кіхтенко Тетяна Олександрівна","name_unclear":false},{"inn":"","relations":"Дитина","relations_other":"","inn_hidden":false,"family_name":"Кіхтенко Кирило Сергійович","name_hidden":false,"name_unclear":false}],"patronymic":"Олександрович","inn_hidden":true,"family_raw":"","last_name":"Кіхтенко","post":{"office":"Загальний місцевий суд","region":"Київська область","office_unclear":false,"post":"суддя богуславського районного суду київської області"},"full_name":"Кіхтенко Сергій Олександрович","addresses":[{"place_district":"","place_city_hidden":false,"place_city":"Богуслав","place_city_type_hidden":false,"place_district_hidden":false,"place_city_type":"Місто","place_address_hidden":true,"place_address":"09700","place_hidden":false,"place":"Київська область"}],"patronymic_hidden":false,"full_name_suggest":{"output":"Кіхтенко Сергій Олександрович","input":["Кіхтенко Сергій Олександрович","Сергій Олександрович Кіхтенко","Сергій Кіхтенко"]}},"source":"VULYK","estate":{"25":[{"space_comment_unclear":false,"space_unclear":false,"costs":"","costs_comment":"","address_hidden":false,"region_hidden":false,"space_comment":"","space_hidden":false,"space":"65","address":"м. Корсунь-Шевченківський","costs_rent_comment_unclear":false,"region":"Черкаська область","address_unclear":false,"costs_rent_comment":"","costs_unclear":false,"space_comment_hidden":false,"space_units":"м²","costs_rent":""}],"31":[{"space_unclear":false,"address_hidden":false,"region_hidden":false,"space_comment":"","space_hidden":false,"space":"17.5","address":"м. Черкаси","region":"Черкаська область","costs_property":"","costs_rent_comment":"","address_unclear":false,"space_units":"м²","costs_property_comment":"","costs_rent":""}]},"intro":{"declaration_year":"2015","isnotdeclaration":""}}},{"provider":"declarations.com.ua","document":{"income":{"5":{"value":"201608","family_comment":"","value_unclear":false,"family_unclear":false,"family":"8790","comment":""},"6":{"family_comment":"","value":"200685","value_unclear":false,"family":"8790","comment":""},"7":{"value":"923","value_unclear":false,"family_comment":"","source_name":"Богуславський гуманітарний коледж ім. І. С. Нечуя-Левицького","family":"","comment":""},"8":{"family_comment":"","value":"","family":"","comment":""},"9":{"value":"","family_comment":"","value_unclear":false,"family_unclear":false,"family":"","comment":""},"10":{"family_comment":"","value":"","comment_unclear":false,"family":"","comment":""},"11":{"family_comment":"","value":"","family":"","comment":""},"12":{"family_comment":"","value":"","family":"","comment":""},"13":{"family_comment":"","value":"","value_unclear":false,"family":"","comment":""},"14":{"family_comment":"","value":"","family":"","comment":""},"15":{"family_comment":"","value":"","family":"","comment":""},"16":{"family_comment":"","family_unclear":false,"value":"","family":"","comment":""},"17":{"family_comment":"","family_unclear":false,"value":"","family":"","comment":""},"18":{"family_comment":"","value":"","family":"","comment":""},"19":{"family_comment":"","value":"","family":"","comment":""},"20":{"value":"","family_comment":"","value_unclear":false,"family_hidden":false,"value_hidden":false,"family_unclear":false,"comment_unclear":false,"comment":"","family":""}},"vehicle":{"35":[{"brand_info":"2.4 , 160","sum_rent_comment":"","brand_info_unclear":false,"year":"2008","brand_info_hidden":false,"sum_rent_comment_unclear":false,"sum_rent":"","sum":"","brand":"Mitsubishi","sum_comment":"","brand_unclear":false,"brand_hidden":false}]},"id":"vulyk_100_108","declaration":{"additional_info_text":"","notfull_lostpages":"","date":"2015-03-26T00:00:00","notfull":"","additional_info":"","url":"http://static.declarations.com.ua/declarations/chosen_ones/judges_batch/4312_kikhtenko_serhii_oleksandrovych.pdf"},"liabilities":{"54":{"sum_foreign_comment":"","sum":"","sum_comment":"","sum_comment_hidden":false,"sum_unclear":false,"sum_foreign":""},"55":{"sum_foreign_comment":"","sum":"","sum_comment":"","sum_foreign":""},"56":{"sum_foreign_comment":"","sum":"","sum_comment":"","sum_unclear":false,"sum_foreign":""},"57":{"sum_foreign_comment":"","sum":"","sum_comment":"","sum_comment_unclear":false,"sum_comment_hidden":false,"sum_unclear":false,"sum_foreign":""},"58":{"sum_foreign_comment":"","sum":"","sum_comment":"","sum_comment_hidden":false,"sum_unclear":false,"sum_foreign":""},"59":{"sum_foreign_comment":"","sum":"","sum_comment":"","sum_foreign":""},"60":{"sum_foreign_comment":"","sum_comment_hidden":false,"sum":"","sum_comment":"","sum_foreign":""},"61":{"sum_foreign_comment":"","sum":"","sum_comment":"","sum_foreign":""},"62":{"sum_foreign_comment":"","sum":"","sum_comment":"","sum_unclear":false,"sum_foreign":""},"63":{"sum_foreign_comment":"","sum_comment_hidden":false,"sum":"","sum_comment":"","sum_foreign":""},"64":{"sum_foreign_comment":"","sum_comment_hidden":false,"sum":"","sum_comment":"","sum_foreign":""}},"ft_src":"Богуслав\nКиївська область\nКіхтенко Сергій Олександрович\nсуддя богуславського районного суду київської області\nКиївська область\nЗагальний місцевий суд\nСергій\nКіхтенко Тетяна Олександрівна\nПодружжя\nКіхтенко Кирило Сергійович\nДитина\nКіхтенко Сергій Олександрович\nСергій Олександрович Кіхтенко\nСергій Кіхтенко\nКіхтенко Сергій Олександрович\nКіхтенко\nОлександрович\n2.4 , 160\nMitsubishi\n2008\nЧеркаська область\nм. Черкаси\n17.5\nм. Корсунь-Шевченківський\n65\nЧеркаська область\n2014\n8790\n200685\nБогуславський гуманітарний коледж ім. І. С. Нечуя-Левицького\n923\n8790\n201608\n2.4 , 160\nMitsubishi\n2008\n17.5\nЧеркаська область\nм. Черкаси\n65\nЧеркаська область\nм. Корсунь-Шевченківський\nПодружжя\nКіхтенко Тетяна Олександрівна\nДитина\nКіхтенко Кирило Сергійович\nОлександрович\nКиївська область\nБогуслав\nКіхтенко\nКіхтенко Сергій Олександрович\nСергій Олександрович Кіхтенко\nСергій Кіхтенко\nКіхтенко Сергій Олександрович\nКіхтенко Сергій Олександрович\nСергій\nЗагальний місцевий суд\nКиївська область\nсуддя богуславського районного суду київської області\n923\nБогуславський гуманітарний коледж ім. І. С. Нечуя-Левицького\n200685\n8790\n201608\n8790\n2014\nКіхтенко Тетяна Олександрівна\nПодружжя\nДитина\nКіхтенко Кирило Сергійович\nБогуслав\nКиївська область\nОлександрович\nКіхтенко\nКиївська область\nЗагальний місцевий суд\nсуддя богуславського районного суду київської області\nКіхтенко Сергій Олександрович\nКіхтенко Сергій Олександрович\nСергій Олександрович Кіхтенко\nСергій Кіхтенко\nКіхтенко Сергій Олександрович\nСергій\n2008\nMitsubishi\n2.4 , 160\n201608\n8790\n923\nБогуславський гуманітарний коледж ім. І. С. Нечуя-Левицького\n8790\n200685\nм. Черкаси\nЧеркаська область\n17.5\nм. Корсунь-Шевченківський\nЧеркаська область\n65\n2014","general":{"inn":"","inn_hidden":true,"last_name":"Кіхтенко","post":{"post_unclear":false,"region_unclear":false,"post":"суддя богуславського районного суду київської області","office":"Загальний місцевий суд","region":"Київська область","post_hidden":false,"office_unclear":false},"name":"Сергій","full_name":"Кіхтенко Сергій Олександрович","family_raw":"","addresses":[{"place_district":"","place_city_hidden":false,"place_city":"Богуслав","place_city_unclear":false,"place_district_hidden":false,"place_city_type":"Місто","place_address_hidden":true,"place_city_type_hidden":false,"place_address":"","place_hidden":false,"place":"Київська область"}],"family":[{"inn_hidden":true,"inn":"","name_hidden":true,"family_name":"Кіхтенко Тетяна Олександрівна","relations":"Подружжя","name_unclear":false},{"inn":"","relations":"Дитина","relations_other":"","inn_hidden":true,"family_name":"Кіхтенко Кирило Сергійович","name_hidden":false,"name_unclear":false}],"full_name_suggest":{"output":"Кіхтенко Сергій Олександрович","input":["Кіхтенко Сергій Олександрович","Сергій Олександрович Кіхтенко","Сергій Кіхтенко"]},"patronymic":"Олександрович"},"source":"VULYK","estate":{"25":[{"space_unclear":false,"costs":"","costs_comment":"","address_hidden":true,"region_hidden":false,"space_comment":"","space":"65","address":"м. Корсунь-Шевченківський","costs_comment_unclear":false,"region":"Черкаська область","address_unclear":false,"costs_rent_comment":"","space_comment_unclear":false,"space_units":"м²","costs_rent":""}],"31":[{"region_unclear":false,"space_unclear":false,"costs_property_comment_unclear":false,"address_hidden":true,"region_hidden":false,"space_comment":"","space":"17.5","address":"м. Черкаси","region":"Черкаська область","costs_property":"","costs_rent_comment":"","space_comment_unclear":false,"address_unclear":false,"space_units":"м²","costs_property_comment":"","costs_rent":""}]},"intro":{"declaration_year":"2014"}}},{"provider":"public-api.nazk.gov.ua","document":{"step_0":{"declarationType":"1","declarationYear1":"2015"},"step_1":{"city":"[Конфіденційна інформація]","region":"[Конфіденційна інформація]","street":"[Конфіденційна інформація]","country":"1","cityPath":"[Конфіденційна інформація]","cityType":"[Конфіденційна інформація]","district":"[Конфіденційна інформація]","lastname":"Кіхтенко","postCode":"[Конфіденційна інформація]","postType":"","workPost":"Суддя","firstname":"Сергій","workPlace":"Богуславський районний суд Київської області","middlename":"Олександрович","streetType":"[Конфіденційна інформація]","changedName":false,"countryPath":"","eng_postCode":"","postCategory":"","actual_street":"[Конфіденційна інформація]","actual_cityPath":"[Конфіденційна інформація]","actual_cityType":"[Конфіденційна інформація]","actual_postCode":"[Конфіденційна інформація]","actual_streetType":"[Конфіденційна інформація]","previous_lastname":"","corruptionAffected":"Ні","eng_actualPostCode":"[Конфіденційна інформація]","previous_firstname":"","previous_middlename":"","responsiblePosition":"Суддя суду загальної юрисдикції, суддя Конституційного Суду України","sameRegLivingAddress":"[Конфіденційна інформація]","postType_extendedstatus":"1","eng_sameRegLivingAddress":"[Конфіденційна інформація]","housePartNum_extendedstatus":"1","postCategory_extendedstatus":"1"},"step_2":{"1476688879050":{"lastname":"Кіхтенко","firstname":"Тетяна","middlename":"Олександрівна","changedName":false,"citizenship":"1","eng_lastname":"","no_taxNumber":false,"eng_firstname":"","eng_middlename":"","isNotApplicable":"","subjectRelation":"дружина","previous_lastname":"","previous_firstname":"","previous_middlename":"","previous_eng_lastname":"","previous_eng_firstname":"","previous_eng_middlename":""},"1476689348124":{"lastname":"Кіхтенко ","firstname":"Кирило","middlename":"Сергійович","changedName":false,"citizenship":"1","eng_lastname":"","no_taxNumber":true,"eng_firstname":"","eng_middlename":"","isNotApplicable":"","subjectRelation":"син","previous_lastname":"","previous_firstname":"","previous_middlename":"","previous_eng_lastname":"","previous_eng_firstname":"","previous_eng_middlename":""}},"step_3":{"1476689392259":{"city":"[Конфіденційна інформація]","person":"1","region":"[Конфіденційна інформація]","rights":{"1":{"citizen":"","ua_city":"","ua_street":"[Конфіденційна інформація]","ua_lastname":"","ua_postCode":"","eng_lastname":"","eng_postCode":"","rightBelongs":"1","ua_firstname":"","ukr_lastname":"","eng_firstname":"","ownershipType":"Власність","ua_middlename":"","ua_streetType":"[Конфіденційна інформація]","ukr_firstname":"","eng_middlename":"","otherOwnership":"","ukr_middlename":"","rights_cityPath":"","ua_company_name":"","eng_company_name":"","ukr_company_name":"","percent-ownership":"100","ua_street_extendedstatus":"","ua_houseNum_extendedstatus":"","ua_postCode_extendedstatus":"","eng_postCode_extendedstatus":"","ua_middlename_extendedstatus":"","eng_middlename_extendedstatus":"","ukr_middlename_extendedstatus":"","ua_housePartNum_extendedstatus":"","ua_apartmentsNum_extendedstatus":""}},"country":"1","cityPath":"[Конфіденційна інформація]","costDate":"14137","district":"[Конфіденційна інформація]","postCode":"[Конфіденційна інформація]","totalArea":"63,90","ua_street":"[Конфіденційна інформація]","objectType":"Квартира","owningDate":"10.08.2006","ua_cityType":"Корсунь-Шевченківський / Корсунь-Шевченківський Район / Черкаська Область / Україна","ua_postCode":"19400","ua_streetType":"[Конфіденційна інформація]","costAssessment":"","otherObjectType":"","costAssessment_extendedstatus":"1","ua_housePartNum_extendedstatus":"1"},"1476689496526":{"person":"1476688879050","region":"[Конфіденційна інформація]","rights":{"1476688879050":{"citizen":"","ua_city":"","ua_street":"[Конфіденційна інформація]","ua_lastname":"","ua_postCode":"","eng_lastname":"","eng_postCode":"","rightBelongs":"1476688879050","ua_firstname":"","ukr_lastname":"","eng_firstname":"","ownershipType":"Спільна власність","ua_middlename":"","ua_streetType":"[Конфіденційна інформація]","ukr_firstname":"","eng_middlename":"","otherOwnership":"","ukr_middlename":"","rights_cityPath":"","ua_company_name":"","eng_company_name":"","ukr_company_name":"","percent-ownership":"25","ua_street_extendedstatus":"","ua_houseNum_extendedstatus":"","ua_postCode_extendedstatus":"","eng_postCode_extendedstatus":"","ua_middlename_extendedstatus":"","eng_middlename_extendedstatus":"","ukr_middlename_extendedstatus":"","ua_housePartNum_extendedstatus":"","ua_apartmentsNum_extendedstatus":""},"1476689742895":{"citizen":"Громадянин України","ua_city":"Черкаси / Черкаська Область / Україна","ua_street":"[Конфіденційна інформація]","ua_lastname":"Костенко","ua_postCode":"18000","eng_lastname":"","eng_postCode":"","rightBelongs":"j","ua_firstname":"Олександр","ukr_lastname":"","eng_firstname":"","ownershipType":"Спільна власність","ua_middlename":"Петрович","ua_streetType":"[Конфіденційна інформація]","ukr_firstname":"","eng_middlename":"","otherOwnership":"","ukr_middlename":"","rights_cityPath":"1.2.71.1.1","ua_company_name":"","eng_company_name":"","ukr_company_name":"","percent-ownership":"25","ua_street_extendedstatus":"","ua_houseNum_extendedstatus":"","ua_postCode_extendedstatus":"","eng_postCode_extendedstatus":"","ua_taxNumber_extendedstatus":"1","ua_middlename_extendedstatus":"","eng_middlename_extendedstatus":"","ukr_middlename_extendedstatus":"","ua_housePartNum_extendedstatus":"1","ua_apartmentsNum_extendedstatus":""},"1476689816671":{"citizen":"Громадянин України","ua_city":"Черкаси / Черкаська Область / Україна","ua_street":"[Конфіденційна інформація]","ua_lastname":"Костенко","ua_postCode":"18000","eng_lastname":"","eng_postCode":"","rightBelongs":"j","ua_firstname":"Сергій","ukr_lastname":"","eng_firstname":"","ownershipType":"Спільна власність","ua_middlename":"Олександрович","ua_streetType":"[Конфіденційна інформація]","ukr_firstname":"","eng_middlename":"","otherOwnership":"","ukr_middlename":"","rights_cityPath":"1.2.71.1.1","ua_company_name":"","eng_company_name":"","ukr_company_name":"","percent-ownership":"25","ua_street_extendedstatus":"","ua_houseNum_extendedstatus":"","ua_postCode_extendedstatus":"","eng_postCode_extendedstatus":"","ua_taxNumber_extendedstatus":"1","ua_middlename_extendedstatus":"","eng_middlename_extendedstatus":"","ukr_middlename_extendedstatus":"","ua_housePartNum_extendedstatus":"1","ua_apartmentsNum_extendedstatus":""},"1476689861790":{"citizen":"Громадянин України","ua_city":"Черкаси / Черкаська Область / Україна","ua_street":"[Конфіденційна інформація]","ua_lastname":"Костенко","ua_postCode":"18000","eng_lastname":"","eng_postCode":"","rightBelongs":"j","ua_firstname":"Любов","ukr_lastname":"","eng_firstname":"","ownershipType":"Спільна власність","ua_middlename":"Іванівна","ua_streetType":"[Конфіденційна інформація]","ukr_firstname":"","eng_middlename":"","otherOwnership":"","ukr_middlename":"","rights_cityPath":"1.2.71.1.1","ua_company_name":"","eng_company_name":"","ukr_company_name":"","percent-ownership":"25","ua_street_extendedstatus":"","ua_houseNum_extendedstatus":"","ua_postCode_extendedstatus":"","eng_postCode_extendedstatus":"","ua_taxNumber_extendedstatus":"1","ua_middlename_extendedstatus":"","eng_middlename_extendedstatus":"","ukr_middlename_extendedstatus":"","ua_housePartNum_extendedstatus":"1","ua_apartmentsNum_extendedstatus":""}},"country":"1","cityPath":"[Конфіденційна інформація]","costDate":"","district":"[Конфіденційна інформація]","postCode":"[Конфіденційна інформація]","totalArea":"69,30","ua_street":"[Конфіденційна інформація]","objectType":"Квартира","owningDate":"26.04.2005","ua_cityType":"Черкаси / Черкаська Область / Україна","ua_postCode":"18000","ua_streetType":"[Конфіденційна інформація]","costAssessment":"","otherObjectType":"","costDate_extendedstatus":"2","costAssessment_extendedstatus":"1","ua_housePartNum_extendedstatus":"1"},"1476774972123":{"city":"[Конфіденційна інформація]","person":"1","region":"[Конфіденційна інформація]","rights":{"1":{"citizen":"","ua_city":"","ua_street":"[Конфіденційна інформація]","ua_lastname":"","ua_postCode":"","eng_lastname":"","eng_postCode":"","rightBelongs":"1","ua_firstname":"","ukr_lastname":"","eng_firstname":"","ownershipType":"Оренда","ua_middlename":"","ua_streetType":"[Конфіденційна інформація]","ukr_firstname":"","eng_middlename":"","otherOwnership":"","ukr_middlename":"","rights_cityPath":"","ua_company_name":"","eng_company_name":"","ukr_company_name":"","percent-ownership":"100","ua_street_extendedstatus":"","ua_houseNum_extendedstatus":"","ua_postCode_extendedstatus":"","eng_postCode_extendedstatus":"","ua_middlename_extendedstatus":"","eng_middlename_extendedstatus":"","ukr_middlename_extendedstatus":"","ua_housePartNum_extendedstatus":"","ua_apartmentsNum_extendedstatus":""}},"country":"1","cityPath":"[Конфіденційна інформація]","costDate":"","district":"[Конфіденційна інформація]","postCode":"[Конфіденційна інформація]","totalArea":"40,40","ua_street":"[Конфіденційна інформація]","objectType":"Квартира","owningDate":"22.04.2010","ua_cityType":"Богуслав / Богуславський Район / Київська Область / Україна","ua_postCode":"09701","ua_streetType":"[Конфіденційна інформація]","costAssessment":"","otherObjectType":"","costDate_extendedstatus":"2","costAssessment_extendedstatus":"1","ua_housePartNum_extendedstatus":"1"}},"step_4":[],"step_5":[],"step_6":{"1476689914220":{"brand":"MITSUBISHI","model":"OUTLANDER","person":"1","rights":{"1":{"citizen":"","ua_city":"","ua_street":"[Конфіденційна інформація]","ua_lastname":"","ua_postCode":"","eng_lastname":"","eng_postCode":"","rightBelongs":"1","ua_firstname":"","ukr_lastname":"","eng_firstname":"","ownershipType":"Власність","ua_middlename":"","ua_streetType":"[Конфіденційна інформація]","ukr_firstname":"","eng_middlename":"","otherOwnership":"","ukr_middlename":"","rights_cityPath":"","ua_company_name":"","eng_company_name":"","ukr_company_name":"","percent-ownership":"","ua_street_extendedstatus":"","ua_houseNum_extendedstatus":"","ua_postCode_extendedstatus":"","eng_postCode_extendedstatus":"","ua_middlename_extendedstatus":"","eng_middlename_extendedstatus":"","ukr_middlename_extendedstatus":"","ua_housePartNum_extendedstatus":"","ua_apartmentsNum_extendedstatus":""}},"costDate":"197000","objectType":"Автомобіль легковий","owningDate":"16.12.2008","typeProperty":"","graduationYear":"2008","otherTypeProperty":""}},"step_7":[],"step_8":[],"step_9":[],"step_10":[],"step_11":{"1476690160601":{"person":"1","rights":{"1":{"citizen":"","ua_city":"","ua_street":"[Конфіденційна інформація]","ua_lastname":"","ua_postCode":"","eng_lastname":"","eng_postCode":"","rightBelongs":"1","ua_firstname":"","ukr_lastname":"","eng_firstname":"","ownershipType":"Власність","ua_middlename":"","ua_streetType":"[Конфіденційна інформація]","ukr_firstname":"","eng_middlename":"","otherOwnership":"","ukr_middlename":"","rights_cityPath":"","ua_company_name":"","eng_company_name":"","ukr_company_name":"","percent-ownership":"","ua_street_extendedstatus":"","ua_houseNum_extendedstatus":"","ua_postCode_extendedstatus":"","eng_postCode_extendedstatus":"","ua_middlename_extendedstatus":"","eng_middlename_extendedstatus":"","ukr_middlename_extendedstatus":"","ua_housePartNum_extendedstatus":"","ua_apartmentsNum_extendedstatus":""}},"objectType":"Заробітна плата отримана за основним місцем роботи","sizeIncome":"162467","incomeSource":"j","source_citizen":"Юридична особа, зареєстрована в Україні","otherObjectType":"","source_ua_lastname":"","source_eng_lastname":"","source_ua_firstname":"","source_ukr_lastname":"","source_eng_firstname":"","source_ua_middlename":"","source_ukr_firstname":"","source_eng_middlename":"","source_ukr_middlename":"","source_ua_company_name":"ТЕРИТОРІАЛЬНЕ УПРАВЛІННЯ ДЕРЖАВНОЇ СУДОВОЇ АДМІНІСТРАЦІЇ УКРАЇНИ В КИЇВСЬКІЙ ОБЛАСТІ ( ТУ ДСАУ В КИЇВСЬКІЙ ОБЛАСТІ )","source_eng_company_name":"","source_ukr_company_name":"","source_ua_sameRegLivingAddress":"","source_eng_sameRegLivingAddress":""},"1476690228111":{"person":"1476688879050","rights":{"1476688879050":{"citizen":"","ua_city":"","ua_street":"[Конфіденційна інформація]","ua_lastname":"","ua_postCode":"","eng_lastname":"","eng_postCode":"","rightBelongs":"1476688879050","ua_firstname":"","ukr_lastname":"","eng_firstname":"","ownershipType":"Власність","ua_middlename":"","ua_streetType":"[Конфіденційна інформація]","ukr_firstname":"","eng_middlename":"","otherOwnership":"","ukr_middlename":"","rights_cityPath":"","ua_company_name":"","eng_company_name":"","ukr_company_name":"","percent-ownership":"","ua_street_extendedstatus":"","ua_houseNum_extendedstatus":"","ua_postCode_extendedstatus":"","eng_postCode_extendedstatus":"","ua_middlename_extendedstatus":"","eng_middlename_extendedstatus":"","ukr_middlename_extendedstatus":"","ua_housePartNum_extendedstatus":"","ua_apartmentsNum_extendedstatus":""}},"objectType":"Інше","sizeIncome":"1266","incomeSource":"j","source_citizen":"Юридична особа, зареєстрована в Україні","otherObjectType":"Допомога по догляду за дитиною","source_ua_lastname":"","source_eng_lastname":"","source_ua_firstname":"","source_ukr_lastname":"","source_eng_firstname":"","source_ua_middlename":"","source_ukr_firstname":"","source_eng_middlename":"","source_ukr_middlename":"","source_ua_company_name":"УПРАВЛІННЯ СОЦІАЛЬНОГО ЗАХИСТУ НАСЕЛЕННЯ БОГУСЛАВСЬКОЇ РАЙОННОЇ ДЕРЖАВНОЇ АДМІНІСТРАЦІЇ","source_eng_company_name":"","source_ukr_company_name":"","source_ua_sameRegLivingAddress":"","source_eng_sameRegLivingAddress":""}},"step_12":[],"step_13":[],"step_14":[],"step_15":[],"step_16":[],"id":"1c8f4f93-acf9-4423-97af-c752c662245a"}}],"declarations":[{"income":{"5":{"family_comment":"","family_unclear":false,"value":"162467","family":"1266","comment":""},"6":{"value":"162467","family_comment":"","value_unclear":false,"family_unclear":false,"family":"1266","comment":""},"7":{"value":"","family_comment":"","value_unclear":false,"family_unclear":false,"source_name":"","family":"","comment":"","source_name_hidden":false},"8":{"family_comment":"","value":"","family":"","comment":""},"9":{"family_comment":"","value":"","family":"","comment":""},"10":{"family_comment":"","value":"","value_unclear":false,"family":"","comment":""},"11":{"family_comment":"","value":"","family":"","comment":""},"12":{"family_comment":"","value":"","family":"","comment":""},"13":{"family_comment":"","value":"","family":"","comment":""},"14":{"family_comment":"","value":"","family":"","comment":""},"15":{"family_comment":"","value":"","family":"","comment":""},"16":{"family_comment":"","value":"","family":"","comment":""},"17":{"family_comment":"","value":"","family":"","comment":""},"18":{"family_comment":"","value":"","family":"","comment":""},"19":{"family_comment":"","value":"","family":"","comment":""},"20":{"value":"","value_unclear":false,"comment_hidden":false,"family_comment":"","comment_unclear":false,"comment":"","family":""}},"vehicle":{"35":[{"year_hidden":false,"brand_info":"2.4 л., 160 к.с.","sum_rent_comment":"","year":"2008","brand_info_hidden":false,"year_unclear":false,"sum_rent":"","sum":"","brand":"Mitsubishi","sum_comment":"","brand_unclear":false,"brand_hidden":false,"sum_unclear":false}]},"id":"vulyk_96_31","declaration":{"additional_info_text":"","notfull_lostpages":"","date":"2016-03-29T00:00:00","notfull":"","additional_info":"","url":"http://static.declarations.com.ua/declarations/chosen_ones/judges_batch/245_kikhtenko_serhii_oleksandrovych_2015.pdf"},"liabilities":{"54":{"sum_foreign_comment":"","sum":"","sum_comment":"","sum_hidden":false,"sum_comment_hidden":false,"sum_foreign":""},"55":{"sum_foreign_comment":"","sum":"","sum_comment":"","sum_foreign":""},"56":{"sum_foreign_comment":"","sum":"","sum_comment":"","sum_unclear":false,"sum_foreign":""},"57":{"sum_foreign_comment":"","sum_comment_hidden":false,"sum":"","sum_comment":"","sum_foreign":""},"58":{"sum_foreign_comment":"","sum":"","sum_comment":"","sum_comment_hidden":false,"sum_unclear":false,"sum_foreign":""},"59":{"sum_foreign_comment":"","sum":"","sum_comment":"","sum_foreign":""},"60":{"sum_foreign_comment":"","sum_comment_hidden":false,"sum":"","sum_comment":"","sum_foreign":""},"61":{"sum_foreign_comment":"","sum":"","sum_comment":"","sum_foreign":""},"62":{"sum_foreign_comment":"","sum":"","sum_comment":"","sum_foreign":""},"63":{"sum_foreign_comment":"","sum_comment_hidden":false,"sum":"","sum_comment":"","sum_foreign":""},"64":{"sum_foreign_comment":"","sum_comment_hidden":false,"sum":"","sum_comment":"","sum_foreign":""}},"ft_src":"Богуслав\n09700\nКиївська область\nсуддя богуславського районного суду київської області\nКиївська область\nЗагальний місцевий суд\nСергій\nКіхтенко Тетяна Олександрівна\nПодружжя\nКіхтенко Кирило Сергійович\nДитина\nОлександрович\nКіхтенко Сергій Олександрович\nКіхтенко\nКіхтенко Сергій Олександрович\nСергій Олександрович Кіхтенко\nСергій Кіхтенко\nКіхтенко Сергій Олександрович\n2.4 л., 160 к.с.\nMitsubishi\n2008\nЧеркаська область\nм. Черкаси\n17.5\nм. Корсунь-Шевченківський\n65\nЧеркаська область\n2015\n1266\n162467\n1266\n162467\n2.4 л., 160 к.с.\nMitsubishi\n2008\n2015\nКіхтенко Сергій Олександрович\nСергій Олександрович Кіхтенко\nСергій Кіхтенко\nКіхтенко Сергій Олександрович\nКіхтенко Сергій Олександрович\nСергій\nКіхтенко\nКиївська область\nсуддя богуславського районного суду київської області\nЗагальний місцевий суд\nОлександрович\n09700\nКиївська область\nБогуслав\nПодружжя\nКіхтенко Тетяна Олександрівна\nДитина\nКіхтенко Кирило Сергійович\n1266\n162467\n162467\n1266\nм. Черкаси\nЧеркаська область\n17.5\n65\nм. Корсунь-Шевченківський\nЧеркаська область\nКіхтенко Тетяна Олександрівна\nПодружжя\nДитина\nКіхтенко Кирило Сергійович\nСергій\nОлександрович\nКіхтенко\nКіхтенко Сергій Олександрович\nСергій Олександрович Кіхтенко\nСергій Кіхтенко\nКіхтенко Сергій Олександрович\nКиївська область\nБогуслав\n09700\nсуддя богуславського районного суду київської області\nКиївська область\nЗагальний місцевий суд\nКіхтенко Сергій Олександрович\nMitsubishi\n2.4 л., 160 к.с.\n2008\n1266\n162467\n162467\n1266\nм. Черкаси\nЧеркаська область\n17.5\n65\nм. Корсунь-Шевченківський\nЧеркаська область\n2015","general":{"inn":"","name":"Сергій","family":[{"inn":"","inn_hidden":true,"inn_unclear":false,"relations_hidden":false,"relations_other":"","relations":"Подружжя","name_hidden":true,"family_name":"Кіхтенко Тетяна Олександрівна","name_unclear":false},{"inn":"","relations":"Дитина","relations_other":"","inn_hidden":false,"family_name":"Кіхтенко Кирило Сергійович","name_hidden":false,"name_unclear":false}],"patronymic":"Олександрович","inn_hidden":true,"family_raw":"","last_name":"Кіхтенко","post":{"office":"Загальний місцевий суд","region":"Київська область","office_unclear":false,"post":"суддя богуславського районного суду київської області"},"full_name":"Кіхтенко Сергій Олександрович","addresses":[{"place_district":"","place_city_hidden":false,"place_city":"Богуслав","place_city_type_hidden":false,"place_district_hidden":false,"place_city_type":"Місто","place_address_hidden":true,"place_address":"09700","place_hidden":false,"place":"Київська область"}],"patronymic_hidden":false,"full_name_suggest":{"output":"Кіхтенко Сергій Олександрович","input":["Кіхтенко Сергій Олександрович","Сергій Олександрович Кіхтенко","Сергій Кіхтенко"]}},"source":"VULYK","estate":{"25":[{"space_comment_unclear":false,"space_unclear":false,"costs":"","costs_comment":"","address_hidden":false,"region_hidden":false,"space_comment":"","space_hidden":false,"space":"65","address":"м. Корсунь-Шевченківський","costs_rent_comment_unclear":false,"region":"Черкаська область","address_unclear":false,"costs_rent_comment":"","costs_unclear":false,"space_comment_hidden":false,"space_units":"м²","costs_rent":""}],"31":[{"space_unclear":false,"address_hidden":false,"region_hidden":false,"space_comment":"","space_hidden":false,"space":"17.5","address":"м. Черкаси","region":"Черкаська область","costs_property":"","costs_rent_comment":"","address_unclear":false,"space_units":"м²","costs_property_comment":"","costs_rent":""}]},"intro":{"declaration_year":"2015","isnotdeclaration":""}},{"income":{"5":{"value":"201608","family_comment":"","value_unclear":false,"family_unclear":false,"family":"8790","comment":""},"6":{"family_comment":"","value":"200685","value_unclear":false,"family":"8790","comment":""},"7":{"value":"923","value_unclear":false,"family_comment":"","source_name":"Богуславський гуманітарний коледж ім. І. С. Нечуя-Левицького","family":"","comment":""},"8":{"family_comment":"","value":"","family":"","comment":""},"9":{"value":"","family_comment":"","value_unclear":false,"family_unclear":false,"family":"","comment":""},"10":{"family_comment":"","value":"","comment_unclear":false,"family":"","comment":""},"11":{"family_comment":"","value":"","family":"","comment":""},"12":{"family_comment":"","value":"","family":"","comment":""},"13":{"family_comment":"","value":"","value_unclear":false,"family":"","comment":""},"14":{"family_comment":"","value":"","family":"","comment":""},"15":{"family_comment":"","value":"","family":"","comment":""},"16":{"family_comment":"","family_unclear":false,"value":"","family":"","comment":""},"17":{"family_comment":"","family_unclear":false,"value":"","family":"","comment":""},"18":{"family_comment":"","value":"","family":"","comment":""},"19":{"family_comment":"","value":"","family":"","comment":""},"20":{"value":"","family_comment":"","value_unclear":false,"family_hidden":false,"value_hidden":false,"family_unclear":false,"comment_unclear":false,"comment":"","family":""}},"vehicle":{"35":[{"brand_info":"2.4 , 160","sum_rent_comment":"","brand_info_unclear":false,"year":"2008","brand_info_hidden":false,"sum_rent_comment_unclear":false,"sum_rent":"","sum":"","brand":"Mitsubishi","sum_comment":"","brand_unclear":false,"brand_hidden":false}]},"id":"vulyk_100_108","declaration":{"additional_info_text":"","notfull_lostpages":"","date":"2015-03-26T00:00:00","notfull":"","additional_info":"","url":"http://static.declarations.com.ua/declarations/chosen_ones/judges_batch/4312_kikhtenko_serhii_oleksandrovych.pdf"},"liabilities":{"54":{"sum_foreign_comment":"","sum":"","sum_comment":"","sum_comment_hidden":false,"sum_unclear":false,"sum_foreign":""},"55":{"sum_foreign_comment":"","sum":"","sum_comment":"","sum_foreign":""},"56":{"sum_foreign_comment":"","sum":"","sum_comment":"","sum_unclear":false,"sum_foreign":""},"57":{"sum_foreign_comment":"","sum":"","sum_comment":"","sum_comment_unclear":false,"sum_comment_hidden":false,"sum_unclear":false,"sum_foreign":""},"58":{"sum_foreign_comment":"","sum":"","sum_comment":"","sum_comment_hidden":false,"sum_unclear":false,"sum_foreign":""},"59":{"sum_foreign_comment":"","sum":"","sum_comment":"","sum_foreign":""},"60":{"sum_foreign_comment":"","sum_comment_hidden":false,"sum":"","sum_comment":"","sum_foreign":""},"61":{"sum_foreign_comment":"","sum":"","sum_comment":"","sum_foreign":""},"62":{"sum_foreign_comment":"","sum":"","sum_comment":"","sum_unclear":false,"sum_foreign":""},"63":{"sum_foreign_comment":"","sum_comment_hidden":false,"sum":"","sum_comment":"","sum_foreign":""},"64":{"sum_foreign_comment":"","sum_comment_hidden":false,"sum":"","sum_comment":"","sum_foreign":""}},"ft_src":"Богуслав\nКиївська область\nКіхтенко Сергій Олександрович\nсуддя богуславського районного суду київської області\nКиївська область\nЗагальний місцевий суд\nСергій\nКіхтенко Тетяна Олександрівна\nПодружжя\nКіхтенко Кирило Сергійович\nДитина\nКіхтенко Сергій Олександрович\nСергій Олександрович Кіхтенко\nСергій Кіхтенко\nКіхтенко Сергій Олександрович\nКіхтенко\nОлександрович\n2.4 , 160\nMitsubishi\n2008\nЧеркаська область\nм. Черкаси\n17.5\nм. Корсунь-Шевченківський\n65\nЧеркаська область\n2014\n8790\n200685\nБогуславський гуманітарний коледж ім. І. С. Нечуя-Левицького\n923\n8790\n201608\n2.4 , 160\nMitsubishi\n2008\n17.5\nЧеркаська область\nм. Черкаси\n65\nЧеркаська область\nм. Корсунь-Шевченківський\nПодружжя\nКіхтенко Тетяна Олександрівна\nДитина\nКіхтенко Кирило Сергійович\nОлександрович\nКиївська область\nБогуслав\nКіхтенко\nКіхтенко Сергій Олександрович\nСергій Олександрович Кіхтенко\nСергій Кіхтенко\nКіхтенко Сергій Олександрович\nКіхтенко Сергій Олександрович\nСергій\nЗагальний місцевий суд\nКиївська область\nсуддя богуславського районного суду київської області\n923\nБогуславський гуманітарний коледж ім. І. С. Нечуя-Левицького\n200685\n8790\n201608\n8790\n2014\nКіхтенко Тетяна Олександрівна\nПодружжя\nДитина\nКіхтенко Кирило Сергійович\nБогуслав\nКиївська область\nОлександрович\nКіхтенко\nКиївська область\nЗагальний місцевий суд\nсуддя богуславського районного суду київської області\nКіхтенко Сергій Олександрович\nКіхтенко Сергій Олександрович\nСергій Олександрович Кіхтенко\nСергій Кіхтенко\nКіхтенко Сергій Олександрович\nСергій\n2008\nMitsubishi\n2.4 , 160\n201608\n8790\n923\nБогуславський гуманітарний коледж ім. І. С. Нечуя-Левицького\n8790\n200685\nм. Черкаси\nЧеркаська область\n17.5\nм. Корсунь-Шевченківський\nЧеркаська область\n65\n2014","general":{"inn":"","inn_hidden":true,"last_name":"Кіхтенко","post":{"post_unclear":false,"region_unclear":false,"post":"суддя богуславського районного суду київської області","office":"Загальний місцевий суд","region":"Київська область","post_hidden":false,"office_unclear":false},"name":"Сергій","full_name":"Кіхтенко Сергій Олександрович","family_raw":"","addresses":[{"place_district":"","place_city_hidden":false,"place_city":"Богуслав","place_city_unclear":false,"place_district_hidden":false,"place_city_type":"Місто","place_address_hidden":true,"place_city_type_hidden":false,"place_address":"","place_hidden":false,"place":"Київська область"}],"family":[{"inn_hidden":true,"inn":"","name_hidden":true,"family_name":"Кіхтенко Тетяна Олександрівна","relations":"Подружжя","name_unclear":false},{"inn":"","relations":"Дитина","relations_other":"","inn_hidden":true,"family_name":"Кіхтенко Кирило Сергійович","name_hidden":false,"name_unclear":false}],"full_name_suggest":{"output":"Кіхтенко Сергій Олександрович","input":["Кіхтенко Сергій Олександрович","Сергій Олександрович Кіхтенко","Сергій Кіхтенко"]},"patronymic":"Олександрович"},"source":"VULYK","estate":{"25":[{"space_unclear":false,"costs":"","costs_comment":"","address_hidden":true,"region_hidden":false,"space_comment":"","space":"65","address":"м. Корсунь-Шевченківський","costs_comment_unclear":false,"region":"Черкаська область","address_unclear":false,"costs_rent_comment":"","space_comment_unclear":false,"space_units":"м²","costs_rent":""}],"31":[{"region_unclear":false,"space_unclear":false,"costs_property_comment_unclear":false,"address_hidden":true,"region_hidden":false,"space_comment":"","space":"17.5","address":"м. Черкаси","region":"Черкаська область","costs_property":"","costs_rent_comment":"","space_comment_unclear":false,"address_unclear":false,"space_units":"м²","costs_property_comment":"","costs_rent":""}]},"intro":{"declaration_year":"2014"}}],"declarationsLength":2,"analytics":[{"y":2015,"i":162467,"c":1,"k":65,"ka":1,"fi":1266,"ff":17.5,"ffa":1},{"y":2014,"i":201608,"c":1,"k":65,"ka":1,"fi":8790,"ff":17.5,"ffa":1}]}