{"2010":"","2016":"","Department":"Мар'їнський районний суд Донецької області","Region":"Донецька область","Position":"Голова Мар'їнського районного суду Донецької області","Name":"Ліпчанський Сергій Миколайович","Link":"http://court.gov.ua/lustration/41e43dfc3d8d15a848e05742ae9ae358.pdf","Note":"","AdditionalNote":"","field8":"","field9":"","field10":"","Кількість справ":"","Оскаржені":"","Кількість скарг":3,"Кількість дисциплінарних стягнень":"","Клейма":"","Фото":"","Як живе":"","key":"lipchanskiy_sergiy_mikolayovich","allDeclarations":[{"provider":"declarations.com.ua","document":{"income":{"5":{"family_comment":"","family_unclear":false,"value":"163710","family":"15560","comment":""},"6":{"value":"163710","family_comment":"","value_unclear":false,"family_unclear":false,"family":"","comment":""},"7":{"value":"","family_comment":"","value_unclear":false,"family_unclear":false,"source_name":"","family":"","comment":"","source_name_hidden":false},"8":{"family_comment":"","value":"","family":"","comment":""},"9":{"family_comment":"","value":"","family":"1495","comment":""},"10":{"family_comment":"","value":"","value_unclear":false,"family":"","comment":""},"11":{"family_comment":"","value":"","family":"","comment":""},"12":{"family_comment":"","value":"","family":"","comment":""},"13":{"family_comment":"","value":"","family":"","comment":""},"14":{"family_comment":"","value":"","family":"","comment":""},"15":{"family_comment":"","value":"","family":"","comment":""},"16":{"family_comment":"","value":"","family":"","comment":""},"17":{"family_comment":"","value":"","family":"","comment":""},"18":{"family_comment":"","value":"","family":"","comment":""},"19":{"family_comment":"","value":"","family":"","comment":""},"20":{"value":"","value_unclear":false,"comment_hidden":false,"family_comment":"","comment_unclear":false,"comment":"","family":"14065"}},"id":"vulyk_96_53","banks":{"51":[{"sum_foreign_comment":"","sum_units":"UAH","sum_comment":"Промислово-інвестиційний банк України","sum_hidden":false,"sum_foreign_units":"UAH","sum_foreign_hidden":false,"sum_comment_hidden":false,"sum_unclear":false,"sum":"77664.83","sum_foreign":""}]},"declaration":{"additional_info_text":"","notfull_lostpages":"","date":"2016-03-01T00:00:00","notfull":"","additional_info":"","url":"http://static.declarations.com.ua/declarations/chosen_ones/judges_batch/267_lipchanskyi_serhii_mykolaiovych_2015.pdf"},"liabilities":{"54":{"sum_foreign_comment":"","sum":"","sum_comment":"","sum_hidden":false,"sum_comment_hidden":false,"sum_foreign":""},"55":{"sum_foreign_comment":"","sum":"","sum_comment":"","sum_foreign":""},"56":{"sum_foreign_comment":"","sum":"","sum_comment":"","sum_unclear":false,"sum_foreign":""},"57":{"sum_foreign_comment":"","sum_comment_hidden":false,"sum":"","sum_comment":"","sum_foreign":""},"58":{"sum_foreign_comment":"","sum":"","sum_comment":"","sum_comment_hidden":false,"sum_unclear":false,"sum_foreign":""},"59":{"sum_foreign_comment":"","sum":"","sum_comment":"","sum_foreign":""},"60":{"sum_foreign_comment":"","sum_comment_hidden":false,"sum":"","sum_comment":"","sum_foreign":""},"61":{"sum_foreign_comment":"","sum":"","sum_comment":"","sum_foreign":""},"62":{"sum_foreign_comment":"","sum":"","sum_comment":"","sum_foreign":""},"63":{"sum_foreign_comment":"","sum_comment_hidden":false,"sum":"","sum_comment":"","sum_foreign":""},"64":{"sum_foreign_comment":"","sum_comment_hidden":false,"sum":"","sum_comment":"","sum_foreign":""}},"ft_src":"Донецьк\nМісце проживання: 85612, м, Курахове, вул. Лермонтова, б. 1 кв. 1, зареєстрований: м. Донецьк, вул. Куйбишева, б. 244 кв. 14\nДонецька область\n2934707695\nсуддя мар'їнського районного суду донецької області\nДонецька область\nЗагальний місцевий суд\nСергій\n2878800085\nЛіпчанська Ю. Я. 26. 10. 1978\nПодружжя\n4124302228\nЛіпчанська Е. С. 01. 12. 2012\nДитина\nМиколайович\nЛіпчанський Сергій Миколайович\nЛіпчанський\nЛіпчанський Сергій Миколайович\nСергій Миколайович Ліпчанський\nСергій Ліпчанський\nЛіпчанський Сергій Миколайович\n1495\n14065\n15560\n163710\n163710\nПромислово-інвестиційний банк України\n77664.83\nСпільна часткова власність 1/4\nДонецька область\nм. Донецьк, вул. Богдана Хмельницького, 92 кв. 54\n74\nособиста власність\nм. Донецьк, вул. Куйбишева, б. 244 кв. 14\n48\nДонецька область\n2015\n163710\n1495\n15560\n163710\n14065\nПромислово-інвестиційний банк України\n77664.83\n2015\nЛіпчанський Сергій Миколайович\nСергій Миколайович Ліпчанський\nСергій Ліпчанський\nЛіпчанський Сергій Миколайович\nЛіпчанський Сергій Миколайович\n2934707695\nСергій\nЛіпчанський\nДонецька область\nсуддя мар'їнського районного суду донецької області\nЗагальний місцевий суд\nМиколайович\nМісце проживання: 85612, м, Курахове, вул. Лермонтова, б. 1 кв. 1, зареєстрований: м. Донецьк, вул. Куйбишева, б. 244 кв. 14\nДонецька область\nДонецьк\nПодружжя\nЛіпчанська Ю. Я. 26. 10. 1978\n2878800085\nДитина\nЛіпчанська Е. С. 01. 12. 2012\n4124302228\n163710\n14065\n163710\n15560\n1495\nСпільна часткова власність 1/4\nм. Донецьк, вул. Богдана Хмельницького, 92 кв. 54\nДонецька область\n74\nособиста власність\n48\nм. Донецьк, вул. Куйбишева, б. 244 кв. 14\nДонецька область\n2878800085\nЛіпчанська Ю. Я. 26. 10. 1978\nПодружжя\n4124302228\nДитина\nЛіпчанська Е. С. 01. 12. 2012\n2934707695\nСергій\nМиколайович\nЛіпчанський\nЛіпчанський Сергій Миколайович\nСергій Миколайович Ліпчанський\nСергій Ліпчанський\nЛіпчанський Сергій Миколайович\nДонецька область\nДонецьк\nМісце проживання: 85612, м, Курахове, вул. Лермонтова, б. 1 кв. 1, зареєстрований: м. Донецьк, вул. Куйбишева, б. 244 кв. 14\nсуддя мар'їнського районного суду донецької області\nДонецька область\nЗагальний місцевий суд\nЛіпчанський Сергій Миколайович\nСпільна часткова власність 1/4\nм. Донецьк, вул. Богдана Хмельницького, 92 кв. 54\nДонецька область\n74\n48\nособиста власність\nм. Донецьк, вул. Куйбишева, б. 244 кв. 14\nДонецька область\nПромислово-інвестиційний банк України\n77664.83\n2015","general":{"inn":"2934707695","name":"Сергій","family":[{"inn":"2878800085","inn_hidden":false,"inn_unclear":false,"relations_hidden":false,"relations_other":"","relations":"Подружжя","name_hidden":false,"family_name":"Ліпчанська Ю. Я. 26. 10. 1978","name_unclear":false},{"inn":"4124302228","relations":"Дитина","relations_other":"","inn_hidden":false,"family_name":"Ліпчанська Е. С. 01. 12. 2012","name_hidden":false,"name_unclear":false}],"patronymic":"Миколайович","inn_hidden":false,"family_raw":"","last_name":"Ліпчанський","post":{"office":"Загальний місцевий суд","region":"Донецька область","office_unclear":false,"post":"суддя мар'їнського районного суду донецької області"},"full_name":"Ліпчанський Сергій Миколайович","addresses":[{"place_district":"","place_city_hidden":false,"place_city":"Донецьк","place_city_type_hidden":false,"place_district_hidden":false,"place_city_type":"Місто","place_address_hidden":false,"place_address":"Місце проживання: 85612, м, Курахове, вул. Лермонтова, б. 1 кв. 1, зареєстрований: м. Донецьк, вул. Куйбишева, б. 244 кв. 14","place_hidden":false,"place":"Донецька область"}],"patronymic_hidden":false,"full_name_suggest":{"output":"Ліпчанський Сергій Миколайович","input":["Ліпчанський Сергій Миколайович","Сергій Миколайович Ліпчанський","Сергій Ліпчанський"]}},"source":"VULYK","estate":{"25":[{"space_comment_unclear":false,"space_unclear":false,"costs":"","costs_comment":"","address_hidden":false,"region_hidden":false,"space_comment":"особиста власність","space_hidden":false,"space":"48","address":"м. Донецьк, вул. Куйбишева, б. 244 кв. 14","costs_rent_comment_unclear":false,"region":"Донецька область","address_unclear":false,"costs_rent_comment":"","costs_unclear":false,"space_comment_hidden":false,"space_units":"м²","costs_rent":""}],"31":[{"space_unclear":false,"address_hidden":false,"region_hidden":false,"space_comment":"Спільна часткова власність 1/4","space_hidden":false,"space":"74","address":"м. Донецьк, вул. Богдана Хмельницького, 92 кв. 54","region":"Донецька область","costs_property":"","costs_rent_comment":"","address_unclear":false,"space_units":"м²","costs_property_comment":"","costs_rent":""}]},"intro":{"declaration_year":"2015","isnotdeclaration":""}}},{"provider":"declarations.com.ua","document":{"income":{"5":{"value":"129534.63","family_comment":"","value_unclear":false,"family_unclear":false,"family":"10389.96","comment":""},"6":{"value":"129534.63","family_comment":"","value_unclear":false,"value_hidden":false,"family_unclear":false,"family":"","comment":""},"7":{"family_comment":"","value":"","source_name":"","family":"","comment":""},"8":{"family_comment":"","value":"","family":"","comment":""},"9":{"value":"","family_comment":"","value_unclear":false,"family_unclear":false,"family":"","comment":""},"10":{"value":"","family_comment":"","value_unclear":false,"family_unclear":false,"family":"","comment":""},"11":{"family_comment":"","value":"","family":"","comment":""},"12":{"family_comment":"","value":"","family":"","comment":""},"13":{"family_comment":"","value":"","family":"","comment":""},"14":{"family_comment":"","value":"","family":"","comment":""},"15":{"family_comment":"","value":"","family":"","comment":""},"16":{"family_comment":"","value":"","family":"","comment":""},"17":{"family_comment":"","family_unclear":false,"value":"","family":"","comment":""},"18":{"family_comment":"","value":"","family":"","comment":""},"19":{"family_comment":"","value":"","family":"","comment":""},"20":{"value":"","comment_unclear":false,"family_comment":"","family":"10389.96","comment":"","family_comment_unclear":false}},"id":"vulyk_37_101","banks":{"45":[{"sum_foreign_comment":"","sum_units":"UAH","sum_units_hidden":false,"sum_comment":"","sum_comment_unclear":false,"sum_hidden":false,"sum_foreign_units":"UAH","sum_comment_hidden":false,"sum_unclear":false,"sum":"","sum_foreign":""},{"sum_foreign_comment":"","sum_units":"","sum_comment":"","sum_foreign_units":"","sum":"","sum_foreign":""},{"sum_foreign_comment":"","sum_units":"","sum_comment":"","sum_foreign_units":"","sum":"","sum_foreign":""}],"46":[{"sum_foreign_comment":"","sum_units":"UAH","sum_comment":"","sum_foreign_units":"UAH","sum":"","sum_foreign":""},{"sum_foreign_comment":"","sum_units":"","sum_comment":"","sum_foreign_units":"","sum":"","sum_foreign":""}],"47":[{"sum_foreign_comment":"","sum_units":"UAH","sum_comment":"","sum_foreign_units":"UAH","sum_comment_hidden":false,"sum":"","sum_foreign":""}],"48":[{"sum_foreign_comment":"","sum_units":"UAH","sum_comment":"","sum_foreign_units":"UAH","sum":"","sum_foreign":""}],"49":[{"sum_foreign_comment":"","sum_units":"UAH","sum_comment":"","sum_foreign_units":"UAH","sum":"","sum_foreign":""}],"50":[{"sum_foreign_comment":"","sum_units":"UAH","sum_comment":"","sum_foreign_units":"UAH","sum":"","sum_foreign":""}],"51":[{"sum_foreign_comment":"","sum_units":"UAH","sum_comment":"","sum_hidden":false,"sum_foreign_units":"UAH","sum_comment_hidden":false,"sum_unclear":false,"sum":"82959.28","sum_foreign":""}],"52":[{"sum_foreign_comment":"","sum_units":"UAH","sum_comment":"","sum_foreign_units":"UAH","sum_comment_hidden":false,"sum":"","sum_foreign":""}],"53":[{"sum_foreign_comment":"","sum_units":"UAH","sum_comment":"","sum_comment_unclear":false,"sum_foreign_units":"UAH","sum":"","sum_foreign":""}]},"declaration":{"additional_info_text":"","notfull_lostpages":"","date":"2015-03-23T00:00:00","notfull":"","additional_info":"","url":"http://static.declarations.com.ua/declarations/chosen_ones/mega_batch/lipchanskyi_serhii_mykolaiovych.pdf"},"liabilities":{"54":{"sum_foreign_comment":"","sum_comment_hidden":false,"sum":"","sum_comment":"","sum_foreign":""},"55":{"sum_foreign_comment":"","sum":"","sum_comment":"","sum_foreign":""},"56":{"sum_foreign_comment":"","sum":"3891","sum_comment":"","sum_unclear":false,"sum_foreign":""},"57":{"sum_foreign_comment":"","sum":"","sum_comment":"","sum_hidden":false,"sum_comment_hidden":false,"sum_unclear":false,"sum_foreign":""},"58":{"sum_foreign_comment":"","sum":"","sum_comment":"","sum_hidden":false,"sum_comment_hidden":false,"sum_foreign":""},"59":{"sum_foreign_comment":"","sum":"","sum_hidden":false,"sum_comment":"","sum_foreign":""},"60":{"sum_foreign_comment":"","sum_comment_hidden":false,"sum":"","sum_comment":"","sum_foreign":""},"61":{"sum_foreign_comment":"","sum":"","sum_comment":"","sum_foreign":""},"62":{"sum_foreign_comment":"","sum":"","sum_comment":"","sum_unclear":false,"sum_foreign":""},"63":{"sum_foreign_comment":"","sum_comment_hidden":false,"sum":"","sum_comment":"","sum_foreign":""},"64":{"sum_foreign_comment":"","sum_comment_hidden":false,"sum":"","sum_comment":"","sum_foreign":""}},"ft_src":"3891\nсуддя мар'їнського районного суду донецької області\nДонецька область\nЗагальний місцевий суд\nСергій\nЛіпчанська Ю. Я\nПодружжя\nЛіпчанська Є. С\nДитина\nМиколайович\nЛіпчанський Сергій Миколайович\nСергій Миколайович Ліпчанський\nСергій Ліпчанський\nЛіпчанський Сергій Миколайович\nЛіпчанський\nЛіпчанський Сергій Миколайович\n10389.96\n129534.63\n10389.96\n129534.63\n82959.28\n48.7\n2014\n129534.63\n10389.96\n129534.63\n10389.96\n82959.28\n2014\nПодружжя\nЛіпчанська Ю. Я\nДитина\nЛіпчанська Є. С\nЛіпчанський Сергій Миколайович\nСергій Миколайович Ліпчанський\nСергій Ліпчанський\nЛіпчанський Сергій Миколайович\nЛіпчанський Сергій Миколайович\nСергій\nМиколайович\nЗагальний місцевий суд\nсуддя мар'їнського районного суду донецької області\nДонецька область\nЛіпчанський\n3891\n129534.63\n10389.96\n129534.63\n10389.96\n48.7\n3891\nЛіпчанська Ю. Я\nПодружжя\nЛіпчанська Є. С\nДитина\nМиколайович\nЛіпчанський\nСергій\nЛіпчанський Сергій Миколайович\nСергій Миколайович Ліпчанський\nСергій Ліпчанський\nЛіпчанський Сергій Миколайович\nДонецька область\nсуддя мар'їнського районного суду донецької області\nЗагальний місцевий суд\nЛіпчанський Сергій Миколайович\n48.7\n82959.28\n2014","general":{"inn":"","name":"Сергій","patronymic_unclear":false,"family":[{"inn":"","inn_hidden":false,"relations_unclear":false,"relations_hidden":false,"relations_other":"","relations":"Подружжя","name_hidden":false,"family_name":"Ліпчанська Ю. Я","name_unclear":false},{"inn":"","relations":"Дитина","relations_unclear":false,"family_name":"Ліпчанська Є. С","inn_hidden":false,"relations_other":"","name_hidden":false,"name_unclear":false}],"patronymic":"Миколайович","inn_hidden":true,"family_raw":"","last_name":"Ліпчанський","post":{"post_unclear":false,"post":"суддя мар'їнського районного суду донецької області","post_hidden":false,"region":"Донецька область","region_hidden":false,"office":"Загальний місцевий суд","office_hidden":false,"office_unclear":false},"last_name_unclear":false,"full_name":"Ліпчанський Сергій Миколайович","addresses":[{"place_district":"","place_city_hidden":false,"place_city":"","place_city_type_hidden":false,"place_district_hidden":false,"place_city_type":"","place_address_hidden":true,"place_address":"","place_hidden":true,"place":""}],"full_name_suggest":{"output":"Ліпчанський Сергій Миколайович","input":["Ліпчанський Сергій Миколайович","Сергій Миколайович Ліпчанський","Сергій Ліпчанський"]},"name_unclear":false},"source":"VULYK","estate":{"23":[{"space_unclear":false,"costs":"","costs_comment":"","address_hidden":false,"region_hidden":false,"space_comment":"","space_hidden":false,"space":"","address":"","region":"","space_units_unclear":false,"space_units":"м²","costs_rent":"","costs_rent_comment":""},{"costs_rent":"","space_unclear":false,"region":"","costs":"","costs_rent_comment":"","costs_comment":"","space_comment":"","space_units":"","space":"","address":""},{"costs_rent":"","region":"","costs":"","costs_rent_comment":"","costs_comment":"","space_comment":"","space_units":"","space":"","address":""},{"costs_rent":"","region":"","costs":"","costs_rent_comment":"","costs_comment":"","space_comment":"","space_units":"","space":"","address":""},{"costs_rent":"","region":"","costs":"","costs_rent_comment":"","costs_comment":"","space_comment":"","space_units":"","space":"","address":""},{"costs_rent":"","region":"","costs":"","costs_rent_comment":"","costs_comment":"","space_comment":"","space_units":"","space":"","address":""},{"costs_rent":"","region":"","costs":"","costs_rent_comment":"","costs_comment":"","space_comment":"","space_units":"","space":"","address":""},{"costs_rent":"","region":"","costs":"","costs_rent_comment":"","costs_comment":"","space_comment":"","space_units":"","space":"","address":""}],"25":[{"region_unclear":false,"space_hidden":false,"costs":"","costs_rent_unclear":false,"costs_comment":"","address_hidden":true,"region_hidden":true,"space_comment":"","space_unclear":false,"space":"48.7","address":"","region":"","address_unclear":false,"costs_rent_comment":"","space_comment_unclear":false,"space_units":"м²","costs_rent":""}]},"intro":{"declaration_year":"2014","isnotdeclaration":"","declaration_year_unclear":false}}},{"provider":"public-api.nazk.gov.ua","document":{"step_0":{"declarationType":"1","declarationYear1":"2015"},"step_1":{"city":"[Конфіденційна інформація]","region":"[Конфіденційна інформація]","street":"[Конфіденційна інформація]","country":"1","cityPath":"[Конфіденційна інформація]","cityType":"[Конфіденційна інформація]","district":"[Конфіденційна інформація]","lastname":"Ліпчанський","postCode":"[Конфіденційна інформація]","postType":"Посада державної служби","workPost":"суддя","firstname":"Сергій","workPlace":"Мар\"їнський районний суд Донецької області","middlename":"Миколайович","streetType":"[Конфіденційна інформація]","actual_city":"1.2.14.2.33.1.6","changedName":false,"countryPath":"","eng_postCode":"","postCategory":"А","actual_region":"1.2.14","actual_street":"[Конфіденційна інформація]","actual_country":"1","actual_cityPath":"[Конфіденційна інформація]","actual_cityType":"[Конфіденційна інформація]","actual_district":"1.2.14.2.33","actual_postCode":"[Конфіденційна інформація]","actual_streetType":"[Конфіденційна інформація]","previous_lastname":"","corruptionAffected":"Ні","eng_actualPostCode":"[Конфіденційна інформація]","previous_firstname":"","city_extendedstatus":"1","previous_middlename":"","responsiblePosition":"Суддя суду загальної юрисдикції, суддя Конституційного Суду України","sameRegLivingAddress":"[Конфіденційна інформація]","eng_sameRegLivingAddress":"[Конфіденційна інформація]","housePartNum_extendedstatus":"1","actual_housePartNum_extendedstatus":"1"},"step_2":{"1476967748379":{"lastname":"Ліпчанська ","firstname":"Юлія ","middlename":"Яківна","changedName":false,"citizenship":"1","eng_lastname":"","no_taxNumber":false,"eng_firstname":"","eng_middlename":"","isNotApplicable":"","subjectRelation":"дружина","previous_lastname":"","previous_firstname":"","previous_middlename":"","previous_eng_lastname":"","previous_eng_firstname":"","previous_eng_middlename":""},"1476968243780":{"lastname":"Ліпчанська","firstname":"Єлизавета ","middlename":"Сергіївна","changedName":false,"citizenship":"1","eng_lastname":"","no_taxNumber":false,"eng_firstname":"","eng_middlename":"","isNotApplicable":"","subjectRelation":"дочка","previous_lastname":"","previous_firstname":"","previous_middlename":"","previous_eng_lastname":"","previous_eng_firstname":"","previous_eng_middlename":""},"1476968388266":{"lastname":"Ліпчанський ","firstname":"Микола ","middlename":"Маркович","changedName":false,"citizenship":"1","eng_lastname":"","no_taxNumber":false,"eng_firstname":"","eng_middlename":"","isNotApplicable":"","subjectRelation":"батько","previous_lastname":"","previous_firstname":"","previous_middlename":"","previous_eng_lastname":"","previous_eng_firstname":"","previous_eng_middlename":""}},"step_3":{"1476969249703":{"city":"[Конфіденційна інформація]","person":"1","region":"[Конфіденційна інформація]","rights":[],"country":"1","cityPath":"[Конфіденційна інформація]","costDate":"103350","district":"[Конфіденційна інформація]","postCode":"[Конфіденційна інформація]","iteration":"1476969249703","totalArea":"48,1","ua_street":"[Конфіденційна інформація]","objectType":"Квартира","owningDate":"14.10.2004","ua_cityType":"Донецьк / Донецька Область / Україна","ua_postCode":"83122","ua_streetType":"[Конфіденційна інформація]","costAssessment":"","otherObjectType":"","costAssessment_extendedstatus":"2","ua_housePartNum_extendedstatus":"1"},"1477459886122":{"city":"[Конфіденційна інформація]","person":"1476967748379","region":"[Конфіденційна інформація]","rights":[],"country":"1","cityPath":"[Конфіденційна інформація]","costDate":"","district":"[Конфіденційна інформація]","postCode":"[Конфіденційна інформація]","iteration":"1477459886122","totalArea":"76,5","ua_street":"[Конфіденційна інформація]","objectType":"Квартира","owningDate":"04.09.1997","ua_cityType":"Донецьк / Донецька Область / Україна","ua_postCode":"83050","ua_streetType":"[Конфіденційна інформація]","costAssessment":"","otherObjectType":"","costDate_extendedstatus":"2","regNumber_extendedstatus":"0","costAssessment_extendedstatus":"1","ua_housePartNum_extendedstatus":"1"},"1477460309262":{"city":"[Конфіденційна інформація]","person":"1476968388266","region":"[Конфіденційна інформація]","rights":[],"country":"1","cityPath":"[Конфіденційна інформація]","costDate":"","district":"[Конфіденційна інформація]","postCode":"[Конфіденційна інформація]","totalArea":"84,6","ua_street":"[Конфіденційна інформація]","objectType":"Квартира","owningDate":"31.12.1997","ua_cityType":"Донецьк / Донецька Область / Україна","ua_postCode":"83122","ua_streetType":"[Конфіденційна інформація]","costAssessment":"","otherObjectType":"","costDate_extendedstatus":"2","costAssessment_extendedstatus":"2","ua_housePartNum_extendedstatus":"1"},"1477479159514":{"city":"[Конфіденційна інформація]","person":"1476968388266","region":"[Конфіденційна інформація]","rights":[],"country":"1","cityPath":"[Конфіденційна інформація]","costDate":"","district":"[Конфіденційна інформація]","postCode":"[Конфіденційна інформація]","totalArea":"1000","ua_street":"[Конфіденційна інформація]","objectType":"Земельна ділянка","owningDate":"19.09.2008","ua_cityType":"Донецьк / Донецька Область / Україна","ua_postCode":"83000","ua_streetType":"[Конфіденційна інформація]","costAssessment":"","otherObjectType":"","costDate_extendedstatus":"2","ua_houseNum_extendedstatus":"1","ua_postCode_extendedstatus":"0","costAssessment_extendedstatus":"2","ua_housePartNum_extendedstatus":"1","ua_apartmentsNum_extendedstatus":"1"},"1477479679183":{"city":"[Конфіденційна інформація]","person":"1476968388266","region":"[Конфіденційна інформація]","rights":[],"country":"1","cityPath":"[Конфіденційна інформація]","costDate":"","district":"[Конфіденційна інформація]","postCode":"[Конфіденційна інформація]","totalArea":"729","ua_street":"[Конфіденційна інформація]","objectType":"Земельна ділянка","owningDate":"16.05.2008","ua_cityType":"Піски / Ясинуватський Район / Донецька Область / Україна","ua_postCode":"83000","ua_streetType":"[Конфіденційна інформація]","costAssessment":"","otherObjectType":"","costDate_extendedstatus":"2","ua_street_extendedstatus":"1","ua_houseNum_extendedstatus":"1","ua_streetType_extendedstatus":"1","costAssessment_extendedstatus":"2","ua_housePartNum_extendedstatus":"1","ua_apartmentsNum_extendedstatus":"1"}},"step_4":[],"step_5":[],"step_6":{"1476969651079":{"brand":"Форд","model":"Фьюжен","person":"1","rights":{"1476968388266":{"citizen":"","ua_city":"","ua_street":"[Конфіденційна інформація]","ua_lastname":"","ua_postCode":"","eng_lastname":"","eng_postCode":"","rightBelongs":"1476968388266","ua_firstname":"","ukr_lastname":"","eng_firstname":"","ownershipType":"Інше право користування","ua_middlename":"","ua_streetType":"[Конфіденційна інформація]","ukr_firstname":"","eng_middlename":"","otherOwnership":"Керування за довіреністю","ukr_middlename":"","rights_cityPath":"","ua_company_name":"","eng_company_name":"","ukr_company_name":"","percent-ownership":"","ua_street_extendedstatus":"","ua_houseNum_extendedstatus":"","ua_postCode_extendedstatus":"","eng_postCode_extendedstatus":"","ua_middlename_extendedstatus":"","eng_middlename_extendedstatus":"","ukr_middlename_extendedstatus":"","ua_housePartNum_extendedstatus":"","ua_apartmentsNum_extendedstatus":""}},"costDate":"86000","objectType":"Автомобіль легковий","owningDate":"25.09.2010","typeProperty":"","graduationYear":"2010","otherTypeProperty":""},"1477377586027":{"brand":"ВАЗ","model":"2107","person":"1476968388266","rights":[],"costDate":"","objectType":"Автомобіль легковий","owningDate":"19.09.1989","graduationYear":"1989","otherObjectType":"","costDate_extendedstatus":"2"}},"step_7":[],"step_8":[],"step_9":[],"step_10":[],"step_11":{"1476970171630":{"person":"1","rights":{"1":{"citizen":"","ua_city":"","ua_street":"[Конфіденційна інформація]","ua_lastname":"","ua_postCode":"","eng_lastname":"","eng_postCode":"","rightBelongs":"1","ua_firstname":"","ukr_lastname":"","eng_firstname":"","ownershipType":"Власність","ua_middlename":"","ua_streetType":"[Конфіденційна інформація]","ukr_firstname":"","eng_middlename":"","otherOwnership":"","ukr_middlename":"","rights_cityPath":"","ua_company_name":"","eng_company_name":"","ukr_company_name":"","percent-ownership":"","ua_street_extendedstatus":"","ua_houseNum_extendedstatus":"","ua_postCode_extendedstatus":"","eng_postCode_extendedstatus":"","ua_middlename_extendedstatus":"","eng_middlename_extendedstatus":"","ukr_middlename_extendedstatus":"","ua_housePartNum_extendedstatus":"","ua_apartmentsNum_extendedstatus":""}},"objectType":"Заробітна плата отримана за основним місцем роботи","sizeIncome":"163710","incomeSource":"1","source_citizen":"","otherObjectType":"","source_ua_lastname":"","source_eng_lastname":"","source_ua_firstname":"","source_ukr_lastname":"","source_eng_firstname":"","source_ua_middlename":"","source_ukr_firstname":"","source_eng_middlename":"","source_ukr_middlename":"","source_ua_company_name":"","source_eng_company_name":"","source_ukr_company_name":"","source_ua_sameRegLivingAddress":"","source_eng_sameRegLivingAddress":""},"1476970316609":{"person":"1476967748379","rights":[],"objectType":"Проценти","sizeIncome":"1495","incomeSource":"1476967748379","source_citizen":"","otherObjectType":"","source_ua_lastname":"","source_eng_lastname":"","source_ua_firstname":"","source_ukr_lastname":"","source_eng_firstname":"","source_ua_middlename":"","source_ukr_firstname":"","source_eng_middlename":"","source_ukr_middlename":"","source_ua_company_name":"","source_eng_company_name":"","source_ukr_company_name":"","source_ua_sameRegLivingAddress":"","source_eng_sameRegLivingAddress":""},"1476970413988":{"person":"1476967748379","rights":[],"objectType":"Інше","sizeIncome":"14065","incomeSource":"1476967748379","source_citizen":"","otherObjectType":"Допомога переселенцям","source_ua_lastname":"","source_eng_lastname":"","source_ua_firstname":"","source_ukr_lastname":"","source_eng_firstname":"","source_ua_middlename":"","source_ukr_firstname":"","source_eng_middlename":"","source_ukr_middlename":"","source_ua_company_name":"","source_eng_company_name":"","source_ukr_company_name":"","source_ua_sameRegLivingAddress":"","source_eng_sameRegLivingAddress":""},"1477458731461":{"person":"1476968388266","rights":[],"objectType":"Пенсія","sizeIncome":"65298","incomeSource":"1476968388266","source_citizen":"","otherObjectType":"","source_ua_lastname":"","source_eng_fullname":"","source_ua_firstname":"","source_ukr_fullname":"","source_ua_middlename":"","source_ua_company_name":"","source_eng_company_name":"","source_ukr_company_name":"","source_ua_sameRegLivingAddress":""}},"step_12":{"1476970523648":{"person":"1476967748379","rights":[],"objectType":"Кошти, розміщені на банківських рахунках","sizeAssets":"3235","organization":"j","assetsCurrency":"USD","otherObjectType":"","organization_type":"Юридична особа, зареєстрована в Україні","debtor_ua_lastname":"","debtor_eng_lastname":"","debtor_ua_firstname":"","debtor_ukr_lastname":"","debtor_eng_firstname":"","debtor_ua_middlename":"","debtor_ukr_firstname":"","debtor_eng_middlename":"","debtor_ukr_middlename":"","organization_ua_company_name":"ПАТ \"Промислово Інвестиційний банк України\"","organization_eng_company_name":"","organization_ukr_company_name":"","debtor_ua_sameRegLivingAddress":"","debtor_eng_sameRegLivingAddress":"","organization_ua_company_code_extendedstatus":"2"},"1477745894848":{"person":"1476968388266","rights":[],"iteration":"1477745894848","objectType":"Кошти, розміщені на банківських рахунках","sizeAssets":"100250","organization":"j","assetsCurrency":"UAH","otherObjectType":"","organization_type":"Юридична особа, зареєстрована в Україні","debtor_ua_lastname":"","debtor_eng_lastname":"","debtor_ua_firstname":"","debtor_ukr_lastname":"","debtor_eng_firstname":"","debtor_ua_middlename":"","debtor_ukr_firstname":"","debtor_eng_middlename":"","debtor_ukr_middlename":"","organization_ua_company_name":"АКБ \"Приватбанк\"","organization_eng_company_name":"","organization_ukr_company_name":"","debtor_ua_sameRegLivingAddress":"","debtor_eng_sameRegLivingAddress":"","organization_ua_company_code_extendedstatus":"2"}},"step_13":[],"step_14":[],"step_15":[],"step_16":[],"id":"baefe619-9631-4f47-a1b1-94d4231fb74e"}}],"declarations":[{"income":{"5":{"family_comment":"","family_unclear":false,"value":"163710","family":"15560","comment":""},"6":{"value":"163710","family_comment":"","value_unclear":false,"family_unclear":false,"family":"","comment":""},"7":{"value":"","family_comment":"","value_unclear":false,"family_unclear":false,"source_name":"","family":"","comment":"","source_name_hidden":false},"8":{"family_comment":"","value":"","family":"","comment":""},"9":{"family_comment":"","value":"","family":"1495","comment":""},"10":{"family_comment":"","value":"","value_unclear":false,"family":"","comment":""},"11":{"family_comment":"","value":"","family":"","comment":""},"12":{"family_comment":"","value":"","family":"","comment":""},"13":{"family_comment":"","value":"","family":"","comment":""},"14":{"family_comment":"","value":"","family":"","comment":""},"15":{"family_comment":"","value":"","family":"","comment":""},"16":{"family_comment":"","value":"","family":"","comment":""},"17":{"family_comment":"","value":"","family":"","comment":""},"18":{"family_comment":"","value":"","family":"","comment":""},"19":{"family_comment":"","value":"","family":"","comment":""},"20":{"value":"","value_unclear":false,"comment_hidden":false,"family_comment":"","comment_unclear":false,"comment":"","family":"14065"}},"id":"vulyk_96_53","banks":{"51":[{"sum_foreign_comment":"","sum_units":"UAH","sum_comment":"Промислово-інвестиційний банк України","sum_hidden":false,"sum_foreign_units":"UAH","sum_foreign_hidden":false,"sum_comment_hidden":false,"sum_unclear":false,"sum":"77664.83","sum_foreign":""}]},"declaration":{"additional_info_text":"","notfull_lostpages":"","date":"2016-03-01T00:00:00","notfull":"","additional_info":"","url":"http://static.declarations.com.ua/declarations/chosen_ones/judges_batch/267_lipchanskyi_serhii_mykolaiovych_2015.pdf"},"liabilities":{"54":{"sum_foreign_comment":"","sum":"","sum_comment":"","sum_hidden":false,"sum_comment_hidden":false,"sum_foreign":""},"55":{"sum_foreign_comment":"","sum":"","sum_comment":"","sum_foreign":""},"56":{"sum_foreign_comment":"","sum":"","sum_comment":"","sum_unclear":false,"sum_foreign":""},"57":{"sum_foreign_comment":"","sum_comment_hidden":false,"sum":"","sum_comment":"","sum_foreign":""},"58":{"sum_foreign_comment":"","sum":"","sum_comment":"","sum_comment_hidden":false,"sum_unclear":false,"sum_foreign":""},"59":{"sum_foreign_comment":"","sum":"","sum_comment":"","sum_foreign":""},"60":{"sum_foreign_comment":"","sum_comment_hidden":false,"sum":"","sum_comment":"","sum_foreign":""},"61":{"sum_foreign_comment":"","sum":"","sum_comment":"","sum_foreign":""},"62":{"sum_foreign_comment":"","sum":"","sum_comment":"","sum_foreign":""},"63":{"sum_foreign_comment":"","sum_comment_hidden":false,"sum":"","sum_comment":"","sum_foreign":""},"64":{"sum_foreign_comment":"","sum_comment_hidden":false,"sum":"","sum_comment":"","sum_foreign":""}},"ft_src":"Донецьк\nМісце проживання: 85612, м, Курахове, вул. Лермонтова, б. 1 кв. 1, зареєстрований: м. Донецьк, вул. Куйбишева, б. 244 кв. 14\nДонецька область\n2934707695\nсуддя мар'їнського районного суду донецької області\nДонецька область\nЗагальний місцевий суд\nСергій\n2878800085\nЛіпчанська Ю. Я. 26. 10. 1978\nПодружжя\n4124302228\nЛіпчанська Е. С. 01. 12. 2012\nДитина\nМиколайович\nЛіпчанський Сергій Миколайович\nЛіпчанський\nЛіпчанський Сергій Миколайович\nСергій Миколайович Ліпчанський\nСергій Ліпчанський\nЛіпчанський Сергій Миколайович\n1495\n14065\n15560\n163710\n163710\nПромислово-інвестиційний банк України\n77664.83\nСпільна часткова власність 1/4\nДонецька область\nм. Донецьк, вул. Богдана Хмельницького, 92 кв. 54\n74\nособиста власність\nм. Донецьк, вул. Куйбишева, б. 244 кв. 14\n48\nДонецька область\n2015\n163710\n1495\n15560\n163710\n14065\nПромислово-інвестиційний банк України\n77664.83\n2015\nЛіпчанський Сергій Миколайович\nСергій Миколайович Ліпчанський\nСергій Ліпчанський\nЛіпчанський Сергій Миколайович\nЛіпчанський Сергій Миколайович\n2934707695\nСергій\nЛіпчанський\nДонецька область\nсуддя мар'їнського районного суду донецької області\nЗагальний місцевий суд\nМиколайович\nМісце проживання: 85612, м, Курахове, вул. Лермонтова, б. 1 кв. 1, зареєстрований: м. Донецьк, вул. Куйбишева, б. 244 кв. 14\nДонецька область\nДонецьк\nПодружжя\nЛіпчанська Ю. Я. 26. 10. 1978\n2878800085\nДитина\nЛіпчанська Е. С. 01. 12. 2012\n4124302228\n163710\n14065\n163710\n15560\n1495\nСпільна часткова власність 1/4\nм. Донецьк, вул. Богдана Хмельницького, 92 кв. 54\nДонецька область\n74\nособиста власність\n48\nм. Донецьк, вул. Куйбишева, б. 244 кв. 14\nДонецька область\n2878800085\nЛіпчанська Ю. Я. 26. 10. 1978\nПодружжя\n4124302228\nДитина\nЛіпчанська Е. С. 01. 12. 2012\n2934707695\nСергій\nМиколайович\nЛіпчанський\nЛіпчанський Сергій Миколайович\nСергій Миколайович Ліпчанський\nСергій Ліпчанський\nЛіпчанський Сергій Миколайович\nДонецька область\nДонецьк\nМісце проживання: 85612, м, Курахове, вул. Лермонтова, б. 1 кв. 1, зареєстрований: м. Донецьк, вул. Куйбишева, б. 244 кв. 14\nсуддя мар'їнського районного суду донецької області\nДонецька область\nЗагальний місцевий суд\nЛіпчанський Сергій Миколайович\nСпільна часткова власність 1/4\nм. Донецьк, вул. Богдана Хмельницького, 92 кв. 54\nДонецька область\n74\n48\nособиста власність\nм. Донецьк, вул. Куйбишева, б. 244 кв. 14\nДонецька область\nПромислово-інвестиційний банк України\n77664.83\n2015","general":{"inn":"2934707695","name":"Сергій","family":[{"inn":"2878800085","inn_hidden":false,"inn_unclear":false,"relations_hidden":false,"relations_other":"","relations":"Подружжя","name_hidden":false,"family_name":"Ліпчанська Ю. Я. 26. 10. 1978","name_unclear":false},{"inn":"4124302228","relations":"Дитина","relations_other":"","inn_hidden":false,"family_name":"Ліпчанська Е. С. 01. 12. 2012","name_hidden":false,"name_unclear":false}],"patronymic":"Миколайович","inn_hidden":false,"family_raw":"","last_name":"Ліпчанський","post":{"office":"Загальний місцевий суд","region":"Донецька область","office_unclear":false,"post":"суддя мар'їнського районного суду донецької області"},"full_name":"Ліпчанський Сергій Миколайович","addresses":[{"place_district":"","place_city_hidden":false,"place_city":"Донецьк","place_city_type_hidden":false,"place_district_hidden":false,"place_city_type":"Місто","place_address_hidden":false,"place_address":"Місце проживання: 85612, м, Курахове, вул. Лермонтова, б. 1 кв. 1, зареєстрований: м. Донецьк, вул. Куйбишева, б. 244 кв. 14","place_hidden":false,"place":"Донецька область"}],"patronymic_hidden":false,"full_name_suggest":{"output":"Ліпчанський Сергій Миколайович","input":["Ліпчанський Сергій Миколайович","Сергій Миколайович Ліпчанський","Сергій Ліпчанський"]}},"source":"VULYK","estate":{"25":[{"space_comment_unclear":false,"space_unclear":false,"costs":"","costs_comment":"","address_hidden":false,"region_hidden":false,"space_comment":"особиста власність","space_hidden":false,"space":"48","address":"м. Донецьк, вул. Куйбишева, б. 244 кв. 14","costs_rent_comment_unclear":false,"region":"Донецька область","address_unclear":false,"costs_rent_comment":"","costs_unclear":false,"space_comment_hidden":false,"space_units":"м²","costs_rent":""}],"31":[{"space_unclear":false,"address_hidden":false,"region_hidden":false,"space_comment":"Спільна часткова власність 1/4","space_hidden":false,"space":"74","address":"м. Донецьк, вул. Богдана Хмельницького, 92 кв. 54","region":"Донецька область","costs_property":"","costs_rent_comment":"","address_unclear":false,"space_units":"м²","costs_property_comment":"","costs_rent":""}]},"intro":{"declaration_year":"2015","isnotdeclaration":""}},{"income":{"5":{"value":"129534.63","family_comment":"","value_unclear":false,"family_unclear":false,"family":"10389.96","comment":""},"6":{"value":"129534.63","family_comment":"","value_unclear":false,"value_hidden":false,"family_unclear":false,"family":"","comment":""},"7":{"family_comment":"","value":"","source_name":"","family":"","comment":""},"8":{"family_comment":"","value":"","family":"","comment":""},"9":{"value":"","family_comment":"","value_unclear":false,"family_unclear":false,"family":"","comment":""},"10":{"value":"","family_comment":"","value_unclear":false,"family_unclear":false,"family":"","comment":""},"11":{"family_comment":"","value":"","family":"","comment":""},"12":{"family_comment":"","value":"","family":"","comment":""},"13":{"family_comment":"","value":"","family":"","comment":""},"14":{"family_comment":"","value":"","family":"","comment":""},"15":{"family_comment":"","value":"","family":"","comment":""},"16":{"family_comment":"","value":"","family":"","comment":""},"17":{"family_comment":"","family_unclear":false,"value":"","family":"","comment":""},"18":{"family_comment":"","value":"","family":"","comment":""},"19":{"family_comment":"","value":"","family":"","comment":""},"20":{"value":"","comment_unclear":false,"family_comment":"","family":"10389.96","comment":"","family_comment_unclear":false}},"id":"vulyk_37_101","banks":{"45":[{"sum_foreign_comment":"","sum_units":"UAH","sum_units_hidden":false,"sum_comment":"","sum_comment_unclear":false,"sum_hidden":false,"sum_foreign_units":"UAH","sum_comment_hidden":false,"sum_unclear":false,"sum":"","sum_foreign":""},{"sum_foreign_comment":"","sum_units":"","sum_comment":"","sum_foreign_units":"","sum":"","sum_foreign":""},{"sum_foreign_comment":"","sum_units":"","sum_comment":"","sum_foreign_units":"","sum":"","sum_foreign":""}],"46":[{"sum_foreign_comment":"","sum_units":"UAH","sum_comment":"","sum_foreign_units":"UAH","sum":"","sum_foreign":""},{"sum_foreign_comment":"","sum_units":"","sum_comment":"","sum_foreign_units":"","sum":"","sum_foreign":""}],"47":[{"sum_foreign_comment":"","sum_units":"UAH","sum_comment":"","sum_foreign_units":"UAH","sum_comment_hidden":false,"sum":"","sum_foreign":""}],"48":[{"sum_foreign_comment":"","sum_units":"UAH","sum_comment":"","sum_foreign_units":"UAH","sum":"","sum_foreign":""}],"49":[{"sum_foreign_comment":"","sum_units":"UAH","sum_comment":"","sum_foreign_units":"UAH","sum":"","sum_foreign":""}],"50":[{"sum_foreign_comment":"","sum_units":"UAH","sum_comment":"","sum_foreign_units":"UAH","sum":"","sum_foreign":""}],"51":[{"sum_foreign_comment":"","sum_units":"UAH","sum_comment":"","sum_hidden":false,"sum_foreign_units":"UAH","sum_comment_hidden":false,"sum_unclear":false,"sum":"82959.28","sum_foreign":""}],"52":[{"sum_foreign_comment":"","sum_units":"UAH","sum_comment":"","sum_foreign_units":"UAH","sum_comment_hidden":false,"sum":"","sum_foreign":""}],"53":[{"sum_foreign_comment":"","sum_units":"UAH","sum_comment":"","sum_comment_unclear":false,"sum_foreign_units":"UAH","sum":"","sum_foreign":""}]},"declaration":{"additional_info_text":"","notfull_lostpages":"","date":"2015-03-23T00:00:00","notfull":"","additional_info":"","url":"http://static.declarations.com.ua/declarations/chosen_ones/mega_batch/lipchanskyi_serhii_mykolaiovych.pdf"},"liabilities":{"54":{"sum_foreign_comment":"","sum_comment_hidden":false,"sum":"","sum_comment":"","sum_foreign":""},"55":{"sum_foreign_comment":"","sum":"","sum_comment":"","sum_foreign":""},"56":{"sum_foreign_comment":"","sum":"3891","sum_comment":"","sum_unclear":false,"sum_foreign":""},"57":{"sum_foreign_comment":"","sum":"","sum_comment":"","sum_hidden":false,"sum_comment_hidden":false,"sum_unclear":false,"sum_foreign":""},"58":{"sum_foreign_comment":"","sum":"","sum_comment":"","sum_hidden":false,"sum_comment_hidden":false,"sum_foreign":""},"59":{"sum_foreign_comment":"","sum":"","sum_hidden":false,"sum_comment":"","sum_foreign":""},"60":{"sum_foreign_comment":"","sum_comment_hidden":false,"sum":"","sum_comment":"","sum_foreign":""},"61":{"sum_foreign_comment":"","sum":"","sum_comment":"","sum_foreign":""},"62":{"sum_foreign_comment":"","sum":"","sum_comment":"","sum_unclear":false,"sum_foreign":""},"63":{"sum_foreign_comment":"","sum_comment_hidden":false,"sum":"","sum_comment":"","sum_foreign":""},"64":{"sum_foreign_comment":"","sum_comment_hidden":false,"sum":"","sum_comment":"","sum_foreign":""}},"ft_src":"3891\nсуддя мар'їнського районного суду донецької області\nДонецька область\nЗагальний місцевий суд\nСергій\nЛіпчанська Ю. Я\nПодружжя\nЛіпчанська Є. С\nДитина\nМиколайович\nЛіпчанський Сергій Миколайович\nСергій Миколайович Ліпчанський\nСергій Ліпчанський\nЛіпчанський Сергій Миколайович\nЛіпчанський\nЛіпчанський Сергій Миколайович\n10389.96\n129534.63\n10389.96\n129534.63\n82959.28\n48.7\n2014\n129534.63\n10389.96\n129534.63\n10389.96\n82959.28\n2014\nПодружжя\nЛіпчанська Ю. Я\nДитина\nЛіпчанська Є. С\nЛіпчанський Сергій Миколайович\nСергій Миколайович Ліпчанський\nСергій Ліпчанський\nЛіпчанський Сергій Миколайович\nЛіпчанський Сергій Миколайович\nСергій\nМиколайович\nЗагальний місцевий суд\nсуддя мар'їнського районного суду донецької області\nДонецька область\nЛіпчанський\n3891\n129534.63\n10389.96\n129534.63\n10389.96\n48.7\n3891\nЛіпчанська Ю. Я\nПодружжя\nЛіпчанська Є. С\nДитина\nМиколайович\nЛіпчанський\nСергій\nЛіпчанський Сергій Миколайович\nСергій Миколайович Ліпчанський\nСергій Ліпчанський\nЛіпчанський Сергій Миколайович\nДонецька область\nсуддя мар'їнського районного суду донецької області\nЗагальний місцевий суд\nЛіпчанський Сергій Миколайович\n48.7\n82959.28\n2014","general":{"inn":"","name":"Сергій","patronymic_unclear":false,"family":[{"inn":"","inn_hidden":false,"relations_unclear":false,"relations_hidden":false,"relations_other":"","relations":"Подружжя","name_hidden":false,"family_name":"Ліпчанська Ю. Я","name_unclear":false},{"inn":"","relations":"Дитина","relations_unclear":false,"family_name":"Ліпчанська Є. С","inn_hidden":false,"relations_other":"","name_hidden":false,"name_unclear":false}],"patronymic":"Миколайович","inn_hidden":true,"family_raw":"","last_name":"Ліпчанський","post":{"post_unclear":false,"post":"суддя мар'їнського районного суду донецької області","post_hidden":false,"region":"Донецька область","region_hidden":false,"office":"Загальний місцевий суд","office_hidden":false,"office_unclear":false},"last_name_unclear":false,"full_name":"Ліпчанський Сергій Миколайович","addresses":[{"place_district":"","place_city_hidden":false,"place_city":"","place_city_type_hidden":false,"place_district_hidden":false,"place_city_type":"","place_address_hidden":true,"place_address":"","place_hidden":true,"place":""}],"full_name_suggest":{"output":"Ліпчанський Сергій Миколайович","input":["Ліпчанський Сергій Миколайович","Сергій Миколайович Ліпчанський","Сергій Ліпчанський"]},"name_unclear":false},"source":"VULYK","estate":{"23":[{"space_unclear":false,"costs":"","costs_comment":"","address_hidden":false,"region_hidden":false,"space_comment":"","space_hidden":false,"space":"","address":"","region":"","space_units_unclear":false,"space_units":"м²","costs_rent":"","costs_rent_comment":""},{"costs_rent":"","space_unclear":false,"region":"","costs":"","costs_rent_comment":"","costs_comment":"","space_comment":"","space_units":"","space":"","address":""},{"costs_rent":"","region":"","costs":"","costs_rent_comment":"","costs_comment":"","space_comment":"","space_units":"","space":"","address":""},{"costs_rent":"","region":"","costs":"","costs_rent_comment":"","costs_comment":"","space_comment":"","space_units":"","space":"","address":""},{"costs_rent":"","region":"","costs":"","costs_rent_comment":"","costs_comment":"","space_comment":"","space_units":"","space":"","address":""},{"costs_rent":"","region":"","costs":"","costs_rent_comment":"","costs_comment":"","space_comment":"","space_units":"","space":"","address":""},{"costs_rent":"","region":"","costs":"","costs_rent_comment":"","costs_comment":"","space_comment":"","space_units":"","space":"","address":""},{"costs_rent":"","region":"","costs":"","costs_rent_comment":"","costs_comment":"","space_comment":"","space_units":"","space":"","address":""}],"25":[{"region_unclear":false,"space_hidden":false,"costs":"","costs_rent_unclear":false,"costs_comment":"","address_hidden":true,"region_hidden":true,"space_comment":"","space_unclear":false,"space":"48.7","address":"","region":"","address_unclear":false,"costs_rent_comment":"","space_comment_unclear":false,"space_units":"м²","costs_rent":""}]},"intro":{"declaration_year":"2014","isnotdeclaration":"","declaration_year_unclear":false}}],"declarationsLength":2,"analytics":[{"y":2015,"i":163710,"k":48,"ka":1,"fi":15560,"ff":74,"ffa":1,"j":3},{"y":2014,"i":129534.63,"k":48.7,"ka":1,"la":8,"fi":10389.96}]}