{"2010":"","2016":"","Department":"Апеляційний суд Донецької області","Region":"Донецька область","Position":"Суддя Апеляційного суду Донецької області","Name":"Мальцева Євгенія Євгенівна","Link":"https://drive.google.com/open?id=0BygiyWAl79DMOWEtRG1JcldENDQ","Note":"","AdditionalNote":"","field8":"","field9":"","field10":"","Кількість справ":"","Оскаржені":"","Кількість скарг":3,"Кількість дисциплінарних стягнень":"","Клейма":"","Фото":"","Як живе":"","key":"malceva_ievgeniya_ievgenivna","allDeclarations":[{"provider":"declarations.com.ua","document":{"income":{"5":{"family_comment":"","value":"209438.48","family":"","comment":""},"6":{"family_comment":"","value":"196040.48","family":"","comment":"","family_comment_unclear":false},"7":{"value":"","comment_hidden":false,"family_comment":"","source_name":"","family":"","comment":"","source_name_hidden":false},"8":{"family_comment":"","value":"","family":"","comment":""},"9":{"family_comment":"","value":"","family":"","comment":""},"10":{"value":"13398","value_unclear":false,"value_hidden":false,"family_comment":"","family":"","comment":""},"11":{"family_comment":"","value":"","family":"","comment":""},"12":{"family_comment":"","value":"","family":"","comment":""},"13":{"family_comment":"","value":"","family":"","comment":""},"14":{"family_comment":"","value":"","family":"","comment":""},"15":{"family_comment":"","value":"","family":"","comment":""},"16":{"family_comment":"","value":"","family":"","comment":""},"17":{"family_comment":"","value":"","family":"","comment":""},"18":{"family_comment":"","value":"","family":"","comment":""},"19":{"family_comment":"","value":"","family":"","comment":""},"20":{"family_comment":"","value":"","comment_unclear":false,"family":"","comment":""}},"vehicle":{"40":[{"brand_info":"2000 куб. см.","sum_rent_comment":"","brand":"Hyundai Sonata","sum_comment":"","brand_unclear":false,"year":"2007","sum":"","sum_rent":""}]},"id":"vulyk_86_35","declaration":{"additional_info_text":"","notfull_lostpages":"","date":"2015-03-24T00:00:00","notfull":"","additional_info":"","url":"http://static.declarations.com.ua/declarations/chosen_ones/judges_batch/2738_maltseva_ievheniia_ievhenivna.pdf"},"liabilities":{"54":{"sum_foreign_comment":"","sum":"","sum_comment":"","sum_unclear":false,"sum_foreign":""},"55":{"sum_foreign_comment":"","sum":"","sum_comment":"","sum_foreign":""},"56":{"sum_foreign_comment":"","sum":"","sum_hidden":false,"sum_comment":"","sum_foreign":""},"57":{"sum_foreign_comment":"","sum":"","sum_comment":"","sum_unclear":false,"sum_foreign":""},"58":{"sum_foreign_comment":"","sum":"","sum_comment":"","sum_unclear":false,"sum_foreign":""},"59":{"sum_foreign_comment":"","sum":"","sum_comment":"","sum_foreign":""},"60":{"sum_foreign_comment":"","sum_comment_hidden":false,"sum":"","sum_comment":"","sum_foreign":""},"61":{"sum_foreign_comment":"","sum":"","sum_comment":"","sum_foreign":""},"62":{"sum_foreign_comment":"","sum":"","sum_comment":"","sum_foreign":""},"63":{"sum_foreign_comment":"","sum":"","sum_comment":"","sum_foreign":""},"64":{"sum_foreign_comment":"","sum":"","sum_comment":"","sum_foreign":""}},"ft_src":"суддя апеляційного суду донецької області\nДонецька область\nЗагальний апеляційний суд\nЄвгенія\nМальцев І. С\nПодружжя\nМальцева О. І\nДитина\nЄвгеніївна\nМальцева Євгенія Євгеніївна\nЄвгенія Євгеніївна Мальцева\nЄвгенія Мальцева\nМальцева Євгенія Євгеніївна\nМальцева Євгенія Євгеніївна\nМальцева\n2007\n2000 куб. см.\nHyundai Sonata\n4.3\n44.2\n16\n63.8\n2014\n196040.48\n13398\n209438.48\n2000 куб. см.\nHyundai Sonata\n2007\n2014\nМальцева Євгенія Євгеніївна\nЄвгенія Євгеніївна Мальцева\nЄвгенія Мальцева\nМальцева Євгенія Євгеніївна\nМальцева Євгенія Євгеніївна\nПодружжя\nМальцев І. С\nДитина\nМальцева О. І\nЄвгенія\nМальцева\nЗагальний апеляційний суд\nДонецька область\nсуддя апеляційного суду донецької області\nЄвгеніївна\n196040.48\n209438.48\n13398\n16\n44.2\n4.3\n63.8\nМальцев І. С\nПодружжя\nМальцева О. І\nДитина\nЄвгеніївна\nМальцева\nЄвгенія\nМальцева Євгенія Євгеніївна\nЄвгенія Євгеніївна Мальцева\nЄвгенія Мальцева\nМальцева Євгенія Євгеніївна\nДонецька область\nЗагальний апеляційний суд\nсуддя апеляційного суду донецької області\nМальцева Євгенія Євгеніївна\n2007\n2000 куб. см.\nHyundai Sonata\n13398\n209438.48\n196040.48\n44.2\n63.8\n4.3\n16\n2014","general":{"inn":"","name":"Євгенія","patronymic_unclear":false,"family":[{"inn":"","inn_hidden":true,"relations_hidden":false,"family_name":"Мальцев І. С","relations_other":"","relations":"Подружжя","name_hidden":false,"name_unclear":false},{"inn":"","relations":"Дитина","relations_other":"","inn_hidden":true,"family_name":"Мальцева О. І","name_hidden":false,"name_unclear":false}],"patronymic":"Євгеніївна","inn_hidden":true,"family_raw":"","inn_unclear":false,"post":{"post_unclear":false,"post":"суддя апеляційного суду донецької області","candidate":"","office_hidden":false,"region":"Донецька область","office":"Загальний апеляційний суд","office_unclear":false,"region_hidden":false},"full_name":"Мальцева Євгенія Євгеніївна","addresses":[{"place_district":"","place_unclear":false,"place_city":"","place_city_type_hidden":false,"place_district_hidden":false,"place_city_type":"","place_city_hidden":true,"place_address_hidden":true,"place_address":"","place_hidden":true,"place":""}],"last_name":"Мальцева","full_name_suggest":{"output":"Мальцева Євгенія Євгеніївна","input":["Мальцева Євгенія Євгеніївна","Євгенія Євгеніївна Мальцева","Євгенія Мальцева"]}},"source":"VULYK","estate":{"25":[{"space_unclear":false,"costs":"","costs_comment":"","address_hidden":false,"region_hidden":true,"space_comment":"","space_hidden":false,"space":"63.8","address":"","region":"","address_unclear":false,"costs_rent_comment":"","space_units":"м²","costs_rent":""}],"27":[{"costs_rent":"","region":"","costs":"","costs_rent_comment":"","costs_comment":"","address_hidden":false,"region_hidden":true,"space_comment":"","space_units":"м²","space":"16","address":""}],"28":[{"costs":"","costs_comment":"","address_hidden":false,"region_hidden":true,"space_comment":"","space":"4.3","address":"","region":"","address_unclear":false,"costs_rent_comment":"","space_units":"м²","costs_rent":""}],"31":[{"space_unclear":false,"address_hidden":false,"region_hidden":true,"space_comment":"","space_hidden":false,"space":"44.2","address":"","region":"","costs_property":"","costs_rent_comment":"","space_units":"м²","costs_property_comment":"","costs_rent":""}]},"intro":{"declaration_year":"2014","declaration_year_unclear":false}}},{"provider":"declarations.com.ua","document":{"income":{"5":{"value":"195187.31","family_comment":"","value_unclear":false,"family_hidden":false,"value_hidden":false,"family_unclear":false,"comment_unclear":false,"comment":"","family":""},"6":{"value":"182570.31","family_unclear":false,"family_hidden":false,"family_comment":"","family":"","comment":""},"7":{"value":"","family_hidden":false,"value_hidden":false,"family_comment":"","source_name":"","family":"","comment":""},"8":{"family_comment":"","value":"","family":"","comment":""},"9":{"family_comment":"","value":"","value_unclear":false,"family":"","comment":""},"10":{"family_comment":"","family_unclear":false,"value":"12617","family":"","comment":""},"11":{"family_comment":"","value":"","family":"","comment":""},"12":{"family_comment":"","value":"","family":"","comment":""},"13":{"family_comment":"","value":"","family":"","comment":""},"14":{"family_comment":"","value":"","family":"","comment":""},"15":{"family_comment":"","value":"","family":"","comment":""},"16":{"family_comment":"","value":"","family":"","comment":""},"17":{"family_comment":"","value":"","family":"","comment":""},"18":{"family_comment":"","value":"","family":"","comment":""},"19":{"family_comment":"","value":"","family":"","comment":""},"20":{"value":"","value_unclear":false,"family_comment":"","comment_unclear":false,"comment":"","family":""}},"vehicle":{"40":[{"brand_info":"2000 куб. см.","sum":"","brand":"Hyundai Sonata","sum_comment":"","brand_unclear":false,"year":"2007","brand_info_hidden":false,"brand_info_unclear":false,"sum_rent_comment":"","sum_rent":""}]},"id":"vulyk_71_49","declaration":{"additional_info_text":"","notfull_lostpages":"","date":"2014-03-24T00:00:00","notfull":"","additional_info":"","url":"http://static.declarations.com.ua/declarations/chosen_ones/judges_batch/586_maltseva_ievheniia_ievhenivna.pdf"},"liabilities":{"54":{"sum_foreign_comment":"","sum":"","sum_comment":"","sum_comment_unclear":false,"sum_comment_hidden":false,"sum_unclear":false,"sum_foreign":""},"55":{"sum_foreign_comment":"","sum":"","sum_comment":"","sum_foreign":""},"56":{"sum_foreign_comment":"","sum":"","sum_comment":"","sum_comment_unclear":false,"sum_unclear":false,"sum_foreign":""},"57":{"sum_foreign_comment":"","sum":"","sum_comment":"","sum_comment_hidden":false,"sum_unclear":false,"sum_foreign":""},"58":{"sum_foreign_comment":"","sum":"","sum_comment":"","sum_comment_hidden":false,"sum_unclear":false,"sum_foreign":""},"59":{"sum_foreign_comment":"","sum_comment_hidden":false,"sum":"","sum_comment":"","sum_foreign":""},"60":{"sum_foreign_comment":"","sum_comment_hidden":false,"sum":"","sum_comment":"","sum_foreign":""},"61":{"sum_foreign_comment":"","sum":"","sum_comment":"","sum_foreign":""},"62":{"sum_foreign_comment":"","sum":"","sum_comment":"","sum_foreign":""},"63":{"sum_foreign_comment":"","sum":"","sum_comment":"","sum_unclear":false,"sum_foreign":""},"64":{"sum_foreign_comment":"","sum":"","sum_comment":"","sum_unclear":false,"sum_foreign":""}},"ft_src":"суддя апеляційного суду донецької області\nДонецька область\nЗагальний апеляційний суд\nЄвгенія\nМальцев І. С\nПодружжя\nМальцева О. І\nДитина\nЄвгеніївна\nМальцева Євгенія Євгеніївна\nЄвгенія Євгеніївна Мальцева\nЄвгенія Мальцева\nМальцева Євгенія Євгеніївна\nМальцева Євгенія Євгеніївна\nМальцева\n2000 куб. см.\nHyundai Sonata\n2007\n4.3\n44.2\n16\n4599\n63.8\n2013\n182570.31\n12617\n195187.31\n2000 куб. см.\n2007\nHyundai Sonata\n16\n44.2\n4.3\n63.8\n4599\nПодружжя\nМальцев І. С\nДитина\nМальцева О. І\nМальцева Євгенія Євгеніївна\nЄвгенія Євгеніївна Мальцева\nЄвгенія Мальцева\nМальцева Євгенія Євгеніївна\nМальцева Євгенія Євгеніївна\nЄвгенія\nЄвгеніївна\nЗагальний апеляційний суд\nДонецька область\nсуддя апеляційного суду донецької області\nМальцева\n182570.31\n195187.31\n12617\n2013\nМальцев І. С\nПодружжя\nМальцева О. І\nДитина\nЄвгеніївна\nМальцева\nЄвгенія\nМальцева Євгенія Євгеніївна\nЄвгенія Євгеніївна Мальцева\nЄвгенія Мальцева\nМальцева Євгенія Євгеніївна\nДонецька область\nЗагальний апеляційний суд\nсуддя апеляційного суду донецької області\nМальцева Євгенія Євгеніївна\nHyundai Sonata\n2000 куб. см.\n2007\n12617\n195187.31\n182570.31\n44.2\n63.8\n4599\n4.3\n16\n2013","general":{"inn":"","name":"Євгенія","family":[{"inn":"","inn_hidden":true,"relations_hidden":false,"family_name":"Мальцев І. С","relations_other":"","relations":"Подружжя","name_hidden":true,"name_unclear":false},{"inn":"","inn_hidden":false,"relations_hidden":false,"family_name":"Мальцева О. І","relations_other":"","relations":"Дитина","name_hidden":false,"name_unclear":false}],"patronymic":"Євгеніївна","inn_hidden":true,"family_raw":"","inn_unclear":false,"post":{"post_unclear":false,"region_unclear":false,"post":"суддя апеляційного суду донецької області","office":"Загальний апеляційний суд","region":"Донецька область","post_hidden":false,"office_unclear":false},"full_name_suggest":{"output":"Мальцева Євгенія Євгеніївна","input":["Мальцева Євгенія Євгеніївна","Євгенія Євгеніївна Мальцева","Євгенія Мальцева"]},"full_name":"Мальцева Євгенія Євгеніївна","addresses":[{"place_district":"","place_unclear":false,"place_city":"","place_city_type_hidden":true,"place_district_hidden":true,"place_city_type":"","place_city_hidden":true,"place_address_hidden":true,"place_address":"","place_hidden":true,"place":""}],"last_name":"Мальцева","patronymic_hidden":false,"last_name_unclear":false,"name_unclear":false},"source":"VULYK","estate":{"25":[{"region_unclear":false,"space_unclear":false,"costs":"","costs_rent_unclear":false,"costs_comment":"","costs_hidden":false,"address_hidden":true,"region_hidden":true,"space_comment":"","space_hidden":false,"space":"63.8","address":"","costs_unclear":false,"region":"","address_unclear":false,"costs_rent_comment":"","costs_rent_hidden":false,"space_comment_unclear":false,"space_units":"м²","costs_rent":"4599"}],"27":[{"space_unclear":false,"costs":"","costs_comment":"","costs_hidden":false,"address_hidden":true,"region_hidden":true,"space_comment":"","space":"16","address":"","region":"","costs_rent_comment":"","costs_comment_hidden":false,"space_units":"м²","costs_rent":""}],"28":[{"costs_rent":"","region":"","costs":"","costs_rent_comment":"","costs_comment":"","address_hidden":true,"region_hidden":true,"space_comment":"","space_units":"м²","space":"4.3","address":""}],"31":[{"space_hidden":false,"costs_property_comment":"","address_hidden":true,"region_hidden":true,"space_comment":"","space":"44.2","address":"","region":"","costs_property":"","costs_rent_comment":"","space_comment_unclear":false,"space_units":"м²","space_units_hidden":false,"costs_rent":""}]},"intro":{"declaration_year":"2013","isnotdeclaration":""}}}],"declarations":[{"income":{"5":{"family_comment":"","value":"209438.48","family":"","comment":""},"6":{"family_comment":"","value":"196040.48","family":"","comment":"","family_comment_unclear":false},"7":{"value":"","comment_hidden":false,"family_comment":"","source_name":"","family":"","comment":"","source_name_hidden":false},"8":{"family_comment":"","value":"","family":"","comment":""},"9":{"family_comment":"","value":"","family":"","comment":""},"10":{"value":"13398","value_unclear":false,"value_hidden":false,"family_comment":"","family":"","comment":""},"11":{"family_comment":"","value":"","family":"","comment":""},"12":{"family_comment":"","value":"","family":"","comment":""},"13":{"family_comment":"","value":"","family":"","comment":""},"14":{"family_comment":"","value":"","family":"","comment":""},"15":{"family_comment":"","value":"","family":"","comment":""},"16":{"family_comment":"","value":"","family":"","comment":""},"17":{"family_comment":"","value":"","family":"","comment":""},"18":{"family_comment":"","value":"","family":"","comment":""},"19":{"family_comment":"","value":"","family":"","comment":""},"20":{"family_comment":"","value":"","comment_unclear":false,"family":"","comment":""}},"vehicle":{"40":[{"brand_info":"2000 куб. см.","sum_rent_comment":"","brand":"Hyundai Sonata","sum_comment":"","brand_unclear":false,"year":"2007","sum":"","sum_rent":""}]},"id":"vulyk_86_35","declaration":{"additional_info_text":"","notfull_lostpages":"","date":"2015-03-24T00:00:00","notfull":"","additional_info":"","url":"http://static.declarations.com.ua/declarations/chosen_ones/judges_batch/2738_maltseva_ievheniia_ievhenivna.pdf"},"liabilities":{"54":{"sum_foreign_comment":"","sum":"","sum_comment":"","sum_unclear":false,"sum_foreign":""},"55":{"sum_foreign_comment":"","sum":"","sum_comment":"","sum_foreign":""},"56":{"sum_foreign_comment":"","sum":"","sum_hidden":false,"sum_comment":"","sum_foreign":""},"57":{"sum_foreign_comment":"","sum":"","sum_comment":"","sum_unclear":false,"sum_foreign":""},"58":{"sum_foreign_comment":"","sum":"","sum_comment":"","sum_unclear":false,"sum_foreign":""},"59":{"sum_foreign_comment":"","sum":"","sum_comment":"","sum_foreign":""},"60":{"sum_foreign_comment":"","sum_comment_hidden":false,"sum":"","sum_comment":"","sum_foreign":""},"61":{"sum_foreign_comment":"","sum":"","sum_comment":"","sum_foreign":""},"62":{"sum_foreign_comment":"","sum":"","sum_comment":"","sum_foreign":""},"63":{"sum_foreign_comment":"","sum":"","sum_comment":"","sum_foreign":""},"64":{"sum_foreign_comment":"","sum":"","sum_comment":"","sum_foreign":""}},"ft_src":"суддя апеляційного суду донецької області\nДонецька область\nЗагальний апеляційний суд\nЄвгенія\nМальцев І. С\nПодружжя\nМальцева О. І\nДитина\nЄвгеніївна\nМальцева Євгенія Євгеніївна\nЄвгенія Євгеніївна Мальцева\nЄвгенія Мальцева\nМальцева Євгенія Євгеніївна\nМальцева Євгенія Євгеніївна\nМальцева\n2007\n2000 куб. см.\nHyundai Sonata\n4.3\n44.2\n16\n63.8\n2014\n196040.48\n13398\n209438.48\n2000 куб. см.\nHyundai Sonata\n2007\n2014\nМальцева Євгенія Євгеніївна\nЄвгенія Євгеніївна Мальцева\nЄвгенія Мальцева\nМальцева Євгенія Євгеніївна\nМальцева Євгенія Євгеніївна\nПодружжя\nМальцев І. С\nДитина\nМальцева О. І\nЄвгенія\nМальцева\nЗагальний апеляційний суд\nДонецька область\nсуддя апеляційного суду донецької області\nЄвгеніївна\n196040.48\n209438.48\n13398\n16\n44.2\n4.3\n63.8\nМальцев І. С\nПодружжя\nМальцева О. І\nДитина\nЄвгеніївна\nМальцева\nЄвгенія\nМальцева Євгенія Євгеніївна\nЄвгенія Євгеніївна Мальцева\nЄвгенія Мальцева\nМальцева Євгенія Євгеніївна\nДонецька область\nЗагальний апеляційний суд\nсуддя апеляційного суду донецької області\nМальцева Євгенія Євгеніївна\n2007\n2000 куб. см.\nHyundai Sonata\n13398\n209438.48\n196040.48\n44.2\n63.8\n4.3\n16\n2014","general":{"inn":"","name":"Євгенія","patronymic_unclear":false,"family":[{"inn":"","inn_hidden":true,"relations_hidden":false,"family_name":"Мальцев І. С","relations_other":"","relations":"Подружжя","name_hidden":false,"name_unclear":false},{"inn":"","relations":"Дитина","relations_other":"","inn_hidden":true,"family_name":"Мальцева О. І","name_hidden":false,"name_unclear":false}],"patronymic":"Євгеніївна","inn_hidden":true,"family_raw":"","inn_unclear":false,"post":{"post_unclear":false,"post":"суддя апеляційного суду донецької області","candidate":"","office_hidden":false,"region":"Донецька область","office":"Загальний апеляційний суд","office_unclear":false,"region_hidden":false},"full_name":"Мальцева Євгенія Євгеніївна","addresses":[{"place_district":"","place_unclear":false,"place_city":"","place_city_type_hidden":false,"place_district_hidden":false,"place_city_type":"","place_city_hidden":true,"place_address_hidden":true,"place_address":"","place_hidden":true,"place":""}],"last_name":"Мальцева","full_name_suggest":{"output":"Мальцева Євгенія Євгеніївна","input":["Мальцева Євгенія Євгеніївна","Євгенія Євгеніївна Мальцева","Євгенія Мальцева"]}},"source":"VULYK","estate":{"25":[{"space_unclear":false,"costs":"","costs_comment":"","address_hidden":false,"region_hidden":true,"space_comment":"","space_hidden":false,"space":"63.8","address":"","region":"","address_unclear":false,"costs_rent_comment":"","space_units":"м²","costs_rent":""}],"27":[{"costs_rent":"","region":"","costs":"","costs_rent_comment":"","costs_comment":"","address_hidden":false,"region_hidden":true,"space_comment":"","space_units":"м²","space":"16","address":""}],"28":[{"costs":"","costs_comment":"","address_hidden":false,"region_hidden":true,"space_comment":"","space":"4.3","address":"","region":"","address_unclear":false,"costs_rent_comment":"","space_units":"м²","costs_rent":""}],"31":[{"space_unclear":false,"address_hidden":false,"region_hidden":true,"space_comment":"","space_hidden":false,"space":"44.2","address":"","region":"","costs_property":"","costs_rent_comment":"","space_units":"м²","costs_property_comment":"","costs_rent":""}]},"intro":{"declaration_year":"2014","declaration_year_unclear":false}},{"income":{"5":{"value":"195187.31","family_comment":"","value_unclear":false,"family_hidden":false,"value_hidden":false,"family_unclear":false,"comment_unclear":false,"comment":"","family":""},"6":{"value":"182570.31","family_unclear":false,"family_hidden":false,"family_comment":"","family":"","comment":""},"7":{"value":"","family_hidden":false,"value_hidden":false,"family_comment":"","source_name":"","family":"","comment":""},"8":{"family_comment":"","value":"","family":"","comment":""},"9":{"family_comment":"","value":"","value_unclear":false,"family":"","comment":""},"10":{"family_comment":"","family_unclear":false,"value":"12617","family":"","comment":""},"11":{"family_comment":"","value":"","family":"","comment":""},"12":{"family_comment":"","value":"","family":"","comment":""},"13":{"family_comment":"","value":"","family":"","comment":""},"14":{"family_comment":"","value":"","family":"","comment":""},"15":{"family_comment":"","value":"","family":"","comment":""},"16":{"family_comment":"","value":"","family":"","comment":""},"17":{"family_comment":"","value":"","family":"","comment":""},"18":{"family_comment":"","value":"","family":"","comment":""},"19":{"family_comment":"","value":"","family":"","comment":""},"20":{"value":"","value_unclear":false,"family_comment":"","comment_unclear":false,"comment":"","family":""}},"vehicle":{"40":[{"brand_info":"2000 куб. см.","sum":"","brand":"Hyundai Sonata","sum_comment":"","brand_unclear":false,"year":"2007","brand_info_hidden":false,"brand_info_unclear":false,"sum_rent_comment":"","sum_rent":""}]},"id":"vulyk_71_49","declaration":{"additional_info_text":"","notfull_lostpages":"","date":"2014-03-24T00:00:00","notfull":"","additional_info":"","url":"http://static.declarations.com.ua/declarations/chosen_ones/judges_batch/586_maltseva_ievheniia_ievhenivna.pdf"},"liabilities":{"54":{"sum_foreign_comment":"","sum":"","sum_comment":"","sum_comment_unclear":false,"sum_comment_hidden":false,"sum_unclear":false,"sum_foreign":""},"55":{"sum_foreign_comment":"","sum":"","sum_comment":"","sum_foreign":""},"56":{"sum_foreign_comment":"","sum":"","sum_comment":"","sum_comment_unclear":false,"sum_unclear":false,"sum_foreign":""},"57":{"sum_foreign_comment":"","sum":"","sum_comment":"","sum_comment_hidden":false,"sum_unclear":false,"sum_foreign":""},"58":{"sum_foreign_comment":"","sum":"","sum_comment":"","sum_comment_hidden":false,"sum_unclear":false,"sum_foreign":""},"59":{"sum_foreign_comment":"","sum_comment_hidden":false,"sum":"","sum_comment":"","sum_foreign":""},"60":{"sum_foreign_comment":"","sum_comment_hidden":false,"sum":"","sum_comment":"","sum_foreign":""},"61":{"sum_foreign_comment":"","sum":"","sum_comment":"","sum_foreign":""},"62":{"sum_foreign_comment":"","sum":"","sum_comment":"","sum_foreign":""},"63":{"sum_foreign_comment":"","sum":"","sum_comment":"","sum_unclear":false,"sum_foreign":""},"64":{"sum_foreign_comment":"","sum":"","sum_comment":"","sum_unclear":false,"sum_foreign":""}},"ft_src":"суддя апеляційного суду донецької області\nДонецька область\nЗагальний апеляційний суд\nЄвгенія\nМальцев І. С\nПодружжя\nМальцева О. І\nДитина\nЄвгеніївна\nМальцева Євгенія Євгеніївна\nЄвгенія Євгеніївна Мальцева\nЄвгенія Мальцева\nМальцева Євгенія Євгеніївна\nМальцева Євгенія Євгеніївна\nМальцева\n2000 куб. см.\nHyundai Sonata\n2007\n4.3\n44.2\n16\n4599\n63.8\n2013\n182570.31\n12617\n195187.31\n2000 куб. см.\n2007\nHyundai Sonata\n16\n44.2\n4.3\n63.8\n4599\nПодружжя\nМальцев І. С\nДитина\nМальцева О. І\nМальцева Євгенія Євгеніївна\nЄвгенія Євгеніївна Мальцева\nЄвгенія Мальцева\nМальцева Євгенія Євгеніївна\nМальцева Євгенія Євгеніївна\nЄвгенія\nЄвгеніївна\nЗагальний апеляційний суд\nДонецька область\nсуддя апеляційного суду донецької області\nМальцева\n182570.31\n195187.31\n12617\n2013\nМальцев І. С\nПодружжя\nМальцева О. І\nДитина\nЄвгеніївна\nМальцева\nЄвгенія\nМальцева Євгенія Євгеніївна\nЄвгенія Євгеніївна Мальцева\nЄвгенія Мальцева\nМальцева Євгенія Євгеніївна\nДонецька область\nЗагальний апеляційний суд\nсуддя апеляційного суду донецької області\nМальцева Євгенія Євгеніївна\nHyundai Sonata\n2000 куб. см.\n2007\n12617\n195187.31\n182570.31\n44.2\n63.8\n4599\n4.3\n16\n2013","general":{"inn":"","name":"Євгенія","family":[{"inn":"","inn_hidden":true,"relations_hidden":false,"family_name":"Мальцев І. С","relations_other":"","relations":"Подружжя","name_hidden":true,"name_unclear":false},{"inn":"","inn_hidden":false,"relations_hidden":false,"family_name":"Мальцева О. І","relations_other":"","relations":"Дитина","name_hidden":false,"name_unclear":false}],"patronymic":"Євгеніївна","inn_hidden":true,"family_raw":"","inn_unclear":false,"post":{"post_unclear":false,"region_unclear":false,"post":"суддя апеляційного суду донецької області","office":"Загальний апеляційний суд","region":"Донецька область","post_hidden":false,"office_unclear":false},"full_name_suggest":{"output":"Мальцева Євгенія Євгеніївна","input":["Мальцева Євгенія Євгеніївна","Євгенія Євгеніївна Мальцева","Євгенія Мальцева"]},"full_name":"Мальцева Євгенія Євгеніївна","addresses":[{"place_district":"","place_unclear":false,"place_city":"","place_city_type_hidden":true,"place_district_hidden":true,"place_city_type":"","place_city_hidden":true,"place_address_hidden":true,"place_address":"","place_hidden":true,"place":""}],"last_name":"Мальцева","patronymic_hidden":false,"last_name_unclear":false,"name_unclear":false},"source":"VULYK","estate":{"25":[{"region_unclear":false,"space_unclear":false,"costs":"","costs_rent_unclear":false,"costs_comment":"","costs_hidden":false,"address_hidden":true,"region_hidden":true,"space_comment":"","space_hidden":false,"space":"63.8","address":"","costs_unclear":false,"region":"","address_unclear":false,"costs_rent_comment":"","costs_rent_hidden":false,"space_comment_unclear":false,"space_units":"м²","costs_rent":"4599"}],"27":[{"space_unclear":false,"costs":"","costs_comment":"","costs_hidden":false,"address_hidden":true,"region_hidden":true,"space_comment":"","space":"16","address":"","region":"","costs_rent_comment":"","costs_comment_hidden":false,"space_units":"м²","costs_rent":""}],"28":[{"costs_rent":"","region":"","costs":"","costs_rent_comment":"","costs_comment":"","address_hidden":true,"region_hidden":true,"space_comment":"","space_units":"м²","space":"4.3","address":""}],"31":[{"space_hidden":false,"costs_property_comment":"","address_hidden":true,"region_hidden":true,"space_comment":"","space":"44.2","address":"","region":"","costs_property":"","costs_rent_comment":"","space_comment_unclear":false,"space_units":"м²","space_units_hidden":false,"costs_rent":""}]},"intro":{"declaration_year":"2013","isnotdeclaration":""}}],"declarationsLength":2,"analytics":[{"y":2014,"i":209438.48,"k":63.8,"ka":1,"ff":44.2,"ffa":1},{"y":2013,"i":195187.31,"k":63.8,"ka":1,"ff":44.2,"ffa":1}]}