{"2010":1,"2016":1,"Department":"Братський районний суд Миколаївської області","Region":"Миколаївська область","Position":"Голова Братського районного суду Миколаївської області","Name":"Марценюк Сергій Анатолійович","Link":"https://drive.google.com/open?id=0BygiyWAl79DMTHl6Qkp5djZzcE0","Note":"У меня","AdditionalNote":"","field8":"","field9":"","field10":"","Кількість справ":"","Оскаржені":"","Кількість скарг":0,"Кількість дисциплінарних стягнень":"","Клейма":3,"Фото":"http://picua.org/img/2016-10/06/l4hyhu10zdc6fkyrhnwa2t0n5.jpg","Як живе":"","key":"marcenyuk_sergiy_anatoliyovich","allDeclarations":[{"provider":"declarations.com.ua","document":{"income":{"5":{"value":"248550","family_comment":"","value_unclear":false,"family_hidden":false,"value_hidden":false,"family_unclear":false,"comment_unclear":false,"comment":"","family":"72200"},"6":{"value":"236370","family_comment":"","value_unclear":false,"family_hidden":false,"value_hidden":false,"family_unclear":false,"comment_unclear":false,"comment":"","family":""},"7":{"source_name_unclear":false,"value":"","family_comment":"","source_name":"","family":"","comment":""},"8":{"family_comment":"","value":"","family":"","comment":""},"9":{"value":"","value_unclear":false,"comment_hidden":false,"family_comment":"","comment_unclear":false,"comment":"","family":""},"10":{"value":"12180","comment_unclear":false,"value_hidden":false,"family_comment":"","family":"","comment":""},"11":{"family_comment":"","value":"","family":"","comment":""},"12":{"family_comment":"","value":"","family":"","comment":""},"13":{"family_comment":"","value":"","family":"","comment":""},"14":{"family_comment":"","value":"","family":"","comment":""},"15":{"family_comment":"","value":"","family":"","comment":""},"16":{"family_comment":"","value":"","family":"","comment":""},"17":{"family_comment":"","value":"","family":"72200","comment":""},"18":{"value":"","family_hidden":false,"value_hidden":false,"family_comment":"","family":"","comment":""},"19":{"family_comment":"","value":"","family":"","comment":""},"20":{"value":"","family_comment":"","value_unclear":false,"family_hidden":false,"value_hidden":false,"family_unclear":false,"family":"","comment":""}},"id":"vulyk_66_175","declaration":{"additional_info_text":"","notfull_lostpages":"","date":"2015-03-17T00:00:00","notfull":"","additional_info":"","url":"http://static.declarations.com.ua/declarations/chosen_ones/mega_batch/martseniuk_serhii_anatoliiovych.pdf"},"liabilities":{"54":{"sum_foreign_comment":"","sum":"","sum_comment":"","sum_comment_unclear":false,"sum_comment_hidden":false,"sum_unclear":false,"sum_foreign":""},"55":{"sum_foreign_comment":"","sum":"","sum_comment":"","sum_foreign":""},"56":{"sum_foreign_comment":"","sum_foreign_hidden":false,"sum_comment":"","sum_hidden":false,"sum_comment_hidden":false,"sum":"6921","sum_foreign":""},"57":{"sum_foreign_comment":"","sum":"","sum_comment":"","sum_comment_unclear":false,"sum_hidden":false,"sum_comment_hidden":false,"sum_unclear":false,"sum_foreign":""},"58":{"sum_foreign_comment":"","sum":"","sum_comment":"","sum_comment_unclear":false,"sum_unclear":false,"sum_foreign":""},"59":{"sum_foreign_comment":"","sum_foreign_hidden":false,"sum_comment":"","sum_comment_unclear":false,"sum_hidden":false,"sum":"","sum_foreign":""},"60":{"sum_foreign_comment":"","sum":"","sum_comment":"","sum_comment_unclear":false,"sum_foreign":""},"61":{"sum_foreign_comment":"","sum":"","sum_comment":"","sum_foreign":""},"62":{"sum_foreign_comment":"","sum_foreign_hidden":false,"sum_comment":"","sum_hidden":false,"sum":"","sum_unclear":false,"sum_foreign":""},"63":{"sum_foreign_comment":"","sum":"","sum_comment":"","sum_comment_unclear":false,"sum_comment_hidden":false,"sum_unclear":false,"sum_foreign":""},"64":{"sum_foreign_comment":"","sum":"","sum_comment":"","sum_comment_unclear":false,"sum_foreign":""}},"ft_src":"6921\nБратське\n55401\nБратський\nМиколаївська область\nСМТ\nсуддя, голова братського районного суду миколаївської області\nМиколаївська область\nЗагальний місцевий суд\nСергій\nМарценюк І. Є\nПодружжя\nМарценюк Р. С\nДитина\nАнатолійович\nМарценюк Сергій Анатолійович\nСергій Анатолійович Марценюк\nСергій Марценюк\nМарценюк Сергій Анатолійович\nМарценюк Сергій Анатолійович\nМарценюк\n12180\n248550\n72200\n72200\n236370\nс. Братське\n.15\nМиколаївська область\nс. Братське\n805\nМиколаївська область\nм. Конотоп\n0.1083\nСумська область\nм. Конотоп\n590\nСумська область\nс. Братське\n96\nМиколаївська область\nм. Конотоп\n38.3\nСумська область\nм. Конотоп\n69.1\nСумська область\n2014\n236370\n12180\n72200\n248550\n72200\n.15\nМиколаївська область\nс. Братське\n805\nс. Братське\nМиколаївська область\n0.1083\nм. Конотоп\nСумська область\n590\nм. Конотоп\nСумська область\n96\nс. Братське\nМиколаївська область\nм. Конотоп\n38.3\nСумська область\n69.1\nм. Конотоп\nСумська область\nЗагальний місцевий суд\nсуддя, голова братського районного суду миколаївської області\nМиколаївська область\nПодружжя\nМарценюк І. Є\nДитина\nМарценюк Р. С\nМарценюк Сергій Анатолійович\nСергій Анатолійович Марценюк\nСергій Марценюк\nМарценюк Сергій Анатолійович\nМарценюк Сергій Анатолійович\nСергій\nМарценюк\nАнатолійович\nСМТ\nБратське\n55401\nМиколаївська область\nБратський\n6921\n236370\n72200\n248550\n72200\n12180\n2014\n6921\nМарценюк І. Є\nПодружжя\nМарценюк Р. С\nДитина\nАнатолійович\nМарценюк\nСергій\nМарценюк Сергій Анатолійович\nСергій Анатолійович Марценюк\nСергій Марценюк\nМарценюк Сергій Анатолійович\nМиколаївська область\nБратське\nБратський\nСМТ\n55401\nМиколаївська область\nсуддя, голова братського районного суду миколаївської області\nЗагальний місцевий суд\nМарценюк Сергій Анатолійович\nс. Братське\nМиколаївська область\n.15\nс. Братське\nМиколаївська область\n805\nм. Конотоп\nСумська область\n0.1083\nм. Конотоп\nСумська область\n590\nс. Братське\nМиколаївська область\n96\nСумська область\nм. Конотоп\n38.3\nм. Конотоп\nСумська область\n69.1\n2014","general":{"inn":"","name":"Сергій","last_name_hidden":false,"family":[{"inn":"","inn_hidden":true,"relations_hidden":false,"family_name":"Марценюк І. Є","relations_other":"","relations":"Подружжя","name_hidden":false,"name_unclear":false},{"inn":"","inn_hidden":false,"relations_unclear":false,"relations_hidden":false,"relations_other":"","relations":"Дитина","name_hidden":false,"family_name":"Марценюк Р. С","name_unclear":false}],"patronymic":"Анатолійович","inn_hidden":true,"family_raw":"","inn_unclear":false,"post":{"post_unclear":false,"post":"суддя, голова братського районного суду миколаївської області","candidate":"","office_hidden":false,"region":"Миколаївська область","office":"Загальний місцевий суд","office_unclear":false},"full_name_suggest":{"output":"Марценюк Сергій Анатолійович","input":["Марценюк Сергій Анатолійович","Сергій Анатолійович Марценюк","Сергій Марценюк"]},"full_name":"Марценюк Сергій Анатолійович","addresses":[{"place_city_type_unclear":true,"place_address":"55401","place_district_hidden":false,"place_city_type":"СМТ","place_address_hidden":true,"place_address_unclear":false,"place_city_type_hidden":false,"place":"Миколаївська область","place_district":"Братський","place_unclear":false,"place_city":"Братське","place_city_unclear":false,"place_hidden":false,"place_city_hidden":false,"place_district_unclear":false}],"last_name":"Марценюк","last_name_unclear":false},"source":"VULYK","estate":{"23":[{"space_unclear":false,"costs":"","costs_comment":"","costs_hidden":false,"address_hidden":true,"region_hidden":false,"space_comment":"","space_hidden":false,"space":".15","space_units_hidden":false,"region":"Миколаївська область","address_unclear":false,"space_units_unclear":false,"space_units":"га","address":"с. Братське","costs_rent":"","costs_rent_comment":""},{"costs_rent":"","region":"Миколаївська область","costs":"","costs_rent_comment":"","costs_comment":"","address_hidden":false,"space_comment":"","space_units":"м²","space":"805","address":"с. Братське"},{"costs_rent":"","region":"Сумська область","costs":"","costs_rent_comment":"","costs_comment":"","address_hidden":false,"space_comment":"","space_units":"м²","space":"0.1083","address":"м. Конотоп"},{"costs_rent":"","region":"Сумська область","costs":"","costs_rent_comment":"","costs_comment":"","space_comment":"","space_units":"м²","space":"590","address":"м. Конотоп"}],"24":[{"space_unclear":false,"costs":"","costs_comment":"","costs_hidden":false,"address_hidden":true,"region_hidden":false,"space_comment":"","space_hidden":false,"space":"96","address":"с. Братське","region":"Миколаївська область","address_unclear":false,"costs_rent_comment":"","costs_rent_hidden":false,"space_comment_unclear":false,"space_units":"м²","costs_rent":""},{"costs_rent":"","region":"Сумська область","costs":"","costs_rent_comment":"","costs_comment":"","region_hidden":false,"space_comment":"","space_units":"м²","space":"38.3","address":"м. Конотоп"},{"costs_rent":"","region":"Сумська область","costs":"","costs_rent_comment":"","costs_comment":"","space_comment":"","space_units":"м²","space":"69.1","address":"м. Конотоп"}]},"intro":{"declaration_year":"2014","isnotdeclaration":"","declaration_year_unclear":false}}},{"provider":"public-api.nazk.gov.ua","document":{"step_0":{"declarationType":"1","declarationYear1":"2015"},"step_1":{"street":"[Конфіденційна інформація]","country":"1","birthday":"[Конфіденційна інформація]","cityPath":"[Конфіденційна інформація]","cityType":"[Конфіденційна інформація]","lastname":"Марценюк","postCode":"[Конфіденційна інформація]","postType":"Посада державної служби","workPost":"суддя","buildType":"житловий будинок","firstname":"Сергій","workPlace":"голова Братського районного суду Миколаївської області","middlename":"Анатолійович","streetType":"[Конфіденційна інформація]","changedName":false,"eng_postCode":"","postCategory":"","actual_street":"[Конфіденційна інформація]","actual_cityType":"[Конфіденційна інформація]","actual_postCode":"[Конфіденційна інформація]","actual_buildType":"","actual_streetType":"[Конфіденційна інформація]","previous_lastname":"","corruptionAffected":"Ні","eng_actualPostCode":"[Конфіденційна інформація]","previous_firstname":"","previous_middlename":"","responsiblePosition":"Суддя суду загальної юрисдикції, суддя Конституційного Суду України","sameRegLivingAddress":"[Конфіденційна інформація]","eng_sameRegLivingAddress":"[Конфіденційна інформація]"},"step_2":{"1473925257737":{"lastname":"Марценюк","firstname":"Роман","middlename":"Сергійович","changedName":false,"citizenship":"1","eng_lastname":"","no_taxNumber":true,"eng_firstname":"","eng_middlename":"","isNotApplicable":"","subjectRelation":"син","previous_lastname":"","previous_firstname":"","previous_middlename":"","previous_eng_lastname":"","previous_eng_firstname":"","previous_eng_middlename":""}},"step_3":{"1473925638972":{"person":"1","rights":{"1":{"citizen":"","ua_lastname":"","eng_lastname":"","rightBelongs":"1","ua_firstname":"","eng_firstname":"","ownershipType":"Власність","ua_middlename":"","eng_middlename":"","otherOwnership":"","ua_company_name":"","eng_company_name":"","ukr_company_name":"","percent-ownership":""}},"country":"1","costDate":"00","postCode":"[Конфіденційна інформація]","totalArea":"1000","ua_street":"[Конфіденційна інформація]","objectType":"Земельна ділянка","owningDate":"03.06.2009","ua_cityType":"Конотоп / Сумська Область/м.Суми / Україна","ua_postCode":"41606","ua_buildType":"","ua_streetType":"[Конфіденційна інформація]","costAssessment":"00","otherObjectType":"","costDate_extendedstatus":"0"},"1473926213792":{"person":"1","rights":{"1":{"citizen":"","ua_lastname":"","eng_lastname":"","rightBelongs":"1","ua_firstname":"","eng_firstname":"","ownershipType":"Власність","ua_middlename":"","eng_middlename":"","otherOwnership":"","ua_company_name":"","eng_company_name":"","ukr_company_name":"","percent-ownership":""}},"country":"1","costDate":"00","postCode":"[Конфіденційна інформація]","totalArea":"830","ua_street":"[Конфіденційна інформація]","objectType":"Земельна ділянка","owningDate":"03.05.2009","ua_cityType":"Конотоп","ua_postCode":"41606","ua_buildType":"","ua_streetType":"[Конфіденційна інформація]","costAssessment":"00","otherObjectType":""},"1473926357591":{"person":"1","rights":{"1":{"citizen":"","ua_lastname":"","eng_lastname":"","rightBelongs":"1","ua_firstname":"","eng_firstname":"","ownershipType":"Власність","ua_middlename":"","eng_middlename":"","otherOwnership":"","ua_company_name":"","eng_company_name":"","ukr_company_name":"","percent-ownership":""}},"country":"1","costDate":"00","postCode":"[Конфіденційна інформація]","totalArea":"590","ua_street":"[Конфіденційна інформація]","objectType":"Земельна ділянка","owningDate":"17.03.2009","ua_cityType":"Конотоп","ua_postCode":"41606","ua_buildType":"","ua_streetType":"[Конфіденційна інформація]","costAssessment":"00","otherObjectType":""},"1473926507854":{"person":"1","rights":{"1":{"citizen":"","ua_lastname":"","eng_lastname":"","rightBelongs":"1","ua_firstname":"","eng_firstname":"","ownershipType":"Власність","ua_middlename":"","eng_middlename":"","otherOwnership":"","ua_company_name":"","eng_company_name":"","ukr_company_name":"","percent-ownership":""}},"country":"1","costDate":"00","postCode":"[Конфіденційна інформація]","totalArea":"69","ua_street":"[Конфіденційна інформація]","objectType":"Житловий будинок","owningDate":"22.09.2009","ua_cityType":"Конотоп","ua_postCode":"41606","ua_buildType":"житловий будинок","ua_streetType":"[Конфіденційна інформація]","costAssessment":"00","otherObjectType":""},"1473926690224":{"person":"1","rights":{"1":{"citizen":"","ua_lastname":"","eng_lastname":"","rightBelongs":"1","ua_firstname":"","eng_firstname":"","ownershipType":"Власність","ua_middlename":"","eng_middlename":"","otherOwnership":"","ua_company_name":"","eng_company_name":"","ukr_company_name":"","percent-ownership":""}},"country":"1","costDate":"00","postCode":"[Конфіденційна інформація]","totalArea":"38","ua_street":"[Конфіденційна інформація]","objectType":"Житловий будинок","owningDate":"06.06.2008","ua_cityType":"Конотоп","ua_postCode":"41606","ua_buildType":"житловий будинок","ua_streetType":"[Конфіденційна інформація]","costAssessment":"00","otherObjectType":""}},"step_4":[],"step_5":[],"step_6":[],"step_7":[],"step_8":[],"step_9":[],"step_10":[],"step_11":{"1473926989587":{"person":"1","rights":{"1":{"citizen":"","ua_lastname":"","eng_lastname":"","rightBelongs":"1","ua_firstname":"","eng_firstname":"","ownershipType":"Власність","ua_middlename":"","eng_middlename":"","otherOwnership":"","ua_company_name":"","eng_company_name":"","ukr_company_name":"","percent-ownership":""}},"objectType":"Заробітна плата отримана за основним місцем роботи","sizeIncome":"254537","incomeSource":"1","source_citizen":"","otherObjectType":"","source_ua_lastname":"","source_eng_lastname":"","source_ua_firstname":"","source_ukr_lastname":"","source_eng_firstname":"","source_ua_middlename":"","source_ukr_firstname":"","source_eng_middlename":"","source_ukr_middlename":"","source_ua_company_name":"","source_eng_company_name":"","source_ukr_company_name":"","source_ua_sameRegLivingAddress":"","source_eng_sameRegLivingAddress":""}},"step_12":[],"step_13":[],"step_14":[],"step_15":[],"step_16":{"org":[],"part_org":[]},"id":"88fe06d4-6dcd-402e-b1fa-6dec7b0ca490"}}],"declarations":[{"income":{"5":{"value":"248550","family_comment":"","value_unclear":false,"family_hidden":false,"value_hidden":false,"family_unclear":false,"comment_unclear":false,"comment":"","family":"72200"},"6":{"value":"236370","family_comment":"","value_unclear":false,"family_hidden":false,"value_hidden":false,"family_unclear":false,"comment_unclear":false,"comment":"","family":""},"7":{"source_name_unclear":false,"value":"","family_comment":"","source_name":"","family":"","comment":""},"8":{"family_comment":"","value":"","family":"","comment":""},"9":{"value":"","value_unclear":false,"comment_hidden":false,"family_comment":"","comment_unclear":false,"comment":"","family":""},"10":{"value":"12180","comment_unclear":false,"value_hidden":false,"family_comment":"","family":"","comment":""},"11":{"family_comment":"","value":"","family":"","comment":""},"12":{"family_comment":"","value":"","family":"","comment":""},"13":{"family_comment":"","value":"","family":"","comment":""},"14":{"family_comment":"","value":"","family":"","comment":""},"15":{"family_comment":"","value":"","family":"","comment":""},"16":{"family_comment":"","value":"","family":"","comment":""},"17":{"family_comment":"","value":"","family":"72200","comment":""},"18":{"value":"","family_hidden":false,"value_hidden":false,"family_comment":"","family":"","comment":""},"19":{"family_comment":"","value":"","family":"","comment":""},"20":{"value":"","family_comment":"","value_unclear":false,"family_hidden":false,"value_hidden":false,"family_unclear":false,"family":"","comment":""}},"id":"vulyk_66_175","declaration":{"additional_info_text":"","notfull_lostpages":"","date":"2015-03-17T00:00:00","notfull":"","additional_info":"","url":"http://static.declarations.com.ua/declarations/chosen_ones/mega_batch/martseniuk_serhii_anatoliiovych.pdf"},"liabilities":{"54":{"sum_foreign_comment":"","sum":"","sum_comment":"","sum_comment_unclear":false,"sum_comment_hidden":false,"sum_unclear":false,"sum_foreign":""},"55":{"sum_foreign_comment":"","sum":"","sum_comment":"","sum_foreign":""},"56":{"sum_foreign_comment":"","sum_foreign_hidden":false,"sum_comment":"","sum_hidden":false,"sum_comment_hidden":false,"sum":"6921","sum_foreign":""},"57":{"sum_foreign_comment":"","sum":"","sum_comment":"","sum_comment_unclear":false,"sum_hidden":false,"sum_comment_hidden":false,"sum_unclear":false,"sum_foreign":""},"58":{"sum_foreign_comment":"","sum":"","sum_comment":"","sum_comment_unclear":false,"sum_unclear":false,"sum_foreign":""},"59":{"sum_foreign_comment":"","sum_foreign_hidden":false,"sum_comment":"","sum_comment_unclear":false,"sum_hidden":false,"sum":"","sum_foreign":""},"60":{"sum_foreign_comment":"","sum":"","sum_comment":"","sum_comment_unclear":false,"sum_foreign":""},"61":{"sum_foreign_comment":"","sum":"","sum_comment":"","sum_foreign":""},"62":{"sum_foreign_comment":"","sum_foreign_hidden":false,"sum_comment":"","sum_hidden":false,"sum":"","sum_unclear":false,"sum_foreign":""},"63":{"sum_foreign_comment":"","sum":"","sum_comment":"","sum_comment_unclear":false,"sum_comment_hidden":false,"sum_unclear":false,"sum_foreign":""},"64":{"sum_foreign_comment":"","sum":"","sum_comment":"","sum_comment_unclear":false,"sum_foreign":""}},"ft_src":"6921\nБратське\n55401\nБратський\nМиколаївська область\nСМТ\nсуддя, голова братського районного суду миколаївської області\nМиколаївська область\nЗагальний місцевий суд\nСергій\nМарценюк І. Є\nПодружжя\nМарценюк Р. С\nДитина\nАнатолійович\nМарценюк Сергій Анатолійович\nСергій Анатолійович Марценюк\nСергій Марценюк\nМарценюк Сергій Анатолійович\nМарценюк Сергій Анатолійович\nМарценюк\n12180\n248550\n72200\n72200\n236370\nс. Братське\n.15\nМиколаївська область\nс. Братське\n805\nМиколаївська область\nм. Конотоп\n0.1083\nСумська область\nм. Конотоп\n590\nСумська область\nс. Братське\n96\nМиколаївська область\nм. Конотоп\n38.3\nСумська область\nм. Конотоп\n69.1\nСумська область\n2014\n236370\n12180\n72200\n248550\n72200\n.15\nМиколаївська область\nс. Братське\n805\nс. Братське\nМиколаївська область\n0.1083\nм. Конотоп\nСумська область\n590\nм. Конотоп\nСумська область\n96\nс. Братське\nМиколаївська область\nм. Конотоп\n38.3\nСумська область\n69.1\nм. Конотоп\nСумська область\nЗагальний місцевий суд\nсуддя, голова братського районного суду миколаївської області\nМиколаївська область\nПодружжя\nМарценюк І. Є\nДитина\nМарценюк Р. С\nМарценюк Сергій Анатолійович\nСергій Анатолійович Марценюк\nСергій Марценюк\nМарценюк Сергій Анатолійович\nМарценюк Сергій Анатолійович\nСергій\nМарценюк\nАнатолійович\nСМТ\nБратське\n55401\nМиколаївська область\nБратський\n6921\n236370\n72200\n248550\n72200\n12180\n2014\n6921\nМарценюк І. Є\nПодружжя\nМарценюк Р. С\nДитина\nАнатолійович\nМарценюк\nСергій\nМарценюк Сергій Анатолійович\nСергій Анатолійович Марценюк\nСергій Марценюк\nМарценюк Сергій Анатолійович\nМиколаївська область\nБратське\nБратський\nСМТ\n55401\nМиколаївська область\nсуддя, голова братського районного суду миколаївської області\nЗагальний місцевий суд\nМарценюк Сергій Анатолійович\nс. Братське\nМиколаївська область\n.15\nс. Братське\nМиколаївська область\n805\nм. Конотоп\nСумська область\n0.1083\nм. Конотоп\nСумська область\n590\nс. Братське\nМиколаївська область\n96\nСумська область\nм. Конотоп\n38.3\nм. Конотоп\nСумська область\n69.1\n2014","general":{"inn":"","name":"Сергій","last_name_hidden":false,"family":[{"inn":"","inn_hidden":true,"relations_hidden":false,"family_name":"Марценюк І. Є","relations_other":"","relations":"Подружжя","name_hidden":false,"name_unclear":false},{"inn":"","inn_hidden":false,"relations_unclear":false,"relations_hidden":false,"relations_other":"","relations":"Дитина","name_hidden":false,"family_name":"Марценюк Р. С","name_unclear":false}],"patronymic":"Анатолійович","inn_hidden":true,"family_raw":"","inn_unclear":false,"post":{"post_unclear":false,"post":"суддя, голова братського районного суду миколаївської області","candidate":"","office_hidden":false,"region":"Миколаївська область","office":"Загальний місцевий суд","office_unclear":false},"full_name_suggest":{"output":"Марценюк Сергій Анатолійович","input":["Марценюк Сергій Анатолійович","Сергій Анатолійович Марценюк","Сергій Марценюк"]},"full_name":"Марценюк Сергій Анатолійович","addresses":[{"place_city_type_unclear":true,"place_address":"55401","place_district_hidden":false,"place_city_type":"СМТ","place_address_hidden":true,"place_address_unclear":false,"place_city_type_hidden":false,"place":"Миколаївська область","place_district":"Братський","place_unclear":false,"place_city":"Братське","place_city_unclear":false,"place_hidden":false,"place_city_hidden":false,"place_district_unclear":false}],"last_name":"Марценюк","last_name_unclear":false},"source":"VULYK","estate":{"23":[{"space_unclear":false,"costs":"","costs_comment":"","costs_hidden":false,"address_hidden":true,"region_hidden":false,"space_comment":"","space_hidden":false,"space":".15","space_units_hidden":false,"region":"Миколаївська область","address_unclear":false,"space_units_unclear":false,"space_units":"га","address":"с. Братське","costs_rent":"","costs_rent_comment":""},{"costs_rent":"","region":"Миколаївська область","costs":"","costs_rent_comment":"","costs_comment":"","address_hidden":false,"space_comment":"","space_units":"м²","space":"805","address":"с. Братське"},{"costs_rent":"","region":"Сумська область","costs":"","costs_rent_comment":"","costs_comment":"","address_hidden":false,"space_comment":"","space_units":"м²","space":"0.1083","address":"м. Конотоп"},{"costs_rent":"","region":"Сумська область","costs":"","costs_rent_comment":"","costs_comment":"","space_comment":"","space_units":"м²","space":"590","address":"м. Конотоп"}],"24":[{"space_unclear":false,"costs":"","costs_comment":"","costs_hidden":false,"address_hidden":true,"region_hidden":false,"space_comment":"","space_hidden":false,"space":"96","address":"с. Братське","region":"Миколаївська область","address_unclear":false,"costs_rent_comment":"","costs_rent_hidden":false,"space_comment_unclear":false,"space_units":"м²","costs_rent":""},{"costs_rent":"","region":"Сумська область","costs":"","costs_rent_comment":"","costs_comment":"","region_hidden":false,"space_comment":"","space_units":"м²","space":"38.3","address":"м. Конотоп"},{"costs_rent":"","region":"Сумська область","costs":"","costs_rent_comment":"","costs_comment":"","space_comment":"","space_units":"м²","space":"69.1","address":"м. Конотоп"}]},"intro":{"declaration_year":"2014","isnotdeclaration":"","declaration_year_unclear":false}}],"declarationsLength":1,"analytics":[{"y":2014,"i":248550,"h":203.4,"ha":3,"l":2895.11,"la":4,"fi":72200},{"y":2015,"i":254537,"h":107,"ha":2,"l":2420,"la":3}]}