{"2010":"","2016":"","Department":"Жовтневий районний суд м. Дніпропетровська","Region":"Дніпропетровська область","Position":"Суддя Жовтневого районного суду м. Дніпропетровська","Name":"Наумова Ольга Сергіївна","Link":"https://drive.google.com/open?id=0BygiyWAl79DMSkJyNlNfVGtxT3M","Note":"У меня","AdditionalNote":"","field8":"","field9":"","Link 2015":"","Кількість справ":"","Оскаржені":"","Кількість скарг":4,"Кількість дисциплінарних стягнень":"","Клейма":"","Фото":"","Як живе":"","key":"naumova_olga_sergiyivna","allDeclarations":[{"provider":"declarations.com.ua","document":{"income":{"5":{"value":"129622","family_comment":"","value_unclear":false,"family_unclear":false,"family":"127140","comment":""},"6":{"family_comment":"","family_unclear":false,"value":"102626","family":"126718","comment":""},"7":{"source_name_unclear":false,"value":"","family_comment":"","source_name":"","family":"","comment":""},"8":{"family_comment":"","value":"","family":"","comment":""},"9":{"value":"","family_comment":"","comment_hidden":false,"family_unclear":false,"family":"","comment":"","family_comment_hidden":false},"10":{"family_comment":"","value":"26996","family":"300","comment":""},"11":{"family_comment":"","value":"","family":"122","comment":""},"12":{"family_comment":"","value":"","family":"","comment":""},"13":{"family_comment":"","value":"","family":"","comment":""},"14":{"family_comment":"","value":"","family":"","comment":""},"15":{"family_comment":"","value":"","family":"","comment":""},"16":{"family_comment":"","value":"","family":"","comment":""},"17":{"family_comment":"","value":"","family":"","comment":""},"18":{"family_comment":"","value":"","family":"","comment":""},"19":{"family_comment":"","value":"","family":"","comment":""},"20":{"value":"","value_unclear":false,"comment_hidden":false,"family_comment":"","comment_unclear":false,"comment":"","family":""}},"id":"vulyk_108_154","declaration":{"additional_info_text":"","notfull_lostpages":"","date":"2016-03-25T00:00:00","notfull":"","additional_info":"","url":"http://static.declarations.com.ua/declarations/chosen_ones/judges_batch/2453_naumova_olha_serhiivna_2015.pdf"},"liabilities":{"54":{"sum_foreign_comment":"","sum":"","sum_hidden":false,"sum_comment":"","sum_foreign":""},"55":{"sum_foreign_comment":"","sum":"","sum_comment":"","sum_foreign":""},"56":{"sum_foreign_comment":"","sum":"","sum_comment":"","sum_unclear":false,"sum_foreign":""},"57":{"sum_foreign_comment":"","sum":"","sum_comment":"","sum_hidden":false,"sum_comment_hidden":false,"sum_foreign":""},"58":{"sum_foreign_comment":"","sum_comment_hidden":false,"sum":"","sum_comment":"","sum_foreign":""},"59":{"sum_foreign_comment":"","sum":"","sum_comment":"","sum_unclear":false,"sum_foreign":""},"60":{"sum_foreign_comment":"","sum_comment_hidden":false,"sum":"","sum_comment":"","sum_foreign":""},"61":{"sum_foreign_comment":"","sum_comment_hidden":false,"sum":"","sum_comment":"","sum_foreign":""},"62":{"sum_foreign_comment":"","sum":"","sum_comment":"","sum_foreign":""},"63":{"sum_foreign_comment":"","sum":"","sum_comment":"","sum_hidden":false,"sum_comment_hidden":false,"sum_unclear":false,"sum_foreign":""},"64":{"sum_foreign_comment":"","sum":"","sum_comment":"","sum_comment_hidden":false,"sum_unclear":false,"sum_foreign":""}},"ft_src":"Дніпропетровськ\nДніпропетровська область\nсуддя жовтневого районного суду м. дніпропетровська\nДніпропетровська область\nЗагальний місцевий суд\nОльга\nЧернов А. О\nПодружжя\nЧернова С. А\nДитина\nСергіївна\nНаумова Ольга Сергіївна\nОльга Сергіївна Наумова\nОльга Наумова\nНаумова Ольга Сергіївна\nНаумова Ольга Сергіївна\nНаумова\n122\n300\n26996\n129622\n127140\n126718\n102626\nДніпропетровська область\nм. Дніпропетровськ\n16\nм. Добропілля\n45000\n64.8\nДонецька область\n2015\n126718\n102626\n122\n300\n26996\n127140\n129622\n16\nДніпропетровська область\nм. Дніпропетровськ\n45000\n64.8\nм. Добропілля\nДонецька область\nНаумова Ольга Сергіївна\nОльга Сергіївна Наумова\nОльга Наумова\nНаумова Ольга Сергіївна\nОльга\nПодружжя\nЧернов А. О\nДитина\nЧернова С. А\nНаумова Ольга Сергіївна\nСергіївна\nЗагальний місцевий суд\nДніпропетровська область\nсуддя жовтневого районного суду м. дніпропетровська\nНаумова\nДніпропетровськ\nДніпропетровська область\n102626\n126718\n129622\n127140\n26996\n300\n122\n2015\nПодружжя\nЧернов А. О\nДитина\nЧернова С. А\nСергіївна\nНаумова\nОльга\nНаумова Ольга Сергіївна\nОльга Сергіївна Наумова\nОльга Наумова\nНаумова Ольга Сергіївна\nДніпропетровська область\nДніпропетровськ\nДніпропетровська область\nсуддя жовтневого районного суду м. дніпропетровська\nЗагальний місцевий суд\nНаумова Ольга Сергіївна\n45000\nм. Добропілля\nДонецька область\n64.8\nм. Дніпропетровськ\nДніпропетровська область\n16\n2015","general":{"inn":"","name":"Ольга","inn_unclear":false,"family":[{"inn":"","relations":"Подружжя","inn_unclear":false,"relations_hidden":false,"inn_hidden":true,"relations_other":"","name_hidden":true,"family_name":"Чернов А. О","name_unclear":false},{"inn":"","relations":"Дитина","relations_other":"","inn_hidden":false,"family_name":"Чернова С. А","name_hidden":false,"name_unclear":false}],"inn_hidden":true,"family_raw":"","last_name":"Наумова","post":{"post_unclear":false,"post":"суддя жовтневого районного суду м. дніпропетровська","office_hidden":false,"region":"Дніпропетровська область","office":"Загальний місцевий суд","office_unclear":false},"full_name":"Наумова Ольга Сергіївна","addresses":[{"place_city_type_hidden":false,"place_district_hidden":false,"place_city_type":"Місто","place_city_hidden":false,"place_address_unclear":false,"place_address":"","place_hidden":false,"place":"Дніпропетровська область","place_district":"","place_unclear":false,"place_city":"Дніпропетровськ","place_address_hidden":true}],"patronymic":"Сергіївна","full_name_suggest":{"output":"Наумова Ольга Сергіївна","input":["Наумова Ольга Сергіївна","Ольга Сергіївна Наумова","Ольга Наумова"]}},"source":"VULYK","estate":{"25":[{"space_unclear":false,"costs":"45000","costs_comment":"","address_hidden":true,"region_hidden":false,"space_comment":"","space":"64.8","address":"м. Добропілля","region":"Донецька область","costs_rent_comment":"","space_comment_unclear":false,"space_units":"м²","space_units_unclear":false,"costs_rent":""}],"34":[{"costs_rent":"","region":"Дніпропетровська область","costs_property":"","costs_rent_comment":"","address_hidden":true,"region_hidden":false,"space_comment":"","costs_property_comment":"","space_units":"м²","space":"16","address":"м. Дніпропетровськ"}]},"intro":{"declaration_year":"2015","isnotdeclaration":"","declaration_year_hidden":false}}},{"provider":"declarations.com.ua","document":{"income":{"5":{"family_comment":"","value":"130476","family":"96156","comment":""},"6":{"family_comment":"","value":"118296","family_hidden":false,"comment":"","family":"96156"},"7":{"family_comment":"","value":"","source_name":"","family":"","comment":""},"8":{"family_comment":"","value":"","family":"","comment":""},"9":{"value":"","value_unclear":false,"family_hidden":false,"family_comment":"","family":"","comment":""},"10":{"value":"12180","family_comment":"","family_hidden":false,"value_hidden":false,"family_unclear":false,"family":"","comment":""},"11":{"family_comment":"","value":"","family":"","comment":""},"12":{"family_comment":"","value":"","family":"","comment":""},"13":{"family_comment":"","value":"","family":"","comment":""},"14":{"family_comment":"","value":"","family":"","comment":""},"15":{"family_comment":"","value":"","family":"","comment":""},"16":{"family_comment":"","value":"","family":"","comment":""},"17":{"family_comment":"","value":"","family":"","comment":""},"18":{"family_comment":"","value":"","family":"","comment":""},"19":{"family_comment":"","value":"","family":"","comment":""},"20":{"value":"","comment_unclear":false,"family_comment":"","family":"","comment":"","family_comment_unclear":false}},"id":"vulyk_75_2","declaration":{"additional_info_text":"","notfull_lostpages":"","date":"2015-03-30T00:00:00","notfull":"","additional_info":"","url":"http://static.declarations.com.ua/declarations/chosen_ones/judges_batch/1933_naumova_olha_serhiivna.pdf"},"liabilities":{"54":{"sum_foreign_comment":"","sum":"","sum_comment":"","sum_foreign":""},"55":{"sum_foreign_comment":"","sum":"","sum_comment":"","sum_foreign":""},"56":{"sum_foreign_comment":"","sum":"","sum_comment":"","sum_foreign":""},"57":{"sum_foreign_comment":"","sum":"","sum_comment":"","sum_foreign":""},"58":{"sum_foreign_comment":"","sum":"","sum_comment":"","sum_foreign":""},"59":{"sum_foreign_comment":"","sum":"","sum_comment":"","sum_comment_unclear":false,"sum_unclear":false,"sum_foreign":""},"60":{"sum_foreign_comment":"","sum":"","sum_comment":"","sum_foreign":""},"61":{"sum_foreign_comment":"","sum":"","sum_comment":"","sum_foreign":""},"62":{"sum_foreign_comment":"","sum":"","sum_comment":"","sum_unclear":false,"sum_foreign":""},"63":{"sum_foreign_comment":"","sum":"","sum_comment":"","sum_foreign":""},"64":{"sum_foreign_comment":"","sum":"","sum_comment":"","sum_foreign":""}},"ft_src":"Дніпропетровськ\nДніпропетровська область\nНаумова Ольга Сергіївна\nсуддя жовтневого районного суду м. дніпропетровська\nДніпропетровська область\nЗагальний місцевий суд\nОльга\nЧернов А. О\nПодружжя\nНаумова Ольга Сергіївна\nОльга Сергіївна Наумова\nОльга Наумова\nНаумова Ольга Сергіївна\nНаумова\nСергіївна\n12180\n96156\n130476\n96156\n118296\nДніпропетровська область\n49005\n16\nДонецька область\n85000, Донецкая обл.\n64.8\n45000\nДонецька область\n7450\n83003 м. Донецьк\n67.2\n2014\n96156\n118296\n12180\n96156\n130476\n2014\nНаумова\nСергіївна\nДніпропетровська область\nДніпропетровськ\nПодружжя\nЧернов А. О\nНаумова Ольга Сергіївна\nОльга Сергіївна Наумова\nОльга Наумова\nНаумова Ольга Сергіївна\nОльга\nНаумова Ольга Сергіївна\nЗагальний місцевий суд\nсуддя жовтневого районного суду м. дніпропетровська\nДніпропетровська область\n118296\n96156\n130476\n96156\n12180\n16\n49005\nДніпропетровська область\n45000\n64.8\nДонецька область\n85000, Донецкая обл.\n7450\n67.2\nДонецька область\n83003 м. Донецьк\nЧернов А. О\nПодружжя\nНаумова\nСергіївна\nДніпропетровська область\nДніпропетровськ\nсуддя жовтневого районного суду м. дніпропетровська\nДніпропетровська область\nЗагальний місцевий суд\nНаумова Ольга Сергіївна\nНаумова Ольга Сергіївна\nОльга Сергіївна Наумова\nОльга Наумова\nНаумова Ольга Сергіївна\nОльга\n45000\n85000, Донецкая обл.\nДонецька область\n64.8\n83003 м. Донецьк\nДонецька область\n67.2\n7450\n49005\nДніпропетровська область\n16\n2014","general":{"inn":"","inn_hidden":true,"last_name":"Наумова","post":{"office":"Загальний місцевий суд","region":"Дніпропетровська область","post":"суддя жовтневого районного суду м. дніпропетровська"},"name":"Ольга","full_name":"Наумова Ольга Сергіївна","family_raw":"","addresses":[{"place_district":"","place_address_hidden":true,"place_city":"Дніпропетровськ","place_city_type_hidden":false,"place_district_hidden":false,"place_city_type":"Місто","place_city_hidden":false,"place_address":"","place_hidden":false,"place":"Дніпропетровська область"}],"family":[{"inn":"","inn_hidden":true,"relations_hidden":false,"family_name":"Чернов А. О","relations_other":"","relations":"Подружжя","name_hidden":false,"name_unclear":true}],"full_name_suggest":{"output":"Наумова Ольга Сергіївна","input":["Наумова Ольга Сергіївна","Ольга Сергіївна Наумова","Ольга Наумова"]},"patronymic":"Сергіївна"},"source":"VULYK","estate":{"25":[{"space_hidden":false,"costs":"45000","costs_comment":"","address_hidden":true,"region_hidden":false,"space_comment":"","space_unclear":false,"space":"64.8","address":"85000, Донецкая обл.","region":"Донецька область","costs_rent_comment":"","space_units":"м²","costs_rent":""},{"costs_rent":"7450","space_unclear":false,"region":"Донецька область","costs":"","costs_rent_comment":"","costs_comment":"","region_hidden":false,"space_comment":"","space_units":"м²","space":"67.2","address":"83003 м. Донецьк"}],"34":[{"costs_rent":"","region":"Дніпропетровська область","costs_property":"","costs_rent_comment":"","address_hidden":true,"region_hidden":false,"space_comment":"","costs_property_comment":"","space_units":"м²","space":"16","address":"49005"}]},"intro":{"declaration_year":"2014","isnotdeclaration":""}}},{"provider":"public-api.nazk.gov.ua","document":{"step_0":{"declarationType":"1","declarationYear1":"2015"},"step_1":{"city":"[Конфіденційна інформація]","region":"[Конфіденційна інформація]","street":"[Конфіденційна інформація]","country":"1","cityPath":"[Конфіденційна інформація]","cityType":"[Конфіденційна інформація]","district":"[Конфіденційна інформація]","lastname":"Наумова","postCode":"[Конфіденційна інформація]","postType":"Посада державної служби","workPost":"суддя ","firstname":"Ольга","workPlace":"Жовтневий суд м. Дніпропетровська","middlename":"Сергіївна","streetType":"[Конфіденційна інформація]","changedName":false,"countryPath":"","eng_postCode":"","postCategory":"В","actual_street":"[Конфіденційна інформація]","actual_cityPath":"[Конфіденційна інформація]","actual_cityType":"[Конфіденційна інформація]","actual_postCode":"[Конфіденційна інформація]","actual_streetType":"[Конфіденційна інформація]","previous_lastname":"","corruptionAffected":"Так","eng_actualPostCode":"[Конфіденційна інформація]","previous_firstname":"","previous_middlename":"","responsiblePosition":"Суддя суду загальної юрисдикції, суддя Конституційного Суду України","sameRegLivingAddress":"[Конфіденційна інформація]","eng_sameRegLivingAddress":"[Конфіденційна інформація]"},"step_2":{"1477231968905":{"lastname":"Чернова","firstname":"Софія","middlename":"Антонівна","changedName":false,"citizenship":"1","eng_lastname":"","no_taxNumber":true,"eng_firstname":"","eng_middlename":"","isNotApplicable":"","subjectRelation":"дочка","previous_lastname":"","previous_firstname":"","previous_middlename":"","previous_eng_lastname":"","previous_eng_firstname":"","previous_eng_middlename":""},"1477232011944":{"lastname":"Чернов","firstname":"Антон","middlename":"Олександрович","changedName":false,"citizenship":"1","eng_lastname":"","no_taxNumber":false,"eng_firstname":"","eng_middlename":"","isNotApplicable":"","subjectRelation":"чоловік","previous_lastname":"","previous_firstname":"","previous_middlename":"","previous_eng_lastname":"","previous_eng_firstname":"","previous_eng_middlename":""}},"step_3":{"1477232089774":{"city":"[Конфіденційна інформація]","person":"1","region":"[Конфіденційна інформація]","rights":{"1":{"citizen":"","ua_city":"","ua_street":"[Конфіденційна інформація]","ua_lastname":"","ua_postCode":"","eng_fullname":"","eng_lastname":"","eng_postCode":"","rightBelongs":"1","ua_firstname":"","ukr_fullname":"","ukr_lastname":"","eng_firstname":"","ownershipType":"Власність","ua_middlename":"","ua_streetType":"[Конфіденційна інформація]","ukr_firstname":"","eng_middlename":"","otherOwnership":"","ukr_middlename":"","rights_cityPath":"","ua_company_name":"","eng_company_name":"","ukr_company_name":"","percent-ownership":"100","ua_street_extendedstatus":"","ua_houseNum_extendedstatus":"","ua_postCode_extendedstatus":"","eng_postCode_extendedstatus":"","ua_middlename_extendedstatus":"","eng_middlename_extendedstatus":"","ukr_middlename_extendedstatus":"","ua_housePartNum_extendedstatus":"","ua_apartmentsNum_extendedstatus":""}},"country":"1","cityPath":"[Конфіденційна інформація]","costDate":"45000","district":"[Конфіденційна інформація]","postCode":"[Конфіденційна інформація]","totalArea":"64,80","ua_street":"[Конфіденційна інформація]","objectType":"Квартира","owningDate":"16.03.2007","ua_cityType":"Білицьке / Добропілля / Донецька Область / Україна","ua_postCode":"85000","ua_streetType":"[Конфіденційна інформація]","costAssessment":"45000","otherObjectType":""},"1477232236640":{"city":"[Конфіденційна інформація]","person":"1477232011944","region":"[Конфіденційна інформація]","rights":{"1477232426529":{"citizen":"Юридична особа, зареєстрована в Україні","ua_city":"","ua_street":"[Конфіденційна інформація]","ua_lastname":"","ua_postCode":"","eng_fullname":"","eng_lastname":"","eng_postCode":"","rightBelongs":"j","ua_firstname":"","ukr_fullname":"","ukr_lastname":"","eng_firstname":"","ownershipType":"Інше право користування","ua_middlename":"","ua_streetType":"[Конфіденційна інформація]","ukr_firstname":"","eng_middlename":"","otherOwnership":"Проживання в гуртожитку","ukr_middlename":"","rights_cityPath":"","ua_company_name":"ДЕРЖАВНИЙ ВИЩИЙ НАВЧАЛЬНИЙ ЗАКЛАД \"ПРИДНІПРОВСЬКА ДЕРЖАВНА АКАДЕМІЯ БУДІВНИЦТВА ТА АРХІТЕКТУРИ\"","eng_company_name":"","ukr_company_name":"","percent-ownership":"0","ua_street_extendedstatus":"","ua_houseNum_extendedstatus":"","ua_postCode_extendedstatus":"","eng_postCode_extendedstatus":"","ua_middlename_extendedstatus":"","eng_middlename_extendedstatus":"","ukr_middlename_extendedstatus":"","ua_housePartNum_extendedstatus":"","ua_apartmentsNum_extendedstatus":""}},"country":"1","cityPath":"[Конфіденційна інформація]","costDate":"250","district":"[Конфіденційна інформація]","postCode":"[Конфіденційна інформація]","totalArea":"16","ua_street":"[Конфіденційна інформація]","objectType":"Кімната","owningDate":"15.12.2014","ua_cityType":"Авіаторське / Дніпро / Дніпропетровська Область / Україна","ua_postCode":"49044","ua_streetType":"[Конфіденційна інформація]","costAssessment":"250","otherObjectType":""}},"step_4":[],"step_5":[],"step_6":{"1477232475961":{"brand":"Ford","model":"Kuga","person":"1477232011944","rights":{"1477233132585":{"citizen":"Громадянин України","ua_city":"","ua_street":"[Конфіденційна інформація]","ua_lastname":"Чернов","ua_postCode":"","eng_fullname":"","eng_lastname":"","eng_postCode":"","rightBelongs":"j","ua_firstname":"Олександр","ukr_fullname":"","ukr_lastname":"","eng_firstname":"","ownershipType":"Власником є третя особа","ua_middlename":"Іванович","ua_streetType":"[Конфіденційна інформація]","ukr_firstname":"","eng_middlename":"","otherOwnership":"","ukr_middlename":"","rights_cityPath":"","ua_company_name":"","eng_company_name":"","ukr_company_name":"","percent-ownership":"","ua_sameRegLivingAddress":true,"ua_street_extendedstatus":"","ua_houseNum_extendedstatus":"","ua_postCode_extendedstatus":"","eng_postCode_extendedstatus":"","ua_middlename_extendedstatus":"","eng_middlename_extendedstatus":"","ukr_middlename_extendedstatus":"","ua_housePartNum_extendedstatus":"","ua_apartmentsNum_extendedstatus":""}},"costDate":"260000","objectType":"Автомобіль легковий","owningDate":"13.04.2013","graduationYear":"2012","otherObjectType":""}},"step_7":[],"step_8":[],"step_9":[],"step_10":[],"step_11":{"1477233195056":{"person":"1","rights":{"1":{"citizen":"","ua_city":"","ua_street":"[Конфіденційна інформація]","ua_lastname":"","ua_postCode":"","eng_fullname":"","eng_lastname":"","eng_postCode":"","rightBelongs":"1","ua_firstname":"","ukr_fullname":"","ukr_lastname":"","eng_firstname":"","ownershipType":"Власність","ua_middlename":"","ua_streetType":"[Конфіденційна інформація]","ukr_firstname":"","eng_middlename":"","otherOwnership":"","ukr_middlename":"","rights_cityPath":"","ua_company_name":"","eng_company_name":"","ukr_company_name":"","percent-ownership":"","ua_street_extendedstatus":"","ua_houseNum_extendedstatus":"","ua_postCode_extendedstatus":"","eng_postCode_extendedstatus":"","ua_middlename_extendedstatus":"","eng_middlename_extendedstatus":"","ukr_middlename_extendedstatus":"","ua_housePartNum_extendedstatus":"","ua_apartmentsNum_extendedstatus":""}},"objectType":"Заробітна плата отримана за основним місцем роботи","sizeIncome":"102626","incomeSource":"1","source_citizen":"","otherObjectType":"","source_ua_lastname":"","source_eng_fullname":"","source_ua_firstname":"","source_ukr_fullname":"","source_ua_middlename":"","source_ua_company_name":"","source_eng_company_name":"","source_ukr_company_name":"","source_ua_sameRegLivingAddress":""},"1477233309618":{"person":"1","rights":{"1":{"citizen":"","ua_city":"","ua_street":"[Конфіденційна інформація]","ua_lastname":"","ua_postCode":"","eng_fullname":"","eng_lastname":"","eng_postCode":"","rightBelongs":"1","ua_firstname":"","ukr_fullname":"","ukr_lastname":"","eng_firstname":"","ownershipType":"Власність","ua_middlename":"","ua_streetType":"[Конфіденційна інформація]","ukr_firstname":"","eng_middlename":"","otherOwnership":"","ukr_middlename":"","rights_cityPath":"","ua_company_name":"","eng_company_name":"","ukr_company_name":"","percent-ownership":"","ua_street_extendedstatus":"","ua_houseNum_extendedstatus":"","ua_postCode_extendedstatus":"","eng_postCode_extendedstatus":"","ua_middlename_extendedstatus":"","eng_middlename_extendedstatus":"","ukr_middlename_extendedstatus":"","ua_housePartNum_extendedstatus":"","ua_apartmentsNum_extendedstatus":""}},"objectType":"Інше","sizeIncome":"26996","incomeSource":"1","source_citizen":"","otherObjectType":"Матеріальна допомога","source_ua_lastname":"","source_eng_fullname":"","source_ua_firstname":"","source_ukr_fullname":"","source_ua_middlename":"","source_ua_company_name":"","source_eng_company_name":"","source_ukr_company_name":"","source_ua_sameRegLivingAddress":""},"1477233404975":{"person":"1477232011944","rights":{"1477232011944":{"citizen":"","ua_city":"","ua_street":"[Конфіденційна інформація]","ua_lastname":"","ua_postCode":"","eng_fullname":"","eng_lastname":"","eng_postCode":"","rightBelongs":"1477232011944","ua_firstname":"","ukr_fullname":"","ukr_lastname":"","eng_firstname":"","ownershipType":"Власність","ua_middlename":"","ua_streetType":"[Конфіденційна інформація]","ukr_firstname":"","eng_middlename":"","otherOwnership":"","ukr_middlename":"","rights_cityPath":"","ua_company_name":"","eng_company_name":"","ukr_company_name":"","percent-ownership":"","ua_street_extendedstatus":"","ua_houseNum_extendedstatus":"","ua_postCode_extendedstatus":"","eng_postCode_extendedstatus":"","ua_middlename_extendedstatus":"","eng_middlename_extendedstatus":"","ukr_middlename_extendedstatus":"","ua_housePartNum_extendedstatus":"","ua_apartmentsNum_extendedstatus":""}},"objectType":"Заробітна плата отримана за основним місцем роботи","sizeIncome":"126718","incomeSource":"1477232011944","source_citizen":"","otherObjectType":"","source_ua_lastname":"","source_eng_fullname":"","source_ua_firstname":"","source_ukr_fullname":"","source_ua_middlename":"","source_ua_company_name":"","source_eng_company_name":"","source_ukr_company_name":"","source_ua_sameRegLivingAddress":""},"1477233465640":{"person":"1477232011944","rights":{"1477232011944":{"citizen":"","ua_city":"","ua_street":"[Конфіденційна інформація]","ua_lastname":"","ua_postCode":"","eng_fullname":"","eng_lastname":"","eng_postCode":"","rightBelongs":"1477232011944","ua_firstname":"","ukr_fullname":"","ukr_lastname":"","eng_firstname":"","ownershipType":"Власність","ua_middlename":"","ua_streetType":"[Конфіденційна інформація]","ukr_firstname":"","eng_middlename":"","otherOwnership":"","ukr_middlename":"","rights_cityPath":"","ua_company_name":"","eng_company_name":"","ukr_company_name":"","percent-ownership":"","ua_street_extendedstatus":"","ua_houseNum_extendedstatus":"","ua_postCode_extendedstatus":"","eng_postCode_extendedstatus":"","ua_middlename_extendedstatus":"","eng_middlename_extendedstatus":"","ukr_middlename_extendedstatus":"","ua_housePartNum_extendedstatus":"","ua_apartmentsNum_extendedstatus":""}},"objectType":"Інше","sizeIncome":"300","incomeSource":"1477232011944","source_citizen":"","otherObjectType":"матеріальна допомога","source_ua_lastname":"","source_eng_fullname":"","source_ua_firstname":"","source_ukr_fullname":"","source_ua_middlename":"","source_ua_company_name":"","source_eng_company_name":"","source_ukr_company_name":"","source_ua_sameRegLivingAddress":""}},"step_12":[],"step_13":[],"step_14":[],"step_15":[],"step_16":[],"id":"ae8ea889-f806-40c7-bff8-a323ade43ad1"}}],"declarations":[{"income":{"5":{"value":"129622","family_comment":"","value_unclear":false,"family_unclear":false,"family":"127140","comment":""},"6":{"family_comment":"","family_unclear":false,"value":"102626","family":"126718","comment":""},"7":{"source_name_unclear":false,"value":"","family_comment":"","source_name":"","family":"","comment":""},"8":{"family_comment":"","value":"","family":"","comment":""},"9":{"value":"","family_comment":"","comment_hidden":false,"family_unclear":false,"family":"","comment":"","family_comment_hidden":false},"10":{"family_comment":"","value":"26996","family":"300","comment":""},"11":{"family_comment":"","value":"","family":"122","comment":""},"12":{"family_comment":"","value":"","family":"","comment":""},"13":{"family_comment":"","value":"","family":"","comment":""},"14":{"family_comment":"","value":"","family":"","comment":""},"15":{"family_comment":"","value":"","family":"","comment":""},"16":{"family_comment":"","value":"","family":"","comment":""},"17":{"family_comment":"","value":"","family":"","comment":""},"18":{"family_comment":"","value":"","family":"","comment":""},"19":{"family_comment":"","value":"","family":"","comment":""},"20":{"value":"","value_unclear":false,"comment_hidden":false,"family_comment":"","comment_unclear":false,"comment":"","family":""}},"id":"vulyk_108_154","declaration":{"additional_info_text":"","notfull_lostpages":"","date":"2016-03-25T00:00:00","notfull":"","additional_info":"","url":"http://static.declarations.com.ua/declarations/chosen_ones/judges_batch/2453_naumova_olha_serhiivna_2015.pdf"},"liabilities":{"54":{"sum_foreign_comment":"","sum":"","sum_hidden":false,"sum_comment":"","sum_foreign":""},"55":{"sum_foreign_comment":"","sum":"","sum_comment":"","sum_foreign":""},"56":{"sum_foreign_comment":"","sum":"","sum_comment":"","sum_unclear":false,"sum_foreign":""},"57":{"sum_foreign_comment":"","sum":"","sum_comment":"","sum_hidden":false,"sum_comment_hidden":false,"sum_foreign":""},"58":{"sum_foreign_comment":"","sum_comment_hidden":false,"sum":"","sum_comment":"","sum_foreign":""},"59":{"sum_foreign_comment":"","sum":"","sum_comment":"","sum_unclear":false,"sum_foreign":""},"60":{"sum_foreign_comment":"","sum_comment_hidden":false,"sum":"","sum_comment":"","sum_foreign":""},"61":{"sum_foreign_comment":"","sum_comment_hidden":false,"sum":"","sum_comment":"","sum_foreign":""},"62":{"sum_foreign_comment":"","sum":"","sum_comment":"","sum_foreign":""},"63":{"sum_foreign_comment":"","sum":"","sum_comment":"","sum_hidden":false,"sum_comment_hidden":false,"sum_unclear":false,"sum_foreign":""},"64":{"sum_foreign_comment":"","sum":"","sum_comment":"","sum_comment_hidden":false,"sum_unclear":false,"sum_foreign":""}},"ft_src":"Дніпропетровськ\nДніпропетровська область\nсуддя жовтневого районного суду м. дніпропетровська\nДніпропетровська область\nЗагальний місцевий суд\nОльга\nЧернов А. О\nПодружжя\nЧернова С. А\nДитина\nСергіївна\nНаумова Ольга Сергіївна\nОльга Сергіївна Наумова\nОльга Наумова\nНаумова Ольга Сергіївна\nНаумова Ольга Сергіївна\nНаумова\n122\n300\n26996\n129622\n127140\n126718\n102626\nДніпропетровська область\nм. Дніпропетровськ\n16\nм. Добропілля\n45000\n64.8\nДонецька область\n2015\n126718\n102626\n122\n300\n26996\n127140\n129622\n16\nДніпропетровська область\nм. Дніпропетровськ\n45000\n64.8\nм. Добропілля\nДонецька область\nНаумова Ольга Сергіївна\nОльга Сергіївна Наумова\nОльга Наумова\nНаумова Ольга Сергіївна\nОльга\nПодружжя\nЧернов А. О\nДитина\nЧернова С. А\nНаумова Ольга Сергіївна\nСергіївна\nЗагальний місцевий суд\nДніпропетровська область\nсуддя жовтневого районного суду м. дніпропетровська\nНаумова\nДніпропетровськ\nДніпропетровська область\n102626\n126718\n129622\n127140\n26996\n300\n122\n2015\nПодружжя\nЧернов А. О\nДитина\nЧернова С. А\nСергіївна\nНаумова\nОльга\nНаумова Ольга Сергіївна\nОльга Сергіївна Наумова\nОльга Наумова\nНаумова Ольга Сергіївна\nДніпропетровська область\nДніпропетровськ\nДніпропетровська область\nсуддя жовтневого районного суду м. дніпропетровська\nЗагальний місцевий суд\nНаумова Ольга Сергіївна\n45000\nм. Добропілля\nДонецька область\n64.8\nм. Дніпропетровськ\nДніпропетровська область\n16\n2015","general":{"inn":"","name":"Ольга","inn_unclear":false,"family":[{"inn":"","relations":"Подружжя","inn_unclear":false,"relations_hidden":false,"inn_hidden":true,"relations_other":"","name_hidden":true,"family_name":"Чернов А. О","name_unclear":false},{"inn":"","relations":"Дитина","relations_other":"","inn_hidden":false,"family_name":"Чернова С. А","name_hidden":false,"name_unclear":false}],"inn_hidden":true,"family_raw":"","last_name":"Наумова","post":{"post_unclear":false,"post":"суддя жовтневого районного суду м. дніпропетровська","office_hidden":false,"region":"Дніпропетровська область","office":"Загальний місцевий суд","office_unclear":false},"full_name":"Наумова Ольга Сергіївна","addresses":[{"place_city_type_hidden":false,"place_district_hidden":false,"place_city_type":"Місто","place_city_hidden":false,"place_address_unclear":false,"place_address":"","place_hidden":false,"place":"Дніпропетровська область","place_district":"","place_unclear":false,"place_city":"Дніпропетровськ","place_address_hidden":true}],"patronymic":"Сергіївна","full_name_suggest":{"output":"Наумова Ольга Сергіївна","input":["Наумова Ольга Сергіївна","Ольга Сергіївна Наумова","Ольга Наумова"]}},"source":"VULYK","estate":{"25":[{"space_unclear":false,"costs":"45000","costs_comment":"","address_hidden":true,"region_hidden":false,"space_comment":"","space":"64.8","address":"м. Добропілля","region":"Донецька область","costs_rent_comment":"","space_comment_unclear":false,"space_units":"м²","space_units_unclear":false,"costs_rent":""}],"34":[{"costs_rent":"","region":"Дніпропетровська область","costs_property":"","costs_rent_comment":"","address_hidden":true,"region_hidden":false,"space_comment":"","costs_property_comment":"","space_units":"м²","space":"16","address":"м. Дніпропетровськ"}]},"intro":{"declaration_year":"2015","isnotdeclaration":"","declaration_year_hidden":false}},{"income":{"5":{"family_comment":"","value":"130476","family":"96156","comment":""},"6":{"family_comment":"","value":"118296","family_hidden":false,"comment":"","family":"96156"},"7":{"family_comment":"","value":"","source_name":"","family":"","comment":""},"8":{"family_comment":"","value":"","family":"","comment":""},"9":{"value":"","value_unclear":false,"family_hidden":false,"family_comment":"","family":"","comment":""},"10":{"value":"12180","family_comment":"","family_hidden":false,"value_hidden":false,"family_unclear":false,"family":"","comment":""},"11":{"family_comment":"","value":"","family":"","comment":""},"12":{"family_comment":"","value":"","family":"","comment":""},"13":{"family_comment":"","value":"","family":"","comment":""},"14":{"family_comment":"","value":"","family":"","comment":""},"15":{"family_comment":"","value":"","family":"","comment":""},"16":{"family_comment":"","value":"","family":"","comment":""},"17":{"family_comment":"","value":"","family":"","comment":""},"18":{"family_comment":"","value":"","family":"","comment":""},"19":{"family_comment":"","value":"","family":"","comment":""},"20":{"value":"","comment_unclear":false,"family_comment":"","family":"","comment":"","family_comment_unclear":false}},"id":"vulyk_75_2","declaration":{"additional_info_text":"","notfull_lostpages":"","date":"2015-03-30T00:00:00","notfull":"","additional_info":"","url":"http://static.declarations.com.ua/declarations/chosen_ones/judges_batch/1933_naumova_olha_serhiivna.pdf"},"liabilities":{"54":{"sum_foreign_comment":"","sum":"","sum_comment":"","sum_foreign":""},"55":{"sum_foreign_comment":"","sum":"","sum_comment":"","sum_foreign":""},"56":{"sum_foreign_comment":"","sum":"","sum_comment":"","sum_foreign":""},"57":{"sum_foreign_comment":"","sum":"","sum_comment":"","sum_foreign":""},"58":{"sum_foreign_comment":"","sum":"","sum_comment":"","sum_foreign":""},"59":{"sum_foreign_comment":"","sum":"","sum_comment":"","sum_comment_unclear":false,"sum_unclear":false,"sum_foreign":""},"60":{"sum_foreign_comment":"","sum":"","sum_comment":"","sum_foreign":""},"61":{"sum_foreign_comment":"","sum":"","sum_comment":"","sum_foreign":""},"62":{"sum_foreign_comment":"","sum":"","sum_comment":"","sum_unclear":false,"sum_foreign":""},"63":{"sum_foreign_comment":"","sum":"","sum_comment":"","sum_foreign":""},"64":{"sum_foreign_comment":"","sum":"","sum_comment":"","sum_foreign":""}},"ft_src":"Дніпропетровськ\nДніпропетровська область\nНаумова Ольга Сергіївна\nсуддя жовтневого районного суду м. дніпропетровська\nДніпропетровська область\nЗагальний місцевий суд\nОльга\nЧернов А. О\nПодружжя\nНаумова Ольга Сергіївна\nОльга Сергіївна Наумова\nОльга Наумова\nНаумова Ольга Сергіївна\nНаумова\nСергіївна\n12180\n96156\n130476\n96156\n118296\nДніпропетровська область\n49005\n16\nДонецька область\n85000, Донецкая обл.\n64.8\n45000\nДонецька область\n7450\n83003 м. Донецьк\n67.2\n2014\n96156\n118296\n12180\n96156\n130476\n2014\nНаумова\nСергіївна\nДніпропетровська область\nДніпропетровськ\nПодружжя\nЧернов А. О\nНаумова Ольга Сергіївна\nОльга Сергіївна Наумова\nОльга Наумова\nНаумова Ольга Сергіївна\nОльга\nНаумова Ольга Сергіївна\nЗагальний місцевий суд\nсуддя жовтневого районного суду м. дніпропетровська\nДніпропетровська область\n118296\n96156\n130476\n96156\n12180\n16\n49005\nДніпропетровська область\n45000\n64.8\nДонецька область\n85000, Донецкая обл.\n7450\n67.2\nДонецька область\n83003 м. Донецьк\nЧернов А. О\nПодружжя\nНаумова\nСергіївна\nДніпропетровська область\nДніпропетровськ\nсуддя жовтневого районного суду м. дніпропетровська\nДніпропетровська область\nЗагальний місцевий суд\nНаумова Ольга Сергіївна\nНаумова Ольга Сергіївна\nОльга Сергіївна Наумова\nОльга Наумова\nНаумова Ольга Сергіївна\nОльга\n45000\n85000, Донецкая обл.\nДонецька область\n64.8\n83003 м. Донецьк\nДонецька область\n67.2\n7450\n49005\nДніпропетровська область\n16\n2014","general":{"inn":"","inn_hidden":true,"last_name":"Наумова","post":{"office":"Загальний місцевий суд","region":"Дніпропетровська область","post":"суддя жовтневого районного суду м. дніпропетровська"},"name":"Ольга","full_name":"Наумова Ольга Сергіївна","family_raw":"","addresses":[{"place_district":"","place_address_hidden":true,"place_city":"Дніпропетровськ","place_city_type_hidden":false,"place_district_hidden":false,"place_city_type":"Місто","place_city_hidden":false,"place_address":"","place_hidden":false,"place":"Дніпропетровська область"}],"family":[{"inn":"","inn_hidden":true,"relations_hidden":false,"family_name":"Чернов А. О","relations_other":"","relations":"Подружжя","name_hidden":false,"name_unclear":true}],"full_name_suggest":{"output":"Наумова Ольга Сергіївна","input":["Наумова Ольга Сергіївна","Ольга Сергіївна Наумова","Ольга Наумова"]},"patronymic":"Сергіївна"},"source":"VULYK","estate":{"25":[{"space_hidden":false,"costs":"45000","costs_comment":"","address_hidden":true,"region_hidden":false,"space_comment":"","space_unclear":false,"space":"64.8","address":"85000, Донецкая обл.","region":"Донецька область","costs_rent_comment":"","space_units":"м²","costs_rent":""},{"costs_rent":"7450","space_unclear":false,"region":"Донецька область","costs":"","costs_rent_comment":"","costs_comment":"","region_hidden":false,"space_comment":"","space_units":"м²","space":"67.2","address":"83003 м. Донецьк"}],"34":[{"costs_rent":"","region":"Дніпропетровська область","costs_property":"","costs_rent_comment":"","address_hidden":true,"region_hidden":false,"space_comment":"","costs_property_comment":"","space_units":"м²","space":"16","address":"49005"}]},"intro":{"declaration_year":"2014","isnotdeclaration":""}}],"declarationsLength":2,"analytics":[{"y":2015,"i":129622,"k":64.8,"ka":1,"fi":127140,"j":4},{"y":2014,"i":130476,"k":132,"ka":2,"fi":96156}]}