{"2010":1,"2016":"","Department":"Сокальський районний суд Львівської області","Region":"Львівська область","Position":"Суддя Сокальського районного суду Львівської області","Name":"Пахут Сергій Олександрович","Link":"https://drive.google.com/open?id=0BygiyWAl79DMbzQ2VlNRZGlxbTg","Note":"У меня","AdditionalNote":"","field8":"","field9":"","field10":"","Кількість справ":"","Оскаржені":"","Кількість скарг":5,"Кількість дисциплінарних стягнень":"","Клейма":3,"Фото":"","Як живе":"","key":"pahut_sergiy_oleksandrovich","allDeclarations":[{"provider":"declarations.com.ua","document":{"income":{"5":{"value":"233555.82","family_comment":"","value_unclear":false,"family_hidden":false,"value_hidden":false,"family_unclear":false,"family":"31482","comment":""},"6":{"value":"221375.82","family_comment":"","value_unclear":false,"family_unclear":false,"family":"","comment":""},"7":{"source_name_unclear":false,"value":"","comment_hidden":false,"family_comment":"","source_name":"","family":"","comment":"","source_name_hidden":false},"8":{"family_comment":"","value":"","family":"","comment":""},"9":{"value":"","family_comment":"","value_unclear":false,"family_hidden":false,"family_unclear":false,"family":"","comment":"","family_comment_unclear":false},"10":{"family_comment":"","value":"12180","family":"","comment":""},"11":{"family_comment":"","value":"","family":"","comment":""},"12":{"family_comment":"","value":"","family":"","comment":""},"13":{"family_comment":"","value":"","family":"","comment":""},"14":{"family_comment":"","value":"","family":"","comment":""},"15":{"family_comment":"","value":"13062.7","family":"","comment":""},"16":{"family_comment":"","value":"","family":"","comment":""},"17":{"family_comment":"","value":"","family":"31482","comment":""},"18":{"family_comment":"","value":"","family":"","comment":""},"19":{"family_comment":"","value":"","family":"","comment":""},"20":{"value":"","family_comment":"","value_unclear":false,"family_comment_hidden":false,"family_unclear":false,"family_comment_unclear":false,"comment_unclear":false,"comment":"","family":""}},"vehicle":{"35":[{"year_hidden":false,"brand_info":"3828 куб. см. 184 кВт","sum_rent_comment":"","year":"2007","brand_info_hidden":false,"brand_info_unclear":false,"sum_rent":"","sum":"","brand":"Mitsubishi Pajero","sum_comment":"","brand_unclear":false,"brand_hidden":false}],"40":[{"brand_info":"1598 куб. см. 77 кВт","sum_rent_comment":"","brand":"Mazda 3","sum_comment":"","year":"2007","brand_info_unclear":false,"sum":"","sum_rent":""}]},"id":"vulyk_93_62","declaration":{"additional_info_text":"","notfull_lostpages":"","date":"2015-03-30T00:00:00","notfull":"","additional_info":"","url":"http://static.declarations.com.ua/declarations/chosen_ones/judges_batch/3508_pakhut_serhii_oleksandrovych.pdf"},"liabilities":{"54":{"sum_foreign_comment":"","sum":"17671.35","sum_hidden":false,"sum_comment":"","sum_foreign":""},"55":{"sum_foreign_comment":"","sum":"","sum_comment":"","sum_foreign":""},"56":{"sum_foreign_comment":"","sum":"","sum_comment":"","sum_foreign":""},"57":{"sum_foreign_comment":"","sum":"","sum_comment":"","sum_hidden":false,"sum_comment_hidden":false,"sum_unclear":false,"sum_foreign":""},"58":{"sum_foreign_comment":"","sum":"","sum_comment":"","sum_comment_unclear":false,"sum_hidden":false,"sum_unclear":false,"sum_foreign":""},"59":{"sum_foreign_comment":"","sum":"","sum_comment":"","sum_foreign":""},"60":{"sum_foreign_comment":"","sum":"","sum_hidden":false,"sum_comment":"","sum_foreign":""},"61":{"sum_foreign_comment":"","sum":"","sum_comment":"","sum_foreign":""},"62":{"sum_foreign_comment":"","sum":"","sum_comment":"","sum_foreign":""},"63":{"sum_foreign_comment":"","sum":"","sum_comment":"","sum_foreign":""},"64":{"sum_foreign_comment":"","sum":"","sum_comment":"","sum_foreign":""}},"ft_src":"17671.35\nПахут Сергій Олександрович\nсуддя сокальського районного суду львівської області\nЛьвівська область\nЗагальний місцевий суд\nСергій\nКолодій О. Я\nПодружжя\nПахут Ю. С\nДитина\nПахут Сергій Олександрович\nСергій Олександрович Пахут\nСергій Пахут\nПахут Сергій Олександрович\nПахут\nОлександрович\n3828 куб. см. 184 кВт\nMitsubishi Pajero\n2007\n1598 куб. см. 77 кВт\n2007\nMazda 3\nчастка\n40\n40.8\n31.4\n50.4\n71.6\n2014\n221375.82\n13062.7\n12180\n31482\n233555.82\n31482\n3828 куб. см. 184 кВт\nMitsubishi Pajero\n2007\n1598 куб. см. 77 кВт\nMazda 3\n2007\n71.6\n40\nчастка\n40.8\n31.4\n50.4\nПахут\nПодружжя\nКолодій О. Я\nДитина\nПахут Ю. С\nПахут Сергій Олександрович\nСергій Олександрович Пахут\nСергій Пахут\nПахут Сергій Олександрович\nПахут Сергій Олександрович\nСергій\nОлександрович\nЛьвівська область\nЗагальний місцевий суд\nсуддя сокальського районного суду львівської області\n17671.35\n221375.82\n31482\n13062.7\n233555.82\n31482\n12180\n2014\n17671.35\nПодружжя\nКолодій О. Я\nДитина\nПахут Ю. С\nПахут\nОлександрович\nЛьвівська область\nЗагальний місцевий суд\nсуддя сокальського районного суду львівської області\nПахут Сергій Олександрович\nПахут Сергій Олександрович\nСергій Олександрович Пахут\nСергій Пахут\nПахут Сергій Олександрович\nСергій\nMitsubishi Pajero\n3828 куб. см. 184 кВт\n2007\n2007\n1598 куб. см. 77 кВт\nMazda 3\n13062.7\n12180\n233555.82\n31482\n31482\n221375.82\nчастка\n40\n40.8\n31.4\n71.6\n50.4\n2014","general":{"inn":"","inn_hidden":true,"last_name":"Пахут","post":{"post_unclear":false,"region_unclear":false,"region":"Львівська область","candidate":"","post":"суддя сокальського районного суду львівської області","office":"Загальний місцевий суд","office_unclear":false},"name":"Сергій","full_name":"Пахут Сергій Олександрович","family_raw":"","addresses":[{"place_district":"","place_city_hidden":true,"place_city":"","place_city_type_hidden":true,"place_district_hidden":true,"place_city_type":"","place_address_hidden":true,"place_address":"","place_hidden":true,"place":""}],"family":[{"inn":"","relations":"Подружжя","relations_hidden":false,"inn_hidden":true,"relations_other":"","name_hidden":false,"family_name":"Колодій О. Я","name_unclear":false},{"inn":"","relations":"Дитина","relations_other":"","inn_hidden":true,"family_name":"Пахут Ю. С","name_hidden":false,"name_unclear":false}],"full_name_suggest":{"output":"Пахут Сергій Олександрович","input":["Пахут Сергій Олександрович","Сергій Олександрович Пахут","Сергій Пахут"]},"patronymic":"Олександрович"},"source":"VULYK","estate":{"24":[{"space_unclear":false,"costs":"","costs_comment":"","address_hidden":true,"region_hidden":true,"space_comment":"","space":"71.6","address":"","region":"","costs_rent_comment":"","space_comment_unclear":false,"space_units":"м²","costs_rent":""}],"31":[{"space_hidden":false,"address_hidden":true,"region_hidden":true,"space_comment":"частка","space":"40","address":"","region":"","costs_property":"","costs_rent_comment":"","space_comment_unclear":false,"space_units":"м²","costs_property_comment":"","costs_rent":""},{"costs_rent":"","region":"","costs_property":"","costs_rent_comment":"","region_hidden":false,"space_comment":"","costs_property_comment":"","space_units":"м²","space":"40.8","address":""},{"costs_rent":"","costs_property":"","costs_rent_comment":"","region_hidden":false,"space_comment":"","costs_property_comment":"","space_units":"м²","space":"31.4","address":""}],"34":[{"costs_rent":"","costs_property":"","costs_rent_comment":"","address_hidden":true,"region_hidden":true,"space_comment":"","costs_property_comment":"","space_units":"м²","space":"50.4","address":""}]},"intro":{"declaration_year":"2014","isnotdeclaration":""}}}],"declarations":[{"income":{"5":{"value":"233555.82","family_comment":"","value_unclear":false,"family_hidden":false,"value_hidden":false,"family_unclear":false,"family":"31482","comment":""},"6":{"value":"221375.82","family_comment":"","value_unclear":false,"family_unclear":false,"family":"","comment":""},"7":{"source_name_unclear":false,"value":"","comment_hidden":false,"family_comment":"","source_name":"","family":"","comment":"","source_name_hidden":false},"8":{"family_comment":"","value":"","family":"","comment":""},"9":{"value":"","family_comment":"","value_unclear":false,"family_hidden":false,"family_unclear":false,"family":"","comment":"","family_comment_unclear":false},"10":{"family_comment":"","value":"12180","family":"","comment":""},"11":{"family_comment":"","value":"","family":"","comment":""},"12":{"family_comment":"","value":"","family":"","comment":""},"13":{"family_comment":"","value":"","family":"","comment":""},"14":{"family_comment":"","value":"","family":"","comment":""},"15":{"family_comment":"","value":"13062.7","family":"","comment":""},"16":{"family_comment":"","value":"","family":"","comment":""},"17":{"family_comment":"","value":"","family":"31482","comment":""},"18":{"family_comment":"","value":"","family":"","comment":""},"19":{"family_comment":"","value":"","family":"","comment":""},"20":{"value":"","family_comment":"","value_unclear":false,"family_comment_hidden":false,"family_unclear":false,"family_comment_unclear":false,"comment_unclear":false,"comment":"","family":""}},"vehicle":{"35":[{"year_hidden":false,"brand_info":"3828 куб. см. 184 кВт","sum_rent_comment":"","year":"2007","brand_info_hidden":false,"brand_info_unclear":false,"sum_rent":"","sum":"","brand":"Mitsubishi Pajero","sum_comment":"","brand_unclear":false,"brand_hidden":false}],"40":[{"brand_info":"1598 куб. см. 77 кВт","sum_rent_comment":"","brand":"Mazda 3","sum_comment":"","year":"2007","brand_info_unclear":false,"sum":"","sum_rent":""}]},"id":"vulyk_93_62","declaration":{"additional_info_text":"","notfull_lostpages":"","date":"2015-03-30T00:00:00","notfull":"","additional_info":"","url":"http://static.declarations.com.ua/declarations/chosen_ones/judges_batch/3508_pakhut_serhii_oleksandrovych.pdf"},"liabilities":{"54":{"sum_foreign_comment":"","sum":"17671.35","sum_hidden":false,"sum_comment":"","sum_foreign":""},"55":{"sum_foreign_comment":"","sum":"","sum_comment":"","sum_foreign":""},"56":{"sum_foreign_comment":"","sum":"","sum_comment":"","sum_foreign":""},"57":{"sum_foreign_comment":"","sum":"","sum_comment":"","sum_hidden":false,"sum_comment_hidden":false,"sum_unclear":false,"sum_foreign":""},"58":{"sum_foreign_comment":"","sum":"","sum_comment":"","sum_comment_unclear":false,"sum_hidden":false,"sum_unclear":false,"sum_foreign":""},"59":{"sum_foreign_comment":"","sum":"","sum_comment":"","sum_foreign":""},"60":{"sum_foreign_comment":"","sum":"","sum_hidden":false,"sum_comment":"","sum_foreign":""},"61":{"sum_foreign_comment":"","sum":"","sum_comment":"","sum_foreign":""},"62":{"sum_foreign_comment":"","sum":"","sum_comment":"","sum_foreign":""},"63":{"sum_foreign_comment":"","sum":"","sum_comment":"","sum_foreign":""},"64":{"sum_foreign_comment":"","sum":"","sum_comment":"","sum_foreign":""}},"ft_src":"17671.35\nПахут Сергій Олександрович\nсуддя сокальського районного суду львівської області\nЛьвівська область\nЗагальний місцевий суд\nСергій\nКолодій О. Я\nПодружжя\nПахут Ю. С\nДитина\nПахут Сергій Олександрович\nСергій Олександрович Пахут\nСергій Пахут\nПахут Сергій Олександрович\nПахут\nОлександрович\n3828 куб. см. 184 кВт\nMitsubishi Pajero\n2007\n1598 куб. см. 77 кВт\n2007\nMazda 3\nчастка\n40\n40.8\n31.4\n50.4\n71.6\n2014\n221375.82\n13062.7\n12180\n31482\n233555.82\n31482\n3828 куб. см. 184 кВт\nMitsubishi Pajero\n2007\n1598 куб. см. 77 кВт\nMazda 3\n2007\n71.6\n40\nчастка\n40.8\n31.4\n50.4\nПахут\nПодружжя\nКолодій О. Я\nДитина\nПахут Ю. С\nПахут Сергій Олександрович\nСергій Олександрович Пахут\nСергій Пахут\nПахут Сергій Олександрович\nПахут Сергій Олександрович\nСергій\nОлександрович\nЛьвівська область\nЗагальний місцевий суд\nсуддя сокальського районного суду львівської області\n17671.35\n221375.82\n31482\n13062.7\n233555.82\n31482\n12180\n2014\n17671.35\nПодружжя\nКолодій О. Я\nДитина\nПахут Ю. С\nПахут\nОлександрович\nЛьвівська область\nЗагальний місцевий суд\nсуддя сокальського районного суду львівської області\nПахут Сергій Олександрович\nПахут Сергій Олександрович\nСергій Олександрович Пахут\nСергій Пахут\nПахут Сергій Олександрович\nСергій\nMitsubishi Pajero\n3828 куб. см. 184 кВт\n2007\n2007\n1598 куб. см. 77 кВт\nMazda 3\n13062.7\n12180\n233555.82\n31482\n31482\n221375.82\nчастка\n40\n40.8\n31.4\n71.6\n50.4\n2014","general":{"inn":"","inn_hidden":true,"last_name":"Пахут","post":{"post_unclear":false,"region_unclear":false,"region":"Львівська область","candidate":"","post":"суддя сокальського районного суду львівської області","office":"Загальний місцевий суд","office_unclear":false},"name":"Сергій","full_name":"Пахут Сергій Олександрович","family_raw":"","addresses":[{"place_district":"","place_city_hidden":true,"place_city":"","place_city_type_hidden":true,"place_district_hidden":true,"place_city_type":"","place_address_hidden":true,"place_address":"","place_hidden":true,"place":""}],"family":[{"inn":"","relations":"Подружжя","relations_hidden":false,"inn_hidden":true,"relations_other":"","name_hidden":false,"family_name":"Колодій О. Я","name_unclear":false},{"inn":"","relations":"Дитина","relations_other":"","inn_hidden":true,"family_name":"Пахут Ю. С","name_hidden":false,"name_unclear":false}],"full_name_suggest":{"output":"Пахут Сергій Олександрович","input":["Пахут Сергій Олександрович","Сергій Олександрович Пахут","Сергій Пахут"]},"patronymic":"Олександрович"},"source":"VULYK","estate":{"24":[{"space_unclear":false,"costs":"","costs_comment":"","address_hidden":true,"region_hidden":true,"space_comment":"","space":"71.6","address":"","region":"","costs_rent_comment":"","space_comment_unclear":false,"space_units":"м²","costs_rent":""}],"31":[{"space_hidden":false,"address_hidden":true,"region_hidden":true,"space_comment":"частка","space":"40","address":"","region":"","costs_property":"","costs_rent_comment":"","space_comment_unclear":false,"space_units":"м²","costs_property_comment":"","costs_rent":""},{"costs_rent":"","region":"","costs_property":"","costs_rent_comment":"","region_hidden":false,"space_comment":"","costs_property_comment":"","space_units":"м²","space":"40.8","address":""},{"costs_rent":"","costs_property":"","costs_rent_comment":"","region_hidden":false,"space_comment":"","costs_property_comment":"","space_units":"м²","space":"31.4","address":""}],"34":[{"costs_rent":"","costs_property":"","costs_rent_comment":"","address_hidden":true,"region_hidden":true,"space_comment":"","costs_property_comment":"","space_units":"м²","space":"50.4","address":""}]},"intro":{"declaration_year":"2014","isnotdeclaration":""}}],"declarationsLength":1,"analytics":[{"y":2014,"i":233555.82,"c":1,"h":71.6,"ha":1,"fi":31482,"ff":112.2,"ffa":3}]}