{"2010":"","2016":"","Department":"Голосіївський районний суд міста Києва","Region":"м. Київ","Position":"Суддя Голосіївського районного суду міста Києва","Name":"Полякова Людмила Володимирівна","Link":"http://gl.ki.court.gov.ua/userfiles/2%2884%29.pdf","Note":"","AdditionalNote":"","field8":"","field9":"","field10":"","Кількість справ":0,"Оскаржені":0,"Кількість скарг":"","Кількість дисциплінарних стягнень":"","Клейма":"","Фото":"","Як живе":"","key":"polyakova_lyudmila_volodimirivna","allDeclarations":[{"provider":"declarations.com.ua","document":{"income":{"5":{"value":"","family_comment":"","value_unclear":false,"comment_hidden":false,"family_hidden":false,"value_hidden":false,"family_unclear":false,"family_comment_hidden":false,"comment":"","family":"538436.16"},"6":{"value":"","family_comment":"","value_unclear":false,"family_hidden":false,"family_unclear":false,"family":"389891.91","comment":""},"7":{"source_name_unclear":false,"value":"","family_hidden":false,"family_comment":"","source_name":"","family":"","comment":"","source_name_hidden":false},"8":{"family_comment":"","value":"","family":"","comment":""},"9":{"value":"","value_unclear":false,"family_hidden":false,"family_comment":"","family":"","comment":""},"10":{"value":"","value_unclear":false,"family_hidden":false,"value_hidden":false,"family_comment":"","comment_unclear":false,"comment":"","family":""},"11":{"family_comment":"","value":"","family":"","comment":""},"12":{"family_comment":"","value":"","family":"","comment":""},"13":{"family_comment":"","value":"","family":"","comment":""},"14":{"family_comment":"","value":"","family":"","comment":""},"15":{"family_comment":"ПАТ 'Страxова група 'ТАС',м. Київ","value":"","family_hidden":false,"comment":"","family":"8544.26"},"16":{"value":"","value_unclear":false,"family_hidden":false,"family_comment":"","family":"140000","comment":""},"17":{"family_comment":"","value":"","family_hidden":false,"comment":"","family":""},"18":{"family_comment":"","value":"","value_unclear":false,"family":"","comment":""},"19":{"family_comment":"","value":"","family":"","comment":""},"20":{"value":"12930","family_comment":"","value_unclear":false,"family_hidden":false,"family_unclear":false,"comment_unclear":false,"comment":"допомога по догляду за дитиною до 3х років","family":""}},"vehicle":{"35":[{"brand_info":"об'єм двигуна 1332 , потужність 95 к. с","sum_rent_comment":"","brand_info_unclear":false,"year":"2009","sum_rent_unclear":false,"brand_info_hidden":false,"sum_rent_comment_unclear":false,"sum_hidden":false,"sum_rent":"","sum":"","brand":"Mitsubishi Colt","sum_comment":"","brand_unclear":false,"brand_hidden":false}],"40":[{"year_hidden":false,"brand_info":"об'єм двигуна 1597 , потужність 103 к. с","sum_rent_comment":"","year":"2002","brand_info_hidden":false,"brand_info_unclear":false,"year_unclear":false,"sum_rent":"","sum":"","brand":"Mitsubishi Carisma","sum_comment":"","brand_unclear":true,"brand_hidden":false},{"brand_info":"об'єм двигуна 2360 , потужність 170 к. с","sum_rent_comment":"","brand":"Mitsubishi Outlander","sum_comment":"","year":"2007","sum":"","sum_rent":""}]},"id":"vulyk_72_155","declaration":{"additional_info_text":"","notfull_lostpages":"","date":"2015-03-30T00:00:00","notfull":"","additional_info":"","url":"http://static.declarations.com.ua/declarations/chosen_ones/epic_batch/poliakova_liudmyla_volodymyrivna.pdf"},"liabilities":{"54":{"sum_foreign_comment":"","sum":"","sum_comment":"","sum_comment_hidden":false,"sum_unclear":true,"sum_foreign":""},"55":{"sum_foreign_comment":"","sum":"","sum_comment":"","sum_foreign":""},"56":{"sum_foreign_comment":"","sum":"","sum_hidden":false,"sum_comment":"","sum_foreign":""},"57":{"sum_foreign_comment":"","sum":"","sum_comment":"","sum_comment_unclear":false,"sum_hidden":false,"sum_comment_hidden":false,"sum_unclear":false,"sum_foreign":""},"58":{"sum_foreign_comment":"","sum":"","sum_comment":"","sum_comment_unclear":false,"sum_hidden":false,"sum_comment_hidden":false,"sum_unclear":false,"sum_foreign":""},"59":{"sum_foreign_comment":"","sum_foreign_hidden":false,"sum_comment":"","sum_foreign_unclear":false,"sum_comment_hidden":false,"sum":"","sum_foreign":""},"60":{"sum_foreign_comment":"","sum_foreign_hidden":false,"sum_comment":"","sum_hidden":false,"sum":"15370","sum_foreign":""},"61":{"sum_foreign_comment":"","sum_foreign_hidden":false,"sum_comment":"","sum_hidden":false,"sum":"","sum_foreign":""},"62":{"sum_foreign_comment":"","sum_foreign_hidden":false,"sum_comment":"","sum_hidden":false,"sum":"","sum_foreign":""},"63":{"sum_foreign_comment":"","sum_foreign_hidden":false,"sum_comment":"","sum_comment_unclear":false,"sum_hidden":false,"sum_comment_hidden":false,"sum_unclear":false,"sum":"","sum_foreign":""},"64":{"sum_foreign_comment":"","sum_foreign_hidden":false,"sum_comment":"","sum_hidden":false,"sum":"","sum_foreign":""}},"ft_src":"15370\nКиїв\n3028\nм. Київ\nсуддя голосіївського районного суду міста києва\nм. Київ\nЗагальний місцевий суд\nЛюдмила\nГригорцов Костянтин Вадимович\nПодружжя\nГригорцов Костянтин Костянтинович\nДитина\nГригорцов Іван Костянтинович\nДитина\nВолодимирівна\nПолякова\nПолякова Людмила Володимирівна\nПолякова Людмила Володимирівна\nЛюдмила Володимирівна Полякова\nЛюдмила Полякова\nПолякова Людмила Володимирівна\nоб'єм двигуна 1332 , потужність 95 к. с\nMitsubishi Colt\n2009\nоб'єм двигуна 1597 , потужність 103 к. с\nMitsubishi Carisma\n2002\nоб'єм двигуна 2360 , потужність 170 к. с\n2007\nMitsubishi Outlander\nм. Київ\nпр. Феодосіївський\n143.5\nКиївська область\n1/15 частина\nсмт. Клавдієво-Тарасове, вул. Леніна\n1/3 частина\nсмт. Клавдієво-Тарасове, вул. Лісова\nКиївська область\n74.2\nвул. Саперно-Слобідська\nм. Київ\n2014\n389891.91\n8544.26\nПАТ 'Страxова група 'ТАС',м. Київ\n538436.16\n140000\nдопомога по догляду за дитиною до 3х років\n12930\nоб'єм двигуна 1332 , потужність 95 к. с\nMitsubishi Colt\n2009\nоб'єм двигуна 1597 , потужність 103 к. с\nMitsubishi Carisma\n2002\nоб'єм двигуна 2360 , потужність 170 к. с\nMitsubishi Outlander\n2007\n1/3 частина\nКиївська область\nсмт. Клавдієво-Тарасове, вул. Лісова\nм. Київ\nпр. Феодосіївський\n143.5\n1/15 частина\nсмт. Клавдієво-Тарасове, вул. Леніна\nКиївська область\nвул. Саперно-Слобідська\n74.2\nм. Київ\nПодружжя\nГригорцов Костянтин Вадимович\nДитина\nГригорцов Костянтин Костянтинович\nДитина\nГригорцов Іван Костянтинович\nПолякова Людмила Володимирівна\nЛюдмила Володимирівна Полякова\nЛюдмила Полякова\nПолякова Людмила Володимирівна\nЛюдмила\nПолякова Людмила Володимирівна\nПолякова\nм. Київ\nЗагальний місцевий суд\nсуддя голосіївського районного суду міста києва\nВолодимирівна\nКиїв\n3028\nм. Київ\n15370\n389891.91\n12930\nдопомога по догляду за дитиною до 3х років\n8544.26\nПАТ 'Страxова група 'ТАС',м. Київ\n538436.16\n140000\n2014\n15370\nГригорцов Костянтин Вадимович\nПодружжя\nГригорцов Костянтин Костянтинович\nДитина\nГригорцов Іван Костянтинович\nДитина\nВолодимирівна\nПолякова\nПолякова Людмила Володимирівна\nЛюдмила Володимирівна Полякова\nЛюдмила Полякова\nПолякова Людмила Володимирівна\nм. Київ\nКиїв\n3028\nм. Київ\nЗагальний місцевий суд\nсуддя голосіївського районного суду міста києва\nПолякова Людмила Володимирівна\nЛюдмила\n2009\nMitsubishi Colt\nоб'єм двигуна 1332 , потужність 95 к. с\nMitsubishi Carisma\nоб'єм двигуна 1597 , потужність 103 к. с\n2002\nMitsubishi Outlander\nоб'єм двигуна 2360 , потужність 170 к. с\n2007\n8544.26\nПАТ 'Страxова група 'ТАС',м. Київ\nдопомога по догляду за дитиною до 3х років\n12930\n538436.16\n140000\n389891.91\nм. Київ\nпр. Феодосіївський\n143.5\n1/15 частина\nсмт. Клавдієво-Тарасове, вул. Леніна\nКиївська область\n1/3 частина\nсмт. Клавдієво-Тарасове, вул. Лісова\nКиївська область\n74.2\nвул. Саперно-Слобідська\nм. Київ\n2014","general":{"inn":"","name":"Людмила","patronymic_unclear":false,"family":[{"inn":"","inn_hidden":true,"relations_unclear":false,"relations_hidden":false,"relations_other":"","relations":"Подружжя","name_hidden":true,"inn_unclear":false,"family_name":"Григорцов Костянтин Вадимович","name_unclear":true},{"inn":"","inn_hidden":false,"relations_hidden":false,"family_name":"Григорцов Костянтин Костянтинович","relations_other":"","relations":"Дитина","name_hidden":true,"name_unclear":true},{"inn":"","inn_hidden":false,"relations_hidden":false,"family_name":"Григорцов Іван Костянтинович","relations_other":"","relations":"Дитина","name_hidden":true,"name_unclear":true}],"patronymic":"Володимирівна","inn_hidden":true,"family_raw":"","inn_unclear":false,"post":{"post_unclear":false,"region_unclear":false,"post":"суддя голосіївського районного суду міста києва","candidate":"","office_hidden":false,"region":"м. Київ","post_hidden":false,"office":"Загальний місцевий суд","office_unclear":false,"region_hidden":false},"last_name_unclear":false,"full_name":"Полякова Людмила Володимирівна","addresses":[{"place_city_type_hidden":false,"place_district_hidden":true,"place_city_type":"Місто","place_city_hidden":true,"place_address_unclear":false,"place_address":"3028","place":"м. Київ","place_district":"","place_unclear":false,"place_city":"Київ","place_city_unclear":false,"place_hidden":true,"place_address_hidden":true,"place_district_unclear":false}],"last_name":"Полякова","patronymic_hidden":false,"full_name_suggest":{"output":"Полякова Людмила Володимирівна","input":["Полякова Людмила Володимирівна","Людмила Володимирівна Полякова","Людмила Полякова"]},"name_unclear":false},"source":"VULYK","estate":{"25":[{"space_unclear":false,"costs":"","costs_rent_unclear":false,"costs_comment":"","costs_hidden":false,"space_hidden":false,"costs_comment_unclear":false,"costs_rent_comment_unclear":false,"region":"м. Київ","space_comment_hidden":false,"space_comment_unclear":false,"costs_rent_comment_hidden":false,"costs_rent":"","costs_comment_hidden":false,"address_hidden":true,"region_hidden":true,"space_comment":"","space":"74.2","address":"вул. Саперно-Слобідська","address_unclear":false,"costs_rent_comment":"","costs_rent_hidden":false,"space_units":"м²"}],"30":[{"region_unclear":false,"space_unclear":false,"address_hidden":true,"region_hidden":true,"space_comment":"1/3 частина","space_hidden":true,"space":"","address":"смт. Клавдієво-Тарасове, вул. Лісова","region":"Київська область","costs_property":"","costs_rent_comment":"","space_units":"м²","costs_property_comment":"","costs_rent":""}],"31":[{"space_unclear":false,"address_hidden":true,"region_hidden":true,"space_comment":"","space_units_hidden":false,"space_hidden":false,"space":"143.5","address":"пр. Феодосіївський","region":"м. Київ","address_unclear":true,"costs_rent_comment":"","costs_property":"","space_units":"м²","costs_property_comment":"","costs_rent":""},{"costs_rent":"","region":"Київська область","costs_property":"","costs_rent_comment":"","address_hidden":true,"region_hidden":false,"space_comment":"1/15 частина","costs_property_comment":"","space_units":"м²","space":"","address":"смт. Клавдієво-Тарасове, вул. Леніна"}]},"intro":{"declaration_year":"2014","isnotdeclaration":"","declaration_year_unclear":false}}}],"declarations":[{"income":{"5":{"value":"","family_comment":"","value_unclear":false,"comment_hidden":false,"family_hidden":false,"value_hidden":false,"family_unclear":false,"family_comment_hidden":false,"comment":"","family":"538436.16"},"6":{"value":"","family_comment":"","value_unclear":false,"family_hidden":false,"family_unclear":false,"family":"389891.91","comment":""},"7":{"source_name_unclear":false,"value":"","family_hidden":false,"family_comment":"","source_name":"","family":"","comment":"","source_name_hidden":false},"8":{"family_comment":"","value":"","family":"","comment":""},"9":{"value":"","value_unclear":false,"family_hidden":false,"family_comment":"","family":"","comment":""},"10":{"value":"","value_unclear":false,"family_hidden":false,"value_hidden":false,"family_comment":"","comment_unclear":false,"comment":"","family":""},"11":{"family_comment":"","value":"","family":"","comment":""},"12":{"family_comment":"","value":"","family":"","comment":""},"13":{"family_comment":"","value":"","family":"","comment":""},"14":{"family_comment":"","value":"","family":"","comment":""},"15":{"family_comment":"ПАТ 'Страxова група 'ТАС',м. Київ","value":"","family_hidden":false,"comment":"","family":"8544.26"},"16":{"value":"","value_unclear":false,"family_hidden":false,"family_comment":"","family":"140000","comment":""},"17":{"family_comment":"","value":"","family_hidden":false,"comment":"","family":""},"18":{"family_comment":"","value":"","value_unclear":false,"family":"","comment":""},"19":{"family_comment":"","value":"","family":"","comment":""},"20":{"value":"12930","family_comment":"","value_unclear":false,"family_hidden":false,"family_unclear":false,"comment_unclear":false,"comment":"допомога по догляду за дитиною до 3х років","family":""}},"vehicle":{"35":[{"brand_info":"об'єм двигуна 1332 , потужність 95 к. с","sum_rent_comment":"","brand_info_unclear":false,"year":"2009","sum_rent_unclear":false,"brand_info_hidden":false,"sum_rent_comment_unclear":false,"sum_hidden":false,"sum_rent":"","sum":"","brand":"Mitsubishi Colt","sum_comment":"","brand_unclear":false,"brand_hidden":false}],"40":[{"year_hidden":false,"brand_info":"об'єм двигуна 1597 , потужність 103 к. с","sum_rent_comment":"","year":"2002","brand_info_hidden":false,"brand_info_unclear":false,"year_unclear":false,"sum_rent":"","sum":"","brand":"Mitsubishi Carisma","sum_comment":"","brand_unclear":true,"brand_hidden":false},{"brand_info":"об'єм двигуна 2360 , потужність 170 к. с","sum_rent_comment":"","brand":"Mitsubishi Outlander","sum_comment":"","year":"2007","sum":"","sum_rent":""}]},"id":"vulyk_72_155","declaration":{"additional_info_text":"","notfull_lostpages":"","date":"2015-03-30T00:00:00","notfull":"","additional_info":"","url":"http://static.declarations.com.ua/declarations/chosen_ones/epic_batch/poliakova_liudmyla_volodymyrivna.pdf"},"liabilities":{"54":{"sum_foreign_comment":"","sum":"","sum_comment":"","sum_comment_hidden":false,"sum_unclear":true,"sum_foreign":""},"55":{"sum_foreign_comment":"","sum":"","sum_comment":"","sum_foreign":""},"56":{"sum_foreign_comment":"","sum":"","sum_hidden":false,"sum_comment":"","sum_foreign":""},"57":{"sum_foreign_comment":"","sum":"","sum_comment":"","sum_comment_unclear":false,"sum_hidden":false,"sum_comment_hidden":false,"sum_unclear":false,"sum_foreign":""},"58":{"sum_foreign_comment":"","sum":"","sum_comment":"","sum_comment_unclear":false,"sum_hidden":false,"sum_comment_hidden":false,"sum_unclear":false,"sum_foreign":""},"59":{"sum_foreign_comment":"","sum_foreign_hidden":false,"sum_comment":"","sum_foreign_unclear":false,"sum_comment_hidden":false,"sum":"","sum_foreign":""},"60":{"sum_foreign_comment":"","sum_foreign_hidden":false,"sum_comment":"","sum_hidden":false,"sum":"15370","sum_foreign":""},"61":{"sum_foreign_comment":"","sum_foreign_hidden":false,"sum_comment":"","sum_hidden":false,"sum":"","sum_foreign":""},"62":{"sum_foreign_comment":"","sum_foreign_hidden":false,"sum_comment":"","sum_hidden":false,"sum":"","sum_foreign":""},"63":{"sum_foreign_comment":"","sum_foreign_hidden":false,"sum_comment":"","sum_comment_unclear":false,"sum_hidden":false,"sum_comment_hidden":false,"sum_unclear":false,"sum":"","sum_foreign":""},"64":{"sum_foreign_comment":"","sum_foreign_hidden":false,"sum_comment":"","sum_hidden":false,"sum":"","sum_foreign":""}},"ft_src":"15370\nКиїв\n3028\nм. Київ\nсуддя голосіївського районного суду міста києва\nм. Київ\nЗагальний місцевий суд\nЛюдмила\nГригорцов Костянтин Вадимович\nПодружжя\nГригорцов Костянтин Костянтинович\nДитина\nГригорцов Іван Костянтинович\nДитина\nВолодимирівна\nПолякова\nПолякова Людмила Володимирівна\nПолякова Людмила Володимирівна\nЛюдмила Володимирівна Полякова\nЛюдмила Полякова\nПолякова Людмила Володимирівна\nоб'єм двигуна 1332 , потужність 95 к. с\nMitsubishi Colt\n2009\nоб'єм двигуна 1597 , потужність 103 к. с\nMitsubishi Carisma\n2002\nоб'єм двигуна 2360 , потужність 170 к. с\n2007\nMitsubishi Outlander\nм. Київ\nпр. Феодосіївський\n143.5\nКиївська область\n1/15 частина\nсмт. Клавдієво-Тарасове, вул. Леніна\n1/3 частина\nсмт. Клавдієво-Тарасове, вул. Лісова\nКиївська область\n74.2\nвул. Саперно-Слобідська\nм. Київ\n2014\n389891.91\n8544.26\nПАТ 'Страxова група 'ТАС',м. Київ\n538436.16\n140000\nдопомога по догляду за дитиною до 3х років\n12930\nоб'єм двигуна 1332 , потужність 95 к. с\nMitsubishi Colt\n2009\nоб'єм двигуна 1597 , потужність 103 к. с\nMitsubishi Carisma\n2002\nоб'єм двигуна 2360 , потужність 170 к. с\nMitsubishi Outlander\n2007\n1/3 частина\nКиївська область\nсмт. Клавдієво-Тарасове, вул. Лісова\nм. Київ\nпр. Феодосіївський\n143.5\n1/15 частина\nсмт. Клавдієво-Тарасове, вул. Леніна\nКиївська область\nвул. Саперно-Слобідська\n74.2\nм. Київ\nПодружжя\nГригорцов Костянтин Вадимович\nДитина\nГригорцов Костянтин Костянтинович\nДитина\nГригорцов Іван Костянтинович\nПолякова Людмила Володимирівна\nЛюдмила Володимирівна Полякова\nЛюдмила Полякова\nПолякова Людмила Володимирівна\nЛюдмила\nПолякова Людмила Володимирівна\nПолякова\nм. Київ\nЗагальний місцевий суд\nсуддя голосіївського районного суду міста києва\nВолодимирівна\nКиїв\n3028\nм. Київ\n15370\n389891.91\n12930\nдопомога по догляду за дитиною до 3х років\n8544.26\nПАТ 'Страxова група 'ТАС',м. Київ\n538436.16\n140000\n2014\n15370\nГригорцов Костянтин Вадимович\nПодружжя\nГригорцов Костянтин Костянтинович\nДитина\nГригорцов Іван Костянтинович\nДитина\nВолодимирівна\nПолякова\nПолякова Людмила Володимирівна\nЛюдмила Володимирівна Полякова\nЛюдмила Полякова\nПолякова Людмила Володимирівна\nм. Київ\nКиїв\n3028\nм. Київ\nЗагальний місцевий суд\nсуддя голосіївського районного суду міста києва\nПолякова Людмила Володимирівна\nЛюдмила\n2009\nMitsubishi Colt\nоб'єм двигуна 1332 , потужність 95 к. с\nMitsubishi Carisma\nоб'єм двигуна 1597 , потужність 103 к. с\n2002\nMitsubishi Outlander\nоб'єм двигуна 2360 , потужність 170 к. с\n2007\n8544.26\nПАТ 'Страxова група 'ТАС',м. Київ\nдопомога по догляду за дитиною до 3х років\n12930\n538436.16\n140000\n389891.91\nм. Київ\nпр. Феодосіївський\n143.5\n1/15 частина\nсмт. Клавдієво-Тарасове, вул. Леніна\nКиївська область\n1/3 частина\nсмт. Клавдієво-Тарасове, вул. Лісова\nКиївська область\n74.2\nвул. Саперно-Слобідська\nм. Київ\n2014","general":{"inn":"","name":"Людмила","patronymic_unclear":false,"family":[{"inn":"","inn_hidden":true,"relations_unclear":false,"relations_hidden":false,"relations_other":"","relations":"Подружжя","name_hidden":true,"inn_unclear":false,"family_name":"Григорцов Костянтин Вадимович","name_unclear":true},{"inn":"","inn_hidden":false,"relations_hidden":false,"family_name":"Григорцов Костянтин Костянтинович","relations_other":"","relations":"Дитина","name_hidden":true,"name_unclear":true},{"inn":"","inn_hidden":false,"relations_hidden":false,"family_name":"Григорцов Іван Костянтинович","relations_other":"","relations":"Дитина","name_hidden":true,"name_unclear":true}],"patronymic":"Володимирівна","inn_hidden":true,"family_raw":"","inn_unclear":false,"post":{"post_unclear":false,"region_unclear":false,"post":"суддя голосіївського районного суду міста києва","candidate":"","office_hidden":false,"region":"м. Київ","post_hidden":false,"office":"Загальний місцевий суд","office_unclear":false,"region_hidden":false},"last_name_unclear":false,"full_name":"Полякова Людмила Володимирівна","addresses":[{"place_city_type_hidden":false,"place_district_hidden":true,"place_city_type":"Місто","place_city_hidden":true,"place_address_unclear":false,"place_address":"3028","place":"м. Київ","place_district":"","place_unclear":false,"place_city":"Київ","place_city_unclear":false,"place_hidden":true,"place_address_hidden":true,"place_district_unclear":false}],"last_name":"Полякова","patronymic_hidden":false,"full_name_suggest":{"output":"Полякова Людмила Володимирівна","input":["Полякова Людмила Володимирівна","Людмила Володимирівна Полякова","Людмила Полякова"]},"name_unclear":false},"source":"VULYK","estate":{"25":[{"space_unclear":false,"costs":"","costs_rent_unclear":false,"costs_comment":"","costs_hidden":false,"space_hidden":false,"costs_comment_unclear":false,"costs_rent_comment_unclear":false,"region":"м. Київ","space_comment_hidden":false,"space_comment_unclear":false,"costs_rent_comment_hidden":false,"costs_rent":"","costs_comment_hidden":false,"address_hidden":true,"region_hidden":true,"space_comment":"","space":"74.2","address":"вул. Саперно-Слобідська","address_unclear":false,"costs_rent_comment":"","costs_rent_hidden":false,"space_units":"м²"}],"30":[{"region_unclear":false,"space_unclear":false,"address_hidden":true,"region_hidden":true,"space_comment":"1/3 частина","space_hidden":true,"space":"","address":"смт. Клавдієво-Тарасове, вул. Лісова","region":"Київська область","costs_property":"","costs_rent_comment":"","space_units":"м²","costs_property_comment":"","costs_rent":""}],"31":[{"space_unclear":false,"address_hidden":true,"region_hidden":true,"space_comment":"","space_units_hidden":false,"space_hidden":false,"space":"143.5","address":"пр. Феодосіївський","region":"м. Київ","address_unclear":true,"costs_rent_comment":"","costs_property":"","space_units":"м²","costs_property_comment":"","costs_rent":""},{"costs_rent":"","region":"Київська область","costs_property":"","costs_rent_comment":"","address_hidden":true,"region_hidden":false,"space_comment":"1/15 частина","costs_property_comment":"","space_units":"м²","space":"","address":"смт. Клавдієво-Тарасове, вул. Леніна"}]},"intro":{"declaration_year":"2014","isnotdeclaration":"","declaration_year_unclear":false}}],"declarationsLength":1,"analytics":[{"y":2014,"c":1,"k":74.2,"ka":1,"fi":538436.16,"ff":143.5,"ffa":2,"fha":1}]}