{"2010":"","2016":"","Department":"Лозівський міськрайонний суд Харківської області","Region":"Харківська область","Position":"Заступник Голови Лозівського міськрайонного суду Харківської області","Name":"Помазан Вікторія Анатоліївна","Link":"http://lzm.hr.court.gov.ua/userfiles/Pomazan.pdf","Note":"","AdditionalNote":"","field8":"","field9":"","field10":"","Кількість справ":"","Оскаржені":"","Кількість скарг":1,"Кількість дисциплінарних стягнень":"","Клейма":"","Фото":"","Як живе":"","key":"pomazan_viktoriya_anatoliyivna","allDeclarations":[{"provider":"declarations.com.ua","document":{"income":{"5":{"family_comment":"","value":"231257","family":"","comment":""},"6":{"value":"231206","family_comment":"","value_unclear":true,"comment_hidden":false,"family_unclear":false,"family":"","comment":""},"7":{"family_comment":"","value":"","source_name":"","family":"","comment":""},"8":{"family_comment":"","value":"","family":"","comment":""},"9":{"family_comment":"","family_unclear":false,"value":"51","family":"","comment":""},"10":{"family_comment":"","value":"","value_unclear":false,"family":"","comment":""},"11":{"family_comment":"","value":"","family":"","comment":""},"12":{"family_comment":"","value":"","family":"","comment":""},"13":{"family_comment":"","value":"","family":"","comment":""},"14":{"family_comment":"","value":"","family":"","comment":""},"15":{"family_comment":"","value":"","family":"","comment":""},"16":{"family_comment":"","value":"","family":"","comment":""},"17":{"family_comment":"","value":"","family":"","comment":""},"18":{"family_comment":"","value":"","family":"","comment":""},"19":{"family_comment":"","value":"","family":"","comment":""},"20":{"value":"","comment_unclear":false,"family_hidden":false,"family_comment":"","value_unclear":false,"family":"","comment":"","family_comment_unclear":false}},"vehicle":{"35":[{"year_hidden":false,"brand_info":"1.6 куб. см.","sum_rent_comment":"","year":"2011","brand_info_hidden":false,"brand_info_unclear":false,"sum_rent":"","sum":"","brand":"Kia Soul","sum_comment":"","brand_unclear":true,"brand_hidden":false}]},"id":"vulyk_97_137","banks":{"45":[{"sum_foreign_comment":"","sum_units":"UAH","sum_comment":"","sum_comment_unclear":false,"sum_hidden":false,"sum_foreign_units":"UAH","sum_comment_hidden":false,"sum_unclear":true,"sum":"701","sum_foreign":""}]},"declaration":{"additional_info_text":"","notfull_lostpages":"","date":"2015-03-23T00:00:00","notfull":"","additional_info":"","url":"http://static.declarations.com.ua/declarations/chosen_ones/judges_batch/4039_pomazan_viktoriia_anatoliivna.pdf"},"liabilities":{"54":{"sum_foreign_comment":"","sum":"6207","sum_comment":"UNIQA","sum_comment_unclear":true,"sum_hidden":false,"sum_comment_hidden":false,"sum_unclear":true,"sum_foreign":""},"55":{"sum_foreign_comment":"","sum":"","sum_comment":"","sum_foreign":""},"56":{"sum_foreign_comment":"","sum":"","sum_comment":"","sum_foreign":""},"57":{"sum_foreign_comment":"","sum":"16724","sum_comment":"м. Київ, АвтоТак","sum_comment_unclear":true,"sum_hidden":false,"sum_comment_hidden":false,"sum_unclear":true,"sum_foreign":""},"58":{"sum_foreign_comment":"","sum":"11968","sum_comment":"м. Київ, АвтоТак","sum_comment_unclear":true,"sum_hidden":false,"sum_comment_hidden":false,"sum_unclear":true,"sum_foreign":""},"59":{"sum_foreign_comment":"","sum":"","sum_comment":"","sum_foreign":""},"60":{"sum_foreign_comment":"","sum":"","sum_comment":"","sum_comment_unclear":false,"sum_hidden":false,"sum_comment_hidden":false,"sum_foreign":""},"61":{"sum_foreign_comment":"","sum":"","sum_comment":"","sum_foreign":""},"62":{"sum_foreign_comment":"","sum":"","sum_comment":"","sum_unclear":false,"sum_foreign":""},"63":{"sum_foreign_comment":"","sum":"","sum_foreign":"","sum_comment":"","sum_hidden":false},"64":{"sum_foreign_comment":"","sum":"","sum_comment":"","sum_foreign":""}},"ft_src":"1.6 куб. см.\nKia Soul\n2011\nу користуванні\nм. Лозова\n.2\nХарківська область\nприватна\n53.2\nм. Лозова\nХарківська область\n701\n2014\n1.6 куб. см.\nKia Soul\n2011\n2014\nЗагальний місцевий суд\nХарківська область\nзаступник голови лозівського міськрайонного суду харківської області\nПомазан Вікторія Анатоліївна\nВікторія Анатоліївна Помазан\nВікторія Помазан\nПомазан Вікторія Анатоліївна\nПомазан Вікторія Анатоліївна\nВікторія\nПомазан\nАнатоліївна\nХарківська область\n64600\nЛозова\n11968\nм. Київ, АвтоТак\n16724\nм. Київ, АвтоТак\n6207\nUNIQA\n231206\n231257\n51\n.2\nу користуванні\nм. Лозова\nХарківська область\n53.2\nприватна\nм. Лозова\nХарківська область\n701\nм. Київ, АвтоТак\n11968\nм. Київ, АвтоТак\n16724\nUNIQA\n6207\n231206\n51\n231257\nАнатоліївна\nПомазан\nВікторія\nПомазан Вікторія Анатоліївна\nВікторія Анатоліївна Помазан\nВікторія Помазан\nПомазан Вікторія Анатоліївна\n64600\nЛозова\nХарківська область\nХарківська область\nЗагальний місцевий суд\nзаступник голови лозівського міськрайонного суду харківської області\nПомазан Вікторія Анатоліївна","general":{"name_hidden":false,"name":"Вікторія","last_name_hidden":false,"inn":"","last_name":"Помазан","patronymic":"Анатоліївна","inn_hidden":true,"family_raw":"","inn_unclear":false,"post":{"region_unclear":false,"post":"заступник голови лозівського міськрайонного суду харківської області","post_hidden":false,"region":"Харківська область","office":"Загальний місцевий суд","office_unclear":false},"full_name":"Помазан Вікторія Анатоліївна","addresses":[{"place_district":"","place_address_hidden":true,"place_city":"Лозова","place_city_unclear":false,"place_district_hidden":false,"place_city_type":"Місто","place_city_hidden":false,"place_city_type_hidden":false,"place_address":"64600","place_hidden":false,"place":"Харківська область"}],"patronymic_hidden":false,"full_name_suggest":{"output":"Помазан Вікторія Анатоліївна","input":["Помазан Вікторія Анатоліївна","Вікторія Анатоліївна Помазан","Вікторія Помазан"]}},"source":"VULYK","estate":{"23":[{"region_unclear":false,"space_unclear":false,"costs":"","costs_rent_unclear":false,"costs_comment":"","address_hidden":true,"region_hidden":false,"space_comment":"у користуванні","space":".2","address":"м. Лозова","region":"Харківська область","address_unclear":false,"costs_rent_comment":"","space_units":"га","costs_rent":""}],"25":[{"region_unclear":false,"space_hidden":false,"costs":"","costs_comment":"","address_hidden":true,"region_hidden":false,"space_comment":"приватна","space_unclear":false,"space":"53.2","address":"м. Лозова","region":"Харківська область","costs_rent_comment":"","space_comment_unclear":false,"space_comment_hidden":false,"space_units":"м²","costs_rent":""}]},"intro":{"declaration_year":"2014","isnotdeclaration":""}}}],"declarations":[{"income":{"5":{"family_comment":"","value":"231257","family":"","comment":""},"6":{"value":"231206","family_comment":"","value_unclear":true,"comment_hidden":false,"family_unclear":false,"family":"","comment":""},"7":{"family_comment":"","value":"","source_name":"","family":"","comment":""},"8":{"family_comment":"","value":"","family":"","comment":""},"9":{"family_comment":"","family_unclear":false,"value":"51","family":"","comment":""},"10":{"family_comment":"","value":"","value_unclear":false,"family":"","comment":""},"11":{"family_comment":"","value":"","family":"","comment":""},"12":{"family_comment":"","value":"","family":"","comment":""},"13":{"family_comment":"","value":"","family":"","comment":""},"14":{"family_comment":"","value":"","family":"","comment":""},"15":{"family_comment":"","value":"","family":"","comment":""},"16":{"family_comment":"","value":"","family":"","comment":""},"17":{"family_comment":"","value":"","family":"","comment":""},"18":{"family_comment":"","value":"","family":"","comment":""},"19":{"family_comment":"","value":"","family":"","comment":""},"20":{"value":"","comment_unclear":false,"family_hidden":false,"family_comment":"","value_unclear":false,"family":"","comment":"","family_comment_unclear":false}},"vehicle":{"35":[{"year_hidden":false,"brand_info":"1.6 куб. см.","sum_rent_comment":"","year":"2011","brand_info_hidden":false,"brand_info_unclear":false,"sum_rent":"","sum":"","brand":"Kia Soul","sum_comment":"","brand_unclear":true,"brand_hidden":false}]},"id":"vulyk_97_137","banks":{"45":[{"sum_foreign_comment":"","sum_units":"UAH","sum_comment":"","sum_comment_unclear":false,"sum_hidden":false,"sum_foreign_units":"UAH","sum_comment_hidden":false,"sum_unclear":true,"sum":"701","sum_foreign":""}]},"declaration":{"additional_info_text":"","notfull_lostpages":"","date":"2015-03-23T00:00:00","notfull":"","additional_info":"","url":"http://static.declarations.com.ua/declarations/chosen_ones/judges_batch/4039_pomazan_viktoriia_anatoliivna.pdf"},"liabilities":{"54":{"sum_foreign_comment":"","sum":"6207","sum_comment":"UNIQA","sum_comment_unclear":true,"sum_hidden":false,"sum_comment_hidden":false,"sum_unclear":true,"sum_foreign":""},"55":{"sum_foreign_comment":"","sum":"","sum_comment":"","sum_foreign":""},"56":{"sum_foreign_comment":"","sum":"","sum_comment":"","sum_foreign":""},"57":{"sum_foreign_comment":"","sum":"16724","sum_comment":"м. Київ, АвтоТак","sum_comment_unclear":true,"sum_hidden":false,"sum_comment_hidden":false,"sum_unclear":true,"sum_foreign":""},"58":{"sum_foreign_comment":"","sum":"11968","sum_comment":"м. Київ, АвтоТак","sum_comment_unclear":true,"sum_hidden":false,"sum_comment_hidden":false,"sum_unclear":true,"sum_foreign":""},"59":{"sum_foreign_comment":"","sum":"","sum_comment":"","sum_foreign":""},"60":{"sum_foreign_comment":"","sum":"","sum_comment":"","sum_comment_unclear":false,"sum_hidden":false,"sum_comment_hidden":false,"sum_foreign":""},"61":{"sum_foreign_comment":"","sum":"","sum_comment":"","sum_foreign":""},"62":{"sum_foreign_comment":"","sum":"","sum_comment":"","sum_unclear":false,"sum_foreign":""},"63":{"sum_foreign_comment":"","sum":"","sum_foreign":"","sum_comment":"","sum_hidden":false},"64":{"sum_foreign_comment":"","sum":"","sum_comment":"","sum_foreign":""}},"ft_src":"1.6 куб. см.\nKia Soul\n2011\nу користуванні\nм. Лозова\n.2\nХарківська область\nприватна\n53.2\nм. Лозова\nХарківська область\n701\n2014\n1.6 куб. см.\nKia Soul\n2011\n2014\nЗагальний місцевий суд\nХарківська область\nзаступник голови лозівського міськрайонного суду харківської області\nПомазан Вікторія Анатоліївна\nВікторія Анатоліївна Помазан\nВікторія Помазан\nПомазан Вікторія Анатоліївна\nПомазан Вікторія Анатоліївна\nВікторія\nПомазан\nАнатоліївна\nХарківська область\n64600\nЛозова\n11968\nм. Київ, АвтоТак\n16724\nм. Київ, АвтоТак\n6207\nUNIQA\n231206\n231257\n51\n.2\nу користуванні\nм. Лозова\nХарківська область\n53.2\nприватна\nм. Лозова\nХарківська область\n701\nм. Київ, АвтоТак\n11968\nм. Київ, АвтоТак\n16724\nUNIQA\n6207\n231206\n51\n231257\nАнатоліївна\nПомазан\nВікторія\nПомазан Вікторія Анатоліївна\nВікторія Анатоліївна Помазан\nВікторія Помазан\nПомазан Вікторія Анатоліївна\n64600\nЛозова\nХарківська область\nХарківська область\nЗагальний місцевий суд\nзаступник голови лозівського міськрайонного суду харківської області\nПомазан Вікторія Анатоліївна","general":{"name_hidden":false,"name":"Вікторія","last_name_hidden":false,"inn":"","last_name":"Помазан","patronymic":"Анатоліївна","inn_hidden":true,"family_raw":"","inn_unclear":false,"post":{"region_unclear":false,"post":"заступник голови лозівського міськрайонного суду харківської області","post_hidden":false,"region":"Харківська область","office":"Загальний місцевий суд","office_unclear":false},"full_name":"Помазан Вікторія Анатоліївна","addresses":[{"place_district":"","place_address_hidden":true,"place_city":"Лозова","place_city_unclear":false,"place_district_hidden":false,"place_city_type":"Місто","place_city_hidden":false,"place_city_type_hidden":false,"place_address":"64600","place_hidden":false,"place":"Харківська область"}],"patronymic_hidden":false,"full_name_suggest":{"output":"Помазан Вікторія Анатоліївна","input":["Помазан Вікторія Анатоліївна","Вікторія Анатоліївна Помазан","Вікторія Помазан"]}},"source":"VULYK","estate":{"23":[{"region_unclear":false,"space_unclear":false,"costs":"","costs_rent_unclear":false,"costs_comment":"","address_hidden":true,"region_hidden":false,"space_comment":"у користуванні","space":".2","address":"м. Лозова","region":"Харківська область","address_unclear":false,"costs_rent_comment":"","space_units":"га","costs_rent":""}],"25":[{"region_unclear":false,"space_hidden":false,"costs":"","costs_comment":"","address_hidden":true,"region_hidden":false,"space_comment":"приватна","space_unclear":false,"space":"53.2","address":"м. Лозова","region":"Харківська область","costs_rent_comment":"","space_comment_unclear":false,"space_comment_hidden":false,"space_units":"м²","costs_rent":""}]},"intro":{"declaration_year":"2014","isnotdeclaration":""}}],"declarationsLength":1,"analytics":[{"y":2014,"b":701,"i":231257,"c":1,"k":53.2,"ka":1,"l":2000,"la":1}]}