{"2010":"Попова Наталія Іванівна","2016":1,"Department":"Знам'янський міськрайонний суд Кіровоградської області","Region":"Кіровоградська область","Position":"Голова Знам'янського міськрайонного суду Кіровоградської області","Name":"Проценко Олександр Миколайович","Link":"https://drive.google.com/open?id=0BygiyWAl79DMSE5rSVZBcE9RaVU","Note":"У меня","AdditionalNote":"","field8":"","field9":"","field10":"","Кількість справ":"","Оскаржені":"","Кількість скарг":1,"Кількість дисциплінарних стягнень":"","Клейма":"","Фото":"","Як живе":"","key":"procenko_oleksandr_mikolayovich","allDeclarations":[{"provider":"declarations.com.ua","document":{"income":{"5":{"family_comment":"","value":"250530.47","family":"","comment":""},"6":{"value":"205966.4","comment_hidden":false,"family_comment":"","family":"","comment":"","family_comment_hidden":false},"7":{"value":"","comment_unclear":false,"family_comment":"","source_name":"","family":"","comment":""},"8":{"family_comment":"","value":"","family":"","comment":""},"9":{"family_comment":"","value":"","family":"","comment":""},"10":{"family_comment":"","value":"12180","family_hidden":false,"comment":"","family":""},"11":{"family_comment":"","value":"","family":"","comment":""},"12":{"family_comment":"","value":"","family":"","comment":""},"13":{"family_comment":"","value":"","family":"","comment":""},"14":{"family_comment":"","value":"","family":"","comment":""},"15":{"family_comment":"","value":"","family":"","comment":""},"16":{"family_comment":"","value":"","family":"","comment":""},"17":{"family_comment":"","value":"","family":"","comment":""},"18":{"family_comment":"","value":"","family":"","comment":""},"19":{"family_comment":"","value":"","family":"","comment":""},"20":{"value":"32384.07","value_unclear":false,"family_hidden":false,"family_comment":"","family":"","comment":""}},"vehicle":{"35":[{"brand_info":"2993 куб. см., 238 к.с.","sum_rent_comment":"","brand":"Infiniti QX70","sum_comment":"","year":"2013","brand_info_unclear":false,"sum":"180000","sum_rent":""}]},"id":"vulyk_83_53","declaration":{"additional_info_text":"","notfull_lostpages":"","date":"2015-03-25T00:00:00","notfull":"","additional_info":"","url":"http://static.declarations.com.ua/declarations/chosen_ones/judges_batch/2323_protsenko_oleksandr_mykolaiovych.pdf"},"liabilities":{"54":{"sum_foreign_comment":"","sum":"28551","sum_comment":"","sum_foreign":""},"55":{"sum_foreign_comment":"","sum":"","sum_comment":"","sum_foreign":""},"56":{"sum_foreign_comment":"","sum":"56006.6","sum_comment":"","sum_foreign":""},"57":{"sum_foreign_comment":"","sum":"59567.05","sum_comment":"","sum_foreign":""},"58":{"sum_foreign_comment":"","sum":"59432.95","sum_comment":"","sum_foreign":""},"59":{"sum_foreign_comment":"","sum":"","sum_comment":"","sum_foreign":""},"60":{"sum_foreign_comment":"","sum":"","sum_comment":"","sum_foreign":""},"61":{"sum_foreign_comment":"","sum":"","sum_comment":"","sum_foreign":""},"62":{"sum_foreign_comment":"","sum":"","sum_comment":"","sum_foreign":""},"63":{"sum_foreign_comment":"","sum":"","sum_comment":"","sum_foreign":""},"64":{"sum_foreign_comment":"","sum":"","sum_comment":"","sum_foreign":""}},"ft_src":"59567.05\n28551\n59432.95\n56006.6\nзаступник голови знам'янського міськрайонного суду кіровоградської області\nКіровоградська область\nЗагальний місцевий суд\nОлександр\nПроценко М. В\nПодружжя\nМиколайович\nПроценко Олександр Миколайович\nОлександр Миколайович Проценко\nОлександр Проценко\nПроценко Олександр Миколайович\nПроценко Олександр Миколайович\nПроценко\n2993 куб. см., 238 к.с.\n2013\nInfiniti QX70\n180000\n65.1\n2014\n205966.4\n12180\n250530.47\n32384.07\n2993 куб. см., 238 к.с.\nInfiniti QX70\n2013\n180000\n65.1\nПодружжя\nПроценко М. В\nПроценко Олександр Миколайович\nОлександр Миколайович Проценко\nОлександр Проценко\nПроценко Олександр Миколайович\nПроценко Олександр Миколайович\nОлександр\nМиколайович\nЗагальний місцевий суд\nКіровоградська область\nзаступник голови знам'янського міськрайонного суду кіровоградської області\nПроценко\n59432.95\n28551\n59567.05\n56006.6\n205966.4\n32384.07\n250530.47\n12180\n2014\n59432.95\n59567.05\n56006.6\n28551\nПроценко М. В\nПодружжя\nМиколайович\nПроценко\nОлександр\nПроценко Олександр Миколайович\nОлександр Миколайович Проценко\nОлександр Проценко\nПроценко Олександр Миколайович\nКіровоградська область\nЗагальний місцевий суд\nзаступник голови знам'янського міськрайонного суду кіровоградської області\nПроценко Олександр Миколайович\n2013\n2993 куб. см., 238 к.с.\nInfiniti QX70\n180000\n12180\n32384.07\n250530.47\n205966.4\n65.1\n2014","general":{"inn":"","name":"Олександр","inn_unclear":false,"family":[{"inn":"","inn_hidden":false,"relations_hidden":false,"family_name":"Проценко М. В","relations_other":"","relations":"Подружжя","name_hidden":false,"name_unclear":false}],"inn_hidden":true,"family_raw":"","last_name":"Проценко","post":{"post_unclear":false,"post":"заступник голови знам'янського міськрайонного суду кіровоградської області","candidate":"","region":"Кіровоградська область","office":"Загальний місцевий суд","office_unclear":false},"full_name_suggest":{"output":"Проценко Олександр Миколайович","input":["Проценко Олександр Миколайович","Олександр Миколайович Проценко","Олександр Проценко"]},"full_name":"Проценко Олександр Миколайович","addresses":[{"place_city_type_unclear":false,"place_address":"","place_district_hidden":false,"place_city_type":"","place_address_hidden":false,"place_address_unclear":false,"place_city_type_hidden":false,"place":"","place_district":"","place_city_hidden":false,"place_city":"","place_city_unclear":false,"place_hidden":true}],"patronymic":"Миколайович","last_name_unclear":false},"source":"VULYK","estate":{"25":[{"region_unclear":false,"space_hidden":false,"costs":"","costs_comment":"","address_hidden":false,"region_hidden":true,"space_comment":"","space_unclear":false,"space":"65.1","address":"","region":"","costs_rent_comment":"","space_comment_unclear":false,"space_units":"м²","costs_rent":""}]},"intro":{"declaration_year":"2014"}}},{"provider":"public-api.nazk.gov.ua","document":{"step_0":{"declarationType":"1","declarationYear1":"2015"},"step_1":{"city":"[Конфіденційна інформація]","region":"[Конфіденційна інформація]","street":"[Конфіденційна інформація]","country":"1","cityPath":"[Конфіденційна інформація]","cityType":"[Конфіденційна інформація]","district":"[Конфіденційна інформація]","lastname":"Проценко","postCode":"[Конфіденційна інформація]","postType":"","workPost":"суддя","firstname":"Олександр","workPlace":"Знам'янський міськрайонний суд Кіровоградської області","middlename":"Миколайович","streetType":"[Конфіденційна інформація]","changedName":false,"countryPath":"","eng_postCode":"","postCategory":"","actual_street":"[Конфіденційна інформація]","actual_cityPath":"[Конфіденційна інформація]","actual_cityType":"[Конфіденційна інформація]","actual_postCode":"[Конфіденційна інформація]","actual_streetType":"[Конфіденційна інформація]","previous_lastname":"","corruptionAffected":"Так","eng_actualPostCode":"[Конфіденційна інформація]","previous_firstname":"","city_extendedstatus":"1","previous_middlename":"","responsiblePosition":"","sameRegLivingAddress":"[Конфіденційна інформація]","postType_extendedstatus":"1","eng_sameRegLivingAddress":"[Конфіденційна інформація]","housePartNum_extendedstatus":"1","postCategory_extendedstatus":"1"},"step_2":{"1477391304073":{"lastname":"Проценко","firstname":"Марина","middlename":"Василівна","changedName":false,"citizenship":"1","eng_lastname":"","eng_firstname":"","eng_middlename":"","isNotApplicable":"","subjectRelation":"дружина","previous_lastname":"","previous_firstname":"","previous_middlename":"","previous_eng_lastname":"","previous_eng_firstname":"","previous_eng_middlename":""}},"step_3":{"1477391432307":{"city":"[Конфіденційна інформація]","person":"1","region":"[Конфіденційна інформація]","rights":[],"country":"1","cityPath":"[Конфіденційна інформація]","costDate":"","district":"[Конфіденційна інформація]","postCode":"[Конфіденційна інформація]","totalArea":"65,1","ua_street":"[Конфіденційна інформація]","objectType":"Квартира","owningDate":"16.10.2013","ua_cityType":"Знам'янка / Кіровоградська Область / Україна","ua_postCode":"27400","ua_streetType":"[Конфіденційна інформація]","costAssessment":"","otherObjectType":"","costDate_extendedstatus":"2","costAssessment_extendedstatus":"2","ua_housePartNum_extendedstatus":"1"}},"step_4":[],"step_5":[],"step_6":{"1477391938167":{"brand":"infiniti","model":"qx70","person":"1","rights":[],"costDate":"601071","objectType":"Автомобіль легковий","owningDate":"21.01.2014","graduationYear":"2013","otherObjectType":""}},"step_7":[],"step_8":[],"step_9":[],"step_10":[],"step_11":{"1477392631724":{"person":"1","rights":{"1":{"citizen":"","ua_city":"","ua_street":"[Конфіденційна інформація]","ua_lastname":"","ua_postCode":"","eng_fullname":"","eng_lastname":"","eng_postCode":"","rightBelongs":"1","ua_firstname":"","ukr_fullname":"","ukr_lastname":"","eng_firstname":"","ownershipType":"Власність","ua_middlename":"","ua_streetType":"[Конфіденційна інформація]","ukr_firstname":"","eng_middlename":"","otherOwnership":"","ukr_middlename":"","rights_cityPath":"","ua_company_name":"","eng_company_name":"","ukr_company_name":"","percent-ownership":"","ua_street_extendedstatus":"","ua_houseNum_extendedstatus":"","ua_postCode_extendedstatus":"","eng_postCode_extendedstatus":"","ua_middlename_extendedstatus":"","eng_middlename_extendedstatus":"","ukr_middlename_extendedstatus":"","ua_housePartNum_extendedstatus":"","ua_apartmentsNum_extendedstatus":""}},"objectType":"Заробітна плата отримана за основним місцем роботи","sizeIncome":"258110","incomeSource":"1","source_citizen":"","otherObjectType":"","source_ua_lastname":"","source_eng_fullname":"","source_ua_firstname":"","source_ukr_fullname":"","source_ua_middlename":"","source_ua_company_name":"","source_eng_company_name":"","source_ukr_company_name":"","source_ua_sameRegLivingAddress":""},"1477392971558":{"person":"1","rights":[],"objectType":"Пенсія","sizeIncome":"45278","incomeSource":"1","source_citizen":"","otherObjectType":"","source_ua_lastname":"","source_eng_fullname":"","source_ua_firstname":"","source_ukr_fullname":"","source_ua_middlename":"","source_ua_company_name":"","source_eng_company_name":"","source_ukr_company_name":"","source_ua_sameRegLivingAddress":""}},"step_12":[],"step_13":{"1477393202617":{"person":"1","currency":"UAH","guarantor":{"1477393818273":{"guarantor":"1477391304073","guarantor_type":"","guarantor_exist":"","guarantor_ua_lastname":"","guarantor_eng_lastname":"","guarantor_ua_firstname":"","guarantor_ukr_lastname":"","guarantor_eng_firstname":"","guarantor_ua_middlename":"","guarantor_ukr_firstname":"","guarantor_eng_middlename":"","guarantor_ukr_middlename":"","guarantor_ua_company_name":"","guarantor_eng_company_name":"","guarantor_ukr_company_name":"","guarantor_ua_sameRegLivingAddress":"","guarantor_eng_sameRegLivingAddress":""}},"dateOrigin":"22.01.2014","objectType":"Отримані кредити","margin-emitent":"j","sizeObligation":"420751","emitent_citizen":"Юридична особа, зареєстрована в Україні","otherObjectType":"","guarantor_exist_":true,"guarantor_realty":[],"ownerThirdPerson":"","emitent_ua_lastname":"","emitent_eng_fullname":"","emitent_ua_firstname":"","emitent_ukr_fullname":"","emitent_ua_middlename":"","ownerThirdPersonThing":"","emitent_ua_company_name":"ЮнікредітБанк","guarantor_realty_exist_":false,"emitent_eng_company_name":"","emitent_ukr_company_name":"","emitent_ua_sameRegLivingAddress":""}},"step_14":{"1477397734571":{"type":1,"person":"","country":"1","costAmount":"150636","costsAmount":"","specExpenses":"Інше","specOtherExpenses":"кредит","specExpensesSubject":"Рухоме майно","specExpensesOtherSubject":"","specExpensesAssetsSubject":"","specExpensesRealtySubject":"","specExpensesMovableSubject":"Грошові кошти","specExpensesOtherRealtySubject":"","specExpensesOtherMovableSubject":""}},"step_15":[],"step_16":[],"id":"baa0c426-43e2-43cf-be24-e2703800b34b"}}],"declarations":[{"income":{"5":{"family_comment":"","value":"250530.47","family":"","comment":""},"6":{"value":"205966.4","comment_hidden":false,"family_comment":"","family":"","comment":"","family_comment_hidden":false},"7":{"value":"","comment_unclear":false,"family_comment":"","source_name":"","family":"","comment":""},"8":{"family_comment":"","value":"","family":"","comment":""},"9":{"family_comment":"","value":"","family":"","comment":""},"10":{"family_comment":"","value":"12180","family_hidden":false,"comment":"","family":""},"11":{"family_comment":"","value":"","family":"","comment":""},"12":{"family_comment":"","value":"","family":"","comment":""},"13":{"family_comment":"","value":"","family":"","comment":""},"14":{"family_comment":"","value":"","family":"","comment":""},"15":{"family_comment":"","value":"","family":"","comment":""},"16":{"family_comment":"","value":"","family":"","comment":""},"17":{"family_comment":"","value":"","family":"","comment":""},"18":{"family_comment":"","value":"","family":"","comment":""},"19":{"family_comment":"","value":"","family":"","comment":""},"20":{"value":"32384.07","value_unclear":false,"family_hidden":false,"family_comment":"","family":"","comment":""}},"vehicle":{"35":[{"brand_info":"2993 куб. см., 238 к.с.","sum_rent_comment":"","brand":"Infiniti QX70","sum_comment":"","year":"2013","brand_info_unclear":false,"sum":"180000","sum_rent":""}]},"id":"vulyk_83_53","declaration":{"additional_info_text":"","notfull_lostpages":"","date":"2015-03-25T00:00:00","notfull":"","additional_info":"","url":"http://static.declarations.com.ua/declarations/chosen_ones/judges_batch/2323_protsenko_oleksandr_mykolaiovych.pdf"},"liabilities":{"54":{"sum_foreign_comment":"","sum":"28551","sum_comment":"","sum_foreign":""},"55":{"sum_foreign_comment":"","sum":"","sum_comment":"","sum_foreign":""},"56":{"sum_foreign_comment":"","sum":"56006.6","sum_comment":"","sum_foreign":""},"57":{"sum_foreign_comment":"","sum":"59567.05","sum_comment":"","sum_foreign":""},"58":{"sum_foreign_comment":"","sum":"59432.95","sum_comment":"","sum_foreign":""},"59":{"sum_foreign_comment":"","sum":"","sum_comment":"","sum_foreign":""},"60":{"sum_foreign_comment":"","sum":"","sum_comment":"","sum_foreign":""},"61":{"sum_foreign_comment":"","sum":"","sum_comment":"","sum_foreign":""},"62":{"sum_foreign_comment":"","sum":"","sum_comment":"","sum_foreign":""},"63":{"sum_foreign_comment":"","sum":"","sum_comment":"","sum_foreign":""},"64":{"sum_foreign_comment":"","sum":"","sum_comment":"","sum_foreign":""}},"ft_src":"59567.05\n28551\n59432.95\n56006.6\nзаступник голови знам'янського міськрайонного суду кіровоградської області\nКіровоградська область\nЗагальний місцевий суд\nОлександр\nПроценко М. В\nПодружжя\nМиколайович\nПроценко Олександр Миколайович\nОлександр Миколайович Проценко\nОлександр Проценко\nПроценко Олександр Миколайович\nПроценко Олександр Миколайович\nПроценко\n2993 куб. см., 238 к.с.\n2013\nInfiniti QX70\n180000\n65.1\n2014\n205966.4\n12180\n250530.47\n32384.07\n2993 куб. см., 238 к.с.\nInfiniti QX70\n2013\n180000\n65.1\nПодружжя\nПроценко М. В\nПроценко Олександр Миколайович\nОлександр Миколайович Проценко\nОлександр Проценко\nПроценко Олександр Миколайович\nПроценко Олександр Миколайович\nОлександр\nМиколайович\nЗагальний місцевий суд\nКіровоградська область\nзаступник голови знам'янського міськрайонного суду кіровоградської області\nПроценко\n59432.95\n28551\n59567.05\n56006.6\n205966.4\n32384.07\n250530.47\n12180\n2014\n59432.95\n59567.05\n56006.6\n28551\nПроценко М. В\nПодружжя\nМиколайович\nПроценко\nОлександр\nПроценко Олександр Миколайович\nОлександр Миколайович Проценко\nОлександр Проценко\nПроценко Олександр Миколайович\nКіровоградська область\nЗагальний місцевий суд\nзаступник голови знам'янського міськрайонного суду кіровоградської області\nПроценко Олександр Миколайович\n2013\n2993 куб. см., 238 к.с.\nInfiniti QX70\n180000\n12180\n32384.07\n250530.47\n205966.4\n65.1\n2014","general":{"inn":"","name":"Олександр","inn_unclear":false,"family":[{"inn":"","inn_hidden":false,"relations_hidden":false,"family_name":"Проценко М. В","relations_other":"","relations":"Подружжя","name_hidden":false,"name_unclear":false}],"inn_hidden":true,"family_raw":"","last_name":"Проценко","post":{"post_unclear":false,"post":"заступник голови знам'янського міськрайонного суду кіровоградської області","candidate":"","region":"Кіровоградська область","office":"Загальний місцевий суд","office_unclear":false},"full_name_suggest":{"output":"Проценко Олександр Миколайович","input":["Проценко Олександр Миколайович","Олександр Миколайович Проценко","Олександр Проценко"]},"full_name":"Проценко Олександр Миколайович","addresses":[{"place_city_type_unclear":false,"place_address":"","place_district_hidden":false,"place_city_type":"","place_address_hidden":false,"place_address_unclear":false,"place_city_type_hidden":false,"place":"","place_district":"","place_city_hidden":false,"place_city":"","place_city_unclear":false,"place_hidden":true}],"patronymic":"Миколайович","last_name_unclear":false},"source":"VULYK","estate":{"25":[{"region_unclear":false,"space_hidden":false,"costs":"","costs_comment":"","address_hidden":false,"region_hidden":true,"space_comment":"","space_unclear":false,"space":"65.1","address":"","region":"","costs_rent_comment":"","space_comment_unclear":false,"space_units":"м²","costs_rent":""}]},"intro":{"declaration_year":"2014"}}],"declarationsLength":1,"analytics":[{"y":2014,"i":250530.47,"c":1,"k":65.1,"ka":1},{"y":2015,"i":303388,"c":1,"k":65.1,"ka":1,"j":1}]}