{"2010":1,"2016":1,"Department":"Коломийський міськрайонний суд Івано-Франківської області","Region":"Івано-Франківська область","Position":"Голова Коломийського міськрайонного суду Івано-Франківської області","Name":"П'ятковський Володимир Іванович","Link":"https://drive.google.com/open?id=0BygiyWAl79DMaE1NendpSDBUaVE","Note":"У меня","AdditionalNote":"","field8":"","field9":"","field10":"","Кількість справ":"","Оскаржені":"","Кількість скарг":1,"Кількість дисциплінарних стягнень":"","Клейма":"","Фото":"http://blog.prosud.info/images/pyatkovskiy.jpg","Як живе":"http://blog.prosud.info/prosud_pyatkovskiy_volodimir_ivanovich.html","key":"pyatkovskiy_volodimir_ivanovich","allDeclarations":[{"provider":"declarations.com.ua","document":{"income":{"5":{"value":"254054","family_hidden":false,"value_hidden":false,"family_comment":"","family":"17051","comment":""},"6":{"family_comment":"","value":"254054","family":"","comment":""},"7":{"family_comment":"","value":"","source_name":"","family":"","comment":""},"8":{"family_comment":"","value":"","family":"","comment":""},"9":{"family_comment":"","value":"","family":"","comment":""},"10":{"family_comment":"","value":"","family":"","comment":""},"11":{"family_comment":"","value":"","family":"","comment":""},"12":{"family_comment":"","value":"","family":"","comment":""},"13":{"family_comment":"","value":"","family":"","comment":""},"14":{"family_comment":"","value":"","family":"","comment":""},"15":{"family_comment":"","value":"","family":"","comment":""},"16":{"family_comment":"","value":"","family":"","comment":""},"17":{"family_comment":"","value":"","family":"","comment":""},"18":{"family_comment":"","value":"","family":"","comment":""},"19":{"family_comment":"","value":"","family":"","comment":""},"20":{"family_comment":"","value":"","family":"17051","comment":""}},"vehicle":{"40":[{"brand_info":"1798 куб. см.","sum":"","brand":"Volkswagen Passat","sum_comment":"","year":"2011","sum_rent_comment":"","sum_rent":""}]},"id":"vulyk_89_16","declaration":{"date":"2015-03-25T00:00:00","notfull":"","notfull_lostpages":"","url":"http://static.declarations.com.ua/declarations/chosen_ones/judges_batch/3019_p_iatkovskyi_volodymyr_ivanovych.pdf"},"liabilities":{"54":{"sum_foreign_comment":"","sum":"","sum_comment":"","sum_foreign":""},"55":{"sum_foreign_comment":"","sum":"","sum_comment":"","sum_foreign":""},"56":{"sum_foreign_comment":"","sum":"","sum_comment":"","sum_unclear":false,"sum_foreign":""},"57":{"sum_foreign_comment":"","sum":"","sum_comment":"","sum_foreign":""},"58":{"sum_foreign_comment":"","sum":"","sum_comment":"","sum_foreign":""},"59":{"sum_foreign_comment":"","sum":"","sum_comment":"","sum_foreign":""},"60":{"sum_foreign_comment":"","sum":"","sum_comment":"","sum_foreign":""},"61":{"sum_foreign_comment":"","sum":"","sum_comment":"","sum_foreign":""},"62":{"sum_foreign_comment":"","sum":"","sum_comment":"","sum_unclear":false,"sum_foreign":""},"63":{"sum_foreign_comment":"","sum":"","sum_comment":"","sum_foreign":""},"64":{"sum_foreign_comment":"","sum":"","sum_comment":"","sum_foreign":""}},"ft_src":"1798 куб. см.\n2011\nVolkswagen Passat\nІвано-Франківська область\n1500\nКоломийський р-н, с. Струпків\n1500\nІвано-Франківська область\nм. Коломия\n2727\nІвано-Франківська область\nм. Коломия\n1000\nм. Коломия,садове товариство 'Мічурінець'\nІвано-Франківська область\nсадове товариство 'Мічурінець', не має данних\nІвано-Франківська область\nм. Коломия,садове товариство 'Мічурінець'\n2014\n254054\n17051\n254054\n17051\n1798 куб. см.\nVolkswagen Passat\n2011\n2014\nІванович\nП'ятковська Л. Я\nПодружжя\nДитина\nП'ятковський О. В\nП'ятковський І. В\nДитина\nП'ятковський Я. В\nДитина\nП'ятковський Володимир Іванович\nВолодимир Іванович П'ятковський\nВолодимир П'ятковський\nП'ятковський Володимир Іванович\nП'ятковський Володимир Іванович\n78200\nІвано-Франківська область\nКоломия\nВолодимир\nП'ятковський\nІвано-Франківська область\nголова коломийського міськрайонного суду івано-франківської області\nЗагальний місцевий суд\n254054\n17051\n254054\n17051\n1500\nІвано-Франківська область\n1500\nКоломийський р-н, с. Струпків\n2727\nІвано-Франківська область\nм. Коломия\n1000\nІвано-Франківська область\nм. Коломия\nм. Коломия,садове товариство 'Мічурінець'\nІвано-Франківська область\nсадове товариство 'Мічурінець', не має данних\nм. Коломия,садове товариство 'Мічурінець'\nІвано-Франківська область\nП'ятковська Л. Я\nПодружжя\nП'ятковський О. В\nДитина\nДитина\nП'ятковський І. В\nП'ятковський Я. В\nДитина\nІвано-Франківська область\nКоломия\n78200\nІванович\nП'ятковський\nголова коломийського міськрайонного суду івано-франківської області\nІвано-Франківська область\nЗагальний місцевий суд\nП'ятковський Володимир Іванович\nП'ятковський Володимир Іванович\nВолодимир Іванович П'ятковський\nВолодимир П'ятковський\nП'ятковський Володимир Іванович\nВолодимир","general":{"inn":"","inn_hidden":true,"last_name":"П'ятковський","post":{"office":"Загальний місцевий суд","region":"Івано-Франківська область","post":"голова коломийського міськрайонного суду івано-франківської області"},"name":"Володимир","full_name":"П'ятковський Володимир Іванович","family_raw":"","addresses":[{"place_district":"","place_address_hidden":true,"place_city":"Коломия","place_address":"78200","place_district_hidden":false,"place_city_type":"Місто","place_city_hidden":false,"place_city_type_hidden":false,"place_hidden":false,"place":"Івано-Франківська область"}],"family":[{"inn":"","inn_hidden":true,"relations":"Подружжя","family_name":"П'ятковська Л. Я","name_hidden":false},{"inn":"","inn_hidden":false,"family_name":"П'ятковський О. В","relations_other":"","relations":"Дитина","name_hidden":false,"name_unclear":false},{"inn":"","inn_hidden":false,"relations":"Дитина","name_unclear":false,"family_name":"П'ятковський І. В"},{"inn":"","family_name":"П'ятковський Я. В","relations":"Дитина"}],"full_name_suggest":{"output":"П'ятковський Володимир Іванович","input":["П'ятковський Володимир Іванович","Володимир Іванович П'ятковський","Володимир П'ятковський"]},"patronymic":"Іванович"},"source":"VULYK","estate":{"23":[{"costs":"","costs_comment":"","address_hidden":false,"region_hidden":false,"space_comment":"","space":"1500","address":"Коломийський р-н, с. Струпків","region":"Івано-Франківська область","address_unclear":false,"costs_rent_comment":"","space_units":"м²","costs_rent":"1500"}],"29":[{"costs_rent":"","region":"Івано-Франківська область","costs_property":"","costs_rent_comment":"","address_hidden":false,"region_hidden":false,"space_comment":"","costs_property_comment":"","space_units":"м²","space":"2727","address":"м. Коломия"},{"costs_rent":"","region":"Івано-Франківська область","costs_property":"","costs_rent_comment":"","space_comment":"","costs_property_comment":"","space_units":"м²","space":"1000","address":"м. Коломия"}],"31":[{"space_hidden":true,"address_hidden":false,"region_hidden":false,"space_comment":"","space":"","address":"м. Коломия,садове товариство 'Мічурінець'","region":"Івано-Франківська область","costs_property":"","costs_rent_comment":"","space_units":"м²","costs_property_comment":"","costs_rent":""}],"32":[{"space_hidden":true,"address_hidden":false,"region_hidden":false,"space_comment":"садове товариство 'Мічурінець', не має данних","space":"","address":"м. Коломия,садове товариство 'Мічурінець'","region":"Івано-Франківська область","costs_property":"","costs_rent_comment":"","space_units":"м²","costs_property_comment":"","costs_rent":""}]},"intro":{"declaration_year":"2014"}}}],"declarations":[{"income":{"5":{"value":"254054","family_hidden":false,"value_hidden":false,"family_comment":"","family":"17051","comment":""},"6":{"family_comment":"","value":"254054","family":"","comment":""},"7":{"family_comment":"","value":"","source_name":"","family":"","comment":""},"8":{"family_comment":"","value":"","family":"","comment":""},"9":{"family_comment":"","value":"","family":"","comment":""},"10":{"family_comment":"","value":"","family":"","comment":""},"11":{"family_comment":"","value":"","family":"","comment":""},"12":{"family_comment":"","value":"","family":"","comment":""},"13":{"family_comment":"","value":"","family":"","comment":""},"14":{"family_comment":"","value":"","family":"","comment":""},"15":{"family_comment":"","value":"","family":"","comment":""},"16":{"family_comment":"","value":"","family":"","comment":""},"17":{"family_comment":"","value":"","family":"","comment":""},"18":{"family_comment":"","value":"","family":"","comment":""},"19":{"family_comment":"","value":"","family":"","comment":""},"20":{"family_comment":"","value":"","family":"17051","comment":""}},"vehicle":{"40":[{"brand_info":"1798 куб. см.","sum":"","brand":"Volkswagen Passat","sum_comment":"","year":"2011","sum_rent_comment":"","sum_rent":""}]},"id":"vulyk_89_16","declaration":{"date":"2015-03-25T00:00:00","notfull":"","notfull_lostpages":"","url":"http://static.declarations.com.ua/declarations/chosen_ones/judges_batch/3019_p_iatkovskyi_volodymyr_ivanovych.pdf"},"liabilities":{"54":{"sum_foreign_comment":"","sum":"","sum_comment":"","sum_foreign":""},"55":{"sum_foreign_comment":"","sum":"","sum_comment":"","sum_foreign":""},"56":{"sum_foreign_comment":"","sum":"","sum_comment":"","sum_unclear":false,"sum_foreign":""},"57":{"sum_foreign_comment":"","sum":"","sum_comment":"","sum_foreign":""},"58":{"sum_foreign_comment":"","sum":"","sum_comment":"","sum_foreign":""},"59":{"sum_foreign_comment":"","sum":"","sum_comment":"","sum_foreign":""},"60":{"sum_foreign_comment":"","sum":"","sum_comment":"","sum_foreign":""},"61":{"sum_foreign_comment":"","sum":"","sum_comment":"","sum_foreign":""},"62":{"sum_foreign_comment":"","sum":"","sum_comment":"","sum_unclear":false,"sum_foreign":""},"63":{"sum_foreign_comment":"","sum":"","sum_comment":"","sum_foreign":""},"64":{"sum_foreign_comment":"","sum":"","sum_comment":"","sum_foreign":""}},"ft_src":"1798 куб. см.\n2011\nVolkswagen Passat\nІвано-Франківська область\n1500\nКоломийський р-н, с. Струпків\n1500\nІвано-Франківська область\nм. Коломия\n2727\nІвано-Франківська область\nм. Коломия\n1000\nм. Коломия,садове товариство 'Мічурінець'\nІвано-Франківська область\nсадове товариство 'Мічурінець', не має данних\nІвано-Франківська область\nм. Коломия,садове товариство 'Мічурінець'\n2014\n254054\n17051\n254054\n17051\n1798 куб. см.\nVolkswagen Passat\n2011\n2014\nІванович\nП'ятковська Л. Я\nПодружжя\nДитина\nП'ятковський О. В\nП'ятковський І. В\nДитина\nП'ятковський Я. В\nДитина\nП'ятковський Володимир Іванович\nВолодимир Іванович П'ятковський\nВолодимир П'ятковський\nП'ятковський Володимир Іванович\nП'ятковський Володимир Іванович\n78200\nІвано-Франківська область\nКоломия\nВолодимир\nП'ятковський\nІвано-Франківська область\nголова коломийського міськрайонного суду івано-франківської області\nЗагальний місцевий суд\n254054\n17051\n254054\n17051\n1500\nІвано-Франківська область\n1500\nКоломийський р-н, с. Струпків\n2727\nІвано-Франківська область\nм. Коломия\n1000\nІвано-Франківська область\nм. Коломия\nм. Коломия,садове товариство 'Мічурінець'\nІвано-Франківська область\nсадове товариство 'Мічурінець', не має данних\nм. Коломия,садове товариство 'Мічурінець'\nІвано-Франківська область\nП'ятковська Л. Я\nПодружжя\nП'ятковський О. В\nДитина\nДитина\nП'ятковський І. В\nП'ятковський Я. В\nДитина\nІвано-Франківська область\nКоломия\n78200\nІванович\nП'ятковський\nголова коломийського міськрайонного суду івано-франківської області\nІвано-Франківська область\nЗагальний місцевий суд\nП'ятковський Володимир Іванович\nП'ятковський Володимир Іванович\nВолодимир Іванович П'ятковський\nВолодимир П'ятковський\nП'ятковський Володимир Іванович\nВолодимир","general":{"inn":"","inn_hidden":true,"last_name":"П'ятковський","post":{"office":"Загальний місцевий суд","region":"Івано-Франківська область","post":"голова коломийського міськрайонного суду івано-франківської області"},"name":"Володимир","full_name":"П'ятковський Володимир Іванович","family_raw":"","addresses":[{"place_district":"","place_address_hidden":true,"place_city":"Коломия","place_address":"78200","place_district_hidden":false,"place_city_type":"Місто","place_city_hidden":false,"place_city_type_hidden":false,"place_hidden":false,"place":"Івано-Франківська область"}],"family":[{"inn":"","inn_hidden":true,"relations":"Подружжя","family_name":"П'ятковська Л. Я","name_hidden":false},{"inn":"","inn_hidden":false,"family_name":"П'ятковський О. В","relations_other":"","relations":"Дитина","name_hidden":false,"name_unclear":false},{"inn":"","inn_hidden":false,"relations":"Дитина","name_unclear":false,"family_name":"П'ятковський І. В"},{"inn":"","family_name":"П'ятковський Я. В","relations":"Дитина"}],"full_name_suggest":{"output":"П'ятковський Володимир Іванович","input":["П'ятковський Володимир Іванович","Володимир Іванович П'ятковський","Володимир П'ятковський"]},"patronymic":"Іванович"},"source":"VULYK","estate":{"23":[{"costs":"","costs_comment":"","address_hidden":false,"region_hidden":false,"space_comment":"","space":"1500","address":"Коломийський р-н, с. Струпків","region":"Івано-Франківська область","address_unclear":false,"costs_rent_comment":"","space_units":"м²","costs_rent":"1500"}],"29":[{"costs_rent":"","region":"Івано-Франківська область","costs_property":"","costs_rent_comment":"","address_hidden":false,"region_hidden":false,"space_comment":"","costs_property_comment":"","space_units":"м²","space":"2727","address":"м. Коломия"},{"costs_rent":"","region":"Івано-Франківська область","costs_property":"","costs_rent_comment":"","space_comment":"","costs_property_comment":"","space_units":"м²","space":"1000","address":"м. Коломия"}],"31":[{"space_hidden":true,"address_hidden":false,"region_hidden":false,"space_comment":"","space":"","address":"м. Коломия,садове товариство 'Мічурінець'","region":"Івано-Франківська область","costs_property":"","costs_rent_comment":"","space_units":"м²","costs_property_comment":"","costs_rent":""}],"32":[{"space_hidden":true,"address_hidden":false,"region_hidden":false,"space_comment":"садове товариство 'Мічурінець', не має данних","space":"","address":"м. Коломия,садове товариство 'Мічурінець'","region":"Івано-Франківська область","costs_property":"","costs_rent_comment":"","space_units":"м²","costs_property_comment":"","costs_rent":""}]},"intro":{"declaration_year":"2014"}}],"declarationsLength":1,"analytics":[{"y":2014,"i":254054,"l":1500,"la":1,"fi":17051,"ffa":1,"fl":3727,"fla":2}]}