{"2010":"","2016":"","Department":"Дніпропетровський апеляційний адміністративний суд","Region":"Дніпропетровська область","Position":"Суддя Дніпропетровського апеляційного адміністративного суду","Name":"Сафронова Світлана Володимирівна","Link":"http://apladm.dp.court.gov.ua/userfiles/Untitled_FR12(9).pdf","Note":"","AdditionalNote":"","field8":"","field9":"","Link 2015":"","Кількість справ":"","Оскаржені":"","Кількість скарг":1,"Кількість дисциплінарних стягнень":"","Клейма":"","Фото":"","Як живе":"","key":"safronova_svitlana_volodimirivna","allDeclarations":[{"provider":"declarations.com.ua","document":{"income":{"5":{"family_comment":"","value":"219629","family":"28500","comment":""},"6":{"family_comment":"","value":"219629","family":"","comment":""},"7":{"family_comment":"","value":"","source_name":"","family":"","comment":""},"8":{"family_comment":"","value":"","family":"","comment":""},"9":{"value":"","comment_unclear":false,"family_comment":"","family":"","comment":"","family_comment_unclear":false},"10":{"family_comment":"","value":"","family":"","comment":""},"11":{"family_comment":"","value":"","family":"","comment":""},"12":{"family_comment":"","value":"","family":"","comment":""},"13":{"family_comment":"","value":"","family":"","comment":""},"14":{"family_comment":"","value":"","family":"","comment":""},"15":{"family_comment":"","value":"","family":"","comment":""},"16":{"family_comment":"","value":"","family":"","comment":""},"17":{"family_comment":"","value":"","family":"28500","comment":""},"18":{"family_comment":"","value":"","family":"","comment":""},"19":{"value":"","family_comment":"","value_unclear":false,"family_unclear":false,"family":"","comment":""},"20":{"value":"","family_comment":"","value_unclear":false,"comment_hidden":false,"family_comment_hidden":false,"family_unclear":false,"family_comment_unclear":false,"comment_unclear":false,"comment":"","family":""}},"vehicle":{"35":[{"brand_info":"2000 куб. см.","sum_rent_comment":"","brand":"Hyundai IX35","sum_comment":"","year":"2011","sum_hidden":false,"brand_info_hidden":false,"brand_info_unclear":false,"year_unclear":false,"sum":"","sum_rent":""}]},"id":"vulyk_106_123","declaration":{"additional_info_text":"","notfull_lostpages":"","date":"2016-03-31T00:00:00","notfull":"","additional_info":"","url":"http://static.declarations.com.ua/declarations/chosen_ones/judges_batch/2262_safronova_svitlana_volodymyrivna.pdf"},"liabilities":{"54":{"sum_foreign_comment":"","sum":"","sum_comment":"","sum_comment_unclear":false,"sum_hidden":false,"sum_comment_hidden":false,"sum_foreign":""},"55":{"sum_foreign_comment":"","sum":"","sum_hidden":false,"sum_comment":"","sum_foreign":""},"56":{"sum_foreign_comment":"","sum":"","sum_comment":"","sum_hidden":false,"sum_comment_hidden":false,"sum_unclear":false,"sum_foreign":""},"57":{"sum_foreign_comment":"","sum":"60305.21","sum_comment":"","sum_hidden":false,"sum_comment_hidden":false,"sum_foreign":""},"58":{"sum_foreign_comment":"","sum":"","sum_comment":"","sum_hidden":false,"sum_comment_hidden":false,"sum_foreign":""},"59":{"sum_foreign_comment":"","sum":"","sum_comment":"","sum_foreign":""},"60":{"sum_foreign_comment":"","sum":"","sum_comment":"","sum_hidden":false,"sum_comment_hidden":false,"sum_foreign":""},"61":{"sum_foreign_comment":"","sum":"","sum_comment":"","sum_foreign":""},"62":{"sum_foreign_comment":"","sum":"","sum_comment":"","sum_comment_hidden":false,"sum_unclear":false,"sum_foreign":""},"63":{"sum_foreign_comment":"","sum":"","sum_comment":"","sum_foreign":""},"64":{"sum_foreign_comment":"","sum":"","sum_comment":"","sum_foreign":""}},"ft_src":"60305.21\nсуддя дніпропетровського апеляційного адміністративного суду\nДніпропетровська область\nАпеляційний адміністративний суд\nСвітлана\nСафронов О. С\nПодружжя\nСафронова М. О\nДитина\nВолодимирівна\nСафронова Світлана Володимирівна\nСвітлана Володимирівна Сафронова\nСвітлана Сафронова\nСафронова Світлана Володимирівна\nСафронова Світлана Володимирівна\nСафронова\nHyundai IX35\n2000 куб. см.\n2011\n106.8\n2015\n219629\n28500\n219629\n28500\n2000 куб. см.\n2011\nHyundai IX35\n106.8\nСафронова Світлана Володимирівна\nСвітлана Володимирівна Сафронова\nСвітлана Сафронова\nСафронова Світлана Володимирівна\nСафронова Світлана Володимирівна\nПодружжя\nСафронов О. С\nДитина\nСафронова М. О\nСвітлана\nСафронова\nДніпропетровська область\nАпеляційний адміністративний суд\nсуддя дніпропетровського апеляційного адміністративного суду\nВолодимирівна\n60305.21\n219629\n28500\n219629\n28500\n2015\n60305.21\nСафронов О. С\nПодружжя\nСафронова М. О\nДитина\nВолодимирівна\nСафронова\nСвітлана\nСафронова Світлана Володимирівна\nСвітлана Володимирівна Сафронова\nСвітлана Сафронова\nСафронова Світлана Володимирівна\nДніпропетровська область\nАпеляційний адміністративний суд\nсуддя дніпропетровського апеляційного адміністративного суду\nСафронова Світлана Володимирівна\n2011\nHyundai IX35\n2000 куб. см.\n28500\n219629\n28500\n219629\n106.8\n2015","general":{"inn":"","name":"Світлана","inn_unclear":false,"family":[{"inn":"","inn_hidden":true,"relations_unclear":false,"relations_hidden":false,"relations_other":"","relations":"Подружжя","name_hidden":true,"family_name":"Сафронов О. С","name_unclear":false},{"inn":"","relations":"Дитина","relations_unclear":false,"family_name":"Сафронова М. О","inn_hidden":false,"relations_other":"","name_hidden":false,"name_unclear":false}],"inn_hidden":true,"family_raw":"","last_name":"Сафронова","post":{"region_unclear":false,"region":"Дніпропетровська область","post":"суддя дніпропетровського апеляційного адміністративного суду","office":"Апеляційний адміністративний суд","office_unclear":false,"post_hidden":false},"full_name":"Сафронова Світлана Володимирівна","addresses":[{"place_district":"","place_city_hidden":true,"place_city":"","place_city_type_hidden":true,"place_district_hidden":true,"place_city_type":"","place_address_hidden":true,"place_address":"","place_hidden":true,"place":""}],"patronymic":"Володимирівна","full_name_suggest":{"output":"Сафронова Світлана Володимирівна","input":["Сафронова Світлана Володимирівна","Світлана Володимирівна Сафронова","Світлана Сафронова"]},"name_unclear":false},"source":"VULYK","estate":{"24":[{"space_unclear":false,"costs":"","costs_comment":"","address_hidden":true,"region_hidden":true,"space_comment":"","space_hidden":false,"space":"106.8","address":"","region":"","costs_rent_comment":"","space_comment_unclear":false,"space_comment_hidden":false,"space_units":"м²","costs_rent":""}]},"intro":{"declaration_year":"2015","isnotdeclaration":""}}},{"provider":"declarations.com.ua","document":{"income":{"5":{"value":"224304","value_unclear":false,"comment_hidden":false,"family_hidden":false,"value_hidden":false,"family_comment":"","family":"26500","comment":""},"6":{"value":"210906","value_unclear":false,"comment_hidden":false,"family_hidden":false,"value_hidden":false,"family_comment":"","family_comment_hidden":false,"comment":"","family":""},"7":{"family_comment":"","value":"","source_name":"","family":"","comment":""},"8":{"family_comment":"","value":"","family":"","comment":""},"9":{"family_comment":"","value":"","family":"","comment":""},"10":{"value":"13398","value_unclear":false,"family_hidden":false,"family_comment":"","family":"","comment":""},"11":{"family_comment":"","value":"","family":"","comment":""},"12":{"family_comment":"","value":"","family":"","comment":""},"13":{"family_comment":"","value":"","family":"","comment":""},"14":{"family_comment":"","value":"","family":"","comment":""},"15":{"family_comment":"","value":"","comment_unclear":false,"family":"","comment":""},"16":{"family_comment":"","value":"","family":"","comment":""},"17":{"family_comment":"","value":"","family":"26500","comment":""},"18":{"family_comment":"","value":"","family":"","comment":""},"19":{"family_comment":"","value":"","family":"","comment":""},"20":{"family_comment":"","value":"","family":"","comment":"","family_comment_hidden":false}},"vehicle":{"35":[{"brand_info":"2000 куб. см.","sum":"","brand":"Hyundai IX35","sum_comment":"","brand_unclear":false,"year":"2011","brand_info_hidden":false,"sum_rent_comment":"","sum_rent":""}]},"id":"vulyk_79_47","declaration":{"date":"2015-03-30T00:00:00","additional_info_text":"","additional_info":"","url":"http://static.declarations.com.ua/declarations/chosen_ones/judges_batch/2052_safronova_svitlana_volodymyrivna.pdf"},"liabilities":{"54":{"sum_foreign_comment":"","sum_comment_hidden":false,"sum":"","sum_comment":"","sum_foreign":""},"55":{"sum_foreign_comment":"","sum":"","sum_comment":"","sum_foreign":""},"56":{"sum_foreign_comment":"","sum":"12000","sum_hidden":false,"sum_comment":"","sum_foreign":""},"57":{"sum_foreign_comment":"","sum":"133027","sum_comment":"","sum_comment_unclear":false,"sum_hidden":false,"sum_comment_hidden":false,"sum_foreign":""},"58":{"sum_foreign_comment":"","sum":"1100","sum_comment":"","sum_comment_unclear":false,"sum_hidden":false,"sum_comment_hidden":false,"sum_unclear":false,"sum_foreign":""},"59":{"sum_foreign_comment":"","sum":"","sum_comment":"","sum_foreign":""},"60":{"sum_foreign_comment":"","sum_comment_hidden":false,"sum":"","sum_comment":"","sum_foreign":""},"61":{"sum_foreign_comment":"","sum":"","sum_comment":"","sum_foreign":""},"62":{"sum_foreign_comment":"","sum":"","sum_comment":"","sum_foreign":""},"63":{"sum_foreign_comment":"","sum":"","sum_comment":"","sum_unclear":false,"sum_foreign":""},"64":{"sum_foreign_comment":"","sum":"","sum_comment":"","sum_unclear":false,"sum_foreign":""}},"ft_src":"133027\n1100\n12000\nсуддя дніпропетровського апеляційного адміністративного суду\nДніпропетровська область\nАпеляційний адміністративний суд\nСвітлана\nПодружжя\nДитина\nВолодимирівна\nСафронова Світлана Володимирівна\nСвітлана Володимирівна Сафронова\nСвітлана Сафронова\nСафронова Світлана Володимирівна\nСафронова Світлана Володимирівна\nСафронова\n2011\nHyundai IX35\n2000 куб. см.\n106.8\n2014\n210906\n13398\n26500\n224304\n26500\nHyundai IX35\n2000 куб. см.\n2011\n106.8\nПодружжя\nДитина\nСафронова Світлана Володимирівна\nСвітлана Володимирівна Сафронова\nСвітлана Сафронова\nСафронова Світлана Володимирівна\nСафронова Світлана Володимирівна\nСвітлана\nСафронова\nАпеляційний адміністративний суд\nДніпропетровська область\nсуддя дніпропетровського апеляційного адміністративного суду\nВолодимирівна\n1100\n133027\n12000\n210906\n26500\n224304\n26500\n13398\n2014\n1100\n133027\n12000\nПодружжя\nДитина\nВолодимирівна\nСафронова\nСвітлана\nСафронова Світлана Володимирівна\nСвітлана Володимирівна Сафронова\nСвітлана Сафронова\nСафронова Світлана Володимирівна\nДніпропетровська область\nАпеляційний адміністративний суд\nсуддя дніпропетровського апеляційного адміністративного суду\nСафронова Світлана Володимирівна\n2011\nHyundai IX35\n2000 куб. см.\n13398\n224304\n26500\n26500\n210906\n106.8\n2014","general":{"inn":"","name":"Світлана","last_name_hidden":false,"family":[{"inn":"","inn_hidden":false,"relations_hidden":false,"family_name":"","relations_other":"","relations":"Подружжя","name_hidden":true,"name_unclear":false},{"inn_hidden":false,"inn":"","name_hidden":false,"family_name":"","relations":"Дитина","name_unclear":false}],"patronymic":"Володимирівна","inn_hidden":true,"family_raw":"","inn_unclear":false,"post":{"post_unclear":false,"post":"суддя дніпропетровського апеляційного адміністративного суду","post_hidden":false,"region":"Дніпропетровська область","region_hidden":false,"office":"Апеляційний адміністративний суд","office_hidden":false,"office_unclear":false},"full_name":"Сафронова Світлана Володимирівна","addresses":[{"place_district":"","place_city_hidden":false,"place_city":"","place_city_type_hidden":false,"place_district_hidden":false,"place_city_type":"","place_address_hidden":false,"place_address":"","place_hidden":true,"place":""}],"last_name":"Сафронова","full_name_suggest":{"output":"Сафронова Світлана Володимирівна","input":["Сафронова Світлана Володимирівна","Світлана Володимирівна Сафронова","Світлана Сафронова"]}},"source":"VULYK","estate":{"24":[{"costs":"","costs_comment":"","costs_hidden":false,"address_hidden":false,"region_hidden":true,"space_comment":"","space":"106.8","address":"","region":"","costs_rent_comment":"","costs_rent_hidden":false,"costs_rent_comment_hidden":false,"space_units":"м²","costs_comment_hidden":false,"costs_rent":""}]},"intro":{"declaration_year":"2014"}}},{"provider":"declarations.com.ua","document":{"income":{"5":{"family_comment":"","value":"221627","family":"25000","comment":""},"6":{"family_comment":"","value":"208986","family":"0","comment":""},"7":{"family_comment":"","value":"0","source_name":"0","family":"0","comment":""},"8":{"family_comment":"","value":"0","family":"0","comment":""},"9":{"family_comment":"","value":"0","family":"0","comment":""},"10":{"family_comment":"","value":"12617","family":"0","comment":""},"11":{"family_comment":"","value":"0","family":"0","comment":""},"12":{"family_comment":"","value":"0","family":"0","comment":""},"13":{"family_comment":"","value":"0","family":"0","comment":""},"14":{"family_comment":"","value":"0","family":"0","comment":""},"15":{"family_comment":"","value":"0","family":"0","comment":""},"16":{"family_comment":"","value":"0","family":"0","comment":""},"17":{"family_comment":"","value":"0","family":"25000","comment":""},"18":{"family_comment":"","value":"0","family":"0","comment":""},"19":{"family_comment":"","value":"0","family":"0","comment":""},"20":{"family_comment":"","value":"24","family":"0","comment":""},"21":[{"cur":"0","country":"0","uah_equal":"0","country_comment":""},{"cur":"0","country":"0","uah_equal":"0","country_comment":""},{"cur":"0","country":"0","uah_equal":"0","country_comment":""},{"cur":"0","country":"0","uah_equal":"0","country_comment":""},{"cur":"0","country":"0","uah_equal":"0","country_comment":""}],"22":[{"cur":"0","country":"0","uah_equal":"0","country_comment":""},{"cur":"0","country":"0","uah_equal":"0","country_comment":""},{"cur":"0","country":"0","uah_equal":"0","country_comment":""},{"cur":"0","country":"0","uah_equal":"0","country_comment":""},{"cur":"0","country":"0","uah_equal":"0","country_comment":""}]},"vehicle":{"35":[{"brand_info":"","sum_rent_comment":"","brand":"Hyundai,ix35","sum_comment":"","year":"2011","brand_hidden":false,"sum":"","sum_rent":""}]},"id":"7909","banks":{"45":[{"sum_foreign_comment":"","sum_units":"UAH","sum_comment":"","sum_foreign_units":"","sum":"","sum_foreign":""},{"sum_foreign_comment":"","sum_units":"USD","sum_comment":"","sum_foreign_units":"","sum":"","sum_foreign":""},{"sum_foreign_comment":"","sum_units":"EUR","sum_comment":"","sum_foreign_units":"","sum":"","sum_foreign":""}],"46":[{"sum_foreign_comment":"","sum_units":"UAH","sum_comment":"","sum_foreign_units":"","sum":"","sum_foreign":""},{"sum_foreign_comment":"","sum_units":"USD","sum_comment":"","sum_foreign_units":"","sum":"","sum_foreign":""},{"sum_foreign_comment":"","sum_units":"EUR","sum_comment":"","sum_foreign_units":"","sum":"","sum_foreign":""}],"47":[{"sum_foreign_comment":"","sum_units":"","sum_comment":"","sum_foreign_units":"","sum":"","sum_foreign":""}],"48":[{"sum_foreign_comment":"","sum_units":"","sum_comment":"","sum_foreign_units":"","sum":"","sum_foreign":""}],"49":[{"sum_foreign_comment":"","sum_units":"","sum_comment":"","sum_foreign_units":"","sum":"","sum_foreign":""}],"50":[{"sum_foreign_comment":"","sum_units":"","sum_comment":"","sum_foreign_units":"","sum":"","sum_foreign":""}],"51":[{"sum_foreign_comment":"","sum_units":"UAH","sum_comment":"","sum_foreign_units":"","sum":"","sum_foreign":""},{"sum_foreign_comment":"","sum_units":"USD","sum_comment":"","sum_foreign_units":"","sum":"","sum_foreign":""},{"sum_foreign_comment":"","sum_units":"EUR","sum_comment":"","sum_foreign_units":"","sum":"","sum_foreign":""}],"52":[{"sum_foreign_comment":"","sum_units":"","sum_comment":"","sum_foreign_units":"","sum":"","sum_foreign":""}],"53":[{"sum_foreign_comment":"","sum_units":"","sum_comment":"","sum_foreign_units":"","sum":"","sum_foreign":""}]},"declaration":{"needs_scancopy_check":false,"additional_info_text":"","notfull_lostpages":"","notfull":"FALSE","additional_info":"FALSE","url":"http://static.declarations.com.ua/declarations/sudy/apeliatsiini_administratyvni_sudy/dnipropetrovskyi/safronova_declaration.pdf"},"liabilities":{"54":{"sum_foreign_comment":"","sum":"","sum_comment":"","sum_foreign":""},"55":{"sum_foreign_comment":"","sum_units":"","sum_comment":"","sum_foreign_units":"","sum":"","sum_foreign":""},"56":{"sum_foreign_comment":"","sum":"","sum_comment":"","sum_foreign":"12000"},"57":{"sum_foreign_comment":"","sum":"","sum_comment":"","sum_foreign":""},"58":{"sum_foreign_comment":"","sum":"","sum_comment":"","sum_foreign":""},"59":{"sum_foreign_comment":"","sum":"","sum_comment":"","sum_foreign":""},"60":{"sum_foreign_comment":"","sum":"","sum_comment":"","sum_foreign":""},"61":{"sum_foreign_comment":"","sum_units":"","sum_comment":"","sum_foreign_units":"","sum":"","sum_foreign":""},"62":{"sum_foreign_comment":"","sum":"","sum_comment":"","sum_foreign":""},"63":{"sum_foreign_comment":"","sum_units":"","sum_comment":"","sum":"","sum_foreign":""},"64":{"sum_foreign_comment":"","sum_units":"","sum_comment":"","sum":"","sum_foreign":""}},"estate":{"23":[{"costs_rent":"","location_raw":"","region":"","costs":"","costs_rent_comment":"","costs_comment":"","space_comment":"","space_units":"","space":"","address":""},{"costs_rent":"","location_raw":"","region":"","costs":"","costs_rent_comment":"","costs_comment":"","space_comment":"","space_units":"","space":"","address":""},{"costs_rent":"","location_raw":"","region":"","costs":"","costs_rent_comment":"","costs_comment":"","space_comment":"","space_units":"","space":"","address":""}],"24":[{"costs_rent":"","location_raw":"приховано","region":"","costs":"","costs_rent_comment":"","costs_comment":"","space_comment":"","space_units":"","space":"106,8","address":""}]},"general":{"name_hidden":false,"name":"Світлана","patronymic_unclear":false,"last_name_hidden":false,"addresses_raw":"приховано","post_raw":"Суддя Дніпропетровського апеляційного адміністративного суду","patronymic":"Володимирівна","inn":"","family_raw":"Чоловік Сафронов О.С., 25.07.1964;дочка Сафронова М.О., 10.01.2005","last_name":"Сафронова","post":{"office":"Апеляційний адміністративний суд","region":"Дніпропетровська область","post":"Суддя"},"addresses_raw_hidden":true,"last_name_unclear":false,"full_name":"Сафронова Світлана Володимирівна","patronymic_hidden":false,"full_name_suggest":{"output":"Сафронова Світлана Володимирівна","input":["Сафронова Світлана Володимирівна","Світлана Володимирівна Сафронова","Світлана Сафронова"]},"name_unclear":false},"ft_src":"12000\nFALSE\nFALSE\n12617\n24\n25000\n221627\n208986\n25000\nHyundai,ix35\n2011\nHyundai,ix35\n2011\n106,8\nFALSE\nFALSE\nFALSE\n2013\n208986\n12617\n25000\n221627\n25000\n24\nHyundai,ix35\n2011\nFALSE\nFALSE\n106,8\nСуддя Дніпропетровського апеляційного адміністративного суду\nЧоловік Сафронов О.С., 25.07.1964;дочка Сафронова М.О., 10.01.2005\nСафронова\nСафронова Світлана Володимирівна\nСвітлана Володимирівна Сафронова\nСвітлана Сафронова\nСафронова Світлана Володимирівна\nСвітлана\nСафронова Світлана Володимирівна\nАпеляційний адміністративний суд\nСуддя\nДніпропетровська область\nВолодимирівна\n12000\n208986\n25000\n24\n221627\n25000\n12617\n2013\nFALSE\n12000\nСафронова\nВолодимирівна\nЧоловік Сафронов О.С., 25.07.1964;дочка Сафронова М.О., 10.01.2005\nСафронова Світлана Володимирівна\nСвітлана Володимирівна Сафронова\nСвітлана Сафронова\nСафронова Світлана Володимирівна\nСвітлана\nСуддя Дніпропетровського апеляційного адміністративного суду\nСуддя\nДніпропетровська область\nАпеляційний адміністративний суд\nСафронова Світлана Володимирівна\n106,8\nСуддя\nДніпропетровська область\nАпеляційний адміністративний суд\nСуддя Дніпропетровського апеляційного адміністративного суду\nСвітлана\nВолодимирівна\nЧоловік Сафронов О.С., 25.07.1964;дочка Сафронова М.О., 10.01.2005\nСафронова\nСафронова Світлана Володимирівна\nСафронова Світлана Володимирівна\nСвітлана Володимирівна Сафронова\nСвітлана Сафронова\nСафронова Світлана Володимирівна\nFALSE\n2013","intro":{"declaration_year":"2013","isnotdeclaration":"FALSE"}}},{"provider":"public-api.nazk.gov.ua","document":{"step_0":{"declarationType":"1","declarationYear1":"2015"},"step_1":{"street":"[Конфіденційна інформація]","country":"1","cityPath":"[Конфіденційна інформація]","cityType":"[Конфіденційна інформація]","lastname":"Сафронова","postCode":"[Конфіденційна інформація]","postType":"","workPost":"суддя","buildType":"гуртожиток","firstname":"Світлана","workPlace":"Дніпропетровський апеляційний адміністративний суд","middlename":"Володимирівна","streetType":"[Конфіденційна інформація]","changedName":false,"countryPath":"","eng_postCode":"","postCategory":"","actual_street":"[Конфіденційна інформація]","actual_cityPath":"[Конфіденційна інформація]","actual_cityType":"[Конфіденційна інформація]","actual_postCode":"[Конфіденційна інформація]","actual_buildType":"житловий будинок","actual_streetType":"[Конфіденційна інформація]","previous_lastname":"","corruptionAffected":"Ні","eng_actualPostCode":"[Конфіденційна інформація]","previous_firstname":"","previous_middlename":"","responsiblePosition":"Суддя суду загальної юрисдикції, суддя Конституційного Суду України","sameRegLivingAddress":"[Конфіденційна інформація]","eng_sameRegLivingAddress":"[Конфіденційна інформація]"},"step_2":{"1475824191206":{"lastname":"Сафронов","firstname":"Олег","middlename":"Сергійович","changedName":false,"citizenship":"1","eng_lastname":"","no_taxNumber":false,"eng_firstname":"","eng_middlename":"","isNotApplicable":"","subjectRelation":"чоловік","previous_lastname":"","previous_firstname":"","previous_middlename":"","previous_eng_lastname":"","previous_eng_firstname":"","previous_eng_middlename":""},"1475824237237":{"lastname":"Сафронова","firstname":"Марія","middlename":"Олегівна","changedName":false,"citizenship":"1","eng_lastname":"","no_taxNumber":false,"eng_firstname":"","eng_middlename":"","isNotApplicable":"","subjectRelation":"дочка","previous_lastname":"","previous_firstname":"","previous_middlename":"","previous_eng_lastname":"","previous_eng_firstname":"","previous_eng_middlename":""}},"step_3":{"1475824314991":{"person":"1","rights":{"1":{"citizen":"","ua_city":"","ua_street":"[Конфіденційна інформація]","ua_lastname":"","ua_postCode":"","eng_lastname":"","eng_postCode":"","rightBelongs":"1","ua_buildType":"","ua_firstname":"","ukr_lastname":"","eng_firstname":"","ownershipType":"Спільна власність","ua_middlename":"","ua_streetType":"[Конфіденційна інформація]","ukr_firstname":"","eng_middlename":"","otherOwnership":"","ukr_middlename":"","rights_cityPath":"","ua_company_name":"","eng_company_name":"","ukr_company_name":"","percent-ownership":"75","ua_street_extendedstatus":"","ua_houseNum_extendedstatus":"","ua_postCode_extendedstatus":"","eng_postCode_extendedstatus":"","ua_middlename_extendedstatus":"","eng_middlename_extendedstatus":"","ukr_middlename_extendedstatus":"","ua_housePartNum_extendedstatus":"","ua_apartmentsNum_extendedstatus":""},"1475825433243":{"citizen":"Громадянин України","ua_city":"Кам'янське / Дніпропетровська Область/м.Дніпро / Україна","ua_street":"[Конфіденційна інформація]","ua_lastname":"Сафронов","ua_postCode":"51931","eng_lastname":"","eng_postCode":"","rightBelongs":"j","ua_buildType":"багатоквартирний будинок","ua_firstname":"Гліб","ukr_lastname":"","eng_firstname":"","ownershipType":"Спільна власність","ua_middlename":"Олегович","ua_streetType":"[Конфіденційна інформація]","ukr_firstname":"","eng_middlename":"","otherOwnership":"","ukr_middlename":"","rights_cityPath":"1.2.12.1.4","ua_company_name":"","eng_company_name":"","ukr_company_name":"","percent-ownership":"25","ua_street_extendedstatus":"","ua_houseNum_extendedstatus":"","ua_postCode_extendedstatus":"","eng_postCode_extendedstatus":"","ua_middlename_extendedstatus":"","eng_middlename_extendedstatus":"","ukr_middlename_extendedstatus":"","ua_housePartNum_extendedstatus":"","ua_apartmentsNum_extendedstatus":""}},"country":"1","cityPath":"[Конфіденційна інформація]","costDate":"21587","postCode":"[Конфіденційна інформація]","totalArea":"180","ua_street":"[Конфіденційна інформація]","objectType":"Житловий будинок","owningDate":"15.01.1998","ua_cityType":"Кам'янське / Дніпропетровська Область/м.Дніпро / Україна","ua_postCode":"51927","ua_buildType":"житловий будинок","ua_streetType":"[Конфіденційна інформація]","costAssessment":"","otherObjectType":"","costAssessment_extendedstatus":"2"}},"step_4":[],"step_5":[],"step_6":{"1475825792493":{"brand":"HYUNDAI","model":"IX35","person":"1","rights":{"1":{"citizen":"","ua_city":"","ua_street":"[Конфіденційна інформація]","ua_lastname":"","ua_postCode":"","eng_lastname":"","eng_postCode":"","rightBelongs":"1","ua_buildType":"","ua_firstname":"","ukr_lastname":"","eng_firstname":"","ownershipType":"Власність","ua_middlename":"","ua_streetType":"[Конфіденційна інформація]","ukr_firstname":"","eng_middlename":"","otherOwnership":"","ukr_middlename":"","rights_cityPath":"","ua_company_name":"","eng_company_name":"","ukr_company_name":"","percent-ownership":"","ua_street_extendedstatus":"","ua_houseNum_extendedstatus":"","ua_postCode_extendedstatus":"","eng_postCode_extendedstatus":"","ua_middlename_extendedstatus":"","eng_middlename_extendedstatus":"","ukr_middlename_extendedstatus":"","ua_housePartNum_extendedstatus":"","ua_apartmentsNum_extendedstatus":""}},"costDate":"209370","objectType":"Автомобіль легковий","owningDate":"18.05.2011","typeProperty":"","graduationYear":"2011","otherTypeProperty":""}},"step_7":[],"step_8":[],"step_9":[],"step_10":[],"step_11":{"1475826076288":{"person":"1","rights":{"1":{"citizen":"","ua_city":"","ua_street":"[Конфіденційна інформація]","ua_lastname":"","ua_postCode":"","eng_lastname":"","eng_postCode":"","rightBelongs":"1","ua_buildType":"","ua_firstname":"","ukr_lastname":"","eng_firstname":"","ownershipType":"Власність","ua_middlename":"","ua_streetType":"[Конфіденційна інформація]","ukr_firstname":"","eng_middlename":"","otherOwnership":"","ukr_middlename":"","rights_cityPath":"","ua_company_name":"","eng_company_name":"","ukr_company_name":"","percent-ownership":"","ua_street_extendedstatus":"","ua_houseNum_extendedstatus":"","ua_postCode_extendedstatus":"","eng_postCode_extendedstatus":"","ua_middlename_extendedstatus":"","eng_middlename_extendedstatus":"","ukr_middlename_extendedstatus":"","ua_housePartNum_extendedstatus":"","ua_apartmentsNum_extendedstatus":""}},"objectType":"Заробітна плата отримана за основним місцем роботи","sizeIncome":"219629","incomeSource":"j","source_citizen":"Юридична особа, зареєстрована в Україні","otherObjectType":"","source_ua_lastname":"","source_eng_lastname":"","source_ua_firstname":"","source_ukr_lastname":"","source_eng_firstname":"","source_ua_middlename":"","source_ukr_firstname":"","source_eng_middlename":"","source_ukr_middlename":"","source_ua_company_name":"Дніпропетровський апеляційний адміністративний суд","source_eng_company_name":"","source_ukr_company_name":"","source_ua_sameRegLivingAddress":"","source_eng_sameRegLivingAddress":""},"1475826182071":{"person":"1475824191206","rights":{"1475824191206":{"citizen":"","ua_city":"","ua_street":"[Конфіденційна інформація]","ua_lastname":"","ua_postCode":"","eng_lastname":"","eng_postCode":"","rightBelongs":"1475824191206","ua_buildType":"","ua_firstname":"","ukr_lastname":"","eng_firstname":"","ownershipType":"Власність","ua_middlename":"","ua_streetType":"[Конфіденційна інформація]","ukr_firstname":"","eng_middlename":"","otherOwnership":"","ukr_middlename":"","rights_cityPath":"","ua_company_name":"","eng_company_name":"","ukr_company_name":"","percent-ownership":"","ua_street_extendedstatus":"","ua_houseNum_extendedstatus":"","ua_postCode_extendedstatus":"","eng_postCode_extendedstatus":"","ua_middlename_extendedstatus":"","eng_middlename_extendedstatus":"","ukr_middlename_extendedstatus":"","ua_housePartNum_extendedstatus":"","ua_apartmentsNum_extendedstatus":""}},"objectType":"Дохід від зайняття незалежною професійною діяльністю","sizeIncome":"28500","incomeSource":"1475824191206","source_citizen":"","otherObjectType":"","source_ua_lastname":"","source_eng_lastname":"","source_ua_firstname":"","source_ukr_lastname":"","source_eng_firstname":"","source_ua_middlename":"","source_ukr_firstname":"","source_eng_middlename":"","source_ukr_middlename":"","source_ua_company_name":"","source_eng_company_name":"","source_ukr_company_name":"","source_ua_sameRegLivingAddress":"","source_eng_sameRegLivingAddress":""}},"step_12":[],"step_13":{"1475826328768":{"person":"1","currency":"UAH","guarantor":[],"dateOrigin":"18.05.2011","objectType":"Розмір сплачених коштів в рахунок основної суми позики (кредиту)","margin-emitent":"j","sizeObligation":"60306","emitent_citizen":"Юридична особа, зареєстрована в Україні","otherObjectType":"","guarantor_realty":{"1475826691912":{"realty_cost":"209370","realty_rights":"1","realty_country":"1","realty_cityPath":"","realty_postCode":"","realty_ua_street":"Тургенєва","realty_objectType":"Автомобіль легковий","realty_rights_type":"","realty_ua_cityType":"Кам'янське / Дніпропетровська Область/м.Дніпро / Україна","realty_ua_postCode":"51927","realty_ua_buildType":"житловий будинок","realty_ua_streetType":"вулиця","guarantor_realty_exist":true,"realty_otherObjectType":"","realty_rights_cityPath":"1.2.12.1.4","realty_rights_ua_lastname":"","realty_rights_eng_lastname":"","realty_rights_ua_firstname":"","realty_rights_ukr_lastname":"","realty_rights_eng_firstname":"","realty_rights_ua_middlename":"","realty_rights_ukr_firstname":"","realty_rights_eng_middlename":"","realty_rights_ukr_middlename":"","realty_rights_ua_company_name":"","realty_rights_eng_company_name":"","realty_rights_ukr_company_name":"","realty_rights_ua_sameRegLivingAddress":"","realty_rights_eng_sameRegLivingAddress":""}},"ownerThirdPerson":"","emitent_ua_lastname":"","emitent_eng_lastname":"","emitent_ua_firstname":"","emitent_ukr_lastname":"","emitent_eng_firstname":"","emitent_ua_middlename":"","emitent_ukr_firstname":"","ownerThirdPersonThing":"","emitent_eng_middlename":"","emitent_ukr_middlename":"","emitent_ua_company_name":"ПАТ КБ \"ПРАВЕКС-БАНК\"","emitent_eng_company_name":"","emitent_ukr_company_name":"","emitent_ua_sameRegLivingAddress":"","emitent_eng_sameRegLivingAddress":""}},"step_14":[],"step_15":[],"step_16":{"org":[],"part_org":[]},"id":"f3d2dee2-8247-4a37-b5ed-d0d7532d41ca"}}],"declarations":[{"income":{"5":{"family_comment":"","value":"219629","family":"28500","comment":""},"6":{"family_comment":"","value":"219629","family":"","comment":""},"7":{"family_comment":"","value":"","source_name":"","family":"","comment":""},"8":{"family_comment":"","value":"","family":"","comment":""},"9":{"value":"","comment_unclear":false,"family_comment":"","family":"","comment":"","family_comment_unclear":false},"10":{"family_comment":"","value":"","family":"","comment":""},"11":{"family_comment":"","value":"","family":"","comment":""},"12":{"family_comment":"","value":"","family":"","comment":""},"13":{"family_comment":"","value":"","family":"","comment":""},"14":{"family_comment":"","value":"","family":"","comment":""},"15":{"family_comment":"","value":"","family":"","comment":""},"16":{"family_comment":"","value":"","family":"","comment":""},"17":{"family_comment":"","value":"","family":"28500","comment":""},"18":{"family_comment":"","value":"","family":"","comment":""},"19":{"value":"","family_comment":"","value_unclear":false,"family_unclear":false,"family":"","comment":""},"20":{"value":"","family_comment":"","value_unclear":false,"comment_hidden":false,"family_comment_hidden":false,"family_unclear":false,"family_comment_unclear":false,"comment_unclear":false,"comment":"","family":""}},"vehicle":{"35":[{"brand_info":"2000 куб. см.","sum_rent_comment":"","brand":"Hyundai IX35","sum_comment":"","year":"2011","sum_hidden":false,"brand_info_hidden":false,"brand_info_unclear":false,"year_unclear":false,"sum":"","sum_rent":""}]},"id":"vulyk_106_123","declaration":{"additional_info_text":"","notfull_lostpages":"","date":"2016-03-31T00:00:00","notfull":"","additional_info":"","url":"http://static.declarations.com.ua/declarations/chosen_ones/judges_batch/2262_safronova_svitlana_volodymyrivna.pdf"},"liabilities":{"54":{"sum_foreign_comment":"","sum":"","sum_comment":"","sum_comment_unclear":false,"sum_hidden":false,"sum_comment_hidden":false,"sum_foreign":""},"55":{"sum_foreign_comment":"","sum":"","sum_hidden":false,"sum_comment":"","sum_foreign":""},"56":{"sum_foreign_comment":"","sum":"","sum_comment":"","sum_hidden":false,"sum_comment_hidden":false,"sum_unclear":false,"sum_foreign":""},"57":{"sum_foreign_comment":"","sum":"60305.21","sum_comment":"","sum_hidden":false,"sum_comment_hidden":false,"sum_foreign":""},"58":{"sum_foreign_comment":"","sum":"","sum_comment":"","sum_hidden":false,"sum_comment_hidden":false,"sum_foreign":""},"59":{"sum_foreign_comment":"","sum":"","sum_comment":"","sum_foreign":""},"60":{"sum_foreign_comment":"","sum":"","sum_comment":"","sum_hidden":false,"sum_comment_hidden":false,"sum_foreign":""},"61":{"sum_foreign_comment":"","sum":"","sum_comment":"","sum_foreign":""},"62":{"sum_foreign_comment":"","sum":"","sum_comment":"","sum_comment_hidden":false,"sum_unclear":false,"sum_foreign":""},"63":{"sum_foreign_comment":"","sum":"","sum_comment":"","sum_foreign":""},"64":{"sum_foreign_comment":"","sum":"","sum_comment":"","sum_foreign":""}},"ft_src":"60305.21\nсуддя дніпропетровського апеляційного адміністративного суду\nДніпропетровська область\nАпеляційний адміністративний суд\nСвітлана\nСафронов О. С\nПодружжя\nСафронова М. О\nДитина\nВолодимирівна\nСафронова Світлана Володимирівна\nСвітлана Володимирівна Сафронова\nСвітлана Сафронова\nСафронова Світлана Володимирівна\nСафронова Світлана Володимирівна\nСафронова\nHyundai IX35\n2000 куб. см.\n2011\n106.8\n2015\n219629\n28500\n219629\n28500\n2000 куб. см.\n2011\nHyundai IX35\n106.8\nСафронова Світлана Володимирівна\nСвітлана Володимирівна Сафронова\nСвітлана Сафронова\nСафронова Світлана Володимирівна\nСафронова Світлана Володимирівна\nПодружжя\nСафронов О. С\nДитина\nСафронова М. О\nСвітлана\nСафронова\nДніпропетровська область\nАпеляційний адміністративний суд\nсуддя дніпропетровського апеляційного адміністративного суду\nВолодимирівна\n60305.21\n219629\n28500\n219629\n28500\n2015\n60305.21\nСафронов О. С\nПодружжя\nСафронова М. О\nДитина\nВолодимирівна\nСафронова\nСвітлана\nСафронова Світлана Володимирівна\nСвітлана Володимирівна Сафронова\nСвітлана Сафронова\nСафронова Світлана Володимирівна\nДніпропетровська область\nАпеляційний адміністративний суд\nсуддя дніпропетровського апеляційного адміністративного суду\nСафронова Світлана Володимирівна\n2011\nHyundai IX35\n2000 куб. см.\n28500\n219629\n28500\n219629\n106.8\n2015","general":{"inn":"","name":"Світлана","inn_unclear":false,"family":[{"inn":"","inn_hidden":true,"relations_unclear":false,"relations_hidden":false,"relations_other":"","relations":"Подружжя","name_hidden":true,"family_name":"Сафронов О. С","name_unclear":false},{"inn":"","relations":"Дитина","relations_unclear":false,"family_name":"Сафронова М. О","inn_hidden":false,"relations_other":"","name_hidden":false,"name_unclear":false}],"inn_hidden":true,"family_raw":"","last_name":"Сафронова","post":{"region_unclear":false,"region":"Дніпропетровська область","post":"суддя дніпропетровського апеляційного адміністративного суду","office":"Апеляційний адміністративний суд","office_unclear":false,"post_hidden":false},"full_name":"Сафронова Світлана Володимирівна","addresses":[{"place_district":"","place_city_hidden":true,"place_city":"","place_city_type_hidden":true,"place_district_hidden":true,"place_city_type":"","place_address_hidden":true,"place_address":"","place_hidden":true,"place":""}],"patronymic":"Володимирівна","full_name_suggest":{"output":"Сафронова Світлана Володимирівна","input":["Сафронова Світлана Володимирівна","Світлана Володимирівна Сафронова","Світлана Сафронова"]},"name_unclear":false},"source":"VULYK","estate":{"24":[{"space_unclear":false,"costs":"","costs_comment":"","address_hidden":true,"region_hidden":true,"space_comment":"","space_hidden":false,"space":"106.8","address":"","region":"","costs_rent_comment":"","space_comment_unclear":false,"space_comment_hidden":false,"space_units":"м²","costs_rent":""}]},"intro":{"declaration_year":"2015","isnotdeclaration":""}},{"income":{"5":{"value":"224304","value_unclear":false,"comment_hidden":false,"family_hidden":false,"value_hidden":false,"family_comment":"","family":"26500","comment":""},"6":{"value":"210906","value_unclear":false,"comment_hidden":false,"family_hidden":false,"value_hidden":false,"family_comment":"","family_comment_hidden":false,"comment":"","family":""},"7":{"family_comment":"","value":"","source_name":"","family":"","comment":""},"8":{"family_comment":"","value":"","family":"","comment":""},"9":{"family_comment":"","value":"","family":"","comment":""},"10":{"value":"13398","value_unclear":false,"family_hidden":false,"family_comment":"","family":"","comment":""},"11":{"family_comment":"","value":"","family":"","comment":""},"12":{"family_comment":"","value":"","family":"","comment":""},"13":{"family_comment":"","value":"","family":"","comment":""},"14":{"family_comment":"","value":"","family":"","comment":""},"15":{"family_comment":"","value":"","comment_unclear":false,"family":"","comment":""},"16":{"family_comment":"","value":"","family":"","comment":""},"17":{"family_comment":"","value":"","family":"26500","comment":""},"18":{"family_comment":"","value":"","family":"","comment":""},"19":{"family_comment":"","value":"","family":"","comment":""},"20":{"family_comment":"","value":"","family":"","comment":"","family_comment_hidden":false}},"vehicle":{"35":[{"brand_info":"2000 куб. см.","sum":"","brand":"Hyundai IX35","sum_comment":"","brand_unclear":false,"year":"2011","brand_info_hidden":false,"sum_rent_comment":"","sum_rent":""}]},"id":"vulyk_79_47","declaration":{"date":"2015-03-30T00:00:00","additional_info_text":"","additional_info":"","url":"http://static.declarations.com.ua/declarations/chosen_ones/judges_batch/2052_safronova_svitlana_volodymyrivna.pdf"},"liabilities":{"54":{"sum_foreign_comment":"","sum_comment_hidden":false,"sum":"","sum_comment":"","sum_foreign":""},"55":{"sum_foreign_comment":"","sum":"","sum_comment":"","sum_foreign":""},"56":{"sum_foreign_comment":"","sum":"12000","sum_hidden":false,"sum_comment":"","sum_foreign":""},"57":{"sum_foreign_comment":"","sum":"133027","sum_comment":"","sum_comment_unclear":false,"sum_hidden":false,"sum_comment_hidden":false,"sum_foreign":""},"58":{"sum_foreign_comment":"","sum":"1100","sum_comment":"","sum_comment_unclear":false,"sum_hidden":false,"sum_comment_hidden":false,"sum_unclear":false,"sum_foreign":""},"59":{"sum_foreign_comment":"","sum":"","sum_comment":"","sum_foreign":""},"60":{"sum_foreign_comment":"","sum_comment_hidden":false,"sum":"","sum_comment":"","sum_foreign":""},"61":{"sum_foreign_comment":"","sum":"","sum_comment":"","sum_foreign":""},"62":{"sum_foreign_comment":"","sum":"","sum_comment":"","sum_foreign":""},"63":{"sum_foreign_comment":"","sum":"","sum_comment":"","sum_unclear":false,"sum_foreign":""},"64":{"sum_foreign_comment":"","sum":"","sum_comment":"","sum_unclear":false,"sum_foreign":""}},"ft_src":"133027\n1100\n12000\nсуддя дніпропетровського апеляційного адміністративного суду\nДніпропетровська область\nАпеляційний адміністративний суд\nСвітлана\nПодружжя\nДитина\nВолодимирівна\nСафронова Світлана Володимирівна\nСвітлана Володимирівна Сафронова\nСвітлана Сафронова\nСафронова Світлана Володимирівна\nСафронова Світлана Володимирівна\nСафронова\n2011\nHyundai IX35\n2000 куб. см.\n106.8\n2014\n210906\n13398\n26500\n224304\n26500\nHyundai IX35\n2000 куб. см.\n2011\n106.8\nПодружжя\nДитина\nСафронова Світлана Володимирівна\nСвітлана Володимирівна Сафронова\nСвітлана Сафронова\nСафронова Світлана Володимирівна\nСафронова Світлана Володимирівна\nСвітлана\nСафронова\nАпеляційний адміністративний суд\nДніпропетровська область\nсуддя дніпропетровського апеляційного адміністративного суду\nВолодимирівна\n1100\n133027\n12000\n210906\n26500\n224304\n26500\n13398\n2014\n1100\n133027\n12000\nПодружжя\nДитина\nВолодимирівна\nСафронова\nСвітлана\nСафронова Світлана Володимирівна\nСвітлана Володимирівна Сафронова\nСвітлана Сафронова\nСафронова Світлана Володимирівна\nДніпропетровська область\nАпеляційний адміністративний суд\nсуддя дніпропетровського апеляційного адміністративного суду\nСафронова Світлана Володимирівна\n2011\nHyundai IX35\n2000 куб. см.\n13398\n224304\n26500\n26500\n210906\n106.8\n2014","general":{"inn":"","name":"Світлана","last_name_hidden":false,"family":[{"inn":"","inn_hidden":false,"relations_hidden":false,"family_name":"","relations_other":"","relations":"Подружжя","name_hidden":true,"name_unclear":false},{"inn_hidden":false,"inn":"","name_hidden":false,"family_name":"","relations":"Дитина","name_unclear":false}],"patronymic":"Володимирівна","inn_hidden":true,"family_raw":"","inn_unclear":false,"post":{"post_unclear":false,"post":"суддя дніпропетровського апеляційного адміністративного суду","post_hidden":false,"region":"Дніпропетровська область","region_hidden":false,"office":"Апеляційний адміністративний суд","office_hidden":false,"office_unclear":false},"full_name":"Сафронова Світлана Володимирівна","addresses":[{"place_district":"","place_city_hidden":false,"place_city":"","place_city_type_hidden":false,"place_district_hidden":false,"place_city_type":"","place_address_hidden":false,"place_address":"","place_hidden":true,"place":""}],"last_name":"Сафронова","full_name_suggest":{"output":"Сафронова Світлана Володимирівна","input":["Сафронова Світлана Володимирівна","Світлана Володимирівна Сафронова","Світлана Сафронова"]}},"source":"VULYK","estate":{"24":[{"costs":"","costs_comment":"","costs_hidden":false,"address_hidden":false,"region_hidden":true,"space_comment":"","space":"106.8","address":"","region":"","costs_rent_comment":"","costs_rent_hidden":false,"costs_rent_comment_hidden":false,"space_units":"м²","costs_comment_hidden":false,"costs_rent":""}]},"intro":{"declaration_year":"2014"}},{"income":{"5":{"family_comment":"","value":"221627","family":"25000","comment":""},"6":{"family_comment":"","value":"208986","family":"0","comment":""},"7":{"family_comment":"","value":"0","source_name":"0","family":"0","comment":""},"8":{"family_comment":"","value":"0","family":"0","comment":""},"9":{"family_comment":"","value":"0","family":"0","comment":""},"10":{"family_comment":"","value":"12617","family":"0","comment":""},"11":{"family_comment":"","value":"0","family":"0","comment":""},"12":{"family_comment":"","value":"0","family":"0","comment":""},"13":{"family_comment":"","value":"0","family":"0","comment":""},"14":{"family_comment":"","value":"0","family":"0","comment":""},"15":{"family_comment":"","value":"0","family":"0","comment":""},"16":{"family_comment":"","value":"0","family":"0","comment":""},"17":{"family_comment":"","value":"0","family":"25000","comment":""},"18":{"family_comment":"","value":"0","family":"0","comment":""},"19":{"family_comment":"","value":"0","family":"0","comment":""},"20":{"family_comment":"","value":"24","family":"0","comment":""},"21":[{"cur":"0","country":"0","uah_equal":"0","country_comment":""},{"cur":"0","country":"0","uah_equal":"0","country_comment":""},{"cur":"0","country":"0","uah_equal":"0","country_comment":""},{"cur":"0","country":"0","uah_equal":"0","country_comment":""},{"cur":"0","country":"0","uah_equal":"0","country_comment":""}],"22":[{"cur":"0","country":"0","uah_equal":"0","country_comment":""},{"cur":"0","country":"0","uah_equal":"0","country_comment":""},{"cur":"0","country":"0","uah_equal":"0","country_comment":""},{"cur":"0","country":"0","uah_equal":"0","country_comment":""},{"cur":"0","country":"0","uah_equal":"0","country_comment":""}]},"vehicle":{"35":[{"brand_info":"","sum_rent_comment":"","brand":"Hyundai,ix35","sum_comment":"","year":"2011","brand_hidden":false,"sum":"","sum_rent":""}]},"id":"7909","banks":{"45":[{"sum_foreign_comment":"","sum_units":"UAH","sum_comment":"","sum_foreign_units":"","sum":"","sum_foreign":""},{"sum_foreign_comment":"","sum_units":"USD","sum_comment":"","sum_foreign_units":"","sum":"","sum_foreign":""},{"sum_foreign_comment":"","sum_units":"EUR","sum_comment":"","sum_foreign_units":"","sum":"","sum_foreign":""}],"46":[{"sum_foreign_comment":"","sum_units":"UAH","sum_comment":"","sum_foreign_units":"","sum":"","sum_foreign":""},{"sum_foreign_comment":"","sum_units":"USD","sum_comment":"","sum_foreign_units":"","sum":"","sum_foreign":""},{"sum_foreign_comment":"","sum_units":"EUR","sum_comment":"","sum_foreign_units":"","sum":"","sum_foreign":""}],"47":[{"sum_foreign_comment":"","sum_units":"","sum_comment":"","sum_foreign_units":"","sum":"","sum_foreign":""}],"48":[{"sum_foreign_comment":"","sum_units":"","sum_comment":"","sum_foreign_units":"","sum":"","sum_foreign":""}],"49":[{"sum_foreign_comment":"","sum_units":"","sum_comment":"","sum_foreign_units":"","sum":"","sum_foreign":""}],"50":[{"sum_foreign_comment":"","sum_units":"","sum_comment":"","sum_foreign_units":"","sum":"","sum_foreign":""}],"51":[{"sum_foreign_comment":"","sum_units":"UAH","sum_comment":"","sum_foreign_units":"","sum":"","sum_foreign":""},{"sum_foreign_comment":"","sum_units":"USD","sum_comment":"","sum_foreign_units":"","sum":"","sum_foreign":""},{"sum_foreign_comment":"","sum_units":"EUR","sum_comment":"","sum_foreign_units":"","sum":"","sum_foreign":""}],"52":[{"sum_foreign_comment":"","sum_units":"","sum_comment":"","sum_foreign_units":"","sum":"","sum_foreign":""}],"53":[{"sum_foreign_comment":"","sum_units":"","sum_comment":"","sum_foreign_units":"","sum":"","sum_foreign":""}]},"declaration":{"needs_scancopy_check":false,"additional_info_text":"","notfull_lostpages":"","notfull":"FALSE","additional_info":"FALSE","url":"http://static.declarations.com.ua/declarations/sudy/apeliatsiini_administratyvni_sudy/dnipropetrovskyi/safronova_declaration.pdf"},"liabilities":{"54":{"sum_foreign_comment":"","sum":"","sum_comment":"","sum_foreign":""},"55":{"sum_foreign_comment":"","sum_units":"","sum_comment":"","sum_foreign_units":"","sum":"","sum_foreign":""},"56":{"sum_foreign_comment":"","sum":"","sum_comment":"","sum_foreign":"12000"},"57":{"sum_foreign_comment":"","sum":"","sum_comment":"","sum_foreign":""},"58":{"sum_foreign_comment":"","sum":"","sum_comment":"","sum_foreign":""},"59":{"sum_foreign_comment":"","sum":"","sum_comment":"","sum_foreign":""},"60":{"sum_foreign_comment":"","sum":"","sum_comment":"","sum_foreign":""},"61":{"sum_foreign_comment":"","sum_units":"","sum_comment":"","sum_foreign_units":"","sum":"","sum_foreign":""},"62":{"sum_foreign_comment":"","sum":"","sum_comment":"","sum_foreign":""},"63":{"sum_foreign_comment":"","sum_units":"","sum_comment":"","sum":"","sum_foreign":""},"64":{"sum_foreign_comment":"","sum_units":"","sum_comment":"","sum":"","sum_foreign":""}},"estate":{"23":[{"costs_rent":"","location_raw":"","region":"","costs":"","costs_rent_comment":"","costs_comment":"","space_comment":"","space_units":"","space":"","address":""},{"costs_rent":"","location_raw":"","region":"","costs":"","costs_rent_comment":"","costs_comment":"","space_comment":"","space_units":"","space":"","address":""},{"costs_rent":"","location_raw":"","region":"","costs":"","costs_rent_comment":"","costs_comment":"","space_comment":"","space_units":"","space":"","address":""}],"24":[{"costs_rent":"","location_raw":"приховано","region":"","costs":"","costs_rent_comment":"","costs_comment":"","space_comment":"","space_units":"","space":"106,8","address":""}]},"general":{"name_hidden":false,"name":"Світлана","patronymic_unclear":false,"last_name_hidden":false,"addresses_raw":"приховано","post_raw":"Суддя Дніпропетровського апеляційного адміністративного суду","patronymic":"Володимирівна","inn":"","family_raw":"Чоловік Сафронов О.С., 25.07.1964;дочка Сафронова М.О., 10.01.2005","last_name":"Сафронова","post":{"office":"Апеляційний адміністративний суд","region":"Дніпропетровська область","post":"Суддя"},"addresses_raw_hidden":true,"last_name_unclear":false,"full_name":"Сафронова Світлана Володимирівна","patronymic_hidden":false,"full_name_suggest":{"output":"Сафронова Світлана Володимирівна","input":["Сафронова Світлана Володимирівна","Світлана Володимирівна Сафронова","Світлана Сафронова"]},"name_unclear":false},"ft_src":"12000\nFALSE\nFALSE\n12617\n24\n25000\n221627\n208986\n25000\nHyundai,ix35\n2011\nHyundai,ix35\n2011\n106,8\nFALSE\nFALSE\nFALSE\n2013\n208986\n12617\n25000\n221627\n25000\n24\nHyundai,ix35\n2011\nFALSE\nFALSE\n106,8\nСуддя Дніпропетровського апеляційного адміністративного суду\nЧоловік Сафронов О.С., 25.07.1964;дочка Сафронова М.О., 10.01.2005\nСафронова\nСафронова Світлана Володимирівна\nСвітлана Володимирівна Сафронова\nСвітлана Сафронова\nСафронова Світлана Володимирівна\nСвітлана\nСафронова Світлана Володимирівна\nАпеляційний адміністративний суд\nСуддя\nДніпропетровська область\nВолодимирівна\n12000\n208986\n25000\n24\n221627\n25000\n12617\n2013\nFALSE\n12000\nСафронова\nВолодимирівна\nЧоловік Сафронов О.С., 25.07.1964;дочка Сафронова М.О., 10.01.2005\nСафронова Світлана Володимирівна\nСвітлана Володимирівна Сафронова\nСвітлана Сафронова\nСафронова Світлана Володимирівна\nСвітлана\nСуддя Дніпропетровського апеляційного адміністративного суду\nСуддя\nДніпропетровська область\nАпеляційний адміністративний суд\nСафронова Світлана Володимирівна\n106,8\nСуддя\nДніпропетровська область\nАпеляційний адміністративний суд\nСуддя Дніпропетровського апеляційного адміністративного суду\nСвітлана\nВолодимирівна\nЧоловік Сафронов О.С., 25.07.1964;дочка Сафронова М.О., 10.01.2005\nСафронова\nСафронова Світлана Володимирівна\nСафронова Світлана Володимирівна\nСвітлана Володимирівна Сафронова\nСвітлана Сафронова\nСафронова Світлана Володимирівна\nFALSE\n2013","intro":{"declaration_year":"2013","isnotdeclaration":"FALSE"}}],"declarationsLength":3,"analytics":[{"y":2015,"i":219629,"c":1,"h":106.8,"ha":1,"fi":28500,"j":1},{"y":2014,"i":224304,"c":1,"h":106.8,"ha":1,"fi":26500},{"y":2013,"i":221627,"c":1,"h":106.8,"ha":1,"la":3,"fi":25000}]}