{"2010":"","2016":"","Department":"Дружківський міський суд Донецької області","Region":"Донецька область","Position":"Суддя Дружківського міського суду Донецької області","Name":"Серікова Олена Олегівна","Link":"https://drive.google.com/open?id=0BygiyWAl79DMR0FOUUVOWVl6VEk","Note":"У меня","AdditionalNote":"","field8":"","field9":"","field10":"","Кількість справ":"","Оскаржені":"","Кількість скарг":0,"Кількість дисциплінарних стягнень":"","Клейма":"","Фото":"","Як живе":"","key":"serikova_olena_olegivna","allDeclarations":[{"provider":"declarations.com.ua","document":{"income":{"5":{"value":"252963","family_comment":"","value_unclear":false,"family_unclear":false,"family":"32249","comment":""},"6":{"value":"240783","family_comment":"","value_unclear":false,"family_unclear":false,"family":"","comment":""},"7":{"family_comment":"","value":"","source_name":"","family":"","comment":""},"8":{"family_comment":"","value":"","family":"","comment":""},"9":{"family_comment":"","value":"","family":"","comment":"","family_comment_unclear":false},"10":{"family_comment":"","value":"12180","family":"","comment":""},"11":{"family_comment":"","value":"","family":"","comment":""},"12":{"family_comment":"","value":"","family":"","comment":""},"13":{"family_comment":"","value":"","family":"","comment":""},"14":{"family_comment":"","value":"","family":"","comment":""},"15":{"family_comment":"","value":"","family":"","comment":""},"16":{"family_comment":"","family_unclear":false,"value":"","family":"","comment":""},"17":{"family_comment":"","family_unclear":false,"value":"","family":"13177","comment":""},"18":{"family_comment":"","value":"","family":"","comment":""},"19":{"family_comment":"","value":"","family":"","comment":""},"20":{"family_comment":"","value":"","family":"19072","comment":""}},"vehicle":{"40":[{"brand_info":"2.4","sum":"","brand":"ГАЗ 31105-501","sum_comment":"","year":"2007","brand_hidden":false,"brand_info_hidden":false,"sum_rent_comment":"","sum_rent":""},{"brand_info":"2.0 л","sum":"","brand":"Hyundai Tucson","sum_comment":"","year":"2010","sum_rent_comment":"","sum_rent":""}]},"id":"vulyk_88_58","declaration":{"additional_info_text":"","notfull_lostpages":"","date":"2015-03-28T00:00:00","notfull":"","additional_info":"","url":"http://static.declarations.com.ua/declarations/chosen_ones/judges_batch/2961_serikova_olena_olehivna.pdf"},"liabilities":{"54":{"sum_foreign_comment":"","sum":"","sum_comment":"","sum_comment_unclear":false,"sum_foreign":""},"55":{"sum_foreign_comment":"","sum":"","sum_comment":"","sum_foreign":""},"56":{"sum_foreign_comment":"","sum":"","sum_comment":"","sum_foreign":""},"57":{"sum_foreign_comment":"","sum":"150","sum_comment":"","sum_hidden":false,"sum_comment_hidden":false,"sum_unclear":false,"sum_foreign":""},"58":{"sum_foreign_comment":"","sum":"50","sum_comment":"","sum_hidden":false,"sum_comment_hidden":false,"sum_foreign":""},"59":{"sum_foreign_comment":"","sum":"","sum_comment":"","sum_foreign":""},"60":{"sum_foreign_comment":"","sum":"2112","sum_comment":"","sum_comment_unclear":false,"sum_hidden":false,"sum_comment_hidden":false,"sum_foreign":""},"61":{"sum_foreign_comment":"","sum":"","sum_comment":"","sum_foreign":""},"62":{"sum_foreign_comment":"","sum":"","sum_comment":"","sum_foreign":""},"63":{"sum_foreign_comment":"","sum":"","sum_comment":"","sum_foreign":""},"64":{"sum_foreign_comment":"","sum":"","sum_comment":"","sum_foreign":""}},"ft_src":"2007\nГАЗ 31105-501\n2.4\n2.0 л\n2010\nHyundai Tucson\nм. Дружківка\nДонецька область\n66.51\nм. Дружківка\n66.51\nДонецька область\n2014\n240783\n12180\n32249\n252963\n13177\n19072\n2.4\n2007\nГАЗ 31105-501\n2.0 л\n2010\nHyundai Tucson\n66.51\nм. Дружківка\nДонецька область\n66.51\nм. Дружківка\nДонецька область\nСєрікова Олена Олегівна\nОлена Олегівна Сєрікова\nОлена Сєрікова\nСєрікова Олена Олегівна\nОлена\nПодружжя\nСєріков І. Ж., 28. 10. 1956 р. н\nБатьки\nЛітовцева В. П., 24. 03. 1932 р. н\nСєрікова Олена Олегівна\nСєрікова\nЗагальний місцевий суд\nсуддя дружківського міського суду 2 клас\nДонецька область\nОлегівна\nДружківка\nДонецька область\n150\n2112\n50\n240783\n19072\n13177\n252963\n32249\n12180\n2014\n50\n150\n2112\nСєріков І. Ж., 28. 10. 1956 р. н\nПодружжя\nЛітовцева В. П., 24. 03. 1932 р. н\nБатьки\nОлегівна\nСєрікова\nОлена\nСєрікова Олена Олегівна\nОлена Олегівна Сєрікова\nОлена Сєрікова\nСєрікова Олена Олегівна\nДонецька область\nДружківка\nДонецька область\nЗагальний місцевий суд\nсуддя дружківського міського суду 2 клас\nСєрікова Олена Олегівна","general":{"inn":"","name":"Олена","patronymic_unclear":false,"family":[{"inn":"","relations":"Подружжя","name_hidden":false,"inn_hidden":true,"family_name":"Сєріков І. Ж., 28. 10. 1956 р. н","name_unclear":false},{"inn":"","inn_hidden":false,"family_name":"Літовцева В. П., 24. 03. 1932 р. н","relations_other":"","relations":"Батьки","name_hidden":false,"name_unclear":false}],"patronymic":"Олегівна","inn_hidden":true,"family_raw":"","last_name":"Сєрікова","post":{"post":"суддя дружківського міського суду 2 клас","region":"Донецька область","candidate":"","office":"Загальний місцевий суд","region_hidden":false,"office_hidden":false},"full_name_suggest":{"output":"Сєрікова Олена Олегівна","input":["Сєрікова Олена Олегівна","Олена Олегівна Сєрікова","Олена Сєрікова"]},"full_name":"Сєрікова Олена Олегівна","addresses":[{"place_district":"","place_address_hidden":true,"place_city":"Дружківка","place_address":"","place_district_hidden":false,"place_city_type":"Місто","place_city_hidden":false,"place_city_type_hidden":false,"place_hidden":false,"place":"Донецька область"}],"patronymic_hidden":false,"last_name_unclear":false},"source":"VULYK","estate":{"25":[{"space_unclear":false,"costs":"","costs_comment":"","address_hidden":true,"region_hidden":false,"space_comment":"","space_hidden":false,"space":"66.51","address":"м. Дружківка","region":"Донецька область","address_unclear":false,"costs_rent_comment":"","space_comment_unclear":false,"space_units":"м²","costs_rent":""}],"31":[{"space_unclear":false,"address_hidden":true,"region_hidden":false,"space_comment":"","space":"66.51","address":"м. Дружківка","region":"Донецька область","costs_property":"","costs_rent_comment":"","space_units":"м²","costs_property_comment":"","costs_rent":""}]},"intro":{"declaration_year":"2014","isnotdeclaration":""}}}],"declarations":[{"income":{"5":{"value":"252963","family_comment":"","value_unclear":false,"family_unclear":false,"family":"32249","comment":""},"6":{"value":"240783","family_comment":"","value_unclear":false,"family_unclear":false,"family":"","comment":""},"7":{"family_comment":"","value":"","source_name":"","family":"","comment":""},"8":{"family_comment":"","value":"","family":"","comment":""},"9":{"family_comment":"","value":"","family":"","comment":"","family_comment_unclear":false},"10":{"family_comment":"","value":"12180","family":"","comment":""},"11":{"family_comment":"","value":"","family":"","comment":""},"12":{"family_comment":"","value":"","family":"","comment":""},"13":{"family_comment":"","value":"","family":"","comment":""},"14":{"family_comment":"","value":"","family":"","comment":""},"15":{"family_comment":"","value":"","family":"","comment":""},"16":{"family_comment":"","family_unclear":false,"value":"","family":"","comment":""},"17":{"family_comment":"","family_unclear":false,"value":"","family":"13177","comment":""},"18":{"family_comment":"","value":"","family":"","comment":""},"19":{"family_comment":"","value":"","family":"","comment":""},"20":{"family_comment":"","value":"","family":"19072","comment":""}},"vehicle":{"40":[{"brand_info":"2.4","sum":"","brand":"ГАЗ 31105-501","sum_comment":"","year":"2007","brand_hidden":false,"brand_info_hidden":false,"sum_rent_comment":"","sum_rent":""},{"brand_info":"2.0 л","sum":"","brand":"Hyundai Tucson","sum_comment":"","year":"2010","sum_rent_comment":"","sum_rent":""}]},"id":"vulyk_88_58","declaration":{"additional_info_text":"","notfull_lostpages":"","date":"2015-03-28T00:00:00","notfull":"","additional_info":"","url":"http://static.declarations.com.ua/declarations/chosen_ones/judges_batch/2961_serikova_olena_olehivna.pdf"},"liabilities":{"54":{"sum_foreign_comment":"","sum":"","sum_comment":"","sum_comment_unclear":false,"sum_foreign":""},"55":{"sum_foreign_comment":"","sum":"","sum_comment":"","sum_foreign":""},"56":{"sum_foreign_comment":"","sum":"","sum_comment":"","sum_foreign":""},"57":{"sum_foreign_comment":"","sum":"150","sum_comment":"","sum_hidden":false,"sum_comment_hidden":false,"sum_unclear":false,"sum_foreign":""},"58":{"sum_foreign_comment":"","sum":"50","sum_comment":"","sum_hidden":false,"sum_comment_hidden":false,"sum_foreign":""},"59":{"sum_foreign_comment":"","sum":"","sum_comment":"","sum_foreign":""},"60":{"sum_foreign_comment":"","sum":"2112","sum_comment":"","sum_comment_unclear":false,"sum_hidden":false,"sum_comment_hidden":false,"sum_foreign":""},"61":{"sum_foreign_comment":"","sum":"","sum_comment":"","sum_foreign":""},"62":{"sum_foreign_comment":"","sum":"","sum_comment":"","sum_foreign":""},"63":{"sum_foreign_comment":"","sum":"","sum_comment":"","sum_foreign":""},"64":{"sum_foreign_comment":"","sum":"","sum_comment":"","sum_foreign":""}},"ft_src":"2007\nГАЗ 31105-501\n2.4\n2.0 л\n2010\nHyundai Tucson\nм. Дружківка\nДонецька область\n66.51\nм. Дружківка\n66.51\nДонецька область\n2014\n240783\n12180\n32249\n252963\n13177\n19072\n2.4\n2007\nГАЗ 31105-501\n2.0 л\n2010\nHyundai Tucson\n66.51\nм. Дружківка\nДонецька область\n66.51\nм. Дружківка\nДонецька область\nСєрікова Олена Олегівна\nОлена Олегівна Сєрікова\nОлена Сєрікова\nСєрікова Олена Олегівна\nОлена\nПодружжя\nСєріков І. Ж., 28. 10. 1956 р. н\nБатьки\nЛітовцева В. П., 24. 03. 1932 р. н\nСєрікова Олена Олегівна\nСєрікова\nЗагальний місцевий суд\nсуддя дружківського міського суду 2 клас\nДонецька область\nОлегівна\nДружківка\nДонецька область\n150\n2112\n50\n240783\n19072\n13177\n252963\n32249\n12180\n2014\n50\n150\n2112\nСєріков І. Ж., 28. 10. 1956 р. н\nПодружжя\nЛітовцева В. П., 24. 03. 1932 р. н\nБатьки\nОлегівна\nСєрікова\nОлена\nСєрікова Олена Олегівна\nОлена Олегівна Сєрікова\nОлена Сєрікова\nСєрікова Олена Олегівна\nДонецька область\nДружківка\nДонецька область\nЗагальний місцевий суд\nсуддя дружківського міського суду 2 клас\nСєрікова Олена Олегівна","general":{"inn":"","name":"Олена","patronymic_unclear":false,"family":[{"inn":"","relations":"Подружжя","name_hidden":false,"inn_hidden":true,"family_name":"Сєріков І. Ж., 28. 10. 1956 р. н","name_unclear":false},{"inn":"","inn_hidden":false,"family_name":"Літовцева В. П., 24. 03. 1932 р. н","relations_other":"","relations":"Батьки","name_hidden":false,"name_unclear":false}],"patronymic":"Олегівна","inn_hidden":true,"family_raw":"","last_name":"Сєрікова","post":{"post":"суддя дружківського міського суду 2 клас","region":"Донецька область","candidate":"","office":"Загальний місцевий суд","region_hidden":false,"office_hidden":false},"full_name_suggest":{"output":"Сєрікова Олена Олегівна","input":["Сєрікова Олена Олегівна","Олена Олегівна Сєрікова","Олена Сєрікова"]},"full_name":"Сєрікова Олена Олегівна","addresses":[{"place_district":"","place_address_hidden":true,"place_city":"Дружківка","place_address":"","place_district_hidden":false,"place_city_type":"Місто","place_city_hidden":false,"place_city_type_hidden":false,"place_hidden":false,"place":"Донецька область"}],"patronymic_hidden":false,"last_name_unclear":false},"source":"VULYK","estate":{"25":[{"space_unclear":false,"costs":"","costs_comment":"","address_hidden":true,"region_hidden":false,"space_comment":"","space_hidden":false,"space":"66.51","address":"м. Дружківка","region":"Донецька область","address_unclear":false,"costs_rent_comment":"","space_comment_unclear":false,"space_units":"м²","costs_rent":""}],"31":[{"space_unclear":false,"address_hidden":true,"region_hidden":false,"space_comment":"","space":"66.51","address":"м. Дружківка","region":"Донецька область","costs_property":"","costs_rent_comment":"","space_units":"м²","costs_property_comment":"","costs_rent":""}]},"intro":{"declaration_year":"2014","isnotdeclaration":""}}],"declarationsLength":1,"analytics":[{"y":2014,"i":252963,"k":66.51,"ka":1,"fi":32249,"ff":66.51,"ffa":1}]}