{"2010":"","2016":"","Department":"Диканський районний суд Полтавської області","Region":"Полтавська область","Position":"Суддя Диканського районного суду Полтавської області","Name":"Щабельська Ірина Володимирівна","Link":"https://drive.google.com/open?id=0BygiyWAl79DMdHZvODFKZW8tT2c","Note":"У меня","AdditionalNote":"","field8":"","field9":"","field10":"","Кількість справ":"","Оскаржені":"","Кількість скарг":1,"Кількість дисциплінарних стягнень":"","Клейма":"","Фото":"","Як живе":"","key":"shchabelska_irina_volodimirivna","allDeclarations":[{"provider":"declarations.com.ua","document":{"income":{"5":{"family_comment":"","family_unclear":false,"value":"229414.42","family":"24965","comment":""},"6":{"value":"229414.42","family_comment":"","value_unclear":false,"family_unclear":false,"family":"","comment":""},"7":{"source_name_unclear":false,"value":"","family_comment":"","source_name":"","family":"","comment":"","source_name_hidden":false},"8":{"family_comment":"","value":"","family":"","comment":""},"9":{"family_comment":"","family_unclear":false,"value":"","family":"","comment":""},"10":{"family_comment":"","value":"","family":"","comment":""},"11":{"family_comment":"","value":"","family":"","comment":""},"12":{"family_comment":"","value":"","family":"","comment":""},"13":{"family_comment":"","value":"","family":"","comment":""},"14":{"family_comment":"","value":"","family":"","comment":""},"15":{"family_comment":"","value":"","family":"","comment":""},"16":{"family_comment":"","family_unclear":false,"value":"","family":"","comment":""},"17":{"family_comment":"","family_unclear":false,"value":"","family":"","comment":""},"18":{"family_comment":"","value":"","family":"","comment":""},"19":{"family_comment":"","value":"","family":"","comment":""},"20":{"family_comment":"пенсія","value":"","comment_unclear":false,"family":"24965","comment":""}},"vehicle":{"40":[{"brand_info":"1452 куб. см., 400.0 см","sum":"","brand":"ВАЗ 21070","sum_comment":"","brand_unclear":false,"year":"2006","brand_hidden":false,"brand_info_hidden":false,"brand_info_unclear":false,"sum_rent_comment":"","sum_rent":""}]},"id":"vulyk_95_182","declaration":{"additional_info_text":"","notfull_lostpages":"","date":"2016-03-31T00:00:00","notfull":"","additional_info":"","url":"http://static.declarations.com.ua/declarations/chosen_ones/judges_batch/184_shchabelska_iryna_volodymyrivna_2015.pdf"},"liabilities":{"54":{"sum_foreign_comment":"","sum":"2214","sum_comment":"","sum_hidden":false,"sum_comment_hidden":false,"sum_unclear":false,"sum_foreign":""},"55":{"sum_foreign_comment":"","sum":"","sum_comment":"","sum_foreign":""},"56":{"sum_foreign_comment":"","sum":"","sum_comment":"","sum_foreign":""},"57":{"sum_foreign_comment":"","sum":"48836.91","sum_comment":"","sum_hidden":false,"sum_comment_hidden":false,"sum_unclear":false,"sum_foreign":""},"58":{"sum_foreign_comment":"","sum":"62047.01","sum_comment":"","sum_hidden":false,"sum_comment_hidden":false,"sum_unclear":false,"sum_foreign":""},"59":{"sum_foreign_comment":"","sum":"","sum_comment":"","sum_foreign":""},"60":{"sum_foreign_comment":"","sum":"200","sum_comment":"","sum_hidden":false,"sum_comment_hidden":false,"sum_foreign":""},"61":{"sum_foreign_comment":"","sum":"","sum_comment":"","sum_foreign":""},"62":{"sum_foreign_comment":"","sum":"","sum_comment":"","sum_unclear":false,"sum_foreign":""},"63":{"sum_foreign_comment":"","sum":"","sum_comment":"","sum_unclear":false,"sum_foreign":""},"64":{"sum_foreign_comment":"","sum":"","sum_comment":"","sum_foreign":""}},"ft_src":"48836.91\n2214\n62047.01\n200\nсуддя диканського районного суду полтавської області\nПолтавська область\nЗагальний місцевий суд\nЩабельська Ірина Володимирівна\nЩабельська\nІрина\nЩабельський Р. С\nПодружжя\nЩабельський В. Р\nДитина\nЩабельська К. Р\nДитина\nЩабельська Ірина Володимирівна\nІрина Володимирівна Щабельська\nІрина Щабельська\nЩабельська Ірина Володимирівна\nВолодимирівна\n24965\nпенсія\n24965\n229414.42\n229414.42\nВАЗ 21070\n1452 куб. см., 400.0 см\n2006\nВАЗ 21070\n1452 куб. см., 400.0 см\n2006\n2015\n229414.42\n24965\n229414.42\n24965\nпенсія\nВАЗ 21070\n1452 куб. см., 400.0 см\n2006\n2015\nВолодимирівна\nПодружжя\nЩабельський Р. С\nДитина\nЩабельський В. Р\nДитина\nЩабельська К. Р\nЩабельська\nЩабельська Ірина Володимирівна\nІрина Володимирівна Щабельська\nІрина Щабельська\nЩабельська Ірина Володимирівна\nІрина\nЩабельська Ірина Володимирівна\nЗагальний місцевий суд\nсуддя диканського районного суду полтавської області\nПолтавська область\n62047.01\n200\n48836.91\n2214\n229414.42\n24965\nпенсія\n229414.42\n24965\n62047.01\n48836.91\n2214\n200\nЩабельський Р. С\nПодружжя\nЩабельський В. Р\nДитина\nЩабельська К. Р\nДитина\nВолодимирівна\nЩабельська\nПолтавська область\nЗагальний місцевий суд\nсуддя диканського районного суду полтавської області\nЩабельська Ірина Володимирівна\nЩабельська Ірина Володимирівна\nІрина Володимирівна Щабельська\nІрина Щабельська\nЩабельська Ірина Володимирівна\nІрина\n2015","general":{"inn":"","family_raw":"","last_name":"Щабельська","post":{"post":"суддя диканського районного суду полтавської області","region":"Полтавська область","candidate":"","office_hidden":false,"office":"Загальний місцевий суд","office_unclear":false},"name":"Ірина","full_name":"Щабельська Ірина Володимирівна","inn_hidden":true,"family":[{"inn":"","inn_hidden":true,"inn_unclear":false,"relations_hidden":false,"relations_other":"","relations":"Подружжя","name_hidden":false,"family_name":"Щабельський Р. С","name_unclear":false},{"inn":"","inn_hidden":false,"inn_unclear":false,"relations_hidden":false,"relations_other":"","relations":"Дитина","name_hidden":false,"family_name":"Щабельський В. Р","name_unclear":false},{"inn":"","inn_hidden":false,"inn_unclear":false,"relations_hidden":false,"relations_other":"","relations":"Дитина","name_hidden":false,"family_name":"Щабельська К. Р","name_unclear":false}],"full_name_suggest":{"output":"Щабельська Ірина Володимирівна","input":["Щабельська Ірина Володимирівна","Ірина Володимирівна Щабельська","Ірина Щабельська"]},"patronymic":"Володимирівна"},"source":"VULYK","intro":{"declaration_year":"2015","isnotdeclaration":""}}},{"provider":"declarations.com.ua","document":{"income":{"5":{"value":"258920","family_comment":"","value_unclear":false,"family_unclear":false,"family":"101098","comment":""},"6":{"family_comment":"","value":"220853","value_unclear":false,"family":"","comment":""},"7":{"value":"","value_unclear":false,"family_comment":"","source_name":"","family":"","comment":""},"8":{"family_comment":"","value":"","family":"","comment":""},"9":{"value":"","family_comment":"","value_unclear":false,"family_unclear":false,"family":"","comment":""},"10":{"family_comment":"","value":"","comment_unclear":false,"family":"","comment":""},"11":{"family_comment":"","value":"","family":"","comment":""},"12":{"family_comment":"","value":"","family":"","comment":""},"13":{"family_comment":"","value":"","value_unclear":false,"family":"","comment":""},"14":{"family_comment":"","value":"","family":"","comment":""},"15":{"family_comment":"","value":"","family":"","comment":""},"16":{"family_comment":"","family_unclear":false,"value":"38066","family":"76133","comment":""},"17":{"family_comment":"","family_unclear":false,"value":"","family":"","comment":""},"18":{"family_comment":"","value":"","family":"","comment":""},"19":{"family_comment":"","value":"","family":"","comment":""},"20":{"value":"","family_comment":"пенсія","value_unclear":false,"family_hidden":false,"value_hidden":false,"family_unclear":false,"comment_unclear":false,"comment":"","family":"24965"}},"vehicle":{"40":[{"brand_info":"1452 куб. см., 400.0 см","sum_rent_comment":"","brand":"ВАЗ 21070","sum_comment":"","year":"2006","brand_info_hidden":false,"brand_info_unclear":false,"sum":"","sum_rent":""}]},"id":"vulyk_100_32","banks":{"45":[{"sum_foreign_comment":"","sum_units":"UAH","sum_comment":"","sum_comment_unclear":false,"sum_foreign_units":"UAH","sum_units_unclear":false,"sum_comment_hidden":false,"sum_unclear":false,"sum":"7250","sum_foreign":""}],"46":[{"sum_foreign_comment":"","sum_units":"UAH","sum_comment":"","sum_comment_unclear":false,"sum_foreign_units":"UAH","sum":"7250","sum_unclear":false,"sum_foreign":""}],"47":[{"sum_foreign_comment":"","sum_units":"UAH","sum_comment":"","sum_comment_unclear":false,"sum_foreign_units":"UAH","sum":"12","sum_unclear":false,"sum_foreign":""}],"52":[{"sum_foreign_comment":"","sum_units":"UAH","sum_comment":"","sum_comment_unclear":false,"sum_foreign_units":"UAH","sum":"12","sum_unclear":true,"sum_foreign":""}]},"declaration":{"additional_info_text":"","notfull_lostpages":"","date":"2015-03-25T00:00:00","notfull":"","additional_info":"","url":"http://static.declarations.com.ua/declarations/chosen_ones/judges_batch/4191_shchabelska_iryna_volodymyrivna.pdf"},"liabilities":{"54":{"sum_foreign_comment":"","sum":"2214","sum_comment":"","sum_comment_hidden":false,"sum_unclear":false,"sum_foreign":""},"55":{"sum_foreign_comment":"","sum":"","sum_comment":"","sum_foreign":""},"56":{"sum_foreign_comment":"","sum":"","sum_comment":"","sum_unclear":false,"sum_foreign":""},"57":{"sum_foreign_comment":"","sum":"197473","sum_comment":"","sum_comment_unclear":false,"sum_comment_hidden":false,"sum_unclear":false,"sum_foreign":""},"58":{"sum_foreign_comment":"","sum":"47360","sum_comment":"","sum_comment_hidden":false,"sum_unclear":false,"sum_foreign":""},"59":{"sum_foreign_comment":"","sum":"","sum_comment":"","sum_foreign":""},"60":{"sum_foreign_comment":"","sum_comment_hidden":false,"sum":"200","sum_comment":"","sum_foreign":""},"61":{"sum_foreign_comment":"","sum":"","sum_comment":"","sum_foreign":""},"62":{"sum_foreign_comment":"","sum":"","sum_comment":"","sum_unclear":false,"sum_foreign":""},"63":{"sum_foreign_comment":"","sum_comment_hidden":false,"sum":"","sum_comment":"","sum_foreign":""},"64":{"sum_foreign_comment":"","sum_comment_hidden":false,"sum":"","sum_comment":"","sum_foreign":""}},"ft_src":"197473\n2214\n47360\n200\nЩабельська Ірина Володимирівна\nсуддя диканського районного суду полтавської області\nПолтавська область\nЗагальний місцевий суд\nІрина\nЩабельський Р. С\nПодружжя\nЩабельський В. Р\nДитина\nЩабельська К. Р\nДитина\nЩабельська Ірина Володимирівна\nІрина Володимирівна Щабельська\nІрина Щабельська\nЩабельська Ірина Володимирівна\nЩабельська\nВолодимирівна\n2006\n1452 куб. см., 400.0 см\nВАЗ 21070\n7250\n12\n12\n7250\n2014\nВАЗ 21070\n1452 куб. см., 400.0 см\n2006\n7250\n12\n7250\n12\n31300\nПодружжя\nЩабельський Р. С\nДитина\nЩабельський В. Р\nДитина\nЩабельська К. Р\nВолодимирівна\nЩабельська\nЩабельська Ірина Володимирівна\nІрина Володимирівна Щабельська\nІрина Щабельська\nЩабельська Ірина Володимирівна\nЩабельська Ірина Володимирівна\nІрина\nЗагальний місцевий суд\nПолтавська область\nсуддя диканського районного суду полтавської області\n2214\n197473\n200\n47360\n220853\n24965\nпенсія\n258920\n101098\n38066\n76133\n2014\n47360\n197473\n2214\n200\n31300\nЩабельський Р. С\nПодружжя\nДитина\nЩабельський В. Р\nДитина\nЩабельська К. Р\nВолодимирівна\nЩабельська\nПолтавська область\nЗагальний місцевий суд\nсуддя диканського районного суду полтавської області\nЩабельська Ірина Володимирівна\nЩабельська Ірина Володимирівна\nІрина Володимирівна Щабельська\nІрина Щабельська\nЩабельська Ірина Володимирівна\nІрина\n220853\n101098\n258920\n76133\n38066\n24965\nпенсія\n2006\n1452 куб. см., 400.0 см\nВАЗ 21070\nпенсія\n24965\n258920\n101098\n76133\n38066\n220853\n31300\n12\n7250\n7250\n12\n2014","general":{"inn":"","inn_hidden":true,"last_name":"Щабельська","post":{"post_unclear":false,"region_unclear":false,"post":"суддя диканського районного суду полтавської області","office":"Загальний місцевий суд","region":"Полтавська область","post_hidden":false,"office_unclear":false},"name":"Ірина","full_name":"Щабельська Ірина Володимирівна","family_raw":"","addresses":[{"place_district":"","place_city_hidden":true,"place_city":"","place_city_unclear":false,"place_district_hidden":true,"place_city_type":"","place_address_hidden":true,"place_city_type_hidden":true,"place_address":"","place_hidden":true,"place":""}],"family":[{"inn_hidden":true,"inn":"","name_hidden":true,"family_name":"Щабельський Р. С","relations":"Подружжя","name_unclear":true},{"inn":"","relations":"Дитина","relations_other":"","inn_hidden":false,"family_name":"Щабельський В. Р","name_hidden":false,"name_unclear":true},{"inn":"","relations":"Дитина","relations_other":"","inn_hidden":false,"family_name":"Щабельська К. Р","name_hidden":false,"name_unclear":true}],"full_name_suggest":{"output":"Щабельська Ірина Володимирівна","input":["Щабельська Ірина Володимирівна","Ірина Володимирівна Щабельська","Ірина Щабельська"]},"patronymic":"Володимирівна"},"source":"VULYK","estate":{"23":[{"space_unclear":false,"costs":"","costs_comment":"","address_hidden":true,"region_hidden":true,"space_comment":"","space":"","address":"","costs_comment_unclear":false,"region":"","address_unclear":false,"costs_rent_comment":"","space_comment_unclear":false,"space_units":"м²","costs_rent":""}],"29":[{"region_unclear":false,"space_unclear":false,"address_hidden":false,"region_hidden":true,"space_comment":"","space":"31300","address":"","region":"","costs_property":"","costs_rent_comment":"","address_unclear":false,"space_units":"м²","costs_property_comment":"","costs_rent":""}]},"intro":{"declaration_year":"2014"}}},{"provider":"public-api.nazk.gov.ua","document":{"step_0":{"declarationType":"1","declarationYear1":"2015"},"step_1":{"city":"[Конфіденційна інформація]","region":"[Конфіденційна інформація]","street":"[Конфіденційна інформація]","country":"1","cityPath":"[Конфіденційна інформація]","cityType":"[Конфіденційна інформація]","district":"[Конфіденційна інформація]","lastname":"Щабельська","postCode":"[Конфіденційна інформація]","postType":"","workPost":"суддя","firstname":"Ірина","workPlace":"Диканський районний суд Полтавської області","middlename":"Володимирівна","streetType":"[Конфіденційна інформація]","changedName":false,"countryPath":"","eng_postCode":"","postCategory":"","actual_street":"[Конфіденційна інформація]","actual_cityPath":"[Конфіденційна інформація]","actual_cityType":"[Конфіденційна інформація]","actual_postCode":"[Конфіденційна інформація]","actual_streetType":"[Конфіденційна інформація]","previous_lastname":"","corruptionAffected":"Так","eng_actualPostCode":"[Конфіденційна інформація]","previous_firstname":"","previous_middlename":"","responsiblePosition":"Суддя суду загальної юрисдикції, суддя Конституційного Суду України","sameRegLivingAddress":"[Конфіденційна інформація]","postType_extendedstatus":"1","eng_sameRegLivingAddress":"[Конфіденційна інформація]","housePartNum_extendedstatus":"1","postCategory_extendedstatus":"1","apartmentsNum_extendedstatus":"1"},"step_2":{"1477293001119":{"lastname":"щабельський","firstname":"руслан","middlename":"станіславович","changedName":false,"citizenship":"1","eng_lastname":"","no_taxNumber":false,"eng_firstname":"","eng_middlename":"","isNotApplicable":"","subjectRelation":"чоловік","previous_lastname":"","previous_firstname":"","previous_middlename":"","previous_eng_lastname":"","previous_eng_firstname":"","previous_eng_middlename":""},"1477293308043":{"lastname":"щабельський ","firstname":"валерій","middlename":"русланович","changedName":false,"citizenship":"1","eng_lastname":"","no_taxNumber":false,"eng_firstname":"","eng_middlename":"","isNotApplicable":"","subjectRelation":"син","previous_lastname":"","previous_firstname":"","previous_middlename":"","previous_eng_lastname":"","previous_eng_firstname":"","previous_eng_middlename":""},"1477293418725":{"lastname":"щабельська ","firstname":"катерина","middlename":"русланівна","changedName":false,"citizenship":"1","eng_lastname":"","no_taxNumber":true,"eng_firstname":"","eng_middlename":"","isNotApplicable":"","subjectRelation":"дочка","previous_lastname":"","previous_firstname":"","previous_middlename":"","previous_eng_lastname":"","previous_eng_firstname":"","previous_eng_middlename":""}},"step_3":[],"step_4":[],"step_5":[],"step_6":{"1477295819524":{"brand":"ВАЗ","model":"21070","person":"1477293001119","rights":{"1477293001119":{"citizen":"","ua_city":"","ua_street":"[Конфіденційна інформація]","ua_lastname":"","ua_postCode":"","eng_fullname":"","eng_lastname":"","eng_postCode":"","rightBelongs":"1477293001119","ua_firstname":"","ukr_fullname":"","ukr_lastname":"","eng_firstname":"","ownershipType":"Власність","ua_middlename":"","ua_streetType":"[Конфіденційна інформація]","ukr_firstname":"","eng_middlename":"","otherOwnership":"","ukr_middlename":"","rights_cityPath":"","ua_company_name":"","eng_company_name":"","ukr_company_name":"","percent-ownership":"","ua_street_extendedstatus":"","ua_houseNum_extendedstatus":"","ua_postCode_extendedstatus":"","eng_postCode_extendedstatus":"","ua_middlename_extendedstatus":"","eng_middlename_extendedstatus":"","ukr_middlename_extendedstatus":"","ua_housePartNum_extendedstatus":"","ua_apartmentsNum_extendedstatus":""}},"costDate":"33000","objectType":"Автомобіль легковий","owningDate":"20.05.2016","graduationYear":"2005","otherObjectType":""}},"step_7":[],"step_8":[],"step_9":[],"step_10":[],"step_11":{"1477297276953":{"person":"1","rights":{"1":{"citizen":"","ua_city":"","ua_street":"[Конфіденційна інформація]","ua_lastname":"","ua_postCode":"","eng_fullname":"","eng_lastname":"","eng_postCode":"","rightBelongs":"1","ua_firstname":"","ukr_fullname":"","ukr_lastname":"","eng_firstname":"","ownershipType":"Власність","ua_middlename":"","ua_streetType":"[Конфіденційна інформація]","ukr_firstname":"","eng_middlename":"","otherOwnership":"","ukr_middlename":"","rights_cityPath":"","ua_company_name":"","eng_company_name":"","ukr_company_name":"","percent-ownership":"","ua_street_extendedstatus":"","ua_houseNum_extendedstatus":"","ua_postCode_extendedstatus":"","eng_postCode_extendedstatus":"","ua_middlename_extendedstatus":"","eng_middlename_extendedstatus":"","ukr_middlename_extendedstatus":"","ua_housePartNum_extendedstatus":"","ua_apartmentsNum_extendedstatus":""}},"objectType":"Заробітна плата отримана за основним місцем роботи","sizeIncome":"229414","incomeSource":"j","source_citizen":"Юридична особа, зареєстрована в Україні","otherObjectType":"","source_ua_lastname":"","source_eng_fullname":"","source_ua_firstname":"","source_ukr_fullname":"","source_ua_middlename":"","source_ua_company_name":"Диканський районний суд","source_eng_company_name":"","source_ukr_company_name":"","source_ua_sameRegLivingAddress":""},"1477297622129":{"person":"1477293001119","rights":{"1477293001119":{"citizen":"","ua_city":"","ua_street":"[Конфіденційна інформація]","ua_lastname":"","ua_postCode":"","eng_fullname":"","eng_lastname":"","eng_postCode":"","rightBelongs":"1477293001119","ua_firstname":"","ukr_fullname":"","ukr_lastname":"","eng_firstname":"","ownershipType":"Власність","ua_middlename":"","ua_streetType":"[Конфіденційна інформація]","ukr_firstname":"","eng_middlename":"","otherOwnership":"","ukr_middlename":"","rights_cityPath":"","ua_company_name":"","eng_company_name":"","ukr_company_name":"","percent-ownership":"","ua_street_extendedstatus":"","ua_houseNum_extendedstatus":"","ua_postCode_extendedstatus":"","eng_postCode_extendedstatus":"","ua_middlename_extendedstatus":"","eng_middlename_extendedstatus":"","ukr_middlename_extendedstatus":"","ua_housePartNum_extendedstatus":"","ua_apartmentsNum_extendedstatus":""}},"objectType":"Пенсія","sizeIncome":"24965","incomeSource":"j","source_citizen":"Юридична особа, зареєстрована в Україні","otherObjectType":"","source_ua_lastname":"","source_eng_fullname":"","source_ua_firstname":"","source_ukr_fullname":"","source_ua_middlename":"","source_ua_company_name":"Головне Управління пенсійного фонду України в Полтавській області","source_eng_company_name":"","source_ukr_company_name":"","source_ua_sameRegLivingAddress":""}},"step_12":[],"step_13":{"1477294912056":{"person":"1","currency":"UAH","guarantor":[],"dateOrigin":"13.02.2015","objectType":"Отримані кредити","margin-emitent":"1477293001119","sizeObligation":"871488","emitent_citizen":"","otherObjectType":"","guarantor_exist_":false,"guarantor_realty":[],"ownerThirdPerson":"","emitent_ua_lastname":"","emitent_eng_fullname":"","emitent_ua_firstname":"","emitent_ukr_fullname":"","emitent_ua_middlename":"","ownerThirdPersonThing":"","emitent_ua_company_name":"","guarantor_realty_exist_":false,"emitent_eng_company_name":"","emitent_ukr_company_name":"","emitent_ua_sameRegLivingAddress":""}},"step_14":[],"step_15":[],"step_16":[],"id":"001f0dbe-e70d-40ae-af6f-818a42117f6e"}}],"declarations":[{"income":{"5":{"family_comment":"","family_unclear":false,"value":"229414.42","family":"24965","comment":""},"6":{"value":"229414.42","family_comment":"","value_unclear":false,"family_unclear":false,"family":"","comment":""},"7":{"source_name_unclear":false,"value":"","family_comment":"","source_name":"","family":"","comment":"","source_name_hidden":false},"8":{"family_comment":"","value":"","family":"","comment":""},"9":{"family_comment":"","family_unclear":false,"value":"","family":"","comment":""},"10":{"family_comment":"","value":"","family":"","comment":""},"11":{"family_comment":"","value":"","family":"","comment":""},"12":{"family_comment":"","value":"","family":"","comment":""},"13":{"family_comment":"","value":"","family":"","comment":""},"14":{"family_comment":"","value":"","family":"","comment":""},"15":{"family_comment":"","value":"","family":"","comment":""},"16":{"family_comment":"","family_unclear":false,"value":"","family":"","comment":""},"17":{"family_comment":"","family_unclear":false,"value":"","family":"","comment":""},"18":{"family_comment":"","value":"","family":"","comment":""},"19":{"family_comment":"","value":"","family":"","comment":""},"20":{"family_comment":"пенсія","value":"","comment_unclear":false,"family":"24965","comment":""}},"vehicle":{"40":[{"brand_info":"1452 куб. см., 400.0 см","sum":"","brand":"ВАЗ 21070","sum_comment":"","brand_unclear":false,"year":"2006","brand_hidden":false,"brand_info_hidden":false,"brand_info_unclear":false,"sum_rent_comment":"","sum_rent":""}]},"id":"vulyk_95_182","declaration":{"additional_info_text":"","notfull_lostpages":"","date":"2016-03-31T00:00:00","notfull":"","additional_info":"","url":"http://static.declarations.com.ua/declarations/chosen_ones/judges_batch/184_shchabelska_iryna_volodymyrivna_2015.pdf"},"liabilities":{"54":{"sum_foreign_comment":"","sum":"2214","sum_comment":"","sum_hidden":false,"sum_comment_hidden":false,"sum_unclear":false,"sum_foreign":""},"55":{"sum_foreign_comment":"","sum":"","sum_comment":"","sum_foreign":""},"56":{"sum_foreign_comment":"","sum":"","sum_comment":"","sum_foreign":""},"57":{"sum_foreign_comment":"","sum":"48836.91","sum_comment":"","sum_hidden":false,"sum_comment_hidden":false,"sum_unclear":false,"sum_foreign":""},"58":{"sum_foreign_comment":"","sum":"62047.01","sum_comment":"","sum_hidden":false,"sum_comment_hidden":false,"sum_unclear":false,"sum_foreign":""},"59":{"sum_foreign_comment":"","sum":"","sum_comment":"","sum_foreign":""},"60":{"sum_foreign_comment":"","sum":"200","sum_comment":"","sum_hidden":false,"sum_comment_hidden":false,"sum_foreign":""},"61":{"sum_foreign_comment":"","sum":"","sum_comment":"","sum_foreign":""},"62":{"sum_foreign_comment":"","sum":"","sum_comment":"","sum_unclear":false,"sum_foreign":""},"63":{"sum_foreign_comment":"","sum":"","sum_comment":"","sum_unclear":false,"sum_foreign":""},"64":{"sum_foreign_comment":"","sum":"","sum_comment":"","sum_foreign":""}},"ft_src":"48836.91\n2214\n62047.01\n200\nсуддя диканського районного суду полтавської області\nПолтавська область\nЗагальний місцевий суд\nЩабельська Ірина Володимирівна\nЩабельська\nІрина\nЩабельський Р. С\nПодружжя\nЩабельський В. Р\nДитина\nЩабельська К. Р\nДитина\nЩабельська Ірина Володимирівна\nІрина Володимирівна Щабельська\nІрина Щабельська\nЩабельська Ірина Володимирівна\nВолодимирівна\n24965\nпенсія\n24965\n229414.42\n229414.42\nВАЗ 21070\n1452 куб. см., 400.0 см\n2006\nВАЗ 21070\n1452 куб. см., 400.0 см\n2006\n2015\n229414.42\n24965\n229414.42\n24965\nпенсія\nВАЗ 21070\n1452 куб. см., 400.0 см\n2006\n2015\nВолодимирівна\nПодружжя\nЩабельський Р. С\nДитина\nЩабельський В. Р\nДитина\nЩабельська К. Р\nЩабельська\nЩабельська Ірина Володимирівна\nІрина Володимирівна Щабельська\nІрина Щабельська\nЩабельська Ірина Володимирівна\nІрина\nЩабельська Ірина Володимирівна\nЗагальний місцевий суд\nсуддя диканського районного суду полтавської області\nПолтавська область\n62047.01\n200\n48836.91\n2214\n229414.42\n24965\nпенсія\n229414.42\n24965\n62047.01\n48836.91\n2214\n200\nЩабельський Р. С\nПодружжя\nЩабельський В. Р\nДитина\nЩабельська К. Р\nДитина\nВолодимирівна\nЩабельська\nПолтавська область\nЗагальний місцевий суд\nсуддя диканського районного суду полтавської області\nЩабельська Ірина Володимирівна\nЩабельська Ірина Володимирівна\nІрина Володимирівна Щабельська\nІрина Щабельська\nЩабельська Ірина Володимирівна\nІрина\n2015","general":{"inn":"","family_raw":"","last_name":"Щабельська","post":{"post":"суддя диканського районного суду полтавської області","region":"Полтавська область","candidate":"","office_hidden":false,"office":"Загальний місцевий суд","office_unclear":false},"name":"Ірина","full_name":"Щабельська Ірина Володимирівна","inn_hidden":true,"family":[{"inn":"","inn_hidden":true,"inn_unclear":false,"relations_hidden":false,"relations_other":"","relations":"Подружжя","name_hidden":false,"family_name":"Щабельський Р. С","name_unclear":false},{"inn":"","inn_hidden":false,"inn_unclear":false,"relations_hidden":false,"relations_other":"","relations":"Дитина","name_hidden":false,"family_name":"Щабельський В. Р","name_unclear":false},{"inn":"","inn_hidden":false,"inn_unclear":false,"relations_hidden":false,"relations_other":"","relations":"Дитина","name_hidden":false,"family_name":"Щабельська К. Р","name_unclear":false}],"full_name_suggest":{"output":"Щабельська Ірина Володимирівна","input":["Щабельська Ірина Володимирівна","Ірина Володимирівна Щабельська","Ірина Щабельська"]},"patronymic":"Володимирівна"},"source":"VULYK","intro":{"declaration_year":"2015","isnotdeclaration":""}},{"income":{"5":{"value":"258920","family_comment":"","value_unclear":false,"family_unclear":false,"family":"101098","comment":""},"6":{"family_comment":"","value":"220853","value_unclear":false,"family":"","comment":""},"7":{"value":"","value_unclear":false,"family_comment":"","source_name":"","family":"","comment":""},"8":{"family_comment":"","value":"","family":"","comment":""},"9":{"value":"","family_comment":"","value_unclear":false,"family_unclear":false,"family":"","comment":""},"10":{"family_comment":"","value":"","comment_unclear":false,"family":"","comment":""},"11":{"family_comment":"","value":"","family":"","comment":""},"12":{"family_comment":"","value":"","family":"","comment":""},"13":{"family_comment":"","value":"","value_unclear":false,"family":"","comment":""},"14":{"family_comment":"","value":"","family":"","comment":""},"15":{"family_comment":"","value":"","family":"","comment":""},"16":{"family_comment":"","family_unclear":false,"value":"38066","family":"76133","comment":""},"17":{"family_comment":"","family_unclear":false,"value":"","family":"","comment":""},"18":{"family_comment":"","value":"","family":"","comment":""},"19":{"family_comment":"","value":"","family":"","comment":""},"20":{"value":"","family_comment":"пенсія","value_unclear":false,"family_hidden":false,"value_hidden":false,"family_unclear":false,"comment_unclear":false,"comment":"","family":"24965"}},"vehicle":{"40":[{"brand_info":"1452 куб. см., 400.0 см","sum_rent_comment":"","brand":"ВАЗ 21070","sum_comment":"","year":"2006","brand_info_hidden":false,"brand_info_unclear":false,"sum":"","sum_rent":""}]},"id":"vulyk_100_32","banks":{"45":[{"sum_foreign_comment":"","sum_units":"UAH","sum_comment":"","sum_comment_unclear":false,"sum_foreign_units":"UAH","sum_units_unclear":false,"sum_comment_hidden":false,"sum_unclear":false,"sum":"7250","sum_foreign":""}],"46":[{"sum_foreign_comment":"","sum_units":"UAH","sum_comment":"","sum_comment_unclear":false,"sum_foreign_units":"UAH","sum":"7250","sum_unclear":false,"sum_foreign":""}],"47":[{"sum_foreign_comment":"","sum_units":"UAH","sum_comment":"","sum_comment_unclear":false,"sum_foreign_units":"UAH","sum":"12","sum_unclear":false,"sum_foreign":""}],"52":[{"sum_foreign_comment":"","sum_units":"UAH","sum_comment":"","sum_comment_unclear":false,"sum_foreign_units":"UAH","sum":"12","sum_unclear":true,"sum_foreign":""}]},"declaration":{"additional_info_text":"","notfull_lostpages":"","date":"2015-03-25T00:00:00","notfull":"","additional_info":"","url":"http://static.declarations.com.ua/declarations/chosen_ones/judges_batch/4191_shchabelska_iryna_volodymyrivna.pdf"},"liabilities":{"54":{"sum_foreign_comment":"","sum":"2214","sum_comment":"","sum_comment_hidden":false,"sum_unclear":false,"sum_foreign":""},"55":{"sum_foreign_comment":"","sum":"","sum_comment":"","sum_foreign":""},"56":{"sum_foreign_comment":"","sum":"","sum_comment":"","sum_unclear":false,"sum_foreign":""},"57":{"sum_foreign_comment":"","sum":"197473","sum_comment":"","sum_comment_unclear":false,"sum_comment_hidden":false,"sum_unclear":false,"sum_foreign":""},"58":{"sum_foreign_comment":"","sum":"47360","sum_comment":"","sum_comment_hidden":false,"sum_unclear":false,"sum_foreign":""},"59":{"sum_foreign_comment":"","sum":"","sum_comment":"","sum_foreign":""},"60":{"sum_foreign_comment":"","sum_comment_hidden":false,"sum":"200","sum_comment":"","sum_foreign":""},"61":{"sum_foreign_comment":"","sum":"","sum_comment":"","sum_foreign":""},"62":{"sum_foreign_comment":"","sum":"","sum_comment":"","sum_unclear":false,"sum_foreign":""},"63":{"sum_foreign_comment":"","sum_comment_hidden":false,"sum":"","sum_comment":"","sum_foreign":""},"64":{"sum_foreign_comment":"","sum_comment_hidden":false,"sum":"","sum_comment":"","sum_foreign":""}},"ft_src":"197473\n2214\n47360\n200\nЩабельська Ірина Володимирівна\nсуддя диканського районного суду полтавської області\nПолтавська область\nЗагальний місцевий суд\nІрина\nЩабельський Р. С\nПодружжя\nЩабельський В. Р\nДитина\nЩабельська К. Р\nДитина\nЩабельська Ірина Володимирівна\nІрина Володимирівна Щабельська\nІрина Щабельська\nЩабельська Ірина Володимирівна\nЩабельська\nВолодимирівна\n2006\n1452 куб. см., 400.0 см\nВАЗ 21070\n7250\n12\n12\n7250\n2014\nВАЗ 21070\n1452 куб. см., 400.0 см\n2006\n7250\n12\n7250\n12\n31300\nПодружжя\nЩабельський Р. С\nДитина\nЩабельський В. Р\nДитина\nЩабельська К. Р\nВолодимирівна\nЩабельська\nЩабельська Ірина Володимирівна\nІрина Володимирівна Щабельська\nІрина Щабельська\nЩабельська Ірина Володимирівна\nЩабельська Ірина Володимирівна\nІрина\nЗагальний місцевий суд\nПолтавська область\nсуддя диканського районного суду полтавської області\n2214\n197473\n200\n47360\n220853\n24965\nпенсія\n258920\n101098\n38066\n76133\n2014\n47360\n197473\n2214\n200\n31300\nЩабельський Р. С\nПодружжя\nДитина\nЩабельський В. Р\nДитина\nЩабельська К. Р\nВолодимирівна\nЩабельська\nПолтавська область\nЗагальний місцевий суд\nсуддя диканського районного суду полтавської області\nЩабельська Ірина Володимирівна\nЩабельська Ірина Володимирівна\nІрина Володимирівна Щабельська\nІрина Щабельська\nЩабельська Ірина Володимирівна\nІрина\n220853\n101098\n258920\n76133\n38066\n24965\nпенсія\n2006\n1452 куб. см., 400.0 см\nВАЗ 21070\nпенсія\n24965\n258920\n101098\n76133\n38066\n220853\n31300\n12\n7250\n7250\n12\n2014","general":{"inn":"","inn_hidden":true,"last_name":"Щабельська","post":{"post_unclear":false,"region_unclear":false,"post":"суддя диканського районного суду полтавської області","office":"Загальний місцевий суд","region":"Полтавська область","post_hidden":false,"office_unclear":false},"name":"Ірина","full_name":"Щабельська Ірина Володимирівна","family_raw":"","addresses":[{"place_district":"","place_city_hidden":true,"place_city":"","place_city_unclear":false,"place_district_hidden":true,"place_city_type":"","place_address_hidden":true,"place_city_type_hidden":true,"place_address":"","place_hidden":true,"place":""}],"family":[{"inn_hidden":true,"inn":"","name_hidden":true,"family_name":"Щабельський Р. С","relations":"Подружжя","name_unclear":true},{"inn":"","relations":"Дитина","relations_other":"","inn_hidden":false,"family_name":"Щабельський В. Р","name_hidden":false,"name_unclear":true},{"inn":"","relations":"Дитина","relations_other":"","inn_hidden":false,"family_name":"Щабельська К. Р","name_hidden":false,"name_unclear":true}],"full_name_suggest":{"output":"Щабельська Ірина Володимирівна","input":["Щабельська Ірина Володимирівна","Ірина Володимирівна Щабельська","Ірина Щабельська"]},"patronymic":"Володимирівна"},"source":"VULYK","estate":{"23":[{"space_unclear":false,"costs":"","costs_comment":"","address_hidden":true,"region_hidden":true,"space_comment":"","space":"","address":"","costs_comment_unclear":false,"region":"","address_unclear":false,"costs_rent_comment":"","space_comment_unclear":false,"space_units":"м²","costs_rent":""}],"29":[{"region_unclear":false,"space_unclear":false,"address_hidden":false,"region_hidden":true,"space_comment":"","space":"31300","address":"","region":"","costs_property":"","costs_rent_comment":"","address_unclear":false,"space_units":"м²","costs_property_comment":"","costs_rent":""}]},"intro":{"declaration_year":"2014"}}],"declarationsLength":2,"analytics":[{"y":2015,"i":229414.42,"fi":24965,"j":1},{"y":2014,"b":7250,"i":258920,"la":1,"fi":101098,"fl":31300,"fla":1}]}