{"2010":"","2016":"","Department":"Томаківський районний Дніпропетровської області","Region":"Дніпропетровська область","Position":"Суддя Томаківського районного суду Дніпропетровської області","Name":"Тетеревятников Анатолій Петрович","Link":"https://drive.google.com/open?id=0BygiyWAl79DMeXlPSkFYd1dXdzg&authuser=0","Note":"У меня Архив с jpg-файлами","AdditionalNote":"","field8":"","field9":"","Link 2015":"","Кількість справ":"","Оскаржені":"","Кількість скарг":1,"Кількість дисциплінарних стягнень":"","Клейма":3,"Фото":"","Як живе":"","key":"teterevyatnikov_anatoliy_petrovich","allDeclarations":[{"provider":"declarations.com.ua","document":{"income":{"5":{"value":"307395","family_comment":"","value_unclear":false,"family_hidden":false,"family_unclear":false,"family":"41540","comment":""},"6":{"value":"240773","value_unclear":false,"comment_hidden":false,"family_hidden":false,"value_hidden":false,"family_comment":"","family":"28152","comment":""},"7":{"value":"","family_comment":"","source_name":"","family":"","comment":"","source_name_hidden":false},"8":{"family_comment":"","value":"","family":"","comment":""},"9":{"family_comment":"","value":"","family":"","comment":"","value_hidden":false},"10":{"value":"12180","value_unclear":false,"family_hidden":false,"value_hidden":false,"family_comment":"","family":"","comment":""},"11":{"family_comment":"","value":"","family":"","comment":""},"12":{"family_comment":"","value":"","family":"","comment":""},"13":{"family_comment":"","value":"","comment_hidden":false,"family":"","comment":""},"14":{"value":"","comment_hidden":false,"value_hidden":false,"family_comment":"","family":"","comment":""},"15":{"family_comment":"","value":"","family":"","comment":""},"16":{"family_comment":"","value":"","family":"","comment":"","value_hidden":false},"17":{"family_comment":"","value":"","family":"","comment":""},"18":{"family_comment":"","value":"","family":"","comment":""},"19":{"family_comment":"","value":"","family":"","comment":"","value_hidden":false},"20":{"value":"66622","family_comment":"","comment_unclear":false,"family_unclear":false,"family":"13388","comment":""}},"id":"vulyk_12_52","banks":{"45":[{"sum_foreign_comment":"","sum":"","sum_comment":"","sum_hidden":false,"sum_foreign_units":"UAH","sum_foreign_hidden":false,"sum_units":"UAH","sum_comment_hidden":false,"sum_unclear":false,"sum_foreign":"","sum_units_hidden":false},{"sum_foreign_comment":"","sum_units":"","sum_comment":"","sum_foreign_units":"","sum":"","sum_foreign":""}],"46":[{"sum_foreign_comment":"","sum_units":"UAH","sum_comment":"","sum_hidden":false,"sum_foreign_units":"UAH","sum":"","sum_foreign_hidden":false,"sum_foreign":""}],"47":[{"sum_foreign_comment":"","sum_units":"UAH","sum_comment":"","sum_comment_unclear":false,"sum_foreign_units":"UAH","sum":"","sum_foreign":""},{"sum_foreign_comment":"","sum_units":"","sum_comment":"","sum_foreign_units":"","sum":"","sum_foreign":""}],"48":[{"sum_foreign_comment":"","sum_units":"UAH","sum_comment":"","sum_foreign_units":"UAH","sum":"","sum_foreign":""}],"49":[{"sum_foreign_comment":"","sum_units":"UAH","sum_comment":"","sum_foreign_units":"UAH","sum":"","sum_foreign":""}],"50":[{"sum_foreign_comment":"","sum_units":"UAH","sum_comment":"","sum_foreign_units":"UAH","sum":"","sum_foreign":""}],"51":[{"sum_foreign_comment":"","sum_units":"UAH","sum_comment":"","sum_hidden":false,"sum_foreign_units":"UAH","sum_comment_hidden":false,"sum_units_hidden":false,"sum":"","sum_foreign":""}],"52":[{"sum_foreign_comment":"","sum_units":"UAH","sum_comment":"","sum_comment_unclear":false,"sum_foreign_units":"UAH","sum":"","sum_foreign":""},{"sum_foreign_comment":"","sum_units":"","sum_comment":"","sum_foreign_units":"","sum":"","sum_foreign":""},{"sum_foreign_comment":"","sum_units":"","sum_comment":"","sum_foreign_units":"","sum":"","sum_foreign":""},{"sum_foreign_comment":"","sum_units":"","sum_comment":"","sum_foreign_units":"","sum":"","sum_foreign":""}],"53":[{"sum_foreign_comment":"","sum_units":"UAH","sum_comment":"","sum_foreign_units":"UAH","sum":"","sum_foreign":""}]},"declaration":{"additional_info_text":"","notfull_lostpages":"","date":"2015-03-27T00:00:00","notfull":"","additional_info":"","url":"http://static.declarations.com.ua/declarations/chosen_ones/mega_batch/tetereviatnykov_anatolii_petrovych.pdf"},"liabilities":{"54":{"sum_foreign_comment":"","sum":"","sum_comment":"","sum_hidden":false,"sum_comment_hidden":false,"sum_foreign":""},"55":{"sum_foreign_comment":"","sum":"","sum_comment":"","sum_foreign":""},"56":{"sum_foreign_comment":"","sum":"","sum_comment":"","sum_foreign":""},"57":{"sum_foreign_comment":"","sum":"","sum_comment":"","sum_comment_unclear":false,"sum_hidden":false,"sum_comment_hidden":false,"sum_unclear":false,"sum_foreign":""},"58":{"sum_foreign_comment":"","sum":"","sum_comment":"","sum_comment_unclear":false,"sum_hidden":false,"sum_foreign":""},"59":{"sum_foreign_comment":"","sum":"5000","sum_hidden":false,"sum_comment":"","sum_foreign":""},"60":{"sum_foreign_comment":"","sum":"","sum_comment":"","sum_hidden":false,"sum_comment_hidden":false,"sum_foreign":""},"61":{"sum_foreign_comment":"","sum":"","sum_comment":"","sum_foreign":""},"62":{"sum_foreign_comment":"","sum":"12000","sum_comment":"","sum_comment_unclear":false,"sum_unclear":false,"sum_foreign":""},"63":{"sum_foreign_comment":"","sum":"","sum_comment":"","sum_comment_unclear":false,"sum_foreign":""},"64":{"sum_foreign_comment":"","sum":"","sum_comment":"","sum_comment_unclear":false,"sum_foreign":""}},"ft_src":"5000\n12000\nсуддя\nДніпропетровська область\nЗагальний місцевий суд\nАнатолій\nПрокопенко Любов Іванівна\nПодружжя\nПетрович\nТетеревятников\nТетеревятников Анатолій Петрович\nТетеревятников Анатолій Петрович\nАнатолій Петрович Тетеревятников\nАнатолій Тетеревятников\nТетеревятников Анатолій Петрович\n12180\n66622\n13388\n307395\n41540\n240773\n28152\nсмт. Томаківка, вул. Леніна,35,\n19.25\nДніпропетровська область\nДніпропетровська область\nТолмаківський район, смт. Томаківка\n76000\nДніпропетровська область\nсмт. Томаківка, вул. Леніна,39,кв. 9\n20.5\nсмт. Томаківка, вул. Леніна,35, кв. 7\n52.75\nДніпропетровська область\n2014\n28152\n240773\n12180\n41540\n307395\n13388\n66622\n2014\nЗагальний місцевий суд\nсуддя\nДніпропетровська область\nПодружжя\nПрокопенко Любов Іванівна\nТетеревятников Анатолій Петрович\nАнатолій Петрович Тетеревятников\nАнатолій Тетеревятников\nТетеревятников Анатолій Петрович\nАнатолій\nТетеревятников Анатолій Петрович\nТетеревятников\nПетрович\n5000\n12000\n240773\n28152\n66622\n13388\n41540\n307395\n12180\n76000\nТолмаківський район, смт. Томаківка\nДніпропетровська область\n19.25\nсмт. Томаківка, вул. Леніна,35,\nДніпропетровська область\nсмт. Томаківка, вул. Леніна,39,кв. 9\nДніпропетровська область\n20.5\n52.75\nДніпропетровська область\nсмт. Томаківка, вул. Леніна,35, кв. 7\n12000\n5000\nПодружжя\nПрокопенко Любов Іванівна\nПетрович\nТетеревятников\nАнатолій\nТетеревятников Анатолій Петрович\nАнатолій Петрович Тетеревятников\nАнатолій Тетеревятников\nТетеревятников Анатолій Петрович\nДніпропетровська область\nЗагальний місцевий суд\nсуддя\nТетеревятников Анатолій Петрович\nсмт. Томаківка, вул. Леніна,39,кв. 9\nДніпропетровська область\n20.5\nсмт. Томаківка, вул. Леніна,35,\nДніпропетровська область\n19.25\nсмт. Томаківка, вул. Леніна,35, кв. 7\nДніпропетровська область\n52.75\nТолмаківський район, смт. Томаківка\nДніпропетровська область\n76000\n2014","general":{"inn":"","name":"Анатолій","patronymic_unclear":false,"last_name_hidden":false,"family":[{"inn":"","inn_hidden":true,"relations_unclear":false,"relations_hidden":false,"relations_other":"","relations":"Подружжя","name_hidden":false,"inn_unclear":false,"family_name":"Прокопенко Любов Іванівна","name_unclear":false}],"patronymic":"Петрович","inn_hidden":true,"family_raw":"","inn_unclear":false,"post":{"post_unclear":false,"post":"суддя","candidate":"","office_hidden":false,"region":"Дніпропетровська область","post_hidden":false,"office":"Загальний місцевий суд","office_unclear":false},"last_name_unclear":false,"full_name":"Тетеревятников Анатолій Петрович","addresses":[{"place_district":"","place_city_hidden":true,"place_city":"","place_city_type_hidden":true,"place_district_hidden":true,"place_city_type":"","place_address_hidden":false,"place_address":"","place_hidden":true,"place":""}],"last_name":"Тетеревятников","patronymic_hidden":false,"full_name_suggest":{"output":"Тетеревятников Анатолій Петрович","input":["Тетеревятников Анатолій Петрович","Анатолій Петрович Тетеревятников","Анатолій Тетеревятников"]}},"source":"VULYK","estate":{"23":[{"space_unclear":false,"costs":"","costs_comment":"","address_hidden":false,"region_hidden":false,"space_comment":"","space_hidden":false,"space":"","address":"","costs_comment_unclear":false,"region":"","address_unclear":false,"costs_rent_comment":"","space_units":"м²","costs_rent":""},{"space_unclear":false,"costs":"","costs_comment":"","address_hidden":false,"region_hidden":false,"space_comment":"","space":"","address":"","region":"","costs_rent_comment":"","space_units":"","costs_rent":""},{"space_hidden":false,"costs":"","costs_comment":"","address_hidden":false,"region_hidden":false,"space_comment":"","space":"","address":"","region":"","costs_rent_comment":"","space_units":"","costs_rent":""},{"costs_rent":"","region":"","costs":"","costs_rent_comment":"","costs_comment":"","space_comment":"","space_units":"","space":"","address":""}],"25":[{"region_unclear":false,"space_hidden":false,"costs":"","costs_comment":"","costs_hidden":false,"address_hidden":false,"region_hidden":false,"space_comment":"","space_unclear":false,"space":"52.75","address":"смт. Томаківка, вул. Леніна,35, кв. 7","region":"Дніпропетровська область","address_unclear":false,"costs_rent_comment":"","costs_rent_hidden":false,"space_comment_unclear":false,"space_units":"м²","costs_rent":""}],"27":[{"space_hidden":false,"costs":"","costs_comment":"","address_hidden":false,"region_hidden":false,"space_comment":"","space":"19.25","address":"смт. Томаківка, вул. Леніна,35,","region":"Дніпропетровська область","costs_rent_comment":"","space_units":"м²","costs_rent":""}],"29":[{"region_unclear":false,"space_unclear":false,"address_hidden":false,"region_hidden":false,"space_comment":"","space":"76000","address":"Толмаківський район, смт. Томаківка","region":"Дніпропетровська область","costs_property":"","costs_rent_comment":"","space_comment_unclear":false,"address_unclear":false,"space_units":"м²","costs_property_comment":"","costs_rent":""}],"31":[{"space_hidden":false,"costs_property_hidden":false,"address_hidden":false,"region_hidden":false,"space_comment":"","space":"20.5","address":"смт. Томаківка, вул. Леніна,39,кв. 9","region":"Дніпропетровська область","costs_property":"","costs_rent_comment":"","costs_rent_hidden":false,"space_units":"м²","costs_property_comment":"","costs_rent":""}]},"intro":{"declaration_year":"2014","isnotdeclaration":""}}}],"declarations":[{"income":{"5":{"value":"307395","family_comment":"","value_unclear":false,"family_hidden":false,"family_unclear":false,"family":"41540","comment":""},"6":{"value":"240773","value_unclear":false,"comment_hidden":false,"family_hidden":false,"value_hidden":false,"family_comment":"","family":"28152","comment":""},"7":{"value":"","family_comment":"","source_name":"","family":"","comment":"","source_name_hidden":false},"8":{"family_comment":"","value":"","family":"","comment":""},"9":{"family_comment":"","value":"","family":"","comment":"","value_hidden":false},"10":{"value":"12180","value_unclear":false,"family_hidden":false,"value_hidden":false,"family_comment":"","family":"","comment":""},"11":{"family_comment":"","value":"","family":"","comment":""},"12":{"family_comment":"","value":"","family":"","comment":""},"13":{"family_comment":"","value":"","comment_hidden":false,"family":"","comment":""},"14":{"value":"","comment_hidden":false,"value_hidden":false,"family_comment":"","family":"","comment":""},"15":{"family_comment":"","value":"","family":"","comment":""},"16":{"family_comment":"","value":"","family":"","comment":"","value_hidden":false},"17":{"family_comment":"","value":"","family":"","comment":""},"18":{"family_comment":"","value":"","family":"","comment":""},"19":{"family_comment":"","value":"","family":"","comment":"","value_hidden":false},"20":{"value":"66622","family_comment":"","comment_unclear":false,"family_unclear":false,"family":"13388","comment":""}},"id":"vulyk_12_52","banks":{"45":[{"sum_foreign_comment":"","sum":"","sum_comment":"","sum_hidden":false,"sum_foreign_units":"UAH","sum_foreign_hidden":false,"sum_units":"UAH","sum_comment_hidden":false,"sum_unclear":false,"sum_foreign":"","sum_units_hidden":false},{"sum_foreign_comment":"","sum_units":"","sum_comment":"","sum_foreign_units":"","sum":"","sum_foreign":""}],"46":[{"sum_foreign_comment":"","sum_units":"UAH","sum_comment":"","sum_hidden":false,"sum_foreign_units":"UAH","sum":"","sum_foreign_hidden":false,"sum_foreign":""}],"47":[{"sum_foreign_comment":"","sum_units":"UAH","sum_comment":"","sum_comment_unclear":false,"sum_foreign_units":"UAH","sum":"","sum_foreign":""},{"sum_foreign_comment":"","sum_units":"","sum_comment":"","sum_foreign_units":"","sum":"","sum_foreign":""}],"48":[{"sum_foreign_comment":"","sum_units":"UAH","sum_comment":"","sum_foreign_units":"UAH","sum":"","sum_foreign":""}],"49":[{"sum_foreign_comment":"","sum_units":"UAH","sum_comment":"","sum_foreign_units":"UAH","sum":"","sum_foreign":""}],"50":[{"sum_foreign_comment":"","sum_units":"UAH","sum_comment":"","sum_foreign_units":"UAH","sum":"","sum_foreign":""}],"51":[{"sum_foreign_comment":"","sum_units":"UAH","sum_comment":"","sum_hidden":false,"sum_foreign_units":"UAH","sum_comment_hidden":false,"sum_units_hidden":false,"sum":"","sum_foreign":""}],"52":[{"sum_foreign_comment":"","sum_units":"UAH","sum_comment":"","sum_comment_unclear":false,"sum_foreign_units":"UAH","sum":"","sum_foreign":""},{"sum_foreign_comment":"","sum_units":"","sum_comment":"","sum_foreign_units":"","sum":"","sum_foreign":""},{"sum_foreign_comment":"","sum_units":"","sum_comment":"","sum_foreign_units":"","sum":"","sum_foreign":""},{"sum_foreign_comment":"","sum_units":"","sum_comment":"","sum_foreign_units":"","sum":"","sum_foreign":""}],"53":[{"sum_foreign_comment":"","sum_units":"UAH","sum_comment":"","sum_foreign_units":"UAH","sum":"","sum_foreign":""}]},"declaration":{"additional_info_text":"","notfull_lostpages":"","date":"2015-03-27T00:00:00","notfull":"","additional_info":"","url":"http://static.declarations.com.ua/declarations/chosen_ones/mega_batch/tetereviatnykov_anatolii_petrovych.pdf"},"liabilities":{"54":{"sum_foreign_comment":"","sum":"","sum_comment":"","sum_hidden":false,"sum_comment_hidden":false,"sum_foreign":""},"55":{"sum_foreign_comment":"","sum":"","sum_comment":"","sum_foreign":""},"56":{"sum_foreign_comment":"","sum":"","sum_comment":"","sum_foreign":""},"57":{"sum_foreign_comment":"","sum":"","sum_comment":"","sum_comment_unclear":false,"sum_hidden":false,"sum_comment_hidden":false,"sum_unclear":false,"sum_foreign":""},"58":{"sum_foreign_comment":"","sum":"","sum_comment":"","sum_comment_unclear":false,"sum_hidden":false,"sum_foreign":""},"59":{"sum_foreign_comment":"","sum":"5000","sum_hidden":false,"sum_comment":"","sum_foreign":""},"60":{"sum_foreign_comment":"","sum":"","sum_comment":"","sum_hidden":false,"sum_comment_hidden":false,"sum_foreign":""},"61":{"sum_foreign_comment":"","sum":"","sum_comment":"","sum_foreign":""},"62":{"sum_foreign_comment":"","sum":"12000","sum_comment":"","sum_comment_unclear":false,"sum_unclear":false,"sum_foreign":""},"63":{"sum_foreign_comment":"","sum":"","sum_comment":"","sum_comment_unclear":false,"sum_foreign":""},"64":{"sum_foreign_comment":"","sum":"","sum_comment":"","sum_comment_unclear":false,"sum_foreign":""}},"ft_src":"5000\n12000\nсуддя\nДніпропетровська область\nЗагальний місцевий суд\nАнатолій\nПрокопенко Любов Іванівна\nПодружжя\nПетрович\nТетеревятников\nТетеревятников Анатолій Петрович\nТетеревятников Анатолій Петрович\nАнатолій Петрович Тетеревятников\nАнатолій Тетеревятников\nТетеревятников Анатолій Петрович\n12180\n66622\n13388\n307395\n41540\n240773\n28152\nсмт. Томаківка, вул. Леніна,35,\n19.25\nДніпропетровська область\nДніпропетровська область\nТолмаківський район, смт. Томаківка\n76000\nДніпропетровська область\nсмт. Томаківка, вул. Леніна,39,кв. 9\n20.5\nсмт. Томаківка, вул. Леніна,35, кв. 7\n52.75\nДніпропетровська область\n2014\n28152\n240773\n12180\n41540\n307395\n13388\n66622\n2014\nЗагальний місцевий суд\nсуддя\nДніпропетровська область\nПодружжя\nПрокопенко Любов Іванівна\nТетеревятников Анатолій Петрович\nАнатолій Петрович Тетеревятников\nАнатолій Тетеревятников\nТетеревятников Анатолій Петрович\nАнатолій\nТетеревятников Анатолій Петрович\nТетеревятников\nПетрович\n5000\n12000\n240773\n28152\n66622\n13388\n41540\n307395\n12180\n76000\nТолмаківський район, смт. Томаківка\nДніпропетровська область\n19.25\nсмт. Томаківка, вул. Леніна,35,\nДніпропетровська область\nсмт. Томаківка, вул. Леніна,39,кв. 9\nДніпропетровська область\n20.5\n52.75\nДніпропетровська область\nсмт. Томаківка, вул. Леніна,35, кв. 7\n12000\n5000\nПодружжя\nПрокопенко Любов Іванівна\nПетрович\nТетеревятников\nАнатолій\nТетеревятников Анатолій Петрович\nАнатолій Петрович Тетеревятников\nАнатолій Тетеревятников\nТетеревятников Анатолій Петрович\nДніпропетровська область\nЗагальний місцевий суд\nсуддя\nТетеревятников Анатолій Петрович\nсмт. Томаківка, вул. Леніна,39,кв. 9\nДніпропетровська область\n20.5\nсмт. Томаківка, вул. Леніна,35,\nДніпропетровська область\n19.25\nсмт. Томаківка, вул. Леніна,35, кв. 7\nДніпропетровська область\n52.75\nТолмаківський район, смт. Томаківка\nДніпропетровська область\n76000\n2014","general":{"inn":"","name":"Анатолій","patronymic_unclear":false,"last_name_hidden":false,"family":[{"inn":"","inn_hidden":true,"relations_unclear":false,"relations_hidden":false,"relations_other":"","relations":"Подружжя","name_hidden":false,"inn_unclear":false,"family_name":"Прокопенко Любов Іванівна","name_unclear":false}],"patronymic":"Петрович","inn_hidden":true,"family_raw":"","inn_unclear":false,"post":{"post_unclear":false,"post":"суддя","candidate":"","office_hidden":false,"region":"Дніпропетровська область","post_hidden":false,"office":"Загальний місцевий суд","office_unclear":false},"last_name_unclear":false,"full_name":"Тетеревятников Анатолій Петрович","addresses":[{"place_district":"","place_city_hidden":true,"place_city":"","place_city_type_hidden":true,"place_district_hidden":true,"place_city_type":"","place_address_hidden":false,"place_address":"","place_hidden":true,"place":""}],"last_name":"Тетеревятников","patronymic_hidden":false,"full_name_suggest":{"output":"Тетеревятников Анатолій Петрович","input":["Тетеревятников Анатолій Петрович","Анатолій Петрович Тетеревятников","Анатолій Тетеревятников"]}},"source":"VULYK","estate":{"23":[{"space_unclear":false,"costs":"","costs_comment":"","address_hidden":false,"region_hidden":false,"space_comment":"","space_hidden":false,"space":"","address":"","costs_comment_unclear":false,"region":"","address_unclear":false,"costs_rent_comment":"","space_units":"м²","costs_rent":""},{"space_unclear":false,"costs":"","costs_comment":"","address_hidden":false,"region_hidden":false,"space_comment":"","space":"","address":"","region":"","costs_rent_comment":"","space_units":"","costs_rent":""},{"space_hidden":false,"costs":"","costs_comment":"","address_hidden":false,"region_hidden":false,"space_comment":"","space":"","address":"","region":"","costs_rent_comment":"","space_units":"","costs_rent":""},{"costs_rent":"","region":"","costs":"","costs_rent_comment":"","costs_comment":"","space_comment":"","space_units":"","space":"","address":""}],"25":[{"region_unclear":false,"space_hidden":false,"costs":"","costs_comment":"","costs_hidden":false,"address_hidden":false,"region_hidden":false,"space_comment":"","space_unclear":false,"space":"52.75","address":"смт. Томаківка, вул. Леніна,35, кв. 7","region":"Дніпропетровська область","address_unclear":false,"costs_rent_comment":"","costs_rent_hidden":false,"space_comment_unclear":false,"space_units":"м²","costs_rent":""}],"27":[{"space_hidden":false,"costs":"","costs_comment":"","address_hidden":false,"region_hidden":false,"space_comment":"","space":"19.25","address":"смт. Томаківка, вул. Леніна,35,","region":"Дніпропетровська область","costs_rent_comment":"","space_units":"м²","costs_rent":""}],"29":[{"region_unclear":false,"space_unclear":false,"address_hidden":false,"region_hidden":false,"space_comment":"","space":"76000","address":"Толмаківський район, смт. Томаківка","region":"Дніпропетровська область","costs_property":"","costs_rent_comment":"","space_comment_unclear":false,"address_unclear":false,"space_units":"м²","costs_property_comment":"","costs_rent":""}],"31":[{"space_hidden":false,"costs_property_hidden":false,"address_hidden":false,"region_hidden":false,"space_comment":"","space":"20.5","address":"смт. Томаківка, вул. Леніна,39,кв. 9","region":"Дніпропетровська область","costs_property":"","costs_rent_comment":"","costs_rent_hidden":false,"space_units":"м²","costs_property_comment":"","costs_rent":""}]},"intro":{"declaration_year":"2014","isnotdeclaration":""}}],"declarationsLength":1,"analytics":[{"y":2014,"i":307395,"k":52.75,"ka":1,"la":4,"fi":41540,"ff":20.5,"ffa":1,"fl":76000,"fla":1}]}