{"2010":"","2016":"","Department":"Житомирський окружний адміністративний суд","Region":"Житомирська область","Position":"Суддя Житомирського окружного адміністративного суду","Name":"Токарева Марія Сергівна","Link":"https://drive.google.com/open?id=0BygiyWAl79DMWTlDRDlQQ1FuNW8","Note":"У меня","AdditionalNote":"","field8":"","Link 2015":"","field10":"","Кількість справ":"","Оскаржені":"","Кількість скарг":3,"Кількість дисциплінарних стягнень":"","Клейма":"","Фото":"","Як живе":"","key":"tokareva_mariya_sergivna","allDeclarations":[{"provider":"declarations.com.ua","document":{"income":{"5":{"value":"215759.77","family_comment":"","value_unclear":false,"family_hidden":false,"value_hidden":false,"family_unclear":false,"family":"","comment":"","family_comment_unclear":false},"6":{"family_comment":"","family_unclear":false,"value":"215759.77","family":"","comment":""},"7":{"source_name_unclear":false,"value":"","family_comment":"","source_name":"","family":"","comment":"","source_name_hidden":false},"8":{"family_comment":"","value":"","family":"","comment":""},"9":{"family_comment":"","family_unclear":false,"value":"","family":"","comment":""},"10":{"family_comment":"","value":"","family":"","comment":""},"11":{"family_comment":"","value":"","family":"","comment":""},"12":{"family_comment":"","value":"","family":"","comment":""},"13":{"family_comment":"","value":"","family":"","comment":""},"14":{"family_comment":"","value":"","family":"","comment":""},"15":{"family_comment":"","value":"","family":"","comment":""},"16":{"value":"","value_unclear":false,"value_hidden":false,"family_comment":"","family":"","comment":""},"17":{"family_comment":"","value":"","family":"","comment":""},"18":{"family_comment":"","value":"","family":"","comment":""},"19":{"family_comment":"","value":"","family":"","comment":""},"20":{"value":"","family_comment":"","value_unclear":false,"comment_hidden":false,"family_hidden":false,"family":"","value_hidden":false,"family_unclear":false,"comment_unclear":false,"comment":"","family_comment_unclear":false}},"vehicle":{"35":[{"year_hidden":false,"brand_info":"1996 куб. см., 147 кВт , 450 см","sum_rent_comment":"","sum_rent_hidden":false,"year":"2006","sum_hidden":false,"brand_info_hidden":false,"brand_info_unclear":false,"year_unclear":false,"sum_rent":"","sum":"","brand":"SsangYong","sum_comment":"","brand_unclear":false,"brand_hidden":true}]},"id":"vulyk_62_51","declaration":{"additional_info_text":"","notfull_lostpages":"","date":"2015-03-30T00:00:00","notfull":"","additional_info":"","url":"http://static.declarations.com.ua/declarations/chosen_ones/mega_batch/tokareva_mariia_serhivna.pdf"},"liabilities":{"54":{"sum_foreign_comment":"","sum":"","sum_comment":"","sum_hidden":false,"sum_comment_hidden":false,"sum_foreign":""},"55":{"sum_foreign_comment":"","sum":"","sum_comment":"","sum_hidden":false,"sum_comment_hidden":false,"sum_unclear":false,"sum_foreign":""},"56":{"sum_foreign_comment":"","sum":"","sum_comment":"","sum_hidden":false,"sum_unclear":false,"sum_foreign":""},"57":{"sum_foreign_comment":"","sum":"","sum_comment":"","sum_hidden":false,"sum_comment_hidden":false,"sum_unclear":false,"sum_foreign":""},"58":{"sum_foreign_comment":"","sum_foreign_hidden":false,"sum_comment":"","sum_hidden":false,"sum_comment_hidden":false,"sum_unclear":false,"sum":"","sum_foreign":""},"59":{"sum_foreign_comment":"","sum":"","sum_comment":"","sum_foreign":""},"60":{"sum_foreign_comment":"","sum_foreign_hidden":false,"sum_comment":"","sum_hidden":false,"sum_comment_hidden":false,"sum_unclear":false,"sum":"","sum_foreign":""},"61":{"sum_foreign_comment":"","sum_foreign_hidden":false,"sum_comment":"","sum_hidden":false,"sum":"","sum_foreign":""},"62":{"sum_foreign_comment":"","sum":"","sum_comment":"","sum_unclear":false,"sum_foreign":""},"63":{"sum_foreign_comment":"","sum":"","sum_comment":"","sum_hidden":false,"sum_comment_hidden":false,"sum_unclear":false,"sum_foreign":""},"64":{"sum_foreign_comment":"","sum":"","sum_comment":"","sum_comment_unclear":false,"sum_hidden":false,"sum_comment_hidden":false,"sum_foreign":""}},"ft_src":"суддя житомирського окружного адміністративного суду\nЖитомирська область\nАдміністративний місцевий суд\nМарія\nЕнченко І. М. 10. 12. 2010\nДитина\nСергіївна\nТокарева Марія Сергіївна\nМарія Сергіївна Токарева\nМарія Токарева\nТокарева Марія Сергіївна\nТокарева Марія Сергіївна\nТокарева\n1996 куб. см., 147 кВт , 450 см\nSsangYong\n2006\nкористування\n43.8\n2014\n215759.77\n215759.77\n1996 куб. см., 147 кВт , 450 см\nSsangYong\n2006\n43.8\nкористування\nДитина\nЕнченко І. М. 10. 12. 2010\nТокарева Марія Сергіївна\nМарія Сергіївна Токарева\nМарія Токарева\nТокарева Марія Сергіївна\nТокарева Марія Сергіївна\nМарія\nСергіївна\nАдміністративний місцевий суд\nсуддя житомирського окружного адміністративного суду\nЖитомирська область\nТокарева\n215759.77\n215759.77\n2014\nДитина\nЕнченко І. М. 10. 12. 2010\nСергіївна\nТокарева\nМарія\nТокарева Марія Сергіївна\nМарія Сергіївна Токарева\nМарія Токарева\nТокарева Марія Сергіївна\nЖитомирська область\nсуддя житомирського окружного адміністративного суду\nАдміністративний місцевий суд\nТокарева Марія Сергіївна\nSsangYong\n1996 куб. см., 147 кВт , 450 см\n2006\n215759.77\n215759.77\nкористування\n43.8\n2014","general":{"inn":"","name":"Марія","inn_unclear":false,"family":[{"inn":"","inn_hidden":true,"relations_unclear":false,"relations_hidden":false,"relations_other":"","relations":"Дитина","name_hidden":false,"inn_unclear":false,"family_name":"Енченко І. М. 10. 12. 2010","name_unclear":false}],"inn_hidden":true,"family_raw":"","last_name":"Токарева","post":{"post_unclear":false,"post":"суддя житомирського окружного адміністративного суду","post_hidden":false,"region":"Житомирська область","region_hidden":false,"office":"Адміністративний місцевий суд","office_hidden":false,"office_unclear":false},"full_name_suggest":{"output":"Токарева Марія Сергіївна","input":["Токарева Марія Сергіївна","Марія Сергіївна Токарева","Марія Токарева"]},"full_name":"Токарева Марія Сергіївна","addresses":[{"place_city_type_unclear":false,"place_address":"","place_district_hidden":true,"place_city_type":"","place_address_hidden":false,"place_address_unclear":false,"place_city_type_hidden":false,"place":"","place_district":"","place_unclear":false,"place_city":"","place_city_unclear":false,"place_hidden":true,"place_city_hidden":true,"place_district_unclear":false}],"patronymic":"Сергіївна","last_name_unclear":false,"name_unclear":false},"source":"VULYK","estate":{"25":[{"region_unclear":false,"space_hidden":false,"costs":"","costs_comment":"","costs_hidden":false,"address_hidden":false,"region_hidden":true,"space_comment":"користування","space_unclear":false,"space":"43.8","address":"","region":"","costs_rent_comment":"","space_units":"м²","costs_rent":""}]},"intro":{"declaration_year":"2014","isnotdeclaration":"","declaration_year_unclear":false,"declaration_year_hidden":false}}}],"declarations":[{"income":{"5":{"value":"215759.77","family_comment":"","value_unclear":false,"family_hidden":false,"value_hidden":false,"family_unclear":false,"family":"","comment":"","family_comment_unclear":false},"6":{"family_comment":"","family_unclear":false,"value":"215759.77","family":"","comment":""},"7":{"source_name_unclear":false,"value":"","family_comment":"","source_name":"","family":"","comment":"","source_name_hidden":false},"8":{"family_comment":"","value":"","family":"","comment":""},"9":{"family_comment":"","family_unclear":false,"value":"","family":"","comment":""},"10":{"family_comment":"","value":"","family":"","comment":""},"11":{"family_comment":"","value":"","family":"","comment":""},"12":{"family_comment":"","value":"","family":"","comment":""},"13":{"family_comment":"","value":"","family":"","comment":""},"14":{"family_comment":"","value":"","family":"","comment":""},"15":{"family_comment":"","value":"","family":"","comment":""},"16":{"value":"","value_unclear":false,"value_hidden":false,"family_comment":"","family":"","comment":""},"17":{"family_comment":"","value":"","family":"","comment":""},"18":{"family_comment":"","value":"","family":"","comment":""},"19":{"family_comment":"","value":"","family":"","comment":""},"20":{"value":"","family_comment":"","value_unclear":false,"comment_hidden":false,"family_hidden":false,"family":"","value_hidden":false,"family_unclear":false,"comment_unclear":false,"comment":"","family_comment_unclear":false}},"vehicle":{"35":[{"year_hidden":false,"brand_info":"1996 куб. см., 147 кВт , 450 см","sum_rent_comment":"","sum_rent_hidden":false,"year":"2006","sum_hidden":false,"brand_info_hidden":false,"brand_info_unclear":false,"year_unclear":false,"sum_rent":"","sum":"","brand":"SsangYong","sum_comment":"","brand_unclear":false,"brand_hidden":true}]},"id":"vulyk_62_51","declaration":{"additional_info_text":"","notfull_lostpages":"","date":"2015-03-30T00:00:00","notfull":"","additional_info":"","url":"http://static.declarations.com.ua/declarations/chosen_ones/mega_batch/tokareva_mariia_serhivna.pdf"},"liabilities":{"54":{"sum_foreign_comment":"","sum":"","sum_comment":"","sum_hidden":false,"sum_comment_hidden":false,"sum_foreign":""},"55":{"sum_foreign_comment":"","sum":"","sum_comment":"","sum_hidden":false,"sum_comment_hidden":false,"sum_unclear":false,"sum_foreign":""},"56":{"sum_foreign_comment":"","sum":"","sum_comment":"","sum_hidden":false,"sum_unclear":false,"sum_foreign":""},"57":{"sum_foreign_comment":"","sum":"","sum_comment":"","sum_hidden":false,"sum_comment_hidden":false,"sum_unclear":false,"sum_foreign":""},"58":{"sum_foreign_comment":"","sum_foreign_hidden":false,"sum_comment":"","sum_hidden":false,"sum_comment_hidden":false,"sum_unclear":false,"sum":"","sum_foreign":""},"59":{"sum_foreign_comment":"","sum":"","sum_comment":"","sum_foreign":""},"60":{"sum_foreign_comment":"","sum_foreign_hidden":false,"sum_comment":"","sum_hidden":false,"sum_comment_hidden":false,"sum_unclear":false,"sum":"","sum_foreign":""},"61":{"sum_foreign_comment":"","sum_foreign_hidden":false,"sum_comment":"","sum_hidden":false,"sum":"","sum_foreign":""},"62":{"sum_foreign_comment":"","sum":"","sum_comment":"","sum_unclear":false,"sum_foreign":""},"63":{"sum_foreign_comment":"","sum":"","sum_comment":"","sum_hidden":false,"sum_comment_hidden":false,"sum_unclear":false,"sum_foreign":""},"64":{"sum_foreign_comment":"","sum":"","sum_comment":"","sum_comment_unclear":false,"sum_hidden":false,"sum_comment_hidden":false,"sum_foreign":""}},"ft_src":"суддя житомирського окружного адміністративного суду\nЖитомирська область\nАдміністративний місцевий суд\nМарія\nЕнченко І. М. 10. 12. 2010\nДитина\nСергіївна\nТокарева Марія Сергіївна\nМарія Сергіївна Токарева\nМарія Токарева\nТокарева Марія Сергіївна\nТокарева Марія Сергіївна\nТокарева\n1996 куб. см., 147 кВт , 450 см\nSsangYong\n2006\nкористування\n43.8\n2014\n215759.77\n215759.77\n1996 куб. см., 147 кВт , 450 см\nSsangYong\n2006\n43.8\nкористування\nДитина\nЕнченко І. М. 10. 12. 2010\nТокарева Марія Сергіївна\nМарія Сергіївна Токарева\nМарія Токарева\nТокарева Марія Сергіївна\nТокарева Марія Сергіївна\nМарія\nСергіївна\nАдміністративний місцевий суд\nсуддя житомирського окружного адміністративного суду\nЖитомирська область\nТокарева\n215759.77\n215759.77\n2014\nДитина\nЕнченко І. М. 10. 12. 2010\nСергіївна\nТокарева\nМарія\nТокарева Марія Сергіївна\nМарія Сергіївна Токарева\nМарія Токарева\nТокарева Марія Сергіївна\nЖитомирська область\nсуддя житомирського окружного адміністративного суду\nАдміністративний місцевий суд\nТокарева Марія Сергіївна\nSsangYong\n1996 куб. см., 147 кВт , 450 см\n2006\n215759.77\n215759.77\nкористування\n43.8\n2014","general":{"inn":"","name":"Марія","inn_unclear":false,"family":[{"inn":"","inn_hidden":true,"relations_unclear":false,"relations_hidden":false,"relations_other":"","relations":"Дитина","name_hidden":false,"inn_unclear":false,"family_name":"Енченко І. М. 10. 12. 2010","name_unclear":false}],"inn_hidden":true,"family_raw":"","last_name":"Токарева","post":{"post_unclear":false,"post":"суддя житомирського окружного адміністративного суду","post_hidden":false,"region":"Житомирська область","region_hidden":false,"office":"Адміністративний місцевий суд","office_hidden":false,"office_unclear":false},"full_name_suggest":{"output":"Токарева Марія Сергіївна","input":["Токарева Марія Сергіївна","Марія Сергіївна Токарева","Марія Токарева"]},"full_name":"Токарева Марія Сергіївна","addresses":[{"place_city_type_unclear":false,"place_address":"","place_district_hidden":true,"place_city_type":"","place_address_hidden":false,"place_address_unclear":false,"place_city_type_hidden":false,"place":"","place_district":"","place_unclear":false,"place_city":"","place_city_unclear":false,"place_hidden":true,"place_city_hidden":true,"place_district_unclear":false}],"patronymic":"Сергіївна","last_name_unclear":false,"name_unclear":false},"source":"VULYK","estate":{"25":[{"region_unclear":false,"space_hidden":false,"costs":"","costs_comment":"","costs_hidden":false,"address_hidden":false,"region_hidden":true,"space_comment":"користування","space_unclear":false,"space":"43.8","address":"","region":"","costs_rent_comment":"","space_units":"м²","costs_rent":""}]},"intro":{"declaration_year":"2014","isnotdeclaration":"","declaration_year_unclear":false,"declaration_year_hidden":false}}],"declarationsLength":1,"analytics":[{"y":2014,"i":215759.77,"c":1,"k":43.8,"ka":1}]}