{"2010":"","2016":"","Department":"Московський районний суд м. Харкова","Region":"Харківська область","Position":"Суддя Московського районного суду м. Харкова","Name":"Яремчук Валерій Іванович","Link":"https://drive.google.com/open?id=0BygiyWAl79DMdWY5MEFqZ0lXMFE","Note":"У меня","AdditionalNote":"","field8":"","field9":"","field10":"","Кількість справ":"","Оскаржені":"","Кількість скарг":0,"Кількість дисциплінарних стягнень":"","Клейма":"","Фото":"","Як живе":"","key":"yaremchuk_valeriy_ivanovich","allDeclarations":[{"provider":"declarations.com.ua","document":{"income":{"5":{"value":"243807","family_comment":"","value_unclear":false,"family":"13164","family_unclear":false,"comment_unclear":false,"comment":"","family_comment_unclear":false},"6":{"value":"231627","family_comment":"","value_unclear":false,"family_unclear":false,"family":"","comment":""},"7":{"source_name_unclear":false,"value":"","value_unclear":false,"family_comment":"","source_name":"","family":"","comment":"","source_name_hidden":false},"8":{"family_comment":"","value":"","family":"","comment":""},"9":{"family_comment":"","value":"","family":"","comment":""},"10":{"family_comment":"","value":"12180","value_unclear":false,"family":"","comment":""},"11":{"value":"","value_unclear":false,"value_hidden":false,"family_comment":"","family":"","comment":""},"12":{"family_comment":"","value":"","family":"","comment":"","value_hidden":false},"13":{"family_comment":"","value":"","family":"","comment":""},"14":{"family_comment":"","value":"","family":"","comment":""},"15":{"family_comment":"","value":"","family":"","comment":""},"16":{"family_comment":"","value":"","family":"","comment":""},"17":{"family_comment":"","value":"","family":"","comment":""},"18":{"family_comment":"","value":"","family":"","comment":""},"19":{"family_comment":"","family_unclear":false,"value":"","family":"","comment":""},"20":{"family_comment":"","family_unclear":false,"value":"","family":"13164","comment":""}},"vehicle":{"35":[{"year_hidden":false,"brand_info":"1.4 л","sum_rent_comment":"","year":"1997","sum_hidden":false,"brand_info_hidden":false,"brand_info_unclear":false,"year_unclear":false,"sum_rent":"","sum":"","brand":"Honda Civic","sum_comment":"","brand_unclear":false,"brand_hidden":false}]},"id":"vulyk_61_37","declaration":{"additional_info_text":"","notfull_lostpages":"","date":"2015-03-19T00:00:00","notfull":"","additional_info":"","url":"http://static.declarations.com.ua/declarations/chosen_ones/mega_batch/yaremchuk_valerii_ivanovych.pdf"},"liabilities":{"54":{"sum_foreign_comment":"","sum":"","sum_comment":"","sum_comment_unclear":false,"sum_unclear":false,"sum_foreign":""},"55":{"sum_foreign_comment":"","sum":"","sum_comment":"","sum_foreign":""},"56":{"sum_foreign_comment":"","sum":"","sum_comment":"","sum_unclear":false,"sum_foreign":""},"57":{"sum_foreign_comment":"","sum":"","sum_comment":"","sum_comment_hidden":false,"sum_unclear":false,"sum_foreign":""},"58":{"sum_foreign_comment":"","sum":"","sum_comment":"","sum_unclear":false,"sum_foreign":""},"59":{"sum_foreign_comment":"","sum":"","sum_comment":"","sum_foreign":""},"60":{"sum_foreign_comment":"","sum_foreign_hidden":false,"sum_comment":"","sum_hidden":false,"sum":"","sum_foreign":""},"61":{"sum_foreign_comment":"","sum":"","sum_comment":"","sum_foreign":""},"62":{"sum_foreign_comment":"","sum":"","sum_comment":"","sum_unclear":false,"sum_foreign":""},"63":{"sum_foreign_comment":"","sum":"","sum_comment":"","sum_hidden":false,"sum_unclear":false,"sum_foreign":""},"64":{"sum_foreign_comment":"","sum":"","sum_hidden":false,"sum_comment":"","sum_foreign":""}},"ft_src":"Харків\nХарківська область\nсуддя московського районного суду м. харкова\nХарківська область\nЗагальний місцевий суд\nВалерій\nЯремчук Л. О\nПодружжя\nІванович\nЯремчук\nЯремчук Валерій Іванович\nЯремчук Валерій Іванович\nВалерій Іванович Яремчук\nВалерій Яремчук\nЯремчук Валерій Іванович\n1.4 л\nHonda Civic\n1997\nм. Харків\nХарківська область\n27\n78\nХарківська область\nм. Харків\n525\nХарківська область\nм. Харків\n2014\n231627\n12180\n13164\n243807\n13164\n1.4 л\nHonda Civic\n1997\nХарківська область\nм. Харків\n525\n78\nм. Харків\nХарківська область\n27\nХарківська область\nм. Харків\nПодружжя\nЯремчук Л. О\nЯремчук Валерій Іванович\nВалерій Іванович Яремчук\nВалерій Яремчук\nЯремчук Валерій Іванович\nВалерій\nЯремчук Валерій Іванович\nЯремчук\nХарківська область\nЗагальний місцевий суд\nсуддя московського районного суду м. харкова\nІванович\nХарків\nХарківська область\n231627\n13164\n243807\n13164\n12180\n2014\nЯремчук Л. О\nПодружжя\nІванович\nЯремчук\nЯремчук Валерій Іванович\nВалерій Іванович Яремчук\nВалерій Яремчук\nЯремчук Валерій Іванович\nХарківська область\nХарків\nХарківська область\nсуддя московського районного суду м. харкова\nЗагальний місцевий суд\nЯремчук Валерій Іванович\nВалерій\nHonda Civic\n1.4 л\n1997\n12180\n13164\n243807\n13164\n231627\nХарківська область\nм. Харків\n78\nм. Харків\nХарківська область\n27\nХарківська область\nм. Харків\n525\n2014","general":{"inn":"","name":"Валерій","patronymic_unclear":false,"family":[{"inn":"","inn_hidden":false,"relations_unclear":false,"relations_hidden":false,"relations_other":"","relations":"Подружжя","name_hidden":false,"family_name":"Яремчук Л. О","name_unclear":false}],"patronymic":"Іванович","inn_hidden":false,"family_raw":"","inn_unclear":false,"post":{"post_unclear":false,"region_unclear":false,"post":"суддя московського районного суду м. харкова","office":"Загальний місцевий суд","region":"Харківська область","post_hidden":false,"office_hidden":false,"region_hidden":false},"last_name_unclear":false,"full_name":"Яремчук Валерій Іванович","addresses":[{"place_address":"","place_district_hidden":false,"place_city_type":"Місто","place_city_hidden":false,"place_address_unclear":false,"place_city_type_hidden":false,"place_hidden":false,"place":"Харківська область","place_district":"","place_address_hidden":false,"place_city":"Харків","place_district_unclear":false}],"last_name":"Яремчук","patronymic_hidden":false,"full_name_suggest":{"output":"Яремчук Валерій Іванович","input":["Яремчук Валерій Іванович","Валерій Іванович Яремчук","Валерій Яремчук"]},"name_unclear":false},"source":"VULYK","estate":{"29":[{"space_hidden":false,"costs_property":"","address_hidden":false,"region_hidden":false,"space_comment":"","space_units_hidden":false,"space_unclear":false,"space_units_unclear":false,"address":"м. Харків","region":"Харківська область","address_unclear":false,"space":"525","space_comment_hidden":false,"space_units":"м²","costs_property_comment":"","costs_rent":"","costs_rent_comment":""}],"30":[{"space_hidden":false,"costs_property":"","address_hidden":false,"region_hidden":false,"space_comment":"","space_units_hidden":false,"space":"78","address":"м. Харків","region":"Харківська область","address_unclear":false,"costs_rent_comment":"","space_comment_unclear":false,"space_comment_hidden":false,"space_units":"м²","costs_property_comment":"","costs_rent":""}],"33":[{"space_unclear":false,"address_hidden":false,"region_hidden":false,"space_comment":"","space":"27","address":"м. Харків","region":"Харківська область","costs_property":"","costs_rent_comment":"","space_units":"м²","costs_property_comment":"","costs_rent":""}]},"intro":{"declaration_year":"2014","isnotdeclaration":"","declaration_year_hidden":false}}}],"declarations":[{"income":{"5":{"value":"243807","family_comment":"","value_unclear":false,"family":"13164","family_unclear":false,"comment_unclear":false,"comment":"","family_comment_unclear":false},"6":{"value":"231627","family_comment":"","value_unclear":false,"family_unclear":false,"family":"","comment":""},"7":{"source_name_unclear":false,"value":"","value_unclear":false,"family_comment":"","source_name":"","family":"","comment":"","source_name_hidden":false},"8":{"family_comment":"","value":"","family":"","comment":""},"9":{"family_comment":"","value":"","family":"","comment":""},"10":{"family_comment":"","value":"12180","value_unclear":false,"family":"","comment":""},"11":{"value":"","value_unclear":false,"value_hidden":false,"family_comment":"","family":"","comment":""},"12":{"family_comment":"","value":"","family":"","comment":"","value_hidden":false},"13":{"family_comment":"","value":"","family":"","comment":""},"14":{"family_comment":"","value":"","family":"","comment":""},"15":{"family_comment":"","value":"","family":"","comment":""},"16":{"family_comment":"","value":"","family":"","comment":""},"17":{"family_comment":"","value":"","family":"","comment":""},"18":{"family_comment":"","value":"","family":"","comment":""},"19":{"family_comment":"","family_unclear":false,"value":"","family":"","comment":""},"20":{"family_comment":"","family_unclear":false,"value":"","family":"13164","comment":""}},"vehicle":{"35":[{"year_hidden":false,"brand_info":"1.4 л","sum_rent_comment":"","year":"1997","sum_hidden":false,"brand_info_hidden":false,"brand_info_unclear":false,"year_unclear":false,"sum_rent":"","sum":"","brand":"Honda Civic","sum_comment":"","brand_unclear":false,"brand_hidden":false}]},"id":"vulyk_61_37","declaration":{"additional_info_text":"","notfull_lostpages":"","date":"2015-03-19T00:00:00","notfull":"","additional_info":"","url":"http://static.declarations.com.ua/declarations/chosen_ones/mega_batch/yaremchuk_valerii_ivanovych.pdf"},"liabilities":{"54":{"sum_foreign_comment":"","sum":"","sum_comment":"","sum_comment_unclear":false,"sum_unclear":false,"sum_foreign":""},"55":{"sum_foreign_comment":"","sum":"","sum_comment":"","sum_foreign":""},"56":{"sum_foreign_comment":"","sum":"","sum_comment":"","sum_unclear":false,"sum_foreign":""},"57":{"sum_foreign_comment":"","sum":"","sum_comment":"","sum_comment_hidden":false,"sum_unclear":false,"sum_foreign":""},"58":{"sum_foreign_comment":"","sum":"","sum_comment":"","sum_unclear":false,"sum_foreign":""},"59":{"sum_foreign_comment":"","sum":"","sum_comment":"","sum_foreign":""},"60":{"sum_foreign_comment":"","sum_foreign_hidden":false,"sum_comment":"","sum_hidden":false,"sum":"","sum_foreign":""},"61":{"sum_foreign_comment":"","sum":"","sum_comment":"","sum_foreign":""},"62":{"sum_foreign_comment":"","sum":"","sum_comment":"","sum_unclear":false,"sum_foreign":""},"63":{"sum_foreign_comment":"","sum":"","sum_comment":"","sum_hidden":false,"sum_unclear":false,"sum_foreign":""},"64":{"sum_foreign_comment":"","sum":"","sum_hidden":false,"sum_comment":"","sum_foreign":""}},"ft_src":"Харків\nХарківська область\nсуддя московського районного суду м. харкова\nХарківська область\nЗагальний місцевий суд\nВалерій\nЯремчук Л. О\nПодружжя\nІванович\nЯремчук\nЯремчук Валерій Іванович\nЯремчук Валерій Іванович\nВалерій Іванович Яремчук\nВалерій Яремчук\nЯремчук Валерій Іванович\n1.4 л\nHonda Civic\n1997\nм. Харків\nХарківська область\n27\n78\nХарківська область\nм. Харків\n525\nХарківська область\nм. Харків\n2014\n231627\n12180\n13164\n243807\n13164\n1.4 л\nHonda Civic\n1997\nХарківська область\nм. Харків\n525\n78\nм. Харків\nХарківська область\n27\nХарківська область\nм. Харків\nПодружжя\nЯремчук Л. О\nЯремчук Валерій Іванович\nВалерій Іванович Яремчук\nВалерій Яремчук\nЯремчук Валерій Іванович\nВалерій\nЯремчук Валерій Іванович\nЯремчук\nХарківська область\nЗагальний місцевий суд\nсуддя московського районного суду м. харкова\nІванович\nХарків\nХарківська область\n231627\n13164\n243807\n13164\n12180\n2014\nЯремчук Л. О\nПодружжя\nІванович\nЯремчук\nЯремчук Валерій Іванович\nВалерій Іванович Яремчук\nВалерій Яремчук\nЯремчук Валерій Іванович\nХарківська область\nХарків\nХарківська область\nсуддя московського районного суду м. харкова\nЗагальний місцевий суд\nЯремчук Валерій Іванович\nВалерій\nHonda Civic\n1.4 л\n1997\n12180\n13164\n243807\n13164\n231627\nХарківська область\nм. Харків\n78\nм. Харків\nХарківська область\n27\nХарківська область\nм. Харків\n525\n2014","general":{"inn":"","name":"Валерій","patronymic_unclear":false,"family":[{"inn":"","inn_hidden":false,"relations_unclear":false,"relations_hidden":false,"relations_other":"","relations":"Подружжя","name_hidden":false,"family_name":"Яремчук Л. О","name_unclear":false}],"patronymic":"Іванович","inn_hidden":false,"family_raw":"","inn_unclear":false,"post":{"post_unclear":false,"region_unclear":false,"post":"суддя московського районного суду м. харкова","office":"Загальний місцевий суд","region":"Харківська область","post_hidden":false,"office_hidden":false,"region_hidden":false},"last_name_unclear":false,"full_name":"Яремчук Валерій Іванович","addresses":[{"place_address":"","place_district_hidden":false,"place_city_type":"Місто","place_city_hidden":false,"place_address_unclear":false,"place_city_type_hidden":false,"place_hidden":false,"place":"Харківська область","place_district":"","place_address_hidden":false,"place_city":"Харків","place_district_unclear":false}],"last_name":"Яремчук","patronymic_hidden":false,"full_name_suggest":{"output":"Яремчук Валерій Іванович","input":["Яремчук Валерій Іванович","Валерій Іванович Яремчук","Валерій Яремчук"]},"name_unclear":false},"source":"VULYK","estate":{"29":[{"space_hidden":false,"costs_property":"","address_hidden":false,"region_hidden":false,"space_comment":"","space_units_hidden":false,"space_unclear":false,"space_units_unclear":false,"address":"м. Харків","region":"Харківська область","address_unclear":false,"space":"525","space_comment_hidden":false,"space_units":"м²","costs_property_comment":"","costs_rent":"","costs_rent_comment":""}],"30":[{"space_hidden":false,"costs_property":"","address_hidden":false,"region_hidden":false,"space_comment":"","space_units_hidden":false,"space":"78","address":"м. Харків","region":"Харківська область","address_unclear":false,"costs_rent_comment":"","space_comment_unclear":false,"space_comment_hidden":false,"space_units":"м²","costs_property_comment":"","costs_rent":""}],"33":[{"space_unclear":false,"address_hidden":false,"region_hidden":false,"space_comment":"","space":"27","address":"м. Харків","region":"Харківська область","costs_property":"","costs_rent_comment":"","space_units":"м²","costs_property_comment":"","costs_rent":""}]},"intro":{"declaration_year":"2014","isnotdeclaration":"","declaration_year_hidden":false}}],"declarationsLength":1,"analytics":[{"y":2014,"i":243807,"c":1,"fi":13164,"fh":78,"fha":1,"fl":525,"fla":1}]}