{"2010":"","2016":"","Department":"Апеляційний суд Хмельницької області","Region":"Хмельницька область","Position":"Суддя Апеляційного суду Хмельницької області","Name":"Задворний Олександр Леонідович","Link":"https://drive.google.com/open?id=0BygiyWAl79DMLUFFaTFMNGpQc2s","Note":"У меня","AdditionalNote":"","field8":"","field9":"","field10":"","Кількість справ":"","Оскаржені":"","Кількість скарг":2,"Кількість дисциплінарних стягнень":"","Клейма":3,"Фото":"","Як живе":"","key":"zadvorniy_oleksandr_leonidovich","allDeclarations":[{"provider":"declarations.com.ua","document":{"income":{"5":{"value":"300788","family_comment":"","comment_unclear":false,"family_unclear":false,"family":"57188","comment":""},"6":{"family_comment":"","value":"276849","family":"57188","comment":""},"7":{"source_name_unclear":false,"value":"","comment_unclear":false,"family_comment":"","source_name":"","family":"","comment":""},"8":{"family_comment":"","value":"","family":"","comment":""},"9":{"family_comment":"","value":"21219","family":"","comment":"дивіденди 6672, проценти 14447"},"10":{"family_comment":"","value":"","family":"","comment":""},"11":{"family_comment":"","value":"","family":"","comment":""},"12":{"family_comment":"","value":"","family":"","comment":""},"13":{"family_comment":"","value":"","family":"","comment":""},"14":{"family_comment":"","value":"","family":"","comment":""},"15":{"family_comment":"","value":"","family":"","comment":""},"16":{"family_comment":"","family_unclear":false,"value":"","family":"","comment":""},"17":{"family_comment":"","value":"","family":"","comment":""},"18":{"family_comment":"","value":"","family":"","comment":""},"19":{"family_comment":"","value":"","family":"","comment":""},"20":{"value":"2720","family_comment":"","comment_unclear":true,"family_unclear":false,"family":"","comment":"податкова знижка","family_comment_unclear":false}},"vehicle":{"35":[{"brand_info":"Об'єм циліндрів двигуна - 1591","sum_rent_comment":"","brand":"Kia Cerato","sum_comment":"","brand_unclear":false,"year":"2007","brand_info_unclear":false,"sum":"","sum_rent":""}],"40":[{"brand_info":"Об'єм циліндрів двигуна - 1500","sum_rent_comment":"","brand":"Daewoo Lanos","sum_comment":"","year":"2007","brand_hidden":false,"sum":"","sum_rent":""}]},"id":"vulyk_107_146","banks":{"45":[{"sum_foreign_comment":"","sum_units":"UAH","sum_comment":"ВАТ 'Ощадбанк' Хмельницьке відділення №202 заморожений вклад","sum_comment_unclear":true,"sum_foreign_units":"UAH","sum_comment_hidden":false,"sum_unclear":false,"sum":"13948","sum_foreign":""}],"47":[{"sum_foreign_comment":"","sum_units":"UAH","sum_comment":"Хмельницькі - ВАТ 'Взутекс', ВАТ 'Укрелектроапарат', Київське ВАТ 'Готельний комплекс 'Русь'","sum_foreign_units":"UAH","sum_comment_hidden":false,"sum":"349","sum_foreign":""}],"51":[{"sum_foreign_comment":"","sum_units":"UAH","sum_comment":"ВАТ 'Ощадбанк' Хмельницьке відділення №202 заморожений вклад","sum_comment_unclear":true,"sum_foreign_units":"UAH","sum":"7420","sum_unclear":false,"sum_foreign":""}],"52":[{"sum_foreign_comment":"","sum_units":"UAH","sum_comment":"ВАТ 'Готельний комплекс 'Русь', ТОВ 'Шепетівський м'ясокомбінат', Харьковское ОАО 'Южєнергомонтажизоляция'","sum_comment_unclear":false,"sum_foreign_units":"UAH","sum_comment_hidden":false,"sum":"238","sum_foreign":""}]},"declaration":{"additional_info_text":"","notfull_lostpages":"","date":"2016-03-28T00:00:00","notfull":"","additional_info":"","url":"http://static.declarations.com.ua/declarations/chosen_ones/judges_batch/2125_zadvornyi_oleksandr_leonidovych.pdf"},"liabilities":{"54":{"sum_foreign_comment":"","sum":"","sum_comment":"","sum_comment_unclear":false,"sum_comment_hidden":false,"sum_foreign":""},"55":{"sum_foreign_comment":"","sum":"","sum_comment":"","sum_foreign":""},"56":{"sum_foreign_comment":"","sum":"","sum_comment":"","sum_unclear":false,"sum_foreign":""},"57":{"sum_foreign_comment":"","sum":"3000","sum_comment":"","sum_comment_unclear":false,"sum_foreign":""},"58":{"sum_foreign_comment":"","sum":"300","sum_comment":"","sum_comment_unclear":false,"sum_unclear":false,"sum_foreign":""},"59":{"sum_foreign_comment":"","sum":"","sum_comment":"","sum_unclear":false,"sum_foreign":""},"60":{"sum_foreign_comment":"","sum":"","sum_comment":"","sum_comment_unclear":false,"sum_comment_hidden":false,"sum_foreign":""},"61":{"sum_foreign_comment":"","sum":"","sum_comment":"","sum_foreign":""},"62":{"sum_foreign_comment":"","sum":"","sum_comment":"","sum_foreign":""},"63":{"sum_foreign_comment":"","sum":"","sum_comment":"","sum_foreign":""},"64":{"sum_foreign_comment":"","sum":"","sum_comment":"","sum_foreign":""}},"ft_src":"3000\n300\nЗадворний Олександр Леонідович\nсуддя апеляційного суду хмельницької області\nХмельницька область\nЗагальний апеляційний суд\nОлександр\nЗадворна О. В. 11. 09. 1964\nПодружжя\nЗадворний В. О. 03. 06. 1991\nДитина\nЗадворний Олександр Леонідович\nОлександр Леонідович Задворний\nОлександр Задворний\nЗадворний Олександр Леонідович\nЗадворний\nЛеонідович\n2007\nKia Cerato\nОб'єм циліндрів двигуна - 1591\n2007\nОб'єм циліндрів двигуна - 1500\nDaewoo Lanos\nХмельницькі - ВАТ 'Взутекс', ВАТ 'Укрелектроапарат', Київське ВАТ 'Готельний комплекс 'Русь'\n349\nВАТ 'Готельний комплекс 'Русь', ТОВ 'Шепетівський м'ясокомбінат', Харьковское ОАО 'Южєнергомонтажизоляция'\n238\nВАТ 'Ощадбанк' Хмельницьке відділення №202 заморожений вклад\n7420\nВАТ 'Ощадбанк' Хмельницьке відділення №202 заморожений вклад\n13948\n2015\nОб'єм циліндрів двигуна - 1591\n2007\nKia Cerato\nОб'єм циліндрів двигуна - 1500\n2007\nDaewoo Lanos\n13948\nВАТ 'Ощадбанк' Хмельницьке відділення №202 заморожений вклад\n349\nХмельницькі - ВАТ 'Взутекс', ВАТ 'Укрелектроапарат', Київське ВАТ 'Готельний комплекс 'Русь'\n7420\nВАТ 'Ощадбанк' Хмельницьке відділення №202 заморожений вклад\n238\nВАТ 'Готельний комплекс 'Русь', ТОВ 'Шепетівський м'ясокомбінат', Харьковское ОАО 'Южєнергомонтажизоляция'\n2015\nЗадворний\nПодружжя\nЗадворна О. В. 11. 09. 1964\nДитина\nЗадворний В. О. 03. 06. 1991\nЗадворний Олександр Леонідович\nОлександр Леонідович Задворний\nОлександр Задворний\nЗадворний Олександр Леонідович\nОлександр\nЛеонідович\nЗадворний Олександр Леонідович\nЗагальний апеляційний суд\nсуддя апеляційного суду хмельницької області\nХмельницька область\n3000\n300\n276849\n57188\n2720\nподаткова знижка\n300788\n57188\nдивіденди 6672, проценти 14447\n21219\n1/4 частина\n67\n66.1\n48.5\n300\n3000\n1/4 частина\n67\n66.1\n48.5\nЗадворна О. В. 11. 09. 1964\nПодружжя\nЗадворний В. О. 03. 06. 1991\nДитина\nЗадворний\nЛеонідович\nсуддя апеляційного суду хмельницької області\nХмельницька область\nЗагальний апеляційний суд\nЗадворний Олександр Леонідович\nЗадворний Олександр Леонідович\nОлександр Леонідович Задворний\nОлександр Задворний\nЗадворний Олександр Леонідович\nОлександр\n57188\n276849\nдивіденди 6672, проценти 14447\n21219\n57188\n300788\nподаткова знижка\n2720\n2007\nОб'єм циліндрів двигуна - 1591\nKia Cerato\n2007\nОб'єм циліндрів двигуна - 1500\nDaewoo Lanos\nдивіденди 6672, проценти 14447\n21219\nподаткова знижка\n2720\n300788\n57188\n57188\n276849\n1/4 частина\n67\n66.1\n48.5\nХмельницькі - ВАТ 'Взутекс', ВАТ 'Укрелектроапарат', Київське ВАТ 'Готельний комплекс 'Русь'\n349\nВАТ 'Ощадбанк' Хмельницьке відділення №202 заморожений вклад\n13948\nВАТ 'Ощадбанк' Хмельницьке відділення №202 заморожений вклад\n7420\nВАТ 'Готельний комплекс 'Русь', ТОВ 'Шепетівський м'ясокомбінат', Харьковское ОАО 'Южєнергомонтажизоляция'\n238\n2015","general":{"inn":"","inn_hidden":true,"last_name":"Задворний","post":{"post_unclear":false,"office":"Загальний апеляційний суд","post":"суддя апеляційного суду хмельницької області","region":"Хмельницька область"},"name":"Олександр","full_name":"Задворний Олександр Леонідович","family_raw":"","addresses":[{"place_district":"","place_city_hidden":false,"place_city":"","place_city_type_hidden":false,"place_district_hidden":false,"place_city_type":"","place_address_hidden":false,"place_address":"","place_hidden":true,"place":""}],"family":[{"inn":"","relations":"Подружжя","relations_other":"","inn_hidden":false,"family_name":"Задворна О. В. 11. 09. 1964","name_hidden":false,"name_unclear":false},{"inn":"","relations":"Дитина","relations_other":"","inn_hidden":false,"family_name":"Задворний В. О. 03. 06. 1991","name_hidden":false,"name_unclear":false}],"full_name_suggest":{"output":"Задворний Олександр Леонідович","input":["Задворний Олександр Леонідович","Олександр Леонідович Задворний","Олександр Задворний"]},"patronymic":"Леонідович"},"source":"VULYK","estate":{"31":[{"space_unclear":false,"address_hidden":true,"region_hidden":true,"space_comment":"1/4 частина","space_hidden":false,"space":"67","address":"","region":"","costs_property":"","costs_rent_comment":"","space_comment_unclear":true,"space_units":"м²","costs_property_comment":"","costs_rent":""},{"costs_rent":"","costs_property":"","costs_rent_comment":"","region_hidden":false,"space_comment":"","costs_property_comment":"","space_units":"м²","space":"66.1","address":""},{"costs_rent":"","costs_property":"","costs_rent_comment":"","space_comment":"","costs_property_comment":"","space_units":"м²","space":"48.5","address":""}]},"intro":{"declaration_year":"2015","isnotdeclaration":""}}},{"provider":"declarations.com.ua","document":{"income":{"5":{"family_comment":"","value":"363264","family_hidden":false,"comment":"","family":"48295"},"6":{"value":"272020","value_unclear":false,"family_hidden":false,"family_comment":"","family":"42831","comment":""},"7":{"family_comment":"","value":"","source_name":"","family":"","comment":""},"8":{"family_comment":"","value":"","family":"","comment":""},"9":{"family_comment":"","value":"10637","value_unclear":false,"family":"5264","comment":""},"10":{"family_comment":"","value":"","value_unclear":false,"family":"","comment":""},"11":{"family_comment":"","value":"","family":"","comment":""},"12":{"family_comment":"","value":"","family":"","comment":""},"13":{"family_comment":"","value":"","family":"","comment":""},"14":{"family_comment":"","value":"","family":"","comment":""},"15":{"family_comment":"","value":"5607","family":"","comment":""},"16":{"family_comment":"","value":"75000","family":"","comment":"","family_comment_hidden":false},"17":{"family_comment":"","value":"","family_hidden":false,"comment":"","family":""},"18":{"family_comment":"","value":"","family":"","comment":""},"19":{"family_comment":"","value":"","family":"","comment":""},"20":{"value":"","value_unclear":false,"family_comment_hidden":false,"family_comment":"","comment_unclear":false,"comment":"","family":"200"}},"vehicle":{"35":[{"year_hidden":false,"brand_info":"1591 куб. см.","sum_rent_comment":"","year":"2007","brand_info_hidden":false,"brand_info_unclear":false,"year_unclear":false,"sum_rent":"","sum":"45500","brand":"Kia Cerato","sum_comment":"","brand_unclear":false,"brand_hidden":false,"sum_unclear":false}]},"id":"vulyk_42_107","banks":{"45":[{"sum_foreign_comment":"","sum_units":"UAH","sum_comment":"","sum_foreign_comment_hidden":false,"sum_hidden":false,"sum_foreign_units":"UAH","sum_foreign_hidden":false,"sum_comment_hidden":false,"sum_unclear":false,"sum":"23494","sum_foreign":""},{"sum_foreign_comment":"","sum_units":"","sum_comment":"","sum_foreign_units":"","sum":"","sum_foreign":""}],"46":[{"sum_foreign_comment":"","sum_units":"UAH","sum_comment":"","sum_hidden":false,"sum_foreign_units":"UAH","sum_comment_hidden":false,"sum_unclear":false,"sum":"","sum_foreign":""}],"47":[{"sum_foreign_comment":"","sum_units":"UAH","sum_comment":"","sum_comment_unclear":false,"sum_hidden":false,"sum_foreign_units":"UAH","sum":"349","sum_foreign":""},{"sum_foreign_comment":"","sum":"","sum_comment":"","sum_foreign":""}],"48":[{"sum_foreign_comment":"","sum_units":"UAH","sum_comment":"","sum_foreign_units":"UAH","sum":"","sum_foreign":""}],"49":[{"sum_foreign_comment":"","sum_units":"UAH","sum_comment":"","sum_foreign_units":"UAH","sum":"","sum_foreign":""}],"50":[{"sum_foreign_comment":"","sum_units":"UAH","sum_comment":"","sum_foreign_units":"UAH","sum":"","sum_foreign":""}],"51":[{"sum_foreign_comment":"","sum_units":"UAH","sum_comment":"","sum_comment_unclear":false,"sum_hidden":false,"sum_foreign_units":"UAH","sum_comment_hidden":false,"sum":"7420","sum_foreign":""},{"sum_foreign_comment":"","sum_units":"","sum_comment":"","sum_hidden":false,"sum_foreign_units":"","sum":"","sum_units_hidden":false,"sum_foreign":""}],"52":[{"sum_foreign_comment":"","sum_units":"UAH","sum_comment":"","sum_comment_unclear":false,"sum_hidden":false,"sum_foreign_units":"UAH","sum":"238","sum_units_hidden":false,"sum_foreign":""}],"53":[{"sum_foreign_comment":"","sum_units":"UAH","sum_comment":"","sum_foreign_units":"UAH","sum":"","sum_foreign":""}]},"declaration":{"additional_info_text":"","notfull_lostpages":"","date":"2015-03-24T00:00:00","notfull":"","additional_info":"","url":"http://static.declarations.com.ua/declarations/chosen_ones/mega_batch/﻿zadvornyi_oleksandr_leonidovych.pdf"},"liabilities":{"54":{"sum_foreign_comment":"","sum":"","sum_comment":"","sum_foreign_comment_hidden":false,"sum_comment_hidden":false,"sum_foreign":""},"55":{"sum_foreign_comment":"","sum":"","sum_comment":"","sum_foreign":""},"56":{"sum_foreign_comment":"","sum":"","sum_comment":"","sum_foreign":""},"57":{"sum_foreign_comment":"","sum":"","sum_comment":"","sum_comment_unclear":false,"sum_comment_hidden":false,"sum_unclear":false,"sum_foreign":""},"58":{"sum_foreign_comment":"","sum":"","sum_comment":"","sum_foreign_unclear":false,"sum_comment_hidden":false,"sum_unclear":false,"sum_foreign":""},"59":{"sum_foreign_comment":"","sum":"","sum_comment":"","sum_foreign":""},"60":{"sum_foreign_comment":"","sum":"","sum_comment":"","sum_comment_unclear":false,"sum_hidden":false,"sum_comment_hidden":false,"sum_foreign":""},"61":{"sum_foreign_comment":"","sum":"","sum_comment":"","sum_foreign":""},"62":{"sum_foreign_comment":"","sum":"","sum_comment":"","sum_hidden":false,"sum_comment_hidden":false,"sum_foreign":""},"63":{"sum_foreign_comment":"","sum":"","sum_comment":"","sum_comment_hidden":false,"sum_unclear":false,"sum_foreign":""},"64":{"sum_foreign_comment":"","sum":"","sum_comment":"","sum_hidden":false,"sum_comment_hidden":false,"sum_foreign":""}},"ft_src":"Хмельницький\nХмельницька область\nсуддя апеляційного суду хмельницької області\nХмельницька область\nЗагальний апеляційний суд\nОлександр\nЗадворна О. В. 11. 09. 1964\nПодружжя\nЗадворний В. О. 03. 06. 1991\nДитина\nЛеонідович\nЗадворний Олександр Леонідович\nОлександр Леонідович Задворний\nОлександр Задворний\nЗадворний Олександр Леонідович\nЗадворний\nЗадворний Олександр Леонідович\n1591 куб. см.\nKia Cerato\n2007\n45500\n349\n7420\n23494\n238\n2014\n1591 куб. см.\n45500\nKia Cerato\n2007\n23494\n7420\n238\n349\n67.1\n1/4\n66.1\n67.1\n2/4 частини\nм. Хмельницький\nХмельницька область\nПодружжя\nЗадворна О. В. 11. 09. 1964\nДитина\nЗадворний В. О. 03. 06. 1991\nЗадворний Олександр Леонідович\nОлександр Леонідович Задворний\nОлександр Задворний\nЗадворний Олександр Леонідович\nЗадворний Олександр Леонідович\nОлександр\nЗадворний\nсуддя апеляційного суду хмельницької області\nЗагальний апеляційний суд\nХмельницька область\nЛеонідович\nХмельницька область\nХмельницький\n272020\n42831\n200\n5607\n363264\n48295\n75000\n10637\n5264\n2014\n1/4\n67.1\n66.1\n2/4 частини\nм. Хмельницький\nХмельницька область\n67.1\nЗадворна О. В. 11. 09. 1964\nПодружжя\nЗадворний В. О. 03. 06. 1991\nДитина\nЛеонідович\nЗадворний\nОлександр\nЗадворний Олександр Леонідович\nОлександр Леонідович Задворний\nОлександр Задворний\nЗадворний Олександр Леонідович\nХмельницька область\nХмельницький\nХмельницька область\nсуддя апеляційного суду хмельницької області\nЗагальний апеляційний суд\nЗадворний Олександр Леонідович\n42831\n272020\n5607\n48295\n363264\n75000\n5264\n10637\n200\nKia Cerato\n45500\n1591 куб. см.\n2007\n5607\n200\n48295\n363264\n75000\n5264\n10637\n272020\n42831\n1/4\n67.1\n66.1\n2/4 частини\nм. Хмельницький\nХмельницька область\n67.1\n349\n23494\n238\n7420\n2014","general":{"inn":"","name":"Олександр","patronymic_unclear":false,"last_name_hidden":false,"family":[{"inn":"","inn_hidden":true,"relations_hidden":false,"family_name":"Задворна О. В. 11. 09. 1964","relations_other":"","relations":"Подружжя","name_hidden":false,"name_unclear":false},{"inn":"","relations":"Дитина","relations_other":"","inn_hidden":true,"family_name":"Задворний В. О. 03. 06. 1991","name_hidden":false,"name_unclear":false}],"patronymic":"Леонідович","inn_hidden":true,"family_raw":"","last_name":"Задворний","post":{"region_unclear":false,"region":"Хмельницька область","post":"суддя апеляційного суду хмельницької області","office":"Загальний апеляційний суд","office_hidden":false,"region_hidden":false},"last_name_unclear":false,"full_name":"Задворний Олександр Леонідович","addresses":[{"place_district":"","place_city_hidden":false,"place_city":"Хмельницький","place_city_type_hidden":false,"place_district_hidden":false,"place_city_type":"Місто","place_address_hidden":true,"place_address":"","place_hidden":false,"place":"Хмельницька область"}],"full_name_suggest":{"output":"Задворний Олександр Леонідович","input":["Задворний Олександр Леонідович","Олександр Леонідович Задворний","Олександр Задворний"]}},"source":"VULYK","estate":{"23":[{"space_unclear":false,"costs":"","costs_comment":"","address_hidden":false,"region_hidden":false,"space_comment":"","space_hidden":false,"space":"","address":"","region":"","address_unclear":false,"space_units_unclear":false,"space_comment_unclear":false,"space_units":"м²","costs_rent":"","costs_rent_comment":""},{"costs":"","costs_comment":"","address_hidden":false,"region_hidden":false,"space_comment":"","space_units_unclear":false,"address":"","space":"","region":"","costs_rent_comment":"","space_units":"","costs_rent":""},{"costs_rent":"","region":"","costs":"","costs_rent_comment":"","costs_comment":"","space_comment":"","space_units":"","space":"","address":""},{"costs_rent":"","region":"","costs":"","costs_rent_comment":"","costs_comment":"","space_comment":"","space_units":"","space":"","address":""},{"costs_rent":"","region":"","costs":"","costs_rent_comment":"","costs_comment":"","space_comment":"","space_units":"","space":"","address":""},{"costs_rent":"","costs":"","costs_rent_comment":"","costs_comment":"","space_comment":"","space_units":"","space":"","address":""}],"25":[{"space_unclear":false,"costs":"","costs_comment":"","address_hidden":true,"region_hidden":false,"space_comment":"2/4 частини","space_hidden":false,"space":"67.1","address":"м. Хмельницький","region":"Хмельницька область","costs_rent_comment":"","space_comment_unclear":false,"space_units":"м²","costs_rent":""}],"30":[{"space_hidden":false,"address_hidden":true,"region_hidden":false,"space_comment":"","space":"","address":"","region":"","costs_property":"","costs_rent_comment":"","space_units":"м²","costs_property_comment":"","costs_rent":""}],"31":[{"space_hidden":false,"address_hidden":false,"region_hidden":true,"space_comment":"1/4","space":"67.1","address":"","region":"","costs_property":"","costs_rent_comment":"","space_units":"м²","costs_property_comment":"","costs_rent":""},{"costs_rent":"","region":"","costs_property":"","costs_rent_comment":"","region_hidden":false,"space_comment":"","costs_property_comment":"","space_units":"м²","space":"66.1","address":""}]},"intro":{"declaration_year":"2014","isnotdeclaration":""}}},{"provider":"declarations.com.ua","document":{"income":{"5":{"value":"266193","family_comment":"","value_unclear":false,"family_hidden":false,"family_unclear":false,"family":"40015","comment":""},"6":{"value":"253576","family_comment":"","value_unclear":false,"family_hidden":false,"family_unclear":false,"family":"40015","comment":"","family_comment_unclear":false},"7":{"value":"","family_comment":"","source_name":"","family":"","comment":"","source_name_hidden":false},"8":{"family_comment":"","value":"","family":"","comment":""},"9":{"family_comment":"","value":"567","value_unclear":false,"family":"","comment":"дивіденди"},"10":{"family_comment":"","value":"12617","value_unclear":false,"family":"","comment":""},"11":{"family_comment":"","value":"","family":"","comment":""},"12":{"family_comment":"","value":"","family":"","comment":""},"13":{"family_comment":"","value":"","family":"","comment":""},"14":{"family_comment":"","value":"","family":"","comment":""},"15":{"family_comment":"","value":"13742","family":"","comment":"страхові відшкодування"},"16":{"family_comment":"","value":"58248","family":"","comment":""},"17":{"family_comment":"","value":"","family":"","comment":""},"18":{"family_comment":"","value":"","family":"","comment":""},"19":{"family_comment":"","value":"","value_unclear":false,"family":"","comment":""},"20":{"value":"","family_comment":"","value_unclear":false,"comment_hidden":false,"family_hidden":false,"value_hidden":false,"family_unclear":false,"family_comment_unclear":false,"family":"","comment":"","family_comment_hidden":false}},"vehicle":{"35":[{"brand_info":"двигун 1496 куб. см.","sum_rent_comment":"","brand":"Chevrolet Lanos","sum_comment":"","brand_unclear":false,"year":"2008","brand_hidden":false,"brand_info_unclear":false,"year_unclear":false,"sum":"54000","sum_rent":""}]},"id":"vulyk_1_756","banks":{"45":[{"sum_foreign_comment":"","sum_units":"UAH","sum_units_hidden":false,"sum_comment":"","sum_comment_unclear":false,"sum_hidden":false,"sum_foreign_units":"UAH","sum_comment_hidden":false,"sum_unclear":false,"sum":"66041","sum_foreign":""},{"sum_foreign_comment":"","sum_units":"","sum_comment":"","sum_hidden":false,"sum_foreign_units":"","sum_comment_hidden":false,"sum_unclear":false,"sum":"","sum_foreign":""},{"sum_foreign_comment":"","sum_units":"","sum_comment":"","sum_foreign_units":"","sum":"","sum_unclear":false,"sum_foreign":""},{"sum_foreign_comment":"","sum_units":"","sum_comment":"","sum_foreign_units":"","sum":"","sum_foreign":""}],"46":[{"sum_foreign_comment":"","sum_unclear":false,"sum_units":"UAH","sum_comment":"","sum_hidden":false,"sum_foreign_units":"UAH","sum_comment_hidden":false,"sum_units_hidden":false,"sum":"","sum_foreign":""},{"sum_foreign_comment":"","sum_units":"","sum_comment":"","sum_hidden":false,"sum_foreign_units":"","sum":"","sum_foreign":""},{"sum_foreign_comment":"","sum_units":"","sum_comment":"","sum_foreign_units":"","sum":"","sum_foreign":""},{"sum_foreign_comment":"","sum_units":"","sum_comment":"","sum_foreign_units":"","sum":"","sum_foreign":""}],"47":[{"sum_foreign_comment":"","sum_units":"UAH","sum_comment":"","sum_foreign_units":"UAH","sum":"349","sum_foreign":""}],"48":[{"sum_foreign_comment":"","sum_units":"UAH","sum_comment":"","sum_foreign_units":"UAH","sum":"","sum_foreign":""}],"49":[{"sum_foreign_comment":"","sum_units":"UAH","sum_comment":"","sum_foreign_units":"UAH","sum_comment_hidden":false,"sum":"","sum_foreign":""}],"50":[{"sum_foreign_comment":"","sum_units":"UAH","sum_comment":"","sum_foreign_units":"UAH","sum":"","sum_foreign":""}],"51":[{"sum_foreign_comment":"","sum_units":"UAH","sum_comment":"","sum_hidden":false,"sum_foreign_units":"UAH","sum_comment_hidden":false,"sum_unclear":false,"sum":"57100","sum_foreign":""}],"52":[{"sum_foreign_comment":"","sum_units":"UAH","sum_comment":"","sum_foreign_units":"UAH","sum":"238","sum_foreign":""}],"53":[{"sum_foreign_comment":"","sum_units":"UAH","sum_comment":"","sum_foreign_units":"UAH","sum":"","sum_foreign":""},{"sum_foreign_comment":"","sum_units":"","sum_comment":"","sum_hidden":false,"sum_foreign_units":"","sum":"","sum_foreign":""},{"sum_foreign_comment":"","sum_units":"","sum_comment":"","sum_foreign_units":"","sum":"","sum_foreign":""},{"sum_foreign_comment":"","sum_units":"","sum_comment":"","sum_foreign_units":"","sum":"","sum_foreign":""}]},"declaration":{"additional_info_text":"","notfull_lostpages":"","date":"2014-03-24T00:00:00","notfull":"","additional_info":"","url":"http://static.declarations.com.ua/declarations/sudy/apeliatsiini_sudy_oblastei__m.kyieva/khmelnytska/dekl_zadvorniy(1).pdf"},"liabilities":{"54":{"sum_foreign_comment":"","sum":"","sum_comment":"","sum_hidden":false,"sum_comment_hidden":false,"sum_foreign":""},"55":{"sum_foreign_comment":"","sum":"","sum_comment":"","sum_foreign":""},"56":{"sum_foreign_comment":"","sum":"","sum_comment":"","sum_unclear":false,"sum_foreign":""},"57":{"sum_foreign_comment":"","sum":"","sum_comment":"","sum_comment_unclear":false,"sum_hidden":false,"sum_comment_hidden":false,"sum_unclear":false,"sum_foreign":""},"58":{"sum_foreign_comment":"","sum":"","sum_comment":"","sum_hidden":false,"sum_comment_hidden":false,"sum_unclear":false,"sum_foreign":""},"59":{"sum_foreign_comment":"","sum":"","sum_comment":"","sum_comment_unclear":false,"sum_unclear":false,"sum_foreign":""},"60":{"sum_foreign_comment":"","sum":"","sum_comment":"","sum_foreign":""},"61":{"sum_foreign_comment":"","sum":"","sum_comment":"","sum_foreign":""},"62":{"sum_foreign_comment":"","sum":"","sum_comment":"","sum_unclear":false,"sum_foreign":""},"63":{"sum_foreign_comment":"","sum":"","sum_comment":"","sum_unclear":false,"sum_foreign":""},"64":{"sum_foreign_comment":"","sum":"","sum_comment":"","sum_foreign":""}},"ft_src":"суддя апеляційного суду хмельницької області\nХмельницька область\nЗагальний апеляційний суд\nОлександр\nЗадворна О. В\nПодружжя\nЗадворний В. О\nДитина\nЛеонідович\nЗадворний\nЗадворний Олександр Леонідович\nЗадворний Олександр Леонідович\nОлександр Леонідович Задворний\nОлександр Задворний\nЗадворний Олександр Леонідович\nChevrolet Lanos\n54000\nдвигун 1496 куб. см.\n2008\n349\n57100\n66041\n238\n2013\nдвигун 1496 куб. см.\n54000\n2008\nChevrolet Lanos\n66041\n57100\n238\n349\n66.1\nХмельницька область\nм. Хмельницький\n67.1\n2/4 частини\nХмельницька область\nм. Хмельницький\nЗагальний апеляційний суд\nХмельницька область\nсуддя апеляційного суду хмельницької області\nПодружжя\nЗадворна О. В\nДитина\nЗадворний В. О\nЗадворний Олександр Леонідович\nОлександр Леонідович Задворний\nОлександр Задворний\nЗадворний Олександр Леонідович\nОлександр\nЗадворний Олександр Леонідович\nЗадворний\nЛеонідович\n253576\n40015\nстрахові відшкодування\n13742\n40015\n266193\n58248\n12617\n567\nдивіденди\n2013\nХмельницька область\nм. Хмельницький\n66.1\n2/4 частини\nм. Хмельницький\n67.1\nХмельницька область\nЗадворна О. В\nПодружжя\nЗадворний В. О\nДитина\nЛеонідович\nЗадворний\nЗадворний Олександр Леонідович\nОлександр Леонідович Задворний\nОлександр Задворний\nЗадворний Олександр Леонідович\nОлександр\nХмельницька область\nЗагальний апеляційний суд\nсуддя апеляційного суду хмельницької області\nЗадворний Олександр Леонідович\n40015\n253576\nстрахові відшкодування\n13742\n12617\n40015\n266193\n58248\nдивіденди\n567\n54000\n2008\nChevrolet Lanos\nдвигун 1496 куб. см.\nстрахові відшкодування\n13742\n12617\n266193\n40015\n58248\nдивіденди\n567\n253576\n40015\nм. Хмельницький\nХмельницька область\n66.1\n2/4 частини\nм. Хмельницький\nХмельницька область\n67.1\n349\n66041\n238\n57100\n2013","general":{"inn":"","name":"Олександр","patronymic_unclear":false,"last_name_hidden":false,"family":[{"inn":"","inn_hidden":false,"inn_unclear":false,"relations_hidden":false,"relations_other":"","relations":"Подружжя","name_hidden":false,"family_name":"Задворна О. В","name_unclear":false},{"inn":"","relations":"Дитина","relations_other":"","inn_hidden":false,"family_name":"Задворний В. О","name_hidden":false,"name_unclear":false}],"patronymic":"Леонідович","inn_hidden":true,"family_raw":"","inn_unclear":false,"post":{"post_unclear":false,"region_unclear":false,"post":"суддя апеляційного суду хмельницької області","candidate":"","office_hidden":false,"region":"Хмельницька область","post_hidden":false,"office":"Загальний апеляційний суд","office_unclear":false,"region_hidden":false},"last_name_unclear":false,"full_name":"Задворний Олександр Леонідович","addresses":[{"place_city_type_unclear":false,"place_address":"","place_district_hidden":true,"place_city_type":"","place_address_hidden":true,"place_address_unclear":false,"place_city_type_hidden":true,"place":"","place_district":"","place_unclear":false,"place_city":"","place_city_unclear":false,"place_hidden":true,"place_city_hidden":true,"place_district_unclear":false}],"last_name":"Задворний","patronymic_hidden":false,"full_name_suggest":{"output":"Задворний Олександр Леонідович","input":["Задворний Олександр Леонідович","Олександр Леонідович Задворний","Олександр Задворний"]},"name_unclear":false},"source":"VULYK","estate":{"23":[{"space_unclear":false,"costs":"","costs_comment":"","costs_hidden":false,"address_hidden":false,"region_hidden":false,"space_comment":"","space":"","address":"","region":"","address_unclear":false,"space_units_unclear":false,"costs_rent_hidden":false,"space_comment_hidden":false,"space_units":"м²","costs_rent":"","costs_rent_comment":""},{"space_unclear":false,"costs":"","costs_comment":"","address_hidden":false,"region_hidden":false,"space_comment":"","space_hidden":false,"space":"","address":"","region":"","address_unclear":false,"costs_rent_comment":"","space_units":"","costs_rent":""},{"costs":"","costs_comment":"","address_hidden":false,"region_hidden":false,"space_comment":"","space":"","address":"","region":"","address_unclear":false,"costs_rent_comment":"","space_units":"","costs_rent":""},{"space":"","region":"","costs":"","costs_rent_comment":"","costs_comment":"","region_hidden":false,"address_unclear":false,"space_comment":"","space_units":"","costs_rent":"","address":""},{"costs_rent":"","region":"","costs":"","costs_rent_comment":"","costs_comment":"","region_hidden":false,"space_comment":"","space_units":"","space":"","address":""},{"costs_rent":"","region":"","costs":"","costs_rent_comment":"","costs_comment":"","space_comment":"","space_units":"","space":"","address":""}],"25":[{"region_unclear":false,"space_unclear":false,"costs":"","costs_comment":"","address_hidden":true,"region_hidden":true,"space_comment":"2/4 частини","space_hidden":false,"space":"67.1","address":"м. Хмельницький","region":"Хмельницька область","costs_rent_comment":"","space_comment_unclear":true,"space_comment_hidden":false,"space_units":"м²","costs_rent":""}],"31":[{"space_unclear":true,"address_hidden":true,"region_hidden":false,"space_comment":"","space":"66.1","address":"м. Хмельницький","region":"Хмельницька область","costs_property":"","costs_rent_comment":"","space_comment_unclear":true,"address_unclear":false,"space_units":"м²","costs_property_comment":"","costs_rent":""}]},"intro":{"declaration_year":"2013","isnotdeclaration":""}}},{"provider":"public-api.nazk.gov.ua","document":{"step_0":{"declarationType":"1","declarationYear1":"2015"},"step_1":{"street":"[Конфіденційна інформація]","country":"1","birthday":"[Конфіденційна інформація]","cityPath":"[Конфіденційна інформація]","cityType":"[Конфіденційна інформація]","lastname":"Задворний","postCode":"[Конфіденційна інформація]","postType":"","workPost":"суддя","buildType":"багатоквартирний будинок","firstname":"Олександр","workPlace":"Апеляційний суд Хмельницької області","middlename":"Леонідович","streetType":"[Конфіденційна інформація]","changedName":false,"eng_postCode":"","postCategory":"","actual_street":"[Конфіденційна інформація]","actual_cityType":"[Конфіденційна інформація]","actual_postCode":"[Конфіденційна інформація]","actual_buildType":"","actual_streetType":"[Конфіденційна інформація]","previous_lastname":"","corruptionAffected":"Ні","eng_actualPostCode":"[Конфіденційна інформація]","previous_firstname":"","previous_middlename":"","responsiblePosition":"Суддя суду загальної юрисдикції, суддя Конституційного Суду України","sameRegLivingAddress":"[Конфіденційна інформація]","eng_sameRegLivingAddress":"[Конфіденційна інформація]","housePartNum_extendedstatus":"1"},"step_2":{"1474018293799":{"lastname":"Задворна","firstname":"Оксана","middlename":"Вікторівна","changedName":false,"citizenship":"1","eng_lastname":"","no_taxNumber":false,"eng_firstname":"","eng_middlename":"","isNotApplicable":"","subjectRelation":"дружина","previous_lastname":"","previous_firstname":"","previous_middlename":"","previous_eng_lastname":"","previous_eng_firstname":"","previous_eng_middlename":""},"1474018440648":{"lastname":"Задворний","firstname":"Віталій ","middlename":"Олександрович","changedName":false,"citizenship":"1","eng_lastname":"","no_taxNumber":false,"eng_firstname":"","eng_middlename":"","isNotApplicable":"","subjectRelation":"син","previous_lastname":"","previous_firstname":"","previous_middlename":"","previous_eng_lastname":"","previous_eng_firstname":"","previous_eng_middlename":""}},"step_3":{"1474022410931":{"person":"1474018293799","rights":{"1474018293799":{"citizen":"","ua_lastname":"","eng_lastname":"","rightBelongs":"1474018293799","ua_firstname":"","eng_firstname":"","ownershipType":"Власність","ua_middlename":"","eng_middlename":"","otherOwnership":"","ua_company_name":"","eng_company_name":"","ukr_company_name":"","percent-ownership":""}},"country":"1","costDate":"323106","postCode":"[Конфіденційна інформація]","totalArea":"66","ua_street":"[Конфіденційна інформація]","objectType":"Квартира","owningDate":"07.04.2010","ua_cityType":"Хмельницький / Хмельницька Область/м.Хмельницький / Україна","ua_postCode":"29015","ua_buildType":"багатоквартирний будинок","ua_streetType":"[Конфіденційна інформація]","costAssessment":"","otherObjectType":"","costAssessment_extendedstatus":"2","ua_housePartNum_extendedstatus":"1"},"1474022745375":{"person":"1474018293799","rights":{"1474018293799":{"citizen":"","ua_lastname":"","eng_lastname":"","rightBelongs":"1474018293799","ua_firstname":"","eng_firstname":"","ownershipType":"Власність","ua_middlename":"","eng_middlename":"","otherOwnership":"","ua_company_name":"","eng_company_name":"","ukr_company_name":"","percent-ownership":""}},"country":"1","costDate":"383373","postCode":"[Конфіденційна інформація]","totalArea":"49","ua_street":"[Конфіденційна інформація]","objectType":"Квартира","owningDate":"29.01.2016","ua_cityType":"Хмельницький","ua_postCode":"29015","ua_buildType":"багатоквартирний будинок","ua_streetType":"[Конфіденційна інформація]","costAssessment":"","otherObjectType":"","costAssessment_extendedstatus":"2","ua_housePartNum_extendedstatus":"1"},"1474029642371":{"person":"1","rights":{"1":{"citizen":"","ua_lastname":"","eng_lastname":"","rightBelongs":"1","ua_firstname":"","eng_firstname":"","ownershipType":"Спільна власність","ua_middlename":"","eng_middlename":"","otherOwnership":"","ua_company_name":"","eng_company_name":"","ukr_company_name":"","percent-ownership":"50"},"1474018293799":{"citizen":"","ua_lastname":"","eng_lastname":"","rightBelongs":"1474018293799","ua_firstname":"","eng_firstname":"","ownershipType":"Спільна власність","ua_middlename":"","eng_middlename":"","otherOwnership":"","ua_company_name":"","eng_company_name":"","ukr_company_name":"","percent-ownership":"25"},"8911b6b35e5578f9052268e6098458b0":{"citizen":"Громадянин України","ua_city":"Хмельницький / Хмельницька Область/м.Хмельницький / Україна","ua_street":"[Конфіденційна інформація]","ua_lastname":"Салдан","ua_postCode":"29015","eng_lastname":"","rightBelongs":"j","ua_buildType":"багатоквартирний будинок","ua_firstname":"Юлія","eng_firstname":"","ownershipType":"Спільна власність","ua_middlename":"Олександрівна","ua_streetType":"[Конфіденційна інформація]","eng_middlename":"","otherOwnership":"","ua_company_name":"","eng_company_name":"","ukr_company_name":"","percent-ownership":"25"}},"country":"1","costDate":"","postCode":"[Конфіденційна інформація]","totalArea":"67","ua_street":"[Конфіденційна інформація]","objectType":"Квартира","owningDate":"06.09.1999","ua_cityType":"місто Хмельницький","ua_postCode":"29016","ua_buildType":"багатоквартирний будинок","ua_streetType":"[Конфіденційна інформація]","costAssessment":"203892","otherObjectType":"","costDate_extendedstatus":"2","ua_housePartNum_extendedstatus":"1"}},"step_4":[],"step_5":[],"step_6":{"1474023147709":{"brand":"KIA","model":"CERATO","person":"1","rights":{"1":{"citizen":"","ua_lastname":"","eng_lastname":"","rightBelongs":"1","ua_firstname":"","eng_firstname":"","ownershipType":"Власність","ua_middlename":"","eng_middlename":"","otherOwnership":"","ua_company_name":"","eng_company_name":"","ukr_company_name":"","percent-ownership":""}},"costDate":"75000","objectType":"Автомобіль легковий","owningDate":"09.10.2014","typeProperty":"","graduationYear":"2007","otherTypeProperty":""}},"step_7":{"1474023835702":{"cost":"186","amount":"186","person":"1","rights":{"1":{"citizen":"","ua_lastname":"","eng_lastname":"","rightBelongs":"1","ua_firstname":"","eng_firstname":"","ownershipType":"Власність","ua_middlename":"","eng_middlename":"","otherOwnership":"","ua_company_name":"","eng_company_name":"","ukr_company_name":"","percent-ownership":""}},"emitent":"j","owningDate":"05.05.1999","emitent_type":"Юридична особа, зареєстрована в Україні","typeProperty":"Акції","otherObjectType":"","subTypeProperty":"","emitent_ua_lastname":"","emitent_eng_lastname":"","emitent_ua_firstname":"","emitent_ukr_lastname":"","emitent_eng_firstname":"","emitent_ua_middlename":"","emitent_ukr_firstname":"","emitent_eng_middlename":"","emitent_ukr_middlename":"","emitent_ua_company_name":"ВАТ Готельний комплекс Русь","emitent_eng_company_name":"","emitent_ukr_company_name":"","emitent_ua_sameRegLivingAddress":"","emitent_eng_sameRegLivingAddress":""},"1474024373826":{"cost":"11","amount":"210","person":"1","rights":{"1":{"citizen":"","ua_lastname":"","eng_lastname":"","rightBelongs":"1","ua_firstname":"","eng_firstname":"","ownershipType":"Власність","ua_middlename":"","eng_middlename":"","otherOwnership":"","ua_company_name":"","eng_company_name":"","ukr_company_name":"","percent-ownership":""}},"emitent":"j","owningDate":"07.09.2006","emitent_type":"Юридична особа, зареєстрована в Україні","typeProperty":"Акції","otherObjectType":"","subTypeProperty":"","emitent_ua_lastname":"","emitent_eng_lastname":"","emitent_ua_firstname":"","emitent_ukr_lastname":"","emitent_eng_firstname":"","emitent_ua_middlename":"","emitent_ukr_firstname":"","emitent_eng_middlename":"","emitent_ukr_middlename":"","emitent_ua_company_name":"ВАТ Взутекс","emitent_eng_company_name":"","emitent_ukr_company_name":"","emitent_ua_sameRegLivingAddress":"","emitent_eng_sameRegLivingAddress":""},"1474024574015":{"cost":"153","amount":"609","person":"1","rights":{"1":{"citizen":"","ua_lastname":"","eng_lastname":"","rightBelongs":"1","ua_firstname":"","eng_firstname":"","ownershipType":"Власність","ua_middlename":"","eng_middlename":"","otherOwnership":"","ua_company_name":"","eng_company_name":"","ukr_company_name":"","percent-ownership":""}},"emitent":"j","owningDate":"18.09.2007","emitent_type":"Юридична особа, зареєстрована в Україні","typeProperty":"Акції","otherObjectType":"","subTypeProperty":"","emitent_ua_lastname":"","emitent_eng_lastname":"","emitent_ua_firstname":"","emitent_ukr_lastname":"","emitent_eng_firstname":"","emitent_ua_middlename":"","emitent_ukr_firstname":"","emitent_eng_middlename":"","emitent_ukr_middlename":"","emitent_ua_company_name":"ВАТ Укрелектроапарат","emitent_eng_company_name":"","emitent_ukr_company_name":"","emitent_ua_sameRegLivingAddress":"","emitent_eng_sameRegLivingAddress":""},"1474026729180":{"cost":"","amount":"6","person":"1474018440648","rights":{"1474018440648":{"citizen":"","ua_lastname":"","eng_lastname":"","rightBelongs":"1474018440648","ua_firstname":"","eng_firstname":"","ownershipType":"Власність","ua_middlename":"","eng_middlename":"","otherOwnership":"","ua_company_name":"","eng_company_name":"","ukr_company_name":"","percent-ownership":""}},"emitent":"j","owningDate":"29.10.1996","emitent_type":"Юридична особа, зареєстрована в Україні","typeProperty":"Акції","otherObjectType":"","subTypeProperty":"","emitent_ua_lastname":"","emitent_eng_lastname":"","emitent_ua_firstname":"","emitent_ukr_lastname":"","emitent_eng_firstname":"","emitent_ua_middlename":"","emitent_ukr_firstname":"","emitent_eng_middlename":"","emitent_ukr_middlename":"","emitent_ua_company_name":"ВАТ Південенергомонтажізоляція","emitent_eng_company_name":"","emitent_ukr_company_name":"","emitent_ua_sameRegLivingAddress":"","emitent_eng_sameRegLivingAddress":"","emitent_ua_company_code_extendedstatus":"2"},"1474027190158":{"cost":"186","amount":"186","person":"1474018293799","rights":{"1474018293799":{"citizen":"","ua_lastname":"","eng_lastname":"","rightBelongs":"1474018293799","ua_firstname":"","eng_firstname":"","ownershipType":"Власність","ua_middlename":"","eng_middlename":"","otherOwnership":"","ua_company_name":"","eng_company_name":"","ukr_company_name":"","percent-ownership":""}},"emitent":"j","owningDate":"05.05.1999","emitent_type":"Юридична особа, зареєстрована в Україні","typeProperty":"Акції","otherObjectType":"","subTypeProperty":"","emitent_ua_lastname":"","emitent_eng_lastname":"","emitent_ua_firstname":"","emitent_ukr_lastname":"","emitent_eng_firstname":"","emitent_ua_middlename":"","emitent_ukr_firstname":"","emitent_eng_middlename":"","emitent_ukr_middlename":"","emitent_ua_company_name":"ВАТ Гогтельний комплекс Русь","emitent_eng_company_name":"","emitent_ukr_company_name":"","emitent_ua_sameRegLivingAddress":"","emitent_eng_sameRegLivingAddress":""},"1474027347787":{"cost":"","amount":"42","person":"1474018293799","rights":{"1474018293799":{"citizen":"","ua_lastname":"","eng_lastname":"","rightBelongs":"1474018293799","ua_firstname":"","eng_firstname":"","ownershipType":"Власність","ua_middlename":"","eng_middlename":"","otherOwnership":"","ua_company_name":"","eng_company_name":"","ukr_company_name":"","percent-ownership":""}},"emitent":"j","owningDate":"27.10.1995","emitent_type":"Юридична особа, зареєстрована в Україні","typeProperty":"Акції","otherObjectType":"","subTypeProperty":"","emitent_ua_lastname":"","emitent_eng_lastname":"","emitent_ua_firstname":"","emitent_ukr_lastname":"","emitent_eng_firstname":"","emitent_ua_middlename":"","emitent_ukr_firstname":"","emitent_eng_middlename":"","emitent_ukr_middlename":"","emitent_ua_company_name":"ВАТ Шепетівський м'ясокомбінат","emitent_eng_company_name":"","emitent_ukr_company_name":"","emitent_ua_sameRegLivingAddress":"","emitent_eng_sameRegLivingAddress":""}},"step_8":[],"step_9":[],"step_10":[],"step_11":{"1474027724059":{"person":"1","rights":{"1":{"citizen":"","ua_lastname":"","eng_lastname":"","rightBelongs":"1","ua_firstname":"","eng_firstname":"","ownershipType":"Власність","ua_middlename":"","eng_middlename":"","otherOwnership":"","ua_company_name":"","eng_company_name":"","ukr_company_name":"","percent-ownership":""}},"objectType":"Заробітна плата отримана за основним місцем роботи","sizeIncome":"276849","incomeSource":"j","source_citizen":"Юридична особа, зареєстрована в Україні","otherObjectType":"","source_ua_lastname":"","source_eng_lastname":"","source_ua_firstname":"","source_ukr_lastname":"","source_eng_firstname":"","source_ua_middlename":"","source_ukr_firstname":"","source_eng_middlename":"","source_ukr_middlename":"","source_ua_company_name":"Апеляційний суд Хмельницької області","source_eng_company_name":"","source_ukr_company_name":"","source_ua_sameRegLivingAddress":"","source_eng_sameRegLivingAddress":""},"1474027843286":{"person":"1474018293799","rights":{"1474018293799":{"citizen":"","ua_lastname":"","eng_lastname":"","rightBelongs":"1474018293799","ua_firstname":"","eng_firstname":"","ownershipType":"Власність","ua_middlename":"","eng_middlename":"","otherOwnership":"","ua_company_name":"","eng_company_name":"","ukr_company_name":"","percent-ownership":""}},"objectType":"Заробітна плата отримана за основним місцем роботи","sizeIncome":"57188","incomeSource":"j","source_citizen":"Юридична особа, зареєстрована в Україні","otherObjectType":"","source_ua_lastname":"","source_eng_lastname":"","source_ua_firstname":"","source_ukr_lastname":"","source_eng_firstname":"","source_ua_middlename":"","source_ukr_firstname":"","source_eng_middlename":"","source_ukr_middlename":"","source_ua_company_name":"Хмельницький дошкільний навчальний заклад Ялинка","source_eng_company_name":"","source_ukr_company_name":"","source_ua_sameRegLivingAddress":"","source_eng_sameRegLivingAddress":""},"1474028023022":{"person":"1","rights":{"1":{"citizen":"","ua_lastname":"","eng_lastname":"","rightBelongs":"1","ua_firstname":"","eng_firstname":"","ownershipType":"Власність","ua_middlename":"","eng_middlename":"","otherOwnership":"","ua_company_name":"","eng_company_name":"","ukr_company_name":"","percent-ownership":""}},"objectType":"Дивіденди","sizeIncome":"6772","incomeSource":"j","source_citizen":"Юридична особа, зареєстрована в Україні","otherObjectType":"","source_ua_lastname":"","source_eng_lastname":"","source_ua_firstname":"","source_ukr_lastname":"","source_eng_firstname":"","source_ua_middlename":"","source_ukr_firstname":"","source_eng_middlename":"","source_ukr_middlename":"","source_ua_company_name":"ВАТ Укрелектроапарат","source_eng_company_name":"","source_ukr_company_name":"","source_ua_sameRegLivingAddress":"","source_eng_sameRegLivingAddress":""},"1474028904410":{"person":"1","rights":{"1":{"citizen":"","ua_lastname":"","eng_lastname":"","rightBelongs":"1","ua_firstname":"","eng_firstname":"","ownershipType":"Власність","ua_middlename":"","eng_middlename":"","otherOwnership":"","ua_company_name":"","eng_company_name":"","ukr_company_name":"","percent-ownership":""}},"objectType":"Інше","sizeIncome":"2720","incomeSource":"j","source_citizen":"Юридична особа, зареєстрована в Україні","otherObjectType":"податкова знижка","source_ua_lastname":"","source_eng_lastname":"","source_ua_firstname":"","source_ukr_lastname":"","source_eng_firstname":"","source_ua_middlename":"","source_ukr_firstname":"","source_eng_middlename":"","source_ukr_middlename":"","source_ua_company_name":"ДПІ міста Хмельницького","source_eng_company_name":"","source_ukr_company_name":"","source_ua_sameRegLivingAddress":"","source_eng_sameRegLivingAddress":""}},"step_12":[],"step_13":[],"step_14":[],"step_15":[],"step_16":{"org":[],"part_org":[]},"id":"b80bfe74-5a45-41d0-a40c-f2ace977b11c"}}],"declarations":[{"income":{"5":{"value":"300788","family_comment":"","comment_unclear":false,"family_unclear":false,"family":"57188","comment":""},"6":{"family_comment":"","value":"276849","family":"57188","comment":""},"7":{"source_name_unclear":false,"value":"","comment_unclear":false,"family_comment":"","source_name":"","family":"","comment":""},"8":{"family_comment":"","value":"","family":"","comment":""},"9":{"family_comment":"","value":"21219","family":"","comment":"дивіденди 6672, проценти 14447"},"10":{"family_comment":"","value":"","family":"","comment":""},"11":{"family_comment":"","value":"","family":"","comment":""},"12":{"family_comment":"","value":"","family":"","comment":""},"13":{"family_comment":"","value":"","family":"","comment":""},"14":{"family_comment":"","value":"","family":"","comment":""},"15":{"family_comment":"","value":"","family":"","comment":""},"16":{"family_comment":"","family_unclear":false,"value":"","family":"","comment":""},"17":{"family_comment":"","value":"","family":"","comment":""},"18":{"family_comment":"","value":"","family":"","comment":""},"19":{"family_comment":"","value":"","family":"","comment":""},"20":{"value":"2720","family_comment":"","comment_unclear":true,"family_unclear":false,"family":"","comment":"податкова знижка","family_comment_unclear":false}},"vehicle":{"35":[{"brand_info":"Об'єм циліндрів двигуна - 1591","sum_rent_comment":"","brand":"Kia Cerato","sum_comment":"","brand_unclear":false,"year":"2007","brand_info_unclear":false,"sum":"","sum_rent":""}],"40":[{"brand_info":"Об'єм циліндрів двигуна - 1500","sum_rent_comment":"","brand":"Daewoo Lanos","sum_comment":"","year":"2007","brand_hidden":false,"sum":"","sum_rent":""}]},"id":"vulyk_107_146","banks":{"45":[{"sum_foreign_comment":"","sum_units":"UAH","sum_comment":"ВАТ 'Ощадбанк' Хмельницьке відділення №202 заморожений вклад","sum_comment_unclear":true,"sum_foreign_units":"UAH","sum_comment_hidden":false,"sum_unclear":false,"sum":"13948","sum_foreign":""}],"47":[{"sum_foreign_comment":"","sum_units":"UAH","sum_comment":"Хмельницькі - ВАТ 'Взутекс', ВАТ 'Укрелектроапарат', Київське ВАТ 'Готельний комплекс 'Русь'","sum_foreign_units":"UAH","sum_comment_hidden":false,"sum":"349","sum_foreign":""}],"51":[{"sum_foreign_comment":"","sum_units":"UAH","sum_comment":"ВАТ 'Ощадбанк' Хмельницьке відділення №202 заморожений вклад","sum_comment_unclear":true,"sum_foreign_units":"UAH","sum":"7420","sum_unclear":false,"sum_foreign":""}],"52":[{"sum_foreign_comment":"","sum_units":"UAH","sum_comment":"ВАТ 'Готельний комплекс 'Русь', ТОВ 'Шепетівський м'ясокомбінат', Харьковское ОАО 'Южєнергомонтажизоляция'","sum_comment_unclear":false,"sum_foreign_units":"UAH","sum_comment_hidden":false,"sum":"238","sum_foreign":""}]},"declaration":{"additional_info_text":"","notfull_lostpages":"","date":"2016-03-28T00:00:00","notfull":"","additional_info":"","url":"http://static.declarations.com.ua/declarations/chosen_ones/judges_batch/2125_zadvornyi_oleksandr_leonidovych.pdf"},"liabilities":{"54":{"sum_foreign_comment":"","sum":"","sum_comment":"","sum_comment_unclear":false,"sum_comment_hidden":false,"sum_foreign":""},"55":{"sum_foreign_comment":"","sum":"","sum_comment":"","sum_foreign":""},"56":{"sum_foreign_comment":"","sum":"","sum_comment":"","sum_unclear":false,"sum_foreign":""},"57":{"sum_foreign_comment":"","sum":"3000","sum_comment":"","sum_comment_unclear":false,"sum_foreign":""},"58":{"sum_foreign_comment":"","sum":"300","sum_comment":"","sum_comment_unclear":false,"sum_unclear":false,"sum_foreign":""},"59":{"sum_foreign_comment":"","sum":"","sum_comment":"","sum_unclear":false,"sum_foreign":""},"60":{"sum_foreign_comment":"","sum":"","sum_comment":"","sum_comment_unclear":false,"sum_comment_hidden":false,"sum_foreign":""},"61":{"sum_foreign_comment":"","sum":"","sum_comment":"","sum_foreign":""},"62":{"sum_foreign_comment":"","sum":"","sum_comment":"","sum_foreign":""},"63":{"sum_foreign_comment":"","sum":"","sum_comment":"","sum_foreign":""},"64":{"sum_foreign_comment":"","sum":"","sum_comment":"","sum_foreign":""}},"ft_src":"3000\n300\nЗадворний Олександр Леонідович\nсуддя апеляційного суду хмельницької області\nХмельницька область\nЗагальний апеляційний суд\nОлександр\nЗадворна О. В. 11. 09. 1964\nПодружжя\nЗадворний В. О. 03. 06. 1991\nДитина\nЗадворний Олександр Леонідович\nОлександр Леонідович Задворний\nОлександр Задворний\nЗадворний Олександр Леонідович\nЗадворний\nЛеонідович\n2007\nKia Cerato\nОб'єм циліндрів двигуна - 1591\n2007\nОб'єм циліндрів двигуна - 1500\nDaewoo Lanos\nХмельницькі - ВАТ 'Взутекс', ВАТ 'Укрелектроапарат', Київське ВАТ 'Готельний комплекс 'Русь'\n349\nВАТ 'Готельний комплекс 'Русь', ТОВ 'Шепетівський м'ясокомбінат', Харьковское ОАО 'Южєнергомонтажизоляция'\n238\nВАТ 'Ощадбанк' Хмельницьке відділення №202 заморожений вклад\n7420\nВАТ 'Ощадбанк' Хмельницьке відділення №202 заморожений вклад\n13948\n2015\nОб'єм циліндрів двигуна - 1591\n2007\nKia Cerato\nОб'єм циліндрів двигуна - 1500\n2007\nDaewoo Lanos\n13948\nВАТ 'Ощадбанк' Хмельницьке відділення №202 заморожений вклад\n349\nХмельницькі - ВАТ 'Взутекс', ВАТ 'Укрелектроапарат', Київське ВАТ 'Готельний комплекс 'Русь'\n7420\nВАТ 'Ощадбанк' Хмельницьке відділення №202 заморожений вклад\n238\nВАТ 'Готельний комплекс 'Русь', ТОВ 'Шепетівський м'ясокомбінат', Харьковское ОАО 'Южєнергомонтажизоляция'\n2015\nЗадворний\nПодружжя\nЗадворна О. В. 11. 09. 1964\nДитина\nЗадворний В. О. 03. 06. 1991\nЗадворний Олександр Леонідович\nОлександр Леонідович Задворний\nОлександр Задворний\nЗадворний Олександр Леонідович\nОлександр\nЛеонідович\nЗадворний Олександр Леонідович\nЗагальний апеляційний суд\nсуддя апеляційного суду хмельницької області\nХмельницька область\n3000\n300\n276849\n57188\n2720\nподаткова знижка\n300788\n57188\nдивіденди 6672, проценти 14447\n21219\n1/4 частина\n67\n66.1\n48.5\n300\n3000\n1/4 частина\n67\n66.1\n48.5\nЗадворна О. В. 11. 09. 1964\nПодружжя\nЗадворний В. О. 03. 06. 1991\nДитина\nЗадворний\nЛеонідович\nсуддя апеляційного суду хмельницької області\nХмельницька область\nЗагальний апеляційний суд\nЗадворний Олександр Леонідович\nЗадворний Олександр Леонідович\nОлександр Леонідович Задворний\nОлександр Задворний\nЗадворний Олександр Леонідович\nОлександр\n57188\n276849\nдивіденди 6672, проценти 14447\n21219\n57188\n300788\nподаткова знижка\n2720\n2007\nОб'єм циліндрів двигуна - 1591\nKia Cerato\n2007\nОб'єм циліндрів двигуна - 1500\nDaewoo Lanos\nдивіденди 6672, проценти 14447\n21219\nподаткова знижка\n2720\n300788\n57188\n57188\n276849\n1/4 частина\n67\n66.1\n48.5\nХмельницькі - ВАТ 'Взутекс', ВАТ 'Укрелектроапарат', Київське ВАТ 'Готельний комплекс 'Русь'\n349\nВАТ 'Ощадбанк' Хмельницьке відділення №202 заморожений вклад\n13948\nВАТ 'Ощадбанк' Хмельницьке відділення №202 заморожений вклад\n7420\nВАТ 'Готельний комплекс 'Русь', ТОВ 'Шепетівський м'ясокомбінат', Харьковское ОАО 'Южєнергомонтажизоляция'\n238\n2015","general":{"inn":"","inn_hidden":true,"last_name":"Задворний","post":{"post_unclear":false,"office":"Загальний апеляційний суд","post":"суддя апеляційного суду хмельницької області","region":"Хмельницька область"},"name":"Олександр","full_name":"Задворний Олександр Леонідович","family_raw":"","addresses":[{"place_district":"","place_city_hidden":false,"place_city":"","place_city_type_hidden":false,"place_district_hidden":false,"place_city_type":"","place_address_hidden":false,"place_address":"","place_hidden":true,"place":""}],"family":[{"inn":"","relations":"Подружжя","relations_other":"","inn_hidden":false,"family_name":"Задворна О. В. 11. 09. 1964","name_hidden":false,"name_unclear":false},{"inn":"","relations":"Дитина","relations_other":"","inn_hidden":false,"family_name":"Задворний В. О. 03. 06. 1991","name_hidden":false,"name_unclear":false}],"full_name_suggest":{"output":"Задворний Олександр Леонідович","input":["Задворний Олександр Леонідович","Олександр Леонідович Задворний","Олександр Задворний"]},"patronymic":"Леонідович"},"source":"VULYK","estate":{"31":[{"space_unclear":false,"address_hidden":true,"region_hidden":true,"space_comment":"1/4 частина","space_hidden":false,"space":"67","address":"","region":"","costs_property":"","costs_rent_comment":"","space_comment_unclear":true,"space_units":"м²","costs_property_comment":"","costs_rent":""},{"costs_rent":"","costs_property":"","costs_rent_comment":"","region_hidden":false,"space_comment":"","costs_property_comment":"","space_units":"м²","space":"66.1","address":""},{"costs_rent":"","costs_property":"","costs_rent_comment":"","space_comment":"","costs_property_comment":"","space_units":"м²","space":"48.5","address":""}]},"intro":{"declaration_year":"2015","isnotdeclaration":""}},{"income":{"5":{"family_comment":"","value":"363264","family_hidden":false,"comment":"","family":"48295"},"6":{"value":"272020","value_unclear":false,"family_hidden":false,"family_comment":"","family":"42831","comment":""},"7":{"family_comment":"","value":"","source_name":"","family":"","comment":""},"8":{"family_comment":"","value":"","family":"","comment":""},"9":{"family_comment":"","value":"10637","value_unclear":false,"family":"5264","comment":""},"10":{"family_comment":"","value":"","value_unclear":false,"family":"","comment":""},"11":{"family_comment":"","value":"","family":"","comment":""},"12":{"family_comment":"","value":"","family":"","comment":""},"13":{"family_comment":"","value":"","family":"","comment":""},"14":{"family_comment":"","value":"","family":"","comment":""},"15":{"family_comment":"","value":"5607","family":"","comment":""},"16":{"family_comment":"","value":"75000","family":"","comment":"","family_comment_hidden":false},"17":{"family_comment":"","value":"","family_hidden":false,"comment":"","family":""},"18":{"family_comment":"","value":"","family":"","comment":""},"19":{"family_comment":"","value":"","family":"","comment":""},"20":{"value":"","value_unclear":false,"family_comment_hidden":false,"family_comment":"","comment_unclear":false,"comment":"","family":"200"}},"vehicle":{"35":[{"year_hidden":false,"brand_info":"1591 куб. см.","sum_rent_comment":"","year":"2007","brand_info_hidden":false,"brand_info_unclear":false,"year_unclear":false,"sum_rent":"","sum":"45500","brand":"Kia Cerato","sum_comment":"","brand_unclear":false,"brand_hidden":false,"sum_unclear":false}]},"id":"vulyk_42_107","banks":{"45":[{"sum_foreign_comment":"","sum_units":"UAH","sum_comment":"","sum_foreign_comment_hidden":false,"sum_hidden":false,"sum_foreign_units":"UAH","sum_foreign_hidden":false,"sum_comment_hidden":false,"sum_unclear":false,"sum":"23494","sum_foreign":""},{"sum_foreign_comment":"","sum_units":"","sum_comment":"","sum_foreign_units":"","sum":"","sum_foreign":""}],"46":[{"sum_foreign_comment":"","sum_units":"UAH","sum_comment":"","sum_hidden":false,"sum_foreign_units":"UAH","sum_comment_hidden":false,"sum_unclear":false,"sum":"","sum_foreign":""}],"47":[{"sum_foreign_comment":"","sum_units":"UAH","sum_comment":"","sum_comment_unclear":false,"sum_hidden":false,"sum_foreign_units":"UAH","sum":"349","sum_foreign":""},{"sum_foreign_comment":"","sum":"","sum_comment":"","sum_foreign":""}],"48":[{"sum_foreign_comment":"","sum_units":"UAH","sum_comment":"","sum_foreign_units":"UAH","sum":"","sum_foreign":""}],"49":[{"sum_foreign_comment":"","sum_units":"UAH","sum_comment":"","sum_foreign_units":"UAH","sum":"","sum_foreign":""}],"50":[{"sum_foreign_comment":"","sum_units":"UAH","sum_comment":"","sum_foreign_units":"UAH","sum":"","sum_foreign":""}],"51":[{"sum_foreign_comment":"","sum_units":"UAH","sum_comment":"","sum_comment_unclear":false,"sum_hidden":false,"sum_foreign_units":"UAH","sum_comment_hidden":false,"sum":"7420","sum_foreign":""},{"sum_foreign_comment":"","sum_units":"","sum_comment":"","sum_hidden":false,"sum_foreign_units":"","sum":"","sum_units_hidden":false,"sum_foreign":""}],"52":[{"sum_foreign_comment":"","sum_units":"UAH","sum_comment":"","sum_comment_unclear":false,"sum_hidden":false,"sum_foreign_units":"UAH","sum":"238","sum_units_hidden":false,"sum_foreign":""}],"53":[{"sum_foreign_comment":"","sum_units":"UAH","sum_comment":"","sum_foreign_units":"UAH","sum":"","sum_foreign":""}]},"declaration":{"additional_info_text":"","notfull_lostpages":"","date":"2015-03-24T00:00:00","notfull":"","additional_info":"","url":"http://static.declarations.com.ua/declarations/chosen_ones/mega_batch/﻿zadvornyi_oleksandr_leonidovych.pdf"},"liabilities":{"54":{"sum_foreign_comment":"","sum":"","sum_comment":"","sum_foreign_comment_hidden":false,"sum_comment_hidden":false,"sum_foreign":""},"55":{"sum_foreign_comment":"","sum":"","sum_comment":"","sum_foreign":""},"56":{"sum_foreign_comment":"","sum":"","sum_comment":"","sum_foreign":""},"57":{"sum_foreign_comment":"","sum":"","sum_comment":"","sum_comment_unclear":false,"sum_comment_hidden":false,"sum_unclear":false,"sum_foreign":""},"58":{"sum_foreign_comment":"","sum":"","sum_comment":"","sum_foreign_unclear":false,"sum_comment_hidden":false,"sum_unclear":false,"sum_foreign":""},"59":{"sum_foreign_comment":"","sum":"","sum_comment":"","sum_foreign":""},"60":{"sum_foreign_comment":"","sum":"","sum_comment":"","sum_comment_unclear":false,"sum_hidden":false,"sum_comment_hidden":false,"sum_foreign":""},"61":{"sum_foreign_comment":"","sum":"","sum_comment":"","sum_foreign":""},"62":{"sum_foreign_comment":"","sum":"","sum_comment":"","sum_hidden":false,"sum_comment_hidden":false,"sum_foreign":""},"63":{"sum_foreign_comment":"","sum":"","sum_comment":"","sum_comment_hidden":false,"sum_unclear":false,"sum_foreign":""},"64":{"sum_foreign_comment":"","sum":"","sum_comment":"","sum_hidden":false,"sum_comment_hidden":false,"sum_foreign":""}},"ft_src":"Хмельницький\nХмельницька область\nсуддя апеляційного суду хмельницької області\nХмельницька область\nЗагальний апеляційний суд\nОлександр\nЗадворна О. В. 11. 09. 1964\nПодружжя\nЗадворний В. О. 03. 06. 1991\nДитина\nЛеонідович\nЗадворний Олександр Леонідович\nОлександр Леонідович Задворний\nОлександр Задворний\nЗадворний Олександр Леонідович\nЗадворний\nЗадворний Олександр Леонідович\n1591 куб. см.\nKia Cerato\n2007\n45500\n349\n7420\n23494\n238\n2014\n1591 куб. см.\n45500\nKia Cerato\n2007\n23494\n7420\n238\n349\n67.1\n1/4\n66.1\n67.1\n2/4 частини\nм. Хмельницький\nХмельницька область\nПодружжя\nЗадворна О. В. 11. 09. 1964\nДитина\nЗадворний В. О. 03. 06. 1991\nЗадворний Олександр Леонідович\nОлександр Леонідович Задворний\nОлександр Задворний\nЗадворний Олександр Леонідович\nЗадворний Олександр Леонідович\nОлександр\nЗадворний\nсуддя апеляційного суду хмельницької області\nЗагальний апеляційний суд\nХмельницька область\nЛеонідович\nХмельницька область\nХмельницький\n272020\n42831\n200\n5607\n363264\n48295\n75000\n10637\n5264\n2014\n1/4\n67.1\n66.1\n2/4 частини\nм. Хмельницький\nХмельницька область\n67.1\nЗадворна О. В. 11. 09. 1964\nПодружжя\nЗадворний В. О. 03. 06. 1991\nДитина\nЛеонідович\nЗадворний\nОлександр\nЗадворний Олександр Леонідович\nОлександр Леонідович Задворний\nОлександр Задворний\nЗадворний Олександр Леонідович\nХмельницька область\nХмельницький\nХмельницька область\nсуддя апеляційного суду хмельницької області\nЗагальний апеляційний суд\nЗадворний Олександр Леонідович\n42831\n272020\n5607\n48295\n363264\n75000\n5264\n10637\n200\nKia Cerato\n45500\n1591 куб. см.\n2007\n5607\n200\n48295\n363264\n75000\n5264\n10637\n272020\n42831\n1/4\n67.1\n66.1\n2/4 частини\nм. Хмельницький\nХмельницька область\n67.1\n349\n23494\n238\n7420\n2014","general":{"inn":"","name":"Олександр","patronymic_unclear":false,"last_name_hidden":false,"family":[{"inn":"","inn_hidden":true,"relations_hidden":false,"family_name":"Задворна О. В. 11. 09. 1964","relations_other":"","relations":"Подружжя","name_hidden":false,"name_unclear":false},{"inn":"","relations":"Дитина","relations_other":"","inn_hidden":true,"family_name":"Задворний В. О. 03. 06. 1991","name_hidden":false,"name_unclear":false}],"patronymic":"Леонідович","inn_hidden":true,"family_raw":"","last_name":"Задворний","post":{"region_unclear":false,"region":"Хмельницька область","post":"суддя апеляційного суду хмельницької області","office":"Загальний апеляційний суд","office_hidden":false,"region_hidden":false},"last_name_unclear":false,"full_name":"Задворний Олександр Леонідович","addresses":[{"place_district":"","place_city_hidden":false,"place_city":"Хмельницький","place_city_type_hidden":false,"place_district_hidden":false,"place_city_type":"Місто","place_address_hidden":true,"place_address":"","place_hidden":false,"place":"Хмельницька область"}],"full_name_suggest":{"output":"Задворний Олександр Леонідович","input":["Задворний Олександр Леонідович","Олександр Леонідович Задворний","Олександр Задворний"]}},"source":"VULYK","estate":{"23":[{"space_unclear":false,"costs":"","costs_comment":"","address_hidden":false,"region_hidden":false,"space_comment":"","space_hidden":false,"space":"","address":"","region":"","address_unclear":false,"space_units_unclear":false,"space_comment_unclear":false,"space_units":"м²","costs_rent":"","costs_rent_comment":""},{"costs":"","costs_comment":"","address_hidden":false,"region_hidden":false,"space_comment":"","space_units_unclear":false,"address":"","space":"","region":"","costs_rent_comment":"","space_units":"","costs_rent":""},{"costs_rent":"","region":"","costs":"","costs_rent_comment":"","costs_comment":"","space_comment":"","space_units":"","space":"","address":""},{"costs_rent":"","region":"","costs":"","costs_rent_comment":"","costs_comment":"","space_comment":"","space_units":"","space":"","address":""},{"costs_rent":"","region":"","costs":"","costs_rent_comment":"","costs_comment":"","space_comment":"","space_units":"","space":"","address":""},{"costs_rent":"","costs":"","costs_rent_comment":"","costs_comment":"","space_comment":"","space_units":"","space":"","address":""}],"25":[{"space_unclear":false,"costs":"","costs_comment":"","address_hidden":true,"region_hidden":false,"space_comment":"2/4 частини","space_hidden":false,"space":"67.1","address":"м. Хмельницький","region":"Хмельницька область","costs_rent_comment":"","space_comment_unclear":false,"space_units":"м²","costs_rent":""}],"30":[{"space_hidden":false,"address_hidden":true,"region_hidden":false,"space_comment":"","space":"","address":"","region":"","costs_property":"","costs_rent_comment":"","space_units":"м²","costs_property_comment":"","costs_rent":""}],"31":[{"space_hidden":false,"address_hidden":false,"region_hidden":true,"space_comment":"1/4","space":"67.1","address":"","region":"","costs_property":"","costs_rent_comment":"","space_units":"м²","costs_property_comment":"","costs_rent":""},{"costs_rent":"","region":"","costs_property":"","costs_rent_comment":"","region_hidden":false,"space_comment":"","costs_property_comment":"","space_units":"м²","space":"66.1","address":""}]},"intro":{"declaration_year":"2014","isnotdeclaration":""}},{"income":{"5":{"value":"266193","family_comment":"","value_unclear":false,"family_hidden":false,"family_unclear":false,"family":"40015","comment":""},"6":{"value":"253576","family_comment":"","value_unclear":false,"family_hidden":false,"family_unclear":false,"family":"40015","comment":"","family_comment_unclear":false},"7":{"value":"","family_comment":"","source_name":"","family":"","comment":"","source_name_hidden":false},"8":{"family_comment":"","value":"","family":"","comment":""},"9":{"family_comment":"","value":"567","value_unclear":false,"family":"","comment":"дивіденди"},"10":{"family_comment":"","value":"12617","value_unclear":false,"family":"","comment":""},"11":{"family_comment":"","value":"","family":"","comment":""},"12":{"family_comment":"","value":"","family":"","comment":""},"13":{"family_comment":"","value":"","family":"","comment":""},"14":{"family_comment":"","value":"","family":"","comment":""},"15":{"family_comment":"","value":"13742","family":"","comment":"страхові відшкодування"},"16":{"family_comment":"","value":"58248","family":"","comment":""},"17":{"family_comment":"","value":"","family":"","comment":""},"18":{"family_comment":"","value":"","family":"","comment":""},"19":{"family_comment":"","value":"","value_unclear":false,"family":"","comment":""},"20":{"value":"","family_comment":"","value_unclear":false,"comment_hidden":false,"family_hidden":false,"value_hidden":false,"family_unclear":false,"family_comment_unclear":false,"family":"","comment":"","family_comment_hidden":false}},"vehicle":{"35":[{"brand_info":"двигун 1496 куб. см.","sum_rent_comment":"","brand":"Chevrolet Lanos","sum_comment":"","brand_unclear":false,"year":"2008","brand_hidden":false,"brand_info_unclear":false,"year_unclear":false,"sum":"54000","sum_rent":""}]},"id":"vulyk_1_756","banks":{"45":[{"sum_foreign_comment":"","sum_units":"UAH","sum_units_hidden":false,"sum_comment":"","sum_comment_unclear":false,"sum_hidden":false,"sum_foreign_units":"UAH","sum_comment_hidden":false,"sum_unclear":false,"sum":"66041","sum_foreign":""},{"sum_foreign_comment":"","sum_units":"","sum_comment":"","sum_hidden":false,"sum_foreign_units":"","sum_comment_hidden":false,"sum_unclear":false,"sum":"","sum_foreign":""},{"sum_foreign_comment":"","sum_units":"","sum_comment":"","sum_foreign_units":"","sum":"","sum_unclear":false,"sum_foreign":""},{"sum_foreign_comment":"","sum_units":"","sum_comment":"","sum_foreign_units":"","sum":"","sum_foreign":""}],"46":[{"sum_foreign_comment":"","sum_unclear":false,"sum_units":"UAH","sum_comment":"","sum_hidden":false,"sum_foreign_units":"UAH","sum_comment_hidden":false,"sum_units_hidden":false,"sum":"","sum_foreign":""},{"sum_foreign_comment":"","sum_units":"","sum_comment":"","sum_hidden":false,"sum_foreign_units":"","sum":"","sum_foreign":""},{"sum_foreign_comment":"","sum_units":"","sum_comment":"","sum_foreign_units":"","sum":"","sum_foreign":""},{"sum_foreign_comment":"","sum_units":"","sum_comment":"","sum_foreign_units":"","sum":"","sum_foreign":""}],"47":[{"sum_foreign_comment":"","sum_units":"UAH","sum_comment":"","sum_foreign_units":"UAH","sum":"349","sum_foreign":""}],"48":[{"sum_foreign_comment":"","sum_units":"UAH","sum_comment":"","sum_foreign_units":"UAH","sum":"","sum_foreign":""}],"49":[{"sum_foreign_comment":"","sum_units":"UAH","sum_comment":"","sum_foreign_units":"UAH","sum_comment_hidden":false,"sum":"","sum_foreign":""}],"50":[{"sum_foreign_comment":"","sum_units":"UAH","sum_comment":"","sum_foreign_units":"UAH","sum":"","sum_foreign":""}],"51":[{"sum_foreign_comment":"","sum_units":"UAH","sum_comment":"","sum_hidden":false,"sum_foreign_units":"UAH","sum_comment_hidden":false,"sum_unclear":false,"sum":"57100","sum_foreign":""}],"52":[{"sum_foreign_comment":"","sum_units":"UAH","sum_comment":"","sum_foreign_units":"UAH","sum":"238","sum_foreign":""}],"53":[{"sum_foreign_comment":"","sum_units":"UAH","sum_comment":"","sum_foreign_units":"UAH","sum":"","sum_foreign":""},{"sum_foreign_comment":"","sum_units":"","sum_comment":"","sum_hidden":false,"sum_foreign_units":"","sum":"","sum_foreign":""},{"sum_foreign_comment":"","sum_units":"","sum_comment":"","sum_foreign_units":"","sum":"","sum_foreign":""},{"sum_foreign_comment":"","sum_units":"","sum_comment":"","sum_foreign_units":"","sum":"","sum_foreign":""}]},"declaration":{"additional_info_text":"","notfull_lostpages":"","date":"2014-03-24T00:00:00","notfull":"","additional_info":"","url":"http://static.declarations.com.ua/declarations/sudy/apeliatsiini_sudy_oblastei__m.kyieva/khmelnytska/dekl_zadvorniy(1).pdf"},"liabilities":{"54":{"sum_foreign_comment":"","sum":"","sum_comment":"","sum_hidden":false,"sum_comment_hidden":false,"sum_foreign":""},"55":{"sum_foreign_comment":"","sum":"","sum_comment":"","sum_foreign":""},"56":{"sum_foreign_comment":"","sum":"","sum_comment":"","sum_unclear":false,"sum_foreign":""},"57":{"sum_foreign_comment":"","sum":"","sum_comment":"","sum_comment_unclear":false,"sum_hidden":false,"sum_comment_hidden":false,"sum_unclear":false,"sum_foreign":""},"58":{"sum_foreign_comment":"","sum":"","sum_comment":"","sum_hidden":false,"sum_comment_hidden":false,"sum_unclear":false,"sum_foreign":""},"59":{"sum_foreign_comment":"","sum":"","sum_comment":"","sum_comment_unclear":false,"sum_unclear":false,"sum_foreign":""},"60":{"sum_foreign_comment":"","sum":"","sum_comment":"","sum_foreign":""},"61":{"sum_foreign_comment":"","sum":"","sum_comment":"","sum_foreign":""},"62":{"sum_foreign_comment":"","sum":"","sum_comment":"","sum_unclear":false,"sum_foreign":""},"63":{"sum_foreign_comment":"","sum":"","sum_comment":"","sum_unclear":false,"sum_foreign":""},"64":{"sum_foreign_comment":"","sum":"","sum_comment":"","sum_foreign":""}},"ft_src":"суддя апеляційного суду хмельницької області\nХмельницька область\nЗагальний апеляційний суд\nОлександр\nЗадворна О. В\nПодружжя\nЗадворний В. О\nДитина\nЛеонідович\nЗадворний\nЗадворний Олександр Леонідович\nЗадворний Олександр Леонідович\nОлександр Леонідович Задворний\nОлександр Задворний\nЗадворний Олександр Леонідович\nChevrolet Lanos\n54000\nдвигун 1496 куб. см.\n2008\n349\n57100\n66041\n238\n2013\nдвигун 1496 куб. см.\n54000\n2008\nChevrolet Lanos\n66041\n57100\n238\n349\n66.1\nХмельницька область\nм. Хмельницький\n67.1\n2/4 частини\nХмельницька область\nм. Хмельницький\nЗагальний апеляційний суд\nХмельницька область\nсуддя апеляційного суду хмельницької області\nПодружжя\nЗадворна О. В\nДитина\nЗадворний В. О\nЗадворний Олександр Леонідович\nОлександр Леонідович Задворний\nОлександр Задворний\nЗадворний Олександр Леонідович\nОлександр\nЗадворний Олександр Леонідович\nЗадворний\nЛеонідович\n253576\n40015\nстрахові відшкодування\n13742\n40015\n266193\n58248\n12617\n567\nдивіденди\n2013\nХмельницька область\nм. Хмельницький\n66.1\n2/4 частини\nм. Хмельницький\n67.1\nХмельницька область\nЗадворна О. В\nПодружжя\nЗадворний В. О\nДитина\nЛеонідович\nЗадворний\nЗадворний Олександр Леонідович\nОлександр Леонідович Задворний\nОлександр Задворний\nЗадворний Олександр Леонідович\nОлександр\nХмельницька область\nЗагальний апеляційний суд\nсуддя апеляційного суду хмельницької області\nЗадворний Олександр Леонідович\n40015\n253576\nстрахові відшкодування\n13742\n12617\n40015\n266193\n58248\nдивіденди\n567\n54000\n2008\nChevrolet Lanos\nдвигун 1496 куб. см.\nстрахові відшкодування\n13742\n12617\n266193\n40015\n58248\nдивіденди\n567\n253576\n40015\nм. Хмельницький\nХмельницька область\n66.1\n2/4 частини\nм. Хмельницький\nХмельницька область\n67.1\n349\n66041\n238\n57100\n2013","general":{"inn":"","name":"Олександр","patronymic_unclear":false,"last_name_hidden":false,"family":[{"inn":"","inn_hidden":false,"inn_unclear":false,"relations_hidden":false,"relations_other":"","relations":"Подружжя","name_hidden":false,"family_name":"Задворна О. В","name_unclear":false},{"inn":"","relations":"Дитина","relations_other":"","inn_hidden":false,"family_name":"Задворний В. О","name_hidden":false,"name_unclear":false}],"patronymic":"Леонідович","inn_hidden":true,"family_raw":"","inn_unclear":false,"post":{"post_unclear":false,"region_unclear":false,"post":"суддя апеляційного суду хмельницької області","candidate":"","office_hidden":false,"region":"Хмельницька область","post_hidden":false,"office":"Загальний апеляційний суд","office_unclear":false,"region_hidden":false},"last_name_unclear":false,"full_name":"Задворний Олександр Леонідович","addresses":[{"place_city_type_unclear":false,"place_address":"","place_district_hidden":true,"place_city_type":"","place_address_hidden":true,"place_address_unclear":false,"place_city_type_hidden":true,"place":"","place_district":"","place_unclear":false,"place_city":"","place_city_unclear":false,"place_hidden":true,"place_city_hidden":true,"place_district_unclear":false}],"last_name":"Задворний","patronymic_hidden":false,"full_name_suggest":{"output":"Задворний Олександр Леонідович","input":["Задворний Олександр Леонідович","Олександр Леонідович Задворний","Олександр Задворний"]},"name_unclear":false},"source":"VULYK","estate":{"23":[{"space_unclear":false,"costs":"","costs_comment":"","costs_hidden":false,"address_hidden":false,"region_hidden":false,"space_comment":"","space":"","address":"","region":"","address_unclear":false,"space_units_unclear":false,"costs_rent_hidden":false,"space_comment_hidden":false,"space_units":"м²","costs_rent":"","costs_rent_comment":""},{"space_unclear":false,"costs":"","costs_comment":"","address_hidden":false,"region_hidden":false,"space_comment":"","space_hidden":false,"space":"","address":"","region":"","address_unclear":false,"costs_rent_comment":"","space_units":"","costs_rent":""},{"costs":"","costs_comment":"","address_hidden":false,"region_hidden":false,"space_comment":"","space":"","address":"","region":"","address_unclear":false,"costs_rent_comment":"","space_units":"","costs_rent":""},{"space":"","region":"","costs":"","costs_rent_comment":"","costs_comment":"","region_hidden":false,"address_unclear":false,"space_comment":"","space_units":"","costs_rent":"","address":""},{"costs_rent":"","region":"","costs":"","costs_rent_comment":"","costs_comment":"","region_hidden":false,"space_comment":"","space_units":"","space":"","address":""},{"costs_rent":"","region":"","costs":"","costs_rent_comment":"","costs_comment":"","space_comment":"","space_units":"","space":"","address":""}],"25":[{"region_unclear":false,"space_unclear":false,"costs":"","costs_comment":"","address_hidden":true,"region_hidden":true,"space_comment":"2/4 частини","space_hidden":false,"space":"67.1","address":"м. Хмельницький","region":"Хмельницька область","costs_rent_comment":"","space_comment_unclear":true,"space_comment_hidden":false,"space_units":"м²","costs_rent":""}],"31":[{"space_unclear":true,"address_hidden":true,"region_hidden":false,"space_comment":"","space":"66.1","address":"м. Хмельницький","region":"Хмельницька область","costs_property":"","costs_rent_comment":"","space_comment_unclear":true,"address_unclear":false,"space_units":"м²","costs_property_comment":"","costs_rent":""}]},"intro":{"declaration_year":"2013","isnotdeclaration":""}}],"declarationsLength":3,"analytics":[{"y":2015,"b":13948,"i":300788,"c":1,"fi":57188,"ff":181.6,"ffa":3,"j":2},{"y":2014,"b":23494,"i":363264,"c":1,"k":67.1,"ka":1,"la":6,"fi":48295,"ff":133.2,"ffa":2,"fha":1},{"y":2013,"b":66041,"i":266193,"c":1,"k":67.1,"ka":1,"la":6,"fi":40015,"ff":66.1,"ffa":1}]}