{"2010":"","2016":"","Department":"Ленінський районний суд м. Дніпропетровська","Region":"Дніпропетровська область","Position":"Суддя Ленінського районного суду м. Дніпропетровська","Name":"Залімська Неля Володимирівна","Link":"https://drive.google.com/open?id=0BygiyWAl79DMLVhQbWFzT0Y5Mm8","Note":"У меня","AdditionalNote":"","field8":"","field9":"","Link 2015":"","Кількість справ":"","Оскаржені":"","Кількість скарг":4,"Кількість дисциплінарних стягнень":"","Клейма":"","Фото":"","Як живе":"","key":"zalimska_nelya_volodimirivna","allDeclarations":[{"provider":"declarations.com.ua","document":{"income":{"5":{"value":"268838.8","family_comment":"","value_unclear":false,"family_unclear":false,"comment_unclear":false,"comment":"","family":"30846.49"},"6":{"family_comment":"","value":"252658.8","comment_unclear":false,"family":"27207.4","comment":""},"7":{"family_comment":"","value":"","source_name":"","family":"","comment":""},"8":{"family_comment":"","value":"","family":"","comment":""},"9":{"family_comment":"","value":"","value_unclear":false,"family":"","comment":""},"10":{"family_comment":"","value":"16180","value_unclear":false,"family":"1639.09","comment":""},"11":{"family_comment":"","value":"","family":"","comment":""},"12":{"family_comment":"","value":"","family":"","comment":""},"13":{"family_comment":"","value":"","family":"2000","comment":""},"14":{"family_comment":"","value":"","family":"","comment":""},"15":{"family_comment":"","value":"","family":"","comment":""},"16":{"family_comment":"","value":"","family":"","comment":""},"17":{"family_comment":"","value":"","value_unclear":false,"family":"","comment":""},"18":{"family_comment":"","value":"","value_unclear":false,"family":"","comment":""},"19":{"family_comment":"","value":"","family":"","comment":""},"20":{"value":"120.05","family_comment":"","value_unclear":false,"family_unclear":false,"comment_unclear":false,"comment":"","family":""}},"vehicle":{"35":[{"year_hidden":false,"brand_info":"","sum_rent_comment":"","year":"2012","sum_hidden":false,"brand_info_hidden":false,"brand_info_unclear":false,"year_unclear":false,"sum_rent":"","sum":"","brand":"Kia Rio","sum_comment":"","brand_unclear":false,"brand_hidden":false}]},"id":"vulyk_84_27","declaration":{"additional_info_text":"","notfull_lostpages":"","date":"2015-03-26T00:00:00","notfull":"","additional_info":"","url":"http://static.declarations.com.ua/declarations/chosen_ones/judges_batch/2441_zalimska_nelia_volodymyrivna.pdf"},"liabilities":{"54":{"sum_foreign_comment":"","sum_comment_hidden":false,"sum":"11500","sum_comment":"","sum_foreign":""},"55":{"sum_foreign_comment":"","sum":"","sum_comment":"","sum_foreign":""},"56":{"sum_foreign_comment":"","sum":"","sum_comment":"","sum_foreign":""},"57":{"sum_foreign_comment":"","sum_comment_hidden":false,"sum":"18135.6","sum_comment":"","sum_foreign":""},"58":{"sum_foreign_comment":"","sum_comment_hidden":false,"sum":"16432.4","sum_comment":"","sum_foreign":""},"59":{"sum_foreign_comment":"","sum":"","sum_comment":"","sum_foreign":""},"60":{"sum_foreign_comment":"","sum":"","sum_comment":"","sum_foreign":""},"61":{"sum_foreign_comment":"","sum":"","sum_comment":"","sum_foreign":""},"62":{"sum_foreign_comment":"","sum":"","sum_comment":"","sum_foreign":""},"63":{"sum_foreign_comment":"","sum_comment_hidden":false,"sum":"","sum_comment":"","sum_foreign":""},"64":{"sum_foreign_comment":"","sum_comment_hidden":false,"sum":"","sum_comment":"","sum_foreign":""}},"ft_src":"18135.6\n11500\n16432.4\nДніпропетровськ\nДніпропетровська область\nсуддя ленінського районного суду м. дніпропетровська\nДніпропетровська область\nЗагальний місцевий суд\nНелля\nДитина\nДитина\nВолодимирівна\nЗалімська Нелля Володимирівна\nНелля Володимирівна Залімська\nНелля Залімська\nЗалімська Нелля Володимирівна\nЗалімська Нелля Володимирівна\nЗалімська\nKia Rio\n2012\nДніпропетровська область\nм. Дніпропетровськ\n81.2\n2014\n27207.4\n252658.8\n2000\n1639.09\n16180\n30846.49\n268838.8\n120.05\nKia Rio\n2012\n2014\nЗалімська Нелля Володимирівна\nНелля Володимирівна Залімська\nНелля Залімська\nЗалімська Нелля Володимирівна\nНелля\nДитина\nДитина\nЗалімська Нелля Володимирівна\nВолодимирівна\nсуддя ленінського районного суду м. дніпропетровська\nЗагальний місцевий суд\nДніпропетровська область\nЗалімська\nДніпропетровськ\nДніпропетровська область\n16432.4\n18135.6\n11500\n252658.8\n27207.4\n120.05\n2000\n268838.8\n30846.49\n16180\n1639.09\nм. Дніпропетровськ\nДніпропетровська область\n81.2\n16432.4\n18135.6\n11500\nДитина\nДитина\nВолодимирівна\nЗалімська\nНелля\nЗалімська Нелля Володимирівна\nНелля Володимирівна Залімська\nНелля Залімська\nЗалімська Нелля Володимирівна\nДніпропетровська область\nДніпропетровськ\nДніпропетровська область\nсуддя ленінського районного суду м. дніпропетровська\nЗагальний місцевий суд\nЗалімська Нелля Володимирівна\nKia Rio\n2012\n1639.09\n16180\n120.05\n268838.8\n30846.49\n27207.4\n252658.8\n2000\nм. Дніпропетровськ\nДніпропетровська область\n81.2\n2014","general":{"inn":"","name":"Нелля","inn_unclear":false,"family":[{"inn":"","inn_hidden":true,"inn_unclear":false,"relations_hidden":false,"relations_other":"","relations":"Дитина","name_hidden":true,"family_name":"","name_unclear":false},{"inn":"","relations":"Дитина","relations_other":"","inn_hidden":false,"family_name":"","name_hidden":false,"name_unclear":false}],"inn_hidden":true,"family_raw":"","last_name":"Залімська","post":{"post_unclear":false,"region_unclear":false,"post":"суддя ленінського районного суду м. дніпропетровська","candidate":"","office_hidden":false,"region":"Дніпропетровська область","post_hidden":false,"office":"Загальний місцевий суд","office_unclear":false,"region_hidden":false},"full_name":"Залімська Нелля Володимирівна","addresses":[{"place_city_type_unclear":false,"place_address":"","place_district_hidden":false,"place_city_type":"Місто","place_address_hidden":true,"place_address_unclear":false,"place_city_type_hidden":false,"place":"Дніпропетровська область","place_district":"","place_unclear":false,"place_city":"Дніпропетровськ","place_city_unclear":false,"place_hidden":false,"place_city_hidden":false,"place_district_unclear":false}],"patronymic":"Володимирівна","full_name_suggest":{"output":"Залімська Нелля Володимирівна","input":["Залімська Нелля Володимирівна","Нелля Володимирівна Залімська","Нелля Залімська"]}},"source":"VULYK","estate":{"31":[{"space_unclear":false,"address_hidden":true,"region_hidden":false,"space_comment":"","space":"81.2","address":"м. Дніпропетровськ","region":"Дніпропетровська область","costs_property":"","costs_rent_comment":"","address_unclear":false,"space_units":"м²","costs_property_comment":"","costs_rent":""}]},"intro":{"declaration_year":"2014","isnotdeclaration":"","declaration_year_unclear":false}}}],"declarations":[{"income":{"5":{"value":"268838.8","family_comment":"","value_unclear":false,"family_unclear":false,"comment_unclear":false,"comment":"","family":"30846.49"},"6":{"family_comment":"","value":"252658.8","comment_unclear":false,"family":"27207.4","comment":""},"7":{"family_comment":"","value":"","source_name":"","family":"","comment":""},"8":{"family_comment":"","value":"","family":"","comment":""},"9":{"family_comment":"","value":"","value_unclear":false,"family":"","comment":""},"10":{"family_comment":"","value":"16180","value_unclear":false,"family":"1639.09","comment":""},"11":{"family_comment":"","value":"","family":"","comment":""},"12":{"family_comment":"","value":"","family":"","comment":""},"13":{"family_comment":"","value":"","family":"2000","comment":""},"14":{"family_comment":"","value":"","family":"","comment":""},"15":{"family_comment":"","value":"","family":"","comment":""},"16":{"family_comment":"","value":"","family":"","comment":""},"17":{"family_comment":"","value":"","value_unclear":false,"family":"","comment":""},"18":{"family_comment":"","value":"","value_unclear":false,"family":"","comment":""},"19":{"family_comment":"","value":"","family":"","comment":""},"20":{"value":"120.05","family_comment":"","value_unclear":false,"family_unclear":false,"comment_unclear":false,"comment":"","family":""}},"vehicle":{"35":[{"year_hidden":false,"brand_info":"","sum_rent_comment":"","year":"2012","sum_hidden":false,"brand_info_hidden":false,"brand_info_unclear":false,"year_unclear":false,"sum_rent":"","sum":"","brand":"Kia Rio","sum_comment":"","brand_unclear":false,"brand_hidden":false}]},"id":"vulyk_84_27","declaration":{"additional_info_text":"","notfull_lostpages":"","date":"2015-03-26T00:00:00","notfull":"","additional_info":"","url":"http://static.declarations.com.ua/declarations/chosen_ones/judges_batch/2441_zalimska_nelia_volodymyrivna.pdf"},"liabilities":{"54":{"sum_foreign_comment":"","sum_comment_hidden":false,"sum":"11500","sum_comment":"","sum_foreign":""},"55":{"sum_foreign_comment":"","sum":"","sum_comment":"","sum_foreign":""},"56":{"sum_foreign_comment":"","sum":"","sum_comment":"","sum_foreign":""},"57":{"sum_foreign_comment":"","sum_comment_hidden":false,"sum":"18135.6","sum_comment":"","sum_foreign":""},"58":{"sum_foreign_comment":"","sum_comment_hidden":false,"sum":"16432.4","sum_comment":"","sum_foreign":""},"59":{"sum_foreign_comment":"","sum":"","sum_comment":"","sum_foreign":""},"60":{"sum_foreign_comment":"","sum":"","sum_comment":"","sum_foreign":""},"61":{"sum_foreign_comment":"","sum":"","sum_comment":"","sum_foreign":""},"62":{"sum_foreign_comment":"","sum":"","sum_comment":"","sum_foreign":""},"63":{"sum_foreign_comment":"","sum_comment_hidden":false,"sum":"","sum_comment":"","sum_foreign":""},"64":{"sum_foreign_comment":"","sum_comment_hidden":false,"sum":"","sum_comment":"","sum_foreign":""}},"ft_src":"18135.6\n11500\n16432.4\nДніпропетровськ\nДніпропетровська область\nсуддя ленінського районного суду м. дніпропетровська\nДніпропетровська область\nЗагальний місцевий суд\nНелля\nДитина\nДитина\nВолодимирівна\nЗалімська Нелля Володимирівна\nНелля Володимирівна Залімська\nНелля Залімська\nЗалімська Нелля Володимирівна\nЗалімська Нелля Володимирівна\nЗалімська\nKia Rio\n2012\nДніпропетровська область\nм. Дніпропетровськ\n81.2\n2014\n27207.4\n252658.8\n2000\n1639.09\n16180\n30846.49\n268838.8\n120.05\nKia Rio\n2012\n2014\nЗалімська Нелля Володимирівна\nНелля Володимирівна Залімська\nНелля Залімська\nЗалімська Нелля Володимирівна\nНелля\nДитина\nДитина\nЗалімська Нелля Володимирівна\nВолодимирівна\nсуддя ленінського районного суду м. дніпропетровська\nЗагальний місцевий суд\nДніпропетровська область\nЗалімська\nДніпропетровськ\nДніпропетровська область\n16432.4\n18135.6\n11500\n252658.8\n27207.4\n120.05\n2000\n268838.8\n30846.49\n16180\n1639.09\nм. Дніпропетровськ\nДніпропетровська область\n81.2\n16432.4\n18135.6\n11500\nДитина\nДитина\nВолодимирівна\nЗалімська\nНелля\nЗалімська Нелля Володимирівна\nНелля Володимирівна Залімська\nНелля Залімська\nЗалімська Нелля Володимирівна\nДніпропетровська область\nДніпропетровськ\nДніпропетровська область\nсуддя ленінського районного суду м. дніпропетровська\nЗагальний місцевий суд\nЗалімська Нелля Володимирівна\nKia Rio\n2012\n1639.09\n16180\n120.05\n268838.8\n30846.49\n27207.4\n252658.8\n2000\nм. Дніпропетровськ\nДніпропетровська область\n81.2\n2014","general":{"inn":"","name":"Нелля","inn_unclear":false,"family":[{"inn":"","inn_hidden":true,"inn_unclear":false,"relations_hidden":false,"relations_other":"","relations":"Дитина","name_hidden":true,"family_name":"","name_unclear":false},{"inn":"","relations":"Дитина","relations_other":"","inn_hidden":false,"family_name":"","name_hidden":false,"name_unclear":false}],"inn_hidden":true,"family_raw":"","last_name":"Залімська","post":{"post_unclear":false,"region_unclear":false,"post":"суддя ленінського районного суду м. дніпропетровська","candidate":"","office_hidden":false,"region":"Дніпропетровська область","post_hidden":false,"office":"Загальний місцевий суд","office_unclear":false,"region_hidden":false},"full_name":"Залімська Нелля Володимирівна","addresses":[{"place_city_type_unclear":false,"place_address":"","place_district_hidden":false,"place_city_type":"Місто","place_address_hidden":true,"place_address_unclear":false,"place_city_type_hidden":false,"place":"Дніпропетровська область","place_district":"","place_unclear":false,"place_city":"Дніпропетровськ","place_city_unclear":false,"place_hidden":false,"place_city_hidden":false,"place_district_unclear":false}],"patronymic":"Володимирівна","full_name_suggest":{"output":"Залімська Нелля Володимирівна","input":["Залімська Нелля Володимирівна","Нелля Володимирівна Залімська","Нелля Залімська"]}},"source":"VULYK","estate":{"31":[{"space_unclear":false,"address_hidden":true,"region_hidden":false,"space_comment":"","space":"81.2","address":"м. Дніпропетровськ","region":"Дніпропетровська область","costs_property":"","costs_rent_comment":"","address_unclear":false,"space_units":"м²","costs_property_comment":"","costs_rent":""}]},"intro":{"declaration_year":"2014","isnotdeclaration":"","declaration_year_unclear":false}}],"declarationsLength":1,"analytics":[{"y":2014,"i":268838.8,"c":1,"fi":30846.49,"ff":81.2,"ffa":1}]}