{"2010":"","2016":"","Department":"Апеляційний суд Одеської області","Region":"Одеська область","Position":"Суддя Апеляційного суду Одеської області","Name":"Железнов Валентин Миколайович","Link":"https://drive.google.com/open?id=0BygiyWAl79DMNmkwamtZUTRxNjQ","Note":"У меня","AdditionalNote":"","field8":"","field9":"","field10":"","Кількість справ":"","Оскаржені":"","Кількість скарг":3,"Кількість дисциплінарних стягнень":"","Клейма":"","Фото":"","Як живе":"","key":"zheleznov_valentin_mikolayovich","allDeclarations":[{"provider":"declarations.com.ua","document":{"income":{"5":{"family_comment":"","value":"331095","value_unclear":false,"family":"325788","comment":""},"6":{"value":"254295","value_unclear":false,"family_hidden":false,"family_comment":"","family":"36147","comment":""},"7":{"source_name_unclear":false,"value":"","family_comment":"","source_name":"","family":"","comment":""},"8":{"family_comment":"","value":"","family":"","comment":""},"9":{"family_comment":"","value":"","family":"","comment":""},"10":{"family_comment":"","value":"","family":"","comment":""},"11":{"family_comment":"","value":"","comment_unclear":false,"family":"","comment":""},"12":{"family_comment":"","value":"","family":"","comment":""},"13":{"family_comment":"","value":"","family":"","comment":""},"14":{"family_comment":"","value":"","family":"","comment":""},"15":{"family_comment":"","value":"","family":"","comment":""},"16":{"family_comment":"","value":"76800","family":"","comment":""},"17":{"family_comment":"","value":"","family":"289641","comment":""},"18":{"family_comment":"","value":"","family":"","comment":""},"19":{"family_comment":"","value":"","family":"","comment":""},"20":{"value":"","family_comment":"","value_unclear":false,"family_unclear":false,"comment_unclear":false,"comment":"","family":""}},"vehicle":{"35":[{"brand_info":"","sum_rent_comment":"","brand":"","sum_comment":"","brand_unclear":false,"year":"","sum_rent_unclear":false,"brand_info_hidden":true,"brand_info_unclear":false,"sum":"","sum_rent":""}],"40":[{"brand_info":"","sum_rent_comment":"","brand":"Toyota Corolla","sum_comment":"","year":"2007","brand_hidden":false,"brand_info_hidden":false,"brand_info_unclear":false,"sum":"","sum_rent":""}]},"id":"vulyk_101_25","declaration":{"additional_info_text":"","notfull_lostpages":"","date":"2016-03-30T00:00:00","notfull":"","additional_info":"","url":"http://static.declarations.com.ua/declarations/chosen_ones/judges_batch/689_zheleznov_valentyn_mykolaiovych_2015.pdf"},"liabilities":{"54":{"sum_foreign_comment":"","sum":"","sum_comment":"","sum_comment_unclear":false,"sum_hidden":false,"sum_comment_hidden":false,"sum_unclear":false,"sum_foreign":""},"55":{"sum_foreign_comment":"","sum":"","sum_comment":"","sum_foreign":""},"56":{"sum_foreign_comment":"","sum":"","sum_comment":"","sum_comment_hidden":false,"sum_unclear":false,"sum_foreign":""},"57":{"sum_foreign_comment":"","sum":"","sum_comment":"","sum_hidden":false,"sum_comment_hidden":false,"sum_unclear":false,"sum_foreign":""},"58":{"sum_foreign_comment":"","sum":"","sum_comment":"","sum_comment_unclear":false,"sum_hidden":false,"sum_comment_hidden":false,"sum_unclear":false,"sum_foreign":""},"59":{"sum_foreign_comment":"","sum":"","sum_comment":"","sum_foreign":""},"60":{"sum_foreign_comment":"","sum":"","sum_comment":"","sum_hidden":false,"sum_comment_hidden":false,"sum_unclear":false,"sum_foreign":""},"61":{"sum_foreign_comment":"","sum":"","sum_comment":"","sum_foreign":""},"62":{"sum_foreign_comment":"","sum":"","sum_comment":"","sum_comment_unclear":false,"sum_foreign":""},"63":{"sum_foreign_comment":"","sum_comment_hidden":false,"sum":"","sum_comment":"","sum_foreign":""},"64":{"sum_foreign_comment":"","sum_comment_hidden":false,"sum":"","sum_comment":"","sum_foreign":""}},"ft_src":"суддя апеляційного суду одеської області\nОдеська область\nЗагальний апеляційний суд\nВалентин\nЖелєзнова М. Г\nПодружжя\nМиколайович\nЖелєзнов Валентин Миколайович\nЖелєзнов\nЖелєзнов Валентин Миколайович\nВалентин Миколайович Желєзнов\nВалентин Желєзнов\nЖелєзнов Валентин Миколайович\nToyota Corolla\n2007\n24.5\n64.1\n30.66\n33.6\n164.1\n39.9\n282971\n2015\n36147\n254295\n325788\n331095\n76800\n289641\n2007\nToyota Corolla\n33.6\n64.1\n30.66\n24.5\n282971\n39.9\n164.1\nЖелєзнов Валентин Миколайович\nВалентин Миколайович Желєзнов\nВалентин Желєзнов\nЖелєзнов Валентин Миколайович\nВалентин\nЖелєзнов Валентин Миколайович\nМиколайович\nсуддя апеляційного суду одеської області\nОдеська область\nЗагальний апеляційний суд\nЖелєзнов\nПодружжя\nЖелєзнова М. Г\n254295\n36147\n289641\n331095\n325788\n76800\n2015\nЖелєзнова М. Г\nПодружжя\nВалентин\nМиколайович\nЖелєзнов\nЖелєзнов Валентин Миколайович\nВалентин Миколайович Желєзнов\nВалентин Желєзнов\nЖелєзнов Валентин Миколайович\nсуддя апеляційного суду одеської області\nОдеська область\nЗагальний апеляційний суд\nЖелєзнов Валентин Миколайович\nToyota Corolla\n2007\n325788\n331095\n76800\n289641\n254295\n36147\n64.1\n30.66\n282971\n39.9\n24.5\n164.1\n33.6\n2015","general":{"inn":"","name":"Валентин","inn_unclear":false,"family":[{"inn":"","relations":"Подружжя","relations_other":"","inn_hidden":true,"family_name":"Желєзнова М. Г","name_hidden":true,"name_unclear":false}],"inn_hidden":true,"family_raw":"","last_name":"Желєзнов","post":{"region":"Одеська область","region_unclear":false,"post":"суддя апеляційного суду одеської області","office_unclear":false,"office":"Загальний апеляційний суд"},"full_name":"Желєзнов Валентин Миколайович","addresses":[{"place_district":"","place_address_hidden":true,"place_city":"","place_city_type_hidden":false,"place_district_hidden":false,"place_city_type":"","place_city_hidden":true,"place_address":"","place_hidden":true,"place":""}],"patronymic":"Миколайович","patronymic_hidden":false,"full_name_suggest":{"output":"Желєзнов Валентин Миколайович","input":["Желєзнов Валентин Миколайович","Валентин Миколайович Желєзнов","Валентин Желєзнов"]}},"source":"VULYK","estate":{"25":[{"space_unclear":false,"costs":"282971","costs_comment":"","address_hidden":false,"region_hidden":true,"space_comment":"","space_hidden":false,"space":"39.9","address":"","region":"","costs_rent_comment":"","space_comment_unclear":false,"space_units":"м²","costs_rent":""}],"27":[{"space_hidden":false,"costs":"","costs_comment":"","address_hidden":false,"region_hidden":true,"space_comment":"","space":"33.6","address":"","region":"","costs_rent_comment":"","space_units":"м²","costs_rent":""}],"28":[{"costs_rent":"","region":"","costs":"","costs_rent_comment":"","costs_comment":"","address_hidden":false,"region_hidden":true,"space_comment":"","space_units":"м²","space":"24.5","address":""}],"31":[{"space_unclear":false,"address_hidden":false,"region_hidden":true,"space_comment":"","space_hidden":false,"space":"64.1","address":"","costs_rent_comment_unclear":false,"region":"","costs_property":"","costs_rent_comment":"","space_units":"м²","costs_property_comment":"","costs_rent":""},{"costs_rent":"","region":"","costs_property":"","costs_rent_comment":"","space_comment":"","costs_property_comment":"","space_units":"м²","space":"30.66","address":""}],"34":[{"space_hidden":false,"address_hidden":false,"region_hidden":true,"space_comment":"","space":"164.1","address":"","region":"","costs_property":"","costs_rent_comment":"","space_comment_unclear":false,"address_unclear":false,"space_units":"м²","costs_property_comment":"","costs_rent":""}]},"intro":{"declaration_year":"2015"}}},{"provider":"declarations.com.ua","document":{"income":{"5":{"value":"259541","family_comment":"","value_unclear":false,"family_unclear":false,"family":"278906","comment":""},"6":{"family_comment":"","value":"259541","value_unclear":false,"family":"28142","comment":""},"7":{"value":"","value_unclear":false,"family_comment":"","source_name":"","family":"","comment":""},"8":{"family_comment":"","value":"","family":"","comment":""},"9":{"value":"","family_comment":"","value_unclear":false,"family_unclear":false,"family":"","comment":""},"10":{"family_comment":"","value":"","comment_unclear":false,"family":"","comment":""},"11":{"family_comment":"","value":"","family":"","comment":""},"12":{"family_comment":"","value":"","family":"","comment":""},"13":{"family_comment":"","value":"","value_unclear":false,"family":"","comment":""},"14":{"family_comment":"","value":"","family":"","comment":""},"15":{"family_comment":"","value":"","family":"","comment":""},"16":{"family_comment":"","family_unclear":false,"value":"","family":"","comment":""},"17":{"family_comment":"","family_unclear":false,"value":"","family":"250764","comment":""},"18":{"family_comment":"","value":"","family":"","comment":""},"19":{"family_comment":"","value":"","family":"","comment":""},"20":{"value":"","family_comment":"","value_unclear":false,"family_hidden":false,"value_hidden":false,"family_unclear":false,"comment_unclear":false,"comment":"","family":""}},"vehicle":{"35":[{"brand_info":"","sum_rent_comment":"","brand_info_unclear":false,"year":"1993","brand_info_hidden":false,"sum_rent_comment_unclear":false,"sum_rent":"","sum":"","brand":"Toyota Camry","sum_comment":"","brand_unclear":false,"brand_hidden":false}],"40":[{"brand_info":"","sum_rent_comment":"","brand":"Toyota Corolla","sum_comment":"","year":"2007","brand_info_hidden":false,"brand_info_unclear":false,"sum":"","sum_rent":""}]},"id":"vulyk_100_121","declaration":{"additional_info_text":"","notfull_lostpages":"","date":"2015-03-30T00:00:00","notfull":"","additional_info":"","url":"http://static.declarations.com.ua/declarations/chosen_ones/judges_batch/4325_zheleznov_valentyn_mykolaiovych.pdf"},"liabilities":{"54":{"sum_foreign_comment":"","sum":"","sum_comment":"","sum_comment_hidden":false,"sum_unclear":false,"sum_foreign":""},"55":{"sum_foreign_comment":"","sum":"","sum_comment":"","sum_foreign":""},"56":{"sum_foreign_comment":"","sum":"","sum_comment":"","sum_unclear":false,"sum_foreign":""},"57":{"sum_foreign_comment":"","sum":"","sum_comment":"","sum_comment_unclear":false,"sum_comment_hidden":false,"sum_unclear":false,"sum_foreign":""},"58":{"sum_foreign_comment":"","sum":"","sum_comment":"","sum_comment_hidden":false,"sum_unclear":false,"sum_foreign":""},"59":{"sum_foreign_comment":"","sum":"","sum_comment":"","sum_foreign":""},"60":{"sum_foreign_comment":"","sum_comment_hidden":false,"sum":"","sum_comment":"","sum_foreign":""},"61":{"sum_foreign_comment":"","sum":"","sum_comment":"","sum_foreign":""},"62":{"sum_foreign_comment":"","sum":"","sum_comment":"","sum_unclear":false,"sum_foreign":""},"63":{"sum_foreign_comment":"","sum_comment_hidden":false,"sum":"","sum_comment":"","sum_foreign":""},"64":{"sum_foreign_comment":"","sum_comment_hidden":false,"sum":"","sum_comment":"","sum_foreign":""}},"ft_src":"Желєзнов Валентин Миколайович\nсуддя апеляційного суду одеської області\nОдеська область\nЗагальний апеляційний суд\nВалентин\nЖелєзнова М. Г\nПодружжя\nЖелєзнов Валентин Миколайович\nВалентин Миколайович Желєзнов\nВалентин Желєзнов\nЖелєзнов Валентин Миколайович\nЖелєзнов\nМиколайович\nToyota Camry\n1993\n2007\nToyota Corolla\n64.1\n33.6\n164.1\n24.5\n2014\n28142\n259541\n278906\n259541\n250764\nToyota Camry\n1993\nToyota Corolla\n2007\n33.6\n64.1\n164.1\n24.5\nПодружжя\nЖелєзнова М. Г\nМиколайович\nЖелєзнов\nЖелєзнов Валентин Миколайович\nВалентин Миколайович Желєзнов\nВалентин Желєзнов\nЖелєзнов Валентин Миколайович\nЖелєзнов Валентин Миколайович\nВалентин\nЗагальний апеляційний суд\nОдеська область\nсуддя апеляційного суду одеської області\n259541\n28142\n250764\n259541\n278906\n2014\nЖелєзнова М. Г\nПодружжя\nМиколайович\nЖелєзнов\nОдеська область\nЗагальний апеляційний суд\nсуддя апеляційного суду одеської області\nЖелєзнов Валентин Миколайович\nЖелєзнов Валентин Миколайович\nВалентин Миколайович Желєзнов\nВалентин Желєзнов\nЖелєзнов Валентин Миколайович\nВалентин\n1993\nToyota Camry\n2007\nToyota Corolla\n259541\n278906\n250764\n28142\n259541\n64.1\n24.5\n164.1\n33.6\n2014","general":{"inn":"","inn_hidden":true,"last_name":"Желєзнов","post":{"post_unclear":false,"region_unclear":false,"post":"суддя апеляційного суду одеської області","office":"Загальний апеляційний суд","region":"Одеська область","post_hidden":false,"office_unclear":false},"name":"Валентин","full_name":"Желєзнов Валентин Миколайович","family_raw":"","addresses":[{"place_district":"","place_city_hidden":true,"place_city":"","place_city_unclear":false,"place_district_hidden":false,"place_city_type":"","place_address_hidden":true,"place_city_type_hidden":false,"place_address":"","place_hidden":true,"place":""}],"family":[{"inn_hidden":true,"inn":"","name_hidden":true,"family_name":"Желєзнова М. Г","relations":"Подружжя","name_unclear":false}],"full_name_suggest":{"output":"Желєзнов Валентин Миколайович","input":["Желєзнов Валентин Миколайович","Валентин Миколайович Желєзнов","Валентин Желєзнов"]},"patronymic":"Миколайович"},"source":"VULYK","estate":{"27":[{"space_unclear":false,"costs":"","costs_comment":"","address_hidden":false,"region_hidden":true,"space_comment":"","space":"33.6","address":"","region":"","address_unclear":false,"costs_rent_comment":"","space_units":"м²","costs_rent":""}],"28":[{"costs_rent":"","region":"","costs":"","costs_rent_comment":"","costs_comment":"","address_hidden":false,"region_hidden":true,"space_comment":"","space_units":"м²","space":"24.5","address":""}],"31":[{"region_unclear":false,"space_unclear":false,"costs_property_comment_unclear":false,"address_hidden":true,"region_hidden":true,"space_comment":"","space":"64.1","address":"","region":"","costs_property":"","costs_rent_comment":"","space_comment_unclear":false,"address_unclear":false,"space_units":"м²","costs_property_comment":"","costs_rent":""}],"34":[{"costs_rent":"","region":"","costs_property":"","costs_rent_comment":"","address_hidden":true,"region_hidden":true,"space_comment":"","costs_property_comment":"","space_units":"м²","space":"164.1","address":""}]},"intro":{"declaration_year":"2014"}}},{"provider":"declarations.com.ua","document":{"income":{"5":{"family_comment":"","value":"242234","family":"326472","comment":""},"6":{"family_comment":"","value":"242234","family":"26792","comment":""},"7":{"family_comment":"","value":"0","source_name":"0","family":"0","comment":""},"8":{"family_comment":"","value":"0","family":"0","comment":""},"9":{"family_comment":"","value":"0","family":"4416","comment":""},"10":{"family_comment":"","value":"0","family":"0","comment":""},"11":{"family_comment":"","value":"0","family":"0","comment":""},"12":{"family_comment":"","value":"0","family":"0","comment":""},"13":{"family_comment":"","value":"0","family":"0","comment":""},"14":{"family_comment":"","value":"0","family":"0","comment":""},"15":{"family_comment":"","value":"0","family":"0","comment":""},"16":{"family_comment":"","value":"0","family":"0","comment":""},"17":{"family_comment":"","value":"0","family":"295264","comment":""},"18":{"family_comment":"","value":"0","family":"0","comment":""},"19":{"family_comment":"","value":"0","family":"0","comment":""},"20":{"family_comment":"","value":"0","family":"0","comment":""},"21":[{"cur":"0","country":"0","uah_equal":"0","country_comment":""},{"cur":"0","country":"0","uah_equal":"0","country_comment":""},{"cur":"0","country":"0","uah_equal":"0","country_comment":""},{"cur":"0","country":"0","uah_equal":"0","country_comment":""},{"cur":"0","country":"0","uah_equal":"0","country_comment":""}],"22":[{"cur":"0","country":"0","uah_equal":"0","country_comment":""},{"cur":"0","country":"0","uah_equal":"0","country_comment":""},{"cur":"0","country":"0","uah_equal":"0","country_comment":""},{"cur":"0","country":"0","uah_equal":"0","country_comment":""},{"cur":"0","country":"0","uah_equal":"0","country_comment":""}]},"vehicle":{"35":[{"brand_info":"","sum_rent_comment":"","brand":"Toyota,Camry","sum_comment":"","year":"1993","brand_hidden":false,"sum":"","sum_rent":""}]},"id":"4432","banks":{"45":[{"sum_foreign_comment":"","sum_units":"UAH","sum_comment":"","sum_foreign_units":"","sum":"","sum_foreign":""},{"sum_foreign_comment":"","sum_units":"USD","sum_comment":"","sum_foreign_units":"","sum":"","sum_foreign":""},{"sum_foreign_comment":"","sum_units":"EUR","sum_comment":"","sum_foreign_units":"","sum":"","sum_foreign":""}],"46":[{"sum_foreign_comment":"","sum_units":"UAH","sum_comment":"","sum_foreign_units":"","sum":"","sum_foreign":""},{"sum_foreign_comment":"","sum_units":"USD","sum_comment":"","sum_foreign_units":"","sum":"","sum_foreign":""},{"sum_foreign_comment":"","sum_units":"EUR","sum_comment":"","sum_foreign_units":"","sum":"","sum_foreign":""}],"47":[{"sum_foreign_comment":"","sum_units":"","sum_comment":"","sum_foreign_units":"","sum":"","sum_foreign":""}],"48":[{"sum_foreign_comment":"","sum_units":"","sum_comment":"","sum_foreign_units":"","sum":"","sum_foreign":""}],"49":[{"sum_foreign_comment":"","sum_units":"","sum_comment":"","sum_foreign_units":"","sum":"","sum_foreign":""}],"50":[{"sum_foreign_comment":"","sum_units":"","sum_comment":"","sum_foreign_units":"","sum":"","sum_foreign":""}],"51":[{"sum_foreign_comment":"","sum_units":"UAH","sum_comment":"","sum_foreign_units":"","sum":"160000","sum_foreign":""},{"sum_foreign_comment":"","sum_units":"USD","sum_comment":"","sum_foreign_units":"","sum":"","sum_foreign":""},{"sum_foreign_comment":"","sum_units":"EUR","sum_comment":"","sum_foreign_units":"","sum":"","sum_foreign":""}],"52":[{"sum_foreign_comment":"","sum_units":"","sum_comment":"","sum_foreign_units":"","sum":"","sum_foreign":""}],"53":[{"sum_foreign_comment":"","sum_units":"","sum_comment":"","sum_foreign_units":"","sum":"","sum_foreign":""}]},"declaration":{"needs_scancopy_check":false,"additional_info_text":"","notfull_lostpages":"","notfull":"FALSE","additional_info":"FALSE","url":"http://static.declarations.com.ua/declarations/sudy/apeliatsiini_sudy_oblastei__m.kyieva/odeska/geleznov_dec.pdf"},"liabilities":{"54":{"sum_foreign_comment":"","sum":"","sum_comment":"","sum_foreign":""},"55":{"sum_foreign_comment":"","sum_units":"","sum_comment":"","sum_foreign_units":"","sum":"","sum_foreign":""},"56":{"sum_foreign_comment":"","sum":"","sum_comment":"","sum_foreign":""},"57":{"sum_foreign_comment":"","sum":"","sum_comment":"","sum_foreign":""},"58":{"sum_foreign_comment":"","sum":"","sum_comment":"","sum_foreign":""},"59":{"sum_foreign_comment":"","sum":"","sum_comment":"","sum_foreign":""},"60":{"sum_foreign_comment":"","sum":"","sum_comment":"","sum_foreign":""},"61":{"sum_foreign_comment":"","sum_units":"","sum_comment":"","sum_foreign_units":"","sum":"","sum_foreign":""},"62":{"sum_foreign_comment":"","sum":"","sum_comment":"","sum_foreign":""},"63":{"sum_foreign_comment":"","sum_units":"","sum_comment":"","sum":"","sum_foreign":""},"64":{"sum_foreign_comment":"","sum_units":"","sum_comment":"","sum":"","sum_foreign":""}},"estate":{"23":[{"costs_rent":"","location_raw":"","region":"","costs":"","costs_rent_comment":"","costs_comment":"","space_comment":"","space_units":"","space":"","address":""},{"costs_rent":"","location_raw":"","region":"","costs":"","costs_rent_comment":"","costs_comment":"","space_comment":"","space_units":"","space":"","address":""},{"costs_rent":"","location_raw":"","region":"","costs":"","costs_rent_comment":"","costs_comment":"","space_comment":"","space_units":"","space":"","address":""}],"27":[{"costs_rent":"","location_raw":"приховано","region":"","costs":"","costs_rent_comment":"","costs_comment":"","space_comment":"","space_units":"","space":"33,6","address":""}],"28":[{"costs_rent":"","location_raw":"приховано","region":"","costs":"","costs_rent_comment":"","costs_comment":"","space_comment":"","space_units":"","space":"24,5","address":""}],"31":[{"costs_rent":"","location_raw":"приховано","region":"","costs_property":"","costs_rent_comment":"","space_comment":"","costs_property_comment":"","space_units":"","space":"64,1","address":""},{"costs_rent":"","location_raw":"приховано","region":"","costs_property":"","costs_rent_comment":"","space_comment":"","costs_property_comment":"","space_units":"","space":"30,66","address":""}],"34":[{"costs_rent":"","location_raw":"приховано","region":"","costs_property":"","costs_rent_comment":"","space_comment":"","costs_property_comment":"","space_units":"","space":"164,1","address":""}]},"general":{"name_hidden":false,"name":"Валентин","patronymic_unclear":false,"last_name_hidden":false,"addresses_raw":"приховано","post_raw":"Суддя апеляційного суду Одеської області","patronymic":"Миколайович","inn":"","family_raw":"Дружина - Желєзнова М.Г.;Син - Желєзнов В.В.","last_name":"Желєзнов","post":{"office":"Загальний апеляційний суд","region":"Одеська область","post":"Суддя"},"addresses_raw_hidden":true,"last_name_unclear":false,"full_name":"Желєзнов Валентин Миколайович","patronymic_hidden":false,"full_name_suggest":{"output":"Желєзнов Валентин Миколайович","input":["Желєзнов Валентин Миколайович","Валентин Миколайович Желєзнов","Валентин Желєзнов"]},"name_unclear":false},"ft_src":"FALSE\nFALSE\n326472\n242234\n4416\n26792\n242234\n295264\nToyota,Camry\n1993\nToyota,Camry\n1993\n33,6\n164,1\n64,1\n30,66\n24,5\n160000\nFALSE\nFALSE\nFALSE\n2013\n26792\n242234\n326472\n242234\n295264\n4416\nToyota,Camry\n1993\nFALSE\nFALSE\n33,6\n64,1\n30,66\n164,1\n24,5\nСуддя апеляційного суду Одеської області\nДружина - Желєзнова М.Г.;Син - Желєзнов В.В.\nЖелєзнов\nЖелєзнов Валентин Миколайович\nВалентин Миколайович Желєзнов\nВалентин Желєзнов\nЖелєзнов Валентин Миколайович\nВалентин\nЖелєзнов Валентин Миколайович\nЗагальний апеляційний суд\nСуддя\nОдеська область\nМиколайович\n242234\n26792\n295264\n242234\n326472\n4416\n160000\n2013\nFALSE\nЖелєзнов\nМиколайович\nДружина - Желєзнова М.Г.;Син - Желєзнов В.В.\nЖелєзнов Валентин Миколайович\nВалентин Миколайович Желєзнов\nВалентин Желєзнов\nЖелєзнов Валентин Миколайович\nВалентин\nСуддя апеляційного суду Одеської області\nСуддя\nОдеська область\nЗагальний апеляційний суд\nЖелєзнов Валентин Миколайович\n64,1\n30,66\n24,5\n164,1\n33,6\nСуддя\nОдеська область\nЗагальний апеляційний суд\nСуддя апеляційного суду Одеської області\nВалентин\nМиколайович\nДружина - Желєзнова М.Г.;Син - Желєзнов В.В.\nЖелєзнов\nЖелєзнов Валентин Миколайович\nЖелєзнов Валентин Миколайович\nВалентин Миколайович Желєзнов\nВалентин Желєзнов\nЖелєзнов Валентин Миколайович\n160000\nFALSE\n2013","intro":{"declaration_year":"2013","isnotdeclaration":"FALSE"}}}],"declarations":[{"income":{"5":{"family_comment":"","value":"331095","value_unclear":false,"family":"325788","comment":""},"6":{"value":"254295","value_unclear":false,"family_hidden":false,"family_comment":"","family":"36147","comment":""},"7":{"source_name_unclear":false,"value":"","family_comment":"","source_name":"","family":"","comment":""},"8":{"family_comment":"","value":"","family":"","comment":""},"9":{"family_comment":"","value":"","family":"","comment":""},"10":{"family_comment":"","value":"","family":"","comment":""},"11":{"family_comment":"","value":"","comment_unclear":false,"family":"","comment":""},"12":{"family_comment":"","value":"","family":"","comment":""},"13":{"family_comment":"","value":"","family":"","comment":""},"14":{"family_comment":"","value":"","family":"","comment":""},"15":{"family_comment":"","value":"","family":"","comment":""},"16":{"family_comment":"","value":"76800","family":"","comment":""},"17":{"family_comment":"","value":"","family":"289641","comment":""},"18":{"family_comment":"","value":"","family":"","comment":""},"19":{"family_comment":"","value":"","family":"","comment":""},"20":{"value":"","family_comment":"","value_unclear":false,"family_unclear":false,"comment_unclear":false,"comment":"","family":""}},"vehicle":{"35":[{"brand_info":"","sum_rent_comment":"","brand":"","sum_comment":"","brand_unclear":false,"year":"","sum_rent_unclear":false,"brand_info_hidden":true,"brand_info_unclear":false,"sum":"","sum_rent":""}],"40":[{"brand_info":"","sum_rent_comment":"","brand":"Toyota Corolla","sum_comment":"","year":"2007","brand_hidden":false,"brand_info_hidden":false,"brand_info_unclear":false,"sum":"","sum_rent":""}]},"id":"vulyk_101_25","declaration":{"additional_info_text":"","notfull_lostpages":"","date":"2016-03-30T00:00:00","notfull":"","additional_info":"","url":"http://static.declarations.com.ua/declarations/chosen_ones/judges_batch/689_zheleznov_valentyn_mykolaiovych_2015.pdf"},"liabilities":{"54":{"sum_foreign_comment":"","sum":"","sum_comment":"","sum_comment_unclear":false,"sum_hidden":false,"sum_comment_hidden":false,"sum_unclear":false,"sum_foreign":""},"55":{"sum_foreign_comment":"","sum":"","sum_comment":"","sum_foreign":""},"56":{"sum_foreign_comment":"","sum":"","sum_comment":"","sum_comment_hidden":false,"sum_unclear":false,"sum_foreign":""},"57":{"sum_foreign_comment":"","sum":"","sum_comment":"","sum_hidden":false,"sum_comment_hidden":false,"sum_unclear":false,"sum_foreign":""},"58":{"sum_foreign_comment":"","sum":"","sum_comment":"","sum_comment_unclear":false,"sum_hidden":false,"sum_comment_hidden":false,"sum_unclear":false,"sum_foreign":""},"59":{"sum_foreign_comment":"","sum":"","sum_comment":"","sum_foreign":""},"60":{"sum_foreign_comment":"","sum":"","sum_comment":"","sum_hidden":false,"sum_comment_hidden":false,"sum_unclear":false,"sum_foreign":""},"61":{"sum_foreign_comment":"","sum":"","sum_comment":"","sum_foreign":""},"62":{"sum_foreign_comment":"","sum":"","sum_comment":"","sum_comment_unclear":false,"sum_foreign":""},"63":{"sum_foreign_comment":"","sum_comment_hidden":false,"sum":"","sum_comment":"","sum_foreign":""},"64":{"sum_foreign_comment":"","sum_comment_hidden":false,"sum":"","sum_comment":"","sum_foreign":""}},"ft_src":"суддя апеляційного суду одеської області\nОдеська область\nЗагальний апеляційний суд\nВалентин\nЖелєзнова М. Г\nПодружжя\nМиколайович\nЖелєзнов Валентин Миколайович\nЖелєзнов\nЖелєзнов Валентин Миколайович\nВалентин Миколайович Желєзнов\nВалентин Желєзнов\nЖелєзнов Валентин Миколайович\nToyota Corolla\n2007\n24.5\n64.1\n30.66\n33.6\n164.1\n39.9\n282971\n2015\n36147\n254295\n325788\n331095\n76800\n289641\n2007\nToyota Corolla\n33.6\n64.1\n30.66\n24.5\n282971\n39.9\n164.1\nЖелєзнов Валентин Миколайович\nВалентин Миколайович Желєзнов\nВалентин Желєзнов\nЖелєзнов Валентин Миколайович\nВалентин\nЖелєзнов Валентин Миколайович\nМиколайович\nсуддя апеляційного суду одеської області\nОдеська область\nЗагальний апеляційний суд\nЖелєзнов\nПодружжя\nЖелєзнова М. Г\n254295\n36147\n289641\n331095\n325788\n76800\n2015\nЖелєзнова М. Г\nПодружжя\nВалентин\nМиколайович\nЖелєзнов\nЖелєзнов Валентин Миколайович\nВалентин Миколайович Желєзнов\nВалентин Желєзнов\nЖелєзнов Валентин Миколайович\nсуддя апеляційного суду одеської області\nОдеська область\nЗагальний апеляційний суд\nЖелєзнов Валентин Миколайович\nToyota Corolla\n2007\n325788\n331095\n76800\n289641\n254295\n36147\n64.1\n30.66\n282971\n39.9\n24.5\n164.1\n33.6\n2015","general":{"inn":"","name":"Валентин","inn_unclear":false,"family":[{"inn":"","relations":"Подружжя","relations_other":"","inn_hidden":true,"family_name":"Желєзнова М. Г","name_hidden":true,"name_unclear":false}],"inn_hidden":true,"family_raw":"","last_name":"Желєзнов","post":{"region":"Одеська область","region_unclear":false,"post":"суддя апеляційного суду одеської області","office_unclear":false,"office":"Загальний апеляційний суд"},"full_name":"Желєзнов Валентин Миколайович","addresses":[{"place_district":"","place_address_hidden":true,"place_city":"","place_city_type_hidden":false,"place_district_hidden":false,"place_city_type":"","place_city_hidden":true,"place_address":"","place_hidden":true,"place":""}],"patronymic":"Миколайович","patronymic_hidden":false,"full_name_suggest":{"output":"Желєзнов Валентин Миколайович","input":["Желєзнов Валентин Миколайович","Валентин Миколайович Желєзнов","Валентин Желєзнов"]}},"source":"VULYK","estate":{"25":[{"space_unclear":false,"costs":"282971","costs_comment":"","address_hidden":false,"region_hidden":true,"space_comment":"","space_hidden":false,"space":"39.9","address":"","region":"","costs_rent_comment":"","space_comment_unclear":false,"space_units":"м²","costs_rent":""}],"27":[{"space_hidden":false,"costs":"","costs_comment":"","address_hidden":false,"region_hidden":true,"space_comment":"","space":"33.6","address":"","region":"","costs_rent_comment":"","space_units":"м²","costs_rent":""}],"28":[{"costs_rent":"","region":"","costs":"","costs_rent_comment":"","costs_comment":"","address_hidden":false,"region_hidden":true,"space_comment":"","space_units":"м²","space":"24.5","address":""}],"31":[{"space_unclear":false,"address_hidden":false,"region_hidden":true,"space_comment":"","space_hidden":false,"space":"64.1","address":"","costs_rent_comment_unclear":false,"region":"","costs_property":"","costs_rent_comment":"","space_units":"м²","costs_property_comment":"","costs_rent":""},{"costs_rent":"","region":"","costs_property":"","costs_rent_comment":"","space_comment":"","costs_property_comment":"","space_units":"м²","space":"30.66","address":""}],"34":[{"space_hidden":false,"address_hidden":false,"region_hidden":true,"space_comment":"","space":"164.1","address":"","region":"","costs_property":"","costs_rent_comment":"","space_comment_unclear":false,"address_unclear":false,"space_units":"м²","costs_property_comment":"","costs_rent":""}]},"intro":{"declaration_year":"2015"}},{"income":{"5":{"value":"259541","family_comment":"","value_unclear":false,"family_unclear":false,"family":"278906","comment":""},"6":{"family_comment":"","value":"259541","value_unclear":false,"family":"28142","comment":""},"7":{"value":"","value_unclear":false,"family_comment":"","source_name":"","family":"","comment":""},"8":{"family_comment":"","value":"","family":"","comment":""},"9":{"value":"","family_comment":"","value_unclear":false,"family_unclear":false,"family":"","comment":""},"10":{"family_comment":"","value":"","comment_unclear":false,"family":"","comment":""},"11":{"family_comment":"","value":"","family":"","comment":""},"12":{"family_comment":"","value":"","family":"","comment":""},"13":{"family_comment":"","value":"","value_unclear":false,"family":"","comment":""},"14":{"family_comment":"","value":"","family":"","comment":""},"15":{"family_comment":"","value":"","family":"","comment":""},"16":{"family_comment":"","family_unclear":false,"value":"","family":"","comment":""},"17":{"family_comment":"","family_unclear":false,"value":"","family":"250764","comment":""},"18":{"family_comment":"","value":"","family":"","comment":""},"19":{"family_comment":"","value":"","family":"","comment":""},"20":{"value":"","family_comment":"","value_unclear":false,"family_hidden":false,"value_hidden":false,"family_unclear":false,"comment_unclear":false,"comment":"","family":""}},"vehicle":{"35":[{"brand_info":"","sum_rent_comment":"","brand_info_unclear":false,"year":"1993","brand_info_hidden":false,"sum_rent_comment_unclear":false,"sum_rent":"","sum":"","brand":"Toyota Camry","sum_comment":"","brand_unclear":false,"brand_hidden":false}],"40":[{"brand_info":"","sum_rent_comment":"","brand":"Toyota Corolla","sum_comment":"","year":"2007","brand_info_hidden":false,"brand_info_unclear":false,"sum":"","sum_rent":""}]},"id":"vulyk_100_121","declaration":{"additional_info_text":"","notfull_lostpages":"","date":"2015-03-30T00:00:00","notfull":"","additional_info":"","url":"http://static.declarations.com.ua/declarations/chosen_ones/judges_batch/4325_zheleznov_valentyn_mykolaiovych.pdf"},"liabilities":{"54":{"sum_foreign_comment":"","sum":"","sum_comment":"","sum_comment_hidden":false,"sum_unclear":false,"sum_foreign":""},"55":{"sum_foreign_comment":"","sum":"","sum_comment":"","sum_foreign":""},"56":{"sum_foreign_comment":"","sum":"","sum_comment":"","sum_unclear":false,"sum_foreign":""},"57":{"sum_foreign_comment":"","sum":"","sum_comment":"","sum_comment_unclear":false,"sum_comment_hidden":false,"sum_unclear":false,"sum_foreign":""},"58":{"sum_foreign_comment":"","sum":"","sum_comment":"","sum_comment_hidden":false,"sum_unclear":false,"sum_foreign":""},"59":{"sum_foreign_comment":"","sum":"","sum_comment":"","sum_foreign":""},"60":{"sum_foreign_comment":"","sum_comment_hidden":false,"sum":"","sum_comment":"","sum_foreign":""},"61":{"sum_foreign_comment":"","sum":"","sum_comment":"","sum_foreign":""},"62":{"sum_foreign_comment":"","sum":"","sum_comment":"","sum_unclear":false,"sum_foreign":""},"63":{"sum_foreign_comment":"","sum_comment_hidden":false,"sum":"","sum_comment":"","sum_foreign":""},"64":{"sum_foreign_comment":"","sum_comment_hidden":false,"sum":"","sum_comment":"","sum_foreign":""}},"ft_src":"Желєзнов Валентин Миколайович\nсуддя апеляційного суду одеської області\nОдеська область\nЗагальний апеляційний суд\nВалентин\nЖелєзнова М. Г\nПодружжя\nЖелєзнов Валентин Миколайович\nВалентин Миколайович Желєзнов\nВалентин Желєзнов\nЖелєзнов Валентин Миколайович\nЖелєзнов\nМиколайович\nToyota Camry\n1993\n2007\nToyota Corolla\n64.1\n33.6\n164.1\n24.5\n2014\n28142\n259541\n278906\n259541\n250764\nToyota Camry\n1993\nToyota Corolla\n2007\n33.6\n64.1\n164.1\n24.5\nПодружжя\nЖелєзнова М. Г\nМиколайович\nЖелєзнов\nЖелєзнов Валентин Миколайович\nВалентин Миколайович Желєзнов\nВалентин Желєзнов\nЖелєзнов Валентин Миколайович\nЖелєзнов Валентин Миколайович\nВалентин\nЗагальний апеляційний суд\nОдеська область\nсуддя апеляційного суду одеської області\n259541\n28142\n250764\n259541\n278906\n2014\nЖелєзнова М. Г\nПодружжя\nМиколайович\nЖелєзнов\nОдеська область\nЗагальний апеляційний суд\nсуддя апеляційного суду одеської області\nЖелєзнов Валентин Миколайович\nЖелєзнов Валентин Миколайович\nВалентин Миколайович Желєзнов\nВалентин Желєзнов\nЖелєзнов Валентин Миколайович\nВалентин\n1993\nToyota Camry\n2007\nToyota Corolla\n259541\n278906\n250764\n28142\n259541\n64.1\n24.5\n164.1\n33.6\n2014","general":{"inn":"","inn_hidden":true,"last_name":"Желєзнов","post":{"post_unclear":false,"region_unclear":false,"post":"суддя апеляційного суду одеської області","office":"Загальний апеляційний суд","region":"Одеська область","post_hidden":false,"office_unclear":false},"name":"Валентин","full_name":"Желєзнов Валентин Миколайович","family_raw":"","addresses":[{"place_district":"","place_city_hidden":true,"place_city":"","place_city_unclear":false,"place_district_hidden":false,"place_city_type":"","place_address_hidden":true,"place_city_type_hidden":false,"place_address":"","place_hidden":true,"place":""}],"family":[{"inn_hidden":true,"inn":"","name_hidden":true,"family_name":"Желєзнова М. Г","relations":"Подружжя","name_unclear":false}],"full_name_suggest":{"output":"Желєзнов Валентин Миколайович","input":["Желєзнов Валентин Миколайович","Валентин Миколайович Желєзнов","Валентин Желєзнов"]},"patronymic":"Миколайович"},"source":"VULYK","estate":{"27":[{"space_unclear":false,"costs":"","costs_comment":"","address_hidden":false,"region_hidden":true,"space_comment":"","space":"33.6","address":"","region":"","address_unclear":false,"costs_rent_comment":"","space_units":"м²","costs_rent":""}],"28":[{"costs_rent":"","region":"","costs":"","costs_rent_comment":"","costs_comment":"","address_hidden":false,"region_hidden":true,"space_comment":"","space_units":"м²","space":"24.5","address":""}],"31":[{"region_unclear":false,"space_unclear":false,"costs_property_comment_unclear":false,"address_hidden":true,"region_hidden":true,"space_comment":"","space":"64.1","address":"","region":"","costs_property":"","costs_rent_comment":"","space_comment_unclear":false,"address_unclear":false,"space_units":"м²","costs_property_comment":"","costs_rent":""}],"34":[{"costs_rent":"","region":"","costs_property":"","costs_rent_comment":"","address_hidden":true,"region_hidden":true,"space_comment":"","costs_property_comment":"","space_units":"м²","space":"164.1","address":""}]},"intro":{"declaration_year":"2014"}},{"income":{"5":{"family_comment":"","value":"242234","family":"326472","comment":""},"6":{"family_comment":"","value":"242234","family":"26792","comment":""},"7":{"family_comment":"","value":"0","source_name":"0","family":"0","comment":""},"8":{"family_comment":"","value":"0","family":"0","comment":""},"9":{"family_comment":"","value":"0","family":"4416","comment":""},"10":{"family_comment":"","value":"0","family":"0","comment":""},"11":{"family_comment":"","value":"0","family":"0","comment":""},"12":{"family_comment":"","value":"0","family":"0","comment":""},"13":{"family_comment":"","value":"0","family":"0","comment":""},"14":{"family_comment":"","value":"0","family":"0","comment":""},"15":{"family_comment":"","value":"0","family":"0","comment":""},"16":{"family_comment":"","value":"0","family":"0","comment":""},"17":{"family_comment":"","value":"0","family":"295264","comment":""},"18":{"family_comment":"","value":"0","family":"0","comment":""},"19":{"family_comment":"","value":"0","family":"0","comment":""},"20":{"family_comment":"","value":"0","family":"0","comment":""},"21":[{"cur":"0","country":"0","uah_equal":"0","country_comment":""},{"cur":"0","country":"0","uah_equal":"0","country_comment":""},{"cur":"0","country":"0","uah_equal":"0","country_comment":""},{"cur":"0","country":"0","uah_equal":"0","country_comment":""},{"cur":"0","country":"0","uah_equal":"0","country_comment":""}],"22":[{"cur":"0","country":"0","uah_equal":"0","country_comment":""},{"cur":"0","country":"0","uah_equal":"0","country_comment":""},{"cur":"0","country":"0","uah_equal":"0","country_comment":""},{"cur":"0","country":"0","uah_equal":"0","country_comment":""},{"cur":"0","country":"0","uah_equal":"0","country_comment":""}]},"vehicle":{"35":[{"brand_info":"","sum_rent_comment":"","brand":"Toyota,Camry","sum_comment":"","year":"1993","brand_hidden":false,"sum":"","sum_rent":""}]},"id":"4432","banks":{"45":[{"sum_foreign_comment":"","sum_units":"UAH","sum_comment":"","sum_foreign_units":"","sum":"","sum_foreign":""},{"sum_foreign_comment":"","sum_units":"USD","sum_comment":"","sum_foreign_units":"","sum":"","sum_foreign":""},{"sum_foreign_comment":"","sum_units":"EUR","sum_comment":"","sum_foreign_units":"","sum":"","sum_foreign":""}],"46":[{"sum_foreign_comment":"","sum_units":"UAH","sum_comment":"","sum_foreign_units":"","sum":"","sum_foreign":""},{"sum_foreign_comment":"","sum_units":"USD","sum_comment":"","sum_foreign_units":"","sum":"","sum_foreign":""},{"sum_foreign_comment":"","sum_units":"EUR","sum_comment":"","sum_foreign_units":"","sum":"","sum_foreign":""}],"47":[{"sum_foreign_comment":"","sum_units":"","sum_comment":"","sum_foreign_units":"","sum":"","sum_foreign":""}],"48":[{"sum_foreign_comment":"","sum_units":"","sum_comment":"","sum_foreign_units":"","sum":"","sum_foreign":""}],"49":[{"sum_foreign_comment":"","sum_units":"","sum_comment":"","sum_foreign_units":"","sum":"","sum_foreign":""}],"50":[{"sum_foreign_comment":"","sum_units":"","sum_comment":"","sum_foreign_units":"","sum":"","sum_foreign":""}],"51":[{"sum_foreign_comment":"","sum_units":"UAH","sum_comment":"","sum_foreign_units":"","sum":"160000","sum_foreign":""},{"sum_foreign_comment":"","sum_units":"USD","sum_comment":"","sum_foreign_units":"","sum":"","sum_foreign":""},{"sum_foreign_comment":"","sum_units":"EUR","sum_comment":"","sum_foreign_units":"","sum":"","sum_foreign":""}],"52":[{"sum_foreign_comment":"","sum_units":"","sum_comment":"","sum_foreign_units":"","sum":"","sum_foreign":""}],"53":[{"sum_foreign_comment":"","sum_units":"","sum_comment":"","sum_foreign_units":"","sum":"","sum_foreign":""}]},"declaration":{"needs_scancopy_check":false,"additional_info_text":"","notfull_lostpages":"","notfull":"FALSE","additional_info":"FALSE","url":"http://static.declarations.com.ua/declarations/sudy/apeliatsiini_sudy_oblastei__m.kyieva/odeska/geleznov_dec.pdf"},"liabilities":{"54":{"sum_foreign_comment":"","sum":"","sum_comment":"","sum_foreign":""},"55":{"sum_foreign_comment":"","sum_units":"","sum_comment":"","sum_foreign_units":"","sum":"","sum_foreign":""},"56":{"sum_foreign_comment":"","sum":"","sum_comment":"","sum_foreign":""},"57":{"sum_foreign_comment":"","sum":"","sum_comment":"","sum_foreign":""},"58":{"sum_foreign_comment":"","sum":"","sum_comment":"","sum_foreign":""},"59":{"sum_foreign_comment":"","sum":"","sum_comment":"","sum_foreign":""},"60":{"sum_foreign_comment":"","sum":"","sum_comment":"","sum_foreign":""},"61":{"sum_foreign_comment":"","sum_units":"","sum_comment":"","sum_foreign_units":"","sum":"","sum_foreign":""},"62":{"sum_foreign_comment":"","sum":"","sum_comment":"","sum_foreign":""},"63":{"sum_foreign_comment":"","sum_units":"","sum_comment":"","sum":"","sum_foreign":""},"64":{"sum_foreign_comment":"","sum_units":"","sum_comment":"","sum":"","sum_foreign":""}},"estate":{"23":[{"costs_rent":"","location_raw":"","region":"","costs":"","costs_rent_comment":"","costs_comment":"","space_comment":"","space_units":"","space":"","address":""},{"costs_rent":"","location_raw":"","region":"","costs":"","costs_rent_comment":"","costs_comment":"","space_comment":"","space_units":"","space":"","address":""},{"costs_rent":"","location_raw":"","region":"","costs":"","costs_rent_comment":"","costs_comment":"","space_comment":"","space_units":"","space":"","address":""}],"27":[{"costs_rent":"","location_raw":"приховано","region":"","costs":"","costs_rent_comment":"","costs_comment":"","space_comment":"","space_units":"","space":"33,6","address":""}],"28":[{"costs_rent":"","location_raw":"приховано","region":"","costs":"","costs_rent_comment":"","costs_comment":"","space_comment":"","space_units":"","space":"24,5","address":""}],"31":[{"costs_rent":"","location_raw":"приховано","region":"","costs_property":"","costs_rent_comment":"","space_comment":"","costs_property_comment":"","space_units":"","space":"64,1","address":""},{"costs_rent":"","location_raw":"приховано","region":"","costs_property":"","costs_rent_comment":"","space_comment":"","costs_property_comment":"","space_units":"","space":"30,66","address":""}],"34":[{"costs_rent":"","location_raw":"приховано","region":"","costs_property":"","costs_rent_comment":"","space_comment":"","costs_property_comment":"","space_units":"","space":"164,1","address":""}]},"general":{"name_hidden":false,"name":"Валентин","patronymic_unclear":false,"last_name_hidden":false,"addresses_raw":"приховано","post_raw":"Суддя апеляційного суду Одеської області","patronymic":"Миколайович","inn":"","family_raw":"Дружина - Желєзнова М.Г.;Син - Желєзнов В.В.","last_name":"Желєзнов","post":{"office":"Загальний апеляційний суд","region":"Одеська область","post":"Суддя"},"addresses_raw_hidden":true,"last_name_unclear":false,"full_name":"Желєзнов Валентин Миколайович","patronymic_hidden":false,"full_name_suggest":{"output":"Желєзнов Валентин Миколайович","input":["Желєзнов Валентин Миколайович","Валентин Миколайович Желєзнов","Валентин Желєзнов"]},"name_unclear":false},"ft_src":"FALSE\nFALSE\n326472\n242234\n4416\n26792\n242234\n295264\nToyota,Camry\n1993\nToyota,Camry\n1993\n33,6\n164,1\n64,1\n30,66\n24,5\n160000\nFALSE\nFALSE\nFALSE\n2013\n26792\n242234\n326472\n242234\n295264\n4416\nToyota,Camry\n1993\nFALSE\nFALSE\n33,6\n64,1\n30,66\n164,1\n24,5\nСуддя апеляційного суду Одеської області\nДружина - Желєзнова М.Г.;Син - Желєзнов В.В.\nЖелєзнов\nЖелєзнов Валентин Миколайович\nВалентин Миколайович Желєзнов\nВалентин Желєзнов\nЖелєзнов Валентин Миколайович\nВалентин\nЖелєзнов Валентин Миколайович\nЗагальний апеляційний суд\nСуддя\nОдеська область\nМиколайович\n242234\n26792\n295264\n242234\n326472\n4416\n160000\n2013\nFALSE\nЖелєзнов\nМиколайович\nДружина - Желєзнова М.Г.;Син - Желєзнов В.В.\nЖелєзнов Валентин Миколайович\nВалентин Миколайович Желєзнов\nВалентин Желєзнов\nЖелєзнов Валентин Миколайович\nВалентин\nСуддя апеляційного суду Одеської області\nСуддя\nОдеська область\nЗагальний апеляційний суд\nЖелєзнов Валентин Миколайович\n64,1\n30,66\n24,5\n164,1\n33,6\nСуддя\nОдеська область\nЗагальний апеляційний суд\nСуддя апеляційного суду Одеської області\nВалентин\nМиколайович\nДружина - Желєзнова М.Г.;Син - Желєзнов В.В.\nЖелєзнов\nЖелєзнов Валентин Миколайович\nЖелєзнов Валентин Миколайович\nВалентин Миколайович Желєзнов\nВалентин Желєзнов\nЖелєзнов Валентин Миколайович\n160000\nFALSE\n2013","intro":{"declaration_year":"2013","isnotdeclaration":"FALSE"}}],"declarationsLength":3,"analytics":[{"y":2015,"i":331095,"c":1,"k":39.9,"ka":1,"fi":325788,"ff":94.76,"ffa":2,"j":3},{"y":2014,"i":259541,"c":1,"fi":278906,"ff":64.1,"ffa":1},{"y":2013,"i":242234,"c":1,"la":3,"fi":326472,"ff":94.76,"ffa":2}]}