{"2010":"","2016":"","Department":"Господарський суд Закарпатської області","Region":"Закарпатська область","Position":"Заступник Голови Господарського суду Закарпатської області","Name":"Журавчак Лідія Степанівна","Link":"https://drive.google.com/open?id=0BygiyWAl79DMczYzZnlkRjM3LUk","Note":"У меня","AdditionalNote":"","field8":"","field9":"","field10":"","Кількість справ":"","Оскаржені":"","Кількість скарг":0,"Кількість дисциплінарних стягнень":"","Клейма":"","Фото":"http://picua.org/img/2016-09/22/n970ezfv103dsrzfogv7a749t.jpg","Як живе":"","key":"zhuravchak_lidiya_stepanivna","allDeclarations":[{"provider":"declarations.com.ua","document":{"income":{"5":{"value":"326662","value_unclear":false,"value_hidden":false,"family_comment":"","family":"","comment":""},"6":{"value":"252096","family_comment":"","value_unclear":false,"family_unclear":false,"family":"","comment":""},"7":{"source_name_unclear":false,"value":"","family_hidden":false,"family_comment":"","source_name":"","family":"","comment":""},"8":{"family_comment":"","value":"","family":"","comment":""},"9":{"family_comment":"","value":"267","family":"","comment":""},"10":{"family_comment":"","value":"","family":"","comment":""},"11":{"family_comment":"","value":"","family":"","comment":""},"12":{"family_comment":"","value":"","family":"","comment":""},"13":{"family_comment":"","value":"","family":"","comment":""},"14":{"family_comment":"","value":"","family":"","comment":""},"15":{"family_comment":"","value":"","family":"","comment":""},"16":{"family_comment":"","value":"","comment_unclear":false,"family":"","comment":""},"17":{"family_comment":"","family_unclear":false,"value":"","family":"","comment":""},"18":{"family_comment":"","value":"","family":"","comment":""},"19":{"value":"","family_hidden":false,"value_hidden":false,"family_comment":"","family":"","comment":""},"20":{"family_comment":"","value":"74299","comment_unclear":false,"family":"","comment":""}},"vehicle":{"35":[{"brand_info":"1781 куб. см.","sum_rent_comment":"","year":"1987","sum_rent_unclear":false,"brand_info_hidden":false,"brand_info_unclear":false,"year_unclear":false,"sum_rent":"","sum":"","brand":"Audi 80","sum_comment":"","sum_comment_unclear":false,"brand_hidden":false,"sum_unclear":false,"brand_unclear":false},{"brand_info":"2354 куб. см.","sum_rent_comment":"","brand":"Honda CR-V","sum_comment":"","sum_comment_unclear":false,"year":"2008","brand_info_unclear":false,"sum":"","sum_rent":""}],"44":[{"year_hidden":false,"brand_info":"124 куб. см.","sum_rent_comment":"","brand":"Yamaha YBR-125","sum_comment":"","year":"2012","brand_hidden":false,"sum":"","sum_rent":""}]},"id":"vulyk_67_133","declaration":{"additional_info_text":"","notfull_lostpages":"","date":"2015-03-30T00:00:00","notfull":"","additional_info":"","url":"http://static.declarations.com.ua/declarations/chosen_ones/mega_batch/zhuravchak_lidiia_stepanivna.pdf"},"liabilities":{"54":{"sum_foreign_comment":"","sum_foreign_hidden":false,"sum_comment":"","sum_comment_unclear":false,"sum_hidden":false,"sum":"9295","sum_unclear":false,"sum_foreign":""},"55":{"sum_foreign_comment":"","sum":"","sum_comment":"","sum_foreign":""},"56":{"sum_foreign_comment":"","sum_foreign_hidden":false,"sum_comment":"","sum_hidden":false,"sum":"","sum_unclear":false,"sum_foreign":""},"57":{"sum_foreign_comment":"","sum_foreign_hidden":false,"sum_comment":"","sum_comment_unclear":false,"sum_hidden":false,"sum_comment_hidden":false,"sum_unclear":false,"sum":"","sum_foreign":""},"58":{"sum_foreign_comment":"","sum_foreign_hidden":false,"sum_comment":"","sum_comment_unclear":false,"sum_hidden":false,"sum_comment_hidden":false,"sum_unclear":false,"sum":"","sum_foreign":""},"59":{"sum_foreign_comment":"","sum":"","sum_hidden":false,"sum_comment":"","sum_foreign":""},"60":{"sum_foreign_comment":"","sum":"9299","sum_comment":"","sum_foreign":""},"61":{"sum_foreign_comment":"","sum_foreign_hidden":false,"sum_comment":"","sum_hidden":false,"sum":"","sum_foreign":""},"62":{"sum_foreign_comment":"","sum":"","sum_hidden":false,"sum_comment":"","sum_foreign":""},"63":{"sum_foreign_comment":"","sum":"","sum_comment":"","sum_comment_unclear":false,"sum_hidden":false,"sum_unclear":false,"sum_foreign":""},"64":{"sum_foreign_comment":"","sum":"","sum_comment":"","sum_hidden":false,"sum_unclear":false,"sum_foreign":""}},"ft_src":"9295\n9299\nУжгород\nЗакарпатська область\nзаступник голови господарського суду закарпатської області\nЗакарпатська область\nГосподарський місцевий суд\nЛідія\nШвед Олег Сергійович\nДитина\nШвед Сергій Сергійович\nДитина\nСтепанівна\nЖуравчак Лідія Степанівна\nЖуравчак\nЖуравчак Лідія Степанівна\nЛідія Степанівна Журавчак\nЛідія Журавчак\nЖуравчак Лідія Степанівна\n1781 куб. см.\nAudi 80\n1987\n2008\nHonda CR-V\n2354 куб. см.\n2012\nYamaha YBR-125\n124 куб. см.\nУжгородський р-н,с. Оноківці\n700\nЗакарпатська область\nм. Ужгород\n640\nЗакарпатська область\nм. Ужгород\n279\nЗакарпатська область\nжила\nм. Ужгород\n37.9\nЗакарпатська область\n2014\n252096\n326662\n267\n74299\n1781 куб. см.\nAudi 80\n1987\nHonda CR-V\n2354 куб. см.\n2008\n124 куб. см.\n2012\nYamaha YBR-125\n700\nЗакарпатська область\nУжгородський р-н,с. Оноківці\n640\nм. Ужгород\nЗакарпатська область\n279\nм. Ужгород\nЗакарпатська область\n37.9\nжила\nЗакарпатська область\nм. Ужгород\nГосподарський місцевий суд\nзаступник голови господарського суду закарпатської області\nЗакарпатська область\nДитина\nШвед Олег Сергійович\nДитина\nШвед Сергій Сергійович\nЖуравчак Лідія Степанівна\nЛідія Степанівна Журавчак\nЛідія Журавчак\nЖуравчак Лідія Степанівна\nЖуравчак Лідія Степанівна\nЛідія\nЖуравчак\nСтепанівна\nУжгород\nЗакарпатська область\n9299\n9295\n252096\n74299\n326662\n267\n2014\n9295\n9299\nДитина\nШвед Олег Сергійович\nДитина\nШвед Сергій Сергійович\nСтепанівна\nЖуравчак\nЛідія\nЖуравчак Лідія Степанівна\nЛідія Степанівна Журавчак\nЛідія Журавчак\nЖуравчак Лідія Степанівна\nЗакарпатська область\nУжгород\nЗакарпатська область\nзаступник голови господарського суду закарпатської області\nГосподарський місцевий суд\nЖуравчак Лідія Степанівна\n2012\nYamaha YBR-125\n124 куб. см.\n1987\nAudi 80\n1781 куб. см.\n2008\n2354 куб. см.\nHonda CR-V\n74299\n326662\n267\n252096\nжила\nм. Ужгород\nЗакарпатська область\n37.9\nУжгородський р-н,с. Оноківці\nЗакарпатська область\n700\nм. Ужгород\nЗакарпатська область\n640\nм. Ужгород\nЗакарпатська область\n279\n2014","general":{"inn":"","name":"Лідія","patronymic_unclear":false,"last_name_hidden":false,"family":[{"inn":"","inn_hidden":true,"relations_unclear":false,"relations_hidden":false,"relations_other":"","relations":"Дитина","name_hidden":false,"inn_unclear":false,"family_name":"Швед Олег Сергійович","name_unclear":false},{"inn":"","inn_hidden":false,"relations_unclear":false,"relations_hidden":false,"relations_other":"","relations":"Дитина","name_hidden":false,"inn_unclear":false,"family_name":"Швед Сергій Сергійович","name_unclear":false}],"patronymic":"Степанівна","inn_hidden":true,"family_raw":"","inn_unclear":false,"post":{"post_unclear":false,"post":"заступник голови господарського суду закарпатської області","post_hidden":false,"region":"Закарпатська область","region_hidden":false,"office":"Господарський місцевий суд","office_hidden":false,"office_unclear":false},"last_name_unclear":false,"full_name":"Журавчак Лідія Степанівна","addresses":[{"place_city_type_hidden":false,"place_district_hidden":false,"place_city_type":"Місто","place_city_hidden":false,"place_address_unclear":false,"place_address":"","place":"Закарпатська область","place_district":"","place_unclear":false,"place_city":"Ужгород","place_city_unclear":false,"place_hidden":false,"place_address_hidden":true,"place_district_unclear":false}],"last_name":"Журавчак","full_name_suggest":{"output":"Журавчак Лідія Степанівна","input":["Журавчак Лідія Степанівна","Лідія Степанівна Журавчак","Лідія Журавчак"]},"name_unclear":false},"source":"VULYK","estate":{"23":[{"space_hidden":false,"costs":"","costs_comment":"","costs_hidden":false,"address_hidden":false,"region_hidden":false,"space_comment":"","space_unclear":false,"space":"700","address":"Ужгородський р-н,с. Оноківці","region":"Закарпатська область","address_unclear":false,"space_units_unclear":false,"costs_rent_hidden":false,"space_comment_unclear":false,"space_units":"м²","costs_rent":"","costs_rent_comment":""},{"space_unclear":false,"costs":"","costs_comment":"","address_hidden":true,"region_hidden":false,"space_comment":"","space":"640","address":"м. Ужгород","region":"Закарпатська область","costs_rent_comment":"","space_comment_unclear":false,"space_units":"м²","space_units_unclear":false,"costs_rent":""}],"24":[{"space_hidden":false,"costs":"","costs_comment":"","costs_hidden":false,"address_hidden":false,"region_hidden":false,"space_comment":"","space":"279","address":"м. Ужгород","region":"Закарпатська область","costs_rent_comment":"","space_comment_unclear":false,"space_units":"м²","costs_rent":""}],"25":[{"space_unclear":false,"costs":"","costs_comment":"","costs_hidden":false,"address_hidden":false,"region_hidden":false,"space_comment":"жила","space":"37.9","address":"м. Ужгород","region":"Закарпатська область","address_unclear":false,"space_units_unclear":false,"space_comment_unclear":false,"space_units":"м²","costs_rent":"","costs_rent_comment":""}]},"intro":{"declaration_year":"2014","isnotdeclaration":"","declaration_year_hidden":false}}},{"provider":"declarations.com.ua","document":{"income":{"5":{"family_comment":"","value":"291809","family":"218839","comment":""},"6":{"family_comment":"","value":"249976","family":"218756","comment":""},"7":{"family_comment":"","value":"0","source_name":"0","family":"0","comment":""},"8":{"family_comment":"","value":"0","family":"0","comment":""},"9":{"family_comment":"","value":"0","family":"83","comment":""},"10":{"family_comment":"","value":"0","family":"0","comment":""},"11":{"family_comment":"","value":"0","family":"0","comment":""},"12":{"family_comment":"","value":"0","family":"0","comment":""},"13":{"family_comment":"","value":"0","family":"0","comment":""},"14":{"family_comment":"","value":"0","family":"0","comment":""},"15":{"family_comment":"","value":"0","family":"0","comment":""},"16":{"family_comment":"","value":"0","family":"0","comment":""},"17":{"family_comment":"","value":"0","family":"0","comment":""},"18":{"family_comment":"","value":"0","family":"0","comment":""},"19":{"family_comment":"","value":"0","family":"0","comment":""},"20":{"family_comment":"","value":"41833","family":"0","comment":""},"21":[{"cur":"0","country":"0","uah_equal":"0","country_comment":""},{"cur":"0","country":"0","uah_equal":"0","country_comment":""},{"cur":"0","country":"0","uah_equal":"0","country_comment":""},{"cur":"0","country":"0","uah_equal":"0","country_comment":""},{"cur":"0","country":"0","uah_equal":"0","country_comment":""}],"22":[{"cur":"0","country":"0","uah_equal":"0","country_comment":""},{"cur":"0","country":"0","uah_equal":"0","country_comment":""},{"cur":"0","country":"0","uah_equal":"0","country_comment":""},{"cur":"0","country":"0","uah_equal":"0","country_comment":""},{"cur":"0","country":"0","uah_equal":"0","country_comment":""}]},"vehicle":{"40":[{"brand_info":"","sum_rent_comment":"","brand":"Audi,80","sum_comment":"","year":"1987","brand_hidden":false,"sum":"","sum_rent":""},{"brand_info":"","sum_rent_comment":"","brand":"Honda,CR-V","sum_comment":"","year":"2008","brand_hidden":false,"sum":"","sum_rent":""}],"44":[{"brand_info":"","sum_rent_comment":"","brand":"Yamaha,YBR-125","sum_comment":"","year":"2012","brand_hidden":false,"sum":"","sum_rent":""}]},"id":"2065","banks":{"45":[{"sum_foreign_comment":"","sum_units":"UAH","sum_comment":"","sum_foreign_units":"","sum":"","sum_foreign":""},{"sum_foreign_comment":"","sum_units":"USD","sum_comment":"","sum_foreign_units":"","sum":"","sum_foreign":""},{"sum_foreign_comment":"","sum_units":"EUR","sum_comment":"","sum_foreign_units":"","sum":"","sum_foreign":""}],"46":[{"sum_foreign_comment":"","sum_units":"UAH","sum_comment":"","sum_foreign_units":"","sum":"","sum_foreign":""},{"sum_foreign_comment":"","sum_units":"USD","sum_comment":"","sum_foreign_units":"","sum":"","sum_foreign":""},{"sum_foreign_comment":"","sum_units":"EUR","sum_comment":"","sum_foreign_units":"","sum":"","sum_foreign":""}],"47":[{"sum_foreign_comment":"","sum_units":"","sum_comment":"","sum_foreign_units":"","sum":"","sum_foreign":""}],"48":[{"sum_foreign_comment":"","sum_units":"","sum_comment":"","sum_foreign_units":"","sum":"","sum_foreign":""}],"49":[{"sum_foreign_comment":"","sum_units":"","sum_comment":"","sum_foreign_units":"","sum":"","sum_foreign":""}],"50":[{"sum_foreign_comment":"","sum_units":"","sum_comment":"","sum_foreign_units":"","sum":"","sum_foreign":""}],"51":[{"sum_foreign_comment":"","sum_units":"UAH","sum_comment":"","sum_foreign_units":"","sum":"","sum_foreign":""},{"sum_foreign_comment":"","sum_units":"USD","sum_comment":"","sum_foreign_units":"","sum":"","sum_foreign":""},{"sum_foreign_comment":"","sum_units":"EUR","sum_comment":"","sum_foreign_units":"","sum":"","sum_foreign":""}],"52":[{"sum_foreign_comment":"","sum_units":"","sum_comment":"","sum_foreign_units":"","sum":"","sum_foreign":""}],"53":[{"sum_foreign_comment":"","sum_units":"","sum_comment":"","sum_foreign_units":"","sum":"","sum_foreign":""}]},"declaration":{"needs_scancopy_check":false,"additional_info_text":"","notfull_lostpages":"","notfull":"FALSE","additional_info":"FALSE","url":"http://static.declarations.com.ua/declarations/sudy/hospodarski_mistsevi_sudy/zakarpatska_oblast/shuravchak.pdf"},"liabilities":{"54":{"sum_foreign_comment":"","sum":"8610","sum_comment":"","sum_foreign":""},"55":{"sum_foreign_comment":"","sum_units":"","sum_comment":"","sum_foreign_units":"","sum":"","sum_foreign":""},"56":{"sum_foreign_comment":"","sum":"","sum_comment":"","sum_foreign":""},"57":{"sum_foreign_comment":"","sum":"","sum_comment":"","sum_foreign":""},"58":{"sum_foreign_comment":"","sum":"","sum_comment":"","sum_foreign":""},"59":{"sum_foreign_comment":"","sum":"20000","sum_comment":"","sum_foreign":""},"60":{"sum_foreign_comment":"","sum":"8614","sum_comment":"","sum_foreign":""},"61":{"sum_foreign_comment":"","sum_units":"","sum_comment":"","sum_foreign_units":"","sum":"","sum_foreign":""},"62":{"sum_foreign_comment":"","sum":"22000","sum_comment":"","sum_foreign":""},"63":{"sum_foreign_comment":"","sum_units":"","sum_comment":"","sum":"","sum_foreign":""},"64":{"sum_foreign_comment":"","sum_units":"","sum_comment":"","sum":"","sum_foreign":""}},"estate":{"23":[{"costs_rent":"","location_raw":"Україна, територія Оноківської сільської ради","region":"","costs":"","costs_rent_comment":"","costs_comment":"","space_comment":"","space_units":"","space":"700","address":""},{"costs_rent":"","location_raw":"","region":"","costs":"","costs_rent_comment":"","costs_comment":"","space_comment":"","space_units":"","space":"","address":""},{"costs_rent":"","location_raw":"","region":"","costs":"","costs_rent_comment":"","costs_comment":"","space_comment":"","space_units":"","space":"","address":""}],"29":[{"costs_rent":"","location_raw":"Україна, м. Ужгород, приховано","region":"","costs_property":"","costs_rent_comment":"","space_comment":"","costs_property_comment":"","space_units":"","space":"640","address":""}],"30":[{"costs_rent":"","location_raw":"Україна, м. Ужгород, приховано","region":"","costs_property":"","costs_rent_comment":"","space_comment":"","costs_property_comment":"","space_units":"","space":"279","address":""}],"31":[{"costs_rent":"","location_raw":"Україна, м. Ужгород, приховано","region":"","costs_property":"","costs_rent_comment":"","space_comment":"","costs_property_comment":"","space_units":"","space":"37,9","address":""}]},"general":{"name_hidden":false,"name":"Лідія","patronymic_unclear":false,"last_name_hidden":false,"addresses_raw":"Закарпатська область м. Ужгород;приховано","post_raw":"Суддя господарського суду Закарпатської області","patronymic":"Степанівна","inn":"","family_raw":"Чоловік: Швед Сергій Борисович;26.01.1953 р.н.,;помер 29.09.2013;;Син: Швед Олег Сергійович;30.07.1978 р.н.;;Син: Швед Сергій Сергійович;6.02.1987 р.н.","last_name":"Журавчак","post":{"office":"Господарський місцевий суд","region":"Закарпатська область","post":"Суддя"},"addresses_raw_hidden":true,"last_name_unclear":false,"full_name":"Журавчак Лідія Степанівна","addresses":[{"place_district":"","place_city":"Ужгород","place_city_type":"","place_address_type":"","place_address":"","place":"Закарпатська"}],"patronymic_hidden":false,"full_name_suggest":{"output":"Журавчак Лідія Степанівна","input":["Журавчак Лідія Степанівна","Лідія Степанівна Журавчак","Лідія Журавчак"]},"name_unclear":false},"ft_src":"20000\n22000\n8610\n8614\nFALSE\nFALSE\n41833\n218839\n291809\n83\n218756\n249976\nYamaha,YBR-125\n2012\nAudi,80\n1987\nHonda,CR-V\n2008\nAudi,80\n1987\nHonda,CR-V\n2008\nYamaha,YBR-125\n2012\nУкраїна, територія Оноківської сільської ради\n700\nУкраїна, м. Ужгород, приховано\n279\nУкраїна, м. Ужгород, приховано\n640\nУкраїна, м. Ужгород, приховано\n37,9\nFALSE\nFALSE\nFALSE\n2013\n218756\n249976\n218839\n291809\n83\n41833\nAudi,80\n1987\nHonda,CR-V\n2008\nYamaha,YBR-125\n2012\nFALSE\nFALSE\nУкраїна, територія Оноківської сільської ради\n700\nУкраїна, м. Ужгород, приховано\n640\nУкраїна, м. Ужгород, приховано\n279\nУкраїна, м. Ужгород, приховано\n37,9\nСуддя господарського суду Закарпатської області\nЧоловік: Швед Сергій Борисович;26.01.1953 р.н.,;помер 29.09.2013;;Син: Швед Олег Сергійович;30.07.1978 р.н.;;Син: Швед Сергій Сергійович;6.02.1987 р.н.\nЗакарпатська\nУжгород\nЖуравчак\nЖуравчак Лідія Степанівна\nЛідія Степанівна Журавчак\nЛідія Журавчак\nЖуравчак Лідія Степанівна\nЛідія\nЖуравчак Лідія Степанівна\nГосподарський місцевий суд\nСуддя\nЗакарпатська область\nСтепанівна\nЗакарпатська область м. Ужгород;приховано\n20000\n8614\n22000\n8610\n249976\n218756\n41833\n291809\n218839\n83\n2013\nFALSE\n22000\n8610\n20000\n8614\nЖуравчак\nСтепанівна\nЧоловік: Швед Сергій Борисович;26.01.1953 р.н.,;помер 29.09.2013;;Син: Швед Олег Сергійович;30.07.1978 р.н.;;Син: Швед Сергій Сергійович;6.02.1987 р.н.\nЖуравчак Лідія Степанівна\nЛідія Степанівна Журавчак\nЛідія Журавчак\nЖуравчак Лідія Степанівна\nЛідія\nСуддя господарського суду Закарпатської області\nЗакарпатська\nУжгород\nСуддя\nЗакарпатська область\nГосподарський місцевий суд\nЖуравчак Лідія Степанівна\nЗакарпатська область м. Ужгород;приховано\nУкраїна, м. Ужгород, приховано\n37,9\nУкраїна, м. Ужгород, приховано\n279\nУкраїна, м. Ужгород, приховано\n640\nУкраїна, територія Оноківської сільської ради\n700\nУжгород\nЗакарпатська\nСуддя господарського суду Закарпатської області\nСуддя\nЗакарпатська область\nГосподарський місцевий суд\nЛідія\nЗакарпатська область м. Ужгород;приховано\nСтепанівна\nЧоловік: Швед Сергій Борисович;26.01.1953 р.н.,;помер 29.09.2013;;Син: Швед Олег Сергійович;30.07.1978 р.н.;;Син: Швед Сергій Сергійович;6.02.1987 р.н.\nЖуравчак\nЖуравчак Лідія Степанівна\nЖуравчак Лідія Степанівна\nЛідія Степанівна Журавчак\nЛідія Журавчак\nЖуравчак Лідія Степанівна\nFALSE\n2013","intro":{"declaration_year":"2013","isnotdeclaration":"FALSE"}}},{"provider":"public-api.nazk.gov.ua","document":{"step_0":{"declarationType":"1","declarationYear1":"2015"},"step_1":{"region":"[Конфіденційна інформація]","street":"[Конфіденційна інформація]","country":"1","cityPath":"[Конфіденційна інформація]","cityType":"[Конфіденційна інформація]","district":"[Конфіденційна інформація]","lastname":"Журавчак","postCode":"[Конфіденційна інформація]","postType":"","workPost":"заступник голови суду, суддя","firstname":"Лідія","workPlace":"господарський суд Закарпатської області","middlename":"Степанівна","streetType":"[Конфіденційна інформація]","changedName":false,"countryPath":"","eng_postCode":"","postCategory":"","actual_region":"1.2.21","actual_street":"[Конфіденційна інформація]","actual_country":"1","actual_cityPath":"[Конфіденційна інформація]","actual_cityType":"[Конфіденційна інформація]","actual_district":"1.2.21.1.1","actual_postCode":"[Конфіденційна інформація]","actual_streetType":"[Конфіденційна інформація]","previous_lastname":"","corruptionAffected":"Так","eng_actualPostCode":"[Конфіденційна інформація]","previous_firstname":"","previous_middlename":"","responsiblePosition":"Суддя суду загальної юрисдикції, суддя Конституційного Суду України","sameRegLivingAddress":"[Конфіденційна інформація]","postType_extendedstatus":"1","eng_sameRegLivingAddress":"[Конфіденційна інформація]","housePartNum_extendedstatus":"1","postCategory_extendedstatus":"1","actual_housePartNum_extendedstatus":"1","actual_apartmentsNum_extendedstatus":"1"},"step_2":{"1477035105932":{"lastname":"Швед","firstname":"Олег","middlename":"Сергійович","changedName":false,"citizenship":"1","eng_lastname":"","no_taxNumber":false,"eng_firstname":"","eng_middlename":"","isNotApplicable":"","subjectRelation":"син","previous_lastname":"","previous_firstname":"","previous_middlename":"","previous_eng_lastname":"","previous_eng_firstname":"","previous_eng_middlename":""},"1477035174413":{"lastname":"Швед","firstname":"Сергій","middlename":"Сергійович","changedName":false,"citizenship":"1","eng_lastname":"","no_taxNumber":false,"eng_firstname":"","eng_middlename":"","isNotApplicable":"","subjectRelation":"син","previous_lastname":"","previous_firstname":"","previous_middlename":"","previous_eng_lastname":"","previous_eng_firstname":"","previous_eng_middlename":""}},"step_3":{"1477035245463":{"city":"[Конфіденційна інформація]","person":"1","region":"[Конфіденційна інформація]","rights":{"1":{"citizen":"","ua_city":"","ua_street":"[Конфіденційна інформація]","ua_lastname":"","ua_postCode":"","eng_fullname":"","eng_lastname":"","eng_postCode":"","rightBelongs":"1","ua_firstname":"","ukr_fullname":"","ukr_lastname":"","eng_firstname":"","ownershipType":"Власність","ua_middlename":"","ua_streetType":"[Конфіденційна інформація]","ukr_firstname":"","eng_middlename":"","otherOwnership":"","ukr_middlename":"","rights_cityPath":"","ua_company_name":"","eng_company_name":"","ukr_company_name":"","percent-ownership":"100","ua_street_extendedstatus":"","ua_houseNum_extendedstatus":"","ua_postCode_extendedstatus":"","eng_postCode_extendedstatus":"","ua_middlename_extendedstatus":"","eng_middlename_extendedstatus":"","ukr_middlename_extendedstatus":"","ua_housePartNum_extendedstatus":"","ua_apartmentsNum_extendedstatus":""}},"country":"1","cityPath":"[Конфіденційна інформація]","costDate":"","district":"[Конфіденційна інформація]","postCode":"[Конфіденційна інформація]","totalArea":"700","ua_street":"[Конфіденційна інформація]","objectType":"Земельна ділянка","owningDate":"27.09.1994","ua_cityType":"Оноківці / Ужгородський Район / Закарпатська Область / Україна","ua_postCode":"89412","ua_streetType":"[Конфіденційна інформація]","costAssessment":"","otherObjectType":"","costDate_extendedstatus":"2","regNumber_extendedstatus":"2","ua_houseNum_extendedstatus":"1","costAssessment_extendedstatus":"2","ua_housePartNum_extendedstatus":"1","ua_apartmentsNum_extendedstatus":"1"},"1477035797939":{"city":"[Конфіденційна інформація]","person":"1","region":"[Конфіденційна інформація]","rights":{"1":{"citizen":"","ua_city":"","ua_street":"[Конфіденційна інформація]","ua_lastname":"","ua_postCode":"","eng_fullname":"","eng_lastname":"","eng_postCode":"","rightBelongs":"1","ua_firstname":"","ukr_fullname":"","ukr_lastname":"","eng_firstname":"","ownershipType":"Власність","ua_middlename":"","ua_streetType":"[Конфіденційна інформація]","ukr_firstname":"","eng_middlename":"","otherOwnership":"","ukr_middlename":"","rights_cityPath":"","ua_company_name":"","eng_company_name":"","ukr_company_name":"","percent-ownership":"100","ua_street_extendedstatus":"","ua_houseNum_extendedstatus":"","ua_postCode_extendedstatus":"","eng_postCode_extendedstatus":"","ua_middlename_extendedstatus":"","eng_middlename_extendedstatus":"","ukr_middlename_extendedstatus":"","ua_housePartNum_extendedstatus":"","ua_apartmentsNum_extendedstatus":""}},"country":"1","cityPath":"[Конфіденційна інформація]","costDate":"","district":"[Конфіденційна інформація]","postCode":"[Конфіденційна інформація]","totalArea":"640","ua_street":"[Конфіденційна інформація]","objectType":"Земельна ділянка","owningDate":"12.10.2000","ua_cityType":"Ужгород / Закарпатська Область / Україна","ua_postCode":"88017","ua_streetType":"[Конфіденційна інформація]","costAssessment":"","otherObjectType":"","costDate_extendedstatus":"2","regNumber_extendedstatus":"1","costAssessment_extendedstatus":"2","ua_housePartNum_extendedstatus":"1","ua_apartmentsNum_extendedstatus":"1"},"1477036050235":{"city":"[Конфіденційна інформація]","person":"1","region":"[Конфіденційна інформація]","rights":{"1":{"citizen":"","ua_city":"","ua_street":"[Конфіденційна інформація]","ua_lastname":"","ua_postCode":"","eng_fullname":"","eng_lastname":"","eng_postCode":"","rightBelongs":"1","ua_firstname":"","ukr_fullname":"","ukr_lastname":"","eng_firstname":"","ownershipType":"Власність","ua_middlename":"","ua_streetType":"[Конфіденційна інформація]","ukr_firstname":"","eng_middlename":"","otherOwnership":"","ukr_middlename":"","rights_cityPath":"","ua_company_name":"","eng_company_name":"","ukr_company_name":"","percent-ownership":"100","ua_street_extendedstatus":"","ua_houseNum_extendedstatus":"","ua_postCode_extendedstatus":"","eng_postCode_extendedstatus":"","ua_middlename_extendedstatus":"","eng_middlename_extendedstatus":"","ukr_middlename_extendedstatus":"","ua_housePartNum_extendedstatus":"","ua_apartmentsNum_extendedstatus":""}},"country":"1","cityPath":"[Конфіденційна інформація]","costDate":"165000","district":"[Конфіденційна інформація]","postCode":"[Конфіденційна інформація]","totalArea":"279","ua_street":"[Конфіденційна інформація]","objectType":"Житловий будинок","owningDate":"08.12.2000","ua_cityType":"Ужгород / Закарпатська Область / Україна","ua_postCode":"88000","ua_streetType":"[Конфіденційна інформація]","costAssessment":"165000","otherObjectType":"","regNumber_extendedstatus":"2","ua_housePartNum_extendedstatus":"1","ua_apartmentsNum_extendedstatus":"1"},"1477036441684":{"city":"[Конфіденційна інформація]","person":"1","region":"[Конфіденційна інформація]","rights":{"1":{"citizen":"","ua_city":"","ua_street":"[Конфіденційна інформація]","ua_lastname":"","ua_postCode":"","eng_fullname":"","eng_lastname":"","eng_postCode":"","rightBelongs":"1","ua_firstname":"","ukr_fullname":"","ukr_lastname":"","eng_firstname":"","ownershipType":"Власність","ua_middlename":"","ua_streetType":"[Конфіденційна інформація]","ukr_firstname":"","eng_middlename":"","otherOwnership":"","ukr_middlename":"","rights_cityPath":"","ua_company_name":"","eng_company_name":"","ukr_company_name":"","percent-ownership":"100","ua_street_extendedstatus":"","ua_houseNum_extendedstatus":"","ua_postCode_extendedstatus":"","eng_postCode_extendedstatus":"","ua_middlename_extendedstatus":"","eng_middlename_extendedstatus":"","ukr_middlename_extendedstatus":"","ua_housePartNum_extendedstatus":"","ua_apartmentsNum_extendedstatus":""}},"country":"1","cityPath":"[Конфіденційна інформація]","costDate":"","district":"[Конфіденційна інформація]","postCode":"[Конфіденційна інформація]","totalArea":"38","ua_street":"[Конфіденційна інформація]","objectType":"Квартира","owningDate":"28.07.1993","ua_cityType":"Ужгород / Закарпатська Область / Україна","ua_postCode":"88000","ua_streetType":"[Конфіденційна інформація]","costAssessment":"","otherObjectType":"","costDate_extendedstatus":"2","regNumber_extendedstatus":"2","costAssessment_extendedstatus":"2","ua_housePartNum_extendedstatus":"1"}},"step_4":[],"step_5":[],"step_6":{"1477036828352":{"brand":"Ауді","model":"80","person":"1","rights":{"1":{"citizen":"","ua_city":"","ua_street":"[Конфіденційна інформація]","ua_lastname":"","ua_postCode":"","eng_fullname":"","eng_lastname":"","eng_postCode":"","rightBelongs":"1","ua_firstname":"","ukr_fullname":"","ukr_lastname":"","eng_firstname":"","ownershipType":"Власність","ua_middlename":"","ua_streetType":"[Конфіденційна інформація]","ukr_firstname":"","eng_middlename":"","otherOwnership":"","ukr_middlename":"","rights_cityPath":"","ua_company_name":"","eng_company_name":"","ukr_company_name":"","percent-ownership":"","ua_street_extendedstatus":"","ua_houseNum_extendedstatus":"","ua_postCode_extendedstatus":"","eng_postCode_extendedstatus":"","ua_middlename_extendedstatus":"","eng_middlename_extendedstatus":"","ukr_middlename_extendedstatus":"","ua_housePartNum_extendedstatus":"","ua_apartmentsNum_extendedstatus":""}},"costDate":"","objectType":"Автомобіль легковий","owningDate":"28.09.1998","graduationYear":"1987","otherObjectType":"","costDate_extendedstatus":"2"},"1477036986668":{"brand":"HONDA","model":"CR-V 2.4I-VTEC","person":"1","rights":{"1":{"citizen":"","ua_city":"","ua_street":"[Конфіденційна інформація]","ua_lastname":"","ua_postCode":"","eng_fullname":"","eng_lastname":"","eng_postCode":"","rightBelongs":"1","ua_firstname":"","ukr_fullname":"","ukr_lastname":"","eng_firstname":"","ownershipType":"Власність","ua_middlename":"","ua_streetType":"[Конфіденційна інформація]","ukr_firstname":"","eng_middlename":"","otherOwnership":"","ukr_middlename":"","rights_cityPath":"","ua_company_name":"","eng_company_name":"","ukr_company_name":"","percent-ownership":"","ua_street_extendedstatus":"","ua_houseNum_extendedstatus":"","ua_postCode_extendedstatus":"","eng_postCode_extendedstatus":"","ua_middlename_extendedstatus":"","eng_middlename_extendedstatus":"","ukr_middlename_extendedstatus":"","ua_housePartNum_extendedstatus":"","ua_apartmentsNum_extendedstatus":""}},"costDate":"216155","objectType":"Автомобіль легковий","owningDate":"21.08.2008","graduationYear":"2008","otherObjectType":""},"1477037129025":{"brand":"Yamaha","model":"YBR-125","person":"1477035174413","rights":{"1477035174413":{"citizen":"","ua_city":"","ua_street":"[Конфіденційна інформація]","ua_lastname":"","ua_postCode":"","eng_fullname":"","eng_lastname":"","eng_postCode":"","rightBelongs":"1477035174413","ua_firstname":"","ukr_fullname":"","ukr_lastname":"","eng_firstname":"","ownershipType":"Власність","ua_middlename":"","ua_streetType":"[Конфіденційна інформація]","ukr_firstname":"","eng_middlename":"","otherOwnership":"","ukr_middlename":"","rights_cityPath":"","ua_company_name":"","eng_company_name":"","ukr_company_name":"","percent-ownership":"","ua_street_extendedstatus":"","ua_houseNum_extendedstatus":"","ua_postCode_extendedstatus":"","eng_postCode_extendedstatus":"","ua_middlename_extendedstatus":"","eng_middlename_extendedstatus":"","ukr_middlename_extendedstatus":"","ua_housePartNum_extendedstatus":"","ua_apartmentsNum_extendedstatus":""}},"costDate":"20500","objectType":"Мотоцикл (мопед)","owningDate":"30.03.2013","graduationYear":"2012","otherObjectType":"","costDate_extendedstatus":"0"}},"step_7":[],"step_8":[],"step_9":[],"step_10":[],"step_11":{"1477037277225":{"person":"1","rights":{"1":{"citizen":"","ua_city":"","ua_street":"[Конфіденційна інформація]","ua_lastname":"","ua_postCode":"","eng_fullname":"","eng_lastname":"","eng_postCode":"","rightBelongs":"1","ua_firstname":"","ukr_fullname":"","ukr_lastname":"","eng_firstname":"","ownershipType":"Власність","ua_middlename":"","ua_streetType":"[Конфіденційна інформація]","ukr_firstname":"","eng_middlename":"","otherOwnership":"","ukr_middlename":"","rights_cityPath":"","ua_company_name":"","eng_company_name":"","ukr_company_name":"","percent-ownership":"","ua_street_extendedstatus":"","ua_houseNum_extendedstatus":"","ua_postCode_extendedstatus":"","eng_postCode_extendedstatus":"","ua_middlename_extendedstatus":"","eng_middlename_extendedstatus":"","ukr_middlename_extendedstatus":"","ua_housePartNum_extendedstatus":"","ua_apartmentsNum_extendedstatus":""}},"objectType":"Заробітна плата отримана за основним місцем роботи","sizeIncome":"258007","incomeSource":"j","source_citizen":"Юридична особа, зареєстрована в Україні","otherObjectType":"","source_ua_lastname":"","source_eng_fullname":"","source_ua_firstname":"","source_ukr_fullname":"","source_ua_middlename":"","source_ua_company_name":"Господарський суд Закарпатської області","source_eng_company_name":"","source_ukr_company_name":"","source_ua_sameRegLivingAddress":""},"1477037390284":{"person":"1","rights":{"1":{"citizen":"","ua_city":"","ua_street":"[Конфіденційна інформація]","ua_lastname":"","ua_postCode":"","eng_fullname":"","eng_lastname":"","eng_postCode":"","rightBelongs":"1","ua_firstname":"","ukr_fullname":"","ukr_lastname":"","eng_firstname":"","ownershipType":"Власність","ua_middlename":"","ua_streetType":"[Конфіденційна інформація]","ukr_firstname":"","eng_middlename":"","otherOwnership":"","ukr_middlename":"","rights_cityPath":"","ua_company_name":"","eng_company_name":"","ukr_company_name":"","percent-ownership":"","ua_street_extendedstatus":"","ua_houseNum_extendedstatus":"","ua_postCode_extendedstatus":"","eng_postCode_extendedstatus":"","ua_middlename_extendedstatus":"","eng_middlename_extendedstatus":"","ukr_middlename_extendedstatus":"","ua_housePartNum_extendedstatus":"","ua_apartmentsNum_extendedstatus":""}},"objectType":"Пенсія","sizeIncome":"18575","incomeSource":"j","source_citizen":"Юридична особа, зареєстрована в Україні","otherObjectType":"","source_ua_lastname":"","source_eng_fullname":"","source_ua_firstname":"","source_ukr_fullname":"","source_ua_middlename":"","source_ua_company_name":"Ужгородське Об'єднане Управління ПФУ Закарпатської області","source_eng_company_name":"","source_ukr_company_name":"","source_ua_sameRegLivingAddress":""}},"step_12":[],"step_13":{"1477038144912":{"person":"1","currency":"UAH","guarantor":[],"dateOrigin":"21.06.2015","objectType":"Зобов'язання за договорами страхування","margin-emitent":"j","sizeObligation":"10035","emitent_citizen":"Юридична особа, зареєстрована в Україні","otherObjectType":"","guarantor_exist_":false,"guarantor_realty":[],"ownerThirdPerson":"","emitent_ua_lastname":"","emitent_eng_fullname":"","emitent_ua_firstname":"","emitent_ukr_fullname":"","emitent_ua_middlename":"","ownerThirdPersonThing":"","emitent_ua_company_name":"ПРАТ \"Метлайф\"","guarantor_realty_exist_":false,"emitent_eng_company_name":"","emitent_ukr_company_name":"","emitent_ua_sameRegLivingAddress":""},"1477038374947":{"person":"1477035174413","currency":"UAH","guarantor":[],"dateOrigin":"21.06.2015","objectType":"Зобов'язання за договорами страхування","margin-emitent":"j","sizeObligation":"10038","emitent_citizen":"Юридична особа, зареєстрована в Україні","otherObjectType":"","guarantor_exist_":false,"guarantor_realty":[],"ownerThirdPerson":"","emitent_ua_lastname":"","emitent_eng_fullname":"","emitent_ua_firstname":"","emitent_ukr_fullname":"","emitent_ua_middlename":"","ownerThirdPersonThing":"","emitent_ua_company_name":"ПРАТ \"Метлайф\"","guarantor_realty_exist_":false,"emitent_eng_company_name":"","emitent_ukr_company_name":"","emitent_ua_sameRegLivingAddress":""}},"step_14":[],"step_15":[],"step_16":[],"id":"70f0f330-492d-451f-8e18-983e9c8df5ad"}}],"declarations":[{"income":{"5":{"value":"326662","value_unclear":false,"value_hidden":false,"family_comment":"","family":"","comment":""},"6":{"value":"252096","family_comment":"","value_unclear":false,"family_unclear":false,"family":"","comment":""},"7":{"source_name_unclear":false,"value":"","family_hidden":false,"family_comment":"","source_name":"","family":"","comment":""},"8":{"family_comment":"","value":"","family":"","comment":""},"9":{"family_comment":"","value":"267","family":"","comment":""},"10":{"family_comment":"","value":"","family":"","comment":""},"11":{"family_comment":"","value":"","family":"","comment":""},"12":{"family_comment":"","value":"","family":"","comment":""},"13":{"family_comment":"","value":"","family":"","comment":""},"14":{"family_comment":"","value":"","family":"","comment":""},"15":{"family_comment":"","value":"","family":"","comment":""},"16":{"family_comment":"","value":"","comment_unclear":false,"family":"","comment":""},"17":{"family_comment":"","family_unclear":false,"value":"","family":"","comment":""},"18":{"family_comment":"","value":"","family":"","comment":""},"19":{"value":"","family_hidden":false,"value_hidden":false,"family_comment":"","family":"","comment":""},"20":{"family_comment":"","value":"74299","comment_unclear":false,"family":"","comment":""}},"vehicle":{"35":[{"brand_info":"1781 куб. см.","sum_rent_comment":"","year":"1987","sum_rent_unclear":false,"brand_info_hidden":false,"brand_info_unclear":false,"year_unclear":false,"sum_rent":"","sum":"","brand":"Audi 80","sum_comment":"","sum_comment_unclear":false,"brand_hidden":false,"sum_unclear":false,"brand_unclear":false},{"brand_info":"2354 куб. см.","sum_rent_comment":"","brand":"Honda CR-V","sum_comment":"","sum_comment_unclear":false,"year":"2008","brand_info_unclear":false,"sum":"","sum_rent":""}],"44":[{"year_hidden":false,"brand_info":"124 куб. см.","sum_rent_comment":"","brand":"Yamaha YBR-125","sum_comment":"","year":"2012","brand_hidden":false,"sum":"","sum_rent":""}]},"id":"vulyk_67_133","declaration":{"additional_info_text":"","notfull_lostpages":"","date":"2015-03-30T00:00:00","notfull":"","additional_info":"","url":"http://static.declarations.com.ua/declarations/chosen_ones/mega_batch/zhuravchak_lidiia_stepanivna.pdf"},"liabilities":{"54":{"sum_foreign_comment":"","sum_foreign_hidden":false,"sum_comment":"","sum_comment_unclear":false,"sum_hidden":false,"sum":"9295","sum_unclear":false,"sum_foreign":""},"55":{"sum_foreign_comment":"","sum":"","sum_comment":"","sum_foreign":""},"56":{"sum_foreign_comment":"","sum_foreign_hidden":false,"sum_comment":"","sum_hidden":false,"sum":"","sum_unclear":false,"sum_foreign":""},"57":{"sum_foreign_comment":"","sum_foreign_hidden":false,"sum_comment":"","sum_comment_unclear":false,"sum_hidden":false,"sum_comment_hidden":false,"sum_unclear":false,"sum":"","sum_foreign":""},"58":{"sum_foreign_comment":"","sum_foreign_hidden":false,"sum_comment":"","sum_comment_unclear":false,"sum_hidden":false,"sum_comment_hidden":false,"sum_unclear":false,"sum":"","sum_foreign":""},"59":{"sum_foreign_comment":"","sum":"","sum_hidden":false,"sum_comment":"","sum_foreign":""},"60":{"sum_foreign_comment":"","sum":"9299","sum_comment":"","sum_foreign":""},"61":{"sum_foreign_comment":"","sum_foreign_hidden":false,"sum_comment":"","sum_hidden":false,"sum":"","sum_foreign":""},"62":{"sum_foreign_comment":"","sum":"","sum_hidden":false,"sum_comment":"","sum_foreign":""},"63":{"sum_foreign_comment":"","sum":"","sum_comment":"","sum_comment_unclear":false,"sum_hidden":false,"sum_unclear":false,"sum_foreign":""},"64":{"sum_foreign_comment":"","sum":"","sum_comment":"","sum_hidden":false,"sum_unclear":false,"sum_foreign":""}},"ft_src":"9295\n9299\nУжгород\nЗакарпатська область\nзаступник голови господарського суду закарпатської області\nЗакарпатська область\nГосподарський місцевий суд\nЛідія\nШвед Олег Сергійович\nДитина\nШвед Сергій Сергійович\nДитина\nСтепанівна\nЖуравчак Лідія Степанівна\nЖуравчак\nЖуравчак Лідія Степанівна\nЛідія Степанівна Журавчак\nЛідія Журавчак\nЖуравчак Лідія Степанівна\n1781 куб. см.\nAudi 80\n1987\n2008\nHonda CR-V\n2354 куб. см.\n2012\nYamaha YBR-125\n124 куб. см.\nУжгородський р-н,с. Оноківці\n700\nЗакарпатська область\nм. Ужгород\n640\nЗакарпатська область\nм. Ужгород\n279\nЗакарпатська область\nжила\nм. Ужгород\n37.9\nЗакарпатська область\n2014\n252096\n326662\n267\n74299\n1781 куб. см.\nAudi 80\n1987\nHonda CR-V\n2354 куб. см.\n2008\n124 куб. см.\n2012\nYamaha YBR-125\n700\nЗакарпатська область\nУжгородський р-н,с. Оноківці\n640\nм. Ужгород\nЗакарпатська область\n279\nм. Ужгород\nЗакарпатська область\n37.9\nжила\nЗакарпатська область\nм. Ужгород\nГосподарський місцевий суд\nзаступник голови господарського суду закарпатської області\nЗакарпатська область\nДитина\nШвед Олег Сергійович\nДитина\nШвед Сергій Сергійович\nЖуравчак Лідія Степанівна\nЛідія Степанівна Журавчак\nЛідія Журавчак\nЖуравчак Лідія Степанівна\nЖуравчак Лідія Степанівна\nЛідія\nЖуравчак\nСтепанівна\nУжгород\nЗакарпатська область\n9299\n9295\n252096\n74299\n326662\n267\n2014\n9295\n9299\nДитина\nШвед Олег Сергійович\nДитина\nШвед Сергій Сергійович\nСтепанівна\nЖуравчак\nЛідія\nЖуравчак Лідія Степанівна\nЛідія Степанівна Журавчак\nЛідія Журавчак\nЖуравчак Лідія Степанівна\nЗакарпатська область\nУжгород\nЗакарпатська область\nзаступник голови господарського суду закарпатської області\nГосподарський місцевий суд\nЖуравчак Лідія Степанівна\n2012\nYamaha YBR-125\n124 куб. см.\n1987\nAudi 80\n1781 куб. см.\n2008\n2354 куб. см.\nHonda CR-V\n74299\n326662\n267\n252096\nжила\nм. Ужгород\nЗакарпатська область\n37.9\nУжгородський р-н,с. Оноківці\nЗакарпатська область\n700\nм. Ужгород\nЗакарпатська область\n640\nм. Ужгород\nЗакарпатська область\n279\n2014","general":{"inn":"","name":"Лідія","patronymic_unclear":false,"last_name_hidden":false,"family":[{"inn":"","inn_hidden":true,"relations_unclear":false,"relations_hidden":false,"relations_other":"","relations":"Дитина","name_hidden":false,"inn_unclear":false,"family_name":"Швед Олег Сергійович","name_unclear":false},{"inn":"","inn_hidden":false,"relations_unclear":false,"relations_hidden":false,"relations_other":"","relations":"Дитина","name_hidden":false,"inn_unclear":false,"family_name":"Швед Сергій Сергійович","name_unclear":false}],"patronymic":"Степанівна","inn_hidden":true,"family_raw":"","inn_unclear":false,"post":{"post_unclear":false,"post":"заступник голови господарського суду закарпатської області","post_hidden":false,"region":"Закарпатська область","region_hidden":false,"office":"Господарський місцевий суд","office_hidden":false,"office_unclear":false},"last_name_unclear":false,"full_name":"Журавчак Лідія Степанівна","addresses":[{"place_city_type_hidden":false,"place_district_hidden":false,"place_city_type":"Місто","place_city_hidden":false,"place_address_unclear":false,"place_address":"","place":"Закарпатська область","place_district":"","place_unclear":false,"place_city":"Ужгород","place_city_unclear":false,"place_hidden":false,"place_address_hidden":true,"place_district_unclear":false}],"last_name":"Журавчак","full_name_suggest":{"output":"Журавчак Лідія Степанівна","input":["Журавчак Лідія Степанівна","Лідія Степанівна Журавчак","Лідія Журавчак"]},"name_unclear":false},"source":"VULYK","estate":{"23":[{"space_hidden":false,"costs":"","costs_comment":"","costs_hidden":false,"address_hidden":false,"region_hidden":false,"space_comment":"","space_unclear":false,"space":"700","address":"Ужгородський р-н,с. Оноківці","region":"Закарпатська область","address_unclear":false,"space_units_unclear":false,"costs_rent_hidden":false,"space_comment_unclear":false,"space_units":"м²","costs_rent":"","costs_rent_comment":""},{"space_unclear":false,"costs":"","costs_comment":"","address_hidden":true,"region_hidden":false,"space_comment":"","space":"640","address":"м. Ужгород","region":"Закарпатська область","costs_rent_comment":"","space_comment_unclear":false,"space_units":"м²","space_units_unclear":false,"costs_rent":""}],"24":[{"space_hidden":false,"costs":"","costs_comment":"","costs_hidden":false,"address_hidden":false,"region_hidden":false,"space_comment":"","space":"279","address":"м. Ужгород","region":"Закарпатська область","costs_rent_comment":"","space_comment_unclear":false,"space_units":"м²","costs_rent":""}],"25":[{"space_unclear":false,"costs":"","costs_comment":"","costs_hidden":false,"address_hidden":false,"region_hidden":false,"space_comment":"жила","space":"37.9","address":"м. Ужгород","region":"Закарпатська область","address_unclear":false,"space_units_unclear":false,"space_comment_unclear":false,"space_units":"м²","costs_rent":"","costs_rent_comment":""}]},"intro":{"declaration_year":"2014","isnotdeclaration":"","declaration_year_hidden":false}},{"income":{"5":{"family_comment":"","value":"291809","family":"218839","comment":""},"6":{"family_comment":"","value":"249976","family":"218756","comment":""},"7":{"family_comment":"","value":"0","source_name":"0","family":"0","comment":""},"8":{"family_comment":"","value":"0","family":"0","comment":""},"9":{"family_comment":"","value":"0","family":"83","comment":""},"10":{"family_comment":"","value":"0","family":"0","comment":""},"11":{"family_comment":"","value":"0","family":"0","comment":""},"12":{"family_comment":"","value":"0","family":"0","comment":""},"13":{"family_comment":"","value":"0","family":"0","comment":""},"14":{"family_comment":"","value":"0","family":"0","comment":""},"15":{"family_comment":"","value":"0","family":"0","comment":""},"16":{"family_comment":"","value":"0","family":"0","comment":""},"17":{"family_comment":"","value":"0","family":"0","comment":""},"18":{"family_comment":"","value":"0","family":"0","comment":""},"19":{"family_comment":"","value":"0","family":"0","comment":""},"20":{"family_comment":"","value":"41833","family":"0","comment":""},"21":[{"cur":"0","country":"0","uah_equal":"0","country_comment":""},{"cur":"0","country":"0","uah_equal":"0","country_comment":""},{"cur":"0","country":"0","uah_equal":"0","country_comment":""},{"cur":"0","country":"0","uah_equal":"0","country_comment":""},{"cur":"0","country":"0","uah_equal":"0","country_comment":""}],"22":[{"cur":"0","country":"0","uah_equal":"0","country_comment":""},{"cur":"0","country":"0","uah_equal":"0","country_comment":""},{"cur":"0","country":"0","uah_equal":"0","country_comment":""},{"cur":"0","country":"0","uah_equal":"0","country_comment":""},{"cur":"0","country":"0","uah_equal":"0","country_comment":""}]},"vehicle":{"40":[{"brand_info":"","sum_rent_comment":"","brand":"Audi,80","sum_comment":"","year":"1987","brand_hidden":false,"sum":"","sum_rent":""},{"brand_info":"","sum_rent_comment":"","brand":"Honda,CR-V","sum_comment":"","year":"2008","brand_hidden":false,"sum":"","sum_rent":""}],"44":[{"brand_info":"","sum_rent_comment":"","brand":"Yamaha,YBR-125","sum_comment":"","year":"2012","brand_hidden":false,"sum":"","sum_rent":""}]},"id":"2065","banks":{"45":[{"sum_foreign_comment":"","sum_units":"UAH","sum_comment":"","sum_foreign_units":"","sum":"","sum_foreign":""},{"sum_foreign_comment":"","sum_units":"USD","sum_comment":"","sum_foreign_units":"","sum":"","sum_foreign":""},{"sum_foreign_comment":"","sum_units":"EUR","sum_comment":"","sum_foreign_units":"","sum":"","sum_foreign":""}],"46":[{"sum_foreign_comment":"","sum_units":"UAH","sum_comment":"","sum_foreign_units":"","sum":"","sum_foreign":""},{"sum_foreign_comment":"","sum_units":"USD","sum_comment":"","sum_foreign_units":"","sum":"","sum_foreign":""},{"sum_foreign_comment":"","sum_units":"EUR","sum_comment":"","sum_foreign_units":"","sum":"","sum_foreign":""}],"47":[{"sum_foreign_comment":"","sum_units":"","sum_comment":"","sum_foreign_units":"","sum":"","sum_foreign":""}],"48":[{"sum_foreign_comment":"","sum_units":"","sum_comment":"","sum_foreign_units":"","sum":"","sum_foreign":""}],"49":[{"sum_foreign_comment":"","sum_units":"","sum_comment":"","sum_foreign_units":"","sum":"","sum_foreign":""}],"50":[{"sum_foreign_comment":"","sum_units":"","sum_comment":"","sum_foreign_units":"","sum":"","sum_foreign":""}],"51":[{"sum_foreign_comment":"","sum_units":"UAH","sum_comment":"","sum_foreign_units":"","sum":"","sum_foreign":""},{"sum_foreign_comment":"","sum_units":"USD","sum_comment":"","sum_foreign_units":"","sum":"","sum_foreign":""},{"sum_foreign_comment":"","sum_units":"EUR","sum_comment":"","sum_foreign_units":"","sum":"","sum_foreign":""}],"52":[{"sum_foreign_comment":"","sum_units":"","sum_comment":"","sum_foreign_units":"","sum":"","sum_foreign":""}],"53":[{"sum_foreign_comment":"","sum_units":"","sum_comment":"","sum_foreign_units":"","sum":"","sum_foreign":""}]},"declaration":{"needs_scancopy_check":false,"additional_info_text":"","notfull_lostpages":"","notfull":"FALSE","additional_info":"FALSE","url":"http://static.declarations.com.ua/declarations/sudy/hospodarski_mistsevi_sudy/zakarpatska_oblast/shuravchak.pdf"},"liabilities":{"54":{"sum_foreign_comment":"","sum":"8610","sum_comment":"","sum_foreign":""},"55":{"sum_foreign_comment":"","sum_units":"","sum_comment":"","sum_foreign_units":"","sum":"","sum_foreign":""},"56":{"sum_foreign_comment":"","sum":"","sum_comment":"","sum_foreign":""},"57":{"sum_foreign_comment":"","sum":"","sum_comment":"","sum_foreign":""},"58":{"sum_foreign_comment":"","sum":"","sum_comment":"","sum_foreign":""},"59":{"sum_foreign_comment":"","sum":"20000","sum_comment":"","sum_foreign":""},"60":{"sum_foreign_comment":"","sum":"8614","sum_comment":"","sum_foreign":""},"61":{"sum_foreign_comment":"","sum_units":"","sum_comment":"","sum_foreign_units":"","sum":"","sum_foreign":""},"62":{"sum_foreign_comment":"","sum":"22000","sum_comment":"","sum_foreign":""},"63":{"sum_foreign_comment":"","sum_units":"","sum_comment":"","sum":"","sum_foreign":""},"64":{"sum_foreign_comment":"","sum_units":"","sum_comment":"","sum":"","sum_foreign":""}},"estate":{"23":[{"costs_rent":"","location_raw":"Україна, територія Оноківської сільської ради","region":"","costs":"","costs_rent_comment":"","costs_comment":"","space_comment":"","space_units":"","space":"700","address":""},{"costs_rent":"","location_raw":"","region":"","costs":"","costs_rent_comment":"","costs_comment":"","space_comment":"","space_units":"","space":"","address":""},{"costs_rent":"","location_raw":"","region":"","costs":"","costs_rent_comment":"","costs_comment":"","space_comment":"","space_units":"","space":"","address":""}],"29":[{"costs_rent":"","location_raw":"Україна, м. Ужгород, приховано","region":"","costs_property":"","costs_rent_comment":"","space_comment":"","costs_property_comment":"","space_units":"","space":"640","address":""}],"30":[{"costs_rent":"","location_raw":"Україна, м. Ужгород, приховано","region":"","costs_property":"","costs_rent_comment":"","space_comment":"","costs_property_comment":"","space_units":"","space":"279","address":""}],"31":[{"costs_rent":"","location_raw":"Україна, м. Ужгород, приховано","region":"","costs_property":"","costs_rent_comment":"","space_comment":"","costs_property_comment":"","space_units":"","space":"37,9","address":""}]},"general":{"name_hidden":false,"name":"Лідія","patronymic_unclear":false,"last_name_hidden":false,"addresses_raw":"Закарпатська область м. Ужгород;приховано","post_raw":"Суддя господарського суду Закарпатської області","patronymic":"Степанівна","inn":"","family_raw":"Чоловік: Швед Сергій Борисович;26.01.1953 р.н.,;помер 29.09.2013;;Син: Швед Олег Сергійович;30.07.1978 р.н.;;Син: Швед Сергій Сергійович;6.02.1987 р.н.","last_name":"Журавчак","post":{"office":"Господарський місцевий суд","region":"Закарпатська область","post":"Суддя"},"addresses_raw_hidden":true,"last_name_unclear":false,"full_name":"Журавчак Лідія Степанівна","addresses":[{"place_district":"","place_city":"Ужгород","place_city_type":"","place_address_type":"","place_address":"","place":"Закарпатська"}],"patronymic_hidden":false,"full_name_suggest":{"output":"Журавчак Лідія Степанівна","input":["Журавчак Лідія Степанівна","Лідія Степанівна Журавчак","Лідія Журавчак"]},"name_unclear":false},"ft_src":"20000\n22000\n8610\n8614\nFALSE\nFALSE\n41833\n218839\n291809\n83\n218756\n249976\nYamaha,YBR-125\n2012\nAudi,80\n1987\nHonda,CR-V\n2008\nAudi,80\n1987\nHonda,CR-V\n2008\nYamaha,YBR-125\n2012\nУкраїна, територія Оноківської сільської ради\n700\nУкраїна, м. Ужгород, приховано\n279\nУкраїна, м. Ужгород, приховано\n640\nУкраїна, м. Ужгород, приховано\n37,9\nFALSE\nFALSE\nFALSE\n2013\n218756\n249976\n218839\n291809\n83\n41833\nAudi,80\n1987\nHonda,CR-V\n2008\nYamaha,YBR-125\n2012\nFALSE\nFALSE\nУкраїна, територія Оноківської сільської ради\n700\nУкраїна, м. Ужгород, приховано\n640\nУкраїна, м. Ужгород, приховано\n279\nУкраїна, м. Ужгород, приховано\n37,9\nСуддя господарського суду Закарпатської області\nЧоловік: Швед Сергій Борисович;26.01.1953 р.н.,;помер 29.09.2013;;Син: Швед Олег Сергійович;30.07.1978 р.н.;;Син: Швед Сергій Сергійович;6.02.1987 р.н.\nЗакарпатська\nУжгород\nЖуравчак\nЖуравчак Лідія Степанівна\nЛідія Степанівна Журавчак\nЛідія Журавчак\nЖуравчак Лідія Степанівна\nЛідія\nЖуравчак Лідія Степанівна\nГосподарський місцевий суд\nСуддя\nЗакарпатська область\nСтепанівна\nЗакарпатська область м. Ужгород;приховано\n20000\n8614\n22000\n8610\n249976\n218756\n41833\n291809\n218839\n83\n2013\nFALSE\n22000\n8610\n20000\n8614\nЖуравчак\nСтепанівна\nЧоловік: Швед Сергій Борисович;26.01.1953 р.н.,;помер 29.09.2013;;Син: Швед Олег Сергійович;30.07.1978 р.н.;;Син: Швед Сергій Сергійович;6.02.1987 р.н.\nЖуравчак Лідія Степанівна\nЛідія Степанівна Журавчак\nЛідія Журавчак\nЖуравчак Лідія Степанівна\nЛідія\nСуддя господарського суду Закарпатської області\nЗакарпатська\nУжгород\nСуддя\nЗакарпатська область\nГосподарський місцевий суд\nЖуравчак Лідія Степанівна\nЗакарпатська область м. Ужгород;приховано\nУкраїна, м. Ужгород, приховано\n37,9\nУкраїна, м. Ужгород, приховано\n279\nУкраїна, м. Ужгород, приховано\n640\nУкраїна, територія Оноківської сільської ради\n700\nУжгород\nЗакарпатська\nСуддя господарського суду Закарпатської області\nСуддя\nЗакарпатська область\nГосподарський місцевий суд\nЛідія\nЗакарпатська область м. Ужгород;приховано\nСтепанівна\nЧоловік: Швед Сергій Борисович;26.01.1953 р.н.,;помер 29.09.2013;;Син: Швед Олег Сергійович;30.07.1978 р.н.;;Син: Швед Сергій Сергійович;6.02.1987 р.н.\nЖуравчак\nЖуравчак Лідія Степанівна\nЖуравчак Лідія Степанівна\nЛідія Степанівна Журавчак\nЛідія Журавчак\nЖуравчак Лідія Степанівна\nFALSE\n2013","intro":{"declaration_year":"2013","isnotdeclaration":"FALSE"}}],"declarationsLength":2,"analytics":[{"y":2014,"i":326662,"c":2,"k":37.9,"ka":1,"h":279,"ha":1,"l":1340,"la":2},{"y":2013,"i":291809,"l":700,"la":3,"fi":218839,"ff":37.9,"ffa":1,"fh":279,"fha":1,"fl":640,"fla":1},{"y":2015,"i":276582,"c":2,"k":38,"ka":1,"h":279,"ha":1,"l":1340,"la":2}]}