{"2010":1,"2016":1,"Department":"Катеринопільский районний суд Черкаської області","Region":"Черкаська область","Position":"Голова Катеринопільского районного суду Черкаської області","Name":"Зінченко Микола Григорович","Link":"http://court.gov.ua/lustration/4548459490200f37ad0c89378ab0651a.pdf","Note":"","AdditionalNote":"","field8":"","field9":1,"field10":"","Кількість справ":"","Оскаржені":"","Кількість скарг":2,"Кількість дисциплінарних стягнень":"","Клейма":3,"Фото":"","Як живе":"","key":"zinchenko_mikola_grigorovich","allDeclarations":[{"provider":"declarations.com.ua","document":{"income":{"5":{"family_comment":"","family_unclear":false,"value":"254829","family":"53822","comment":""},"6":{"value":"254829","family_comment":"","value_unclear":false,"family_unclear":false,"family":"53822","comment":""},"7":{"source_name_unclear":false,"value":"","family_comment":"","source_name":"","family":"","comment":"","source_name_hidden":false},"8":{"family_comment":"","value":"","family":"","comment":""},"9":{"family_comment":"","family_unclear":false,"value":"","family":"","comment":""},"10":{"family_comment":"","value":"","family":"","comment":""},"11":{"family_comment":"","value":"","family":"","comment":""},"12":{"family_comment":"","value":"","family":"","comment":""},"13":{"family_comment":"","value":"","family":"","comment":""},"14":{"family_comment":"","value":"","family":"","comment":""},"15":{"family_comment":"","value":"","family":"","comment":""},"16":{"family_comment":"","family_unclear":false,"value":"","family":"","comment":""},"17":{"family_comment":"","family_unclear":false,"value":"","family":"","comment":""},"18":{"family_comment":"","value":"","family":"","comment":""},"19":{"family_comment":"","value":"","family":"","comment":""},"20":{"family_comment":"","value":"","comment_unclear":false,"family":"","comment":""}},"vehicle":{"35":[{"brand_info":"1800 куб. см.","sum":"","brand":"Chevrolet Lacetti","sum_comment":"","brand_unclear":false,"year":"2007","brand_hidden":false,"brand_info_hidden":false,"brand_info_unclear":false,"sum_rent_comment":"","sum_rent":""}]},"id":"vulyk_95_39","declaration":{"additional_info_text":"","notfull_lostpages":"","date":"2016-03-30T00:00:00","notfull":"","additional_info":"","url":"http://static.declarations.com.ua/declarations/chosen_ones/judges_batch/40_zinchenko_mykola_hryhorovych_2015.pdf"},"liabilities":{"54":{"sum_foreign_comment":"","sum":"","sum_comment":"","sum_hidden":false,"sum_comment_hidden":false,"sum_unclear":false,"sum_foreign":""},"55":{"sum_foreign_comment":"","sum":"","sum_comment":"","sum_foreign":""},"56":{"sum_foreign_comment":"","sum":"","sum_comment":"","sum_foreign":""},"57":{"sum_foreign_comment":"","sum":"","sum_comment":"","sum_hidden":false,"sum_comment_hidden":false,"sum_unclear":false,"sum_foreign":""},"58":{"sum_foreign_comment":"","sum":"","sum_comment":"","sum_hidden":false,"sum_comment_hidden":false,"sum_unclear":false,"sum_foreign":""},"59":{"sum_foreign_comment":"","sum":"","sum_comment":"","sum_foreign":""},"60":{"sum_foreign_comment":"","sum":"","sum_comment":"","sum_hidden":false,"sum_comment_hidden":false,"sum_foreign":""},"61":{"sum_foreign_comment":"","sum":"","sum_comment":"","sum_foreign":""},"62":{"sum_foreign_comment":"","sum":"","sum_comment":"","sum_unclear":false,"sum_foreign":""},"63":{"sum_foreign_comment":"","sum":"","sum_comment":"","sum_unclear":false,"sum_foreign":""},"64":{"sum_foreign_comment":"","sum":"","sum_comment":"","sum_foreign":""}},"ft_src":"Зінченко Микола Григорович\nголова катеринопільского районного суду черкаської області\nЧеркаська область\nЗагальний місцевий суд\nМикола\nДитина\nЗінченко Микола Григорович\nМикола Григорович Зінченко\nМикола Зінченко\nЗінченко Микола Григорович\nЗінченко\nГригорович\nChevrolet Lacetti\n1800 куб. см.\n2007\n.1\n60.1\n2015\n53822\n254829\n53822\n254829\nChevrolet Lacetti\n1800 куб. см.\n2007\n.1\n60.1\nГригорович\nДитина\nЗінченко Микола Григорович\nМикола Григорович Зінченко\nМикола Зінченко\nЗінченко Микола Григорович\nМикола\nЗінченко Микола Григорович\nЗінченко\nЗагальний місцевий суд\nголова катеринопільского районного суду черкаської області\nЧеркаська область\n254829\n53822\n254829\n53822\n2015\nДитина\nГригорович\nЗінченко\nЧеркаська область\nЗагальний місцевий суд\nголова катеринопільского районного суду черкаської області\nЗінченко Микола Григорович\nЗінченко Микола Григорович\nМикола Григорович Зінченко\nМикола Зінченко\nЗінченко Микола Григорович\nМикола\nChevrolet Lacetti\n1800 куб. см.\n2007\n53822\n254829\n254829\n53822\n60.1\n.1\n2015","general":{"inn":"","inn_hidden":true,"last_name":"Зінченко","post":{"post":"голова катеринопільского районного суду черкаської області","region":"Черкаська область","candidate":"","office_hidden":false,"office":"Загальний місцевий суд","office_unclear":false},"name":"Микола","full_name":"Зінченко Микола Григорович","family_raw":"","addresses":[{"place_address":"","place_district_hidden":true,"place_city_type":"","place_city_hidden":true,"place_address_unclear":false,"place_city_type_hidden":true,"place_city":"","place":"","place_district":"","place_address_hidden":true,"place_hidden":false,"place_city_unclear":false}],"family":[{"inn":"","inn_hidden":true,"inn_unclear":false,"relations_hidden":false,"relations_other":"","relations":"Дитина","name_hidden":true,"family_name":"","name_unclear":false}],"full_name_suggest":{"output":"Зінченко Микола Григорович","input":["Зінченко Микола Григорович","Микола Григорович Зінченко","Микола Зінченко"]},"patronymic":"Григорович"},"source":"VULYK","estate":{"23":[{"region_unclear":false,"space_unclear":false,"costs":"","costs_comment":"","address_hidden":true,"region_hidden":true,"space_comment":"","space":".1","address":"","region":"","address_unclear":false,"costs_rent_comment":"","costs_comment_hidden":false,"space_units":"га","costs_rent":""},{"costs":"","costs_comment":"","address_hidden":false,"region_hidden":false,"space_units_unclear":true,"space":"","address":"","region":"","costs_rent_comment":"","space_units":"","space_units_hidden":true,"space_comment":"","costs_rent":""}],"25":[{"space_unclear":false,"costs":"","costs_comment":"","address_hidden":false,"region_hidden":false,"space_comment":"","space_hidden":false,"space":"60.1","address":"","region":"","address_unclear":false,"costs_rent_comment":"","space_comment_unclear":false,"space_units":"м²","costs_rent":""}],"26":[{"costs_rent":"","region":"","costs":"","costs_rent_comment":"","costs_comment":"","address_hidden":true,"region_hidden":false,"space_comment":"","space_units":"м²","space":"","address":""}]},"intro":{"declaration_year":"2015","isnotdeclaration":""}}},{"provider":"declarations.com.ua","document":{"income":{"5":{"value":"283574","value_unclear":false,"family_hidden":false,"family_comment":"","family":"74148","comment":""},"6":{"family_comment":"","value":"283574","value_unclear":false,"family":"74148","comment":""},"7":{"source_name_unclear":false,"value":"","family_comment":"","source_name":"","family":"","comment":"","source_name_hidden":false},"8":{"family_comment":"","value":"","family":"","comment":""},"9":{"family_comment":"","value":"","comment_unclear":false,"family":"","comment":""},"10":{"family_comment":"","value":"","family":"1562","comment":""},"11":{"family_comment":"","family_unclear":false,"value":"","family":"","comment":""},"12":{"family_comment":"","value":"","family":"","comment":""},"13":{"family_comment":"","value":"","family":"","comment":""},"14":{"family_comment":"","value":"","family":"","comment":""},"15":{"family_comment":"","value":"","family":"","comment":""},"16":{"family_comment":"","value":"","family":"","comment":""},"17":{"family_comment":"","value":"","family":"","comment":""},"18":{"family_comment":"","value":"","family":"","comment":""},"19":{"family_comment":"","value":"","family":"","comment":""},"20":{"value":"","value_unclear":false,"family_comment":"","comment_unclear":false,"comment":"","family":""}},"vehicle":{"35":[{"year_hidden":false,"brand_info":"1.8 л","sum_rent_comment":"","year":"2007","brand_info_hidden":false,"brand_info_unclear":false,"year_unclear":false,"sum_rent":"","sum":"","brand":"Chevrolet Lacetti","sum_comment":"","brand_unclear":false,"brand_hidden":false}]},"id":"vulyk_94_174","declaration":{"additional_info_text":"","notfull_lostpages":"","date":"2015-03-31T00:00:00","notfull":"","additional_info":"","url":"http://static.declarations.com.ua/declarations/chosen_ones/judges_batch/3820_zinchenko_mykola_hryhorovych.pdf"},"liabilities":{"54":{"sum_foreign_comment":"","sum":"","sum_comment":"","sum_comment_unclear":false,"sum_comment_hidden":false,"sum_unclear":false,"sum_foreign":""},"55":{"sum_foreign_comment":"","sum":"","sum_comment":"","sum_foreign":""},"56":{"sum_foreign_comment":"","sum":"","sum_comment":"","sum_unclear":false,"sum_foreign":""},"57":{"sum_foreign_comment":"","sum":"","sum_comment":"","sum_hidden":false,"sum_unclear":false,"sum_foreign":""},"58":{"sum_foreign_comment":"","sum":"","sum_comment":"","sum_hidden":false,"sum_unclear":false,"sum_foreign":""},"59":{"sum_foreign_comment":"","sum":"","sum_comment":"","sum_foreign":""},"60":{"sum_foreign_comment":"","sum_comment_hidden":false,"sum":"","sum_comment":"","sum_foreign":""},"61":{"sum_foreign_comment":"","sum":"","sum_comment":"","sum_foreign":""},"62":{"sum_foreign_comment":"","sum":"","sum_hidden":false,"sum_comment":"","sum_foreign":""},"63":{"sum_foreign_comment":"","sum_comment_hidden":false,"sum":"","sum_comment":"","sum_foreign":""},"64":{"sum_foreign_comment":"","sum":"","sum_comment":"","sum_unclear":false,"sum_foreign":""}},"ft_src":"голова катеринопільського районного суду черкаської області\nЧеркаська область\nЗагальний місцевий суд\nМикола\nЗінченко Г. І\nПодружжя\nЗінченко В. М\nДитина\nГригорович\nЗінченко Микола Григорович\nМикола Григорович Зінченко\nМикола Зінченко\nЗінченко Микола Григорович\nЗінченко Микола Григорович\nЗінченко\n1.8 л\nChevrolet Lacetti\n2007\n.1\n.15\n163.4\n60.1\n2014\n74148\n283574\n1562\n74148\n283574\n1.8 л\nChevrolet Lacetti\n2007\n2014\nПодружжя\nЗінченко Г. І\nДитина\nЗінченко В. М\nЗінченко Микола Григорович\nМикола Григорович Зінченко\nМикола Зінченко\nЗінченко Микола Григорович\nЗінченко Микола Григорович\nМикола\nГригорович\nЗагальний місцевий суд\nЧеркаська область\nголова катеринопільського районного суду черкаської області\nЗінченко\n283574\n74148\n283574\n74148\n1562\n.1\n.15\n163.4\n60.1\nЗінченко Г. І\nПодружжя\nЗінченко В. М\nДитина\nГригорович\nЗінченко\nМикола\nЗінченко Микола Григорович\nМикола Григорович Зінченко\nМикола Зінченко\nЗінченко Микола Григорович\nЧеркаська область\nЗагальний місцевий суд\nголова катеринопільського районного суду черкаської області\nЗінченко Микола Григорович\nChevrolet Lacetti\n1.8 л\n2007\n1562\n283574\n74148\n74148\n283574\n60.1\n.1\n163.4\n.15\n2014","general":{"inn":"","name":"Микола","last_name":"Зінченко","family":[{"inn":"","relations":"Подружжя","relations_hidden":false,"inn_hidden":true,"family_name":"Зінченко Г. І","name_hidden":false,"name_unclear":true},{"inn":"","relations":"Дитина","relations_unclear":false,"family_name":"Зінченко В. М","inn_hidden":false,"relations_other":"","name_hidden":false,"name_unclear":true}],"inn_hidden":true,"family_raw":"","inn_unclear":false,"post":{"post_unclear":false,"region_unclear":false,"post":"голова катеринопільського районного суду черкаської області","candidate":"","post_hidden":false,"region":"Черкаська область","office":"Загальний місцевий суд","office_unclear":false},"full_name":"Зінченко Микола Григорович","addresses":[{"place_district":"","place_address_hidden":false,"place_city":"","place_city_type_hidden":false,"place_district_hidden":false,"place_city_type":"","place_city_hidden":false,"place_address":"","place_hidden":true,"place":""}],"patronymic":"Григорович","patronymic_hidden":false,"full_name_suggest":{"output":"Зінченко Микола Григорович","input":["Зінченко Микола Григорович","Микола Григорович Зінченко","Микола Зінченко"]}},"source":"VULYK","estate":{"23":[{"region_unclear":false,"space_unclear":false,"costs":"","costs_comment":"","address_hidden":false,"region_hidden":true,"space_comment":"","space_hidden":false,"space":".1","address":"","region":"","address_unclear":false,"space_units_unclear":false,"costs_rent_hidden":false,"costs_rent_comment_hidden":false,"space_units":"га","costs_rent":"","costs_rent_comment":""}],"24":[{"space_unclear":false,"costs":"","costs_comment":"","address_hidden":false,"region_hidden":true,"space_comment":"","space_hidden":false,"space":"163.4","address":"","region":"","costs_rent_comment":"","costs_rent_hidden":false,"costs_rent_comment_hidden":false,"space_units":"м²","costs_rent":""}],"25":[{"region_unclear":false,"space_unclear":false,"costs":"","costs_comment":"","address_hidden":false,"region_hidden":true,"space_comment":"","space_hidden":false,"space":"60.1","address":"","region":"","address_unclear":false,"costs_rent_comment":"","costs_rent_hidden":false,"space_comment_unclear":false,"costs_rent_comment_hidden":false,"space_units":"м²","costs_rent":""}],"29":[{"costs_rent":"","region":"","costs_property":"","costs_rent_comment":"","address_hidden":true,"region_hidden":true,"space_comment":"","costs_property_comment":"","space_units":"га","space":".15","address":""}]},"intro":{"declaration_year":"2014","isnotdeclaration":""}}}],"declarations":[{"income":{"5":{"family_comment":"","family_unclear":false,"value":"254829","family":"53822","comment":""},"6":{"value":"254829","family_comment":"","value_unclear":false,"family_unclear":false,"family":"53822","comment":""},"7":{"source_name_unclear":false,"value":"","family_comment":"","source_name":"","family":"","comment":"","source_name_hidden":false},"8":{"family_comment":"","value":"","family":"","comment":""},"9":{"family_comment":"","family_unclear":false,"value":"","family":"","comment":""},"10":{"family_comment":"","value":"","family":"","comment":""},"11":{"family_comment":"","value":"","family":"","comment":""},"12":{"family_comment":"","value":"","family":"","comment":""},"13":{"family_comment":"","value":"","family":"","comment":""},"14":{"family_comment":"","value":"","family":"","comment":""},"15":{"family_comment":"","value":"","family":"","comment":""},"16":{"family_comment":"","family_unclear":false,"value":"","family":"","comment":""},"17":{"family_comment":"","family_unclear":false,"value":"","family":"","comment":""},"18":{"family_comment":"","value":"","family":"","comment":""},"19":{"family_comment":"","value":"","family":"","comment":""},"20":{"family_comment":"","value":"","comment_unclear":false,"family":"","comment":""}},"vehicle":{"35":[{"brand_info":"1800 куб. см.","sum":"","brand":"Chevrolet Lacetti","sum_comment":"","brand_unclear":false,"year":"2007","brand_hidden":false,"brand_info_hidden":false,"brand_info_unclear":false,"sum_rent_comment":"","sum_rent":""}]},"id":"vulyk_95_39","declaration":{"additional_info_text":"","notfull_lostpages":"","date":"2016-03-30T00:00:00","notfull":"","additional_info":"","url":"http://static.declarations.com.ua/declarations/chosen_ones/judges_batch/40_zinchenko_mykola_hryhorovych_2015.pdf"},"liabilities":{"54":{"sum_foreign_comment":"","sum":"","sum_comment":"","sum_hidden":false,"sum_comment_hidden":false,"sum_unclear":false,"sum_foreign":""},"55":{"sum_foreign_comment":"","sum":"","sum_comment":"","sum_foreign":""},"56":{"sum_foreign_comment":"","sum":"","sum_comment":"","sum_foreign":""},"57":{"sum_foreign_comment":"","sum":"","sum_comment":"","sum_hidden":false,"sum_comment_hidden":false,"sum_unclear":false,"sum_foreign":""},"58":{"sum_foreign_comment":"","sum":"","sum_comment":"","sum_hidden":false,"sum_comment_hidden":false,"sum_unclear":false,"sum_foreign":""},"59":{"sum_foreign_comment":"","sum":"","sum_comment":"","sum_foreign":""},"60":{"sum_foreign_comment":"","sum":"","sum_comment":"","sum_hidden":false,"sum_comment_hidden":false,"sum_foreign":""},"61":{"sum_foreign_comment":"","sum":"","sum_comment":"","sum_foreign":""},"62":{"sum_foreign_comment":"","sum":"","sum_comment":"","sum_unclear":false,"sum_foreign":""},"63":{"sum_foreign_comment":"","sum":"","sum_comment":"","sum_unclear":false,"sum_foreign":""},"64":{"sum_foreign_comment":"","sum":"","sum_comment":"","sum_foreign":""}},"ft_src":"Зінченко Микола Григорович\nголова катеринопільского районного суду черкаської області\nЧеркаська область\nЗагальний місцевий суд\nМикола\nДитина\nЗінченко Микола Григорович\nМикола Григорович Зінченко\nМикола Зінченко\nЗінченко Микола Григорович\nЗінченко\nГригорович\nChevrolet Lacetti\n1800 куб. см.\n2007\n.1\n60.1\n2015\n53822\n254829\n53822\n254829\nChevrolet Lacetti\n1800 куб. см.\n2007\n.1\n60.1\nГригорович\nДитина\nЗінченко Микола Григорович\nМикола Григорович Зінченко\nМикола Зінченко\nЗінченко Микола Григорович\nМикола\nЗінченко Микола Григорович\nЗінченко\nЗагальний місцевий суд\nголова катеринопільского районного суду черкаської області\nЧеркаська область\n254829\n53822\n254829\n53822\n2015\nДитина\nГригорович\nЗінченко\nЧеркаська область\nЗагальний місцевий суд\nголова катеринопільского районного суду черкаської області\nЗінченко Микола Григорович\nЗінченко Микола Григорович\nМикола Григорович Зінченко\nМикола Зінченко\nЗінченко Микола Григорович\nМикола\nChevrolet Lacetti\n1800 куб. см.\n2007\n53822\n254829\n254829\n53822\n60.1\n.1\n2015","general":{"inn":"","inn_hidden":true,"last_name":"Зінченко","post":{"post":"голова катеринопільского районного суду черкаської області","region":"Черкаська область","candidate":"","office_hidden":false,"office":"Загальний місцевий суд","office_unclear":false},"name":"Микола","full_name":"Зінченко Микола Григорович","family_raw":"","addresses":[{"place_address":"","place_district_hidden":true,"place_city_type":"","place_city_hidden":true,"place_address_unclear":false,"place_city_type_hidden":true,"place_city":"","place":"","place_district":"","place_address_hidden":true,"place_hidden":false,"place_city_unclear":false}],"family":[{"inn":"","inn_hidden":true,"inn_unclear":false,"relations_hidden":false,"relations_other":"","relations":"Дитина","name_hidden":true,"family_name":"","name_unclear":false}],"full_name_suggest":{"output":"Зінченко Микола Григорович","input":["Зінченко Микола Григорович","Микола Григорович Зінченко","Микола Зінченко"]},"patronymic":"Григорович"},"source":"VULYK","estate":{"23":[{"region_unclear":false,"space_unclear":false,"costs":"","costs_comment":"","address_hidden":true,"region_hidden":true,"space_comment":"","space":".1","address":"","region":"","address_unclear":false,"costs_rent_comment":"","costs_comment_hidden":false,"space_units":"га","costs_rent":""},{"costs":"","costs_comment":"","address_hidden":false,"region_hidden":false,"space_units_unclear":true,"space":"","address":"","region":"","costs_rent_comment":"","space_units":"","space_units_hidden":true,"space_comment":"","costs_rent":""}],"25":[{"space_unclear":false,"costs":"","costs_comment":"","address_hidden":false,"region_hidden":false,"space_comment":"","space_hidden":false,"space":"60.1","address":"","region":"","address_unclear":false,"costs_rent_comment":"","space_comment_unclear":false,"space_units":"м²","costs_rent":""}],"26":[{"costs_rent":"","region":"","costs":"","costs_rent_comment":"","costs_comment":"","address_hidden":true,"region_hidden":false,"space_comment":"","space_units":"м²","space":"","address":""}]},"intro":{"declaration_year":"2015","isnotdeclaration":""}},{"income":{"5":{"value":"283574","value_unclear":false,"family_hidden":false,"family_comment":"","family":"74148","comment":""},"6":{"family_comment":"","value":"283574","value_unclear":false,"family":"74148","comment":""},"7":{"source_name_unclear":false,"value":"","family_comment":"","source_name":"","family":"","comment":"","source_name_hidden":false},"8":{"family_comment":"","value":"","family":"","comment":""},"9":{"family_comment":"","value":"","comment_unclear":false,"family":"","comment":""},"10":{"family_comment":"","value":"","family":"1562","comment":""},"11":{"family_comment":"","family_unclear":false,"value":"","family":"","comment":""},"12":{"family_comment":"","value":"","family":"","comment":""},"13":{"family_comment":"","value":"","family":"","comment":""},"14":{"family_comment":"","value":"","family":"","comment":""},"15":{"family_comment":"","value":"","family":"","comment":""},"16":{"family_comment":"","value":"","family":"","comment":""},"17":{"family_comment":"","value":"","family":"","comment":""},"18":{"family_comment":"","value":"","family":"","comment":""},"19":{"family_comment":"","value":"","family":"","comment":""},"20":{"value":"","value_unclear":false,"family_comment":"","comment_unclear":false,"comment":"","family":""}},"vehicle":{"35":[{"year_hidden":false,"brand_info":"1.8 л","sum_rent_comment":"","year":"2007","brand_info_hidden":false,"brand_info_unclear":false,"year_unclear":false,"sum_rent":"","sum":"","brand":"Chevrolet Lacetti","sum_comment":"","brand_unclear":false,"brand_hidden":false}]},"id":"vulyk_94_174","declaration":{"additional_info_text":"","notfull_lostpages":"","date":"2015-03-31T00:00:00","notfull":"","additional_info":"","url":"http://static.declarations.com.ua/declarations/chosen_ones/judges_batch/3820_zinchenko_mykola_hryhorovych.pdf"},"liabilities":{"54":{"sum_foreign_comment":"","sum":"","sum_comment":"","sum_comment_unclear":false,"sum_comment_hidden":false,"sum_unclear":false,"sum_foreign":""},"55":{"sum_foreign_comment":"","sum":"","sum_comment":"","sum_foreign":""},"56":{"sum_foreign_comment":"","sum":"","sum_comment":"","sum_unclear":false,"sum_foreign":""},"57":{"sum_foreign_comment":"","sum":"","sum_comment":"","sum_hidden":false,"sum_unclear":false,"sum_foreign":""},"58":{"sum_foreign_comment":"","sum":"","sum_comment":"","sum_hidden":false,"sum_unclear":false,"sum_foreign":""},"59":{"sum_foreign_comment":"","sum":"","sum_comment":"","sum_foreign":""},"60":{"sum_foreign_comment":"","sum_comment_hidden":false,"sum":"","sum_comment":"","sum_foreign":""},"61":{"sum_foreign_comment":"","sum":"","sum_comment":"","sum_foreign":""},"62":{"sum_foreign_comment":"","sum":"","sum_hidden":false,"sum_comment":"","sum_foreign":""},"63":{"sum_foreign_comment":"","sum_comment_hidden":false,"sum":"","sum_comment":"","sum_foreign":""},"64":{"sum_foreign_comment":"","sum":"","sum_comment":"","sum_unclear":false,"sum_foreign":""}},"ft_src":"голова катеринопільського районного суду черкаської області\nЧеркаська область\nЗагальний місцевий суд\nМикола\nЗінченко Г. І\nПодружжя\nЗінченко В. М\nДитина\nГригорович\nЗінченко Микола Григорович\nМикола Григорович Зінченко\nМикола Зінченко\nЗінченко Микола Григорович\nЗінченко Микола Григорович\nЗінченко\n1.8 л\nChevrolet Lacetti\n2007\n.1\n.15\n163.4\n60.1\n2014\n74148\n283574\n1562\n74148\n283574\n1.8 л\nChevrolet Lacetti\n2007\n2014\nПодружжя\nЗінченко Г. І\nДитина\nЗінченко В. М\nЗінченко Микола Григорович\nМикола Григорович Зінченко\nМикола Зінченко\nЗінченко Микола Григорович\nЗінченко Микола Григорович\nМикола\nГригорович\nЗагальний місцевий суд\nЧеркаська область\nголова катеринопільського районного суду черкаської області\nЗінченко\n283574\n74148\n283574\n74148\n1562\n.1\n.15\n163.4\n60.1\nЗінченко Г. І\nПодружжя\nЗінченко В. М\nДитина\nГригорович\nЗінченко\nМикола\nЗінченко Микола Григорович\nМикола Григорович Зінченко\nМикола Зінченко\nЗінченко Микола Григорович\nЧеркаська область\nЗагальний місцевий суд\nголова катеринопільського районного суду черкаської області\nЗінченко Микола Григорович\nChevrolet Lacetti\n1.8 л\n2007\n1562\n283574\n74148\n74148\n283574\n60.1\n.1\n163.4\n.15\n2014","general":{"inn":"","name":"Микола","last_name":"Зінченко","family":[{"inn":"","relations":"Подружжя","relations_hidden":false,"inn_hidden":true,"family_name":"Зінченко Г. І","name_hidden":false,"name_unclear":true},{"inn":"","relations":"Дитина","relations_unclear":false,"family_name":"Зінченко В. М","inn_hidden":false,"relations_other":"","name_hidden":false,"name_unclear":true}],"inn_hidden":true,"family_raw":"","inn_unclear":false,"post":{"post_unclear":false,"region_unclear":false,"post":"голова катеринопільського районного суду черкаської області","candidate":"","post_hidden":false,"region":"Черкаська область","office":"Загальний місцевий суд","office_unclear":false},"full_name":"Зінченко Микола Григорович","addresses":[{"place_district":"","place_address_hidden":false,"place_city":"","place_city_type_hidden":false,"place_district_hidden":false,"place_city_type":"","place_city_hidden":false,"place_address":"","place_hidden":true,"place":""}],"patronymic":"Григорович","patronymic_hidden":false,"full_name_suggest":{"output":"Зінченко Микола Григорович","input":["Зінченко Микола Григорович","Микола Григорович Зінченко","Микола Зінченко"]}},"source":"VULYK","estate":{"23":[{"region_unclear":false,"space_unclear":false,"costs":"","costs_comment":"","address_hidden":false,"region_hidden":true,"space_comment":"","space_hidden":false,"space":".1","address":"","region":"","address_unclear":false,"space_units_unclear":false,"costs_rent_hidden":false,"costs_rent_comment_hidden":false,"space_units":"га","costs_rent":"","costs_rent_comment":""}],"24":[{"space_unclear":false,"costs":"","costs_comment":"","address_hidden":false,"region_hidden":true,"space_comment":"","space_hidden":false,"space":"163.4","address":"","region":"","costs_rent_comment":"","costs_rent_hidden":false,"costs_rent_comment_hidden":false,"space_units":"м²","costs_rent":""}],"25":[{"region_unclear":false,"space_unclear":false,"costs":"","costs_comment":"","address_hidden":false,"region_hidden":true,"space_comment":"","space_hidden":false,"space":"60.1","address":"","region":"","address_unclear":false,"costs_rent_comment":"","costs_rent_hidden":false,"space_comment_unclear":false,"costs_rent_comment_hidden":false,"space_units":"м²","costs_rent":""}],"29":[{"costs_rent":"","region":"","costs_property":"","costs_rent_comment":"","address_hidden":true,"region_hidden":true,"space_comment":"","costs_property_comment":"","space_units":"га","space":".15","address":""}]},"intro":{"declaration_year":"2014","isnotdeclaration":""}}],"declarationsLength":2,"analytics":[{"y":2015,"i":254829,"c":1,"k":60.1,"ka":1,"l":1000,"la":2,"fi":53822,"j":2},{"y":2014,"i":283574,"c":1,"k":60.1,"ka":1,"h":163.4,"ha":1,"l":1000,"la":1,"fi":74148,"fl":1500,"fla":1}]}