{"ft_src":"Nissan,Note\n2011\n1500\n18\n164\n10917,43\nTRUE\nп. 3. Посада;Суддя Апеляційного суду Київської області - нема впевненості, що вірно розпізнана назва ’Київської’ області);;п. 4. Члени сім’ї декларанта;син Перевуенчев Ю. О. - (нема впевненості, що вірно розпізнане Прізвище сина);;п. 24. Житлові будинки і. Сума витрат на оренду;В колонці ’Сума витрат (грн) на оренду чи на інше право користування’ замість вартості нерозбірливо внесене якесь слово;;п. 45. Сума коштів на рахунках у банках усього;в колонці ’Усього’ вказано: ;Приват банк - 2917.43 грн,;Укрсиббанк - 8000 грн;Замість суми 10917.43\nFALSE\nFALSE\n2013\n225093,59\n48000\n11470\n284563,59\nNissan,Note\n2011\nп. 3. Посада;Суддя Апеляційного суду Київської області - нема впевненості, що вірно розпізнана назва ’Київської’ області);;п. 4. Члени сім’ї декларанта;син Перевуенчев Ю. О. - (нема впевненості, що вірно розпізнане Прізвище сина);;п. 24. Житлові будинки і. Сума витрат на оренду;В колонці ’Сума витрат (грн) на оренду чи на інше право користування’ замість вартості нерозбірливо внесене якесь слово;;п. 45. Сума коштів на рахунках у банках усього;в колонці ’Усього’ вказано: ;Приват банк - 2917.43 грн,;Укрсиббанк - 8000 грн;Замість суми 10917.43\nFALSE\nTRUE\n1500\n18\n164\nСуддя Апеляційного суду Київської області\nСин Перевуенчев Ю. О.\nСушко\nСушко Людмила Петрівна\nЛюдмила Петрівна Сушко\nЛюдмила Сушко\nСушко Людмила Петрівна\nЛюдмила\nСушко Людмила Петрівна\nЗагальний апеляційний суд\nСуддя\nКиївська область\nПетрівна\n225093,59\n48000\n284563,59\n11470\n10917,43\n2013\nFALSE\nСушко\nПетрівна\nСин Перевуенчев Ю. О.\nСушко Людмила Петрівна\nЛюдмила Петрівна Сушко\nЛюдмила Сушко\nСушко Людмила Петрівна\nЛюдмила\nСуддя Апеляційного суду Київської області\nСуддя\nКиївська область\nЗагальний апеляційний суд\nСушко Людмила Петрівна","estate":{"23":[{"costs":"","address":"","space_units":"","costs_rent_comment":"","space":"1500","costs_comment":"","costs_rent":"","space_comment":"","region":"","location_raw":"приховано"},{"costs":"","address":"","space_units":"","costs_rent_comment":"","space":"","costs_comment":"","costs_rent":"","space_comment":"","region":"","location_raw":""},{"costs":"","address":"","space_units":"","costs_rent_comment":"","space":"","costs_comment":"","costs_rent":"","space_comment":"","region":"","location_raw":""}],"24":[{"costs":"","address":"","space_units":"","costs_rent_comment":"","space":"","costs_comment":"","costs_rent":"","space_comment":"","region":"","location_raw":"приховано"}],"25":[{"costs":"","address":"","space_units":"","costs_rent_comment":"","space":"164","costs_comment":"","costs_rent":"","space_comment":"","region":"","location_raw":"приховано"}],"27":[{"costs":"","address":"","space_units":"","costs_rent_comment":"","space":"18","costs_comment":"","costs_rent":"","space_comment":"","region":"","location_raw":"приховано"}]},"vehicle":{"35":[{"sum_comment":"","brand_info":"","sum":"","sum_rent_comment":"","year":"2011","brand":"Nissan,Note","sum_rent":"","brand_hidden":false}]},"id":"1127","income":{"5":{"family_comment":"","value":"284563,59","family":"0","comment":""},"6":{"family_comment":"","value":"225093,59","family":"0","comment":""},"7":{"family":"0","family_comment":"","value":"0","comment":"","source_name":"0"},"8":{"family_comment":"","value":"0","family":"0","comment":""},"9":{"family_comment":"","value":"0","family":"0","comment":""},"10":{"family_comment":"","value":"11470","family":"0","comment":""},"11":{"family_comment":"","value":"0","family":"0","comment":""},"12":{"family_comment":"","value":"0","family":"0","comment":""},"13":{"family_comment":"","value":"48000","family":"0","comment":""},"14":{"family_comment":"","value":"0","family":"0","comment":""},"15":{"family_comment":"","value":"0","family":"0","comment":""},"16":{"family_comment":"","value":"0","family":"0","comment":""},"17":{"family_comment":"","value":"0","family":"0","comment":""},"18":{"family_comment":"","value":"0","family":"0","comment":""},"19":{"family_comment":"","value":"0","family":"0","comment":""},"20":{"family_comment":"","value":"0","family":"0","comment":""},"21":[{"country_comment":"","uah_equal":"0","country":"0","cur":"0"},{"country_comment":"","uah_equal":"0","country":"0","cur":"0"},{"country_comment":"","uah_equal":"0","country":"0","cur":"0"},{"country_comment":"","uah_equal":"0","country":"0","cur":"0"},{"country_comment":"","uah_equal":"0","country":"0","cur":"0"}],"22":[{"country_comment":"","uah_equal":"0","country":"0","cur":"0"},{"country_comment":"","uah_equal":"0","country":"0","cur":"0"},{"country_comment":"","uah_equal":"0","country":"0","cur":"0"},{"country_comment":"","uah_equal":"0","country":"0","cur":"0"},{"country_comment":"","uah_equal":"0","country":"0","cur":"0"}]},"banks":{"45":[{"sum_units":"UAH","sum_comment":"","sum_foreign_units":"","sum":"10917,43","sum_foreign_comment":"","sum_foreign":""},{"sum_units":"USD","sum_comment":"","sum_foreign_units":"","sum":"","sum_foreign_comment":"","sum_foreign":""},{"sum_units":"EUR","sum_comment":"","sum_foreign_units":"","sum":"","sum_foreign_comment":"","sum_foreign":""}],"46":[{"sum_units":"UAH","sum_comment":"","sum_foreign_units":"","sum":"","sum_foreign_comment":"","sum_foreign":""},{"sum_units":"USD","sum_comment":"","sum_foreign_units":"","sum":"","sum_foreign_comment":"","sum_foreign":""},{"sum_units":"EUR","sum_comment":"","sum_foreign_units":"","sum":"","sum_foreign_comment":"","sum_foreign":""}],"47":[{"sum_units":"","sum_comment":"","sum_foreign_units":"","sum":"","sum_foreign_comment":"","sum_foreign":""}],"48":[{"sum_units":"","sum_comment":"","sum_foreign_units":"","sum":"","sum_foreign_comment":"","sum_foreign":""}],"49":[{"sum_units":"","sum_comment":"","sum_foreign_units":"","sum":"","sum_foreign_comment":"","sum_foreign":""}],"50":[{"sum_units":"","sum_comment":"","sum_foreign_units":"","sum":"","sum_foreign_comment":"","sum_foreign":""}],"51":[{"sum_units":"UAH","sum_comment":"","sum_foreign_units":"","sum":"","sum_foreign_comment":"","sum_foreign":""},{"sum_units":"USD","sum_comment":"","sum_foreign_units":"","sum":"","sum_foreign_comment":"","sum_foreign":""},{"sum_units":"EUR","sum_comment":"","sum_foreign_units":"","sum":"","sum_foreign_comment":"","sum_foreign":""}],"52":[{"sum_units":"","sum_comment":"","sum_foreign_units":"","sum":"","sum_foreign_comment":"","sum_foreign":""}],"53":[{"sum_units":"","sum_comment":"","sum_foreign_units":"","sum":"","sum_foreign_comment":"","sum_foreign":""}]},"declaration":{"notfull_lostpages":"","additional_info_text":"п. 3. Посада;Суддя Апеляційного суду Київської області - нема впевненості, що вірно розпізнана назва ’Київської’ області);;п. 4. Члени сім’ї декларанта;син Перевуенчев Ю. О. - (нема впевненості, що вірно розпізнане Прізвище сина);;п. 24. Житлові будинки і. Сума витрат на оренду;В колонці ’Сума витрат (грн) на оренду чи на інше право користування’ замість вартості нерозбірливо внесене якесь слово;;п. 45. Сума коштів на рахунках у банках усього;в колонці ’Усього’ вказано: ;Приват банк - 2917.43 грн,;Укрсиббанк - 8000 грн;Замість суми 10917.43","additional_info":"TRUE","notfull":"FALSE","url":"http://static.declarations.com.ua/declarations/sudy/apeliatsiini_sudy_oblastei__m.kyieva/kyivska/sushko.pdf","needs_scancopy_check":false},"general":{"family_raw":"Син Перевуенчев Ю. О.","name":"Людмила","full_name_suggest":{"input":["Сушко Людмила Петрівна","Людмила Петрівна Сушко","Людмила Сушко"],"output":"Сушко Людмила Петрівна"},"post_raw":"Суддя Апеляційного суду Київської області","name_unclear":false,"patronymic":"Петрівна","patronymic_unclear":false,"last_name_hidden":false,"patronymic_hidden":false,"inn":"","addresses_raw_hidden":true,"last_name":"Сушко","full_name":"Сушко Людмила Петрівна","post":{"office":"Загальний апеляційний суд","region":"Київська область","post":"Суддя"},"addresses_raw":"приховано","name_hidden":false,"last_name_unclear":false},"liabilities":{"54":{"sum_comment":"","sum_foreign_comment":"","sum_foreign":"","sum":""},"55":{"sum_units":"","sum_comment":"","sum_foreign_units":"","sum":"","sum_foreign_comment":"","sum_foreign":""},"56":{"sum_comment":"","sum_foreign_comment":"","sum_foreign":"","sum":""},"57":{"sum_comment":"","sum_foreign_comment":"","sum_foreign":"","sum":""},"58":{"sum_comment":"","sum_foreign_comment":"","sum_foreign":"","sum":""},"59":{"sum_comment":"","sum_foreign_comment":"","sum_foreign":"","sum":""},"60":{"sum_comment":"","sum_foreign_comment":"","sum_foreign":"","sum":""},"61":{"sum_units":"","sum_comment":"","sum_foreign_units":"","sum":"","sum_foreign_comment":"","sum_foreign":""},"62":{"sum_comment":"","sum_foreign_comment":"","sum_foreign":"","sum":""},"63":{"sum_comment":"","sum_units":"","sum_foreign":"","sum":"","sum_foreign_comment":""},"64":{"sum_comment":"","sum_units":"","sum_foreign":"","sum":"","sum_foreign_comment":""}},"intro":{"isnotdeclaration":"FALSE","declaration_year":"2013"}}