{"ft_src":"Daewoo,Sens\n2004\nSkoda,Octavia A5\n2005\nУкраїна, Дніпропетр. обл\n495\nУкраїна, Дніпропетр. обл\n98\nTRUE\nпункти 29 та 31 - частково прихована інформація по місцезнаходженню земельної ділянки та квартири\nFALSE\nFALSE\n2013\n1062\n176390\n24635\n176390\n4791\n18782\nDaewoo,Sens\n2004\nSkoda,Octavia A5\n2005\nпункти 29 та 31 - частково прихована інформація по місцезнаходженню земельної ділянки та квартири\nFALSE\nTRUE\nУкраїна, Дніпропетр. обл\n495\nУкраїна, Дніпропетр. обл\n98\nСуддя Дніпропетровського окружного адміністративного суду\nЧоловік Бондар О.О., частково приховано\nДніпропетровська\nДніпропетровськ\nБондар\nБондар Марина Володимирівна\nМарина Володимирівна Бондар\nМарина Бондар\nБондар Марина Володимирівна\nМарина\nБондар Марина Володимирівна\nАдміністративний місцевий суд\nСуддя\nДніпропетровська область\nВолодимирівна\n49000, Дніпропетровська область, м. Дніпропетровськ, частково приховано\n176390\n1062\n18782\n4791\n176390\n24635\n2013\nFALSE\nБондар\nВолодимирівна\nЧоловік Бондар О.О., частково приховано\nБондар Марина Володимирівна\nМарина Володимирівна Бондар\nМарина Бондар\nБондар Марина Володимирівна\nМарина\nСуддя Дніпропетровського окружного адміністративного суду\nДніпропетровська\nДніпропетровськ\nСуддя\nДніпропетровська область\nАдміністративний місцевий суд\nБондар Марина Володимирівна\n49000, Дніпропетровська область, м. Дніпропетровськ, частково приховано","estate":{"23":[{"costs":"","address":"","space_units":"","costs_rent_comment":"","space":"","costs_comment":"","costs_rent":"","space_comment":"","region":"","location_raw":""},{"costs":"","address":"","space_units":"","costs_rent_comment":"","space":"","costs_comment":"","costs_rent":"","space_comment":"","region":"","location_raw":""},{"costs":"","address":"","space_units":"","costs_rent_comment":"","space":"","costs_comment":"","costs_rent":"","space_comment":"","region":"","location_raw":""}],"29":[{"costs_property_comment":"","address":"","space_units":"","costs_rent_comment":"","space":"495","space_comment":"","costs_property":"","region":"","location_raw":"Україна, Дніпропетр. обл","costs_rent":""}],"31":[{"costs_property_comment":"","address":"","space_units":"","costs_rent_comment":"","space":"98","space_comment":"","costs_property":"","region":"","location_raw":"Україна, Дніпропетр. обл","costs_rent":""}]},"vehicle":{"35":[{"sum_comment":"","brand_info":"","sum":"","sum_rent_comment":"","year":"2004","brand":"Daewoo,Sens","sum_rent":"","brand_hidden":false}],"40":[{"sum_comment":"","brand_info":"","sum":"","sum_rent_comment":"","year":"2005","brand":"Skoda,Octavia A5","sum_rent":"","brand_hidden":false}]},"id":"1145","income":{"5":{"family_comment":"","value":"176390","family":"24635","comment":""},"6":{"family_comment":"","value":"176390","family":"1062","comment":""},"7":{"family":"0","family_comment":"","value":"0","comment":"","source_name":"0"},"8":{"family_comment":"","value":"0","family":"0","comment":""},"9":{"family_comment":"","value":"0","family":"0","comment":""},"10":{"family_comment":"","value":"0","family":"0","comment":""},"11":{"family_comment":"","value":"0","family":"0","comment":""},"12":{"family_comment":"","value":"0","family":"18782","comment":""},"13":{"family_comment":"","value":"0","family":"0","comment":""},"14":{"family_comment":"","value":"0","family":"0","comment":""},"15":{"family_comment":"","value":"0","family":"0","comment":""},"16":{"family_comment":"","value":"0","family":"0","comment":""},"17":{"family_comment":"","value":"0","family":"0","comment":""},"18":{"family_comment":"","value":"0","family":"0","comment":""},"19":{"family_comment":"","value":"0","family":"0","comment":""},"20":{"family_comment":"","value":"0","family":"4791","comment":""},"21":[{"country_comment":"","uah_equal":"0","country":"0","cur":"0"},{"country_comment":"","uah_equal":"0","country":"0","cur":"0"},{"country_comment":"","uah_equal":"0","country":"0","cur":"0"},{"country_comment":"","uah_equal":"0","country":"0","cur":"0"},{"country_comment":"","uah_equal":"0","country":"0","cur":"0"}],"22":[{"country_comment":"","uah_equal":"0","country":"0","cur":"0"},{"country_comment":"","uah_equal":"0","country":"0","cur":"0"},{"country_comment":"","uah_equal":"0","country":"0","cur":"0"},{"country_comment":"","uah_equal":"0","country":"0","cur":"0"},{"country_comment":"","uah_equal":"0","country":"0","cur":"0"}]},"banks":{"45":[{"sum_units":"UAH","sum_comment":"","sum_foreign_units":"","sum":"","sum_foreign_comment":"","sum_foreign":""},{"sum_units":"USD","sum_comment":"","sum_foreign_units":"","sum":"","sum_foreign_comment":"","sum_foreign":""},{"sum_units":"EUR","sum_comment":"","sum_foreign_units":"","sum":"","sum_foreign_comment":"","sum_foreign":""}],"46":[{"sum_units":"UAH","sum_comment":"","sum_foreign_units":"","sum":"","sum_foreign_comment":"","sum_foreign":""},{"sum_units":"USD","sum_comment":"","sum_foreign_units":"","sum":"","sum_foreign_comment":"","sum_foreign":""},{"sum_units":"EUR","sum_comment":"","sum_foreign_units":"","sum":"","sum_foreign_comment":"","sum_foreign":""}],"47":[{"sum_units":"","sum_comment":"","sum_foreign_units":"","sum":"","sum_foreign_comment":"","sum_foreign":""}],"48":[{"sum_units":"","sum_comment":"","sum_foreign_units":"","sum":"","sum_foreign_comment":"","sum_foreign":""}],"49":[{"sum_units":"","sum_comment":"","sum_foreign_units":"","sum":"","sum_foreign_comment":"","sum_foreign":""}],"50":[{"sum_units":"","sum_comment":"","sum_foreign_units":"","sum":"","sum_foreign_comment":"","sum_foreign":""}],"51":[{"sum_units":"UAH","sum_comment":"","sum_foreign_units":"","sum":"","sum_foreign_comment":"","sum_foreign":""},{"sum_units":"USD","sum_comment":"","sum_foreign_units":"","sum":"","sum_foreign_comment":"","sum_foreign":""},{"sum_units":"EUR","sum_comment":"","sum_foreign_units":"","sum":"","sum_foreign_comment":"","sum_foreign":""}],"52":[{"sum_units":"","sum_comment":"","sum_foreign_units":"","sum":"","sum_foreign_comment":"","sum_foreign":""}],"53":[{"sum_units":"","sum_comment":"","sum_foreign_units":"","sum":"","sum_foreign_comment":"","sum_foreign":""}]},"declaration":{"notfull_lostpages":"","additional_info_text":"пункти 29 та 31 - частково прихована інформація по місцезнаходженню земельної ділянки та квартири","additional_info":"TRUE","notfull":"FALSE","url":"http://static.declarations.com.ua/declarations/sudy/mistsevi_sudy/okruzhni_administratyvni_sudy/dnipropetrovska/bondar.pdf","needs_scancopy_check":false},"general":{"family_raw":"Чоловік Бондар О.О., частково приховано","name":"Марина","full_name_suggest":{"input":["Бондар Марина Володимирівна","Марина Володимирівна Бондар","Марина Бондар"],"output":"Бондар Марина Володимирівна"},"post_raw":"Суддя Дніпропетровського окружного адміністративного суду","name_unclear":false,"patronymic":"Володимирівна","patronymic_unclear":false,"last_name_hidden":false,"patronymic_hidden":false,"inn":"","addresses_raw_hidden":true,"last_name":"Бондар","full_name":"Бондар Марина Володимирівна","post":{"office":"Адміністративний місцевий суд","region":"Дніпропетровська область","post":"Суддя"},"addresses":[{"place_district":"","place_city_type":"","place_address_type":"","place":"Дніпропетровська","place_address":"","place_city":"Дніпропетровськ"}],"name_hidden":false,"last_name_unclear":false,"addresses_raw":"49000, Дніпропетровська область, м. Дніпропетровськ, частково приховано"},"liabilities":{"54":{"sum_comment":"","sum_foreign_comment":"","sum_foreign":"","sum":""},"55":{"sum_units":"","sum_comment":"","sum_foreign_units":"","sum":"","sum_foreign_comment":"","sum_foreign":""},"56":{"sum_comment":"","sum_foreign_comment":"","sum_foreign":"","sum":""},"57":{"sum_comment":"","sum_foreign_comment":"","sum_foreign":"","sum":""},"58":{"sum_comment":"","sum_foreign_comment":"","sum_foreign":"","sum":""},"59":{"sum_comment":"","sum_foreign_comment":"","sum_foreign":"","sum":""},"60":{"sum_comment":"","sum_foreign_comment":"","sum_foreign":"","sum":""},"61":{"sum_units":"","sum_comment":"","sum_foreign_units":"","sum":"","sum_foreign_comment":"","sum_foreign":""},"62":{"sum_comment":"","sum_foreign_comment":"","sum_foreign":"","sum":""},"63":{"sum_comment":"","sum_units":"","sum_foreign":"","sum":"","sum_foreign_comment":""},"64":{"sum_comment":"","sum_units":"","sum_foreign":"","sum":"","sum_foreign_comment":""}},"intro":{"isnotdeclaration":"FALSE","declaration_year":"2013"}}