{"income":{"5":{"value":"308258","family_comment":"","value_unclear":false,"value_hidden":false,"family_unclear":false,"family":"211727","comment":""},"6":{"value":"307510","family_hidden":false,"value_hidden":false,"family_comment":"","family_comment_hidden":false,"comment":"","family":""},"7":{"value":"478","value_unclear":false,"family_hidden":false,"value_hidden":false,"family_comment":"","source_name":"Національна школа суддів України","family":"","comment":"","source_name_hidden":false},"8":{"value":"","comment_hidden":false,"family_hidden":false,"value_hidden":false,"family_comment":"","family":"","comment":""},"9":{"value":"","family_comment":"","comment_hidden":false,"family_hidden":false,"value_hidden":false,"family_unclear":false,"family":"","comment":""},"10":{"value":"","comment_hidden":false,"family_hidden":false,"value_hidden":false,"family_comment":"","family":"","comment":""},"11":{"value":"","value_unclear":false,"comment_hidden":false,"family_hidden":false,"value_hidden":false,"family_comment":"","family":"","comment":""},"12":{"value":"","comment_hidden":false,"family_hidden":false,"value_hidden":false,"family_comment":"","family":"","comment":""},"13":{"value":"","comment_hidden":false,"family_hidden":false,"value_hidden":false,"family_comment":"","family":"","comment":""},"14":{"value":"","comment_hidden":false,"family_hidden":false,"value_hidden":false,"family_comment":"","family":"147536","comment":""},"15":{"value":"","comment_hidden":false,"family_hidden":false,"value_hidden":false,"family_comment":"","family":"24910","comment":""},"16":{"value":"","comment_hidden":false,"family_hidden":false,"value_hidden":false,"family_comment":"","family":"","comment":""},"17":{"value":"","comment_hidden":false,"family_hidden":false,"value_hidden":false,"family_comment":"","family":"","comment":""},"18":{"value":"","value_unclear":false,"comment_hidden":false,"family_hidden":false,"value_hidden":false,"family_comment":"","family":"","comment":""},"19":{"value":"","comment_hidden":false,"family_hidden":false,"value_hidden":false,"family_comment":"","family":"","comment":""},"20":{"value":"270","value_unclear":false,"family_comment":"","comment_unclear":false,"comment":"","family":"39281"}},"vehicle":{"40":[{"year_hidden":false,"brand_info":"легковий універсал В, обєм двигуна 2672 , потужність двигуна 185","sum_rent_comment":"","brand":"Toyota Venza","sum_comment":"","brand_unclear":false,"year":"2012","brand_hidden":false,"brand_info_unclear":false,"sum":"","sum_rent":""}]},"id":"1291","declaration":{"additional_info_text":"","notfull_lostpages":"","date":"2014-03-26T00:00:00","notfull":"","additional_info":"","url":"http://static.declarations.com.ua/declarations/chosen_ones/judges_batch/236_vysotska_valentyna_stepanivna.pdf"},"liabilities":{"54":{"sum_foreign_comment":"","sum_foreign_hidden":false,"sum_comment":"","sum_hidden":false,"sum_comment_hidden":false,"sum":"","sum_foreign":""},"55":{"sum_foreign_comment":"","sum":"","sum_hidden":false,"sum_comment":"","sum_foreign":""},"56":{"sum_foreign_comment":"","sum":"","sum_comment":"","sum_foreign":""},"57":{"sum_foreign_comment":"","sum_foreign_hidden":false,"sum_comment":"","sum_hidden":false,"sum_comment_hidden":false,"sum_unclear":false,"sum":"","sum_foreign":""},"58":{"sum_foreign_comment":"","sum_foreign_hidden":false,"sum_comment":"","sum_hidden":false,"sum_comment_hidden":false,"sum_unclear":false,"sum":"","sum_foreign":""},"59":{"sum_foreign_comment":"","sum":"","sum_hidden":false,"sum_comment":"","sum_foreign":""},"60":{"sum_foreign_comment":"","sum_foreign_hidden":false,"sum_comment":"","sum_hidden":false,"sum_comment_hidden":false,"sum_unclear":false,"sum":"","sum_foreign":""},"61":{"sum_foreign_comment":"","sum":"","sum_hidden":false,"sum_comment":"","sum_foreign":""},"62":{"sum_foreign_comment":"","sum":"","sum_comment":"","sum_hidden":false,"sum_comment_hidden":false,"sum_foreign":""},"63":{"sum_foreign_comment":"","sum":"","sum_hidden":false,"sum_comment":"","sum_foreign":""},"64":{"sum_foreign_comment":"","sum":"","sum_hidden":false,"sum_comment":"","sum_foreign":""}},"ft_src":"суддя вищого спецiалiзованого суду україни з розгляду цивiльних і кримiнальних справ\nЗагальнодержавний регіон\nВищий спеціалізований суд з розгляду цивільних і кримінальних справ\nВалентина\nВисоцький М. М\nПодружжя\nСтепанівна\nВисоцька Валентина Степанівна\nВалентина Степанівна Висоцька\nВалентина Висоцька\nВисоцька Валентина Степанівна\nВисоцька Валентина Степанівна\nВисоцька\nToyota Venza\nлегковий універсал В, обєм двигуна 2672 , потужність двигуна 185\n2012\n750\n69.7\n629\n22.4\n83.1\n22.4\n83.1\n2013\n307510\n147536\n24910\nНаціональна школа суддів України\n478\n211727\n308258\n39281\n270\nлегковий універсал В, обєм двигуна 2672 , потужність двигуна 185\nToyota Venza\n2012\n750\n629\n69.7\n22.4\n83.1\n22.4\n83.1\nВисоцька Валентина Степанівна\nВалентина Степанівна Висоцька\nВалентина Висоцька\nВисоцька Валентина Степанівна\nВисоцька Валентина Степанівна\nПодружжя\nВисоцький М. М\nВалентина\nСтепанівна\nВищий спеціалізований суд з розгляду цивільних і кримінальних справ\nсуддя вищого спецiалiзованого суду україни з розгляду цивiльних і кримiнальних справ\nЗагальнодержавний регіон\nВисоцька\n478\nНаціональна школа суддів України\n307510\n270\n39281\n24910\n147536\n308258\n211727\n2013\nВисоцький М. М\nПодружжя\nСтепанівна\nВисоцька\nВалентина\nВисоцька Валентина Степанівна\nВалентина Степанівна Висоцька\nВалентина Висоцька\nВисоцька Валентина Степанівна\nЗагальнодержавний регіон\nсуддя вищого спецiалiзованого суду україни з розгляду цивiльних і кримiнальних справ\nВищий спеціалізований суд з розгляду цивільних і кримінальних справ\nВисоцька Валентина Степанівна\n2012\nToyota Venza\nлегковий універсал В, обєм двигуна 2672 , потужність двигуна 185\n24910\n147536\n270\n39281\n308258\n211727\n478\nНаціональна школа суддів України\n307510\n22.4\n83.1\n69.7\n629\n22.4\n83.1\n750\n2013","general":{"inn":"","name":"Валентина","inn_unclear":false,"family":[{"inn":"","inn_hidden":true,"relations_unclear":false,"relations_hidden":false,"relations_other":"","relations":"Подружжя","name_hidden":false,"family_name":"Висоцький М. М","name_unclear":false}],"inn_hidden":true,"family_raw":"","last_name":"Висоцька","post":{"post_unclear":false,"post":"суддя вищого спецiалiзованого суду україни з розгляду цивiльних і кримiнальних справ","candidate":"","office_hidden":false,"region":"Загальнодержавний регіон","office":"Вищий спеціалізований суд з розгляду цивільних і кримінальних справ","office_unclear":false,"region_hidden":false},"full_name_suggest":{"output":"Висоцька Валентина Степанівна","input":["Висоцька Валентина Степанівна","Валентина Степанівна Висоцька","Валентина Висоцька"]},"full_name":"Висоцька Валентина Степанівна","addresses":[{"place_city_type_unclear":false,"place_address":"","place_district_hidden":true,"place_city_type":"","place_city_hidden":true,"place_city_type_hidden":true,"place":"","place_district":"","place_unclear":false,"place_city":"","place_city_unclear":false,"place_hidden":true,"place_address_hidden":true}],"patronymic":"Степанівна","last_name_unclear":false,"name_unclear":false},"source":"VULYK","estate":{"23":[{"space_hidden":false,"costs":"","costs_comment":"","address_hidden":false,"region_hidden":true,"space_comment":"","space_unclear":false,"space":"750","address":"","space_comment_unclear":false,"region":"","costs_rent_comment":"","costs_unclear":false,"space_comment_hidden":false,"space_units":"м²","costs_rent":""}],"25":[{"space_unclear":false,"costs":"","costs_comment":"","address_hidden":false,"region_hidden":true,"space_comment":"","space_hidden":false,"space":"22.4","address":"","region":"","costs_rent_comment":"","space_comment_unclear":false,"space_comment_hidden":false,"space_units":"м²","costs_rent":""},{"space_unclear":false,"costs":"","costs_comment":"","address_hidden":false,"region_hidden":false,"space_comment":"","space":"83.1","address":"","region":"","address_unclear":false,"costs_rent_comment":"","space_comment_hidden":false,"space_units":"м²","costs_rent":""}],"29":[{"space_unclear":false,"address_hidden":false,"region_hidden":true,"space_comment":"","space_hidden":false,"space":"629","address":"","region":"","costs_property":"","costs_rent_comment":"","space_units":"м²","costs_property_comment":"","costs_rent":""}],"30":[{"space_hidden":false,"address_hidden":false,"region_hidden":false,"space_comment":"","space":"69.7","address":"","region":"","costs_property":"","costs_rent_comment":"","space_units":"м²","costs_property_comment":"","costs_rent":""}],"31":[{"space_unclear":false,"address_hidden":false,"region_hidden":true,"space_comment":"","space_hidden":false,"space":"22.4","address":"","region":"","costs_property":"","costs_rent_comment":"","space_comment_unclear":false,"space_units":"м²","costs_property_comment":"","costs_rent":""},{"costs_rent":"","region":"","costs_property":"","costs_rent_comment":"","space_comment_unclear":false,"region_hidden":false,"space_comment":"","costs_property_comment":"","space_units":"м²","space":"83.1","address":""}]},"intro":{"declaration_year":"2013","isnotdeclaration":"","declaration_year_unclear":false,"declaration_year_hidden":false}}