{"ft_src":"110000\n3000\nTRUE\nРозділ 2. Відомості про доходи.;Пункт 7. Дохід від викладацької, наукової і творчої діяльності, медичної практики, інструкторської та суддівської практики із спорту.;В декларації записано 2 рядки. Перший в розшифровку доданий.;Другий - Національна школа(?) суддів України, Сума одержаного доходу декларанта - 3661\nFALSE\nFALSE\n2013\n225147\n11417\nНУ ’Одеська юридична академія’;Національна школа суддів України\n236564\nРозділ 2. Відомості про доходи.;Пункт 7. Дохід від викладацької, наукової і творчої діяльності, медичної практики, інструкторської та суддівської практики із спорту.;В декларації записано 2 рядки. Перший в розшифровку доданий.;Другий - Національна школа(?) суддів України, Сума одержаного доходу декларанта - 3661\nFALSE\nTRUE\n110000\n3000\nСуддя апеляційного суду Одеської області\nГрідіна\nГрідіна Наталія Вікторівна\nНаталія Вікторівна Грідіна\nНаталія Грідіна\nГрідіна Наталія Вікторівна\nНаталія\nГрідіна Наталія Вікторівна\nЗагальний апеляційний суд\nСуддя\nОдеська область\nВікторівна\nНУ ’Одеська юридична академія’;Національна школа суддів України\n11417\n225147\n236564\n2013\nFALSE\nГрідіна\nВікторівна\nГрідіна Наталія Вікторівна\nНаталія Вікторівна Грідіна\nНаталія Грідіна\nГрідіна Наталія Вікторівна\nНаталія\nСуддя апеляційного суду Одеської області\nСуддя\nОдеська область\nЗагальний апеляційний суд\nГрідіна Наталія Вікторівна","estate":{"23":[{"costs":"110000","address":"","space_units":"","costs_rent_comment":"","space":"3000","costs_comment":"","costs_rent":"","space_comment":"","region":"","location_raw":"приховано"},{"costs":"","address":"","space_units":"","costs_rent_comment":"","space":"","costs_comment":"","costs_rent":"","space_comment":"","region":"","location_raw":""},{"costs":"","address":"","space_units":"","costs_rent_comment":"","space":"","costs_comment":"","costs_rent":"","space_comment":"","region":"","location_raw":""}]},"id":"1501","income":{"5":{"family_comment":"","value":"236564","family":"0","comment":""},"6":{"family_comment":"","value":"225147","family":"0","comment":""},"7":{"family":"0","family_comment":"","value":"11417","comment":"","source_name":"НУ ’Одеська юридична академія’;Національна школа суддів України"},"8":{"family_comment":"","value":"0","family":"0","comment":""},"9":{"family_comment":"","value":"0","family":"0","comment":""},"10":{"family_comment":"","value":"0","family":"0","comment":""},"11":{"family_comment":"","value":"0","family":"0","comment":""},"12":{"family_comment":"","value":"0","family":"0","comment":""},"13":{"family_comment":"","value":"0","family":"0","comment":""},"14":{"family_comment":"","value":"0","family":"0","comment":""},"15":{"family_comment":"","value":"0","family":"0","comment":""},"16":{"family_comment":"","value":"0","family":"0","comment":""},"17":{"family_comment":"","value":"0","family":"0","comment":""},"18":{"family_comment":"","value":"0","family":"0","comment":""},"19":{"family_comment":"","value":"0","family":"0","comment":""},"20":{"family_comment":"","value":"0","family":"0","comment":""},"21":[{"country_comment":"","uah_equal":"0","country":"0","cur":"0"},{"country_comment":"","uah_equal":"0","country":"0","cur":"0"},{"country_comment":"","uah_equal":"0","country":"0","cur":"0"},{"country_comment":"","uah_equal":"0","country":"0","cur":"0"},{"country_comment":"","uah_equal":"0","country":"0","cur":"0"}],"22":[{"country_comment":"","uah_equal":"0","country":"0","cur":"0"},{"country_comment":"","uah_equal":"0","country":"0","cur":"0"},{"country_comment":"","uah_equal":"0","country":"0","cur":"0"},{"country_comment":"","uah_equal":"0","country":"0","cur":"0"},{"country_comment":"","uah_equal":"0","country":"0","cur":"0"}]},"banks":{"45":[{"sum_units":"UAH","sum_comment":"","sum_foreign_units":"","sum":"","sum_foreign_comment":"","sum_foreign":""},{"sum_units":"USD","sum_comment":"","sum_foreign_units":"","sum":"","sum_foreign_comment":"","sum_foreign":""},{"sum_units":"EUR","sum_comment":"","sum_foreign_units":"","sum":"","sum_foreign_comment":"","sum_foreign":""}],"46":[{"sum_units":"UAH","sum_comment":"","sum_foreign_units":"","sum":"","sum_foreign_comment":"","sum_foreign":""},{"sum_units":"USD","sum_comment":"","sum_foreign_units":"","sum":"","sum_foreign_comment":"","sum_foreign":""},{"sum_units":"EUR","sum_comment":"","sum_foreign_units":"","sum":"","sum_foreign_comment":"","sum_foreign":""}],"47":[{"sum_units":"","sum_comment":"","sum_foreign_units":"","sum":"","sum_foreign_comment":"","sum_foreign":""}],"48":[{"sum_units":"","sum_comment":"","sum_foreign_units":"","sum":"","sum_foreign_comment":"","sum_foreign":""}],"49":[{"sum_units":"","sum_comment":"","sum_foreign_units":"","sum":"","sum_foreign_comment":"","sum_foreign":""}],"50":[{"sum_units":"","sum_comment":"","sum_foreign_units":"","sum":"","sum_foreign_comment":"","sum_foreign":""}],"51":[{"sum_units":"UAH","sum_comment":"","sum_foreign_units":"","sum":"","sum_foreign_comment":"","sum_foreign":""},{"sum_units":"USD","sum_comment":"","sum_foreign_units":"","sum":"","sum_foreign_comment":"","sum_foreign":""},{"sum_units":"EUR","sum_comment":"","sum_foreign_units":"","sum":"","sum_foreign_comment":"","sum_foreign":""}],"52":[{"sum_units":"","sum_comment":"","sum_foreign_units":"","sum":"","sum_foreign_comment":"","sum_foreign":""}],"53":[{"sum_units":"","sum_comment":"","sum_foreign_units":"","sum":"","sum_foreign_comment":"","sum_foreign":""}]},"declaration":{"notfull_lostpages":"","additional_info_text":"Розділ 2. Відомості про доходи.;Пункт 7. Дохід від викладацької, наукової і творчої діяльності, медичної практики, інструкторської та суддівської практики із спорту.;В декларації записано 2 рядки. Перший в розшифровку доданий.;Другий - Національна школа(?) суддів України, Сума одержаного доходу декларанта - 3661","additional_info":"TRUE","notfull":"FALSE","url":"http://static.declarations.com.ua/declarations/sudy/apeliatsiini_sudy_oblastei__m.kyieva/odeska/gridina_dec.pdf","needs_scancopy_check":false},"general":{"family_raw":"","name":"Наталія","full_name_suggest":{"input":["Грідіна Наталія Вікторівна","Наталія Вікторівна Грідіна","Наталія Грідіна"],"output":"Грідіна Наталія Вікторівна"},"post_raw":"Суддя апеляційного суду Одеської області","name_unclear":false,"patronymic":"Вікторівна","patronymic_unclear":false,"last_name_hidden":false,"patronymic_hidden":false,"inn":"","addresses_raw_hidden":true,"last_name":"Грідіна","full_name":"Грідіна Наталія Вікторівна","post":{"office":"Загальний апеляційний суд","region":"Одеська область","post":"Суддя"},"addresses_raw":"приховано","name_hidden":false,"last_name_unclear":false},"liabilities":{"54":{"sum_comment":"","sum_foreign_comment":"","sum_foreign":"","sum":""},"55":{"sum_units":"","sum_comment":"","sum_foreign_units":"","sum":"","sum_foreign_comment":"","sum_foreign":""},"56":{"sum_comment":"","sum_foreign_comment":"","sum_foreign":"","sum":""},"57":{"sum_comment":"","sum_foreign_comment":"","sum_foreign":"","sum":""},"58":{"sum_comment":"","sum_foreign_comment":"","sum_foreign":"","sum":""},"59":{"sum_comment":"","sum_foreign_comment":"","sum_foreign":"","sum":""},"60":{"sum_comment":"","sum_foreign_comment":"","sum_foreign":"","sum":""},"61":{"sum_units":"","sum_comment":"","sum_foreign_units":"","sum":"","sum_foreign_comment":"","sum_foreign":""},"62":{"sum_comment":"","sum_foreign_comment":"","sum_foreign":"","sum":""},"63":{"sum_comment":"","sum_units":"","sum_foreign":"","sum":"","sum_foreign_comment":""},"64":{"sum_comment":"","sum_units":"","sum_foreign":"","sum":"","sum_foreign_comment":""}},"intro":{"isnotdeclaration":"FALSE","declaration_year":"2013"}}