{"ft_src":"Toyota,Yaris\n2007\nГАЗ,21\n1968\nMitsubishi,Pajero\n2010\n979\n900\n900\n81,3\n80,5\n204,7\n8500\n557\n80,5\n28663,49\n238618,42\nFALSE\nFALSE\nFALSE\n2013\n254513,55\n6820,8\n50000\n24\n24\n452350,56\n35508,29\n5000\n18815,77\n2654,32\n123997,24\n26009,17\nToyota,Yaris\n2007\nГАЗ,21\n1968\nMitsubishi,Pajero\n2010\nFALSE\nFALSE\n204,7\n80,5\n8500\n557\n979\n900\n900\n81,3\n80,5\nСуддя апедяційного суду Луганської області\nЧоловік - Луганський В.І, дата народження - приховано, інші дані - приховано;Донька - Луганська В.В., дата народження - приховано, інші дані - приховано;Донька - Луганська В.В., дата народження - приховано, інші дані - приховано\nЛуганська\nЛуганська Валентина Миколаївна\nВалентина Миколаївна Луганська\nВалентина Луганська\nЛуганська Валентина Миколаївна\nВалентина\nЛуганська Валентина Миколаївна\nЗагальний апеляційний суд\nСуддя\nЛуганська область\nМиколаївна\n3000\n30000\n320\n6820,8\n254513,55\n26009,17\n123997,24\n50000\n35508,29\n452350,56\n5000\n24\n24\n2654,32\n18815,77\n238618,42\n28663,49\n2013\nFALSE\n3000\n30000\n320\nЛуганська\nМиколаївна\nЧоловік - Луганський В.І, дата народження - приховано, інші дані - приховано;Донька - Луганська В.В., дата народження - приховано, інші дані - приховано;Донька - Луганська В.В., дата народження - приховано, інші дані - приховано\nЛуганська Валентина Миколаївна\nВалентина Миколаївна Луганська\nВалентина Луганська\nЛуганська Валентина Миколаївна\nВалентина\nСуддя апедяційного суду Луганської області\nСуддя\nЛуганська область\nЗагальний апеляційний суд\nЛуганська Валентина Миколаївна","estate":{"23":[{"costs":"","address":"","space_units":"","costs_rent_comment":"","space":"8500","costs_comment":"","costs_rent":"","space_comment":"","region":"","location_raw":"приховано"},{"costs":"","address":"","space_units":"","costs_rent_comment":"","space":"557","costs_comment":"","costs_rent":"","space_comment":"","region":"","location_raw":""},{"costs":"","address":"","space_units":"","costs_rent_comment":"","space":"","costs_comment":"","costs_rent":"","space_comment":"","region":"","location_raw":""}],"24":[{"costs":"","address":"","space_units":"","costs_rent_comment":"","space":"81,3","costs_comment":"","costs_rent":"","space_comment":"","region":"","location_raw":"приховано"}],"25":[{"costs":"","address":"","space_units":"","costs_rent_comment":"","space":"80,5","costs_comment":"","costs_rent":"","space_comment":"","region":"","location_raw":"приховано"}],"29":[{"costs_property_comment":"","address":"","space_units":"","costs_rent_comment":"","space":"979","space_comment":"","costs_property":"","region":"","location_raw":"приховано","costs_rent":""},{"costs_property_comment":"","address":"","space_units":"","costs_rent_comment":"","space":"900","space_comment":"","costs_property":"","region":"","location_raw":"приховано","costs_rent":""},{"costs_property_comment":"","address":"","space_units":"","costs_rent_comment":"","space":"900","space_comment":"","costs_property":"","region":"","location_raw":"приховано","costs_rent":""}],"30":[{"costs_property_comment":"","address":"","space_units":"","costs_rent_comment":"","space":"204,7","space_comment":"","costs_property":"","region":"","location_raw":"","costs_rent":""},{"costs_property_comment":"","address":"","space_units":"","costs_rent_comment":"","space":"","space_comment":"","costs_property":"","region":"","location_raw":"приховано","costs_rent":""}],"31":[{"costs_property_comment":"","address":"","space_units":"","costs_rent_comment":"","space":"80,5","space_comment":"","costs_property":"","region":"","location_raw":"приховано","costs_rent":""}]},"vehicle":{"35":[{"sum_comment":"","brand_info":"","sum":"","sum_rent_comment":"","year":"2007","brand":"Toyota,Yaris","sum_rent":"","brand_hidden":false}],"40":[{"sum_comment":"","brand_info":"","sum":"","sum_rent_comment":"","year":"1968","brand":"ГАЗ,21","sum_rent":"","brand_hidden":false},{"sum_comment":"","brand_info":"","sum":"","sum_rent_comment":"","year":"2010","brand":"Mitsubishi,Pajero","sum_rent":"","brand_hidden":false}]},"id":"174","income":{"5":{"family_comment":"","value":"35508,29","family":"452350,56","comment":""},"6":{"family_comment":"","value":"6820,8","family":"254513,55","comment":""},"7":{"family":"0","family_comment":"","value":"0","comment":"","source_name":"0"},"8":{"family_comment":"","value":"0","family":"0","comment":""},"9":{"family_comment":"","value":"2654,32","family":"18815,77","comment":""},"10":{"family_comment":"","value":"0","family":"0","comment":""},"11":{"family_comment":"","value":"24","family":"24","comment":""},"12":{"family_comment":"","value":"0","family":"0","comment":""},"13":{"family_comment":"","value":"0","family":"0","comment":""},"14":{"family_comment":"","value":"0","family":"0","comment":""},"15":{"family_comment":"","value":"0","family":"50000","comment":""},"16":{"family_comment":"","value":"0","family":"5000","comment":""},"17":{"family_comment":"","value":"0","family":"0","comment":""},"18":{"family_comment":"","value":"0","family":"0","comment":""},"19":{"family_comment":"","value":"0","family":"0","comment":""},"20":{"family_comment":"","value":"26009,17","family":"123997,24","comment":""},"21":[{"country_comment":"","uah_equal":"0","country":"0","cur":"0"},{"country_comment":"","uah_equal":"0","country":"0","cur":"0"},{"country_comment":"","uah_equal":"0","country":"0","cur":"0"},{"country_comment":"","uah_equal":"0","country":"0","cur":"0"},{"country_comment":"","uah_equal":"0","country":"0","cur":"0"}],"22":[{"country_comment":"","uah_equal":"0","country":"0","cur":"0"},{"country_comment":"","uah_equal":"0","country":"0","cur":"0"},{"country_comment":"","uah_equal":"0","country":"0","cur":"0"},{"country_comment":"","uah_equal":"0","country":"0","cur":"0"},{"country_comment":"","uah_equal":"0","country":"0","cur":"0"}]},"banks":{"45":[{"sum_units":"UAH","sum_comment":"","sum_foreign_units":"","sum":"","sum_foreign_comment":"","sum_foreign":""},{"sum_units":"USD","sum_comment":"","sum_foreign_units":"","sum":"","sum_foreign_comment":"","sum_foreign":""},{"sum_units":"EUR","sum_comment":"","sum_foreign_units":"","sum":"","sum_foreign_comment":"","sum_foreign":""}],"46":[{"sum_units":"UAH","sum_comment":"","sum_foreign_units":"","sum":"28663,49","sum_foreign_comment":"","sum_foreign":""},{"sum_units":"USD","sum_comment":"","sum_foreign_units":"","sum":"","sum_foreign_comment":"","sum_foreign":""},{"sum_units":"EUR","sum_comment":"","sum_foreign_units":"","sum":"","sum_foreign_comment":"","sum_foreign":""}],"47":[{"sum_units":"","sum_comment":"","sum_foreign_units":"","sum":"","sum_foreign_comment":"","sum_foreign":""}],"48":[{"sum_units":"","sum_comment":"","sum_foreign_units":"","sum":"","sum_foreign_comment":"","sum_foreign":""}],"49":[{"sum_units":"","sum_comment":"","sum_foreign_units":"","sum":"","sum_foreign_comment":"","sum_foreign":""}],"50":[{"sum_units":"","sum_comment":"","sum_foreign_units":"","sum":"","sum_foreign_comment":"","sum_foreign":""}],"51":[{"sum_units":"UAH","sum_comment":"","sum_foreign_units":"","sum":"238618,42","sum_foreign_comment":"","sum_foreign":""},{"sum_units":"USD","sum_comment":"","sum_foreign_units":"","sum":"","sum_foreign_comment":"","sum_foreign":""},{"sum_units":"EUR","sum_comment":"","sum_foreign_units":"","sum":"","sum_foreign_comment":"","sum_foreign":""}],"52":[{"sum_units":"","sum_comment":"","sum_foreign_units":"","sum":"","sum_foreign_comment":"","sum_foreign":""}],"53":[{"sum_units":"","sum_comment":"","sum_foreign_units":"","sum":"","sum_foreign_comment":"","sum_foreign":""}]},"declaration":{"notfull_lostpages":"","additional_info_text":"","additional_info":"FALSE","notfull":"FALSE","url":"http://static.declarations.com.ua/declarations/sudy/apeliatsiini_sudy_oblastei__m.kyieva/luhanska_(m.sievierodonetsk)/luhanska.pdf","needs_scancopy_check":false},"general":{"family_raw":"Чоловік - Луганський В.І, дата народження - приховано, інші дані - приховано;Донька - Луганська В.В., дата народження - приховано, інші дані - приховано;Донька - Луганська В.В., дата народження - приховано, інші дані - приховано","name":"Валентина","full_name_suggest":{"input":["Луганська Валентина Миколаївна","Валентина Миколаївна Луганська","Валентина Луганська"],"output":"Луганська Валентина Миколаївна"},"post_raw":"Суддя апедяційного суду Луганської області","name_unclear":false,"patronymic":"Миколаївна","patronymic_unclear":false,"last_name_hidden":false,"patronymic_hidden":false,"inn":"","addresses_raw_hidden":true,"last_name":"Луганська","full_name":"Луганська Валентина Миколаївна","post":{"office":"Загальний апеляційний суд","region":"Луганська область","post":"Суддя"},"addresses_raw":"приховано","name_hidden":false,"last_name_unclear":false},"liabilities":{"54":{"sum_comment":"","sum_foreign_comment":"","sum_foreign":"","sum":"320"},"55":{"sum_units":"","sum_comment":"","sum_foreign_units":"","sum":"","sum_foreign_comment":"","sum_foreign":""},"56":{"sum_comment":"","sum_foreign_comment":"","sum_foreign":"","sum":"3000"},"57":{"sum_comment":"","sum_foreign_comment":"","sum_foreign":"","sum":""},"58":{"sum_comment":"","sum_foreign_comment":"","sum_foreign":"","sum":""},"59":{"sum_comment":"","sum_foreign_comment":"","sum_foreign":"","sum":""},"60":{"sum_comment":"","sum_foreign_comment":"","sum_foreign":"","sum":""},"61":{"sum_units":"","sum_comment":"","sum_foreign_units":"","sum":"","sum_foreign_comment":"","sum_foreign":""},"62":{"sum_comment":"","sum_foreign_comment":"","sum_foreign":"","sum":"30000"},"63":{"sum_comment":"","sum_units":"","sum_foreign":"","sum":"","sum_foreign_comment":""},"64":{"sum_comment":"","sum_units":"","sum_foreign":"","sum":"","sum_foreign_comment":""}},"intro":{"isnotdeclaration":"FALSE","declaration_year":"2013"}}