{"income":{"5":{"family_comment":"","value":"396643","value_unclear":false,"family":"21905","comment":""},"6":{"family_comment":"","value":"380643","value_unclear":false,"family":"21905","comment":""},"7":{"source_name_unclear":false,"value":"1089","family_hidden":false,"value_hidden":false,"family_comment":"","source_name":"ТОВ 'ДК 'Управління знаннями', Національна школа суддів України","family":"","comment":"","source_name_hidden":false},"8":{"value":"","family_hidden":false,"value_hidden":false,"family_comment":"","family":"","comment":""},"9":{"value":"","value_unclear":false,"value_hidden":false,"family_comment":"","comment_unclear":false,"comment":"","family":""},"10":{"value":"14911","family_hidden":false,"value_hidden":false,"family_comment":"","family":"","comment":""},"11":{"value":"","family_hidden":false,"value_hidden":false,"family_comment":"","family":"","comment":""},"12":{"value":"","family_hidden":false,"value_hidden":false,"family_comment":"","family":"","comment":""},"13":{"value":"","family_hidden":false,"value_hidden":false,"family_comment":"","family":"","comment":""},"14":{"value":"","family_hidden":false,"value_hidden":false,"family_comment":"","family":"","comment":""},"15":{"value":"","family_hidden":false,"value_hidden":false,"family_comment":"","family":"","comment":""},"16":{"value":"","family_hidden":false,"value_hidden":false,"family_comment":"","family":"","comment":""},"17":{"value":"","family_hidden":false,"value_hidden":false,"family_comment":"","family":"","comment":""},"18":{"value":"","comment_unclear":false,"family_hidden":false,"value_hidden":false,"family_comment":"","family":"","comment":""},"19":{"value":"","family_hidden":false,"value_hidden":false,"family_comment":"","family":"","comment":""},"20":{"value":"","value_unclear":false,"family_hidden":false,"value_hidden":false,"family_comment":"","comment_unclear":false,"comment":"","family":""}},"id":"193","declaration":{"additional_info_text":"","notfull_lostpages":"","date":"2014-03-31T00:00:00","notfull":"","additional_info":"","url":"http://static.declarations.com.ua/declarations/chosen_ones/judges_batch/20_husak_mykola_borysovych.pdf"},"liabilities":{"54":{"sum_foreign_comment":"","sum_foreign_hidden":false,"sum_comment":"","sum_hidden":false,"sum_foreign_comment_unclear":false,"sum_comment_hidden":false,"sum":"","sum_foreign":""},"55":{"sum_foreign_comment":"","sum":"","sum_hidden":false,"sum_comment":"","sum_foreign":""},"56":{"sum_foreign_comment":"","sum":"9800","sum_comment":"","sum_foreign":""},"57":{"sum_foreign_comment":"","sum_foreign_hidden":false,"sum_comment":"","sum_hidden":false,"sum_comment_hidden":false,"sum":"","sum_foreign":""},"58":{"sum_foreign_comment":"","sum":"","sum_comment":"","sum_hidden":false,"sum_comment_hidden":false,"sum_foreign":""},"59":{"sum_foreign_comment":"","sum_foreign_hidden":false,"sum_comment":"","sum_hidden":false,"sum":"","sum_foreign":""},"60":{"sum_foreign_comment":"","sum":"","sum_comment":"","sum_comment_unclear":false,"sum_hidden":false,"sum_comment_hidden":false,"sum_foreign":""},"61":{"sum_foreign_comment":"","sum":"","sum_hidden":false,"sum_comment":"","sum_foreign":""},"62":{"sum_foreign_comment":"","sum_foreign_hidden":false,"sum_comment":"","sum_comment_hidden":false,"sum_unclear":false,"sum":"3100","sum_foreign":""},"63":{"sum_foreign_comment":"","sum_foreign_hidden":false,"sum_comment":"","sum_hidden":false,"sum_comment_hidden":false,"sum":"","sum_foreign":""},"64":{"sum_foreign_comment":"","sum":"","sum_comment":"","sum_hidden":false,"sum_comment_hidden":false,"sum_foreign":""}},"ft_src":"3100\n9800\nсуддя верховного суду україни\nЗагальнодержавний регіон\nВерховний суд\nМикола\nГусак С. В\nПодружжя\nБорисович\nГусак Микола Борисович\nМикола Борисович Гусак\nМикола Гусак\nГусак Микола Борисович\nГусак Микола Борисович\nГусак\n14911\n21905\n396643\n1089\nТОВ 'ДК 'Управління знаннями', Національна школа суддів України\n21905\n380643\nприватизована\n1700\n42\nприватизована\n90\n2013\n21905\n380643\n14911\nТОВ 'ДК 'Управління знаннями', Національна школа суддів України\n1089\n21905\n396643\n1089\nТОВ 'ДК 'Управління знаннями', Національна школа суддів України\n380643\n21905\n396643\n21905\n14911\nГусак Микола Борисович\nМикола Борисович Гусак\nМикола Гусак\nГусак Микола Борисович\nГусак Микола Борисович\nПодружжя\nГусак С. В\nМикола\nБорисович\nсуддя верховного суду україни\nВерховний суд\nЗагальнодержавний регіон\nГусак\n9800\n3100\n1700\nприватизована\n42\n90\nприватизована\n2013\n9800\n3100\nПодружжя\nГусак С. В\nБорисович\nГусак\nМикола\nГусак Микола Борисович\nМикола Борисович Гусак\nМикола Гусак\nГусак Микола Борисович\nЗагальнодержавний регіон\nВерховний суд\nсуддя верховного суду україни\nГусак Микола Борисович\nприватизована\n90\n1700\nприватизована\n42\n2013","general":{"inn":"","name":"Микола","inn_unclear":false,"family":[{"inn":"","relations":"Подружжя","inn_unclear":false,"relations_hidden":false,"inn_hidden":false,"relations_other":"","name_hidden":false,"family_name":"Гусак С. В","name_unclear":false}],"inn_hidden":false,"family_raw":"","last_name":"Гусак","post":{"post":"суддя верховного суду україни","region":"Загальнодержавний регіон","candidate":"","office_hidden":false,"post_hidden":false,"office":"Верховний суд","region_hidden":false},"full_name_suggest":{"output":"Гусак Микола Борисович","input":["Гусак Микола Борисович","Микола Борисович Гусак","Микола Гусак"]},"full_name":"Гусак Микола Борисович","patronymic":"Борисович","last_name_unclear":false,"name_unclear":false},"source":"VULYK","estate":{"23":[{"region_unclear":false,"space_unclear":false,"costs":"","costs_comment":"приватизована","costs_hidden":false,"address_hidden":false,"region_hidden":false,"space_comment":"","space_hidden":false,"space_units_unclear":false,"address":"","costs_comment_unclear":false,"region":"","address_unclear":false,"space":"1700","costs_rent_hidden":false,"costs_rent_comment_hidden":false,"space_units":"м²","costs_comment_hidden":false,"costs_rent":"","costs_rent_comment":""}],"25":[{"region_unclear":false,"space_unclear":false,"costs":"","costs_comment":"приватизована","costs_hidden":false,"address_hidden":false,"region_hidden":false,"space_comment":"","space":"90","address":"","costs_rent_comment_unclear":false,"region":"","costs_rent_comment":"","costs_rent_hidden":false,"space_comment_unclear":false,"costs_rent_comment_hidden":false,"space_units":"м²","costs_comment_hidden":false,"costs_rent":"","costs_unclear":false}],"27":[{"space_hidden":false,"costs":"","costs_comment":"","costs_hidden":false,"address_hidden":false,"region_hidden":false,"space_comment":"","space_unclear":false,"space":"42","address":"","region":"","costs_rent_comment":"","costs_rent_hidden":false,"costs_rent_comment_hidden":false,"space_units":"м²","costs_comment_hidden":false,"costs_rent":""}]},"intro":{"declaration_year":"2013","isnotdeclaration":"","declaration_year_unclear":false,"declaration_year_hidden":false}}