{"ft_src":"ВАЗ,21093\n1998\n8000\nБула інформація\n30800\nБула інформація\n20\nм. Житомир\n67,53\nБула інформація\n3000\n28,5\n40000\n40000\nTRUE\nп. 23 не вмістилася та не внесена інформація ’місцезнаходження об’єктів (країна, адреса)’:; Житомирська область, Любарський р-н;;п. 25 вмістилася та не внесена інформація ’місцезнаходження об’єктів (країна, адреса)’:;Житомирська область, смт Любар\nFALSE\nFALSE\n2013\n14342\n204871\n23296\n15837\n231507\n3340\n1495\nВАЗ,21093\n1998\n8000\nп. 23 не вмістилася та не внесена інформація ’місцезнаходження об’єктів (країна, адреса)’:; Житомирська область, Любарський р-н;;п. 25 вмістилася та не внесена інформація ’місцезнаходження об’єктів (країна, адреса)’:;Житомирська область, смт Любар\nFALSE\nTRUE\nБула інформація\n30800\nБула інформація\n20\nм. Житомир\n67,53\nБула інформація\n3000\n28,5\nСуддя Житомирського апеляційного адміністративного суду\nДружина Шидловська Є. Г.;син Шидловський О. В.\nЖитомирська\nШидловський\nШидловський Віктор Броніславович\nВіктор Броніславович Шидловський\nВіктор Шидловський\nШидловський Віктор Броніславович\nВіктор\nШидловський Віктор Броніславович\nАпеляційний адміністративний суд\nСуддя\nЖитомирська область\nБроніславович\nЖитомирська обл.\n11000\n6000\n204871\n14342\n1495\n231507\n15837\n23296\n3340\n40000\n40000\n2013\nFALSE\n11000\n6000\nШидловський\nБроніславович\nДружина Шидловська Є. Г.;син Шидловський О. В.\nШидловський Віктор Броніславович\nВіктор Броніславович Шидловський\nВіктор Шидловський\nШидловський Віктор Броніславович\nВіктор\nСуддя Житомирського апеляційного адміністративного суду\nЖитомирська\nСуддя\nЖитомирська область\nАпеляційний адміністративний суд\nШидловський Віктор Броніславович\nЖитомирська обл.","estate":{"23":[{"costs":"","address":"","space_units":"","costs_rent_comment":"","space":"30800","costs_comment":"","costs_rent":"","space_comment":"","region":"","location_raw":"Була інформація"},{"costs":"","address":"","space_units":"","costs_rent_comment":"","space":"","costs_comment":"","costs_rent":"","space_comment":"","region":"","location_raw":""},{"costs":"","address":"","space_units":"","costs_rent_comment":"","space":"","costs_comment":"","costs_rent":"","space_comment":"","region":"","location_raw":""}],"25":[{"costs":"","address":"","space_units":"","costs_rent_comment":"","space":"28,5","costs_comment":"","costs_rent":"3000","space_comment":"","region":"","location_raw":"Була інформація"}],"27":[{"costs":"","address":"","space_units":"","costs_rent_comment":"","space":"20","costs_comment":"","costs_rent":"","space_comment":"","region":"","location_raw":"Була інформація"}],"31":[{"costs_property_comment":"","address":"","space_units":"","costs_rent_comment":"","space":"67,53","space_comment":"","costs_property":"","region":"","location_raw":"м. Житомир","costs_rent":""}]},"vehicle":{"35":[{"sum_comment":"","brand_info":"","sum":"","sum_rent_comment":"","year":"1998","brand":"ВАЗ,21093","sum_rent":"8000","brand_hidden":false}]},"id":"2867","income":{"5":{"family_comment":"","value":"231507","family":"15837","comment":""},"6":{"family_comment":"","value":"204871","family":"14342","comment":""},"7":{"family":"0","family_comment":"","value":"0","comment":"","source_name":"0"},"8":{"family_comment":"","value":"0","family":"0","comment":""},"9":{"family_comment":"","value":"0","family":"0","comment":""},"10":{"family_comment":"","value":"23296","family":"0","comment":""},"11":{"family_comment":"","value":"0","family":"0","comment":""},"12":{"family_comment":"","value":"0","family":"1495","comment":""},"13":{"family_comment":"","value":"0","family":"0","comment":""},"14":{"family_comment":"","value":"0","family":"0","comment":""},"15":{"family_comment":"","value":"0","family":"0","comment":""},"16":{"family_comment":"","value":"0","family":"0","comment":""},"17":{"family_comment":"","value":"0","family":"0","comment":""},"18":{"family_comment":"","value":"0","family":"0","comment":""},"19":{"family_comment":"","value":"3340","family":"0","comment":""},"20":{"family_comment":"","value":"0","family":"0","comment":""},"21":[{"country_comment":"","uah_equal":"0","country":"0","cur":"0"},{"country_comment":"","uah_equal":"0","country":"0","cur":"0"},{"country_comment":"","uah_equal":"0","country":"0","cur":"0"},{"country_comment":"","uah_equal":"0","country":"0","cur":"0"},{"country_comment":"","uah_equal":"0","country":"0","cur":"0"}],"22":[{"country_comment":"","uah_equal":"0","country":"0","cur":"0"},{"country_comment":"","uah_equal":"0","country":"0","cur":"0"},{"country_comment":"","uah_equal":"0","country":"0","cur":"0"},{"country_comment":"","uah_equal":"0","country":"0","cur":"0"},{"country_comment":"","uah_equal":"0","country":"0","cur":"0"}]},"banks":{"45":[{"sum_units":"UAH","sum_comment":"","sum_foreign_units":"","sum":"40000","sum_foreign_comment":"","sum_foreign":""},{"sum_units":"USD","sum_comment":"","sum_foreign_units":"","sum":"","sum_foreign_comment":"","sum_foreign":""},{"sum_units":"EUR","sum_comment":"","sum_foreign_units":"","sum":"","sum_foreign_comment":"","sum_foreign":""}],"46":[{"sum_units":"UAH","sum_comment":"","sum_foreign_units":"","sum":"40000","sum_foreign_comment":"","sum_foreign":""},{"sum_units":"USD","sum_comment":"","sum_foreign_units":"","sum":"","sum_foreign_comment":"","sum_foreign":""},{"sum_units":"EUR","sum_comment":"","sum_foreign_units":"","sum":"","sum_foreign_comment":"","sum_foreign":""}],"47":[{"sum_units":"","sum_comment":"","sum_foreign_units":"","sum":"","sum_foreign_comment":"","sum_foreign":""}],"48":[{"sum_units":"","sum_comment":"","sum_foreign_units":"","sum":"","sum_foreign_comment":"","sum_foreign":""}],"49":[{"sum_units":"","sum_comment":"","sum_foreign_units":"","sum":"","sum_foreign_comment":"","sum_foreign":""}],"50":[{"sum_units":"","sum_comment":"","sum_foreign_units":"","sum":"","sum_foreign_comment":"","sum_foreign":""}],"51":[{"sum_units":"UAH","sum_comment":"","sum_foreign_units":"","sum":"","sum_foreign_comment":"","sum_foreign":""},{"sum_units":"USD","sum_comment":"","sum_foreign_units":"","sum":"","sum_foreign_comment":"","sum_foreign":""},{"sum_units":"EUR","sum_comment":"","sum_foreign_units":"","sum":"","sum_foreign_comment":"","sum_foreign":""}],"52":[{"sum_units":"","sum_comment":"","sum_foreign_units":"","sum":"","sum_foreign_comment":"","sum_foreign":""}],"53":[{"sum_units":"","sum_comment":"","sum_foreign_units":"","sum":"","sum_foreign_comment":"","sum_foreign":""}]},"declaration":{"notfull_lostpages":"","additional_info_text":"п. 23 не вмістилася та не внесена інформація ’місцезнаходження об’єктів (країна, адреса)’:; Житомирська область, Любарський р-н;;п. 25 вмістилася та не внесена інформація ’місцезнаходження об’єктів (країна, адреса)’:;Житомирська область, смт Любар","additional_info":"TRUE","notfull":"FALSE","url":"http://static.declarations.com.ua/declarations/sudy/apeliatsiini_administratyvni_sudy/zhytomyrskyi/shidlovskii_declaration.pdf","needs_scancopy_check":false},"general":{"family_raw":"Дружина Шидловська Є. Г.;син Шидловський О. В.","name":"Віктор","full_name_suggest":{"input":["Шидловський Віктор Броніславович","Віктор Броніславович Шидловський","Віктор Шидловський"],"output":"Шидловський Віктор Броніславович"},"post_raw":"Суддя Житомирського апеляційного адміністративного суду","name_unclear":false,"patronymic":"Броніславович","patronymic_unclear":false,"last_name_hidden":false,"patronymic_hidden":false,"inn":"","addresses_raw_hidden":true,"last_name":"Шидловський","full_name":"Шидловський Віктор Броніславович","post":{"office":"Апеляційний адміністративний суд","region":"Житомирська область","post":"Суддя"},"addresses":[{"place_district":"","place_city_type":"","place_address_type":"","place":"Житомирська","place_address":"","place_city":""}],"name_hidden":false,"last_name_unclear":false,"addresses_raw":"Житомирська обл."},"liabilities":{"54":{"sum_comment":"","sum_foreign_comment":"","sum_foreign":"","sum":""},"55":{"sum_units":"","sum_comment":"","sum_foreign_units":"","sum":"","sum_foreign_comment":"","sum_foreign":""},"56":{"sum_comment":"","sum_foreign_comment":"","sum_foreign":"","sum":"11000"},"57":{"sum_comment":"","sum_foreign_comment":"","sum_foreign":"","sum":""},"58":{"sum_comment":"","sum_foreign_comment":"","sum_foreign":"","sum":""},"59":{"sum_comment":"","sum_foreign_comment":"","sum_foreign":"","sum":""},"60":{"sum_comment":"","sum_foreign_comment":"","sum_foreign":"","sum":""},"61":{"sum_units":"","sum_comment":"","sum_foreign_units":"","sum":"","sum_foreign_comment":"","sum_foreign":""},"62":{"sum_comment":"","sum_foreign_comment":"","sum_foreign":"","sum":"6000"},"63":{"sum_comment":"","sum_units":"","sum_foreign":"","sum":"","sum_foreign_comment":""},"64":{"sum_comment":"","sum_units":"","sum_foreign":"","sum":"","sum_foreign_comment":""}},"intro":{"isnotdeclaration":"FALSE","declaration_year":"2013"}}