{"income":{"5":{"family_comment":"","value":"663369","value_unclear":false,"family":"15600","comment":""},"6":{"family_comment":"","value":"316605","value_unclear":false,"family":"15600","comment":""},"7":{"source_name_unclear":false,"value":"","family_hidden":false,"value_hidden":false,"family_comment":"","source_name":"","family":"","comment":"","source_name_hidden":false},"8":{"value":"","family_hidden":false,"value_hidden":false,"family_comment":"","family":"","comment":""},"9":{"value":"","value_unclear":false,"value_hidden":false,"family_comment":"","comment_unclear":false,"comment":"","family":""},"10":{"value":"13764","family_hidden":false,"value_hidden":false,"family_comment":"","family":"","comment":""},"11":{"value":"","family_hidden":false,"value_hidden":false,"family_comment":"","family":"","comment":""},"12":{"value":"","family_hidden":false,"value_hidden":false,"family_comment":"","family":"","comment":""},"13":{"value":"","family_hidden":false,"value_hidden":false,"family_comment":"","family":"","comment":""},"14":{"value":"","family_hidden":false,"value_hidden":false,"family_comment":"","family":"","comment":""},"15":{"value":"","family_hidden":false,"value_hidden":false,"family_comment":"","family":"","comment":""},"16":{"value":"333000","family_hidden":false,"value_hidden":false,"family_comment":"","family":"","comment":""},"17":{"value":"","family_hidden":false,"value_hidden":false,"family_comment":"","family":"","comment":""},"18":{"value":"","comment_unclear":false,"family_hidden":false,"value_hidden":false,"family_comment":"","family":"","comment":""},"19":{"value":"","family_hidden":false,"value_hidden":false,"family_comment":"","family":"","comment":""},"20":{"value":"","value_unclear":false,"family_hidden":false,"value_hidden":false,"family_comment":"","comment_unclear":false,"comment":"","family":""}},"vehicle":{"35":[{"brand_info":"3500","sum_rent_comment":"","sum_rent_hidden":false,"year":"2006","sum_hidden":false,"brand_info_unclear":false,"sum_rent":"","sum":"","brand":"Toyota Avalon","sum_comment":"","brand_unclear":false,"sum_rent_comment_hidden":false,"sum_comment_hidden":true,"sum_unclear":false}],"40":[{"brand_info":"2000 куб.см.","sum":"","brand":"Toyota Rav 4","sum_comment":"","brand_unclear":false,"year":"2011","brand_hidden":false,"brand_info_hidden":false,"brand_info_unclear":false,"sum_rent_comment":"","sum_rent":""}]},"id":"2934","banks":{"45":[{"sum_units":"UAH","sum_foreign":"","sum_hidden":false,"sum":"250000","sum_units_hidden":false,"sum_foreign_comment":"","sum_foreign_hidden":false,"sum_comment":"","sum_foreign_units":"UAH","sum_units_unclear":false,"sum_comment_hidden":false,"sum_unclear":false}],"46":[{"sum_foreign_comment":"","sum":"250000","sum_comment":"","sum_hidden":false,"sum_foreign_units":"UAH","sum_foreign_hidden":false,"sum_units":"UAH","sum_comment_hidden":false,"sum_unclear":false,"sum_foreign":"","sum_units_hidden":false}]},"declaration":{"additional_info_text":"Дек5ларація зроблена вся з шматків - вирізані частини та склеєні в текстовому редакторі - все те що ту не заповнено - взагалі відсутнє в файлі","notfull":"1","additional_info":"1","notfull_lostpages":"","url":"http://static.declarations.com.ua/declarations/chosen_ones/judges_batch/151_saraniuk_vasyl_ivanovych.pdf"},"liabilities":{"54":{"sum_foreign_comment":"","sum_foreign_hidden":false,"sum_comment":"","sum_hidden":false,"sum_foreign_comment_unclear":false,"sum_comment_hidden":false,"sum":"","sum_foreign":""},"55":{"sum_foreign_comment":"","sum":"","sum_hidden":false,"sum_comment":"","sum_foreign":""},"56":{"sum_foreign_comment":"","sum":"","sum_comment":"","sum_foreign":""},"57":{"sum_foreign_comment":"","sum_foreign_hidden":false,"sum_comment":"","sum_hidden":false,"sum_comment_hidden":false,"sum":"","sum_foreign":""},"58":{"sum_foreign_comment":"","sum":"","sum_comment":"","sum_hidden":false,"sum_comment_hidden":false,"sum_foreign":""},"59":{"sum_foreign_comment":"","sum_foreign_hidden":false,"sum_comment":"","sum_hidden":false,"sum":"","sum_foreign":""},"60":{"sum_foreign_comment":"","sum":"7037","sum_comment":"","sum_comment_unclear":false,"sum_hidden":false,"sum_comment_hidden":false,"sum_foreign":""},"61":{"sum_foreign_comment":"","sum":"","sum_hidden":false,"sum_comment":"","sum_foreign":""},"62":{"sum_foreign_comment":"","sum_foreign_hidden":false,"sum_comment":"","sum_comment_hidden":false,"sum_unclear":false,"sum":"","sum_foreign":""},"63":{"sum_foreign_comment":"","sum_foreign_hidden":false,"sum_comment":"","sum_hidden":false,"sum_comment_hidden":false,"sum":"","sum_foreign":""},"64":{"sum_foreign_comment":"","sum":"","sum_comment":"","sum_hidden":false,"sum_comment_hidden":false,"sum_foreign":""}},"ft_src":"7037\n1\n1\nДек5ларація зроблена вся з шматків - вирізані частини та склеєні в текстовому редакторі - все те що ту не заповнено - взагалі відсутнє в файлі\nсуддя вищого господарського суду україни\nЗагальнодержавний регіон\nВищий господарський суд\nВасиль\nСаранюк Т. В\nПодружжя\nІванович\nСаранюк\nСаранюк Василь Іванович\nСаранюк Василь Іванович\nВасиль Іванович Саранюк\nВасиль Саранюк\nСаранюк Василь Іванович\nToyota Avalon\n3500\n2006\nToyota Rav 4\n2000 куб.см.\n2011\n600\n1183\n69\n500\n1037\n919\n69\n250000\n250000\n1\n1\nДек5ларація зроблена вся з шматків - вирізані частини та склеєні в текстовому редакторі - все те що ту не заповнено - взагалі відсутнє в файлі\n2013\n3500\nToyota Avalon\n2006\n2000 куб.см.\n2011\nToyota Rav 4\nДек5ларація зроблена вся з шматків - вирізані частини та склеєні в текстовому редакторі - все те що ту не заповнено - взагалі відсутнє в файлі\n1\n1\n2013\nПодружжя\nСаранюк Т. В\nСаранюк Василь Іванович\nВасиль Іванович Саранюк\nВасиль Саранюк\nСаранюк Василь Іванович\nВасиль\nСаранюк Василь Іванович\nІванович\nсуддя вищого господарського суду україни\nВищий господарський суд\nЗагальнодержавний регіон\nСаранюк\n7037\n316605\n15600\n663369\n15600\n333000\n13764\n600\n1183\n500\n1037\n919\n69\n69\n250000\n250000\n7037\n15600\n316605\n13764\n15600\n663369\n333000\nПодружжя\nСаранюк Т. В\nВасиль\nІванович\nСаранюк\nСаранюк Василь Іванович\nВасиль Іванович Саранюк\nВасиль Саранюк\nСаранюк Василь Іванович\nЗагальнодержавний регіон\nВищий господарський суд\nсуддя вищого господарського суду україни\nСаранюк Василь Іванович\n2006\nToyota Avalon\n3500\nToyota Rav 4\n2000 куб.см.\n2011\n13764\n15600\n663369\n333000\n15600\n316605\n69\n600\n1183\n69\n500\n1037\n919\n250000\n250000\n2013","general":{"inn":"","name":"Василь","inn_unclear":false,"family":[{"inn":"","relations":"Подружжя","inn_unclear":false,"relations_hidden":false,"inn_hidden":true,"relations_other":"","name_hidden":false,"family_name":"Саранюк Т. В","name_unclear":false}],"inn_hidden":true,"family_raw":"","last_name":"Саранюк","post":{"post":"суддя вищого господарського суду україни","region":"Загальнодержавний регіон","candidate":"","office_hidden":false,"post_hidden":false,"office":"Вищий господарський суд","region_hidden":false},"last_name_unclear":false,"full_name":"Саранюк Василь Іванович","addresses":[{"place_city_type_unclear":false,"place_address":"","place_district_hidden":true,"place_city_type":"","place_address_hidden":true,"place_address_unclear":false,"place_city_type_hidden":true,"place":"","place_district":"","place_unclear":false,"place_city":"","place_city_unclear":false,"place_hidden":true,"place_city_hidden":true,"place_district_unclear":false}],"patronymic":"Іванович","full_name_suggest":{"output":"Саранюк Василь Іванович","input":["Саранюк Василь Іванович","Василь Іванович Саранюк","Василь Саранюк"]},"name_unclear":false},"source":"VULYK","estate":{"23":[{"region_unclear":false,"space_unclear":false,"costs":"","costs_comment":"","costs_hidden":false,"address_hidden":true,"region_hidden":true,"space_comment":"","space_hidden":false,"space_units_unclear":false,"address":"","costs_comment_unclear":false,"region":"","address_unclear":false,"space":"600","costs_rent_hidden":false,"costs_rent_comment_hidden":false,"space_units":"м²","costs_comment_hidden":false,"costs_rent":"","costs_rent_comment":""},{"space_unclear":false,"costs":"","costs_comment":"","costs_hidden":false,"address_hidden":true,"region_hidden":true,"space_comment":"","space":"1183","address":"","region":"","costs_rent_comment":"","costs_rent_hidden":false,"space_units":"м²","costs_rent":""}],"24":[{"space_unclear":false,"costs":"","costs_comment":"","costs_hidden":false,"address_hidden":true,"region_hidden":true,"space_comment":"","space_hidden":false,"space":"69","address":"","region":"","costs_rent_comment":"","costs_rent_hidden":false,"costs_rent_comment_hidden":false,"space_units":"м²","costs_comment_hidden":false,"costs_rent":""}],"29":[{"space_unclear":false,"costs_property_hidden":false,"address_hidden":true,"region_hidden":true,"space_comment":"","space_hidden":false,"space":"500","address":"","region":"","costs_property":"","costs_rent_comment":"","costs_rent_hidden":false,"space_comment_hidden":false,"space_units":"м²","costs_property_comment":"","costs_rent":""},{"space_unclear":false,"region_hidden":false,"space_comment":"","space":"1037","address":"","region":"","costs_property":"","costs_rent_comment":"","space_comment_unclear":false,"space_units":"м²","costs_property_comment":"","costs_rent":""},{"space_unclear":false,"region_hidden":false,"space_comment":"","space":"919","address":"","region":"","costs_property":"","costs_rent_comment":"","space_comment_unclear":false,"space_units":"м²","costs_property_comment":"","costs_rent":""}],"30":[{"space_hidden":false,"costs_property_hidden":false,"address_hidden":true,"region_hidden":true,"space_comment":"","space_units_hidden":false,"space_unclear":false,"space":"69","address":"","region":"","costs_property":"","costs_rent_comment":"","costs_rent_hidden":false,"space_comment_unclear":false,"space_units":"м²","costs_property_comment":"","costs_rent":""}]},"intro":{"declaration_year":"2013","isnotdeclaration":"","declaration_year_unclear":false,"declaration_year_hidden":false}}