{"ft_src":"м. Київ\n43\nFALSE\nFALSE\nFALSE\n2013\n62611\n20775\n5727\n89113\nFALSE\nFALSE\nм. Київ\n43\nПровідний спеціаліст відділу податкового законодавства;Управління фінансового законодавства Департаменту цивільного фінансового законодавства та законодавства з питань земельних відносин, категорія 5\nДочка Денисенко С.А.;Дочка Денисенко В.А.\nКиївська\nКиїв\nДенисенко\nДенисенко Наталія Олександрівна\nНаталія Олександрівна Денисенко\nНаталія Денисенко\nДенисенко Наталія Олександрівна\nНаталія\nДенисенко Наталія Олександрівна\nМіністерство юстиції\nПровідний спеціаліст відділу податкового законодавства;Управління фінансового законодавства Департаменту цивільного фінансового законодавства та законодавства з питань земельних відносин, категорія 5\nЗагальнодержавний регіон\nОлександрівна\nм. Київ (мабуть приховано)\n62611\n20775\n89113\n5727\n2013\nFALSE\nДенисенко\nОлександрівна\nДочка Денисенко С.А.;Дочка Денисенко В.А.\nДенисенко Наталія Олександрівна\nНаталія Олександрівна Денисенко\nНаталія Денисенко\nДенисенко Наталія Олександрівна\nНаталія\nПровідний спеціаліст відділу податкового законодавства;Управління фінансового законодавства Департаменту цивільного фінансового законодавства та законодавства з питань земельних відносин, категорія 5\nКиївська\nКиїв\nПровідний спеціаліст відділу податкового законодавства;Управління фінансового законодавства Департаменту цивільного фінансового законодавства та законодавства з питань земельних відносин, категорія 5\nЗагальнодержавний регіон\nМіністерство юстиції\nДенисенко Наталія Олександрівна\nм. Київ (мабуть приховано)","estate":{"23":[{"costs":"","address":"","space_units":"","costs_rent_comment":"","space":"","costs_comment":"","costs_rent":"","space_comment":"","region":"","location_raw":""},{"costs":"","address":"","space_units":"","costs_rent_comment":"","space":"","costs_comment":"","costs_rent":"","space_comment":"","region":"","location_raw":""},{"costs":"","address":"","space_units":"","costs_rent_comment":"","space":"","costs_comment":"","costs_rent":"","space_comment":"","region":"","location_raw":""}],"25":[{"costs":"","address":"","space_units":"","costs_rent_comment":"","space":"43","costs_comment":"","costs_rent":"","space_comment":"","region":"","location_raw":"м. Київ"}]},"id":"3134","income":{"5":{"family_comment":"","value":"89113","family":"0","comment":""},"6":{"family_comment":"","value":"62611","family":"0","comment":""},"7":{"family":"0","family_comment":"","value":"0","comment":"","source_name":"0"},"8":{"family_comment":"","value":"0","family":"0","comment":""},"9":{"family_comment":"","value":"0","family":"0","comment":""},"10":{"family_comment":"","value":"5727","family":"0","comment":""},"11":{"family_comment":"","value":"0","family":"0","comment":""},"12":{"family_comment":"","value":"0","family":"0","comment":""},"13":{"family_comment":"","value":"20775","family":"0","comment":""},"14":{"family_comment":"","value":"0","family":"0","comment":""},"15":{"family_comment":"","value":"0","family":"0","comment":""},"16":{"family_comment":"","value":"0","family":"0","comment":""},"17":{"family_comment":"","value":"0","family":"0","comment":""},"18":{"family_comment":"","value":"0","family":"0","comment":""},"19":{"family_comment":"","value":"0","family":"0","comment":""},"20":{"family_comment":"","value":"0","family":"0","comment":""},"21":[{"country_comment":"","uah_equal":"0","country":"0","cur":"0"},{"country_comment":"","uah_equal":"0","country":"0","cur":"0"},{"country_comment":"","uah_equal":"0","country":"0","cur":"0"},{"country_comment":"","uah_equal":"0","country":"0","cur":"0"},{"country_comment":"","uah_equal":"0","country":"0","cur":"0"}],"22":[{"country_comment":"","uah_equal":"0","country":"0","cur":"0"},{"country_comment":"","uah_equal":"0","country":"0","cur":"0"},{"country_comment":"","uah_equal":"0","country":"0","cur":"0"},{"country_comment":"","uah_equal":"0","country":"0","cur":"0"},{"country_comment":"","uah_equal":"0","country":"0","cur":"0"}]},"banks":{"45":[{"sum_units":"UAH","sum_comment":"","sum_foreign_units":"","sum":"","sum_foreign_comment":"","sum_foreign":""},{"sum_units":"USD","sum_comment":"","sum_foreign_units":"","sum":"","sum_foreign_comment":"","sum_foreign":""},{"sum_units":"EUR","sum_comment":"","sum_foreign_units":"","sum":"","sum_foreign_comment":"","sum_foreign":""}],"46":[{"sum_units":"UAH","sum_comment":"","sum_foreign_units":"","sum":"","sum_foreign_comment":"","sum_foreign":""},{"sum_units":"USD","sum_comment":"","sum_foreign_units":"","sum":"","sum_foreign_comment":"","sum_foreign":""},{"sum_units":"EUR","sum_comment":"","sum_foreign_units":"","sum":"","sum_foreign_comment":"","sum_foreign":""}],"47":[{"sum_units":"","sum_comment":"","sum_foreign_units":"","sum":"","sum_foreign_comment":"","sum_foreign":""}],"48":[{"sum_units":"","sum_comment":"","sum_foreign_units":"","sum":"","sum_foreign_comment":"","sum_foreign":""}],"49":[{"sum_units":"","sum_comment":"","sum_foreign_units":"","sum":"","sum_foreign_comment":"","sum_foreign":""}],"50":[{"sum_units":"","sum_comment":"","sum_foreign_units":"","sum":"","sum_foreign_comment":"","sum_foreign":""}],"51":[{"sum_units":"UAH","sum_comment":"","sum_foreign_units":"","sum":"","sum_foreign_comment":"","sum_foreign":""},{"sum_units":"USD","sum_comment":"","sum_foreign_units":"","sum":"","sum_foreign_comment":"","sum_foreign":""},{"sum_units":"EUR","sum_comment":"","sum_foreign_units":"","sum":"","sum_foreign_comment":"","sum_foreign":""}],"52":[{"sum_units":"","sum_comment":"","sum_foreign_units":"","sum":"","sum_foreign_comment":"","sum_foreign":""}],"53":[{"sum_units":"","sum_comment":"","sum_foreign_units":"","sum":"","sum_foreign_comment":"","sum_foreign":""}]},"declaration":{"notfull_lostpages":"","additional_info_text":"","additional_info":"FALSE","notfull":"FALSE","url":"http://static.declarations.com.ua/lustration/54748d257b524.pdf","needs_scancopy_check":false},"general":{"family_raw":"Дочка Денисенко С.А.;Дочка Денисенко В.А.","name":"Наталія","full_name_suggest":{"input":["Денисенко Наталія Олександрівна","Наталія Олександрівна Денисенко","Наталія Денисенко"],"output":"Денисенко Наталія Олександрівна"},"post_raw":"Провідний спеціаліст відділу податкового законодавства;Управління фінансового законодавства Департаменту цивільного фінансового законодавства та законодавства з питань земельних відносин, категорія 5","name_unclear":false,"patronymic":"Олександрівна","patronymic_unclear":false,"last_name_hidden":false,"patronymic_hidden":false,"inn":"","addresses_raw_hidden":true,"last_name":"Денисенко","full_name":"Денисенко Наталія Олександрівна","post":{"office":"Міністерство юстиції","region":"Загальнодержавний регіон","post":"Провідний спеціаліст відділу податкового законодавства;Управління фінансового законодавства Департаменту цивільного фінансового законодавства та законодавства з питань земельних відносин, категорія 5"},"addresses":[{"place_district":"","place_city_type":"","place_address_type":"","place":"Київська","place_address":"","place_city":"Київ"}],"name_hidden":false,"last_name_unclear":false,"addresses_raw":"м. Київ (мабуть приховано)"},"liabilities":{"54":{"sum_comment":"","sum_foreign_comment":"","sum_foreign":"","sum":""},"55":{"sum_units":"","sum_comment":"","sum_foreign_units":"","sum":"","sum_foreign_comment":"","sum_foreign":""},"56":{"sum_comment":"","sum_foreign_comment":"","sum_foreign":"","sum":""},"57":{"sum_comment":"","sum_foreign_comment":"","sum_foreign":"","sum":""},"58":{"sum_comment":"","sum_foreign_comment":"","sum_foreign":"","sum":""},"59":{"sum_comment":"","sum_foreign_comment":"","sum_foreign":"","sum":""},"60":{"sum_comment":"","sum_foreign_comment":"","sum_foreign":"","sum":""},"61":{"sum_units":"","sum_comment":"","sum_foreign_units":"","sum":"","sum_foreign_comment":"","sum_foreign":""},"62":{"sum_comment":"","sum_foreign_comment":"","sum_foreign":"","sum":""},"63":{"sum_comment":"","sum_units":"","sum_foreign":"","sum":"","sum_foreign_comment":""},"64":{"sum_comment":"","sum_units":"","sum_foreign":"","sum":"","sum_foreign_comment":""}},"intro":{"isnotdeclaration":"FALSE","declaration_year":"2013"}}