{"income":{"5":{"value":"378126.66","family_comment":"","value_unclear":false,"value_hidden":false,"family_unclear":false,"family":"11424","comment":""},"6":{"value":"378126.66","family_hidden":false,"value_hidden":false,"family_comment":"","family_comment_hidden":false,"comment":"","family":"11424"},"7":{"value":"","value_unclear":true,"family_hidden":false,"value_hidden":false,"family_comment":"","source_name":"","family":"","comment":"","source_name_hidden":false},"8":{"value":"","comment_hidden":false,"family_hidden":false,"value_hidden":false,"family_comment":"","family":"","comment":""},"9":{"value":"","family_comment":"","comment_hidden":false,"family_hidden":false,"value_hidden":false,"family_unclear":false,"family":"","comment":""},"10":{"value":"","comment_hidden":false,"family_hidden":false,"value_hidden":false,"family_comment":"","family":"","comment":""},"11":{"value":"","value_unclear":false,"comment_hidden":false,"family_hidden":false,"value_hidden":false,"family_comment":"","family":"","comment":""},"12":{"value":"","comment_hidden":false,"family_hidden":false,"value_hidden":false,"family_comment":"","family":"","comment":""},"13":{"value":"","comment_hidden":false,"family_hidden":false,"value_hidden":false,"family_comment":"","family":"","comment":""},"14":{"value":"","comment_hidden":false,"family_hidden":false,"value_hidden":false,"family_comment":"","family":"","comment":""},"15":{"value":"","comment_hidden":false,"family_hidden":false,"value_hidden":false,"family_comment":"","family":"","comment":""},"16":{"value":"","comment_hidden":false,"family_hidden":false,"value_hidden":false,"family_comment":"","family":"","comment":""},"17":{"value":"","comment_hidden":false,"family_hidden":false,"value_hidden":false,"family_comment":"","family":"","comment":""},"18":{"value":"","value_unclear":false,"comment_hidden":false,"family_hidden":false,"value_hidden":false,"family_comment":"","family":"","comment":""},"19":{"value":"","comment_hidden":false,"family_hidden":false,"value_hidden":false,"family_comment":"","family":"","comment":""},"20":{"value":"","value_unclear":false,"family_comment":"","comment_unclear":false,"comment":"","family":""}},"vehicle":{"35":[{"brand_info":"1788","sum_rent_comment":"","sum_rent_hidden":false,"year":"2011","sum_rent_unclear":false,"brand_info_hidden":false,"brand_info_unclear":false,"year_unclear":false,"sum_hidden":false,"sum_rent":"","sum":"","brand":"Mazda 6","sum_comment":"","brand_unclear":false,"sum_rent_comment_hidden":false,"sum_comment_hidden":false,"sum_unclear":false}]},"id":"3682","banks":{"51":[{"sum_foreign_comment":"","sum_unclear":false,"sum_units":"USD","sum_comment":"","sum_hidden":true,"sum_foreign_units":"UAH","sum_comment_hidden":false,"sum_units_hidden":false,"sum":"15237","sum_foreign":""}]},"declaration":{"additional_info_text":"","notfull_lostpages":"","date":"2014-03-26T00:00:00","notfull":"","additional_info":"","url":"http://static.declarations.com.ua/declarations/chosen_ones/judges_batch/254_kolodiichuk_viktor_mykolaiovych.pdf"},"liabilities":{"54":{"sum_foreign_comment":"","sum_foreign_hidden":false,"sum_comment":"","sum_hidden":false,"sum_comment_hidden":false,"sum":"","sum_foreign":""},"55":{"sum_foreign_comment":"","sum":"","sum_hidden":false,"sum_comment":"","sum_foreign":""},"56":{"sum_foreign_comment":"","sum":"","sum_comment":"","sum_foreign":""},"57":{"sum_foreign_comment":"","sum_foreign_hidden":false,"sum_comment":"","sum_hidden":false,"sum_comment_hidden":false,"sum_unclear":false,"sum":"","sum_foreign":""},"58":{"sum_foreign_comment":"","sum_foreign_hidden":false,"sum_comment":"","sum_hidden":false,"sum_comment_hidden":false,"sum_unclear":false,"sum":"","sum_foreign":""},"59":{"sum_foreign_comment":"","sum":"","sum_hidden":false,"sum_comment":"","sum_foreign":""},"60":{"sum_foreign_comment":"","sum_foreign_hidden":false,"sum_comment":"","sum_hidden":false,"sum_comment_hidden":false,"sum_unclear":false,"sum":"","sum_foreign":""},"61":{"sum_foreign_comment":"","sum":"","sum_hidden":false,"sum_comment":"","sum_foreign":""},"62":{"sum_foreign_comment":"","sum":"","sum_comment":"","sum_hidden":false,"sum_comment_hidden":false,"sum_foreign":""},"63":{"sum_foreign_comment":"","sum":"","sum_hidden":false,"sum_comment":"","sum_foreign":""},"64":{"sum_foreign_comment":"","sum":"","sum_hidden":false,"sum_comment":"","sum_foreign":""}},"ft_src":"суддя вищого спецiалiзованого суду україни україни з розгляду цивiльних і кримiнальних справ\nЗагальнодержавний регіон\nВищий спеціалізований суд з розгляду цивільних і кримінальних справ\nВіктор\nКолодійчук Тетьяна Володимирівна\nПодружжя\nМиколайович\nКолодійчук Віктор Миколайович\nВіктор Миколайович Колодійчук\nВіктор Колодійчук\nКолодійчук Віктор Миколайович\nКолодійчук Віктор Миколайович\nКолодійчук\n1788\n2011\nMazda 6\n67\n18\n1300\n67\n15237\n2013\n1788\nMazda 6\n2011\n1300\n18\n67\n67\nПодружжя\nКолодійчук Тетьяна Володимирівна\nКолодійчук Віктор Миколайович\nВіктор Миколайович Колодійчук\nВіктор Колодійчук\nКолодійчук Віктор Миколайович\nКолодійчук Віктор Миколайович\nВіктор\nМиколайович\nВищий спеціалізований суд з розгляду цивільних і кримінальних справ\nсуддя вищого спецiалiзованого суду україни україни з розгляду цивiльних і кримiнальних справ\nЗагальнодержавний регіон\nКолодійчук\n378126.66\n11424\n378126.66\n11424\n15237\n2013\n11424\n378126.66\n11424\n378126.66\nКолодійчук Тетьяна Володимирівна\nПодружжя\nМиколайович\nКолодійчук\nВіктор\nКолодійчук Віктор Миколайович\nВіктор Миколайович Колодійчук\nВіктор Колодійчук\nКолодійчук Віктор Миколайович\nЗагальнодержавний регіон\nсуддя вищого спецiалiзованого суду україни україни з розгляду цивiльних і кримiнальних справ\nВищий спеціалізований суд з розгляду цивільних і кримінальних справ\nКолодійчук Віктор Миколайович\n2011\nMazda 6\n1788\n378126.66\n11424\n378126.66\n11424\n67\n67\n18\n1300\n15237\n2013","general":{"inn":"","name":"Віктор","inn_unclear":true,"family":[{"inn":"","inn_hidden":false,"relations_unclear":false,"relations_hidden":false,"relations_other":"","relations":"Подружжя","name_hidden":false,"family_name":"Колодійчук Тетьяна Володимирівна","name_unclear":false}],"inn_hidden":true,"family_raw":"","last_name":"Колодійчук","post":{"post_unclear":false,"post":"суддя вищого спецiалiзованого суду україни україни з розгляду цивiльних і кримiнальних справ","candidate":"","office_hidden":false,"region":"Загальнодержавний регіон","office":"Вищий спеціалізований суд з розгляду цивільних і кримінальних справ","office_unclear":false,"region_hidden":false},"full_name_suggest":{"output":"Колодійчук Віктор Миколайович","input":["Колодійчук Віктор Миколайович","Віктор Миколайович Колодійчук","Віктор Колодійчук"]},"full_name":"Колодійчук Віктор Миколайович","patronymic":"Миколайович","last_name_unclear":false,"name_unclear":false},"source":"VULYK","estate":{"25":[{"space_unclear":false,"costs":"","costs_comment":"","address_hidden":false,"region_hidden":true,"space_comment":"","space_hidden":false,"space":"67","address":"","region":"","costs_rent_comment":"","space_comment_unclear":false,"space_comment_hidden":false,"space_units":"м²","costs_rent":""}],"27":[{"space_hidden":false,"costs":"","costs_comment":"","costs_hidden":false,"address_hidden":false,"region_hidden":true,"space_comment":"","space":"18","address":"","region":"","address_unclear":false,"costs_rent_comment":"","space_units":"м²","costs_rent":""}],"29":[{"space_unclear":false,"address_hidden":false,"region_hidden":true,"space_comment":"","space_hidden":false,"space":"1300","address":"","region":"","costs_property":"","costs_rent_comment":"","space_units":"м²","costs_property_comment":"","costs_rent":""}],"31":[{"space_unclear":false,"address_hidden":false,"region_hidden":true,"space_comment":"","space_hidden":false,"space":"67","address":"","region":"","costs_property":"","costs_rent_comment":"","space_comment_unclear":false,"space_units":"м²","costs_property_comment":"","costs_rent":""}]},"intro":{"declaration_year":"2013","isnotdeclaration":"","declaration_year_unclear":true,"declaration_year_hidden":true}}