{"income":{"5":{"value":"256566","comment_hidden":false,"family_comment":"","family":"175812","comment":"","family_comment_hidden":false},"6":{"value":"243949","family_comment":"","comment_hidden":false,"family_hidden":false,"family_unclear":false,"family_comment_hidden":false,"comment":"","family":"75486"},"7":{"value":"","comment_hidden":false,"family_comment_hidden":false,"family_comment":"","source_name":"","family":"","comment":"","source_name_hidden":false},"8":{"family_comment":"","value":"","family":"","comment":""},"9":{"value":"","family_comment":"","value_unclear":false,"family_unclear":false,"comment_unclear":false,"comment":"","family":""},"10":{"family_comment":"","family_unclear":false,"value":"12617","family":"7509","comment":""},"11":{"family_comment":"","value":"","family":"","comment":""},"12":{"family_comment":"","value":"","family":"","comment":""},"13":{"family_comment":"","value":"","family":"","comment":""},"14":{"family_comment":"","value":"","family":"24301","comment":""},"15":{"family_comment":"","value":"","comment_unclear":false,"family":"","comment":""},"16":{"family_comment":"","value":"","comment_unclear":false,"family":"","comment":""},"17":{"family_comment":"","value":"","family":"68516","comment":""},"18":{"family_comment":"","value":"","family":"","comment":""},"19":{"family_comment":"","value":"","family":"","comment":""},"20":{"value":"","family_comment":"","value_unclear":false,"family_unclear":false,"family_comment_unclear":false,"family_comment_hidden":false,"comment":"","family":""}},"vehicle":{"40":[{"brand_info":"1598 куб. см., 84 кВт , 4332 см","sum_rent_comment":"","brand":"Nissan Qashqai","sum_comment":"","brand_unclear":false,"year":"2012","brand_info_unclear":false,"sum":"","sum_rent":""}]},"id":"3892","banks":{"51":[{"sum_foreign_comment":"","sum_units":"UAH","sum_comment":"","sum_hidden":false,"sum_foreign_units":"UAH","sum_comment_hidden":false,"sum":"148644","sum_foreign":""}]},"declaration":{"additional_info_text":"","notfull_lostpages":"","date":"2014-03-28T00:00:00","notfull":"","additional_info":"","url":"http://static.declarations.com.ua/declarations/chosen_ones/judges_batch/1160_starunskyi_dmytro_mykolaiovych.pdf"},"liabilities":{"54":{"sum_foreign_comment":"","sum_foreign_hidden":false,"sum_comment":"","sum_comment_unclear":false,"sum_hidden":false,"sum_comment_hidden":false,"sum_unclear":false,"sum":"","sum_foreign":""},"55":{"sum_foreign_comment":"","sum_comment_hidden":false,"sum":"","sum_comment":"","sum_foreign":""},"56":{"sum_foreign_comment":"","sum":"","sum_comment":"","sum_comment_unclear":false,"sum_foreign":""},"57":{"sum_foreign_comment":"","sum":"","sum_comment":"","sum_hidden":false,"sum_comment_hidden":false,"sum_unclear":false,"sum_foreign":""},"58":{"sum_foreign_comment":"","sum":"","sum_comment":"","sum_hidden":false,"sum_comment_hidden":false,"sum_foreign":""},"59":{"sum_foreign_comment":"","sum":"","sum_comment":"","sum_comment_unclear":false,"sum_unclear":false,"sum_foreign":""},"60":{"sum_foreign_comment":"","sum":"","sum_comment":"","sum_hidden":false,"sum_comment_hidden":false,"sum_unclear":false,"sum_foreign":""},"61":{"sum_foreign_comment":"","sum":"","sum_comment":"","sum_foreign":""},"62":{"sum_foreign_comment":"","sum":"","sum_comment":"","sum_foreign":""},"63":{"sum_foreign_comment":"","sum":"","sum_comment":"","sum_hidden":false,"sum_comment_hidden":false,"sum_foreign":""},"64":{"sum_foreign_comment":"","sum":"","sum_comment":"","sum_foreign":""}},"ft_src":"суддя львівського апеляційного адміністративного суду\nЛьвівська область\nАпеляційний адміністративний суд\nДмитро\nСтарунська Л. Л\nПодружжя\nСтарунський О. Д\nДитина\nСтарунський-британ В. Д\nДитина\nМиколайович\nСтарунський Дмитро Миколайович\nДмитро Миколайович Старунський\nДмитро Старунський\nСтарунський Дмитро Миколайович\nСтарунський\nСтарунський Дмитро Миколайович\n2012\nNissan Qashqai\n1598 куб. см., 84 кВт , 4332 см\n15\n51.08\n21.2\n44.5\n454\n17.2\n43.3\n50\n148644\n2013\n1598 куб. см., 84 кВт , 4332 см\nNissan Qashqai\n2012\n2013\nСтарунський Дмитро Миколайович\nДмитро Миколайович Старунський\nДмитро Старунський\nСтарунський Дмитро Миколайович\nДмитро\nПодружжя\nСтарунська Л. Л\nДитина\nСтарунський О. Д\nДитина\nСтарунський-британ В. Д\nСтарунський Дмитро Миколайович\nМиколайович\nАпеляційний адміністративний суд\nЛьвівська область\nсуддя львівського апеляційного адміністративного суду\nСтарунський\n75486\n243949\n68516\n24301\n256566\n175812\n12617\n7509\n15\n44.5\n51.08\n21.2\n17.2\n43.3\n50\n454\n148644\n75486\n243949\n24301\n7509\n12617\n175812\n256566\n68516\nПодружжя\nСтарунська Л. Л\nДитина\nСтарунський О. Д\nДитина\nСтарунський-британ В. Д\nМиколайович\nСтарунський\nДмитро\nСтарунський Дмитро Миколайович\nДмитро Миколайович Старунський\nДмитро Старунський\nСтарунський Дмитро Миколайович\nЛьвівська область\nАпеляційний адміністративний суд\nсуддя львівського апеляційного адміністративного суду\nСтарунський Дмитро Миколайович\n2012\n1598 куб. см., 84 кВт , 4332 см\nNissan Qashqai\n24301\n7509\n12617\n256566\n175812\n68516\n243949\n75486\n51.08\n21.2\n44.5\n15\n17.2\n43.3\n50\n454\n148644\n2013","general":{"inn":"","name":"Дмитро","family":[{"inn":"","relations":"Подружжя","inn_unclear":false,"relations_hidden":false,"inn_hidden":true,"relations_other":"","name_hidden":false,"family_name":"Старунська Л. Л","name_unclear":false},{"inn":"","relations":"Дитина","inn_unclear":false,"family_name":"Старунський О. Д","inn_hidden":false,"relations_other":"","name_hidden":false,"name_unclear":false},{"inn":"","relations":"Дитина","relations_other":"","inn_hidden":false,"family_name":"Старунський-британ В. Д","name_hidden":false,"name_unclear":true}],"patronymic":"Миколайович","inn_hidden":true,"family_raw":"","last_name":"Старунський","post":{"post_unclear":false,"region_unclear":false,"post":"суддя львівського апеляційного адміністративного суду","office":"Апеляційний адміністративний суд","region":"Львівська область","post_hidden":false,"office_hidden":false,"office_unclear":false,"region_hidden":false},"last_name_unclear":false,"full_name":"Старунський Дмитро Миколайович","addresses":[{"place_district":"","place_city_hidden":true,"place_city":"","place_city_type_hidden":true,"place_district_hidden":true,"place_city_type":"","place_address_hidden":true,"place_address":"","place_hidden":true,"place":""}],"full_name_suggest":{"output":"Старунський Дмитро Миколайович","input":["Старунський Дмитро Миколайович","Дмитро Миколайович Старунський","Дмитро Старунський"]},"name_unclear":false},"source":"VULYK","estate":{"25":[{"space_unclear":false,"costs":"","costs_comment":"","costs_hidden":false,"address_hidden":true,"region_hidden":true,"space_comment":"","space_hidden":false,"space":"17.2","address":"","region":"","costs_rent_comment":"","space_comment_hidden":false,"space_units":"м²","costs_rent":""},{"space_unclear":false,"costs":"","costs_comment":"","address_hidden":true,"region_hidden":true,"space_comment":"","space":"43.3","address":"","region":"","costs_rent_comment":"","space_comment_unclear":false,"space_units":"м²","costs_rent":""},{"costs_rent":"","region":"","costs":"","costs_rent_comment":"","costs_comment":"","address_hidden":true,"space_comment":"","space_units":"м²","space":"50","address":""}],"29":[{"space_unclear":false,"address_hidden":true,"region_hidden":true,"space_comment":"","space":"454","address":"","region":"","costs_property":"","costs_rent_comment":"","space_units":"м²","costs_property_comment":"","costs_rent":""}],"30":[{"space_unclear":false,"address_hidden":true,"region_hidden":true,"space_comment":"","space_hidden":false,"space":"44.5","address":"","region":"","costs_property":"","costs_rent_comment":"","space_comment_unclear":false,"space_units":"м²","costs_property_comment":"","costs_rent":""}],"31":[{"space_unclear":false,"address_hidden":true,"region_hidden":true,"space_comment":"","space":"51.08","address":"","region":"","costs_property":"","costs_rent_comment":"","space_units":"м²","costs_property_comment":"","costs_rent":""},{"costs_rent":"","space_unclear":false,"region":"","costs_property":"","costs_rent_comment":"","region_hidden":false,"space_comment":"","costs_property_comment":"","space_units":"м²","space":"21.2","address":""}],"33":[{"space_hidden":false,"address_hidden":true,"region_hidden":true,"space_comment":"","space":"15","address":"","region":"","costs_property":"","costs_rent_comment":"","space_units":"м²","costs_property_comment":"","costs_rent":""}]},"intro":{"declaration_year":"2013"}}