{"income":{"5":{"value":"428800","family_comment":"","value_unclear":false,"value_hidden":false,"family_unclear":false,"family":"2169934","comment":""},"6":{"value":"220282","family_hidden":false,"value_hidden":false,"family_comment":"","family_comment_hidden":false,"comment":"","family":"1710162"},"7":{"value":"","value_unclear":false,"family_hidden":false,"value_hidden":false,"family_comment":"","source_name":"","family":"","comment":"","source_name_hidden":false},"8":{"value":"","comment_hidden":false,"family_hidden":false,"value_hidden":false,"family_comment":"","family":"","comment":""},"9":{"value":"","family_comment":"","comment_hidden":false,"family_hidden":false,"value_hidden":false,"family_unclear":false,"family":"","comment":""},"10":{"value":"","comment_hidden":false,"family_hidden":false,"value_hidden":false,"family_comment":"","family":"","comment":""},"11":{"value":"","value_unclear":false,"comment_hidden":false,"family_hidden":false,"value_hidden":false,"family_comment":"","family":"","comment":""},"12":{"value":"","comment_hidden":false,"family_hidden":false,"value_hidden":false,"family_comment":"","family":"","comment":""},"13":{"value":"","comment_hidden":false,"family_hidden":false,"value_hidden":false,"family_comment":"","family":"","comment":""},"14":{"value":"","comment_hidden":false,"family_hidden":false,"value_hidden":false,"family_comment":"","family":"","comment":""},"15":{"value":"","comment_hidden":false,"family_hidden":false,"value_hidden":false,"family_comment":"","family":"","comment":""},"16":{"value":"208000","comment_hidden":false,"family_hidden":false,"value_hidden":false,"family_comment":"","family":"240000","comment":""},"17":{"value":"","comment_hidden":false,"family_hidden":false,"value_hidden":false,"family_comment":"","family":"","comment":""},"18":{"value":"","value_unclear":false,"comment_hidden":false,"family_hidden":false,"value_hidden":false,"family_comment":"","family":"","comment":""},"19":{"value":"","comment_hidden":false,"family_hidden":false,"value_hidden":false,"family_comment":"","family":"","comment":""},"20":{"value":"518","value_unclear":false,"family_comment":"","comment_unclear":false,"comment":"","family":"219772"}},"vehicle":{"40":[{"year_hidden":false,"brand_info":"3000","sum_rent_comment":"","brand":"BMW X5","sum_comment":"","brand_unclear":false,"year":"2012","brand_hidden":false,"brand_info_unclear":false,"sum":"","sum_rent":""},{"brand_info":"3000","sum_rent_comment":"","brand":"Audi Q7","sum_comment":"","year":"2013","brand_info_unclear":false,"sum":"","sum_rent":""}]},"id":"3976","banks":{"51":[{"sum_foreign_comment":"","sum_unclear":false,"sum_units":"UAH","sum_comment":"","sum_hidden":false,"sum_foreign_units":"UAH","sum_comment_hidden":false,"sum_units_hidden":false,"sum":"2637275","sum_foreign":""}]},"declaration":{"additional_info_text":"","notfull_lostpages":"","date":"2014-03-28T00:00:00","notfull":"","additional_info":"","url":"http://static.declarations.com.ua/declarations/chosen_ones/judges_batch/238_hrymych_maiia_kostiantynivna.pdf"},"liabilities":{"54":{"sum_foreign_comment":"","sum_foreign_hidden":false,"sum_comment":"","sum_hidden":false,"sum_comment_hidden":false,"sum":"","sum_foreign":""},"55":{"sum_foreign_comment":"","sum":"","sum_hidden":false,"sum_comment":"","sum_foreign":""},"56":{"sum_foreign_comment":"","sum":"","sum_comment":"","sum_foreign":""},"57":{"sum_foreign_comment":"","sum_foreign_hidden":false,"sum_comment":"","sum_hidden":false,"sum_comment_hidden":false,"sum_unclear":false,"sum":"","sum_foreign":""},"58":{"sum_foreign_comment":"","sum_foreign_hidden":false,"sum_comment":"","sum_hidden":false,"sum_comment_hidden":false,"sum_unclear":false,"sum":"","sum_foreign":""},"59":{"sum_foreign_comment":"","sum":"","sum_hidden":false,"sum_comment":"","sum_foreign":""},"60":{"sum_foreign_comment":"","sum_foreign_hidden":false,"sum_comment":"","sum_hidden":false,"sum_comment_hidden":false,"sum_unclear":false,"sum":"78245","sum_foreign":""},"61":{"sum_foreign_comment":"","sum":"","sum_hidden":false,"sum_comment":"","sum_foreign":""},"62":{"sum_foreign_comment":"","sum":"","sum_comment":"","sum_hidden":false,"sum_comment_hidden":false,"sum_foreign":""},"63":{"sum_foreign_comment":"","sum":"","sum_hidden":false,"sum_comment":"","sum_foreign":""},"64":{"sum_foreign_comment":"","sum":"","sum_hidden":false,"sum_comment":"","sum_foreign":""}},"ft_src":"78245\nсуддя вищого спецiалiзованого суду україни з розгляду цивiльних і кримiнальних справ\nЗагальнодержавний регіон\nВищий спецiалiзований суд з розгляду цивiльних i кримiнальних справ\nМайя\nГримич С. В\nПодружжя\nГримич М. С\nДитина\nГримич А. С\nДитина\nКостянтинівна\nГримич Майя Костянтинівна\nМайя Костянтинівна Гримич\nМайя Гримич\nГримич Майя Костянтинівна\nГримич Майя Костянтинівна\nГримич\nBMW X5\n3000\n2012\n3000\n2013\nAudi Q7\n3200\nберегоукріплююча споруда\n90\n95\n40\n399\n2637275\n2013\n3000\nBMW X5\n2012\n3000\nAudi Q7\n2013\n3200\n399\n95\n40\n90\nберегоукріплююча споруда\nГримич Майя Костянтинівна\nМайя Костянтинівна Гримич\nМайя Гримич\nГримич Майя Костянтинівна\nГримич Майя Костянтинівна\nПодружжя\nГримич С. В\nДитина\nГримич М. С\nДитина\nГримич А. С\nМайя\nКостянтинівна\nВищий спецiалiзований суд з розгляду цивiльних i кримiнальних справ\nсуддя вищого спецiалiзованого суду україни з розгляду цивiльних і кримiнальних справ\nЗагальнодержавний регіон\nГримич\n78245\n220282\n1710162\n518\n219772\n428800\n2169934\n208000\n240000\n2637275\n2013\n78245\n1710162\n220282\n2169934\n428800\n240000\n208000\n219772\n518\nГримич С. В\nПодружжя\nДитина\nГримич М. С\nГримич А. С\nДитина\nКостянтинівна\nГримич\nМайя\nГримич Майя Костянтинівна\nМайя Костянтинівна Гримич\nМайя Гримич\nГримич Майя Костянтинівна\nЗагальнодержавний регіон\nсуддя вищого спецiалiзованого суду україни з розгляду цивiльних і кримiнальних справ\nВищий спецiалiзований суд з розгляду цивiльних i кримiнальних справ\nГримич Майя Костянтинівна\n2012\nBMW X5\n3000\n2013\n3000\nAudi Q7\n518\n219772\n428800\n2169934\n208000\n240000\n220282\n1710162\n95\n40\n3200\n399\nберегоукріплююча споруда\n90\n2637275\n2013","general":{"inn":"","name":"Майя","inn_unclear":false,"family":[{"inn":"","inn_hidden":true,"relations_unclear":false,"relations_hidden":false,"relations_other":"","relations":"Подружжя","name_hidden":false,"family_name":"Гримич С. В","name_unclear":false},{"inn":"","inn_hidden":false,"relations_unclear":false,"relations_hidden":false,"relations_other":"","relations":"Дитина","name_hidden":false,"family_name":"Гримич М. С","name_unclear":false},{"inn":"","relations":"Дитина","relations_other":"","inn_hidden":false,"family_name":"Гримич А. С","name_hidden":false,"name_unclear":false}],"inn_hidden":true,"family_raw":"","last_name":"Гримич","post":{"post_unclear":false,"post":"суддя вищого спецiалiзованого суду україни з розгляду цивiльних і кримiнальних справ","candidate":"","office_hidden":true,"region":"Загальнодержавний регіон","office":"Вищий спецiалiзований суд з розгляду цивiльних i кримiнальних справ","office_unclear":false,"region_hidden":true},"full_name_suggest":{"output":"Гримич Майя Костянтинівна","input":["Гримич Майя Костянтинівна","Майя Костянтинівна Гримич","Майя Гримич"]},"full_name":"Гримич Майя Костянтинівна","addresses":[{"place_city_type_unclear":false,"place_address":"","place_district_hidden":false,"place_city_type":"","place_city_hidden":false,"place_city_type_hidden":false,"place":"","place_district":"","place_unclear":false,"place_city":"","place_city_unclear":false,"place_hidden":true,"place_address_hidden":false}],"patronymic":"Костянтинівна","last_name_unclear":false,"name_unclear":false},"source":"VULYK","estate":{"23":[{"space_hidden":false,"costs":"","costs_comment":"","address_hidden":false,"region_hidden":true,"space_comment":"","space_unclear":false,"space":"3200","address":"","space_comment_unclear":false,"region":"","costs_rent_comment":"","costs_unclear":false,"space_comment_hidden":false,"space_units":"м²","costs_rent":""}],"24":[{"costs":"","costs_comment":"","address_hidden":false,"region_hidden":true,"space_comment":"","space":"399","address":"","region":"","address_unclear":false,"costs_rent_comment":"","space_comment_unclear":false,"space_units":"м²","costs_rent":""}],"31":[{"space_unclear":false,"address_hidden":false,"region_hidden":true,"space_comment":"","space_hidden":false,"space":"95","address":"","region":"","costs_property":"","costs_rent_comment":"","space_comment_unclear":false,"space_units":"м²","costs_property_comment":"","costs_rent":""},{"costs_rent":"","region":"","costs_property":"","costs_rent_comment":"","space_comment_unclear":false,"region_hidden":false,"space_comment":"","costs_property_comment":"","space_units":"м²","space":"40","address":""}],"34":[{"space_unclear":false,"address_hidden":false,"region_hidden":true,"space_comment":"берегоукріплююча споруда","space_hidden":false,"space":"90","address":"","region":"","costs_property":"","costs_rent_comment":"","space_units":"м²","costs_property_comment":"","costs_rent":""}]},"intro":{"declaration_year":"2013","isnotdeclaration":"","declaration_year_unclear":false,"declaration_year_hidden":false}}