{"income":{"5":{"family_comment":"","value":"334445","value_unclear":false,"family":"31300","comment":""},"6":{"family_comment":"","value":"334445","value_unclear":false,"family":"2100","comment":""},"7":{"source_name_unclear":false,"value":"","family_hidden":false,"value_hidden":false,"family_comment":"","source_name":"","family":"","comment":"","source_name_hidden":false},"8":{"value":"","family_hidden":false,"value_hidden":false,"family_comment":"","family":"","comment":""},"9":{"value":"","value_unclear":false,"value_hidden":false,"family_comment":"","comment_unclear":false,"comment":"","family":""},"10":{"value":"","family_hidden":false,"value_hidden":false,"family_comment":"","family":"","comment":""},"11":{"value":"","family_hidden":false,"value_hidden":false,"family_comment":"","family":"","comment":""},"12":{"value":"","family_hidden":false,"value_hidden":false,"family_comment":"","family":"","comment":""},"13":{"value":"","family_hidden":false,"value_hidden":false,"family_comment":"","family":"","comment":""},"14":{"value":"","family_hidden":false,"value_hidden":false,"family_comment":"","family":"","comment":""},"15":{"value":"","family_hidden":false,"value_hidden":false,"family_comment":"","family":"","comment":""},"16":{"value":"","family_hidden":false,"value_hidden":false,"family_comment":"","family":"","comment":""},"17":{"value":"","family_hidden":false,"value_hidden":false,"family_comment":"","family":"","comment":""},"18":{"value":"","comment_unclear":false,"family_hidden":false,"value_hidden":false,"family_comment":"","family":"","comment":""},"19":{"value":"","family_hidden":false,"value_hidden":false,"family_comment":"","family":"","comment":""},"20":{"value":"","value_unclear":false,"family_hidden":false,"value_hidden":false,"family_comment":"допомога при нородженні дитини","comment_unclear":false,"comment":"","family":"29200"}},"vehicle":{"35":[{"brand_info":"4000","sum_rent_comment":"","sum_rent_hidden":false,"year":"2007","sum_hidden":false,"brand_info_unclear":false,"sum_rent":"","sum":"","brand":"Toyota Land Cruiser Prado","sum_comment":"","brand_unclear":false,"sum_rent_comment_hidden":false,"sum_comment_hidden":false,"sum_unclear":false}],"40":[{"brand_info":"2500","sum":"","brand":"Toyota Camry","sum_comment":"","brand_unclear":false,"year":"2012","brand_hidden":false,"brand_info_hidden":false,"brand_info_unclear":false,"sum_rent_comment":"","sum_rent":""}]},"id":"4199","banks":{"45":[{"sum_units":"UAH","sum_foreign":"","sum_hidden":false,"sum":"12000","sum_units_hidden":false,"sum_foreign_comment":"","sum_foreign_hidden":false,"sum_comment":"","sum_foreign_units":"UAH","sum_units_unclear":false,"sum_comment_hidden":false,"sum_unclear":false}],"46":[{"sum_foreign_comment":"","sum":"12000","sum_comment":"","sum_hidden":false,"sum_foreign_units":"UAH","sum_foreign_hidden":false,"sum_units":"UAH","sum_comment_hidden":false,"sum_unclear":false,"sum_foreign":"","sum_units_hidden":false}]},"declaration":{"additional_info_text":"","notfull":"1","additional_info":"","notfull_lostpages":"в наявності лише нарізки з декларації","url":"http://static.declarations.com.ua/declarations/chosen_ones/judges_batch/182_kovalenko_volodymyr_mykolaiovych.pdf"},"liabilities":{"54":{"sum_foreign_comment":"","sum_foreign_hidden":false,"sum_comment":"","sum_hidden":false,"sum_foreign_comment_unclear":false,"sum_comment_hidden":false,"sum":"14600","sum_foreign":""},"55":{"sum_foreign_comment":"","sum":"","sum_hidden":false,"sum_comment":"","sum_foreign":""},"56":{"sum_foreign_comment":"","sum":"48620","sum_comment":"","sum_foreign":""},"57":{"sum_foreign_comment":"","sum_foreign_hidden":false,"sum_comment":"","sum_hidden":false,"sum_comment_hidden":false,"sum":"116727","sum_foreign":""},"58":{"sum_foreign_comment":"","sum":"9526","sum_comment":"","sum_hidden":false,"sum_comment_hidden":false,"sum_foreign":""},"59":{"sum_foreign_comment":"","sum_foreign_hidden":false,"sum_comment":"","sum_hidden":false,"sum":"","sum_foreign":""},"60":{"sum_foreign_comment":"","sum":"20155","sum_comment":"","sum_comment_unclear":false,"sum_hidden":false,"sum_comment_hidden":false,"sum_foreign":""},"61":{"sum_foreign_comment":"","sum":"","sum_hidden":false,"sum_comment":"","sum_foreign":""},"62":{"sum_foreign_comment":"","sum_foreign_hidden":false,"sum_comment":"","sum_comment_hidden":false,"sum_unclear":false,"sum":"7200","sum_foreign":""},"63":{"sum_foreign_comment":"","sum_foreign_hidden":false,"sum_comment":"","sum_hidden":false,"sum_comment_hidden":false,"sum":"","sum_foreign":""},"64":{"sum_foreign_comment":"","sum":"","sum_comment":"","sum_hidden":false,"sum_comment_hidden":false,"sum_foreign":""}},"ft_src":"116727\n7200\n14600\n9526\n48620\n20155\n1\nв наявності лише нарізки з декларації\nсуддя вищого господарського суду україни\nЗагальнодержавний регіон\nВищий господарський суд\nВолодимир\nКоваленко Т. В\nПодружжя\nКоваленко І. В\nДитина\nКоваленко А. В\nДитина\nКоваленко К. В\nДитина\nКоваленко О. В\nДитина\nМиколайович\nКоваленко Володимир Миколайович\nВолодимир Миколайович Коваленко\nВолодимир Коваленко\nКоваленко Володимир Миколайович\nКоваленко Володимир Миколайович\nКоваленко\nToyota Land Cruiser Prado\n4000\n2007\nToyota Camry\n2500\n2012\n80519\n57.2\n52.6\n12000\n12000\nв наявності лише нарізки з декларації\n1\n2013\n4000\nToyota Land Cruiser Prado\n2007\n2500\n2012\nToyota Camry\n1\nв наявності лише нарізки з декларації\n2013\nКоваленко Володимир Миколайович\nВолодимир Миколайович Коваленко\nВолодимир Коваленко\nКоваленко Володимир Миколайович\nКоваленко Володимир Миколайович\nПодружжя\nКоваленко Т. В\nДитина\nКоваленко І. В\nДитина\nКоваленко А. В\nДитина\nКоваленко К. В\nКоваленко О. В\nДитина\nВолодимир\nМиколайович\nсуддя вищого господарського суду україни\nВищий господарський суд\nЗагальнодержавний регіон\nКоваленко\n9526\n14600\n116727\n20155\n48620\n7200\n334445\n2100\nдопомога при нородженні дитини\n29200\n334445\n31300\n80519\n52.6\n57.2\n12000\n12000\n9526\n116727\n48620\n7200\n14600\n20155\n2100\n334445\n31300\n334445\nдопомога при нородженні дитини\n29200\nПодружжя\nКоваленко Т. В\nДитина\nКоваленко І. В\nДитина\nКоваленко А. В\nКоваленко К. В\nДитина\nДитина\nКоваленко О. В\nМиколайович\nКоваленко\nВолодимир\nКоваленко Володимир Миколайович\nВолодимир Миколайович Коваленко\nВолодимир Коваленко\nКоваленко Володимир Миколайович\nЗагальнодержавний регіон\nВищий господарський суд\nсуддя вищого господарського суду україни\nКоваленко Володимир Миколайович\n2007\nToyota Land Cruiser Prado\n4000\nToyota Camry\n2500\n2012\nдопомога при нородженні дитини\n29200\n31300\n334445\n2100\n334445\n57.2\n80519\n52.6\n12000\n12000\n2013","general":{"inn":"","name":"Володимир","inn_unclear":false,"family":[{"inn":"","relations":"Подружжя","inn_unclear":false,"relations_hidden":false,"inn_hidden":true,"relations_other":"","name_hidden":true,"family_name":"Коваленко Т. В","name_unclear":false},{"inn":"","relations":"Дитина","relations_hidden":false,"inn_hidden":false,"relations_other":"","name_hidden":false,"family_name":"Коваленко І. В","name_unclear":false},{"inn":"","relations":"Дитина","relations_other":"","inn_hidden":false,"family_name":"Коваленко А. В","name_hidden":false,"name_unclear":false},{"inn":"","relations":"Дитина","relations_other":"","inn_hidden":false,"family_name":"Коваленко К. В","name_unclear":false},{"inn":"","family_name":"Коваленко О. В","relations":"Дитина","relations_other":""}],"inn_hidden":false,"family_raw":"","last_name":"Коваленко","post":{"post":"суддя вищого господарського суду україни","region":"Загальнодержавний регіон","candidate":"","office_hidden":true,"post_hidden":false,"office":"Вищий господарський суд","region_hidden":false},"full_name_suggest":{"output":"Коваленко Володимир Миколайович","input":["Коваленко Володимир Миколайович","Володимир Миколайович Коваленко","Володимир Коваленко"]},"full_name":"Коваленко Володимир Миколайович","patronymic":"Миколайович","last_name_unclear":false,"name_unclear":false},"source":"VULYK","estate":{"23":[{"region_unclear":false,"space_unclear":false,"costs":"","costs_comment":"","costs_hidden":false,"address_hidden":true,"region_hidden":true,"space_comment":"","space_hidden":false,"space_units_unclear":false,"address":"","costs_comment_unclear":false,"region":"","address_unclear":false,"space":"80519","costs_rent_hidden":false,"costs_rent_comment_hidden":false,"space_units":"м²","costs_comment_hidden":false,"costs_rent":"","costs_rent_comment":""}],"24":[{"space_unclear":false,"costs":"","costs_comment":"","costs_hidden":false,"address_hidden":true,"region_hidden":true,"space_comment":"","space_hidden":false,"space":"52.6","address":"","region":"","costs_rent_comment":"","costs_rent_hidden":false,"costs_rent_comment_hidden":false,"space_units":"м²","costs_comment_hidden":false,"costs_rent":""}],"31":[{"region_unclear":false,"space_unclear":false,"costs_property_hidden":false,"address_hidden":true,"region_hidden":true,"space_comment":"","space_units_hidden":false,"space_hidden":false,"space":"57.2","address":"","region":"","costs_property":"","costs_rent_comment":"","space_comment_unclear":false,"space_units":"м²","costs_property_comment":"","costs_rent":""}]},"intro":{"declaration_year":"2013","isnotdeclaration":"","declaration_year_unclear":false,"declaration_year_hidden":false}}