{"ft_src":"Причіп легковий\n2008\nToyota,Land Cruiser Prado\n2008\nBrig,F450L\n2007\nVolkswagen,Golf\n2011\nУкраїна, Апостоловський район, приховано\n72,5\nУкраїна, Апостоловський район, приховано\n124470\nУкраїна, Павлоградський район, приховано\n4810\nУкраїна, м.Дніпропетровськ\n57,6\n15100\n15100\nFALSE\nFALSE\nFALSE\n2013\n169945\n33834\n169945\n8400\n25434\nBrig,F450L\n2007\nVolkswagen,Golf\n2011\nПричіп легковий\n2008\nToyota,Land Cruiser Prado\n2008\nFALSE\nFALSE\nУкраїна, Апостоловський район, приховано\n124470\nУкраїна, Павлоградський район, приховано\n4810\nУкраїна, м.Дніпропетровськ\n57,6\nУкраїна, Апостоловський район, приховано\n72,5\nСуддя. Заступник голови Дніпроветровського окружного адміністративного суду\nДружина Кальник О.А.;син Кальник М.В.;донька Кальник А.В.\nДніпропетровська\nДніпропетровськ\nКальник\nКальник Віталій Валерійович\nВіталій Валерійович Кальник\nВіталій Кальник\nКальник Віталій Валерійович\nВіталій\nКальник Віталій Валерійович\nАдміністративний місцевий суд\nСуддя. Заступник голови Дніпропетровського окружного адміністративного суду\nДніпропетровська область\nВалерійович\n49114 м.Дніпропетровськ\n476\n9800\n4500\n169945\n25434\n169945\n33834\n8400\n15100\n15100\n2013\nFALSE\n9800\n4500\n476\nКальник\nВалерійович\nДружина Кальник О.А.;син Кальник М.В.;донька Кальник А.В.\nКальник Віталій Валерійович\nВіталій Валерійович Кальник\nВіталій Кальник\nКальник Віталій Валерійович\nВіталій\nСуддя. Заступник голови Дніпроветровського окружного адміністративного суду\nДніпропетровська\nДніпропетровськ\nСуддя. Заступник голови Дніпропетровського окружного адміністративного суду\nДніпропетровська область\nАдміністративний місцевий суд\nКальник Віталій Валерійович\n49114 м.Дніпропетровськ","estate":{"23":[{"costs":"","address":"","space_units":"","costs_rent_comment":"","space":"","costs_comment":"","costs_rent":"","space_comment":"","region":"","location_raw":""},{"costs":"","address":"","space_units":"","costs_rent_comment":"","space":"","costs_comment":"","costs_rent":"","space_comment":"","region":"","location_raw":""},{"costs":"","address":"","space_units":"","costs_rent_comment":"","space":"","costs_comment":"","costs_rent":"","space_comment":"","region":"","location_raw":""}],"24":[{"costs":"","address":"","space_units":"","costs_rent_comment":"","space":"57,6","costs_comment":"","costs_rent":"","space_comment":"","region":"","location_raw":"Україна, м.Дніпропетровськ"}],"29":[{"costs_property_comment":"","address":"","space_units":"","costs_rent_comment":"","space":"124470","space_comment":"","costs_property":"","region":"","location_raw":"Україна, Апостоловський район, приховано","costs_rent":""},{"costs_property_comment":"","address":"","space_units":"","costs_rent_comment":"","space":"4810","space_comment":"","costs_property":"","region":"","location_raw":"Україна, Павлоградський район, приховано","costs_rent":""}],"30":[{"costs_property_comment":"","address":"","space_units":"","costs_rent_comment":"","space":"72,5","space_comment":"","costs_property":"","region":"","location_raw":"Україна, Апостоловський район, приховано","costs_rent":""}]},"vehicle":{"35":[{"sum_comment":"","brand_info":"","sum":"","sum_rent_comment":"","year":"2008","brand":"Toyota,Land Cruiser Prado","sum_rent":"","brand_hidden":false}],"37":[{"sum_comment":"","brand_info":"","sum":"","sum_rent_comment":"","year":"2007","brand":"Brig,F450L","sum_rent":"","brand_hidden":false}],"39":[{"sum_comment":"","brand_info":"","sum":"","sum_rent_comment":"","year":"2008","brand":"Причіп легковий","sum_rent":"","brand_hidden":false}],"40":[{"sum_comment":"","brand_info":"","sum":"","sum_rent_comment":"","year":"2011","brand":"Volkswagen,Golf","sum_rent":"","brand_hidden":false}]},"id":"447","income":{"5":{"family_comment":"","value":"169945","family":"33834","comment":""},"6":{"family_comment":"","value":"169945","family":"0","comment":""},"7":{"family":"0","family_comment":"","value":"0","comment":"","source_name":"0"},"8":{"family_comment":"","value":"0","family":"0","comment":""},"9":{"family_comment":"","value":"0","family":"0","comment":""},"10":{"family_comment":"","value":"0","family":"0","comment":""},"11":{"family_comment":"","value":"0","family":"0","comment":""},"12":{"family_comment":"","value":"0","family":"0","comment":""},"13":{"family_comment":"","value":"0","family":"0","comment":""},"14":{"family_comment":"","value":"0","family":"0","comment":""},"15":{"family_comment":"","value":"0","family":"0","comment":""},"16":{"family_comment":"","value":"0","family":"0","comment":""},"17":{"family_comment":"","value":"0","family":"0","comment":""},"18":{"family_comment":"","value":"0","family":"0","comment":""},"19":{"family_comment":"","value":"0","family":"8400","comment":""},"20":{"family_comment":"","value":"0","family":"25434","comment":""},"21":[{"country_comment":"","uah_equal":"0","country":"0","cur":"0"},{"country_comment":"","uah_equal":"0","country":"0","cur":"0"},{"country_comment":"","uah_equal":"0","country":"0","cur":"0"},{"country_comment":"","uah_equal":"0","country":"0","cur":"0"},{"country_comment":"","uah_equal":"0","country":"0","cur":"0"}],"22":[{"country_comment":"","uah_equal":"0","country":"0","cur":"0"},{"country_comment":"","uah_equal":"0","country":"0","cur":"0"},{"country_comment":"","uah_equal":"0","country":"0","cur":"0"},{"country_comment":"","uah_equal":"0","country":"0","cur":"0"},{"country_comment":"","uah_equal":"0","country":"0","cur":"0"}]},"banks":{"45":[{"sum_units":"UAH","sum_comment":"","sum_foreign_units":"","sum":"15100","sum_foreign_comment":"","sum_foreign":""},{"sum_units":"USD","sum_comment":"","sum_foreign_units":"","sum":"","sum_foreign_comment":"","sum_foreign":""},{"sum_units":"EUR","sum_comment":"","sum_foreign_units":"","sum":"","sum_foreign_comment":"","sum_foreign":""}],"46":[{"sum_units":"UAH","sum_comment":"","sum_foreign_units":"","sum":"15100","sum_foreign_comment":"","sum_foreign":""},{"sum_units":"USD","sum_comment":"","sum_foreign_units":"","sum":"","sum_foreign_comment":"","sum_foreign":""},{"sum_units":"EUR","sum_comment":"","sum_foreign_units":"","sum":"","sum_foreign_comment":"","sum_foreign":""}],"47":[{"sum_units":"","sum_comment":"","sum_foreign_units":"","sum":"","sum_foreign_comment":"","sum_foreign":""}],"48":[{"sum_units":"","sum_comment":"","sum_foreign_units":"","sum":"","sum_foreign_comment":"","sum_foreign":""}],"49":[{"sum_units":"","sum_comment":"","sum_foreign_units":"","sum":"","sum_foreign_comment":"","sum_foreign":""}],"50":[{"sum_units":"","sum_comment":"","sum_foreign_units":"","sum":"","sum_foreign_comment":"","sum_foreign":""}],"51":[{"sum_units":"UAH","sum_comment":"","sum_foreign_units":"","sum":"","sum_foreign_comment":"","sum_foreign":""},{"sum_units":"USD","sum_comment":"","sum_foreign_units":"","sum":"","sum_foreign_comment":"","sum_foreign":""},{"sum_units":"EUR","sum_comment":"","sum_foreign_units":"","sum":"","sum_foreign_comment":"","sum_foreign":""}],"52":[{"sum_units":"","sum_comment":"","sum_foreign_units":"","sum":"","sum_foreign_comment":"","sum_foreign":""}],"53":[{"sum_units":"","sum_comment":"","sum_foreign_units":"","sum":"","sum_foreign_comment":"","sum_foreign":""}]},"declaration":{"notfull_lostpages":"","additional_info_text":"","additional_info":"FALSE","notfull":"FALSE","url":"http://static.declarations.com.ua/declarations/sudy/mistsevi_sudy/okruzhni_administratyvni_sudy/dnipropetrovska/kalnyk.pdf","needs_scancopy_check":false},"general":{"family_raw":"Дружина Кальник О.А.;син Кальник М.В.;донька Кальник А.В.","name":"Віталій","full_name_suggest":{"input":["Кальник Віталій Валерійович","Віталій Валерійович Кальник","Віталій Кальник"],"output":"Кальник Віталій Валерійович"},"post_raw":"Суддя. Заступник голови Дніпроветровського окружного адміністративного суду","name_unclear":false,"patronymic":"Валерійович","patronymic_unclear":false,"last_name_hidden":false,"patronymic_hidden":false,"inn":"","addresses_raw_hidden":true,"last_name":"Кальник","full_name":"Кальник Віталій Валерійович","post":{"office":"Адміністративний місцевий суд","region":"Дніпропетровська область","post":"Суддя. Заступник голови Дніпропетровського окружного адміністративного суду"},"addresses":[{"place_district":"","place_city_type":"","place_address_type":"","place":"Дніпропетровська","place_address":"","place_city":"Дніпропетровськ"}],"name_hidden":false,"last_name_unclear":false,"addresses_raw":"49114 м.Дніпропетровськ"},"liabilities":{"54":{"sum_comment":"","sum_foreign_comment":"","sum_foreign":"","sum":""},"55":{"sum_units":"","sum_comment":"","sum_foreign_units":"","sum":"","sum_foreign_comment":"","sum_foreign":""},"56":{"sum_comment":"","sum_foreign_comment":"","sum_foreign":"","sum":"9800"},"57":{"sum_comment":"","sum_foreign_comment":"","sum_foreign":"","sum":""},"58":{"sum_comment":"","sum_foreign_comment":"","sum_foreign":"","sum":""},"59":{"sum_comment":"","sum_foreign_comment":"","sum_foreign":"","sum":""},"60":{"sum_comment":"","sum_foreign_comment":"","sum_foreign":"","sum":"476"},"61":{"sum_units":"","sum_comment":"","sum_foreign_units":"","sum":"","sum_foreign_comment":"","sum_foreign":""},"62":{"sum_comment":"","sum_foreign_comment":"","sum_foreign":"","sum":"4500"},"63":{"sum_comment":"","sum_units":"","sum_foreign":"","sum":"","sum_foreign_comment":""},"64":{"sum_comment":"","sum_units":"","sum_foreign":"","sum":"","sum_foreign_comment":""}},"intro":{"isnotdeclaration":"FALSE","declaration_year":"2013"}}