{"income":{"5":{"value":"226595","family_comment":"","value_unclear":false,"value_hidden":false,"family_unclear":false,"family":"7193","comment":""},"6":{"value":"223953","family_hidden":false,"value_hidden":false,"family_comment":"","family_comment_hidden":false,"comment":"","family":""},"7":{"value":"","value_unclear":false,"family_hidden":false,"value_hidden":false,"family_comment":"","source_name":"","family":"","comment":"","source_name_hidden":false},"8":{"value":"","comment_hidden":false,"family_hidden":false,"value_hidden":false,"family_comment":"","family":"","comment":""},"9":{"value":"","family_comment":"","comment_hidden":false,"family_hidden":false,"value_hidden":false,"family_unclear":false,"family":"","comment":""},"10":{"value":"","comment_hidden":false,"family_hidden":false,"value_hidden":false,"family_comment":"","family":"","comment":""},"11":{"value":"","value_unclear":false,"comment_hidden":false,"family_hidden":false,"value_hidden":false,"family_comment":"","family":"","comment":""},"12":{"value":"","comment_hidden":false,"family_hidden":false,"value_hidden":false,"family_comment":"","family":"","comment":""},"13":{"value":"","comment_hidden":false,"family_hidden":false,"value_hidden":false,"family_comment":"","family":"","comment":""},"14":{"value":"","comment_hidden":false,"family_hidden":false,"value_hidden":false,"family_comment":"","family":"","comment":""},"15":{"value":"1507","comment_hidden":false,"family_hidden":false,"value_hidden":false,"family_comment":"","family":"","comment":""},"16":{"value":"","comment_hidden":false,"family_hidden":false,"value_hidden":false,"family_comment":"","family":"","comment":""},"17":{"value":"","comment_hidden":false,"family_hidden":false,"value_hidden":false,"family_comment":"","family":"","comment":""},"18":{"value":"","value_unclear":false,"comment_hidden":false,"family_hidden":false,"value_hidden":false,"family_comment":"","family":"","comment":""},"19":{"value":"","comment_hidden":false,"family_hidden":false,"value_hidden":false,"family_comment":"","family":"","comment":""},"20":{"value":"1135","value_unclear":false,"family_comment":"","comment_unclear":false,"comment":"","family":"7193"}},"vehicle":{"35":[{"brand_info":"1968 куб см, у власності","sum_rent_comment":"","sum_rent_hidden":false,"year":"2012","sum_rent_unclear":false,"brand_info_hidden":false,"brand_info_unclear":false,"year_unclear":false,"sum_hidden":false,"sum_rent":"","sum":"","brand":"Volkswagen Tiguan","sum_comment":"","brand_unclear":false,"sum_rent_comment_hidden":false,"sum_comment_hidden":false,"sum_unclear":false},{"brand_info":"E250, 1796 куб. см, у користуванні","sum_rent_comment":"","brand":"Mercedes-Benz E-Class","sum_comment":"","brand_unclear":false,"year":"2010","brand_info_unclear":false,"sum":"","sum_rent":""}]},"id":"4525","declaration":{"additional_info_text":"","notfull_lostpages":"","date":"2014-03-31T00:00:00","notfull":"","additional_info":"","url":"http://static.declarations.com.ua/declarations/chosen_ones/judges_batch/329_kurko_oleh_petrovych.pdf"},"liabilities":{"54":{"sum_foreign_comment":"","sum_foreign_hidden":false,"sum_comment":"","sum_hidden":false,"sum_comment_hidden":false,"sum":"280","sum_foreign":""},"55":{"sum_foreign_comment":"","sum":"","sum_hidden":false,"sum_comment":"","sum_foreign":""},"56":{"sum_foreign_comment":"","sum":"","sum_comment":"","sum_foreign":""},"57":{"sum_foreign_comment":"","sum_foreign_hidden":false,"sum_comment":"","sum_hidden":false,"sum_comment_hidden":false,"sum_unclear":false,"sum":"36370.42","sum_foreign":""},"58":{"sum_foreign_comment":"","sum_foreign_hidden":false,"sum_comment":"","sum_hidden":false,"sum_comment_hidden":false,"sum_unclear":false,"sum":"14765.72","sum_foreign":""},"59":{"sum_foreign_comment":"","sum":"","sum_hidden":false,"sum_comment":"","sum_foreign":""},"60":{"sum_foreign_comment":"","sum_foreign_hidden":false,"sum_comment":"","sum_hidden":false,"sum_comment_hidden":false,"sum_unclear":false,"sum":"","sum_foreign":""},"61":{"sum_foreign_comment":"","sum":"","sum_hidden":false,"sum_comment":"","sum_foreign":""},"62":{"sum_foreign_comment":"","sum":"","sum_comment":"","sum_hidden":false,"sum_comment_hidden":false,"sum_foreign":""},"63":{"sum_foreign_comment":"","sum":"","sum_hidden":false,"sum_comment":"","sum_foreign":""},"64":{"sum_foreign_comment":"","sum":"","sum_hidden":false,"sum_comment":"","sum_foreign":""}},"ft_src":"36370.42\n280\n14765.72\nзаступник голови вінницького апеляційного адміністративного суду\nВінницька область\nАпеляційний адміністративний суд\nОлег\nКурко О. С\nПодружжя\nКурко Н. О\nДитина\nПетрович\nКурко Олег Петрович\nОлег Петрович Курко\nОлег Курко\nКурко Олег Петрович\nКурко Олег Петрович\nКурко\nВінниця\nВінницька область\n1968 куб см, у власності\n2012\nVolkswagen Tiguan\n2010\nMercedes-Benz E-Class\nE250, 1796 куб. см, у користуванні\n1000\nВінницька область\nм. Вінниця\nВінницька область\nм. Вінниця\n360\n2013\n223953\n1507\n7193\n226595\n7193\n1135\n1968 куб см, у власності\nVolkswagen Tiguan\n2012\nE250, 1796 куб. см, у користуванні\nMercedes-Benz E-Class\n2010\n1000\nВінницька область\nм. Вінниця\n360\nВінницька область\nм. Вінниця\nКурко Олег Петрович\nОлег Петрович Курко\nОлег Курко\nКурко Олег Петрович\nКурко Олег Петрович\nПодружжя\nКурко О. С\nДитина\nКурко Н. О\nОлег\nПетрович\nАпеляційний адміністративний суд\nзаступник голови вінницького апеляційного адміністративного суду\nВінницька область\nКурко\nВінниця\nВінницька область\n14765.72\n280\n36370.42\n223953\n1135\n7193\n1507\n226595\n7193\n2013\n14765.72\n36370.42\n280\nКурко О. С\nПодружжя\nДитина\nКурко Н. О\nПетрович\nКурко\nОлег\nКурко Олег Петрович\nОлег Петрович Курко\nОлег Курко\nКурко Олег Петрович\nВінницька область\nВінниця\nВінницька область\nзаступник голови вінницького апеляційного адміністративного суду\nАпеляційний адміністративний суд\nКурко Олег Петрович\n2012\nVolkswagen Tiguan\n1968 куб см, у власності\n2010\nE250, 1796 куб. см, у користуванні\nMercedes-Benz E-Class\n1507\n1135\n7193\n226595\n7193\n223953\nм. Вінниця\nВінницька область\n1000\nм. Вінниця\nВінницька область\n360\n2013","general":{"inn":"","name":"Олег","inn_unclear":false,"family":[{"inn":"","inn_hidden":true,"relations_unclear":false,"relations_hidden":false,"relations_other":"","relations":"Подружжя","name_hidden":false,"family_name":"Курко О. С","name_unclear":false},{"inn":"","inn_hidden":false,"relations_unclear":false,"relations_hidden":false,"relations_other":"","relations":"Дитина","name_hidden":false,"family_name":"Курко Н. О","name_unclear":false}],"inn_hidden":true,"family_raw":"","last_name":"Курко","post":{"post_unclear":false,"post":"заступник голови вінницького апеляційного адміністративного суду","candidate":"","office_hidden":false,"region":"Вінницька область","office":"Апеляційний адміністративний суд","office_unclear":false,"region_hidden":false},"full_name_suggest":{"output":"Курко Олег Петрович","input":["Курко Олег Петрович","Олег Петрович Курко","Олег Курко"]},"full_name":"Курко Олег Петрович","addresses":[{"place_city_type_unclear":false,"place_address":"","place_district_hidden":false,"place_city_type":"Місто","place_city_hidden":false,"place_city_type_hidden":false,"place":"Вінницька область","place_district":"","place_unclear":false,"place_city":"Вінниця","place_city_unclear":false,"place_hidden":false,"place_address_hidden":true}],"patronymic":"Петрович","last_name_unclear":false,"name_unclear":false},"source":"VULYK","estate":{"23":[{"space_hidden":false,"costs":"","costs_comment":"","address_hidden":true,"region_hidden":false,"space_comment":"","space_unclear":false,"space":"1000","address":"м. Вінниця","space_comment_unclear":false,"region":"Вінницька область","costs_rent_comment":"","costs_unclear":false,"space_comment_hidden":false,"space_units":"м²","costs_rent":""}],"24":[{"costs":"","costs_comment":"","address_hidden":true,"region_hidden":false,"space_comment":"","space":"360","address":"м. Вінниця","region":"Вінницька область","address_unclear":false,"costs_rent_comment":"","space_comment_unclear":false,"space_units":"м²","costs_rent":""}]},"intro":{"declaration_year":"2013","isnotdeclaration":"","declaration_year_unclear":false,"declaration_year_hidden":false}}