{"ft_src":"800\n535330\n74,85\n2519\nFALSE\nп.17 приписка: адвокатская;п.20 приписка: пенсия;п 23.10 в декларации указано 0.0800 га. Я внес 800 (кв.м);п 23.10 адрес не указан (похоже что не написан вообще, а не скрыт);п 25.10 аналогично\nFALSE\nFALSE\n2013\n227821\n113000\n394212\n112000\n112000\n1000\n270\n54121\nп.17 приписка: адвокатская;п.20 приписка: пенсия;п 23.10 в декларации указано 0.0800 га. Я внес 800 (кв.м);п 23.10 адрес не указан (похоже что не написан вообще, а не скрыт);п 25.10 аналогично\nFALSE\nFALSE\n800\n535330\n74,85\nСуддя Апеляційного суду Запорізької області\nДочка Жовніренко Юлія Ігорівна\nЖовніренко\nЖовніренко Валентина Петрівна\nВалентина Петрівна Жовніренко\nВалентина Жовніренко\nЖовніренко Валентина Петрівна\nВалентина\nЖовніренко Валентина Петрівна\nЗагальний апеляційний суд\nСуддя\nЗапорізька область\nПетрівна\n227821\n1000\n54121\n394212\n113000\n112000\n112000\n270\n2519\n2013\nFALSE\nЖовніренко\nПетрівна\nДочка Жовніренко Юлія Ігорівна\nЖовніренко Валентина Петрівна\nВалентина Петрівна Жовніренко\nВалентина Жовніренко\nЖовніренко Валентина Петрівна\nВалентина\nСуддя Апеляційного суду Запорізької області\nСуддя\nЗапорізька область\nЗагальний апеляційний суд\nЖовніренко Валентина Петрівна","estate":{"23":[{"costs":"","address":"","space_units":"","costs_rent_comment":"","space":"800","costs_comment":"","costs_rent":"","space_comment":"","region":"","location_raw":""},{"costs":"","address":"","space_units":"","costs_rent_comment":"","space":"","costs_comment":"","costs_rent":"","space_comment":"","region":"","location_raw":""},{"costs":"","address":"","space_units":"","costs_rent_comment":"","space":"","costs_comment":"","costs_rent":"","space_comment":"","region":"","location_raw":""}],"25":[{"costs":"535330","address":"","space_units":"","costs_rent_comment":"","space":"74,85","costs_comment":"","costs_rent":"","space_comment":"","region":"","location_raw":""}]},"id":"4584","income":{"5":{"family_comment":"","value":"394212","family":"113000","comment":""},"6":{"family_comment":"","value":"227821","family":"0","comment":""},"7":{"family":"0","family_comment":"","value":"0","comment":"","source_name":"0"},"8":{"family_comment":"","value":"0","family":"0","comment":""},"9":{"family_comment":"","value":"270","family":"0","comment":""},"10":{"family_comment":"","value":"0","family":"0","comment":""},"11":{"family_comment":"","value":"0","family":"0","comment":""},"12":{"family_comment":"","value":"0","family":"0","comment":""},"13":{"family_comment":"","value":"0","family":"0","comment":""},"14":{"family_comment":"","value":"0","family":"0","comment":""},"15":{"family_comment":"","value":"0","family":"0","comment":""},"16":{"family_comment":"","value":"112000","family":"112000","comment":""},"17":{"family_comment":"","value":"0","family":"1000","comment":""},"18":{"family_comment":"","value":"0","family":"0","comment":""},"19":{"family_comment":"","value":"0","family":"0","comment":""},"20":{"family_comment":"","value":"54121","family":"0","comment":""},"21":[{"country_comment":"","uah_equal":"0","country":"0","cur":"0"},{"country_comment":"","uah_equal":"0","country":"0","cur":"0"},{"country_comment":"","uah_equal":"0","country":"0","cur":"0"},{"country_comment":"","uah_equal":"0","country":"0","cur":"0"},{"country_comment":"","uah_equal":"0","country":"0","cur":"0"}],"22":[{"country_comment":"","uah_equal":"0","country":"0","cur":"0"},{"country_comment":"","uah_equal":"0","country":"0","cur":"0"},{"country_comment":"","uah_equal":"0","country":"0","cur":"0"},{"country_comment":"","uah_equal":"0","country":"0","cur":"0"},{"country_comment":"","uah_equal":"0","country":"0","cur":"0"}]},"banks":{"45":[{"sum_units":"UAH","sum_comment":"","sum_foreign_units":"","sum":"2519","sum_foreign_comment":"","sum_foreign":""},{"sum_units":"USD","sum_comment":"","sum_foreign_units":"","sum":"","sum_foreign_comment":"","sum_foreign":""},{"sum_units":"EUR","sum_comment":"","sum_foreign_units":"","sum":"","sum_foreign_comment":"","sum_foreign":""}],"46":[{"sum_units":"UAH","sum_comment":"","sum_foreign_units":"","sum":"","sum_foreign_comment":"","sum_foreign":""},{"sum_units":"USD","sum_comment":"","sum_foreign_units":"","sum":"","sum_foreign_comment":"","sum_foreign":""},{"sum_units":"EUR","sum_comment":"","sum_foreign_units":"","sum":"","sum_foreign_comment":"","sum_foreign":""}],"47":[{"sum_units":"","sum_comment":"","sum_foreign_units":"","sum":"","sum_foreign_comment":"","sum_foreign":""}],"48":[{"sum_units":"","sum_comment":"","sum_foreign_units":"","sum":"","sum_foreign_comment":"","sum_foreign":""}],"49":[{"sum_units":"","sum_comment":"","sum_foreign_units":"","sum":"","sum_foreign_comment":"","sum_foreign":""}],"50":[{"sum_units":"","sum_comment":"","sum_foreign_units":"","sum":"","sum_foreign_comment":"","sum_foreign":""}],"51":[{"sum_units":"UAH","sum_comment":"","sum_foreign_units":"","sum":"","sum_foreign_comment":"","sum_foreign":""},{"sum_units":"USD","sum_comment":"","sum_foreign_units":"","sum":"","sum_foreign_comment":"","sum_foreign":""},{"sum_units":"EUR","sum_comment":"","sum_foreign_units":"","sum":"","sum_foreign_comment":"","sum_foreign":""}],"52":[{"sum_units":"","sum_comment":"","sum_foreign_units":"","sum":"","sum_foreign_comment":"","sum_foreign":""}],"53":[{"sum_units":"","sum_comment":"","sum_foreign_units":"","sum":"","sum_foreign_comment":"","sum_foreign":""}]},"declaration":{"notfull_lostpages":"","additional_info_text":"п.17 приписка: адвокатская;п.20 приписка: пенсия;п 23.10 в декларации указано 0.0800 га. Я внес 800 (кв.м);п 23.10 адрес не указан (похоже что не написан вообще, а не скрыт);п 25.10 аналогично","additional_info":"FALSE","notfull":"FALSE","url":"http://static.declarations.com.ua/declarations/sudy/apeliatsiini_sudy_oblastei__m.kyieva/zaporizka/jovnirenko.pdf","needs_scancopy_check":false},"general":{"family_raw":"Дочка Жовніренко Юлія Ігорівна","name":"Валентина","full_name_suggest":{"input":["Жовніренко Валентина Петрівна","Валентина Петрівна Жовніренко","Валентина Жовніренко"],"output":"Жовніренко Валентина Петрівна"},"post_raw":"Суддя Апеляційного суду Запорізької області","name_unclear":false,"patronymic":"Петрівна","patronymic_unclear":false,"last_name_hidden":false,"patronymic_hidden":false,"inn":"","addresses_raw_hidden":true,"last_name":"Жовніренко","full_name":"Жовніренко Валентина Петрівна","post":{"office":"Загальний апеляційний суд","region":"Запорізька область","post":"Суддя"},"addresses_raw":"приховано","name_hidden":false,"last_name_unclear":false},"liabilities":{"54":{"sum_comment":"","sum_foreign_comment":"","sum_foreign":"","sum":""},"55":{"sum_units":"","sum_comment":"","sum_foreign_units":"","sum":"","sum_foreign_comment":"","sum_foreign":""},"56":{"sum_comment":"","sum_foreign_comment":"","sum_foreign":"","sum":""},"57":{"sum_comment":"","sum_foreign_comment":"","sum_foreign":"","sum":""},"58":{"sum_comment":"","sum_foreign_comment":"","sum_foreign":"","sum":""},"59":{"sum_comment":"","sum_foreign_comment":"","sum_foreign":"","sum":""},"60":{"sum_comment":"","sum_foreign_comment":"","sum_foreign":"","sum":""},"61":{"sum_units":"","sum_comment":"","sum_foreign_units":"","sum":"","sum_foreign_comment":"","sum_foreign":""},"62":{"sum_comment":"","sum_foreign_comment":"","sum_foreign":"","sum":""},"63":{"sum_comment":"","sum_units":"","sum_foreign":"","sum":"","sum_foreign_comment":""},"64":{"sum_comment":"","sum_units":"","sum_foreign":"","sum":"","sum_foreign_comment":""}},"intro":{"isnotdeclaration":"FALSE","declaration_year":"2013"}}