{"ft_src":"Mitsubishi,Outlander\n2008\nKia,Rio\n2012\n212,5\n1750\n39,7\n6392\n1068\n1812\nTRUE\n1) стор. 9, розділ V, п. 45, 46, 51 - декларант вказав, у якому саме банку він має вклади;;2) стор. 9, розділ VI, п. 56, 57, 58, 60, 62, 64 - декларант конкретизував, перед якими установами має фінансові зобов’язання він та члени його сім’ї;Note: стор. 8, розділ V. Сума, вказана у п. 45, менша за суму, вказану у п. 46, хоча такого не може бути.\n9.00\nFALSE\nFALSE\n2013\n90343\n228273\n90361\n228340\n18\n67\nMitsubishi,Outlander\n2008\nKia,Rio\n2012\n9.00\n1) стор. 9, розділ V, п. 45, 46, 51 - декларант вказав, у якому саме банку він має вклади;;2) стор. 9, розділ VI, п. 56, 57, 58, 60, 62, 64 - декларант конкретизував, перед якими установами має фінансові зобов’язання він та члени його сім’ї;Note: стор. 8, розділ V. Сума, вказана у п. 45, менша за суму, вказану у п. 46, хоча такого не може бути.\nFALSE\nTRUE\n1750\n212,5\n39,7\nГолова Любомльського районного суду Волинської області\nДружина Чишій Н.М.;син Чишій М.С.\nЧишій\nЧишій Степан Степанович\nСтепан Степанович Чишій\nСтепан Чишій\nЧишій Степан Степанович\nСтепан\nЧишій Степан Степанович\nЗагальний місцевий суд\nГолова Любомльського районного суду Волинської області\nВолинська область\nСтепанович\n106913\n28732\n16634\n528\n2420\n10618\n1110\n228273\n90343\n228340\n90361\n67\n18\n1812\n1068\n6392\n2013\nFALSE\n1110\n16634\n28732\n2420\n10618\n528\n106913\nЧишій\nСтепанович\nДружина Чишій Н.М.;син Чишій М.С.\nЧишій Степан Степанович\nСтепан Степанович Чишій\nСтепан Чишій\nЧишій Степан Степанович\nСтепан\nГолова Любомльського районного суду Волинської області\nГолова Любомльського районного суду Волинської області\nВолинська область\nЗагальний місцевий суд\nЧишій Степан Степанович","estate":{"23":[{"costs":"","address":"","space_units":"","costs_rent_comment":"","space":"","costs_comment":"","costs_rent":"","space_comment":"","region":"","location_raw":""},{"costs":"","address":"","space_units":"","costs_rent_comment":"","space":"","costs_comment":"","costs_rent":"","space_comment":"","region":"","location_raw":""},{"costs":"","address":"","space_units":"","costs_rent_comment":"","space":"","costs_comment":"","costs_rent":"","space_comment":"","region":"","location_raw":""}],"25":[{"costs":"","address":"","space_units":"","costs_rent_comment":"","space":"39,7","costs_comment":"","costs_rent":"","space_comment":"","region":"","location_raw":"приховано"}],"29":[{"costs_property_comment":"","address":"","space_units":"","costs_rent_comment":"","space":"1750","space_comment":"","costs_property":"","region":"","location_raw":"приховано","costs_rent":""}],"30":[{"costs_property_comment":"","address":"","space_units":"","costs_rent_comment":"","space":"212,5","space_comment":"","costs_property":"","region":"","location_raw":"приховано","costs_rent":""}]},"vehicle":{"40":[{"sum_comment":"","brand_info":"","sum":"","sum_rent_comment":"","year":"2008","brand":"Mitsubishi,Outlander","sum_rent":"","brand_hidden":false},{"sum_comment":"","brand_info":"","sum":"","sum_rent_comment":"","year":"2012","brand":"Kia,Rio","sum_rent":"","brand_hidden":false}]},"id":"4909","income":{"5":{"family_comment":"","value":"228340","family":"90361","comment":""},"6":{"family_comment":"","value":"228273","family":"90343","comment":""},"7":{"family":"0","family_comment":"","value":"0","comment":"","source_name":"0"},"8":{"family_comment":"","value":"0","family":"0","comment":""},"9":{"family_comment":"","value":"67","family":"18","comment":""},"10":{"family_comment":"","value":"0","family":"0","comment":""},"11":{"family_comment":"","value":"0","family":"0","comment":""},"12":{"family_comment":"","value":"0","family":"0","comment":""},"13":{"family_comment":"","value":"0","family":"0","comment":""},"14":{"family_comment":"","value":"0","family":"0","comment":""},"15":{"family_comment":"","value":"0","family":"0","comment":""},"16":{"family_comment":"","value":"0","family":"0","comment":""},"17":{"family_comment":"","value":"0","family":"0","comment":""},"18":{"family_comment":"","value":"0","family":"0","comment":""},"19":{"family_comment":"","value":"0","family":"0","comment":""},"20":{"family_comment":"","value":"0","family":"0","comment":""},"21":[{"country_comment":"","uah_equal":"0","country":"0","cur":"0"},{"country_comment":"","uah_equal":"0","country":"0","cur":"0"},{"country_comment":"","uah_equal":"0","country":"0","cur":"0"},{"country_comment":"","uah_equal":"0","country":"0","cur":"0"},{"country_comment":"","uah_equal":"0","country":"0","cur":"0"}],"22":[{"country_comment":"","uah_equal":"0","country":"0","cur":"0"},{"country_comment":"","uah_equal":"0","country":"0","cur":"0"},{"country_comment":"","uah_equal":"0","country":"0","cur":"0"},{"country_comment":"","uah_equal":"0","country":"0","cur":"0"},{"country_comment":"","uah_equal":"0","country":"0","cur":"0"}]},"banks":{"45":[{"sum_units":"UAH","sum_comment":"","sum_foreign_units":"","sum":"1812","sum_foreign_comment":"","sum_foreign":""},{"sum_units":"USD","sum_comment":"","sum_foreign_units":"","sum":"","sum_foreign_comment":"","sum_foreign":""},{"sum_units":"EUR","sum_comment":"","sum_foreign_units":"","sum":"","sum_foreign_comment":"","sum_foreign":""}],"46":[{"sum_units":"UAH","sum_comment":"","sum_foreign_units":"","sum":"6392","sum_foreign_comment":"","sum_foreign":""},{"sum_units":"USD","sum_comment":"","sum_foreign_units":"","sum":"","sum_foreign_comment":"","sum_foreign":""},{"sum_units":"EUR","sum_comment":"","sum_foreign_units":"","sum":"","sum_foreign_comment":"","sum_foreign":""}],"47":[{"sum_units":"","sum_comment":"","sum_foreign_units":"","sum":"","sum_foreign_comment":"","sum_foreign":""}],"48":[{"sum_units":"","sum_comment":"","sum_foreign_units":"","sum":"","sum_foreign_comment":"","sum_foreign":""}],"49":[{"sum_units":"","sum_comment":"","sum_foreign_units":"","sum":"","sum_foreign_comment":"","sum_foreign":""}],"50":[{"sum_units":"","sum_comment":"","sum_foreign_units":"","sum":"","sum_foreign_comment":"","sum_foreign":""}],"51":[{"sum_units":"UAH","sum_comment":"","sum_foreign_units":"","sum":"1068","sum_foreign_comment":"","sum_foreign":""},{"sum_units":"USD","sum_comment":"","sum_foreign_units":"","sum":"","sum_foreign_comment":"","sum_foreign":""},{"sum_units":"EUR","sum_comment":"","sum_foreign_units":"","sum":"","sum_foreign_comment":"","sum_foreign":""}],"52":[{"sum_units":"","sum_comment":"","sum_foreign_units":"","sum":"","sum_foreign_comment":"","sum_foreign":""}],"53":[{"sum_units":"","sum_comment":"","sum_foreign_units":"","sum":"","sum_foreign_comment":"","sum_foreign":""}]},"declaration":{"notfull_lostpages":"9.00","additional_info_text":"1) стор. 9, розділ V, п. 45, 46, 51 - декларант вказав, у якому саме банку він має вклади;;2) стор. 9, розділ VI, п. 56, 57, 58, 60, 62, 64 - декларант конкретизував, перед якими установами має фінансові зобов’язання він та члени його сім’ї;Note: стор. 8, розділ V. Сума, вказана у п. 45, менша за суму, вказану у п. 46, хоча такого не може бути.","additional_info":"TRUE","notfull":"FALSE","url":"http://static.declarations.com.ua/lustration/5480185f0364a.pdf","needs_scancopy_check":false},"general":{"family_raw":"Дружина Чишій Н.М.;син Чишій М.С.","name":"Степан","full_name_suggest":{"input":["Чишій Степан Степанович","Степан Степанович Чишій","Степан Чишій"],"output":"Чишій Степан Степанович"},"post_raw":"Голова Любомльського районного суду Волинської області","name_unclear":false,"patronymic":"Степанович","patronymic_unclear":false,"last_name_hidden":false,"patronymic_hidden":false,"inn":"","addresses_raw_hidden":true,"last_name":"Чишій","full_name":"Чишій Степан Степанович","post":{"office":"Загальний місцевий суд","region":"Волинська область","post":"Голова Любомльського районного суду Волинської області"},"addresses_raw":"приховано","name_hidden":false,"last_name_unclear":false},"liabilities":{"54":{"sum_comment":"","sum_foreign_comment":"","sum_foreign":"","sum":""},"55":{"sum_units":"","sum_comment":"","sum_foreign_units":"","sum":"","sum_foreign_comment":"","sum_foreign":""},"56":{"sum_comment":"","sum_foreign_comment":"","sum_foreign":"","sum":"2420"},"57":{"sum_comment":"","sum_foreign_comment":"","sum_foreign":"","sum":"16634"},"58":{"sum_comment":"","sum_foreign_comment":"","sum_foreign":"","sum":"1110"},"59":{"sum_comment":"","sum_foreign_comment":"","sum_foreign":"","sum":""},"60":{"sum_comment":"","sum_foreign_comment":"","sum_foreign":"","sum":"528"},"61":{"sum_units":"","sum_comment":"","sum_foreign_units":"","sum":"","sum_foreign_comment":"","sum_foreign":""},"62":{"sum_comment":"","sum_foreign_comment":"","sum_foreign":"","sum":"10618"},"63":{"sum_comment":"","sum_units":"грн","sum_foreign":"","sum":"106913","sum_foreign_comment":""},"64":{"sum_comment":"","sum_units":"грн","sum_foreign":"","sum":"28732","sum_foreign_comment":""}},"intro":{"isnotdeclaration":"FALSE","declaration_year":"2013"}}