{"income":{"5":{"value":"12849","comment_hidden":false,"family_comment":"","family":"70316","comment":"","family_comment_hidden":false},"6":{"value":"841","family_comment":"","comment_hidden":false,"family_hidden":false,"family_unclear":false,"family_comment_hidden":false,"comment":"","family":"70316"},"7":{"value":"","comment_hidden":false,"family_comment_hidden":false,"family_comment":"","source_name":"","family":"","comment":"","source_name_hidden":false},"8":{"family_comment":"","value":"","family":"","comment":""},"9":{"value":"","family_comment":"","value_unclear":false,"family_unclear":false,"comment_unclear":false,"comment":"","family":""},"10":{"family_comment":"","family_unclear":false,"value":"","family":"","comment":""},"11":{"family_comment":"","value":"48","family":"","comment":""},"12":{"family_comment":"","value":"","family":"","comment":""},"13":{"family_comment":"","value":"","family":"","comment":""},"14":{"family_comment":"","value":"","family":"","comment":""},"15":{"family_comment":"","value":"","comment_unclear":false,"family":"","comment":""},"16":{"family_comment":"","value":"","comment_unclear":false,"family":"","comment":""},"17":{"family_comment":"","value":"","family":"","comment":""},"18":{"family_comment":"","value":"","family":"","comment":""},"19":{"family_comment":"","value":"","family":"","comment":""},"20":{"value":"11960","family_comment":"","value_unclear":false,"family_unclear":false,"family_comment_unclear":false,"family_comment_hidden":false,"comment":"","family":""}},"vehicle":{"35":[{"brand_info":"1299 куб. см., 64 кВт","sum_rent_comment":"","brand":"Toyota Yaris","sum_comment":"","brand_unclear":false,"year":"2008","sum_hidden":false,"brand_info_unclear":false,"sum":"","sum_rent":""}],"40":[{"brand_info":"1498 куб. см., 64 кВт","sum_rent_comment":"","brand":"Daewoo Lanos","sum_comment":"","brand_unclear":false,"year":"2003","brand_info_unclear":false,"sum":"","sum_rent":""}]},"id":"5366","declaration":{"additional_info_text":"","notfull_lostpages":"","date":"2014-03-19T00:00:00","notfull":"","additional_info":"","url":"http://static.declarations.com.ua/declarations/chosen_ones/judges_batch/1192_ilchyshyn_nadiia_vasylivna.pdf"},"liabilities":{"54":{"sum_foreign_comment":"","sum_foreign_hidden":false,"sum_comment":"","sum_comment_unclear":false,"sum_hidden":false,"sum_comment_hidden":false,"sum_unclear":false,"sum":"","sum_foreign":""},"55":{"sum_foreign_comment":"","sum_comment_hidden":false,"sum":"","sum_comment":"","sum_foreign":""},"56":{"sum_foreign_comment":"","sum":"","sum_comment":"","sum_comment_unclear":false,"sum_foreign":""},"57":{"sum_foreign_comment":"","sum":"","sum_comment":"","sum_hidden":false,"sum_comment_hidden":false,"sum_unclear":false,"sum_foreign":""},"58":{"sum_foreign_comment":"","sum":"","sum_comment":"","sum_hidden":false,"sum_comment_hidden":false,"sum_foreign":""},"59":{"sum_foreign_comment":"","sum":"","sum_comment":"","sum_comment_unclear":false,"sum_unclear":false,"sum_foreign":""},"60":{"sum_foreign_comment":"","sum":"","sum_comment":"","sum_hidden":false,"sum_comment_hidden":false,"sum_unclear":false,"sum_foreign":""},"61":{"sum_foreign_comment":"","sum":"","sum_comment":"","sum_foreign":""},"62":{"sum_foreign_comment":"","sum":"","sum_comment":"","sum_foreign":""},"63":{"sum_foreign_comment":"","sum":"","sum_comment":"","sum_hidden":false,"sum_comment_hidden":false,"sum_foreign":""},"64":{"sum_foreign_comment":"","sum":"","sum_comment":"","sum_foreign":""}},"ft_src":"суддя львівського апеляційного адміністративного суду\nЛьвівська область\nАпеляційний адміністративний суд\nНадія\nІльчишин В. Д\nПодружжя\nІльчишин М. В\nДитина\nІльчишин С. В\nДитина\nВасилівна\nІльчишин Надія Василівна\nНадія Василівна Ільчишин\nНадія Ільчишин\nІльчишин Надія Василівна\nІльчишин\nІльчишин Надія Василівна\nToyota Yaris\n1299 куб. см., 64 кВт\n2008\n2003\nDaewoo Lanos\n1498 куб. см., 64 кВт\n725\n1033\n48.1\n90\n334.2\n2013\n70316\n841\n48\n70316\n12849\n11960\n1299 куб. см., 64 кВт\nToyota Yaris\n2008\n1498 куб. см., 64 кВт\nDaewoo Lanos\n2003\n2013\nІльчишин Надія Василівна\nНадія Василівна Ільчишин\nНадія Ільчишин\nІльчишин Надія Василівна\nНадія\nПодружжя\nІльчишин В. Д\nДитина\nІльчишин М. В\nДитина\nІльчишин С. В\nІльчишин Надія Василівна\nВасилівна\nАпеляційний адміністративний суд\nЛьвівська область\nсуддя львівського апеляційного адміністративного суду\nІльчишин\n70316\n841\n11960\n12849\n70316\n48\n725\n1033\n90\n334.2\n48.1\nПодружжя\nІльчишин В. Д\nДитина\nІльчишин М. В\nДитина\nІльчишин С. В\nВасилівна\nІльчишин\nНадія\nІльчишин Надія Василівна\nНадія Василівна Ільчишин\nНадія Ільчишин\nІльчишин Надія Василівна\nЛьвівська область\nАпеляційний адміністративний суд\nсуддя львівського апеляційного адміністративного суду\nІльчишин Надія Василівна\n2008\n1299 куб. см., 64 кВт\nToyota Yaris\n2003\n1498 куб. см., 64 кВт\nDaewoo Lanos\n48\n11960\n12849\n70316\n841\n70316\n48.1\n725\n1033\n90\n334.2\n2013","general":{"inn":"","name":"Надія","family":[{"inn":"","relations":"Подружжя","inn_unclear":false,"relations_hidden":false,"inn_hidden":true,"relations_other":"","name_hidden":true,"family_name":"Ільчишин В. Д","name_unclear":false},{"inn":"","relations":"Дитина","inn_unclear":false,"family_name":"Ільчишин М. В","inn_hidden":false,"relations_other":"","name_hidden":false,"name_unclear":false},{"inn":"","relations":"Дитина","relations_other":"","inn_hidden":false,"family_name":"Ільчишин С. В","name_hidden":false,"name_unclear":false}],"patronymic":"Василівна","inn_hidden":true,"family_raw":"","last_name":"Ільчишин","post":{"post_unclear":false,"region_unclear":false,"post":"суддя львівського апеляційного адміністративного суду","office":"Апеляційний адміністративний суд","region":"Львівська область","post_hidden":false,"office_hidden":false,"office_unclear":false,"region_hidden":false},"last_name_unclear":false,"full_name":"Ільчишин Надія Василівна","addresses":[{"place_district":"","place_city_hidden":true,"place_city":"","place_city_type_hidden":true,"place_district_hidden":true,"place_city_type":"","place_address_hidden":true,"place_address":"","place_hidden":true,"place":""}],"full_name_suggest":{"output":"Ільчишин Надія Василівна","input":["Ільчишин Надія Василівна","Надія Василівна Ільчишин","Надія Ільчишин"]},"name_unclear":false},"source":"VULYK","estate":{"23":[{"space_hidden":false,"costs":"","costs_comment":"","costs_hidden":false,"address_hidden":true,"region_hidden":true,"space_comment":"","space_unclear":false,"space":"725","address":"","region":"","space_units_unclear":false,"costs_unclear":false,"space_units":"м²","costs_rent":"","costs_rent_comment":""},{"costs_rent":"","region":"","costs":"","costs_rent_comment":"","costs_comment":"","address_hidden":false,"region_hidden":false,"space_comment":"","space_units":"м²","space":"1033","address":""}],"24":[{"space_unclear":false,"costs":"","costs_comment":"","costs_hidden":false,"address_hidden":true,"region_hidden":true,"space_comment":"","space":"90","address":"","region":"","space_units_unclear":false,"space_comment_unclear":false,"space_comment_hidden":false,"space_units":"м²","costs_rent":"","costs_rent_comment":""},{"space":"334.2","costs":"","costs_rent_comment":"","costs_comment":"","space_comment_hidden":false,"space_comment":"","space_units":"м²","costs_rent":"","address":""}],"31":[{"space_unclear":false,"address_hidden":true,"region_hidden":true,"space_comment":"","space":"48.1","address":"","region":"","costs_property":"","costs_rent_comment":"","space_units":"м²","costs_property_comment":"","costs_rent":""}]},"intro":{"declaration_year":"2013"}}