{"ft_src":"Toyota,RAV4\n336563\n2013\nToyota,Land Cruiser 150\n2010\nNissan,Micra\n2008\nToyota,Camry\n2012\nсмт Гуйва Житомирського р-ну\n2100\nмс Полонне Хмельницької обл.\n1564\nУкраїна, смт. Гуйва\n164\nУкраїна смт Гуйва Житомирського р-ну\n384,1\nУкраїна м. Полонне Хмельницької обл.\n74,26\nУкраїна м. Житомир\n141,28\nБолгарія м. Варна\n21,9\nУкраїна м.Хмельницький\n92\nБолгарія Варна\n55388\n21,9\nFALSE\nFALSE\nFALSE\n2013\n249974\n230240\n12617\n12617\n483016\n433207\n190350\n220425\n336563\nToyota,RAV4\n2013\nToyota,Land Cruiser 150\n2010\nNissan,Micra\n2008\nToyota,Camry\n2012\nFALSE\nFALSE\nУкраїна смт Гуйва Житомирського р-ну\n384,1\nУкраїна м. Полонне Хмельницької обл.\n74,26\nУкраїна м.Хмельницький\n92\nБолгарія Варна\n55388\n21,9\nУкраїна, смт. Гуйва\n164\nсмт Гуйва Житомирського р-ну\n2100\nмс Полонне Хмельницької обл.\n1564\nУкраїна м. Житомир\n141,28\nБолгарія м. Варна\n21,9\nСуддя Житомирського апеляційного адміністративного суду\nЧоловік Жизнєвський Юрій Васильович\nЖитомирська\nЖитомир\nЖизневська\nЖизневська Анжела Владиславівна\nАнжела Владиславівна Жизневська\nАнжела Жизневська\nЖизневська Анжела Владиславівна\nАнжела\nЖизневська Анжела Владиславівна\nАпеляційний адміністративний суд\nСуддя\nЖитомирська область\nВладиславівна\nм. Житомир\n232001\n11309\n2875\n16100\n2875\n32900\n230240\n249974\n220425\n433207\n483016\n190350\n12617\n12617\n2013\nFALSE\n11309\n2875\n16100\n2875\n32900\n232001\nЖизневська\nВладиславівна\nЧоловік Жизнєвський Юрій Васильович\nЖизневська Анжела Владиславівна\nАнжела Владиславівна Жизневська\nАнжела Жизневська\nЖизневська Анжела Владиславівна\nАнжела\nСуддя Житомирського апеляційного адміністративного суду\nЖитомирська\nЖитомир\nСуддя\nЖитомирська область\nАпеляційний адміністративний суд\nЖизневська Анжела Владиславівна\nм. Житомир","estate":{"23":[{"costs":"","address":"","space_units":"","costs_rent_comment":"","space":"","costs_comment":"","costs_rent":"","space_comment":"","region":"","location_raw":""},{"costs":"","address":"","space_units":"","costs_rent_comment":"","space":"","costs_comment":"","costs_rent":"","space_comment":"","region":"","location_raw":""},{"costs":"","address":"","space_units":"","costs_rent_comment":"","space":"","costs_comment":"","costs_rent":"","space_comment":"","region":"","location_raw":""}],"25":[{"costs":"","address":"","space_units":"","costs_rent_comment":"","space":"92","costs_comment":"","costs_rent":"","space_comment":"","region":"","location_raw":"Україна м.Хмельницький"},{"costs":"55388","address":"","space_units":"","costs_rent_comment":"","space":"21,9","costs_comment":"","costs_rent":"","space_comment":"","region":"","location_raw":"Болгарія Варна"}],"29":[{"costs_property_comment":"","address":"","space_units":"","costs_rent_comment":"","space":"2100","space_comment":"","costs_property":"","region":"","location_raw":"смт Гуйва Житомирського р-ну","costs_rent":""},{"costs_property_comment":"","address":"","space_units":"","costs_rent_comment":"","space":"1564","space_comment":"","costs_property":"","region":"","location_raw":"мс Полонне Хмельницької обл.","costs_rent":""}],"30":[{"costs_property_comment":"","address":"","space_units":"","costs_rent_comment":"","space":"384,1","space_comment":"","costs_property":"","region":"","location_raw":"Україна смт Гуйва Житомирського р-ну","costs_rent":""},{"costs_property_comment":"","address":"","space_units":"","costs_rent_comment":"","space":"74,26","space_comment":"","costs_property":"","region":"","location_raw":"Україна м. Полонне Хмельницької обл.","costs_rent":""}],"31":[{"costs_property_comment":"","address":"","space_units":"","costs_rent_comment":"","space":"141,28","space_comment":"","costs_property":"","region":"","location_raw":"Україна м. Житомир","costs_rent":""},{"costs_property_comment":"","address":"","space_units":"","costs_rent_comment":"","space":"21,9","space_comment":"","costs_property":"","region":"","location_raw":"Болгарія м. Варна","costs_rent":""}],"33":[{"costs_property_comment":"","address":"","space_units":"","costs_rent_comment":"","space":"164","space_comment":"","costs_property":"","region":"","location_raw":"Україна, смт. Гуйва","costs_rent":""}]},"vehicle":{"35":[{"sum_comment":"","brand_info":"","sum":"336563","sum_rent_comment":"","year":"2013","brand":"Toyota,RAV4","sum_rent":"","brand_hidden":false}],"40":[{"sum_comment":"","brand_info":"","sum":"","sum_rent_comment":"","year":"2010","brand":"Toyota,Land Cruiser 150","sum_rent":"","brand_hidden":false},{"sum_comment":"","brand_info":"","sum":"","sum_rent_comment":"","year":"2008","brand":"Nissan,Micra","sum_rent":"","brand_hidden":false},{"sum_comment":"","brand_info":"","sum":"","sum_rent_comment":"","year":"2012","brand":"Toyota,Camry","sum_rent":"","brand_hidden":false}]},"id":"5939","income":{"5":{"family_comment":"","value":"433207","family":"483016","comment":""},"6":{"family_comment":"","value":"230240","family":"249974","comment":""},"7":{"family":"0","family_comment":"","value":"0","comment":"","source_name":"0"},"8":{"family_comment":"","value":"0","family":"0","comment":""},"9":{"family_comment":"","value":"0","family":"0","comment":""},"10":{"family_comment":"","value":"12617","family":"12617","comment":""},"11":{"family_comment":"","value":"0","family":"0","comment":""},"12":{"family_comment":"","value":"0","family":"0","comment":""},"13":{"family_comment":"","value":"0","family":"0","comment":""},"14":{"family_comment":"","value":"0","family":"0","comment":""},"15":{"family_comment":"","value":"0","family":"0","comment":""},"16":{"family_comment":"","value":"190350","family":"0","comment":""},"17":{"family_comment":"","value":"0","family":"0","comment":""},"18":{"family_comment":"","value":"0","family":"0","comment":""},"19":{"family_comment":"","value":"0","family":"0","comment":""},"20":{"family_comment":"","value":"0","family":"220425","comment":""},"21":[{"country_comment":"","uah_equal":"0","country":"0","cur":"0"},{"country_comment":"","uah_equal":"0","country":"0","cur":"0"},{"country_comment":"","uah_equal":"0","country":"0","cur":"0"},{"country_comment":"","uah_equal":"0","country":"0","cur":"0"},{"country_comment":"","uah_equal":"0","country":"0","cur":"0"}],"22":[{"country_comment":"","uah_equal":"0","country":"0","cur":"0"},{"country_comment":"","uah_equal":"0","country":"0","cur":"0"},{"country_comment":"","uah_equal":"0","country":"0","cur":"0"},{"country_comment":"","uah_equal":"0","country":"0","cur":"0"},{"country_comment":"","uah_equal":"0","country":"0","cur":"0"}]},"banks":{"45":[{"sum_units":"UAH","sum_comment":"","sum_foreign_units":"","sum":"","sum_foreign_comment":"","sum_foreign":""},{"sum_units":"USD","sum_comment":"","sum_foreign_units":"","sum":"","sum_foreign_comment":"","sum_foreign":""},{"sum_units":"EUR","sum_comment":"","sum_foreign_units":"","sum":"","sum_foreign_comment":"","sum_foreign":""}],"46":[{"sum_units":"UAH","sum_comment":"","sum_foreign_units":"","sum":"","sum_foreign_comment":"","sum_foreign":""},{"sum_units":"USD","sum_comment":"","sum_foreign_units":"","sum":"","sum_foreign_comment":"","sum_foreign":""},{"sum_units":"EUR","sum_comment":"","sum_foreign_units":"","sum":"","sum_foreign_comment":"","sum_foreign":""}],"47":[{"sum_units":"","sum_comment":"","sum_foreign_units":"","sum":"","sum_foreign_comment":"","sum_foreign":""}],"48":[{"sum_units":"","sum_comment":"","sum_foreign_units":"","sum":"","sum_foreign_comment":"","sum_foreign":""}],"49":[{"sum_units":"","sum_comment":"","sum_foreign_units":"","sum":"","sum_foreign_comment":"","sum_foreign":""}],"50":[{"sum_units":"","sum_comment":"","sum_foreign_units":"","sum":"","sum_foreign_comment":"","sum_foreign":""}],"51":[{"sum_units":"UAH","sum_comment":"","sum_foreign_units":"","sum":"","sum_foreign_comment":"","sum_foreign":""},{"sum_units":"USD","sum_comment":"","sum_foreign_units":"","sum":"","sum_foreign_comment":"","sum_foreign":""},{"sum_units":"EUR","sum_comment":"","sum_foreign_units":"","sum":"","sum_foreign_comment":"","sum_foreign":""}],"52":[{"sum_units":"","sum_comment":"","sum_foreign_units":"","sum":"","sum_foreign_comment":"","sum_foreign":""}],"53":[{"sum_units":"","sum_comment":"","sum_foreign_units":"","sum":"","sum_foreign_comment":"","sum_foreign":""}]},"declaration":{"notfull_lostpages":"","additional_info_text":"","additional_info":"FALSE","notfull":"FALSE","url":"http://static.declarations.com.ua/declarations/sudy/apeliatsiini_administratyvni_sudy/zhytomyrskyi/zhyznevska_declaration.pdf","needs_scancopy_check":false},"general":{"family_raw":"Чоловік Жизнєвський Юрій Васильович","name":"Анжела","full_name_suggest":{"input":["Жизневська Анжела Владиславівна","Анжела Владиславівна Жизневська","Анжела Жизневська"],"output":"Жизневська Анжела Владиславівна"},"post_raw":"Суддя Житомирського апеляційного адміністративного суду","name_unclear":false,"patronymic":"Владиславівна","patronymic_unclear":false,"last_name_hidden":false,"patronymic_hidden":false,"inn":"","addresses_raw_hidden":true,"last_name":"Жизневська","full_name":"Жизневська Анжела Владиславівна","post":{"office":"Апеляційний адміністративний суд","region":"Житомирська область","post":"Суддя"},"addresses":[{"place_district":"","place_city_type":"","place_address_type":"","place":"Житомирська","place_address":"","place_city":"Житомир"}],"name_hidden":false,"last_name_unclear":false,"addresses_raw":"м. Житомир"},"liabilities":{"54":{"sum_comment":"","sum_foreign_comment":"","sum_foreign":"","sum":""},"55":{"sum_units":"","sum_comment":"","sum_foreign_units":"","sum":"","sum_foreign_comment":"","sum_foreign":""},"56":{"sum_comment":"","sum_foreign_comment":"","sum_foreign":"2875","sum":"16100"},"57":{"sum_comment":"","sum_foreign_comment":"","sum_foreign":"","sum":""},"58":{"sum_comment":"","sum_foreign_comment":"","sum_foreign":"","sum":""},"59":{"sum_comment":"","sum_foreign_comment":"","sum_foreign":"","sum":""},"60":{"sum_comment":"","sum_foreign_comment":"","sum_foreign":"","sum":""},"61":{"sum_units":"","sum_comment":"","sum_foreign_units":"","sum":"","sum_foreign_comment":"","sum_foreign":""},"62":{"sum_comment":"","sum_foreign_comment":"","sum_foreign":"2875","sum":"32900"},"63":{"sum_comment":"","sum_units":"грн","sum_foreign":"","sum":"232001","sum_foreign_comment":""},"64":{"sum_comment":"","sum_units":"грн","sum_foreign":"","sum":"11309","sum_foreign_comment":""}},"intro":{"isnotdeclaration":"FALSE","declaration_year":"2013"}}