{"income":{"5":{"family_comment":"","value":"252665.25","value_unclear":false,"family":"4281054","comment":""},"6":{"family_comment":"","value":"238691.25","value_unclear":false,"family":"","comment":""},"7":{"source_name_unclear":false,"value":"","family_hidden":false,"value_hidden":false,"family_comment":"","source_name":"","family":"","comment":"","source_name_hidden":false},"8":{"value":"","family_hidden":false,"value_hidden":false,"family_comment":"","family":"","comment":""},"9":{"value":"","value_unclear":false,"value_hidden":false,"family_comment":"","comment_unclear":false,"comment":"","family":""},"10":{"value":"13764","family_hidden":false,"value_hidden":false,"family_comment":"","family":"","comment":""},"11":{"value":"210","family_hidden":false,"value_hidden":false,"family_comment":"","family":"","comment":""},"12":{"value":"","family_hidden":false,"value_hidden":false,"family_comment":"","family":"","comment":""},"13":{"value":"","family_hidden":false,"value_hidden":false,"family_comment":"","family":"","comment":""},"14":{"value":"","family_hidden":false,"value_hidden":false,"family_comment":"","family":"","comment":""},"15":{"value":"","family_hidden":false,"value_hidden":false,"family_comment":"","family":"","comment":""},"16":{"value":"","family_hidden":false,"value_hidden":false,"family_comment":"","family":"4281054","comment":""},"17":{"value":"","family_hidden":false,"value_hidden":false,"family_comment":"","family":"","comment":""},"18":{"value":"","comment_unclear":false,"family_hidden":false,"value_hidden":false,"family_comment":"","family":"","comment":""},"19":{"value":"","family_hidden":false,"value_hidden":false,"family_comment":"","family":"","comment":""},"20":{"value":"","value_unclear":false,"family_hidden":false,"value_hidden":false,"family_comment":"","comment_unclear":false,"comment":"","family":""}},"vehicle":{"35":[{"brand_info":"1600 куб. см.","sum_rent_comment":"","sum_rent_hidden":false,"year":"2009","sum_hidden":false,"brand_info_unclear":false,"sum_rent":"","sum":"","brand":"MINI Cooper","sum_comment":"","brand_unclear":false,"sum_rent_comment_hidden":false,"sum_comment_hidden":false,"sum_unclear":false}],"40":[{"brand_info":"","sum":"","brand":"Jeep Wrangler","sum_comment":"","brand_unclear":false,"year":"2013","brand_hidden":false,"brand_info_hidden":false,"brand_info_unclear":false,"sum_rent_comment":"","sum_rent":""}]},"id":"6282","declaration":{"additional_info_text":"","notfull_lostpages":"","date":"2014-03-14T00:00:00","notfull":"","additional_info":"","url":"http://static.declarations.com.ua/declarations/chosen_ones/judges_batch/58_kalashnikova_olena_volodymyrivna.pdf"},"liabilities":{"54":{"sum_foreign_comment":"","sum_foreign_hidden":false,"sum_comment":"","sum_hidden":false,"sum_foreign_comment_unclear":false,"sum_comment_hidden":false,"sum":"","sum_foreign":""},"55":{"sum_foreign_comment":"","sum":"","sum_hidden":false,"sum_comment":"","sum_foreign":""},"56":{"sum_foreign_comment":"","sum":"","sum_comment":"","sum_foreign":""},"57":{"sum_foreign_comment":"","sum_foreign_hidden":false,"sum_comment":"","sum_hidden":false,"sum_comment_hidden":false,"sum":"","sum_foreign":""},"58":{"sum_foreign_comment":"","sum":"","sum_comment":"","sum_hidden":false,"sum_comment_hidden":false,"sum_foreign":""},"59":{"sum_foreign_comment":"","sum_foreign_hidden":false,"sum_comment":"","sum_hidden":false,"sum":"","sum_foreign":""},"60":{"sum_foreign_comment":"","sum":"","sum_comment":"","sum_comment_unclear":false,"sum_hidden":false,"sum_comment_hidden":false,"sum_foreign":""},"61":{"sum_foreign_comment":"","sum":"","sum_hidden":false,"sum_comment":"","sum_foreign":""},"62":{"sum_foreign_comment":"","sum_foreign_hidden":false,"sum_comment":"","sum_comment_hidden":false,"sum_unclear":false,"sum":"","sum_foreign":""},"63":{"sum_foreign_comment":"","sum_foreign_hidden":false,"sum_comment":"","sum_hidden":false,"sum_comment_hidden":false,"sum":"","sum_foreign":""},"64":{"sum_foreign_comment":"","sum":"","sum_comment":"","sum_hidden":false,"sum_comment_hidden":false,"sum_foreign":""}},"ft_src":"суддя вищого адміністративного суду україни\nЗагальнодержавний регіон\nВищий адміністративний суд\nОлена\nПодружжя\nВолодимирівна\nКалашнікова\nКалашнікова Олена Володимирівна\nКалашнікова Олена Володимирівна\nОлена Володимирівна Калашнікова\nОлена Калашнікова\nКалашнікова Олена Володимирівна\nMINI Cooper\n1600 куб. см.\n2009\nJeep Wrangler\n2013\n42\nприватизована\n96.7\n.15\n1636000\n83.7\n2013\n238691.25\n210\n13764\n4281054\n252665.25\n4281054\n1600 куб. см.\nMINI Cooper\n2009\n2013\nJeep Wrangler\n2013\nПодружжя\nКалашнікова Олена Володимирівна\nОлена Володимирівна Калашнікова\nОлена Калашнікова\nКалашнікова Олена Володимирівна\nОлена\nКалашнікова Олена Володимирівна\nВолодимирівна\nсуддя вищого адміністративного суду україни\nВищий адміністративний суд\nЗагальнодержавний регіон\nКалашнікова\n238691.25\n252665.25\n4281054\n4281054\n13764\n210\n42\nприватизована\n96.7\n1636000\n83.7\n.15\nПодружжя\nОлена\nВолодимирівна\nКалашнікова\nКалашнікова Олена Володимирівна\nОлена Володимирівна Калашнікова\nОлена Калашнікова\nКалашнікова Олена Володимирівна\nЗагальнодержавний регіон\nВищий адміністративний суд\nсуддя вищого адміністративного суду україни\nКалашнікова Олена Володимирівна\n2009\nMINI Cooper\n1600 куб. см.\nJeep Wrangler\n2013\n210\n13764\n4281054\n252665.25\n4281054\n238691.25\nприватизована\n96.7\n1636000\n83.7\n42\n.15\n2013","general":{"inn":"","name":"Олена","inn_unclear":false,"family":[{"inn":"","relations":"Подружжя","inn_unclear":false,"relations_hidden":false,"inn_hidden":true,"relations_other":"","name_hidden":true,"family_name":"","name_unclear":false}],"inn_hidden":true,"family_raw":"","last_name":"Калашнікова","post":{"post":"суддя вищого адміністративного суду україни","region":"Загальнодержавний регіон","candidate":"","office_hidden":false,"post_hidden":false,"office":"Вищий адміністративний суд","region_hidden":true},"last_name_unclear":false,"full_name":"Калашнікова Олена Володимирівна","addresses":[{"place_city_type_unclear":false,"place_address":"","place_district_hidden":true,"place_city_type":"","place_address_hidden":true,"place_address_unclear":false,"place_city_type_hidden":true,"place":"","place_district":"","place_unclear":false,"place_city":"","place_city_unclear":false,"place_hidden":true,"place_city_hidden":true,"place_district_unclear":false}],"patronymic":"Володимирівна","full_name_suggest":{"output":"Калашнікова Олена Володимирівна","input":["Калашнікова Олена Володимирівна","Олена Володимирівна Калашнікова","Олена Калашнікова"]},"name_unclear":false},"source":"VULYK","estate":{"25":[{"region_unclear":false,"space_unclear":false,"costs":"1636000","costs_comment":"","costs_hidden":false,"address_hidden":true,"region_hidden":true,"space_comment":"","space":"83.7","address":"","costs_rent_comment_unclear":false,"region":"","costs_rent_comment":"","costs_rent_hidden":false,"space_comment_unclear":false,"costs_rent_comment_hidden":false,"space_units":"м²","costs_comment_hidden":false,"costs_rent":"","costs_unclear":false}],"29":[{"space_unclear":false,"costs_property_hidden":false,"address_hidden":true,"region_hidden":true,"space_comment":"","space_hidden":false,"space":".15","address":"","region":"","costs_property":"","costs_rent_comment":"","costs_rent_hidden":false,"space_comment_hidden":false,"space_units":"га","costs_property_comment":"","costs_rent":""}],"31":[{"region_unclear":false,"space_unclear":false,"costs_property_hidden":false,"address_hidden":true,"region_hidden":true,"space_comment":"приватизована","space_units_hidden":false,"space_hidden":false,"space":"96.7","address":"","region":"","costs_property":"","costs_rent_comment":"","space_comment_unclear":false,"space_units":"м²","costs_property_comment":"","costs_rent":""}],"33":[{"region_unclear":false,"space_hidden":false,"costs_property_hidden":false,"address_hidden":true,"region_hidden":true,"space_comment":"","space_units_hidden":false,"space":"42","address":"","region":"","costs_property":"","costs_rent_comment":"","costs_rent_hidden":false,"space_units":"м²","costs_property_comment":"","costs_rent":""}]},"intro":{"declaration_year":"2013","isnotdeclaration":"","declaration_year_unclear":false,"declaration_year_hidden":false}}