{"income":{"5":{"family_comment":"","value":"362719","value_unclear":false,"family":"11481","comment":""},"6":{"family_comment":"","value":"348955","value_unclear":false,"family":"11481","comment":""},"7":{"source_name_unclear":false,"value":"","family_hidden":false,"value_hidden":false,"family_comment":"","source_name":"","family":"","comment":"","source_name_hidden":false},"8":{"value":"","family_hidden":false,"value_hidden":false,"family_comment":"","family":"","comment":""},"9":{"value":"","value_unclear":false,"value_hidden":false,"family_comment":"","comment_unclear":false,"comment":"","family":""},"10":{"value":"13764","family_hidden":false,"value_hidden":false,"family_comment":"","family":"","comment":""},"11":{"value":"","family_hidden":false,"value_hidden":false,"family_comment":"","family":"","comment":""},"12":{"value":"","family_hidden":false,"value_hidden":false,"family_comment":"","family":"","comment":""},"13":{"value":"","family_hidden":false,"value_hidden":false,"family_comment":"","family":"","comment":""},"14":{"value":"","family_hidden":false,"value_hidden":false,"family_comment":"","family":"","comment":""},"15":{"value":"","family_hidden":false,"value_hidden":false,"family_comment":"","family":"","comment":""},"16":{"value":"","family_hidden":false,"value_hidden":false,"family_comment":"","family":"","comment":""},"17":{"value":"","family_hidden":false,"value_hidden":false,"family_comment":"","family":"","comment":""},"18":{"value":"","comment_unclear":false,"family_hidden":false,"value_hidden":false,"family_comment":"","family":"","comment":""},"19":{"value":"","family_hidden":false,"value_hidden":false,"family_comment":"","family":"","comment":""},"20":{"value":"","value_unclear":false,"family_hidden":false,"value_hidden":false,"family_comment":"","comment_unclear":false,"comment":"","family":""}},"id":"6584","banks":{"45":[{"sum_units":"UAH","sum_foreign":"","sum_hidden":false,"sum":"9188","sum_units_hidden":false,"sum_foreign_comment":"","sum_foreign_hidden":false,"sum_comment":"","sum_foreign_units":"UAH","sum_units_unclear":false,"sum_comment_hidden":false,"sum_unclear":false}]},"declaration":{"additional_info_text":"","notfull_lostpages":"","date":"2014-03-14T00:00:00","notfull":"","additional_info":"","url":"http://static.declarations.com.ua/declarations/chosen_ones/judges_batch/103_butenko_volodymyr_ivanovych.pdf"},"liabilities":{"54":{"sum_foreign_comment":"","sum_foreign_hidden":false,"sum_comment":"","sum_hidden":false,"sum_foreign_comment_unclear":false,"sum_comment_hidden":false,"sum":"","sum_foreign":""},"55":{"sum_foreign_comment":"","sum":"","sum_hidden":false,"sum_comment":"","sum_foreign":""},"56":{"sum_foreign_comment":"","sum":"","sum_comment":"","sum_foreign":""},"57":{"sum_foreign_comment":"","sum_foreign_hidden":false,"sum_comment":"","sum_hidden":false,"sum_comment_hidden":false,"sum":"","sum_foreign":""},"58":{"sum_foreign_comment":"","sum":"","sum_comment":"","sum_hidden":false,"sum_comment_hidden":false,"sum_foreign":""},"59":{"sum_foreign_comment":"","sum_foreign_hidden":false,"sum_comment":"","sum_hidden":false,"sum":"","sum_foreign":""},"60":{"sum_foreign_comment":"","sum":"","sum_comment":"","sum_comment_unclear":false,"sum_hidden":false,"sum_comment_hidden":false,"sum_foreign":""},"61":{"sum_foreign_comment":"","sum":"","sum_hidden":false,"sum_comment":"","sum_foreign":""},"62":{"sum_foreign_comment":"","sum_foreign_hidden":false,"sum_comment":"","sum_comment_hidden":false,"sum_unclear":false,"sum":"","sum_foreign":""},"63":{"sum_foreign_comment":"","sum_foreign_hidden":false,"sum_comment":"","sum_hidden":false,"sum_comment_hidden":false,"sum":"","sum_foreign":""},"64":{"sum_foreign_comment":"","sum":"","sum_comment":"","sum_hidden":false,"sum_comment_hidden":false,"sum_foreign":""}},"ft_src":"суддя вищого адміністративного суду україни\nЗагальнодержавний регіон\nВищий адміністративний суд\nВолодимир\nДружина\nПодружжя\nІванович\nБутенко\nБутенко Володимир Іванович\nБутенко Володимир Іванович\nВолодимир Іванович Бутенко\nВолодимир Бутенко\nБутенко Володимир Іванович\n110\nна праві користування\nна праві користування\n92.5\n9188\n2013\n2013\nПодружжя\nДружина\nБутенко Володимир Іванович\nВолодимир Іванович Бутенко\nВолодимир Бутенко\nБутенко Володимир Іванович\nВолодимир\nБутенко Володимир Іванович\nІванович\nсуддя вищого адміністративного суду україни\nВищий адміністративний суд\nЗагальнодержавний регіон\nБутенко\n348955\n11481\n362719\n11481\n13764\n110\n92.5\nна праві користування\nна праві користування\n9188\n11481\n348955\n13764\n11481\n362719\nПодружжя\nДружина\nВолодимир\nІванович\nБутенко\nБутенко Володимир Іванович\nВолодимир Іванович Бутенко\nВолодимир Бутенко\nБутенко Володимир Іванович\nЗагальнодержавний регіон\nВищий адміністративний суд\nсуддя вищого адміністративного суду україни\nБутенко Володимир Іванович\n13764\n11481\n362719\n11481\n348955\n110\nна праві користування\nна праві користування\n92.5\n9188\n2013","general":{"inn":"","name":"Володимир","inn_unclear":false,"family":[{"inn":"","relations":"Подружжя","inn_unclear":false,"relations_hidden":false,"inn_hidden":true,"relations_other":"","name_hidden":true,"family_name":"Дружина","name_unclear":false}],"inn_hidden":true,"family_raw":"","last_name":"Бутенко","post":{"post":"суддя вищого адміністративного суду україни","region":"Загальнодержавний регіон","candidate":"","office_hidden":false,"post_hidden":false,"office":"Вищий адміністративний суд","region_hidden":false},"last_name_unclear":false,"full_name":"Бутенко Володимир Іванович","addresses":[{"place_city_type_unclear":false,"place_address":"","place_district_hidden":true,"place_city_type":"","place_address_hidden":true,"place_address_unclear":false,"place_city_type_hidden":true,"place":"","place_district":"","place_unclear":false,"place_city":"","place_city_unclear":false,"place_hidden":true,"place_city_hidden":true,"place_district_unclear":false}],"patronymic":"Іванович","full_name_suggest":{"output":"Бутенко Володимир Іванович","input":["Бутенко Володимир Іванович","Володимир Іванович Бутенко","Володимир Бутенко"]},"name_unclear":false},"source":"VULYK","estate":{"25":[{"region_unclear":false,"space_unclear":false,"costs":"","costs_comment":"","costs_hidden":false,"address_hidden":false,"region_hidden":true,"space_comment":"на праві користування","space":"92.5","address":"","costs_rent_comment_unclear":false,"region":"","costs_rent_comment":"на праві користування","costs_rent_hidden":false,"space_comment_unclear":false,"costs_rent_comment_hidden":false,"space_units":"м²","costs_comment_hidden":false,"costs_rent":"","costs_unclear":false}],"30":[{"space_hidden":false,"costs_property_hidden":false,"address_hidden":false,"region_hidden":true,"space_comment":"","space_units_hidden":false,"space_unclear":false,"space":"110","address":"","region":"","costs_property":"","costs_rent_comment":"","costs_rent_hidden":false,"space_comment_unclear":false,"space_units":"м²","costs_property_comment":"","costs_rent":""}]},"intro":{"declaration_year":"2013","isnotdeclaration":"","declaration_year_unclear":false,"declaration_year_hidden":false}}