{"income":{"5":{"value":"263626","comment_hidden":false,"family_comment":"","family":"24135","comment":"","family_comment_hidden":false},"6":{"value":"251009","family_comment":"","comment_hidden":false,"family_hidden":false,"family_unclear":false,"family_comment_hidden":false,"comment":"","family":"24135"},"7":{"value":"","comment_hidden":false,"family_comment_hidden":false,"family_comment":"","source_name":"","family":"","comment":"","source_name_hidden":false},"8":{"family_comment":"","value":"","family":"","comment":""},"9":{"value":"","family_comment":"","value_unclear":false,"family_unclear":false,"comment_unclear":false,"comment":"","family":""},"10":{"family_comment":"","family_unclear":false,"value":"12617","family":"","comment":""},"11":{"family_comment":"","value":"","family":"","comment":""},"12":{"family_comment":"","value":"","family":"","comment":""},"13":{"family_comment":"","value":"","family":"","comment":""},"14":{"family_comment":"","value":"","family":"","comment":""},"15":{"family_comment":"","value":"","comment_unclear":false,"family":"","comment":""},"16":{"family_comment":"","value":"","comment_unclear":false,"family":"","comment":""},"17":{"family_comment":"","value":"","family":"","comment":""},"18":{"family_comment":"","value":"","family":"","comment":""},"19":{"family_comment":"","value":"","family":"","comment":""},"20":{"value":"","family_comment":"","value_unclear":false,"family_unclear":false,"family_comment_unclear":false,"family_comment_hidden":false,"comment":"","family":""}},"id":"6698","declaration":{"additional_info_text":"","notfull_lostpages":"","date":"2014-03-20T00:00:00","notfull":"","additional_info":"","url":"http://static.declarations.com.ua/declarations/chosen_ones/judges_batch/1151_ulytskyi_vasyl_zinoviiovych.pdf"},"liabilities":{"54":{"sum_foreign_comment":"","sum_foreign_hidden":false,"sum_comment":"","sum_comment_unclear":false,"sum_hidden":false,"sum_comment_hidden":false,"sum_unclear":false,"sum":"","sum_foreign":""},"55":{"sum_foreign_comment":"","sum_comment_hidden":false,"sum":"","sum_comment":"","sum_foreign":""},"56":{"sum_foreign_comment":"","sum":"","sum_comment":"","sum_comment_unclear":false,"sum_foreign":""},"57":{"sum_foreign_comment":"","sum":"","sum_comment":"","sum_hidden":false,"sum_comment_hidden":false,"sum_unclear":false,"sum_foreign":""},"58":{"sum_foreign_comment":"","sum":"","sum_comment":"","sum_hidden":false,"sum_comment_hidden":false,"sum_foreign":""},"59":{"sum_foreign_comment":"","sum":"","sum_comment":"","sum_comment_unclear":false,"sum_unclear":false,"sum_foreign":""},"60":{"sum_foreign_comment":"","sum":"","sum_comment":"","sum_hidden":false,"sum_comment_hidden":false,"sum_unclear":false,"sum_foreign":""},"61":{"sum_foreign_comment":"","sum":"","sum_comment":"","sum_foreign":""},"62":{"sum_foreign_comment":"","sum":"","sum_comment":"","sum_foreign":""},"63":{"sum_foreign_comment":"","sum":"","sum_comment":"","sum_hidden":false,"sum_comment_hidden":false,"sum_foreign":""},"64":{"sum_foreign_comment":"","sum":"","sum_comment":"","sum_foreign":""}},"ft_src":"заступник голови львівського апеляційного адміністративного суду\nЛьвівська область\nАпеляційний адміністративний суд\nВасиль\nУлицька Н. В\nПодружжя\nУлицька С. В\nДитина\nУлицька С. В\nДитина\nЗіновійович\nУлицький Василь Зіновійович\nВасиль Зіновійович Улицький\nВасиль Улицький\nУлицький Василь Зіновійович\nУлицький\nУлицький Василь Зіновійович\n12617\n263626\n24135\n251009\n24135\n186\n17\n2013\n24135\n251009\n12617\n24135\n263626\n24135\n251009\n263626\n24135\n12617\nУлицький Василь Зіновійович\nВасиль Зіновійович Улицький\nВасиль Улицький\nУлицький Василь Зіновійович\nВасиль\nПодружжя\nУлицька Н. В\nДитина\nУлицька С. В\nДитина\nУлицька С. В\nУлицький Василь Зіновійович\nЗіновійович\nАпеляційний адміністративний суд\nЛьвівська область\nзаступник голови львівського апеляційного адміністративного суду\nУлицький\n17\n186\n2013\nПодружжя\nУлицька Н. В\nДитина\nУлицька С. В\nДитина\nУлицька С. В\nЗіновійович\nУлицький\nВасиль\nУлицький Василь Зіновійович\nВасиль Зіновійович Улицький\nВасиль Улицький\nУлицький Василь Зіновійович\nЛьвівська область\nАпеляційний адміністративний суд\nзаступник голови львівського апеляційного адміністративного суду\nУлицький Василь Зіновійович\n186\n17\n2013","general":{"inn":"","name":"Василь","family":[{"inn":"","relations":"Подружжя","inn_unclear":false,"relations_hidden":false,"inn_hidden":true,"relations_other":"","name_hidden":true,"family_name":"Улицька Н. В","name_unclear":false},{"inn":"","relations":"Дитина","inn_unclear":false,"family_name":"Улицька С. В","inn_hidden":false,"relations_other":"","name_hidden":false,"name_unclear":false},{"inn":"","relations":"Дитина","relations_other":"","inn_hidden":false,"family_name":"Улицька С. В","name_hidden":false,"name_unclear":false}],"patronymic":"Зіновійович","inn_hidden":true,"family_raw":"","last_name":"Улицький","post":{"post_unclear":false,"region_unclear":false,"post":"заступник голови львівського апеляційного адміністративного суду","office":"Апеляційний адміністративний суд","region":"Львівська область","post_hidden":false,"office_hidden":false,"office_unclear":false,"region_hidden":false},"last_name_unclear":false,"full_name":"Улицький Василь Зіновійович","addresses":[{"place_district":"","place_city_hidden":true,"place_city":"","place_city_type_hidden":false,"place_district_hidden":false,"place_city_type":"","place_address_hidden":true,"place_address":"","place_hidden":true,"place":""}],"full_name_suggest":{"output":"Улицький Василь Зіновійович","input":["Улицький Василь Зіновійович","Василь Зіновійович Улицький","Василь Улицький"]},"name_unclear":false},"source":"VULYK","estate":{"31":[{"space_unclear":false,"address_hidden":true,"region_hidden":true,"space_comment":"","space":"186","address":"","region":"","costs_property":"","costs_rent_comment":"","space_units":"м²","costs_property_comment":"","costs_rent":""}],"33":[{"space_hidden":false,"address_hidden":true,"region_hidden":true,"space_comment":"","space":"17","address":"","region":"","costs_property":"","costs_rent_comment":"","space_units":"м²","costs_property_comment":"","costs_rent":""}]},"intro":{"declaration_year":"2013"}}