{"income":{"5":{"value":"289510","family_comment":"","value_unclear":false,"value_hidden":false,"family_unclear":false,"family":"","comment":""},"6":{"value":"289510","family_hidden":false,"value_hidden":false,"family_comment":"","family_comment_hidden":false,"comment":"","family":""},"7":{"value":"","value_unclear":false,"family_hidden":false,"value_hidden":false,"family_comment":"","source_name":"","family":"","comment":"","source_name_hidden":false},"8":{"value":"","comment_hidden":false,"family_hidden":false,"value_hidden":false,"family_comment":"","family":"","comment":""},"9":{"value":"","family_comment":"","comment_hidden":false,"family_hidden":false,"value_hidden":false,"family_unclear":false,"family":"","comment":""},"10":{"value":"","comment_hidden":false,"family_hidden":false,"value_hidden":false,"family_comment":"","family":"","comment":""},"11":{"value":"","value_unclear":false,"comment_hidden":false,"family_hidden":false,"value_hidden":false,"family_comment":"","family":"","comment":""},"12":{"value":"","comment_hidden":false,"family_hidden":false,"value_hidden":false,"family_comment":"","family":"","comment":""},"13":{"value":"","comment_hidden":false,"family_hidden":false,"value_hidden":false,"family_comment":"","family":"","comment":""},"14":{"value":"","comment_hidden":false,"family_hidden":false,"value_hidden":false,"family_comment":"","family":"","comment":""},"15":{"value":"","comment_hidden":false,"family_hidden":false,"value_hidden":false,"family_comment":"","family":"","comment":""},"16":{"value":"","comment_hidden":false,"family_hidden":false,"value_hidden":false,"family_comment":"","family":"","comment":""},"17":{"value":"","comment_hidden":false,"family_hidden":false,"value_hidden":false,"family_comment":"","family":"","comment":""},"18":{"value":"","value_unclear":false,"comment_hidden":false,"family_hidden":false,"value_hidden":false,"family_comment":"","family":"","comment":""},"19":{"value":"","comment_hidden":false,"family_hidden":false,"value_hidden":false,"family_comment":"","family":"","comment":""},"20":{"value":"","value_unclear":false,"family_comment":"","comment_unclear":false,"comment":"","family":""}},"vehicle":{"35":[{"brand_info":"1300","sum_rent_comment":"","sum_rent_hidden":false,"year":"1987","sum_rent_unclear":false,"brand_info_hidden":false,"brand_info_unclear":false,"year_unclear":false,"sum_hidden":false,"sum_rent":"","sum":"","brand":"ВАЗ 2106","sum_comment":"","brand_unclear":false,"sum_rent_comment_hidden":false,"sum_comment_hidden":false,"sum_unclear":false},{"brand_info":"2500","sum_rent_comment":"","brand":"Toyota Camry","sum_comment":"","brand_unclear":false,"year":"2012","brand_info_unclear":false,"sum":"","sum_rent":""}]},"id":"6901","declaration":{"additional_info_text":"","notfull_lostpages":"","date":"2014-03-26T00:00:00","notfull":"","additional_info":"","url":"http://static.declarations.com.ua/declarations/chosen_ones/judges_batch/291_kvasnevska_natalia_dmytrivna.pdf"},"liabilities":{"54":{"sum_foreign_comment":"","sum_foreign_hidden":false,"sum_comment":"","sum_hidden":false,"sum_comment_hidden":false,"sum":"","sum_foreign":""},"55":{"sum_foreign_comment":"","sum":"","sum_hidden":false,"sum_comment":"","sum_foreign":""},"56":{"sum_foreign_comment":"","sum":"","sum_comment":"","sum_foreign":""},"57":{"sum_foreign_comment":"","sum_foreign_hidden":false,"sum_comment":"","sum_hidden":false,"sum_comment_hidden":true,"sum_unclear":false,"sum":"5573","sum_foreign":""},"58":{"sum_foreign_comment":"","sum_foreign_hidden":false,"sum_comment":"","sum_hidden":false,"sum_comment_hidden":false,"sum_unclear":false,"sum":"","sum_foreign":""},"59":{"sum_foreign_comment":"","sum":"","sum_hidden":false,"sum_comment":"","sum_foreign":""},"60":{"sum_foreign_comment":"","sum_foreign_hidden":false,"sum_comment":"","sum_hidden":false,"sum_comment_hidden":false,"sum_unclear":false,"sum":"","sum_foreign":""},"61":{"sum_foreign_comment":"","sum":"","sum_hidden":false,"sum_comment":"","sum_foreign":""},"62":{"sum_foreign_comment":"","sum":"","sum_comment":"","sum_hidden":false,"sum_comment_hidden":false,"sum_foreign":""},"63":{"sum_foreign_comment":"","sum":"","sum_hidden":false,"sum_comment":"","sum_foreign":""},"64":{"sum_foreign_comment":"","sum":"","sum_hidden":false,"sum_comment":"","sum_foreign":""}},"ft_src":"5573\nсуддя вищого спецiалiзованого суду україни\nЗагальнодержавний регіон\nВищий спеціалізований суд з розгляду цивільних і кримінальних справ\nНаталя\nДмитрівна\nКвасневська\nКвасневська Наталя Дмитрівна\nКвасневська Наталя Дмитрівна\nНаталя Дмитрівна Квасневська\nНаталя Квасневська\nКвасневська Наталя Дмитрівна\n1300\n1987\nВАЗ 2106\n2012\nToyota Camry\n2500\n20\n60\n50\n2013\n289510\n289510\n1300\nВАЗ 2106\n1987\n2500\nToyota Camry\n2012\n60\n20\n50\nКвасневська Наталя Дмитрівна\nНаталя Дмитрівна Квасневська\nНаталя Квасневська\nКвасневська Наталя Дмитрівна\nКвасневська Наталя Дмитрівна\nНаталя\nДмитрівна\nВищий спеціалізований суд з розгляду цивільних і кримінальних справ\nсуддя вищого спецiалiзованого суду україни\nЗагальнодержавний регіон\nКвасневська\n5573\n289510\n289510\n2013\n5573\nДмитрівна\nКвасневська\nНаталя\nКвасневська Наталя Дмитрівна\nНаталя Дмитрівна Квасневська\nНаталя Квасневська\nКвасневська Наталя Дмитрівна\nЗагальнодержавний регіон\nсуддя вищого спецiалiзованого суду україни\nВищий спеціалізований суд з розгляду цивільних і кримінальних справ\nКвасневська Наталя Дмитрівна\n1987\nВАЗ 2106\n1300\n2012\n2500\nToyota Camry\n289510\n289510\n50\n60\n20\n2013","general":{"inn":"","name":"Наталя","inn_unclear":false,"patronymic":"Дмитрівна","inn_hidden":true,"family_raw":"","last_name":"Квасневська","post":{"post_unclear":false,"post":"суддя вищого спецiалiзованого суду україни","candidate":"","office_hidden":false,"region":"Загальнодержавний регіон","office":"Вищий спеціалізований суд з розгляду цивільних і кримінальних справ","office_unclear":false,"region_hidden":false},"last_name_unclear":false,"full_name":"Квасневська Наталя Дмитрівна","addresses":[{"place_city_type_unclear":false,"place_address":"","place_district_hidden":true,"place_city_type":"","place_city_hidden":true,"place_city_type_hidden":true,"place":"","place_district":"","place_unclear":false,"place_city":"","place_city_unclear":false,"place_hidden":true,"place_address_hidden":true}],"full_name_suggest":{"output":"Квасневська Наталя Дмитрівна","input":["Квасневська Наталя Дмитрівна","Наталя Дмитрівна Квасневська","Наталя Квасневська"]},"name_unclear":false},"source":"VULYK","estate":{"24":[{"costs":"","costs_comment":"","address_hidden":true,"region_hidden":true,"space_comment":"","space":"60","address":"","region":"","address_unclear":false,"costs_rent_comment":"","space_comment_unclear":false,"space_units":"м²","costs_rent":""}],"25":[{"space_unclear":false,"costs":"","costs_comment":"","address_hidden":true,"region_hidden":true,"space_comment":"","space_hidden":false,"space":"50","address":"","region":"","costs_rent_comment":"","space_comment_unclear":false,"space_comment_hidden":false,"space_units":"м²","costs_rent":""}],"27":[{"space_hidden":false,"costs":"","costs_comment":"","costs_hidden":false,"address_hidden":true,"region_hidden":true,"space_comment":"","space":"20","address":"","region":"","address_unclear":false,"costs_rent_comment":"","space_units":"м²","costs_rent":""}]},"intro":{"declaration_year":"2013","isnotdeclaration":"","declaration_year_unclear":false,"declaration_year_hidden":false}}