{"income":{"5":{"value":"328262","family_comment":"","value_unclear":false,"value_hidden":false,"family_unclear":false,"family":"2546993","comment":""},"6":{"value":"328262","family_hidden":false,"value_hidden":false,"family_comment":"","family_comment_hidden":false,"comment":"","family":""},"7":{"value":"","value_unclear":false,"family_hidden":false,"value_hidden":false,"family_comment":"","source_name":"","family":"","comment":"","source_name_hidden":false},"8":{"value":"","comment_hidden":false,"family_hidden":false,"value_hidden":false,"family_comment":"","family":"","comment":""},"9":{"value":"","family_comment":"","comment_hidden":false,"family_hidden":false,"value_hidden":false,"family_unclear":false,"family":"","comment":""},"10":{"value":"","comment_hidden":false,"family_hidden":false,"value_hidden":false,"family_comment":"","family":"","comment":""},"11":{"value":"","value_unclear":false,"comment_hidden":false,"family_hidden":false,"value_hidden":false,"family_comment":"","family":"","comment":""},"12":{"value":"","comment_hidden":false,"family_hidden":false,"value_hidden":false,"family_comment":"","family":"","comment":""},"13":{"value":"","comment_hidden":false,"family_hidden":false,"value_hidden":false,"family_comment":"","family":"","comment":""},"14":{"value":"","comment_hidden":false,"family_hidden":false,"value_hidden":false,"family_comment":"","family":"","comment":""},"15":{"value":"","comment_hidden":false,"family_hidden":false,"value_hidden":false,"family_comment":"","family":"","comment":""},"16":{"value":"","comment_hidden":false,"family_hidden":false,"value_hidden":false,"family_comment":"","family":"","comment":""},"17":{"value":"","comment_hidden":false,"family_hidden":false,"value_hidden":false,"family_comment":"","family":"485300","comment":""},"18":{"value":"","value_unclear":false,"comment_hidden":false,"family_hidden":false,"value_hidden":false,"family_comment":"","family":"2057000","comment":""},"19":{"value":"","comment_hidden":false,"family_hidden":false,"value_hidden":false,"family_comment":"","family":"","comment":""},"20":{"value":"","value_unclear":false,"family_comment":"","comment_unclear":false,"comment":"","family":"4693"}},"vehicle":{"40":[{"year_hidden":false,"brand_info":"2500","sum_rent_comment":"","brand":"Subaru Impreza","sum_comment":"","brand_unclear":false,"year":"2008","brand_hidden":false,"brand_info_unclear":false,"sum":"","sum_rent":""}]},"id":"6938","banks":{"51":[{"sum_foreign_comment":"","sum_unclear":false,"sum_units":"UAH","sum_comment":"","sum_hidden":false,"sum_foreign_units":"UAH","sum_comment_hidden":false,"sum_units_hidden":false,"sum":"20","sum_foreign":""}]},"declaration":{"additional_info_text":"","notfull_lostpages":"","date":"2014-03-27T00:00:00","notfull":"","additional_info":"","url":"http://static.declarations.com.ua/declarations/chosen_ones/judges_batch/309_solodkov_andrii_andriiovych.pdf"},"liabilities":{"54":{"sum_foreign_comment":"","sum_foreign_hidden":false,"sum_comment":"","sum_hidden":false,"sum_comment_hidden":false,"sum":"","sum_foreign":""},"55":{"sum_foreign_comment":"","sum":"","sum_hidden":false,"sum_comment":"","sum_foreign":""},"56":{"sum_foreign_comment":"","sum":"","sum_comment":"","sum_foreign":""},"57":{"sum_foreign_comment":"","sum_foreign_hidden":false,"sum_comment":"","sum_hidden":false,"sum_comment_hidden":false,"sum_unclear":false,"sum":"","sum_foreign":""},"58":{"sum_foreign_comment":"","sum_foreign_hidden":false,"sum_comment":"","sum_hidden":false,"sum_comment_hidden":false,"sum_unclear":false,"sum":"","sum_foreign":""},"59":{"sum_foreign_comment":"","sum":"","sum_hidden":false,"sum_comment":"","sum_foreign":""},"60":{"sum_foreign_comment":"","sum_foreign_hidden":false,"sum_comment":"","sum_hidden":false,"sum_comment_hidden":false,"sum_unclear":false,"sum":"","sum_foreign":""},"61":{"sum_foreign_comment":"","sum":"","sum_hidden":false,"sum_comment":"","sum_foreign":""},"62":{"sum_foreign_comment":"","sum":"","sum_comment":"","sum_hidden":false,"sum_comment_hidden":false,"sum_foreign":""},"63":{"sum_foreign_comment":"","sum":"","sum_hidden":false,"sum_comment":"","sum_foreign":""},"64":{"sum_foreign_comment":"","sum":"","sum_hidden":false,"sum_comment":"","sum_foreign":""}},"ft_src":"голова вссу\nЗагальнодержавний регіон\nВищий спеціалізований суд з розгляду цивільних і кримінальних справ\nАндрій\nСолодкова О. В\nПодружжя\nСолодкова М. А\nДитина\nСолодкова Д. А\nДитина\nАндрійович\nСолодков Андрій Андрійович\nАндрій Андрійович Солодков\nАндрій Солодков\nСолодков Андрій Андрійович\nСолодков Андрій Андрійович\nСолодков\nSubaru Impreza\n2500\n2008\n34\n20\n2013\n2500\nSubaru Impreza\n2008\n34\nСолодков Андрій Андрійович\nАндрій Андрійович Солодков\nАндрій Солодков\nСолодков Андрій Андрійович\nСолодков Андрій Андрійович\nПодружжя\nСолодкова О. В\nДитина\nСолодкова М. А\nДитина\nСолодкова Д. А\nАндрій\nАндрійович\nВищий спеціалізований суд з розгляду цивільних і кримінальних справ\nголова вссу\nЗагальнодержавний регіон\nСолодков\n328262\n4693\n485300\n2057000\n328262\n2546993\n20\n2013\n328262\n2057000\n2546993\n328262\n485300\n4693\nСолодкова О. В\nПодружжя\nДитина\nСолодкова М. А\nСолодкова Д. А\nДитина\nАндрійович\nСолодков\nАндрій\nСолодков Андрій Андрійович\nАндрій Андрійович Солодков\nАндрій Солодков\nСолодков Андрій Андрійович\nЗагальнодержавний регіон\nголова вссу\nВищий спеціалізований суд з розгляду цивільних і кримінальних справ\nСолодков Андрій Андрійович\n2008\nSubaru Impreza\n2500\n4693\n328262\n2546993\n485300\n328262\n2057000\n34\n20\n2013","general":{"inn":"","name":"Андрій","inn_unclear":false,"family":[{"inn":"","inn_hidden":true,"relations_unclear":false,"relations_hidden":false,"relations_other":"","relations":"Подружжя","name_hidden":false,"family_name":"Солодкова О. В","name_unclear":false},{"inn":"","inn_hidden":false,"relations_unclear":false,"relations_hidden":false,"relations_other":"","relations":"Дитина","name_hidden":false,"family_name":"Солодкова М. А","name_unclear":false},{"inn":"","relations":"Дитина","relations_other":"","inn_hidden":true,"family_name":"Солодкова Д. А","name_hidden":false,"name_unclear":false}],"inn_hidden":true,"family_raw":"","last_name":"Солодков","post":{"post_unclear":false,"post":"голова вссу","candidate":"","office_hidden":false,"region":"Загальнодержавний регіон","office":"Вищий спеціалізований суд з розгляду цивільних і кримінальних справ","office_unclear":false,"region_hidden":false},"full_name_suggest":{"output":"Солодков Андрій Андрійович","input":["Солодков Андрій Андрійович","Андрій Андрійович Солодков","Андрій Солодков"]},"full_name":"Солодков Андрій Андрійович","addresses":[{"place_city_type_unclear":false,"place_address":"","place_district_hidden":true,"place_city_type":"","place_city_hidden":true,"place_city_type_hidden":false,"place":"","place_district":"","place_unclear":false,"place_city":"","place_city_unclear":false,"place_hidden":true,"place_address_hidden":false}],"patronymic":"Андрійович","last_name_unclear":false,"name_unclear":false},"source":"VULYK","estate":{"31":[{"space_unclear":false,"address_hidden":false,"region_hidden":true,"space_comment":"","space_hidden":false,"space":"34","address":"","region":"","costs_property":"","costs_rent_comment":"","space_comment_unclear":false,"space_units":"м²","costs_property_comment":"","costs_rent":""}]},"intro":{"declaration_year":"2013","isnotdeclaration":"","declaration_year_unclear":false,"declaration_year_hidden":false}}