{"income":{"5":{"value":"243882","comment_hidden":false,"family_comment":"","family":"48459","comment":"","family_comment_hidden":false},"6":{"value":"229076","family_comment":"","comment_hidden":false,"family_hidden":false,"family_unclear":false,"family_comment_hidden":false,"comment":"","family":"46035"},"7":{"value":"","comment_hidden":false,"family_comment_hidden":false,"family_comment":"","source_name":"","family":"","comment":"","source_name_hidden":false},"8":{"family_comment":"","value":"","family":"","comment":""},"9":{"value":"","family_comment":"","value_unclear":false,"family_unclear":false,"comment_unclear":false,"comment":"","family":""},"10":{"family_comment":"","family_unclear":false,"value":"12617","family":"2400","comment":""},"11":{"family_comment":"","value":"24","family":"24","comment":""},"12":{"family_comment":"","value":"","family":"","comment":""},"13":{"family_comment":"","value":"","family":"","comment":""},"14":{"family_comment":"","value":"","family":"","comment":""},"15":{"family_comment":"","value":"2165","comment_unclear":false,"family":"","comment":""},"16":{"family_comment":"","value":"","comment_unclear":false,"family":"","comment":""},"17":{"family_comment":"","value":"","family":"","comment":""},"18":{"family_comment":"","value":"","family":"","comment":""},"19":{"family_comment":"","value":"","family":"","comment":""},"20":{"value":"","family_comment":"","value_unclear":false,"family_unclear":false,"family_comment_unclear":false,"family_comment_hidden":false,"comment":"","family":""}},"vehicle":{"35":[{"brand_info":"1997 куб.см., 120 кВт","sum_rent_comment":"","brand":"Ford Kuga","sum_comment":"","brand_unclear":false,"year":"2012","sum_hidden":false,"brand_info_unclear":false,"sum":"","sum_rent":""}]},"id":"7155","declaration":{"additional_info_text":"","notfull_lostpages":"","date":"2014-03-31T00:00:00","notfull":"","additional_info":"","url":"http://static.declarations.com.ua/declarations/chosen_ones/judges_batch/1155_nos_stepan_petrovych.pdf"},"liabilities":{"54":{"sum_foreign_comment":"","sum_foreign_hidden":false,"sum_comment":"","sum_comment_unclear":false,"sum_hidden":false,"sum_comment_hidden":false,"sum_unclear":false,"sum":"13165","sum_foreign":""},"55":{"sum_foreign_comment":"","sum_comment_hidden":false,"sum":"","sum_comment":"","sum_foreign":""},"56":{"sum_foreign_comment":"","sum":"","sum_comment":"","sum_comment_unclear":false,"sum_foreign":""},"57":{"sum_foreign_comment":"","sum":"","sum_comment":"","sum_hidden":false,"sum_comment_hidden":false,"sum_unclear":false,"sum_foreign":""},"58":{"sum_foreign_comment":"","sum":"","sum_comment":"","sum_hidden":false,"sum_comment_hidden":false,"sum_foreign":""},"59":{"sum_foreign_comment":"","sum":"","sum_comment":"","sum_comment_unclear":false,"sum_unclear":false,"sum_foreign":""},"60":{"sum_foreign_comment":"","sum":"","sum_comment":"","sum_hidden":false,"sum_comment_hidden":false,"sum_unclear":false,"sum_foreign":""},"61":{"sum_foreign_comment":"","sum":"","sum_comment":"","sum_foreign":""},"62":{"sum_foreign_comment":"","sum":"","sum_comment":"","sum_foreign":""},"63":{"sum_foreign_comment":"","sum":"","sum_comment":"","sum_hidden":false,"sum_comment_hidden":false,"sum_foreign":""},"64":{"sum_foreign_comment":"","sum":"","sum_comment":"","sum_foreign":""}},"ft_src":"13165\nсуддя, заступник голови львівського апеляційного адміністративного суду\nЛьвівська область\nАпеляційний адміністративний суд\nСтепан\nНос І. Ю\nПодружжя\nНос Ю. С\nДитина\nПетрович\nНос\nНос Степан Петрович\nНос Степан Петрович\nСтепан Петрович Нос\nСтепан Нос\nНос Степан Петрович\nFord Kuga\n1997 куб.см., 120 кВт\n2012\n949\n2013\n46035\n229076\n2165\n24\n24\n2400\n12617\n48459\n243882\n1997 куб.см., 120 кВт\nFord Kuga\n2012\n2013\nНос Степан Петрович\nСтепан Петрович Нос\nСтепан Нос\nНос Степан Петрович\nНос Степан Петрович\nПодружжя\nНос І. Ю\nДитина\nНос Ю. С\nСтепан\nПетрович\nАпеляційний адміністративний суд\nЛьвівська область\nсуддя, заступник голови львівського апеляційного адміністративного суду\nНос\n13165\n46035\n229076\n2165\n243882\n48459\n12617\n2400\n24\n24\n949\n13165\nПодружжя\nНос І. Ю\nДитина\nНос Ю. С\nСтепан\nПетрович\nНос\nНос Степан Петрович\nСтепан Петрович Нос\nСтепан Нос\nНос Степан Петрович\nЛьвівська область\nАпеляційний адміністративний суд\nсуддя, заступник голови львівського апеляційного адміністративного суду\nНос Степан Петрович\n2012\n1997 куб.см., 120 кВт\nFord Kuga\n24\n24\n2165\n2400\n12617\n243882\n48459\n229076\n46035\n949\n2013","general":{"inn":"","name":"Степан","family":[{"inn":"","relations":"Подружжя","inn_unclear":false,"relations_hidden":false,"inn_hidden":false,"relations_other":"","name_hidden":false,"family_name":"Нос І. Ю","name_unclear":false},{"inn":"","relations":"Дитина","inn_unclear":false,"family_name":"Нос Ю. С","inn_hidden":false,"relations_other":"","name_hidden":false,"name_unclear":false}],"patronymic":"Петрович","inn_hidden":false,"family_raw":"","last_name":"Нос","post":{"post_unclear":false,"region_unclear":false,"post":"суддя, заступник голови львівського апеляційного адміністративного суду","office":"Апеляційний адміністративний суд","region":"Львівська область","post_hidden":false,"office_hidden":false,"office_unclear":false,"region_hidden":false},"full_name_suggest":{"output":"Нос Степан Петрович","input":["Нос Степан Петрович","Степан Петрович Нос","Степан Нос"]},"full_name":"Нос Степан Петрович","last_name_unclear":false,"name_unclear":false},"source":"VULYK","estate":{"23":[{"space_hidden":false,"costs":"","costs_comment":"","costs_hidden":false,"address_hidden":false,"region_hidden":false,"space_comment":"","space_unclear":false,"space":"949","address":"","region":"","space_units_unclear":false,"costs_unclear":false,"space_units":"м²","costs_rent":"","costs_rent_comment":""}]},"intro":{"declaration_year":"2013"}}