{"income":{"5":{"value":"201116","comment_hidden":false,"family_comment":"","family":"18262","comment":"","family_comment_hidden":false},"6":{"value":"188499","family_comment":"","comment_hidden":false,"family_hidden":false,"family_unclear":false,"family_comment_hidden":false,"comment":"","family":""},"7":{"value":"","comment_hidden":false,"family_comment_hidden":false,"family_comment":"","source_name":"","family":"","comment":"","source_name_hidden":false},"8":{"family_comment":"","value":"","family":"","comment":""},"9":{"value":"","family_comment":"","value_unclear":false,"family_unclear":false,"comment_unclear":false,"comment":"","family":""},"10":{"family_comment":"","family_unclear":false,"value":"12617","family":"","comment":""},"11":{"family_comment":"","value":"","family":"","comment":""},"12":{"family_comment":"","value":"","family":"","comment":""},"13":{"family_comment":"","value":"","family":"","comment":""},"14":{"family_comment":"","value":"","family":"","comment":""},"15":{"family_comment":"","value":"","comment_unclear":false,"family":"","comment":""},"16":{"family_comment":"","value":"","comment_unclear":false,"family":"","comment":""},"17":{"family_comment":"","value":"","family":"","comment":""},"18":{"family_comment":"","value":"","family":"","comment":""},"19":{"family_comment":"","value":"","family":"","comment":""},"20":{"value":"","family_comment":"","value_unclear":false,"family_unclear":false,"family_comment_unclear":false,"family_comment_hidden":false,"comment":"","family":"18262"}},"vehicle":{"40":[{"brand_info":"1896 куб. см., 77 кВт","sum_rent_comment":"","brand":"Skoda Octavia A5","sum_comment":"","brand_unclear":false,"year":"2012","brand_info_unclear":false,"sum":"","sum_rent":""}]},"id":"7240","declaration":{"additional_info_text":"","notfull_lostpages":"","date":"2014-03-20T00:00:00","notfull":"","additional_info":"","url":"http://static.declarations.com.ua/declarations/chosen_ones/judges_batch/1170_huliak_vasyl_vasylovych.pdf"},"liabilities":{"54":{"sum_foreign_comment":"","sum_foreign_hidden":false,"sum_comment":"","sum_comment_unclear":false,"sum_hidden":false,"sum_comment_hidden":false,"sum_unclear":false,"sum":"","sum_foreign":""},"55":{"sum_foreign_comment":"","sum_comment_hidden":false,"sum":"","sum_comment":"","sum_foreign":""},"56":{"sum_foreign_comment":"","sum":"","sum_comment":"","sum_comment_unclear":false,"sum_foreign":""},"57":{"sum_foreign_comment":"","sum":"","sum_comment":"","sum_hidden":false,"sum_comment_hidden":false,"sum_unclear":false,"sum_foreign":""},"58":{"sum_foreign_comment":"","sum":"","sum_comment":"","sum_hidden":false,"sum_comment_hidden":false,"sum_foreign":""},"59":{"sum_foreign_comment":"","sum":"","sum_comment":"","sum_comment_unclear":false,"sum_unclear":false,"sum_foreign":""},"60":{"sum_foreign_comment":"","sum":"","sum_comment":"","sum_hidden":false,"sum_comment_hidden":false,"sum_unclear":false,"sum_foreign":""},"61":{"sum_foreign_comment":"","sum":"","sum_comment":"","sum_foreign":""},"62":{"sum_foreign_comment":"","sum":"","sum_comment":"","sum_foreign":""},"63":{"sum_foreign_comment":"","sum":"","sum_comment":"","sum_hidden":false,"sum_comment_hidden":false,"sum_foreign":""},"64":{"sum_foreign_comment":"","sum":"","sum_comment":"","sum_foreign":""}},"ft_src":"суддя львівського апеляційного адміністративного суду\nЛьвівська область\nАпеляційний адміністративний суд\nВасиль\nГуляк Я. Б\nПодружжя\nГуляк С. В\nДитина\nГуляк С. В\nДитина\nГуляк Д. В\nДитина\nВасильович\nГуляк Василь Васильович\nВасиль Васильович Гуляк\nВасиль Гуляк\nГуляк Василь Васильович\nГуляк\nГуляк Василь Васильович\n2012\nSkoda Octavia A5\n1896 куб. см., 77 кВт\n53.2\n2013\n188499\n12617\n18262\n201116\n18262\n1896 куб. см., 77 кВт\nSkoda Octavia A5\n2012\n2013\nГуляк Василь Васильович\nВасиль Васильович Гуляк\nВасиль Гуляк\nГуляк Василь Васильович\nВасиль\nПодружжя\nГуляк Я. Б\nДитина\nГуляк С. В\nДитина\nГуляк С. В\nГуляк Д. В\nДитина\nГуляк Василь Васильович\nВасильович\nАпеляційний адміністративний суд\nЛьвівська область\nсуддя львівського апеляційного адміністративного суду\nГуляк\n188499\n18262\n201116\n18262\n12617\n53.2\nПодружжя\nГуляк Я. Б\nДитина\nГуляк С. В\nДитина\nГуляк С. В\nДитина\nГуляк Д. В\nВасильович\nГуляк\nВасиль\nГуляк Василь Васильович\nВасиль Васильович Гуляк\nВасиль Гуляк\nГуляк Василь Васильович\nЛьвівська область\nАпеляційний адміністративний суд\nсуддя львівського апеляційного адміністративного суду\nГуляк Василь Васильович\n2012\n1896 куб. см., 77 кВт\nSkoda Octavia A5\n12617\n18262\n201116\n18262\n188499\n53.2\n2013","general":{"inn":"","name":"Василь","family":[{"inn":"","relations":"Подружжя","inn_unclear":false,"relations_hidden":false,"inn_hidden":true,"relations_other":"","name_hidden":true,"family_name":"Гуляк Я. Б","name_unclear":false},{"inn":"","relations":"Дитина","inn_unclear":false,"family_name":"Гуляк С. В","inn_hidden":false,"relations_other":"","name_hidden":false,"name_unclear":false},{"inn":"","relations":"Дитина","relations_other":"","inn_hidden":false,"family_name":"Гуляк С. В","name_hidden":false,"name_unclear":false},{"inn":"","family_name":"Гуляк Д. В","relations":"Дитина","inn_hidden":false,"relations_other":""}],"patronymic":"Васильович","inn_hidden":true,"family_raw":"","last_name":"Гуляк","post":{"post_unclear":false,"region_unclear":false,"post":"суддя львівського апеляційного адміністративного суду","office":"Апеляційний адміністративний суд","region":"Львівська область","post_hidden":false,"office_hidden":false,"office_unclear":false,"region_hidden":false},"last_name_unclear":false,"full_name":"Гуляк Василь Васильович","addresses":[{"place_district":"","place_city_hidden":true,"place_city":"","place_city_type_hidden":true,"place_district_hidden":true,"place_city_type":"","place_address_hidden":true,"place_address":"","place_hidden":true,"place":""}],"full_name_suggest":{"output":"Гуляк Василь Васильович","input":["Гуляк Василь Васильович","Василь Васильович Гуляк","Василь Гуляк"]},"name_unclear":false},"source":"VULYK","estate":{"25":[{"space_unclear":false,"costs":"","costs_comment":"","costs_hidden":false,"address_hidden":true,"region_hidden":true,"space_comment":"","space_hidden":false,"space":"53.2","address":"","region":"","costs_rent_comment":"","space_comment_hidden":false,"space_units":"м²","costs_rent":""}]},"intro":{"declaration_year":"2013"}}