{"income":{"5":{"value":"429794","family_comment":"","value_unclear":false,"value_hidden":false,"family_unclear":false,"family":"21165","comment":""},"6":{"value":"429794","family_hidden":false,"value_hidden":false,"family_comment":"","family_comment_hidden":false,"comment":"","family":""},"7":{"value":"","value_unclear":false,"family_hidden":false,"value_hidden":false,"family_comment":"","source_name":"","family":"","comment":"","source_name_hidden":false},"8":{"value":"","comment_hidden":false,"family_hidden":false,"value_hidden":false,"family_comment":"","family":"","comment":""},"9":{"value":"","family_comment":"","comment_hidden":false,"family_hidden":false,"value_hidden":false,"family_unclear":false,"family":"","comment":""},"10":{"value":"","comment_hidden":false,"family_hidden":false,"value_hidden":false,"family_comment":"","family":"","comment":""},"11":{"value":"","value_unclear":false,"comment_hidden":false,"family_hidden":false,"value_hidden":false,"family_comment":"","family":"","comment":""},"12":{"value":"","comment_hidden":false,"family_hidden":false,"value_hidden":false,"family_comment":"","family":"","comment":""},"13":{"value":"","comment_hidden":false,"family_hidden":false,"value_hidden":false,"family_comment":"","family":"","comment":""},"14":{"value":"","comment_hidden":false,"family_hidden":false,"value_hidden":false,"family_comment":"","family":"","comment":""},"15":{"value":"","comment_hidden":false,"family_hidden":false,"value_hidden":false,"family_comment":"","family":"","comment":""},"16":{"value":"","comment_hidden":false,"family_hidden":false,"value_hidden":false,"family_comment":"","family":"","comment":""},"17":{"value":"","comment_hidden":false,"family_hidden":false,"value_hidden":false,"family_comment":"","family":"","comment":""},"18":{"value":"","value_unclear":false,"comment_hidden":false,"family_hidden":false,"value_hidden":false,"family_comment":"","family":"","comment":""},"19":{"value":"","comment_hidden":false,"family_hidden":false,"value_hidden":false,"family_comment":"","family":"","comment":""},"20":{"value":"","value_unclear":false,"family_comment":"","comment_unclear":false,"comment":"","family":"21165"}},"vehicle":{"35":[{"brand_info":"2.0 , 145","sum_rent_comment":"","sum_rent_hidden":false,"year":"2006","sum_rent_unclear":false,"brand_info_hidden":false,"brand_info_unclear":false,"year_unclear":false,"sum_hidden":false,"sum_rent":"","sum":"","brand":"Kia Magentis","sum_comment":"","brand_unclear":false,"sum_rent_comment_hidden":false,"sum_comment_hidden":false,"sum_unclear":false}]},"id":"7434","declaration":{"additional_info_text":"","notfull_lostpages":"","date":"2014-03-25T00:00:00","notfull":"","additional_info":"","url":"http://static.declarations.com.ua/declarations/chosen_ones/judges_batch/256_kuznietsov_viktor_oleksiiovych.pdf"},"liabilities":{"54":{"sum_foreign_comment":"","sum_foreign_hidden":false,"sum_comment":"","sum_hidden":false,"sum_comment_hidden":false,"sum":"","sum_foreign":""},"55":{"sum_foreign_comment":"","sum":"","sum_hidden":false,"sum_comment":"","sum_foreign":""},"56":{"sum_foreign_comment":"","sum":"","sum_comment":"","sum_foreign":""},"57":{"sum_foreign_comment":"","sum_foreign_hidden":false,"sum_comment":"","sum_hidden":false,"sum_comment_hidden":false,"sum_unclear":false,"sum":"","sum_foreign":""},"58":{"sum_foreign_comment":"","sum_foreign_hidden":false,"sum_comment":"","sum_hidden":false,"sum_comment_hidden":false,"sum_unclear":false,"sum":"","sum_foreign":""},"59":{"sum_foreign_comment":"","sum":"","sum_hidden":false,"sum_comment":"","sum_foreign":""},"60":{"sum_foreign_comment":"","sum_foreign_hidden":false,"sum_comment":"","sum_hidden":false,"sum_comment_hidden":false,"sum_unclear":false,"sum":"","sum_foreign":""},"61":{"sum_foreign_comment":"","sum":"","sum_hidden":false,"sum_comment":"","sum_foreign":""},"62":{"sum_foreign_comment":"","sum":"","sum_comment":"","sum_hidden":false,"sum_comment_hidden":false,"sum_foreign":""},"63":{"sum_foreign_comment":"","sum":"","sum_hidden":false,"sum_comment":"","sum_foreign":""},"64":{"sum_foreign_comment":"","sum":"","sum_hidden":false,"sum_comment":"","sum_foreign":""}},"ft_src":"суддя вссу\nЗагальнодержавний регіон\nВищий спеціалізований суд з розгляду цивільних і кримінальних справ\nВіктор\nКузнєцова Ж. В\nПодружжя\nОлексійович\nКузнєцов Віктор Олексійович\nВіктор Олексійович Кузнєцов\nВіктор Кузнєцов\nКузнєцов Віктор Олексійович\nКузнєцов Віктор Олексійович\nКузнєцов\n2.0 , 145\n2006\nKia Magentis\n43.3\n87.99\n2013\n429794\n21165\n429794\n21165\n2.0 , 145\nKia Magentis\n2006\n43.3\n87.99\nПодружжя\nКузнєцова Ж. В\nКузнєцов Віктор Олексійович\nВіктор Олексійович Кузнєцов\nВіктор Кузнєцов\nКузнєцов Віктор Олексійович\nКузнєцов Віктор Олексійович\nВіктор\nОлексійович\nВищий спеціалізований суд з розгляду цивільних і кримінальних справ\nсуддя вссу\nЗагальнодержавний регіон\nКузнєцов\n429794\n21165\n429794\n21165\n2013\nКузнєцова Ж. В\nПодружжя\nОлексійович\nКузнєцов\nВіктор\nКузнєцов Віктор Олексійович\nВіктор Олексійович Кузнєцов\nВіктор Кузнєцов\nКузнєцов Віктор Олексійович\nЗагальнодержавний регіон\nсуддя вссу\nВищий спеціалізований суд з розгляду цивільних і кримінальних справ\nКузнєцов Віктор Олексійович\n2006\nKia Magentis\n2.0 , 145\n21165\n429794\n21165\n429794\n43.3\n87.99\n2013","general":{"inn":"","name":"Віктор","inn_unclear":false,"family":[{"inn":"","inn_hidden":false,"relations_unclear":false,"relations_hidden":false,"relations_other":"","relations":"Подружжя","name_hidden":false,"family_name":"Кузнєцова Ж. В","name_unclear":false}],"inn_hidden":false,"family_raw":"","last_name":"Кузнєцов","post":{"post_unclear":false,"post":"суддя вссу","candidate":"","office_hidden":false,"region":"Загальнодержавний регіон","office":"Вищий спеціалізований суд з розгляду цивільних і кримінальних справ","office_unclear":false,"region_hidden":false},"full_name_suggest":{"output":"Кузнєцов Віктор Олексійович","input":["Кузнєцов Віктор Олексійович","Віктор Олексійович Кузнєцов","Віктор Кузнєцов"]},"full_name":"Кузнєцов Віктор Олексійович","patronymic":"Олексійович","last_name_unclear":false,"name_unclear":false},"source":"VULYK","estate":{"25":[{"space_unclear":false,"costs":"","costs_comment":"","address_hidden":false,"region_hidden":false,"space_comment":"","space_hidden":false,"space":"87.99","address":"","region":"","costs_rent_comment":"","space_comment_unclear":false,"space_comment_hidden":false,"space_units":"м²","costs_rent":""}],"31":[{"space_unclear":false,"address_hidden":false,"region_hidden":false,"space_comment":"","space_hidden":false,"space":"43.3","address":"","region":"","costs_property":"","costs_rent_comment":"","space_comment_unclear":false,"space_units":"м²","costs_property_comment":"","costs_rent":""}]},"intro":{"declaration_year":"2013","isnotdeclaration":"","declaration_year_unclear":false,"declaration_year_hidden":false}}