{"income":{"5":{"value":"256137","family_comment":"","value_unclear":false,"value_hidden":false,"family_unclear":false,"family":"53775","comment":""},"6":{"value":"256113","family_hidden":false,"value_hidden":false,"family_comment":"","family_comment_hidden":false,"comment":"","family":"53775"},"7":{"value":"","value_unclear":false,"family_hidden":false,"value_hidden":false,"family_comment":"","source_name":"","family":"","comment":"","source_name_hidden":false},"8":{"value":"","comment_hidden":false,"family_hidden":false,"value_hidden":false,"family_comment":"","family":"","comment":""},"9":{"value":"","family_comment":"","comment_hidden":false,"family_hidden":false,"value_hidden":false,"family_unclear":false,"family":"","comment":""},"10":{"value":"","comment_hidden":false,"family_hidden":false,"value_hidden":false,"family_comment":"","family":"","comment":""},"11":{"value":"24","value_unclear":false,"comment_hidden":false,"family_hidden":false,"value_hidden":false,"family_comment":"","family":"","comment":""},"12":{"value":"","comment_hidden":false,"family_hidden":false,"value_hidden":false,"family_comment":"","family":"","comment":""},"13":{"value":"","comment_hidden":false,"family_hidden":false,"value_hidden":false,"family_comment":"","family":"","comment":""},"14":{"value":"","comment_hidden":false,"family_hidden":false,"value_hidden":false,"family_comment":"","family":"","comment":""},"15":{"value":"","comment_hidden":false,"family_hidden":false,"value_hidden":false,"family_comment":"","family":"","comment":""},"16":{"value":"","comment_hidden":false,"family_hidden":false,"value_hidden":false,"family_comment":"","family":"","comment":""},"17":{"value":"","comment_hidden":false,"family_hidden":false,"value_hidden":false,"family_comment":"","family":"","comment":""},"18":{"value":"","value_unclear":false,"comment_hidden":false,"family_hidden":false,"value_hidden":false,"family_comment":"","family":"","comment":""},"19":{"value":"","comment_hidden":false,"family_hidden":false,"value_hidden":false,"family_comment":"","family":"","comment":""},"20":{"value":"","value_unclear":false,"family_comment":"","comment_unclear":false,"comment":"","family":""}},"vehicle":{"35":[{"brand_info":"1600 куб. см.","sum_rent_comment":"","sum_rent_hidden":false,"year":"2008","sum_rent_unclear":false,"brand_info_hidden":false,"brand_info_unclear":false,"year_unclear":false,"sum_hidden":false,"sum_rent":"","sum":"","brand":"Skoda Octavia A5","sum_comment":"","brand_unclear":false,"sum_rent_comment_hidden":false,"sum_comment_hidden":false,"sum_unclear":false}],"40":[{"year_hidden":false,"brand_info":"1600 куб. см.","sum_rent_comment":"","brand":"Opel Kadett","sum_comment":"","brand_unclear":false,"year":"1986","brand_hidden":false,"brand_info_unclear":false,"sum":"","sum_rent":""}],"44":[{"brand_info":"Причіп бортовий до легкового автомобіля, модель 810021","sum_rent_comment":"","brand":"ММЗ","sum_comment":"","year":"1993","brand_hidden":false,"brand_info_hidden":false,"sum":"","sum_rent":""}]},"id":"7652","banks":{"51":[{"sum_foreign_comment":"","sum_unclear":false,"sum_units":"UAH","sum_comment":"","sum_hidden":false,"sum_foreign_units":"UAH","sum_comment_hidden":true,"sum_units_hidden":false,"sum":"2115","sum_foreign":""}]},"declaration":{"additional_info_text":"","notfull_lostpages":"","date":"2013-03-27T00:00:00","notfull":"","additional_info":"","url":"http://static.declarations.com.ua/declarations/chosen_ones/judges_batch/338_strilchuk_viktor_andriiovych.pdf"},"liabilities":{"54":{"sum_foreign_comment":"","sum_foreign_hidden":false,"sum_comment":"","sum_hidden":false,"sum_comment_hidden":true,"sum":"252","sum_foreign":""},"55":{"sum_foreign_comment":"","sum":"","sum_hidden":false,"sum_comment":"","sum_foreign":""},"56":{"sum_foreign_comment":"","sum":"8320","sum_comment":"","sum_foreign":""},"57":{"sum_foreign_comment":"","sum_foreign_hidden":false,"sum_comment":"","sum_hidden":false,"sum_comment_hidden":false,"sum_unclear":false,"sum":"","sum_foreign":""},"58":{"sum_foreign_comment":"","sum_foreign_hidden":false,"sum_comment":"","sum_hidden":false,"sum_comment_hidden":false,"sum_unclear":false,"sum":"","sum_foreign":""},"59":{"sum_foreign_comment":"","sum":"","sum_hidden":false,"sum_comment":"","sum_foreign":""},"60":{"sum_foreign_comment":"","sum_foreign_hidden":false,"sum_comment":"","sum_hidden":false,"sum_comment_hidden":false,"sum_unclear":false,"sum":"","sum_foreign":""},"61":{"sum_foreign_comment":"","sum":"","sum_hidden":false,"sum_comment":"","sum_foreign":""},"62":{"sum_foreign_comment":"","sum":"4396","sum_comment":"","sum_hidden":false,"sum_comment_hidden":false,"sum_foreign":""},"63":{"sum_foreign_comment":"","sum":"","sum_hidden":false,"sum_comment":"","sum_foreign":""},"64":{"sum_foreign_comment":"","sum":"","sum_hidden":false,"sum_comment":"","sum_foreign":""}},"ft_src":"4396\n252\n8320\nсуддя апеляційного суду волинської області\nВолинська область\nЗагальний апеляційний суд\nВіктор\nСтрільчук Г. М\nПодружжя\nСтрільчук К. В\nДитина\nАндрійович\nСтрільчук Віктор Андрійович\nВіктор Андрійович Стрільчук\nВіктор Стрільчук\nСтрільчук Віктор Андрійович\nСтрільчук Віктор Андрійович\nСтрільчук\n1600 куб. см.\n2008\nSkoda Octavia A5\nOpel Kadett\n1600 куб. см.\n1986\nПричіп бортовий до легкового автомобіля, модель 810021\nММЗ\n1993\n5,6м х 5,6м\n31.36\n20.48\n25.2\n1000\n60.5\n125.3\n600\n60.5\n2115\n2013\n1600 куб. см.\nSkoda Octavia A5\n2008\n1600 куб. см.\nOpel Kadett\n1986\nММЗ\nПричіп бортовий до легкового автомобіля, модель 810021\n1993\n20.48\n25.2\n125.3\n60.5\n600\n1000\n60.5\n31.36\n5,6м х 5,6м\nСтрільчук Віктор Андрійович\nВіктор Андрійович Стрільчук\nВіктор Стрільчук\nСтрільчук Віктор Андрійович\nСтрільчук Віктор Андрійович\nПодружжя\nСтрільчук Г. М\nДитина\nСтрільчук К. В\nВіктор\nАндрійович\nЗагальний апеляційний суд\nсуддя апеляційного суду волинської області\nВолинська область\nСтрільчук\n252\n8320\n4396\n256113\n53775\n256137\n53775\n24\n2115\n2013\n8320\n4396\n252\n53775\n256113\n24\n53775\n256137\nСтрільчук Г. М\nПодружжя\nДитина\nСтрільчук К. В\nАндрійович\nСтрільчук\nВіктор\nСтрільчук Віктор Андрійович\nВіктор Андрійович Стрільчук\nВіктор Стрільчук\nСтрільчук Віктор Андрійович\nВолинська область\nсуддя апеляційного суду волинської області\nЗагальний апеляційний суд\nСтрільчук Віктор Андрійович\nПричіп бортовий до легкового автомобіля, модель 810021\nММЗ\n1993\n2008\nSkoda Octavia A5\n1600 куб. см.\n1986\nOpel Kadett\n1600 куб. см.\n24\n256137\n53775\n256113\n53775\n60.5\n600\n5,6м х 5,6м\n31.36\n20.48\n25.2\n125.3\n60.5\n1000\n2115\n2013","general":{"inn":"","name":"Віктор","inn_unclear":false,"family":[{"inn":"","inn_hidden":true,"relations_unclear":false,"relations_hidden":false,"relations_other":"","relations":"Подружжя","name_hidden":true,"family_name":"Стрільчук Г. М","name_unclear":false},{"inn":"","inn_hidden":false,"relations_unclear":false,"relations_hidden":false,"relations_other":"","relations":"Дитина","name_hidden":false,"family_name":"Стрільчук К. В","name_unclear":false}],"inn_hidden":true,"family_raw":"","last_name":"Стрільчук","post":{"post_unclear":false,"post":"суддя апеляційного суду волинської області","candidate":"","office_hidden":false,"region":"Волинська область","office":"Загальний апеляційний суд","office_unclear":false,"region_hidden":false},"full_name_suggest":{"output":"Стрільчук Віктор Андрійович","input":["Стрільчук Віктор Андрійович","Віктор Андрійович Стрільчук","Віктор Стрільчук"]},"full_name":"Стрільчук Віктор Андрійович","addresses":[{"place_city_type_unclear":false,"place_address":"","place_district_hidden":true,"place_city_type":"","place_city_hidden":true,"place_city_type_hidden":true,"place":"","place_district":"","place_unclear":false,"place_city":"","place_city_unclear":false,"place_hidden":true,"place_address_hidden":true}],"patronymic":"Андрійович","last_name_unclear":false,"name_unclear":false},"source":"VULYK","estate":{"23":[{"space_hidden":false,"costs":"","costs_comment":"","address_hidden":false,"region_hidden":true,"space_comment":"","space_unclear":false,"space":"600","address":"","space_comment_unclear":false,"region":"","costs_rent_comment":"","costs_unclear":false,"space_comment_hidden":false,"space_units":"м²","costs_rent":""}],"25":[{"space_unclear":false,"costs":"","costs_comment":"","address_hidden":false,"region_hidden":true,"space_comment":"","space_hidden":false,"space":"60.5","address":"","region":"","costs_rent_comment":"","space_comment_unclear":false,"space_comment_hidden":false,"space_units":"м²","costs_rent":""}],"26":[{"space_hidden":false,"costs":"","costs_comment":"","address_hidden":false,"region_hidden":true,"space_comment":"5,6м х 5,6м","space":"31.36","address":"","region":"","costs_rent_comment":"","space_units":"м²","costs_rent":""}],"27":[{"space_hidden":false,"costs":"","costs_comment":"","costs_hidden":false,"address_hidden":false,"region_hidden":true,"space_comment":"","space":"20.48","address":"","region":"","address_unclear":false,"costs_rent_comment":"","space_units":"м²","costs_rent":""},{"costs_rent":"","region":"","costs":"","costs_rent_comment":"","costs_comment":"","space_comment":"","space_units":"м²","space":"25.2","address":""}],"29":[{"space_unclear":false,"address_hidden":false,"region_hidden":true,"space_comment":"","space_hidden":false,"space":"1000","address":"","region":"","costs_property":"","costs_rent_comment":"","space_units":"м²","costs_property_comment":"","costs_rent":""}],"30":[{"space_hidden":false,"address_hidden":false,"region_hidden":true,"space_comment":"","space":"125.3","address":"","region":"","costs_property":"","costs_rent_comment":"","space_units":"м²","costs_property_comment":"","costs_rent":""}],"31":[{"space_unclear":false,"address_hidden":false,"region_hidden":false,"space_comment":"","space_hidden":false,"space":"60.5","address":"","region":"","costs_property":"","costs_rent_comment":"","space_comment_unclear":false,"space_units":"м²","costs_property_comment":"","costs_rent":""}]},"intro":{"declaration_year":"2013","isnotdeclaration":"","declaration_year_unclear":false,"declaration_year_hidden":false}}