{"ft_src":"Volkswagen,Passat B6\n2008\nм. Кривий Ріг (інша інформація прихована)\n600\nм. Кривий Ріг (інша інформація прихована)\n24,1\nм. Кривий Ріг (інша інформація прихована)\n135,7\nм. Дніпропетровськ (інша інформація прихована)\n54\nм. Дніпропетровськ (інша інформація прихована)\n100,3\nм. Дніпропетровськ (інша інформація прихована)\n54\nFALSE\n9.00\nFALSE\nFALSE\n2013\n170573\n81353,6\n236063\n65490\n81358,6\nVolkswagen,Passat B6\n2008\n9.00\nFALSE\nFALSE\nм. Кривий Ріг (інша інформація прихована)\n135,7\nм. Дніпропетровськ (інша інформація прихована)\n54\nм. Кривий Ріг (інша інформація прихована)\n24,1\nм. Кривий Ріг (інша інформація прихована)\n600\nм. Дніпропетровськ (інша інформація прихована)\n54\nм. Дніпропетровськ (інша інформація прихована)\n100,3\nСуддя Дніпропетровського окружного адміністративного суду\nБатько Кучма Сергій Валентинович (інша інформація прихована) ;мати Кучма Галина Ігорівна (інша інформація прихована)\nДніпропетровська\nДніпропетровськ\nКучма\nКучма Костянтин Сергійович\nКостянтин Сергійович Кучма\nКостянтин Кучма\nКучма Костянтин Сергійович\nКостянтин\nКучма Костянтин Сергійович\nАдміністративний місцевий суд\nСуддя\nДніпропетровська область\nСергійович\n49106, Дніпропетровська область, м. Дніпропетровськ. (інша інформація прихована)\n1501\n170573\n81358,6\n236063\n81353,6\n65490\n2013\nFALSE\n1501\nКучма\nСергійович\nБатько Кучма Сергій Валентинович (інша інформація прихована) ;мати Кучма Галина Ігорівна (інша інформація прихована)\nКучма Костянтин Сергійович\nКостянтин Сергійович Кучма\nКостянтин Кучма\nКучма Костянтин Сергійович\nКостянтин\nСуддя Дніпропетровського окружного адміністративного суду\nДніпропетровська\nДніпропетровськ\nСуддя\nДніпропетровська область\nАдміністративний місцевий суд\nКучма Костянтин Сергійович\n49106, Дніпропетровська область, м. Дніпропетровськ. (інша інформація прихована)","estate":{"23":[{"costs":"","address":"","space_units":"","costs_rent_comment":"","space":"","costs_comment":"","costs_rent":"","space_comment":"","region":"","location_raw":""},{"costs":"","address":"","space_units":"","costs_rent_comment":"","space":"","costs_comment":"","costs_rent":"","space_comment":"","region":"","location_raw":""},{"costs":"","address":"","space_units":"","costs_rent_comment":"","space":"","costs_comment":"","costs_rent":"","space_comment":"","region":"","location_raw":""}],"25":[{"costs":"","address":"","space_units":"","costs_rent_comment":"","space":"54","costs_comment":"","costs_rent":"","space_comment":"","region":"","location_raw":"м. Дніпропетровськ (інша інформація прихована)"}],"29":[{"costs_property_comment":"","address":"","space_units":"","costs_rent_comment":"","space":"600","space_comment":"","costs_property":"","region":"","location_raw":"м. Кривий Ріг (інша інформація прихована)","costs_rent":""}],"30":[{"costs_property_comment":"","address":"","space_units":"","costs_rent_comment":"","space":"135,7","space_comment":"","costs_property":"","region":"","location_raw":"м. Кривий Ріг (інша інформація прихована)","costs_rent":""}],"31":[{"costs_property_comment":"","address":"","space_units":"","costs_rent_comment":"","space":"54","space_comment":"","costs_property":"","region":"","location_raw":"м. Дніпропетровськ (інша інформація прихована)","costs_rent":""},{"costs_property_comment":"","address":"","space_units":"","costs_rent_comment":"","space":"100,3","space_comment":"","costs_property":"","region":"","location_raw":"м. Дніпропетровськ (інша інформація прихована)","costs_rent":""}],"33":[{"costs_property_comment":"","address":"","space_units":"","costs_rent_comment":"","space":"24,1","space_comment":"","costs_property":"","region":"","location_raw":"м. Кривий Ріг (інша інформація прихована)","costs_rent":""}]},"vehicle":{"40":[{"sum_comment":"","brand_info":"","sum":"","sum_rent_comment":"","year":"2008","brand":"Volkswagen,Passat B6","sum_rent":"","brand_hidden":false}]},"id":"7741","income":{"5":{"family_comment":"","value":"236063","family":"81353,6","comment":""},"6":{"family_comment":"","value":"170573","family":"0","comment":""},"7":{"family":"0","family_comment":"","value":"0","comment":"","source_name":"0"},"8":{"family_comment":"","value":"0","family":"0","comment":""},"9":{"family_comment":"","value":"0","family":"0","comment":""},"10":{"family_comment":"","value":"0","family":"0","comment":""},"11":{"family_comment":"","value":"0","family":"0","comment":""},"12":{"family_comment":"","value":"0","family":"0","comment":""},"13":{"family_comment":"","value":"0","family":"0","comment":""},"14":{"family_comment":"","value":"0","family":"0","comment":""},"15":{"family_comment":"","value":"0","family":"0","comment":""},"16":{"family_comment":"","value":"65490","family":"0","comment":""},"17":{"family_comment":"","value":"0","family":"0","comment":""},"18":{"family_comment":"","value":"0","family":"0","comment":""},"19":{"family_comment":"","value":"0","family":"0","comment":""},"20":{"family_comment":"","value":"0","family":"81358,6","comment":""},"21":[{"country_comment":"","uah_equal":"0","country":"0","cur":"0"},{"country_comment":"","uah_equal":"0","country":"0","cur":"0"},{"country_comment":"","uah_equal":"0","country":"0","cur":"0"},{"country_comment":"","uah_equal":"0","country":"0","cur":"0"},{"country_comment":"","uah_equal":"0","country":"0","cur":"0"}],"22":[{"country_comment":"","uah_equal":"0","country":"0","cur":"0"},{"country_comment":"","uah_equal":"0","country":"0","cur":"0"},{"country_comment":"","uah_equal":"0","country":"0","cur":"0"},{"country_comment":"","uah_equal":"0","country":"0","cur":"0"},{"country_comment":"","uah_equal":"0","country":"0","cur":"0"}]},"banks":{"45":[{"sum_units":"UAH","sum_comment":"","sum_foreign_units":"","sum":"","sum_foreign_comment":"","sum_foreign":""},{"sum_units":"USD","sum_comment":"","sum_foreign_units":"","sum":"","sum_foreign_comment":"","sum_foreign":""},{"sum_units":"EUR","sum_comment":"","sum_foreign_units":"","sum":"","sum_foreign_comment":"","sum_foreign":""}],"46":[{"sum_units":"UAH","sum_comment":"","sum_foreign_units":"","sum":"","sum_foreign_comment":"","sum_foreign":""},{"sum_units":"USD","sum_comment":"","sum_foreign_units":"","sum":"","sum_foreign_comment":"","sum_foreign":""},{"sum_units":"EUR","sum_comment":"","sum_foreign_units":"","sum":"","sum_foreign_comment":"","sum_foreign":""}],"47":[{"sum_units":"","sum_comment":"","sum_foreign_units":"","sum":"","sum_foreign_comment":"","sum_foreign":""}],"48":[{"sum_units":"","sum_comment":"","sum_foreign_units":"","sum":"","sum_foreign_comment":"","sum_foreign":""}],"49":[{"sum_units":"","sum_comment":"","sum_foreign_units":"","sum":"","sum_foreign_comment":"","sum_foreign":""}],"50":[{"sum_units":"","sum_comment":"","sum_foreign_units":"","sum":"","sum_foreign_comment":"","sum_foreign":""}],"51":[{"sum_units":"UAH","sum_comment":"","sum_foreign_units":"","sum":"","sum_foreign_comment":"","sum_foreign":""},{"sum_units":"USD","sum_comment":"","sum_foreign_units":"","sum":"","sum_foreign_comment":"","sum_foreign":""},{"sum_units":"EUR","sum_comment":"","sum_foreign_units":"","sum":"","sum_foreign_comment":"","sum_foreign":""}],"52":[{"sum_units":"","sum_comment":"","sum_foreign_units":"","sum":"","sum_foreign_comment":"","sum_foreign":""}],"53":[{"sum_units":"","sum_comment":"","sum_foreign_units":"","sum":"","sum_foreign_comment":"","sum_foreign":""}]},"declaration":{"notfull_lostpages":"9.00","additional_info_text":"","additional_info":"FALSE","notfull":"FALSE","url":"http://static.declarations.com.ua/declarations/sudy/mistsevi_sudy/okruzhni_administratyvni_sudy/dnipropetrovska/kuchma.pdf","needs_scancopy_check":false},"general":{"family_raw":"Батько Кучма Сергій Валентинович (інша інформація прихована) ;мати Кучма Галина Ігорівна (інша інформація прихована)","name":"Костянтин","full_name_suggest":{"input":["Кучма Костянтин Сергійович","Костянтин Сергійович Кучма","Костянтин Кучма"],"output":"Кучма Костянтин Сергійович"},"post_raw":"Суддя Дніпропетровського окружного адміністративного суду","name_unclear":false,"patronymic":"Сергійович","patronymic_unclear":false,"last_name_hidden":false,"patronymic_hidden":false,"inn":"","addresses_raw_hidden":true,"last_name":"Кучма","full_name":"Кучма Костянтин Сергійович","post":{"office":"Адміністративний місцевий суд","region":"Дніпропетровська область","post":"Суддя"},"addresses":[{"place_district":"","place_city_type":"","place_address_type":"","place":"Дніпропетровська","place_address":"","place_city":"Дніпропетровськ"}],"name_hidden":false,"last_name_unclear":false,"addresses_raw":"49106, Дніпропетровська область, м. Дніпропетровськ. (інша інформація прихована)"},"liabilities":{"54":{"sum_comment":"","sum_foreign_comment":"","sum_foreign":"","sum":"1501"},"55":{"sum_units":"","sum_comment":"","sum_foreign_units":"","sum":"","sum_foreign_comment":"","sum_foreign":""},"56":{"sum_comment":"","sum_foreign_comment":"","sum_foreign":"","sum":""},"57":{"sum_comment":"","sum_foreign_comment":"","sum_foreign":"","sum":""},"58":{"sum_comment":"","sum_foreign_comment":"","sum_foreign":"","sum":""},"59":{"sum_comment":"","sum_foreign_comment":"","sum_foreign":"","sum":""},"60":{"sum_comment":"","sum_foreign_comment":"","sum_foreign":"","sum":""},"61":{"sum_units":"","sum_comment":"","sum_foreign_units":"","sum":"","sum_foreign_comment":"","sum_foreign":""},"62":{"sum_comment":"","sum_foreign_comment":"","sum_foreign":"","sum":""},"63":{"sum_comment":"","sum_units":"","sum_foreign":"","sum":"","sum_foreign_comment":""},"64":{"sum_comment":"","sum_units":"","sum_foreign":"","sum":"","sum_foreign_comment":""}},"intro":{"isnotdeclaration":"FALSE","declaration_year":"2013"}}