{"income":{"5":{"value":"333237.69","family_comment":"","value_unclear":false,"value_hidden":false,"family_unclear":false,"family":"","comment":""},"6":{"value":"274910.79","family_hidden":false,"value_hidden":false,"family_comment":"","family_comment_hidden":false,"comment":"","family":""},"7":{"value":"58326.9","value_unclear":false,"family_hidden":false,"value_hidden":false,"family_comment":"","source_name":"1. Київський національний університет культури і мистецтв 2. Національна школа суддів","family":"","comment":"","source_name_hidden":false},"8":{"value":"","comment_hidden":false,"family_hidden":false,"value_hidden":false,"family_comment":"","family":"","comment":""},"9":{"value":"","family_comment":"","comment_hidden":false,"family_hidden":false,"value_hidden":false,"family_unclear":false,"family":"","comment":""},"10":{"value":"","comment_hidden":false,"family_hidden":false,"value_hidden":false,"family_comment":"","family":"","comment":""},"11":{"value":"","value_unclear":false,"comment_hidden":false,"family_hidden":false,"value_hidden":false,"family_comment":"","family":"","comment":""},"12":{"value":"","comment_hidden":false,"family_hidden":false,"value_hidden":false,"family_comment":"","family":"","comment":""},"13":{"value":"","comment_hidden":false,"family_hidden":false,"value_hidden":false,"family_comment":"","family":"","comment":""},"14":{"value":"","comment_hidden":false,"family_hidden":false,"value_hidden":false,"family_comment":"","family":"","comment":""},"15":{"value":"","comment_hidden":false,"family_hidden":false,"value_hidden":false,"family_comment":"","family":"","comment":""},"16":{"value":"","comment_hidden":false,"family_hidden":false,"value_hidden":false,"family_comment":"","family":"","comment":""},"17":{"value":"","comment_hidden":false,"family_hidden":false,"value_hidden":false,"family_comment":"","family":"","comment":""},"18":{"value":"","value_unclear":false,"comment_hidden":false,"family_hidden":false,"value_hidden":false,"family_comment":"","family":"","comment":""},"19":{"value":"","comment_hidden":false,"family_hidden":false,"value_hidden":false,"family_comment":"","family":"","comment":""},"20":{"value":"","value_unclear":false,"family_comment":"","comment_unclear":false,"comment":"","family":""}},"vehicle":{"35":[{"brand_info":"об'єм циліндрів 2.2 L, потужність 150","sum_rent_comment":"","sum_rent_hidden":false,"year":"2013","sum_rent_unclear":false,"brand_info_hidden":false,"brand_info_unclear":false,"year_unclear":false,"sum_hidden":false,"sum_rent":"","sum":"341282.62","brand":"Toyota Rav 4","sum_comment":"","brand_unclear":false,"sum_rent_comment_hidden":false,"sum_comment_hidden":false,"sum_unclear":false}]},"id":"8215","declaration":{"additional_info_text":"","notfull_lostpages":"","date":"2014-03-31T00:00:00","notfull":"","additional_info":"","url":"http://static.declarations.com.ua/declarations/chosen_ones/judges_batch/266_oliinyk_alla_serhiivna.pdf"},"liabilities":{"54":{"sum_foreign_comment":"","sum_foreign_hidden":false,"sum_comment":"","sum_hidden":false,"sum_comment_hidden":false,"sum":"22763.55","sum_foreign":""},"55":{"sum_foreign_comment":"","sum":"","sum_hidden":false,"sum_comment":"","sum_foreign":""},"56":{"sum_foreign_comment":"","sum":"","sum_comment":"","sum_foreign":""},"57":{"sum_foreign_comment":"","sum_foreign_hidden":false,"sum_comment":"","sum_hidden":false,"sum_comment_hidden":false,"sum_unclear":false,"sum":"","sum_foreign":""},"58":{"sum_foreign_comment":"","sum_foreign_hidden":false,"sum_comment":"","sum_hidden":false,"sum_comment_hidden":false,"sum_unclear":false,"sum":"","sum_foreign":""},"59":{"sum_foreign_comment":"","sum":"","sum_hidden":false,"sum_comment":"","sum_foreign":""},"60":{"sum_foreign_comment":"","sum_foreign_hidden":false,"sum_comment":"","sum_hidden":false,"sum_comment_hidden":false,"sum_unclear":false,"sum":"","sum_foreign":""},"61":{"sum_foreign_comment":"","sum":"","sum_hidden":false,"sum_comment":"","sum_foreign":""},"62":{"sum_foreign_comment":"","sum":"","sum_comment":"","sum_hidden":false,"sum_comment_hidden":false,"sum_foreign":""},"63":{"sum_foreign_comment":"","sum":"","sum_hidden":false,"sum_comment":"","sum_foreign":""},"64":{"sum_foreign_comment":"","sum":"","sum_hidden":false,"sum_comment":"","sum_foreign":""}},"ft_src":"22763.55\nсуддя вссу\nЗагальнодержавний регіон\nВищий спеціалізований суд з розгляду цивільних і кримінальних справ\nАлла\nСергіївна\nОлійник\nОлійник Алла Сергіївна\nОлійник Алла Сергіївна\nАлла Сергіївна Олійник\nАлла Олійник\nОлійник Алла Сергіївна\nоб'єм циліндрів 2.2 L, потужність 150\n2013\n341282.62\nToyota Rav 4\n44.5\n2013\n274910.79\n1. Київський національний університет культури і мистецтв 2. Національна школа суддів\n58326.9\n333237.69\nоб'єм циліндрів 2.2 L, потужність 150\nToyota Rav 4\n2013\n341282.62\n44.5\nОлійник Алла Сергіївна\nАлла Сергіївна Олійник\nАлла Олійник\nОлійник Алла Сергіївна\nОлійник Алла Сергіївна\nАлла\nСергіївна\nВищий спеціалізований суд з розгляду цивільних і кримінальних справ\nсуддя вссу\nЗагальнодержавний регіон\nОлійник\n22763.55\n58326.9\n1. Київський національний університет культури і мистецтв 2. Національна школа суддів\n274910.79\n333237.69\n2013\n22763.55\nСергіївна\nОлійник\nАлла\nОлійник Алла Сергіївна\nАлла Сергіївна Олійник\nАлла Олійник\nОлійник Алла Сергіївна\nЗагальнодержавний регіон\nсуддя вссу\nВищий спеціалізований суд з розгляду цивільних і кримінальних справ\nОлійник Алла Сергіївна\n2013\n341282.62\nToyota Rav 4\nоб'єм циліндрів 2.2 L, потужність 150\n333237.69\n58326.9\n1. Київський національний університет культури і мистецтв 2. Національна школа суддів\n274910.79\n44.5\n2013","general":{"inn":"","name":"Алла","inn_unclear":false,"patronymic":"Сергіївна","inn_hidden":true,"family_raw":"","last_name":"Олійник","post":{"post_unclear":false,"post":"суддя вссу","candidate":"","office_hidden":false,"region":"Загальнодержавний регіон","office":"Вищий спеціалізований суд з розгляду цивільних і кримінальних справ","office_unclear":false,"region_hidden":false},"last_name_unclear":false,"full_name":"Олійник Алла Сергіївна","addresses":[{"place_city_type_unclear":false,"place_address":"","place_district_hidden":true,"place_city_type":"","place_city_hidden":true,"place_city_type_hidden":true,"place":"","place_district":"","place_unclear":false,"place_city":"","place_city_unclear":false,"place_hidden":true,"place_address_hidden":true}],"full_name_suggest":{"output":"Олійник Алла Сергіївна","input":["Олійник Алла Сергіївна","Алла Сергіївна Олійник","Алла Олійник"]},"name_unclear":false},"source":"VULYK","estate":{"25":[{"space_unclear":false,"costs":"","costs_comment":"","address_hidden":true,"region_hidden":true,"space_comment":"","space_hidden":false,"space":"44.5","address":"","region":"","costs_rent_comment":"","space_comment_unclear":false,"space_comment_hidden":false,"space_units":"м²","costs_rent":""}]},"intro":{"declaration_year":"2013","isnotdeclaration":"","declaration_year_unclear":false,"declaration_year_hidden":false}}