{"ft_src":"Volkswagen,Golf\n1999\n1500\n1000\n2000\n22,5\n22,5\n693\n1920\n693\n765\nFALSE\nFALSE\nFALSE\n2013\n38598\n191147\n1560\n70518\n204189\n30360\n13042\nVolkswagen,Golf\n1999\nFALSE\nFALSE\n1500\n1000\n2000\n22,5\n22,5\nСуддя Окружного адміністративного суду міста Києва\nДружина : ПІБ- приховано, дата народження - приховано; інші дані - приховано.;Мати : ПІБ- приховано, дата народження - приховано; інші дані - приховано.;Дочка : ПІБ- приховано, дата народження - приховано; інші дані - приховано.\nКаракашьян\nКаракашьян Сергій Костянтинович\nСергій Костянтинович Каракашьян\nСергій Каракашьян\nКаракашьян Сергій Костянтинович\nСергій\nКаракашьян Сергій Костянтинович\nАдміністративний місцевий суд\nСуддя\nм. Київ\nКостянтинович\n24725\n3521\n8926\n4145\n191147\n38598\n13042\n30360\n204189\n70518\n1560\n693\n1920\n765\n693\n2013\nFALSE\n8926\n24725\n3521\n4145\nКаракашьян\nКостянтинович\nДружина : ПІБ- приховано, дата народження - приховано; інші дані - приховано.;Мати : ПІБ- приховано, дата народження - приховано; інші дані - приховано.;Дочка : ПІБ- приховано, дата народження - приховано; інші дані - приховано.\nКаракашьян Сергій Костянтинович\nСергій Костянтинович Каракашьян\nСергій Каракашьян\nКаракашьян Сергій Костянтинович\nСергій\nСуддя Окружного адміністративного суду міста Києва\nСуддя\nм. Київ\nАдміністративний місцевий суд\nКаракашьян Сергій Костянтинович","estate":{"23":[{"costs":"","address":"","space_units":"","costs_rent_comment":"","space":"1500","costs_comment":"","costs_rent":"","space_comment":"","region":"","location_raw":"приховано"},{"costs":"","address":"","space_units":"","costs_rent_comment":"","space":"","costs_comment":"","costs_rent":"","space_comment":"","region":"","location_raw":""},{"costs":"","address":"","space_units":"","costs_rent_comment":"","space":"","costs_comment":"","costs_rent":"","space_comment":"","region":"","location_raw":""}],"25":[{"costs":"","address":"","space_units":"","costs_rent_comment":"","space":"22,5","costs_comment":"","costs_rent":"","space_comment":"","region":"","location_raw":"приховано"}],"29":[{"costs_property_comment":"","address":"","space_units":"","costs_rent_comment":"","space":"1000","space_comment":"","costs_property":"","region":"","location_raw":"приховано","costs_rent":""},{"costs_property_comment":"","address":"","space_units":"","costs_rent_comment":"","space":"2000","space_comment":"","costs_property":"","region":"","location_raw":"приховано","costs_rent":""}],"31":[{"costs_property_comment":"","address":"","space_units":"","costs_rent_comment":"","space":"22,5","space_comment":"","costs_property":"","region":"","location_raw":"приховано","costs_rent":""}]},"vehicle":{"35":[{"sum_comment":"","brand_info":"","sum":"","sum_rent_comment":"","year":"1999","brand":"Volkswagen,Golf","sum_rent":"","brand_hidden":false}]},"id":"840","income":{"5":{"family_comment":"","value":"204189","family":"70518","comment":""},"6":{"family_comment":"","value":"191147","family":"38598","comment":""},"7":{"family":"0","family_comment":"","value":"0","comment":"","source_name":"0"},"8":{"family_comment":"","value":"0","family":"0","comment":""},"9":{"family_comment":"","value":"0","family":"0","comment":""},"10":{"family_comment":"","value":"0","family":"1560","comment":""},"11":{"family_comment":"","value":"0","family":"0","comment":""},"12":{"family_comment":"","value":"0","family":"0","comment":""},"13":{"family_comment":"","value":"0","family":"0","comment":""},"14":{"family_comment":"","value":"0","family":"0","comment":""},"15":{"family_comment":"","value":"0","family":"0","comment":""},"16":{"family_comment":"","value":"0","family":"0","comment":""},"17":{"family_comment":"","value":"0","family":"0","comment":""},"18":{"family_comment":"","value":"0","family":"0","comment":""},"19":{"family_comment":"","value":"0","family":"0","comment":""},"20":{"family_comment":"","value":"13042","family":"30360","comment":""},"21":[{"country_comment":"","uah_equal":"0","country":"0","cur":"0"},{"country_comment":"","uah_equal":"0","country":"0","cur":"0"},{"country_comment":"","uah_equal":"0","country":"0","cur":"0"},{"country_comment":"","uah_equal":"0","country":"0","cur":"0"},{"country_comment":"","uah_equal":"0","country":"0","cur":"0"}],"22":[{"country_comment":"","uah_equal":"0","country":"0","cur":"0"},{"country_comment":"","uah_equal":"0","country":"0","cur":"0"},{"country_comment":"","uah_equal":"0","country":"0","cur":"0"},{"country_comment":"","uah_equal":"0","country":"0","cur":"0"},{"country_comment":"","uah_equal":"0","country":"0","cur":"0"}]},"banks":{"45":[{"sum_units":"UAH","sum_comment":"","sum_foreign_units":"","sum":"693","sum_foreign_comment":"","sum_foreign":""},{"sum_units":"USD","sum_comment":"","sum_foreign_units":"","sum":"","sum_foreign_comment":"","sum_foreign":""},{"sum_units":"EUR","sum_comment":"","sum_foreign_units":"","sum":"","sum_foreign_comment":"","sum_foreign":""}],"46":[{"sum_units":"UAH","sum_comment":"","sum_foreign_units":"","sum":"693","sum_foreign_comment":"","sum_foreign":""},{"sum_units":"USD","sum_comment":"","sum_foreign_units":"","sum":"","sum_foreign_comment":"","sum_foreign":""},{"sum_units":"EUR","sum_comment":"","sum_foreign_units":"","sum":"","sum_foreign_comment":"","sum_foreign":""}],"47":[{"sum_units":"","sum_comment":"","sum_foreign_units":"","sum":"","sum_foreign_comment":"","sum_foreign":""}],"48":[{"sum_units":"","sum_comment":"","sum_foreign_units":"","sum":"","sum_foreign_comment":"","sum_foreign":""}],"49":[{"sum_units":"","sum_comment":"","sum_foreign_units":"","sum":"","sum_foreign_comment":"","sum_foreign":""}],"50":[{"sum_units":"","sum_comment":"","sum_foreign_units":"","sum":"","sum_foreign_comment":"","sum_foreign":""}],"51":[{"sum_units":"UAH","sum_comment":"","sum_foreign_units":"","sum":"1920","sum_foreign_comment":"","sum_foreign":""},{"sum_units":"USD","sum_comment":"","sum_foreign_units":"","sum":"","sum_foreign_comment":"","sum_foreign":""},{"sum_units":"EUR","sum_comment":"","sum_foreign_units":"","sum":"","sum_foreign_comment":"","sum_foreign":""}],"52":[{"sum_units":"","sum_comment":"","sum_foreign_units":"","sum":"765","sum_foreign_comment":"","sum_foreign":""}],"53":[{"sum_units":"","sum_comment":"","sum_foreign_units":"","sum":"","sum_foreign_comment":"","sum_foreign":""}]},"declaration":{"notfull_lostpages":"","additional_info_text":"","additional_info":"FALSE","notfull":"FALSE","url":"http://static.declarations.com.ua/declarations/sudy/mistsevi_sudy/okruzhni_administratyvni_sudy/m._kyiv/karakashyan.pdf","needs_scancopy_check":false},"general":{"family_raw":"Дружина : ПІБ- приховано, дата народження - приховано; інші дані - приховано.;Мати : ПІБ- приховано, дата народження - приховано; інші дані - приховано.;Дочка : ПІБ- приховано, дата народження - приховано; інші дані - приховано.","name":"Сергій","full_name_suggest":{"input":["Каракашьян Сергій Костянтинович","Сергій Костянтинович Каракашьян","Сергій Каракашьян"],"output":"Каракашьян Сергій Костянтинович"},"post_raw":"Суддя Окружного адміністративного суду міста Києва","name_unclear":false,"patronymic":"Костянтинович","patronymic_unclear":false,"last_name_hidden":false,"patronymic_hidden":false,"inn":"","addresses_raw_hidden":true,"last_name":"Каракашьян","full_name":"Каракашьян Сергій Костянтинович","post":{"office":"Адміністративний місцевий суд","region":"м. Київ","post":"Суддя"},"addresses_raw":"приховано","name_hidden":false,"last_name_unclear":false},"liabilities":{"54":{"sum_comment":"","sum_foreign_comment":"","sum_foreign":"","sum":"4145"},"55":{"sum_units":"","sum_comment":"","sum_foreign_units":"","sum":"","sum_foreign_comment":"","sum_foreign":""},"56":{"sum_comment":"","sum_foreign_comment":"","sum_foreign":"","sum":"3521"},"57":{"sum_comment":"","sum_foreign_comment":"","sum_foreign":"","sum":"24725"},"58":{"sum_comment":"","sum_foreign_comment":"","sum_foreign":"","sum":"8926"},"59":{"sum_comment":"","sum_foreign_comment":"","sum_foreign":"","sum":""},"60":{"sum_comment":"","sum_foreign_comment":"","sum_foreign":"","sum":""},"61":{"sum_units":"","sum_comment":"","sum_foreign_units":"","sum":"","sum_foreign_comment":"","sum_foreign":""},"62":{"sum_comment":"","sum_foreign_comment":"","sum_foreign":"","sum":""},"63":{"sum_comment":"","sum_units":"","sum_foreign":"","sum":"","sum_foreign_comment":""},"64":{"sum_comment":"","sum_units":"","sum_foreign":"","sum":"","sum_foreign_comment":""}},"intro":{"isnotdeclaration":"FALSE","declaration_year":"2013"}}