{"income":{"5":{"family_comment":"","value":"889988","value_unclear":false,"family":"12903","comment":""},"6":{"family_comment":"","value":"320100","value_unclear":false,"family":"","comment":""},"7":{"source_name_unclear":false,"value":"","family_hidden":false,"value_hidden":false,"family_comment":"","source_name":"","family":"","comment":"","source_name_hidden":false},"8":{"value":"","family_hidden":false,"value_hidden":false,"family_comment":"","family":"","comment":""},"9":{"value":"","value_unclear":false,"value_hidden":false,"family_comment":"","comment_unclear":false,"comment":"","family":""},"10":{"value":"13764","family_hidden":false,"value_hidden":false,"family_comment":"","family":"","comment":""},"11":{"value":"","family_hidden":false,"value_hidden":false,"family_comment":"","family":"","comment":""},"12":{"value":"","family_hidden":false,"value_hidden":false,"family_comment":"","family":"","comment":""},"13":{"value":"","family_hidden":false,"value_hidden":false,"family_comment":"","family":"","comment":""},"14":{"value":"","family_hidden":false,"value_hidden":false,"family_comment":"","family":"","comment":""},"15":{"value":"","family_hidden":false,"value_hidden":false,"family_comment":"","family":"","comment":""},"16":{"value":"556124","family_hidden":false,"value_hidden":false,"family_comment":"","family":"","comment":""},"17":{"value":"","family_hidden":false,"value_hidden":false,"family_comment":"","family":"","comment":""},"18":{"value":"","comment_unclear":false,"family_hidden":false,"value_hidden":false,"family_comment":"","family":"","comment":""},"19":{"value":"","family_hidden":false,"value_hidden":false,"family_comment":"","family":"","comment":""},"20":{"value":"","value_unclear":false,"family_hidden":false,"value_hidden":false,"family_comment":"","comment_unclear":false,"comment":"","family":"12903"}},"vehicle":{"35":[{"brand_info":"1998 куб. см.","sum_rent_comment":"","sum_rent_hidden":false,"year":"2011","sum_hidden":false,"brand_info_unclear":false,"sum_rent":"","sum":"","brand":"Hyundai IX35","sum_comment":"","brand_unclear":false,"sum_rent_comment_hidden":false,"sum_comment_hidden":false,"sum_unclear":false}]},"id":"849","banks":{"45":[{"sum_units":"UAH","sum_foreign":"","sum_hidden":false,"sum":"1678","sum_units_hidden":false,"sum_foreign_comment":"","sum_foreign_hidden":false,"sum_comment":"","sum_foreign_units":"UAH","sum_units_unclear":false,"sum_comment_hidden":false,"sum_unclear":false}],"51":[{"sum_units":"UAH","sum_hidden":false,"sum":"82694","sum_units_hidden":false,"sum_foreign_comment":"","sum_foreign_hidden":false,"sum_comment":"","sum_comment_unclear":false,"sum_foreign_units":"UAH","sum_foreign":"","sum_comment_hidden":false,"sum_unclear":false}]},"declaration":{"additional_info_text":"","notfull_lostpages":"","date":"2014-03-14T00:00:00","notfull":"","additional_info":"","url":"http://static.declarations.com.ua/declarations/chosen_ones/judges_batch/119_retseburynskyi_iurii_iosypovych.pdf"},"liabilities":{"54":{"sum_foreign_comment":"","sum_foreign_hidden":false,"sum_comment":"","sum_hidden":false,"sum_foreign_comment_unclear":false,"sum_comment_hidden":false,"sum":"576","sum_foreign":""},"55":{"sum_foreign_comment":"","sum":"","sum_hidden":false,"sum_comment":"","sum_foreign":""},"56":{"sum_foreign_comment":"","sum":"","sum_comment":"","sum_foreign":""},"57":{"sum_foreign_comment":"","sum_foreign_hidden":false,"sum_comment":"","sum_hidden":false,"sum_comment_hidden":false,"sum":"","sum_foreign":""},"58":{"sum_foreign_comment":"","sum":"","sum_comment":"","sum_hidden":false,"sum_comment_hidden":false,"sum_foreign":""},"59":{"sum_foreign_comment":"","sum_foreign_hidden":false,"sum_comment":"","sum_hidden":false,"sum":"","sum_foreign":""},"60":{"sum_foreign_comment":"","sum":"","sum_comment":"","sum_comment_unclear":false,"sum_hidden":false,"sum_comment_hidden":false,"sum_foreign":""},"61":{"sum_foreign_comment":"","sum":"","sum_hidden":false,"sum_comment":"","sum_foreign":""},"62":{"sum_foreign_comment":"","sum_foreign_hidden":false,"sum_comment":"","sum_comment_hidden":false,"sum_unclear":false,"sum":"","sum_foreign":""},"63":{"sum_foreign_comment":"","sum_foreign_hidden":false,"sum_comment":"","sum_hidden":false,"sum_comment_hidden":false,"sum":"","sum_foreign":""},"64":{"sum_foreign_comment":"","sum":"","sum_comment":"","sum_hidden":false,"sum_comment_hidden":false,"sum_foreign":""}},"ft_src":"576\nсуддя вищого адміністративного суду україни\nЗагальнодержавний регіон\nВищий адміністративний суд\nЮрій\nПодружжя\nЙосипович\nРецебуринський\nРецебуринський Юрій Йосипович\nРецебуринський Юрій Йосипович\nЮрій Йосипович Рецебуринський\nЮрій Рецебуринський\nРецебуринський Юрій Йосипович\nHyundai IX35\n1998 куб. см.\n2011\n1/2 ч\n62.8\n1/2 ч\n855000\n62.8\n82694\n1678\n2013\n1998 куб. см.\nHyundai IX35\n2011\n2013\nПодружжя\nРецебуринський Юрій Йосипович\nЮрій Йосипович Рецебуринський\nЮрій Рецебуринський\nРецебуринський Юрій Йосипович\nЮрій\nРецебуринський Юрій Йосипович\nЙосипович\nсуддя вищого адміністративного суду україни\nВищий адміністративний суд\nЗагальнодержавний регіон\nРецебуринський\n576\n320100\n12903\n889988\n12903\n556124\n13764\n1/2 ч\n62.8\n855000\n62.8\n1/2 ч\n1678\n82694\n576\n320100\n13764\n12903\n889988\n556124\n12903\nПодружжя\nЮрій\nЙосипович\nРецебуринський\nРецебуринський Юрій Йосипович\nЮрій Йосипович Рецебуринський\nЮрій Рецебуринський\nРецебуринський Юрій Йосипович\nЗагальнодержавний регіон\nВищий адміністративний суд\nсуддя вищого адміністративного суду україни\nРецебуринський Юрій Йосипович\n2011\nHyundai IX35\n1998 куб. см.\n13764\n12903\n12903\n889988\n556124\n320100\n1/2 ч\n62.8\n855000\n1/2 ч\n62.8\n1678\n82694\n2013","general":{"inn":"","name":"Юрій","inn_unclear":true,"family":[{"inn":"","relations":"Подружжя","inn_unclear":true,"relations_hidden":false,"inn_hidden":true,"relations_other":"","name_hidden":true,"family_name":"","name_unclear":true}],"inn_hidden":true,"family_raw":"","last_name":"Рецебуринський","post":{"post":"суддя вищого адміністративного суду україни","region":"Загальнодержавний регіон","candidate":"","office_hidden":false,"post_hidden":false,"office":"Вищий адміністративний суд","region_hidden":false},"last_name_unclear":false,"full_name":"Рецебуринський Юрій Йосипович","addresses":[{"place_city_type_unclear":true,"place_address":"","place_district_hidden":true,"place_city_type":"","place_address_hidden":true,"place_address_unclear":true,"place_city_type_hidden":true,"place":"","place_district":"","place_unclear":true,"place_city":"","place_city_unclear":true,"place_hidden":true,"place_city_hidden":true,"place_district_unclear":true}],"patronymic":"Йосипович","full_name_suggest":{"output":"Рецебуринський Юрій Йосипович","input":["Рецебуринський Юрій Йосипович","Юрій Йосипович Рецебуринський","Юрій Рецебуринський"]},"name_unclear":false},"source":"VULYK","estate":{"25":[{"region_unclear":true,"space_unclear":false,"costs":"855000","costs_comment":"","costs_hidden":false,"address_hidden":false,"region_hidden":true,"space_comment":"1/2 ч","space":"62.8","address":"","costs_rent_comment_unclear":false,"region":"","costs_rent_comment":"","costs_rent_hidden":false,"space_comment_unclear":false,"costs_rent_comment_hidden":false,"space_units":"м²","costs_comment_hidden":false,"costs_rent":"","costs_unclear":false}],"31":[{"region_unclear":true,"space_unclear":false,"costs_property_hidden":false,"address_hidden":false,"region_hidden":true,"space_comment":"1/2 ч","space_units_hidden":false,"space_hidden":false,"space":"62.8","address":"","region":"","costs_property":"","costs_rent_comment":"","space_comment_unclear":false,"space_units":"м²","costs_property_comment":"","costs_rent":""}]},"intro":{"declaration_year":"2013","isnotdeclaration":"","declaration_year_unclear":false,"declaration_year_hidden":false}}