[{"id":"vulyk_96_75","ft_src":"2464 куб. см.\n2007\nГАЗ 2705-4143 НГ\n2006\n1799 куб. см.\nChevrolet Lacetti\nЛуганська область\nм. Попасна, вул. Громової, 17\n.687\nм. Попасна, вул. Кошевого,18\nЛуганська область\n60\nЛуганська область\nм. Попасна, вул. Громової, 17\n17\n.66\nм. Попасна, вул. Кошевого,18\nЛуганська область\nЛуганська область\nм. Попасна, вул. Громової, 17\n52\nЛуганська область\nм. Попасна, вул. Миру, 152/11\n44.6\nм. Сєвєродонецьк, вул. Космонавтів, 29/113\n68.1\nЛуганська область\nУкраїна, м. Попасна, Кошевого, 30/2\n49.5\nЛуганська область\n2015\n34363\n209254\n46341\n209284\n11977\nChevrolet Lacetti\n1799 куб. см.\n2006\n2464 куб. см.\n2007\nГАЗ 2705-4143 НГ\n2015\nАрхипенко Анжеліка Вікторівна\nАнжеліка Вікторівна Архипенко\nАнжеліка Архипенко\nАрхипенко Анжеліка Вікторівна\nАрхипенко Анжеліка Вікторівна\n2519411327\nАнжеліка\nАрхипенко\nЛуганська область\nсуддя попаснянського районного суду луганської області\nЗагальний місцевий суд\nВікторівна\nвул. О. Кошевого, 18\nЛуганська область\nПопасна\nПодружжя\nАрхипенко В. М. 1968\n2505512970\nДитина\nАрхипенко О. В., 1993\n3429203042\n3520\n69\n34363\n209254\n11977\n209284\n46341\n52\nм. Попасна, вул. Громової, 17\nЛуганська область\n68.1\nм. Сєвєродонецьк, вул. Космонавтів, 29/113\nЛуганська область\n49.5\nУкраїна, м. Попасна, Кошевого, 30/2\nЛуганська область\n17\nм. Попасна, вул. Громової, 17\nЛуганська область\n.66\nЛуганська область\nм. Попасна, вул. Кошевого,18\nм. Попасна, вул. Громової, 17\n.687\nЛуганська область\n60\nм. Попасна, вул. Кошевого,18\nЛуганська область\nм. Попасна, вул. Миру, 152/11\nЛуганська область\n44.6\n3520\n69\n2505512970\nАрхипенко В. М. 1968\nПодружжя\n3429203042\nДитина\nАрхипенко О. В., 1993\n2519411327\nАнжеліка\nВікторівна\nАрхипенко\nАрхипенко Анжеліка Вікторівна\nАнжеліка Вікторівна Архипенко\nАнжеліка Архипенко\nАрхипенко Анжеліка Вікторівна\nЛуганська область\nПопасна\nвул. О. Кошевого, 18\nсуддя попаснянського районного суду луганської області\nЛуганська область\nЗагальний місцевий суд\nАрхипенко Анжеліка Вікторівна","estate":{"23":[{"address":"м. Попасна, вул. Кошевого,18","space_units":"га","costs_rent_unclear":false,"space_hidden":false,"space_unclear":false,"region_hidden":false,"space_units_unclear":false,"costs_comment":"","space_comment_unclear":false,"space":".66","address_unclear":false,"space_comment":"","address_hidden":false,"costs_rent_comment":"","costs":"","region_unclear":false,"region":"Луганська область","costs_rent":""}],"24":[{"address":"м. Попасна, вул. Кошевого,18","space_units":"м²","space_hidden":false,"space_unclear":false,"region_hidden":false,"costs_comment":"","space_comment":"","address_hidden":false,"space":"60","space_comment_unclear":false,"costs_rent_comment":"","costs":"","region":"Луганська область","costs_rent":""}],"25":[{"costs":"","costs_unclear":false,"address":"м. Сєвєродонецьк, вул. Космонавтів, 29/113","space_units":"м²","space_hidden":false,"space_comment":"","region_hidden":false,"costs_comment":"","space_comment_unclear":false,"space_comment_hidden":false,"space_unclear":false,"address_unclear":true,"address_hidden":false,"costs_rent_comment":"","space":"68.1","costs_rent":"","region":"Луганська область","costs_rent_comment_unclear":false},{"address":"Україна, м. Попасна, Кошевого, 30/2","space_units":"м²","space_hidden":false,"space_comment":"","region_hidden":false,"costs_comment":"","address_hidden":false,"costs":"","address_unclear":true,"space_comment_unclear":false,"costs_rent_comment":"","space":"49.5","region":"Луганська область","costs_rent":""}],"29":[{"costs_property_comment":"","address":"м. Попасна, вул. Громової, 17","space_units":"га","space_unclear":false,"region_hidden":false,"costs_property":"","space_comment":"","address_hidden":false,"address_unclear":false,"costs_rent_comment":"","space":".687","region_unclear":false,"region":"Луганська область","costs_rent":""}],"30":[{"costs_property_comment":"","address":"м. Попасна, вул. Громової, 17","space_units":"м²","costs_rent_comment":"","space":"52","region":"Луганська область","region_hidden":false,"costs_property":"","space_comment":"","address_hidden":false,"costs_rent":""}],"31":[{"costs_property_comment":"","address":"м. Попасна, вул. Миру, 152/11","space_units":"м²","space_hidden":false,"space_unclear":false,"region_hidden":false,"costs_property":"","space_comment":"","address_hidden":false,"address_unclear":false,"costs_rent_comment":"","space":"44.6","region":"Луганська область","costs_rent":""}],"33":[{"costs_property_comment":"","address":"м. Попасна, вул. Громової, 17","space_units":"м²","costs_rent_comment":"","space":"17","region":"Луганська область","region_hidden":false,"costs_property":"","space_comment":"","address_hidden":false,"costs_rent":""}]},"vehicle":{"40":[{"sum_comment":"","brand_info_hidden":false,"brand_info":"1799 куб. см.","sum":"","sum_rent_comment":"","year":"2006","brand":"Chevrolet Lacetti","sum_rent":"","year_unclear":false}],"41":[{"sum_comment":"","brand_info":"2464 куб. см.","sum":"","sum_rent_comment":"","year":"2007","brand":"ГАЗ 2705-4143 НГ","sum_rent":""}]},"source":"VULYK","income":{"5":{"family_comment":"","value":"209284","family_unclear":false,"family":"46341","comment":""},"6":{"family_comment":"","family":"34363","comment":"","value_unclear":false,"family_unclear":false,"value":"209254"},"7":{"source_name_hidden":false,"family_comment":"","family":"","comment":"","value_unclear":false,"family_unclear":false,"value":"","source_name":""},"8":{"family_comment":"","value":"","family":"","comment":""},"9":{"family_comment":"","value":"","family":"","comment":""},"10":{"family_comment":"","value":"","family":"","comment":"","value_unclear":false},"11":{"family_comment":"","value":"","family":"","comment":""},"12":{"family_comment":"","value":"","family":"","comment":""},"13":{"family_comment":"","value":"","family":"","comment":""},"14":{"family_comment":"","value":"","family":"","comment":""},"15":{"family_comment":"","value":"","family":"","comment":""},"16":{"family_comment":"","value":"","family":"","comment":""},"17":{"family_comment":"","value":"","family":"","comment":""},"18":{"family_comment":"","value":"","family":"","comment":""},"19":{"family_comment":"","value":"","family":"","comment":""},"20":{"family_comment":"","comment":"","family":"11977","value_unclear":false,"comment_hidden":false,"comment_unclear":false,"value":""}},"general":{"family":[{"inn":"2505512970","inn_unclear":false,"family_name":"Архипенко В. М. 1968","relations_other":"","relations_hidden":false,"name_unclear":false,"inn_hidden":false,"name_hidden":false,"relations":"Подружжя"},{"inn":"3429203042","family_name":"Архипенко О. В., 1993","relations_other":"","name_unclear":false,"inn_hidden":false,"name_hidden":false,"relations":"Дитина"}],"family_raw":"","name":"Анжеліка","full_name_suggest":{"input":["Архипенко Анжеліка Вікторівна","Анжеліка Вікторівна Архипенко","Анжеліка Архипенко"],"output":"Архипенко Анжеліка Вікторівна"},"patronymic":"Вікторівна","inn_hidden":false,"patronymic_hidden":false,"inn":"2519411327","addresses":[{"place_city_type_hidden":false,"place_city_type":"Місто","place_city_hidden":false,"place_hidden":false,"place_district":"","place_district_hidden":false,"place":"Луганська область","place_address":"вул. О. Кошевого, 18","place_address_hidden":false,"place_city":"Попасна"}],"last_name":"Архипенко","full_name":"Архипенко Анжеліка Вікторівна","post":{"office_unclear":false,"post":"суддя попаснянського районного суду луганської області","region":"Луганська область","office":"Загальний місцевий суд"}},"liabilities":{"54":{"sum_comment":"","sum_hidden":false,"sum":"","sum_foreign_comment":"","sum_foreign":"","sum_comment_hidden":false},"55":{"sum_comment":"","sum_foreign_comment":"","sum_foreign":"","sum":""},"56":{"sum_comment":"","sum_foreign_comment":"","sum_foreign":"","sum_unclear":false,"sum":"3520"},"57":{"sum_comment":"","sum_foreign_comment":"","sum_foreign":"","sum":"","sum_comment_hidden":false},"58":{"sum_comment":"","sum":"","sum_foreign_comment":"","sum_foreign":"","sum_unclear":false,"sum_comment_hidden":false},"59":{"sum_comment":"","sum_foreign_comment":"","sum_foreign":"","sum":""},"60":{"sum_comment":"","sum_foreign_comment":"","sum_foreign":"","sum":"","sum_comment_hidden":false},"61":{"sum_comment":"","sum_foreign_comment":"","sum_foreign":"","sum":""},"62":{"sum_comment":"","sum_foreign_comment":"","sum_foreign":"","sum":"69"},"63":{"sum_comment":"","sum_foreign_comment":"","sum_foreign":"","sum":"","sum_comment_hidden":false},"64":{"sum_comment":"","sum_foreign_comment":"","sum_foreign":"","sum":"","sum_comment_hidden":false}},"declaration":{"notfull_lostpages":"","additional_info_text":"","additional_info":"","date":"2016-03-28T00:00:00","notfull":"","url":"http://static.declarations.com.ua/declarations/chosen_ones/judges_batch/289_arkhypenko_anzhelika_viktorivna_2015.pdf"},"intro":{"isnotdeclaration":"","declaration_year":"2015"}},{"id":"vulyk_100_76","ft_src":"4143 НГ, 2464 куб. см.\n2007\nГАЗ 2705 Газель\n2006\n1799 куб. см.\nChevrolet Lacetti\nЛуганська область\nм. Попасна, вул. Громовой, 17\n.687\nм. Попасна, вул. Кошевого, 18\n60\nЛуганська область\nЛуганська область\nм. Попасна, вул. Громовой, 17\n17\nм. Попасна, вул. Кошевого, 18\n.66\nЛуганська область\nЛуганська область\nм. Попасна, вул. Громовой, 17\n52\nЛуганська область\nм. Попасна, вул. Леніна, 152/11\n44.6\nм. Сєвєродонецьк, пр. Космонавтів, 29/113\n68.1\nЛуганська область\nм. Попасна, вул. Кошевого, 30/2\n49.5\nЛуганська область\n2014\n50380\n217890\n50380\n217890\n25667\nChevrolet Lacetti\n1799 куб. см.\n2006\n4143 НГ, 2464 куб. см.\nГАЗ 2705 Газель\n2007\n52\nЛуганська область\nм. Попасна, вул. Громовой, 17\n68.1\nЛуганська область\nм. Сєвєродонецьк, пр. Космонавтів, 29/113\nм. Попасна, вул. Кошевого, 30/2\n49.5\nЛуганська область\nЛуганська область\nм. Попасна, вул. Громовой, 17\n17\n.66\nЛуганська область\nм. Попасна, вул. Кошевого, 18\nм. Попасна, вул. Громовой, 17\n.687\nЛуганська область\n60\nм. Попасна, вул. Кошевого, 18\nЛуганська область\n44.6\nЛуганська область\nм. Попасна, вул. Леніна, 152/11\nПодружжя\nАрхипенко В. М. 1968\n2505512970\nДитина\nАрхипенко О. В. 1993\n3429203042\nВікторівна\nЛуганська область\n93300, вул. О. Кошевого, 18\nПопасна\nАрхипенко\nАрхипенко Анжеліка Вікторівна\nАнжеліка Вікторівна Архипенко\nАнжеліка Архипенко\nАрхипенко Анжеліка Вікторівна\nАрхипенко Анжеліка Вікторівна\n2519411327\nАнжеліка\nЗагальний місцевий суд\nЛуганська область\nсуддя попаснянського районного суду луганської області\n4230\n217890\n50380\n25667\n217890\n50380\n2014\n4230\n2505512970\nАрхипенко В. М. 1968\nПодружжя\n3429203042\nДитина\nАрхипенко О. В. 1993\n2519411327\n93300, вул. О. Кошевого, 18\nПопасна\nЛуганська область\nВікторівна\nАрхипенко\nЛуганська область\nЗагальний місцевий суд\nсуддя попаснянського районного суду луганської області\nАрхипенко Анжеліка Вікторівна\nАрхипенко Анжеліка Вікторівна\nАнжеліка Вікторівна Архипенко\nАнжеліка Архипенко\nАрхипенко Анжеліка Вікторівна\nАнжеліка","estate":{"23":[{"address":"м. Попасна, вул. Кошевого, 18","space_units":"га","costs_comment":"","space_unclear":false,"region_hidden":false,"space_comment":"","address_hidden":false,"costs":"","address_unclear":false,"space_comment_unclear":false,"costs_comment_unclear":false,"costs_rent_comment":"","space":".66","region":"Луганська область","costs_rent":""}],"24":[{"address":"м. Попасна, вул. Кошевого, 18","space_units":"м²","costs_comment":"","space_unclear":false,"region_hidden":false,"space_comment":"","address_hidden":false,"space":"60","space_comment_unclear":false,"costs_rent_comment":"","costs":"","region":"Луганська область","costs_rent":""}],"25":[{"address":"м. Сєвєродонецьк, пр. Космонавтів, 29/113","space_units":"м²","costs_comment":"","space_unclear":false,"region_hidden":false,"space_comment":"","address_hidden":false,"costs":"","address_unclear":false,"space_comment_unclear":false,"costs_comment_unclear":false,"costs_rent_comment":"","space":"68.1","region":"Луганська область","costs_rent":""},{"costs":"","address":"м. Попасна, вул. Кошевого, 30/2","space_units":"м²","costs_rent_comment":"","space":"49.5","space_comment":"","region_hidden":false,"costs_comment":"","region":"Луганська область","costs_rent":""}],"29":[{"costs_property_comment":"","address":"м. Попасна, вул. Громовой, 17","space_units":"га","space_unclear":false,"region_hidden":false,"costs_property":"","space_comment":"","address_hidden":false,"address_unclear":false,"costs_rent_comment":"","space":".687","region_unclear":true,"region":"Луганська область","costs_rent":""}],"30":[{"costs_property_comment":"","address":"м. Попасна, вул. Громовой, 17","space_units":"м²","costs_rent_comment":"","space":"52","region":"Луганська область","region_hidden":false,"costs_property":"","space_comment":"","address_hidden":false,"costs_rent":""}],"31":[{"costs_property_comment":"","address":"м. Попасна, вул. Леніна, 152/11","space_units":"м²","space_unclear":false,"region_hidden":false,"costs_property":"","space_comment":"","address_hidden":false,"address_unclear":false,"space_comment_unclear":false,"costs_rent_comment":"","space":"44.6","costs_property_comment_unclear":false,"region_unclear":false,"region":"Луганська область","costs_rent":""}],"33":[{"costs_property_comment":"","address":"м. Попасна, вул. Громовой, 17","space_units":"м²","space_unclear":false,"region_hidden":false,"costs_property":"","space_comment":"","address_hidden":false,"address_unclear":false,"costs_rent_comment":"","space":"17","region":"Луганська область","costs_rent":""}]},"vehicle":{"40":[{"sum_comment":"","brand_info_hidden":false,"brand_info":"1799 куб. см.","sum":"","sum_rent_comment":"","year":"2006","brand":"Chevrolet Lacetti","sum_rent":"","brand_info_unclear":false}],"41":[{"sum_comment":"","brand_info":"4143 НГ, 2464 куб. см.","sum":"","sum_rent_comment":"","year":"2007","brand":"ГАЗ 2705 Газель","sum_rent":""}]},"source":"VULYK","income":{"5":{"family_comment":"","family":"50380","comment":"","value_unclear":false,"family_unclear":false,"value":"217890"},"6":{"family_comment":"","value":"217890","family":"50380","comment":"","value_unclear":false},"7":{"family_comment":"","comment":"","family":"","value_unclear":false,"value":"","source_name":""},"8":{"family_comment":"","value":"","family":"","comment":""},"9":{"family_comment":"","family":"","comment":"","value_unclear":false,"family_unclear":false,"value":""},"10":{"family_comment":"","comment_unclear":false,"value":"","family":"","comment":""},"11":{"family_comment":"","value":"","family":"","comment":""},"12":{"family_comment":"","value":"","family":"","comment":""},"13":{"family_comment":"","value":"","family":"","comment":"","value_unclear":false},"14":{"family_comment":"","value":"","family":"","comment":""},"15":{"family_comment":"","value":"","family":"","comment":""},"16":{"family_comment":"","value":"","family_unclear":false,"family":"","comment":""},"17":{"family_comment":"","value":"","family_unclear":false,"family":"","comment":""},"18":{"family_comment":"","value":"","family":"","comment":""},"19":{"family_comment":"","value":"","family":"","comment":""},"20":{"family":"25667","family_comment":"","comment":"","value_hidden":false,"value_unclear":false,"value":"","comment_unclear":false,"family_unclear":false,"family_hidden":false}},"general":{"inn":"2519411327","addresses":[{"place_city_type":"Місто","place_city_type_hidden":false,"place_hidden":false,"place_city_hidden":false,"place_district_hidden":false,"place_district":"","place_city_unclear":false,"place":"Луганська область","place_city":"Попасна","place_address_hidden":false,"place_address":"93300, вул. О. Кошевого, 18"}],"last_name":"Архипенко","full_name":"Архипенко Анжеліка Вікторівна","family":[{"inn":"2505512970","family_name":"Архипенко В. М. 1968","name_unclear":false,"inn_hidden":false,"name_hidden":false,"relations":"Подружжя"},{"inn":"3429203042","family_name":"Архипенко О. В. 1993","relations_other":"","name_unclear":false,"inn_hidden":false,"name_hidden":false,"relations":"Дитина"}],"patronymic":"Вікторівна","inn_hidden":false,"name":"Анжеліка","post":{"post_hidden":false,"office":"Загальний місцевий суд","post":"суддя попаснянського районного суду луганської області","office_unclear":false,"region_unclear":false,"region":"Луганська область","post_unclear":false},"family_raw":"","full_name_suggest":{"input":["Архипенко Анжеліка Вікторівна","Анжеліка Вікторівна Архипенко","Анжеліка Архипенко"],"output":"Архипенко Анжеліка Вікторівна"}},"liabilities":{"54":{"sum_comment":"","sum":"","sum_foreign_comment":"","sum_foreign":"","sum_unclear":false,"sum_comment_hidden":false},"55":{"sum_comment":"","sum_foreign_comment":"","sum_foreign":"","sum":""},"56":{"sum_comment":"","sum_foreign_comment":"","sum_foreign":"","sum_unclear":false,"sum":"4230"},"57":{"sum_comment_unclear":false,"sum_comment":"","sum":"","sum_foreign_comment":"","sum_foreign":"","sum_unclear":false,"sum_comment_hidden":false},"58":{"sum_comment":"","sum":"","sum_foreign_comment":"","sum_foreign":"","sum_unclear":false,"sum_comment_hidden":false},"59":{"sum_comment":"","sum_foreign_comment":"","sum_foreign":"","sum":""},"60":{"sum_comment":"","sum_foreign_comment":"","sum_foreign":"","sum":"","sum_comment_hidden":false},"61":{"sum_comment":"","sum_foreign_comment":"","sum_foreign":"","sum":""},"62":{"sum_comment":"","sum_foreign_comment":"","sum_foreign":"","sum_unclear":false,"sum":""},"63":{"sum_comment":"","sum_foreign_comment":"","sum_foreign":"","sum":"","sum_comment_hidden":false},"64":{"sum_comment":"","sum_foreign_comment":"","sum_foreign":"","sum":"","sum_comment_hidden":false}},"declaration":{"notfull_lostpages":"","additional_info_text":"","additional_info":"","date":"2015-03-30T00:00:00","notfull":"","url":"http://static.declarations.com.ua/declarations/chosen_ones/judges_batch/4276_arkhypenko_anzhelika_viktorivna.pdf"},"intro":{"declaration_year":"2014"}}]