[{"id":"vulyk_87_27","ft_src":"52.1\n2014\n202507\n97040\n330237\n97040\n127730\n202507\n330237\n97040\n127730\n97040\nПодружжя\nБарановський Роман Анатолійович\nРоман Анатолійович Барановський\nРоман Барановський\nБарановський Роман Анатолійович\nРоман\nБарановський Роман Анатолійович\nБарановський\nАдміністративний місцевий суд\nДніпропетровська область\nсуддя дніпропетровського окружного адміністративного суду\nАнатолійович\n52.1\n2014\nПодружжя\nРоман\nАнатолійович\nБарановський\nБарановський Роман Анатолійович\nРоман Анатолійович Барановський\nРоман Барановський\nБарановський Роман Анатолійович\nДніпропетровська область\nАдміністративний місцевий суд\nсуддя дніпропетровського окружного адміністративного суду\nБарановський Роман Анатолійович","estate":{"31":[{"costs_property_comment":"","address":"","space_units":"м²","space_hidden":false,"space_unclear":false,"region_hidden":false,"costs_property":"","space_comment":"","address_hidden":true,"address_unclear":false,"costs_rent_comment":"","space":"52.1","region":"","costs_rent":""}]},"source":"VULYK","income":{"5":{"family_comment":"","value":"330237","family_unclear":false,"family":"97040","comment":""},"6":{"family_comment":"","value":"202507","family":"","comment":""},"7":{"family":"","family_comment":"","value":"","comment":"","source_name":""},"8":{"family_comment":"","value":"","family":"","comment":""},"9":{"family_comment":"","value":"","family":"","comment":""},"10":{"family_comment":"","value":"","family":"","comment":""},"11":{"family_comment":"","value":"","family":"","comment":""},"12":{"family_comment":"","value":"","family":"","comment":""},"13":{"family_comment":"","value":"","family":"","comment":""},"14":{"family_comment":"","value":"","family":"","comment":""},"15":{"family_comment":"","value":"","family":"","comment":""},"16":{"family_comment":"","value":"127730","family":"97040","comment":""},"17":{"family_comment":"","value":"","family":"","comment":""},"18":{"family_comment":"","value":"","family":"","comment":""},"19":{"family_comment":"","value":"","family":"","comment":""},"20":{"family_comment":"","value":"","family":"","comment":""}},"general":{"family_raw":"","name":"Роман","full_name_suggest":{"input":["Барановський Роман Анатолійович","Роман Анатолійович Барановський","Роман Барановський"],"output":"Барановський Роман Анатолійович"},"patronymic":"Анатолійович","inn_hidden":true,"addresses":[{"place_city_type_hidden":false,"place_hidden":false,"place_address_unclear":false,"place":"","place_city":"","place_city_type_unclear":false,"place_city_type":"","place_city_hidden":true,"place_district":"","place_district_hidden":false,"place_address":"","place_address_hidden":true}],"inn":"","inn_unclear":false,"last_name":"Барановський","full_name":"Барановський Роман Анатолійович","family":[{"inn":"","family_name":"","relations_other":"","relations_hidden":false,"name_unclear":false,"inn_hidden":true,"name_hidden":true,"relations":"Подружжя"}],"post":{"office":"Адміністративний місцевий суд","post":"суддя дніпропетровського окружного адміністративного суду","candidate":"","office_unclear":false,"region":"Дніпропетровська область","post_unclear":false}},"liabilities":{"54":{"sum_comment":"","sum_comment_unclear":false,"sum_foreign_comment":"","sum":"","sum_foreign":""},"55":{"sum_comment":"","sum_foreign_comment":"","sum_foreign":"","sum":""},"56":{"sum_comment":"","sum_foreign_comment":"","sum_foreign":"","sum":""},"57":{"sum_comment":"","sum_hidden":false,"sum":"","sum_foreign_comment":"","sum_foreign":"","sum_unclear":false},"58":{"sum_comment":"","sum_foreign_comment":"","sum_foreign":"","sum_unclear":false,"sum":""},"59":{"sum_comment":"","sum_foreign_comment":"","sum_foreign":"","sum":""},"60":{"sum_comment":"","sum_comment_unclear":false,"sum_foreign_comment":"","sum":"","sum_foreign":""},"61":{"sum_comment":"","sum_foreign_comment":"","sum_foreign":"","sum":""},"62":{"sum_comment":"","sum_foreign_comment":"","sum_foreign":"","sum_unclear":false,"sum":""},"63":{"sum_comment":"","sum_foreign_comment":"","sum_foreign":"","sum_unclear":false,"sum":""},"64":{"sum_comment":"","sum_foreign_comment":"","sum_foreign":"","sum":""}},"declaration":{"notfull_lostpages":"","additional_info_text":"","additional_info":"","date":"2015-03-19T00:00:00","notfull":"","url":"http://static.declarations.com.ua/declarations/chosen_ones/judges_batch/2830_baranovskyi_roman_anatoliiovych.pdf"},"intro":{"isnotdeclaration":"","declaration_year":"2014"}}]