[{"id":"vulyk_101_144","ft_src":"1/2 частина квартири\nм. Костянтинівка\nДонецька область\n42.2\nм. Краматорськ\n176.6\nДонецька область\n1/2 частина квартири\nм. Костянтинівка\nДонецька область\n42.2\n2015\n183497\n183497\n176.6\nм. Краматорськ\nДонецька область\n1/2 частина квартири\n42.2\nДонецька область\nм. Костянтинівка\n42.2\n1/2 частина квартири\nм. Костянтинівка\nДонецька область\nДитина\nБєлостоцька А. О\nБєлостоцька Олена Василівна\nОлена Василівна Бєлостоцька\nОлена Бєлостоцька\nБєлостоцька Олена Василівна\nОлена\nБєлостоцька Олена Василівна\nВасилівна\nЗагальний місцевий суд\nсуддя костянтинівського міськрайонного суду донецької області\nДонецька область\nБєлостоцька\n6748\n183497\n183497\n2015\n6748\nБєлостоцька А. О\nДитина\nОлена\nВасилівна\nБєлостоцька\nБєлостоцька Олена Василівна\nОлена Василівна Бєлостоцька\nОлена Бєлостоцька\nБєлостоцька Олена Василівна\nсуддя костянтинівського міськрайонного суду донецької області\nЗагальний місцевий суд\nДонецька область\nБєлостоцька Олена Василівна","estate":{"24":[{"address":"м. Краматорськ","space_units":"м²","costs_comment":"","space_unclear":false,"region_hidden":false,"space_comment":"","address_hidden":true,"costs":"","costs_rent_comment":"","space":"176.6","region":"Донецька область","costs_rent":""}],"25":[{"address":"м. Костянтинівка","space_units":"м²","space_hidden":false,"space_unclear":false,"region_hidden":false,"costs_comment":"","space_comment":"1/2 частина квартири","address_hidden":true,"space":"42.2","space_comment_unclear":false,"costs_rent_comment":"","costs":"","region":"Донецька область","costs_rent":""}],"31":[{"costs_property_comment":"","address":"м. Костянтинівка","space_units":"м²","space_hidden":false,"space_unclear":false,"region_hidden":false,"costs_property":"","space_comment":"1/2 частина квартири","address_hidden":true,"costs_rent_comment_unclear":false,"costs_rent_comment":"","space":"42.2","region":"Донецька область","costs_rent":""}]},"source":"VULYK","income":{"5":{"family_comment":"","value":"183497","family":"","comment":"","value_unclear":false},"6":{"family_comment":"","family":"","comment":"","value_unclear":false,"family_hidden":false,"value":"183497"},"7":{"family_comment":"","comment":"","family":"","source_name_unclear":false,"value":"","source_name":""},"8":{"family_comment":"","value":"","family":"","comment":""},"9":{"family_comment":"","value":"","family":"","comment":""},"10":{"family_comment":"","value":"","family":"","comment":""},"11":{"family_comment":"","comment_unclear":false,"value":"","family":"","comment":""},"12":{"family_comment":"","value":"","family":"","comment":""},"13":{"family_comment":"","value":"","family":"","comment":""},"14":{"family_comment":"","value":"","family":"","comment":""},"15":{"family_comment":"","value":"","family":"","comment":""},"16":{"family_comment":"","value":"","family":"","comment":""},"17":{"family_comment":"","value":"","family":"","comment":""},"18":{"family_comment":"","value":"","family":"","comment":""},"19":{"family_comment":"","value":"","family":"","comment":""},"20":{"family_comment":"","family":"","comment":"","value_unclear":false,"family_unclear":false,"comment_unclear":false,"value":""}},"general":{"family":[{"inn":"","family_name":"Бєлостоцька А. О","relations_other":"","name_unclear":false,"inn_hidden":true,"name_hidden":true,"relations":"Дитина"}],"family_raw":"","name":"Олена","full_name_suggest":{"input":["Бєлостоцька Олена Василівна","Олена Василівна Бєлостоцька","Олена Бєлостоцька"],"output":"Бєлостоцька Олена Василівна"},"patronymic":"Василівна","inn_hidden":true,"addresses":[{"place_city_type_hidden":false,"place_city_type":"","place_city_hidden":true,"place_hidden":true,"place_district":"","place_district_hidden":false,"place":"","place_address":"","place_address_hidden":true,"place_city":""}],"patronymic_hidden":false,"inn":"","inn_unclear":false,"last_name":"Бєлостоцька","full_name":"Бєлостоцька Олена Василівна","post":{"office":"Загальний місцевий суд","region_unclear":false,"post":"суддя костянтинівського міськрайонного суду донецької області","region":"Донецька область","office_unclear":false}},"liabilities":{"54":{"sum_comment_unclear":false,"sum_comment":"","sum_hidden":false,"sum":"","sum_foreign_comment":"","sum_foreign":"","sum_unclear":false,"sum_comment_hidden":false},"55":{"sum_comment":"","sum_foreign_comment":"","sum_foreign":"","sum":""},"56":{"sum_comment":"","sum":"6748","sum_foreign_comment":"","sum_foreign":"","sum_unclear":false,"sum_comment_hidden":false},"57":{"sum_comment":"","sum_hidden":false,"sum":"","sum_foreign_comment":"","sum_foreign":"","sum_unclear":false,"sum_comment_hidden":false},"58":{"sum_comment_unclear":false,"sum_comment":"","sum_hidden":false,"sum":"","sum_foreign_comment":"","sum_foreign":"","sum_unclear":false,"sum_comment_hidden":false},"59":{"sum_comment":"","sum_foreign_comment":"","sum_foreign":"","sum":""},"60":{"sum_comment":"","sum_hidden":false,"sum":"","sum_foreign_comment":"","sum_foreign":"","sum_unclear":false,"sum_comment_hidden":false},"61":{"sum_comment":"","sum_foreign_comment":"","sum_foreign":"","sum":""},"62":{"sum_comment":"","sum_comment_unclear":false,"sum_foreign_comment":"","sum":"","sum_foreign":""},"63":{"sum_comment":"","sum_foreign_comment":"","sum_foreign":"","sum":"","sum_comment_hidden":false},"64":{"sum_comment":"","sum_foreign_comment":"","sum_foreign":"","sum":"","sum_comment_hidden":false}},"declaration":{"notfull_lostpages":"","additional_info_text":"","additional_info":"","date":"2016-03-21T00:00:00","notfull":"","url":"http://static.declarations.com.ua/declarations/chosen_ones/judges_batch/859_bielostotska_olena_vasylivna_2015.pdf"},"intro":{"declaration_year":"2015"}},{"id":"vulyk_98_42","ft_src":"1/2 частина квартири\nДонецька область\nм. Костянтинівка\n42.2\nм. Краматорськ\n170\nДонецька область\n1/2 частина квартири\nм. Костянтинівка\n42.2\nДонецька область\n2014\n184925\n11\n184936\n184925\n184936\n11\nЗагальний місцевий суд\nсуддя костянтинівського міськрайонного суду донецької області\nДонецька область\nБєлостоцька Олена Василівна\nОлена Василівна Бєлостоцька\nОлена Бєлостоцька\nБєлостоцька Олена Василівна\nБєлостоцька Олена Василівна\nДитина\nБєлостоцька А. О\nОлена\nБєлостоцька\nВасилівна\n3950\n170\nм. Краматорськ\nДонецька область\n1/2 частина квартири\nм. Костянтинівка\n42.2\nДонецька область\n42.2\n1/2 частина квартири\nДонецька область\nм. Костянтинівка\n2014\n3950\nДитина\nБєлостоцька А. О\nВасилівна\nБєлостоцька\nОлена\nБєлостоцька Олена Василівна\nОлена Василівна Бєлостоцька\nОлена Бєлостоцька\nБєлостоцька Олена Василівна\nсуддя костянтинівського міськрайонного суду донецької області\nДонецька область\nЗагальний місцевий суд\nБєлостоцька Олена Василівна","estate":{"24":[{"costs":"","address":"м. Краматорськ","space_units":"м²","costs_rent_comment":"","space":"170","space_comment":"","region_hidden":false,"costs_comment":"","region":"Донецька область","address_hidden":true,"costs_rent":""}],"25":[{"address":"м. Костянтинівка","space_units":"м²","costs_comment":"","space_unclear":true,"region_hidden":false,"space_comment":"1/2 частина квартири","address_hidden":true,"costs":"","address_unclear":true,"costs_rent_comment":"","space":"42.2","region":"Донецька область","costs_rent":""}],"31":[{"costs_property_comment":"","address":"м. Костянтинівка","space_units":"м²","space_comment":"1/2 частина квартири","region_hidden":false,"costs_property":"","region":"Донецька область","address_hidden":true,"costs_rent_comment":"","space":"42.2","region_unclear":true,"costs_rent":""}]},"source":"VULYK","income":{"5":{"family_comment":"","family":"","comment":"","value_unclear":false,"family_unclear":false,"value":"184936"},"6":{"family_comment":"","value":"184925","family":"","comment":"","value_unclear":false},"7":{"family":"","family_comment":"","value":"","comment":"","source_name":""},"8":{"family_comment":"","value":"","family":"","comment":""},"9":{"family_comment":"","value":"11","family":"","comment":"","value_unclear":false},"10":{"family_comment":"","value":"","family":"","comment":""},"11":{"family_comment":"","value":"","family":"","comment":""},"12":{"family_comment":"","value":"","family":"","comment":""},"13":{"family_comment":"","value":"","family":"","comment":""},"14":{"family_comment":"","value":"","family":"","comment":""},"15":{"family_comment":"","value":"","family":"","comment":""},"16":{"family_comment":"","value":"","family":"","comment":""},"17":{"family_comment":"","value":"","family":"","comment":""},"18":{"family_comment":"","value":"","family":"","comment":""},"19":{"family_comment":"","value":"","family":"","comment":""},"20":{"family_comment":"","value":"","family":"","comment":"","value_unclear":false}},"general":{"family":[{"inn":"","family_name":"Бєлостоцька А. О","relations_other":"","name_unclear":false,"inn_hidden":true,"name_hidden":true,"relations":"Дитина"}],"family_raw":"","name":"Олена","full_name_suggest":{"input":["Бєлостоцька Олена Василівна","Олена Василівна Бєлостоцька","Олена Бєлостоцька"],"output":"Бєлостоцька Олена Василівна"},"patronymic":"Василівна","inn_hidden":true,"addresses":[{"place_city_type_hidden":false,"place_city_type":"","place_city_hidden":true,"place_hidden":true,"place_district":"","place_district_hidden":false,"place":"","place_address":"","place_address_hidden":true,"place_city":""}],"last_name_hidden":false,"patronymic_hidden":false,"inn":"","inn_unclear":false,"last_name":"Бєлостоцька","full_name":"Бєлостоцька Олена Василівна","post":{"office":"Загальний місцевий суд","region":"Донецька область","post_unclear":false,"post":"суддя костянтинівського міськрайонного суду донецької області"},"last_name_unclear":false},"liabilities":{"54":{"sum_comment_unclear":false,"sum_comment":"","sum_hidden":false,"sum":"","sum_foreign_comment":"","sum_foreign":"","sum_unclear":false,"sum_comment_hidden":false},"55":{"sum_comment":"","sum_foreign_comment":"","sum_foreign":"","sum":""},"56":{"sum_comment":"","sum_foreign_comment":"","sum_foreign":"","sum_unclear":false,"sum":"3950"},"57":{"sum_comment_unclear":false,"sum_comment":"","sum_hidden":false,"sum":"","sum_foreign_comment":"","sum_foreign":"","sum_unclear":false,"sum_comment_hidden":false},"58":{"sum_comment":"","sum_hidden":false,"sum":"","sum_foreign_comment":"","sum_foreign":"","sum_unclear":false,"sum_comment_hidden":false},"59":{"sum_comment":"","sum_comment_unclear":false,"sum_foreign_comment":"","sum":"","sum_foreign":""},"60":{"sum_comment":"","sum_hidden":false,"sum":"","sum_foreign_comment":"","sum_foreign":"","sum_comment_hidden":false},"61":{"sum_comment":"","sum_foreign_comment":"","sum_foreign":"","sum":""},"62":{"sum_comment":"","sum":"","sum_foreign_comment":"","sum_foreign":"","sum_unclear":false,"sum_comment_hidden":false},"63":{"sum_comment_unclear":false,"sum_comment":"","sum":"","sum_foreign_comment":"","sum_foreign":"","sum_comment_hidden":false},"64":{"sum_comment":"","sum_foreign_comment":"","sum_foreign":"","sum":"","sum_comment_hidden":false}},"declaration":{"date":"2015-03-27T00:00:00","url":"http://static.declarations.com.ua/declarations/chosen_ones/judges_batch/4539_bielostotska_olena_vasylivna.pdf"},"intro":{"declaration_year":"2014"}}]