[{"id":"vulyk_96_78","ft_src":"1.3 л\nDaewoo Sens\n2006\n2009\n2.0 л\nKia Sportage\n1200\n800\n2015\n195170\n172718\n207182\n172718\n12012.48\n1.3 л\nDaewoo Sens\n2006\nKia Sportage\n2.0 л\n2009\n2015\nБондарчук Володимир Володимирович\nВолодимир Володимирович Бондарчук\nВолодимир Бондарчук\nБондарчук Володимир Володимирович\nБондарчук Володимир Володимирович\nВолодимир\nБондарчук\nХмельницька область\nсуддя хмельницького міськрайонного суду хмельницької області\nЗагальний місцевий суд\nВолодимирович\nПодружжя\nБондарчук Л. А. 07. 06. 1980\nДитина\nБондарчук В. В. 31. 12. 2012\nДитина\nБондарчук О. В. 31. 12. 2012\n45167.22\n3190.75\n195170\n172718\n12012.48\n172718\n207182\n1200\n800\n45167.22\n3190.75\nБондарчук Л. А. 07. 06. 1980\nПодружжя\nДитина\nБондарчук В. В. 31. 12. 2012\nДитина\nБондарчук О. В. 31. 12. 2012\nВолодимир\nВолодимирович\nБондарчук\nБондарчук Володимир Володимирович\nВолодимир Володимирович Бондарчук\nВолодимир Бондарчук\nБондарчук Володимир Володимирович\nсуддя хмельницького міськрайонного суду хмельницької області\nХмельницька область\nЗагальний місцевий суд\nБондарчук Володимир Володимирович","estate":{"23":[{"address":"","space_units":"м²","costs_rent_unclear":false,"space_hidden":false,"space_unclear":false,"region_hidden":true,"space_units_unclear":false,"costs_comment":"","space_comment_unclear":false,"space":"1200","address_unclear":false,"space_comment":"","address_hidden":false,"costs_rent_comment":"","costs":"","region_unclear":false,"region":"","costs_rent":""}],"29":[{"costs_property_comment":"","address":"","space_units":"м²","space_unclear":false,"region_hidden":true,"costs_property":"","space_comment":"","address_hidden":false,"address_unclear":false,"costs_rent_comment":"","space":"800","region_unclear":false,"region":"","costs_rent":""}]},"vehicle":{"35":[{"year_hidden":false,"brand_info":"1.3 л","sum_rent_comment":"","brand_unclear":false,"brand_hidden":false,"year":"2006","brand":"Daewoo Sens","brand_info_hidden":false,"sum_rent":"","sum_comment":"","year_unclear":false,"sum_unclear":false,"sum":""}],"40":[{"sum_comment":"","brand_info_hidden":false,"brand_info":"2.0 л","sum":"","sum_rent_comment":"","year":"2009","brand":"Kia Sportage","sum_rent":"","year_unclear":false}]},"source":"VULYK","income":{"5":{"family_comment":"","value":"172718","family_unclear":false,"family":"207182","comment":""},"6":{"family_comment":"","family":"195170","comment":"","value_unclear":false,"family_unclear":false,"value":"172718"},"7":{"source_name_hidden":false,"family_comment":"","family":"","comment":"","value_unclear":false,"family_unclear":false,"value":"","source_name":""},"8":{"family_comment":"","value":"","family":"","comment":""},"9":{"family_comment":"","value":"","family":"","comment":""},"10":{"family_comment":"","value":"","family":"","comment":"","value_unclear":false},"11":{"family_comment":"","value":"","family":"","comment":""},"12":{"family_comment":"","value":"","family":"","comment":""},"13":{"family_comment":"","value":"","family":"","comment":""},"14":{"family_comment":"","value":"","family":"","comment":""},"15":{"family_comment":"","value":"","family":"","comment":""},"16":{"family_comment":"","value":"","family":"","comment":""},"17":{"family_comment":"","value":"","family":"","comment":""},"18":{"family_comment":"","value":"","family":"","comment":""},"19":{"family_comment":"","value":"","family":"","comment":""},"20":{"family_comment":"","comment":"","family":"12012.48","value_unclear":false,"comment_hidden":false,"comment_unclear":false,"value":""}},"general":{"family":[{"inn":"","inn_unclear":false,"family_name":"Бондарчук Л. А. 07. 06. 1980","relations_other":"","relations_hidden":false,"name_unclear":false,"inn_hidden":true,"name_hidden":false,"relations":"Подружжя"},{"inn":"","family_name":"Бондарчук В. В. 31. 12. 2012","relations_other":"","name_unclear":false,"inn_hidden":false,"name_hidden":false,"relations":"Дитина"},{"inn":"","family_name":"Бондарчук О. В. 31. 12. 2012","relations_other":"","name_unclear":false,"inn_hidden":false,"relations":"Дитина"}],"family_raw":"","name":"Володимир","full_name_suggest":{"input":["Бондарчук Володимир Володимирович","Володимир Володимирович Бондарчук","Володимир Бондарчук"],"output":"Бондарчук Володимир Володимирович"},"patronymic":"Володимирович","inn_hidden":true,"patronymic_hidden":false,"inn":"","addresses":[{"place_city_type_hidden":false,"place_city_type":"","place_city_hidden":true,"place_hidden":true,"place_district":"","place_district_hidden":false,"place":"","place_address":"","place_address_hidden":false,"place_city":""}],"last_name":"Бондарчук","full_name":"Бондарчук Володимир Володимирович","post":{"office_unclear":false,"post":"суддя хмельницького міськрайонного суду хмельницької області","region":"Хмельницька область","office":"Загальний місцевий суд"}},"liabilities":{"54":{"sum_comment":"","sum_hidden":false,"sum":"","sum_foreign_comment":"","sum_foreign":"","sum_comment_hidden":false},"55":{"sum_comment":"","sum_foreign_comment":"","sum_foreign":"","sum":""},"56":{"sum_comment":"","sum_foreign_comment":"","sum_foreign":"","sum_unclear":false,"sum":""},"57":{"sum_comment":"","sum_foreign_comment":"","sum_foreign":"","sum":"","sum_comment_hidden":false},"58":{"sum_comment":"","sum":"","sum_foreign_comment":"","sum_foreign":"","sum_unclear":false,"sum_comment_hidden":false},"59":{"sum_comment":"","sum_foreign_comment":"","sum_foreign":"","sum":""},"60":{"sum_comment":"","sum_foreign_comment":"","sum_foreign":"","sum":"","sum_comment_hidden":false},"61":{"sum_comment":"","sum_foreign_comment":"","sum_foreign":"","sum":""},"62":{"sum_comment":"","sum_foreign_comment":"","sum_foreign":"","sum":""},"63":{"sum_comment":"","sum_foreign_comment":"","sum_foreign":"","sum":"45167.22","sum_comment_hidden":false},"64":{"sum_comment":"","sum_foreign_comment":"","sum_foreign":"","sum":"3190.75","sum_comment_hidden":false}},"declaration":{"notfull_lostpages":"","additional_info_text":"","additional_info":"","date":"2016-03-12T00:00:00","notfull":"","url":"http://static.declarations.com.ua/declarations/chosen_ones/judges_batch/292_bondarchuk_volodymyr_volodymyrovych_2015.pdf"},"intro":{"isnotdeclaration":"","declaration_year":"2015"}},{"id":"vulyk_100_79","ft_src":"1.3\nDaewoo Sens\n2006\n2009\n2\nKia Sportage\n1200\n800\n2014\n210808.97\n231824.27\n232431.41\n231824.27\n21622.44\n1.3\nDaewoo Sens\n2006\nKia Sportage\n2\n2009\n1200\n800\nПодружжя\nБондарчук Л. А\nДитина\nБондарчук В. В\nДитина\nБондарчук О. В\nВолодимирович\nБондарчук\nБондарчук Володимир Володимирович\nВолодимир Володимирович Бондарчук\nВолодимир Бондарчук\nБондарчук Володимир Володимирович\nБондарчук Володимир Володимирович\nВолодимир\nЗагальний місцевий суд\nХмельницька область\nсуддя хмельницького міськрайонного суду хмельницької області\n231824.27\n210808.97\n21622.44\n231824.27\n232431.41\n2014\nБондарчук Л. А\nПодружжя\nДитина\nБондарчук В. В\nДитина\nБондарчук О. В\nВолодимирович\nБондарчук\nХмельницька область\nЗагальний місцевий суд\nсуддя хмельницького міськрайонного суду хмельницької області\nБондарчук Володимир Володимирович\nБондарчук Володимир Володимирович\nВолодимир Володимирович Бондарчук\nВолодимир Бондарчук\nБондарчук Володимир Володимирович\nВолодимир","estate":{"23":[{"address":"","space_units":"м²","costs_comment":"","space_unclear":false,"region_hidden":true,"space_comment":"","address_hidden":false,"costs":"","address_unclear":false,"space_comment_unclear":false,"costs_comment_unclear":false,"costs_rent_comment":"","space":"1200","region":"","costs_rent":""}],"29":[{"costs_property_comment":"","address":"","space_units":"м²","space_unclear":false,"region_hidden":true,"costs_property":"","space_comment":"","address_hidden":true,"address_unclear":false,"costs_rent_comment":"","space":"800","region_unclear":false,"region":"","costs_rent":""}]},"vehicle":{"35":[{"brand_info":"1.3","sum_rent_comment":"","brand_unclear":false,"sum_rent_comment_unclear":false,"brand_hidden":false,"sum_comment":"","brand_info_hidden":false,"sum_rent":"","brand":"Daewoo Sens","brand_info_unclear":false,"year":"2006","sum":""}],"40":[{"sum_comment":"","brand_info_hidden":false,"brand_info":"2","sum":"","sum_rent_comment":"","year":"2009","brand":"Kia Sportage","sum_rent":"","brand_info_unclear":false}]},"source":"VULYK","income":{"5":{"family_comment":"","family":"232431.41","comment":"","value_unclear":false,"family_unclear":false,"value":"231824.27"},"6":{"family_comment":"","value":"231824.27","family":"210808.97","comment":"","value_unclear":false},"7":{"family_comment":"","comment":"","family":"","value_unclear":false,"value":"","source_name":""},"8":{"family_comment":"","value":"","family":"","comment":""},"9":{"family_comment":"","family":"","comment":"","value_unclear":false,"family_unclear":false,"value":""},"10":{"family_comment":"","comment_unclear":false,"value":"","family":"","comment":""},"11":{"family_comment":"","value":"","family":"","comment":""},"12":{"family_comment":"","value":"","family":"","comment":""},"13":{"family_comment":"","value":"","family":"","comment":"","value_unclear":false},"14":{"family_comment":"","value":"","family":"","comment":""},"15":{"family_comment":"","value":"","family":"","comment":""},"16":{"family_comment":"","value":"","family_unclear":false,"family":"","comment":""},"17":{"family_comment":"","value":"","family_unclear":false,"family":"","comment":""},"18":{"family_comment":"","value":"","family":"","comment":""},"19":{"family_comment":"","value":"","family":"","comment":""},"20":{"family":"21622.44","family_comment":"","comment":"","value_hidden":false,"value_unclear":false,"value":"","comment_unclear":false,"family_unclear":false,"family_hidden":false}},"general":{"inn":"","addresses":[{"place_city_type":"","place_city_type_hidden":false,"place_hidden":true,"place_city_hidden":true,"place_district_hidden":false,"place_district":"","place_city_unclear":false,"place":"","place_city":"","place_address_hidden":true,"place_address":""}],"last_name":"Бондарчук","full_name":"Бондарчук Володимир Володимирович","family":[{"inn":"","family_name":"Бондарчук Л. А","name_unclear":false,"inn_hidden":true,"name_hidden":true,"relations":"Подружжя"},{"inn":"","family_name":"Бондарчук В. В","relations_other":"","name_unclear":false,"inn_hidden":false,"name_hidden":false,"relations":"Дитина"},{"inn":"","family_name":"Бондарчук О. В","relations_other":"","name_unclear":false,"inn_hidden":false,"name_hidden":false,"relations":"Дитина"}],"patronymic":"Володимирович","inn_hidden":true,"name":"Володимир","post":{"post_hidden":false,"office":"Загальний місцевий суд","post":"суддя хмельницького міськрайонного суду хмельницької області","office_unclear":false,"region_unclear":false,"region":"Хмельницька область","post_unclear":false},"family_raw":"","full_name_suggest":{"input":["Бондарчук Володимир Володимирович","Володимир Володимирович Бондарчук","Володимир Бондарчук"],"output":"Бондарчук Володимир Володимирович"}},"liabilities":{"54":{"sum_comment":"","sum":"","sum_foreign_comment":"","sum_foreign":"","sum_unclear":false,"sum_comment_hidden":false},"55":{"sum_comment":"","sum_foreign_comment":"","sum_foreign":"","sum":""},"56":{"sum_comment":"","sum_foreign_comment":"","sum_foreign":"","sum_unclear":false,"sum":""},"57":{"sum_comment_unclear":false,"sum_comment":"","sum":"","sum_foreign_comment":"","sum_foreign":"","sum_unclear":false,"sum_comment_hidden":false},"58":{"sum_comment":"","sum":"","sum_foreign_comment":"","sum_foreign":"","sum_unclear":false,"sum_comment_hidden":false},"59":{"sum_comment":"","sum_foreign_comment":"","sum_foreign":"","sum":""},"60":{"sum_comment":"","sum_foreign_comment":"","sum_foreign":"","sum":"","sum_comment_hidden":false},"61":{"sum_comment":"","sum_foreign_comment":"","sum_foreign":"","sum":""},"62":{"sum_comment":"","sum_foreign_comment":"","sum_foreign":"","sum_unclear":false,"sum":""},"63":{"sum_comment":"","sum_foreign_comment":"","sum_foreign":"","sum":"","sum_comment_hidden":false},"64":{"sum_comment":"","sum_foreign_comment":"","sum_foreign":"","sum":"","sum_comment_hidden":false}},"declaration":{"notfull_lostpages":"","additional_info_text":"","additional_info":"","date":"2015-03-12T00:00:00","notfull":"","url":"http://static.declarations.com.ua/declarations/chosen_ones/judges_batch/4279_bondarchuk_volodymyr_volodymyrovych.pdf"},"intro":{"declaration_year":"2014"}}]