[{"id":"vulyk_68_33","ft_src":"Mitsubishi Lancer\n2008\n11.7\n2014\n177161\n209833\n13398\n177161\n223231\n2008\nMitsubishi Lancer\n11.7\nБруновська (савицька) Надія Володимирівна\nНадія Володимирівна Бруновська (савицька)\nНадія Бруновська (савицька)\nБруновська (савицька) Надія Володимирівна\nБруновська (савицька) Надія Володимирівна\nПодружжя\nБруновський М. В\nНадія\nВолодимирівна\nАпеляційний адміністративний суд\nЛьвівська область\nсуддя львівського апеляційного адміністративного суду\nБруновська (савицька)\n209833\n177161\n223231\n177161\n13398\n2014\nПодружжя\nБруновський М. В\nВолодимирівна\nБруновська (савицька)\nНадія\nБруновська (савицька) Надія Володимирівна\nНадія Володимирівна Бруновська (савицька)\nНадія Бруновська (савицька)\nБруновська (савицька) Надія Володимирівна\nЛьвівська область\nАпеляційний адміністративний суд\nсуддя львівського апеляційного адміністративного суду\nБруновська (савицька) Надія Володимирівна","estate":{"25":[{"costs_unclear":false,"costs_comment":"","space_units":"м²","space_hidden":false,"space_unclear":false,"region_hidden":false,"space_comment":"","space_comment_unclear":false,"costs":"","address_unclear":false,"address_hidden":false,"costs_rent_comment":"","space":"11.7","address":"","region":"","space_units_hidden":false,"costs_rent":""}]},"vehicle":{"40":[{"sum_comment":"","brand_info_hidden":false,"brand_info":"","sum":"","sum_rent_comment":"","brand_hidden":false,"brand":"Mitsubishi Lancer","sum_rent":"","brand_info_unclear":false,"year":"2008","year_unclear":false}]},"source":"VULYK","income":{"5":{"family_comment":"","value":"223231","family_unclear":false,"family":"177161","comment":""},"6":{"family_comment":"","value":"209833","family_unclear":false,"family":"177161","comment":""},"7":{"family_comment":"","comment":"","family":"","comment_hidden":false,"value":"","source_name":""},"8":{"family_comment":"","value":"","family":"","comment":""},"9":{"family_comment":"","value":"","family":"","comment":""},"10":{"family_comment":"","value":"13398","family":"","comment":""},"11":{"family_comment":"","value":"","family":"","comment":"","value_unclear":false},"12":{"family_comment":"","value":"","family":"","comment":""},"13":{"family_comment":"","value":"","family":"","comment":""},"14":{"family_comment":"","value":"","family":"","comment":""},"15":{"family_comment":"","value":"","family":"","comment":"","value_unclear":false},"16":{"family_comment":"","value":"","family_unclear":false,"family":"","comment":""},"17":{"family_comment":"","value":"","family":"","comment":""},"18":{"family_comment":"","family_hidden":false,"value":"","family":"","comment":""},"19":{"family_comment":"","value":"","family":"","comment":""},"20":{"family_comment":"","comment":"","family":"","comment_hidden":false,"comment_unclear":false,"value":"","family_comment_hidden":false}},"general":{"family_raw":"","name":"Надія","full_name_suggest":{"input":["Бруновська (савицька) Надія Володимирівна","Надія Володимирівна Бруновська (савицька)","Надія Бруновська (савицька)"],"output":"Бруновська (савицька) Надія Володимирівна"},"name_unclear":false,"patronymic":"Володимирівна","inn_hidden":false,"inn":"","inn_unclear":false,"last_name":"Бруновська (савицька)","full_name":"Бруновська (савицька) Надія Володимирівна","family":[{"inn":"","inn_unclear":false,"family_name":"Бруновський М. В","relations_hidden":false,"relations_unclear":false,"name_unclear":false,"relations":"Подружжя","inn_hidden":false,"name_hidden":false,"relations_other":""}],"post":{"post_hidden":false,"office":"Апеляційний адміністративний суд","post":"суддя львівського апеляційного адміністративного суду","region":"Львівська область","region_hidden":false,"office_unclear":false,"office_hidden":false,"post_unclear":false,"region_unclear":false},"last_name_unclear":false},"liabilities":{"54":{"sum_comment_unclear":false,"sum_comment":"","sum_hidden":false,"sum":"","sum_foreign_comment":"","sum_foreign":"","sum_unclear":false,"sum_comment_hidden":false},"55":{"sum_comment":"","sum_foreign_comment":"","sum_foreign":"","sum_hidden":false,"sum":""},"56":{"sum_comment":"","sum":"","sum_foreign_comment":"","sum_foreign":"","sum_unclear":false,"sum_foreign_hidden":false},"57":{"sum_comment_unclear":false,"sum_comment":"","sum_hidden":false,"sum":"","sum_foreign_comment":"","sum_foreign":"","sum_unclear":false,"sum_comment_hidden":false},"58":{"sum_comment":"","sum_hidden":false,"sum":"","sum_foreign_comment":"","sum_foreign":"","sum_unclear":false,"sum_comment_hidden":false},"59":{"sum_comment":"","sum_foreign_comment":"","sum_foreign":"","sum":""},"60":{"sum_comment_unclear":false,"sum_comment":"","sum_hidden":false,"sum":"","sum_foreign_comment":"","sum_foreign":"","sum_unclear":false,"sum_comment_hidden":false},"61":{"sum_comment":"","sum_foreign_comment":"","sum_foreign":"","sum_hidden":false,"sum":""},"62":{"sum_comment":"","sum_foreign_comment":"","sum_foreign":"","sum_unclear":false,"sum":""},"63":{"sum_comment":"","sum_hidden":false,"sum":"","sum_foreign_comment":"","sum_foreign":"","sum_unclear":false,"sum_comment_hidden":false},"64":{"sum_comment":"","sum_hidden":false,"sum":"","sum_foreign_comment":"","sum_foreign":"","sum_comment_hidden":false}},"declaration":{"notfull_lostpages":"","additional_info_text":"","additional_info":"","date":"2015-03-30T00:00:00","notfull":"","url":"http://static.declarations.com.ua/declarations/chosen_ones/mega_batch/brunovska_(savytska)_nadiia_volodymyrivna.pdf"},"intro":{"isnotdeclaration":"","declaration_year":"2014"}}]