[{"id":"vulyk_72_230","ft_src":"74.3\n297200\nм. Чернігів\nЧернігівська область\n1\nОтримано кредит в ПАТ 'Державний ощадний банк України' на суму 150000,00 гривень\n2014\nзаробітна плата 235688 та мат.допомога 12180\n247868\n19\n903\n537816\n266978\nдвома сумами: 100 та 21948 пенсія по втраті годувальника\n22048\nОтримано кредит в ПАТ 'Державний ощадний банк України' на суму 150000,00 гривень\n1\n247868\nзаробітна плата 235688 та мат.допомога 12180\n22048\nдвома сумами: 100 та 21948 пенсія по втраті годувальника\n537816\n266978\n19\n903\nДитина\nБіла Юлія Вікторівна\nЧенцова Світлана Миколаївна\nСвітлана Миколаївна Ченцова\nСвітлана Ченцова\nЧенцова Світлана Миколаївна\nСвітлана\nЧенцова Світлана Миколаївна\nЧенцова\nЧернігівська область\nЗагальний місцевий суд\nсуддя новозаводського районного суду міста чернігова\nМиколаївна\n10019\n234\n81503\nм. Чернігів\n297200\n74.3\nЧернігівська область\n2014\n10019\n81503\n234\nБіла Юлія Вікторівна\nДитина\nМиколаївна\nЧенцова\nЧенцова Світлана Миколаївна\nСвітлана Миколаївна Ченцова\nСвітлана Ченцова\nЧенцова Світлана Миколаївна\nЧернігівська область\nЗагальний місцевий суд\nсуддя новозаводського районного суду міста чернігова\nЧенцова Світлана Миколаївна\nСвітлана","estate":{"25":[{"space_hidden":false,"space_comment":"","costs_comment":"","address_hidden":true,"space_comment_hidden":false,"address_unclear":false,"costs_rent_comment_unclear":false,"costs":"297200","costs_rent":"","address":"м. Чернігів","space_units":"м²","costs_hidden":false,"costs_rent_unclear":false,"costs_rent_hidden":false,"space_unclear":false,"costs_comment_hidden":false,"costs_rent_comment_hidden":false,"space_comment_unclear":false,"costs_comment_unclear":false,"costs_rent_comment":"","space":"74.3","region_hidden":false,"region":"Чернігівська область"}]},"source":"VULYK","income":{"5":{"family":"","family_comment":"","comment":"","value_hidden":false,"value_unclear":false,"comment_hidden":false,"family_hidden":false,"family_unclear":false,"family_comment_hidden":false,"value":"537816"},"6":{"family_comment":"","family":"","comment":"заробітна плата 235688 та мат.допомога 12180","value_unclear":false,"family_unclear":false,"family_hidden":false,"value":"247868"},"7":{"source_name_hidden":false,"family_comment":"","comment":"","family":"","source_name_unclear":false,"value":"","family_hidden":false,"source_name":""},"8":{"family_comment":"","value":"","family":"","comment":""},"9":{"family_comment":"","family":"","comment":"","value_unclear":false,"family_hidden":false,"value":"19"},"10":{"family_comment":"","family":"","value_hidden":false,"comment":"","comment_unclear":false,"value_unclear":false,"value":"903","family_hidden":false},"11":{"family_comment":"","value":"","family":"","comment":""},"12":{"family_comment":"","value":"","family":"","comment":""},"13":{"family_comment":"","value":"","family":"","comment":""},"14":{"family_comment":"","value":"","family":"","comment":""},"15":{"family_comment":"","family_hidden":false,"value":"","family":"","comment":""},"16":{"family_comment":"","family":"","comment":"","value_unclear":false,"family_hidden":false,"value":"266978"},"17":{"family_comment":"","family_hidden":false,"value":"","family":"","comment":""},"18":{"family_comment":"","value":"","family":"","comment":"","value_unclear":false},"19":{"family_comment":"","value":"","family":"","comment":""},"20":{"family_comment":"","comment":"двома сумами: 100 та 21948 пенсія по втраті годувальника","family":"","value_unclear":false,"family_unclear":false,"comment_unclear":false,"value":"22048","family_hidden":false}},"general":{"family":[{"inn":"","inn_unclear":false,"family_name":"Біла Юлія Вікторівна","relations_other":"","relations_hidden":false,"relations_unclear":false,"name_unclear":false,"inn_hidden":true,"name_hidden":true,"relations":"Дитина"}],"family_raw":"","name":"Світлана","full_name_suggest":{"input":["Ченцова Світлана Миколаївна","Світлана Миколаївна Ченцова","Світлана Ченцова"],"output":"Ченцова Світлана Миколаївна"},"name_unclear":false,"patronymic":"Миколаївна","inn_hidden":true,"patronymic_unclear":false,"patronymic_hidden":false,"inn":"","inn_unclear":false,"last_name":"Ченцова","full_name":"Ченцова Світлана Миколаївна","post":{"post_hidden":false,"office":"Загальний місцевий суд","post":"суддя новозаводського районного суду міста чернігова","region_unclear":false,"candidate":"","region_hidden":false,"region":"Чернігівська область","office_hidden":false,"post_unclear":false,"office_unclear":false},"addresses":[{"place_city_type_hidden":false,"place_district_hidden":true,"place_address_unclear":false,"place":"","place_city":"","place_unclear":false,"place_city_type":"","place_city_hidden":true,"place_city_unclear":false,"place_district":"","place_district_unclear":false,"place_address":"","place_address_hidden":true,"place_hidden":true}],"last_name_unclear":false},"liabilities":{"54":{"sum_comment":"","sum":"234","sum_foreign_comment":"","sum_foreign":"","sum_unclear":false,"sum_comment_hidden":false},"55":{"sum_comment":"","sum_foreign_comment":"","sum_foreign":"","sum":""},"56":{"sum_comment":"","sum_foreign_comment":"","sum_foreign":"","sum_hidden":false,"sum":""},"57":{"sum_comment_unclear":false,"sum_comment":"","sum_hidden":false,"sum":"81503","sum_foreign_comment":"","sum_foreign":"","sum_unclear":false,"sum_comment_hidden":false},"58":{"sum_comment_unclear":false,"sum_comment":"","sum_hidden":false,"sum":"10019","sum_foreign_comment":"","sum_foreign":"","sum_unclear":false,"sum_comment_hidden":false},"59":{"sum_comment":"","sum":"","sum_foreign_comment":"","sum_foreign_unclear":false,"sum_foreign":"","sum_foreign_hidden":false,"sum_comment_hidden":false},"60":{"sum_comment":"","sum_hidden":false,"sum":"","sum_foreign_comment":"","sum_foreign":"","sum_foreign_hidden":false},"61":{"sum_comment":"","sum_hidden":false,"sum":"","sum_foreign_comment":"","sum_foreign":"","sum_foreign_hidden":false},"62":{"sum_comment":"","sum_hidden":false,"sum":"","sum_foreign_comment":"","sum_foreign":"","sum_foreign_hidden":false},"63":{"sum_comment_unclear":false,"sum_comment":"","sum_hidden":false,"sum":"","sum_foreign_comment":"","sum_foreign":"","sum_unclear":false,"sum_foreign_hidden":false,"sum_comment_hidden":false},"64":{"sum_comment":"","sum_hidden":false,"sum":"","sum_foreign_comment":"","sum_foreign":"","sum_foreign_hidden":false}},"declaration":{"notfull_lostpages":"","additional_info_text":"Отримано кредит в ПАТ 'Державний ощадний банк України' на суму 150000,00 гривень","additional_info":"1","date":"2015-03-31T00:00:00","notfull":"","url":"http://static.declarations.com.ua/declarations/chosen_ones/epic_batch/chentsova_svitlana_mykolaivna.pdf"},"intro":{"isnotdeclaration":"","declaration_year_unclear":false,"declaration_year":"2014"}}]