[{"id":"vulyk_106_130","declaration":{"notfull_lostpages":"","additional_info_text":"","additional_info":"","date":"2016-03-31T00:00:00","notfull":"","url":"http://static.declarations.com.ua/declarations/chosen_ones/judges_batch/2269_cherednychenko_vladyslav_ievheniiovych.pdf"},"estate":{"25":[{"address":"","space_units":"м²","costs_comment":"","region_hidden":true,"space_comment":"","address_hidden":true,"costs":"","space_comment_unclear":false,"costs_rent_comment":"","space":"44.7","region":"","costs_rent":""}],"31":[{"costs_property_comment":"","address":"","space_units":"м²","space_hidden":false,"space_unclear":false,"region_hidden":true,"costs_property":"","space_comment":"","address_hidden":true,"space_comment_unclear":false,"costs_rent_comment":"","space":"70.5","region":"","costs_rent":""}],"32":[{"costs_property_comment":"","address":"","space_units":"м²","costs_rent_comment":"","space":"","region_hidden":true,"costs_property":"","space_comment":"","address_hidden":true,"costs_rent":""}],"33":[{"costs_property_comment":"","address":"","space_units":"м²","space_hidden":false,"space_comment":"","region_hidden":true,"costs_property":"","region":"","address_hidden":true,"space_comment_unclear":false,"costs_rent_comment":"","space":"24","costs_rent":""}]},"vehicle":{"35":[{"sum_comment":"","brand_info_hidden":false,"sum_rent":"","sum":"","sum_rent_comment":"","year":"2008","brand":"Mitsubishi L200 invite","brand_info":"2477 куб. см., 100 кВт","brand_info_unclear":false,"year_unclear":false,"sum_hidden":false}],"37":[{"sum_comment":"","brand_info_hidden":false,"brand_info":"судно, довжина 3.1 м, двигун Tohatsu 9.8, потужність 7.2 кВт, об'єм 169 куб. см","sum":"","sum_rent_comment":"","year":"2011","brand":"Шельф 310к","sum_rent":""}]},"source":"VULYK","income":{"5":{"family_comment":"","value":"250244","family":"14220","comment":""},"6":{"family_comment":"","value":"219284","family":"","comment":""},"7":{"family":"","family_comment":"","value":"","comment":"","source_name":""},"8":{"family_comment":"","value":"","family":"","comment":""},"9":{"family_comment":"","comment":"","family":"14220","comment_unclear":false,"value":"30960","family_comment_unclear":false},"10":{"family_comment":"","value":"","family":"","comment":""},"11":{"family_comment":"","value":"","family":"","comment":""},"12":{"family_comment":"","value":"","family":"","comment":""},"13":{"family_comment":"","value":"","family":"","comment":""},"14":{"family_comment":"","value":"","family":"","comment":""},"15":{"family_comment":"","value":"","family":"","comment":""},"16":{"family_comment":"","value":"","family":"","comment":""},"17":{"family_comment":"","value":"","family":"","comment":""},"18":{"family_comment":"","value":"","family":"","comment":""},"19":{"family_comment":"","family":"","comment":"","value_unclear":false,"family_unclear":false,"value":""},"20":{"family_comment":"","family":"","comment":"","value_unclear":false,"value":"","comment_hidden":false,"comment_unclear":false,"family_unclear":false,"family_comment_hidden":false,"family_comment_unclear":false}},"banks":{"45":[{"sum_units":"UAH","sum_comment":"","sum_foreign_units":"UAH","sum_hidden":false,"sum":"479585","sum_foreign_comment_hidden":false,"sum_foreign_comment":"","sum_foreign":"","sum_comment_hidden":true},{"sum_units":"","sum_comment":"","sum_foreign_units":"","sum":"21","sum_foreign_comment":"","sum_foreign":"","sum_comment_hidden":true,"sum_foreign_comment_hidden":false}],"51":[{"sum_comment_unclear":false,"sum_units":"UAH","sum_foreign_units":"UAH","sum_foreign_comment_hidden":false,"sum":"112337","sum_foreign_comment":"","sum_comment":"","sum_foreign":"","sum_comment_hidden":true},{"sum_units":"UAH","sum_comment":"","sum_foreign_units":"","sum":"187172","sum_foreign_comment":"","sum_foreign":"","sum_unclear":false}]},"ft_src":"Mitsubishi L200 invite\n2477 куб. см., 100 кВт\n2008\nсудно, довжина 3.1 м, двигун Tohatsu 9.8, потужність 7.2 кВт, об'єм 169 куб. см\n2011\nШельф 310к\n112337\n187172\n479585\n21\n2015\nШельф 310к\nсудно, довжина 3.1 м, двигун Tohatsu 9.8, потужність 7.2 кВт, об'єм 169 куб. см\n2011\n2477 куб. см., 100 кВт\n2008\nMitsubishi L200 invite\n479585\n21\n112337\n187172\n24\n70.5\n44.7\nЧередниченко Владислав Євгенійович\nВладислав Євгенійович Чередниченко\nВладислав Чередниченко\nЧередниченко Владислав Євгенійович\nЧередниченко Владислав Євгенійович\nПодружжя\nЧередниченко Ганна Вікторівна\nДитина\nЧередниченко Валерія Владиславівна\nДитина\nЧередниченко Олександр Владиславович\nВладислав\nЧередниченко\nДніпропетровська область\nАпеляційний адміністративний суд\nсуддя дніпропетровського апеляційного адміністративного суду\nЄвгенійович\n219284\n250244\n14220\n30960\n14220\n2015\n70.5\n24\n44.7\nЧередниченко Ганна Вікторівна\nПодружжя\nЧередниченко Валерія Владиславівна\nДитина\nЧередниченко Олександр Владиславович\nДитина\nЄвгенійович\nЧередниченко\nВладислав\nЧередниченко Владислав Євгенійович\nВладислав Євгенійович Чередниченко\nВладислав Чередниченко\nЧередниченко Владислав Євгенійович\nДніпропетровська область\nАпеляційний адміністративний суд\nсуддя дніпропетровського апеляційного адміністративного суду\nЧередниченко Владислав Євгенійович\n219284\n14220\n30960\n14220\n250244","general":{"family":[{"inn":"","family_name":"Чередниченко Ганна Вікторівна","relations_other":"","relations_hidden":false,"relations_unclear":false,"name_unclear":false,"inn_hidden":true,"name_hidden":true,"relations":"Подружжя"},{"inn":"","family_name":"Чередниченко Валерія Владиславівна","relations_other":"","relations_unclear":false,"name_unclear":false,"inn_hidden":false,"name_hidden":false,"relations":"Дитина"},{"inn":"","family_name":"Чередниченко Олександр Владиславович","name_unclear":false,"inn_hidden":false,"name_hidden":false,"relations":"Дитина"}],"family_raw":"","name":"Владислав","full_name_suggest":{"input":["Чередниченко Владислав Євгенійович","Владислав Євгенійович Чередниченко","Владислав Чередниченко"],"output":"Чередниченко Владислав Євгенійович"},"name_unclear":false,"patronymic":"Євгенійович","inn_hidden":true,"addresses":[{"place_city_type_hidden":true,"place_city_type":"","place_city_hidden":true,"place_hidden":true,"place_district":"","place_district_hidden":true,"place":"","place_city":"","place_address_hidden":true,"place_address":""}],"inn":"","inn_unclear":false,"last_name":"Чередниченко","full_name":"Чередниченко Владислав Євгенійович","post":{"post_hidden":false,"office":"Апеляційний адміністративний суд","post":"суддя дніпропетровського апеляційного адміністративного суду","office_unclear":false,"region_unclear":false,"region":"Дніпропетровська область"}},"liabilities":{"54":{"sum_comment_unclear":false,"sum_comment":"","sum_hidden":false,"sum":"","sum_foreign_comment":"","sum_foreign":"","sum_comment_hidden":false},"55":{"sum_comment":"","sum_foreign_comment":"","sum_foreign":"","sum_hidden":false,"sum":""},"56":{"sum_comment":"","sum_hidden":false,"sum":"","sum_foreign_comment":"","sum_foreign":"","sum_unclear":false,"sum_comment_hidden":false},"57":{"sum_comment":"","sum_hidden":false,"sum":"","sum_foreign_comment":"","sum_foreign":"","sum_comment_hidden":false},"58":{"sum_comment":"","sum_hidden":false,"sum":"","sum_foreign_comment":"","sum_foreign":"","sum_comment_hidden":false},"59":{"sum_comment":"","sum_foreign_comment":"","sum_foreign":"","sum":""},"60":{"sum_comment":"","sum_hidden":false,"sum":"","sum_foreign_comment":"","sum_foreign":"","sum_comment_hidden":false},"61":{"sum_comment":"","sum_foreign_comment":"","sum_foreign":"","sum":""},"62":{"sum_comment":"","sum":"","sum_foreign_comment":"","sum_foreign":"","sum_unclear":false,"sum_comment_hidden":false},"63":{"sum_comment":"","sum_foreign_comment":"","sum_foreign":"","sum":""},"64":{"sum_comment":"","sum_foreign_comment":"","sum_foreign":"","sum":""}},"intro":{"isnotdeclaration":"","declaration_year":"2015"}},{"id":"vulyk_79_54","declaration":{"additional_info_text":"","additional_info":"","date":"2015-03-31T00:00:00","url":"http://static.declarations.com.ua/declarations/chosen_ones/judges_batch/2059_cherednychenko_vladyslav_ievheniiovych.pdf"},"estate":{"25":[{"costs_unclear":false,"address":"","space_units":"м²","costs_rent_unclear":false,"space_hidden":false,"space_unclear":false,"region_hidden":true,"costs_rent_comment":"","space_comment":"","address_hidden":true,"costs":"","costs_rent_comment_unclear":false,"costs_comment":"","space":"44.7","region":"","costs_rent":""}],"31":[{"costs_property_comment":"","address":"","space_units":"м²","space_hidden":false,"space_unclear":false,"region_hidden":true,"costs_property":"","space_comment":"","address_hidden":true,"costs_rent_comment":"","space":"70.5","region":"","costs_rent":""}],"33":[{"costs_property_comment":"","address":"","space_units":"м²","costs_rent_comment":"","space":"24","region":"","region_hidden":true,"costs_property":"","space_comment":"","address_hidden":true,"costs_rent":""}]},"vehicle":{"35":[{"sum_comment":"","brand_info_hidden":false,"sum_rent":"","sum":"","brand_unclear":false,"year":"2008","brand":"Mitsubishi L 200 invite","brand_info":"об'єм двигуна 2477 куб. см., потужність 100 кВт","sum_rent_comment":""}],"37":[{"sum_comment":"","brand_info":"Судно. Довжина - 3.1 м, двигун Tohatsu 9.8 , потужність 7.2 кВт , об'єм 169 куб см","sum":"","sum_rent_comment":"","year":"2011","brand":"Шельф-310к","sum_rent":""}]},"source":"VULYK","income":{"5":{"family":"145500","family_comment":"","comment":"","value_hidden":false,"value_unclear":false,"comment_hidden":false,"family_hidden":false,"value":"234554"},"6":{"family":"","family_comment":"","comment":"","value_hidden":false,"value_unclear":false,"comment_hidden":false,"family_hidden":false,"value":"223204","family_comment_hidden":false},"7":{"family":"","family_comment":"","value":"","comment":"","source_name":""},"8":{"family_comment":"","value":"","family":"","comment":""},"9":{"family_comment":"","value":"11350","family":"","comment":""},"10":{"family_comment":"","family":"","comment":"","value_unclear":false,"family_hidden":false,"value":""},"11":{"family_comment":"","value":"","family":"","comment":""},"12":{"family_comment":"","value":"","family":"","comment":""},"13":{"family_comment":"","value":"","family":"","comment":""},"14":{"family_comment":"","value":"","family":"","comment":""},"15":{"family_comment":"","comment_unclear":false,"value":"","family":"","comment":""},"16":{"family_comment":"","value":"","family":"145500","comment":""},"17":{"family_comment":"","value":"","family":"","comment":""},"18":{"family_comment":"","value":"","family":"","comment":""},"19":{"family_comment":"","value":"","family":"","comment":""},"20":{"family_comment":"","value":"","family":"","comment":"","family_comment_hidden":false}},"banks":{"45":[{"sum_units":"UAH","sum_comment":"","sum_foreign_units":"UAH","sum":"240019","sum_foreign_comment":"","sum_foreign":"","sum_comment_hidden":true,"sum_foreign_hidden":false,"sum_foreign_comment_hidden":false},{"sum_units":"UAH","sum_comment":"","sum_foreign_units":"","sum":"20000","sum_foreign_comment":"","sum_foreign":"","sum_comment_hidden":true}],"46":[{"sum_units":"UAH","sum_comment":"","sum_foreign_units":"UAH","sum":"240019","sum_foreign_comment":"","sum_foreign":"","sum_comment_hidden":true,"sum_foreign_hidden":false,"sum_foreign_comment_hidden":false},{"sum_units":"UAH","sum_comment":"","sum_foreign_units":"","sum":"20000","sum_foreign_comment":"","sum_foreign":"","sum_comment_hidden":true}],"51":[{"sum_units":"UAH","sum_comment":"","sum_foreign_units":"UAH","sum":"30433","sum_foreign_comment":"","sum_foreign":"","sum_comment_hidden":true,"sum_foreign_hidden":false,"sum_foreign_comment_hidden":false}]},"ft_src":"2008\nMitsubishi L 200 invite\nоб'єм двигуна 2477 куб. см., потужність 100 кВт\nСудно. Довжина - 3.1 м, двигун Tohatsu 9.8 , потужність 7.2 кВт , об'єм 169 куб см\n2011\nШельф-310к\n240019\n20000\n30433\n240019\n20000\n2014\nСудно. Довжина - 3.1 м, двигун Tohatsu 9.8 , потужність 7.2 кВт , об'єм 169 куб см\nШельф-310к\n2011\nMitsubishi L 200 invite\nоб'єм двигуна 2477 куб. см., потужність 100 кВт\n2008\n240019\n20000\n30433\n240019\n20000\n24\n70.5\n44.7\nПодружжя\nДитина\nДитина\nЧередниченко Владислав Євгенійович\nВладислав Євгенійович Чередниченко\nВладислав Чередниченко\nЧередниченко Владислав Євгенійович\nЧередниченко Владислав Євгенійович\nВладислав\nЧередниченко\nАпеляційний адміністративний суд\nДніпропетровська область\nсуддя дніпропетровського апеляційного адміністративного суду\nЄвгенійович\n223204\n234554\n145500\n145500\n11350\n2014\n70.5\n24\n44.7\nПодружжя\nДитина\nДитина\nЄвгенійович\nЧередниченко\nВладислав\nЧередниченко Владислав Євгенійович\nВладислав Євгенійович Чередниченко\nВладислав Чередниченко\nЧередниченко Владислав Євгенійович\nДніпропетровська область\nАпеляційний адміністративний суд\nсуддя дніпропетровського апеляційного адміністративного суду\nЧередниченко Владислав Євгенійович\n223204\n11350\n145500\n234554\n145500","general":{"family":[{"inn":"","family_name":"","relations_other":"","relations_hidden":false,"name_unclear":false,"inn_hidden":true,"name_hidden":true,"relations":"Подружжя"},{"inn":"","family_name":"","name_unclear":false,"inn_hidden":true,"name_hidden":false,"relations":"Дитина"},{"inn":"","family_name":"","inn_hidden":false,"relations":"Дитина"}],"family_raw":"","name":"Владислав","full_name_suggest":{"input":["Чередниченко Владислав Євгенійович","Владислав Євгенійович Чередниченко","Владислав Чередниченко"],"output":"Чередниченко Владислав Євгенійович"},"patronymic":"Євгенійович","inn_hidden":true,"addresses":[{"place_city_type_hidden":true,"place_city_type":"","place_city_hidden":true,"place_hidden":true,"place_district":"","place_district_hidden":true,"place":"","place_address":"","place_address_hidden":true,"place_city":""}],"last_name_hidden":false,"inn":"","inn_unclear":false,"last_name":"Чередниченко","full_name":"Чередниченко Владислав Євгенійович","post":{"post_hidden":false,"office":"Апеляційний адміністративний суд","post":"суддя дніпропетровського апеляційного адміністративного суду","region":"Дніпропетровська область","region_hidden":false,"office_unclear":false,"office_hidden":false,"post_unclear":false}},"liabilities":{"54":{"sum_comment":"","sum_foreign_comment":"","sum_foreign":"","sum":"","sum_comment_hidden":false},"55":{"sum_comment":"","sum_foreign_comment":"","sum_foreign":"","sum":""},"56":{"sum_comment":"","sum_foreign_comment":"","sum_foreign":"","sum_hidden":false,"sum":""},"57":{"sum_comment_unclear":false,"sum_comment":"","sum_hidden":false,"sum":"","sum_foreign_comment":"","sum_foreign":"","sum_comment_hidden":false},"58":{"sum_comment_unclear":false,"sum_comment":"","sum_hidden":false,"sum":"","sum_foreign_comment":"","sum_foreign":"","sum_unclear":false,"sum_comment_hidden":false},"59":{"sum_comment":"","sum_foreign_comment":"","sum_foreign":"","sum":""},"60":{"sum_comment":"","sum_foreign_comment":"","sum_foreign":"","sum":"","sum_comment_hidden":false},"61":{"sum_comment":"","sum_foreign_comment":"","sum_foreign":"","sum":""},"62":{"sum_comment":"","sum_foreign_comment":"","sum_foreign":"","sum":""},"63":{"sum_comment":"","sum_foreign_comment":"","sum_foreign":"","sum_unclear":false,"sum":""},"64":{"sum_comment":"","sum_foreign_comment":"","sum_foreign":"","sum_unclear":false,"sum":""}},"intro":{"declaration_year":"2014"}}]