[{"id":"vulyk_92_71","ft_src":"Харківська область\nм. Харків\nінше право користування\n31.8\nм. Харків\n26.5\nХарківська область\nм. Харків\n64.5\nХарківська область\nм. Харків\n31.8\nХарківська область\nОщадбанк України\n4479\n2014\n2014\nПодружжя\nПересіченська Ольга Михайлівна\nЦілюрик Віктор Петрович\nВіктор Петрович Цілюрик\nВіктор Цілюрик\nЦілюрик Віктор Петрович\nЦілюрик Віктор Петрович\nВіктор\nЦілюрик\nЗагальний апеляційний суд\nсуддя апеляційного суду харківської області\nХарківська область\nПетрович\n239430\n34402\n30\n252858\n34402\n13348\n26.5\nХарківська область\nм. Харків\nХарківська область\nм. Харків\n31.8\nінше право користування\n64.5\nХарківська область\nм. Харків\nм. Харків\n31.8\nХарківська область\nОщадбанк України\n4479\n34402\n239430\n13348\n34402\n252858\n30\nПодружжя\nПересіченська Ольга Михайлівна\nПетрович\nЦілюрик\nВіктор\nЦілюрик Віктор Петрович\nВіктор Петрович Цілюрик\nВіктор Цілюрик\nЦілюрик Віктор Петрович\nХарківська область\nЗагальний апеляційний суд\nсуддя апеляційного суду харківської області\nЦілюрик Віктор Петрович","estate":{"25":[{"address":"м. Харків","space_units":"м²","space_hidden":false,"space_comment":"","region_hidden":false,"costs_comment":"","address_hidden":true,"costs":"","address_unclear":false,"space_comment_unclear":false,"costs_rent_comment":"","space":"64.5","region":"Харківська область","costs_rent":""},{"costs":"","address":"м. Харків","space_units":"м²","costs_rent_comment":"","space":"31.8","space_comment":"","region_hidden":false,"costs_comment":"","region":"Харківська область","address_hidden":false,"costs_rent":""}],"27":[{"address":"м. Харків","space_units":"м²","space_hidden":false,"space_unclear":false,"region_hidden":false,"costs_comment":"","space_comment":"","address_hidden":false,"costs":"","address_unclear":false,"costs_rent_comment":"","space":"26.5","region":"Харківська область","costs_rent":""}],"31":[{"costs_property_comment":"","address":"м. Харків","space_units":"м²","space_hidden":false,"space_unclear":false,"region_hidden":false,"costs_property":"","space_comment":"","address_hidden":true,"address_unclear":true,"costs_rent_comment":"інше право користування","space":"31.8","region":"Харківська область","costs_rent":""}]},"source":"VULYK","income":{"5":{"family_comment":"","family_hidden":false,"value":"252858","family":"34402","comment":""},"6":{"family_comment":"","family":"34402","comment":"","value_unclear":false,"family_hidden":false,"value":"239430"},"7":{"family_comment":"","comment":"","family":"","value_unclear":false,"value":"","source_name":""},"8":{"family_comment":"","value":"","family":"","comment":""},"9":{"family_comment":"","value":"","family":"","comment":""},"10":{"family_comment":"","comment":"","family":"","family_unclear":false,"comment_unclear":false,"value":"13348","family_comment_unclear":false},"11":{"family_comment":"","value":"","family":"","comment":"","value_unclear":false},"12":{"family_comment":"","value":"","family":"","comment":""},"13":{"family_comment":"","value":"","family":"","comment":""},"14":{"family_comment":"","value":"","family":"","comment":""},"15":{"family_comment":"","comment":"","family":"","family_unclear":false,"comment_unclear":false,"value":""},"16":{"family_comment":"","value":"","family":"","comment":""},"17":{"family_comment":"","value":"","family":"","comment":""},"18":{"family_comment":"","value":"","family_unclear":false,"family":"","comment":""},"19":{"family_comment":"","value":"","family":"","comment":""},"20":{"family_comment":"","value":"30","family_unclear":false,"family":"","comment":""}},"banks":{"45":[{"sum_units":"UAH","sum_comment":"Ощадбанк України","sum_foreign_units_hidden":false,"sum_foreign_units":"UAH","sum_hidden":false,"sum":"4479","sum_foreign_comment":"","sum_foreign":"","sum_comment_hidden":false,"sum_foreign_hidden":false,"sum_comment_unclear":false}]},"declaration":{"notfull_lostpages":"","additional_info_text":"","additional_info":"","date":"2015-03-30T00:00:00","notfull":"","url":"http://static.declarations.com.ua/declarations/chosen_ones/judges_batch/3319_tsiliuryk_viktor_petrovych.pdf"},"general":{"family_raw":"","name":"Віктор","full_name_suggest":{"input":["Цілюрик Віктор Петрович","Віктор Петрович Цілюрик","Віктор Цілюрик"],"output":"Цілюрик Віктор Петрович"},"patronymic":"Петрович","inn_hidden":true,"patronymic_unclear":false,"inn":"","inn_unclear":false,"last_name":"Цілюрик","full_name":"Цілюрик Віктор Петрович","family":[{"inn":"","inn_unclear":false,"family_name":"Пересіченська Ольга Михайлівна","relations_hidden":false,"name_unclear":true,"relations":"Подружжя","inn_hidden":true,"name_hidden":true,"relations_other":""}],"post":{"office":"Загальний апеляційний суд","post":"суддя апеляційного суду харківської області","office_unclear":false,"region_hidden":false,"region":"Харківська область","office_hidden":false,"post_unclear":false},"addresses":[{"place_city_type":"","place_address_unclear":false,"place_city_type_hidden":true,"place_hidden":true,"place_city_hidden":true,"place_district":"","place_district_hidden":true,"place":"","place_city":"","place_address_hidden":true,"place_address":""}]},"liabilities":{"54":{"sum_comment":"","sum_hidden":false,"sum":"","sum_foreign_comment":"","sum_foreign":"","sum_unclear":false},"55":{"sum_comment":"","sum_foreign_comment":"","sum_foreign":"","sum_unclear":false,"sum":""},"56":{"sum_comment_unclear":false,"sum_comment":"","sum_hidden":false,"sum":"","sum_foreign_comment":"","sum_foreign":"","sum_unclear":false},"57":{"sum_comment":"","sum_hidden":false,"sum":"","sum_foreign_comment":"","sum_foreign":"","sum_comment_hidden":false},"58":{"sum_comment":"","sum_foreign_comment":"","sum_foreign":"","sum":""},"59":{"sum_comment":"","sum_comment_unclear":false,"sum_foreign_comment":"","sum":"","sum_foreign":""},"60":{"sum_comment":"","sum_foreign_comment":"","sum_foreign":"","sum":""},"61":{"sum_comment":"","sum_foreign_comment":"","sum_foreign":"","sum":""},"62":{"sum_comment_unclear":false,"sum_comment":"","sum_hidden":false,"sum":"","sum_foreign_comment":"","sum_foreign":"","sum_unclear":false},"63":{"sum_comment":"","sum_foreign_comment":"","sum_foreign":"","sum":""},"64":{"sum_comment":"","sum_foreign_comment":"","sum_foreign":"","sum":""}},"intro":{"isnotdeclaration":"","declaration_year":"2014"}},{"id":"vulyk_74_126","ft_src":"26.5\n64.5\n255766\n31.8\n4478.65\n2013\n2013\nЗагальний апеляційний суд\nХарківська область\nсуддя жовтневого районного суду м. харкова, суддя апеляційного суду харківської області\nПетрович\nЦілюрик Віктор Петрович\nВіктор Петрович Цілюрик\nВіктор Цілюрик\nЦілюрик Віктор Петрович\nВіктор\nХарківська область\nХарків\nЦілюрик Віктор Петрович\nЦілюрик\nПодружжя\nПересіченська Ольга Михайлівна, 19. 07. 1980 р. н\n38961.51\n232370.73\n232370.73\n38961.51\n26.5\n64.5\n255766\n31.8\n4478.65\n38961.51\n232370.73\n38961.51\n232370.73\nПодружжя\nПересіченська Ольга Михайлівна, 19. 07. 1980 р. н\nХарківська область\nХарків\nПетрович\nЦілюрик\nХарківська область\nЗагальний апеляційний суд\nсуддя жовтневого районного суду м. харкова, суддя апеляційного суду харківської області\nЦілюрик Віктор Петрович\nЦілюрик Віктор Петрович\nВіктор Петрович Цілюрик\nВіктор Цілюрик\nЦілюрик Віктор Петрович\nВіктор","estate":{"25":[{"address":"","space_units":"м²","space_hidden":false,"space_unclear":false,"region_hidden":true,"costs_comment":"","space_comment":"","address_hidden":false,"space":"64.5","costs_rent_comment":"","costs":"","region":"","costs_rent":""},{"costs":"255766","address":"","space_units":"м²","costs_rent_comment":"","space":"31.8","space_comment":"","region_hidden":false,"costs_comment":"грн","region":"","costs_rent":""}],"27":[{"address":"","space_units":"м²","costs_comment":"","region_hidden":true,"space_comment":"","address_hidden":false,"costs":"","address_unclear":false,"costs_rent_comment":"","space":"26.5","region":"","costs_rent":""}]},"source":"VULYK","income":{"5":{"family_comment":"","family":"38961.51","comment":"","family_unclear":false,"family_hidden":false,"value":"232370.73"},"6":{"family_comment":"","family":"38961.51","comment":"","value_unclear":false,"family_unclear":false,"family_hidden":false,"value":"232370.73"},"7":{"source_name_hidden":false,"family_comment":"","family":"","value_hidden":false,"comment":"","family_hidden":false,"value":"","source_name":""},"8":{"family_comment":"","value":"","family":"","comment":""},"9":{"family_comment":"","value":"","family":"","comment":""},"10":{"family_comment":"","value":"","family":"","comment":"","value_unclear":false},"11":{"family_comment":"","value":"","family":"","comment":""},"12":{"family_comment":"","value":"","family":"","comment":""},"13":{"family_comment":"","value":"","family":"","comment":""},"14":{"family_comment":"","value":"","family":"","comment":""},"15":{"family_comment":"","value":"","family":"","comment":""},"16":{"family_comment":"","value":"","family":"","comment":""},"17":{"family_comment":"","value":"","family":"","comment":""},"18":{"family_comment":"","value":"","family":"","comment":""},"19":{"family_comment":"","value":"","family":"","comment":""},"20":{"family_comment":"","comment":"","family":"","value_unclear":false,"family_unclear":false,"comment_unclear":false,"value":""}},"banks":{"45":[{"sum_comment_unclear":false,"sum_units":"UAH","sum_foreign_units":"UAH","sum_hidden":false,"sum":"4478.65","sum_foreign_comment":"","sum_comment":"","sum_unclear":false,"sum_foreign":"","sum_comment_hidden":false,"sum_foreign_hidden":false}]},"declaration":{"notfull_lostpages":"","additional_info_text":"","additional_info":"","date":"2014-03-18T00:00:00","notfull":"","url":"http://static.declarations.com.ua/declarations/chosen_ones/judges_batch/1567_tsiliuryk_viktor_petrovych.pdf"},"general":{"inn":"","addresses":[{"place_city_type_hidden":false,"place_city_type":"Місто","place_city_hidden":false,"place_hidden":false,"place_district":"","place_district_hidden":true,"place":"Харківська область","place_address":"","place_address_hidden":true,"place_city":"Харків"}],"last_name":"Цілюрик","full_name":"Цілюрик Віктор Петрович","family":[{"inn":"","family_name":"Пересіченська Ольга Михайлівна, 19. 07. 1980 р. н","relations_other":"","name_unclear":false,"inn_hidden":true,"name_hidden":false,"relations":"Подружжя"}],"patronymic":"Петрович","inn_hidden":true,"name":"Віктор","post":{"post_hidden":false,"office":"Загальний апеляційний суд","post":"суддя жовтневого районного суду м. харкова, суддя апеляційного суду харківської області","office_unclear":false,"region_unclear":false,"region":"Харківська область"},"family_raw":"","full_name_suggest":{"input":["Цілюрик Віктор Петрович","Віктор Петрович Цілюрик","Віктор Цілюрик"],"output":"Цілюрик Віктор Петрович"}},"liabilities":{"54":{"sum_comment_unclear":false,"sum_comment":"","sum":"","sum_foreign_comment":"","sum_foreign":"","sum_comment_hidden":false},"55":{"sum_comment":"","sum_hidden":false,"sum":"","sum_foreign_comment":"","sum_foreign":"","sum_unclear":false},"56":{"sum_comment":"","sum_hidden":false,"sum":"","sum_foreign_comment":"","sum_foreign":"","sum_unclear":false},"57":{"sum_comment_unclear":false,"sum_comment":"","sum":"","sum_foreign_comment":"","sum_foreign":"","sum_comment_hidden":false},"58":{"sum_comment":"","sum_foreign_comment":"","sum_foreign":"","sum":"","sum_comment_hidden":false},"59":{"sum_comment":"","sum_foreign_comment":"","sum_foreign":"","sum":""},"60":{"sum_comment":"","sum_foreign_comment":"","sum_foreign":"","sum_hidden":false,"sum":""},"61":{"sum_comment":"","sum_foreign_comment":"","sum_foreign":"","sum":""},"62":{"sum_comment":"","sum_foreign_comment":"","sum_foreign":"","sum":""},"63":{"sum_comment_unclear":false,"sum_comment":"","sum":"","sum_foreign_comment":"","sum_foreign":"","sum_unclear":false},"64":{"sum_comment_unclear":false,"sum_comment":"","sum":"","sum_foreign_comment":"","sum_foreign":"","sum_unclear":false}},"intro":{"isnotdeclaration":"","declaration_year_unclear":false,"declaration_year":"2013"}}]