[{"id":"vulyk_82_34","ft_src":"2007\n2378 - об'єм\nMitsubishi Outlander\n1598 - об'єм\n2008\nPeugeot 308\n2014\n20400\n208581.53\n20400\n209667.97\n1086.44\n2378 - об'єм\n2007\nMitsubishi Outlander\n1598 - об'єм\n2008\nPeugeot 308\n2014\nДаниленко Віталій Валерійович\nВіталій Валерійович Даниленко\nВіталій Даниленко\nДаниленко Віталій Валерійович\nДаниленко Віталій Валерійович\nВіталій\nДаниленко\nЗагальний місцевий суд\nм. Київ\nсуддя дарницького районного суду м. києва\nВалерійович\n208581.53\n20400\n1086.44\n209667.97\n20400\nВалерійович\nДаниленко\nВіталій\nДаниленко Віталій Валерійович\nВіталій Валерійович Даниленко\nВіталій Даниленко\nДаниленко Віталій Валерійович\nм. Київ\nЗагальний місцевий суд\nсуддя дарницького районного суду м. києва\nДаниленко Віталій Валерійович","vehicle":{"35":[{"sum_comment":"","brand_info":"2378 - об'єм","sum":"","brand_unclear":false,"year":"2007","brand":"Mitsubishi Outlander","sum_rent":"","sum_rent_comment":""}],"40":[{"sum_comment":"","brand_info":"1598 - об'єм","sum":"","sum_rent_comment":"","year":"2008","brand":"Peugeot 308","sum_rent":"","year_hidden":false}]},"source":"VULYK","income":{"5":{"family_comment":"","family":"20400","comment":"","value_unclear":false,"family_unclear":false,"family_hidden":false,"value":"209667.97"},"6":{"family_comment":"","value":"208581.53","family":"20400","comment":""},"7":{"family":"","family_comment":"","value":"","comment":"","source_name":""},"8":{"family_comment":"","value":"","family":"","comment":""},"9":{"family_comment":"","value":"","family":"","comment":""},"10":{"family_comment":"","value":"","family":"","comment":"","value_unclear":false},"11":{"family_comment":"","value":"","family":"","comment":""},"12":{"family_comment":"","value":"","family":"","comment":""},"13":{"family_comment":"","value":"","family":"","comment":""},"14":{"family_comment":"","value":"","family":"","comment":""},"15":{"family_comment":"","value":"","family":"","comment":""},"16":{"family_comment":"","value":"","family":"","comment":""},"17":{"family_comment":"","value":"","family":"","comment":""},"18":{"family_comment":"","value":"","family":"","comment":""},"19":{"family_comment":"","value":"","family":"","comment":""},"20":{"family_comment":"","value":"1086.44","family":"","comment":""}},"general":{"family_raw":"","name":"Віталій","full_name_suggest":{"input":["Даниленко Віталій Валерійович","Віталій Валерійович Даниленко","Віталій Даниленко"],"output":"Даниленко Віталій Валерійович"},"patronymic":"Валерійович","inn_hidden":true,"addresses":[{"place_city_type_hidden":true,"place_city_type":"","place_city_hidden":true,"place_hidden":true,"place_district":"","place_district_hidden":true,"place":"","place_address":"","place_address_hidden":true,"place_city":""}],"inn":"","inn_unclear":false,"last_name":"Даниленко","full_name":"Даниленко Віталій Валерійович","family":[{"inn":"","family_name":"","relations_other":"","relations_hidden":true,"name_unclear":false,"inn_hidden":true,"name_hidden":true,"relations":""}],"post":{"post_hidden":false,"office":"Загальний місцевий суд","post":"суддя дарницького районного суду м. києва","region":"м. Київ","region_hidden":false,"office_unclear":false,"office_hidden":false},"last_name_unclear":false},"liabilities":{"54":{"sum_comment":"","sum_foreign_comment":"","sum_foreign":"","sum":"","sum_comment_hidden":false},"55":{"sum_comment":"","sum_foreign_comment":"","sum_foreign":"","sum_hidden":false,"sum":""},"56":{"sum_comment":"","sum_foreign_comment":"","sum_foreign":"","sum":""},"57":{"sum_comment":"","sum_foreign_comment":"","sum_foreign":"","sum":""},"58":{"sum_comment":"","sum_foreign_comment":"","sum_foreign":"","sum":""},"59":{"sum_comment":"","sum_foreign_comment":"","sum_foreign":"","sum":""},"60":{"sum_comment":"","sum_foreign_comment":"","sum_foreign":"","sum":""},"61":{"sum_comment":"","sum_foreign_comment":"","sum_foreign":"","sum":""},"62":{"sum_comment":"","sum_foreign_comment":"","sum_foreign":"","sum":""},"63":{"sum_comment":"","sum_foreign_comment":"","sum_foreign":"","sum":""},"64":{"sum_comment":"","sum_foreign_comment":"","sum_foreign":"","sum":""}},"declaration":{"additional_info_text":"","additional_info":"","date":"2015-03-31T00:00:00","url":"http://static.declarations.com.ua/declarations/chosen_ones/judges_batch/2229_danylenko_vitalii_valeriiovych.pdf"},"intro":{"declaration_year":"2014"}}]