[{"id":"vulyk_99_56","ft_src":"2231 куб. см.\nToyota Rav 4\n2014\n793\n2015\n195093\n1011\n150000\n168477\n196122\nдопомога по народженню дитини\n18477\n18\n2231 куб. см.\n2014\nToyota Rav 4\n2015\nДончик\nДончик Віталій Володимирович\nВіталій Володимирович Дончик\nВіталій Дончик\nДончик Віталій Володимирович\nВіталій\nВолодимирович\nДончик Віталій Володимирович\nАдміністративний місцевий суд\nголова вінницького окружного адміністративного суду\nВінницька область\nПодружжя\nДончик І. В\nДитина\nДончик Є. В\nДитина\nДончик Н. В\nДончик К. В\nДитина\n1303\n8538\n195093\nдопомога по народженню дитини\n18\n18477\n196122\n168477\n1011\n150000\n793\n1303\n8538\nДончик І. В\nПодружжя\nДончик Є. В\nДитина\nДончик Н. В\nДитина\nДитина\nДончик К. В\nВолодимирович\nДончик\nголова вінницького окружного адміністративного суду\nВінницька область\nАдміністративний місцевий суд\nДончик Віталій Володимирович\nДончик Віталій Володимирович\nВіталій Володимирович Дончик\nВіталій Дончик\nДончик Віталій Володимирович\nВіталій","estate":{"23":[{"address":"","space_units":"м²","costs_comment":"","space_unclear":false,"region_hidden":true,"space_comment":"","address_hidden":false,"costs":"","costs_rent_comment":"","space":"793","region":"","costs_rent":""}]},"vehicle":{"40":[{"sum_comment":"","brand_info_hidden":false,"sum_rent":"","sum":"","brand_unclear":false,"year":"2014","brand":"Toyota Rav 4","brand_info":"2231 куб. см.","sum_rent_comment":"","brand_info_unclear":false}]},"source":"VULYK","income":{"5":{"family_comment":"","family":"168477","comment":"","value_unclear":false,"family_unclear":false,"value":"196122"},"6":{"family_comment":"","family":"","comment":"","value_unclear":false,"family_unclear":false,"value":"195093"},"7":{"family":"","family_comment":"","value":"","comment":"","source_name":""},"8":{"family_comment":"","value":"","family":"","comment":""},"9":{"family_comment":"","value":"1011","family":"","comment":""},"10":{"family_comment":"","value":"","family":"","comment":""},"11":{"family_comment":"","value":"","family":"150000","comment":""},"12":{"family_comment":"","value":"","family":"","comment":""},"13":{"family_comment":"","value":"","family":"","comment":""},"14":{"family_comment":"","value":"","family":"","comment":""},"15":{"family_comment":"","value":"","family":"","comment":"","value_unclear":false},"16":{"family_comment":"","value":"","family":"","comment":""},"17":{"family_comment":"","value":"","family":"","comment":""},"18":{"family_comment":"","value":"","family":"","comment":""},"19":{"family_comment":"","value":"","family":"","comment":""},"20":{"family_comment":"допомога по народженню дитини","family":"18477","comment":"","value_unclear":false,"family_unclear":false,"value":"18","family_comment_unclear":false}},"general":{"inn":"","addresses":[{"place_city_type_hidden":false,"place_city_type":"","place_city_hidden":true,"place_hidden":true,"place_district":"","place_district_hidden":false,"place":"","place_address":"","place_address_hidden":true,"place_city":""}],"last_name":"Дончик","full_name":"Дончик Віталій Володимирович","family":[{"inn":"","family_name":"Дончик І. В","name_unclear":false,"inn_hidden":false,"name_hidden":true,"relations":"Подружжя"},{"inn":"","family_name":"Дончик Є. В","relations_other":"","name_unclear":false,"inn_hidden":false,"relations":"Дитина"},{"inn":"","family_name":"Дончик Н. В","relations_other":"","name_unclear":false,"inn_hidden":false,"name_hidden":false,"relations":"Дитина"},{"inn":"","family_name":"Дончик К. В","inn_hidden":false,"relations_other":"","relations":"Дитина"}],"patronymic":"Володимирович","inn_hidden":true,"name":"Віталій","post":{"office":"Адміністративний місцевий суд","region":"Вінницька область","post_unclear":false,"post":"голова вінницького окружного адміністративного суду"},"family_raw":"","full_name_suggest":{"input":["Дончик Віталій Володимирович","Віталій Володимирович Дончик","Віталій Дончик"],"output":"Дончик Віталій Володимирович"}},"liabilities":{"54":{"sum_comment_unclear":false,"sum_comment":"","sum":"","sum_foreign_comment":"","sum_foreign":"","sum_comment_hidden":false},"55":{"sum_comment":"","sum_foreign_comment":"","sum_foreign":"","sum":""},"56":{"sum_comment":"","sum_foreign_comment":"","sum_foreign":"","sum":""},"57":{"sum_comment":"","sum_foreign_comment":"","sum_foreign":"","sum":"8538","sum_comment_hidden":false},"58":{"sum_comment":"","sum_foreign_comment":"","sum_foreign":"","sum":"1303","sum_comment_hidden":false},"59":{"sum_comment":"","sum":"","sum_foreign_comment":"","sum_foreign":"","sum_unclear":false,"sum_comment_hidden":false},"60":{"sum_comment":"","sum_foreign_comment":"","sum_foreign":"","sum":"","sum_comment_hidden":false},"61":{"sum_comment":"","sum_foreign_comment":"","sum_foreign":"","sum":""},"62":{"sum_comment":"","sum_foreign_comment":"","sum_foreign":"","sum":""},"63":{"sum_comment":"","sum_foreign_comment":"","sum_foreign":"","sum":"","sum_comment_hidden":false},"64":{"sum_comment":"","sum_foreign_comment":"","sum_foreign":"","sum":"","sum_comment_hidden":false}},"declaration":{"notfull_lostpages":"","date":"2016-03-25T00:00:00","notfull":"","url":"http://static.declarations.com.ua/declarations/chosen_ones/judges_batch/605_donchyk_vitalii_volodymyrovych_2015.pdf"},"intro":{"declaration_year":"2015"}},{"id":"vulyk_98_6","ft_src":"2231 куб. см.\n2014\nToyota Rav 4\n793\n4606\nПриватбанк\n4606\n2014\n2231 куб. см.\n2014\nToyota Rav 4\n2014\nАдміністративний місцевий суд\nсуддя вінницького окружного адміністративного суду\nВінницька область\nДончик Віталій Володимирович\nВіталій Володимирович Дончик\nВіталій Дончик\nДончик Віталій Володимирович\nДончик Віталій Володимирович\nПодружжя\nДончик І. В\nДитина\nДончик Є. В\nДитина\nДончик Н. В\nВіталій\nДончик\nВолодимирович\n9327\nПриватбанк\n237\nПриватбанк\n210152\n675\n150000\n212914\n2087\n150000\n793\n4606\nПриватбанк\n4606\nПриватбанк\n237\nПриватбанк\n9327\n210152\n2087\n150000\n150000\n212914\n675\nПодружжя\nДончик І. В\nДитина\nДончик Є. В\nДончик Н. В\nДитина\nВолодимирович\nДончик\nВіталій\nДончик Віталій Володимирович\nВіталій Володимирович Дончик\nВіталій Дончик\nДончик Віталій Володимирович\nсуддя вінницького окружного адміністративного суду\nВінницька область\nАдміністративний місцевий суд\nДончик Віталій Володимирович","estate":{"23":[{"address":"","space_units":"м²","costs_comment":"","space_unclear":false,"region_hidden":true,"space_comment":"","address_hidden":false,"costs":"","costs_rent_comment":"","space":"793","region":"","costs_rent":""}]},"vehicle":{"40":[{"sum_comment":"","brand_info":"2231 куб. см.","sum":"","sum_rent_comment":"","year":"2014","brand":"Toyota Rav 4","sum_rent":""}]},"source":"VULYK","income":{"5":{"family_comment":"","family":"150000","comment":"","value_unclear":false,"family_unclear":false,"value":"212914"},"6":{"family_comment":"","value":"210152","family":"","comment":"","value_unclear":false},"7":{"family":"","family_comment":"","value":"","comment":"","source_name":""},"8":{"family_comment":"","value":"","family":"","comment":""},"9":{"family_comment":"","value":"2087","family":"","comment":"","value_unclear":false},"10":{"family_comment":"","value":"","family":"","comment":""},"11":{"family_comment":"","value":"","family":"150000","comment":""},"12":{"family_comment":"","value":"","family":"","comment":""},"13":{"family_comment":"","value":"","family":"","comment":""},"14":{"family_comment":"","value":"","family":"","comment":""},"15":{"family_comment":"","value":"","family":"","comment":""},"16":{"family_comment":"","value":"","family":"","comment":""},"17":{"family_comment":"","value":"","family":"","comment":""},"18":{"family_comment":"","value":"","family":"","comment":""},"19":{"family_comment":"","value":"","family":"","comment":""},"20":{"family_comment":"","value":"675","family":"","comment":"","value_unclear":false}},"banks":{"45":[{"sum_units":"UAH","sum_comment":"Приватбанк","sum_foreign_units":"UAH","sum_hidden":false,"sum":"4606","sum_foreign_comment":"","sum_foreign":"","sum_unclear":false,"sum_comment_hidden":false}],"46":[{"sum_units":"UAH","sum_comment":"","sum_foreign_units":"UAH","sum_hidden":false,"sum":"4606","sum_foreign_comment":"","sum_foreign":"","sum_unclear":false,"sum_comment_hidden":false}]},"declaration":{"date":"2015-03-31T00:00:00","url":"http://static.declarations.com.ua/declarations/chosen_ones/judges_batch/4477_donchyk_vitalii_volodymyrovych.pdf"},"general":{"family":[{"inn":"","family_name":"Дончик І. В","relations_other":"","name_unclear":false,"inn_hidden":true,"name_hidden":true,"relations":"Подружжя"},{"inn":"","family_name":"Дончик Є. В","relations_other":"","name_unclear":false,"inn_hidden":false,"name_hidden":false,"relations":"Дитина"},{"inn":"","family_name":"Дончик Н. В","name_unclear":false,"inn_hidden":true,"name_hidden":false,"relations":"Дитина"}],"family_raw":"","name":"Віталій","full_name_suggest":{"input":["Дончик Віталій Володимирович","Віталій Володимирович Дончик","Віталій Дончик"],"output":"Дончик Віталій Володимирович"},"patronymic":"Володимирович","inn_hidden":true,"addresses":[{"place_city_type_hidden":false,"place_city_type":"","place_city_hidden":true,"place_hidden":true,"place_district":"","place_district_hidden":false,"place":"","place_address":"","place_address_hidden":true,"place_city":""}],"last_name_hidden":false,"patronymic_hidden":false,"inn":"","inn_unclear":false,"last_name":"Дончик","full_name":"Дончик Віталій Володимирович","post":{"office":"Адміністративний місцевий суд","region":"Вінницька область","post_unclear":false,"post":"суддя вінницького окружного адміністративного суду"},"last_name_unclear":false},"liabilities":{"54":{"sum_comment_unclear":false,"sum_comment":"","sum_hidden":false,"sum":"","sum_foreign_comment":"","sum_foreign":"","sum_unclear":false,"sum_comment_hidden":false},"55":{"sum_comment":"","sum_foreign_comment":"","sum_foreign":"","sum":""},"56":{"sum_comment":"","sum_foreign_comment":"","sum_foreign":"","sum_unclear":false,"sum":""},"57":{"sum_comment_unclear":false,"sum_comment":"Приватбанк","sum_hidden":false,"sum":"9327","sum_foreign_comment":"","sum_foreign":"","sum_unclear":false,"sum_comment_hidden":false},"58":{"sum_comment":"Приватбанк","sum_hidden":false,"sum":"237","sum_foreign_comment":"","sum_foreign":"","sum_unclear":false,"sum_comment_hidden":false},"59":{"sum_comment":"","sum_comment_unclear":false,"sum_foreign_comment":"","sum":"","sum_foreign":""},"60":{"sum_comment":"","sum_hidden":false,"sum":"","sum_foreign_comment":"","sum_foreign":"","sum_comment_hidden":false},"61":{"sum_comment":"","sum_foreign_comment":"","sum_foreign":"","sum":""},"62":{"sum_comment":"","sum":"","sum_foreign_comment":"","sum_foreign":"","sum_unclear":false,"sum_comment_hidden":false},"63":{"sum_comment_unclear":false,"sum_comment":"","sum":"","sum_foreign_comment":"","sum_foreign":"","sum_comment_hidden":false},"64":{"sum_comment":"","sum_foreign_comment":"","sum_foreign":"","sum":"","sum_comment_hidden":false}},"intro":{"declaration_year":"2014"}},{"ft_src":"Вінницька обл,, Вінницький р-н, Мізяківсько-Хутірська сільська радаа\n793\n13617\nTRUE\nРозділ 5А, пункт 45. Додатково вказано ПАТ КБ ’Приват Банк\"\nFALSE\nFALSE\n2013\n169275\n11470\n617467\n1617\n435105\nРозділ 5А, пункт 45. Додатково вказано ПАТ КБ ’Приват Банк\"\nFALSE\nTRUE\nВінницька обл,, Вінницький р-н, Мізяківсько-Хутірська сільська радаа\n793\nСуддя Вінницького окружного адміністративного суду\nДружина: Дончик І.В. 18.05.1981;Дочка: Дончик Є. В. 3.03.2004.;Син: Дончик Н.В. 9.07.2007\nКиївська\nКиїв\nДончик\nДончик Віталій Володимирович\nВіталій Володимирович Дончик\nВіталій Дончик\nДончик Віталій Володимирович\nВіталій\nДончик Віталій Володимирович\nАдміністративний місцевий суд\nСуддя\nВінницька область\nВолодимирович\nм. Київ (решта приховано)\n322928\n6631\n1035\n169275\n435105\n617467\n11470\n1617\n13617\n2013\nFALSE\n6631\n322928\n1035\nДончик\nВолодимирович\nДружина: Дончик І.В. 18.05.1981;Дочка: Дончик Є. В. 3.03.2004.;Син: Дончик Н.В. 9.07.2007\nДончик Віталій Володимирович\nВіталій Володимирович Дончик\nВіталій Дончик\nДончик Віталій Володимирович\nВіталій\nСуддя Вінницького окружного адміністративного суду\nКиївська\nКиїв\nСуддя\nВінницька область\nАдміністративний місцевий суд\nДончик Віталій Володимирович\nм. Київ (решта приховано)","estate":{"23":[{"costs":"","address":"","space_units":"","costs_rent_comment":"","space":"793","costs_comment":"","costs_rent":"","space_comment":"","region":"","location_raw":"Вінницька обл,, Вінницький р-н, Мізяківсько-Хутірська сільська радаа"},{"costs":"","address":"","space_units":"","costs_rent_comment":"","space":"","costs_comment":"","costs_rent":"","space_comment":"","region":"","location_raw":""},{"costs":"","address":"","space_units":"","costs_rent_comment":"","space":"","costs_comment":"","costs_rent":"","space_comment":"","region":"","location_raw":""}]},"id":"5227","income":{"5":{"family_comment":"","value":"617467","family":"0","comment":""},"6":{"family_comment":"","value":"169275","family":"0","comment":""},"7":{"family":"0","family_comment":"","value":"0","comment":"","source_name":"0"},"8":{"family_comment":"","value":"0","family":"0","comment":""},"9":{"family_comment":"","value":"1617","family":"0","comment":""},"10":{"family_comment":"","value":"11470","family":"0","comment":""},"11":{"family_comment":"","value":"0","family":"0","comment":""},"12":{"family_comment":"","value":"0","family":"0","comment":""},"13":{"family_comment":"","value":"0","family":"0","comment":""},"14":{"family_comment":"","value":"0","family":"0","comment":""},"15":{"family_comment":"","value":"0","family":"0","comment":""},"16":{"family_comment":"","value":"0","family":"0","comment":""},"17":{"family_comment":"","value":"0","family":"0","comment":""},"18":{"family_comment":"","value":"0","family":"0","comment":""},"19":{"family_comment":"","value":"0","family":"0","comment":""},"20":{"family_comment":"","value":"435105","family":"0","comment":""},"21":[{"country_comment":"","uah_equal":"0","country":"0","cur":"0"},{"country_comment":"","uah_equal":"0","country":"0","cur":"0"},{"country_comment":"","uah_equal":"0","country":"0","cur":"0"},{"country_comment":"","uah_equal":"0","country":"0","cur":"0"},{"country_comment":"","uah_equal":"0","country":"0","cur":"0"}],"22":[{"country_comment":"","uah_equal":"0","country":"0","cur":"0"},{"country_comment":"","uah_equal":"0","country":"0","cur":"0"},{"country_comment":"","uah_equal":"0","country":"0","cur":"0"},{"country_comment":"","uah_equal":"0","country":"0","cur":"0"},{"country_comment":"","uah_equal":"0","country":"0","cur":"0"}]},"banks":{"45":[{"sum_units":"UAH","sum_comment":"","sum_foreign_units":"","sum":"13617","sum_foreign_comment":"","sum_foreign":""},{"sum_units":"USD","sum_comment":"","sum_foreign_units":"","sum":"","sum_foreign_comment":"","sum_foreign":""},{"sum_units":"EUR","sum_comment":"","sum_foreign_units":"","sum":"","sum_foreign_comment":"","sum_foreign":""}],"46":[{"sum_units":"UAH","sum_comment":"","sum_foreign_units":"","sum":"","sum_foreign_comment":"","sum_foreign":""},{"sum_units":"USD","sum_comment":"","sum_foreign_units":"","sum":"","sum_foreign_comment":"","sum_foreign":""},{"sum_units":"EUR","sum_comment":"","sum_foreign_units":"","sum":"","sum_foreign_comment":"","sum_foreign":""}],"47":[{"sum_units":"","sum_comment":"","sum_foreign_units":"","sum":"","sum_foreign_comment":"","sum_foreign":""}],"48":[{"sum_units":"","sum_comment":"","sum_foreign_units":"","sum":"","sum_foreign_comment":"","sum_foreign":""}],"49":[{"sum_units":"","sum_comment":"","sum_foreign_units":"","sum":"","sum_foreign_comment":"","sum_foreign":""}],"50":[{"sum_units":"","sum_comment":"","sum_foreign_units":"","sum":"","sum_foreign_comment":"","sum_foreign":""}],"51":[{"sum_units":"UAH","sum_comment":"","sum_foreign_units":"","sum":"","sum_foreign_comment":"","sum_foreign":""},{"sum_units":"USD","sum_comment":"","sum_foreign_units":"","sum":"","sum_foreign_comment":"","sum_foreign":""},{"sum_units":"EUR","sum_comment":"","sum_foreign_units":"","sum":"","sum_foreign_comment":"","sum_foreign":""}],"52":[{"sum_units":"","sum_comment":"","sum_foreign_units":"","sum":"","sum_foreign_comment":"","sum_foreign":""}],"53":[{"sum_units":"","sum_comment":"","sum_foreign_units":"","sum":"","sum_foreign_comment":"","sum_foreign":""}]},"declaration":{"notfull_lostpages":"","additional_info_text":"Розділ 5А, пункт 45. Додатково вказано ПАТ КБ ’Приват Банк\"","additional_info":"TRUE","notfull":"FALSE","url":"http://static.declarations.com.ua/declarations/sudy/mistsevi_sudy/okruzhni_administratyvni_sudy/vinnytska/860_dc-donchik.pdf","needs_scancopy_check":false},"general":{"family_raw":"Дружина: Дончик І.В. 18.05.1981;Дочка: Дончик Є. В. 3.03.2004.;Син: Дончик Н.В. 9.07.2007","name":"Віталій","full_name_suggest":{"input":["Дончик Віталій Володимирович","Віталій Володимирович Дончик","Віталій Дончик"],"output":"Дончик Віталій Володимирович"},"post_raw":"Суддя Вінницького окружного адміністративного суду","name_unclear":false,"patronymic":"Володимирович","patronymic_unclear":false,"last_name_hidden":false,"patronymic_hidden":false,"inn":"","addresses_raw_hidden":true,"last_name":"Дончик","full_name":"Дончик Віталій Володимирович","post":{"office":"Адміністративний місцевий суд","region":"Вінницька область","post":"Суддя"},"addresses":[{"place_district":"","place_city_type":"","place_address_type":"","place":"Київська","place_address":"","place_city":"Київ"}],"name_hidden":false,"last_name_unclear":false,"addresses_raw":"м. Київ (решта приховано)"},"liabilities":{"54":{"sum_comment":"","sum_foreign_comment":"","sum_foreign":"","sum":"1035"},"55":{"sum_units":"","sum_comment":"","sum_foreign_units":"","sum":"","sum_foreign_comment":"","sum_foreign":""},"56":{"sum_comment":"","sum_foreign_comment":"","sum_foreign":"","sum":""},"57":{"sum_comment":"","sum_foreign_comment":"","sum_foreign":"","sum":"322928"},"58":{"sum_comment":"","sum_foreign_comment":"","sum_foreign":"","sum":"6631"},"59":{"sum_comment":"","sum_foreign_comment":"","sum_foreign":"","sum":""},"60":{"sum_comment":"","sum_foreign_comment":"","sum_foreign":"","sum":""},"61":{"sum_units":"","sum_comment":"","sum_foreign_units":"","sum":"","sum_foreign_comment":"","sum_foreign":""},"62":{"sum_comment":"","sum_foreign_comment":"","sum_foreign":"","sum":""},"63":{"sum_comment":"","sum_units":"","sum_foreign":"","sum":"","sum_foreign_comment":""},"64":{"sum_comment":"","sum_units":"","sum_foreign":"","sum":"","sum_foreign_comment":""}},"intro":{"isnotdeclaration":"FALSE","declaration_year":"2013"}}]