[{"id":"vulyk_93_95","ft_src":"в користуванні\n2967 куб. см., 497.5 см\nVolkswagen Touareg\n2010\n1000\nЛьвівська область\nм. Львів\n23.2\nЛьвівська область\nм. Львів\nЛьвівська область\n18.2\nм. Львів\nЛьвівська область\n86\n44101\n2014\n2967 куб. см., 497.5 см\nв користуванні\nVolkswagen Touareg\n2010\n1000\nЛьвівська область\n18.2\nЛьвівська область\nм. Львів\n23.2\nм. Львів\nЛьвівська область\n86\nЛьвівська область\nм. Львів\nДонченко\nПодружжя\nБонк Т. Б., 23. 09. 1963\nДитина\nДонченко Н. Ю., 03. 10. 2002\nДонченко Юрій Володимирович\nЮрій Володимирович Донченко\nЮрій Донченко\nДонченко Юрій Володимирович\nДонченко Юрій Володимирович\nЛьвівська область\nЛьвів\nЮрій\nВолодимирович\nЛьвівська область\nЗагальний місцевий суд\nсуддя шевченківського районного суду м. львова\n213434.15\n262812.2\n10803.13\n274992.2\n237635.28\n12180\n13398\n44101\n2014\n213434.15\n262812.2\n10803.13\n13398\n12180\n237635.28\n274992.2\nПодружжя\nБонк Т. Б., 23. 09. 1963\nДитина\nДонченко Н. Ю., 03. 10. 2002\nДонченко\nВолодимирович\nЛьвівська область\nЛьвів\nЛьвівська область\nЗагальний місцевий суд\nсуддя шевченківського районного суду м. львова\nДонченко Юрій Володимирович\nДонченко Юрій Володимирович\nЮрій Володимирович Донченко\nЮрій Донченко\nДонченко Юрій Володимирович\nЮрій","estate":{"23":[{"address":"","space_units":"м²","costs_comment":"","space_unclear":false,"region_hidden":false,"space_comment":"","address_hidden":false,"space":"1000","space_comment_unclear":false,"costs_rent_comment":"","costs":"","region":"Львівська область","costs_rent":""}],"25":[{"address":"м. Львів","space_units":"м²","space_hidden":false,"space_unclear":false,"region_hidden":false,"costs_comment":"","space_comment":"","address_hidden":false,"space":"86","costs_rent_comment_unclear":false,"costs_rent_comment":"","costs":"","region":"Львівська область","costs_rent":""}],"27":[{"costs":"","address":"м. Львів","space_units":"м²","costs_rent_comment":"","space":"23.2","space_comment":"","region_hidden":false,"costs_comment":"","region":"Львівська область","address_hidden":false,"costs_rent":""}],"33":[{"costs_property_comment":"","address":"м. Львів","space_units":"м²","space_hidden":false,"space_comment":"","region_hidden":false,"costs_property":"","region":"Львівська область","address_hidden":false,"costs_rent_comment":"","space":"18.2","costs_rent":""}]},"vehicle":{"35":[{"year_hidden":false,"brand_info":"2967 куб. см., 497.5 см","brand_unclear":false,"sum_rent_comment":"","brand_hidden":false,"year":"2010","sum_comment":"в користуванні","brand_info_hidden":false,"sum_rent":"","brand":"Volkswagen Touareg","brand_info_unclear":false,"sum":""}]},"source":"VULYK","income":{"5":{"family":"237635.28","family_comment":"","comment":"","value_hidden":false,"value_unclear":false,"value":"274992.2","family_hidden":false,"family_unclear":false},"6":{"family_comment":"","family":"213434.15","comment":"","value_unclear":false,"family_unclear":false,"value":"262812.2"},"7":{"source_name_hidden":false,"family_comment":"","comment":"","family":"","comment_hidden":false,"source_name_unclear":false,"value":"","source_name":""},"8":{"family_comment":"","value":"","family":"","comment":""},"9":{"family_comment":"","family":"","comment":"","value_unclear":false,"family_unclear":false,"family_hidden":false,"value":"","family_comment_unclear":false},"10":{"family_comment":"","value":"12180","family":"13398","comment":""},"11":{"family_comment":"","value":"","family":"","comment":""},"12":{"family_comment":"","value":"","family":"","comment":""},"13":{"family_comment":"","value":"","family":"","comment":""},"14":{"family_comment":"","value":"","family":"","comment":""},"15":{"family_comment":"","value":"","family":"10803.13","comment":""},"16":{"family_comment":"","value":"","family":"","comment":""},"17":{"family_comment":"","value":"","family":"","comment":""},"18":{"family_comment":"","value":"","family":"","comment":""},"19":{"family_comment":"","value":"","family":"","comment":""},"20":{"family_comment":"","family":"","comment":"","value_unclear":false,"value":"","comment_unclear":false,"family_unclear":false,"family_comment_hidden":false,"family_comment_unclear":false}},"banks":{"51":[{"sum_units":"UAH","sum_comment_unclear":false,"sum_hidden":false,"sum":"44101","sum_units_unclear":false,"sum_comment":"","sum_foreign_units":"UAH","sum_units_hidden":false,"sum_foreign_comment":"","sum_unclear":false,"sum_foreign":"","sum_comment_hidden":false}]},"declaration":{"notfull_lostpages":"","additional_info_text":"","additional_info":"","date":"2015-03-24T00:00:00","notfull":"","url":"http://static.declarations.com.ua/declarations/chosen_ones/judges_batch/3541_donchenko_iurii_volodymyrovych.pdf"},"general":{"inn":"","addresses":[{"place_city_type_hidden":false,"place_city_type":"Місто","place_city_hidden":false,"place_hidden":false,"place_district":"","place_district_hidden":false,"place":"Львівська область","place_address":"","place_address_hidden":true,"place_city":"Львів"}],"last_name":"Донченко","full_name":"Донченко Юрій Володимирович","family":[{"inn":"","family_name":"Бонк Т. Б., 23. 09. 1963","relations_hidden":false,"name_unclear":true,"relations":"Подружжя","inn_hidden":true,"name_hidden":false,"relations_other":""},{"inn":"","family_name":"Донченко Н. Ю., 03. 10. 2002","relations_other":"","name_unclear":false,"inn_hidden":true,"name_hidden":false,"relations":"Дитина"}],"patronymic":"Володимирович","inn_hidden":true,"name":"Юрій","post":{"office":"Загальний місцевий суд","post":"суддя шевченківського районного суду м. львова","candidate":"","office_unclear":false,"region":"Львівська область","region_unclear":false,"post_unclear":false},"family_raw":"","full_name_suggest":{"input":["Донченко Юрій Володимирович","Юрій Володимирович Донченко","Юрій Донченко"],"output":"Донченко Юрій Володимирович"}},"liabilities":{"54":{"sum_comment":"","sum_foreign_comment":"","sum_foreign":"","sum_hidden":false,"sum":""},"55":{"sum_comment":"","sum_foreign_comment":"","sum_foreign":"","sum":""},"56":{"sum_comment":"","sum_foreign_comment":"","sum_foreign":"","sum":""},"57":{"sum_comment":"","sum_hidden":false,"sum":"","sum_foreign_comment":"","sum_foreign":"","sum_unclear":false,"sum_comment_hidden":false},"58":{"sum_comment_unclear":false,"sum_comment":"","sum_hidden":false,"sum":"","sum_foreign_comment":"","sum_foreign":"","sum_unclear":false},"59":{"sum_comment":"","sum_foreign_comment":"","sum_foreign":"","sum":""},"60":{"sum_comment":"","sum_foreign_comment":"","sum_foreign":"","sum_hidden":false,"sum":""},"61":{"sum_comment":"","sum_foreign_comment":"","sum_foreign":"","sum":""},"62":{"sum_comment":"","sum_foreign_comment":"","sum_foreign":"","sum":""},"63":{"sum_comment":"","sum_foreign_comment":"","sum_foreign":"","sum":""},"64":{"sum_comment":"","sum_foreign_comment":"","sum_foreign":"","sum":""}},"intro":{"isnotdeclaration":"","declaration_year":"2014"}}]