[{"ft_src":"Ford,Mondeo\n1999\nВолинська область (далі приховано)\n1600\nВолинська область (далі приховано)\n240\nВолинська область (далі приховано)\n900\nFALSE\nFALSE\nFALSE\n2013\n8926\n55584\n51445\n42505\n46658\n8940\nFord,Mondeo\n1999\nFALSE\nFALSE\nВолинська область (далі приховано)\n1600\nВолинська область (далі приховано)\n900\nВолинська область (далі приховано)\n240\nГоловний спеціаліст відділу державної реєстрації речових прав на нерухоме майно Головного управління юстиції у Волинській області\nСин - Глущенко О.М.;Дочка - Глущенко О.М.;Мати - Мельник Л.С.;Батько - Мельник М.Б.\nВолинська\nГлущенко\nГлущенко Наталія Миколаївна\nНаталія Миколаївна Глущенко\nНаталія Глущенко\nГлущенко Наталія Миколаївна\nНаталія\nГлущенко Наталія Миколаївна\nМіністерство юстиції\nГоловний спеціаліст відділу державної реєстрації речових прав на нерухоме майно Головного управління юстиції у Волинській області\nВолинська область\nМиколаївна\n44500, Волинська область (далі приховано)\n8926\n8940\n46658\n51445\n55584\n42505\n2013\nFALSE\nГлущенко\nМиколаївна\nСин - Глущенко О.М.;Дочка - Глущенко О.М.;Мати - Мельник Л.С.;Батько - Мельник М.Б.\nГлущенко Наталія Миколаївна\nНаталія Миколаївна Глущенко\nНаталія Глущенко\nГлущенко Наталія Миколаївна\nНаталія\nГоловний спеціаліст відділу державної реєстрації речових прав на нерухоме майно Головного управління юстиції у Волинській області\nВолинська\nГоловний спеціаліст відділу державної реєстрації речових прав на нерухоме майно Головного управління юстиції у Волинській області\nВолинська область\nМіністерство юстиції\nГлущенко Наталія Миколаївна\n44500, Волинська область (далі приховано)","estate":{"23":[{"costs":"","address":"","space_units":"","costs_rent_comment":"","space":"1600","costs_comment":"","costs_rent":"","space_comment":"","region":"","location_raw":"Волинська область (далі приховано)"},{"costs":"","address":"","space_units":"","costs_rent_comment":"","space":"","costs_comment":"","costs_rent":"","space_comment":"","region":"","location_raw":""},{"costs":"","address":"","space_units":"","costs_rent_comment":"","space":"","costs_comment":"","costs_rent":"","space_comment":"","region":"","location_raw":""}],"29":[{"costs_property_comment":"","address":"","space_units":"","costs_rent_comment":"","space":"900","space_comment":"","costs_property":"","region":"","location_raw":"Волинська область (далі приховано)","costs_rent":""}],"30":[{"costs_property_comment":"","address":"","space_units":"","costs_rent_comment":"","space":"240","space_comment":"","costs_property":"","region":"","location_raw":"Волинська область (далі приховано)","costs_rent":""}]},"vehicle":{"40":[{"sum_comment":"","brand_info":"","sum":"","sum_rent_comment":"","year":"1999","brand":"Ford,Mondeo","sum_rent":"","brand_hidden":false}]},"id":"2487","income":{"5":{"family_comment":"","value":"51445","family":"55584","comment":""},"6":{"family_comment":"","value":"0","family":"8926","comment":""},"7":{"family":"0","family_comment":"","value":"0","comment":"","source_name":"0"},"8":{"family_comment":"","value":"0","family":"0","comment":""},"9":{"family_comment":"","value":"0","family":"0","comment":""},"10":{"family_comment":"","value":"0","family":"0","comment":""},"11":{"family_comment":"","value":"0","family":"0","comment":""},"12":{"family_comment":"","value":"0","family":"0","comment":""},"13":{"family_comment":"","value":"0","family":"0","comment":""},"14":{"family_comment":"","value":"0","family":"0","comment":""},"15":{"family_comment":"","value":"0","family":"0","comment":""},"16":{"family_comment":"","value":"42505","family":"0","comment":""},"17":{"family_comment":"","value":"0","family":"0","comment":""},"18":{"family_comment":"","value":"0","family":"0","comment":""},"19":{"family_comment":"","value":"0","family":"0","comment":""},"20":{"family_comment":"","value":"8940","family":"46658","comment":""},"21":[{"country_comment":"","uah_equal":"0","country":"0","cur":"0"},{"country_comment":"","uah_equal":"0","country":"0","cur":"0"},{"country_comment":"","uah_equal":"0","country":"0","cur":"0"},{"country_comment":"","uah_equal":"0","country":"0","cur":"0"},{"country_comment":"","uah_equal":"0","country":"0","cur":"0"}],"22":[{"country_comment":"","uah_equal":"0","country":"0","cur":"0"},{"country_comment":"","uah_equal":"0","country":"0","cur":"0"},{"country_comment":"","uah_equal":"0","country":"0","cur":"0"},{"country_comment":"","uah_equal":"0","country":"0","cur":"0"},{"country_comment":"","uah_equal":"0","country":"0","cur":"0"}]},"banks":{"45":[{"sum_units":"UAH","sum_comment":"","sum_foreign_units":"","sum":"","sum_foreign_comment":"","sum_foreign":""},{"sum_units":"USD","sum_comment":"","sum_foreign_units":"","sum":"","sum_foreign_comment":"","sum_foreign":""},{"sum_units":"EUR","sum_comment":"","sum_foreign_units":"","sum":"","sum_foreign_comment":"","sum_foreign":""}],"46":[{"sum_units":"UAH","sum_comment":"","sum_foreign_units":"","sum":"","sum_foreign_comment":"","sum_foreign":""},{"sum_units":"USD","sum_comment":"","sum_foreign_units":"","sum":"","sum_foreign_comment":"","sum_foreign":""},{"sum_units":"EUR","sum_comment":"","sum_foreign_units":"","sum":"","sum_foreign_comment":"","sum_foreign":""}],"47":[{"sum_units":"","sum_comment":"","sum_foreign_units":"","sum":"","sum_foreign_comment":"","sum_foreign":""}],"48":[{"sum_units":"","sum_comment":"","sum_foreign_units":"","sum":"","sum_foreign_comment":"","sum_foreign":""}],"49":[{"sum_units":"","sum_comment":"","sum_foreign_units":"","sum":"","sum_foreign_comment":"","sum_foreign":""}],"50":[{"sum_units":"","sum_comment":"","sum_foreign_units":"","sum":"","sum_foreign_comment":"","sum_foreign":""}],"51":[{"sum_units":"UAH","sum_comment":"","sum_foreign_units":"","sum":"","sum_foreign_comment":"","sum_foreign":""},{"sum_units":"USD","sum_comment":"","sum_foreign_units":"","sum":"","sum_foreign_comment":"","sum_foreign":""},{"sum_units":"EUR","sum_comment":"","sum_foreign_units":"","sum":"","sum_foreign_comment":"","sum_foreign":""}],"52":[{"sum_units":"","sum_comment":"","sum_foreign_units":"","sum":"","sum_foreign_comment":"","sum_foreign":""}],"53":[{"sum_units":"","sum_comment":"","sum_foreign_units":"","sum":"","sum_foreign_comment":"","sum_foreign":""}]},"declaration":{"notfull_lostpages":"","additional_info_text":"","additional_info":"FALSE","notfull":"FALSE","url":"http://static.declarations.com.ua/lustration/5488040c86ffe.pdf","needs_scancopy_check":false},"general":{"family_raw":"Син - Глущенко О.М.;Дочка - Глущенко О.М.;Мати - Мельник Л.С.;Батько - Мельник М.Б.","name":"Наталія","full_name_suggest":{"input":["Глущенко Наталія Миколаївна","Наталія Миколаївна Глущенко","Наталія Глущенко"],"output":"Глущенко Наталія Миколаївна"},"post_raw":"Головний спеціаліст відділу державної реєстрації речових прав на нерухоме майно Головного управління юстиції у Волинській області","name_unclear":false,"patronymic":"Миколаївна","patronymic_unclear":false,"last_name_hidden":false,"patronymic_hidden":false,"inn":"","addresses_raw_hidden":true,"last_name":"Глущенко","full_name":"Глущенко Наталія Миколаївна","post":{"office":"Міністерство юстиції","region":"Волинська область","post":"Головний спеціаліст відділу державної реєстрації речових прав на нерухоме майно Головного управління юстиції у Волинській області"},"addresses":[{"place_district":"","place_city_type":"","place_address_type":"","place":"Волинська","place_address":"","place_city":""}],"name_hidden":false,"last_name_unclear":false,"addresses_raw":"44500, Волинська область (далі приховано)"},"liabilities":{"54":{"sum_comment":"","sum_foreign_comment":"","sum_foreign":"","sum":""},"55":{"sum_units":"","sum_comment":"","sum_foreign_units":"","sum":"","sum_foreign_comment":"","sum_foreign":""},"56":{"sum_comment":"","sum_foreign_comment":"","sum_foreign":"","sum":""},"57":{"sum_comment":"","sum_foreign_comment":"","sum_foreign":"","sum":""},"58":{"sum_comment":"","sum_foreign_comment":"","sum_foreign":"","sum":""},"59":{"sum_comment":"","sum_foreign_comment":"","sum_foreign":"","sum":""},"60":{"sum_comment":"","sum_foreign_comment":"","sum_foreign":"","sum":""},"61":{"sum_units":"","sum_comment":"","sum_foreign_units":"","sum":"","sum_foreign_comment":"","sum_foreign":""},"62":{"sum_comment":"","sum_foreign_comment":"","sum_foreign":"","sum":""},"63":{"sum_comment":"","sum_units":"","sum_foreign":"","sum":"","sum_foreign_comment":""},"64":{"sum_comment":"","sum_units":"","sum_foreign":"","sum":"","sum_foreign_comment":""}},"intro":{"isnotdeclaration":"FALSE","declaration_year":"2013"}}]