[{"id":"vulyk_93_78","ft_src":"1600 куб. см.\nSkoda Octavia\n2007\n2200 куб. см.\n1994\nMercedes-Benz C-Class\n2014\n181024\n181024\n1600 куб. см.\nSkoda Octavia\n2007\n2200 куб. см.\n1994\nMercedes-Benz C-Class\n2014\nГоловатий\nПодружжя\nГоловата (Кіт) З. М., 29. 08. 1979\nДитина\nГоловатий Н. А., 25. 03. 2008\nДитина\nГоловатий П. А., 07. 07. 2010\nГоловатий Андрій Павлович\nАндрій Павлович Головатий\nАндрій Головатий\nГоловатий Андрій Павлович\nГоловатий Андрій Павлович\nЛьвівська область\nЛьвів\n79031\nАндрій\nПавлович\nЛьвівська область\nЗагальний місцевий суд\nсуддя миколаївського районного суду львівської області\n50000\n181024\n181024\n50000\nПодружжя\nГоловата (Кіт) З. М., 29. 08. 1979\nДитина\nГоловатий Н. А., 25. 03. 2008\nДитина\nГоловатий П. А., 07. 07. 2010\nГоловатий\nПавлович\nЛьвівська область\nЛьвів\n79031\nЛьвівська область\nЗагальний місцевий суд\nсуддя миколаївського районного суду львівської області\nГоловатий Андрій Павлович\nГоловатий Андрій Павлович\nАндрій Павлович Головатий\nАндрій Головатий\nГоловатий Андрій Павлович\nАндрій","vehicle":{"35":[{"year_hidden":false,"brand_info":"1600 куб. см.","brand_unclear":false,"sum_rent_comment":"","brand_hidden":false,"year":"2007","sum_comment":"","brand_info_hidden":false,"sum_rent":"","brand":"Skoda Octavia","brand_info_unclear":false,"sum":""},{"sum_comment":"","brand_info":"2200 куб. см.","sum":"","sum_rent_comment":"","year":"1994","brand":"Mercedes-Benz C-Class","sum_rent":""}]},"source":"VULYK","income":{"5":{"family":"","family_comment":"","comment":"","value_hidden":false,"value_unclear":false,"value":"181024","family_hidden":false,"family_unclear":false},"6":{"family_comment":"","family":"","comment":"","value_unclear":false,"family_unclear":false,"value":"181024"},"7":{"source_name_hidden":false,"family_comment":"","comment":"","family":"","comment_hidden":false,"source_name_unclear":false,"value":"","source_name":""},"8":{"family_comment":"","value":"","family":"","comment":""},"9":{"family_comment":"","family":"","comment":"","value_unclear":false,"family_unclear":false,"family_hidden":false,"value":"","family_comment_unclear":false},"10":{"family_comment":"","value":"","family":"","comment":""},"11":{"family_comment":"","value":"","family":"","comment":""},"12":{"family_comment":"","value":"","family":"","comment":""},"13":{"family_comment":"","value":"","family":"","comment":""},"14":{"family_comment":"","value":"","family":"","comment":""},"15":{"family_comment":"","value":"","family":"","comment":""},"16":{"family_comment":"","value":"","family":"","comment":""},"17":{"family_comment":"","value":"","family":"","comment":""},"18":{"family_comment":"","value":"","family":"","comment":""},"19":{"family_comment":"","value":"","family":"","comment":""},"20":{"family_comment":"","family":"","comment":"","value_unclear":false,"value":"","comment_unclear":false,"family_unclear":false,"family_comment_hidden":false,"family_comment_unclear":false}},"general":{"inn":"","addresses":[{"place_city_type_hidden":false,"place_city_type":"Місто","place_city_hidden":false,"place_hidden":false,"place_district":"79031","place_district_hidden":true,"place":"Львівська область","place_address":"","place_address_hidden":true,"place_city":"Львів"}],"last_name":"Головатий","full_name":"Головатий Андрій Павлович","family":[{"inn":"","family_name":"Головата (Кіт) З. М., 29. 08. 1979","relations_hidden":false,"name_unclear":false,"relations":"Подружжя","inn_hidden":true,"name_hidden":false,"relations_other":""},{"inn":"","family_name":"Головатий Н. А., 25. 03. 2008","relations_other":"","name_unclear":false,"inn_hidden":false,"name_hidden":false,"relations":"Дитина"},{"inn":"","family_name":"Головатий П. А., 07. 07. 2010","relations_other":"","name_unclear":false,"inn_hidden":false,"name_hidden":false,"relations":"Дитина"}],"patronymic":"Павлович","inn_hidden":true,"name":"Андрій","post":{"office":"Загальний місцевий суд","post":"суддя миколаївського районного суду львівської області","candidate":"","office_unclear":false,"region":"Львівська область","region_unclear":false,"post_unclear":false},"family_raw":"","full_name_suggest":{"input":["Головатий Андрій Павлович","Андрій Павлович Головатий","Андрій Головатий"],"output":"Головатий Андрій Павлович"}},"liabilities":{"54":{"sum_comment":"","sum_foreign_comment":"","sum_foreign":"","sum_hidden":false,"sum":""},"55":{"sum_comment":"","sum_foreign_comment":"","sum_foreign":"","sum":""},"56":{"sum_comment":"","sum_foreign_comment":"","sum_foreign":"","sum":""},"57":{"sum_comment":"","sum_hidden":false,"sum":"","sum_foreign_comment":"","sum_foreign":"","sum_unclear":false,"sum_comment_hidden":false},"58":{"sum_comment_unclear":false,"sum_comment":"","sum_hidden":false,"sum":"","sum_foreign_comment":"","sum_foreign":"","sum_unclear":false},"59":{"sum_comment":"","sum_foreign_comment":"","sum_foreign":"","sum":"50000"},"60":{"sum_comment":"","sum_foreign_comment":"","sum_foreign":"","sum_hidden":false,"sum":""},"61":{"sum_comment":"","sum_foreign_comment":"","sum_foreign":"","sum":""},"62":{"sum_comment":"","sum_foreign_comment":"","sum_foreign":"","sum":""},"63":{"sum_comment":"","sum_foreign_comment":"","sum_foreign":"","sum":""},"64":{"sum_comment":"","sum_foreign_comment":"","sum_foreign":"","sum":""}},"declaration":{"notfull_lostpages":"","additional_info_text":"","additional_info":"","date":"2015-03-17T00:00:00","notfull":"","url":"http://static.declarations.com.ua/declarations/chosen_ones/judges_batch/3524_holovatyi_andrii_pavlovych.pdf"},"intro":{"isnotdeclaration":"","declaration_year":"2014"}}]