[{"id":"vulyk_92_167","ft_src":"1.6 л\nSkoda Octavia\n2008\n1/2 частки\n65\n2014\n168871\n12180\nЛьвівська комерційна академія\n3252\n184303\n1.6 л\nSkoda Octavia\n2008\n1/2 частки\n65\nПодружжя\nГрабовська О. А., 19. 03. 1988\nДитина\nГрабовська М. В., 20. 05. 2011\nГрабовський Віталій Володимирович\nВіталій Володимирович Грабовський\nВіталій Грабовський\nГрабовський Віталій Володимирович\nГрабовський Віталій Володимирович\nВіталій\nГрабовський\nЗагальний місцевий суд\nсуддя червоноградського міського суду львівської області\nЛьвівська область\nВолодимирович\n3252\nЛьвівська комерційна академія\n168871\n184303\n12180\n2014\nПодружжя\nГрабовська О. А., 19. 03. 1988\nДитина\nГрабовська М. В., 20. 05. 2011\nВолодимирович\nГрабовський\nВіталій\nГрабовський Віталій Володимирович\nВіталій Володимирович Грабовський\nВіталій Грабовський\nГрабовський Віталій Володимирович\nЛьвівська область\nЗагальний місцевий суд\nсуддя червоноградського міського суду львівської області\nГрабовський Віталій Володимирович","estate":{"31":[{"costs_property_comment":"","address":"","space_units":"м²","space_hidden":false,"space_unclear":false,"region_hidden":false,"costs_property":"","space_comment":"1/2 частки","address_hidden":true,"address_unclear":false,"costs_rent_comment":"","space":"65","region":"","costs_rent":""}]},"vehicle":{"35":[{"sum_comment_unclear":false,"brand_info":"1.6 л","sum_rent_comment":"","brand_unclear":false,"brand_hidden":false,"year":"2008","sum_comment":"","brand_info_hidden":false,"sum_rent":"","brand":"Skoda Octavia","year_unclear":false,"brand_info_unclear":false,"sum":""}]},"source":"VULYK","income":{"5":{"family_comment":"","family_hidden":false,"value":"184303","family":"","comment":""},"6":{"family_comment":"","family":"","comment":"","value_unclear":false,"family_hidden":false,"value":"168871"},"7":{"family_comment":"","comment":"","family":"","value_unclear":false,"value":"3252","source_name":"Львівська комерційна академія"},"8":{"family_comment":"","value":"","family":"","comment":""},"9":{"family_comment":"","value":"","family":"","comment":""},"10":{"family_comment":"","comment":"","family":"","family_unclear":false,"comment_unclear":false,"value":"12180","family_comment_unclear":false},"11":{"family_comment":"","value":"","family":"","comment":"","value_unclear":false},"12":{"family_comment":"","value":"","family":"","comment":""},"13":{"family_comment":"","value":"","family":"","comment":""},"14":{"family_comment":"","value":"","family":"","comment":""},"15":{"family_comment":"","comment":"","family":"","family_unclear":false,"comment_unclear":false,"value":""},"16":{"family_comment":"","value":"","family":"","comment":""},"17":{"family_comment":"","value":"","family":"","comment":""},"18":{"family_comment":"","value":"","family_unclear":false,"family":"","comment":""},"19":{"family_comment":"","value":"","family":"","comment":""},"20":{"family_comment":"","value":"","family_unclear":false,"family":"","comment":""}},"general":{"family_raw":"","name":"Віталій","full_name_suggest":{"input":["Грабовський Віталій Володимирович","Віталій Володимирович Грабовський","Віталій Грабовський"],"output":"Грабовський Віталій Володимирович"},"patronymic":"Володимирович","inn_hidden":true,"patronymic_unclear":false,"inn":"","inn_unclear":false,"last_name":"Грабовський","full_name":"Грабовський Віталій Володимирович","family":[{"inn":"","inn_unclear":false,"family_name":"Грабовська О. А., 19. 03. 1988","relations_hidden":false,"name_unclear":false,"relations":"Подружжя","inn_hidden":false,"name_hidden":false,"relations_other":""},{"inn":"","inn_unclear":false,"family_name":"Грабовська М. В., 20. 05. 2011","relations_hidden":false,"name_unclear":false,"relations":"Дитина","inn_hidden":false,"name_hidden":false,"relations_other":""}],"post":{"office":"Загальний місцевий суд","post":"суддя червоноградського міського суду львівської області","office_unclear":false,"region_hidden":false,"region":"Львівська область","office_hidden":false,"post_unclear":false},"addresses":[{"place_city_type":"","place_address_unclear":false,"place_city_type_hidden":false,"place_hidden":true,"place_city_hidden":false,"place_district":"","place_district_hidden":false,"place":"","place_city":"","place_address_hidden":false,"place_address":""}]},"liabilities":{"54":{"sum_comment":"","sum_hidden":false,"sum":"","sum_foreign_comment":"","sum_foreign":"","sum_unclear":false},"55":{"sum_comment":"","sum_foreign_comment":"","sum_foreign":"","sum_unclear":false,"sum":""},"56":{"sum_comment_unclear":false,"sum_comment":"","sum_hidden":false,"sum":"","sum_foreign_comment":"","sum_foreign":"","sum_unclear":false},"57":{"sum_comment":"","sum_hidden":false,"sum":"","sum_foreign_comment":"","sum_foreign":"","sum_comment_hidden":false},"58":{"sum_comment":"","sum_foreign_comment":"","sum_foreign":"","sum":""},"59":{"sum_comment":"","sum_comment_unclear":false,"sum_foreign_comment":"","sum":"","sum_foreign":""},"60":{"sum_comment":"","sum_foreign_comment":"","sum_foreign":"","sum":""},"61":{"sum_comment":"","sum_foreign_comment":"","sum_foreign":"","sum":""},"62":{"sum_comment_unclear":false,"sum_comment":"","sum_hidden":false,"sum":"","sum_foreign_comment":"","sum_foreign":"","sum_unclear":false},"63":{"sum_comment":"","sum_foreign_comment":"","sum_foreign":"","sum":""},"64":{"sum_comment":"","sum_foreign_comment":"","sum_foreign":"","sum":""}},"declaration":{"notfull_lostpages":"","additional_info_text":"","additional_info":"","date":"2015-03-30T00:00:00","notfull":"","url":"http://static.declarations.com.ua/declarations/chosen_ones/judges_batch/3413_hrabovskyi_vitalii_volodymyrovych.pdf"},"intro":{"isnotdeclaration":"","declaration_year":"2014"}}]