[{"id":"vulyk_63_112","ft_src":"1987\nзнята з обліку в зв'язку з вибраковкою 13. 03. 2015 р\nИЖ 2715\nVolkswagen Jetta\nЗнята з обліку 12. 03. 2015 р\n1600\n1990\nЗнята з обліку 03. 09. 2014\n2008\nSkoda Octavia\nПридбана 08. 07. 2014\n1600 куб.см.\n207300\n2013\nSkoda Rapid\nсмт. Ємельчине\n.15\nЖитомирська область\nсмт. Ємельчине\n18\nЖитомирська область\nм. Новоград-Волинський\nЖитомирська область\n48.6\nм. Житомир\nЖитомирська область\n60.7\nсмт. Ємельчине\n78.6\nЖитомирська область\n2014\n41017\n257250\n41017\n289787\nпенсія\n32537\nзнята з обліку в зв'язку з вибраковкою 13. 03. 2015 р\n1987\nИЖ 2715\n1600\nЗнята з обліку 12. 03. 2015 р\n1990\nVolkswagen Jetta\nSkoda Octavia\n2008\nЗнята з обліку 03. 09. 2014\n1600 куб.см.\nSkoda Rapid\n2013\n207300\nПридбана 08. 07. 2014\n.15\nЖитомирська область\nсмт. Ємельчине\n78.6\nЖитомирська область\nсмт. Ємельчине\n48.6\nЖитомирська область\nм. Новоград-Волинський\n60.7\nм. Житомир\nЖитомирська область\n18\nсмт. Ємельчине\nЖитомирська область\nАдамович\nГресько Василь Адамович\nВасиль Адамович Гресько\nВасиль Гресько\nГресько Василь Адамович\nВасиль\nПодружжя\nГресько В. С. 09. 12. 1965\nГресько Василь Адамович\nЗагальний місцевий суд\nЖитомирська область\nсуддя районного суду\nГресько\nСМТ\nЄмільчине\nЖитомирська область\nЄмільчинський\n32708\n12520\n6660\n10247\n257250\n41017\nпенсія\n32537\n289787\n41017\n2014\n10247\n32708\n12520\n6660\nПодружжя\nГресько В. С. 09. 12. 1965\nАдамович\nГресько\nГресько Василь Адамович\nВасиль Адамович Гресько\nВасиль Гресько\nГресько Василь Адамович\nВасиль\nЖитомирська область\nЄмільчине\nЄмільчинський\nСМТ\nЖитомирська область\nсуддя районного суду\nЗагальний місцевий суд\nГресько Василь Адамович","estate":{"23":[{"costs":"","address":"смт. Ємельчине","space_units":"га","costs_hidden":false,"space_hidden":false,"space_unclear":false,"region_hidden":false,"space_units_unclear":false,"costs_comment":"","address_hidden":false,"costs_rent_hidden":false,"space_comment":"","costs_rent_comment":"","space":".15","region":"Житомирська область","space_units_hidden":false,"costs_rent":""}],"24":[{"address":"смт. Ємельчине","space_units":"м²","costs_comment":"","space_unclear":false,"region_hidden":false,"costs_rent_comment":"","space_comment":"","address_hidden":false,"costs":"","address_unclear":false,"space_units_unclear":false,"space":"78.6","region_unclear":false,"region":"Житомирська область","costs_rent":""}],"27":[{"address":"смт. Ємельчине","space_units":"м²","costs_hidden":false,"costs_rent_hidden":false,"space_unclear":false,"region_hidden":false,"costs_comment":"","costs_rent_comment_hidden":false,"address_hidden":false,"costs":"","address_unclear":false,"space_comment":"","costs_rent_comment":"","space":"18","region":"Житомирська область","costs_comment_hidden":false,"costs_rent":""}],"31":[{"costs_property_comment":"","address":"м. Новоград-Волинський","space_units":"м²","space_hidden":false,"region":"Житомирська область","costs_rent_comment_hidden":false,"costs_property":"","space_comment":"","space_comment_unclear":false,"space_units_unclear":false,"costs_rent_hidden":false,"costs_property_hidden":false,"space_unclear":false,"address_hidden":false,"costs_rent_comment":"","space":"48.6","costs_property_comment_hidden":false,"region_hidden":false,"costs_rent":""},{"costs_property_comment":"","address":"м. Житомир","space_units":"м²","space_comment":"","region_hidden":false,"costs_property":"","region":"Житомирська область","address_hidden":false,"space_comment_unclear":true,"costs_rent_comment":"","space":"60.7","costs_rent":""}]},"vehicle":{"35":[{"sum_comment":"","brand_info":"","brand_unclear":false,"sum_rent_comment":"знята з обліку в зв'язку з вибраковкою 13. 03. 2015 р","year":"1987","brand":"ИЖ 2715","sum_rent":"","brand_info_unclear":false,"sum":""},{"sum_comment":"","brand_info_hidden":false,"sum_rent":"","sum":"","brand_unclear":false,"brand_hidden":false,"brand":"Volkswagen Jetta","brand_info":"1600","sum_rent_comment":"Знята з обліку 12. 03. 2015 р","year":"1990"},{"sum_comment":"Знята з обліку 03. 09. 2014","brand_info":"","sum":"","sum_rent_comment":"","year":"2008","brand":"Skoda Octavia","sum_rent":""},{"sum_comment":"Придбана 08. 07. 2014","brand_info":"1600 куб.см.","sum":"207300","sum_rent_comment":"","year":"2013","brand":"Skoda Rapid","sum_rent":""}]},"source":"VULYK","income":{"5":{"family":"41017","family_comment":"","comment":"","value_hidden":false,"value_unclear":false,"comment_hidden":false,"family_hidden":false,"family_unclear":false,"value":"289787"},"6":{"family_comment":"","family":"41017","comment":"","value_unclear":false,"family_unclear":false,"comment_unclear":false,"value":"257250","family_hidden":false},"7":{"source_name_hidden":false,"family_comment":"","family":"","value_hidden":false,"comment":"","source_name_unclear":false,"value":"","source_name":""},"8":{"family":"","family_comment":"","comment":"","value_hidden":false,"family_hidden":false,"value":""},"9":{"family":"","family_comment":"","comment":"","value_hidden":false,"value_unclear":false,"value":"","family_hidden":false,"family_unclear":false},"10":{"family_comment":"","value":"","family":"","comment":""},"11":{"family_comment":"","value":"","family":"","comment":""},"12":{"family_comment":"","value":"","family":"","comment":""},"13":{"family_comment":"","value":"","family":"","comment":""},"14":{"family_comment":"","value":"","family":"","comment":""},"15":{"family_comment":"","value":"","family":"","comment":""},"16":{"family_comment":"","family":"","comment":"","value_unclear":false,"family_unclear":false,"value":""},"17":{"family_comment":"","value":"","family":"","comment":""},"18":{"family_comment":"","value":"","family":"","comment":""},"19":{"family_comment":"","comment_unclear":false,"value":"","family":"","comment":""},"20":{"family_unclear":false,"family_comment":"","comment":"пенсія","family":"","value_unclear":false,"value_hidden":false,"comment_hidden":false,"comment_unclear":false,"value":"32537","family_hidden":false,"family_comment_unclear":false}},"general":{"family":[{"inn":"","inn_unclear":false,"family_name":"Гресько В. С. 09. 12. 1965","relations_hidden":false,"relations_unclear":false,"name_unclear":false,"relations":"Подружжя","inn_hidden":false,"name_hidden":false,"relations_other":""}],"family_raw":"","name":"Василь","full_name_suggest":{"input":["Гресько Василь Адамович","Василь Адамович Гресько","Василь Гресько"],"output":"Гресько Василь Адамович"},"name_unclear":false,"patronymic":"Адамович","inn_hidden":false,"patronymic_unclear":false,"last_name_hidden":false,"inn":"","inn_unclear":false,"last_name":"Гресько","full_name":"Гресько Василь Адамович","post":{"office":"Загальний місцевий суд","post":"суддя районного суду","office_unclear":false,"office_hidden":false,"region":"Житомирська область","region_hidden":false,"post_unclear":false,"region_unclear":false},"addresses":[{"place_city_type_hidden":false,"place_district_hidden":false,"place_address_unclear":false,"place":"Житомирська область","place_city":"Ємільчине","place_unclear":false,"place_city_type_unclear":false,"place_city_type":"СМТ","place_city_hidden":false,"place_city_unclear":false,"place_district":"Ємільчинський","place_district_unclear":false,"place_address":"","place_address_hidden":false,"place_hidden":false}],"name_hidden":false,"last_name_unclear":true},"liabilities":{"54":{"sum_comment":"","sum_foreign_comment":"","sum_foreign":"","sum_unclear":false,"sum":""},"55":{"sum_comment":"","sum_foreign_comment":"","sum_foreign":"","sum":""},"56":{"sum_comment":"","sum_foreign_comment":"","sum_foreign":"","sum_unclear":false,"sum":"12520"},"57":{"sum_comment":"","sum":"32708","sum_foreign_comment":"","sum_foreign":"","sum_unclear":false,"sum_comment_hidden":false},"58":{"sum_comment":"","sum_foreign_comment":"","sum_foreign":"","sum":"10247","sum_comment_hidden":false},"59":{"sum_comment":"","sum_foreign_comment":"","sum_foreign":"","sum":""},"60":{"sum_comment":"","sum_comment_unclear":false,"sum_foreign_comment":"","sum":"","sum_foreign":""},"61":{"sum_comment":"","sum_foreign_comment":"","sum_foreign":"","sum_unclear":false,"sum":""},"62":{"sum_comment":"","sum_foreign_comment":"","sum_foreign":"","sum_unclear":false,"sum":"6660"},"63":{"sum_comment":"","sum_hidden":false,"sum":"","sum_foreign_comment":"","sum_foreign":"","sum_unclear":false,"sum_comment_hidden":false},"64":{"sum_comment":"","sum_foreign_comment":"","sum_foreign":"","sum":"","sum_comment_hidden":false}},"declaration":{"notfull_lostpages":"","additional_info_text":"","additional_info":"","date":"2015-03-18T00:00:00","notfull":"","url":"http://static.declarations.com.ua/declarations/chosen_ones/mega_batch/hresko_vasyl_adamovych.pdf"},"intro":{"isnotdeclaration":"","declaration_year_unclear":false,"declaration_year":"2014"}}]