[{"id":"vulyk_85_70","ft_src":"162\n2870\n3200\n260.7\n2014\n48591\n260686\n10\n27\n49516\n267341\n915\n6628\n162\n2870\n3200\n260.7\nХоминець Марія Миколаївна\nМарія Миколаївна Хоминець\nМарія Хоминець\nХоминець Марія Миколаївна\nМарія\nПодружжя\nХоминець Роман Васильович 04. 10. 1960\nДитина\nХоминець Андрій Романович 24. 11. 1984\nДитина\nХоминець Христина Романівна 26. 05. 1987\nХоминець Христина Ігорівна 28. 06. 1991\nІнше\nневістка\nХоминець Марія Миколаївна\nХоминець\nЗагальний місцевий суд\nсуддя тисменицького районного суду івано-франківської області\nІвано-Франківська область\nМиколаївна\n11042\n13750\n2084\n765\n260686\n48591\n6628\n915\n267341\n49516\n27\n10\n2014\n2084\n13750\n11042\n765\nХоминець Роман Васильович 04. 10. 1960\nПодружжя\nХоминець Андрій Романович 24. 11. 1984\nДитина\nХоминець Христина Романівна 26. 05. 1987\nДитина\nІнше\nневістка\nХоминець Христина Ігорівна 28. 06. 1991\nМиколаївна\nХоминець\nМарія\nХоминець Марія Миколаївна\nМарія Миколаївна Хоминець\nМарія Хоминець\nХоминець Марія Миколаївна\nсуддя тисменицького районного суду івано-франківської області\nІвано-Франківська область\nЗагальний місцевий суд\nХоминець Марія Миколаївна","estate":{"23":[{"costs_unclear":false,"address":"","space_units":"м²","costs_comment":"","space_unclear":false,"region_hidden":true,"space_comment":"","address_hidden":true,"costs":"","costs_rent_comment_unclear":false,"costs_comment_unclear":false,"costs_rent_comment":"","space":"2870","region":"","costs_rent":""}],"24":[{"address":"","space_units":"м²","space_hidden":false,"space_unclear":false,"region_hidden":true,"costs_comment":"","space_comment":"","address_hidden":true,"space":"260.7","costs_rent_comment":"","costs":"","region":"","costs_rent":""}],"29":[{"costs_property_comment":"","address":"","space_units":"м²","space_unclear":false,"region_hidden":true,"costs_property":"","space_comment":"","address_hidden":true,"costs_rent_comment":"","space":"3200","region":"","costs_rent":""}]},"source":"VULYK","income":{"5":{"family_comment":"","family":"49516","comment":"","value_unclear":false,"family_unclear":false,"value":"267341"},"6":{"family_comment":"","family":"48591","comment":"","value_unclear":false,"family_unclear":false,"value":"260686"},"7":{"family":"","family_comment":"","value":"","comment":"","source_name":""},"8":{"family_comment":"","value":"","family":"","comment":""},"9":{"family_comment":"","value":"27","family":"10","comment":"","value_unclear":false},"10":{"family_comment":"","value":"","family":"","comment":"","value_unclear":false},"11":{"family_comment":"","value":"","family":"","comment":""},"12":{"family_comment":"","value":"","family":"","comment":""},"13":{"family_comment":"","value":"","family":"","comment":"","value_unclear":false},"14":{"family_comment":"","value":"","family":"","comment":""},"15":{"family_comment":"","value":"","family":"","comment":""},"16":{"family_comment":"","value":"","family":"","comment":""},"17":{"family_comment":"","value":"","family":"","comment":""},"18":{"family_comment":"","value":"","family":"","comment":""},"19":{"family_comment":"","value":"","family":"","comment":""},"20":{"family_comment":"","value":"6628","family_unclear":false,"family":"915","comment":""}},"banks":{"51":[{"sum_units":"UAH","sum_comment":"","sum_foreign_units":"UAH","sum":"162","sum_foreign_comment":"","sum_foreign":"","sum_comment_hidden":false}]},"declaration":{"notfull_lostpages":"","additional_info_text":"","additional_info":"","date":"2015-03-31T00:00:00","notfull":"","url":"http://static.declarations.com.ua/declarations/chosen_ones/judges_batch/2673_khomynets_mariia_mykolaivna.pdf"},"general":{"family_raw":"","name":"Марія","full_name_suggest":{"input":["Хоминець Марія Миколаївна","Марія Миколаївна Хоминець","Марія Хоминець"],"output":"Хоминець Марія Миколаївна"},"patronymic":"Миколаївна","inn_hidden":true,"last_name_hidden":false,"inn":"","addresses":[{"place_city_type_hidden":false,"place_city_type":"","place_city_hidden":true,"place_hidden":true,"place_district":"","place_district_hidden":true,"place":"","place_city":"","place_address_hidden":true,"place_address":""}],"last_name":"Хоминець","full_name":"Хоминець Марія Миколаївна","family":[{"inn":"","family_name":"Хоминець Роман Васильович 04. 10. 1960","relations_other":"","relations_hidden":false,"relations_unclear":false,"name_unclear":false,"inn_hidden":true,"name_hidden":false,"relations":"Подружжя"},{"inn":"","family_name":"Хоминець Андрій Романович 24. 11. 1984","relations_other":"","name_unclear":false,"inn_hidden":false,"name_hidden":false,"relations":"Дитина"},{"inn":"","family_name":"Хоминець Христина Романівна 26. 05. 1987","relations_other":"","name_unclear":false,"inn_hidden":false,"relations":"Дитина"},{"inn":"","family_name":"Хоминець Христина Ігорівна 28. 06. 1991","relations_other":"невістка","relations":"Інше"}],"post":{"post_hidden":false,"office":"Загальний місцевий суд","region":"Івано-Франківська область","post_unclear":false,"post":"суддя тисменицького районного суду івано-франківської області"},"last_name_unclear":false},"liabilities":{"54":{"sum_comment":"","sum_comment_unclear":false,"sum_foreign_comment":"","sum":"","sum_foreign":""},"55":{"sum_comment":"","sum_foreign_comment":"","sum_foreign":"","sum":""},"56":{"sum_comment":"","sum_foreign_comment":"","sum_foreign":"","sum_unclear":false,"sum":""},"57":{"sum_comment":"","sum_foreign_comment":"","sum_foreign":"","sum":"13750"},"58":{"sum_comment":"","sum_foreign_comment":"","sum_foreign":"","sum":"2084","sum_comment_hidden":false},"59":{"sum_comment":"","sum_foreign_comment":"","sum_foreign":"","sum":""},"60":{"sum_comment":"","sum_foreign_comment":"","sum_foreign":"","sum":""},"61":{"sum_comment":"","sum_foreign_comment":"","sum_foreign":"","sum":""},"62":{"sum_comment":"","sum_foreign_comment":"","sum_foreign":"","sum_unclear":false,"sum":""},"63":{"sum_comment":"","sum_foreign_comment":"","sum_foreign":"","sum_unclear":false,"sum":"11042"},"64":{"sum_comment":"","sum_foreign_comment":"","sum_foreign":"","sum":"765"}},"intro":{"isnotdeclaration":"","declaration_year":"2014"}}]