[{"id":"vulyk_99_14","ft_src":"1998\nпричіп легковий\n2006\nВАЗ 21124\n1.6 л\nмопед, 49 к. с\nViper\nспадщина\n.15\nпередано у власність безкоштовно\n.1613\nспадщина, гараж металевий\n24\nспадщина\n89.1\nдоговір приватизації від 07. 11. 2001\n1/2\n28.9\n2015\n64242\n189192\n12180\n64242\n201372\n1.6 л\nВАЗ 21124\n2006\nпричіп легковий\n1998\nмопед, 49 к. с\nViper\n2015\nЄременко\nЄременко Володимир Максимович\nВолодимир Максимович Єременко\nВолодимир Єременко\nЄременко Володимир Максимович\nВолодимир\nМаксимович\nЄременко Володимир Максимович\nЗагальний місцевий суд\nсуддя баришівського районного суду київської області\nКиївська область\nПодружжя\nЄременко С. А., 11. 01. 1969\n189192\n64242\n201372\n64242\n12180\n.15\nспадщина\n.1613\nпередано у власність безкоштовно\nспадщина\n89.1\n24\nспадщина, гараж металевий\n28.9\n1/2\nдоговір приватизації від 07. 11. 2001\nЄременко С. А., 11. 01. 1969\nПодружжя\nМаксимович\nЄременко\nсуддя баришівського районного суду київської області\nКиївська область\nЗагальний місцевий суд\nЄременко Володимир Максимович\nЄременко Володимир Максимович\nВолодимир Максимович Єременко\nВолодимир Єременко\nЄременко Володимир Максимович\nВолодимир","estate":{"23":[{"address":"","space_units":"га","costs_comment":"спадщина","space_unclear":false,"region_hidden":true,"space_comment":"","address_hidden":false,"costs":"","costs_rent_comment":"","space":".15","region":"","costs_rent":""},{"address":"","space_units":"га","space_unclear":false,"costs_comment":"","space_comment":"передано у власність безкоштовно","address_hidden":false,"space":".1613","address_unclear":false,"costs_comment_unclear":true,"costs_rent_comment":"","costs":"","region":"","costs_rent":""}],"24":[{"costs":"","address":"","space_units":"м²","costs_rent_comment":"","space":"89.1","space_comment":"","region_hidden":true,"costs_comment":"спадщина","region":"","address_hidden":false,"costs_rent":""}],"25":[{"address":"","space_units":"м²","space_hidden":false,"space_unclear":false,"region_hidden":true,"costs_comment":"договір приватизації від 07. 11. 2001","space_comment":"1/2","address_hidden":false,"space":"28.9","costs_rent_comment":"","costs":"","region":"","costs_rent":""}],"27":[{"costs":"","address":"","space_units":"м²","costs_rent_comment":"","space":"24","space_comment":"спадщина, гараж металевий","region_hidden":true,"costs_comment":"","region":"","address_hidden":false,"costs_rent":""}]},"vehicle":{"35":[{"sum_comment":"","brand_info":"1.6 л","brand_unclear":false,"sum_rent_comment":"","year":"2006","brand":"ВАЗ 21124","sum_rent":"","brand_info_unclear":false,"sum":""}],"39":[{"sum_comment":"","brand_info":"","sum":"","brand_unclear":false,"year":"1998","brand":"причіп легковий","sum_rent":"","sum_rent_comment":""}],"44":[{"sum_comment":"","brand_info":"мопед, 49 к. с","sum":"","sum_rent_comment":"","year":"","brand":"Viper","sum_rent":""}]},"source":"VULYK","income":{"5":{"family_comment":"","family":"64242","comment":"","value_unclear":false,"family_unclear":false,"value":"201372"},"6":{"family_comment":"","family":"64242","comment":"","value_unclear":false,"family_unclear":false,"value":"189192"},"7":{"family":"","family_comment":"","value":"","comment":"","source_name":""},"8":{"family_comment":"","value":"","family":"","comment":""},"9":{"family_comment":"","value":"","family":"","comment":""},"10":{"family_comment":"","value":"12180","family":"","comment":""},"11":{"family_comment":"","value":"","family":"","comment":""},"12":{"family_comment":"","value":"","family":"","comment":""},"13":{"family_comment":"","value":"","family":"","comment":""},"14":{"family_comment":"","value":"","family":"","comment":""},"15":{"family_comment":"","value":"","family":"","comment":"","value_unclear":false},"16":{"family_comment":"","value":"","family":"","comment":""},"17":{"family_comment":"","value":"","family":"","comment":""},"18":{"family_comment":"","value":"","family":"","comment":""},"19":{"family_comment":"","value":"","family":"","comment":""},"20":{"family_comment":"","family":"","comment":"","value_unclear":false,"family_unclear":false,"value":"","family_comment_unclear":false}},"general":{"inn":"","addresses":[{"place_city_type_hidden":false,"place_city_type":"","place_city_hidden":true,"place_hidden":true,"place_district":"","place_district_hidden":false,"place":"","place_address":"","place_address_hidden":true,"place_city":""}],"last_name":"Єременко","full_name":"Єременко Володимир Максимович","family":[{"inn":"","family_name":"Єременко С. А., 11. 01. 1969","name_unclear":false,"inn_hidden":true,"name_hidden":false,"relations":"Подружжя"}],"patronymic":"Максимович","inn_hidden":true,"name":"Володимир","post":{"office":"Загальний місцевий суд","region":"Київська область","post_unclear":false,"post":"суддя баришівського районного суду київської області"},"family_raw":"","full_name_suggest":{"input":["Єременко Володимир Максимович","Володимир Максимович Єременко","Володимир Єременко"],"output":"Єременко Володимир Максимович"}},"liabilities":{"54":{"sum_comment_unclear":false,"sum_comment":"","sum":"","sum_foreign_comment":"","sum_foreign":"","sum_comment_hidden":false},"55":{"sum_comment":"","sum_foreign_comment":"","sum_foreign":"","sum":""},"56":{"sum_comment":"","sum_foreign_comment":"","sum_foreign":"","sum":""},"57":{"sum_comment":"","sum_foreign_comment":"","sum_foreign":"","sum":"","sum_comment_hidden":false},"58":{"sum_comment":"","sum_foreign_comment":"","sum_foreign":"","sum":"","sum_comment_hidden":false},"59":{"sum_comment":"","sum":"","sum_foreign_comment":"","sum_foreign":"","sum_unclear":false,"sum_comment_hidden":false},"60":{"sum_comment":"","sum_foreign_comment":"","sum_foreign":"","sum":"","sum_comment_hidden":false},"61":{"sum_comment":"","sum_foreign_comment":"","sum_foreign":"","sum":""},"62":{"sum_comment":"","sum_foreign_comment":"","sum_foreign":"","sum":""},"63":{"sum_comment":"","sum_foreign_comment":"","sum_foreign":"","sum":"","sum_comment_hidden":false},"64":{"sum_comment":"","sum_foreign_comment":"","sum_foreign":"","sum":"","sum_comment_hidden":false}},"declaration":{"notfull_lostpages":"","date":"2016-02-29T00:00:00","notfull":"","url":"http://static.declarations.com.ua/declarations/chosen_ones/judges_batch/563_ieremenko_volodymyr_maksymovych_2015.pdf"},"intro":{"declaration_year":"2015"}},{"id":"vulyk_100_72","ft_src":"причіп до легкового автомобіля\n1998\nоб'єм двиг. 1.6\nВАЗ 21124\n2006\nмопед, 49 м. к\nViper\nспадщина\nспадщина\n.15\nпередано у власність безкоштовно\n.1613\nгараж металевий, спадщина\n24\nпо договору купівлі-продажу від 07. 11. 2001\n1/2 частина однокімнатної квартири\n28.9\nспадщина\nспадщина\n89.1\n2014\n51794\n186696\n12180\n51794\n198876\nоб'єм двиг. 1.6\nВАЗ 21124\n2006\nпричіп до легкового автомобіля\n1998\nмопед, 49 м. к\nViper\n.15\nспадщина\nспадщина\n.1613\nпередано у власність безкоштовно\n89.1\nспадщина\nспадщина\n24\nгараж металевий, спадщина\n28.9\n1/2 частина однокімнатної квартири\nпо договору купівлі-продажу від 07. 11. 2001\nПодружжя\nЄременко С. А. 11. 01. 1964\nМаксимович\nЄременко\nЄременко Володимир Максимович\nВолодимир Максимович Єременко\nВолодимир Єременко\nЄременко Володимир Максимович\nЄременко Володимир Максимович\nВолодимир\nЗагальний місцевий суд\nКиївська область\nсуддя баришівського районного суду київської області\n186696\n51794\n198876\n51794\n12180\n2014\nЄременко С. А. 11. 01. 1964\nПодружжя\nМаксимович\nЄременко\nКиївська область\nЗагальний місцевий суд\nсуддя баришівського районного суду київської області\nЄременко Володимир Максимович\nЄременко Володимир Максимович\nВолодимир Максимович Єременко\nВолодимир Єременко\nЄременко Володимир Максимович\nВолодимир","estate":{"23":[{"address":"","space_units":"га","costs_comment":"спадщина","space_unclear":false,"region_hidden":true,"space_comment":"спадщина","address_hidden":false,"costs":"","address_unclear":false,"space_comment_unclear":false,"costs_comment_unclear":false,"costs_rent_comment":"","space":".15","region":"","costs_rent":""},{"costs":"","address":"","space_units":"га","costs_rent_comment":"","space":".1613","space_unclear":false,"space_comment":"передано у власність безкоштовно","costs_comment":"","region":"","costs_rent":""}],"24":[{"address":"","space_units":"м²","costs_comment":"спадщина","space_unclear":false,"region_hidden":true,"space_comment":"спадщина","address_hidden":false,"space":"89.1","space_comment_unclear":false,"costs_rent_comment":"","costs":"","region":"","costs_rent":""}],"25":[{"address":"","space_units":"м²","costs_comment":"по договору купівлі-продажу від 07. 11. 2001","space_unclear":false,"region_hidden":true,"space_comment":"1/2 частина однокімнатної квартири","address_hidden":false,"costs":"","address_unclear":false,"space_comment_unclear":false,"costs_comment_unclear":false,"costs_rent_comment":"","space":"28.9","region":"","costs_rent":""}],"27":[{"address":"","space_units":"м²","costs_comment":"","space_unclear":false,"region_hidden":true,"space_comment":"гараж металевий, спадщина","address_hidden":false,"costs":"","address_unclear":false,"costs_rent_comment":"","space":"24","region":"","costs_rent":""}],"28":[{"costs":"","address":"","space_units":"м²","costs_rent_comment":"","space":"","space_comment":"","region_hidden":true,"costs_comment":"","region":"","address_hidden":false,"costs_rent":""}]},"vehicle":{"35":[{"brand_info":"об'єм двиг. 1.6","sum_rent_comment":"","brand_unclear":false,"sum_rent_comment_unclear":false,"brand_hidden":false,"sum_comment":"","brand_info_hidden":false,"sum_rent":"","brand":"ВАЗ 21124","brand_info_unclear":false,"year":"2006","sum":""}],"39":[{"sum_comment":"","brand_unclear":false,"sum_rent":"","sum":"","sum_rent_comment":"","brand_hidden":true,"brand":"","brand_info":"причіп до легкового автомобіля","year":"1998"}],"44":[{"sum_comment":"","brand_info":"мопед, 49 м. к","sum":"","sum_rent_comment":"","year":"","brand":"Viper","sum_rent":"","brand_info_unclear":true}]},"source":"VULYK","income":{"5":{"family_comment":"","family":"51794","comment":"","value_unclear":false,"family_unclear":false,"value":"198876"},"6":{"family_comment":"","value":"186696","family":"51794","comment":"","value_unclear":false},"7":{"family_comment":"","comment":"","family":"","value_unclear":false,"value":"","source_name":""},"8":{"family_comment":"","value":"","family":"","comment":""},"9":{"family_comment":"","family":"","comment":"","value_unclear":false,"family_unclear":false,"value":""},"10":{"family_comment":"","comment_unclear":false,"value":"12180","family":"","comment":""},"11":{"family_comment":"","value":"","family":"","comment":""},"12":{"family_comment":"","value":"","family":"","comment":""},"13":{"family_comment":"","value":"","family":"","comment":"","value_unclear":false},"14":{"family_comment":"","value":"","family":"","comment":""},"15":{"family_comment":"","value":"","family":"","comment":""},"16":{"family_comment":"","value":"","family_unclear":false,"family":"","comment":""},"17":{"family_comment":"","value":"","family_unclear":false,"family":"","comment":""},"18":{"family_comment":"","value":"","family":"","comment":""},"19":{"family_comment":"","value":"","family":"","comment":""},"20":{"family":"","family_comment":"","comment":"","value_hidden":false,"value_unclear":false,"value":"","comment_unclear":false,"family_unclear":false,"family_hidden":false}},"general":{"inn":"","addresses":[{"place_city_type":"","place_city_type_hidden":false,"place_hidden":true,"place_city_hidden":true,"place_district_hidden":false,"place_district":"","place_city_unclear":false,"place":"","place_city":"","place_address_hidden":true,"place_address":""}],"last_name":"Єременко","full_name":"Єременко Володимир Максимович","family":[{"inn":"","family_name":"Єременко С. А. 11. 01. 1964","name_unclear":false,"inn_hidden":true,"name_hidden":false,"relations":"Подружжя"}],"patronymic":"Максимович","inn_hidden":true,"name":"Володимир","post":{"post_hidden":false,"office":"Загальний місцевий суд","post":"суддя баришівського районного суду київської області","office_unclear":false,"region_unclear":false,"region":"Київська область","post_unclear":false},"family_raw":"","full_name_suggest":{"input":["Єременко Володимир Максимович","Володимир Максимович Єременко","Володимир Єременко"],"output":"Єременко Володимир Максимович"}},"liabilities":{"54":{"sum_comment":"","sum":"","sum_foreign_comment":"","sum_foreign":"","sum_unclear":false,"sum_comment_hidden":false},"55":{"sum_comment":"","sum_foreign_comment":"","sum_foreign":"","sum":""},"56":{"sum_comment":"","sum_foreign_comment":"","sum_foreign":"","sum_unclear":false,"sum":""},"57":{"sum_comment_unclear":false,"sum_comment":"","sum":"","sum_foreign_comment":"","sum_foreign":"","sum_unclear":false,"sum_comment_hidden":false},"58":{"sum_comment":"","sum":"","sum_foreign_comment":"","sum_foreign":"","sum_unclear":false,"sum_comment_hidden":false},"59":{"sum_comment":"","sum_foreign_comment":"","sum_foreign":"","sum":""},"60":{"sum_comment":"","sum_foreign_comment":"","sum_foreign":"","sum":"","sum_comment_hidden":false},"61":{"sum_comment":"","sum_foreign_comment":"","sum_foreign":"","sum":""},"62":{"sum_comment":"","sum_foreign_comment":"","sum_foreign":"","sum_unclear":false,"sum":""},"63":{"sum_comment":"","sum_foreign_comment":"","sum_foreign":"","sum":"","sum_comment_hidden":false},"64":{"sum_comment":"","sum_foreign_comment":"","sum_foreign":"","sum":"","sum_comment_hidden":false}},"declaration":{"notfull_lostpages":"","additional_info_text":"","additional_info":"","date":"2015-02-23T00:00:00","notfull":"","url":"http://static.declarations.com.ua/declarations/chosen_ones/judges_batch/4271_ieremenko_volodymyr_maksymovych.pdf"},"intro":{"declaration_year":"2014"}}]