[{"id":"vulyk_97_182","ft_src":"об'єм циліндрів двигуна 1.332\nMitsubishi Colt\n2006\n48.1\nм. Дніпродзержинськ\nДніпропетровська область\n2014\n202629.42\n12180\n219212.88\n4403.46\nоб'єм циліндрів двигуна 1.332\nMitsubishi Colt\n2006\n2014\nІвченко Тетяна Павлівна\nТетяна Павлівна Івченко\nТетяна Івченко\nІвченко Тетяна Павлівна\nТетяна\nДитина\nІвченко І. П. 31. 03. 08\nІвченко Тетяна Павлівна\nІвченко\nЗагальний місцевий суд\nДніпропетровська область\nсуддя заводського районного суду м. дніпродзержинська дніпропетровської області\nПавлівна\nДніпропетровська область\n400.48\nСТ Група ТАС автоцивільний поліс-330,48, ПАТ СК Провідна подорожуючих 70,00\n202629.42\n4403.46\n219212.88\n12180\n48.1\nм. Дніпродзержинськ\nДніпропетровська область\nСТ Група ТАС автоцивільний поліс-330,48, ПАТ СК Провідна подорожуючих 70,00\n400.48\nДитина\nІвченко І. П. 31. 03. 08\nПавлівна\nІвченко\nТетяна\nІвченко Тетяна Павлівна\nТетяна Павлівна Івченко\nТетяна Івченко\nІвченко Тетяна Павлівна\nДніпропетровська область\nДніпропетровська область\nЗагальний місцевий суд\nсуддя заводського районного суду м. дніпродзержинська дніпропетровської області\nІвченко Тетяна Павлівна","estate":{"25":[{"address":"м. Дніпродзержинськ","space_units":"м²","space_hidden":false,"space_unclear":false,"region_hidden":false,"costs_rent_comment":"","space_comment":"","address_hidden":true,"space_comment_hidden":false,"costs":"","space_comment_unclear":false,"costs_comment":"","space":"48.1","region_unclear":false,"region":"Дніпропетровська область","costs_rent":""}]},"vehicle":{"35":[{"year_hidden":false,"brand_info":"об'єм циліндрів двигуна 1.332","brand_unclear":false,"sum_rent_comment":"","brand_hidden":false,"year":"2006","sum_comment":"","brand_info_hidden":false,"sum_rent":"","brand":"Mitsubishi Colt","brand_info_unclear":false,"sum":""}]},"source":"VULYK","income":{"5":{"family_comment":"","value":"219212.88","family":"","comment":""},"6":{"family_comment":"","family":"","comment":"","value_unclear":false,"family_unclear":false,"comment_hidden":false,"value":"202629.42"},"7":{"family":"","family_comment":"","value":"","comment":"","source_name":""},"8":{"family_comment":"","value":"","family":"","comment":""},"9":{"family_comment":"","value":"","family_unclear":false,"family":"","comment":""},"10":{"family_comment":"","value":"12180","family":"","comment":"","value_unclear":true},"11":{"family_comment":"","value":"","family":"","comment":""},"12":{"family_comment":"","value":"","family":"","comment":""},"13":{"family_comment":"","value":"","family":"","comment":""},"14":{"family_comment":"","value":"","family":"","comment":""},"15":{"family_comment":"","value":"","family":"","comment":""},"16":{"family_comment":"","value":"","family":"","comment":""},"17":{"family_comment":"","value":"","family":"","comment":""},"18":{"family_comment":"","value":"","family":"","comment":""},"19":{"family_comment":"","value":"","family":"","comment":""},"20":{"family_comment":"","comment":"","family":"","value_unclear":false,"comment_unclear":false,"value":"4403.46","family_hidden":false,"family_comment_unclear":false}},"general":{"family":[{"inn":"","family_name":"Івченко І. П. 31. 03. 08","relations_other":"","name_unclear":false,"inn_hidden":true,"name_hidden":false,"relations":"Дитина"}],"family_raw":"","name":"Тетяна","full_name_suggest":{"input":["Івченко Тетяна Павлівна","Тетяна Павлівна Івченко","Тетяна Івченко"],"output":"Івченко Тетяна Павлівна"},"patronymic":"Павлівна","inn_hidden":true,"addresses":[{"place_city_type":"","place_city_type_hidden":false,"place_hidden":false,"place_city_hidden":true,"place_district_hidden":false,"place_district":"","place_city_unclear":false,"place":"Дніпропетровська область","place_city":"","place_address_hidden":true,"place_address":""}],"last_name_hidden":false,"patronymic_hidden":false,"inn":"","inn_unclear":false,"last_name":"Івченко","full_name":"Івченко Тетяна Павлівна","post":{"post_hidden":false,"office":"Загальний місцевий суд","post":"суддя заводського районного суду м. дніпродзержинська дніпропетровської області","office_unclear":false,"region_unclear":false,"region":"Дніпропетровська область"},"name_hidden":false},"liabilities":{"54":{"sum_comment_unclear":false,"sum_comment":"СТ Група ТАС автоцивільний поліс-330,48, ПАТ СК Провідна подорожуючих 70,00","sum_hidden":false,"sum":"400.48","sum_foreign_comment":"","sum_foreign":"","sum_unclear":false,"sum_comment_hidden":false},"55":{"sum_comment":"","sum_foreign_comment":"","sum_foreign":"","sum":""},"56":{"sum_comment":"","sum_foreign_comment":"","sum_foreign":"","sum":""},"57":{"sum_comment_unclear":false,"sum_comment":"","sum_hidden":false,"sum":"","sum_foreign_comment":"","sum_foreign":"","sum_unclear":false,"sum_comment_hidden":false},"58":{"sum_comment_unclear":false,"sum_comment":"","sum_hidden":false,"sum":"","sum_foreign_comment":"","sum_foreign":"","sum_unclear":false,"sum_comment_hidden":false},"59":{"sum_comment":"","sum_foreign_comment":"","sum_foreign":"","sum":""},"60":{"sum_comment_unclear":false,"sum_comment":"","sum_hidden":false,"sum":"","sum_foreign_comment":"","sum_foreign":"","sum_comment_hidden":false},"61":{"sum_comment":"","sum_foreign_comment":"","sum_foreign":"","sum":""},"62":{"sum_comment":"","sum_foreign_comment":"","sum_foreign":"","sum_unclear":false,"sum":""},"63":{"sum_comment":"","sum_foreign_comment":"","sum_foreign":"","sum_hidden":false,"sum":""},"64":{"sum_comment":"","sum_foreign_comment":"","sum_foreign":"","sum":""}},"declaration":{"notfull_lostpages":"","additional_info_text":"","additional_info":"","date":"2015-03-24T00:00:00","notfull":"","url":"http://static.declarations.com.ua/declarations/chosen_ones/judges_batch/4097_ivchenko_tetiana_pavlivna.pdf"},"intro":{"isnotdeclaration":"","declaration_year":"2014"}}]