[{"id":"vulyk_67_150","ft_src":"1896 куб. см., 76 кВт , 420 см\nSkoda Octavia\n2007\nДружина має право на користування даним автомобілем відповідно до відмітки у технічному паспорті\n1896 куб. см., 76 кВт , 420 см\nSkoda Octavia\n2007\nм. Ужгород\n850\nЗакарпатська область\nм. Хуст\n320\nЗакарпатська область\n2500\n860\n1340\nХустський р-н\n72.9\nЗакарпатська область\nм. Хуст\n89.3\nЗакарпатська область\nм. Ужгород\n66.5\nЗакарпатська область\nХустський р-н\n86.2\nЗакарпатська область\nСарай\nХустський р-н\n25.2\nЗакарпатська область\nСарай\nХустський р-н\n20.9\nЗакарпатська область\nСарай із вбудованою сауною\nХустський р-н\n65.3\nЗакарпатська область\n2014\n36849\n231762\n36849\n231762\n1896 куб. см., 76 кВт , 420 см\nSkoda Octavia\n2007\n1896 куб. см., 76 кВт , 420 см\nДружина має право на користування даним автомобілем відповідно до відмітки у технічному паспорті\n2007\nSkoda Octavia\n850\nЗакарпатська область\nм. Ужгород\n320\nм. Хуст\nЗакарпатська область\n2500\n860\n1340\n86.2\nХустський р-н\nЗакарпатська область\n72.9\nХустський р-н\nЗакарпатська область\n89.3\nЗакарпатська область\nм. Хуст\nм. Ужгород\n66.5\nЗакарпатська область\n25.2\nСарай\nХустський р-н\nЗакарпатська область\n20.9\nСарай\nХустський р-н\nЗакарпатська область\n65.3\nСарай із вбудованою сауною\nХустський р-н\nЗакарпатська область\nЗагальний місцевий суд\nсуддя господарського суду закарпатської області\nЗакарпатська область\nПодружжя\nКарпинець Світлана Степанівна\nДитина\nКарпинець Іван Васильович\nКарпинець Василь Іванович\nВасиль Іванович Карпинець\nВасиль Карпинець\nКарпинець Василь Іванович\nКарпинець Василь Іванович\nВасиль\nКарпинець\nІванович\nУжгород\nЗакарпатська область\n3000\n20000\n11000\n36849\n231762\n231762\n36849\n2014\n11000\n3000\n20000\nПодружжя\nКарпинець Світлана Степанівна\nДитина\nКарпинець Іван Васильович\nІванович\nКарпинець\nВасиль\nКарпинець Василь Іванович\nВасиль Іванович Карпинець\nВасиль Карпинець\nКарпинець Василь Іванович\nЗакарпатська область\nУжгород\nЗакарпатська область\nсуддя господарського суду закарпатської області\nЗагальний місцевий суд\nКарпинець Василь Іванович","estate":{"23":[{"costs":"","address":"м. Ужгород","space_units":"м²","costs_hidden":false,"costs_rent_hidden":false,"space_unclear":false,"region_hidden":false,"space_units_unclear":false,"costs_comment":"","space_comment_unclear":false,"space_hidden":false,"address_unclear":true,"space_comment":"","address_hidden":false,"costs_rent_comment":"","space":"850","region":"Закарпатська область","costs_rent":""},{"address":"м. Хуст","space_units":"м²","costs_comment":"","space_unclear":false,"region_hidden":false,"space_units_unclear":false,"space_comment":"","address_hidden":false,"costs":"","space_comment_unclear":false,"costs_rent_comment":"","space":"320","region":"Закарпатська область","costs_rent":""},{"address":"","space_units":"м²","costs_comment":"","space_unclear":false,"region_hidden":false,"space_units_unclear":false,"space_comment":"","address_hidden":false,"costs":"","costs_rent_comment":"","space":"2500","region":"","costs_rent":""},{"costs":"","address":"","space_units":"м²","costs_rent_comment":"","space":"860","space_comment":"","costs_comment":"","region":"","costs_rent":""},{"costs":"","address":"","space_units":"м²","costs_rent_comment":"","space":"1340","space_comment":"","costs_comment":"","region":"","costs_rent":""}],"24":[{"address":"Хустський р-н","space_units":"м²","costs_hidden":false,"space_hidden":false,"space_comment":"","region_hidden":false,"costs_comment":"","address_hidden":false,"costs":"","space_comment_unclear":false,"costs_rent_comment":"","space":"86.2","region":"Закарпатська область","costs_rent":""}],"25":[{"address":"м. Хуст","space_units":"м²","costs_hidden":false,"costs_comment":"","space_unclear":false,"region_hidden":false,"space_units_unclear":false,"space_comment":"","space_comment_unclear":false,"costs":"","address_unclear":false,"address_hidden":false,"costs_rent_comment":"","space":"89.3","region":"Закарпатська область","costs_rent":""},{"costs":"","address":"м. Ужгород","space_units":"м²","costs_rent_comment":"","space":"66.5","space_comment":"","region_hidden":false,"costs_comment":"","region":"Закарпатська область","costs_rent":""}],"27":[{"address":"Хустський р-н","space_units":"м²","costs_hidden":false,"space_comment":"","region_hidden":false,"costs_comment":"","address_hidden":false,"costs":"","costs_rent_comment":"","space":"72.9","region":"Закарпатська область","costs_rent":""}],"28":[{"address":"Хустський р-н","space_units":"м²","costs_hidden":false,"space_comment":"Сарай","region_hidden":false,"costs_comment":"","address_hidden":false,"costs":"","costs_rent_comment":"","space":"25.2","region":"Закарпатська область","costs_rent":""},{"costs":"","address":"Хустський р-н","space_units":"м²","costs_rent_comment":"","space":"20.9","space_comment":"Сарай","region_hidden":false,"costs_comment":"","region":"Закарпатська область","address_hidden":false,"costs_rent":""},{"costs":"","address":"Хустський р-н","space_units":"м²","costs_rent_comment":"","space":"65.3","space_comment":"Сарай із вбудованою сауною","costs_comment":"","region":"Закарпатська область","costs_rent":""}]},"vehicle":{"35":[{"sum_comment_unclear":false,"brand_info":"1896 куб. см., 76 кВт , 420 см","brand_unclear":false,"sum_rent_comment":"","brand_hidden":false,"year":"2007","brand":"Skoda Octavia","brand_info_hidden":false,"sum_rent":"","sum_rent_unclear":false,"sum_comment":"","year_unclear":false,"brand_info_unclear":false,"sum_unclear":false,"sum":""}],"40":[{"sum_comment":"","brand_info":"1896 куб. см., 76 кВт , 420 см","brand_unclear":false,"sum_rent_comment":"Дружина має право на користування даним автомобілем відповідно до відмітки у технічному паспорті","year":"2007","brand":"Skoda Octavia","sum_rent":"","brand_info_unclear":false,"year_unclear":false,"sum":""}]},"source":"VULYK","income":{"5":{"family":"36849","family_comment":"","comment":"","value_hidden":false,"value_unclear":false,"value":"231762"},"6":{"family_comment":"","family":"36849","comment":"","value_unclear":false,"family_unclear":false,"value":"231762"},"7":{"family_comment":"","comment":"","family":"","source_name_unclear":false,"value":"","family_hidden":false,"source_name":""},"8":{"family_comment":"","value":"","family":"","comment":""},"9":{"family_comment":"","value":"","family":"","comment":""},"10":{"family_comment":"","value":"","family":"","comment":""},"11":{"family_comment":"","value":"","family":"","comment":""},"12":{"family_comment":"","value":"","family":"","comment":""},"13":{"family_comment":"","value":"","family":"","comment":""},"14":{"family_comment":"","value":"","family":"","comment":""},"15":{"family_comment":"","value":"","family":"","comment":""},"16":{"family_comment":"","comment_unclear":false,"value":"","family":"","comment":""},"17":{"family_comment":"","value":"","family_unclear":false,"family":"","comment":""},"18":{"family_comment":"","value":"","family":"","comment":""},"19":{"family":"","family_comment":"","comment":"","value_hidden":false,"family_hidden":false,"value":""},"20":{"family_comment":"","comment_unclear":false,"value":"","family":"","comment":""}},"general":{"family":[{"inn":"","inn_unclear":false,"family_name":"Карпинець Світлана Степанівна","relations_hidden":false,"relations_unclear":false,"name_unclear":false,"relations":"Подружжя","inn_hidden":false,"name_hidden":false,"relations_other":""},{"inn":"","inn_unclear":false,"family_name":"Карпинець Іван Васильович","relations_hidden":false,"relations_unclear":false,"name_unclear":false,"relations":"Дитина","inn_hidden":false,"name_hidden":false,"relations_other":""}],"family_raw":"","name":"Василь","full_name_suggest":{"input":["Карпинець Василь Іванович","Василь Іванович Карпинець","Василь Карпинець"],"output":"Карпинець Василь Іванович"},"name_unclear":false,"patronymic":"Іванович","inn_hidden":false,"patronymic_unclear":false,"last_name_hidden":false,"inn":"","inn_unclear":false,"last_name":"Карпинець","full_name":"Карпинець Василь Іванович","post":{"post_hidden":false,"office":"Загальний місцевий суд","post":"суддя господарського суду закарпатської області","region":"Закарпатська область","office_hidden":false,"office_unclear":false,"region_hidden":false,"post_unclear":false},"addresses":[{"place_city_type_hidden":false,"place_district_hidden":false,"place_address_unclear":false,"place":"Закарпатська область","place_city":"Ужгород","place_unclear":false,"place_city_type":"Місто","place_city_hidden":false,"place_city_unclear":false,"place_district":"","place_district_unclear":false,"place_address":"","place_address_hidden":false,"place_hidden":false}],"last_name_unclear":false},"liabilities":{"54":{"sum_comment_unclear":false,"sum_comment":"","sum_hidden":false,"sum":"","sum_foreign_comment":"","sum_foreign":"","sum_unclear":false,"sum_foreign_hidden":false},"55":{"sum_comment":"","sum_foreign_comment":"","sum_foreign":"","sum":""},"56":{"sum_comment":"","sum_hidden":false,"sum":"20000","sum_foreign_comment":"","sum_foreign":"","sum_unclear":false,"sum_foreign_hidden":false},"57":{"sum_comment_unclear":false,"sum_comment":"","sum_hidden":false,"sum":"3000","sum_foreign_comment":"","sum_foreign":"","sum_unclear":false,"sum_foreign_hidden":false,"sum_comment_hidden":false},"58":{"sum_comment_unclear":false,"sum_comment":"","sum_hidden":false,"sum":"11000","sum_foreign_comment":"","sum_foreign":"","sum_unclear":false,"sum_foreign_hidden":false,"sum_comment_hidden":false},"59":{"sum_comment":"","sum_foreign_comment":"","sum_foreign":"","sum_hidden":false,"sum":""},"60":{"sum_comment":"","sum_foreign_comment":"","sum_foreign":"","sum":""},"61":{"sum_comment":"","sum_hidden":false,"sum":"","sum_foreign_comment":"","sum_foreign":"","sum_foreign_hidden":false},"62":{"sum_comment":"","sum_foreign_comment":"","sum_foreign":"","sum_hidden":false,"sum":""},"63":{"sum_comment_unclear":false,"sum_comment":"","sum_hidden":false,"sum":"","sum_foreign_comment":"","sum_foreign":"","sum_unclear":false},"64":{"sum_comment":"","sum_hidden":false,"sum":"","sum_foreign_comment":"","sum_foreign":"","sum_unclear":false}},"declaration":{"notfull_lostpages":"","additional_info_text":"","additional_info":"","date":"2015-03-19T00:00:00","notfull":"","url":"http://static.declarations.com.ua/declarations/chosen_ones/mega_batch/karpynets_vasyl_ivanovych.pdf"},"intro":{"declaration_year_hidden":false,"isnotdeclaration":"","declaration_year":"2014"}}]