[{"id":"vulyk_99_17","ft_src":"Ощадбанк України\n10189\nОщадбанк України\n1000\nм. Яготин\n.0999\nКиївська область\nКиївська область\nм. Яготин\n.1117\nм. Яготин\n.1\nКиївська область\nКиївська область\nм. Яготин\n130.5\nм. Яготин\n90.7\nКиївська область\n7\n1\n2015\n49247\n126713\n49247\n201538\n74825\n7\n1\nОщадбанк України\n1000\n10189\nОщадбанк України\n2015\nКисіль\nКисіль Олеся Анатоліївна\nОлеся Анатоліївна Кисіль\nОлеся Кисіль\nКисіль Олеся Анатоліївна\nОлеся\nАнатоліївна\n07700\nКиївська область\nЯготин\nКисіль Олеся Анатоліївна\nЗагальний місцевий суд\nсуддя яготинського районного суду київської області\nКиївська область\nПодружжя\nКисіль Євгеній Олександрович\nДитина\nКисіль Владислав Євгенійович\nДитина\nКисіль Назарій Євгенійович\n126713\n49247\n74825\n201538\n49247\n.0999\nм. Яготин\nКиївська область\n.1117\nКиївська область\nм. Яготин\n.1\nКиївська область\nм. Яготин\nКиївська область\n90.7\nм. Яготин\n130.5\nКиївська область\nм. Яготин\nКисіль Євгеній Олександрович\nПодружжя\nКисіль Владислав Євгенійович\nДитина\nКисіль Назарій Євгенійович\nДитина\nАнатоліївна\nКиївська область\nЯготин\n07700\nКисіль\nсуддя яготинського районного суду київської області\nКиївська область\nЗагальний місцевий суд\nКисіль Олеся Анатоліївна\nКисіль Олеся Анатоліївна\nОлеся Анатоліївна Кисіль\nОлеся Кисіль\nКисіль Олеся Анатоліївна\nОлеся","estate":{"23":[{"address":"м. Яготин","space_units":"га","costs_comment":"","space_unclear":false,"region_hidden":false,"space_comment":"","address_hidden":true,"costs":"","costs_rent_comment":"","space":".0999","region":"Київська область","costs_rent":""},{"address":"м. Яготин","space_units":"га","space_unclear":false,"costs_comment":"","space_comment":"","address_hidden":false,"space":".1117","address_unclear":false,"costs_comment_unclear":false,"costs_rent_comment":"","costs":"","region":"Київська область","costs_rent":""},{"costs":"","address":"м. Яготин","space_units":"га","costs_rent_comment":"","space":".1","space_unclear":false,"space_comment":"","costs_comment":"","region":"Київська область","costs_rent":""}],"24":[{"costs":"","address":"м. Яготин","space_units":"м²","costs_rent_comment":"","space":"90.7","space_comment":"","region_hidden":false,"costs_comment":"","region":"Київська область","address_hidden":true,"costs_rent":""}],"30":[{"costs_property_comment":"","address":"м. Яготин","space_units":"м²","costs_rent_comment":"","space":"130.5","region":"Київська область","region_hidden":false,"costs_property":"","space_comment":"","address_hidden":true,"costs_rent":""}]},"source":"VULYK","income":{"5":{"family_comment":"","family":"49247","comment":"","value_unclear":false,"family_unclear":false,"value":"201538"},"6":{"family_comment":"","family":"49247","comment":"","value_unclear":false,"family_unclear":false,"value":"126713"},"7":{"family":"","family_comment":"","value":"","comment":"","source_name":""},"8":{"family_comment":"","value":"","family":"","comment":""},"9":{"family_comment":"","value":"","family":"","comment":""},"10":{"family_comment":"","value":"","family":"","comment":""},"11":{"family_comment":"","value":"","family":"","comment":""},"12":{"family_comment":"","value":"","family":"","comment":""},"13":{"family_comment":"","value":"","family":"","comment":""},"14":{"family_comment":"","value":"","family":"","comment":""},"15":{"family_comment":"","value":"","family":"","comment":"","value_unclear":false},"16":{"family_comment":"","value":"","family":"","comment":""},"17":{"family_comment":"","value":"","family":"","comment":""},"18":{"family_comment":"","value":"","family":"","comment":""},"19":{"family_comment":"","value":"","family":"","comment":""},"20":{"family_comment":"","family":"","comment":"","value_unclear":false,"family_unclear":false,"value":"74825","family_comment_unclear":false}},"banks":{"45":[{"sum_units":"UAH","sum_comment":"Ощадбанк України","sum_foreign_units":"UAH","sum":"1000","sum_foreign_comment":"","sum_foreign":"","sum_comment_hidden":false}],"51":[{"sum_comment_unclear":false,"sum_units":"UAH","sum_foreign_units":"UAH","sum":"10189","sum_foreign_comment":"","sum_comment":"Ощадбанк України","sum_foreign":"","sum_comment_hidden":false}]},"declaration":{"notfull_lostpages":"7","date":"2016-01-25T00:00:00","notfull":"1","url":"http://static.declarations.com.ua/declarations/chosen_ones/judges_batch/566_kysil_olesia_anatoliivna_2015.pdf"},"general":{"inn":"","addresses":[{"place_city_type_hidden":false,"place_city_type":"Місто","place_city_hidden":false,"place_hidden":true,"place_district":"","place_district_hidden":false,"place":"Київська область","place_address":"07700","place_address_hidden":true,"place_city":"Яготин"}],"last_name":"Кисіль","full_name":"Кисіль Олеся Анатоліївна","family":[{"inn":"","family_name":"Кисіль Євгеній Олександрович","name_unclear":false,"inn_hidden":true,"name_hidden":true,"relations":"Подружжя"},{"inn":"","family_name":"Кисіль Владислав Євгенійович","relations_other":"","name_unclear":false,"inn_hidden":true,"relations":"Дитина"},{"inn":"","family_name":"Кисіль Назарій Євгенійович","relations_other":"","name_unclear":false,"inn_hidden":true,"name_hidden":false,"relations":"Дитина"}],"patronymic":"Анатоліївна","inn_hidden":true,"name":"Олеся","post":{"office":"Загальний місцевий суд","region":"Київська область","post_unclear":false,"post":"суддя яготинського районного суду київської області"},"family_raw":"","full_name_suggest":{"input":["Кисіль Олеся Анатоліївна","Олеся Анатоліївна Кисіль","Олеся Кисіль"],"output":"Кисіль Олеся Анатоліївна"}},"liabilities":{"54":{"sum_comment_unclear":false,"sum_comment":"","sum":"","sum_foreign_comment":"","sum_foreign":"","sum_comment_hidden":false},"55":{"sum_comment":"","sum_foreign_comment":"","sum_foreign":"","sum":""},"56":{"sum_comment":"","sum_foreign_comment":"","sum_foreign":"","sum":""},"57":{"sum_comment":"","sum_foreign_comment":"","sum_foreign":"","sum":"","sum_comment_hidden":false},"58":{"sum_comment":"","sum_foreign_comment":"","sum_foreign":"","sum":"","sum_comment_hidden":false},"59":{"sum_comment":"","sum":"","sum_foreign_comment":"","sum_foreign":"","sum_unclear":false,"sum_comment_hidden":false},"60":{"sum_comment":"","sum_foreign_comment":"","sum_foreign":"","sum":"","sum_comment_hidden":false},"61":{"sum_comment":"","sum_foreign_comment":"","sum_foreign":"","sum":""},"62":{"sum_comment":"","sum_foreign_comment":"","sum_foreign":"","sum":""},"63":{"sum_comment":"","sum_foreign_comment":"","sum_foreign":"","sum":"","sum_comment_hidden":false},"64":{"sum_comment":"","sum_foreign_comment":"","sum_foreign":"","sum":"","sum_comment_hidden":false}},"intro":{"declaration_year":"2015"}},{"id":"vulyk_100_67","declaration":{"notfull_lostpages":"","additional_info_text":"","additional_info":"","date":"2015-03-30T00:00:00","notfull":"","url":"http://static.declarations.com.ua/declarations/chosen_ones/judges_batch/4266_kysil_olesia_anatoliivna.pdf"},"estate":{"23":[{"address":"м. Яготин","space_units":"га","costs_comment":"","space_unclear":true,"region_hidden":false,"space_comment":"","address_hidden":true,"costs":"","address_unclear":false,"space_comment_unclear":false,"costs_comment_unclear":false,"costs_rent_comment":"","space":".0999","region":"Київська область","costs_rent":""},{"costs":"","address":"м. Яготин","space_units":"га","costs_rent_comment":"","space":".1117","space_unclear":true,"space_comment":"","costs_comment":"","region":"Київська область","costs_rent":""},{"space":".1","address":"м. Яготин","space_units":"га","costs_rent_comment":"","costs":"","costs_comment":"","space_comment":"","region":"Київська область","costs_rent":""}],"24":[{"address":"м. Яготин","space_units":"м²","costs_comment":"","space_unclear":true,"region_hidden":false,"space_comment":"","address_hidden":true,"space":"90.7","space_comment_unclear":false,"costs_rent_comment":"","costs":"","region":"Київська область","costs_rent":""}],"30":[{"costs_property_comment":"","address":"м. Яготин","space_units":"м²","costs_rent_comment":"","space":"130.5","region":"Київська область","region_hidden":false,"costs_property":"","space_comment":"","address_hidden":true,"costs_rent":""}]},"vehicle":{"40":[{"sum_comment":"","brand_info_hidden":false,"brand_info":"1.9 куб. дм., 120 кВт","sum":"","sum_rent_comment":"","year":"2001","brand":"Renault Kangoo","sum_rent":"","brand_info_unclear":false}]},"source":"VULYK","income":{"5":{"family_comment":"","family":"16155","comment":"","value_unclear":false,"family_unclear":false,"value":"204100"},"6":{"family_comment":"","value":"204100","family":"15792","comment":"","value_unclear":false},"7":{"family_comment":"","comment":"","family":"","value_unclear":false,"value":"","source_name":""},"8":{"family_comment":"","value":"","family":"","comment":""},"9":{"family_comment":"","family":"","comment":"","value_unclear":false,"family_unclear":false,"value":""},"10":{"family_comment":"","comment_unclear":false,"value":"","family":"","comment":""},"11":{"family_comment":"","value":"","family":"","comment":""},"12":{"family_comment":"","value":"","family":"363","comment":""},"13":{"family_comment":"","value":"","family":"","comment":"","value_unclear":false},"14":{"family_comment":"","value":"","family":"","comment":""},"15":{"family_comment":"","value":"","family":"","comment":""},"16":{"family_comment":"","value":"","family_unclear":false,"family":"","comment":""},"17":{"family_comment":"","value":"","family_unclear":false,"family":"","comment":""},"18":{"family_comment":"","value":"","family":"","comment":""},"19":{"family_comment":"","value":"","family":"","comment":""},"20":{"family":"","family_comment":"","comment":"","value_hidden":false,"value_unclear":false,"value":"","comment_unclear":false,"family_unclear":false,"family_hidden":false}},"banks":{"45":[{"sum_comment_unclear":false,"sum_units":"UAH","sum_foreign_comment":"","sum_foreign_units":"UAH","sum":"1000","sum_comment":"Ощадбанк Яготинське відділення, ощадна книжка СРСР","sum_foreign":"","sum_unclear":false,"sum_units_unclear":false,"sum_comment_hidden":false}],"51":[{"sum_comment_unclear":false,"sum_units":"UAH","sum_foreign_comment":"","sum_foreign_units":"UAH","sum":"10188.26","sum_comment":"Ощадбанк Яготинське відділення, ощадна книжка СРСР","sum_foreign":"","sum_unclear":true,"sum_units_unclear":false,"sum_comment_hidden":false}]},"ft_src":"2001\n1.9 куб. дм., 120 кВт\nRenault Kangoo\nОщадбанк Яготинське відділення, ощадна книжка СРСР\n10188.26\nОщадбанк Яготинське відділення, ощадна книжка СРСР\n1000\n2014\nRenault Kangoo\n1.9 куб. дм., 120 кВт\n2001\nОщадбанк Яготинське відділення, ощадна книжка СРСР\n1000\n10188.26\nОщадбанк Яготинське відділення, ощадна книжка СРСР\n.0999\nКиївська область\nм. Яготин\nКиївська область\n.1117\nм. Яготин\nКиївська область\n.1\nм. Яготин\n90.7\nм. Яготин\nКиївська область\n130.5\nКиївська область\nм. Яготин\nПодружжя\nКисіль Е. О. 11. 05. 1982\nДитина\nКисіль В. Е. 09. 09. 2008\nАнатоліївна\nКиївська область\n7700\nЯготин\nКисіль\nКисіль Олеся Анатоліївна\nОлеся Анатоліївна Кисіль\nОлеся Кисіль\nКисіль Олеся Анатоліївна\nКисіль Олеся Анатоліївна\nОлеся\nЗагальний місцевий суд\nКиївська область\nсуддя яготинського районного суду київської області\n204100\n15792\n363\n204100\n16155\n2014\nм. Яготин\n.0999\nКиївська область\nм. Яготин\n.1117\nКиївська область\nКиївська область\nм. Яготин\n.1\nКиївська область\nм. Яготин\n130.5\nм. Яготин\n90.7\nКиївська область\nКисіль Е. О. 11. 05. 1982\nПодружжя\nДитина\nКисіль В. Е. 09. 09. 2008\n7700\nЯготин\nКиївська область\nАнатоліївна\nКисіль\nКиївська область\nЗагальний місцевий суд\nсуддя яготинського районного суду київської області\nКисіль Олеся Анатоліївна\nКисіль Олеся Анатоліївна\nОлеся Анатоліївна Кисіль\nОлеся Кисіль\nКисіль Олеся Анатоліївна\nОлеся\n15792\n204100\n16155\n204100\n363","general":{"inn":"","addresses":[{"place_city_type":"Місто","place_city_type_hidden":false,"place_hidden":false,"place_city_hidden":false,"place_district_hidden":false,"place_district":"","place_city_unclear":false,"place":"Київська область","place_city":"Яготин","place_address_hidden":true,"place_address":"7700"}],"last_name":"Кисіль","full_name":"Кисіль Олеся Анатоліївна","family":[{"inn":"","family_name":"Кисіль Е. О. 11. 05. 1982","name_unclear":false,"inn_hidden":true,"name_hidden":false,"relations":"Подружжя"},{"inn":"","family_name":"Кисіль В. Е. 09. 09. 2008","relations_other":"","name_unclear":false,"inn_hidden":true,"name_hidden":false,"relations":"Дитина"}],"patronymic":"Анатоліївна","inn_hidden":true,"name":"Олеся","post":{"post_hidden":false,"office":"Загальний місцевий суд","post":"суддя яготинського районного суду київської області","office_unclear":false,"region_unclear":false,"region":"Київська область","post_unclear":false},"family_raw":"","full_name_suggest":{"input":["Кисіль Олеся Анатоліївна","Олеся Анатоліївна Кисіль","Олеся Кисіль"],"output":"Кисіль Олеся Анатоліївна"}},"liabilities":{"54":{"sum_comment":"","sum":"","sum_foreign_comment":"","sum_foreign":"","sum_unclear":false,"sum_comment_hidden":false},"55":{"sum_comment":"","sum_foreign_comment":"","sum_foreign":"","sum":""},"56":{"sum_comment":"","sum_foreign_comment":"","sum_foreign":"","sum_unclear":false,"sum":""},"57":{"sum_comment_unclear":false,"sum_comment":"","sum":"","sum_foreign_comment":"","sum_foreign":"","sum_unclear":false,"sum_comment_hidden":false},"58":{"sum_comment":"","sum":"","sum_foreign_comment":"","sum_foreign":"","sum_unclear":false,"sum_comment_hidden":false},"59":{"sum_comment":"","sum_foreign_comment":"","sum_foreign":"","sum":""},"60":{"sum_comment":"","sum_foreign_comment":"","sum_foreign":"","sum":"","sum_comment_hidden":false},"61":{"sum_comment":"","sum_foreign_comment":"","sum_foreign":"","sum":""},"62":{"sum_comment":"","sum_foreign_comment":"","sum_foreign":"","sum_unclear":false,"sum":""},"63":{"sum_comment":"","sum_foreign_comment":"","sum_foreign":"","sum":"","sum_comment_hidden":false},"64":{"sum_comment":"","sum_foreign_comment":"","sum_foreign":"","sum":"","sum_comment_hidden":false}},"intro":{"declaration_year":"2014"}}]