[{"id":"vulyk_101_24","ft_src":"Volkswagen Tiguan\nв користуванні\n1968 куб. см.\n2010\n1598 куб. см.\nNissan TIIDA\n2007\n1/2 від 599 кв. м\n599\n86.4\n1/4 від 93,3 кв. м\n93.3\n2015\n50409\n14099\n5929\n609\nНаціональна школа суддів України, Одеський державний університет внутрішніх справ\n267222\n163845\n281321\n80000\n26899\n1968 куб. см.\nв користуванні\n2010\nVolkswagen Tiguan\n1598 куб. см.\n2007\nNissan TIIDA\n599\n1/2 від 599 кв. м\n86.4\n93.3\n1/4 від 93,3 кв. м\nКопіца Олег Володимирович\nОлег Володимирович Копіца\nОлег Копіца\nКопіца Олег Володимирович\nОлег\nКопіца Олег Володимирович\nВолодимирович\nсуддя апеляційного суду одеської області\nОдеська область\nЗагальний апеляційний суд\nКопіца\nПодружжя\nКопіца Наталя Сергіївна\nДитина\nКопіца Віра Олегівна\nДитина\nКопіца Олег Олегович\n267222\nНаціональна школа суддів України, Одеський державний університет внутрішніх справ\n14099\n50409\n26899\n5929\n281321\n163845\n80000\n609\n2015\nКопіца Наталя Сергіївна\nПодружжя\nКопіца Віра Олегівна\nДитина\nКопіца Олег Олегович\nДитина\nОлег\nВолодимирович\nКопіца\nКопіца Олег Володимирович\nОлег Володимирович Копіца\nОлег Копіца\nКопіца Олег Володимирович\nсуддя апеляційного суду одеської області\nОдеська область\nЗагальний апеляційний суд\nКопіца Олег Володимирович","estate":{"25":[{"address":"","space_units":"м²","space_hidden":false,"space_unclear":false,"region_hidden":true,"costs_comment":"","space_comment":"","address_hidden":false,"space":"86.4","space_comment_unclear":false,"costs_rent_comment":"","costs":"","region":"","costs_rent":""},{"address":"","space_units":"м²","space_hidden":false,"space_unclear":false,"costs_comment":"","space_comment":"1/4 від 93,3 кв. м","space_comment_unclear":false,"space":"93.3","costs_rent_comment":"","costs":"","region":"","costs_rent":""}],"29":[{"costs_property_comment":"","address":"","space_units":"м²","costs_rent_comment":"","space":"599","region":"","region_hidden":true,"costs_property":"","space_comment":"1/2 від 599 кв. м","address_hidden":true,"costs_rent":""}]},"vehicle":{"35":[{"sum_comment":"","brand_info_hidden":false,"sum_rent":"","sum":"","brand_unclear":false,"year":"2010","brand":"Volkswagen Tiguan","brand_info":"1968 куб. см.","sum_rent_comment":"в користуванні","brand_info_unclear":false,"sum_rent_unclear":false}],"40":[{"sum_comment":"","brand_info_hidden":false,"brand_info":"1598 куб. см.","sum":"","sum_rent_comment":"","brand_hidden":false,"brand":"Nissan TIIDA","sum_rent":"","brand_info_unclear":false,"year":"2007"}]},"source":"VULYK","income":{"5":{"family_comment":"","value":"281321","family":"163845","comment":"","value_unclear":false},"6":{"family_comment":"","family":"50409","comment":"","value_unclear":false,"family_hidden":false,"value":"14099"},"7":{"family_comment":"","comment":"","family":"","source_name_unclear":false,"value":"267222","source_name":"Національна школа суддів України, Одеський державний університет внутрішніх справ"},"8":{"family_comment":"","value":"","family":"","comment":""},"9":{"family_comment":"","value":"","family":"","comment":""},"10":{"family_comment":"","value":"","family":"","comment":""},"11":{"family_comment":"","comment_unclear":false,"value":"","family":"609","comment":""},"12":{"family_comment":"","value":"","family":"","comment":""},"13":{"family_comment":"","value":"","family":"","comment":""},"14":{"family_comment":"","value":"","family":"","comment":""},"15":{"family_comment":"","value":"","family":"5929","comment":""},"16":{"family_comment":"","value":"","family":"80000","comment":""},"17":{"family_comment":"","value":"","family":"","comment":""},"18":{"family_comment":"","value":"","family":"","comment":""},"19":{"family_comment":"","value":"","family":"","comment":""},"20":{"family_comment":"","comment":"","family":"26899","value_unclear":false,"family_unclear":false,"comment_unclear":false,"value":""}},"general":{"family":[{"inn":"","family_name":"Копіца Наталя Сергіївна","relations_other":"","name_unclear":false,"inn_hidden":true,"name_hidden":true,"relations":"Подружжя"},{"inn":"","family_name":"Копіца Віра Олегівна","relations_other":"","relations_unclear":false,"name_unclear":false,"inn_hidden":true,"name_hidden":false,"relations":"Дитина"},{"inn":"","family_name":"Копіца Олег Олегович","relations_other":"","name_unclear":false,"inn_hidden":true,"name_hidden":false,"relations":"Дитина"}],"family_raw":"","name":"Олег","full_name_suggest":{"input":["Копіца Олег Володимирович","Олег Володимирович Копіца","Олег Копіца"],"output":"Копіца Олег Володимирович"},"patronymic":"Володимирович","inn_hidden":true,"addresses":[{"place_city_type_hidden":false,"place_city_type":"","place_city_hidden":true,"place_hidden":true,"place_district":"","place_district_hidden":false,"place":"","place_city":"","place_address_hidden":true,"place_address":""}],"patronymic_hidden":false,"inn":"","inn_unclear":false,"last_name":"Копіца","full_name":"Копіца Олег Володимирович","post":{"office_unclear":false,"region_unclear":false,"post":"суддя апеляційного суду одеської області","region":"Одеська область","office":"Загальний апеляційний суд"}},"liabilities":{"54":{"sum_comment_unclear":false,"sum_comment":"","sum_hidden":false,"sum":"","sum_foreign_comment":"","sum_foreign":"","sum_unclear":false,"sum_comment_hidden":false},"55":{"sum_comment":"","sum_foreign_comment":"","sum_foreign":"","sum":""},"56":{"sum_comment":"","sum":"","sum_foreign_comment":"","sum_foreign":"","sum_unclear":false,"sum_comment_hidden":false},"57":{"sum_comment":"","sum_hidden":false,"sum":"","sum_foreign_comment":"","sum_foreign":"","sum_unclear":false,"sum_comment_hidden":false},"58":{"sum_comment_unclear":false,"sum_comment":"","sum_hidden":false,"sum":"","sum_foreign_comment":"","sum_foreign":"","sum_unclear":false,"sum_comment_hidden":false},"59":{"sum_comment":"","sum_foreign_comment":"","sum_foreign":"","sum":""},"60":{"sum_comment":"","sum_hidden":false,"sum":"","sum_foreign_comment":"","sum_foreign":"","sum_unclear":false,"sum_comment_hidden":false},"61":{"sum_comment":"","sum_foreign_comment":"","sum_foreign":"","sum":""},"62":{"sum_comment":"","sum_comment_unclear":false,"sum_foreign_comment":"","sum":"","sum_foreign":""},"63":{"sum_comment":"","sum_foreign_comment":"","sum_foreign":"","sum":"","sum_comment_hidden":false},"64":{"sum_comment":"","sum_foreign_comment":"","sum_foreign":"","sum":"","sum_comment_hidden":false}},"declaration":{"notfull_lostpages":"","additional_info_text":"","additional_info":"","date":"2016-03-30T00:00:00","notfull":"","url":"http://static.declarations.com.ua/declarations/chosen_ones/judges_batch/688_kopitsa_oleh_volodymyrovych_2015.pdf"},"intro":{"declaration_year":"2015"}},{"id":"vulyk_100_120","ft_src":"1968 куб. см., в користуванні\nVolkswagen Tiguan\n2010\n2001\n1000 куб. см., власність\nNissan Micra\n1598 куб. см., користування\n2007\nNissan TIIDA\n1/2 від 599 кв. м\n599\n86.4\n1/4 від 93,3\n93.3\n2014\n103803\n253419\n609\nНаціональна школа суддів України, Одеський державний університет внутрішніх справ\n13243\n276550\n266662\n150316\n21822\n1968 куб. см., в користуванні\nVolkswagen Tiguan\n2010\nNissan Micra\n1000 куб. см., власність\n2001\nNissan TIIDA\n1598 куб. см., користування\n2007\n1/2 від 599 кв. м\n599\n86.4\n93.3\n1/4 від 93,3\nПодружжя\nКопіца Наталя Сергіївна\nДитина\nКопіца Віра Олегівна\nДитина\nКопіца Олег Олегович\nВолодимирович\nКопіца\nКопіца Олег Володимирович\nОлег Володимирович Копіца\nОлег Копіца\nКопіца Олег Володимирович\nКопіца Олег Володимирович\nОлег\nЗагальний апеляційний суд\nОдеська область\nсуддя апеляційного суду одеської області\n13243\nНаціональна школа суддів України, Одеський державний університет внутрішніх справ\n253419\n103803\n21822\n266662\n276550\n150316\n609\n2014\nКопіца Наталя Сергіївна\nПодружжя\nДитина\nКопіца Віра Олегівна\nДитина\nКопіца Олег Олегович\nВолодимирович\nКопіца\nОдеська область\nЗагальний апеляційний суд\nсуддя апеляційного суду одеської області\nКопіца Олег Володимирович\nКопіца Олег Володимирович\nОлег Володимирович Копіца\nОлег Копіца\nКопіца Олег Володимирович\nОлег","estate":{"25":[{"address":"","space_units":"м²","costs_comment":"","space_unclear":false,"region_hidden":true,"space_comment":"","address_hidden":false,"costs":"","address_unclear":false,"space_comment_unclear":false,"costs_comment_unclear":false,"costs_rent_comment":"","space":"86.4","region":"","costs_rent":""},{"costs":"","address":"","space_units":"м²","costs_rent_comment":"","space":"93.3","space_comment":"1/4 від 93,3","region_hidden":true,"costs_comment":"","region":"","costs_rent":""}],"29":[{"costs_property_comment":"","address":"","space_units":"м²","space_unclear":false,"region_hidden":true,"costs_property":"","space_comment":"1/2 від 599 кв. м","address_hidden":true,"address_unclear":false,"costs_rent_comment":"","space":"599","region_unclear":false,"region":"","costs_rent":""}]},"vehicle":{"35":[{"brand_info":"1968 куб. см., в користуванні","sum_rent_comment":"","brand_unclear":false,"sum_rent_comment_unclear":false,"brand_hidden":false,"sum_comment":"","brand_info_hidden":false,"sum_rent":"","brand":"Volkswagen Tiguan","brand_info_unclear":false,"year":"2010","sum":""}],"40":[{"sum_comment":"","brand_info_hidden":false,"brand_info":"1000 куб. см., власність","sum":"","sum_rent_comment":"","year":"2001","brand":"Nissan Micra","sum_rent":"","brand_info_unclear":false},{"sum_comment":"","brand_info_hidden":false,"brand_info":"1598 куб. см., користування","sum":"","sum_rent_comment":"","year":"2007","brand":"Nissan TIIDA","sum_rent":""}]},"source":"VULYK","income":{"5":{"family_comment":"","family":"276550","comment":"","value_unclear":false,"family_unclear":false,"value":"266662"},"6":{"family_comment":"","value":"253419","family":"103803","comment":"","value_unclear":false},"7":{"family_comment":"","comment":"","family":"","value_unclear":false,"value":"13243","source_name":"Національна школа суддів України, Одеський державний університет внутрішніх справ"},"8":{"family_comment":"","value":"","family":"","comment":""},"9":{"family_comment":"","family":"","comment":"","value_unclear":false,"family_unclear":false,"value":""},"10":{"family_comment":"","comment_unclear":false,"value":"","family":"","comment":""},"11":{"family_comment":"","value":"","family":"609","comment":""},"12":{"family_comment":"","value":"","family":"","comment":""},"13":{"family_comment":"","value":"","family":"","comment":"","value_unclear":false},"14":{"family_comment":"","value":"","family":"","comment":""},"15":{"family_comment":"","value":"","family":"","comment":""},"16":{"family_comment":"","value":"","family_unclear":false,"family":"150316","comment":""},"17":{"family_comment":"","value":"","family_unclear":false,"family":"","comment":""},"18":{"family_comment":"","value":"","family":"","comment":""},"19":{"family_comment":"","value":"","family":"","comment":""},"20":{"family":"21822","family_comment":"","comment":"","value_hidden":false,"value_unclear":false,"value":"","comment_unclear":false,"family_unclear":false,"family_hidden":false}},"general":{"inn":"","addresses":[{"place_city_type":"","place_city_type_hidden":false,"place_hidden":true,"place_city_hidden":true,"place_district_hidden":false,"place_district":"","place_city_unclear":false,"place":"","place_city":"","place_address_hidden":true,"place_address":""}],"last_name":"Копіца","full_name":"Копіца Олег Володимирович","family":[{"inn":"","family_name":"Копіца Наталя Сергіївна","name_unclear":false,"inn_hidden":true,"name_hidden":true,"relations":"Подружжя"},{"inn":"","family_name":"Копіца Віра Олегівна","relations_other":"","name_unclear":false,"inn_hidden":true,"name_hidden":false,"relations":"Дитина"},{"inn":"","family_name":"Копіца Олег Олегович","relations_other":"","name_unclear":false,"inn_hidden":true,"name_hidden":false,"relations":"Дитина"}],"patronymic":"Володимирович","inn_hidden":true,"name":"Олег","post":{"post_hidden":false,"office":"Загальний апеляційний суд","post":"суддя апеляційного суду одеської області","office_unclear":false,"region_unclear":false,"region":"Одеська область","post_unclear":false},"family_raw":"","full_name_suggest":{"input":["Копіца Олег Володимирович","Олег Володимирович Копіца","Олег Копіца"],"output":"Копіца Олег Володимирович"}},"liabilities":{"54":{"sum_comment":"","sum":"","sum_foreign_comment":"","sum_foreign":"","sum_unclear":false,"sum_comment_hidden":false},"55":{"sum_comment":"","sum_foreign_comment":"","sum_foreign":"","sum":""},"56":{"sum_comment":"","sum_foreign_comment":"","sum_foreign":"","sum_unclear":false,"sum":""},"57":{"sum_comment_unclear":false,"sum_comment":"","sum":"","sum_foreign_comment":"","sum_foreign":"","sum_unclear":false,"sum_comment_hidden":false},"58":{"sum_comment":"","sum":"","sum_foreign_comment":"","sum_foreign":"","sum_unclear":false,"sum_comment_hidden":false},"59":{"sum_comment":"","sum_foreign_comment":"","sum_foreign":"","sum":""},"60":{"sum_comment":"","sum_foreign_comment":"","sum_foreign":"","sum":"","sum_comment_hidden":false},"61":{"sum_comment":"","sum_foreign_comment":"","sum_foreign":"","sum":""},"62":{"sum_comment":"","sum_foreign_comment":"","sum_foreign":"","sum_unclear":false,"sum":""},"63":{"sum_comment":"","sum_foreign_comment":"","sum_foreign":"","sum":"","sum_comment_hidden":false},"64":{"sum_comment":"","sum_foreign_comment":"","sum_foreign":"","sum":"","sum_comment_hidden":false}},"declaration":{"notfull_lostpages":"","additional_info_text":"","additional_info":"","date":"2015-03-26T00:00:00","notfull":"","url":"http://static.declarations.com.ua/declarations/chosen_ones/judges_batch/4324_kopitsa_oleh_volodymyrovych.pdf"},"intro":{"declaration_year":"2014"}},{"ft_src":"Volkswagen,Tiguan\n2010\nNissan,Micra\n2001\nNissan,Tiida\n2007\n599\n43,8\n86,4\n93,3\n4006\nFALSE\nFALSE\nFALSE\n2013\n13500\n257629\n2082\nНаціональна школа суддів України\n36212\n259710\n22712\nVolkswagen,Tiguan\n2010\nNissan,Micra\n2001\nNissan,Tiida\n2007\nFALSE\nFALSE\n599\n43,8\n86,4\n93,3\nСуддя Комінтернівського районного суду Одеської області, суддя апеляційного суду Одеської області\nДружина: Копіца Наталія Сергіївна приховано;Дочка: Копіца Віра Олегівна;Син: Копіца Олег Олегович\nКопіца\nКопіца Олег Володимирович\nОлег Володимирович Копіца\nОлег Копіца\nКопіца Олег Володимирович\nОлег\nКопіца Олег Володимирович\nЗагальний місцевий суд\nСуддя\nОдеська область\nВолодимирович\nНаціональна школа суддів України\n2082\n257629\n13500\n22712\n259710\n36212\n4006\n2013\nFALSE\nКопіца\nВолодимирович\nДружина: Копіца Наталія Сергіївна приховано;Дочка: Копіца Віра Олегівна;Син: Копіца Олег Олегович\nКопіца Олег Володимирович\nОлег Володимирович Копіца\nОлег Копіца\nКопіца Олег Володимирович\nОлег\nСуддя Комінтернівського районного суду Одеської області, суддя апеляційного суду Одеської області\nСуддя\nОдеська область\nЗагальний місцевий суд\nКопіца Олег Володимирович","estate":{"23":[{"costs":"","address":"","space_units":"","costs_rent_comment":"","space":"","costs_comment":"","costs_rent":"","space_comment":"","region":"","location_raw":""},{"costs":"","address":"","space_units":"","costs_rent_comment":"","space":"","costs_comment":"","costs_rent":"","space_comment":"","region":"","location_raw":""},{"costs":"","address":"","space_units":"","costs_rent_comment":"","space":"","costs_comment":"","costs_rent":"","space_comment":"","region":"","location_raw":""}],"25":[{"costs":"","address":"","space_units":"","costs_rent_comment":"","space":"86,4","costs_comment":"","costs_rent":"","space_comment":"","region":"","location_raw":"приховано"},{"costs":"","address":"","space_units":"","costs_rent_comment":"","space":"93,3","costs_comment":"","costs_rent":"","space_comment":"","region":"","location_raw":"приховано"}],"29":[{"costs_property_comment":"","address":"","space_units":"","costs_rent_comment":"","space":"599","space_comment":"","costs_property":"","region":"","location_raw":"приховано","costs_rent":""}],"31":[{"costs_property_comment":"","address":"","space_units":"","costs_rent_comment":"","space":"43,8","space_comment":"","costs_property":"","region":"","location_raw":"приховано","costs_rent":""}]},"vehicle":{"35":[{"sum_comment":"","brand_info":"","sum":"","sum_rent_comment":"","year":"2010","brand":"Volkswagen,Tiguan","sum_rent":"","brand_hidden":false}],"40":[{"sum_comment":"","brand_info":"","sum":"","sum_rent_comment":"","year":"2001","brand":"Nissan,Micra","sum_rent":"","brand_hidden":false},{"sum_comment":"","brand_info":"","sum":"","sum_rent_comment":"","year":"2007","brand":"Nissan,Tiida","sum_rent":"","brand_hidden":false}]},"id":"6356","income":{"5":{"family_comment":"","value":"259710","family":"36212","comment":""},"6":{"family_comment":"","value":"257629","family":"13500","comment":""},"7":{"family":"0","family_comment":"","value":"2082","comment":"","source_name":"Національна школа суддів України"},"8":{"family_comment":"","value":"0","family":"0","comment":""},"9":{"family_comment":"","value":"0","family":"0","comment":""},"10":{"family_comment":"","value":"0","family":"0","comment":""},"11":{"family_comment":"","value":"0","family":"0","comment":""},"12":{"family_comment":"","value":"0","family":"0","comment":""},"13":{"family_comment":"","value":"0","family":"0","comment":""},"14":{"family_comment":"","value":"0","family":"0","comment":""},"15":{"family_comment":"","value":"0","family":"0","comment":""},"16":{"family_comment":"","value":"0","family":"0","comment":""},"17":{"family_comment":"","value":"0","family":"0","comment":""},"18":{"family_comment":"","value":"0","family":"0","comment":""},"19":{"family_comment":"","value":"0","family":"0","comment":""},"20":{"family_comment":"","value":"0","family":"22712","comment":""},"21":[{"country_comment":"","uah_equal":"0","country":"0","cur":"0"},{"country_comment":"","uah_equal":"0","country":"0","cur":"0"},{"country_comment":"","uah_equal":"0","country":"0","cur":"0"},{"country_comment":"","uah_equal":"0","country":"0","cur":"0"},{"country_comment":"","uah_equal":"0","country":"0","cur":"0"}],"22":[{"country_comment":"","uah_equal":"0","country":"0","cur":"0"},{"country_comment":"","uah_equal":"0","country":"0","cur":"0"},{"country_comment":"","uah_equal":"0","country":"0","cur":"0"},{"country_comment":"","uah_equal":"0","country":"0","cur":"0"},{"country_comment":"","uah_equal":"0","country":"0","cur":"0"}]},"banks":{"45":[{"sum_units":"UAH","sum_comment":"","sum_foreign_units":"","sum":"4006","sum_foreign_comment":"","sum_foreign":""},{"sum_units":"USD","sum_comment":"","sum_foreign_units":"","sum":"","sum_foreign_comment":"","sum_foreign":""},{"sum_units":"EUR","sum_comment":"","sum_foreign_units":"","sum":"","sum_foreign_comment":"","sum_foreign":""}],"46":[{"sum_units":"UAH","sum_comment":"","sum_foreign_units":"","sum":"","sum_foreign_comment":"","sum_foreign":""},{"sum_units":"USD","sum_comment":"","sum_foreign_units":"","sum":"","sum_foreign_comment":"","sum_foreign":""},{"sum_units":"EUR","sum_comment":"","sum_foreign_units":"","sum":"","sum_foreign_comment":"","sum_foreign":""}],"47":[{"sum_units":"","sum_comment":"","sum_foreign_units":"","sum":"","sum_foreign_comment":"","sum_foreign":""}],"48":[{"sum_units":"","sum_comment":"","sum_foreign_units":"","sum":"","sum_foreign_comment":"","sum_foreign":""}],"49":[{"sum_units":"","sum_comment":"","sum_foreign_units":"","sum":"","sum_foreign_comment":"","sum_foreign":""}],"50":[{"sum_units":"","sum_comment":"","sum_foreign_units":"","sum":"","sum_foreign_comment":"","sum_foreign":""}],"51":[{"sum_units":"UAH","sum_comment":"","sum_foreign_units":"","sum":"","sum_foreign_comment":"","sum_foreign":""},{"sum_units":"USD","sum_comment":"","sum_foreign_units":"","sum":"","sum_foreign_comment":"","sum_foreign":""},{"sum_units":"EUR","sum_comment":"","sum_foreign_units":"","sum":"","sum_foreign_comment":"","sum_foreign":""}],"52":[{"sum_units":"","sum_comment":"","sum_foreign_units":"","sum":"","sum_foreign_comment":"","sum_foreign":""}],"53":[{"sum_units":"","sum_comment":"","sum_foreign_units":"","sum":"","sum_foreign_comment":"","sum_foreign":""}]},"declaration":{"notfull_lostpages":"","additional_info_text":"","additional_info":"FALSE","notfull":"FALSE","url":"http://static.declarations.com.ua/declarations/sudy/apeliatsiini_sudy_oblastei__m.kyieva/odeska/kopica_dec.pdf","needs_scancopy_check":false},"general":{"family_raw":"Дружина: Копіца Наталія Сергіївна приховано;Дочка: Копіца Віра Олегівна;Син: Копіца Олег Олегович","name":"Олег","full_name_suggest":{"input":["Копіца Олег Володимирович","Олег Володимирович Копіца","Олег Копіца"],"output":"Копіца Олег Володимирович"},"post_raw":"Суддя Комінтернівського районного суду Одеської області, суддя апеляційного суду Одеської області","name_unclear":false,"patronymic":"Володимирович","patronymic_unclear":false,"last_name_hidden":false,"patronymic_hidden":false,"inn":"","addresses_raw_hidden":true,"last_name":"Копіца","full_name":"Копіца Олег Володимирович","post":{"office":"Загальний місцевий суд","region":"Одеська область","post":"Суддя"},"addresses_raw":"приховано","name_hidden":false,"last_name_unclear":false},"liabilities":{"54":{"sum_comment":"","sum_foreign_comment":"","sum_foreign":"","sum":""},"55":{"sum_units":"","sum_comment":"","sum_foreign_units":"","sum":"","sum_foreign_comment":"","sum_foreign":""},"56":{"sum_comment":"","sum_foreign_comment":"","sum_foreign":"","sum":""},"57":{"sum_comment":"","sum_foreign_comment":"","sum_foreign":"","sum":""},"58":{"sum_comment":"","sum_foreign_comment":"","sum_foreign":"","sum":""},"59":{"sum_comment":"","sum_foreign_comment":"","sum_foreign":"","sum":""},"60":{"sum_comment":"","sum_foreign_comment":"","sum_foreign":"","sum":""},"61":{"sum_units":"","sum_comment":"","sum_foreign_units":"","sum":"","sum_foreign_comment":"","sum_foreign":""},"62":{"sum_comment":"","sum_foreign_comment":"","sum_foreign":"","sum":""},"63":{"sum_comment":"","sum_units":"","sum_foreign":"","sum":"","sum_foreign_comment":""},"64":{"sum_comment":"","sum_units":"","sum_foreign":"","sum":"","sum_foreign_comment":""}},"intro":{"isnotdeclaration":"FALSE","declaration_year":"2013"}}]