[{"id":"vulyk_67_113","ft_src":"1781 куб. см., 66.2 кВт , власність\nVolkswagen Passat\n1989\n2006\nPeugeot 407\n1997 куб. см., 105.18 кВт , користування\n2007\nMitsubishi Pajero\n2477 куб. см., 103 кВт , користування\n.0874\n2014\n38534\n182531\n38534\n182531\n1781 куб. см., 66.2 кВт , власність\nVolkswagen Passat\n1989\nPeugeot 407\n1997 куб. см., 105.18 кВт , користування\n2006\nMitsubishi Pajero\n2477 куб. см., 103 кВт , користування\n2007\n.0874\nЗагальний місцевий суд\nсуддя мукачівського міськрайонного суду закарпатської області\nЗакарпатська область\nПодружжя\nКость О. В\nКость Віталій Володимирович\nВіталій Володимирович Кость\nВіталій Кость\nКость Віталій Володимирович\nКость Віталій Володимирович\nВіталій\nКость\nВолодимирович\n38534\n182531\n182531\n38534\n2014\nПодружжя\nКость О. В\nВолодимирович\nКость\nВіталій\nКость Віталій Володимирович\nВіталій Володимирович Кость\nВіталій Кость\nКость Віталій Володимирович\nЗакарпатська область\nсуддя мукачівського міськрайонного суду закарпатської області\nЗагальний місцевий суд\nКость Віталій Володимирович","estate":{"23":[{"costs":"","address":"","space_units":"га","costs_hidden":false,"costs_rent_hidden":false,"space_unclear":false,"region_hidden":true,"space_units_unclear":false,"costs_comment":"","space_comment_unclear":false,"space_hidden":true,"address_unclear":false,"space_comment":"","address_hidden":true,"costs_rent_comment":"","space":".0874","region":"","costs_rent":""}]},"vehicle":{"35":[{"sum_comment_unclear":false,"brand_info":"1781 куб. см., 66.2 кВт , власність","brand_unclear":false,"sum_rent_comment":"","brand_hidden":false,"year":"1989","brand":"Volkswagen Passat","brand_info_hidden":false,"sum_rent":"","sum_rent_unclear":false,"sum_comment":"","year_unclear":false,"brand_info_unclear":true,"sum_unclear":false,"sum":""},{"sum_comment_unclear":false,"sum_comment":"","brand_info":"1997 куб. см., 105.18 кВт , користування","sum":"","sum_rent_comment":"","year":"2006","brand":"Peugeot 407","sum_rent":"","brand_info_unclear":true},{"sum_comment_unclear":false,"sum_comment":"","brand_info":"2477 куб. см., 103 кВт , користування","sum":"","sum_rent_comment":"","year":"2007","brand":"Mitsubishi Pajero","sum_rent":"","brand_info_unclear":true}]},"source":"VULYK","income":{"5":{"family":"38534","family_comment":"","comment":"","value_hidden":false,"value_unclear":false,"value":"182531"},"6":{"family_comment":"","family":"38534","comment":"","value_unclear":false,"family_unclear":false,"value":"182531"},"7":{"family_comment":"","comment":"","family":"","source_name_unclear":false,"value":"","family_hidden":false,"source_name":""},"8":{"family_comment":"","value":"","family":"","comment":""},"9":{"family_comment":"","value":"","family":"","comment":""},"10":{"family_comment":"","value":"","family":"","comment":""},"11":{"family_comment":"","value":"","family":"","comment":""},"12":{"family_comment":"","value":"","family":"","comment":""},"13":{"family_comment":"","value":"","family":"","comment":""},"14":{"family_comment":"","value":"","family":"","comment":""},"15":{"family_comment":"","value":"","family":"","comment":""},"16":{"family_comment":"","comment_unclear":false,"value":"","family":"","comment":""},"17":{"family_comment":"","value":"","family_unclear":false,"family":"","comment":""},"18":{"family_comment":"","value":"","family":"","comment":""},"19":{"family":"","family_comment":"","comment":"","value_hidden":false,"family_hidden":false,"value":""},"20":{"family_comment":"","comment_unclear":false,"value":"","family":"","comment":""}},"general":{"family":[{"inn":"","inn_unclear":false,"family_name":"Кость О. В","relations_hidden":false,"relations_unclear":false,"name_unclear":false,"relations":"Подружжя","inn_hidden":true,"name_hidden":true,"relations_other":""}],"family_raw":"","name":"Віталій","full_name_suggest":{"input":["Кость Віталій Володимирович","Віталій Володимирович Кость","Віталій Кость"],"output":"Кость Віталій Володимирович"},"name_unclear":false,"patronymic":"Володимирович","inn_hidden":true,"patronymic_unclear":false,"last_name_hidden":false,"inn":"","inn_unclear":false,"last_name":"Кость","full_name":"Кость Віталій Володимирович","post":{"post_hidden":false,"office":"Загальний місцевий суд","post":"суддя мукачівського міськрайонного суду закарпатської області","region":"Закарпатська область","office_hidden":false,"office_unclear":false,"region_hidden":false,"post_unclear":false},"addresses":[{"place_city_type_hidden":true,"place_district_hidden":true,"place_address_unclear":false,"place":"","place_city":"","place_unclear":false,"place_city_type":"","place_city_hidden":true,"place_city_unclear":false,"place_district":"","place_district_unclear":false,"place_address":"","place_address_hidden":true,"place_hidden":true}],"last_name_unclear":false},"liabilities":{"54":{"sum_comment_unclear":false,"sum_comment":"","sum_hidden":false,"sum":"","sum_foreign_comment":"","sum_foreign":"","sum_unclear":false,"sum_foreign_hidden":false},"55":{"sum_comment":"","sum_foreign_comment":"","sum_foreign":"","sum":""},"56":{"sum_comment":"","sum_hidden":false,"sum":"","sum_foreign_comment":"","sum_foreign":"","sum_unclear":false,"sum_foreign_hidden":false},"57":{"sum_comment_unclear":false,"sum_comment":"","sum_hidden":false,"sum":"","sum_foreign_comment":"","sum_foreign":"","sum_unclear":false,"sum_foreign_hidden":false,"sum_comment_hidden":false},"58":{"sum_comment_unclear":false,"sum_comment":"","sum_hidden":false,"sum":"","sum_foreign_comment":"","sum_foreign":"","sum_unclear":false,"sum_foreign_hidden":false,"sum_comment_hidden":false},"59":{"sum_comment":"","sum_foreign_comment":"","sum_foreign":"","sum_hidden":false,"sum":""},"60":{"sum_comment":"","sum_foreign_comment":"","sum_foreign":"","sum":""},"61":{"sum_comment":"","sum_hidden":false,"sum":"","sum_foreign_comment":"","sum_foreign":"","sum_foreign_hidden":false},"62":{"sum_comment":"","sum_foreign_comment":"","sum_foreign":"","sum_hidden":false,"sum":""},"63":{"sum_comment_unclear":false,"sum_comment":"","sum_hidden":false,"sum":"","sum_foreign_comment":"","sum_foreign":"","sum_unclear":false},"64":{"sum_comment":"","sum_hidden":false,"sum":"","sum_foreign_comment":"","sum_foreign":"","sum_unclear":false}},"declaration":{"notfull_lostpages":"","additional_info_text":"","additional_info":"","date":"2015-03-25T00:00:00","notfull":"","url":"http://static.declarations.com.ua/declarations/chosen_ones/mega_batch/kost_vitalii_volodymyrovych.pdf"},"intro":{"declaration_year_hidden":false,"isnotdeclaration":"","declaration_year":"2014"}}]