[{"id":"vulyk_86_76","ft_src":"1400 /40\nVolkswagen Polo\n1998\n1793 /118\nVolkswagen Passat B6\n2008\nм. Красноармійськ\n.0388\nДонецька область\nм. Красноармійськ\n.0064\nДонецька область\nм. Донецьк, кооператив Агат\n32\nДонецька область\nДонецька область\nм. Красноармійськ\n169.8\nДонецька область\nм. Красноармійськ\n25\n2014\n56018\n254672\n23215\n79233\n254672\n1400 /40\n1998\nVolkswagen Polo\n1793 /118\n2008\nVolkswagen Passat B6\n2014\nКоваленко Віктор Олександрович\nВіктор Олександрович Коваленко\nВіктор Коваленко\nКоваленко Віктор Олександрович\nКоваленко Віктор Олександрович\nПодружжя\nЧенченко Т. О\nДитина\nКоваленко М. В\nКоваленко П. В\nДитина\nВіктор\nКоваленко\nЗагальний місцевий суд\nДонецька область\nсуддя красноармійського міськрайонного суду донецької області\nОлександрович\n85300\nДонецька область\nКрасноармійськ\n6695\n254672\n56018\n23215\n254672\n79233\n.0388\nДонецька область\nм. Красноармійськ\nм. Красноармійськ\n.0064\nДонецька область\n169.8\nДонецька область\nм. Красноармійськ\nДонецька область\n32\nм. Донецьк, кооператив Агат\n25\nДонецька область\nм. Красноармійськ\n6695\nЧенченко Т. О\nПодружжя\nКоваленко М. В\nДитина\nДитина\nКоваленко П. В\nОлександрович\nКоваленко\nВіктор\nКоваленко Віктор Олександрович\nВіктор Олександрович Коваленко\nВіктор Коваленко\nКоваленко Віктор Олександрович\n85300\nКрасноармійськ\nДонецька область\nДонецька область\nЗагальний місцевий суд\nсуддя красноармійського міськрайонного суду донецької області\nКоваленко Віктор Олександрович","estate":{"23":[{"address":"м. Красноармійськ","space_units":"га","costs_comment":"","region_hidden":false,"space_comment":"","address_hidden":true,"costs":"","address_unclear":false,"costs_rent_comment":"","space":".0388","region":"Донецька область","costs_rent":""},{"costs":"","address":"м. Красноармійськ","space_units":"га","costs_rent_comment":"","space":".0064","space_comment":"","costs_comment":"","region":"Донецька область","costs_rent":""}],"24":[{"address":"м. Красноармійськ","space_units":"м²","costs_comment":"","space_comment":"","region_hidden":false,"region":"Донецька область","address_hidden":false,"space":"169.8","address_unclear":false,"costs_rent_comment":"","costs":"","costs_rent":""}],"27":[{"costs":"","address":"м. Донецьк, кооператив Агат","space_units":"м²","costs_rent_comment":"","space":"32","space_comment":"","region_hidden":false,"costs_comment":"","region":"Донецька область","address_hidden":true,"costs_rent":""}],"28":[{"address":"м. Красноармійськ","space_units":"м²","costs_comment":"","space_comment":"","region_hidden":false,"region":"Донецька область","address_hidden":false,"space":"25","address_unclear":false,"costs_rent_comment":"","costs":"","costs_rent":""}]},"vehicle":{"35":[{"sum_comment":"","brand_info":"1400 /40","brand_unclear":false,"sum_rent_comment":"","year":"1998","brand":"Volkswagen Polo","sum_rent":"","brand_info_unclear":false,"year_unclear":false,"sum":""},{"sum_comment":"","sum_rent":"","sum":"","brand_unclear":false,"year":"2008","brand":"Volkswagen Passat B6","brand_info":"1793 /118","sum_rent_comment":"","year_unclear":false}]},"source":"VULYK","income":{"5":{"family_comment":"","value":"254672","family":"79233","comment":""},"6":{"family_comment":"","value":"254672","family":"56018","comment":"","family_comment_unclear":false},"7":{"source_name_hidden":false,"family_comment":"","comment":"","family":"","comment_hidden":false,"value":"","source_name":""},"8":{"family_comment":"","value":"","family":"","comment":""},"9":{"family_comment":"","value":"","family":"","comment":""},"10":{"family":"","family_comment":"","comment":"","value_hidden":false,"value_unclear":false,"value":""},"11":{"family_comment":"","value":"","family":"","comment":""},"12":{"family_comment":"","value":"","family":"","comment":""},"13":{"family_comment":"","value":"","family":"","comment":""},"14":{"family_comment":"","value":"","family":"","comment":""},"15":{"family_comment":"","value":"","family":"23215","comment":""},"16":{"family_comment":"","value":"","family":"","comment":""},"17":{"family_comment":"","value":"","family":"","comment":""},"18":{"family_comment":"","value":"","family":"","comment":""},"19":{"family_comment":"","value":"","family":"","comment":""},"20":{"family_comment":"","comment_unclear":false,"value":"","family":"","comment":""}},"general":{"family_raw":"","name":"Віктор","full_name_suggest":{"input":["Коваленко Віктор Олександрович","Віктор Олександрович Коваленко","Віктор Коваленко"],"output":"Коваленко Віктор Олександрович"},"patronymic":"Олександрович","inn_hidden":true,"patronymic_unclear":false,"inn":"","inn_unclear":false,"last_name":"Коваленко","full_name":"Коваленко Віктор Олександрович","family":[{"inn":"","family_name":"Ченченко Т. О","relations_other":"","relations_hidden":false,"name_unclear":false,"inn_hidden":true,"name_hidden":false,"relations":"Подружжя"},{"inn":"","family_name":"Коваленко М. В","relations_other":"","name_unclear":false,"inn_hidden":false,"name_hidden":false,"relations":"Дитина"},{"inn":"","name_unclear":false,"family_name":"Коваленко П. В","inn_hidden":false,"relations":"Дитина"}],"post":{"office":"Загальний місцевий суд","post":"суддя красноармійського міськрайонного суду донецької області","candidate":"","region_hidden":false,"region":"Донецька область","office_hidden":false,"post_unclear":false,"office_unclear":false},"addresses":[{"place_city_type":"Місто","place_city_type_hidden":false,"place_district_hidden":false,"place_city_hidden":false,"place_district":"","place_hidden":false,"place_address":"85300","place":"Донецька область","place_city":"Красноармійськ","place_address_hidden":true,"place_unclear":false}]},"liabilities":{"54":{"sum_comment":"","sum_foreign_comment":"","sum_foreign":"","sum_unclear":false,"sum":""},"55":{"sum_comment":"","sum_foreign_comment":"","sum_foreign":"","sum":""},"56":{"sum_comment":"","sum_foreign_comment":"","sum_foreign":"","sum_hidden":false,"sum":"6695"},"57":{"sum_comment":"","sum_foreign_comment":"","sum_foreign":"","sum_unclear":false,"sum":""},"58":{"sum_comment":"","sum_foreign_comment":"","sum_foreign":"","sum_unclear":false,"sum":""},"59":{"sum_comment":"","sum_foreign_comment":"","sum_foreign":"","sum":""},"60":{"sum_comment":"","sum_foreign_comment":"","sum_foreign":"","sum":"","sum_comment_hidden":false},"61":{"sum_comment":"","sum_foreign_comment":"","sum_foreign":"","sum":""},"62":{"sum_comment":"","sum_foreign_comment":"","sum_foreign":"","sum":""},"63":{"sum_comment":"","sum_foreign_comment":"","sum_foreign":"","sum":""},"64":{"sum_comment":"","sum_foreign_comment":"","sum_foreign":"","sum":""}},"declaration":{"notfull_lostpages":"","additional_info_text":"","additional_info":"","date":"2015-03-23T00:00:00","notfull":"","url":"http://static.declarations.com.ua/declarations/chosen_ones/judges_batch/2779_kovalenko_viktor_oleksandrovych.pdf"},"intro":{"declaration_year_unclear":false,"declaration_year":"2014"}}]