[{"id":"vulyk_96_39","ft_src":"причіп\n2013\nСтарконь\n2400\nLandwind X6\n2008\n2015\n180436\n12180\n192616\n2400\nLandwind X6\n2008\nпричіп\n2013\nСтарконь\n180436\n192616\n12180\nКовтуненко\nКовтуненко Віталій Володимирович\nВіталій Володимирович Ковтуненко\nВіталій Ковтуненко\nКовтуненко Віталій Володимирович\nКовтуненко Віталій Володимирович\nВіталій\nВолодимирович\nВолинська область\nсуддя луцького міськрайонного суду волинської області\nЗагальний місцевий суд\n36000\n24500\n2015\n36000\n24500\nВолодимирович\nКовтуненко\nсуддя луцького міськрайонного суду волинської області\nВолинська область\nЗагальний місцевий суд\nКовтуненко Віталій Володимирович\nКовтуненко Віталій Володимирович\nВіталій Володимирович Ковтуненко\nВіталій Ковтуненко\nКовтуненко Віталій Володимирович\nВіталій","vehicle":{"35":[{"year_hidden":false,"brand_info":"2400","sum_rent_comment":"","brand_unclear":true,"brand_hidden":false,"year":"2008","brand":"Landwind X6","brand_info_hidden":false,"sum_rent":"","sum_comment":"","year_unclear":false,"sum_unclear":false,"sum":""}],"39":[{"sum_comment":"","brand_info":"причіп","sum":"","sum_rent_comment":"","year":"2013","brand":"Старконь","sum_rent":""}]},"source":"VULYK","income":{"5":{"family_comment":"","value":"192616","family_unclear":false,"family":"","comment":""},"6":{"family_comment":"","family":"","comment":"","value_unclear":false,"family_unclear":false,"value":"180436"},"7":{"source_name_hidden":false,"family_comment":"","family":"","comment":"","value_unclear":false,"family_unclear":false,"value":"","source_name":""},"8":{"family_comment":"","value":"","family":"","comment":""},"9":{"family_comment":"","value":"","family":"","comment":""},"10":{"family_comment":"","value":"12180","family":"","comment":"","value_unclear":false},"11":{"family_comment":"","value":"","family":"","comment":""},"12":{"family_comment":"","value":"","family":"","comment":""},"13":{"family_comment":"","value":"","family":"","comment":""},"14":{"family_comment":"","value":"","family":"","comment":""},"15":{"family_comment":"","value":"","family":"","comment":""},"16":{"family_comment":"","value":"","family":"","comment":""},"17":{"family_comment":"","value":"","family":"","comment":""},"18":{"family_comment":"","value":"","family":"","comment":""},"19":{"family_comment":"","value":"","family":"","comment":""},"20":{"family_comment":"","comment":"","family":"","value_unclear":false,"comment_hidden":false,"comment_unclear":false,"value":""}},"general":{"patronymic_hidden":false,"inn":"","addresses":[{"place_city_type_hidden":false,"place_city_type":"","place_city_hidden":false,"place_hidden":true,"place_district":"","place_district_hidden":false,"place":"","place_address":"","place_address_hidden":true,"place_city":""}],"last_name":"Ковтуненко","full_name_suggest":{"input":["Ковтуненко Віталій Володимирович","Віталій Володимирович Ковтуненко","Віталій Ковтуненко"],"output":"Ковтуненко Віталій Володимирович"},"full_name":"Ковтуненко Віталій Володимирович","patronymic":"Володимирович","inn_hidden":true,"name":"Віталій","post":{"office_unclear":false,"post":"суддя луцького міськрайонного суду волинської області","region":"Волинська область","office":"Загальний місцевий суд"},"family_raw":""},"liabilities":{"54":{"sum_comment":"","sum_hidden":false,"sum":"","sum_foreign_comment":"","sum_foreign":"","sum_comment_hidden":false},"55":{"sum_comment":"","sum_foreign_comment":"","sum_foreign":"","sum":""},"56":{"sum_comment":"","sum_foreign_comment":"","sum_foreign":"","sum_unclear":true,"sum":"24500"},"57":{"sum_comment":"","sum_foreign_comment":"","sum_foreign":"","sum":"36000","sum_comment_hidden":false},"58":{"sum_comment":"","sum":"","sum_foreign_comment":"","sum_foreign":"","sum_unclear":false,"sum_comment_hidden":false},"59":{"sum_comment":"","sum_foreign_comment":"","sum_foreign":"","sum":""},"60":{"sum_comment":"","sum_foreign_comment":"","sum_foreign":"","sum":"","sum_comment_hidden":false},"61":{"sum_comment":"","sum_foreign_comment":"","sum_foreign":"","sum":""},"62":{"sum_comment":"","sum_foreign_comment":"","sum_foreign":"","sum":""},"63":{"sum_comment":"","sum_foreign_comment":"","sum_foreign":"","sum":"","sum_comment_hidden":false},"64":{"sum_comment":"","sum_foreign_comment":"","sum_foreign":"","sum":"","sum_comment_hidden":false}},"declaration":{"notfull_lostpages":"","additional_info_text":"","additional_info":"","date":"2016-03-29T00:00:00","notfull":"","url":"http://static.declarations.com.ua/declarations/chosen_ones/judges_batch/253_kovtunenko_vitalii_volodymyrovych_2015.pdf"},"intro":{"isnotdeclaration":"","declaration_year":"2015"}},{"id":"vulyk_100_169","ft_src":"1800 куб. см.\nChevrolet Lacetti\n2008\n2014\n191165\n12180\n203345\n1800 куб. см.\nChevrolet Lacetti\n2008\n2014\nЗагальний місцевий суд\nВолинська область\nсуддя луцького міськрайонного суду волинської області\nВолодимирович\nКовтуненко Віталій Володимирович\nВіталій Володимирович Ковтуненко\nВіталій Ковтуненко\nКовтуненко Віталій Володимирович\nКовтуненко Віталій Володимирович\nВіталій\nКовтуненко\n36000\n18000\n191165\n203345\n12180\n36000\n18000\nВолодимирович\nКовтуненко\nВолинська область\nЗагальний місцевий суд\nсуддя луцького міськрайонного суду волинської області\nКовтуненко Віталій Володимирович\nКовтуненко Віталій Володимирович\nВіталій Володимирович Ковтуненко\nВіталій Ковтуненко\nКовтуненко Віталій Володимирович\nВіталій","vehicle":{"35":[{"brand_info":"1800 куб. см.","sum_rent_comment":"","brand_unclear":false,"sum_rent_comment_unclear":false,"brand_hidden":false,"sum_comment":"","brand_info_hidden":false,"sum_rent":"","brand":"Chevrolet Lacetti","brand_info_unclear":false,"year":"2008","sum":""}]},"source":"VULYK","income":{"5":{"family_comment":"","family":"","comment":"","value_unclear":false,"family_unclear":false,"value":"203345"},"6":{"family_comment":"","value":"191165","family":"","comment":"","value_unclear":false},"7":{"family_comment":"","comment":"","family":"","value_unclear":false,"value":"","source_name":""},"8":{"family_comment":"","value":"","family":"","comment":""},"9":{"family_comment":"","family":"","comment":"","value_unclear":false,"family_unclear":false,"value":""},"10":{"family_comment":"","comment_unclear":false,"value":"12180","family":"","comment":""},"11":{"family_comment":"","value":"","family":"","comment":""},"12":{"family_comment":"","value":"","family":"","comment":""},"13":{"family_comment":"","value":"","family":"","comment":"","value_unclear":false},"14":{"family_comment":"","value":"","family":"","comment":""},"15":{"family_comment":"","value":"","family":"","comment":""},"16":{"family_comment":"","value":"","family_unclear":false,"family":"","comment":""},"17":{"family_comment":"","value":"","family_unclear":false,"family":"","comment":""},"18":{"family_comment":"","value":"","family":"","comment":""},"19":{"family_comment":"","value":"","family":"","comment":""},"20":{"family":"","family_comment":"","comment":"","value_hidden":false,"value_unclear":false,"value":"","comment_unclear":false,"family_unclear":false,"family_hidden":false}},"general":{"inn":"","addresses":[{"place_city_type":"","place_city_type_hidden":false,"place_hidden":true,"place_city_hidden":false,"place_district_hidden":false,"place_district":"","place_city_unclear":false,"place":"","place_city":"","place_address_hidden":true,"place_address":""}],"last_name":"Ковтуненко","full_name_suggest":{"input":["Ковтуненко Віталій Володимирович","Віталій Володимирович Ковтуненко","Віталій Ковтуненко"],"output":"Ковтуненко Віталій Володимирович"},"full_name":"Ковтуненко Віталій Володимирович","patronymic":"Володимирович","inn_hidden":true,"name":"Віталій","post":{"post_hidden":false,"office":"Загальний місцевий суд","post":"суддя луцького міськрайонного суду волинської області","office_unclear":false,"region_unclear":false,"region":"Волинська область","post_unclear":false},"family_raw":""},"liabilities":{"54":{"sum_comment":"","sum":"","sum_foreign_comment":"","sum_foreign":"","sum_unclear":false,"sum_comment_hidden":false},"55":{"sum_comment":"","sum_foreign_comment":"","sum_foreign":"","sum":""},"56":{"sum_comment":"","sum_foreign_comment":"","sum_foreign":"","sum_unclear":false,"sum":"18000"},"57":{"sum_comment_unclear":false,"sum_comment":"","sum":"36000","sum_foreign_comment":"","sum_foreign":"","sum_unclear":false,"sum_comment_hidden":false},"58":{"sum_comment":"","sum":"","sum_foreign_comment":"","sum_foreign":"","sum_unclear":false,"sum_comment_hidden":false},"59":{"sum_comment":"","sum_foreign_comment":"","sum_foreign":"","sum":""},"60":{"sum_comment":"","sum_foreign_comment":"","sum_foreign":"","sum":"","sum_comment_hidden":false},"61":{"sum_comment":"","sum_foreign_comment":"","sum_foreign":"","sum":""},"62":{"sum_comment":"","sum_foreign_comment":"","sum_foreign":"","sum_unclear":false,"sum":""},"63":{"sum_comment":"","sum_foreign_comment":"","sum_foreign":"","sum":"","sum_comment_hidden":false},"64":{"sum_comment":"","sum_foreign_comment":"","sum_foreign":"","sum":"","sum_comment_hidden":false}},"declaration":{"notfull_lostpages":"","additional_info_text":"","additional_info":"","date":"2015-03-26T00:00:00","notfull":"","url":"http://static.declarations.com.ua/declarations/chosen_ones/judges_batch/4439_kovtunenko_vitalii_volodymyrovych.pdf"},"intro":{"declaration_year":"2014"}}]