[{"ft_src":"користування\nOpel,Vectra\n2008\nкористування\nOpel,Corsa\n2008\nвласність\nКРАЗ,8138\n1993\nOpel,Vectra\n2008\nOpel,Corsa\n2008\n960\n660\n3000\n70000\n353,9\n100\n1035\n36\n250\n250\nFALSE\nЗемельну ділянку записав як Інше майно, не було куди 4ту ділянку вписати.\nFALSE\nFALSE\n2013\n74530\n286345\n15360\n12617\n129456\n322360\n39566\n19783\n3515\nOpel,Vectra\n2008\nкористування\nOpel,Corsa\n2008\nкористування\nКРАЗ,8138\n1993\nвласність\nOpel,Vectra\n2008\nOpel,Corsa\n2008\nЗемельну ділянку записав як Інше майно, не було куди 4ту ділянку вписати.\nFALSE\nFALSE\n960\n660\n3000\n1035\n70000\n353,9\n100\n36\nСуддя, голова аппеляційного суду Закарпатської області\nДружина Крегул Ольга Юріївна 2 серпня 1960 р.;дочка Крегул Галина Миколаївна 29 січня 1989 р.\nКрегул\nКрегул Микола Миколайович\nМикола Миколайович Крегул\nМикола Крегул\nКрегул Микола Миколайович\nМикола\nКрегул Микола Миколайович\nЗагальний апеляційний суд\nСуддя, голова аппеляційного суду Закарпатської області\nЗакарпатська область\nМиколайович\n25000\n286345\n74530\n15360\n322360\n129456\n19783\n39566\n12617\n3515\n250\n250\n2013\nFALSE\n25000\nКрегул\nМиколайович\nДружина Крегул Ольга Юріївна 2 серпня 1960 р.;дочка Крегул Галина Миколаївна 29 січня 1989 р.\nКрегул Микола Миколайович\nМикола Миколайович Крегул\nМикола Крегул\nКрегул Микола Миколайович\nМикола\nСуддя, голова аппеляційного суду Закарпатської області\nСуддя, голова аппеляційного суду Закарпатської області\nЗакарпатська область\nЗагальний апеляційний суд\nКрегул Микола Миколайович","estate":{"23":[{"costs":"","address":"","space_units":"","costs_rent_comment":"","space":"960","costs_comment":"","costs_rent":"","space_comment":"","region":"","location_raw":"приховано"},{"costs":"","address":"","space_units":"","costs_rent_comment":"","space":"660","costs_comment":"","costs_rent":"","space_comment":"","region":"","location_raw":"приховано"},{"costs":"","address":"","space_units":"","costs_rent_comment":"","space":"3000","costs_comment":"","costs_rent":"","space_comment":"","region":"","location_raw":"приховано"}],"24":[{"costs":"","address":"","space_units":"","costs_rent_comment":"","space":"353,9","costs_comment":"","costs_rent":"70000","space_comment":"","region":"","location_raw":"приховано"},{"costs":"","address":"","space_units":"","costs_rent_comment":"","space":"100","costs_comment":"","costs_rent":"","space_comment":"","region":"","location_raw":"приховано"}],"26":[{"costs":"","address":"","space_units":"","costs_rent_comment":"","space":"36","costs_comment":"","costs_rent":"","space_comment":"","region":"","location_raw":"приховано"}],"28":[{"costs":"","address":"","space_units":"","costs_rent_comment":"","space":"","costs_comment":"","costs_rent":"","space_comment":"","region":"","location_raw":"приховано"}],"29":[{"costs_property_comment":"","address":"","space_units":"","costs_rent_comment":"","space":"1035","space_comment":"","costs_property":"","region":"","location_raw":"приховано","costs_rent":""}]},"vehicle":{"35":[{"sum_comment":"користування","brand_info":"","sum":"","sum_rent_comment":"","year":"2008","brand":"Opel,Vectra","sum_rent":"","brand_hidden":false},{"sum_comment":"користування","brand_info":"","sum":"","sum_rent_comment":"","year":"2008","brand":"Opel,Corsa","sum_rent":"","brand_hidden":false},{"sum_comment":"власність","brand_info":"","sum":"","sum_rent_comment":"","year":"1993","brand":"КРАЗ,8138","sum_rent":"","brand_hidden":false}],"40":[{"sum_comment":"","brand_info":"","sum":"","sum_rent_comment":"","year":"2008","brand":"Opel,Vectra","sum_rent":"","brand_hidden":false},{"sum_comment":"","brand_info":"","sum":"","sum_rent_comment":"","year":"2008","brand":"Opel,Corsa","sum_rent":"","brand_hidden":false}]},"id":"6647","income":{"5":{"family_comment":"","value":"322360","family":"129456","comment":""},"6":{"family_comment":"","value":"286345","family":"74530","comment":""},"7":{"family":"0","family_comment":"","value":"0","comment":"","source_name":"0"},"8":{"family_comment":"","value":"0","family":"0","comment":""},"9":{"family_comment":"","value":"3515","family":"0","comment":""},"10":{"family_comment":"","value":"12617","family":"0","comment":""},"11":{"family_comment":"","value":"0","family":"0","comment":""},"12":{"family_comment":"","value":"0","family":"0","comment":""},"13":{"family_comment":"","value":"0","family":"0","comment":""},"14":{"family_comment":"","value":"0","family":"0","comment":""},"15":{"family_comment":"","value":"0","family":"15360","comment":""},"16":{"family_comment":"","value":"19783","family":"39566","comment":""},"17":{"family_comment":"","value":"0","family":"0","comment":""},"18":{"family_comment":"","value":"0","family":"0","comment":""},"19":{"family_comment":"","value":"0","family":"0","comment":""},"20":{"family_comment":"","value":"0","family":"0","comment":""},"21":[{"country_comment":"","uah_equal":"0","country":"0","cur":"0"},{"country_comment":"","uah_equal":"0","country":"0","cur":"0"},{"country_comment":"","uah_equal":"0","country":"0","cur":"0"},{"country_comment":"","uah_equal":"0","country":"0","cur":"0"},{"country_comment":"","uah_equal":"0","country":"0","cur":"0"}],"22":[{"country_comment":"","uah_equal":"0","country":"0","cur":"0"},{"country_comment":"","uah_equal":"0","country":"0","cur":"0"},{"country_comment":"","uah_equal":"0","country":"0","cur":"0"},{"country_comment":"","uah_equal":"0","country":"0","cur":"0"},{"country_comment":"","uah_equal":"0","country":"0","cur":"0"}]},"banks":{"45":[{"sum_units":"UAH","sum_comment":"","sum_foreign_units":"","sum":"","sum_foreign_comment":"","sum_foreign":""},{"sum_units":"USD","sum_comment":"","sum_foreign_units":"","sum":"","sum_foreign_comment":"","sum_foreign":""},{"sum_units":"EUR","sum_comment":"","sum_foreign_units":"","sum":"","sum_foreign_comment":"","sum_foreign":""}],"46":[{"sum_units":"UAH","sum_comment":"","sum_foreign_units":"","sum":"","sum_foreign_comment":"","sum_foreign":""},{"sum_units":"USD","sum_comment":"","sum_foreign_units":"","sum":"","sum_foreign_comment":"","sum_foreign":""},{"sum_units":"EUR","sum_comment":"","sum_foreign_units":"","sum":"","sum_foreign_comment":"","sum_foreign":""}],"47":[{"sum_units":"","sum_comment":"","sum_foreign_units":"","sum":"250","sum_foreign_comment":"","sum_foreign":""}],"48":[{"sum_units":"","sum_comment":"","sum_foreign_units":"","sum":"","sum_foreign_comment":"","sum_foreign":""}],"49":[{"sum_units":"","sum_comment":"","sum_foreign_units":"","sum":"","sum_foreign_comment":"","sum_foreign":""}],"50":[{"sum_units":"","sum_comment":"","sum_foreign_units":"","sum":"","sum_foreign_comment":"","sum_foreign":""}],"51":[{"sum_units":"UAH","sum_comment":"","sum_foreign_units":"","sum":"","sum_foreign_comment":"","sum_foreign":""},{"sum_units":"USD","sum_comment":"","sum_foreign_units":"","sum":"","sum_foreign_comment":"","sum_foreign":""},{"sum_units":"EUR","sum_comment":"","sum_foreign_units":"","sum":"","sum_foreign_comment":"","sum_foreign":""}],"52":[{"sum_units":"","sum_comment":"","sum_foreign_units":"","sum":"250","sum_foreign_comment":"","sum_foreign":""}],"53":[{"sum_units":"","sum_comment":"","sum_foreign_units":"","sum":"","sum_foreign_comment":"","sum_foreign":""}]},"declaration":{"notfull_lostpages":"","additional_info_text":"Земельну ділянку записав як Інше майно, не було куди 4ту ділянку вписати.","additional_info":"FALSE","notfull":"FALSE","url":"http://static.declarations.com.ua/declarations/sudy/apeliatsiini_sudy_oblastei__m.kyieva/zakarpatska/kregyl.pdf","needs_scancopy_check":false},"general":{"family_raw":"Дружина Крегул Ольга Юріївна 2 серпня 1960 р.;дочка Крегул Галина Миколаївна 29 січня 1989 р.","name":"Микола","full_name_suggest":{"input":["Крегул Микола Миколайович","Микола Миколайович Крегул","Микола Крегул"],"output":"Крегул Микола Миколайович"},"post_raw":"Суддя, голова аппеляційного суду Закарпатської області","name_unclear":false,"patronymic":"Миколайович","patronymic_unclear":false,"last_name_hidden":false,"patronymic_hidden":false,"inn":"","addresses_raw_hidden":true,"last_name":"Крегул","full_name":"Крегул Микола Миколайович","post":{"office":"Загальний апеляційний суд","region":"Закарпатська область","post":"Суддя, голова аппеляційного суду Закарпатської області"},"addresses_raw":"приховано","name_hidden":false,"last_name_unclear":false},"liabilities":{"54":{"sum_comment":"","sum_foreign_comment":"","sum_foreign":"","sum":""},"55":{"sum_units":"","sum_comment":"","sum_foreign_units":"","sum":"","sum_foreign_comment":"","sum_foreign":""},"56":{"sum_comment":"","sum_foreign_comment":"","sum_foreign":"","sum":"25000"},"57":{"sum_comment":"","sum_foreign_comment":"","sum_foreign":"","sum":""},"58":{"sum_comment":"","sum_foreign_comment":"","sum_foreign":"","sum":""},"59":{"sum_comment":"","sum_foreign_comment":"","sum_foreign":"","sum":""},"60":{"sum_comment":"","sum_foreign_comment":"","sum_foreign":"","sum":""},"61":{"sum_units":"","sum_comment":"","sum_foreign_units":"","sum":"","sum_foreign_comment":"","sum_foreign":""},"62":{"sum_comment":"","sum_foreign_comment":"","sum_foreign":"","sum":""},"63":{"sum_comment":"","sum_units":"","sum_foreign":"","sum":"","sum_foreign_comment":""},"64":{"sum_comment":"","sum_units":"","sum_foreign":"","sum":"","sum_foreign_comment":""}},"intro":{"isnotdeclaration":"FALSE","declaration_year":"2013"}}]