[{"id":"vulyk_41_70","declaration":{"additional_info_text":"","additional_info":"","date":"2015-03-23T00:00:00","url":"http://static.declarations.com.ua/declarations/chosen_ones/mega_batch/kuchma_kostiantyn_serhiiovych.pdf"},"estate":{"23":[{"address":"","space_units":"м²","costs_comment":"","space_unclear":false,"region_hidden":false,"space_units_unclear":false,"space_comment":"","address_hidden":false,"space_comment_hidden":false,"space":"","costs_comment_unclear":false,"costs_rent_comment":"","costs":"","region_unclear":false,"region":"","costs_rent":""},{"costs":"","address":"","space_units":"","costs_rent_comment":"","space":"","space_unclear":false,"space_comment":"","costs_comment":"","region":"","costs_rent":""},{"costs":"","address":"","space_units":"","costs_rent_comment":"","space":"","space_comment":"","costs_comment":"","region":"","costs_rent":""}],"25":[{"costs_unclear":false,"address":"м. Дніпропетровськ","space_units":"м²","space_hidden":false,"space_unclear":false,"region_hidden":false,"costs_rent_comment":"","space_comment":"1/3 частина квартири","address_hidden":true,"costs":"","costs_comment_unclear":false,"costs_comment":"","space":"54","region_unclear":false,"region":"Дніпропетровська область","costs_rent":""}],"29":[{"costs_property_comment":"","costs_property":"","address":"м. Кривий Ріг","space_units":"м²","space_unclear":false,"region_hidden":false,"space_units_unclear":false,"space_comment":"","address_hidden":true,"costs_rent_comment":"","space":"600","region":"Дніпропетровська область","costs_rent":""}],"30":[{"costs_property_comment":"","address":"м. Кривий Ріг","space_units":"м²","costs_rent_comment":"","space":"135.7","region":"Дніпропетровська область","region_hidden":false,"costs_property":"","space_comment":"","address_hidden":true,"costs_rent":""}],"31":[{"costs_property_comment":"","address":"м. Дніпропетровськ","space_units":"м²","space_hidden":false,"space_comment":"2/3 частини квартири","region_hidden":false,"costs_property":"","region":"Дніпропетровська область","address_hidden":true,"space_comment_unclear":false,"costs_rent_comment":"","space":"54","costs_rent":""},{"costs_property_comment":"","address":"м. Дніпропетровськ","space_units":"м²","costs_rent_comment":"","space":"100.3","region":"Дніпропетровська область","costs_property":"","space_comment":"","space_comment_unclear":false,"costs_rent":""}],"33":[{"costs_property_comment":"","address":"м. Кривий Ріг","space_units":"м²","costs_rent_comment":"","space":"24.1","region":"Дніпропетровська область","region_hidden":false,"costs_property":"","space_comment":"","address_hidden":true,"costs_rent":""}]},"vehicle":{"40":[{"sum_comment":"","brand_info_hidden":false,"brand_info":"1800 куб. см. 160 кВт","sum":"","sum_rent_comment":"","year":"2008","brand":"Volkswagen Passat B6","sum_rent":""}]},"source":"VULYK","income":{"5":{"family_comment":"","family":"83664","comment":"","family_unclear":false,"family_hidden":false,"value":"180110"},"6":{"family_comment":"","family_hidden":false,"value":"179762","family":"","comment":""},"7":{"family":"","family_comment":"","value":"","comment":"","source_name":""},"8":{"family_comment":"","value":"","family":"","comment":""},"9":{"family_comment":"","comment":"","family":"","comment_unclear":false,"value":"","family_hidden":false},"10":{"family_comment":"","value":"","family":"","comment":""},"11":{"family_comment":"","value":"","family":"","comment":""},"12":{"family_comment":"","value":"","family":"","comment":""},"13":{"family_comment":"","value":"","family":"","comment":""},"14":{"family_comment":"","value":"","family":"","comment":""},"15":{"family_comment":"","value":"","family":"","comment":"","value_unclear":false},"16":{"family_comment":"","value":"","family":"","comment":""},"17":{"family_comment":"","value":"","family":"","comment":""},"18":{"family_comment":"","value":"","family":"","comment":""},"19":{"family_comment":"","value":"","family":"","comment":""},"20":{"family_comment":"","family":"83664","value_hidden":false,"comment":"","comment_hidden":false,"comment_unclear":false,"value_unclear":false,"value":"348","family_hidden":false,"family_comment_hidden":false}},"banks":{"45":[{"sum_units":"UAH","sum_comment":"","sum_foreign_units":"UAH","sum_hidden":false,"sum":"","sum_foreign_comment":"","sum_foreign_unclear":false,"sum_foreign":"","sum_comment_hidden":false},{"sum_units":"","sum_comment":"","sum_foreign_units":"","sum":"","sum_foreign_comment":"","sum_foreign_unclear":false,"sum_foreign":""}],"46":[{"sum_units":"UAH","sum_comment":"","sum_foreign_units":"UAH","sum":"","sum_foreign_comment":"","sum_foreign":"","sum_unclear":false,"sum_comment_hidden":false},{"sum_units":"","sum_comment":"","sum_foreign_units":"","sum":"","sum_foreign_comment":"","sum_foreign":"","sum_unclear":false}],"47":[{"sum_units":"UAH","sum_comment":"","sum_foreign_units":"UAH","sum":"","sum_foreign_comment":"","sum_foreign":""},{"sum_units":"","sum_comment":"","sum_foreign_units":"","sum":"","sum_foreign_comment":"","sum_foreign":""}],"48":[{"sum_units":"UAH","sum_comment":"","sum_foreign_units":"UAH","sum":"","sum_foreign_comment":"","sum_foreign":""}],"49":[{"sum_units":"UAH","sum_comment":"","sum_foreign_units":"UAH","sum":"","sum_foreign_comment":"","sum_foreign":""}],"50":[{"sum_units":"UAH","sum_comment":"","sum_foreign_units":"UAH","sum":"","sum_foreign_comment":"","sum_foreign":""}],"51":[{"sum_units":"UAH","sum_comment":"","sum_foreign_units":"UAH","sum_hidden":false,"sum":"","sum_foreign_comment":"","sum_foreign":"","sum_unclear":false,"sum_comment_hidden":false},{"sum_units":"","sum_comment":"","sum_foreign_units":"","sum":"","sum_foreign_comment":"","sum_foreign":""}],"52":[{"sum_units":"UAH","sum_comment":"","sum_foreign_units":"UAH","sum":"","sum_foreign_comment":"","sum_foreign":"","sum_unclear":false,"sum_comment_hidden":false}],"53":[{"sum_units":"UAH","sum_comment":"","sum_foreign_units":"UAH","sum":"","sum_foreign_comment":"","sum_foreign":"","sum_comment_hidden":false},{"sum_units":"","sum_comment":"","sum_foreign_units":"","sum":"","sum_foreign_comment":"","sum_foreign":""},{"sum_units":"","sum_comment":"","sum_foreign_units":"","sum":"","sum_foreign_comment":"","sum_foreign":""}]},"ft_src":"1800 куб. см. 160 кВт\n2008\nVolkswagen Passat B6\n2014\nVolkswagen Passat B6\n1800 куб. см. 160 кВт\n2008\n135.7\nм. Кривий Ріг\nДніпропетровська область\n54\n1/3 частина квартири\nм. Дніпропетровськ\nДніпропетровська область\n24.1\nм. Кривий Ріг\nДніпропетровська область\n600\nм. Кривий Ріг\nДніпропетровська область\n54\n2/3 частини квартири\nм. Дніпропетровськ\nДніпропетровська область\n100.3\nДніпропетровська область\nм. Дніпропетровськ\nБатьки\nКучма С. В\nБатьки\nКучма Г. І\nКучма Костянтин Сергійович\nКостянтин Сергійович Кучма\nКостянтин Кучма\nКучма Костянтин Сергійович\nКучма Костянтин Сергійович\nКостянтин\nСергійович\nАдміністративний місцевий суд\nсуддя дніпропетровського окружного адміністративного суду\nДніпропетровська область\nКучма\nДніпропетровська область\nДніпропетровськ\n1501\n179762\n348\n83664\n180110\n83664\n2014\n1501\nм. Кривий Ріг\nДніпропетровська область\n600\nДніпропетровська область\nм. Кривий Ріг\n24.1\nДніпропетровська область\nм. Кривий Ріг\n135.7\n2/3 частини квартири\nм. Дніпропетровськ\nДніпропетровська область\n54\nДніпропетровська область\nм. Дніпропетровськ\n100.3\n1/3 частина квартири\nм. Дніпропетровськ\n54\nДніпропетровська область\nКучма С. В\nБатьки\nКучма Г. І\nБатьки\nСергійович\nКучма\nКостянтин\nКучма Костянтин Сергійович\nКостянтин Сергійович Кучма\nКостянтин Кучма\nКучма Костянтин Сергійович\nДніпропетровська область\nДніпропетровськ\nДніпропетровська область\nсуддя дніпропетровського окружного адміністративного суду\nАдміністративний місцевий суд\nКучма Костянтин Сергійович\n179762\n83664\n180110\n83664\n348","general":{"family":[{"inn":"","family_name":"Кучма С. В","relations_hidden":false,"name_unclear":false,"inn_hidden":true,"name_hidden":true,"relations":"Батьки"},{"inn":"","family_name":"Кучма Г. І","relations_other":"","name_unclear":false,"inn_hidden":false,"name_hidden":false,"relations":"Батьки"}],"family_raw":"","name":"Костянтин","full_name_suggest":{"input":["Кучма Костянтин Сергійович","Костянтин Сергійович Кучма","Костянтин Кучма"],"output":"Кучма Костянтин Сергійович"},"name_unclear":false,"patronymic":"Сергійович","inn_hidden":true,"patronymic_hidden":false,"inn":"","addresses":[{"place_city_type_hidden":false,"place_city_type":"Місто","place_city_hidden":false,"place_hidden":true,"place_district":"","place_district_hidden":false,"place":"Дніпропетровська область","place_address":"","place_address_hidden":true,"place_city":"Дніпропетровськ"}],"last_name":"Кучма","full_name":"Кучма Костянтин Сергійович","post":{"post_hidden":false,"office":"Адміністративний місцевий суд","post":"суддя дніпропетровського окружного адміністративного суду","office_hidden":false,"region":"Дніпропетровська область","region_hidden":false,"post_unclear":false},"last_name_unclear":false},"liabilities":{"54":{"sum_comment":"","sum_foreign_comment":"","sum_foreign":"","sum":"1501","sum_comment_hidden":true},"55":{"sum_comment":"","sum_foreign_comment":"","sum_foreign":"","sum":""},"56":{"sum_comment":"","sum_foreign_comment":"","sum_foreign":"","sum_hidden":false,"sum":""},"57":{"sum_comment":"","sum":"","sum_foreign_comment":"","sum_foreign":"","sum_unclear":false,"sum_comment_hidden":false},"58":{"sum_comment":"","sum_foreign_comment":"","sum_foreign":"","sum":"","sum_comment_hidden":false},"59":{"sum_comment":"","sum_foreign_comment":"","sum_foreign":"","sum":""},"60":{"sum_comment":"","sum_foreign_comment":"","sum_foreign":"","sum":"","sum_comment_hidden":false},"61":{"sum_comment":"","sum_foreign_comment":"","sum_foreign":"","sum":""},"62":{"sum_comment":"","sum_foreign_comment":"","sum_foreign":"","sum":""},"63":{"sum_comment":"","sum":"","sum_foreign_comment":"","sum_foreign":"","sum_unclear":false,"sum_comment_hidden":false},"64":{"sum_comment":"","sum_foreign_comment":"","sum_foreign":"","sum":"","sum_comment_hidden":false}},"intro":{"declaration_year":"2014"}},{"ft_src":"Volkswagen,Passat B6\n2008\nм. Кривий Ріг (інша інформація прихована)\n600\nм. Кривий Ріг (інша інформація прихована)\n24,1\nм. Кривий Ріг (інша інформація прихована)\n135,7\nм. Дніпропетровськ (інша інформація прихована)\n54\nм. Дніпропетровськ (інша інформація прихована)\n100,3\nм. Дніпропетровськ (інша інформація прихована)\n54\nFALSE\n9.00\nFALSE\nFALSE\n2013\n170573\n81353,6\n236063\n65490\n81358,6\nVolkswagen,Passat B6\n2008\n9.00\nFALSE\nFALSE\nм. Кривий Ріг (інша інформація прихована)\n135,7\nм. Дніпропетровськ (інша інформація прихована)\n54\nм. Кривий Ріг (інша інформація прихована)\n24,1\nм. Кривий Ріг (інша інформація прихована)\n600\nм. Дніпропетровськ (інша інформація прихована)\n54\nм. Дніпропетровськ (інша інформація прихована)\n100,3\nСуддя Дніпропетровського окружного адміністративного суду\nБатько Кучма Сергій Валентинович (інша інформація прихована) ;мати Кучма Галина Ігорівна (інша інформація прихована)\nДніпропетровська\nДніпропетровськ\nКучма\nКучма Костянтин Сергійович\nКостянтин Сергійович Кучма\nКостянтин Кучма\nКучма Костянтин Сергійович\nКостянтин\nКучма Костянтин Сергійович\nАдміністративний місцевий суд\nСуддя\nДніпропетровська область\nСергійович\n49106, Дніпропетровська область, м. Дніпропетровськ. (інша інформація прихована)\n1501\n170573\n81358,6\n236063\n81353,6\n65490\n2013\nFALSE\n1501\nКучма\nСергійович\nБатько Кучма Сергій Валентинович (інша інформація прихована) ;мати Кучма Галина Ігорівна (інша інформація прихована)\nКучма Костянтин Сергійович\nКостянтин Сергійович Кучма\nКостянтин Кучма\nКучма Костянтин Сергійович\nКостянтин\nСуддя Дніпропетровського окружного адміністративного суду\nДніпропетровська\nДніпропетровськ\nСуддя\nДніпропетровська область\nАдміністративний місцевий суд\nКучма Костянтин Сергійович\n49106, Дніпропетровська область, м. Дніпропетровськ. (інша інформація прихована)","estate":{"23":[{"costs":"","address":"","space_units":"","costs_rent_comment":"","space":"","costs_comment":"","costs_rent":"","space_comment":"","region":"","location_raw":""},{"costs":"","address":"","space_units":"","costs_rent_comment":"","space":"","costs_comment":"","costs_rent":"","space_comment":"","region":"","location_raw":""},{"costs":"","address":"","space_units":"","costs_rent_comment":"","space":"","costs_comment":"","costs_rent":"","space_comment":"","region":"","location_raw":""}],"25":[{"costs":"","address":"","space_units":"","costs_rent_comment":"","space":"54","costs_comment":"","costs_rent":"","space_comment":"","region":"","location_raw":"м. Дніпропетровськ (інша інформація прихована)"}],"29":[{"costs_property_comment":"","address":"","space_units":"","costs_rent_comment":"","space":"600","space_comment":"","costs_property":"","region":"","location_raw":"м. Кривий Ріг (інша інформація прихована)","costs_rent":""}],"30":[{"costs_property_comment":"","address":"","space_units":"","costs_rent_comment":"","space":"135,7","space_comment":"","costs_property":"","region":"","location_raw":"м. Кривий Ріг (інша інформація прихована)","costs_rent":""}],"31":[{"costs_property_comment":"","address":"","space_units":"","costs_rent_comment":"","space":"54","space_comment":"","costs_property":"","region":"","location_raw":"м. Дніпропетровськ (інша інформація прихована)","costs_rent":""},{"costs_property_comment":"","address":"","space_units":"","costs_rent_comment":"","space":"100,3","space_comment":"","costs_property":"","region":"","location_raw":"м. Дніпропетровськ (інша інформація прихована)","costs_rent":""}],"33":[{"costs_property_comment":"","address":"","space_units":"","costs_rent_comment":"","space":"24,1","space_comment":"","costs_property":"","region":"","location_raw":"м. Кривий Ріг (інша інформація прихована)","costs_rent":""}]},"vehicle":{"40":[{"sum_comment":"","brand_info":"","sum":"","sum_rent_comment":"","year":"2008","brand":"Volkswagen,Passat B6","sum_rent":"","brand_hidden":false}]},"id":"7741","income":{"5":{"family_comment":"","value":"236063","family":"81353,6","comment":""},"6":{"family_comment":"","value":"170573","family":"0","comment":""},"7":{"family":"0","family_comment":"","value":"0","comment":"","source_name":"0"},"8":{"family_comment":"","value":"0","family":"0","comment":""},"9":{"family_comment":"","value":"0","family":"0","comment":""},"10":{"family_comment":"","value":"0","family":"0","comment":""},"11":{"family_comment":"","value":"0","family":"0","comment":""},"12":{"family_comment":"","value":"0","family":"0","comment":""},"13":{"family_comment":"","value":"0","family":"0","comment":""},"14":{"family_comment":"","value":"0","family":"0","comment":""},"15":{"family_comment":"","value":"0","family":"0","comment":""},"16":{"family_comment":"","value":"65490","family":"0","comment":""},"17":{"family_comment":"","value":"0","family":"0","comment":""},"18":{"family_comment":"","value":"0","family":"0","comment":""},"19":{"family_comment":"","value":"0","family":"0","comment":""},"20":{"family_comment":"","value":"0","family":"81358,6","comment":""},"21":[{"country_comment":"","uah_equal":"0","country":"0","cur":"0"},{"country_comment":"","uah_equal":"0","country":"0","cur":"0"},{"country_comment":"","uah_equal":"0","country":"0","cur":"0"},{"country_comment":"","uah_equal":"0","country":"0","cur":"0"},{"country_comment":"","uah_equal":"0","country":"0","cur":"0"}],"22":[{"country_comment":"","uah_equal":"0","country":"0","cur":"0"},{"country_comment":"","uah_equal":"0","country":"0","cur":"0"},{"country_comment":"","uah_equal":"0","country":"0","cur":"0"},{"country_comment":"","uah_equal":"0","country":"0","cur":"0"},{"country_comment":"","uah_equal":"0","country":"0","cur":"0"}]},"banks":{"45":[{"sum_units":"UAH","sum_comment":"","sum_foreign_units":"","sum":"","sum_foreign_comment":"","sum_foreign":""},{"sum_units":"USD","sum_comment":"","sum_foreign_units":"","sum":"","sum_foreign_comment":"","sum_foreign":""},{"sum_units":"EUR","sum_comment":"","sum_foreign_units":"","sum":"","sum_foreign_comment":"","sum_foreign":""}],"46":[{"sum_units":"UAH","sum_comment":"","sum_foreign_units":"","sum":"","sum_foreign_comment":"","sum_foreign":""},{"sum_units":"USD","sum_comment":"","sum_foreign_units":"","sum":"","sum_foreign_comment":"","sum_foreign":""},{"sum_units":"EUR","sum_comment":"","sum_foreign_units":"","sum":"","sum_foreign_comment":"","sum_foreign":""}],"47":[{"sum_units":"","sum_comment":"","sum_foreign_units":"","sum":"","sum_foreign_comment":"","sum_foreign":""}],"48":[{"sum_units":"","sum_comment":"","sum_foreign_units":"","sum":"","sum_foreign_comment":"","sum_foreign":""}],"49":[{"sum_units":"","sum_comment":"","sum_foreign_units":"","sum":"","sum_foreign_comment":"","sum_foreign":""}],"50":[{"sum_units":"","sum_comment":"","sum_foreign_units":"","sum":"","sum_foreign_comment":"","sum_foreign":""}],"51":[{"sum_units":"UAH","sum_comment":"","sum_foreign_units":"","sum":"","sum_foreign_comment":"","sum_foreign":""},{"sum_units":"USD","sum_comment":"","sum_foreign_units":"","sum":"","sum_foreign_comment":"","sum_foreign":""},{"sum_units":"EUR","sum_comment":"","sum_foreign_units":"","sum":"","sum_foreign_comment":"","sum_foreign":""}],"52":[{"sum_units":"","sum_comment":"","sum_foreign_units":"","sum":"","sum_foreign_comment":"","sum_foreign":""}],"53":[{"sum_units":"","sum_comment":"","sum_foreign_units":"","sum":"","sum_foreign_comment":"","sum_foreign":""}]},"declaration":{"notfull_lostpages":"9.00","additional_info_text":"","additional_info":"FALSE","notfull":"FALSE","url":"http://static.declarations.com.ua/declarations/sudy/mistsevi_sudy/okruzhni_administratyvni_sudy/dnipropetrovska/kuchma.pdf","needs_scancopy_check":false},"general":{"family_raw":"Батько Кучма Сергій Валентинович (інша інформація прихована) ;мати Кучма Галина Ігорівна (інша інформація прихована)","name":"Костянтин","full_name_suggest":{"input":["Кучма Костянтин Сергійович","Костянтин Сергійович Кучма","Костянтин Кучма"],"output":"Кучма Костянтин Сергійович"},"post_raw":"Суддя Дніпропетровського окружного адміністративного суду","name_unclear":false,"patronymic":"Сергійович","patronymic_unclear":false,"last_name_hidden":false,"patronymic_hidden":false,"inn":"","addresses_raw_hidden":true,"last_name":"Кучма","full_name":"Кучма Костянтин Сергійович","post":{"office":"Адміністративний місцевий суд","region":"Дніпропетровська область","post":"Суддя"},"addresses":[{"place_district":"","place_city_type":"","place_address_type":"","place":"Дніпропетровська","place_address":"","place_city":"Дніпропетровськ"}],"name_hidden":false,"last_name_unclear":false,"addresses_raw":"49106, Дніпропетровська область, м. Дніпропетровськ. (інша інформація прихована)"},"liabilities":{"54":{"sum_comment":"","sum_foreign_comment":"","sum_foreign":"","sum":"1501"},"55":{"sum_units":"","sum_comment":"","sum_foreign_units":"","sum":"","sum_foreign_comment":"","sum_foreign":""},"56":{"sum_comment":"","sum_foreign_comment":"","sum_foreign":"","sum":""},"57":{"sum_comment":"","sum_foreign_comment":"","sum_foreign":"","sum":""},"58":{"sum_comment":"","sum_foreign_comment":"","sum_foreign":"","sum":""},"59":{"sum_comment":"","sum_foreign_comment":"","sum_foreign":"","sum":""},"60":{"sum_comment":"","sum_foreign_comment":"","sum_foreign":"","sum":""},"61":{"sum_units":"","sum_comment":"","sum_foreign_units":"","sum":"","sum_foreign_comment":"","sum_foreign":""},"62":{"sum_comment":"","sum_foreign_comment":"","sum_foreign":"","sum":""},"63":{"sum_comment":"","sum_units":"","sum_foreign":"","sum":"","sum_foreign_comment":""},"64":{"sum_comment":"","sum_units":"","sum_foreign":"","sum":"","sum_foreign_comment":""}},"intro":{"isnotdeclaration":"FALSE","declaration_year":"2013"}}]