[{"id":"vulyk_97_76","ft_src":"V-2.7 , А/Т Універсал-В\nToyota Highlander\n2014\n474563\nсмт Високий\n38\nХарківська область\nсмт Високий\nХарківська область\n38\nсмт Високий\n179\nХарківська область\nсарай\nсмт Високий\n28\nХарківська область\nХарківська область\nльох\nсмт Високий\n23\nсмт Високий\nХарківська область\n1694\nсмт Високий\n1694\nХарківська область\nсмт Високий\nХарківська область\n179\nсарай\nсмт Високий\nХарківська область\n28\nХарківська область\nльох\nсмт Високий\n23\n36471\n2014\nV-2.7 , А/Т Універсал-В\nToyota Highlander\n2014\n474563\n2014\nКучма Юрій Вікторович\nЮрій Вікторович Кучма\nЮрій Кучма\nКучма Юрій Вікторович\nЮрій\nПодружжя\nКучма В. В\nКучма Юрій Вікторович\nКучма\nАдміністративний місцевий суд\nХарківська область\nголова харківського окружного адміністративного суду\nВікторович\nХарківська область\n62459\nСМТ\nВисокий\nХарківський\n301930\n16098\n777288\n16621\n475314\n44\n523\n38\nХарківська область\nсмт Високий\n179\nХарківська область\nсмт Високий\nХарківська область\n28\nсарай\nсмт Високий\nХарківська область\n23\nльох\nсмт Високий\n1694\nХарківська область\nсмт Високий\n1694\nсмт Високий\nХарківська область\n38\nХарківська область\nсмт Високий\n179\nХарківська область\nсмт Високий\n28\nсарай\nХарківська область\nсмт Високий\n23\nльох\nХарківська область\nсмт Високий\n36471\n301930\n523\n44\n16621\n777288\n475314\n16098\nПодружжя\nКучма В. В\nВікторович\nКучма\nЮрій\nКучма Юрій Вікторович\nЮрій Вікторович Кучма\nЮрій Кучма\nКучма Юрій Вікторович\nСМТ\n62459\nВисокий\nХарківська область\nХарківський\nХарківська область\nАдміністративний місцевий суд\nголова харківського окружного адміністративного суду\nКучма Юрій Вікторович","estate":{"23":[{"address":"смт Високий","space_units":"м²","costs_rent_unclear":false,"costs_comment":"","space_unclear":false,"region_hidden":false,"space_comment":"","address_hidden":false,"costs":"","address_unclear":false,"costs_rent_comment":"","space":"1694","region_unclear":false,"region":"Харківська область","costs_rent":""}],"24":[{"address":"смт Високий","space_units":"м²","space_hidden":false,"space_unclear":false,"region_hidden":false,"costs_rent_comment":"","space_comment":"","address_hidden":false,"costs":"","address_unclear":false,"space_comment_unclear":false,"costs_comment":"","space":"179","region_unclear":false,"region":"Харківська область","costs_rent":""}],"27":[{"address":"смт Високий","space_units":"м²","costs_comment":"","region":"Харківська область","region_hidden":false,"space_comment":"","address_hidden":false,"costs":"","costs_rent_comment":"","space":"38","region_unclear":false,"costs_rent":""}],"28":[{"costs":"","address":"смт Високий","space_units":"м²","costs_rent_comment":"","space":"28","space_comment":"сарай","region_hidden":false,"costs_comment":"","region":"Харківська область","address_hidden":false,"costs_rent":""},{"space":"23","address":"смт Високий","space_units":"м²","costs_rent_comment":"","costs":"","costs_comment":"","space_comment":"льох","region":"Харківська область","costs_rent":""}],"29":[{"costs_property_comment":"","address":"смт Високий","space_units":"м²","space_unclear":false,"region_hidden":false,"costs_property":"","space_comment":"","address_hidden":false,"address_unclear":false,"space_comment_unclear":false,"costs_rent_comment":"","space":"1694","region_unclear":false,"region":"Харківська область","costs_rent":""}],"30":[{"costs_property_comment":"","address":"смт Високий","space_units":"м²","space_comment":"","region_hidden":false,"costs_property":"","region":"Харківська область","address_hidden":false,"address_unclear":false,"costs_rent_comment":"","space":"179","costs_rent":""}],"33":[{"costs_property_comment":"","address":"смт Високий","space_units":"м²","space_hidden":false,"space_comment":"","region_hidden":false,"costs_property":"","region":"Харківська область","address_hidden":false,"costs_rent_comment":"","space":"38","costs_rent":""}],"34":[{"costs_property_comment":"","address":"смт Високий","space_units":"м²","space_hidden":false,"space_comment":"сарай","region_hidden":false,"costs_property":"","region":"Харківська область","address_hidden":false,"costs_rent_comment":"","space":"28","costs_rent":""},{"costs_property_comment":"","address":"смт Високий","space_units":"м²","costs_rent_comment":"","space":"23","region":"Харківська область","costs_property":"","space_comment":"льох","address_hidden":false,"costs_rent":""}]},"vehicle":{"35":[{"year_hidden":false,"brand_info":"V-2.7 , А/Т Універсал-В","brand_unclear":false,"sum_rent_comment":"","brand_hidden":false,"year":"2014","sum_comment":"","brand_info_hidden":false,"sum_rent":"","brand":"Toyota Highlander","brand_info_unclear":false,"sum":"474563"}]},"source":"VULYK","income":{"5":{"family_comment":"","value":"777288","family":"16621","comment":""},"6":{"family_comment":"","family":"","comment":"","value_unclear":false,"family_unclear":false,"comment_hidden":false,"value":"301930"},"7":{"family":"","family_comment":"","value":"","comment":"","source_name":""},"8":{"family_comment":"","value":"","family":"","comment":""},"9":{"family_comment":"","value":"44","family_unclear":false,"family":"523","comment":""},"10":{"family_comment":"","value":"","family":"","comment":"","value_unclear":false},"11":{"family_comment":"","value":"","family":"","comment":""},"12":{"family_comment":"","value":"","family":"","comment":""},"13":{"family_comment":"","value":"","family":"","comment":""},"14":{"family_comment":"","value":"","family":"","comment":""},"15":{"family_comment":"","value":"","family":"","comment":""},"16":{"family_comment":"","value":"475314","family":"","comment":""},"17":{"family_comment":"","value":"","family":"","comment":""},"18":{"family_comment":"","value":"","family":"","comment":""},"19":{"family_comment":"","value":"","family":"","comment":""},"20":{"family_comment":"","comment":"","family":"16098","value_unclear":false,"comment_unclear":false,"value":"","family_hidden":false,"family_comment_unclear":false}},"banks":{"45":[{"sum_comment_unclear":false,"sum_units":"UAH","sum_foreign_units":"UAH","sum_hidden":false,"sum":"36471","sum_foreign_comment":"","sum_comment":"","sum_unclear":false,"sum_foreign":"","sum_comment_hidden":false}]},"declaration":{"notfull_lostpages":"","additional_info_text":"","additional_info":"","date":"2015-03-18T00:00:00","notfull":"","url":"http://static.declarations.com.ua/declarations/chosen_ones/judges_batch/3977_kuchma_iurii_viktorovych.pdf"},"general":{"family":[{"inn":"","family_name":"Кучма В. В","relations_other":"","name_unclear":false,"inn_hidden":false,"name_hidden":false,"relations":"Подружжя"}],"family_raw":"","name":"Юрій","full_name_suggest":{"input":["Кучма Юрій Вікторович","Юрій Вікторович Кучма","Юрій Кучма"],"output":"Кучма Юрій Вікторович"},"patronymic":"Вікторович","inn_hidden":true,"addresses":[{"place_city_type":"СМТ","place_city_type_hidden":false,"place_hidden":false,"place_city_hidden":false,"place_district_hidden":false,"place_district":"Харківський","place_city_unclear":false,"place":"Харківська область","place_city":"Високий","place_address_hidden":true,"place_address":"62459"}],"last_name_hidden":false,"patronymic_hidden":false,"inn":"","inn_unclear":false,"last_name":"Кучма","full_name":"Кучма Юрій Вікторович","post":{"post_hidden":false,"office":"Адміністративний місцевий суд","post":"голова харківського окружного адміністративного суду","office_unclear":false,"region_unclear":false,"region":"Харківська область"},"name_hidden":false},"liabilities":{"54":{"sum_comment_unclear":false,"sum_comment":"","sum_hidden":false,"sum":"","sum_foreign_comment":"","sum_foreign":"","sum_unclear":false,"sum_comment_hidden":false},"55":{"sum_comment":"","sum_foreign_comment":"","sum_foreign":"","sum":""},"56":{"sum_comment":"","sum_foreign_comment":"","sum_foreign":"","sum":""},"57":{"sum_comment_unclear":false,"sum_comment":"","sum_hidden":false,"sum":"","sum_foreign_comment":"","sum_foreign":"","sum_unclear":false,"sum_comment_hidden":false},"58":{"sum_comment_unclear":false,"sum_comment":"","sum_hidden":false,"sum":"","sum_foreign_comment":"","sum_foreign":"","sum_unclear":false,"sum_comment_hidden":false},"59":{"sum_comment":"","sum_foreign_comment":"","sum_foreign":"","sum":""},"60":{"sum_comment_unclear":false,"sum_comment":"","sum_hidden":false,"sum":"","sum_foreign_comment":"","sum_foreign":"","sum_comment_hidden":false},"61":{"sum_comment":"","sum_foreign_comment":"","sum_foreign":"","sum":""},"62":{"sum_comment":"","sum_foreign_comment":"","sum_foreign":"","sum_unclear":false,"sum":""},"63":{"sum_comment":"","sum_foreign_comment":"","sum_foreign":"","sum_hidden":false,"sum":""},"64":{"sum_comment":"","sum_foreign_comment":"","sum_foreign":"","sum":""}},"intro":{"isnotdeclaration":"","declaration_year":"2014"}}]