[{"id":"vulyk_64_112","ft_src":"1498 куб. см., 63 кВт , 403 см\nDaewoo Lanos\n2008\n1595 куб. см., 77.28 кВт , 460 см\n2008\nSkoda Octavia Tour\n17,47 кв. м\n70\n17.47\n2014\n2020\n155204\n6498\n83\n23861\n12180\n32462\n167384\n1498 куб. см., 63 кВт , 403 см\nDaewoo Lanos\n2008\n1595 куб. см., 77.28 кВт , 460 см\nSkoda Octavia Tour\n2008\n70\n17,47 кв. м\n17.47\nЗагальний місцевий суд\nКіровоградська область\nсуддя новоукраїнського районного суду кіровоградської області\nПодружжя\nКухарський Т. О\nДитина\nКухарська Т. Т\nДитина\nКухарський А. Т\nКухарська Наталія Анатоліївна\nНаталія Анатоліївна Кухарська\nНаталія Кухарська\nКухарська Наталія Анатоліївна\nКухарська Наталія Анатоліївна\nНаталія\nКухарська\nАнатоліївна\n1634\n2188\n2020\n155204\n6498\n167384\n32462\n83\n12180\n23861\n2014\n2188\n1634\nПодружжя\nКухарський Т. О\nДитина\nКухарська Т. Т\nКухарський А. Т\nДитина\nАнатоліївна\nКухарська\nНаталія\nКухарська Наталія Анатоліївна\nНаталія Анатоліївна Кухарська\nНаталія Кухарська\nКухарська Наталія Анатоліївна\nКіровоградська область\nЗагальний місцевий суд\nсуддя новоукраїнського районного суду кіровоградської області\nКухарська Наталія Анатоліївна","estate":{"31":[{"costs_property_comment":"","address":"","space_units":"м²","space_comment":"17,47 кв. м","region_hidden":true,"costs_property":"","region":"","address_hidden":true,"space_comment_hidden":false,"costs_rent_comment":"","space":"70","region_unclear":false,"costs_rent":""},{"costs_property_comment":"","address":"","space_units":"м²","space_unclear":true,"region_hidden":false,"costs_property":"","space_comment":"","address_hidden":false,"address_unclear":true,"costs_rent_comment":"","space":"17.47","region_unclear":true,"region":"","costs_rent":""}]},"vehicle":{"40":[{"year_hidden":false,"brand_info":"1498 куб. см., 63 кВт , 403 см","brand_unclear":false,"sum_rent_comment":"","brand_hidden":false,"year":"2008","sum_comment":"","brand_info_hidden":false,"sum_rent":"","brand":"Daewoo Lanos","brand_info_unclear":true,"sum":""},{"sum_comment":"","brand_info":"1595 куб. см., 77.28 кВт , 460 см","sum":"","sum_rent_comment":"","year":"2008","brand":"Skoda Octavia Tour","sum_rent":"","brand_info_unclear":false}]},"source":"VULYK","income":{"5":{"family":"32462","family_comment":"","comment":"","value_hidden":false,"value_unclear":false,"value":"167384","family_hidden":false,"family_unclear":false,"family_comment_unclear":false},"6":{"family":"2020","family_comment":"","comment":"","value_hidden":false,"value_unclear":false,"comment_hidden":false,"family_hidden":false,"family_unclear":false,"value":"155204"},"7":{"source_name_hidden":true,"family_comment":"","family":"","value_hidden":false,"comment":"","value":"","source_name":""},"8":{"family_comment":"","value":"","family":"","comment":""},"9":{"family":"","family_comment":"","comment":"","value_hidden":false,"comment_hidden":false,"value":""},"10":{"family":"23861","family_comment":"","comment":"","value_hidden":false,"value_unclear":false,"value":"12180"},"11":{"family_comment":"","value":"","family":"83","comment":""},"12":{"family_comment":"","value":"","family":"","comment":""},"13":{"family_comment":"","family_hidden":false,"value":"","family":"","comment":""},"14":{"family_comment":"","value":"","family":"","comment":""},"15":{"family_comment":"","value":"","family_unclear":false,"family":"6498","comment":""},"16":{"family_comment":"","value":"","family":"","comment":"","value_unclear":false},"17":{"family_comment":"","value":"","family":"","comment":""},"18":{"family_comment":"","value":"","family":"","comment":""},"19":{"family_comment":"","comment_unclear":false,"value":"","family":"","comment":""},"20":{"family_comment":"","family":"","value_hidden":false,"comment":"","comment_unclear":false,"value":"","family_hidden":false}},"general":{"family":[{"inn":"","inn_unclear":false,"family_name":"Кухарський Т. О","relations_hidden":false,"relations_unclear":false,"name_unclear":false,"relations":"Подружжя","inn_hidden":true,"name_hidden":false,"relations_other":""},{"inn":"","family_name":"Кухарська Т. Т","relations_hidden":false,"relations_unclear":false,"name_unclear":false,"relations":"Дитина","inn_hidden":false,"name_hidden":false,"relations_other":""},{"inn":"","family_name":"Кухарський А. Т","relations_other":"","name_unclear":true,"inn_hidden":false,"name_hidden":false,"relations":"Дитина"}],"family_raw":"","name":"Наталія","full_name_suggest":{"input":["Кухарська Наталія Анатоліївна","Наталія Анатоліївна Кухарська","Наталія Кухарська"],"output":"Кухарська Наталія Анатоліївна"},"name_unclear":false,"patronymic":"Анатоліївна","inn_hidden":true,"addresses":[{"place_city_type_unclear":false,"place_district_hidden":true,"place_hidden":true,"place":"","place_city":"","place_unclear":false,"place_city_type_hidden":true,"place_city_type":"","place_city_hidden":true,"place_district":"","place_city_unclear":false,"place_address":"","place_address_hidden":true}],"last_name_hidden":false,"patronymic_hidden":false,"inn":"","inn_unclear":false,"last_name":"Кухарська","full_name":"Кухарська Наталія Анатоліївна","post":{"post_hidden":false,"office":"Загальний місцевий суд","post":"суддя новоукраїнського районного суду кіровоградської області","candidate":"","region_hidden":false,"region":"Кіровоградська область","office_hidden":false,"post_unclear":false,"office_unclear":false},"last_name_unclear":false},"liabilities":{"54":{"sum_comment":"","sum_hidden":false,"sum":"","sum_foreign_comment":"","sum_comment_hidden":false,"sum_foreign":"","sum_unclear":false,"sum_foreign_comment_hidden":false},"55":{"sum_comment":"","sum_comment_unclear":false,"sum_foreign_comment":"","sum":"","sum_foreign":""},"56":{"sum_comment":"","sum_foreign_comment":"","sum_foreign":"","sum_unclear":false,"sum":""},"57":{"sum_comment":"","sum_hidden":false,"sum":"","sum_foreign_comment":"","sum_foreign":"","sum_unclear":false},"58":{"sum_comment":"","sum_foreign_comment":"","sum_foreign":"","sum_unclear":false,"sum":""},"59":{"sum_comment_unclear":false,"sum_comment":"","sum":"","sum_foreign_comment":"","sum_foreign":"","sum_unclear":false,"sum_comment_hidden":false},"60":{"sum_comment":"","sum_foreign_comment":"","sum_foreign":"","sum":"1634"},"61":{"sum_comment":"","sum_foreign_comment":"","sum_foreign":"","sum":""},"62":{"sum_comment":"","sum_foreign_comment":"","sum_foreign":"","sum_unclear":false,"sum":"2188"},"63":{"sum_comment":"","sum_foreign_comment":"","sum_foreign":"","sum_unclear":false,"sum":""},"64":{"sum_comment_unclear":false,"sum_comment":"","sum":"","sum_foreign_comment":"","sum_foreign":"","sum_unclear":false}},"declaration":{"notfull_lostpages":"","additional_info_text":"","additional_info":"","date":"2015-03-19T00:00:00","notfull":"","url":"http://static.declarations.com.ua/declarations/chosen_ones/mega_batch/kukharska_nataliia_anatoliivna.pdf"},"intro":{"declaration_year_hidden":false,"isnotdeclaration":"","declaration_year_unclear":false,"declaration_year":"2014"}}]