[{"id":"vulyk_72_229","ft_src":"1.6 л\nDaewoo Lanos\n2007\nміні трактор 12.5 к.с., 638 куб. см.\n2014\nБулат\nпричіп\n2014\nЧернігівська область\nм. Чернігів\n22.45\nм. Чернігів, АК 27\n24\nЧернігівська область\nЧернігівська область\nЧернігівський р-н\n4.133\nЧернігівський р-н\nЧернігівська область\n48.3\n22.45\nЧернігів\nЧернігівська область\nЧернігів\n51.6\nЧернігівська область\n452\n2014\n1.6 л\nDaewoo Lanos\n2007\nміні трактор 12.5 к.с., 638 куб. см.\nБулат\n2014\nпричіп\n2014\nЧернігівський р-н\nЧернігівська область\n4.133\n24\nм. Чернігів, АК 27\nЧернігівська область\nЧернігівська область\n48.3\nЧернігівський р-н\nЧернігівська область\nм. Чернігів\n22.45\nЧернігів\n22.45\nЧернігівська область\n51.6\nЧернігів\nЧернігівська область\nПодружжя\nКузьміна Парасковія Олексіївна, 03. 07. 1952\nДитина\nКузьмін Микола Миколайович 25. 04. 1985\nКузьмін Микола Васильович\nМикола Васильович Кузьмін\nМикола Кузьмін\nКузьмін Микола Васильович\nМикола\nКузьмін Микола Васильович\nКузьмін\nЧернігівська область\nЗагальний місцевий суд\nсуддя новозаводського районного суду м. чернігова\nВасильович\nЧернігів\n14000\nЧернігівська область\n3151.48\n8369.44\n224151.86\n41476.49\nпенсія\n43050.48\n21882.64\nпенсія\n279382.28\n68137.25\n12180\n4778.12\n452\n2014\n8369.44\n3151.48\n41476.49\n224151.86\n21882.64\nпенсія\nпенсія\n43050.48\n4778.12\n12180\n68137.25\n279382.28\nКузьміна Парасковія Олексіївна, 03. 07. 1952\nПодружжя\nКузьмін Микола Миколайович 25. 04. 1985\nДитина\nВасильович\nКузьмін\nКузьмін Микола Васильович\nМикола Васильович Кузьмін\nМикола Кузьмін\nКузьмін Микола Васильович\nЧернігівська область\nЧернігів\n14000\nЧернігівська область\nЗагальний місцевий суд\nсуддя новозаводського районного суду м. чернігова\nКузьмін Микола Васильович\nМикола","estate":{"25":[{"space_hidden":false,"space_comment":"","costs_comment":"","address_hidden":true,"space_comment_hidden":false,"address_unclear":false,"costs_rent_comment_unclear":false,"costs":"","costs_rent":"","address":"Чернігів","space_units":"м²","costs_hidden":false,"costs_rent_unclear":false,"costs_rent_hidden":false,"space_unclear":false,"costs_comment_hidden":false,"costs_rent_comment_hidden":false,"space_comment_unclear":false,"costs_comment_unclear":false,"costs_rent_comment":"","space":"22.45","region_hidden":false,"region":"Чернігівська область"},{"costs":"","address":"Чернігів","space_units":"м²","costs_rent_comment":"","space":"51.6","space_comment":"","region_hidden":false,"costs_comment":"","region":"Чернігівська область","address_hidden":false,"costs_rent":""}],"27":[{"address":"м. Чернігів, АК 27","space_units":"м²","costs_comment":"","space_unclear":false,"region_hidden":false,"space_comment":"","address_hidden":false,"costs":"","address_unclear":true,"costs_rent_comment":"","space":"24","region":"Чернігівська область","costs_rent":""}],"29":[{"costs_property_comment":"","address":"Чернігівський р-н","space_units":"га","space_hidden":false,"space_unclear":false,"region_hidden":false,"costs_property":"","space_comment":"","address_hidden":true,"space_units_unclear":false,"address_unclear":false,"costs_rent_comment":"","space":"4.133","region":"Чернігівська область","costs_rent":""}],"30":[{"costs_property_comment":"","address":"Чернігівський р-н","space_units":"м²","space_hidden":false,"space_unclear":false,"region_hidden":false,"costs_property":"","space_comment":"","address_hidden":true,"costs_rent_comment":"","space":"48.3","region_unclear":false,"region":"Чернігівська область","costs_rent":""}],"31":[{"costs_property_comment":"","address":"м. Чернігів","space_units":"м²","space_hidden":false,"space_unclear":false,"region_hidden":false,"costs_property":"","space_comment":"","address_hidden":true,"address_unclear":false,"costs_rent_comment":"","space":"22.45","region":"Чернігівська область","space_units_hidden":false,"costs_rent":""}]},"vehicle":{"35":[{"sum_hidden":false,"brand_unclear":false,"sum_rent_comment":"","sum_rent_comment_unclear":false,"brand_hidden":false,"sum_comment":"","brand_info_hidden":false,"sum_rent":"","sum_rent_unclear":false,"brand":"Daewoo Lanos","brand_info":"1.6 л","brand_info_unclear":false,"year":"2007","sum":""}],"44":[{"sum_comment":"","brand_info":"міні трактор 12.5 к.с., 638 куб. см.","sum":"","sum_rent_comment":"","year":"2014","brand":"Булат","sum_rent":""},{"sum_comment":"","brand_info":"причіп","sum":"","sum_rent_comment":"","year":"2014","brand":"","sum_rent":""}]},"source":"VULYK","income":{"5":{"family":"68137.25","family_comment":"","comment":"","value_hidden":false,"value_unclear":false,"comment_hidden":false,"family_hidden":false,"family_unclear":false,"family_comment_hidden":false,"value":"279382.28"},"6":{"family_comment":"","family":"41476.49","comment":"","value_unclear":false,"family_unclear":false,"family_hidden":false,"value":"224151.86"},"7":{"source_name_hidden":false,"family_comment":"","comment":"","family":"","source_name_unclear":false,"value":"","family_hidden":false,"source_name":""},"8":{"family_comment":"","value":"","family":"","comment":""},"9":{"family_comment":"","family":"","comment":"","value_unclear":false,"family_hidden":false,"value":""},"10":{"family_comment":"","family":"4778.12","value_hidden":false,"comment":"","comment_unclear":false,"value_unclear":false,"value":"12180","family_hidden":false},"11":{"family_comment":"","value":"","family":"","comment":""},"12":{"family_comment":"","value":"","family":"","comment":""},"13":{"family_comment":"","value":"","family":"","comment":""},"14":{"family_comment":"","value":"","family":"","comment":""},"15":{"family_comment":"пенсія","family_hidden":false,"value":"43050.48","family":"21882.64","comment":"пенсія"},"16":{"family_comment":"","family":"","comment":"","value_unclear":false,"family_hidden":false,"value":""},"17":{"family_comment":"","family_hidden":false,"value":"","family":"","comment":""},"18":{"family_comment":"","value":"","family":"","comment":"","value_unclear":false},"19":{"family_comment":"","value":"","family":"","comment":""},"20":{"family_comment":"","comment":"","family":"","value_unclear":false,"family_unclear":false,"comment_unclear":false,"value":"","family_hidden":false}},"banks":{"52":[{"sum_comment_unclear":false,"sum_units":"UAH","sum_foreign_units":"UAH","sum_hidden":false,"sum":"452","sum_foreign_comment":"","sum_comment":"","sum_unclear":false,"sum_foreign":"","sum_comment_hidden":false,"sum_foreign_hidden":false}]},"declaration":{"notfull_lostpages":"","additional_info_text":"","additional_info":"","date":"2015-03-27T00:00:00","notfull":"","url":"http://static.declarations.com.ua/declarations/chosen_ones/epic_batch/kuzmin_mykola_vasylovych.pdf"},"general":{"family":[{"inn":"","inn_unclear":false,"family_name":"Кузьміна Парасковія Олексіївна, 03. 07. 1952","relations_other":"","relations_hidden":false,"relations_unclear":false,"name_unclear":false,"inn_hidden":true,"name_hidden":false,"relations":"Подружжя"},{"inn":"","family_name":"Кузьмін Микола Миколайович 25. 04. 1985","relations_other":"","relations_hidden":false,"name_unclear":false,"inn_hidden":true,"name_hidden":false,"relations":"Дитина"}],"family_raw":"","name":"Микола","full_name_suggest":{"input":["Кузьмін Микола Васильович","Микола Васильович Кузьмін","Микола Кузьмін"],"output":"Кузьмін Микола Васильович"},"name_unclear":false,"patronymic":"Васильович","inn_hidden":true,"patronymic_unclear":false,"patronymic_hidden":false,"inn":"","inn_unclear":false,"last_name":"Кузьмін","full_name":"Кузьмін Микола Васильович","post":{"post_hidden":false,"office":"Загальний місцевий суд","post":"суддя новозаводського районного суду м. чернігова","region_unclear":false,"candidate":"","region_hidden":false,"region":"Чернігівська область","office_hidden":false,"post_unclear":false,"office_unclear":false},"addresses":[{"place_city_type_hidden":false,"place_district_hidden":false,"place_address_unclear":false,"place":"Чернігівська область","place_city":"Чернігів","place_unclear":false,"place_city_type":"Місто","place_city_hidden":false,"place_city_unclear":false,"place_district":"","place_district_unclear":false,"place_address":"14000","place_address_hidden":true,"place_hidden":false}],"last_name_unclear":false},"liabilities":{"54":{"sum_comment":"","sum":"3151.48","sum_foreign_comment":"","sum_foreign":"","sum_unclear":false,"sum_comment_hidden":false},"55":{"sum_comment":"","sum_foreign_comment":"","sum_foreign":"","sum":""},"56":{"sum_comment":"","sum_foreign_comment":"","sum_foreign":"","sum_hidden":false,"sum":"8369.44"},"57":{"sum_comment_unclear":false,"sum_comment":"","sum_hidden":false,"sum":"","sum_foreign_comment":"","sum_foreign":"","sum_unclear":false,"sum_comment_hidden":false},"58":{"sum_comment_unclear":false,"sum_comment":"","sum_hidden":false,"sum":"","sum_foreign_comment":"","sum_foreign":"","sum_unclear":false,"sum_comment_hidden":false},"59":{"sum_comment":"","sum":"","sum_foreign_comment":"","sum_foreign_unclear":false,"sum_foreign":"","sum_foreign_hidden":false,"sum_comment_hidden":false},"60":{"sum_comment":"","sum_hidden":false,"sum":"","sum_foreign_comment":"","sum_foreign":"","sum_foreign_hidden":false},"61":{"sum_comment":"","sum_hidden":false,"sum":"","sum_foreign_comment":"","sum_foreign":"","sum_foreign_hidden":false},"62":{"sum_comment":"","sum_hidden":false,"sum":"","sum_foreign_comment":"","sum_foreign":"","sum_foreign_hidden":false},"63":{"sum_comment_unclear":false,"sum_comment":"","sum_hidden":false,"sum":"","sum_foreign_comment":"","sum_foreign":"","sum_unclear":false,"sum_foreign_hidden":false,"sum_comment_hidden":false},"64":{"sum_comment":"","sum_hidden":false,"sum":"","sum_foreign_comment":"","sum_foreign":"","sum_foreign_hidden":false}},"intro":{"isnotdeclaration":"","declaration_year_unclear":false,"declaration_year":"2014"}}]