[{"id":"vulyk_75_148","ft_src":"121\n16.2\n2013\n208369\n12618\n220986\n2013\nКузьменко\nВолодимирович\nПодружжя\nКузьменко І. Г\nДитина\nКузьменко Г. В\nДитина\nКузьменко І. В\nКузьменко Володимир Володимирович\nВолодимир Володимирович Кузьменко\nВолодимир Кузьменко\nКузьменко Володимир Володимирович\nВолодимир\nКузьменко Володимир Володимирович\nАпеляційний адміністративний суд\nсуддя київського апеляційного адміністративного суду\nм. Київ\n13000\n208369\n220986\n12618\n16.2\n121\n13000\nКузьменко І. Г\nПодружжя\nКузьменко Г. В\nДитина\nКузьменко І. В\nДитина\nКузьменко\nВолодимирович\nсуддя київського апеляційного адміністративного суду\nм. Київ\nАпеляційний адміністративний суд\nКузьменко Володимир Володимирович\nКузьменко Володимир Володимирович\nВолодимир Володимирович Кузьменко\nВолодимир Кузьменко\nКузьменко Володимир Володимирович\nВолодимир","estate":{"31":[{"costs_property_comment":"","address":"","space_units":"м²","space_unclear":false,"region_hidden":true,"costs_property":"","space_comment":"","address_hidden":true,"costs_rent_comment":"","space":"121","region":"","costs_rent":""}],"33":[{"costs_property_comment":"","address":"","space_units":"м²","costs_rent_comment":"","space":"16.2","region":"","region_hidden":true,"costs_property":"","space_comment":"","costs_rent":""}]},"source":"VULYK","income":{"5":{"family_comment":"","value":"220986","family":"","comment":""},"6":{"family_comment":"","family_hidden":false,"value":"208369","family":"","comment":""},"7":{"family":"","family_comment":"","value":"","comment":"","source_name":""},"8":{"family_comment":"","value":"","family":"","comment":""},"9":{"family_comment":"","family":"","comment":"","value_unclear":false,"family_hidden":false,"value":""},"10":{"family":"","family_comment":"","comment":"","value_hidden":false,"value":"12618","family_hidden":false,"family_unclear":false},"11":{"family_comment":"","value":"","family":"","comment":""},"12":{"family_comment":"","value":"","family":"","comment":""},"13":{"family_comment":"","value":"","family":"","comment":""},"14":{"family_comment":"","value":"","family":"","comment":""},"15":{"family_comment":"","value":"","family":"","comment":""},"16":{"family_comment":"","value":"","family":"","comment":""},"17":{"family_comment":"","value":"","family":"","comment":""},"18":{"family_comment":"","value":"","family":"","comment":""},"19":{"family_comment":"","value":"","family":"","comment":""},"20":{"family_comment":"","comment":"","family":"","comment_unclear":false,"value":"","family_comment_unclear":false}},"general":{"inn":"","addresses":[{"place_city_type_hidden":false,"place_city_type":"","place_city_hidden":true,"place_hidden":true,"place_district":"","place_district_hidden":true,"place":"","place_city":"","place_address_hidden":true,"place_address":""}],"last_name":"Кузьменко","full_name":"Кузьменко Володимир Володимирович","family":[{"inn":"","family_name":"Кузьменко І. Г","relations_other":"","relations_hidden":false,"name_unclear":false,"inn_hidden":true,"name_hidden":true,"relations":"Подружжя"},{"inn":"","family_name":"Кузьменко Г. В","relations_other":"","name_unclear":false,"inn_hidden":true,"name_hidden":false,"relations":"Дитина"},{"inn":"","family_name":"Кузьменко І. В","relations_other":"","name_unclear":false,"inn_hidden":false,"name_hidden":false,"relations":"Дитина"}],"patronymic":"Володимирович","inn_hidden":true,"name":"Володимир","post":{"office":"Апеляційний адміністративний суд","region":"м. Київ","post":"суддя київського апеляційного адміністративного суду"},"family_raw":"","full_name_suggest":{"input":["Кузьменко Володимир Володимирович","Володимир Володимирович Кузьменко","Володимир Кузьменко"],"output":"Кузьменко Володимир Володимирович"}},"liabilities":{"54":{"sum_comment":"","sum_foreign_comment":"","sum_foreign":"","sum":""},"55":{"sum_comment":"","sum_foreign_comment":"","sum_foreign":"","sum":""},"56":{"sum_comment":"","sum_foreign_comment":"","sum_foreign":"","sum":""},"57":{"sum_comment":"","sum_foreign_comment":"","sum_foreign":"","sum":""},"58":{"sum_comment":"","sum_foreign_comment":"","sum_foreign":"","sum":""},"59":{"sum_comment_unclear":false,"sum_comment":"","sum":"","sum_foreign_comment":"","sum_foreign":"","sum_unclear":false},"60":{"sum_comment":"","sum_foreign_comment":"","sum_foreign":"","sum":""},"61":{"sum_comment":"","sum_foreign_comment":"","sum_foreign":"","sum":""},"62":{"sum_comment":"","sum_foreign_comment":"","sum_foreign":"","sum_unclear":false,"sum":"13000"},"63":{"sum_comment":"","sum_foreign_comment":"","sum_foreign":"","sum":""},"64":{"sum_comment":"","sum_foreign_comment":"","sum_foreign":"","sum":""}},"declaration":{"notfull_lostpages":"","additional_info_text":"","additional_info":"","date":"2014-03-17T00:00:00","notfull":"","url":"http://static.declarations.com.ua/declarations/chosen_ones/judges_batch/1787_kuzmenko_volodymyr_volodymyrovych.pdf"},"intro":{"isnotdeclaration":"","declaration_year":"2013"}}]