[{"id":"vulyk_65_88","ft_src":"1500 куб. см.\n2005\nм. Первомайськ, ОКСП\n505\nМиколаївська область\nПервомайський р-н, с. Грушівка, вул. Крилова\nМиколаївська область\n207.4\nМиколаївська область\nПервомайський р-н, с. Грушівка, вул. Крилова\n1000\nМиколаївська область\nм. Первомайськ, вул. Рожева\n34\nм. Первомайськ, вул. Рожева\nМиколаївська область\n33.05\nВінницька область\nм. Вінниця, вул. Червоноармійська\n36.3\nм. Первомайськ\nМиколаївська область\n33.05\n2014\n255479\n43571\n255479\n5\n43571\n1500 куб. см.\n2005\n505\nМиколаївська область\nм. Первомайськ, ОКСП\n1000\nМиколаївська область\nПервомайський р-н, с. Грушівка, вул. Крилова\n34\nм. Первомайськ, вул. Рожева\nМиколаївська область\n207.4\nМиколаївська область\nПервомайський р-н, с. Грушівка, вул. Крилова\n33.05\nМиколаївська область\nм. Первомайськ, вул. Рожева\n36.3\nВінницька область\nм. Вінниця, вул. Червоноармійська\n33.05\nм. Первомайськ\nМиколаївська область\nЗагальний місцевий суд\nМиколаївська область\nсуддя первомайського міськрайонного суду миколаївської області\nЛітвіненко Тетяна Яківна\nТетяна Яківна Літвіненко\nТетяна Літвіненко\nЛітвіненко Тетяна Яківна\nТетяна\nПодружжя\nЧоловік 31. 03. 1960 р\nЛітвіненко Тетяна Яківна\nЛітвіненко\nЯківна\nСело\nМиколаївська область\nГрушівка\nПервомайський\n255479\n43571\n255479\n43571\n5\n2014\nЧоловік 31. 03. 1960 р\nПодружжя\nЯківна\nЛітвіненко\nТетяна\nЛітвіненко Тетяна Яківна\nТетяна Яківна Літвіненко\nТетяна Літвіненко\nЛітвіненко Тетяна Яківна\nСело\nГрушівка\nМиколаївська область\nПервомайський\nМиколаївська область\nЗагальний місцевий суд\nсуддя первомайського міськрайонного суду миколаївської області\nЛітвіненко Тетяна Яківна","estate":{"23":[{"address":"м. Первомайськ, ОКСП","space_units":"м²","space_hidden":false,"space_unclear":false,"region_hidden":false,"costs_comment":"","space_comment":"","address_hidden":true,"costs":"","address_unclear":false,"costs_rent_comment":"","space":"505","region":"Миколаївська область","costs_rent":""}],"25":[{"costs_rent_comment_unclear":false,"address":"м. Вінниця, вул. Червоноармійська","space_units":"м²","space_hidden":false,"space_unclear":false,"region_hidden":false,"costs_comment":"","space_comment":"","space_comment_unclear":false,"costs":"","address_unclear":false,"address_hidden":true,"costs_rent_comment":"","space":"36.3","region":"Вінницька область","space_units_hidden":false,"costs_rent":""},{"address":"м. Первомайськ","space_units":"м²","space_hidden":false,"space_unclear":false,"region_hidden":false,"costs_comment":"","space_comment":"","address_hidden":false,"space":"33.05","costs_rent_comment":"","costs":"","region":"Миколаївська область","costs_rent":""}],"29":[{"costs_property_comment":"","address":"Первомайський р-н, с. Грушівка, вул. Крилова","space_units":"м²","space_unclear":false,"region_hidden":false,"costs_property":"","space_comment":"","address_hidden":false,"address_unclear":false,"costs_rent_comment":"","space":"1000","region":"Миколаївська область","space_units_hidden":false,"costs_rent":""},{"costs_property_comment":"","address":"м. Первомайськ, вул. Рожева","space_units":"м²","costs_rent_comment":"","space":"34","region":"Миколаївська область","region_hidden":false,"costs_property":"","space_comment":"","address_hidden":false,"costs_rent":""}],"30":[{"costs_property_comment":"","address":"Первомайський р-н, с. Грушівка, вул. Крилова","space_units":"м²","space_comment":"","region_hidden":false,"costs_property":"","region":"Миколаївська область","address_hidden":false,"address_unclear":true,"space_comment_unclear":false,"costs_rent_comment":"","space":"207.4","costs_rent":""}],"31":[{"costs_property_comment":"","address":"м. Первомайськ, вул. Рожева","space_units":"м²","space_unclear":false,"region_hidden":false,"costs_property":"","space_comment":"","address_hidden":false,"space_comment_unclear":false,"costs_rent_comment":"","space":"33.05","region":"Миколаївська область","costs_rent":""}]},"vehicle":{"40":[{"sum_comment":"","brand_info":"1500 куб. см.","sum":"","brand_unclear":false,"year":"2005","brand":"","sum_rent":"","sum_rent_comment":"","brand_hidden":true,"brand_info_unclear":false,"year_unclear":false}]},"source":"VULYK","income":{"5":{"family":"43571","family_comment":"","comment":"","value_hidden":false,"value_unclear":false,"value":"255479","family_hidden":false,"family_unclear":false},"6":{"family_comment":"","family":"","value_hidden":false,"comment":"","comment_unclear":false,"value_unclear":false,"value":"255479","family_hidden":false},"7":{"source_name_hidden":false,"family_comment":"","family":"","value_hidden":false,"comment":"","value":"","source_name":""},"8":{"family_comment":"","value":"","family":"","comment":""},"9":{"family_comment":"","comment_unclear":false,"value":"5","family":"","comment":""},"10":{"family_comment":"","value":"","family":"","comment":"","value_unclear":false},"11":{"family_comment":"","value":"","family":"","comment":""},"12":{"family_comment":"","value":"","family":"","comment":""},"13":{"family_comment":"","value":"","family":"","comment":""},"14":{"family_comment":"","value":"","family":"","comment":""},"15":{"family_comment":"","value":"","family":"","comment":""},"16":{"family_comment":"","value":"","family":"","comment":""},"17":{"family_comment":"","value":"","family":"","comment":""},"18":{"family_comment":"","value":"","family":"","comment":""},"19":{"family":"","family_comment":"","comment":"","value_hidden":false,"value_unclear":false,"comment_hidden":false,"family_hidden":false,"value":"","family_comment_hidden":false},"20":{"family_comment":"","family":"43571","value_hidden":false,"comment":"","value":"","comment_unclear":false,"value_unclear":false,"family_unclear":false,"family_hidden":false}},"general":{"family":[{"inn":"","inn_unclear":false,"family_name":"Чоловік 31. 03. 1960 р","relations_other":"","relations_hidden":false,"name_unclear":false,"inn_hidden":true,"name_hidden":true,"relations":"Подружжя"}],"family_raw":"","name":"Тетяна","full_name_suggest":{"input":["Літвіненко Тетяна Яківна","Тетяна Яківна Літвіненко","Тетяна Літвіненко"],"output":"Літвіненко Тетяна Яківна"},"name_unclear":false,"patronymic":"Яківна","inn_hidden":true,"addresses":[{"place_city_type":"Село","place_address_unclear":false,"place_city_type_hidden":false,"place_hidden":false,"place_city_hidden":false,"place_district":"Первомайський","place_district_hidden":false,"place":"Миколаївська область","place_city":"Грушівка","place_address_hidden":true,"place_address":""}],"last_name_hidden":false,"patronymic_hidden":false,"inn":"","inn_unclear":false,"last_name":"Літвіненко","full_name":"Літвіненко Тетяна Яківна","post":{"post_hidden":false,"office":"Загальний місцевий суд","post":"суддя первомайського міськрайонного суду миколаївської області","region":"Миколаївська область","region_hidden":false,"office_unclear":false,"office_hidden":false,"post_unclear":false,"region_unclear":false},"name_hidden":false,"last_name_unclear":false},"liabilities":{"54":{"sum_comment_unclear":false,"sum_comment":"","sum_hidden":false,"sum":"","sum_foreign_comment":"","sum_foreign":"","sum_comment_hidden":false},"55":{"sum_comment":"","sum_foreign_comment":"","sum_foreign":"","sum":""},"56":{"sum_comment":"","sum_foreign_comment":"","sum_foreign":"","sum_unclear":false,"sum":""},"57":{"sum_comment_unclear":false,"sum_comment":"","sum":"","sum_foreign_comment":"","sum_foreign":"","sum_unclear":false},"58":{"sum_comment_unclear":false,"sum_comment":"","sum":"","sum_foreign_comment":"","sum_foreign":"","sum_unclear":false},"59":{"sum_comment":"","sum_foreign_comment":"","sum_foreign":"","sum":""},"60":{"sum_comment":"","sum_comment_unclear":false,"sum_foreign_comment":"","sum":"","sum_foreign":""},"61":{"sum_comment":"","sum_foreign_comment":"","sum_foreign":"","sum":""},"62":{"sum_comment":"","sum_foreign_comment":"","sum_foreign":"","sum":""},"63":{"sum_comment":"","sum_foreign_comment":"","sum_foreign":"","sum":""},"64":{"sum_comment":"","sum_foreign_comment":"","sum_foreign":"","sum_unclear":false,"sum":""}},"declaration":{"notfull_lostpages":"","additional_info_text":"","additional_info":"","date":"2015-03-30T00:00:00","notfull":"","url":"http://static.declarations.com.ua/declarations/chosen_ones/mega_batch/litvinenko_tetiana_iakivna.pdf"},"intro":{"declaration_year_hidden":false,"isnotdeclaration":"","declaration_year":"2014"}}]