[{"id":"vulyk_65_86","ft_src":"1800 куб. см.\nVolkswagen Golf III\n1992\nMitsubishi Outlander\n2400 куб. см.\n2004\n2800 куб. см.\n1997\nAudi A6\nм. Одеса\n14.5\nОдеська область\nОдеська область\n1000\nм. Одеса\nОдеська область\n12\n55. 9-спадщина\nм. Одеса\nОдеська область\n86\nОдеська область\nоренда офісу\nм. Одеса\n56.6\nОдеська область\nм. Одеса\n86\n2014\n230459\n756155\n230459\n756155\n1800 куб. см.\nVolkswagen Golf III\n1992\n2400 куб. см.\n2004\nMitsubishi Outlander\n2800 куб. см.\nAudi A6\n1997\n14.5\nОдеська область\nм. Одеса\n86\nОдеська область\nм. Одеса\n12\nОдеська область\nм. Одеса\n1000\nОдеська область\n86\n55. 9-спадщина\nОдеська область\nм. Одеса\n56.6\nоренда офісу\nОдеська область\nм. Одеса\nЗагальний місцевий суд\nОдеська область\nсуддя київського районного суду м. одеси\nЛуняченко Валеріан Олександрович\nВалеріан Олександрович Луняченко\nВалеріан Луняченко\nЛуняченко Валеріан Олександрович\nВалеріан\nПодружжя\nДитина\nЛуняченко Валеріан Олександрович\nЛуняченко\nОлександрович\n65058\nОдеська область\nОдеса\n230459\n756155\n230459\n756155\n2014\nПодружжя\nДитина\nОлександрович\nЛуняченко\nВалеріан\nЛуняченко Валеріан Олександрович\nВалеріан Олександрович Луняченко\nВалеріан Луняченко\nЛуняченко Валеріан Олександрович\n65058\nОдеса\nОдеська область\nОдеська область\nЗагальний місцевий суд\nсуддя київського районного суду м. одеси\nЛуняченко Валеріан Олександрович","estate":{"25":[{"costs_rent_comment_unclear":false,"address":"м. Одеса","space_units":"м²","space_hidden":false,"space_unclear":false,"region_hidden":false,"costs_comment":"","space_comment":"","space_comment_unclear":false,"costs":"","address_unclear":false,"address_hidden":false,"costs_rent_comment":"","space":"86","region":"Одеська область","space_units_hidden":false,"costs_rent":""}],"27":[{"address":"м. Одеса","space_units":"м²","space_hidden":false,"space_comment":"","region_hidden":false,"costs_comment":"","address_hidden":false,"space":"14.5","costs_rent_comment":"","costs":"","region_unclear":false,"region":"Одеська область","space_units_hidden":false,"costs_rent":""}],"29":[{"costs_property_comment":"","address":"","space_units":"м²","space_unclear":false,"region_hidden":false,"costs_property":"","space_comment":"","address_hidden":false,"address_unclear":false,"costs_rent_comment":"","space":"1000","region":"Одеська область","space_units_hidden":false,"costs_rent":""}],"31":[{"costs_property_comment":"","address":"м. Одеса","space_units":"м²","space_unclear":false,"region_hidden":false,"costs_property":"","space_comment":"55. 9-спадщина","address_hidden":false,"space_comment_unclear":false,"costs_rent_comment":"","space":"86","region":"Одеська область","costs_rent":""},{"costs_property_comment":"","address":"","space_units":"","space_unclear":true,"region_hidden":false,"costs_property":"","space_comment":"","address_hidden":false,"costs_rent_comment":"","space":"","region":"","costs_rent":""}],"33":[{"costs_property_comment":"","address":"м. Одеса","space_units":"м²","space_comment":"","region_hidden":false,"costs_property":"","region":"Одеська область","address_hidden":false,"address_unclear":false,"costs_rent_comment":"","space":"12","costs_rent":""}],"34":[{"costs_property_comment":"","address":"м. Одеса","space_units":"м²","costs_rent_comment":"","space":"56.6","region":"Одеська область","region_hidden":false,"costs_property":"","space_comment":"оренда офісу","costs_rent":""}]},"vehicle":{"35":[{"brand_info":"1800 куб. см.","sum_rent_comment":"","brand_unclear":false,"year":"1992","brand_hidden":false,"sum_comment":"","brand_info_hidden":false,"sum_rent":"","brand":"Volkswagen Golf III","year_unclear":false,"brand_info_unclear":false,"sum":""}],"40":[{"sum_comment":"","brand_info":"2400 куб. см.","sum":"","brand_unclear":false,"year":"2004","brand":"Mitsubishi Outlander","sum_rent":"","sum_rent_comment":"","brand_hidden":false,"brand_info_unclear":false,"year_unclear":false},{"sum_comment":"","brand_info":"2800 куб. см.","sum":"","sum_rent_comment":"","year":"1997","brand":"Audi A6","sum_rent":""}]},"source":"VULYK","income":{"5":{"family":"756155","family_comment":"","comment":"","value_hidden":false,"value_unclear":false,"value":"230459","family_hidden":false,"family_unclear":false},"6":{"family_comment":"","family":"","value_hidden":false,"comment":"","comment_unclear":false,"value_unclear":false,"value":"230459","family_hidden":false},"7":{"source_name_hidden":false,"family_comment":"","family":"","value_hidden":false,"comment":"","value":"","source_name":""},"8":{"family_comment":"","value":"","family":"","comment":""},"9":{"family_comment":"","comment_unclear":false,"value":"","family":"","comment":""},"10":{"family_comment":"","value":"","family":"","comment":"","value_unclear":false},"11":{"family_comment":"","value":"","family":"","comment":""},"12":{"family_comment":"","value":"","family":"","comment":""},"13":{"family_comment":"","value":"","family":"","comment":""},"14":{"family_comment":"","value":"","family":"","comment":""},"15":{"family_comment":"","value":"","family":"","comment":""},"16":{"family_comment":"","value":"","family":"","comment":""},"17":{"family_comment":"","value":"","family":"756155","comment":""},"18":{"family_comment":"","value":"","family":"","comment":""},"19":{"family":"","family_comment":"","comment":"","value_hidden":false,"value_unclear":false,"comment_hidden":false,"family_hidden":false,"value":"","family_comment_hidden":false},"20":{"family_comment":"","family":"","value_hidden":false,"comment":"","value":"","comment_unclear":false,"value_unclear":false,"family_unclear":false,"family_hidden":false}},"general":{"family":[{"inn":"","inn_unclear":false,"family_name":"","relations_other":"","relations_hidden":false,"name_unclear":false,"inn_hidden":true,"name_hidden":true,"relations":"Подружжя"},{"inn":"","inn_unclear":false,"family_name":"","relations_hidden":false,"relations_unclear":false,"name_unclear":false,"relations":"Дитина","inn_hidden":true,"name_hidden":true,"relations_other":""}],"family_raw":"","name":"Валеріан","full_name_suggest":{"input":["Луняченко Валеріан Олександрович","Валеріан Олександрович Луняченко","Валеріан Луняченко"],"output":"Луняченко Валеріан Олександрович"},"name_unclear":false,"patronymic":"Олександрович","inn_hidden":true,"addresses":[{"place_city_type":"Місто","place_address_unclear":false,"place_city_type_hidden":false,"place_hidden":false,"place_city_hidden":false,"place_district":"","place_district_hidden":false,"place":"Одеська область","place_city":"Одеса","place_address_hidden":false,"place_address":"65058"}],"last_name_hidden":false,"patronymic_hidden":false,"inn":"","inn_unclear":false,"last_name":"Луняченко","full_name":"Луняченко Валеріан Олександрович","post":{"post_hidden":false,"office":"Загальний місцевий суд","post":"суддя київського районного суду м. одеси","region":"Одеська область","region_hidden":false,"office_unclear":false,"office_hidden":false,"post_unclear":false,"region_unclear":false},"name_hidden":false,"last_name_unclear":false},"liabilities":{"54":{"sum_comment_unclear":false,"sum_comment":"","sum_hidden":false,"sum":"","sum_foreign_comment":"","sum_foreign":"","sum_comment_hidden":false},"55":{"sum_comment":"","sum_foreign_comment":"","sum_foreign":"","sum":""},"56":{"sum_comment":"","sum_foreign_comment":"","sum_foreign":"","sum_unclear":false,"sum":""},"57":{"sum_comment_unclear":false,"sum_comment":"","sum":"","sum_foreign_comment":"","sum_foreign":"","sum_unclear":false},"58":{"sum_comment_unclear":false,"sum_comment":"","sum":"","sum_foreign_comment":"","sum_foreign":"","sum_unclear":false},"59":{"sum_comment":"","sum_foreign_comment":"","sum_foreign":"","sum":""},"60":{"sum_comment":"","sum_comment_unclear":false,"sum_foreign_comment":"","sum":"","sum_foreign":""},"61":{"sum_comment":"","sum_foreign_comment":"","sum_foreign":"","sum":""},"62":{"sum_comment":"","sum_foreign_comment":"","sum_foreign":"","sum":""},"63":{"sum_comment":"","sum_foreign_comment":"","sum_foreign":"","sum":""},"64":{"sum_comment":"","sum_foreign_comment":"","sum_foreign":"","sum_unclear":false,"sum":""}},"declaration":{"notfull_lostpages":"","additional_info_text":"","additional_info":"","date":"2015-04-08T00:00:00","notfull":"","url":"http://static.declarations.com.ua/declarations/chosen_ones/mega_batch/luniachenko_valerian_oleksandrovych.pdf"},"intro":{"declaration_year_hidden":false,"isnotdeclaration":"","declaration_year":"2014"}}]