[{"id":"vulyk_108_108","ft_src":"1596 куб. см., 79 кВт , 451 см\n2012\nNissan Almera\n1568 куб. см., 54 кВт , 416.6 см\nВАЗ 2106\n1985\n55.5\n2015\n220527.44\n1268.82\n73443.88\n221796.26\n38746.9\n1596 куб. см., 79 кВт , 451 см\n2012\nNissan Almera\n1568 куб. см., 54 кВт , 416.6 см\n1985\nВАЗ 2106\n2015\nМакаров Микола Олексійович\nМикола Олексійович Макаров\nМикола Макаров\nМакаров Микола Олексійович\nМикола\nПодружжя\nМакарова С. В\nДитина\nМакаров М. М\nМакарова А. М\nДитина\nДячук М. С\nІнше\nвітчим дружини\nМакаров Микола Олексійович\nОлексійович\nЗагальний апеляційний суд\nДніпропетровська область\nсуддя апеляційного суду дніпропетровської області\nМакаров\n29674.52\n20582.72\n1800.21\n1268.82\n220527.44\n38746.9\n221796.26\n73443.88\n55.5\n1800.21\n29674.52\n20582.72\nПодружжя\nМакарова С. В\nДитина\nМакаров М. М\nМакарова А. М\nДитина\nІнше\nвітчим дружини\nДячук М. С\nОлексійович\nМакаров\nМикола\nМакаров Микола Олексійович\nМикола Олексійович Макаров\nМикола Макаров\nМакаров Микола Олексійович\nДніпропетровська область\nсуддя апеляційного суду дніпропетровської області\nЗагальний апеляційний суд\nМакаров Микола Олексійович","estate":{"30":[{"costs_property_comment":"","address":"","space_units":"м²","costs_rent_comment":"","space":"55.5","region":"","region_hidden":true,"costs_property":"","space_comment":"","address_hidden":true,"costs_rent":""}]},"vehicle":{"35":[{"sum_comment":"","brand_info":"1596 куб. см., 79 кВт , 451 см","sum":"","sum_rent_comment":"","year":"2012","brand":"Nissan Almera","sum_rent":"","brand_info_unclear":false}],"40":[{"sum_comment":"","brand_info":"1568 куб. см., 54 кВт , 416.6 см","brand_unclear":false,"sum_rent_comment":"","year":"1985","brand":"ВАЗ 2106","sum_rent":"","brand_info_unclear":false,"year_unclear":false,"sum":""}]},"source":"VULYK","income":{"5":{"family_comment":"","family":"73443.88","comment":"","value_unclear":false,"family_unclear":false,"value":"221796.26"},"6":{"family_comment":"","value":"220527.44","family_unclear":false,"family":"","comment":""},"7":{"family_comment":"","comment":"","family":"","source_name_unclear":false,"value":"1268.82","source_name":""},"8":{"family_comment":"","value":"","family":"","comment":""},"9":{"family_comment":"","family":"","comment":"","family_unclear":false,"comment_hidden":false,"value":"","family_comment_hidden":false},"10":{"family_comment":"","value":"","family":"","comment":""},"11":{"family_comment":"","value":"","family":"","comment":""},"12":{"family_comment":"","value":"","family":"","comment":""},"13":{"family_comment":"","value":"","family":"","comment":""},"14":{"family_comment":"","value":"","family":"","comment":""},"15":{"family_comment":"","value":"","family":"","comment":""},"16":{"family_comment":"","value":"","family":"","comment":""},"17":{"family_comment":"","value":"","family":"","comment":""},"18":{"family_comment":"","value":"","family":"","comment":""},"19":{"family_comment":"","value":"","family":"","comment":""},"20":{"family_comment":"","comment":"","family":"","value_unclear":false,"comment_hidden":false,"comment_unclear":false,"value":"38746.9"}},"general":{"family_raw":"","name":"Микола","full_name_suggest":{"input":["Макаров Микола Олексійович","Микола Олексійович Макаров","Микола Макаров"],"output":"Макаров Микола Олексійович"},"patronymic":"Олексійович","inn_hidden":true,"addresses":[{"place_city_type_hidden":false,"place_hidden":true,"place_address_unclear":false,"place":"","place_city":"","place_unclear":false,"place_city_type":"","place_city_hidden":false,"place_district":"","place_district_hidden":false,"place_address":"","place_address_hidden":false}],"inn":"","inn_unclear":false,"last_name":"Макаров","full_name":"Макаров Микола Олексійович","family":[{"inn":"","inn_unclear":false,"family_name":"Макарова С. В","relations_hidden":false,"name_unclear":false,"relations":"Подружжя","inn_hidden":false,"name_hidden":false,"relations_other":""},{"inn":"","family_name":"Макаров М. М","relations_other":"","name_unclear":false,"inn_hidden":false,"name_hidden":false,"relations":"Дитина"},{"inn":"","name_hidden":false,"family_name":"Макарова А. М","inn_hidden":false,"relations":"Дитина"},{"inn":"","family_name":"Дячук М. С","relations_other":"вітчим дружини","relations":"Інше"}],"post":{"office":"Загальний апеляційний суд","post":"суддя апеляційного суду дніпропетровської області","office_unclear":false,"office_hidden":false,"region":"Дніпропетровська область","post_unclear":false}},"liabilities":{"54":{"sum_comment":"","sum_foreign_comment":"","sum_foreign":"","sum_hidden":false,"sum":""},"55":{"sum_comment":"","sum_foreign_comment":"","sum_foreign":"","sum":""},"56":{"sum_comment":"","sum_foreign_comment":"","sum_foreign":"","sum_unclear":false,"sum":"20582.72"},"57":{"sum_comment":"","sum_hidden":false,"sum":"29674.52","sum_foreign_comment":"","sum_foreign":"","sum_comment_hidden":false},"58":{"sum_comment":"","sum_foreign_comment":"","sum_foreign":"","sum":"1800.21","sum_comment_hidden":false},"59":{"sum_comment":"","sum_foreign_comment":"","sum_foreign":"","sum_unclear":false,"sum":""},"60":{"sum_comment":"","sum_foreign_comment":"","sum_foreign":"","sum":"","sum_comment_hidden":false},"61":{"sum_comment":"","sum_foreign_comment":"","sum_foreign":"","sum":"","sum_comment_hidden":false},"62":{"sum_comment":"","sum_foreign_comment":"","sum_foreign":"","sum":""},"63":{"sum_comment":"","sum_hidden":false,"sum":"","sum_foreign_comment":"","sum_foreign":"","sum_unclear":false,"sum_comment_hidden":false},"64":{"sum_comment":"","sum":"","sum_foreign_comment":"","sum_foreign":"","sum_unclear":false,"sum_comment_hidden":false}},"declaration":{"notfull_lostpages":"","additional_info_text":"","additional_info":"","date":"2016-03-29T00:00:00","notfull":"","url":"http://static.declarations.com.ua/declarations/chosen_ones/judges_batch/2407_makarov_mykola_oleksiiovych_2015.pdf"},"intro":{"declaration_year_hidden":false,"isnotdeclaration":"","declaration_year":"2015"}},{"id":"vulyk_41_156","declaration":{"additional_info_text":"","additional_info":"","date":"2015-03-18T00:00:00","url":"http://static.declarations.com.ua/declarations/chosen_ones/mega_batch/makarov_mykola_oleksiiovych.pdf"},"estate":{"23":[{"address":"","space_units":"м²","costs_comment":"","space_unclear":false,"region_hidden":false,"space_units_unclear":false,"space_comment":"","address_hidden":false,"space_comment_hidden":false,"space":"","costs_comment_unclear":false,"costs_rent_comment":"","costs":"","region_unclear":false,"region":"","costs_rent":""},{"costs":"","address":"","space_units":"","costs_rent_comment":"","space":"","space_unclear":false,"space_comment":"","costs_comment":"","region":"","costs_rent":""},{"costs":"","address":"","space_units":"","costs_rent_comment":"","space":"","space_comment":"","costs_comment":"","region":"","costs_rent":""}],"30":[{"costs_property_comment":"","address":"","space_units":"м²","costs_rent_comment":"","space":"55.5","region":"","region_hidden":true,"costs_property":"","space_comment":"","address_hidden":false,"costs_rent":""}]},"vehicle":{"35":[{"sum_comment":"","brand_info_hidden":false,"brand_info":"4 1596 79 КвТ 451,0 см","sum":"","sum_rent_comment":"","year":"2012","brand":"Nissan Almera","sum_rent":""}],"40":[{"sum_comment":"","brand_info_hidden":false,"brand_info":"4, 1568 куб.см, 54 кВт , 416,6 см","sum":"","sum_rent_comment":"","year":"1985","brand":"ВАЗ 2106","sum_rent":""}]},"source":"VULYK","income":{"5":{"family_comment":"","family":"80389.06","comment":"","family_unclear":false,"family_hidden":false,"value":"237639.83"},"6":{"family_comment":"","family_hidden":false,"value":"236262.07","family":"","comment":""},"7":{"family":"","family_comment":"","value":"1377.76","comment":"","source_name":""},"8":{"family_comment":"","value":"","family":"","comment":""},"9":{"family_comment":"","comment":"","family":"","comment_unclear":false,"value":"","family_hidden":false},"10":{"family_comment":"","value":"","family":"","comment":""},"11":{"family_comment":"","value":"","family":"","comment":""},"12":{"family_comment":"","value":"","family":"","comment":""},"13":{"family_comment":"","value":"","family":"","comment":""},"14":{"family_comment":"","value":"","family":"","comment":""},"15":{"family_comment":"","value":"","family":"","comment":"","value_unclear":false},"16":{"family_comment":"","value":"","family":"","comment":""},"17":{"family_comment":"","value":"","family":"","comment":""},"18":{"family_comment":"","value":"","family":"","comment":""},"19":{"family_comment":"","value":"","family":"","comment":""},"20":{"family_comment":"","family":"","value_hidden":false,"comment":"","comment_hidden":false,"comment_unclear":false,"value_unclear":false,"value":"15104.22","family_hidden":false,"family_comment_hidden":false}},"banks":{"45":[{"sum_units":"UAH","sum_comment":"","sum_foreign_units":"UAH","sum_hidden":false,"sum":"","sum_foreign_comment":"","sum_foreign_unclear":false,"sum_foreign":"","sum_comment_hidden":false},{"sum_units":"","sum_comment":"","sum_foreign_units":"","sum":"","sum_foreign_comment":"","sum_foreign_unclear":false,"sum_foreign":""}],"46":[{"sum_units":"UAH","sum_comment":"","sum_foreign_units":"UAH","sum":"","sum_foreign_comment":"","sum_foreign":"","sum_unclear":false,"sum_comment_hidden":false},{"sum_units":"","sum_comment":"","sum_foreign_units":"","sum":"","sum_foreign_comment":"","sum_foreign":"","sum_unclear":false}],"47":[{"sum_units":"UAH","sum_comment":"","sum_foreign_units":"UAH","sum":"","sum_foreign_comment":"","sum_foreign":""},{"sum_units":"","sum_comment":"","sum_foreign_units":"","sum":"","sum_foreign_comment":"","sum_foreign":""}],"48":[{"sum_units":"UAH","sum_comment":"","sum_foreign_units":"UAH","sum":"","sum_foreign_comment":"","sum_foreign":""}],"49":[{"sum_units":"UAH","sum_comment":"","sum_foreign_units":"UAH","sum":"","sum_foreign_comment":"","sum_foreign":""}],"50":[{"sum_units":"UAH","sum_comment":"","sum_foreign_units":"UAH","sum":"","sum_foreign_comment":"","sum_foreign":""}],"51":[{"sum_units":"UAH","sum_comment":"","sum_foreign_units":"UAH","sum_hidden":false,"sum":"","sum_foreign_comment":"","sum_foreign":"","sum_unclear":false,"sum_comment_hidden":false},{"sum_units":"","sum_comment":"","sum_foreign_units":"","sum":"","sum_foreign_comment":"","sum_foreign":""}],"52":[{"sum_units":"UAH","sum_comment":"","sum_foreign_units":"UAH","sum":"","sum_foreign_comment":"","sum_foreign":"","sum_unclear":false,"sum_comment_hidden":false}],"53":[{"sum_units":"UAH","sum_comment":"","sum_foreign_units":"UAH","sum":"","sum_foreign_comment":"","sum_foreign":"","sum_comment_hidden":false},{"sum_units":"","sum_comment":"","sum_foreign_units":"","sum":"","sum_foreign_comment":"","sum_foreign":""},{"sum_units":"","sum_comment":"","sum_foreign_units":"","sum":"","sum_foreign_comment":"","sum_foreign":""}]},"ft_src":"4 1596 79 КвТ 451,0 см\n2012\nNissan Almera\n4, 1568 куб.см, 54 кВт , 416,6 см\n1985\nВАЗ 2106\n2014\nNissan Almera\n4 1596 79 КвТ 451,0 см\n2012\nВАЗ 2106\n4, 1568 куб.см, 54 кВт , 416,6 см\n1985\n55.5\nПодружжя\nМакарова С. В\nДитина\nМакаров М. М\nДитина\nМакарова А. М\nДячук М. С\nІнше\nтесть\nМакаров Микола Олексійович\nМикола Олексійович Макаров\nМикола Макаров\nМакаров Микола Олексійович\nМакаров Микола Олексійович\nМикола\nОлексійович\nЗагальний апеляційний суд\nсуддя апеляційного суду дніпропетровської області\nДніпропетровська область\nМакаров\n138524.29\n4257.05\n2160.84\n1377.76\n236262.07\n15104.22\n237639.83\n80389.06\n2014\n2160.84\n138524.29\n4257.05\n55.5\nМакарова С. В\nПодружжя\nМакаров М. М\nДитина\nМакарова А. М\nДитина\nІнше\nтесть\nДячук М. С\nОлексійович\nМакаров\nМикола\nМакаров Микола Олексійович\nМикола Олексійович Макаров\nМикола Макаров\nМакаров Микола Олексійович\nДніпропетровська область\nсуддя апеляційного суду дніпропетровської області\nЗагальний апеляційний суд\nМакаров Микола Олексійович\n236262.07\n1377.76\n80389.06\n237639.83\n15104.22","general":{"family":[{"inn":"","family_name":"Макарова С. В","relations_hidden":false,"name_unclear":false,"inn_hidden":false,"name_hidden":false,"relations":"Подружжя"},{"inn":"","family_name":"Макаров М. М","relations_other":"","name_unclear":false,"inn_hidden":false,"name_hidden":false,"relations":"Дитина"},{"inn":"","family_name":"Макарова А. М","relations_other":"","name_unclear":false,"inn_hidden":false,"name_hidden":false,"relations":"Дитина"},{"inn":"","family_name":"Дячук М. С","relations_other":"тесть","relations":"Інше"}],"family_raw":"","name":"Микола","full_name_suggest":{"input":["Макаров Микола Олексійович","Микола Олексійович Макаров","Микола Макаров"],"output":"Макаров Микола Олексійович"},"name_unclear":false,"patronymic":"Олексійович","inn_hidden":true,"patronymic_hidden":false,"inn":"","addresses":[{"place_city_type_hidden":false,"place_city_type":"","place_city_hidden":false,"place_hidden":true,"place_district":"","place_district_hidden":false,"place":"","place_address":"","place_address_hidden":false,"place_city":""}],"last_name":"Макаров","full_name":"Макаров Микола Олексійович","post":{"post_hidden":false,"office":"Загальний апеляційний суд","post":"суддя апеляційного суду дніпропетровської області","office_hidden":false,"region":"Дніпропетровська область","region_hidden":false,"post_unclear":false},"last_name_unclear":false},"liabilities":{"54":{"sum_comment":"","sum_foreign_comment":"","sum_foreign":"","sum":"","sum_comment_hidden":false},"55":{"sum_comment":"","sum_foreign_comment":"","sum_foreign":"","sum":""},"56":{"sum_comment":"","sum_foreign_comment":"","sum_foreign":"","sum_hidden":false,"sum":""},"57":{"sum_comment":"","sum":"138524.29","sum_foreign_comment":"","sum_foreign":"","sum_unclear":false,"sum_comment_hidden":false},"58":{"sum_comment":"","sum_foreign_comment":"","sum_foreign":"","sum":"2160.84","sum_comment_hidden":false},"59":{"sum_comment":"","sum_foreign_comment":"","sum_foreign":"","sum":""},"60":{"sum_comment":"","sum_foreign_comment":"","sum_foreign":"","sum":"","sum_comment_hidden":false},"61":{"sum_comment":"","sum_foreign_comment":"","sum_foreign":"","sum":""},"62":{"sum_comment":"","sum_foreign_comment":"","sum_foreign":"","sum":"4257.05"},"63":{"sum_comment":"","sum":"","sum_foreign_comment":"","sum_foreign":"","sum_unclear":false,"sum_comment_hidden":false},"64":{"sum_comment":"","sum_foreign_comment":"","sum_foreign":"","sum":"","sum_comment_hidden":false}},"intro":{"declaration_year":"2014"}},{"id":"vulyk_71_171","ft_src":".1596 куб.см., 79 кВт , 4510 мм\nNissan Almera\n2012\n107100\n1568 куб.см., 54 кВт , 4166 мм\nВАЗ 2106\n1985\n55.5\n2013\n225670\n77335.33\n225670\nкредит\n115000\n.1596 куб.см., 79 кВт , 4510 мм\nNissan Almera\n2012\n107100\n1568 куб.см., 54 кВт , 4166 мм\n1985\nВАЗ 2106\n55.5\nПодружжя\nМакарова С. В\nДитина\nМакаров М. М\nДитина\nМакарова А. М\nДячук М. С\nІнше\nМакаров Микола Олексійович\nМикола Олексійович Макаров\nМикола Макаров\nМакаров Микола Олексійович\nМакаров Микола Олексійович\nМикола\nОлексійович\nЗагальний апеляційний суд\nДніпропетровська область\nсуддя апеляційного суду дніпропетровської області\nМакаров\n2489.06\n41668.65\n9947.3\n225670\n115000\nкредит\n225670\n77335.33\n2013\n2489.06\n41668.65\n9947.3\nМакарова С. В\nПодружжя\nМакаров М. М\nДитина\nМакарова А. М\nДитина\nІнше\nДячук М. С\nОлексійович\nМакаров\nМикола\nМакаров Микола Олексійович\nМикола Олексійович Макаров\nМикола Макаров\nМакаров Микола Олексійович\nДніпропетровська область\nЗагальний апеляційний суд\nсуддя апеляційного суду дніпропетровської області\nМакаров Микола Олексійович","estate":{"30":[{"costs_property_comment":"","address":"","space_units":"м²","costs_rent_comment":"","space":"55.5","region":"","region_hidden":false,"costs_property":"","space_comment":"","address_hidden":false,"costs_rent":""}]},"vehicle":{"35":[{"brand_info":".1596 куб.см., 79 кВт , 4510 мм","brand_unclear":false,"sum_rent_comment":"","year":"2012","sum_comment":"","sum_rent":"","sum_rent_unclear":false,"brand":"Nissan Almera","year_unclear":false,"brand_info_unclear":false,"sum_unclear":false,"sum":"107100"}],"40":[{"sum_comment":"","brand_info_hidden":false,"sum_rent":"","sum":"","brand_unclear":false,"year":"1985","brand":"ВАЗ 2106","brand_info":"1568 куб.см., 54 кВт , 4166 мм","sum_rent_comment":"","brand_info_unclear":false}]},"source":"VULYK","income":{"5":{"family_comment":"","family":"77335.33","value_hidden":false,"comment":"","value":"225670","comment_unclear":false,"value_unclear":false,"family_unclear":false,"family_hidden":false},"6":{"family_comment":"","family":"","comment":"","family_unclear":false,"family_hidden":false,"value":"225670"},"7":{"family_comment":"","family":"","value_hidden":false,"comment":"","family_hidden":false,"value":"","source_name":""},"8":{"family_comment":"","value":"","family":"","comment":""},"9":{"family_comment":"","value":"","family":"","comment":"","value_unclear":false},"10":{"family_comment":"","value":"","family_unclear":false,"family":"","comment":""},"11":{"family_comment":"","value":"","family":"","comment":""},"12":{"family_comment":"","value":"","family":"","comment":""},"13":{"family_comment":"","value":"","family":"","comment":""},"14":{"family_comment":"","value":"","family":"","comment":""},"15":{"family_comment":"","value":"","family":"","comment":""},"16":{"family_comment":"","value":"","family":"","comment":""},"17":{"family_comment":"","value":"","family":"","comment":""},"18":{"family_comment":"","value":"","family":"","comment":""},"19":{"family_comment":"","value":"","family":"","comment":""},"20":{"family_comment":"","comment":"кредит","family":"","value_unclear":false,"comment_unclear":true,"value":"115000"}},"general":{"family":[{"inn":"","family_name":"Макарова С. В","relations_other":"","relations_hidden":false,"name_unclear":false,"inn_hidden":false,"name_hidden":false,"relations":"Подружжя"},{"inn":"","family_name":"Макаров М. М","relations_other":"","relations_hidden":false,"name_unclear":false,"inn_hidden":false,"name_hidden":false,"relations":"Дитина"},{"inn":"","family_name":"Макарова А. М","relations_other":"","name_unclear":false,"inn_hidden":false,"relations":"Дитина"},{"inn":"","family_name":"Дячук М. С","inn_hidden":false,"relations_other":"","relations":"Інше"}],"family_raw":"","name":"Микола","full_name_suggest":{"input":["Макаров Микола Олексійович","Микола Олексійович Макаров","Микола Макаров"],"output":"Макаров Микола Олексійович"},"name_unclear":false,"patronymic":"Олексійович","inn_hidden":false,"patronymic_hidden":false,"inn":"","inn_unclear":false,"last_name":"Макаров","full_name":"Макаров Микола Олексійович","post":{"post_hidden":false,"office":"Загальний апеляційний суд","post":"суддя апеляційного суду дніпропетровської області","office_unclear":false,"region_unclear":false,"region":"Дніпропетровська область","post_unclear":false},"last_name_unclear":false},"liabilities":{"54":{"sum_comment_unclear":false,"sum_comment":"","sum":"","sum_foreign_comment":"","sum_foreign":"","sum_unclear":false,"sum_comment_hidden":false},"55":{"sum_comment":"","sum_foreign_comment":"","sum_foreign":"","sum":""},"56":{"sum_comment_unclear":false,"sum_comment":"","sum":"","sum_foreign_comment":"","sum_foreign":"","sum_unclear":false},"57":{"sum_comment":"","sum":"41668.65","sum_foreign_comment":"","sum_foreign":"","sum_unclear":false,"sum_comment_hidden":false},"58":{"sum_comment":"","sum":"2489.06","sum_foreign_comment":"","sum_foreign":"","sum_unclear":false,"sum_comment_hidden":false},"59":{"sum_comment":"","sum_foreign_comment":"","sum_foreign":"","sum":"","sum_comment_hidden":false},"60":{"sum_comment":"","sum_foreign_comment":"","sum_foreign":"","sum":"","sum_comment_hidden":false},"61":{"sum_comment":"","sum_foreign_comment":"","sum_foreign":"","sum":""},"62":{"sum_comment":"","sum_foreign_comment":"","sum_foreign":"","sum":"9947.3"},"63":{"sum_comment":"","sum_foreign_comment":"","sum_foreign":"","sum_unclear":false,"sum":""},"64":{"sum_comment":"","sum_foreign_comment":"","sum_foreign":"","sum_unclear":false,"sum":""}},"declaration":{"notfull_lostpages":"","additional_info_text":"","additional_info":"","date":"2014-03-27T00:00:00","notfull":"","url":"http://static.declarations.com.ua/declarations/chosen_ones/judges_batch/431_makarov_mykola_oleksiiovych.pdf"},"intro":{"isnotdeclaration":"","declaration_year":"2013"}}]