[{"id":"vulyk_103_41","ft_src":"Nissan Murano\n3500 куб. см., 249 к.с.\n2013\n2998 куб. см., 220 к.с.\n2007\nMitsubishi Outlander\n1498 куб. см., 85 к.с.\n2005\nЗАЗ Daewoo Lanos\n1990\nКазанка 5М3\n4.5 м\n75 к. с\nМосквич / АЗЛК ИЖ 21251\n1987\n20.8\n64300\n800\n59800\n49.9\nпаркомісце, договір оренди\nпаркомісце\n8590\n28\n51.8\n8210\nдоговір найму\n87.6\n933\n144437\n2015\n4.5 м\n1990\nКазанка 5М3\n3500 куб. см., 249 к.с.\n2013\nNissan Murano\n2998 куб. см., 220 к.с.\n2007\nMitsubishi Outlander\n1498 куб. см., 85 к.с.\n2005\nЗАЗ Daewoo Lanos\n75 к. с\n1987\nМосквич / АЗЛК ИЖ 21251\n20.8\nпаркомісце, договір оренди\nпаркомісце\n8590\n51.8\n8210\nдоговір найму\n87.6\n28\n64300\n800\n59800\n49.9\nМакарчук\nМакарчук Михайло Андрійович\nМихайло Андрійович Макарчук\nМихайло Макарчук\nМакарчук Михайло Андрійович\nМакарчук Михайло Андрійович\nАндрійович\nПодружжя\nМакарчук Н. М\nМакарчук К. В\nБатьки\nІнше\nЧеревченко М. І\nбатько дружини\nМихайло\nВищий спеціалізований суд з розгляду цивільних і кримінальних справ\nсуддя вищого спецiалiзованого суду україни з розгляду цивiльних і кримiнальних справ, член вищої кваліфікаційної комісії суддів україни\nЗагальнодержавний регіон\n304104\n33462\n304815\n76691\n40000\n729\n711\n2500\n144437\n933\n2015\n304104\n33462\n729\n711\n76691\n304815\n40000\n2500\nПодружжя\nМакарчук Н. М\nБатьки\nМакарчук К. В\nІнше\nЧеревченко М. І\nбатько дружини\nМакарчук\nАндрійович\nсуддя вищого спецiалiзованого суду україни з розгляду цивiльних і кримiнальних справ, член вищої кваліфікаційної комісії суддів україни\nВищий спеціалізований суд з розгляду цивільних і кримінальних справ\nЗагальнодержавний регіон\nМакарчук Михайло Андрійович\nМакарчук Михайло Андрійович\nМихайло Андрійович Макарчук\nМихайло Макарчук\nМакарчук Михайло Андрійович\nМихайло","estate":{"23":[{"costs":"","address":"","space_units":"м²","costs_rent_comment":"","space":"28","space_comment":"","region_hidden":true,"costs_comment":"","region":"","address_hidden":false,"costs_rent":""}],"24":[{"address":"","space_units":"м²","space_hidden":false,"space_unclear":false,"region_hidden":true,"costs_comment":"","space_comment":"","address_hidden":false,"space":"49.9","costs_rent_comment":"","costs":"","region":"","costs_rent":""}],"25":[{"address":"","space_units":"м²","costs_comment":"","region_hidden":true,"space_comment":"","address_hidden":false,"space_comment_hidden":false,"space":"51.8","space_comment_unclear":false,"costs_rent_comment":"","costs":"","region":"","costs_rent":""},{"costs":"","address":"","space_units":"м²","costs_rent_comment":"договір найму","space":"87.6","space_comment":"","region_hidden":false,"costs_comment":"","region":"","costs_rent":"8210"}],"27":[{"costs":"","address":"","space_units":"м²","costs_rent_comment":"","space":"20.8","space_comment":"","region_hidden":true,"costs_comment":"","region":"","address_hidden":false,"costs_rent":""}],"28":[{"address":"паркомісце","space_units":"м²","space_hidden":false,"space_unclear":true,"region_hidden":true,"costs_comment":"","space_comment":"паркомісце, договір оренди","address_hidden":false,"space":"","costs_rent_comment":"","costs":"","region":"","costs_rent":"8590"}],"29":[{"costs_property_comment":"","address":"","space_units":"м²","space_hidden":false,"space_comment":"","region_hidden":true,"costs_property":"","region":"","address_hidden":true,"costs_rent_comment":"","space":"64300","costs_rent":""},{"costs_property_comment":"","address":"","space_units":"м²","costs_rent_comment":"","space":"800","costs_property":"","space_comment":"","costs_rent":""},{"costs_property_comment":"","address":"","space_units":"м²","costs_rent_comment":"","space":"59800","space_unclear":true,"costs_property":"","space_comment":"","costs_rent":""}]},"vehicle":{"35":[{"sum_comment":"","brand_info_hidden":false,"brand_info":"3500 куб. см., 249 к.с.","sum":"","brand_unclear":false,"brand_hidden":false,"brand":"Nissan Murano","sum_rent":"","brand_info_unclear":false,"sum_rent_comment":"","year":"2013"},{"sum_comment":"","brand_info":"2998 куб. см., 220 к.с.","sum":"","sum_rent_comment":"","year":"2007","brand":"Mitsubishi Outlander","sum_rent":""},{"sum_comment":"","brand_info":"1498 куб. см., 85 к.с.","sum":"","sum_rent_comment":"","year":"2005","brand":"ЗАЗ Daewoo Lanos","sum_rent":""}],"37":[{"sum_comment":"","brand_info":"4.5 м","sum":"","sum_rent_comment":"","brand_hidden":false,"brand":"Казанка 5М3","sum_rent":"","brand_info_unclear":true,"year":"1990"}],"40":[{"year_hidden":false,"brand_info":"75 к. с","sum":"","sum_rent_comment":"","brand_hidden":false,"brand":"Москвич / АЗЛК ИЖ 21251","sum_rent":"","sum_comment":"","year":"1987","brand_info_unclear":false}]},"source":"VULYK","income":{"5":{"family_comment":"","family":"76691","comment":"","value_unclear":false,"family_hidden":false,"value":"304815"},"6":{"family_comment":"","value":"304104","family":"","comment":""},"7":{"family":"","family_comment":"","value":"","comment":"","source_name":""},"8":{"family_comment":"","value":"","family":"","comment":""},"9":{"family_comment":"","value":"","family":"729","comment":""},"10":{"family_comment":"","value":"","family":"","comment":""},"11":{"family_comment":"","family_hidden":false,"value":"711","family":"","comment":""},"12":{"family_comment":"","value":"","family":"","comment":""},"13":{"family_comment":"","value":"","family":"","comment":""},"14":{"family_comment":"","value":"","family":"","comment":""},"15":{"family_comment":"","value":"","family":"33462","comment":""},"16":{"family_comment":"","value":"","family":"40000","comment":""},"17":{"family_comment":"","value":"","family":"","comment":"","family_comment_unclear":false},"18":{"family_comment":"","value":"","family":"","comment":""},"19":{"family_comment":"","value":"","family":"2500","comment":""},"20":{"family_comment":"","family":"","comment":"","family_unclear":false,"family_hidden":false,"value":""}},"banks":{"45":[{"sum_units":"UAH","sum_comment":"","sum_foreign_units":"UAH","sum_hidden":true,"sum":"144437","sum_foreign_comment":"","sum_foreign":"","sum_unclear":true,"sum_comment_hidden":true}],"51":[{"sum_units":"UAH","sum_comment":"","sum_foreign_units":"UAH","sum_hidden":true,"sum":"933","sum_foreign_comment_hidden":false,"sum_foreign_comment":"","sum_foreign":"","sum_foreign_hidden":false,"sum_comment_hidden":true}]},"declaration":{"additional_info_text":"","additional_info":"","date":"2016-03-30T00:00:00","url":"http://static.declarations.com.ua/declarations/chosen_ones/judges_batch/1265_makarchuk_mykhailo_andriiovych.pdf"},"general":{"inn":"","addresses":[{"place_city_type_hidden":false,"place_city_type":"","place_city_hidden":true,"place_hidden":true,"place_district":"","place_district_hidden":false,"place":"","place_city":"","place_address_hidden":true,"place_address":""}],"last_name":"Макарчук","full_name":"Макарчук Михайло Андрійович","family":[{"inn":"","family_name":"Макарчук Н. М","relations_hidden":false,"name_unclear":false,"relations":"Подружжя","inn_hidden":true,"name_hidden":true,"relations_other":""},{"inn":"","family_name":"Макарчук К. В","inn_hidden":false,"relations_other":"","relations":"Батьки"},{"inn":"","family_name":"Черевченко М. І","relations_other":"батько дружини","name_unclear":false,"inn_hidden":false,"relations":"Інше"}],"patronymic":"Андрійович","inn_hidden":true,"name":"Михайло","post":{"office":"Вищий спеціалізований суд з розгляду цивільних і кримінальних справ","region_unclear":false,"post":"суддя вищого спецiалiзованого суду україни з розгляду цивiльних і кримiнальних справ, член вищої кваліфікаційної комісії суддів україни","region":"Загальнодержавний регіон","office_unclear":false},"family_raw":"","full_name_suggest":{"input":["Макарчук Михайло Андрійович","Михайло Андрійович Макарчук","Михайло Макарчук"],"output":"Макарчук Михайло Андрійович"}},"liabilities":{"54":{"sum_foreign_comment_hidden":false,"sum_foreign_comment_unclear":false,"sum_hidden":false,"sum":"","sum_foreign_comment":"","sum_comment":"","sum_unclear":false,"sum_foreign":"","sum_comment_hidden":false,"sum_foreign_hidden":false},"55":{"sum_comment":"","sum_foreign_comment":"","sum_foreign":"","sum":""},"56":{"sum_comment":"","sum_foreign_comment":"","sum_foreign":"","sum":""},"57":{"sum_comment":"","sum_hidden":false,"sum":"","sum_foreign_comment":"","sum_foreign":"","sum_comment_hidden":false,"sum_foreign_hidden":false,"sum_foreign_comment_hidden":false},"58":{"sum_comment":"","sum_hidden":false,"sum":"","sum_foreign_comment":"","sum_foreign":"","sum_comment_hidden":false,"sum_foreign_hidden":false,"sum_foreign_comment_hidden":false},"59":{"sum_comment":"","sum_hidden":false,"sum":"","sum_foreign_comment":"","sum_foreign":"","sum_comment_hidden":false,"sum_foreign_hidden":false,"sum_foreign_comment_hidden":false},"60":{"sum_comment":"","sum_hidden":false,"sum":"","sum_foreign_comment":"","sum_foreign":"","sum_comment_hidden":false},"61":{"sum_comment":"","sum_foreign_comment":"","sum_foreign":"","sum":""},"62":{"sum_comment":"","sum_foreign_comment":"","sum_foreign":"","sum":"","sum_comment_hidden":false},"63":{"sum_comment":"","sum_foreign_comment":"","sum_foreign":"","sum":""},"64":{"sum_comment":"","sum_foreign_comment":"","sum_foreign":"","sum":""}},"intro":{"declaration_year":"2015"}},{"id":"vulyk_9_71","declaration":{"additional_info_text":"1. Батьки за станом здоров'я не можуть точно підрахувати розмір отриманих пенсій та розмір орендної плати за землю. 2. Батько дружини - Черевченко М. І. у 2014 році продав належні йому: а) будинко з господарськими будівлями за 34754 грн. б) земельну ділянку площею 0,508 га за 45517 грн. в) земельну ділянку площею 0,13 га за 24483 грн. Вартість земельних ділянок станом на 01. 01. 2015 року покупцем не сплачена. Строк сплати відповідно до угод встановлено 25. 10. 2016 р","additional_info":"1","date":"2015-03-30T00:00:00","url":"http://static.declarations.com.ua/declarations/chosen_ones/batch_10/makarchukma.pdf"},"estate":{"23":[{"address":"","space_units":"м²","costs_comment":"","region_hidden":true,"space_comment":"","address_hidden":false,"costs":"","space_comment_unclear":false,"costs_rent_comment":"","space":"28","region":"","costs_rent":""},{"address":"","space_units":"","costs_comment":"","region_hidden":false,"space_comment":"","address_hidden":false,"costs":"","space_comment_unclear":false,"costs_rent_comment":"","space":"","region":"","costs_rent":""},{"address_hidden":false,"costs":"","address":"","space_units":"","costs_rent_comment":"","space":"","space_comment":"","costs_comment":"","region":"","space_comment_unclear":false,"costs_rent":""},{"costs":"","address":"","space_units":"","costs_rent_comment":"","space":"","space_comment":"","costs_comment":"","region":"","address_hidden":false,"costs_rent":""},{"costs":"","address":"","space_units":"","costs_rent_comment":"","space":"","space_comment":"","costs_comment":"","region":"","address_hidden":false,"costs_rent":""},{"costs":"","address":"","space_units":"","costs_rent_comment":"","space":"","space_comment":"","costs_comment":"","region":"","address_hidden":false,"costs_rent":""},{"costs":"","address":"","space_units":"","costs_rent_comment":"","space":"","space_comment":"","costs_comment":"","region":"","address_hidden":false,"costs_rent":""},{"costs":"","address":"","space_units":"","costs_rent_comment":"","space":"","space_comment":"","costs_comment":"","region":"","address_hidden":false,"costs_rent":""},{"costs":"","address":"","space_units":"","costs_rent_comment":"","space":"","space_comment":"","costs_comment":"","region":"","address_hidden":false,"costs_rent":""},{"costs":"","address":"","space_units":"","costs_rent_comment":"","space":"","space_comment":"","costs_comment":"","region":"","address_hidden":false,"costs_rent":""},{"costs":"","address":"","space_units":"","costs_rent_comment":"","space":"","space_comment":"","costs_comment":"","region":"","costs_rent":""},{"costs":"","address":"","space_units":"","costs_rent_comment":"","space":"","space_comment":"","costs_comment":"","region":"","costs_rent":""},{"costs":"","address":"","space_units":"","costs_rent_comment":"","space":"","space_comment":"","costs_comment":"","region":"","costs_rent":""},{"costs":"","address":"","space_units":"","costs_rent_comment":"","space":"","space_comment":"","costs_comment":"","region":"","costs_rent":""},{"costs":"","address":"","space_units":"","costs_rent_comment":"","space":"","space_comment":"","costs_comment":"","region":"","costs_rent":""},{"costs":"","address":"","space_units":"","costs_rent_comment":"","space":"","space_comment":"","costs_comment":"","region":"","costs_rent":""},{"costs":"","address":"","space_units":"","costs_rent_comment":"","space":"","space_comment":"","costs_comment":"","region":"","costs_rent":""},{"costs":"","address":"","space_units":"","costs_rent_comment":"","space":"","space_comment":"","costs_comment":"","region":"","costs_rent":""},{"costs":"","address":"","space_units":"","costs_rent_comment":"","space":"","space_comment":"","costs_comment":"","region":"","costs_rent":""},{"costs":"","address":"","space_units":"","costs_rent_comment":"","space":"","space_comment":"","costs_comment":"","region":"","costs_rent":""}],"24":[{"costs":"","address":"","space_units":"м²","costs_rent_comment":"","space":"49.9","space_comment":"","region_hidden":true,"costs_comment":"","region":"","address_hidden":false,"costs_rent":""}],"25":[{"address":"","space_units":"м²","space_hidden":false,"space_unclear":false,"region_hidden":true,"costs_comment":"","space_comment":"","address_hidden":false,"space":"51.8","costs_rent_comment":"","costs":"","region":"","costs_rent":""}],"27":[{"costs":"","address":"","space_units":"м²","costs_rent_comment":"","space":"20.8","space_comment":"","region_hidden":true,"costs_comment":"","region":"","address_hidden":false,"costs_rent":""}],"28":[{"address":"","space_units":"м²","space_hidden":true,"space_comment":"","region_hidden":true,"costs_comment":"","address_hidden":false,"space":"","costs_rent_comment":"","costs":"","region":"","costs_rent":"7450"}],"29":[{"costs_property_comment":"","address":"","space_units":"м²","costs_rent_comment":"","space":"64300","region":"","region_hidden":true,"costs_property":"","space_comment":"","address_hidden":false,"costs_rent":""},{"costs_property_comment":"","address":"","space_units":"м²","costs_rent_comment":"","space":"66500","region":"","costs_property":"","space_comment":"","address_hidden":false,"costs_rent":""}]},"vehicle":{"35":[{"sum_comment":"","brand_info_hidden":false,"brand_info":"3500 куб. см., 249 к. с","sum":"","sum_rent_comment":"","brand_hidden":false,"brand":"Nissan Murano","sum_rent":"","brand_info_unclear":false,"year":"2013"},{"sum_comment":"","brand_info":"2998 куб. см., 220 к. с","sum":"","sum_rent_comment":"","year":"2007","brand":"Mitsubishi Outlander","sum_rent":"","brand_hidden":false},{"sum_comment":"","brand_info":"1498 куб. см., 85 к. с","sum":"","brand_unclear":false,"year":"2005","brand":"ЗАЗ Lanos","sum_rent":"","sum_rent_comment":""}],"37":[{"sum_comment":"","brand_unclear":true,"sum_rent":"","sum":"","sum_rent_comment":"","brand_hidden":false,"brand":"Казанка 5М3","brand_info":"5 м3, довжина 4,5 м","year":"1990"}],"40":[{"sum_comment":"","brand_info_hidden":false,"brand_info":"75 к. с","sum":"","sum_rent_comment":"","brand_hidden":false,"brand":"ИЖ 21251","sum_rent":"","brand_info_unclear":false,"year":"1987"}]},"source":"VULYK","income":{"5":{"family_comment":"","family":"85012","comment":"","value_unclear":false,"value":"336815","family_comment_unclear":false},"6":{"family_comment":"","value":"336815","family":"","comment":""},"7":{"family_comment":"","comment":"","family":"","source_name_unclear":false,"value":"","source_name":""},"8":{"family_comment":"","value":"","family":"","comment":""},"9":{"family_comment":"","value":"","family":"12","comment":""},"10":{"family_comment":"","value":"","family":"","comment":""},"11":{"family_comment":"","value":"","family":"","comment":""},"12":{"family_comment":"","value":"","family":"","comment":""},"13":{"family_comment":"","value":"","family":"","comment":""},"14":{"family_comment":"","value":"","family":"","comment":""},"15":{"family_comment":"","value":"","family":"","comment":""},"16":{"family_comment":"","value":"","family":"35000","comment":""},"17":{"family_comment":"","value":"","family":"","comment":""},"18":{"family_comment":"","value":"","family":"","comment":"","value_unclear":false},"19":{"family_comment":"","comment_unclear":false,"value":"","family":"11000","comment":""},"20":{"family_comment":"","value":"","family_unclear":false,"family":"39000","comment":""}},"banks":{"45":[{"sum_units":"UAH","sum_comment":"","sum_foreign_units":"UAH","sum_hidden":false,"sum":"","sum_foreign_comment":"","sum_foreign":"","sum_unclear":false,"sum_comment_hidden":false},{"sum_units":"","sum_comment":"","sum_foreign_units":"","sum_hidden":false,"sum":"","sum_foreign_comment":"","sum_foreign":"","sum_comment_hidden":false}],"46":[{"sum_units":"UAH","sum_comment":"","sum_foreign_units":"UAH","sum_hidden":false,"sum":"","sum_foreign_comment":"","sum_foreign":"","sum_unclear":false},{"sum_units":"","sum_comment":"","sum_foreign_units":"","sum":"","sum_foreign_comment":"","sum_foreign":""},{"sum_units":"","sum_comment":"","sum_foreign_units":"","sum":"","sum_foreign_comment":"","sum_foreign":""},{"sum_units":"","sum_comment":"","sum_foreign_units":"","sum":"","sum_foreign_comment":"","sum_foreign":""}],"47":[{"sum_units":"UAH","sum_comment":"","sum_foreign_units":"UAH","sum":"","sum_foreign_comment":"","sum_foreign":""}],"48":[{"sum_units":"UAH","sum_comment":"","sum_foreign_units":"UAH","sum_hidden":false,"sum":"","sum_foreign_comment":"","sum_foreign":""}],"49":[{"sum_units":"UAH","sum_comment":"","sum_foreign_units":"UAH","sum_hidden":false,"sum":"","sum_foreign_comment":"","sum_foreign":"","sum_comment_hidden":false},{"sum_units":"","sum_comment":"","sum_foreign_units":"","sum":"","sum_foreign_comment":"","sum_foreign":"","sum_comment_hidden":false},{"sum_units":"","sum_comment":"","sum_foreign_units":"","sum":"","sum_foreign_comment":"","sum_foreign":""},{"sum_units":"","sum_comment":"","sum_foreign_units":"","sum":"","sum_foreign_comment":"","sum_foreign":""},{"sum_units":"","sum_comment":"","sum_foreign_units":"","sum":"","sum_foreign_comment":"","sum_foreign":""}],"50":[{"sum_units":"UAH","sum_comment":"","sum_foreign_units":"UAH","sum":"","sum_foreign_comment":"","sum_foreign":""}],"51":[{"sum_comment_unclear":false,"sum_units":"UAH","sum_foreign_units":"UAH","sum_hidden":false,"sum":"330","sum_foreign_comment":"","sum_comment":"","sum_unclear":false,"sum_foreign":"","sum_comment_hidden":false},{"sum_units":"","sum_comment":"","sum_foreign_units":"","sum_hidden":false,"sum":"","sum_foreign_comment":"","sum_foreign":""}],"52":[{"sum_units":"UAH","sum_comment":"","sum_foreign_units":"UAH","sum":"","sum_foreign_comment":"","sum_foreign":""}],"53":[{"sum_units":"UAH","sum_comment":"","sum_foreign_units":"UAH","sum_hidden":false,"sum":"","sum_foreign_comment":"","sum_foreign":"","sum_comment_hidden":false},{"sum_units":"","sum_comment":"","sum_foreign_units":"","sum":"","sum_foreign_comment":"","sum_foreign":""},{"sum_comment_unclear":false,"sum_comment":"","sum_foreign_units":"","sum":"","sum_foreign_comment":"","sum_foreign":"","sum_units":""},{"sum_comment_unclear":false,"sum_comment":"","sum_foreign_units":"","sum":"","sum_foreign_comment":"","sum_foreign":"","sum_units":""},{"sum_units":"","sum_comment":"","sum_foreign_units":"","sum":"","sum_foreign_comment":"","sum_foreign":""},{"sum_units":"","sum_comment":"","sum_foreign_units":"","sum":"","sum_foreign_comment":"","sum_foreign":""},{"sum_units":"","sum_comment":"","sum_foreign_units":"","sum":"","sum_foreign_comment":"","sum_foreign":""}]},"ft_src":"3500 куб. см., 249 к. с\nNissan Murano\n2013\nMitsubishi Outlander\n2007\n2998 куб. см., 220 к. с\n2005\n1498 куб. см., 85 к. с\nЗАЗ Lanos\nКазанка 5М3\n5 м3, довжина 4,5 м\n1990\n75 к. с\nИЖ 21251\n1987\n330\n1\n1. Батьки за станом здоров'я не можуть точно підрахувати розмір отриманих пенсій та розмір орендної плати за землю. 2. Батько дружини - Черевченко М. І. у 2014 році продав належні йому: а) будинко з господарськими будівлями за 34754 грн. б) земельну ділянку площею 0,508 га за 45517 грн. в) земельну ділянку площею 0,13 га за 24483 грн. Вартість земельних ділянок станом на 01. 01. 2015 року покупцем не сплачена. Строк сплати відповідно до угод встановлено 25. 10. 2016 р\n2014\n5 м3, довжина 4,5 м\n1990\nКазанка 5М3\n75 к. с\n1987\nИЖ 21251\n3500 куб. см., 249 к. с\n2013\nNissan Murano\n2998 куб. см., 220 к. с\nMitsubishi Outlander\n2007\n1498 куб. см., 85 к. с\nЗАЗ Lanos\n2005\n1\n1. Батьки за станом здоров'я не можуть точно підрахувати розмір отриманих пенсій та розмір орендної плати за землю. 2. Батько дружини - Черевченко М. І. у 2014 році продав належні йому: а) будинко з господарськими будівлями за 34754 грн. б) земельну ділянку площею 0,508 га за 45517 грн. в) земельну ділянку площею 0,13 га за 24483 грн. Вартість земельних ділянок станом на 01. 01. 2015 року покупцем не сплачена. Строк сплати відповідно до угод встановлено 25. 10. 2016 р\n330\n20.8\n7450\n51.8\n28\n64300\n66500\n49.9\nМакарчук Михайло Андрійович\nМихайло Андрійович Макарчук\nМихайло Макарчук\nМакарчук Михайло Андрійович\nМакарчук Михайло Андрійович\nПодружжя\nМакарчук Н. М\nБатьки\nМакарчук К. В\nІнше\nбатько дружини\nЧеревченко М. І\nЧеревченко М. І\nІнше\nмати дружини\nМихайло\nАндрійович\nВищий спеціалізований суд з розгляду цивільних і кримінальних справ\nЗагальнодержавний регіон\nсуддя вищого спеціалізованого суду україни з розгляду цивільних і кримінальних справ, член вищої кваліфікаційної комісії суддів україни\nМакарчук\n205000\n336815\n39000\n336815\n85012\n35000\n12\n11000\n2014\n205000\n20.8\n64300\n66500\n49.9\n7450\n28\n51.8\nМакарчук Н. М\nПодружжя\nМакарчук К. В\nБатьки\nбатько дружини\nЧеревченко М. І\nІнше\nІнше\nмати дружини\nЧеревченко М. І\nМихайло\nАндрійович\nМакарчук\nМакарчук Михайло Андрійович\nМихайло Андрійович Макарчук\nМихайло Макарчук\nМакарчук Михайло Андрійович\nЗагальнодержавний регіон\nВищий спеціалізований суд з розгляду цивільних і кримінальних справ\nсуддя вищого спеціалізованого суду україни з розгляду цивільних і кримінальних справ, член вищої кваліфікаційної комісії суддів україни\nМакарчук Михайло Андрійович\n336815\n85012\n336815\n35000\n11000\n12\n39000","general":{"family_raw":"","name":"Михайло","full_name_suggest":{"input":["Макарчук Михайло Андрійович","Михайло Андрійович Макарчук","Михайло Макарчук"],"output":"Макарчук Михайло Андрійович"},"patronymic":"Андрійович","inn_hidden":true,"inn":"","addresses":[{"place_city_type_hidden":false,"place_city_type":"","place_city_hidden":false,"place_hidden":true,"place_district":"","place_district_hidden":false,"place":"","place_address":"","place_address_hidden":false,"place_city":""}],"last_name":"Макарчук","full_name":"Макарчук Михайло Андрійович","family":[{"inn":"","inn_unclear":false,"family_name":"Макарчук Н. М","relations_hidden":false,"name_unclear":false,"inn_hidden":true,"name_hidden":true,"relations":"Подружжя"},{"inn":"","inn_unclear":false,"family_name":"Макарчук К. В","name_unclear":false,"inn_hidden":false,"name_hidden":false,"relations":"Батьки"},{"inn":"","family_name":"Черевченко М. І","relations_other":"батько дружини","name_unclear":true,"inn_hidden":false,"name_hidden":false,"relations":"Інше"},{"inn":"","family_name":"Черевченко М. І","inn_hidden":false,"relations_other":"мати дружини","relations":"Інше"}],"post":{"office":"Вищий спеціалізований суд з розгляду цивільних і кримінальних справ","post_unclear":false,"post":"суддя вищого спеціалізованого суду україни з розгляду цивільних і кримінальних справ, член вищої кваліфікаційної комісії суддів україни","candidate":"","region_unclear":false,"region":"Загальнодержавний регіон","region_hidden":false,"office_hidden":false,"office_unclear":false},"last_name_unclear":false},"liabilities":{"54":{"sum_comment_unclear":false,"sum_comment":"","sum":"","sum_foreign_comment":"","sum_foreign":"","sum_comment_hidden":false},"55":{"sum_comment":"","sum_foreign_comment":"","sum_foreign":"","sum":""},"56":{"sum_comment":"","sum_foreign_comment":"","sum_foreign":"","sum":""},"57":{"sum_comment":"","sum_foreign_comment":"","sum_foreign":"","sum":"205000","sum_comment_hidden":false},"58":{"sum_comment":"","sum_foreign_comment":"","sum_foreign":"","sum":"","sum_comment_hidden":false},"59":{"sum_comment":"","sum_foreign_comment":"","sum_foreign":"","sum":""},"60":{"sum_comment":"","sum_hidden":false,"sum":"","sum_foreign_comment":"","sum_foreign":"","sum_comment_hidden":false},"61":{"sum_comment":"","sum_foreign_comment":"","sum_foreign":"","sum":""},"62":{"sum_comment":"","sum_foreign_comment":"","sum_foreign":"","sum":""},"63":{"sum_comment":"","sum_hidden":false,"sum":"","sum_foreign_comment":"","sum_foreign":"","sum_comment_hidden":false},"64":{"sum_comment":"","sum_hidden":false,"sum":"","sum_foreign_comment":"","sum_foreign":"","sum_comment_hidden":false}},"intro":{"isnotdeclaration":"","declaration_year":"2014"}},{"id":"7382","ft_src":"3500 куб см, 249 к. с\n2013\n445730\nNissan Murano\n2007\nMitsubishi Outlander\n2998 куб см, 220 к. с\n1498 куб см, 85 к. с\n2005\nDaewoo Lanos\nКазанка 5М3\nдовжина 4.5 м\n1990\nМосквич ІЖ 21251\n75 к.с.\n1987\n24\n64300\n66500\n49.9\n24\n56\n51.8\n1\nБатьки за станом здоров'я не можуть підрахувати розмір одержаних пенсій та розмір орендної плати\n2013\n385243\n586173\n200930\nдовжина 4.5 м\n1990\nКазанка 5М3\n3500 куб см, 249 к. с\nNissan Murano\n2013\n445730\n2998 куб см, 220 к. с\nMitsubishi Outlander\n2007\n1498 куб см, 85 к. с\nDaewoo Lanos\n2005\n75 к.с.\nМосквич ІЖ 21251\n1987\nБатьки за станом здоров'я не можуть підрахувати розмір одержаних пенсій та розмір орендної плати\n1\n24\n56\n51.8\n24\n64300\n66500\n49.9\nПодружжя\nМакарчук Н. М\nБатьки\nМакарчук К. В\nІнше\nБатько дружини\nЧеревченко М. І\nЧеревченко М. Г\nІнше\nМати дружини\nМакарчук Михайло Андрійович\nМихайло Андрійович Макарчук\nМихайло Макарчук\nМакарчук Михайло Андрійович\nМакарчук Михайло Андрійович\nМихайло\nАндрійович\nВищий спецiалiзований суд України з розгляду цивiльних i кримiнальних справ\nсуддя вищого спецiалiзованого суду україни з розгляду цивільних та кримінальних справ\nЗагальнодержавний регіон\nМакарчук\n26156\n385243\n200930\n586173\n2013\n26156\nМакарчук Н. М\nПодружжя\nБатьки\nМакарчук К. В\nБатько дружини\nЧеревченко М. І\nІнше\nІнше\nМати дружини\nЧеревченко М. Г\nАндрійович\nМакарчук\nМихайло\nМакарчук Михайло Андрійович\nМихайло Андрійович Макарчук\nМихайло Макарчук\nМакарчук Михайло Андрійович\nЗагальнодержавний регіон\nсуддя вищого спецiалiзованого суду україни з розгляду цивільних та кримінальних справ\nВищий спецiалiзований суд України з розгляду цивiльних i кримiнальних справ\nМакарчук Михайло Андрійович","estate":{"23":[{"costs_unclear":false,"address":"","space_units":"м²","space_hidden":false,"space_unclear":false,"region_hidden":true,"costs_rent_comment":"","space_comment":"","space_comment_unclear":false,"space_comment_hidden":false,"space":"24","address_hidden":true,"costs_comment":"","costs":"","region":"","costs_rent":""}],"24":[{"address":"","space_units":"м²","costs_comment":"","space_comment":"","region_hidden":true,"region":"","address_hidden":true,"costs":"","address_unclear":false,"space_comment_unclear":false,"costs_rent_comment":"","space":"49.9","costs_rent":""}],"25":[{"address":"","space_units":"м²","space_hidden":false,"space_unclear":false,"region_hidden":true,"costs_rent_comment":"","space_comment":"","address_hidden":true,"space_comment_hidden":false,"costs":"","space_comment_unclear":false,"costs_comment":"","space":"51.8","region":"","costs_rent":""}],"27":[{"address":"","space_units":"м²","costs_hidden":false,"space_hidden":false,"space_comment":"","region_hidden":true,"costs_comment":"","address_hidden":true,"space":"24","address_unclear":false,"costs_rent_comment":"","costs":"","region":"","costs_rent":""}],"29":[{"costs_property_comment":"","address":"","space_units":"м²","space_hidden":false,"space_unclear":false,"region_hidden":true,"costs_property":"","space_comment":"","address_hidden":true,"costs_rent_comment":"","space":"64300","region":"","costs_rent":""},{"costs_property_comment":"","address":"","space_units":"м²","costs_rent_comment":"","space":"66500","region":"","region_hidden":false,"costs_property":"","space_comment":"","costs_rent":""}],"30":[{"costs_property_comment":"","address":"","space_units":"м²","space_hidden":false,"space_comment":"","region_hidden":true,"costs_property":"","region":"","address_hidden":true,"costs_rent_comment":"","space":"56","costs_rent":""}]},"vehicle":{"35":[{"sum_rent_comment_hidden":false,"brand_info":"3500 куб см, 249 к. с","brand_unclear":false,"sum_rent_comment":"","year":"2013","sum_hidden":false,"sum_comment":"","sum_rent_hidden":false,"brand_info_hidden":false,"sum_rent":"","sum_rent_unclear":false,"brand":"Nissan Murano","year_unclear":false,"brand_info_unclear":false,"sum_unclear":false,"sum_comment_hidden":false,"sum":"445730"},{"sum_comment":"","brand_info":"2998 куб см, 220 к. с","brand_unclear":false,"sum_rent_comment":"","year":"2007","brand":"Mitsubishi Outlander","sum_rent":"","brand_info_unclear":false,"sum":""},{"sum_comment":"","brand_info":"1498 куб см, 85 к. с","sum":"","sum_rent_comment":"","year":"2005","brand":"Daewoo Lanos","sum_rent":""}],"37":[{"sum_comment":"","brand_info":"довжина 4.5 м","sum":"","brand_unclear":false,"year":"1990","brand":"Казанка 5М3","sum_rent":"","sum_rent_comment":"","brand_hidden":false,"brand_info_unclear":false,"year_unclear":false}],"40":[{"year_hidden":false,"sum_rent":"","sum":"","brand_unclear":false,"brand_hidden":false,"sum_comment":"","brand_info":"75 к.с.","brand":"Москвич ІЖ 21251","sum_rent_comment":"","brand_info_unclear":false,"year":"1987"}]},"source":"VULYK","income":{"5":{"family":"","family_comment":"","comment":"","value_hidden":false,"value_unclear":false,"family_unclear":false,"value":"586173"},"6":{"family":"","family_comment":"","comment":"","value_hidden":false,"family_hidden":false,"value":"385243","family_comment_hidden":false},"7":{"source_name_hidden":false,"family_comment":"","comment":"","family":"","value_unclear":false,"value":"","family_hidden":false,"value_hidden":false,"source_name":""},"8":{"family":"","family_comment":"","comment":"","value_hidden":false,"comment_hidden":false,"family_hidden":false,"value":""},"9":{"family":"","family_comment":"","comment":"","value_hidden":false,"comment_hidden":false,"family_hidden":false,"family_unclear":false,"value":""},"10":{"family":"","family_comment":"","comment":"","value_hidden":false,"comment_hidden":false,"family_hidden":false,"value":""},"11":{"family":"","family_comment":"","comment":"","value_hidden":false,"value_unclear":false,"comment_hidden":false,"family_hidden":false,"value":""},"12":{"family":"","family_comment":"","comment":"","value_hidden":false,"comment_hidden":false,"family_hidden":false,"value":""},"13":{"family":"","family_comment":"","comment":"","value_hidden":false,"comment_hidden":false,"family_hidden":false,"value":""},"14":{"family":"","family_comment":"","comment":"","value_hidden":false,"comment_hidden":false,"family_hidden":false,"value":""},"15":{"family":"","family_comment":"","comment":"","value_hidden":false,"comment_hidden":false,"family_hidden":false,"value":""},"16":{"family":"","family_comment":"","comment":"","value_hidden":false,"comment_hidden":false,"family_hidden":false,"value":""},"17":{"family":"","family_comment":"","comment":"","value_hidden":false,"comment_hidden":false,"family_hidden":false,"value":""},"18":{"family":"","family_comment":"","comment":"","value_hidden":false,"value_unclear":false,"comment_hidden":false,"family_hidden":false,"value":""},"19":{"family":"","family_comment":"","comment":"","value_hidden":false,"comment_hidden":false,"family_hidden":false,"value":""},"20":{"family_comment":"","comment":"","family":"","value_unclear":false,"comment_unclear":false,"value":"200930"}},"general":{"family_raw":"","name":"Михайло","full_name_suggest":{"input":["Макарчук Михайло Андрійович","Михайло Андрійович Макарчук","Михайло Макарчук"],"output":"Макарчук Михайло Андрійович"},"name_unclear":false,"patronymic":"Андрійович","inn_hidden":false,"inn":"","inn_unclear":false,"last_name":"Макарчук","full_name":"Макарчук Михайло Андрійович","family":[{"inn":"","family_name":"Макарчук Н. М","relations_other":"","relations_hidden":false,"relations_unclear":false,"name_unclear":false,"inn_hidden":false,"name_hidden":false,"relations":"Подружжя"},{"inn":"","family_name":"Макарчук К. В","relations_hidden":false,"relations_unclear":false,"name_unclear":false,"relations":"Батьки","inn_hidden":false,"name_hidden":false,"relations_other":""},{"inn":"","family_name":"Черевченко М. І","relations_other":"Батько дружини","name_unclear":false,"inn_hidden":false,"name_hidden":false,"relations":"Інше"},{"inn":"","family_name":"Черевченко М. Г","inn_hidden":false,"relations_other":"Мати дружини","relations":"Інше"}],"post":{"office":"Вищий спецiалiзований суд України з розгляду цивiльних i кримiнальних справ","post":"суддя вищого спецiалiзованого суду україни з розгляду цивільних та кримінальних справ","candidate":"","office_hidden":false,"region":"Загальнодержавний регіон","region_hidden":false,"post_unclear":false,"office_unclear":false},"last_name_unclear":false},"liabilities":{"54":{"sum_comment":"","sum_hidden":false,"sum":"26156","sum_foreign_comment":"","sum_foreign":"","sum_foreign_hidden":false,"sum_comment_hidden":false},"55":{"sum_comment":"","sum_foreign_comment":"","sum_foreign":"","sum_hidden":false,"sum":""},"56":{"sum_comment":"","sum_foreign_comment":"","sum_foreign":"","sum":""},"57":{"sum_comment":"","sum_hidden":false,"sum":"","sum_foreign_comment":"","sum_foreign":"","sum_unclear":false,"sum_foreign_hidden":false,"sum_comment_hidden":false},"58":{"sum_comment":"","sum_hidden":false,"sum":"","sum_foreign_comment":"","sum_foreign":"","sum_unclear":false,"sum_foreign_hidden":false,"sum_comment_hidden":false},"59":{"sum_comment":"","sum_foreign_comment":"","sum_foreign":"","sum_hidden":false,"sum":""},"60":{"sum_comment":"","sum_hidden":false,"sum":"","sum_foreign_comment":"","sum_foreign":"","sum_unclear":false,"sum_foreign_hidden":false,"sum_comment_hidden":false},"61":{"sum_comment":"","sum_foreign_comment":"","sum_foreign":"","sum_hidden":false,"sum":""},"62":{"sum_comment":"","sum_hidden":false,"sum":"","sum_foreign_comment":"","sum_foreign":"","sum_comment_hidden":false},"63":{"sum_comment":"","sum_foreign_comment":"","sum_foreign":"","sum_hidden":false,"sum":""},"64":{"sum_comment":"","sum_foreign_comment":"","sum_foreign":"","sum_hidden":false,"sum":""}},"declaration":{"notfull_lostpages":"","additional_info_text":"Батьки за станом здоров'я не можуть підрахувати розмір одержаних пенсій та розмір орендної плати","additional_info":"1","date":"2014-03-31T00:00:00","notfull":"","url":"http://static.declarations.com.ua/declarations/chosen_ones/judges_batch/260_makarchuk_mykhailo_andriiovych.pdf"},"intro":{"declaration_year_hidden":false,"isnotdeclaration":"","declaration_year_unclear":false,"declaration_year":"2013"}}]