[{"id":"vulyk_65_128","ft_src":"право оренди\nсмт. Доманівка, вул. Кірова\n.0053\nМиколаївська область\nмаринівська с/рада Доманівського р-ну\n2\nМиколаївська область\nМиколаївська область\nм. Первомайськ, вул. Толстого\n52\n2014\n188672\n12180\n213002\n12150\n.0053\nправо оренди\nМиколаївська область\nсмт. Доманівка, вул. Кірова\n2\nМиколаївська область\nмаринівська с/рада Доманівського р-ну\n52\nМиколаївська область\nм. Первомайськ, вул. Толстого\nЗагальний місцевий суд\nМиколаївська область\nсуддя первомайського міськрайонного суду миколаївської області\nМаксютенко Оксана Анатоліївна\nОксана Анатоліївна Максютенко\nОксана Максютенко\nМаксютенко Оксана Анатоліївна\nОксана\nДитина\n17. 12. 2010\nДитина\n22. 03. 2013\nМаксютенко Оксана Анатоліївна\nМаксютенко\nАнатоліївна\n55200 вул. Толстого\nМиколаївська область\nПервомайськ\n188672\n12150\n213002\n12180\n2014\n17. 12. 2010\nДитина\nДитина\n22. 03. 2013\nАнатоліївна\nМаксютенко\nОксана\nМаксютенко Оксана Анатоліївна\nОксана Анатоліївна Максютенко\nОксана Максютенко\nМаксютенко Оксана Анатоліївна\n55200 вул. Толстого\nПервомайськ\nМиколаївська область\nМиколаївська область\nЗагальний місцевий суд\nсуддя первомайського міськрайонного суду миколаївської області\nМаксютенко Оксана Анатоліївна","estate":{"23":[{"address":"смт. Доманівка, вул. Кірова","space_units":"га","space_hidden":false,"space_unclear":false,"region_hidden":false,"costs_comment":"","space_comment":"право оренди","address_hidden":false,"costs":"","address_unclear":false,"costs_rent_comment":"","space":".0053","region":"Миколаївська область","costs_rent":""},{"address":"маринівська с/рада Доманівського р-ну","space_units":"га","costs_comment":"","space_unclear":false,"region_hidden":false,"space_comment":"","address_hidden":false,"costs":"","address_unclear":true,"costs_rent_comment":"","space":"2","region":"Миколаївська область","costs_rent":""}],"25":[{"costs_rent_comment_unclear":false,"address":"м. Первомайськ, вул. Толстого","space_units":"м²","space_hidden":false,"space_unclear":false,"region_hidden":false,"costs_comment":"","space_comment":"","space_comment_unclear":false,"costs":"","address_unclear":false,"address_hidden":false,"costs_rent_comment":"","space":"52","region":"Миколаївська область","space_units_hidden":false,"costs_rent":""}]},"source":"VULYK","income":{"5":{"family":"","family_comment":"","comment":"","value_hidden":false,"value_unclear":false,"value":"213002","family_hidden":false,"family_unclear":false},"6":{"family_comment":"","family":"","value_hidden":false,"comment":"","comment_unclear":false,"value_unclear":false,"value":"188672","family_hidden":false},"7":{"source_name_hidden":false,"family_comment":"","family":"","value_hidden":false,"comment":"","value":"","source_name":""},"8":{"family_comment":"","value":"","family":"","comment":""},"9":{"family_comment":"","comment_unclear":false,"value":"","family":"","comment":""},"10":{"family_comment":"","value":"12180","family":"","comment":"","value_unclear":false},"11":{"family_comment":"","value":"","family":"","comment":""},"12":{"family_comment":"","value":"","family":"","comment":""},"13":{"family_comment":"","value":"","family":"","comment":""},"14":{"family_comment":"","value":"","family":"","comment":""},"15":{"family_comment":"","value":"","family":"","comment":""},"16":{"family_comment":"","value":"","family":"","comment":""},"17":{"family_comment":"","value":"","family":"","comment":""},"18":{"family_comment":"","value":"","family":"","comment":""},"19":{"family":"","family_comment":"","comment":"","value_hidden":false,"value_unclear":false,"comment_hidden":false,"family_hidden":false,"value":"","family_comment_hidden":false},"20":{"family_comment":"","family":"","value_hidden":false,"comment":"","value":"12150","comment_unclear":false,"value_unclear":false,"family_unclear":false,"family_hidden":false}},"general":{"family":[{"inn":"","inn_unclear":false,"family_name":"17. 12. 2010","relations_other":"","relations_hidden":false,"name_unclear":false,"inn_hidden":false,"name_hidden":false,"relations":"Дитина"},{"inn":"","inn_unclear":false,"family_name":"22. 03. 2013","relations_hidden":false,"relations_unclear":false,"name_unclear":false,"relations":"Дитина","inn_hidden":false,"name_hidden":false,"relations_other":""}],"family_raw":"","name":"Оксана","full_name_suggest":{"input":["Максютенко Оксана Анатоліївна","Оксана Анатоліївна Максютенко","Оксана Максютенко"],"output":"Максютенко Оксана Анатоліївна"},"name_unclear":false,"patronymic":"Анатоліївна","inn_hidden":true,"addresses":[{"place_city_type":"Місто","place_address_unclear":false,"place_city_type_hidden":false,"place_hidden":false,"place_city_hidden":false,"place_district":"","place_district_hidden":false,"place":"Миколаївська область","place_city":"Первомайськ","place_address_hidden":false,"place_address":"55200 вул. Толстого"}],"last_name_hidden":false,"patronymic_hidden":false,"inn":"","inn_unclear":false,"last_name":"Максютенко","full_name":"Максютенко Оксана Анатоліївна","post":{"post_hidden":false,"office":"Загальний місцевий суд","post":"суддя первомайського міськрайонного суду миколаївської області","region":"Миколаївська область","region_hidden":false,"office_unclear":false,"office_hidden":false,"post_unclear":false,"region_unclear":false},"name_hidden":false,"last_name_unclear":false},"liabilities":{"54":{"sum_comment_unclear":false,"sum_comment":"","sum_hidden":false,"sum":"","sum_foreign_comment":"","sum_foreign":"","sum_comment_hidden":false},"55":{"sum_comment":"","sum_foreign_comment":"","sum_foreign":"","sum":""},"56":{"sum_comment":"","sum_foreign_comment":"","sum_foreign":"","sum_unclear":false,"sum":""},"57":{"sum_comment_unclear":false,"sum_comment":"","sum":"","sum_foreign_comment":"","sum_foreign":"","sum_unclear":false},"58":{"sum_comment_unclear":false,"sum_comment":"","sum":"","sum_foreign_comment":"","sum_foreign":"","sum_unclear":false},"59":{"sum_comment":"","sum_foreign_comment":"","sum_foreign":"","sum":""},"60":{"sum_comment":"","sum_comment_unclear":false,"sum_foreign_comment":"","sum":"","sum_foreign":""},"61":{"sum_comment":"","sum_foreign_comment":"","sum_foreign":"","sum":""},"62":{"sum_comment":"","sum_foreign_comment":"","sum_foreign":"","sum":""},"63":{"sum_comment":"","sum_foreign_comment":"","sum_foreign":"","sum":""},"64":{"sum_comment":"","sum_foreign_comment":"","sum_foreign":"","sum_unclear":false,"sum":""}},"declaration":{"notfull_lostpages":"","additional_info_text":"","additional_info":"","date":"2015-03-27T00:00:00","notfull":"","url":"http://static.declarations.com.ua/declarations/chosen_ones/mega_batch/maksiutenko_(yantsova)_oksana_anatoliivna.pdf"},"intro":{"declaration_year_hidden":false,"isnotdeclaration":"","declaration_year":"2014"}}]