[{"id":"vulyk_75_110","ft_src":"Chevrolet Cruze\n1991 куб. см., 140 к. с\n2010\nЄланецькій р-н, с. Нововасилівка\n7.36\nМиколаївська область\n.093\n2014\n200105.26\n204605.26\n4500\n1991 куб. см., 140 к. с\n2010\nChevrolet Cruze\n2014\nМатяш\nЛеонідівна\nПодружжя\nВелич Михайло Іванович\nДитина\nВелич Катерина Михайлівна\nМатяш Таїсія Леонідівна\nТаїсія Леонідівна Матяш\nТаїсія Матяш\nМатяш Таїсія Леонідівна\nТаїсія\n2921908684\nМатяш Таїсія Леонідівна\nЗагальний місцевий суд\nсуддя білгород-дністровського міськрайонного суду одеської області\nОдеська область\n9538\n20642\n3239.3\n1326.7\n200105.26\n204605.26\n4500\n7.36\nМиколаївська область\nЄланецькій р-н, с. Нововасилівка\n.093\n9538\n20642\n3239.3\n1326.7\nВелич Михайло Іванович\nПодружжя\nВелич Катерина Михайлівна\nДитина\nМатяш\nЛеонідівна\n2921908684\nсуддя білгород-дністровського міськрайонного суду одеської області\nОдеська область\nЗагальний місцевий суд\nМатяш Таїсія Леонідівна\nМатяш Таїсія Леонідівна\nТаїсія Леонідівна Матяш\nТаїсія Матяш\nМатяш Таїсія Леонідівна\nТаїсія","estate":{"23":[{"address":"Єланецькій р-н, с. Нововасилівка","space_units":"га","costs_comment":"","region_hidden":false,"space_comment":"","address_hidden":false,"costs":"","costs_rent_comment":"","space":"7.36","region":"Миколаївська область","space_units_hidden":false,"costs_rent":""}],"29":[{"costs_property_comment":"","costs_property":"","address":"","space_units":"га","space_comment":"","region_hidden":true,"space_units_unclear":false,"region":"","address_hidden":false,"costs_rent_comment":"","space":".093","costs_rent":""}]},"vehicle":{"35":[{"sum_comment":"","brand_unclear":false,"sum_rent":"","sum":"","sum_rent_comment":"","brand_hidden":false,"brand":"Chevrolet Cruze","brand_info":"1991 куб. см., 140 к. с","brand_info_unclear":false,"year":"2010","sum_unclear":false}]},"source":"VULYK","income":{"5":{"family_comment":"","value":"204605.26","family":"","comment":""},"6":{"family_comment":"","family_hidden":false,"value":"200105.26","family":"","comment":""},"7":{"family":"","family_comment":"","value":"","comment":"","source_name":""},"8":{"family_comment":"","value":"","family":"","comment":""},"9":{"family_comment":"","family":"","comment":"","value_unclear":false,"family_hidden":false,"value":""},"10":{"family":"","family_comment":"","comment":"","value_hidden":false,"value":"","family_hidden":false,"family_unclear":false},"11":{"family_comment":"","value":"","family":"","comment":""},"12":{"family_comment":"","value":"","family":"","comment":""},"13":{"family_comment":"","value":"","family":"","comment":""},"14":{"family_comment":"","value":"","family":"","comment":""},"15":{"family_comment":"","value":"","family":"","comment":""},"16":{"family_comment":"","value":"","family":"","comment":""},"17":{"family_comment":"","value":"","family":"","comment":""},"18":{"family_comment":"","value":"","family":"","comment":""},"19":{"family_comment":"","value":"4500","family":"","comment":""},"20":{"family_comment":"","comment":"","family":"","comment_unclear":false,"value":"","family_comment_unclear":false}},"general":{"inn":"2921908684","addresses":[{"place_city_type_hidden":false,"place_city_type":"","place_city_hidden":true,"place_hidden":true,"place_district":"","place_district_hidden":false,"place":"","place_city":"","place_address_hidden":true,"place_address":""}],"last_name":"Матяш","full_name":"Матяш Таїсія Леонідівна","family":[{"inn":"","family_name":"Велич Михайло Іванович","relations_other":"","relations_hidden":false,"name_unclear":false,"inn_hidden":false,"name_hidden":false,"relations":"Подружжя"},{"inn":"","family_name":"Велич Катерина Михайлівна","relations_other":"","name_unclear":false,"inn_hidden":false,"name_hidden":false,"relations":"Дитина"}],"patronymic":"Леонідівна","inn_hidden":true,"name":"Таїсія","post":{"office":"Загальний місцевий суд","region":"Одеська область","post":"суддя білгород-дністровського міськрайонного суду одеської області"},"family_raw":"","full_name_suggest":{"input":["Матяш Таїсія Леонідівна","Таїсія Леонідівна Матяш","Таїсія Матяш"],"output":"Матяш Таїсія Леонідівна"}},"liabilities":{"54":{"sum_comment":"","sum_foreign_comment":"","sum_foreign":"","sum":""},"55":{"sum_comment":"","sum_foreign_comment":"","sum_foreign":"","sum":""},"56":{"sum_comment":"","sum_foreign_comment":"","sum_foreign":"","sum":""},"57":{"sum_comment":"","sum_foreign_comment":"","sum_foreign":"","sum":"20642"},"58":{"sum_comment":"","sum_foreign_comment":"","sum_foreign":"","sum":"9538"},"59":{"sum_comment_unclear":false,"sum_comment":"","sum":"","sum_foreign_comment":"","sum_foreign":"","sum_unclear":false},"60":{"sum_comment":"","sum_foreign_comment":"","sum_foreign":"","sum":""},"61":{"sum_comment":"","sum_foreign_comment":"","sum_foreign":"","sum":""},"62":{"sum_comment":"","sum_foreign_comment":"","sum_foreign":"","sum_unclear":false,"sum":""},"63":{"sum_comment":"","sum_foreign_comment":"","sum_foreign":"","sum":"3239.3"},"64":{"sum_comment":"","sum_foreign_comment":"","sum_foreign":"","sum":"1326.7"}},"declaration":{"notfull_lostpages":"","additional_info_text":"","additional_info":"","date":"2015-03-23T00:00:00","notfull":"","url":"http://static.declarations.com.ua/declarations/chosen_ones/judges_batch/1825_matiash_taisiia_leonidivna.pdf"},"intro":{"isnotdeclaration":"","declaration_year":"2014"}}]