[{"id":"vulyk_85_73","ft_src":"1799 куб. см.\nHonda Civic\n2006\nMazda CX-7\n2260 куб. см.\n2007\nм. Артемівськ\nДонецька область\n.1077\nДонецька область\nм. Артемівськ\n.0054\nДонецька область\nм. Артемівськ\n44.6\n1/3 вiд 86,05\n28.68\nм. Артемівськ\nДонецька область\n235.1\nДонецька область\nм. Артемівськ\n44.56\nДонецька область\nм. Артемівськ\n41.28\n47.2\n1/3 вiд 86,05\n28.68\n2014\n256031.95\n32400\n19567.56\n128400\n310326.51\n96000\n34727\n1799 куб. см.\nHonda Civic\n2006\n2260 куб. см.\n2007\nMazda CX-7\n235.1\nДонецька область\nм. Артемівськ\n44.56\nм. Артемівськ\nДонецька область\n47.2\n28.68\n1/3 вiд 86,05\n.1077\nДонецька область\nм. Артемівськ\n.0054\nм. Артемівськ\nДонецька область\n44.6\nм. Артемівськ\nДонецька область\n28.68\n1/3 вiд 86,05\n41.28\nм. Артемівськ\nДонецька область\nМедінцева Ніна Михайлівна\nНіна Михайлівна Медінцева\nНіна Медінцева\nМедінцева Ніна Михайлівна\nНіна\nПодружжя\nТопузян Р. Х\nМедінцева Ніна Михайлівна\nМедінцева\nЗагальний місцевий суд\nзаступник голови артемівського міськрайонного суду донецької області\nДонецька область\nМихайлівна\nДонецька область\n32214.9\n256031.95\n96000\n34727\n19567.56\n32400\n310326.51\n128400\n2014\n32214.9\nТопузян Р. Х\nПодружжя\nМихайлівна\nМедінцева\nНіна\nМедінцева Ніна Михайлівна\nНіна Михайлівна Медінцева\nНіна Медінцева\nМедінцева Ніна Михайлівна\nДонецька область\nзаступник голови артемівського міськрайонного суду донецької області\nДонецька область\nЗагальний місцевий суд\nМедінцева Ніна Михайлівна","estate":{"25":[{"address":"","space_units":"м²","space_hidden":false,"space_unclear":false,"region_hidden":true,"costs_rent_comment":"","space_comment":"","address_hidden":false,"space":"47.2","space_comment_unclear":false,"costs_comment_unclear":false,"costs_comment":"","costs":"","region":"","costs_rent":""},{"address":"","space_units":"м²","space_hidden":false,"space_comment":"1/3 вiд 86,05","region_hidden":false,"costs_comment":"","address_hidden":false,"space":"28.68","costs_rent_comment":"","costs":"","region":"","costs_rent":""}],"29":[{"costs_property_comment":"","address":"м. Артемівськ","space_units":"га","space_unclear":false,"region_hidden":true,"costs_property":"","space_comment":"","address_hidden":true,"costs_rent_comment":"","space":".1077","region":"Донецька область","costs_rent":""},{"costs_property_comment":"","address":"м. Артемівськ","space_units":"га","costs_rent_comment":"","space":".0054","region":"Донецька область","region_hidden":true,"costs_property":"","space_comment":"","address_hidden":true,"costs_rent":""}],"30":[{"costs_property_comment":"","address":"м. Артемівськ","space_units":"м²","space_unclear":false,"region_hidden":true,"costs_property":"","space_comment":"","address_hidden":true,"costs_rent_comment":"","space":"235.1","region":"Донецька область","costs_rent":""},{"costs_property_comment":"","address":"м. Артемівськ","space_units":"м²","costs_rent_comment":"","space":"44.56","region":"Донецька область","costs_property":"","space_comment":"","costs_rent":""}],"31":[{"costs_property_comment":"","address":"","space_units":"м²","space_unclear":false,"region_hidden":true,"costs_property":"","space_comment":"1/3 вiд 86,05","address_hidden":true,"costs_rent_comment":"","space":"28.68","region":"","costs_rent":""}],"33":[{"costs_property_comment":"","address":"м. Артемівськ","space_units":"м²","costs_rent_comment":"","space":"44.6","region":"Донецька область","region_hidden":false,"costs_property":"","space_comment":"","address_hidden":true,"costs_rent":""}],"34":[{"costs_property_comment":"","address":"м. Артемівськ","space_units":"м²","costs_rent_comment":"","space":"41.28","region":"Донецька область","region_hidden":false,"costs_property":"","space_comment":"","address_hidden":true,"costs_rent":""}]},"vehicle":{"35":[{"sum_comment_unclear":false,"year_hidden":false,"brand_info":"1799 куб. см.","brand_unclear":false,"sum_rent_comment":"","brand_hidden":false,"year":"2006","sum_comment":"","sum_rent":"","brand":"Honda Civic","brand_info_unclear":false,"sum":""}],"40":[{"sum_comment":"","brand_info_hidden":false,"sum_rent":"","sum":"","brand_unclear":false,"year":"2007","brand":"Mazda CX-7","brand_info":"2260 куб. см.","sum_rent_comment":"","brand_info_unclear":true,"year_unclear":false}]},"source":"VULYK","income":{"5":{"family_comment":"","family":"128400","comment":"","value_unclear":false,"family_unclear":false,"value":"310326.51"},"6":{"family_comment":"","family":"","comment":"","value_unclear":false,"family_unclear":false,"value":"256031.95"},"7":{"family":"","family_comment":"","value":"","comment":"","source_name":""},"8":{"family_comment":"","value":"","family":"","comment":""},"9":{"family_comment":"","value":"","family":"","comment":"","value_unclear":false},"10":{"family_comment":"","value":"","family":"","comment":"","value_unclear":false},"11":{"family_comment":"","value":"","family":"","comment":""},"12":{"family_comment":"","value":"","family":"","comment":""},"13":{"family_comment":"","value":"","family":"","comment":"","value_unclear":false},"14":{"family_comment":"","value":"","family":"","comment":""},"15":{"family_comment":"","value":"19567.56","family":"32400","comment":""},"16":{"family_comment":"","value":"","family":"","comment":""},"17":{"family_comment":"","value":"","family":"96000","comment":""},"18":{"family_comment":"","value":"","family":"","comment":""},"19":{"family_comment":"","value":"","family":"","comment":""},"20":{"family_comment":"","value":"34727","family_unclear":false,"family":"","comment":""}},"general":{"family_raw":"","name":"Ніна","full_name_suggest":{"input":["Медінцева Ніна Михайлівна","Ніна Михайлівна Медінцева","Ніна Медінцева"],"output":"Медінцева Ніна Михайлівна"},"patronymic":"Михайлівна","inn_hidden":true,"last_name_hidden":false,"inn":"","addresses":[{"place_city_type_hidden":false,"place_city_type":"","place_city_hidden":true,"place_hidden":false,"place_district":"","place_district_hidden":false,"place":"Донецька область","place_city":"","place_address_hidden":true,"place_address":""}],"last_name":"Медінцева","full_name":"Медінцева Ніна Михайлівна","family":[{"inn":"","family_name":"Топузян Р. Х","relations_other":"","relations_hidden":false,"relations_unclear":false,"name_unclear":false,"inn_hidden":true,"name_hidden":true,"relations":"Подружжя"}],"post":{"post_hidden":false,"office":"Загальний місцевий суд","region":"Донецька область","post_unclear":false,"post":"заступник голови артемівського міськрайонного суду донецької області"},"last_name_unclear":false},"liabilities":{"54":{"sum_comment":"","sum_comment_unclear":false,"sum_foreign_comment":"","sum":"","sum_foreign":""},"55":{"sum_comment":"","sum_foreign_comment":"","sum_foreign":"","sum":""},"56":{"sum_comment":"","sum_foreign_comment":"","sum_foreign":"","sum_unclear":false,"sum":""},"57":{"sum_comment":"","sum_foreign_comment":"","sum_foreign":"","sum":""},"58":{"sum_comment":"","sum_foreign_comment":"","sum_foreign":"","sum":"","sum_comment_hidden":false},"59":{"sum_comment":"","sum_foreign_comment":"","sum_foreign":"","sum":""},"60":{"sum_comment":"","sum_foreign_comment":"","sum_foreign":"","sum":""},"61":{"sum_comment":"","sum_foreign_comment":"","sum_foreign":"","sum":""},"62":{"sum_comment":"","sum_foreign_comment":"","sum_foreign":"","sum_unclear":false,"sum":""},"63":{"sum_comment":"","sum_foreign_comment":"","sum_foreign":"","sum_unclear":false,"sum":"32214.9"},"64":{"sum_comment":"","sum_foreign_comment":"","sum_foreign":"","sum":""}},"declaration":{"notfull_lostpages":"","additional_info_text":"","additional_info":"","date":"2015-03-25T00:00:00","notfull":"","url":"http://static.declarations.com.ua/declarations/chosen_ones/judges_batch/2676_medintseva_nina_mykhailivna.pdf"},"intro":{"isnotdeclaration":"","declaration_year":"2014"}}]