[{"id":"vulyk_66_51","ft_src":"2499 куб. см., 105 кВт\nDodge Ram Van\n2002\n2499 куб. см., 105 кВт\nDodge Ram Van\n2002\n1/2 від 70,9 кв.м у спільній сумісній власності на тер.України\n70.9\n1/3 від 62,5 кв.м у спільній сумісній власності на тер.України\n62.5\n1/2 від 70,9\n70.9\n1/4 від 67\n67\n2014\n36027\n202947\n57327\n202947\n21300\n2499 куб. см., 105 кВт\nDodge Ram Van\n2002\n2499 куб. см., 105 кВт\n2002\nDodge Ram Van\n70.9\n1/2 від 70,9 кв.м у спільній сумісній власності на тер.України\n62.5\n1/3 від 62,5 кв.м у спільній сумісній власності на тер.України\n70.9\n1/2 від 70,9\n67\n1/4 від 67\nАдміністративний місцевий суд\nсуддя миколаївського окружного адміністративного суду\nМиколаївська область\nПодружжя\nПетрова Юлія Ігорівна\nІнше\nтеща\nНікітіна Олена Володимирівна\nДитина\nМельник Олександр Олександрович\nМельник Олександр Михайлович\nОлександр Михайлович Мельник\nОлександр Мельник\nМельник Олександр Михайлович\nМельник Олександр Михайлович\nОлександр\nМельник\nМихайлович\n11519\n4080\n18202\n6637\n202947\n36027\n21300\n202947\n57327\n2014\n6637\n18202\n4080\n11519\nПетрова Юлія Ігорівна\nПодружжя\nтеща\nНікітіна Олена Володимирівна\nІнше\nМельник Олександр Олександрович\nДитина\nМихайлович\nМельник\nОлександр\nМельник Олександр Михайлович\nОлександр Михайлович Мельник\nОлександр Мельник\nМельник Олександр Михайлович\nМиколаївська область\nсуддя миколаївського окружного адміністративного суду\nАдміністративний місцевий суд\nМельник Олександр Михайлович","estate":{"25":[{"address":"","space_units":"м²","costs_hidden":false,"space_hidden":false,"space_unclear":false,"region_hidden":true,"costs_rent_comment":"","space_comment":"1/2 від 70,9","space_comment_unclear":false,"costs":"","address_unclear":false,"address_hidden":true,"costs_comment":"","space":"70.9","region_unclear":false,"region":"","space_units_hidden":false,"costs_rent":""},{"address":"","space_units":"м²","costs_hidden":false,"space_hidden":false,"space_unclear":false,"region_hidden":true,"costs_rent_comment":"","space_comment":"1/4 від 67","address_hidden":false,"costs":"","costs_comment_unclear":false,"costs_comment":"","space":"67","region":"","costs_rent":""}],"31":[{"costs_property_comment":"","address":"","space_units":"м²","space_hidden":false,"space_unclear":false,"region_hidden":true,"costs_property":"","space_comment":"1/2 від 70,9 кв.м у спільній сумісній власності на тер.України","address_hidden":true,"space_comment_hidden":false,"space_comment_unclear":false,"costs_rent_comment":"","space":"70.9","region":"","costs_rent":""},{"costs_property_comment":"","address":"","space_units":"м²","costs_rent_comment":"","space":"62.5","region":"","region_hidden":false,"costs_property":"","space_comment":"1/3 від 62,5 кв.м у спільній сумісній власності на тер.України","address_hidden":true,"costs_rent":""}]},"vehicle":{"35":[{"year_hidden":false,"brand_info":"2499 куб. см., 105 кВт","sum_rent_comment":"","brand_unclear":false,"brand_hidden":false,"year":"2002","sum_comment":"","sum_rent":"","brand":"Dodge Ram Van","year_unclear":false,"brand_info_unclear":false,"sum":""}],"40":[{"sum_comment":"","brand_info":"2499 куб. см., 105 кВт","brand_unclear":false,"sum_rent_comment":"","year":"2002","brand":"Dodge Ram Van","sum_rent":"","brand_info_unclear":false,"year_unclear":false,"sum":""}]},"source":"VULYK","income":{"5":{"family_comment":"","family":"57327","value_hidden":false,"comment":"","value":"202947","comment_unclear":false,"value_unclear":false,"family_unclear":false,"family_hidden":false},"6":{"family":"36027","family_comment":"","comment":"","value_hidden":false,"value_unclear":false,"value":"202947","comment_unclear":false,"family_unclear":false,"family_hidden":false},"7":{"family_comment":"","comment":"","family":"","source_name_unclear":false,"value":"","source_name":""},"8":{"family_comment":"","value":"","family":"","comment":""},"9":{"family_comment":"","comment":"","family":"","value_unclear":false,"comment_hidden":false,"comment_unclear":false,"value":""},"10":{"family_comment":"","family":"","value_hidden":false,"comment":"","comment_unclear":false,"value":""},"11":{"family_comment":"","value":"","family":"","comment":""},"12":{"family_comment":"","value":"","family":"","comment":""},"13":{"family_comment":"","value":"","family":"","comment":""},"14":{"family_comment":"","value":"","family":"","comment":""},"15":{"family_comment":"","value":"","family":"","comment":""},"16":{"family_comment":"","value":"","family":"","comment":""},"17":{"family_comment":"","value":"","family":"","comment":""},"18":{"family":"","family_comment":"","comment":"","value_hidden":false,"family_hidden":false,"value":""},"19":{"family_comment":"","value":"","family":"","comment":""},"20":{"family":"21300","family_comment":"","comment":"","value_hidden":false,"value_unclear":false,"value":"","family_hidden":false,"family_unclear":false}},"general":{"family":[{"inn":"","family_name":"Петрова Юлія Ігорівна","relations_other":"","relations_hidden":false,"name_unclear":false,"inn_hidden":true,"name_hidden":false,"relations":"Подружжя"},{"inn":"","family_name":"Нікітіна Олена Володимирівна","relations_other":"теща","relations_hidden":false,"relations_unclear":false,"name_unclear":false,"inn_hidden":false,"name_hidden":false,"relations":"Інше"},{"inn":"","family_name":"Мельник Олександр Олександрович","relations_other":"","relations_hidden":false,"name_unclear":false,"inn_hidden":true,"name_hidden":false,"relations":"Дитина"}],"family_raw":"","name":"Олександр","full_name_suggest":{"input":["Мельник Олександр Михайлович","Олександр Михайлович Мельник","Олександр Мельник"],"output":"Мельник Олександр Михайлович"},"patronymic":"Михайлович","inn_hidden":true,"addresses":[{"place_city_type_hidden":true,"place_district_hidden":true,"place_address_unclear":false,"place":"","place_city":"","place_unclear":false,"place_city_type_unclear":false,"place_city_type":"","place_city_hidden":true,"place_city_unclear":false,"place_district":"","place_district_unclear":false,"place_address":"","place_address_hidden":true,"place_hidden":true}],"last_name_hidden":false,"inn":"","inn_unclear":false,"last_name":"Мельник","full_name":"Мельник Олександр Михайлович","post":{"office":"Адміністративний місцевий суд","post":"суддя миколаївського окружного адміністративного суду","candidate":"","office_hidden":false,"region":"Миколаївська область","post_unclear":false,"office_unclear":false},"last_name_unclear":false},"liabilities":{"54":{"sum_comment_unclear":false,"sum_comment":"","sum":"","sum_foreign_comment":"","sum_foreign":"","sum_unclear":false,"sum_comment_hidden":false},"55":{"sum_comment":"","sum_foreign_comment":"","sum_foreign":"","sum":""},"56":{"sum_comment":"","sum_hidden":false,"sum":"","sum_foreign_comment":"","sum_foreign":"","sum_foreign_hidden":false,"sum_comment_hidden":false},"57":{"sum_comment_unclear":false,"sum_comment":"","sum_hidden":false,"sum":"18202","sum_foreign_comment":"","sum_foreign":"","sum_unclear":false,"sum_comment_hidden":false},"58":{"sum_comment_unclear":false,"sum_comment":"","sum":"6637","sum_foreign_comment":"","sum_foreign":"","sum_unclear":false},"59":{"sum_comment_unclear":false,"sum_comment":"","sum_hidden":false,"sum":"","sum_foreign_comment":"","sum_foreign":"","sum_foreign_hidden":false},"60":{"sum_comment":"","sum_comment_unclear":false,"sum_foreign_comment":"","sum":"","sum_foreign":""},"61":{"sum_comment":"","sum_foreign_comment":"","sum_foreign":"","sum":""},"62":{"sum_comment":"","sum_hidden":false,"sum":"","sum_foreign_comment":"","sum_foreign":"","sum_unclear":false,"sum_foreign_hidden":false},"63":{"sum_comment_unclear":false,"sum_comment":"","sum":"11519","sum_foreign_comment":"","sum_foreign":"","sum_unclear":false,"sum_comment_hidden":false},"64":{"sum_comment":"","sum_comment_unclear":false,"sum_foreign_comment":"","sum":"4080","sum_foreign":""}},"declaration":{"notfull_lostpages":"","additional_info_text":"","additional_info":"","date":"2015-03-30T00:00:00","notfull":"","url":"http://static.declarations.com.ua/declarations/chosen_ones/mega_batch/melnyk_oleksandr_mykhailovych_1.pdf"},"intro":{"isnotdeclaration":"","declaration_year_unclear":false,"declaration_year":"2014"}}]