[{"id":"vulyk_75_140","ft_src":"Власність\n637\nВласність\n180.5\nоренда\n53952.75\n183.9\n2013\n197023\n48\n11470\n508541\n300000\n2013\nМєзєнцев\nІгорович\nПодружжя\nМєзєнцева О. В\nДитина\nМєзєнцев П. Є\nДитина\nМєзєнцева М. Є\nМєзєнцев Євген Ігорович\nЄвген Ігорович Мєзєнцев\nЄвген Мєзєнцев\nМєзєнцев Євген Ігорович\nЄвген\nМєзєнцев Євген Ігорович\nАпеляційний адміністративний суд\nголова київського апеляційного адміністративного суду\nм. Київ\n11448\n10542\n197023\n508541\n300000\n11470\n48\n637\nВласність\n180.5\nВласність\n183.9\nоренда\n53952.75\n10542\n11448\nМєзєнцева О. В\nПодружжя\nМєзєнцев П. Є\nДитина\nМєзєнцева М. Є\nДитина\nМєзєнцев\nІгорович\nголова київського апеляційного адміністративного суду\nм. Київ\nАпеляційний адміністративний суд\nМєзєнцев Євген Ігорович\nМєзєнцев Євген Ігорович\nЄвген Ігорович Мєзєнцев\nЄвген Мєзєнцев\nМєзєнцев Євген Ігорович\nЄвген","estate":{"23":[{"address":"","space_units":"м²","costs_comment":"","region_hidden":true,"space_comment":"Власність","address_hidden":false,"costs":"","costs_rent_comment":"","space":"637","region":"","space_units_hidden":false,"costs_rent":""}],"24":[{"costs":"","address":"","space_units":"м²","costs_rent_comment":"","space":"180.5","space_comment":"Власність","region_hidden":true,"costs_comment":"","region":"","costs_rent":""}],"25":[{"address":"","space_units":"м²","space_hidden":false,"space_unclear":false,"region_hidden":true,"costs_comment":"","space_comment":"оренда","address_hidden":false,"space":"183.9","costs_rent_comment":"","costs":"","region":"","costs_rent":"53952.75"}]},"source":"VULYK","income":{"5":{"family_comment":"","value":"508541","family":"","comment":""},"6":{"family_comment":"","family_hidden":false,"value":"197023","family":"","comment":""},"7":{"family":"","family_comment":"","value":"","comment":"","source_name":""},"8":{"family_comment":"","value":"","family":"","comment":""},"9":{"family_comment":"","family":"","comment":"","value_unclear":false,"family_hidden":false,"value":""},"10":{"family":"","family_comment":"","comment":"","value_hidden":false,"value":"11470","family_hidden":false,"family_unclear":false},"11":{"family_comment":"","value":"48","family":"","comment":""},"12":{"family_comment":"","value":"","family":"","comment":""},"13":{"family_comment":"","value":"","family":"","comment":""},"14":{"family_comment":"","value":"","family":"","comment":""},"15":{"family_comment":"","value":"","family":"","comment":""},"16":{"family_comment":"","value":"300000","family":"","comment":""},"17":{"family_comment":"","value":"","family":"","comment":""},"18":{"family_comment":"","value":"","family":"","comment":""},"19":{"family_comment":"","value":"","family":"","comment":""},"20":{"family_comment":"","comment":"","family":"","comment_unclear":false,"value":"","family_comment_unclear":false}},"general":{"inn":"","addresses":[{"place_city_type_hidden":false,"place_city_type":"","place_city_hidden":false,"place_hidden":true,"place_district":"","place_district_hidden":false,"place":"","place_city":"","place_address_hidden":false,"place_address":""}],"last_name":"Мєзєнцев","full_name":"Мєзєнцев Євген Ігорович","family":[{"inn":"","family_name":"Мєзєнцева О. В","relations_other":"","relations_hidden":false,"name_unclear":false,"inn_hidden":false,"name_hidden":false,"relations":"Подружжя"},{"inn":"","family_name":"Мєзєнцев П. Є","relations_other":"","name_unclear":false,"inn_hidden":false,"name_hidden":false,"relations":"Дитина"},{"inn":"","family_name":"Мєзєнцева М. Є","relations_other":"","name_unclear":false,"inn_hidden":false,"name_hidden":false,"relations":"Дитина"}],"patronymic":"Ігорович","inn_hidden":true,"name":"Євген","post":{"office":"Апеляційний адміністративний суд","region":"м. Київ","post":"голова київського апеляційного адміністративного суду"},"family_raw":"","full_name_suggest":{"input":["Мєзєнцев Євген Ігорович","Євген Ігорович Мєзєнцев","Євген Мєзєнцев"],"output":"Мєзєнцев Євген Ігорович"}},"liabilities":{"54":{"sum_comment":"","sum_foreign_comment":"","sum_foreign":"","sum":"11448"},"55":{"sum_comment":"","sum_foreign_comment":"","sum_foreign":"","sum":""},"56":{"sum_comment":"","sum_foreign_comment":"","sum_foreign":"","sum":"10542"},"57":{"sum_comment":"","sum_foreign_comment":"","sum_foreign":"","sum":""},"58":{"sum_comment":"","sum_foreign_comment":"","sum_foreign":"","sum":""},"59":{"sum_comment_unclear":false,"sum_comment":"","sum":"","sum_foreign_comment":"","sum_foreign":"","sum_unclear":false},"60":{"sum_comment":"","sum_foreign_comment":"","sum_foreign":"","sum":""},"61":{"sum_comment":"","sum_foreign_comment":"","sum_foreign":"","sum":""},"62":{"sum_comment":"","sum_foreign_comment":"","sum_foreign":"","sum_unclear":false,"sum":""},"63":{"sum_comment":"","sum_foreign_comment":"","sum_foreign":"","sum":""},"64":{"sum_comment":"","sum_foreign_comment":"","sum_foreign":"","sum":""}},"declaration":{"notfull_lostpages":"","additional_info_text":"","additional_info":"","date":"2014-03-17T00:00:00","notfull":"","url":"http://static.declarations.com.ua/declarations/chosen_ones/judges_batch/1795_miezientsev_ievhen_ihorovych.pdf"},"intro":{"isnotdeclaration":"","declaration_year":"2013"}}]