[{"id":"vulyk_87_48","ft_src":"46,82 від 74,9\nм. Донецьк\nДонецька область\n74.9\n2014\n158436.16\n12180\n170616.16\n158436.16\n170616.16\n12180\nДитина\nМихальченко Анастасія Олександрівна\nАнастасія Олександрівна Михальченко\nАнастасія Михальченко\nМихальченко Анастасія Олександрівна\nАнастасія\nМихальченко Анастасія Олександрівна\nМихальченко\nЗагальний місцевий суд\nДонецька область\nсуддя гірницького районного суду м. макіївки донецької області\nОлександрівна\nДонецьк\n83001\nДонецька область\n74.9\n46,82 від 74,9\nДонецька область\nм. Донецьк\n2014\nДитина\nАнастасія\nОлександрівна\nМихальченко\nМихальченко Анастасія Олександрівна\nАнастасія Олександрівна Михальченко\nАнастасія Михальченко\nМихальченко Анастасія Олександрівна\nДонецька область\nДонецьк\n83001\nДонецька область\nЗагальний місцевий суд\nсуддя гірницького районного суду м. макіївки донецької області\nМихальченко Анастасія Олександрівна","estate":{"25":[{"address":"м. Донецьк","space_units":"м²","space_hidden":false,"space_unclear":false,"region_hidden":false,"costs_comment":"","space_comment":"46,82 від 74,9","address_hidden":true,"space":"74.9","space_comment_unclear":false,"costs_rent_comment":"","costs":"","region":"Донецька область","costs_rent":""}]},"source":"VULYK","income":{"5":{"family_comment":"","value":"170616.16","family_unclear":false,"family":"","comment":""},"6":{"family_comment":"","value":"158436.16","family":"","comment":""},"7":{"family":"","family_comment":"","value":"","comment":"","source_name":""},"8":{"family_comment":"","value":"","family":"","comment":""},"9":{"family_comment":"","value":"","family":"","comment":""},"10":{"family_comment":"","value":"12180","family":"","comment":""},"11":{"family_comment":"","value":"","family":"","comment":""},"12":{"family_comment":"","value":"","family":"","comment":""},"13":{"family_comment":"","value":"","family":"","comment":""},"14":{"family_comment":"","value":"","family":"","comment":""},"15":{"family_comment":"","value":"","family":"","comment":""},"16":{"family_comment":"","value":"","family":"","comment":""},"17":{"family_comment":"","value":"","family":"","comment":""},"18":{"family_comment":"","value":"","family":"","comment":""},"19":{"family_comment":"","value":"","family":"","comment":""},"20":{"family_comment":"","value":"","family":"","comment":""}},"general":{"family_raw":"","name":"Анастасія","full_name_suggest":{"input":["Михальченко Анастасія Олександрівна","Анастасія Олександрівна Михальченко","Анастасія Михальченко"],"output":"Михальченко Анастасія Олександрівна"},"patronymic":"Олександрівна","inn_hidden":true,"addresses":[{"place_city_type_hidden":false,"place_hidden":false,"place_address_unclear":false,"place":"Донецька область","place_city":"Донецьк","place_city_type_unclear":false,"place_city_type":"Місто","place_city_hidden":false,"place_district":"","place_district_hidden":false,"place_address":"83001","place_address_hidden":true}],"inn":"","inn_unclear":false,"last_name":"Михальченко","full_name":"Михальченко Анастасія Олександрівна","family":[{"inn":"","family_name":"","relations_other":"","relations_hidden":false,"name_unclear":false,"inn_hidden":true,"name_hidden":true,"relations":"Дитина"}],"post":{"office":"Загальний місцевий суд","post":"суддя гірницького районного суду м. макіївки донецької області","candidate":"","office_unclear":false,"region":"Донецька область","post_unclear":false}},"liabilities":{"54":{"sum_comment":"","sum_comment_unclear":false,"sum_foreign_comment":"","sum":"","sum_foreign":""},"55":{"sum_comment":"","sum_foreign_comment":"","sum_foreign":"","sum":""},"56":{"sum_comment":"","sum_foreign_comment":"","sum_foreign":"","sum":""},"57":{"sum_comment":"","sum_hidden":false,"sum":"","sum_foreign_comment":"","sum_foreign":"","sum_unclear":false},"58":{"sum_comment":"","sum_foreign_comment":"","sum_foreign":"","sum_unclear":false,"sum":""},"59":{"sum_comment":"","sum_foreign_comment":"","sum_foreign":"","sum":""},"60":{"sum_comment":"","sum_comment_unclear":false,"sum_foreign_comment":"","sum":"","sum_foreign":""},"61":{"sum_comment":"","sum_foreign_comment":"","sum_foreign":"","sum":""},"62":{"sum_comment":"","sum_foreign_comment":"","sum_foreign":"","sum_unclear":false,"sum":""},"63":{"sum_comment":"","sum_foreign_comment":"","sum_foreign":"","sum_unclear":false,"sum":""},"64":{"sum_comment":"","sum_foreign_comment":"","sum_foreign":"","sum":""}},"declaration":{"notfull_lostpages":"","additional_info_text":"","additional_info":"","date":"2015-03-26T00:00:00","notfull":"","url":"http://static.declarations.com.ua/declarations/chosen_ones/judges_batch/2851_mykhalchenko_anastasiia_oleksandrivna.pdf"},"intro":{"isnotdeclaration":"","declaration_year":"2014"}}]