[{"id":"vulyk_64_146","ft_src":"554 М, 4750 куб. см., 59 кВт\n1990\nЗИЛ ММЗ\n1197 куб. см., 29.4 кВт\nЛуАЗ 969 М\n1987\n1970\nТрактор, 6333 куб. см., 662 кВт\nТ-74\nТрактор, 4940 куб. см., 45.6 кВт\n1987\nЮМЗ\n20000\n79.2\n110000\n79.2\n46.85\n289805.1\n2014\n19320.7\n171484.05\n12180\n73657.86\n183664.05\nЗгідно з ч. 6 ст. 46 ЗУ 'Про запобігання корупції' від 14. 10. 2014 №1700 у п. 20 Декларації 'сума одержаного (нарахованого) доходу членів сім'ї ' сума вказана без зазначення доходу платника (ід.№ 2021315983) за 4 кв. 2014р. року. ' - Момонт Г. М\n54337.16\n1197 куб. см., 29.4 кВт\nЛуАЗ 969 М\n1987\nТрактор, 6333 куб. см., 662 кВт\nТ-74\n1970\nТрактор, 4940 куб. см., 45.6 кВт\nЮМЗ\n1987\n554 М, 4750 куб. см., 59 кВт\nЗИЛ ММЗ\n1990\n20000\n110000\n79.2\n79.2\n289805.1\n46.85\nАдміністративний місцевий суд\nКіровоградська область\nсуддя кіровоградського окружного адміністративного суду\nБатьки\nМомонт Митрофан Сергійович\nБатьки\nМомонт Лідія Іванівна\nБрат/Сестра\nМомонт Сергій Митрофанович\nМомонт Галина Митрофанівна\nГалина Митрофанівна Момонт\nГалина Момонт\nМомонт Галина Митрофанівна\nМомонт Галина Митрофанівна\nГалина\nМомонт\nМитрофанівна\n3715.13\n5084.87\n3427\n19320.7\n171484.05\nЗгідно з ч. 6 ст. 46 ЗУ 'Про запобігання корупції' від 14. 10. 2014 №1700 у п. 20 Декларації 'сума одержаного (нарахованого) доходу членів сім'ї ' сума вказана без зазначення доходу платника (ід.№ 2021315983) за 4 кв. 2014р. року. ' - Момонт Г. М\n54337.16\n183664.05\n73657.86\n12180\n2014\n5084.87\n3715.13\n3427\nБатьки\nМомонт Митрофан Сергійович\nБатьки\nМомонт Лідія Іванівна\nМомонт Сергій Митрофанович\nБрат/Сестра\nМитрофанівна\nМомонт\nГалина\nМомонт Галина Митрофанівна\nГалина Митрофанівна Момонт\nГалина Момонт\nМомонт Галина Митрофанівна\nКіровоградська область\nАдміністративний місцевий суд\nсуддя кіровоградського окружного адміністративного суду\nМомонт Галина Митрофанівна","estate":{"23":[{"costs_unclear":false,"space_hidden":false,"space_comment":"","costs_comment":"","address_hidden":false,"space_comment_hidden":false,"address_unclear":false,"costs_rent_comment_unclear":false,"space_units_unclear":false,"costs":"","region_unclear":false,"space_units_hidden":false,"costs_rent":"","address":"","space_units":"м²","costs_hidden":false,"costs_rent_unclear":false,"costs_rent_hidden":false,"space_unclear":false,"region_hidden":true,"space_comment_unclear":false,"costs_rent_comment":"","space":"20000","region":""}],"24":[{"costs":"","address":"","space_units":"м²","costs_hidden":false,"space_hidden":false,"space_comment":"","region_hidden":true,"costs_comment":"","address_hidden":false,"costs_rent_hidden":false,"address_unclear":false,"costs_rent_comment":"","space":"79.2","region":"","costs_rent":""}],"25":[{"costs":"289805.1","costs_unclear":false,"address":"","space_units":"м²","costs_hidden":false,"costs_rent_unclear":false,"costs_rent_hidden":false,"space_unclear":false,"region_hidden":true,"costs_comment":"","space_comment_unclear":false,"address_hidden":false,"space_hidden":false,"space_comment":"","costs_rent_comment_unclear":false,"costs_rent_comment":"","space":"46.85","region_unclear":false,"region":"","space_units_hidden":false,"costs_rent":""}],"29":[{"costs_property_comment":"","address":"","space_units":"м²","costs_rent_unclear":false,"space_hidden":false,"space_unclear":false,"region_hidden":true,"costs_property":"","space_comment":"","address_hidden":false,"costs_rent_hidden":false,"costs_property_hidden":false,"address_unclear":false,"costs_rent_comment":"","space":"110000","region_unclear":false,"region":"","costs_rent":""}],"30":[{"costs_property_comment":"","address":"","space_units":"м²","space_hidden":false,"space_unclear":false,"region_hidden":true,"costs_property":"","space_comment":"","space_comment_unclear":false,"costs_rent_hidden":false,"costs_property_hidden":false,"address_unclear":false,"address_hidden":false,"costs_rent_comment":"","space":"79.2","region_unclear":false,"region":"","costs_rent":""}]},"vehicle":{"40":[{"year_hidden":false,"brand_info":"1197 куб. см., 29.4 кВт","brand_unclear":false,"sum_rent_comment":"","brand_hidden":false,"year":"1987","sum_comment":"","brand_info_hidden":false,"sum_rent":"","brand":"ЛуАЗ 969 М","brand_info_unclear":false,"sum":""}],"41":[{"sum_comment":"","brand_info":"554 М, 4750 куб. см., 59 кВт","sum":"","sum_rent_comment":"","year":"1990","brand":"ЗИЛ ММЗ","sum_rent":""}],"44":[{"sum_comment":"","brand_info":"Трактор, 6333 куб. см., 662 кВт","sum":"","brand_unclear":false,"year":"1970","brand":"Т-74","sum_rent":"","sum_rent_comment":""},{"sum_comment":"","brand_info":"Трактор, 4940 куб. см., 45.6 кВт","sum":"","sum_rent_comment":"","year":"1987","brand":"ЮМЗ","sum_rent":""}]},"source":"VULYK","income":{"5":{"family":"73657.86","family_comment":"","comment":"","value_hidden":false,"value_unclear":false,"value":"183664.05","family_hidden":false,"family_unclear":false,"family_comment_unclear":false},"6":{"family":"19320.7","family_comment":"","comment":"","value_hidden":false,"value_unclear":false,"comment_hidden":false,"family_hidden":false,"family_unclear":false,"value":"171484.05"},"7":{"source_name_hidden":false,"family_comment":"","family":"","value_hidden":false,"comment":"","value":"","source_name":""},"8":{"family_comment":"","value":"","family":"","comment":""},"9":{"family":"","family_comment":"","comment":"","value_hidden":false,"comment_hidden":false,"value":""},"10":{"family":"","family_comment":"","comment":"","value_hidden":false,"value_unclear":false,"value":"12180"},"11":{"family_comment":"","value":"","family":"","comment":""},"12":{"family_comment":"","value":"","family":"","comment":""},"13":{"family_comment":"","family_hidden":false,"value":"","family":"","comment":""},"14":{"family_comment":"","value":"","family":"","comment":""},"15":{"family_comment":"","value":"","family_unclear":false,"family":"","comment":""},"16":{"family_comment":"","value":"","family":"","comment":"","value_unclear":false},"17":{"family_comment":"","value":"","family":"","comment":""},"18":{"family_comment":"","value":"","family":"","comment":""},"19":{"family_comment":"","comment_unclear":false,"value":"","family":"","comment":""},"20":{"family_comment":"Згідно з ч. 6 ст. 46 ЗУ 'Про запобігання корупції' від 14. 10. 2014 №1700 у п. 20 Декларації 'сума одержаного (нарахованого) доходу членів сім'ї ' сума вказана без зазначення доходу платника (ід.№ 2021315983) за 4 кв. 2014р. року. ' - Момонт Г. М","family":"54337.16","value_hidden":false,"comment":"","comment_unclear":false,"value":"","family_hidden":false}},"general":{"family":[{"inn":"","inn_unclear":false,"family_name":"Момонт Митрофан Сергійович","relations_hidden":false,"relations_unclear":false,"name_unclear":false,"relations":"Батьки","inn_hidden":true,"name_hidden":false,"relations_other":""},{"inn":"","family_name":"Момонт Лідія Іванівна","relations_hidden":false,"relations_unclear":false,"name_unclear":false,"relations":"Батьки","inn_hidden":false,"name_hidden":false,"relations_other":""},{"inn":"","family_name":"Момонт Сергій Митрофанович","relations_other":"","name_unclear":false,"inn_hidden":false,"name_hidden":false,"relations":"Брат/Сестра"}],"family_raw":"","name":"Галина","full_name_suggest":{"input":["Момонт Галина Митрофанівна","Галина Митрофанівна Момонт","Галина Момонт"],"output":"Момонт Галина Митрофанівна"},"name_unclear":false,"patronymic":"Митрофанівна","inn_hidden":true,"addresses":[{"place_city_type_unclear":false,"place_district_hidden":false,"place_hidden":true,"place":"","place_city":"","place_unclear":false,"place_city_type_hidden":false,"place_city_type":"","place_city_hidden":false,"place_district":"","place_city_unclear":false,"place_address":"","place_address_hidden":false}],"last_name_hidden":false,"patronymic_hidden":false,"inn":"","inn_unclear":false,"last_name":"Момонт","full_name":"Момонт Галина Митрофанівна","post":{"post_hidden":false,"office":"Адміністративний місцевий суд","post":"суддя кіровоградського окружного адміністративного суду","candidate":"","region_hidden":false,"region":"Кіровоградська область","office_hidden":false,"post_unclear":false,"office_unclear":false},"last_name_unclear":false},"liabilities":{"54":{"sum_comment":"","sum_hidden":false,"sum":"3427","sum_foreign_comment":"","sum_comment_hidden":false,"sum_foreign":"","sum_unclear":false,"sum_foreign_comment_hidden":false},"55":{"sum_comment":"","sum_comment_unclear":false,"sum_foreign_comment":"","sum":"","sum_foreign":""},"56":{"sum_comment":"","sum_foreign_comment":"","sum_foreign":"","sum_unclear":false,"sum":""},"57":{"sum_comment":"","sum_hidden":false,"sum":"3715.13","sum_foreign_comment":"","sum_foreign":"","sum_unclear":false},"58":{"sum_comment":"","sum_foreign_comment":"","sum_foreign":"","sum_unclear":false,"sum":"5084.87"},"59":{"sum_comment_unclear":false,"sum_comment":"","sum":"","sum_foreign_comment":"","sum_foreign":"","sum_unclear":false,"sum_comment_hidden":false},"60":{"sum_comment":"","sum_foreign_comment":"","sum_foreign":"","sum":""},"61":{"sum_comment":"","sum_foreign_comment":"","sum_foreign":"","sum":""},"62":{"sum_comment":"","sum_foreign_comment":"","sum_foreign":"","sum_unclear":false,"sum":""},"63":{"sum_comment":"","sum_foreign_comment":"","sum_foreign":"","sum_unclear":false,"sum":""},"64":{"sum_comment_unclear":false,"sum_comment":"","sum":"","sum_foreign_comment":"","sum_foreign":"","sum_unclear":false}},"declaration":{"notfull_lostpages":"","additional_info_text":"","additional_info":"","date":"2015-03-31T00:00:00","notfull":"","url":"http://static.declarations.com.ua/declarations/chosen_ones/mega_batch/momont_halyna_mytrofanivna.pdf"},"intro":{"declaration_year_hidden":false,"isnotdeclaration":"","declaration_year_unclear":false,"declaration_year":"2014"}},{"ft_src":"ЗИЛ,ММЗ 554\n1990\nЛуАЗ,969М\n1987\nТ-74 (трактор)\n1970\nЮМЗ (трактор)\n1987\n20000\n79,2\n110000\nFALSE\nFALSE\nFALSE\n2013\n29778\n159205\n11470\n62678\n170675\n39900\nЛуАЗ,969М\n1987\nТ-74 (трактор)\n1970\nЮМЗ (трактор)\n1987\nЗИЛ,ММЗ 554\n1990\nFALSE\nFALSE\n20000\n110000\n79,2\nСуддя Кіровоградського окружного адміністративного суду\nБатько Момонт Митрофан Сергійович;матір  Момонт Лідія Іванівна;брат Момонт  Сергій Митрофанович\nМомонт\nМомонт Галина Митрофанівна\nГалина Митрофанівна Момонт\nГалина Момонт\nМомонт Галина Митрофанівна\nГалина\nМомонт Галина Митрофанівна\nАдміністративний місцевий суд\nСуддя\nКіровоградська область\nМитрофанівна\n159205\n29778\n39900\n170675\n62678\n11470\n2013\nFALSE\nМомонт\nМитрофанівна\nБатько Момонт Митрофан Сергійович;матір  Момонт Лідія Іванівна;брат Момонт  Сергій Митрофанович\nМомонт Галина Митрофанівна\nГалина Митрофанівна Момонт\nГалина Момонт\nМомонт Галина Митрофанівна\nГалина\nСуддя Кіровоградського окружного адміністративного суду\nСуддя\nКіровоградська область\nАдміністративний місцевий суд\nМомонт Галина Митрофанівна","estate":{"23":[{"costs":"","address":"","space_units":"","costs_rent_comment":"","space":"20000","costs_comment":"","costs_rent":"","space_comment":"","region":"","location_raw":"приховано"},{"costs":"","address":"","space_units":"","costs_rent_comment":"","space":"","costs_comment":"","costs_rent":"","space_comment":"","region":"","location_raw":""},{"costs":"","address":"","space_units":"","costs_rent_comment":"","space":"","costs_comment":"","costs_rent":"","space_comment":"","region":"","location_raw":""}],"29":[{"costs_property_comment":"","address":"","space_units":"","costs_rent_comment":"","space":"110000","space_comment":"","costs_property":"","region":"","location_raw":"приховано","costs_rent":""}],"30":[{"costs_property_comment":"","address":"","space_units":"","costs_rent_comment":"","space":"79,2","space_comment":"","costs_property":"","region":"","location_raw":"приховано","costs_rent":""}]},"vehicle":{"40":[{"sum_comment":"","brand_info":"","sum":"","sum_rent_comment":"","year":"1987","brand":"ЛуАЗ,969М","sum_rent":"","brand_hidden":false}],"41":[{"sum_comment":"","brand_info":"","sum":"","sum_rent_comment":"","year":"1990","brand":"ЗИЛ,ММЗ 554","sum_rent":"","brand_hidden":false}],"44":[{"sum_comment":"","brand_info":"","sum":"","sum_rent_comment":"","year":"1970","brand":"Т-74 (трактор)","sum_rent":"","brand_hidden":false},{"sum_comment":"","brand_info":"","sum":"","sum_rent_comment":"","year":"1987","brand":"ЮМЗ (трактор)","sum_rent":"","brand_hidden":false}]},"id":"4866","income":{"5":{"family_comment":"","value":"170675","family":"62678","comment":""},"6":{"family_comment":"","value":"159205","family":"29778","comment":""},"7":{"family":"0","family_comment":"","value":"0","comment":"","source_name":"0"},"8":{"family_comment":"","value":"0","family":"0","comment":""},"9":{"family_comment":"","value":"0","family":"0","comment":""},"10":{"family_comment":"","value":"11470","family":"0","comment":""},"11":{"family_comment":"","value":"0","family":"0","comment":""},"12":{"family_comment":"","value":"0","family":"0","comment":""},"13":{"family_comment":"","value":"0","family":"0","comment":""},"14":{"family_comment":"","value":"0","family":"0","comment":""},"15":{"family_comment":"","value":"0","family":"0","comment":""},"16":{"family_comment":"","value":"0","family":"0","comment":""},"17":{"family_comment":"","value":"0","family":"0","comment":""},"18":{"family_comment":"","value":"0","family":"0","comment":""},"19":{"family_comment":"","value":"0","family":"0","comment":""},"20":{"family_comment":"","value":"0","family":"39900","comment":""},"21":[{"country_comment":"","uah_equal":"0","country":"0","cur":"0"},{"country_comment":"","uah_equal":"0","country":"0","cur":"0"},{"country_comment":"","uah_equal":"0","country":"0","cur":"0"},{"country_comment":"","uah_equal":"0","country":"0","cur":"0"},{"country_comment":"","uah_equal":"0","country":"0","cur":"0"}],"22":[{"country_comment":"","uah_equal":"0","country":"0","cur":"0"},{"country_comment":"","uah_equal":"0","country":"0","cur":"0"},{"country_comment":"","uah_equal":"0","country":"0","cur":"0"},{"country_comment":"","uah_equal":"0","country":"0","cur":"0"},{"country_comment":"","uah_equal":"0","country":"0","cur":"0"}]},"banks":{"45":[{"sum_units":"UAH","sum_comment":"","sum_foreign_units":"","sum":"","sum_foreign_comment":"","sum_foreign":""},{"sum_units":"USD","sum_comment":"","sum_foreign_units":"","sum":"","sum_foreign_comment":"","sum_foreign":""},{"sum_units":"EUR","sum_comment":"","sum_foreign_units":"","sum":"","sum_foreign_comment":"","sum_foreign":""}],"46":[{"sum_units":"UAH","sum_comment":"","sum_foreign_units":"","sum":"","sum_foreign_comment":"","sum_foreign":""},{"sum_units":"USD","sum_comment":"","sum_foreign_units":"","sum":"","sum_foreign_comment":"","sum_foreign":""},{"sum_units":"EUR","sum_comment":"","sum_foreign_units":"","sum":"","sum_foreign_comment":"","sum_foreign":""}],"47":[{"sum_units":"","sum_comment":"","sum_foreign_units":"","sum":"","sum_foreign_comment":"","sum_foreign":""}],"48":[{"sum_units":"","sum_comment":"","sum_foreign_units":"","sum":"","sum_foreign_comment":"","sum_foreign":""}],"49":[{"sum_units":"","sum_comment":"","sum_foreign_units":"","sum":"","sum_foreign_comment":"","sum_foreign":""}],"50":[{"sum_units":"","sum_comment":"","sum_foreign_units":"","sum":"","sum_foreign_comment":"","sum_foreign":""}],"51":[{"sum_units":"UAH","sum_comment":"","sum_foreign_units":"","sum":"","sum_foreign_comment":"","sum_foreign":""},{"sum_units":"USD","sum_comment":"","sum_foreign_units":"","sum":"","sum_foreign_comment":"","sum_foreign":""},{"sum_units":"EUR","sum_comment":"","sum_foreign_units":"","sum":"","sum_foreign_comment":"","sum_foreign":""}],"52":[{"sum_units":"","sum_comment":"","sum_foreign_units":"","sum":"","sum_foreign_comment":"","sum_foreign":""}],"53":[{"sum_units":"","sum_comment":"","sum_foreign_units":"","sum":"","sum_foreign_comment":"","sum_foreign":""}]},"declaration":{"notfull_lostpages":"","additional_info_text":"","additional_info":"FALSE","notfull":"FALSE","url":"http://static.declarations.com.ua/declarations/sudy/mistsevi_sudy/okruzhni_administratyvni_sudy/kirovohradska/momont.pdf","needs_scancopy_check":false},"general":{"family_raw":"Батько Момонт Митрофан Сергійович;матір  Момонт Лідія Іванівна;брат Момонт  Сергій Митрофанович","name":"Галина","full_name_suggest":{"input":["Момонт Галина Митрофанівна","Галина Митрофанівна Момонт","Галина Момонт"],"output":"Момонт Галина Митрофанівна"},"post_raw":"Суддя Кіровоградського окружного адміністративного суду","name_unclear":false,"patronymic":"Митрофанівна","patronymic_unclear":false,"last_name_hidden":false,"patronymic_hidden":false,"inn":"","addresses_raw_hidden":true,"last_name":"Момонт","full_name":"Момонт Галина Митрофанівна","post":{"office":"Адміністративний місцевий суд","region":"Кіровоградська область","post":"Суддя"},"addresses_raw":"приховано","name_hidden":false,"last_name_unclear":false},"liabilities":{"54":{"sum_comment":"","sum_foreign_comment":"","sum_foreign":"","sum":""},"55":{"sum_units":"","sum_comment":"","sum_foreign_units":"","sum":"","sum_foreign_comment":"","sum_foreign":""},"56":{"sum_comment":"","sum_foreign_comment":"","sum_foreign":"","sum":""},"57":{"sum_comment":"","sum_foreign_comment":"","sum_foreign":"","sum":""},"58":{"sum_comment":"","sum_foreign_comment":"","sum_foreign":"","sum":""},"59":{"sum_comment":"","sum_foreign_comment":"","sum_foreign":"","sum":""},"60":{"sum_comment":"","sum_foreign_comment":"","sum_foreign":"","sum":""},"61":{"sum_units":"","sum_comment":"","sum_foreign_units":"","sum":"","sum_foreign_comment":"","sum_foreign":""},"62":{"sum_comment":"","sum_foreign_comment":"","sum_foreign":"","sum":""},"63":{"sum_comment":"","sum_units":"","sum_foreign":"","sum":"","sum_foreign_comment":""},"64":{"sum_comment":"","sum_units":"","sum_foreign":"","sum":"","sum_foreign_comment":""}},"intro":{"isnotdeclaration":"FALSE","declaration_year":"2013"}}]