[{"id":"vulyk_68_114","ft_src":"2354\nHonda CR-V\n2008\n500\n230\n1\nЗгідно рішення КСУ №2-рп/2012р. від 20. 01. 2012р. члени сім'ї відмовились дати відомості\n2014\n228043.48\nдол. США\n20796\n228043.48\n2354\nHonda CR-V\n2008\nЗгідно рішення КСУ №2-рп/2012р. від 20. 01. 2012р. члени сім'ї відмовились дати відомості\n1\n500\n230\nПодружжя\nКузнецов В. В. 20. 09. 197? р\nДитина\nКузнецов М. В. 27. 02. 200? р\nБатьки\nМонич В. М. 11. 12. 1941 р\nМонич Оксана Ласлівна\nОксана Ласлівна Монич\nОксана Монич\nМонич Оксана Ласлівна\nМонич Оксана Ласлівна\nОксана\nЛаслівна\nЗагальний місцевий суд\nЗакарпатська область\nсуддя ужгородського міськрайонного суду\nМонич\n1000\n228043.48\nдол. США\n20796\n228043.48\n2014\n1000\nПодружжя\nКузнецов В. В. 20. 09. 197? р\nКузнецов М. В. 27. 02. 200? р\nДитина\nМонич В. М. 11. 12. 1941 р\nБатьки\nЛаслівна\nМонич\nОксана\nМонич Оксана Ласлівна\nОксана Ласлівна Монич\nОксана Монич\nМонич Оксана Ласлівна\nЗакарпатська область\nЗагальний місцевий суд\nсуддя ужгородського міськрайонного суду\nМонич Оксана Ласлівна","estate":{"23":[{"address":"","space_units":"м²","costs_comment":"","region_hidden":true,"space_comment":"","address_hidden":false,"space_comment_hidden":false,"space":"500","costs_rent_comment":"","costs":"","region":"","costs_rent":""}],"30":[{"costs_property_comment":"","address":"","space_units":"м²","space_hidden":false,"space_unclear":false,"region_hidden":true,"costs_property":"","space_comment":"","address_hidden":true,"costs_rent_comment":"","space":"230","region":"","costs_rent":""}]},"vehicle":{"35":[{"brand_info":"2354","sum_rent_comment":"","brand_unclear":false,"year":"2008","brand_hidden":false,"sum_comment":"","brand_info_hidden":false,"sum_rent":"","brand":"Honda CR-V","year_unclear":false,"brand_info_unclear":true,"sum":""}]},"source":"VULYK","income":{"5":{"family_comment":"","value":"228043.48","family_unclear":false,"family":"","comment":""},"6":{"family_comment":"","value":"228043.48","family_unclear":false,"family":"","comment":""},"7":{"family_comment":"","comment":"","family":"","comment_hidden":false,"value":"","source_name":""},"8":{"family_comment":"","value":"","family":"","comment":""},"9":{"family_comment":"","value":"","family":"","comment":""},"10":{"family_comment":"","value":"","family":"","comment":""},"11":{"family_comment":"","value":"","family":"","comment":"","value_unclear":false},"12":{"family_comment":"","value":"","family":"","comment":""},"13":{"family_comment":"","value":"","family":"","comment":""},"14":{"family_comment":"","value":"20796","family":"","comment":"дол. США"},"15":{"family_comment":"","value":"","family":"","comment":"","value_unclear":false},"16":{"family_comment":"","value":"","family_unclear":false,"family":"","comment":""},"17":{"family_comment":"","value":"","family":"","comment":""},"18":{"family_comment":"","family_hidden":false,"value":"","family":"","comment":""},"19":{"family_comment":"","value":"","family":"","comment":""},"20":{"family_comment":"","comment":"","family":"","comment_hidden":false,"comment_unclear":false,"value":"","family_comment_hidden":false}},"general":{"family":[{"inn":"","inn_unclear":false,"family_name":"Кузнецов В. В. 20. 09. 197? р","relations_hidden":false,"relations_unclear":false,"name_unclear":false,"relations":"Подружжя","inn_hidden":true,"name_hidden":false,"relations_other":""},{"inn":"","inn_unclear":false,"family_name":"Кузнецов М. В. 27. 02. 200? р","relations_other":"","relations_hidden":false,"name_unclear":false,"inn_hidden":true,"name_hidden":false,"relations":"Дитина"},{"inn":"","family_name":"Монич В. М. 11. 12. 1941 р","relations_other":"","name_unclear":false,"inn_hidden":true,"name_hidden":false,"relations":"Батьки"}],"family_raw":"","name":"Оксана","full_name_suggest":{"input":["Монич Оксана Ласлівна","Оксана Ласлівна Монич","Оксана Монич"],"output":"Монич Оксана Ласлівна"},"name_unclear":false,"patronymic":"Ласлівна","inn_hidden":false,"addresses":[{"place_city_type_hidden":true,"place_hidden":true,"place_address_unclear":false,"place":"","place_city":"","place_unclear":false,"place_city_type":"","place_city_hidden":true,"place_district":"","place_district_hidden":true,"place_address":"","place_address_hidden":true}],"inn":"","inn_unclear":false,"last_name":"Монич","full_name":"Монич Оксана Ласлівна","post":{"post_hidden":false,"office":"Загальний місцевий суд","post":"суддя ужгородського міськрайонного суду","region":"Закарпатська область","region_hidden":false,"office_unclear":false,"office_hidden":false,"post_unclear":false,"region_unclear":false},"last_name_unclear":false},"liabilities":{"54":{"sum_comment_unclear":false,"sum_comment":"","sum_hidden":false,"sum":"1000","sum_foreign_comment":"","sum_foreign":"","sum_unclear":false,"sum_comment_hidden":false},"55":{"sum_comment":"","sum_foreign_comment":"","sum_foreign":"","sum_hidden":false,"sum":""},"56":{"sum_comment":"","sum":"","sum_foreign_comment":"","sum_foreign":"","sum_unclear":false,"sum_foreign_hidden":false},"57":{"sum_comment_unclear":false,"sum_comment":"","sum_hidden":false,"sum":"","sum_foreign_comment":"","sum_foreign":"","sum_unclear":false,"sum_comment_hidden":false},"58":{"sum_comment":"","sum_hidden":false,"sum":"","sum_foreign_comment":"","sum_foreign":"","sum_unclear":false,"sum_comment_hidden":false},"59":{"sum_comment":"","sum_foreign_comment":"","sum_foreign":"","sum":""},"60":{"sum_comment_unclear":false,"sum_comment":"","sum_hidden":false,"sum":"","sum_foreign_comment":"","sum_foreign":"","sum_unclear":false,"sum_comment_hidden":false},"61":{"sum_comment":"","sum_foreign_comment":"","sum_foreign":"","sum_hidden":false,"sum":""},"62":{"sum_comment":"","sum_foreign_comment":"","sum_foreign":"","sum_unclear":false,"sum":""},"63":{"sum_comment":"","sum_hidden":false,"sum":"","sum_foreign_comment":"","sum_foreign":"","sum_unclear":false,"sum_comment_hidden":false},"64":{"sum_comment":"","sum_hidden":false,"sum":"","sum_foreign_comment":"","sum_foreign":"","sum_comment_hidden":false}},"declaration":{"notfull_lostpages":"","additional_info_text":"Згідно рішення КСУ №2-рп/2012р. від 20. 01. 2012р. члени сім'ї відмовились дати відомості","additional_info":"1","date":"2015-03-27T00:00:00","notfull":"","url":"http://static.declarations.com.ua/declarations/chosen_ones/mega_batch/monych_oksana_vasylivna.pdf"},"intro":{"isnotdeclaration":"","declaration_year":"2014"}}]