[{"id":"vulyk_84_30","ft_src":"Toyota Land Cruiser 120\n2694 куб. см.\n2004\nДніпропетровська область\nДніпропетровськ\n76.4\nДніпропетровська область\nв порядку приватизації\nДніпропетровськ\n62.3\n2014\n73076.35\n195698.04\nбонус на картку\n100\n12180\n73076.35\n207978.04\n2694 куб. см.\nToyota Land Cruiser 120\n2004\n2014\nМовчан Дмитро Валентинович\nДмитро Валентинович Мовчан\nДмитро Мовчан\nМовчан Дмитро Валентинович\nДмитро\nПодружжя\nМовчан Дмитро Валентинович\nВалентинович\nсуддя ленінського районного суду м. дніпропетровська\nЗагальний місцевий суд\nДніпропетровська область\nМовчан\nДніпропетровськ\nДніпропетровська область\n18226.02\n25000\n990\n24100\n3702.85\n33325.98\n195698.04\n73076.35\n207978.04\n73076.35\n12180\n100\nбонус на картку\nДніпропетровськ\nДніпропетровська область\n76.4\n62.3\nв порядку приватизації\nДніпропетровськ\nДніпропетровська область\n25000\n18226.02\n24100\n3702.85\n990\n33325.98\nПодружжя\nВалентинович\nМовчан\nДмитро\nМовчан Дмитро Валентинович\nДмитро Валентинович Мовчан\nДмитро Мовчан\nМовчан Дмитро Валентинович\nДніпропетровська область\nДніпропетровськ\nДніпропетровська область\nсуддя ленінського районного суду м. дніпропетровська\nЗагальний місцевий суд\nМовчан Дмитро Валентинович","estate":{"31":[{"costs_property_comment":"","address":"Дніпропетровськ","space_units":"м²","space_unclear":false,"region_hidden":false,"costs_property":"","space_comment":"","address_hidden":true,"address_unclear":false,"costs_rent_comment":"","space":"76.4","region":"Дніпропетровська область","costs_rent":""},{"costs_property_comment":"","address_unclear":false,"address":"Дніпропетровськ","space_units":"м²","costs_rent_comment":"","space":"62.3","region":"Дніпропетровська область","costs_property":"","space_comment":"в порядку приватизації","costs_rent":""}]},"vehicle":{"35":[{"year_hidden":false,"brand_info":"2694 куб. см.","sum_rent_comment":"","brand_unclear":false,"brand_hidden":false,"year":"2004","brand":"Toyota Land Cruiser 120","brand_info_hidden":false,"sum_rent":"","year_unclear":false,"sum_comment":"","sum_hidden":false,"brand_info_unclear":false,"sum":""}]},"source":"VULYK","income":{"5":{"family_comment":"","family":"73076.35","comment":"","value_unclear":false,"family_unclear":false,"comment_unclear":false,"value":"207978.04"},"6":{"family_comment":"","comment_unclear":false,"value":"195698.04","family":"73076.35","comment":""},"7":{"family":"","family_comment":"","value":"","comment":"","source_name":""},"8":{"family_comment":"","value":"","family":"","comment":""},"9":{"family_comment":"","value":"","family":"","comment":"","value_unclear":false},"10":{"family_comment":"","value":"12180","family":"","comment":"","value_unclear":false},"11":{"family_comment":"","value":"100","family":"","comment":"бонус на картку"},"12":{"family_comment":"","value":"","family":"","comment":""},"13":{"family_comment":"","value":"","family":"","comment":""},"14":{"family_comment":"","value":"","family":"","comment":""},"15":{"family_comment":"","value":"","family":"","comment":""},"16":{"family_comment":"","value":"","family":"","comment":""},"17":{"family_comment":"","value":"","family":"","comment":"","value_unclear":false},"18":{"family_comment":"","value":"","family":"","comment":"","value_unclear":false},"19":{"family_comment":"","value":"","family":"","comment":""},"20":{"family_comment":"","family":"","comment":"","value_unclear":false,"family_unclear":false,"comment_unclear":false,"value":""}},"general":{"family_raw":"","name":"Дмитро","full_name_suggest":{"input":["Мовчан Дмитро Валентинович","Дмитро Валентинович Мовчан","Дмитро Мовчан"],"output":"Мовчан Дмитро Валентинович"},"patronymic":"Валентинович","inn_hidden":true,"addresses":[{"place_city_type_hidden":false,"place_district_hidden":false,"place_address_unclear":false,"place":"Дніпропетровська область","place_city":"Дніпропетровськ","place_unclear":false,"place_city_type_unclear":false,"place_city_type":"Місто","place_city_hidden":false,"place_city_unclear":false,"place_district":"","place_district_unclear":false,"place_address":"","place_address_hidden":true,"place_hidden":false}],"inn":"","inn_unclear":false,"last_name":"Мовчан","full_name":"Мовчан Дмитро Валентинович","family":[{"inn":"","inn_unclear":false,"family_name":"","relations_other":"","relations_hidden":false,"name_unclear":false,"inn_hidden":true,"name_hidden":true,"relations":"Подружжя"}],"post":{"post_hidden":false,"office":"Загальний місцевий суд","region_hidden":false,"post":"суддя ленінського районного суду м. дніпропетровська","candidate":"","region_unclear":false,"region":"Дніпропетровська область","office_hidden":false,"post_unclear":false,"office_unclear":false}},"liabilities":{"54":{"sum_comment":"","sum_foreign_comment":"","sum_foreign":"","sum":"","sum_comment_hidden":false},"55":{"sum_comment":"","sum_foreign_comment":"","sum_foreign":"","sum":""},"56":{"sum_comment":"","sum_foreign_comment":"","sum_foreign":"","sum":"24100"},"57":{"sum_comment":"","sum_foreign_comment":"","sum_foreign":"","sum":"25000","sum_comment_hidden":false},"58":{"sum_comment":"","sum_foreign_comment":"","sum_foreign":"","sum":"","sum_comment_hidden":false},"59":{"sum_comment":"","sum_foreign_comment":"","sum_foreign":"","sum":""},"60":{"sum_comment":"","sum_foreign_comment":"","sum_foreign":"","sum":"990"},"61":{"sum_comment":"","sum_foreign_comment":"","sum_foreign":"","sum":""},"62":{"sum_comment":"","sum_foreign_comment":"","sum_foreign":"","sum":"3702.85"},"63":{"sum_comment":"","sum_foreign_comment":"","sum_foreign":"","sum":"33325.98","sum_comment_hidden":false},"64":{"sum_comment":"","sum_foreign_comment":"","sum_foreign":"","sum":"18226.02","sum_comment_hidden":false}},"declaration":{"notfull_lostpages":"","additional_info_text":"","additional_info":"","date":"2015-03-27T00:00:00","notfull":"","url":"http://static.declarations.com.ua/declarations/chosen_ones/judges_batch/2444_movchan_dmytro_valentynovych.pdf"},"intro":{"isnotdeclaration":"","declaration_year_unclear":false,"declaration_year":"2014"}}]