[{"id":"vulyk_108_154","ft_src":"Дніпропетровська область\nм. Дніпропетровськ\n16\nм. Добропілля\n45000\n64.8\nДонецька область\n2015\n126718\n102626\n122\n300\n26996\n127140\n129622\n16\nДніпропетровська область\nм. Дніпропетровськ\n45000\n64.8\nм. Добропілля\nДонецька область\nНаумова Ольга Сергіївна\nОльга Сергіївна Наумова\nОльга Наумова\nНаумова Ольга Сергіївна\nОльга\nПодружжя\nЧернов А. О\nДитина\nЧернова С. А\nНаумова Ольга Сергіївна\nСергіївна\nЗагальний місцевий суд\nДніпропетровська область\nсуддя жовтневого районного суду м. дніпропетровська\nНаумова\nДніпропетровськ\nДніпропетровська область\n102626\n126718\n129622\n127140\n26996\n300\n122\n2015\nПодружжя\nЧернов А. О\nДитина\nЧернова С. А\nСергіївна\nНаумова\nОльга\nНаумова Ольга Сергіївна\nОльга Сергіївна Наумова\nОльга Наумова\nНаумова Ольга Сергіївна\nДніпропетровська область\nДніпропетровськ\nДніпропетровська область\nсуддя жовтневого районного суду м. дніпропетровська\nЗагальний місцевий суд\nНаумова Ольга Сергіївна","estate":{"25":[{"address":"м. Добропілля","space_units":"м²","costs_comment":"","space_unclear":false,"region_hidden":false,"space_units_unclear":false,"space_comment":"","address_hidden":true,"costs":"45000","space_comment_unclear":false,"costs_rent_comment":"","space":"64.8","region":"Донецька область","costs_rent":""}],"34":[{"costs_property_comment":"","address":"м. Дніпропетровськ","space_units":"м²","costs_rent_comment":"","space":"16","region":"Дніпропетровська область","region_hidden":false,"costs_property":"","space_comment":"","address_hidden":true,"costs_rent":""}]},"source":"VULYK","income":{"5":{"family_comment":"","family":"127140","comment":"","value_unclear":false,"family_unclear":false,"value":"129622"},"6":{"family_comment":"","value":"102626","family_unclear":false,"family":"126718","comment":""},"7":{"family_comment":"","comment":"","family":"","source_name_unclear":false,"value":"","source_name":""},"8":{"family_comment":"","value":"","family":"","comment":""},"9":{"family_comment":"","family":"","comment":"","family_unclear":false,"comment_hidden":false,"value":"","family_comment_hidden":false},"10":{"family_comment":"","value":"26996","family":"300","comment":""},"11":{"family_comment":"","value":"","family":"122","comment":""},"12":{"family_comment":"","value":"","family":"","comment":""},"13":{"family_comment":"","value":"","family":"","comment":""},"14":{"family_comment":"","value":"","family":"","comment":""},"15":{"family_comment":"","value":"","family":"","comment":""},"16":{"family_comment":"","value":"","family":"","comment":""},"17":{"family_comment":"","value":"","family":"","comment":""},"18":{"family_comment":"","value":"","family":"","comment":""},"19":{"family_comment":"","value":"","family":"","comment":""},"20":{"family_comment":"","comment":"","family":"","value_unclear":false,"comment_hidden":false,"comment_unclear":false,"value":""}},"general":{"family_raw":"","name":"Ольга","full_name_suggest":{"input":["Наумова Ольга Сергіївна","Ольга Сергіївна Наумова","Ольга Наумова"],"output":"Наумова Ольга Сергіївна"},"patronymic":"Сергіївна","inn_hidden":true,"addresses":[{"place_city_type_hidden":false,"place_hidden":false,"place_address_unclear":false,"place":"Дніпропетровська область","place_city":"Дніпропетровськ","place_unclear":false,"place_city_type":"Місто","place_city_hidden":false,"place_district":"","place_district_hidden":false,"place_address":"","place_address_hidden":true}],"inn":"","inn_unclear":false,"last_name":"Наумова","full_name":"Наумова Ольга Сергіївна","family":[{"inn":"","inn_unclear":false,"family_name":"Чернов А. О","relations_hidden":false,"name_unclear":false,"relations":"Подружжя","inn_hidden":true,"name_hidden":true,"relations_other":""},{"inn":"","family_name":"Чернова С. А","relations_other":"","name_unclear":false,"inn_hidden":false,"name_hidden":false,"relations":"Дитина"}],"post":{"office":"Загальний місцевий суд","post":"суддя жовтневого районного суду м. дніпропетровська","office_unclear":false,"office_hidden":false,"region":"Дніпропетровська область","post_unclear":false}},"liabilities":{"54":{"sum_comment":"","sum_foreign_comment":"","sum_foreign":"","sum_hidden":false,"sum":""},"55":{"sum_comment":"","sum_foreign_comment":"","sum_foreign":"","sum":""},"56":{"sum_comment":"","sum_foreign_comment":"","sum_foreign":"","sum_unclear":false,"sum":""},"57":{"sum_comment":"","sum_hidden":false,"sum":"","sum_foreign_comment":"","sum_foreign":"","sum_comment_hidden":false},"58":{"sum_comment":"","sum_foreign_comment":"","sum_foreign":"","sum":"","sum_comment_hidden":false},"59":{"sum_comment":"","sum_foreign_comment":"","sum_foreign":"","sum_unclear":false,"sum":""},"60":{"sum_comment":"","sum_foreign_comment":"","sum_foreign":"","sum":"","sum_comment_hidden":false},"61":{"sum_comment":"","sum_foreign_comment":"","sum_foreign":"","sum":"","sum_comment_hidden":false},"62":{"sum_comment":"","sum_foreign_comment":"","sum_foreign":"","sum":""},"63":{"sum_comment":"","sum_hidden":false,"sum":"","sum_foreign_comment":"","sum_foreign":"","sum_unclear":false,"sum_comment_hidden":false},"64":{"sum_comment":"","sum":"","sum_foreign_comment":"","sum_foreign":"","sum_unclear":false,"sum_comment_hidden":false}},"declaration":{"notfull_lostpages":"","additional_info_text":"","additional_info":"","date":"2016-03-25T00:00:00","notfull":"","url":"http://static.declarations.com.ua/declarations/chosen_ones/judges_batch/2453_naumova_olha_serhiivna_2015.pdf"},"intro":{"declaration_year_hidden":false,"isnotdeclaration":"","declaration_year":"2015"}},{"id":"vulyk_75_2","ft_src":"Дніпропетровська область\n49005\n16\nДонецька область\n85000, Донецкая обл.\n64.8\n45000\nДонецька область\n7450\n83003 м. Донецьк\n67.2\n2014\n96156\n118296\n12180\n96156\n130476\n2014\nНаумова\nСергіївна\nДніпропетровська область\nДніпропетровськ\nПодружжя\nЧернов А. О\nНаумова Ольга Сергіївна\nОльга Сергіївна Наумова\nОльга Наумова\nНаумова Ольга Сергіївна\nОльга\nНаумова Ольга Сергіївна\nЗагальний місцевий суд\nсуддя жовтневого районного суду м. дніпропетровська\nДніпропетровська область\n118296\n96156\n130476\n96156\n12180\n16\n49005\nДніпропетровська область\n45000\n64.8\nДонецька область\n85000, Донецкая обл.\n7450\n67.2\nДонецька область\n83003 м. Донецьк\nЧернов А. О\nПодружжя\nНаумова\nСергіївна\nДніпропетровська область\nДніпропетровськ\nсуддя жовтневого районного суду м. дніпропетровська\nДніпропетровська область\nЗагальний місцевий суд\nНаумова Ольга Сергіївна\nНаумова Ольга Сергіївна\nОльга Сергіївна Наумова\nОльга Наумова\nНаумова Ольга Сергіївна\nОльга","estate":{"25":[{"address":"85000, Донецкая обл.","space_units":"м²","space_hidden":false,"space_unclear":false,"region_hidden":false,"costs_comment":"","space_comment":"","address_hidden":true,"space":"64.8","costs_rent_comment":"","costs":"45000","region":"Донецька область","costs_rent":""},{"costs":"","address":"83003 м. Донецьк","space_units":"м²","costs_rent_comment":"","space":"67.2","space_unclear":false,"region_hidden":false,"costs_comment":"","space_comment":"","region":"Донецька область","costs_rent":"7450"}],"34":[{"costs_property_comment":"","address":"49005","space_units":"м²","costs_rent_comment":"","space":"16","region":"Дніпропетровська область","region_hidden":false,"costs_property":"","space_comment":"","address_hidden":true,"costs_rent":""}]},"source":"VULYK","income":{"5":{"family_comment":"","value":"130476","family":"96156","comment":""},"6":{"family_comment":"","family_hidden":false,"value":"118296","family":"96156","comment":""},"7":{"family":"","family_comment":"","value":"","comment":"","source_name":""},"8":{"family_comment":"","value":"","family":"","comment":""},"9":{"family_comment":"","family":"","comment":"","value_unclear":false,"family_hidden":false,"value":""},"10":{"family":"","family_comment":"","comment":"","value_hidden":false,"value":"12180","family_hidden":false,"family_unclear":false},"11":{"family_comment":"","value":"","family":"","comment":""},"12":{"family_comment":"","value":"","family":"","comment":""},"13":{"family_comment":"","value":"","family":"","comment":""},"14":{"family_comment":"","value":"","family":"","comment":""},"15":{"family_comment":"","value":"","family":"","comment":""},"16":{"family_comment":"","value":"","family":"","comment":""},"17":{"family_comment":"","value":"","family":"","comment":""},"18":{"family_comment":"","value":"","family":"","comment":""},"19":{"family_comment":"","value":"","family":"","comment":""},"20":{"family_comment":"","comment":"","family":"","comment_unclear":false,"value":"","family_comment_unclear":false}},"general":{"inn":"","addresses":[{"place_city_type_hidden":false,"place_city_type":"Місто","place_city_hidden":false,"place_hidden":false,"place_district":"","place_district_hidden":false,"place":"Дніпропетровська область","place_city":"Дніпропетровськ","place_address_hidden":true,"place_address":""}],"last_name":"Наумова","full_name":"Наумова Ольга Сергіївна","family":[{"inn":"","family_name":"Чернов А. О","relations_other":"","relations_hidden":false,"name_unclear":true,"inn_hidden":true,"name_hidden":false,"relations":"Подружжя"}],"patronymic":"Сергіївна","inn_hidden":true,"name":"Ольга","post":{"office":"Загальний місцевий суд","region":"Дніпропетровська область","post":"суддя жовтневого районного суду м. дніпропетровська"},"family_raw":"","full_name_suggest":{"input":["Наумова Ольга Сергіївна","Ольга Сергіївна Наумова","Ольга Наумова"],"output":"Наумова Ольга Сергіївна"}},"liabilities":{"54":{"sum_comment":"","sum_foreign_comment":"","sum_foreign":"","sum":""},"55":{"sum_comment":"","sum_foreign_comment":"","sum_foreign":"","sum":""},"56":{"sum_comment":"","sum_foreign_comment":"","sum_foreign":"","sum":""},"57":{"sum_comment":"","sum_foreign_comment":"","sum_foreign":"","sum":""},"58":{"sum_comment":"","sum_foreign_comment":"","sum_foreign":"","sum":""},"59":{"sum_comment_unclear":false,"sum_comment":"","sum":"","sum_foreign_comment":"","sum_foreign":"","sum_unclear":false},"60":{"sum_comment":"","sum_foreign_comment":"","sum_foreign":"","sum":""},"61":{"sum_comment":"","sum_foreign_comment":"","sum_foreign":"","sum":""},"62":{"sum_comment":"","sum_foreign_comment":"","sum_foreign":"","sum_unclear":false,"sum":""},"63":{"sum_comment":"","sum_foreign_comment":"","sum_foreign":"","sum":""},"64":{"sum_comment":"","sum_foreign_comment":"","sum_foreign":"","sum":""}},"declaration":{"notfull_lostpages":"","additional_info_text":"","additional_info":"","date":"2015-03-30T00:00:00","notfull":"","url":"http://static.declarations.com.ua/declarations/chosen_ones/judges_batch/1933_naumova_olha_serhiivna.pdf"},"intro":{"isnotdeclaration":"","declaration_year":"2014"}}]