[{"id":"vulyk_96_27","ft_src":"2010\n1596 куб. см. 102 кВт 420 см\nVolkswagen Golf - 6\n1000\nНа території Рокитнянської селищної ради під садівництво\nКиївська область\nсмт Рокитне, вул. Першотравнева, 16\n24\nКиївська область\nКіровоградська область\nс. Семидуби, Голованівського району\n4700\nКиївська область\nм. Біла Церква,, б. 71-б, кв. 59\n22.9\nКиївська область\nм. Біла Церква, бул. Комсомольський, 15 кв. 156\n71\nсмт Рокитне, вул. Першотравнева, 16 кв. 8\n72\nКиївська область\n2015\n224002\n22276\n250546\n7000\n15276\n26544\nVolkswagen Golf - 6\n1596 куб. см. 102 кВт 420 см\n2010\n2015\nНечепоренко Леонід Михайлович\nЛеонід Михайлович Нечепоренко\nЛеонід Нечепоренко\nНечепоренко Леонід Михайлович\nНечепоренко Леонід Михайлович\n1999915993\nЛеонід\nНечепоренко\nКиївська область\nсуддя рокитнянського районного суду київської області\nЗагальний місцевий суд\nМихайлович\nСМТ\n09600, вул. Першотравнева, 16 кв. 8\nКиївська область\nРокитне\nПодружжя\nНечипоренко З. І. 03. 03. 1957\n2088108024\n224002\n26544\n15276\n250546\n22276\n7000\n1000\nКиївська область\nНа території Рокитнянської селищної ради під садівництво\nс. Семидуби, Голованівського району\n4700\nКіровоградська область\n24\nсмт Рокитне, вул. Першотравнева, 16\nКиївська область\nм. Біла Церква,, б. 71-б, кв. 59\nКиївська область\n22.9\n71\nм. Біла Церква, бул. Комсомольський, 15 кв. 156\nКиївська область\n72\nсмт Рокитне, вул. Першотравнева, 16 кв. 8\nКиївська область\n2088108024\nНечипоренко З. І. 03. 03. 1957\nПодружжя\n1999915993\nЛеонід\nМихайлович\nНечепоренко\nНечепоренко Леонід Михайлович\nЛеонід Михайлович Нечепоренко\nЛеонід Нечепоренко\nНечепоренко Леонід Михайлович\nСМТ\nКиївська область\nРокитне\n09600, вул. Першотравнева, 16 кв. 8\nсуддя рокитнянського районного суду київської області\nКиївська область\nЗагальний місцевий суд\nНечепоренко Леонід Михайлович","estate":{"23":[{"address":"На території Рокитнянської селищної ради під садівництво","space_units":"м²","costs_rent_unclear":false,"space_hidden":false,"space_unclear":false,"region_hidden":false,"space_units_unclear":false,"costs_comment":"","space_comment_unclear":false,"space":"1000","address_unclear":true,"space_comment":"","address_hidden":false,"costs_rent_comment":"","costs":"","region_unclear":false,"region":"Київська область","costs_rent":""}],"25":[{"costs":"","costs_unclear":false,"address":"смт Рокитне, вул. Першотравнева, 16 кв. 8","space_units":"м²","space_hidden":false,"space_comment":"","region_hidden":false,"costs_comment":"","space_comment_unclear":false,"space_comment_hidden":false,"space_unclear":false,"address_unclear":false,"address_hidden":false,"costs_rent_comment":"","space":"72","costs_rent":"","region":"Київська область","costs_rent_comment_unclear":false}],"27":[{"address":"смт Рокитне, вул. Першотравнева, 16","space_units":"м²","costs_comment":"","space_unclear":false,"region_hidden":false,"space_comment":"","address_hidden":false,"costs":"","costs_rent_comment":"","space":"24","region":"Київська область","costs_rent":""}],"29":[{"costs_property_comment":"","address":"с. Семидуби, Голованівського району","space_units":"м²","space_unclear":false,"region_hidden":false,"costs_property":"","space_comment":"","address_hidden":false,"address_unclear":false,"costs_rent_comment":"","space":"4700","region_unclear":false,"region":"Кіровоградська область","costs_rent":""}],"31":[{"costs_property_comment":"","address":"м. Біла Церква,, б. 71-б, кв. 59","space_units":"м²","space_hidden":false,"space_unclear":false,"region_hidden":false,"costs_property":"","space_comment":"","address_hidden":false,"address_unclear":true,"costs_rent_comment":"","space":"22.9","region":"Київська область","costs_rent":""},{"costs_property_comment":"","address_unclear":true,"address":"м. Біла Церква, бул. Комсомольський, 15 кв. 156","space_units":"м²","costs_rent_comment":"","space":"71","region":"Київська область","region_hidden":false,"costs_property":"","space_comment":"","costs_rent":""}]},"vehicle":{"40":[{"sum_comment":"","brand_info_hidden":false,"brand_info":"1596 куб. см. 102 кВт 420 см","sum":"","sum_rent_comment":"","year":"2010","brand":"Volkswagen Golf - 6","sum_rent":"","year_unclear":false}]},"source":"VULYK","income":{"5":{"family_comment":"","value":"250546","family_unclear":false,"family":"22276","comment":""},"6":{"family_comment":"","family":"","comment":"","value_unclear":false,"family_unclear":false,"value":"224002"},"7":{"source_name_hidden":false,"family_comment":"","family":"","comment":"","value_unclear":false,"family_unclear":false,"value":"","source_name":""},"8":{"family_comment":"","value":"","family":"","comment":""},"9":{"family_comment":"","value":"","family":"","comment":""},"10":{"family_comment":"","value":"","family":"","comment":"","value_unclear":false},"11":{"family_comment":"","value":"","family":"","comment":""},"12":{"family_comment":"","value":"","family":"","comment":""},"13":{"family_comment":"","value":"","family":"","comment":""},"14":{"family_comment":"","value":"","family":"","comment":""},"15":{"family_comment":"","value":"","family":"","comment":""},"16":{"family_comment":"","value":"","family":"","comment":""},"17":{"family_comment":"","value":"","family":"","comment":""},"18":{"family_comment":"","value":"","family":"","comment":""},"19":{"family_comment":"","value":"","family":"7000","comment":""},"20":{"family_comment":"","comment":"","family":"15276","value_unclear":false,"comment_hidden":false,"comment_unclear":false,"value":"26544"}},"general":{"family":[{"inn":"2088108024","inn_unclear":true,"family_name":"Нечипоренко З. І. 03. 03. 1957","relations_other":"","relations_hidden":false,"name_unclear":false,"inn_hidden":false,"name_hidden":false,"relations":"Подружжя"}],"family_raw":"","name":"Леонід","full_name_suggest":{"input":["Нечепоренко Леонід Михайлович","Леонід Михайлович Нечепоренко","Леонід Нечепоренко"],"output":"Нечепоренко Леонід Михайлович"},"patronymic":"Михайлович","inn_hidden":true,"patronymic_hidden":false,"inn":"1999915993","addresses":[{"place_city_type_hidden":false,"place_city_type":"СМТ","place_city_hidden":false,"place_hidden":true,"place_district":"","place_district_hidden":false,"place":"Київська область","place_address":"09600, вул. Першотравнева, 16 кв. 8","place_address_hidden":false,"place_city":"Рокитне"}],"last_name":"Нечепоренко","full_name":"Нечепоренко Леонід Михайлович","post":{"office_unclear":false,"post":"суддя рокитнянського районного суду київської області","region":"Київська область","office":"Загальний місцевий суд"}},"liabilities":{"54":{"sum_comment":"","sum_hidden":false,"sum":"","sum_foreign_comment":"","sum_foreign":"","sum_comment_hidden":false},"55":{"sum_comment":"","sum_foreign_comment":"","sum_foreign":"","sum":""},"56":{"sum_comment":"","sum_foreign_comment":"","sum_foreign":"","sum_unclear":false,"sum":""},"57":{"sum_comment":"","sum_foreign_comment":"","sum_foreign":"","sum":"","sum_comment_hidden":false},"58":{"sum_comment":"","sum":"","sum_foreign_comment":"","sum_foreign":"","sum_unclear":false,"sum_comment_hidden":false},"59":{"sum_comment":"","sum_foreign_comment":"","sum_foreign":"","sum":""},"60":{"sum_comment":"","sum_foreign_comment":"","sum_foreign":"","sum":"","sum_comment_hidden":false},"61":{"sum_comment":"","sum_foreign_comment":"","sum_foreign":"","sum":""},"62":{"sum_comment":"","sum_foreign_comment":"","sum_foreign":"","sum":""},"63":{"sum_comment":"","sum_foreign_comment":"","sum_foreign":"","sum":"","sum_comment_hidden":false},"64":{"sum_comment":"","sum_foreign_comment":"","sum_foreign":"","sum":"","sum_comment_hidden":false}},"declaration":{"notfull_lostpages":"","additional_info_text":"","additional_info":"","date":"2016-03-16T00:00:00","notfull":"","url":"http://static.declarations.com.ua/declarations/chosen_ones/judges_batch/241_necheporenko_leonid_mykhailovych_2015.pdf"},"intro":{"isnotdeclaration":"","declaration_year":"2015"}},{"id":"vulyk_100_48","ft_src":"2010\n1596 куб. см., 102 /5600, 420 см\nVolkswagen Golf 6\nпід садівництво\nНа території Рокитнянської селищної ради під садивництво\n1000\nКиївська область\nсмт Рокитне, вул. Першотравнева, 16\n24\nКиївська область\nКіровоградська область\nс. Семидуби Голованівського району\n4700\nКиївська область\nм. Біла Церква, вул. Фастівська, 21б кв. 69\n22.9\nКиївська область\nм. Біла Церква, бул. Комсомольський, 15 кв. 156\n71\nсмт Рокитне, вул. Першотравнева, 16, кв. 8\n72\nКиївська область\n2014\n20426\n252559\n38971\n366439\n4000\n14545\n113880\nVolkswagen Golf 6\n1596 куб. см., 102 /5600, 420 см\n2010\n1000\nпід садівництво\nКиївська область\nНа території Рокитнянської селищної ради під садивництво\nс. Семидуби Голованівського району\n4700\nКіровоградська область\n24\nКиївська область\nсмт Рокитне, вул. Першотравнева, 16\n22.9\nКиївська область\nм. Біла Церква, вул. Фастівська, 21б кв. 69\nм. Біла Церква, бул. Комсомольський, 15 кв. 156\n71\nКиївська область\n72\nКиївська область\nсмт Рокитне, вул. Першотравнева, 16, кв. 8\nПодружжя\nНечепоренко З. І. 03. 03. 1957\n2088108024\nМихайлович\nКиївська область\n09600, вул. Першотравнева, 16 кв. 8\nСМТ\nРокитне\nНечепоренко\nНечепоренко Леонід Михайлович\nЛеонід Михайлович Нечепоренко\nЛеонід Нечепоренко\nНечепоренко Леонід Михайлович\nНечепоренко Леонід Михайлович\n1999915993\nЛеонід\nЗагальний місцевий суд\nКиївська область\nзаступник голови рокитнянського районного суду київської області\n252559\n20426\n113880\n14545\n366439\n38971\n4000\n2014\n2088108024\nНечепоренко З. І. 03. 03. 1957\nПодружжя\n1999915993\nСМТ\n09600, вул. Першотравнева, 16 кв. 8\nРокитне\nКиївська область\nМихайлович\nНечепоренко\nКиївська область\nЗагальний місцевий суд\nзаступник голови рокитнянського районного суду київської області\nНечепоренко Леонід Михайлович\nНечепоренко Леонід Михайлович\nЛеонід Михайлович Нечепоренко\nЛеонід Нечепоренко\nНечепоренко Леонід Михайлович\nЛеонід","estate":{"23":[{"address":"На території Рокитнянської селищної ради під садивництво","space_units":"м²","costs_comment":"","space_unclear":false,"region_hidden":false,"space_comment":"під садівництво","address_hidden":false,"costs":"","address_unclear":false,"space_comment_unclear":false,"costs_comment_unclear":false,"costs_rent_comment":"","space":"1000","region":"Київська область","costs_rent":""}],"25":[{"address":"смт Рокитне, вул. Першотравнева, 16, кв. 8","space_units":"м²","costs_comment":"","space_unclear":false,"region_hidden":false,"space_comment":"","address_hidden":false,"costs":"","address_unclear":false,"space_comment_unclear":false,"costs_comment_unclear":false,"costs_rent_comment":"","space":"72","region":"Київська область","costs_rent":""}],"27":[{"address":"смт Рокитне, вул. Першотравнева, 16","space_units":"м²","costs_comment":"","space_unclear":false,"region_hidden":false,"space_comment":"","address_hidden":false,"costs":"","address_unclear":false,"costs_rent_comment":"","space":"24","region":"Київська область","costs_rent":""}],"29":[{"costs_property_comment":"","address":"с. Семидуби Голованівського району","space_units":"м²","space_unclear":false,"region_hidden":false,"costs_property":"","space_comment":"","address_hidden":false,"address_unclear":false,"costs_rent_comment":"","space":"4700","region_unclear":false,"region":"Кіровоградська область","costs_rent":""}],"31":[{"costs_property_comment":"","address":"м. Біла Церква, вул. Фастівська, 21б кв. 69","space_units":"м²","space_unclear":false,"region_hidden":false,"costs_property":"","space_comment":"","address_hidden":false,"address_unclear":true,"space_comment_unclear":false,"costs_rent_comment":"","space":"22.9","costs_property_comment_unclear":false,"region_unclear":false,"region":"Київська область","costs_rent":""},{"costs_property_comment":"","address":"м. Біла Церква, бул. Комсомольський, 15 кв. 156","space_units":"м²","costs_rent_comment":"","space":"71","region":"Київська область","region_hidden":false,"costs_property":"","space_comment":"","region_unclear":false,"costs_rent":""}]},"vehicle":{"40":[{"sum_comment":"","brand_info_hidden":false,"brand_info":"1596 куб. см., 102 /5600, 420 см","sum":"","sum_rent_comment":"","year":"2010","brand":"Volkswagen Golf 6","sum_rent":"","brand_info_unclear":false}]},"source":"VULYK","income":{"5":{"family_comment":"","family":"38971","comment":"","value_unclear":false,"family_unclear":false,"value":"366439"},"6":{"family_comment":"","value":"252559","family":"20426","comment":"","value_unclear":false},"7":{"family_comment":"","comment":"","family":"","value_unclear":false,"value":"","source_name":""},"8":{"family_comment":"","value":"","family":"","comment":""},"9":{"family_comment":"","family":"","comment":"","value_unclear":false,"family_unclear":false,"value":""},"10":{"family_comment":"","comment_unclear":false,"value":"","family":"","comment":""},"11":{"family_comment":"","value":"","family":"","comment":""},"12":{"family_comment":"","value":"","family":"","comment":""},"13":{"family_comment":"","value":"","family":"","comment":"","value_unclear":false},"14":{"family_comment":"","value":"","family":"","comment":""},"15":{"family_comment":"","value":"","family":"","comment":""},"16":{"family_comment":"","value":"","family_unclear":false,"family":"","comment":""},"17":{"family_comment":"","value":"","family_unclear":false,"family":"","comment":""},"18":{"family_comment":"","value":"","family":"","comment":""},"19":{"family_comment":"","value":"","family":"4000","comment":""},"20":{"family":"14545","family_comment":"","comment":"","value_hidden":false,"value_unclear":false,"value":"113880","comment_unclear":false,"family_unclear":false,"family_hidden":false}},"general":{"inn":"1999915993","addresses":[{"place_city_type":"СМТ","place_city_type_hidden":false,"place_hidden":false,"place_city_hidden":false,"place_district_hidden":false,"place_district":"","place_city_unclear":false,"place":"Київська область","place_city":"Рокитне","place_address_hidden":false,"place_address":"09600, вул. Першотравнева, 16 кв. 8"}],"last_name":"Нечепоренко","full_name":"Нечепоренко Леонід Михайлович","family":[{"inn":"2088108024","family_name":"Нечепоренко З. І. 03. 03. 1957","name_unclear":false,"inn_hidden":false,"name_hidden":false,"relations":"Подружжя"}],"patronymic":"Михайлович","inn_hidden":false,"name":"Леонід","post":{"post_hidden":false,"office":"Загальний місцевий суд","post":"заступник голови рокитнянського районного суду київської області","office_unclear":false,"region_unclear":false,"region":"Київська область","post_unclear":false},"family_raw":"","full_name_suggest":{"input":["Нечепоренко Леонід Михайлович","Леонід Михайлович Нечепоренко","Леонід Нечепоренко"],"output":"Нечепоренко Леонід Михайлович"}},"liabilities":{"54":{"sum_comment":"","sum":"","sum_foreign_comment":"","sum_foreign":"","sum_unclear":false,"sum_comment_hidden":false},"55":{"sum_comment":"","sum_foreign_comment":"","sum_foreign":"","sum":""},"56":{"sum_comment":"","sum_foreign_comment":"","sum_foreign":"","sum_unclear":false,"sum":""},"57":{"sum_comment_unclear":false,"sum_comment":"","sum":"","sum_foreign_comment":"","sum_foreign":"","sum_unclear":false,"sum_comment_hidden":false},"58":{"sum_comment":"","sum":"","sum_foreign_comment":"","sum_foreign":"","sum_unclear":false,"sum_comment_hidden":false},"59":{"sum_comment":"","sum_foreign_comment":"","sum_foreign":"","sum":""},"60":{"sum_comment":"","sum_foreign_comment":"","sum_foreign":"","sum":"","sum_comment_hidden":false},"61":{"sum_comment":"","sum_foreign_comment":"","sum_foreign":"","sum":""},"62":{"sum_comment":"","sum_foreign_comment":"","sum_foreign":"","sum_unclear":false,"sum":""},"63":{"sum_comment":"","sum_foreign_comment":"","sum_foreign":"","sum":"","sum_comment_hidden":false},"64":{"sum_comment":"","sum_foreign_comment":"","sum_foreign":"","sum":"","sum_comment_hidden":false}},"declaration":{"notfull_lostpages":"","additional_info_text":"","additional_info":"","date":"2015-03-26T00:00:00","notfull":"","url":"http://static.declarations.com.ua/declarations/chosen_ones/judges_batch/4216_necheporenko_leonid_mykhailovych.pdf"},"intro":{"declaration_year":"2014"}}]