[{"id":"vulyk_97_86","ft_src":"BMW X5\n2979 куб. см.\n2012\n2.4 , 2354 куб. см.\n2007\nHonda Accord\nОбухівський р-н, с. Романків\nКиївська область\n257\nОбухівський р-н, с. Романків\nКиївська область\n1093\n109\nм. Київ\nм. Київ\n884.05\n266400\n732225.52\n884.05\n2014\n2979 куб. см.\nBMW X5\n2012\n2.4 , 2354 куб. см.\n2007\nHonda Accord\n2014\nНіколаєва Ольга Вікторівна\nОльга Вікторівна Ніколаєва\nОльга Ніколаєва\nНіколаєва Ольга Вікторівна\nОльга\nПодружжя\nСвердліченко Я. А\nДитина\nСвердліченко К. Я\nНіколаєва Ольга Вікторівна\nНіколаєва\nАдміністративний місцевий суд\nХарківська область\nсуддя харківського окружного адміністративного суду\nВікторівна\nм. Київ\n02099\nКиїв\n27836.5\n61009.59\n1269474.96\n20291.61\n22003.95\n20291.61\n1362330.17\n9841.67\n257\nКиївська область\nОбухівський р-н, с. Романків\n1093\nКиївська область\nОбухівський р-н, с. Романків\n109\nм. Київ\nм. Київ\n266400\n884.05\n732225.52\n884.05\n27836.5\n61009.59\n22003.95\n9841.67\n1362330.17\n20291.61\n1269474.96\n20291.61\nПодружжя\nСвердліченко Я. А\nСвердліченко К. Я\nДитина\nВікторівна\nНіколаєва\nОльга\nНіколаєва Ольга Вікторівна\nОльга Вікторівна Ніколаєва\nОльга Ніколаєва\nНіколаєва Ольга Вікторівна\n02099\nКиїв\nм. Київ\nХарківська область\nАдміністративний місцевий суд\nсуддя харківського окружного адміністративного суду\nНіколаєва Ольга Вікторівна","estate":{"25":[{"address":"м. Київ","space_units":"м²","space_hidden":false,"space_unclear":false,"region_hidden":false,"costs_rent_comment":"","space_comment":"","address_hidden":true,"space_comment_hidden":false,"costs":"","space_comment_unclear":false,"costs_comment":"","space":"109","region_unclear":false,"region":"м. Київ","costs_rent":""}],"29":[{"costs_property_comment":"","address":"Обухівський р-н, с. Романків","space_units":"м²","space_unclear":false,"region_hidden":false,"costs_property":"","space_comment":"","address_hidden":true,"address_unclear":false,"space_comment_unclear":false,"costs_rent_comment":"","space":"257","region_unclear":false,"region":"Київська область","costs_rent":""},{"costs_property_comment":"","address":"Обухівський р-н, с. Романків","space_units":"м²","space_comment":"","region_hidden":false,"costs_property":"","region":"Київська область","address_hidden":false,"address_unclear":false,"costs_rent_comment":"","space":"1093","costs_rent":""}]},"vehicle":{"40":[{"sum_comment":"","brand_info":"2979 куб. см.","brand_unclear":false,"sum_rent_comment":"","year":"2012","brand":"BMW X5","sum_rent":"","brand_info_unclear":false,"year_unclear":false,"sum":""},{"sum_comment":"","brand_info":"2.4 , 2354 куб. см.","sum":"","sum_rent_comment":"","year":"2007","brand":"Honda Accord","sum_rent":""}]},"source":"VULYK","income":{"5":{"family_comment":"","value":"20291.61","family":"1362330.17","comment":""},"6":{"family_comment":"","family":"61009.59","comment":"","value_unclear":false,"family_unclear":false,"comment_hidden":false,"value":""},"7":{"family":"","family_comment":"","value":"","comment":"","source_name":""},"8":{"family_comment":"","value":"","family":"","comment":""},"9":{"family_comment":"","value":"","family_unclear":false,"family":"9841.67","comment":""},"10":{"family_comment":"","value":"","family":"","comment":"","value_unclear":false},"11":{"family_comment":"","value":"","family":"","comment":""},"12":{"family_comment":"","value":"","family":"","comment":""},"13":{"family_comment":"","value":"","family":"","comment":""},"14":{"family_comment":"","value":"","family":"","comment":""},"15":{"family_comment":"","value":"","family":"22003.95","comment":""},"16":{"family_comment":"","value":"","family":"","comment":""},"17":{"family_comment":"","value":"","family":"1269474.96","comment":""},"18":{"family_comment":"","value":"","family":"","comment":""},"19":{"family_comment":"","value":"","family":"","comment":""},"20":{"family_comment":"","comment":"","family":"","value_unclear":false,"comment_unclear":false,"value":"20291.61","family_hidden":false,"family_comment_unclear":false}},"banks":{"45":[{"sum_comment_unclear":false,"sum_units":"UAH","sum_foreign_units":"UAH","sum_hidden":true,"sum":"884.05","sum_foreign_comment":"","sum_comment":"","sum_unclear":false,"sum_foreign":"","sum_comment_hidden":true}],"46":[{"sum_units":"UAH","sum_comment":"","sum_foreign_units":"UAH","sum":"884.05","sum_foreign_comment":"","sum_foreign":"","sum_comment_hidden":false}],"51":[{"sum_comment_unclear":false,"sum_units":"UAH","sum_foreign_units":"UAH","sum_hidden":false,"sum":"732225.52","sum_foreign_comment":"","sum_comment":"","sum_unclear":true,"sum_foreign":"","sum_comment_hidden":true}],"53":[{"sum_units":"UAH","sum_comment":"","sum_foreign_units":"UAH","sum":"266400","sum_foreign_comment":"","sum_foreign":"","sum_comment_hidden":true}]},"declaration":{"notfull_lostpages":"","additional_info_text":"","additional_info":"","date":"2015-11-16T00:00:00","notfull":"","url":"http://static.declarations.com.ua/declarations/chosen_ones/judges_batch/3987_nikolaieva_olha_viktorivna.pdf"},"general":{"family":[{"inn":"","family_name":"Свердліченко Я. А","relations_other":"","name_unclear":false,"inn_hidden":true,"name_hidden":true,"relations":"Подружжя"},{"inn":"","family_name":"Свердліченко К. Я","name_unclear":false,"inn_hidden":false,"name_hidden":false,"relations":"Дитина"}],"family_raw":"","name":"Ольга","full_name_suggest":{"input":["Ніколаєва Ольга Вікторівна","Ольга Вікторівна Ніколаєва","Ольга Ніколаєва"],"output":"Ніколаєва Ольга Вікторівна"},"patronymic":"Вікторівна","inn_hidden":true,"addresses":[{"place_city_type":"Місто","place_city_type_hidden":false,"place_hidden":false,"place_city_hidden":false,"place_district_hidden":false,"place_district":"","place_city_unclear":false,"place":"м. Київ","place_city":"Київ","place_address_hidden":true,"place_address":"02099"}],"last_name_hidden":false,"patronymic_hidden":false,"inn":"","inn_unclear":false,"last_name":"Ніколаєва","full_name":"Ніколаєва Ольга Вікторівна","post":{"post_hidden":false,"office":"Адміністративний місцевий суд","post":"суддя харківського окружного адміністративного суду","office_unclear":false,"region_unclear":false,"region":"Харківська область"},"name_hidden":false},"liabilities":{"54":{"sum_comment_unclear":false,"sum_comment":"","sum_hidden":false,"sum":"","sum_foreign_comment":"","sum_foreign":"","sum_unclear":false,"sum_comment_hidden":false},"55":{"sum_comment":"","sum_foreign_comment":"","sum_foreign":"","sum":""},"56":{"sum_comment":"","sum_foreign_comment":"","sum_foreign":"","sum":""},"57":{"sum_comment_unclear":false,"sum_comment":"","sum_hidden":false,"sum":"","sum_foreign_comment":"","sum_foreign":"","sum_unclear":false,"sum_comment_hidden":false},"58":{"sum_comment_unclear":false,"sum_comment":"","sum_hidden":false,"sum":"","sum_foreign_comment":"","sum_foreign":"","sum_unclear":false,"sum_comment_hidden":false},"59":{"sum_comment":"","sum_foreign_comment":"","sum_foreign":"","sum":""},"60":{"sum_comment_unclear":false,"sum_comment":"","sum_hidden":false,"sum":"27836.5","sum_foreign_comment":"","sum_foreign":"","sum_comment_hidden":false},"61":{"sum_comment":"","sum_foreign_comment":"","sum_foreign":"","sum":""},"62":{"sum_comment":"","sum_foreign_comment":"","sum_foreign":"","sum_unclear":false,"sum":""},"63":{"sum_comment":"","sum_foreign_comment":"","sum_foreign":"","sum_hidden":false,"sum":""},"64":{"sum_comment":"","sum_foreign_comment":"","sum_foreign":"","sum":""}},"intro":{"isnotdeclaration":"","declaration_year":"2014"}}]