[{"id":"vulyk_85_71","ft_src":"312\n24\n312\n2014\n35843\n204976\n36\n7342\n35928\n213729\n49\n1411\n312\n24\n312\n204976\n35843\n1411\n49\n213729\n35928\n7342\n36\nОрендовський Володимир Анатолійович\nВолодимир Анатолійович Орендовський\nВолодимир Орендовський\nОрендовський Володимир Анатолійович\nВолодимир\nПодружжя\nОрендовська О. В. 25. 05. 1991\nОрендовський Володимир Анатолійович\nОрендовський\nЗагальний місцевий суд\nсуддя новомиргородського районного суду кіровоградської області\nКіровоградська область\nАнатолійович\n2014\nОрендовська О. В. 25. 05. 1991\nПодружжя\nАнатолійович\nОрендовський\nВолодимир\nОрендовський Володимир Анатолійович\nВолодимир Анатолійович Орендовський\nВолодимир Орендовський\nОрендовський Володимир Анатолійович\nсуддя новомиргородського районного суду кіровоградської області\nКіровоградська область\nЗагальний місцевий суд\nОрендовський Володимир Анатолійович","source":"VULYK","income":{"5":{"family_comment":"","family":"35928","comment":"","value_unclear":false,"family_unclear":false,"value":"213729"},"6":{"family_comment":"","family":"35843","comment":"","value_unclear":false,"family_unclear":false,"value":"204976"},"7":{"family":"","family_comment":"","value":"","comment":"","source_name":""},"8":{"family_comment":"","value":"","family":"","comment":""},"9":{"family_comment":"","value":"7342","family":"36","comment":"","value_unclear":false},"10":{"family_comment":"","value":"","family":"","comment":"","value_unclear":false},"11":{"family_comment":"","value":"","family":"","comment":""},"12":{"family_comment":"","value":"","family":"","comment":""},"13":{"family_comment":"","value":"","family":"","comment":"","value_unclear":false},"14":{"family_comment":"","value":"","family":"","comment":""},"15":{"family_comment":"","value":"","family":"","comment":""},"16":{"family_comment":"","value":"","family":"","comment":""},"17":{"family_comment":"","value":"","family":"","comment":""},"18":{"family_comment":"","value":"","family":"","comment":""},"19":{"family_comment":"","value":"","family":"","comment":""},"20":{"family_comment":"","value":"1411","family_unclear":false,"family":"49","comment":""}},"banks":{"45":[{"sum_comment_unclear":false,"sum_units":"UAH","sum_foreign_units":"UAH","sum":"312","sum_foreign_comment":"","sum_comment":"","sum_unclear":false,"sum_foreign":"","sum_comment_hidden":true}],"46":[{"sum_units":"UAH","sum_comment":"","sum_foreign_units":"UAH","sum":"312","sum_foreign_comment":"","sum_foreign":"","sum_unclear":false,"sum_comment_hidden":true}],"51":[{"sum_units":"UAH","sum_comment":"","sum_foreign_units":"UAH","sum":"24","sum_foreign_comment":"","sum_foreign":"","sum_comment_hidden":true}]},"declaration":{"notfull_lostpages":"","additional_info_text":"","additional_info":"","date":"2015-03-25T00:00:00","notfull":"","url":"http://static.declarations.com.ua/declarations/chosen_ones/judges_batch/2674_orendovskyi_volodymyr_anatoliiovych.pdf"},"general":{"family_raw":"","name":"Володимир","full_name_suggest":{"input":["Орендовський Володимир Анатолійович","Володимир Анатолійович Орендовський","Володимир Орендовський"],"output":"Орендовський Володимир Анатолійович"},"patronymic":"Анатолійович","inn_hidden":true,"last_name_hidden":false,"inn":"","addresses":[{"place_city_type_hidden":false,"place_city_type":"","place_city_hidden":true,"place_hidden":true,"place_district":"","place_district_hidden":false,"place":"","place_city":"","place_address_hidden":true,"place_address":""}],"last_name":"Орендовський","full_name":"Орендовський Володимир Анатолійович","family":[{"inn":"","family_name":"Орендовська О. В. 25. 05. 1991","relations_other":"","relations_hidden":false,"relations_unclear":false,"name_unclear":false,"inn_hidden":true,"name_hidden":false,"relations":"Подружжя"}],"post":{"post_hidden":false,"office":"Загальний місцевий суд","region":"Кіровоградська область","post_unclear":false,"post":"суддя новомиргородського районного суду кіровоградської області"},"last_name_unclear":false},"liabilities":{"54":{"sum_comment":"","sum_comment_unclear":false,"sum_foreign_comment":"","sum":"","sum_foreign":""},"55":{"sum_comment":"","sum_foreign_comment":"","sum_foreign":"","sum":""},"56":{"sum_comment":"","sum_foreign_comment":"","sum_foreign":"","sum_unclear":false,"sum":""},"57":{"sum_comment":"","sum_foreign_comment":"","sum_foreign":"","sum":""},"58":{"sum_comment":"","sum_foreign_comment":"","sum_foreign":"","sum":"","sum_comment_hidden":false},"59":{"sum_comment":"","sum_foreign_comment":"","sum_foreign":"","sum":""},"60":{"sum_comment":"","sum_foreign_comment":"","sum_foreign":"","sum":""},"61":{"sum_comment":"","sum_foreign_comment":"","sum_foreign":"","sum":""},"62":{"sum_comment":"","sum_foreign_comment":"","sum_foreign":"","sum_unclear":false,"sum":""},"63":{"sum_comment":"","sum_foreign_comment":"","sum_foreign":"","sum_unclear":false,"sum":""},"64":{"sum_comment":"","sum_foreign_comment":"","sum_foreign":"","sum":""}},"intro":{"isnotdeclaration":"","declaration_year":"2014"}}]