[{"id":"vulyk_97_87","ft_src":"2350 куб. см., 170 к. с., 125 кВт , 464 см\nMitsubishi Outlander XL\n2008\n23.26\nХарківська область\nм. Харків\n38.4\nм. Харків\nХарківська область\nм. Харків\n108.8\nХарківська область\n2014\n196012\n16885\n196012\n16885\n2350 куб. см., 170 к. с., 125 кВт , 464 см\nMitsubishi Outlander XL\n2008\n2014\nПанов Микола Миколайович\nМикола Миколайович Панов\nМикола Панов\nПанов Микола Миколайович\nМикола\nПодружжя\nПанова С. В\nДитина\nПанов А. М\nДитина\nПанова М. М\nПанов Микола Миколайович\nПанов\nАдміністративний місцевий суд\nХарківська область\nсуддя харківського окружного адміністративного суду\nМиколайович\nХарківська область\n61103\nХарків\n196012\n16885\n196012\n16885\n23.26\nХарківська область\nм. Харків\n38.4\nм. Харків\nХарківська область\n108.8\nХарківська область\nм. Харків\nПодружжя\nПанова С. В\nПанов А. М\nДитина\nДитина\nПанова М. М\nМиколайович\nПанов\nМикола\nПанов Микола Миколайович\nМикола Миколайович Панов\nМикола Панов\nПанов Микола Миколайович\n61103\nХарків\nХарківська область\nХарківська область\nАдміністративний місцевий суд\nсуддя харківського окружного адміністративного суду\nПанов Микола Миколайович","estate":{"25":[{"address":"м. Харків","space_units":"м²","space_hidden":false,"space_unclear":false,"region_hidden":false,"costs_rent_comment":"","space_comment":"","address_hidden":false,"space_comment_hidden":false,"costs":"","space_comment_unclear":false,"costs_comment":"","space":"38.4","region_unclear":false,"region":"Харківська область","costs_rent":""},{"address":"м. Харків","space_units":"м²","space_unclear":false,"costs_comment":"","space_comment":"","address_hidden":false,"space":"108.8","space_comment_unclear":false,"costs_rent_comment":"","costs":"","region":"Харківська область","costs_rent":""}],"31":[{"costs_property_comment":"","address":"м. Харків","space_units":"м²","space_hidden":false,"space_unclear":false,"region_hidden":false,"costs_property":"","space_comment":"","address_hidden":false,"space_comment_hidden":false,"costs_rent_comment":"","space":"23.26","region":"Харківська область","costs_rent":""}]},"vehicle":{"35":[{"year_hidden":false,"brand_info":"2350 куб. см., 170 к. с., 125 кВт , 464 см","brand_unclear":false,"sum_rent_comment":"","brand_hidden":false,"year":"2008","sum_comment":"","brand_info_hidden":false,"sum_rent":"","brand":"Mitsubishi Outlander XL","brand_info_unclear":false,"sum":""}]},"source":"VULYK","income":{"5":{"family_comment":"","value":"196012","family":"16885","comment":""},"6":{"family_comment":"","family":"","comment":"","value_unclear":false,"family_unclear":false,"comment_hidden":false,"value":"196012"},"7":{"family":"","family_comment":"","value":"","comment":"","source_name":""},"8":{"family_comment":"","value":"","family":"","comment":""},"9":{"family_comment":"","value":"","family_unclear":false,"family":"","comment":""},"10":{"family_comment":"","value":"","family":"","comment":"","value_unclear":false},"11":{"family_comment":"","value":"","family":"","comment":""},"12":{"family_comment":"","value":"","family":"","comment":""},"13":{"family_comment":"","value":"","family":"","comment":""},"14":{"family_comment":"","value":"","family":"","comment":""},"15":{"family_comment":"","value":"","family":"","comment":""},"16":{"family_comment":"","value":"","family":"","comment":""},"17":{"family_comment":"","value":"","family":"","comment":""},"18":{"family_comment":"","value":"","family":"","comment":""},"19":{"family_comment":"","value":"","family":"","comment":""},"20":{"family_comment":"","comment":"","family":"16885","value_unclear":false,"comment_unclear":false,"value":"","family_hidden":false,"family_comment_unclear":false}},"general":{"family":[{"inn":"","family_name":"Панова С. В","relations_other":"","name_unclear":false,"inn_hidden":true,"name_hidden":false,"relations":"Подружжя"},{"inn":"","family_name":"Панов А. М","name_unclear":false,"inn_hidden":false,"name_hidden":false,"relations":"Дитина"},{"inn":"","family_name":"Панова М. М","relations_other":"","name_unclear":false,"inn_hidden":false,"name_hidden":false,"relations":"Дитина"}],"family_raw":"","name":"Микола","full_name_suggest":{"input":["Панов Микола Миколайович","Микола Миколайович Панов","Микола Панов"],"output":"Панов Микола Миколайович"},"patronymic":"Миколайович","inn_hidden":true,"addresses":[{"place_city_type":"Місто","place_city_type_hidden":false,"place_hidden":false,"place_city_hidden":false,"place_district_hidden":false,"place_district":"","place_city_unclear":false,"place":"Харківська область","place_city":"Харків","place_address_hidden":true,"place_address":"61103"}],"last_name_hidden":false,"patronymic_hidden":false,"inn":"","inn_unclear":false,"last_name":"Панов","full_name":"Панов Микола Миколайович","post":{"post_hidden":false,"office":"Адміністративний місцевий суд","post":"суддя харківського окружного адміністративного суду","office_unclear":false,"region_unclear":false,"region":"Харківська область"},"name_hidden":false},"liabilities":{"54":{"sum_comment_unclear":false,"sum_comment":"","sum_hidden":false,"sum":"","sum_foreign_comment":"","sum_foreign":"","sum_unclear":false,"sum_comment_hidden":false},"55":{"sum_comment":"","sum_foreign_comment":"","sum_foreign":"","sum":""},"56":{"sum_comment":"","sum_foreign_comment":"","sum_foreign":"","sum":""},"57":{"sum_comment_unclear":false,"sum_comment":"","sum_hidden":false,"sum":"","sum_foreign_comment":"","sum_foreign":"","sum_unclear":false,"sum_comment_hidden":false},"58":{"sum_comment_unclear":false,"sum_comment":"","sum_hidden":false,"sum":"","sum_foreign_comment":"","sum_foreign":"","sum_unclear":false,"sum_comment_hidden":false},"59":{"sum_comment":"","sum_foreign_comment":"","sum_foreign":"","sum":""},"60":{"sum_comment_unclear":false,"sum_comment":"","sum_hidden":false,"sum":"","sum_foreign_comment":"","sum_foreign":"","sum_comment_hidden":false},"61":{"sum_comment":"","sum_foreign_comment":"","sum_foreign":"","sum":""},"62":{"sum_comment":"","sum_foreign_comment":"","sum_foreign":"","sum_unclear":false,"sum":""},"63":{"sum_comment":"","sum_foreign_comment":"","sum_foreign":"","sum_hidden":false,"sum":""},"64":{"sum_comment":"","sum_foreign_comment":"","sum_foreign":"","sum":""}},"declaration":{"notfull_lostpages":"","additional_info_text":"","additional_info":"","date":"2015-01-26T00:00:00","notfull":"","url":"http://static.declarations.com.ua/declarations/chosen_ones/judges_batch/3988_panov_mykola_mykolaiovych.pdf"},"intro":{"isnotdeclaration":"","declaration_year":"2014"}}]