[{"id":"vulyk_75_26","ft_src":"Subaru Forester\n2.0 л\n2005\n57.6\n3. 5. 7. 8\n1\n2014\n265089\n256150\n18168\n569847\nпенсія\nпенсія\n18168\n48608\n2.0 л\n2005\nSubaru Forester\n3. 5. 7. 8\n1\n2014\nАпеляційний господарський суд\nсуддя одеського апеляційного господарського суду\nОдеська область\nПироговський\nПироговський Володимир Терентійович\nВолодимир Терентійович Пироговський\nВолодимир Пироговський\nПироговський Володимир Терентійович\nВолодимир\nБатьки\nПироговська Г. П\nПироговський Володимир Терентійович\nТерентійович\n265089\nпенсія\n48608\nпенсія\n18168\n569847\n18168\n256150\n57.6\nПироговська Г. П\nБатьки\nПироговський\nТерентійович\nсуддя одеського апеляційного господарського суду\nОдеська область\nАпеляційний господарський суд\nПироговський Володимир Терентійович\nПироговський Володимир Терентійович\nВолодимир Терентійович Пироговський\nВолодимир Пироговський\nПироговський Володимир Терентійович\nВолодимир","estate":{"25":[{"address":"","space_units":"м²","space_hidden":false,"space_unclear":false,"region_hidden":false,"costs_comment":"","space_comment":"","address_hidden":false,"space":"57.6","costs_rent_comment":"","costs":"","region":"","costs_rent":""}]},"vehicle":{"35":[{"sum_comment":"","brand_unclear":false,"sum_rent":"","sum":"","sum_rent_comment":"","brand_hidden":false,"brand":"Subaru Forester","brand_info":"2.0 л","brand_info_unclear":false,"year":"2005","sum_unclear":false}]},"source":"VULYK","income":{"5":{"family_comment":"","value":"569847","family":"18168","comment":""},"6":{"family_comment":"","family_hidden":false,"value":"265089","family":"","comment":""},"7":{"family":"","family_comment":"","value":"","comment":"","source_name":""},"8":{"family_comment":"","value":"","family":"","comment":""},"9":{"family_comment":"","family":"","comment":"","value_unclear":false,"family_hidden":false,"value":""},"10":{"family":"","family_comment":"","comment":"","value_hidden":false,"value":"","family_hidden":false,"family_unclear":false},"11":{"family_comment":"","value":"256150","family":"","comment":""},"12":{"family_comment":"","value":"","family":"","comment":""},"13":{"family_comment":"","value":"","family":"","comment":""},"14":{"family_comment":"","value":"","family":"","comment":""},"15":{"family_comment":"","value":"","family":"","comment":""},"16":{"family_comment":"","value":"","family":"","comment":""},"17":{"family_comment":"","value":"","family":"","comment":""},"18":{"family_comment":"","value":"","family":"","comment":""},"19":{"family_comment":"","value":"","family":"","comment":""},"20":{"family_comment":"пенсія","comment":"пенсія","family":"18168","comment_unclear":false,"value":"48608","family_comment_unclear":false}},"general":{"inn":"","inn_hidden":false,"last_name":"Пироговський","full_name":"Пироговський Володимир Терентійович","family":[{"inn":"","family_name":"Пироговська Г. П","relations_other":"","relations_hidden":false,"name_unclear":false,"inn_hidden":false,"name_hidden":false,"relations":"Батьки"}],"patronymic":"Терентійович","name":"Володимир","post":{"office":"Апеляційний господарський суд","region":"Одеська область","post":"суддя одеського апеляційного господарського суду"},"family_raw":"","full_name_suggest":{"input":["Пироговський Володимир Терентійович","Володимир Терентійович Пироговський","Володимир Пироговський"],"output":"Пироговський Володимир Терентійович"}},"liabilities":{"54":{"sum_comment":"","sum_foreign_comment":"","sum_foreign":"","sum":""},"55":{"sum_comment":"","sum_foreign_comment":"","sum_foreign":"","sum":""},"56":{"sum_comment":"","sum_foreign_comment":"","sum_foreign":"","sum":""},"57":{"sum_comment":"","sum_foreign_comment":"","sum_foreign":"","sum":""},"58":{"sum_comment":"","sum_foreign_comment":"","sum_foreign":"","sum":""},"59":{"sum_comment_unclear":false,"sum_comment":"","sum":"","sum_foreign_comment":"","sum_foreign":"","sum_unclear":false},"60":{"sum_comment":"","sum_foreign_comment":"","sum_foreign":"","sum":""},"61":{"sum_comment":"","sum_foreign_comment":"","sum_foreign":"","sum":""},"62":{"sum_comment":"","sum_foreign_comment":"","sum_foreign":"","sum_unclear":false,"sum":""},"63":{"sum_comment":"","sum_foreign_comment":"","sum_foreign":"","sum":""},"64":{"sum_comment":"","sum_foreign_comment":"","sum_foreign":"","sum":""}},"declaration":{"notfull_lostpages":"3. 5. 7. 8","additional_info_text":"","additional_info":"","date":"2015-03-20T00:00:00","notfull":"1","url":"http://static.declarations.com.ua/declarations/chosen_ones/judges_batch/1909_pyrohovskyi_volodymyr_terentiiovych.pdf"},"intro":{"isnotdeclaration":"","declaration_year":"2014"}},{"id":"vulyk_73_67","ft_src":"Subaru Forester\n2 л, 116 кВт\n2006\n1/2\n29\n1/2\n29\n2013\n240963.33\n12617\n18875.02\n255671.01\n18875.02\n2090.68\n2 л, 116 кВт\nSubaru Forester\n2006\n2013\nПироговський Володимир Терентійович\nВолодимир Терентійович Пироговський\nВолодимир Пироговський\nПироговський Володимир Терентійович\nВолодимир\nБатьки\nПироговська Г. П., 28. 06. 1923\nБатьки\nПироговський Т. Г., 28. 04. 1923\nПироговський Володимир Терентійович\nТерентійович\nАпеляційний господарський суд\nОдеська область\nсуддя одеського апеляційного господарського суду\nПироговський\n240963.33\n18875.02\n2090.68\n255671.01\n18875.02\n12617\n1/2\n29\n29\n1/2\nБатьки\nПироговська Г. П., 28. 06. 1923\nБатьки\nПироговський Т. Г., 28. 04. 1923\nТерентійович\nПироговський\nВолодимир\nПироговський Володимир Терентійович\nВолодимир Терентійович Пироговський\nВолодимир Пироговський\nПироговський Володимир Терентійович\nОдеська область\nАпеляційний господарський суд\nсуддя одеського апеляційного господарського суду\nПироговський Володимир Терентійович","estate":{"25":[{"address":"","space_units":"м²","costs_hidden":false,"space_hidden":false,"space_unclear":false,"region_hidden":false,"costs_rent_comment":"","space_comment":"1/2","address_hidden":false,"space_comment_hidden":false,"costs":"","costs_comment":"","space":"29","region":"","costs_rent":""}],"31":[{"costs_property_comment":"","address":"","space_units":"м²","space_unclear":false,"region_hidden":false,"costs_property":"","space_comment":"1/2","address_hidden":false,"costs_rent_comment":"","space":"29","region":"","costs_rent":""}]},"vehicle":{"35":[{"brand_info":"2 л, 116 кВт","sum_comment":"","sum_hidden":false,"brand_unclear":false,"sum_rent_comment":"","year":"2006","brand":"Subaru Forester","sum_rent":"","brand_info_unclear":false,"sum":""}]},"source":"VULYK","income":{"5":{"family_comment":"","family":"18875.02","comment":"","comment_hidden":false,"value":"255671.01","family_comment_hidden":false},"6":{"family_comment":"","family":"","comment":"","comment_hidden":false,"family_hidden":false,"family_unclear":false,"family_comment_hidden":false,"value":"240963.33"},"7":{"source_name_hidden":false,"family_comment":"","comment":"","family":"","comment_hidden":false,"value":"","family_comment_hidden":false,"source_name":""},"8":{"family_comment":"","value":"","family":"","comment":""},"9":{"family_comment":"","comment":"","family":"","value_unclear":false,"family_unclear":false,"comment_unclear":false,"value":""},"10":{"family_comment":"","value":"12617","family_unclear":false,"family":"","comment":""},"11":{"family_comment":"","value":"","family":"","comment":""},"12":{"family_comment":"","value":"","family":"","comment":""},"13":{"family_comment":"","value":"","family":"","comment":""},"14":{"family_comment":"","value":"","family":"","comment":""},"15":{"family_comment":"","comment_unclear":false,"value":"","family":"","comment":""},"16":{"family_comment":"","comment_unclear":false,"value":"","family":"","comment":""},"17":{"family_comment":"","value":"","family":"","comment":""},"18":{"family_comment":"","value":"","family":"","comment":""},"19":{"family_comment":"","value":"","family":"","comment":""},"20":{"family_comment":"","family":"18875.02","comment":"","value_unclear":false,"family_unclear":false,"value":"2090.68","family_comment_hidden":false,"family_comment_unclear":false}},"general":{"family_raw":"","name":"Володимир","full_name_suggest":{"input":["Пироговський Володимир Терентійович","Володимир Терентійович Пироговський","Володимир Пироговський"],"output":"Пироговський Володимир Терентійович"},"name_unclear":false,"patronymic":"Терентійович","inn_hidden":true,"inn":"","addresses":[{"place_city_type_hidden":false,"place_city_type":"","place_city_hidden":false,"place_hidden":true,"place_district":"","place_district_hidden":false,"place":"","place_city":"","place_address_hidden":false,"place_address":""}],"last_name":"Пироговський","full_name":"Пироговський Володимир Терентійович","family":[{"inn":"","inn_unclear":false,"family_name":"Пироговська Г. П., 28. 06. 1923","relations_hidden":false,"name_unclear":false,"relations":"Батьки","inn_hidden":false,"name_hidden":false,"relations_other":""},{"inn":"","inn_unclear":false,"family_name":"Пироговський Т. Г., 28. 04. 1923","relations_other":"","name_unclear":false,"inn_hidden":false,"name_hidden":false,"relations":"Батьки"}],"post":{"post_hidden":false,"office":"Апеляційний господарський суд","post":"суддя одеського апеляційного господарського суду","region":"Одеська область","region_hidden":false,"office_unclear":false,"office_hidden":true,"post_unclear":false,"region_unclear":false},"last_name_unclear":false},"liabilities":{"54":{"sum_comment_unclear":false,"sum_comment":"","sum_hidden":false,"sum":"","sum_foreign_comment":"","sum_foreign":"","sum_unclear":false,"sum_foreign_hidden":false,"sum_comment_hidden":false},"55":{"sum_comment":"","sum_foreign_comment":"","sum_foreign":"","sum":"","sum_comment_hidden":false},"56":{"sum_comment":"","sum_comment_unclear":false,"sum_foreign_comment":"","sum":"","sum_foreign":""},"57":{"sum_comment":"","sum_hidden":false,"sum":"","sum_foreign_comment":"","sum_foreign":"","sum_unclear":false,"sum_comment_hidden":false},"58":{"sum_comment":"","sum_hidden":false,"sum":"","sum_foreign_comment":"","sum_foreign":"","sum_comment_hidden":false},"59":{"sum_comment_unclear":false,"sum_comment":"","sum":"","sum_foreign_comment":"","sum_foreign":"","sum_unclear":false},"60":{"sum_comment":"","sum_hidden":false,"sum":"","sum_foreign_comment":"","sum_foreign":"","sum_unclear":false,"sum_comment_hidden":false},"61":{"sum_comment":"","sum_foreign_comment":"","sum_foreign":"","sum":""},"62":{"sum_comment":"","sum_foreign_comment":"","sum_foreign":"","sum":""},"63":{"sum_comment":"","sum_hidden":false,"sum":"","sum_foreign_comment":"","sum_foreign":"","sum_comment_hidden":false},"64":{"sum_comment":"","sum_foreign_comment":"","sum_foreign":"","sum":""}},"declaration":{"notfull_lostpages":"","additional_info_text":"","additional_info":"","date":"2014-12-10T00:00:00","notfull":"","url":"http://static.declarations.com.ua/declarations/chosen_ones/judges_batch/1337_pyrohovskyi_volodymyr_terentiiovych.pdf"},"intro":{"declaration_year":"2013"}}]