[{"id":"vulyk_103_50","ft_src":"Honda CR-V\n2354\n2008\n600\n10\n1\nВідомості про членів сім'ї не зазначено, оскільки вони не надали згоди на їх внесення до цієї декларації\n2015\n242712.45\n242712.45\n2354\n2008\nHonda CR-V\n1\nВідомості про членів сім'ї не зазначено, оскільки вони не надали згоди на їх внесення до цієї декларації\n600\n10\nПисана\nПисана Таміла Олександрівна\nТаміла Олександрівна Писана\nТаміла Писана\nПисана Таміла Олександрівна\nПисана Таміла Олександрівна\nОлександрівна\nПодружжя\nПисаний Віктор Григорович\nПисаний Роман Вікторович\nДитина\nДитина\nПисаний Максим Вікторович\nТаміла\nВищий спеціалізований суд з розгляду цивільних і кримінальних справ\nсуддя вищого спецiалiзованого суду україни з розгляду цивiльних і кримiнальних справ\nЗагальнодержавний регіон\n242712.45\n242712.45\n2015\nПодружжя\nПисаний Віктор Григорович\nДитина\nПисаний Роман Вікторович\nДитина\nПисаний Максим Вікторович\nПисана\nОлександрівна\nсуддя вищого спецiалiзованого суду україни з розгляду цивiльних і кримiнальних справ\nВищий спеціалізований суд з розгляду цивільних і кримінальних справ\nЗагальнодержавний регіон\nПисана Таміла Олександрівна\nПисана Таміла Олександрівна\nТаміла Олександрівна Писана\nТаміла Писана\nПисана Таміла Олександрівна\nТаміла","estate":{"23":[{"costs":"","address":"","space_units":"м²","costs_rent_comment":"","space":"600","space_comment":"","region_hidden":true,"costs_comment":"","region":"","address_hidden":false,"costs_rent":""}],"27":[{"costs":"","address":"","space_units":"м²","costs_rent_comment":"","space":"10","space_comment":"","region_hidden":true,"costs_comment":"","region":"","address_hidden":false,"costs_rent":""}]},"vehicle":{"35":[{"sum_comment":"","brand_info_hidden":false,"brand_info":"2354","sum":"","brand_unclear":false,"brand_hidden":false,"brand":"Honda CR-V","sum_rent":"","brand_info_unclear":false,"sum_rent_comment":"","year":"2008"}]},"source":"VULYK","income":{"5":{"family_comment":"","family":"","comment":"","value_unclear":false,"family_hidden":false,"value":"242712.45"},"6":{"family_comment":"","value":"242712.45","family":"","comment":""},"7":{"family":"","family_comment":"","value":"","comment":"","source_name":""},"8":{"family_comment":"","value":"","family":"","comment":""},"9":{"family_comment":"","value":"","family":"","comment":""},"10":{"family_comment":"","value":"","family":"","comment":""},"11":{"family_comment":"","family_hidden":false,"value":"","family":"","comment":""},"12":{"family_comment":"","value":"","family":"","comment":""},"13":{"family_comment":"","value":"","family":"","comment":""},"14":{"family_comment":"","value":"","family":"","comment":""},"15":{"family_comment":"","value":"","family":"","comment":""},"16":{"family_comment":"","value":"","family":"","comment":""},"17":{"family_comment":"","value":"","family":"","comment":"","family_comment_unclear":false},"18":{"family_comment":"","value":"","family":"","comment":""},"19":{"family_comment":"","value":"","family":"","comment":""},"20":{"family_comment":"","family":"","comment":"","family_unclear":false,"family_hidden":false,"value":""}},"general":{"inn":"","addresses":[{"place_city_type_hidden":false,"place_city_type":"","place_city_hidden":true,"place_hidden":true,"place_district":"","place_district_hidden":false,"place":"","place_city":"","place_address_hidden":true,"place_address":""}],"last_name":"Писана","full_name":"Писана Таміла Олександрівна","family":[{"inn":"","family_name":"Писаний Віктор Григорович","relations_hidden":false,"name_unclear":false,"relations":"Подружжя","inn_hidden":true,"name_hidden":true,"relations_other":""},{"inn":"","family_name":"Писаний Роман Вікторович","inn_hidden":true,"relations_other":"","relations":"Дитина"},{"inn":"","family_name":"Писаний Максим Вікторович","relations_other":"","name_unclear":false,"inn_hidden":false,"relations":"Дитина"}],"patronymic":"Олександрівна","inn_hidden":true,"name":"Таміла","post":{"office":"Вищий спеціалізований суд з розгляду цивільних і кримінальних справ","region_unclear":false,"post":"суддя вищого спецiалiзованого суду україни з розгляду цивiльних і кримiнальних справ","region":"Загальнодержавний регіон","office_unclear":false},"family_raw":"","full_name_suggest":{"input":["Писана Таміла Олександрівна","Таміла Олександрівна Писана","Таміла Писана"],"output":"Писана Таміла Олександрівна"}},"liabilities":{"54":{"sum_foreign_comment_hidden":false,"sum_foreign_comment_unclear":false,"sum_hidden":false,"sum":"","sum_foreign_comment":"","sum_comment":"","sum_unclear":false,"sum_foreign":"","sum_comment_hidden":false,"sum_foreign_hidden":false},"55":{"sum_comment":"","sum_foreign_comment":"","sum_foreign":"","sum":""},"56":{"sum_comment":"","sum_foreign_comment":"","sum_foreign":"","sum":""},"57":{"sum_comment":"","sum_hidden":false,"sum":"","sum_foreign_comment":"","sum_foreign":"","sum_comment_hidden":false,"sum_foreign_hidden":false,"sum_foreign_comment_hidden":false},"58":{"sum_comment":"","sum_hidden":false,"sum":"","sum_foreign_comment":"","sum_foreign":"","sum_comment_hidden":false,"sum_foreign_hidden":false,"sum_foreign_comment_hidden":false},"59":{"sum_comment":"","sum_hidden":false,"sum":"","sum_foreign_comment":"","sum_foreign":"","sum_comment_hidden":false,"sum_foreign_hidden":false,"sum_foreign_comment_hidden":false},"60":{"sum_comment":"","sum_hidden":false,"sum":"","sum_foreign_comment":"","sum_foreign":"","sum_comment_hidden":false},"61":{"sum_comment":"","sum_foreign_comment":"","sum_foreign":"","sum":""},"62":{"sum_comment":"","sum_foreign_comment":"","sum_foreign":"","sum":"","sum_comment_hidden":false},"63":{"sum_comment":"","sum_foreign_comment":"","sum_foreign":"","sum":""},"64":{"sum_comment":"","sum_foreign_comment":"","sum_foreign":"","sum":""}},"declaration":{"additional_info_text":"Відомості про членів сім'ї не зазначено, оскільки вони не надали згоди на їх внесення до цієї декларації","additional_info":"1","date":"2016-03-30T00:00:00","url":"http://static.declarations.com.ua/declarations/chosen_ones/judges_batch/1274_pysana_tamila_oleksandrivna.pdf"},"intro":{"declaration_year":"2015"}},{"id":"vulyk_8_152","declaration":{"notfull_lostpages":"","additional_info_text":"Відомості про членів сім'ї не зазначено, оскільки вони не надали згоди на їх внесення до цієї декларації. '","additional_info":"1","date":"2015-03-30T00:00:00","notfull":"","url":"http://static.declarations.com.ua/declarations/chosen_ones/batch_16/pysana_tamila_oleksandrivna.pdf"},"estate":{"23":[{"address":"","space_units":"м²","costs_comment":"","space_unclear":false,"region_hidden":true,"space_comment":"","address_hidden":false,"space_comment_hidden":false,"space":"600","address_unclear":false,"space_comment_unclear":false,"costs_comment_unclear":false,"costs_rent_comment":"","costs":"","region":"","space_units_hidden":false,"costs_rent":""},{"address":"","space_units":"","costs_comment":"","space_unclear":false,"region_hidden":false,"space_comment":"","address_hidden":false,"space":"","space_comment_unclear":false,"costs_rent_comment":"","costs":"","region":"","costs_rent":""},{"costs":"","address":"","space_units":"","space_units_unclear":false,"space":"","space_comment":"","costs_rent_comment":"","costs_comment":"","region":"","costs_rent":""},{"costs":"","address":"","space_units":"","costs_rent_comment":"","space":"","space_comment":"","costs_comment":"","region":"","address_hidden":false,"costs_rent":""}],"27":[{"costs":"","address":"","space_units":"м²","costs_rent_comment":"","space":"10","space_comment":"","region_hidden":true,"costs_comment":"","region":"","address_hidden":false,"costs_rent":""}]},"vehicle":{"35":[{"sum_comment_unclear":false,"brand_info":"2354","sum_rent_comment":"","brand_unclear":false,"year":"2008","sum_comment":"","brand_info_hidden":false,"sum_rent":"","brand":"Honda CR-V","year_unclear":false,"sum_unclear":false,"sum":""}]},"source":"VULYK","income":{"5":{"family_comment":"","family":"","comment":"","value_unclear":false,"family_unclear":false,"family_hidden":false,"value":"783533"},"6":{"family_comment":"","family":"","comment":"","value_unclear":false,"family_hidden":false,"value":"252616.27"},"7":{"source_name_hidden":false,"family_comment":"","comment":"","family":"","source_name_unclear":false,"value":"","family_hidden":false,"source_name":""},"8":{"family_comment":"","value":"","family":"","comment":""},"9":{"family_comment":"","value":"","family_unclear":false,"family":"","comment":""},"10":{"family_comment":"","value":"","family":"","comment":""},"11":{"family_comment":"","comment_unclear":false,"value":"","family":"","comment":""},"12":{"family_comment":"","value":"","family":"","comment":""},"13":{"family_comment":"","value":"","family":"","comment":""},"14":{"family_comment":"","value":"","family":"","comment":""},"15":{"family_comment":"","value":"","family":"","comment":""},"16":{"family_comment":"","value":"530916.85","family":"","comment":""},"17":{"family_comment":"","value":"","family":"","comment":"","family_comment_unclear":false},"18":{"family_comment":"","value":"","family":"","comment":""},"19":{"family_comment":"","comment_unclear":false,"value":"","family":"","comment":""},"20":{"family_comment":"","family":"","comment":"","comment_hidden":false,"comment_unclear":false,"family_unclear":false,"value":""}},"banks":{"45":[{"sum_units":"UAH","sum_comment":"","sum_foreign_units":"UAH","sum_hidden":false,"sum":"","sum_foreign_comment":"","sum_foreign_unclear":false,"sum_foreign":"","sum_unclear":false,"sum_comment_hidden":false},{"sum_units":"","sum_comment":"","sum_foreign_units":"","sum_hidden":false,"sum":"","sum_foreign_comment":"","sum_foreign":"","sum_unclear":false},{"sum_units":"","sum_comment":"","sum_foreign_units":"","sum":"","sum_foreign_comment":"","sum_foreign":"","sum_unclear":false},{"sum_units":"","sum_comment":"","sum_foreign_units":"","sum":"","sum_foreign_comment":"","sum_foreign":""}],"46":[{"sum_units":"UAH","sum_comment":"","sum_foreign_units":"UAH","sum_hidden":false,"sum":"","sum_foreign_comment_hidden":false,"sum_foreign_comment":"","sum_foreign":"","sum_unclear":false,"sum_foreign_hidden":false,"sum_comment_hidden":false}],"47":[{"sum_units":"UAH","sum_comment":"","sum_foreign_units":"UAH","sum":"","sum_foreign_comment":"","sum_foreign":"","sum_comment_hidden":false}],"48":[{"sum_units":"UAH","sum_comment":"","sum_foreign_units":"UAH","sum":"","sum_foreign_comment":"","sum_foreign":""}],"49":[{"sum_units":"UAH","sum_comment":"","sum_foreign_units":"UAH","sum":"","sum_foreign_comment":"","sum_foreign":""}],"50":[{"sum_units":"UAH","sum_comment":"","sum_foreign_units":"UAH","sum":"","sum_foreign_comment":"","sum_foreign":""}],"51":[{"sum_comment_unclear":false,"sum_units":"UAH","sum_foreign_units":"UAH","sum_hidden":false,"sum":"","sum_foreign_comment":"","sum_comment":"","sum_unclear":false,"sum_foreign":"","sum_comment_hidden":false},{"sum_units":"","sum_comment":"","sum_foreign_units":"","sum_hidden":false,"sum":"","sum_foreign_comment":"","sum_foreign":""}],"52":[{"sum_comment_unclear":false,"sum_units":"UAH","sum_foreign_units":"UAH","sum_hidden":false,"sum":"","sum_foreign_comment":"","sum_comment":"","sum_unclear":false,"sum_foreign":"","sum_comment_hidden":false}],"53":[{"sum_units":"UAH","sum_comment":"","sum_foreign_units":"UAH","sum":"","sum_foreign_comment":"","sum_foreign":"","sum_comment_hidden":false}]},"ft_src":"2354\nHonda CR-V\n2008\n1\nВідомості про членів сім'ї не зазначено, оскільки вони не надали згоди на їх внесення до цієї декларації. '\n2014\n2354\nHonda CR-V\n2008\nВідомості про членів сім'ї не зазначено, оскільки вони не надали згоди на їх внесення до цієї декларації. '\n1\n600\n10\nПодружжя\nПисаний Віктор Григорович\nДитина\nПисаний Роман Вікторович\nДитина\nПисаний Максим Вікторович\nПисана Таміла Олександрівна\nТаміла Олександрівна Писана\nТаміла Писана\nПисана Таміла Олександрівна\nПисана Таміла Олександрівна\nТаміла\nПисана\nВищий спецiалiзований суд України з розгляду цивiльних i кримiнальних справ\nсуддя вищого спеціалізованого суду україни з розгляду цивільних і кримінальних справ\nЗагальнодержавний регіон\nОлександрівна\n252616.27\n783533\n530916.85\n2014\n600\n10\nПисаний Віктор Григорович\nПодружжя\nПисаний Роман Вікторович\nДитина\nПисаний Максим Вікторович\nДитина\nОлександрівна\nПисана\nТаміла\nПисана Таміла Олександрівна\nТаміла Олександрівна Писана\nТаміла Писана\nПисана Таміла Олександрівна\nЗагальнодержавний регіон\nсуддя вищого спеціалізованого суду україни з розгляду цивільних і кримінальних справ\nВищий спецiалiзований суд України з розгляду цивiльних i кримiнальних справ\nПисана Таміла Олександрівна\n252616.27\n783533\n530916.85","general":{"family":[{"inn":"","family_name":"Писаний Віктор Григорович","relations_other":"","relations_hidden":false,"name_unclear":false,"inn_hidden":true,"name_hidden":false,"relations":"Подружжя"},{"inn":"","inn_unclear":false,"family_name":"Писаний Роман Вікторович","relations_other":"","name_unclear":false,"inn_hidden":false,"name_hidden":false,"relations":"Дитина"},{"inn":"","family_name":"Писаний Максим Вікторович","relations_other":"","name_unclear":false,"inn_hidden":false,"name_hidden":false,"relations":"Дитина"}],"family_raw":"","name":"Таміла","full_name_suggest":{"input":["Писана Таміла Олександрівна","Таміла Олександрівна Писана","Таміла Писана"],"output":"Писана Таміла Олександрівна"},"patronymic":"Олександрівна","inn_hidden":true,"patronymic_unclear":false,"last_name_hidden":false,"inn":"","inn_unclear":false,"last_name":"Писана","full_name":"Писана Таміла Олександрівна","post":{"post_hidden":false,"office":"Вищий спецiалiзований суд України з розгляду цивiльних i кримiнальних справ","post":"суддя вищого спеціалізованого суду україни з розгляду цивільних і кримінальних справ","region":"Загальнодержавний регіон","office_hidden":false,"office_unclear":false,"region_hidden":false,"post_unclear":false},"addresses":[{"place_city_type_hidden":false,"place_city_type":"","place_city_hidden":true,"place_hidden":true,"place_district":"","place_district_hidden":true,"place":"","place_address":"","place_address_hidden":false,"place_city":""}]},"liabilities":{"54":{"sum_comment":"","sum_hidden":false,"sum":"","sum_foreign_comment":"","sum_foreign":"","sum_foreign_hidden":false,"sum_comment_hidden":false},"55":{"sum_comment":"","sum_foreign_comment":"","sum_foreign":"","sum":""},"56":{"sum_comment":"","sum_foreign_comment":"","sum_foreign":"","sum_unclear":false,"sum":""},"57":{"sum_comment":"","sum_foreign_comment":"","sum_foreign":"","sum":"","sum_comment_hidden":false},"58":{"sum_comment":"","sum_foreign_comment":"","sum_foreign":"","sum":""},"59":{"sum_comment":"","sum_comment_unclear":false,"sum_foreign_comment":"","sum":"","sum_foreign":""},"60":{"sum_comment":"","sum_hidden":false,"sum":"","sum_foreign_comment":"","sum_foreign":"","sum_foreign_hidden":false,"sum_comment_hidden":false},"61":{"sum_comment":"","sum_foreign_comment":"","sum_foreign":"","sum":""},"62":{"sum_comment":"","sum_foreign_comment":"","sum_foreign":"","sum":""},"63":{"sum_comment":"","sum_foreign_comment":"","sum_foreign":"","sum":""},"64":{"sum_comment":"","sum_foreign_comment":"","sum_foreign":"","sum":""}},"intro":{"isnotdeclaration":"","declaration_year":"2014"}},{"id":"4203","ft_src":"2354\n2008\nHonda CR-V\n600\n10\n89\n1\nВідомості про членів сім'ї не зазначено, оскільки вони не надали згоди на їх внесення до цієї декларації\n2013\n244211\n244235\n24\n2354\nHonda CR-V\n2008\nВідомості про членів сім'ї не зазначено, оскільки вони не надали згоди на їх внесення до цієї декларації\n1\n600\n10\n89\nПисана Таміла Олександрівна\nТаміла Олександрівна Писана\nТаміла Писана\nПисана Таміла Олександрівна\nПисана Таміла Олександрівна\nПодружжя\nПисаний Віктор Григорович\nДитина\nПисаний Роман Вікторович\nДитина\nПисаний Максим Вікторович\nТаміла\nОлександрівна\nВищий спеціалізований суд з розгляду цивільних і кримінальних справ\nсуддя вищого спеціалізованого суду україни з розгляду цивільних і кримінальних справ\nЗагальнодержавний регіон\nПисана\n244211\n24\n244235\n2013\nПисаний Віктор Григорович\nПодружжя\nДитина\nПисаний Роман Вікторович\nПисаний Максим Вікторович\nДитина\nОлександрівна\nПисана\nТаміла\nПисана Таміла Олександрівна\nТаміла Олександрівна Писана\nТаміла Писана\nПисана Таміла Олександрівна\nЗагальнодержавний регіон\nсуддя вищого спеціалізованого суду україни з розгляду цивільних і кримінальних справ\nВищий спеціалізований суд з розгляду цивільних і кримінальних справ\nПисана Таміла Олександрівна","estate":{"23":[{"costs_unclear":false,"address":"","space_units":"м²","space_hidden":false,"space_unclear":false,"region_hidden":true,"costs_rent_comment":"","space_comment":"","space_comment_unclear":false,"space_comment_hidden":false,"space":"600","address_hidden":true,"costs_comment":"","costs":"","region":"","costs_rent":""}],"25":[{"address":"","space_units":"м²","space_hidden":false,"space_unclear":false,"region_hidden":true,"costs_rent_comment":"","space_comment":"","address_hidden":true,"space_comment_hidden":false,"costs":"","space_comment_unclear":false,"costs_comment":"","space":"89","region":"","costs_rent":""}],"27":[{"address":"","space_units":"м²","costs_hidden":false,"space_hidden":false,"space_comment":"","region_hidden":true,"costs_comment":"","address_hidden":true,"space":"10","address_unclear":false,"costs_rent_comment":"","costs":"","region":"","costs_rent":""}]},"vehicle":{"35":[{"sum_rent_comment_hidden":false,"brand_info":"2354","brand_unclear":false,"sum_rent_comment":"","year":"2008","sum_hidden":false,"sum_comment":"","sum_rent_hidden":false,"brand_info_hidden":false,"sum_rent":"","sum_rent_unclear":false,"brand":"Honda CR-V","year_unclear":false,"brand_info_unclear":false,"sum_unclear":false,"sum_comment_hidden":false,"sum":""}]},"source":"VULYK","income":{"5":{"family":"","family_comment":"","comment":"","value_hidden":false,"value_unclear":false,"family_unclear":false,"value":"244235"},"6":{"family":"","family_comment":"","comment":"","value_hidden":false,"family_hidden":false,"value":"244211","family_comment_hidden":false},"7":{"source_name_hidden":false,"family_comment":"","comment":"","family":"","value_unclear":false,"value":"","family_hidden":false,"value_hidden":false,"source_name":""},"8":{"family":"","family_comment":"","comment":"","value_hidden":false,"comment_hidden":false,"family_hidden":false,"value":""},"9":{"family":"","family_comment":"","comment":"","value_hidden":false,"comment_hidden":false,"family_hidden":false,"family_unclear":false,"value":""},"10":{"family":"","family_comment":"","comment":"","value_hidden":false,"comment_hidden":false,"family_hidden":false,"value":""},"11":{"family":"","family_comment":"","comment":"","value_hidden":false,"value_unclear":false,"comment_hidden":false,"family_hidden":false,"value":""},"12":{"family":"","family_comment":"","comment":"","value_hidden":false,"comment_hidden":false,"family_hidden":false,"value":""},"13":{"family":"","family_comment":"","comment":"","value_hidden":false,"comment_hidden":false,"family_hidden":false,"value":""},"14":{"family":"","family_comment":"","comment":"","value_hidden":false,"comment_hidden":false,"family_hidden":false,"value":""},"15":{"family":"","family_comment":"","comment":"","value_hidden":false,"comment_hidden":false,"family_hidden":false,"value":""},"16":{"family":"","family_comment":"","comment":"","value_hidden":false,"comment_hidden":false,"family_hidden":false,"value":""},"17":{"family":"","family_comment":"","comment":"","value_hidden":false,"comment_hidden":false,"family_hidden":false,"value":""},"18":{"family":"","family_comment":"","comment":"","value_hidden":false,"value_unclear":false,"comment_hidden":false,"family_hidden":false,"value":""},"19":{"family":"","family_comment":"","comment":"","value_hidden":false,"comment_hidden":false,"family_hidden":false,"value":""},"20":{"family_comment":"","comment":"","family":"","value_unclear":false,"comment_unclear":false,"value":"24"}},"general":{"family":[{"inn":"","family_name":"Писаний Віктор Григорович","relations_other":"","relations_hidden":false,"relations_unclear":false,"name_unclear":false,"inn_hidden":true,"name_hidden":true,"relations":"Подружжя"},{"inn":"","family_name":"Писаний Роман Вікторович","relations_hidden":false,"relations_unclear":false,"name_unclear":false,"relations":"Дитина","inn_hidden":false,"name_hidden":false,"relations_other":""},{"inn":"","family_name":"Писаний Максим Вікторович","relations_other":"","name_unclear":false,"inn_hidden":false,"name_hidden":false,"relations":"Дитина"}],"family_raw":"","name":"Таміла","full_name_suggest":{"input":["Писана Таміла Олександрівна","Таміла Олександрівна Писана","Таміла Писана"],"output":"Писана Таміла Олександрівна"},"name_unclear":false,"patronymic":"Олександрівна","inn_hidden":true,"addresses":[{"place_city_type_unclear":false,"place_district_hidden":false,"place_hidden":true,"place":"","place_city":"","place_unclear":false,"place_city_type_hidden":false,"place_city_type":"","place_city_hidden":false,"place_district":"","place_city_unclear":false,"place_address":"","place_address_hidden":false}],"inn":"","inn_unclear":false,"last_name":"Писана","full_name":"Писана Таміла Олександрівна","post":{"office":"Вищий спеціалізований суд з розгляду цивільних і кримінальних справ","post":"суддя вищого спеціалізованого суду україни з розгляду цивільних і кримінальних справ","candidate":"","office_hidden":false,"region":"Загальнодержавний регіон","region_hidden":false,"post_unclear":false,"office_unclear":false},"last_name_unclear":false},"liabilities":{"54":{"sum_comment":"","sum_hidden":false,"sum":"","sum_foreign_comment":"","sum_foreign":"","sum_foreign_hidden":false,"sum_comment_hidden":false},"55":{"sum_comment":"","sum_foreign_comment":"","sum_foreign":"","sum_hidden":false,"sum":""},"56":{"sum_comment":"","sum_foreign_comment":"","sum_foreign":"","sum":""},"57":{"sum_comment":"","sum_hidden":false,"sum":"","sum_foreign_comment":"","sum_foreign":"","sum_unclear":false,"sum_foreign_hidden":false,"sum_comment_hidden":false},"58":{"sum_comment":"","sum_hidden":false,"sum":"","sum_foreign_comment":"","sum_foreign":"","sum_unclear":false,"sum_foreign_hidden":false,"sum_comment_hidden":false},"59":{"sum_comment":"","sum_foreign_comment":"","sum_foreign":"","sum_hidden":false,"sum":""},"60":{"sum_comment":"","sum_hidden":false,"sum":"","sum_foreign_comment":"","sum_foreign":"","sum_unclear":false,"sum_foreign_hidden":false,"sum_comment_hidden":false},"61":{"sum_comment":"","sum_foreign_comment":"","sum_foreign":"","sum_hidden":false,"sum":""},"62":{"sum_comment":"","sum_hidden":false,"sum":"","sum_foreign_comment":"","sum_foreign":"","sum_comment_hidden":false},"63":{"sum_comment":"","sum_foreign_comment":"","sum_foreign":"","sum_hidden":false,"sum":""},"64":{"sum_comment":"","sum_foreign_comment":"","sum_foreign":"","sum_hidden":false,"sum":""}},"declaration":{"notfull_lostpages":"","additional_info_text":"Відомості про членів сім'ї не зазначено, оскільки вони не надали згоди на їх внесення до цієї декларації","additional_info":"1","date":"2014-03-28T00:00:00","notfull":"","url":"http://static.declarations.com.ua/declarations/chosen_ones/judges_batch/269_pysana_tamila_oleksandrivna.pdf"},"intro":{"declaration_year_hidden":false,"isnotdeclaration":"","declaration_year_unclear":false,"declaration_year":"2013"}}]