[{"id":"vulyk_104_165","ft_src":"2011\nFiat Linea\n1368 куб. см., 88 кВт\nMitsubishi Colt\n1.3 , 95 к. с\n2006\n63\n2015\n202578\n13398\n31323\n215976\n1368 куб. см., 88 кВт\nFiat Linea\n2011\nMitsubishi Colt\n1.3 , 95 к. с\n2006\n2015\nПодружжя\nПисьменна М. Ю. 12. 05. 1977\nДитина\nПисьменний С. О. 06. 12. 1998\nДитина\nПисьменна Д. О. 20. 10. 06\nПисьменний\nПисьменний Олексій Анатолійович\nОлексій Анатолійович Письменний\nОлексій Письменний\nПисьменний Олексій Анатолійович\nПисьменний Олексій Анатолійович\nОлексій\nАнатолійович\nЗагальний апеляційний суд\nсуддя апеляційного суду кіровоградської області\nКіровоградська область\n202578\n215976\n31323\n13398\n63\nПодружжя\nПисьменна М. Ю. 12. 05. 1977\nДитина\nПисьменний С. О. 06. 12. 1998\nПисьменна Д. О. 20. 10. 06\nДитина\nАнатолійович\nПисьменний\nсуддя апеляційного суду кіровоградської області\nЗагальний апеляційний суд\nКіровоградська область\nПисьменний Олексій Анатолійович\nПисьменний Олексій Анатолійович\nОлексій Анатолійович Письменний\nОлексій Письменний\nПисьменний Олексій Анатолійович\nОлексій","estate":{"25":[{"costs_unclear":false,"address":"","space_units":"м²","space_comment":"","region_hidden":true,"costs_comment":"","address_hidden":false,"space":"63","space_comment_unclear":false,"costs_rent_comment":"","costs":"","region":"","costs_rent":""}]},"vehicle":{"35":[{"sum_comment":"","brand_info":"1368 куб. см., 88 кВт","sum":"","sum_rent_comment":"","year":"2011","brand":"Fiat Linea","sum_rent":"","brand_info_unclear":false,"brand_hidden":false}],"40":[{"sum_comment":"","brand_info_hidden":false,"brand_info":"1.3 , 95 к. с","sum":"","sum_rent_comment":"","brand_hidden":false,"brand":"Mitsubishi Colt","sum_rent":"","brand_info_unclear":false,"year":"2006"}]},"source":"VULYK","income":{"5":{"family_comment":"","value":"215976","family":"31323","comment":""},"6":{"family_comment":"","value":"202578","family":"","comment":"","value_unclear":true},"7":{"source_name_hidden":false,"family_comment":"","comment":"","family":"","value":"","source_name":""},"8":{"family_comment":"","value":"","family":"","comment":""},"9":{"family_comment":"","value":"","family":"","comment":""},"10":{"family_comment":"","value":"13398","family":"","comment":""},"11":{"family_comment":"","value":"","family":"","comment":"","comment_hidden":false},"12":{"family_comment":"","value":"","family":"","comment":""},"13":{"family_comment":"","value":"","family":"","comment":""},"14":{"family_comment":"","value":"","family":"","comment":""},"15":{"family_comment":"","family":"","comment":"","value_unclear":false,"family_unclear":false,"value":""},"16":{"family_comment":"","value":"","family":"","comment":""},"17":{"family_comment":"","value":"","family":"","comment":""},"18":{"family_comment":"","value":"","family":"","comment":""},"19":{"family_comment":"","value":"","family":"","comment":""},"20":{"family_comment":"","comment_unclear":false,"value":"","family":"","comment":""}},"general":{"inn":"","addresses":[{"place_city_type_hidden":false,"place_city_type":"","place_city_hidden":true,"place_hidden":true,"place_district":"","place_district_hidden":false,"place":"","place_address":"","place_address_hidden":true,"place_city":""}],"last_name":"Письменний","full_name":"Письменний Олексій Анатолійович","family":[{"inn":"","family_name":"Письменна М. Ю. 12. 05. 1977","relations_other":"","name_unclear":false,"inn_hidden":true,"name_hidden":false,"relations":"Подружжя"},{"inn":"","family_name":"Письменний С. О. 06. 12. 1998","relations_other":"","name_unclear":false,"inn_hidden":false,"name_hidden":false,"relations":"Дитина"},{"inn":"","family_name":"Письменна Д. О. 20. 10. 06","relations_other":"","name_unclear":false,"inn_hidden":true,"relations":"Дитина"}],"patronymic":"Анатолійович","inn_hidden":true,"name":"Олексій","post":{"office":"Загальний апеляційний суд","region_unclear":false,"post":"суддя апеляційного суду кіровоградської області","region":"Кіровоградська область","office_unclear":false},"family_raw":"","full_name_suggest":{"input":["Письменний Олексій Анатолійович","Олексій Анатолійович Письменний","Олексій Письменний"],"output":"Письменний Олексій Анатолійович"}},"liabilities":{"54":{"sum_comment":"","sum_hidden":false,"sum":"","sum_foreign_comment":"","sum_foreign":"","sum_unclear":false,"sum_foreign_hidden":false,"sum_comment_hidden":false},"55":{"sum_comment":"","sum_foreign_comment":"","sum_foreign":"","sum":""},"56":{"sum_comment":"","sum_foreign_comment":"","sum_foreign":"","sum_unclear":false,"sum":""},"57":{"sum_comment_unclear":false,"sum_comment":"","sum":"","sum_foreign_comment":"","sum_foreign":"","sum_foreign_hidden":false,"sum_comment_hidden":false},"58":{"sum_comment":"","sum_foreign_comment":"","sum_foreign":"","sum_unclear":false,"sum":""},"59":{"sum_comment":"","sum_foreign_comment":"","sum_foreign":"","sum":""},"60":{"sum_comment":"","sum":"","sum_foreign_comment":"","sum_foreign":"","sum_foreign_hidden":false,"sum_comment_hidden":false},"61":{"sum_comment":"","sum_foreign_comment":"","sum_foreign":"","sum":""},"62":{"sum_comment":"","sum_foreign_comment":"","sum_foreign":"","sum":""},"63":{"sum_comment":"","sum_foreign_comment":"","sum_foreign":"","sum":""},"64":{"sum_comment":"","sum_foreign_comment":"","sum_foreign":"","sum":""}},"declaration":{"additional_info_text":"","additional_info":"","date":"2016-03-28T00:00:00","url":"http://static.declarations.com.ua/declarations/chosen_ones/judges_batch/1963_pysmennyi_oleksii_anatoliiovych_2015.pdf"},"intro":{"isnotdeclaration":"","declaration_year":"2015"}},{"id":"vulyk_83_36","ft_src":"1368 куб. см., 88 кВт\n2011\nFiat Linea\n1300 куб. см., 95 к. с\n2006\nMitsubishi Colt\n63\n2014\n27948\n207563\n2334\n13398\n183\n85985\n221145\n55702\n1368 куб. см., 88 кВт\nFiat Linea\n2011\n1300 куб. см., 95 к. с\n2006\nMitsubishi Colt\n63\nПодружжя\nПисьменна М. Ю\nДитина\nПисьменний С. О\nДитина\nПисьменна Д. О\nПисьменний Олексій Анатолійович\nОлексій Анатолійович Письменний\nОлексій Письменний\nПисьменний Олексій Анатолійович\nПисьменний Олексій Анатолійович\nОлексій\nАнатолійович\nЗагальний апеляційний суд\nКіровоградська область\nсуддя апеляційного суду кіровоградської області\nПисьменний\n183\n207563\n27948\n221145\n85985\n55702\n13398\n2334\n2014\nПисьменна М. Ю\nПодружжя\nПисьменний С. О\nДитина\nДитина\nПисьменна Д. О\nАнатолійович\nПисьменний\nОлексій\nПисьменний Олексій Анатолійович\nОлексій Анатолійович Письменний\nОлексій Письменний\nПисьменний Олексій Анатолійович\nКіровоградська область\nЗагальний апеляційний суд\nсуддя апеляційного суду кіровоградської області\nПисьменний Олексій Анатолійович","estate":{"25":[{"address":"","space_units":"м²","space_hidden":false,"space_unclear":false,"region_hidden":true,"costs_comment":"","space_comment":"","address_hidden":false,"costs":"","space_comment_unclear":false,"costs_rent_comment":"","space":"63","region_unclear":false,"region":"","costs_rent":""}]},"vehicle":{"35":[{"sum_comment":"","brand_info":"1368 куб. см., 88 кВт","sum":"","sum_rent_comment":"","year":"2011","brand":"Fiat Linea","sum_rent":"","brand_info_unclear":false}],"40":[{"sum_comment":"","brand_info":"1300 куб. см., 95 к. с","sum":"","sum_rent_comment":"","year":"2006","brand":"Mitsubishi Colt","sum_rent":"","brand_info_unclear":false}]},"source":"VULYK","income":{"5":{"family_comment":"","value":"221145","family":"85985","comment":""},"6":{"family_comment":"","family":"27948","comment":"","comment_hidden":false,"value":"207563","family_comment_hidden":false},"7":{"family_comment":"","comment":"","family":"","comment_unclear":false,"value":"183","source_name":""},"8":{"family_comment":"","value":"","family":"","comment":""},"9":{"family_comment":"","value":"","family":"","comment":""},"10":{"family_comment":"","family_hidden":false,"value":"13398","family":"2334","comment":""},"11":{"family_comment":"","value":"","family":"","comment":""},"12":{"family_comment":"","value":"","family":"","comment":""},"13":{"family_comment":"","value":"","family":"","comment":""},"14":{"family_comment":"","value":"","family":"","comment":""},"15":{"family_comment":"","value":"","family":"","comment":""},"16":{"family_comment":"","value":"","family":"55702","comment":""},"17":{"family_comment":"","value":"","family":"","comment":""},"18":{"family_comment":"","value":"","family":"","comment":""},"19":{"family_comment":"","value":"","family":"","comment":""},"20":{"family_comment":"","family":"","comment":"","value_unclear":false,"family_hidden":false,"value":""}},"general":{"family_raw":"","name":"Олексій","full_name_suggest":{"input":["Письменний Олексій Анатолійович","Олексій Анатолійович Письменний","Олексій Письменний"],"output":"Письменний Олексій Анатолійович"},"patronymic":"Анатолійович","inn_hidden":true,"addresses":[{"place_city_type_hidden":false,"place_district_hidden":false,"place_address_unclear":false,"place":"","place_city":"","place_city_type_unclear":false,"place_city_type":"","place_city_hidden":true,"place_district":"","place_city_unclear":false,"place_address":"","place_address_hidden":false,"place_hidden":true}],"inn":"","inn_unclear":false,"last_name":"Письменний","full_name":"Письменний Олексій Анатолійович","family":[{"inn":"","family_name":"Письменна М. Ю","relations_other":"","relations_hidden":false,"name_unclear":false,"inn_hidden":true,"name_hidden":false,"relations":"Подружжя"},{"inn":"","family_name":"Письменний С. О","relations_other":"","name_unclear":false,"inn_hidden":false,"name_hidden":false,"relations":"Дитина"},{"inn":"","family_name":"Письменна Д. О","relations_other":"","name_unclear":false,"name_hidden":false,"relations":"Дитина"}],"post":{"office":"Загальний апеляційний суд","post":"суддя апеляційного суду кіровоградської області","candidate":"","office_unclear":false,"region":"Кіровоградська область","post_unclear":false},"last_name_unclear":false},"liabilities":{"54":{"sum_comment":"","sum_foreign_comment":"","sum_foreign":"","sum":""},"55":{"sum_comment":"","sum_foreign_comment":"","sum_foreign":"","sum":""},"56":{"sum_comment":"","sum_foreign_comment":"","sum_foreign":"","sum":""},"57":{"sum_comment":"","sum_foreign_comment":"","sum_foreign":"","sum":""},"58":{"sum_comment":"","sum_foreign_comment":"","sum_foreign":"","sum":""},"59":{"sum_comment":"","sum_foreign_comment":"","sum_foreign":"","sum":""},"60":{"sum_comment":"","sum_foreign_comment":"","sum_foreign":"","sum":""},"61":{"sum_comment":"","sum_foreign_comment":"","sum_foreign":"","sum":""},"62":{"sum_comment":"","sum_foreign_comment":"","sum_foreign":"","sum":""},"63":{"sum_comment":"","sum_foreign_comment":"","sum_foreign":"","sum":""},"64":{"sum_comment":"","sum_foreign_comment":"","sum_foreign":"","sum":""}},"declaration":{"notfull_lostpages":"","additional_info_text":"","additional_info":"","date":"2015-03-24T00:00:00","notfull":"","url":"http://static.declarations.com.ua/declarations/chosen_ones/judges_batch/2306_pysmennyi_oleksii_anatoliiovych.pdf"},"intro":{"declaration_year":"2014"}},{"ft_src":"Fiat,Linea\n2011\nDaewoo,Matiz\n2007\n63\nFALSE\nFALSE\nFALSE\n2013\n16945\n182968\n24\n24\n4989\n12617\n21934\n195608\nFiat,Linea\n2011\nDaewoo,Matiz\n2007\nFALSE\nFALSE\n63\nСуддя апеляційного суду Кіровоградської області\nДружина Писмення М.Ю. 12.05.77;син Письменний С.О. 6.12.98;дочка Письменна Д.О. 20.10.06;\nПисьменний\nПисьменний Олексій Анатолійович\nОлексій Анатолійович Письменний\nОлексій Письменний\nПисьменний Олексій Анатолійович\nОлексій\nПисьменний Олексій Анатолійович\nЗагальний апеляційний суд\nСуддя\nКіровоградська область\nАнатолійович\n182968\n16945\n195608\n21934\n24\n24\n12617\n4989\n2013\nFALSE\nПисьменний\nАнатолійович\nДружина Писмення М.Ю. 12.05.77;син Письменний С.О. 6.12.98;дочка Письменна Д.О. 20.10.06;\nПисьменний Олексій Анатолійович\nОлексій Анатолійович Письменний\nОлексій Письменний\nПисьменний Олексій Анатолійович\nОлексій\nСуддя апеляційного суду Кіровоградської області\nСуддя\nКіровоградська область\nЗагальний апеляційний суд\nПисьменний Олексій Анатолійович","estate":{"23":[{"costs":"","address":"","space_units":"","costs_rent_comment":"","space":"","costs_comment":"","costs_rent":"","space_comment":"","region":"","location_raw":""},{"costs":"","address":"","space_units":"","costs_rent_comment":"","space":"","costs_comment":"","costs_rent":"","space_comment":"","region":"","location_raw":""},{"costs":"","address":"","space_units":"","costs_rent_comment":"","space":"","costs_comment":"","costs_rent":"","space_comment":"","region":"","location_raw":""}],"25":[{"costs":"","address":"","space_units":"","costs_rent_comment":"","space":"63","costs_comment":"","costs_rent":"","space_comment":"","region":"","location_raw":""}]},"vehicle":{"35":[{"sum_comment":"","brand_info":"","sum":"","sum_rent_comment":"","year":"2011","brand":"Fiat,Linea","sum_rent":"","brand_hidden":false}],"40":[{"sum_comment":"","brand_info":"","sum":"","sum_rent_comment":"","year":"2007","brand":"Daewoo,Matiz","sum_rent":"","brand_hidden":false}]},"id":"7249","income":{"5":{"family_comment":"","value":"195608","family":"21934","comment":""},"6":{"family_comment":"","value":"182968","family":"16945","comment":""},"7":{"family":"0","family_comment":"","value":"0","comment":"","source_name":"0"},"8":{"family_comment":"","value":"0","family":"0","comment":""},"9":{"family_comment":"","value":"0","family":"0","comment":""},"10":{"family_comment":"","value":"12617","family":"4989","comment":""},"11":{"family_comment":"","value":"24","family":"24","comment":""},"12":{"family_comment":"","value":"0","family":"0","comment":""},"13":{"family_comment":"","value":"0","family":"0","comment":""},"14":{"family_comment":"","value":"0","family":"0","comment":""},"15":{"family_comment":"","value":"0","family":"0","comment":""},"16":{"family_comment":"","value":"0","family":"0","comment":""},"17":{"family_comment":"","value":"0","family":"0","comment":""},"18":{"family_comment":"","value":"0","family":"0","comment":""},"19":{"family_comment":"","value":"0","family":"0","comment":""},"20":{"family_comment":"","value":"0","family":"0","comment":""},"21":[{"country_comment":"","uah_equal":"0","country":"0","cur":"0"},{"country_comment":"","uah_equal":"0","country":"0","cur":"0"},{"country_comment":"","uah_equal":"0","country":"0","cur":"0"},{"country_comment":"","uah_equal":"0","country":"0","cur":"0"},{"country_comment":"","uah_equal":"0","country":"0","cur":"0"}],"22":[{"country_comment":"","uah_equal":"0","country":"0","cur":"0"},{"country_comment":"","uah_equal":"0","country":"0","cur":"0"},{"country_comment":"","uah_equal":"0","country":"0","cur":"0"},{"country_comment":"","uah_equal":"0","country":"0","cur":"0"},{"country_comment":"","uah_equal":"0","country":"0","cur":"0"}]},"banks":{"45":[{"sum_units":"UAH","sum_comment":"","sum_foreign_units":"","sum":"","sum_foreign_comment":"","sum_foreign":""},{"sum_units":"USD","sum_comment":"","sum_foreign_units":"","sum":"","sum_foreign_comment":"","sum_foreign":""},{"sum_units":"EUR","sum_comment":"","sum_foreign_units":"","sum":"","sum_foreign_comment":"","sum_foreign":""}],"46":[{"sum_units":"UAH","sum_comment":"","sum_foreign_units":"","sum":"","sum_foreign_comment":"","sum_foreign":""},{"sum_units":"USD","sum_comment":"","sum_foreign_units":"","sum":"","sum_foreign_comment":"","sum_foreign":""},{"sum_units":"EUR","sum_comment":"","sum_foreign_units":"","sum":"","sum_foreign_comment":"","sum_foreign":""}],"47":[{"sum_units":"","sum_comment":"","sum_foreign_units":"","sum":"","sum_foreign_comment":"","sum_foreign":""}],"48":[{"sum_units":"","sum_comment":"","sum_foreign_units":"","sum":"","sum_foreign_comment":"","sum_foreign":""}],"49":[{"sum_units":"","sum_comment":"","sum_foreign_units":"","sum":"","sum_foreign_comment":"","sum_foreign":""}],"50":[{"sum_units":"","sum_comment":"","sum_foreign_units":"","sum":"","sum_foreign_comment":"","sum_foreign":""}],"51":[{"sum_units":"UAH","sum_comment":"","sum_foreign_units":"","sum":"","sum_foreign_comment":"","sum_foreign":""},{"sum_units":"USD","sum_comment":"","sum_foreign_units":"","sum":"","sum_foreign_comment":"","sum_foreign":""},{"sum_units":"EUR","sum_comment":"","sum_foreign_units":"","sum":"","sum_foreign_comment":"","sum_foreign":""}],"52":[{"sum_units":"","sum_comment":"","sum_foreign_units":"","sum":"","sum_foreign_comment":"","sum_foreign":""}],"53":[{"sum_units":"","sum_comment":"","sum_foreign_units":"","sum":"","sum_foreign_comment":"","sum_foreign":""}]},"declaration":{"notfull_lostpages":"","additional_info_text":"","additional_info":"FALSE","notfull":"FALSE","url":"http://static.declarations.com.ua/declarations/sudy/apeliatsiini_sudy_oblastei__m.kyieva/kirovohradska/pysmennyi.pdf","needs_scancopy_check":false},"general":{"family_raw":"Дружина Писмення М.Ю. 12.05.77;син Письменний С.О. 6.12.98;дочка Письменна Д.О. 20.10.06;","name":"Олексій","full_name_suggest":{"input":["Письменний Олексій Анатолійович","Олексій Анатолійович Письменний","Олексій Письменний"],"output":"Письменний Олексій Анатолійович"},"post_raw":"Суддя апеляційного суду Кіровоградської області","name_unclear":false,"patronymic":"Анатолійович","patronymic_unclear":false,"last_name_hidden":false,"patronymic_hidden":false,"inn":"","addresses_raw_hidden":true,"last_name":"Письменний","full_name":"Письменний Олексій Анатолійович","post":{"office":"Загальний апеляційний суд","region":"Кіровоградська область","post":"Суддя"},"addresses_raw":"","name_hidden":false,"last_name_unclear":false},"liabilities":{"54":{"sum_comment":"","sum_foreign_comment":"","sum_foreign":"","sum":""},"55":{"sum_units":"","sum_comment":"","sum_foreign_units":"","sum":"","sum_foreign_comment":"","sum_foreign":""},"56":{"sum_comment":"","sum_foreign_comment":"","sum_foreign":"","sum":""},"57":{"sum_comment":"","sum_foreign_comment":"","sum_foreign":"","sum":""},"58":{"sum_comment":"","sum_foreign_comment":"","sum_foreign":"","sum":""},"59":{"sum_comment":"","sum_foreign_comment":"","sum_foreign":"","sum":""},"60":{"sum_comment":"","sum_foreign_comment":"","sum_foreign":"","sum":""},"61":{"sum_units":"","sum_comment":"","sum_foreign_units":"","sum":"","sum_foreign_comment":"","sum_foreign":""},"62":{"sum_comment":"","sum_foreign_comment":"","sum_foreign":"","sum":""},"63":{"sum_comment":"","sum_units":"","sum_foreign":"","sum":"","sum_foreign_comment":""},"64":{"sum_comment":"","sum_units":"","sum_foreign":"","sum":"","sum_foreign_comment":""}},"intro":{"isnotdeclaration":"FALSE","declaration_year":"2013"}}]