[{"id":"vulyk_97_117","ft_src":"1600 куб. см.\nВАЗ 2101\n1980\nOpel Kadett\n1400 куб. см.\n1991\n79.2\nм. Херсон\nХерсонська область\n2013\n194368\n194368\n1600 куб. см.\nВАЗ 2101\n1980\nOpel Kadett\n1400 куб. см.\n1991\n2013\nЗагальний місцевий суд\nХерсонська область\nсуддя каховського міськрайонного суду херсонської області\nПодіновська Галина Володимирівна\nГалина Володимирівна Подіновська\nГалина Подіновська\nПодіновська Галина Володимирівна\nПодіновська Галина Володимирівна\nГалина\nПодіновська\nВолодимирівна\nХерсонська область\n74800\nКаховка\n194368\n194368\n79.2\nм. Херсон\nХерсонська область\nВолодимирівна\nПодіновська\nГалина\nПодіновська Галина Володимирівна\nГалина Володимирівна Подіновська\nГалина Подіновська\nПодіновська Галина Володимирівна\n74800\nКаховка\nХерсонська область\nХерсонська область\nЗагальний місцевий суд\nсуддя каховського міськрайонного суду херсонської області\nПодіновська Галина Володимирівна","estate":{"25":[{"address":"м. Херсон","space_units":"м²","space_hidden":false,"space_unclear":false,"region_hidden":false,"costs_rent_comment":"","space_comment":"","address_hidden":false,"space_comment_hidden":false,"costs":"","space_comment_unclear":false,"costs_comment":"","space":"79.2","region_unclear":false,"region":"Херсонська область","costs_rent":""}]},"vehicle":{"35":[{"year_hidden":false,"brand_info":"1600 куб. см.","brand_unclear":false,"sum_rent_comment":"","brand_hidden":false,"year":"1980","sum_comment":"","brand_info_hidden":false,"sum_rent":"","brand":"ВАЗ 2101","brand_info_unclear":false,"sum":""},{"sum_comment":"","brand_info_hidden":false,"sum_rent":"","sum":"","brand_unclear":false,"year":"1991","brand":"Opel Kadett","brand_info":"1400 куб. см.","sum_rent_comment":"","brand_info_unclear":false,"year_unclear":false}]},"source":"VULYK","income":{"5":{"family_comment":"","value":"194368","family":"","comment":""},"6":{"family_comment":"","family":"","comment":"","value_unclear":false,"family_unclear":false,"comment_hidden":false,"value":"194368"},"7":{"family":"","family_comment":"","value":"","comment":"","source_name":""},"8":{"family_comment":"","value":"","family":"","comment":""},"9":{"family_comment":"","value":"","family_unclear":false,"family":"","comment":""},"10":{"family_comment":"","value":"","family":"","comment":"","value_unclear":false},"11":{"family_comment":"","value":"","family":"","comment":""},"12":{"family_comment":"","value":"","family":"","comment":""},"13":{"family_comment":"","value":"","family":"","comment":""},"14":{"family_comment":"","value":"","family":"","comment":""},"15":{"family_comment":"","value":"","family":"","comment":""},"16":{"family_comment":"","value":"","family":"","comment":""},"17":{"family_comment":"","value":"","family":"","comment":""},"18":{"family_comment":"","value":"","family":"","comment":""},"19":{"family_comment":"","value":"","family":"","comment":""},"20":{"family_comment":"","comment":"","family":"","value_unclear":false,"comment_unclear":false,"value":"","family_hidden":false,"family_comment_unclear":false}},"general":{"family_raw":"","name":"Галина","full_name_suggest":{"input":["Подіновська Галина Володимирівна","Галина Володимирівна Подіновська","Галина Подіновська"],"output":"Подіновська Галина Володимирівна"},"patronymic":"Володимирівна","inn_hidden":true,"addresses":[{"place_city_type":"Місто","place_city_type_hidden":false,"place_hidden":false,"place_city_hidden":false,"place_district_hidden":false,"place_district":"","place_city_unclear":false,"place":"Херсонська область","place_city":"Каховка","place_address_hidden":true,"place_address":"74800"}],"last_name_hidden":false,"patronymic_hidden":false,"inn":"","inn_unclear":false,"last_name":"Подіновська","full_name":"Подіновська Галина Володимирівна","post":{"post_hidden":false,"office":"Загальний місцевий суд","post":"суддя каховського міськрайонного суду херсонської області","office_unclear":false,"region_unclear":false,"region":"Херсонська область"},"name_hidden":false},"liabilities":{"54":{"sum_comment_unclear":false,"sum_comment":"","sum_hidden":false,"sum":"","sum_foreign_comment":"","sum_foreign":"","sum_unclear":false,"sum_comment_hidden":false},"55":{"sum_comment":"","sum_foreign_comment":"","sum_foreign":"","sum":""},"56":{"sum_comment":"","sum_foreign_comment":"","sum_foreign":"","sum":""},"57":{"sum_comment_unclear":false,"sum_comment":"","sum_hidden":false,"sum":"","sum_foreign_comment":"","sum_foreign":"","sum_unclear":false,"sum_comment_hidden":false},"58":{"sum_comment_unclear":false,"sum_comment":"","sum_hidden":false,"sum":"","sum_foreign_comment":"","sum_foreign":"","sum_unclear":false,"sum_comment_hidden":false},"59":{"sum_comment":"","sum_foreign_comment":"","sum_foreign":"","sum":""},"60":{"sum_comment_unclear":false,"sum_comment":"","sum_hidden":false,"sum":"","sum_foreign_comment":"","sum_foreign":"","sum_comment_hidden":false},"61":{"sum_comment":"","sum_foreign_comment":"","sum_foreign":"","sum":""},"62":{"sum_comment":"","sum_foreign_comment":"","sum_foreign":"","sum_unclear":false,"sum":""},"63":{"sum_comment":"","sum_foreign_comment":"","sum_foreign":"","sum_hidden":false,"sum":""},"64":{"sum_comment":"","sum_foreign_comment":"","sum_foreign":"","sum":""}},"declaration":{"notfull_lostpages":"","additional_info_text":"","additional_info":"","date":"2014-12-10T00:00:00","notfull":"","url":"http://static.declarations.com.ua/declarations/chosen_ones/judges_batch/4019_podinovska_halyna_volodymyrivna_2013.pdf"},"intro":{"isnotdeclaration":"","declaration_year":"2013"}}]