[{"id":"vulyk_72_155","ft_src":"об'єм двигуна 1332 , потужність 95 к. с\nMitsubishi Colt\n2009\nоб'єм двигуна 1597 , потужність 103 к. с\nMitsubishi Carisma\n2002\nоб'єм двигуна 2360 , потужність 170 к. с\n2007\nMitsubishi Outlander\nм. Київ\nпр. Феодосіївський\n143.5\nКиївська область\n1/15 частина\nсмт. Клавдієво-Тарасове, вул. Леніна\n1/3 частина\nсмт. Клавдієво-Тарасове, вул. Лісова\nКиївська область\n74.2\nвул. Саперно-Слобідська\nм. Київ\n2014\n389891.91\n8544.26\nПАТ 'Страxова група 'ТАС',м. Київ\n538436.16\n140000\nдопомога по догляду за дитиною до 3х років\n12930\nоб'єм двигуна 1332 , потужність 95 к. с\nMitsubishi Colt\n2009\nоб'єм двигуна 1597 , потужність 103 к. с\nMitsubishi Carisma\n2002\nоб'єм двигуна 2360 , потужність 170 к. с\nMitsubishi Outlander\n2007\n1/3 частина\nКиївська область\nсмт. Клавдієво-Тарасове, вул. Лісова\nм. Київ\nпр. Феодосіївський\n143.5\n1/15 частина\nсмт. Клавдієво-Тарасове, вул. Леніна\nКиївська область\nвул. Саперно-Слобідська\n74.2\nм. Київ\nПодружжя\nГригорцов Костянтин Вадимович\nДитина\nГригорцов Костянтин Костянтинович\nДитина\nГригорцов Іван Костянтинович\nПолякова Людмила Володимирівна\nЛюдмила Володимирівна Полякова\nЛюдмила Полякова\nПолякова Людмила Володимирівна\nЛюдмила\nПолякова Людмила Володимирівна\nПолякова\nм. Київ\nЗагальний місцевий суд\nсуддя голосіївського районного суду міста києва\nВолодимирівна\nКиїв\n3028\nм. Київ\n15370\n389891.91\n12930\nдопомога по догляду за дитиною до 3х років\n8544.26\nПАТ 'Страxова група 'ТАС',м. Київ\n538436.16\n140000\n2014\n15370\nГригорцов Костянтин Вадимович\nПодружжя\nГригорцов Костянтин Костянтинович\nДитина\nГригорцов Іван Костянтинович\nДитина\nВолодимирівна\nПолякова\nПолякова Людмила Володимирівна\nЛюдмила Володимирівна Полякова\nЛюдмила Полякова\nПолякова Людмила Володимирівна\nм. Київ\nКиїв\n3028\nм. Київ\nЗагальний місцевий суд\nсуддя голосіївського районного суду міста києва\nПолякова Людмила Володимирівна\nЛюдмила","estate":{"25":[{"space_hidden":false,"space_comment":"","costs_comment":"","address_hidden":true,"space_comment_hidden":false,"address_unclear":false,"costs_rent_comment_unclear":false,"costs":"","costs_rent":"","address":"вул. Саперно-Слобідська","space_units":"м²","costs_hidden":false,"costs_rent_unclear":false,"costs_rent_hidden":false,"space_unclear":false,"costs_comment_hidden":false,"costs_rent_comment_hidden":false,"space_comment_unclear":false,"costs_comment_unclear":false,"costs_rent_comment":"","space":"74.2","region_hidden":true,"region":"м. Київ"}],"30":[{"costs_property_comment":"","address":"смт. Клавдієво-Тарасове, вул. Лісова","space_units":"м²","space_hidden":true,"space_unclear":false,"region_hidden":true,"costs_property":"","space_comment":"1/3 частина","address_hidden":true,"costs_rent_comment":"","space":"","region_unclear":false,"region":"Київська область","costs_rent":""}],"31":[{"costs_property_comment":"","address":"пр. Феодосіївський","space_units":"м²","space_hidden":false,"space_unclear":false,"region_hidden":true,"costs_property":"","space_comment":"","address_hidden":true,"address_unclear":true,"costs_rent_comment":"","space":"143.5","region":"м. Київ","space_units_hidden":false,"costs_rent":""},{"costs_property_comment":"","address":"смт. Клавдієво-Тарасове, вул. Леніна","space_units":"м²","costs_rent_comment":"","space":"","region":"Київська область","region_hidden":false,"costs_property":"","space_comment":"1/15 частина","address_hidden":true,"costs_rent":""}]},"vehicle":{"35":[{"sum_hidden":false,"brand_unclear":false,"sum_rent_comment":"","sum_rent_comment_unclear":false,"brand_hidden":false,"sum_comment":"","brand_info_hidden":false,"sum_rent":"","sum_rent_unclear":false,"brand":"Mitsubishi Colt","brand_info":"об'єм двигуна 1332 , потужність 95 к. с","brand_info_unclear":false,"year":"2009","sum":""}],"40":[{"year_hidden":false,"brand_info":"об'єм двигуна 1597 , потужність 103 к. с","sum_rent_comment":"","brand_unclear":true,"brand_hidden":false,"year":"2002","brand":"Mitsubishi Carisma","brand_info_hidden":false,"sum_rent":"","sum_comment":"","year_unclear":false,"brand_info_unclear":false,"sum":""},{"sum_comment":"","brand_info":"об'єм двигуна 2360 , потужність 170 к. с","sum":"","sum_rent_comment":"","year":"2007","brand":"Mitsubishi Outlander","sum_rent":""}]},"source":"VULYK","income":{"5":{"family":"538436.16","family_comment":"","comment":"","value_hidden":false,"value_unclear":false,"comment_hidden":false,"family_hidden":false,"family_unclear":false,"family_comment_hidden":false,"value":""},"6":{"family_comment":"","family":"389891.91","comment":"","value_unclear":false,"family_unclear":false,"family_hidden":false,"value":""},"7":{"source_name_hidden":false,"family_comment":"","comment":"","family":"","source_name_unclear":false,"value":"","family_hidden":false,"source_name":""},"8":{"family_comment":"","value":"","family":"","comment":""},"9":{"family_comment":"","family":"","comment":"","value_unclear":false,"family_hidden":false,"value":""},"10":{"family_comment":"","family":"","value_hidden":false,"comment":"","comment_unclear":false,"value_unclear":false,"value":"","family_hidden":false},"11":{"family_comment":"","value":"","family":"","comment":""},"12":{"family_comment":"","value":"","family":"","comment":""},"13":{"family_comment":"","value":"","family":"","comment":""},"14":{"family_comment":"","value":"","family":"","comment":""},"15":{"family_comment":"ПАТ 'Страxова група 'ТАС',м. Київ","family_hidden":false,"value":"","family":"8544.26","comment":""},"16":{"family_comment":"","family":"140000","comment":"","value_unclear":false,"family_hidden":false,"value":""},"17":{"family_comment":"","family_hidden":false,"value":"","family":"","comment":""},"18":{"family_comment":"","value":"","family":"","comment":"","value_unclear":false},"19":{"family_comment":"","value":"","family":"","comment":""},"20":{"family_comment":"","comment":"допомога по догляду за дитиною до 3х років","family":"","value_unclear":false,"family_unclear":false,"comment_unclear":false,"value":"12930","family_hidden":false}},"general":{"family":[{"inn":"","inn_unclear":false,"family_name":"Григорцов Костянтин Вадимович","relations_other":"","relations_hidden":false,"relations_unclear":false,"name_unclear":true,"inn_hidden":true,"name_hidden":true,"relations":"Подружжя"},{"inn":"","family_name":"Григорцов Костянтин Костянтинович","relations_other":"","relations_hidden":false,"name_unclear":true,"inn_hidden":false,"name_hidden":true,"relations":"Дитина"},{"inn":"","family_name":"Григорцов Іван Костянтинович","relations_other":"","relations_hidden":false,"name_unclear":true,"inn_hidden":false,"name_hidden":true,"relations":"Дитина"}],"family_raw":"","name":"Людмила","full_name_suggest":{"input":["Полякова Людмила Володимирівна","Людмила Володимирівна Полякова","Людмила Полякова"],"output":"Полякова Людмила Володимирівна"},"name_unclear":false,"patronymic":"Володимирівна","inn_hidden":true,"patronymic_unclear":false,"patronymic_hidden":false,"inn":"","inn_unclear":false,"last_name":"Полякова","full_name":"Полякова Людмила Володимирівна","post":{"post_hidden":false,"office":"Загальний місцевий суд","post":"суддя голосіївського районного суду міста києва","region_unclear":false,"candidate":"","region_hidden":false,"region":"м. Київ","office_hidden":false,"post_unclear":false,"office_unclear":false},"addresses":[{"place_city_type_hidden":false,"place_district_hidden":true,"place_address_unclear":false,"place":"м. Київ","place_city":"Київ","place_unclear":false,"place_city_type":"Місто","place_city_hidden":true,"place_city_unclear":false,"place_district":"","place_district_unclear":false,"place_address":"3028","place_address_hidden":true,"place_hidden":true}],"last_name_unclear":false},"liabilities":{"54":{"sum_comment":"","sum":"","sum_foreign_comment":"","sum_foreign":"","sum_unclear":true,"sum_comment_hidden":false},"55":{"sum_comment":"","sum_foreign_comment":"","sum_foreign":"","sum":""},"56":{"sum_comment":"","sum_foreign_comment":"","sum_foreign":"","sum_hidden":false,"sum":""},"57":{"sum_comment_unclear":false,"sum_comment":"","sum_hidden":false,"sum":"","sum_foreign_comment":"","sum_foreign":"","sum_unclear":false,"sum_comment_hidden":false},"58":{"sum_comment_unclear":false,"sum_comment":"","sum_hidden":false,"sum":"","sum_foreign_comment":"","sum_foreign":"","sum_unclear":false,"sum_comment_hidden":false},"59":{"sum_comment":"","sum":"","sum_foreign_comment":"","sum_foreign_unclear":false,"sum_foreign":"","sum_foreign_hidden":false,"sum_comment_hidden":false},"60":{"sum_comment":"","sum_hidden":false,"sum":"15370","sum_foreign_comment":"","sum_foreign":"","sum_foreign_hidden":false},"61":{"sum_comment":"","sum_hidden":false,"sum":"","sum_foreign_comment":"","sum_foreign":"","sum_foreign_hidden":false},"62":{"sum_comment":"","sum_hidden":false,"sum":"","sum_foreign_comment":"","sum_foreign":"","sum_foreign_hidden":false},"63":{"sum_comment_unclear":false,"sum_comment":"","sum_hidden":false,"sum":"","sum_foreign_comment":"","sum_foreign":"","sum_unclear":false,"sum_foreign_hidden":false,"sum_comment_hidden":false},"64":{"sum_comment":"","sum_hidden":false,"sum":"","sum_foreign_comment":"","sum_foreign":"","sum_foreign_hidden":false}},"declaration":{"notfull_lostpages":"","additional_info_text":"","additional_info":"","date":"2015-03-30T00:00:00","notfull":"","url":"http://static.declarations.com.ua/declarations/chosen_ones/epic_batch/poliakova_liudmyla_volodymyrivna.pdf"},"intro":{"isnotdeclaration":"","declaration_year_unclear":false,"declaration_year":"2014"}}]