[{"id":"vulyk_94_164","ft_src":"свідоцтво про право власності від 05. 12. 2014\n.055\nрішення Черкаської міскради від 14. 11. 2014 оренда (користування\nм. Черкаси\n18\nЧеркаська область\n11/20 свідоцтво про право на спадщину за законом\nм. Черкаси\nЧеркаська область\n85.9\nдоговір п/пр квартири від 11. 05. 2004\n50.3\nЧеркаська область\nм. Черкаси\n2014\n242763\n242763\n.055\nсвідоцтво про право власності від 05. 12. 2014\n18\nрішення Черкаської міскради від 14. 11. 2014 оренда (користування\nЧеркаська область\nм. Черкаси\n85.9\n11/20 свідоцтво про право на спадщину за законом\nм. Черкаси\nЧеркаська область\n50.3\nдоговір п/пр квартири від 11. 05. 2004\nЧеркаська область\nм. Черкаси\nЧеркаська область\nЧеркаси\nПозарецька Світлана Михайлівна\nСвітлана Михайлівна Позарецька\nСвітлана Позарецька\nПозарецька Світлана Михайлівна\nПозарецька Світлана Михайлівна\nСвітлана\nМихайлівна\nЗагальний місцевий суд\nЧеркаська область\nсуддя придніпровського районного суду м. черкаси\nПозарецька\n1207\n242763\n242763\n2014\n1207\nМихайлівна\nПозарецька\nСвітлана\nПозарецька Світлана Михайлівна\nСвітлана Михайлівна Позарецька\nСвітлана Позарецька\nПозарецька Світлана Михайлівна\nЧеркаська область\nЧеркаси\nЧеркаська область\nЗагальний місцевий суд\nсуддя придніпровського районного суду м. черкаси\nПозарецька Світлана Михайлівна","estate":{"23":[{"costs":"","address":"","space_units":"га","costs_rent_hidden":false,"space_unclear":false,"region_hidden":true,"space_units_unclear":false,"costs_comment":"","address_hidden":false,"space_hidden":false,"address_unclear":false,"space_comment":"свідоцтво про право власності від 05. 12. 2014","costs_rent_comment":"","space":".055","region_unclear":false,"costs_rent_comment_hidden":false,"region":"","costs_rent":""},{"address":"м. Черкаси","space_units":"м²","costs_rent_hidden":false,"space_comment":"рішення Черкаської міскради від 14. 11. 2014 оренда (користування","costs_rent_comment_hidden":false,"region":"Черкаська область","costs_comment":"","space":"18","address_unclear":false,"costs_rent_comment":"","costs":"","region_unclear":false,"region_hidden":false,"costs_rent":""}],"24":[{"costs":"","address":"м. Черкаси","space_units":"м²","space_hidden":false,"space_unclear":false,"costs_rent_comment_hidden":false,"costs_comment":"","address_hidden":false,"costs_rent_hidden":false,"space_comment":"11/20 свідоцтво про право на спадщину за законом","costs_rent_comment":"","space":"85.9","region_hidden":true,"region":"Черкаська область","costs_rent":""}],"25":[{"space":"50.3","address":"м. Черкаси","space_units":"м²","costs_rent_hidden":false,"space_unclear":false,"costs_rent_comment_hidden":false,"costs_rent_comment":"","space_comment":"договір п/пр квартири від 11. 05. 2004","space_comment_unclear":false,"space_hidden":false,"address_unclear":false,"address_hidden":false,"costs_comment":"","costs":"","region_unclear":false,"region_hidden":true,"region":"Черкаська область","costs_rent":""}]},"source":"VULYK","income":{"5":{"family_comment":"","family":"","comment":"","value_unclear":false,"family_hidden":false,"value":"242763"},"6":{"family_comment":"","value":"242763","family":"","comment":"","value_unclear":false},"7":{"source_name_hidden":false,"family_comment":"","comment":"","family":"","source_name_unclear":false,"value":"","source_name":""},"8":{"family_comment":"","value":"","family":"","comment":""},"9":{"family_comment":"","comment_unclear":false,"value":"","family":"","comment":""},"10":{"family_comment":"","value":"","family":"","comment":""},"11":{"family_comment":"","value":"","family_unclear":false,"family":"","comment":""},"12":{"family_comment":"","value":"","family":"","comment":""},"13":{"family_comment":"","value":"","family":"","comment":""},"14":{"family_comment":"","value":"","family":"","comment":""},"15":{"family_comment":"","value":"","family":"","comment":""},"16":{"family_comment":"","value":"","family":"","comment":""},"17":{"family_comment":"","value":"","family":"","comment":""},"18":{"family_comment":"","value":"","family":"","comment":""},"19":{"family_comment":"","value":"","family":"","comment":""},"20":{"family_comment":"","comment":"","family":"","value_unclear":false,"comment_unclear":false,"value":""}},"general":{"family_raw":"","name":"Світлана","full_name_suggest":{"input":["Позарецька Світлана Михайлівна","Світлана Михайлівна Позарецька","Світлана Позарецька"],"output":"Позарецька Світлана Михайлівна"},"patronymic":"Михайлівна","inn_hidden":true,"addresses":[{"place_city_type_hidden":false,"place_district_hidden":false,"place_city_hidden":false,"place_district":"","place_city_type":"Місто","place_address":"","place":"Черкаська область","place_city":"Черкаси","place_address_hidden":false,"place_hidden":false}],"patronymic_hidden":false,"inn":"","inn_unclear":false,"last_name":"Позарецька","full_name":"Позарецька Світлана Михайлівна","post":{"post_hidden":false,"office":"Загальний місцевий суд","post":"суддя придніпровського районного суду м. черкаси","candidate":"","region_unclear":false,"region":"Черкаська область","post_unclear":false,"office_unclear":false}},"liabilities":{"54":{"sum_comment_unclear":false,"sum_comment":"","sum":"","sum_foreign_comment":"","sum_foreign":"","sum_unclear":false,"sum_comment_hidden":false},"55":{"sum_comment":"","sum_foreign_comment":"","sum_foreign":"","sum":""},"56":{"sum_comment":"","sum_foreign_comment":"","sum_foreign":"","sum_unclear":false,"sum":"1207"},"57":{"sum_comment":"","sum_hidden":false,"sum":"","sum_foreign_comment":"","sum_foreign":"","sum_unclear":false},"58":{"sum_comment":"","sum_hidden":false,"sum":"","sum_foreign_comment":"","sum_foreign":"","sum_unclear":false},"59":{"sum_comment":"","sum_foreign_comment":"","sum_foreign":"","sum":""},"60":{"sum_comment":"","sum_foreign_comment":"","sum_foreign":"","sum":"","sum_comment_hidden":false},"61":{"sum_comment":"","sum_foreign_comment":"","sum_foreign":"","sum":""},"62":{"sum_comment":"","sum_foreign_comment":"","sum_foreign":"","sum_hidden":false,"sum":""},"63":{"sum_comment":"","sum_foreign_comment":"","sum_foreign":"","sum":"","sum_comment_hidden":false},"64":{"sum_comment":"","sum_foreign_comment":"","sum_foreign":"","sum_unclear":false,"sum":""}},"declaration":{"notfull_lostpages":"","additional_info_text":"","additional_info":"","date":"2015-03-30T00:00:00","notfull":"","url":"http://static.declarations.com.ua/declarations/chosen_ones/judges_batch/3810_pozaretska_svitlana_mykhailivna.pdf"},"intro":{"isnotdeclaration":"","declaration_year":"2014"}}]