[{"id":"vulyk_84_168","ft_src":"Кримська Автономна Республіка\nСакський р-н, с. Михайлівка\n998\n7000\n1\nМісце проживання за реєстрацією 96500, АРК, м. Саки\n2014\nМісце проживання за реєстрацією 96500, АРК, м. Саки\n1\n2014\nРоманюк Євген Вікторович\nЄвген Вікторович Романюк\nЄвген Романюк\nРоманюк Євген Вікторович\nЄвген\nДитина\nРоманюк Єлізавета Євгенівна, 02. 12. 1997\nРоманюк Євген Вікторович\nВікторович\nсуддя кіровського районного суд м. кіровограда\nЗагальний місцевий суд\nКіровоградська область\nРоманюк\nКіровоград\n25006\nКіровоградська область\n231815\n22362\n254177\n998\nКримська Автономна Республіка\nСакський р-н, с. Михайлівка\n7000\n231815\n254177\n22362\nРоманюк Єлізавета Євгенівна, 02. 12. 1997\nДитина\nВікторович\nРоманюк\nЄвген\nРоманюк Євген Вікторович\nЄвген Вікторович Романюк\nЄвген Романюк\nРоманюк Євген Вікторович\nКіровоградська область\nКіровоград\n25006\nКіровоградська область\nсуддя кіровського районного суд м. кіровограда\nЗагальний місцевий суд\nРоманюк Євген Вікторович","estate":{"23":[{"address":"Сакський р-н, с. Михайлівка","space_units":"м²","costs_comment":"","space_comment":"","region_hidden":false,"region":"Кримська Автономна Республіка","address_hidden":false,"costs":"","address_unclear":false,"space_comment_unclear":false,"costs_rent_comment":"","space":"998","region_unclear":false,"costs_rent":""}]},"source":"VULYK","income":{"5":{"family_comment":"","family":"","comment":"","value_unclear":false,"family_unclear":false,"comment_unclear":false,"value":"254177"},"6":{"family_comment":"","comment_unclear":false,"value":"231815","family":"","comment":""},"7":{"family":"","family_comment":"","value":"","comment":"","source_name":""},"8":{"family_comment":"","value":"","family":"","comment":""},"9":{"family_comment":"","value":"","family":"","comment":"","value_unclear":false},"10":{"family_comment":"","value":"","family":"","comment":"","value_unclear":false},"11":{"family_comment":"","value":"","family":"","comment":""},"12":{"family_comment":"","value":"","family":"","comment":""},"13":{"family_comment":"","value":"","family":"","comment":""},"14":{"family_comment":"","value":"","family":"","comment":""},"15":{"family_comment":"","value":"","family":"","comment":""},"16":{"family_comment":"","value":"","family":"","comment":""},"17":{"family_comment":"","value":"","family":"","comment":"","value_unclear":false},"18":{"family_comment":"","value":"","family":"","comment":"","value_unclear":false},"19":{"family_comment":"","value":"","family":"","comment":""},"20":{"family_comment":"","family":"","comment":"","value_unclear":false,"family_unclear":false,"comment_unclear":false,"value":"22362"}},"banks":{"45":[{"sum_comment_unclear":false,"sum_comment":"","sum_foreign_units":"UAH","sum":"7000","sum_foreign_comment":"","sum_foreign":"","sum_unclear":false,"sum_units":"UAH"}]},"declaration":{"notfull_lostpages":"","additional_info_text":"Місце проживання за реєстрацією 96500, АРК, м. Саки","additional_info":"1","date":"2015-03-24T00:00:00","notfull":"","url":"http://static.declarations.com.ua/declarations/chosen_ones/judges_batch/2582_romaniuk_ievhen_viktorovych.pdf"},"general":{"family_raw":"","name":"Євген","full_name_suggest":{"input":["Романюк Євген Вікторович","Євген Вікторович Романюк","Євген Романюк"],"output":"Романюк Євген Вікторович"},"patronymic":"Вікторович","inn_hidden":true,"addresses":[{"place_city_type_hidden":false,"place_district_hidden":false,"place_address_unclear":false,"place":"Кіровоградська область","place_city":"Кіровоград","place_unclear":false,"place_city_type_unclear":false,"place_city_type":"Місто","place_city_hidden":false,"place_city_unclear":false,"place_district":"","place_district_unclear":false,"place_address":"25006","place_address_hidden":false,"place_hidden":false}],"inn":"","inn_unclear":false,"last_name":"Романюк","full_name":"Романюк Євген Вікторович","family":[{"inn":"","inn_unclear":false,"family_name":"Романюк Єлізавета Євгенівна, 02. 12. 1997","relations_other":"","relations_hidden":false,"name_unclear":false,"inn_hidden":true,"name_hidden":false,"relations":"Дитина"}],"post":{"post_hidden":false,"office":"Загальний місцевий суд","region_hidden":false,"post":"суддя кіровського районного суд м. кіровограда","candidate":"","region_unclear":false,"region":"Кіровоградська область","office_hidden":false,"post_unclear":false,"office_unclear":false}},"liabilities":{"54":{"sum_comment":"","sum_foreign_comment":"","sum_foreign":"","sum":"","sum_comment_hidden":false},"55":{"sum_comment":"","sum_foreign_comment":"","sum_foreign":"","sum":""},"56":{"sum_comment":"","sum_foreign_comment":"","sum_foreign":"","sum":""},"57":{"sum_comment":"","sum_foreign_comment":"","sum_foreign":"","sum":"","sum_comment_hidden":false},"58":{"sum_comment":"","sum_foreign_comment":"","sum_foreign":"","sum":"","sum_comment_hidden":false},"59":{"sum_comment":"","sum_foreign_comment":"","sum_foreign":"","sum":""},"60":{"sum_comment":"","sum_foreign_comment":"","sum_foreign":"","sum":""},"61":{"sum_comment":"","sum_foreign_comment":"","sum_foreign":"","sum":""},"62":{"sum_comment":"","sum_foreign_comment":"","sum_foreign":"","sum":""},"63":{"sum_comment":"","sum_foreign_comment":"","sum_foreign":"","sum":"","sum_comment_hidden":false},"64":{"sum_comment":"","sum_foreign_comment":"","sum_foreign":"","sum":"","sum_comment_hidden":false}},"intro":{"isnotdeclaration":"","declaration_year_unclear":false,"declaration_year":"2014"}}]