[{"id":"vulyk_97_2","ft_src":"1330 куб. см., 99 (73 ) /6000\nToyota Corolla\n2010\nToyota Yaris\n998 куб. см., безоплатне право керування\n2012\nToyota Yaris\n998 куб. см., 69 (51 ) /6000\n2012\n1330 куб. см., безоплатне право користування\n2010\nToyota Corolla\n3-х кімнатна\n116.3\n2014\n3068\n191488\n36517\n2624\n989884\n219112\n950299\n1330 куб. см., 99 (73 ) /6000\nToyota Corolla\n2010\nToyota Yaris\n998 куб. см., безоплатне право керування\n2012\n998 куб. см., 69 (51 ) /6000\nToyota Yaris\n2012\n1330 куб. см., безоплатне право користування\n2010\nToyota Corolla\n2014\nШабас Ольга Сергіївна\nОльга Сергіївна Шабас\nОльга Шабас\nШабас Ольга Сергіївна\nОльга\nПодружжя\nШабас І. В\nШабас Ольга Сергіївна\nШабас\nЗагальний місцевий суд\nХарківська область\nсуддя золочівського районного суду харківської області, голова золочівського районного суду харківської області\nСергіївна\n73303\n2196 - Укргазбанк 71107 - Приватбанк\n45003\n6126 - Укргазбанк 38877 - Приватбанк\n7260\n3726 - СК 'ВУСО' 3534 - СК 'АХХА'\nСК 'Інго Україна'\n5910\n191488\n3068\n950299\n2624\n36517\n219112\n989884\n116.3\n3-х кімнатна\n2196 - Укргазбанк 71107 - Приватбанк\n73303\n6126 - Укргазбанк 38877 - Приватбанк\n45003\n3726 - СК 'ВУСО' 3534 - СК 'АХХА'\n7260\nСК 'Інго Україна'\n5910\nПодружжя\nШабас І. В\nСергіївна\nШабас\nОльга\nШабас Ольга Сергіївна\nОльга Сергіївна Шабас\nОльга Шабас\nШабас Ольга Сергіївна\nХарківська область\nЗагальний місцевий суд\nсуддя золочівського районного суду харківської області, голова золочівського районного суду харківської області\nШабас Ольга Сергіївна","estate":{"25":[{"address":"","space_units":"м²","space_hidden":false,"space_unclear":false,"region_hidden":true,"costs_rent_comment":"","space_comment":"3-х кімнатна","address_hidden":true,"space_comment_hidden":false,"costs":"","space_comment_unclear":false,"costs_comment":"","space":"116.3","region_unclear":false,"region":"","costs_rent":""}]},"vehicle":{"35":[{"year_hidden":false,"brand_info":"1330 куб. см., 99 (73 ) /6000","brand_unclear":false,"sum_rent_comment":"","brand_hidden":false,"year":"2010","sum_comment":"","brand_info_hidden":false,"sum_rent":"","brand":"Toyota Corolla","brand_info_unclear":false,"sum":""},{"sum_comment":"","brand_info_hidden":false,"sum_rent":"","sum":"","brand_unclear":false,"year":"2012","brand":"Toyota Yaris","brand_info":"998 куб. см., безоплатне право керування","sum_rent_comment":"","brand_info_unclear":false,"year_unclear":false}],"40":[{"sum_comment":"","brand_info":"998 куб. см., 69 (51 ) /6000","brand_unclear":false,"sum_rent_comment":"","year":"2012","brand":"Toyota Yaris","sum_rent":"","brand_info_unclear":false,"year_unclear":false,"sum":""},{"sum_comment":"","brand_info":"1330 куб. см., безоплатне право користування","sum":"","sum_rent_comment":"","year":"2010","brand":"Toyota Corolla","sum_rent":""}]},"source":"VULYK","income":{"5":{"family_comment":"","value":"219112","family":"989884","comment":""},"6":{"family_comment":"","family":"3068","comment":"","value_unclear":false,"family_unclear":false,"comment_hidden":false,"value":"191488"},"7":{"family":"","family_comment":"","value":"","comment":"","source_name":""},"8":{"family_comment":"","value":"","family":"","comment":""},"9":{"family_comment":"","value":"","family_unclear":false,"family":"","comment":""},"10":{"family_comment":"","value":"","family":"","comment":"","value_unclear":false},"11":{"family_comment":"","value":"","family":"","comment":""},"12":{"family_comment":"","value":"","family":"","comment":""},"13":{"family_comment":"","value":"","family":"","comment":""},"14":{"family_comment":"","value":"","family":"","comment":""},"15":{"family_comment":"","value":"2624","family":"36517","comment":""},"16":{"family_comment":"","value":"","family":"","comment":""},"17":{"family_comment":"","value":"","family":"950299","comment":""},"18":{"family_comment":"","value":"","family":"","comment":""},"19":{"family_comment":"","value":"","family":"","comment":""},"20":{"family_comment":"","comment":"","family":"","value_unclear":false,"comment_unclear":false,"value":"","family_hidden":false,"family_comment_unclear":false}},"general":{"family":[{"inn":"","family_name":"Шабас І. В","relations_other":"","name_unclear":false,"inn_hidden":true,"name_hidden":true,"relations":"Подружжя"}],"family_raw":"","name":"Ольга","full_name_suggest":{"input":["Шабас Ольга Сергіївна","Ольга Сергіївна Шабас","Ольга Шабас"],"output":"Шабас Ольга Сергіївна"},"patronymic":"Сергіївна","inn_hidden":true,"addresses":[{"place_city_type":"","place_city_type_hidden":false,"place_hidden":true,"place_city_hidden":true,"place_district_hidden":true,"place_district":"","place_city_unclear":false,"place":"","place_city":"","place_address_hidden":true,"place_address":""}],"last_name_hidden":false,"patronymic_hidden":false,"inn":"","inn_unclear":false,"last_name":"Шабас","full_name":"Шабас Ольга Сергіївна","post":{"post_hidden":false,"office":"Загальний місцевий суд","post":"суддя золочівського районного суду харківської області, голова золочівського районного суду харківської області","office_unclear":false,"region_unclear":false,"region":"Харківська область"},"name_hidden":false},"liabilities":{"54":{"sum_comment_unclear":false,"sum_comment":"3726 - СК 'ВУСО' 3534 - СК 'АХХА'","sum_hidden":false,"sum":"7260","sum_foreign_comment":"","sum_foreign":"","sum_unclear":false,"sum_comment_hidden":false},"55":{"sum_comment":"","sum_foreign_comment":"","sum_foreign":"","sum":""},"56":{"sum_comment":"","sum_foreign_comment":"","sum_foreign":"","sum":""},"57":{"sum_comment_unclear":false,"sum_comment":"6126 - Укргазбанк 38877 - Приватбанк","sum_hidden":false,"sum":"45003","sum_foreign_comment":"","sum_foreign":"","sum_unclear":false,"sum_comment_hidden":false},"58":{"sum_comment_unclear":false,"sum_comment":"2196 - Укргазбанк 71107 - Приватбанк","sum_hidden":false,"sum":"73303","sum_foreign_comment":"","sum_foreign":"","sum_unclear":false,"sum_comment_hidden":false},"59":{"sum_comment":"","sum_foreign_comment":"","sum_foreign":"","sum":""},"60":{"sum_comment_unclear":false,"sum_comment":"СК 'Інго Україна'","sum_hidden":false,"sum":"5910","sum_foreign_comment":"","sum_foreign":"","sum_comment_hidden":false},"61":{"sum_comment":"","sum_foreign_comment":"","sum_foreign":"","sum":""},"62":{"sum_comment":"","sum_foreign_comment":"","sum_foreign":"","sum_unclear":false,"sum":""},"63":{"sum_comment":"","sum_foreign_comment":"","sum_foreign":"","sum_hidden":false,"sum":""},"64":{"sum_comment":"","sum_foreign_comment":"","sum_foreign":"","sum":""}},"declaration":{"notfull_lostpages":"","additional_info_text":"","additional_info":"","date":"2015-03-31T00:00:00","notfull":"","url":"http://static.declarations.com.ua/declarations/chosen_ones/judges_batch/3823_shabas_olha_serhiivna.pdf"},"intro":{"isnotdeclaration":"","declaration_year":"2014"}}]