[{"id":"vulyk_92_74","ft_src":"у власності 3/4\n45.98\nХарківська область\nу тимчасовому користуванні\nм. Харків\nбезоплатне користування\n36.33\nХарківська область\n8419\n2014\n2014\nШевченко Вікторія Валентинівна\nВікторія Валентинівна Шевченко\nВікторія Шевченко\nШевченко Вікторія Валентинівна\nШевченко Вікторія Валентинівна\nВікторія\nШевченко\nЗагальний апеляційний суд\nсуддя апеляційного суду харківської області\nХарківська область\nВалентинівна\n265661\n265661\n45.98\nу власності 3/4\nХарківська область\nм. Харків\nбезоплатне користування\n36.33\nу тимчасовому користуванні\nХарківська область\n8419\n265661\n265661\nШевченко Вікторія Валентинівна\nВікторія Валентинівна Шевченко\nВікторія Шевченко\nШевченко Вікторія Валентинівна\nВалентинівна\nШевченко\nВікторія\nХарківська область\nЗагальний апеляційний суд\nсуддя апеляційного суду харківської області\nШевченко Вікторія Валентинівна","estate":{"25":[{"address":"","space_units":"м²","space_hidden":false,"space_comment":"у власності 3/4","region_hidden":false,"costs_comment":"","address_hidden":true,"costs":"","address_unclear":false,"space_comment_unclear":false,"costs_rent_comment":"","space":"45.98","region":"Харківська область","costs_rent":""},{"costs":"","address":"м. Харків","space_units":"м²","costs_rent_comment":"безоплатне користування","space":"36.33","space_comment":"у тимчасовому користуванні","region_hidden":false,"costs_comment":"","region":"Харківська область","address_hidden":false,"costs_rent":""}]},"source":"VULYK","income":{"5":{"family_comment":"","family_hidden":false,"value":"265661","family":"","comment":""},"6":{"family_comment":"","family":"","comment":"","value_unclear":false,"family_hidden":false,"value":"265661"},"7":{"family_comment":"","comment":"","family":"","value_unclear":false,"value":"","source_name":""},"8":{"family_comment":"","value":"","family":"","comment":""},"9":{"family_comment":"","value":"","family":"","comment":""},"10":{"family_comment":"","comment":"","family":"","family_unclear":false,"comment_unclear":false,"value":"","family_comment_unclear":false},"11":{"family_comment":"","value":"","family":"","comment":"","value_unclear":false},"12":{"family_comment":"","value":"","family":"","comment":""},"13":{"family_comment":"","value":"","family":"","comment":""},"14":{"family_comment":"","value":"","family":"","comment":""},"15":{"family_comment":"","comment":"","family":"","family_unclear":false,"comment_unclear":false,"value":""},"16":{"family_comment":"","value":"","family":"","comment":""},"17":{"family_comment":"","value":"","family":"","comment":""},"18":{"family_comment":"","value":"","family_unclear":false,"family":"","comment":""},"19":{"family_comment":"","value":"","family":"","comment":""},"20":{"family_comment":"","value":"","family_unclear":false,"family":"","comment":""}},"banks":{"45":[{"sum_units":"UAH","sum_comment":"","sum_foreign_units_hidden":false,"sum_foreign_units":"UAH","sum_hidden":false,"sum":"8419","sum_foreign_comment":"","sum_foreign":"","sum_comment_hidden":false,"sum_foreign_hidden":false,"sum_comment_unclear":false}]},"declaration":{"notfull_lostpages":"","additional_info_text":"","additional_info":"","date":"2015-03-27T00:00:00","notfull":"","url":"http://static.declarations.com.ua/declarations/chosen_ones/judges_batch/3322_shevchenko_viktoriia_valentynivna.pdf"},"general":{"family_raw":"","name":"Вікторія","full_name_suggest":{"input":["Шевченко Вікторія Валентинівна","Вікторія Валентинівна Шевченко","Вікторія Шевченко"],"output":"Шевченко Вікторія Валентинівна"},"patronymic":"Валентинівна","inn_hidden":true,"patronymic_unclear":false,"inn":"","inn_unclear":false,"last_name":"Шевченко","full_name":"Шевченко Вікторія Валентинівна","post":{"office":"Загальний апеляційний суд","post":"суддя апеляційного суду харківської області","office_unclear":false,"region_hidden":false,"region":"Харківська область","office_hidden":false,"post_unclear":false},"addresses":[{"place_city_type":"","place_address_unclear":false,"place_city_type_hidden":false,"place_hidden":true,"place_city_hidden":true,"place_district":"","place_district_hidden":false,"place":"","place_city":"","place_address_hidden":true,"place_address":""}]},"liabilities":{"54":{"sum_comment":"","sum_hidden":false,"sum":"","sum_foreign_comment":"","sum_foreign":"","sum_unclear":false},"55":{"sum_comment":"","sum_foreign_comment":"","sum_foreign":"","sum_unclear":false,"sum":""},"56":{"sum_comment_unclear":false,"sum_comment":"","sum_hidden":false,"sum":"","sum_foreign_comment":"","sum_foreign":"","sum_unclear":false},"57":{"sum_comment":"","sum_hidden":false,"sum":"","sum_foreign_comment":"","sum_foreign":"","sum_comment_hidden":false},"58":{"sum_comment":"","sum_foreign_comment":"","sum_foreign":"","sum":""},"59":{"sum_comment":"","sum_comment_unclear":false,"sum_foreign_comment":"","sum":"","sum_foreign":""},"60":{"sum_comment":"","sum_foreign_comment":"","sum_foreign":"","sum":""},"61":{"sum_comment":"","sum_foreign_comment":"","sum_foreign":"","sum":""},"62":{"sum_comment_unclear":false,"sum_comment":"","sum_hidden":false,"sum":"","sum_foreign_comment":"","sum_foreign":"","sum_unclear":false},"63":{"sum_comment":"","sum_foreign_comment":"","sum_foreign":"","sum":""},"64":{"sum_comment":"","sum_foreign_comment":"","sum_foreign":"","sum":""}},"intro":{"isnotdeclaration":"","declaration_year":"2014"}},{"id":"vulyk_74_123","ft_src":"у безоплатньому тимчасовому користуванні\n43.59\nу власності 3/4 част\n45.98\nу безоплатньому тимчасовому користуванні\n14.53\n8419\n2013\n2013\nЗагальний апеляційний суд\nХарківська область\nсуддя апеляційного суду харківської області\nВалентинівна\nШевченко Вікторія Валентинівна\nВікторія Валентинівна Шевченко\nВікторія Шевченко\nШевченко Вікторія Валентинівна\nВікторія\nШевченко Вікторія Валентинівна\nШевченко\nДитина\nШевченко О. В. 22. 09. 1985\nІнше\nШевченко І. Ю. 28. 10. 1989\nневістка\nШевченко Г. О. 09. 03. 2011\n264086\n1817\n1560\n265903\n1560\nу безоплатньому тимчасовому користуванні\n43.59\n45.98\nу власності 3/4 част\n14.53\nу безоплатньому тимчасовому користуванні\n8419\n264086\n1560\n265903\n1560\n1817\nДитина\nШевченко О. В. 22. 09. 1985\nІнше\nШевченко І. Ю. 28. 10. 1989\nневістка\nШевченко Г. О. 09. 03. 2011\nВалентинівна\nШевченко\nХарківська область\nЗагальний апеляційний суд\nсуддя апеляційного суду харківської області\nШевченко Вікторія Валентинівна\nШевченко Вікторія Валентинівна\nВікторія Валентинівна Шевченко\nВікторія Шевченко\nШевченко Вікторія Валентинівна\nВікторія","estate":{"25":[{"address":"","space_units":"м²","space_hidden":false,"space_unclear":false,"region_hidden":true,"costs_comment":"","space_comment":"у власності 3/4 част","address_hidden":true,"space":"45.98","costs_rent_comment":"","costs":"","region":"","costs_rent":""},{"costs":"","address":"","space_units":"м²","costs_rent_comment":"","space":"14.53","space_comment":"у безоплатньому тимчасовому користуванні","region_hidden":false,"costs_comment":"","region":"","costs_rent":""}],"31":[{"costs_property_comment":"","address":"","space_units":"м²","space_unclear":false,"region_hidden":true,"costs_property":"","space_comment":"у безоплатньому тимчасовому користуванні","address_hidden":true,"address_unclear":false,"costs_rent_comment":"","space":"43.59","region":"","costs_rent":""}]},"source":"VULYK","income":{"5":{"family_comment":"","family":"1560","comment":"","family_unclear":false,"family_hidden":false,"value":"265903"},"6":{"family_comment":"","family":"","comment":"","value_unclear":false,"family_unclear":false,"family_hidden":false,"value":"264086"},"7":{"source_name_hidden":false,"family_comment":"","family":"","value_hidden":false,"comment":"","family_hidden":false,"value":"","source_name":""},"8":{"family_comment":"","value":"","family":"","comment":""},"9":{"family_comment":"","value":"","family":"","comment":""},"10":{"family_comment":"","value":"","family":"","comment":"","value_unclear":false},"11":{"family_comment":"","value":"","family":"","comment":""},"12":{"family_comment":"","value":"","family":"","comment":""},"13":{"family_comment":"","value":"","family":"","comment":""},"14":{"family_comment":"","value":"","family":"","comment":""},"15":{"family_comment":"","value":"","family":"","comment":""},"16":{"family_comment":"","value":"","family":"","comment":""},"17":{"family_comment":"","value":"","family":"","comment":""},"18":{"family_comment":"","value":"","family":"","comment":""},"19":{"family_comment":"","value":"","family":"","comment":""},"20":{"family_comment":"","comment":"","family":"1560","value_unclear":false,"family_unclear":false,"comment_unclear":false,"value":"1817"}},"banks":{"45":[{"sum_comment_unclear":false,"sum_units":"UAH","sum_foreign_units":"UAH","sum_hidden":false,"sum":"8419","sum_foreign_comment":"","sum_comment":"","sum_unclear":false,"sum_foreign":"","sum_comment_hidden":false,"sum_foreign_hidden":false}]},"declaration":{"notfull_lostpages":"","additional_info_text":"","additional_info":"","date":"2014-03-24T00:00:00","notfull":"","url":"http://static.declarations.com.ua/declarations/chosen_ones/judges_batch/1570_shevchenko_viktoriia_valentynivna.pdf"},"general":{"inn":"","addresses":[{"place_city_type_hidden":false,"place_city_type":"","place_city_hidden":true,"place_hidden":true,"place_district":"","place_district_hidden":false,"place":"","place_address":"","place_address_hidden":true,"place_city":""}],"last_name":"Шевченко","full_name":"Шевченко Вікторія Валентинівна","family":[{"inn":"","family_name":"Шевченко О. В. 22. 09. 1985","relations_other":"","name_unclear":false,"inn_hidden":true,"name_hidden":false,"relations":"Дитина"},{"inn":"","family_name":"Шевченко І. Ю. 28. 10. 1989","relations_other":"невістка","name_unclear":false,"inn_hidden":false,"name_hidden":false,"relations":"Інше"},{"inn":"","family_name":"Шевченко Г. О. 09. 03. 2011","relations_other":"","name_unclear":false,"inn_hidden":false,"name_hidden":false,"relations":""}],"patronymic":"Валентинівна","inn_hidden":true,"name":"Вікторія","post":{"post_hidden":false,"office":"Загальний апеляційний суд","post":"суддя апеляційного суду харківської області","office_unclear":false,"region_unclear":false,"region":"Харківська область"},"family_raw":"","full_name_suggest":{"input":["Шевченко Вікторія Валентинівна","Вікторія Валентинівна Шевченко","Вікторія Шевченко"],"output":"Шевченко Вікторія Валентинівна"}},"liabilities":{"54":{"sum_comment_unclear":false,"sum_comment":"","sum":"","sum_foreign_comment":"","sum_foreign":"","sum_comment_hidden":false},"55":{"sum_comment":"","sum_hidden":false,"sum":"","sum_foreign_comment":"","sum_foreign":"","sum_unclear":false},"56":{"sum_comment":"","sum_hidden":false,"sum":"","sum_foreign_comment":"","sum_foreign":"","sum_unclear":false},"57":{"sum_comment_unclear":false,"sum_comment":"","sum":"","sum_foreign_comment":"","sum_foreign":"","sum_comment_hidden":false},"58":{"sum_comment":"","sum_foreign_comment":"","sum_foreign":"","sum":"","sum_comment_hidden":false},"59":{"sum_comment":"","sum_foreign_comment":"","sum_foreign":"","sum":""},"60":{"sum_comment":"","sum_foreign_comment":"","sum_foreign":"","sum_hidden":false,"sum":""},"61":{"sum_comment":"","sum_foreign_comment":"","sum_foreign":"","sum":""},"62":{"sum_comment":"","sum_foreign_comment":"","sum_foreign":"","sum":""},"63":{"sum_comment_unclear":false,"sum_comment":"","sum":"","sum_foreign_comment":"","sum_foreign":"","sum_unclear":false},"64":{"sum_comment_unclear":false,"sum_comment":"","sum":"","sum_foreign_comment":"","sum_foreign":"","sum_unclear":false}},"intro":{"isnotdeclaration":"","declaration_year_unclear":false,"declaration_year":"2013"}}]