[{"id":"vulyk_97_95","ft_src":"1992 куб. см., 150 к. с., 429.5 см\nMitsubishi ASX\n2010\n113.5\nм. Харків\nХарківська область\n2014\n193630.68\n10500\n193630.68\n10500\n1992 куб. см., 150 к. с., 429.5 см\nMitsubishi ASX\n2010\n2014\nШевченко Олександр Володимирович\nОлександр Володимирович Шевченко\nОлександр Шевченко\nШевченко Олександр Володимирович\nОлександр\nПодружжя\nШевченко Г. П\nДитина\nШевченко А. О\nШевченко Олександр Володимирович\nШевченко\nАдміністративний місцевий суд\nХарківська область\nсуддя харківського окружного адміністративного суду\nВолодимирович\nХарківська область\n61000\nХарків\n193630.68\n10500\n193630.68\n10500\n113.5\nм. Харків\nХарківська область\nПодружжя\nШевченко Г. П\nШевченко А. О\nДитина\nВолодимирович\nШевченко\nОлександр\nШевченко Олександр Володимирович\nОлександр Володимирович Шевченко\nОлександр Шевченко\nШевченко Олександр Володимирович\n61000\nХарків\nХарківська область\nХарківська область\nАдміністративний місцевий суд\nсуддя харківського окружного адміністративного суду\nШевченко Олександр Володимирович","estate":{"25":[{"address":"м. Харків","space_units":"м²","space_hidden":false,"space_unclear":false,"region_hidden":false,"costs_rent_comment":"","space_comment":"","address_hidden":true,"space_comment_hidden":false,"costs":"","space_comment_unclear":false,"costs_comment":"","space":"113.5","region_unclear":false,"region":"Харківська область","costs_rent":""}]},"vehicle":{"35":[{"year_hidden":false,"brand_info":"1992 куб. см., 150 к. с., 429.5 см","brand_unclear":false,"sum_rent_comment":"","brand_hidden":false,"year":"2010","sum_comment":"","brand_info_hidden":false,"sum_rent":"","brand":"Mitsubishi ASX","brand_info_unclear":false,"sum":""}]},"source":"VULYK","income":{"5":{"family_comment":"","value":"193630.68","family":"10500","comment":""},"6":{"family_comment":"","family":"","comment":"","value_unclear":false,"family_unclear":false,"comment_hidden":false,"value":"193630.68"},"7":{"family":"","family_comment":"","value":"","comment":"","source_name":""},"8":{"family_comment":"","value":"","family":"","comment":""},"9":{"family_comment":"","value":"","family_unclear":false,"family":"","comment":""},"10":{"family_comment":"","value":"","family":"","comment":"","value_unclear":false},"11":{"family_comment":"","value":"","family":"","comment":""},"12":{"family_comment":"","value":"","family":"","comment":""},"13":{"family_comment":"","value":"","family":"","comment":""},"14":{"family_comment":"","value":"","family":"","comment":""},"15":{"family_comment":"","value":"","family":"","comment":""},"16":{"family_comment":"","value":"","family":"","comment":""},"17":{"family_comment":"","value":"","family":"","comment":""},"18":{"family_comment":"","value":"","family":"","comment":""},"19":{"family_comment":"","value":"","family":"","comment":""},"20":{"family_comment":"","comment":"","family":"10500","value_unclear":false,"comment_unclear":false,"value":"","family_hidden":false,"family_comment_unclear":false}},"general":{"family":[{"inn":"","family_name":"Шевченко Г. П","relations_other":"","name_unclear":false,"inn_hidden":true,"name_hidden":true,"relations":"Подружжя"},{"inn":"","family_name":"Шевченко А. О","name_unclear":false,"inn_hidden":true,"name_hidden":false,"relations":"Дитина"}],"family_raw":"","name":"Олександр","full_name_suggest":{"input":["Шевченко Олександр Володимирович","Олександр Володимирович Шевченко","Олександр Шевченко"],"output":"Шевченко Олександр Володимирович"},"patronymic":"Володимирович","inn_hidden":true,"addresses":[{"place_city_type":"Місто","place_city_type_hidden":false,"place_hidden":false,"place_city_hidden":false,"place_district_hidden":false,"place_district":"","place_city_unclear":false,"place":"Харківська область","place_city":"Харків","place_address_hidden":true,"place_address":"61000"}],"last_name_hidden":false,"patronymic_hidden":false,"inn":"","inn_unclear":false,"last_name":"Шевченко","full_name":"Шевченко Олександр Володимирович","post":{"post_hidden":false,"office":"Адміністративний місцевий суд","post":"суддя харківського окружного адміністративного суду","office_unclear":false,"region_unclear":false,"region":"Харківська область"},"name_hidden":false},"liabilities":{"54":{"sum_comment_unclear":false,"sum_comment":"","sum_hidden":false,"sum":"","sum_foreign_comment":"","sum_foreign":"","sum_unclear":false,"sum_comment_hidden":false},"55":{"sum_comment":"","sum_foreign_comment":"","sum_foreign":"","sum":""},"56":{"sum_comment":"","sum_foreign_comment":"","sum_foreign":"","sum":""},"57":{"sum_comment_unclear":false,"sum_comment":"","sum_hidden":false,"sum":"","sum_foreign_comment":"","sum_foreign":"","sum_unclear":false,"sum_comment_hidden":false},"58":{"sum_comment_unclear":false,"sum_comment":"","sum_hidden":false,"sum":"","sum_foreign_comment":"","sum_foreign":"","sum_unclear":false,"sum_comment_hidden":false},"59":{"sum_comment":"","sum_foreign_comment":"","sum_foreign":"","sum":""},"60":{"sum_comment_unclear":false,"sum_comment":"","sum_hidden":false,"sum":"","sum_foreign_comment":"","sum_foreign":"","sum_comment_hidden":false},"61":{"sum_comment":"","sum_foreign_comment":"","sum_foreign":"","sum":""},"62":{"sum_comment":"","sum_foreign_comment":"","sum_foreign":"","sum_unclear":false,"sum":""},"63":{"sum_comment":"","sum_foreign_comment":"","sum_foreign":"","sum_hidden":false,"sum":""},"64":{"sum_comment":"","sum_foreign_comment":"","sum_foreign":"","sum":""}},"declaration":{"notfull_lostpages":"","additional_info_text":"","additional_info":"","date":"2015-03-30T00:00:00","notfull":"","url":"http://static.declarations.com.ua/declarations/chosen_ones/judges_batch/3996_shevchenko_oleksandr_volodymyrovych.pdf"},"intro":{"isnotdeclaration":"","declaration_year":"2014"}}]