[{"id":"vulyk_72_152","ft_src":"1091 куб. см.\nЗАЗ 11027\n2001\nмашиномісце\nм. Київ\nЧоколівський б-р\n13.1\nМиколаївська область\nЖовтневий район с. Галіцинова вул. Лісова\n2500\nм. Севастополь\nЖовтневий район,Галіцинівська сільрада\n20000\nБалаклавський р-н ст. Гавань\n700\nм. Севастополь\nпр. Октябрьскої революції, ОК 'Лівадія'\n38.5\nм. Севастополь\n85.7\nЧоколівський бульвар\nм. Київ\n2014\n199220\n230303\nпенсія\n31083\n1091 куб. см.\nЗАЗ 11027\n2001\n2500\nЖовтневий район с. Галіцинова вул. Лісова\nМиколаївська область\n20000\nЖовтневий район,Галіцинівська сільрада\nм. Севастополь\n700\nм. Севастополь\nБалаклавський р-н ст. Гавань\n38.5\nпр. Октябрьскої революції, ОК 'Лівадія'\nм. Севастополь\n13.1\nмашиномісце\nм. Київ\nЧоколівський б-р\nЧоколівський бульвар\n85.7\nм. Київ\nШкірай Микола Іванович\nМикола Іванович Шкірай\nМикола Шкірай\nШкірай Микола Іванович\nШкірай Микола Іванович\nМикола\nШкірай\nм. Київ\nЗагальний місцевий суд\nсуддя балаклавського районного суду м. севастополя, тимчасово прикріплений до штату голосіівського районного суду м. києва\nІванович\nм. Київ\n117023\n199220\n31083\nпенсія\n230303\n2014\n117023\nІванович\nШкірай\nМикола\nШкірай Микола Іванович\nМикола Іванович Шкірай\nМикола Шкірай\nШкірай Микола Іванович\nм. Київ\nм. Київ\nЗагальний місцевий суд\nсуддя балаклавського районного суду м. севастополя, тимчасово прикріплений до штату голосіівського районного суду м. києва\nШкірай Микола Іванович","estate":{"23":[{"costs":"","address":"Жовтневий район с. Галіцинова вул. Лісова","space_units":"м²","costs_hidden":false,"costs_rent_unclear":false,"space_hidden":false,"space_unclear":false,"region_hidden":false,"costs_comment":"","address_hidden":false,"costs_rent_hidden":false,"address_unclear":false,"space_comment":"","costs_rent_comment":"","space":"2500","region":"Миколаївська область","space_units_hidden":false,"costs_rent":""},{"address":"Жовтневий район,Галіцинівська сільрада","space_units":"м²","costs_comment":"","space_comment":"","region_hidden":false,"region":"м. Севастополь","address_hidden":false,"space":"20000","address_unclear":false,"costs_rent_comment":"","costs":"","costs_rent":""},{"costs":"","address":"Балаклавський р-н ст. Гавань","space_units":"м²","costs_rent_comment":"","space":"700","space_comment":"","costs_comment":"","region":"м. Севастополь","costs_rent":""}],"25":[{"space_hidden":false,"space_comment":"","costs_comment":"","address_hidden":false,"space_comment_hidden":false,"address_unclear":false,"costs_rent_comment_unclear":false,"costs":"","costs_rent":"","address":"Чоколівський бульвар","space_units":"м²","costs_hidden":false,"costs_rent_unclear":false,"costs_rent_hidden":false,"space_unclear":false,"costs_comment_hidden":false,"costs_rent_comment_hidden":false,"space_comment_unclear":false,"costs_comment_unclear":false,"costs_rent_comment":"","space":"85.7","region_hidden":false,"region":"м. Київ"}],"27":[{"address":"пр. Октябрьскої революції, ОК 'Лівадія'","space_units":"м²","costs_comment":"","space_unclear":false,"region_hidden":false,"space_comment":"","address_hidden":false,"costs":"","address_unclear":false,"costs_rent_comment":"","space":"38.5","region":"м. Севастополь","costs_rent":""}],"28":[{"address":"Чоколівський б-р","space_units":"м²","space_hidden":false,"space_unclear":false,"region_hidden":false,"costs_comment":"","space_comment":"машиномісце","address_hidden":false,"space":"13.1","costs_rent_comment":"","costs":"","region":"м. Київ","costs_rent":""}]},"vehicle":{"35":[{"sum_hidden":false,"brand_unclear":false,"sum_rent_comment":"","sum_rent_comment_unclear":false,"brand_hidden":false,"sum_comment":"","brand_info_hidden":false,"sum_rent":"","sum_rent_unclear":false,"brand":"ЗАЗ 11027","brand_info":"1091 куб. см.","brand_info_unclear":false,"year":"2001","sum":""}]},"source":"VULYK","income":{"5":{"family":"","family_comment":"","comment":"","value_hidden":false,"value_unclear":false,"comment_hidden":false,"family_hidden":false,"family_unclear":false,"family_comment_hidden":false,"value":"230303"},"6":{"family_comment":"","family":"","comment":"","value_unclear":false,"family_unclear":false,"family_hidden":false,"value":"199220"},"7":{"source_name_hidden":false,"family_comment":"","comment":"","family":"","source_name_unclear":false,"value":"","family_hidden":false,"source_name":""},"8":{"family_comment":"","value":"","family":"","comment":""},"9":{"family_comment":"","family":"","comment":"","value_unclear":false,"family_hidden":false,"value":""},"10":{"family_comment":"","family":"","value_hidden":false,"comment":"","comment_unclear":false,"value_unclear":false,"value":"","family_hidden":false},"11":{"family_comment":"","value":"","family":"","comment":""},"12":{"family_comment":"","value":"","family":"","comment":""},"13":{"family_comment":"","value":"","family":"","comment":""},"14":{"family_comment":"","value":"","family":"","comment":""},"15":{"family_comment":"","family_hidden":false,"value":"","family":"","comment":""},"16":{"family_comment":"","family":"","comment":"","value_unclear":false,"family_hidden":false,"value":""},"17":{"family_comment":"","family_hidden":false,"value":"","family":"","comment":""},"18":{"family_comment":"","value":"","family":"","comment":"","value_unclear":false},"19":{"family_comment":"","value":"","family":"","comment":""},"20":{"family_comment":"","comment":"пенсія","family":"","value_unclear":false,"family_unclear":false,"comment_unclear":false,"value":"31083","family_hidden":false}},"general":{"family_raw":"","name":"Микола","full_name_suggest":{"input":["Шкірай Микола Іванович","Микола Іванович Шкірай","Микола Шкірай"],"output":"Шкірай Микола Іванович"},"name_unclear":false,"patronymic":"Іванович","inn_hidden":true,"patronymic_unclear":false,"patronymic_hidden":false,"inn":"","inn_unclear":false,"last_name":"Шкірай","full_name":"Шкірай Микола Іванович","post":{"post_hidden":false,"office":"Загальний місцевий суд","post":"суддя балаклавського районного суду м. севастополя, тимчасово прикріплений до штату голосіівського районного суду м. києва","region_unclear":false,"candidate":"","region_hidden":false,"region":"м. Київ","office_hidden":false,"post_unclear":false,"office_unclear":false},"addresses":[{"place_city_type_hidden":false,"place_district_hidden":false,"place_address_unclear":false,"place":"м. Київ","place_city":"","place_unclear":false,"place_city_type":"","place_city_hidden":false,"place_city_unclear":false,"place_district":"","place_district_unclear":false,"place_address":"","place_address_hidden":true,"place_hidden":false}],"last_name_unclear":false},"liabilities":{"54":{"sum_comment":"","sum":"","sum_foreign_comment":"","sum_foreign":"","sum_unclear":false,"sum_comment_hidden":false},"55":{"sum_comment":"","sum_foreign_comment":"","sum_foreign":"","sum":""},"56":{"sum_comment":"","sum_foreign_comment":"","sum_foreign":"","sum_hidden":false,"sum":""},"57":{"sum_comment_unclear":false,"sum_comment":"","sum_hidden":false,"sum":"117023","sum_foreign_comment":"","sum_foreign":"","sum_unclear":false,"sum_comment_hidden":false},"58":{"sum_comment_unclear":false,"sum_comment":"","sum_hidden":false,"sum":"","sum_foreign_comment":"","sum_foreign":"","sum_unclear":false,"sum_comment_hidden":false},"59":{"sum_comment":"","sum":"","sum_foreign_comment":"","sum_foreign_unclear":false,"sum_foreign":"","sum_foreign_hidden":false,"sum_comment_hidden":false},"60":{"sum_comment":"","sum_hidden":false,"sum":"","sum_foreign_comment":"","sum_foreign":"","sum_foreign_hidden":false},"61":{"sum_comment":"","sum_hidden":false,"sum":"","sum_foreign_comment":"","sum_foreign":"","sum_foreign_hidden":false},"62":{"sum_comment":"","sum_hidden":false,"sum":"","sum_foreign_comment":"","sum_foreign":"","sum_foreign_hidden":false},"63":{"sum_comment_unclear":false,"sum_comment":"","sum_hidden":false,"sum":"","sum_foreign_comment":"","sum_foreign":"","sum_unclear":false,"sum_foreign_hidden":false,"sum_comment_hidden":false},"64":{"sum_comment":"","sum_hidden":false,"sum":"","sum_foreign_comment":"","sum_foreign":"","sum_foreign_hidden":false}},"declaration":{"notfull_lostpages":"","additional_info_text":"","additional_info":"","date":"2015-03-25T00:00:00","notfull":"","url":"http://static.declarations.com.ua/declarations/chosen_ones/epic_batch/shkirai__mykola_ivanovych.pdf"},"intro":{"isnotdeclaration":"","declaration_year_unclear":false,"declaration_year":"2014"}}]