[{"id":"vulyk_78_5","ft_src":"1749 куб. см.\n2005\nPeugeot 407\nправо керування\n1242 куб. см.\n2012\nFord Fiesta\n1388 куб. см.\n2008\nFord Fusion\n1498 куб. см.\n2008\nChevrolet Aveo\nЗакарпатська область\nм. Хуст, вул. Жайворонкова 46/4\n45.4\nЗакарпатська область\nм. Хуст вул Лісна\n172.5\nМ. Хуст, вул. Лісна 64\nЗакарпатська область\n.1\nЗакарпатська область\nм. Хуст віл Кіреші\n.06\n2014\n134003\n203252\n46425\n180428\n203252\n1749 куб. см.\nправо керування\n2005\nPeugeot 407\n1242 куб. см.\n2012\nFord Fiesta\n1388 куб. см.\n2008\nFord Fusion\n1498 куб. см.\n2008\nChevrolet Aveo\n2014\nПодружжя\nСідей Неля Андріївна\n3058801868\nДитина\nСідей Анастасія Ярославівна\n3869502704\nІнше\nПалінкаш Андрій Михайлович\n1864603270\nТесть\nПалінкаш Ольга Миколаївна\nІнше\n1852603564\nТеща\nСідей Ярослав Ярославович\nЯрослав Ярославович Сідей\nЯрослав Сідей\nСідей Ярослав Ярославович\nСідей Ярослав Ярославович\n2859520917\nЯрослав\nЯрославович\nЗагальний місцевий суд\nсуддя хустського районного суду закарпатської області\nЗакарпатська область\nСідей\nвул. Лісная, 64\nЗакарпатська область\nХуст\n203252\n134003\n46425\n203252\n180428\n.1\nЗакарпатська область\nМ. Хуст, вул. Лісна 64\n.06\nЗакарпатська область\nм. Хуст віл Кіреші\nм. Хуст вул Лісна\nЗакарпатська область\n172.5\nм. Хуст, вул. Жайворонкова 46/4\nЗакарпатська область\n45.4\n3058801868\nПодружжя\nСідей Неля Андріївна\n3869502704\nДитина\nСідей Анастасія Ярославівна\n1864603270\nІнше\nПалінкаш Андрій Михайлович\nТесть\n1852603564\nІнше\nТеща\nПалінкаш Ольга Миколаївна\n2859520917\nЯрославович\nСідей\nЯрослав\nСідей Ярослав Ярославович\nЯрослав Ярославович Сідей\nЯрослав Сідей\nСідей Ярослав Ярославович\nЗакарпатська область\nХуст\nвул. Лісная, 64\nЗакарпатська область\nсуддя хустського районного суду закарпатської області\nЗагальний місцевий суд\nСідей Ярослав Ярославович","estate":{"29":[{"costs_property_comment":"","address":"М. Хуст, вул. Лісна 64","space_units":"га","space_unclear":false,"region_hidden":false,"costs_property":"","space_comment":"","address_hidden":false,"costs_rent_comment":"","space":".1","region":"Закарпатська область","costs_rent":""},{"costs_property_comment":"","address":"м. Хуст віл Кіреші","space_units":"га","costs_rent_comment":"","space":".06","region":"Закарпатська область","costs_property":"","space_comment":"","address_hidden":false,"costs_rent":""}],"30":[{"costs_property_comment":"","address":"м. Хуст вул Лісна","space_units":"м²","space_hidden":false,"space_comment":"","region_hidden":false,"costs_property":"","region":"Закарпатська область","address_hidden":false,"costs_rent_comment":"","space":"172.5","costs_rent":""}],"31":[{"costs_property_comment":"","address":"м. Хуст, вул. Жайворонкова 46/4","space_units":"м²","space_comment":"","region_hidden":false,"costs_property":"","region":"Закарпатська область","address_hidden":false,"address_unclear":false,"costs_rent_comment":"","space":"45.4","costs_rent":""}]},"vehicle":{"35":[{"sum_comment":"","brand_info":"1749 куб. см.","sum":"","sum_rent_comment":"право керування","year":"2005","brand":"Peugeot 407","sum_rent":""}],"40":[{"sum_comment":"","brand_info_hidden":false,"brand_info":"1242 куб. см.","sum":"","sum_rent_comment":"","year":"2012","brand":"Ford Fiesta","sum_rent":""},{"sum_comment":"","brand_info":"1388 куб. см.","sum":"","sum_rent_comment":"","year":"2008","brand":"Ford Fusion","sum_rent":""},{"sum_comment":"","brand_info":"1498 куб. см.","sum":"","sum_rent_comment":"","year":"2008","brand":"Chevrolet Aveo","sum_rent":""}]},"source":"VULYK","income":{"5":{"family_comment":"","family":"180428","comment":"","value_unclear":false,"comment_hidden":false,"value":"203252"},"6":{"family":"134003","family_comment":"","value":"203252","comment":"","value_hidden":false},"7":{"family":"","family_comment":"","value":"","comment":"","source_name":""},"8":{"family_comment":"","value":"","family":"","comment":""},"9":{"family_comment":"","value":"","family":"","comment":"","comment_hidden":false},"10":{"family_comment":"","value":"","family":"","comment":""},"11":{"family_comment":"","value":"","family":"","comment":""},"12":{"family_comment":"","value":"","family":"","comment":""},"13":{"family_comment":"","value":"","family":"","comment":""},"14":{"family_comment":"","value":"","family":"","comment":""},"15":{"family_comment":"","value":"","family":"46425","comment":"","family_comment_hidden":false},"16":{"family_comment":"","value":"","family":"","comment":""},"17":{"family_comment":"","value":"","family":"","comment":""},"18":{"family":"","family_comment":"","value":"","comment":"","value_hidden":false},"19":{"family_comment":"","value":"","family":"","comment":""},"20":{"family_comment":"","value":"","family":"","comment":"","family_comment_unclear":false}},"general":{"family_raw":"","name":"Ярослав","full_name_suggest":{"input":["Сідей Ярослав Ярославович","Ярослав Ярославович Сідей","Ярослав Сідей"],"output":"Сідей Ярослав Ярославович"},"name_unclear":false,"patronymic":"Ярославович","inn_hidden":false,"inn":"2859520917","addresses":[{"place_city_type_hidden":false,"place_city_type":"Місто","place_city_hidden":false,"place_hidden":false,"place_district":"","place_district_hidden":false,"place":"Закарпатська область","place_address":"вул. Лісная, 64","place_address_hidden":false,"place_city":"Хуст"}],"last_name":"Сідей","full_name":"Сідей Ярослав Ярославович","family":[{"inn":"3058801868","family_name":"Сідей Неля Андріївна","relations_other":"","name_unclear":false,"inn_hidden":false,"name_hidden":false,"relations":"Подружжя"},{"inn":"3869502704","family_name":"Сідей Анастасія Ярославівна","relations_other":"","name_unclear":false,"inn_hidden":false,"name_hidden":false,"relations":"Дитина"},{"inn":"1864603270","family_name":"Палінкаш Андрій Михайлович","relations_other":"Тесть","name_unclear":false,"inn_hidden":false,"relations":"Інше"},{"inn":"1852603564","family_name":"Палінкаш Ольга Миколаївна","relations_other":"Теща","relations":"Інше"}],"post":{"post_hidden":false,"office":"Загальний місцевий суд","post":"суддя хустського районного суду закарпатської області","office_hidden":false,"region":"Закарпатська область","region_hidden":false,"post_unclear":false},"last_name_unclear":false},"liabilities":{"54":{"sum_comment_unclear":false,"sum_comment":"","sum_hidden":false,"sum":"","sum_foreign_comment":"","sum_foreign":"","sum_foreign_hidden":false,"sum_comment_hidden":false},"55":{"sum_comment":"","sum_foreign_comment":"","sum_foreign":"","sum":""},"56":{"sum_comment":"","sum_foreign_comment":"","sum_foreign":"","sum":""},"57":{"sum_comment":"","sum_foreign_comment":"","sum_foreign":"","sum":""},"58":{"sum_comment":"","sum_foreign_comment":"","sum_foreign":"","sum_unclear":false,"sum":""},"59":{"sum_comment":"","sum_foreign_comment":"","sum_foreign":"","sum":""},"60":{"sum_comment_unclear":false,"sum_comment":"","sum":"","sum_foreign_comment":"","sum_foreign":"","sum_comment_hidden":false},"61":{"sum_comment":"","sum_foreign_comment":"","sum_foreign":"","sum":""},"62":{"sum_comment":"","sum_foreign_comment":"","sum_foreign":"","sum_hidden":false,"sum":""},"63":{"sum_comment":"","sum":"","sum_foreign_comment":"","sum_foreign":"","sum_unclear":false,"sum_foreign_hidden":false},"64":{"sum_comment":"","sum_hidden":false,"sum":"","sum_foreign_comment":"","sum_foreign":"","sum_foreign_hidden":false}},"declaration":{"notfull_lostpages":"","additional_info_text":"","additional_info":"","date":"2015-03-16T00:00:00","notfull":"","url":"http://static.declarations.com.ua/declarations/chosen_ones/judges_batch/2072_sidei_iaroslav_iaroslavovych.pdf"},"intro":{"declaration_year":"2014"}}]