[{"id":"vulyk_78_18","ft_src":"3999 куб. см.\n1999\nBMW 540\n1495 куб. см.\n1989\nВАЗ 2106\n21\n2014\n22800\n206771\n22800\n252648\n45877\n3999 куб. см.\n1999\nBMW 540\n1495 куб. см.\n1989\nВАЗ 2106\n2014\nПодружжя\nСмоляр С. І\nДитина\nСмоляр А. О\nДитина\nСмоляр К. О\nСмоляр Олександр Андрійович\nОлександр Андрійович Смоляр\nОлександр Смоляр\nСмоляр Олександр Андрійович\nСмоляр Олександр Андрійович\nОлександр\nАндрійович\nЗагальний місцевий суд\nсуддя черкаського районного суду черкаської області\nЧеркаська область\nСмоляр\n570\n5000\n206771\n22800\n45877\n252648\n22800\n21\n5000\n570\nПодружжя\nСмоляр С. І\nДитина\nСмоляр А. О\nДитина\nСмоляр К. О\nАндрійович\nСмоляр\nОлександр\nСмоляр Олександр Андрійович\nОлександр Андрійович Смоляр\nОлександр Смоляр\nСмоляр Олександр Андрійович\nЧеркаська область\nсуддя черкаського районного суду черкаської області\nЗагальний місцевий суд\nСмоляр Олександр Андрійович","estate":{"27":[{"costs":"","address":"","space_units":"м²","costs_hidden":false,"space_hidden":false,"space_comment":"","region_hidden":true,"costs_comment":"","address_hidden":true,"space_comment_hidden":false,"costs_rent_hidden":false,"costs_rent_comment":"","space":"21","region":"","costs_rent":""}]},"vehicle":{"35":[{"sum_comment":"","brand_info":"3999 куб. см.","sum":"","sum_rent_comment":"","year":"1999","brand":"BMW 540","sum_rent":""}],"40":[{"sum_comment":"","brand_info_hidden":false,"brand_info":"1495 куб. см.","sum":"","sum_rent_comment":"","year":"1989","brand":"ВАЗ 2106","sum_rent":""}]},"source":"VULYK","income":{"5":{"family_comment":"","family":"22800","comment":"","value_unclear":false,"comment_hidden":false,"value":"252648"},"6":{"family":"22800","family_comment":"","value":"206771","comment":"","value_hidden":false},"7":{"family":"","family_comment":"","value":"","comment":"","source_name":""},"8":{"family_comment":"","value":"","family":"","comment":""},"9":{"family_comment":"","value":"","family":"","comment":"","comment_hidden":false},"10":{"family_comment":"","value":"","family":"","comment":""},"11":{"family_comment":"","value":"","family":"","comment":""},"12":{"family_comment":"","value":"","family":"","comment":""},"13":{"family_comment":"","value":"","family":"","comment":""},"14":{"family_comment":"","value":"","family":"","comment":""},"15":{"family_comment":"","value":"","family":"","comment":"","family_comment_hidden":false},"16":{"family_comment":"","value":"","family":"","comment":""},"17":{"family_comment":"","value":"","family":"","comment":""},"18":{"family":"","family_comment":"","value":"","comment":"","value_hidden":false},"19":{"family_comment":"","value":"","family":"","comment":""},"20":{"family_comment":"","value":"45877","family":"","comment":"","family_comment_unclear":false}},"general":{"family_raw":"","name":"Олександр","full_name_suggest":{"input":["Смоляр Олександр Андрійович","Олександр Андрійович Смоляр","Олександр Смоляр"],"output":"Смоляр Олександр Андрійович"},"name_unclear":false,"patronymic":"Андрійович","inn_hidden":true,"inn":"","addresses":[{"place_city_type_hidden":true,"place_city_type":"","place_city_hidden":true,"place_hidden":true,"place_district":"","place_district_hidden":true,"place":"","place_address":"","place_address_hidden":true,"place_city":""}],"last_name":"Смоляр","full_name":"Смоляр Олександр Андрійович","family":[{"inn":"","family_name":"Смоляр С. І","relations_other":"","name_unclear":false,"inn_hidden":true,"name_hidden":false,"relations":"Подружжя"},{"inn":"","family_name":"Смоляр А. О","relations_other":"","name_unclear":false,"inn_hidden":true,"name_hidden":false,"relations":"Дитина"},{"inn":"","family_name":"Смоляр К. О","relations_other":"","name_unclear":false,"inn_hidden":false,"relations":"Дитина"}],"post":{"post_hidden":false,"office":"Загальний місцевий суд","post":"суддя черкаського районного суду черкаської області","office_hidden":false,"region":"Черкаська область","region_hidden":false,"post_unclear":false},"last_name_unclear":false},"liabilities":{"54":{"sum_comment_unclear":false,"sum_comment":"","sum_hidden":false,"sum":"","sum_foreign_comment":"","sum_foreign":"","sum_foreign_hidden":false,"sum_comment_hidden":false},"55":{"sum_comment":"","sum_foreign_comment":"","sum_foreign":"","sum":""},"56":{"sum_comment":"","sum_foreign_comment":"","sum_foreign":"","sum":"5000"},"57":{"sum_comment":"","sum_foreign_comment":"","sum_foreign":"","sum":""},"58":{"sum_comment":"","sum_foreign_comment":"","sum_foreign":"","sum_unclear":false,"sum":""},"59":{"sum_comment":"","sum_foreign_comment":"","sum_foreign":"","sum":""},"60":{"sum_comment_unclear":false,"sum_comment":"","sum":"570","sum_foreign_comment":"","sum_foreign":"","sum_comment_hidden":false},"61":{"sum_comment":"","sum_foreign_comment":"","sum_foreign":"","sum":""},"62":{"sum_comment":"","sum_foreign_comment":"","sum_foreign":"","sum_hidden":false,"sum":""},"63":{"sum_comment":"","sum":"","sum_foreign_comment":"","sum_foreign":"","sum_unclear":false,"sum_foreign_hidden":false},"64":{"sum_comment":"","sum_hidden":false,"sum":"","sum_foreign_comment":"","sum_foreign":"","sum_foreign_hidden":false}},"declaration":{"notfull_lostpages":"","additional_info_text":"","additional_info":"","date":"2015-03-30T00:00:00","notfull":"","url":"http://static.declarations.com.ua/declarations/chosen_ones/judges_batch/2085_smoliar_oleksandr_andriiovych.pdf"},"intro":{"declaration_year":"2014"}}]