[{"id":"vulyk_97_92","ft_src":"3456\nLexus RX 350\n2008\n89.95\nХарківська область\nм. Харків\nХарківська область\nспільна сумісна власність\nм. Харків\n87.5\nмашиномісце\nм. Харків\n18\nХарківська область\n89.95\nм. Харків\nХарківська область\nм. Харків\n43\nХарківська область\n2014\nстипендія\n4483.66\n44149.6\n4483.66\n67685.93\nсоц. допомога у зв'язку з народженням та доглядом за дитиною\n23536.33\n3456\nLexus RX 350\n2008\n2014\nСтаросельцева Оксана Валеріївна\nОксана Валеріївна Старосельцева\nОксана Старосельцева\nСтаросельцева Оксана Валеріївна\nОксана\nДитина\nСтоляренко К. С\nДитина\nСліденко Д. А\nСтаросельцева Оксана Валеріївна\nСтаросельцева\nАдміністративний місцевий суд\nХарківська область\nсуддя харківського окружного адміністративного суду\nВалеріївна\nХарківська область\n61072\nХарків\nстипендія\n44149.6\n4483.66\nсоц. допомога у зв'язку з народженням та доглядом за дитиною\n23536.33\n67685.93\n4483.66\n89.95\nХарківська область\nм. Харків\n87.5\nспільна сумісна власність\nХарківська область\nм. Харків\nХарківська область\n18\nмашиномісце\nм. Харків\n89.95\nм. Харків\nХарківська область\n43\nХарківська область\nм. Харків\nДитина\nСтоляренко К. С\nСліденко Д. А\nДитина\nВалеріївна\nСтаросельцева\nОксана\nСтаросельцева Оксана Валеріївна\nОксана Валеріївна Старосельцева\nОксана Старосельцева\nСтаросельцева Оксана Валеріївна\n61072\nХарків\nХарківська область\nХарківська область\nАдміністративний місцевий суд\nсуддя харківського окружного адміністративного суду\nСтаросельцева Оксана Валеріївна","estate":{"25":[{"address":"м. Харків","space_units":"м²","space_hidden":false,"space_unclear":false,"region_hidden":false,"costs_rent_comment":"","space_comment":"","address_hidden":true,"space_comment_hidden":false,"costs":"","space_comment_unclear":false,"costs_comment":"","space":"89.95","region_unclear":false,"region":"Харківська область","costs_rent":""},{"address":"м. Харків","space_units":"м²","space_unclear":false,"costs_comment":"","space_comment":"","address_hidden":false,"space":"43","space_comment_unclear":false,"costs_rent_comment":"","costs":"","region":"Харківська область","costs_rent":""}],"28":[{"costs":"","address":"м. Харків","space_units":"м²","costs_rent_comment":"","space":"18","space_comment":"машиномісце","region_hidden":false,"costs_comment":"","region":"Харківська область","address_hidden":true,"costs_rent":""}],"31":[{"costs_property_comment":"","address":"м. Харків","space_units":"м²","space_hidden":false,"space_unclear":false,"region_hidden":false,"costs_property":"","space_comment":"","address_hidden":true,"space_comment_hidden":false,"costs_rent_comment":"","space":"89.95","region":"Харківська область","costs_rent":""},{"costs_property_comment":"","address":"м. Харків","space_units":"м²","costs_rent_comment":"","space":"87.5","region":"Харківська область","costs_property":"","space_comment":"спільна сумісна власність","address_hidden":false,"costs_rent":""}]},"vehicle":{"35":[{"year_hidden":false,"brand_info":"3456","brand_unclear":false,"sum_rent_comment":"","brand_hidden":false,"year":"2008","sum_comment":"","brand_info_hidden":false,"sum_rent":"","brand":"Lexus RX 350","brand_info_unclear":false,"sum":""}]},"source":"VULYK","income":{"5":{"family_comment":"","value":"67685.93","family":"4483.66","comment":""},"6":{"family_comment":"стипендія","family":"4483.66","comment":"","value_unclear":false,"family_unclear":false,"comment_hidden":false,"value":"44149.6"},"7":{"family":"","family_comment":"","value":"","comment":"","source_name":""},"8":{"family_comment":"","value":"","family":"","comment":""},"9":{"family_comment":"","value":"","family_unclear":false,"family":"","comment":""},"10":{"family_comment":"","value":"","family":"","comment":"","value_unclear":false},"11":{"family_comment":"","value":"","family":"","comment":""},"12":{"family_comment":"","value":"","family":"","comment":""},"13":{"family_comment":"","value":"","family":"","comment":""},"14":{"family_comment":"","value":"","family":"","comment":""},"15":{"family_comment":"","value":"","family":"","comment":""},"16":{"family_comment":"","value":"","family":"","comment":""},"17":{"family_comment":"","value":"","family":"","comment":""},"18":{"family_comment":"","value":"","family":"","comment":""},"19":{"family_comment":"","value":"","family":"","comment":""},"20":{"family_comment":"","comment":"соц. допомога у зв'язку з народженням та доглядом за дитиною","family":"","value_unclear":false,"comment_unclear":false,"value":"23536.33","family_hidden":false,"family_comment_unclear":false}},"general":{"family":[{"inn":"","family_name":"Столяренко К. С","relations_other":"","name_unclear":false,"inn_hidden":true,"name_hidden":true,"relations":"Дитина"},{"inn":"","family_name":"Сліденко Д. А","name_unclear":false,"inn_hidden":false,"name_hidden":false,"relations":"Дитина"}],"family_raw":"","name":"Оксана","full_name_suggest":{"input":["Старосельцева Оксана Валеріївна","Оксана Валеріївна Старосельцева","Оксана Старосельцева"],"output":"Старосельцева Оксана Валеріївна"},"patronymic":"Валеріївна","inn_hidden":true,"addresses":[{"place_city_type":"Місто","place_city_type_hidden":false,"place_hidden":false,"place_city_hidden":false,"place_district_hidden":false,"place_district":"","place_city_unclear":false,"place":"Харківська область","place_city":"Харків","place_address_hidden":true,"place_address":"61072"}],"last_name_hidden":false,"patronymic_hidden":false,"inn":"","inn_unclear":false,"last_name":"Старосельцева","full_name":"Старосельцева Оксана Валеріївна","post":{"post_hidden":false,"office":"Адміністративний місцевий суд","post":"суддя харківського окружного адміністративного суду","office_unclear":false,"region_unclear":false,"region":"Харківська область"},"name_hidden":false},"liabilities":{"54":{"sum_comment_unclear":false,"sum_comment":"","sum_hidden":false,"sum":"","sum_foreign_comment":"","sum_foreign":"","sum_unclear":false,"sum_comment_hidden":false},"55":{"sum_comment":"","sum_foreign_comment":"","sum_foreign":"","sum":""},"56":{"sum_comment":"","sum_foreign_comment":"","sum_foreign":"","sum":""},"57":{"sum_comment_unclear":false,"sum_comment":"","sum_hidden":false,"sum":"","sum_foreign_comment":"","sum_foreign":"","sum_unclear":false,"sum_comment_hidden":false},"58":{"sum_comment_unclear":false,"sum_comment":"","sum_hidden":false,"sum":"","sum_foreign_comment":"","sum_foreign":"","sum_unclear":false,"sum_comment_hidden":false},"59":{"sum_comment":"","sum_foreign_comment":"","sum_foreign":"","sum":""},"60":{"sum_comment_unclear":false,"sum_comment":"","sum_hidden":false,"sum":"","sum_foreign_comment":"","sum_foreign":"","sum_comment_hidden":false},"61":{"sum_comment":"","sum_foreign_comment":"","sum_foreign":"","sum":""},"62":{"sum_comment":"","sum_foreign_comment":"","sum_foreign":"","sum_unclear":false,"sum":""},"63":{"sum_comment":"","sum_foreign_comment":"","sum_foreign":"","sum_hidden":false,"sum":""},"64":{"sum_comment":"","sum_foreign_comment":"","sum_foreign":"","sum":""}},"declaration":{"notfull_lostpages":"","additional_info_text":"","additional_info":"","date":"2015-03-24T00:00:00","notfull":"","url":"http://static.declarations.com.ua/declarations/chosen_ones/judges_batch/3993_staroseltseva_oksana_valeriivna.pdf"},"intro":{"isnotdeclaration":"","declaration_year":"2014"}}]