[{"id":"vulyk_55_113","ft_src":"2000\n2000\nПолтавська область\nу власності\nселище Диканька\n2000\nу власності дружини Старокожко Т. В. з 24. 10. 14\nДиканський район, с. Михайлівка, Степова, 8а\nПолтавська область\n21.9\nу власності дружини Старокожко Т. В. з 24. 10. 14\nДиканський район, с. Михайлівка, вул.Степова, 8а\n.2499\nПолтавська область\nПолтавська область\nоренда\nм. Хорол, вул. Жовтнева, 27/2\n60\n1/4 частина від 54м. (у власності\n54\nселище Диканька, вул. Леніна, 6а, кв. 29\nПолтавська область\n2014\n185716\n186619\n903\n2000\n2000\n2014\nПодружжя\nСтарокожко Т. В. 18. 12. 1974\nДитина\nСтарокожко О. В. 24. 07. 2003\nСтарокожко Володимир Петрович\nВолодимир Петрович Старокожко\nВолодимир Старокожко\nСтарокожко Володимир Петрович\nВолодимир\nСтарокожко Володимир Петрович\nПетрович\nЗагальний місцевий суд\nзаступник голови хорольського районного суду полтавської області\nПолтавська область\nСтарокожко\n185716\n903\n186619\n2000\nу власності\nселище Диканька\nПолтавська область\n.2499\nу власності дружини Старокожко Т. В. з 24. 10. 14\nПолтавська область\nДиканський район, с. Михайлівка, вул.Степова, 8а\n60\nоренда\nм. Хорол, вул. Жовтнева, 27/2\nПолтавська область\n21.9\nу власності дружини Старокожко Т. В. з 24. 10. 14\nПолтавська область\nДиканський район, с. Михайлівка, Степова, 8а\n54\n1/4 частина від 54м. (у власності\nПолтавська область\nселище Диканька, вул. Леніна, 6а, кв. 29\nСтарокожко Т. В. 18. 12. 1974\nПодружжя\nСтарокожко О. В. 24. 07. 2003\nДитина\nПетрович\nСтарокожко\nСтарокожко Володимир Петрович\nВолодимир Петрович Старокожко\nВолодимир Старокожко\nСтарокожко Володимир Петрович\nПолтавська область\nзаступник голови хорольського районного суду полтавської області\nЗагальний місцевий суд\nСтарокожко Володимир Петрович\nВолодимир","estate":{"23":[{"address":"селище Диканька","space_units":"м²","space_hidden":false,"space_comment":"у власності","region_hidden":false,"costs_comment":"","address_hidden":false,"space":"2000","address_unclear":false,"costs_rent_comment":"","costs":"","region":"Полтавська область","costs_rent":""},{"costs":"","address":"","space_units":"","costs_rent_comment":"","space":"","space_comment":"","region_hidden":false,"costs_comment":"","region":"","costs_rent":""},{"costs":"","address":"","space_units":"","costs_rent_comment":"","space":"","space_comment":"","costs_comment":"","region":"","costs_rent":""},{"costs":"","address":"","space_units":"","costs_rent_comment":"","space":"","space_comment":"","costs_comment":"","costs_rent":""}],"24":[{"address":"м. Хорол, вул. Жовтнева, 27/2","space_units":"м²","space_hidden":false,"space_comment":"оренда","region_hidden":false,"costs_comment":"","address_hidden":false,"space":"60","address_unclear":false,"costs_rent_comment":"","costs":"","region":"Полтавська область","costs_rent":""}],"25":[{"space":"54","costs_unclear":false,"address":"селище Диканька, вул. Леніна, 6а, кв. 29","space_units":"м²","costs_hidden":false,"space_hidden":false,"space_comment":"1/4 частина від 54м. (у власності","region_hidden":false,"costs_comment":"","space_comment_unclear":false,"space_comment_hidden":false,"space_unclear":false,"address_unclear":false,"address_hidden":false,"costs_rent_comment":"","costs":"","region_unclear":false,"region":"Полтавська область","costs_rent":""}],"29":[{"costs_property_comment":"","address":"Диканський район, с. Михайлівка, вул.Степова, 8а","space_units":"га","space_unclear":false,"region_hidden":false,"costs_property":"","space_comment":"у власності дружини Старокожко Т. В. з 24. 10. 14","address_hidden":false,"space_comment_hidden":false,"address_unclear":true,"costs_rent_comment":"","space":".2499","region":"Полтавська область","costs_rent":""}],"30":[{"costs_property_comment":"","address":"Диканський район, с. Михайлівка, Степова, 8а","space_units":"м²","space_unclear":false,"region_hidden":false,"costs_property":"","space_comment":"у власності дружини Старокожко Т. В. з 24. 10. 14","address_hidden":false,"address_unclear":true,"costs_rent_comment":"","space":"21.9","region":"Полтавська область","costs_rent":""}]},"source":"VULYK","income":{"5":{"family_comment":"","family":"","comment":"","value_unclear":false,"family_unclear":false,"value":"186619"},"6":{"family_comment":"","family":"","comment":"","value_unclear":false,"family_unclear":false,"value":"185716"},"7":{"family_comment":"","comment":"","family":"","value_unclear":false,"value":"","source_name":""},"8":{"family_comment":"","value":"","family":"","comment":""},"9":{"family_comment":"","value":"","family":"","comment":"","value_unclear":false},"10":{"family_comment":"","comment_unclear":false,"value":"","family":"","comment":""},"11":{"family_comment":"","value":"","family":"","comment":""},"12":{"family_comment":"","value":"","family":"","comment":""},"13":{"family_comment":"","value":"","family":"","comment":""},"14":{"family_comment":"","value":"","family":"","comment":""},"15":{"family_comment":"","value":"","family":"","comment":""},"16":{"family_comment":"","value":"","family":"","comment":""},"17":{"family_comment":"","value":"","family":"","comment":""},"18":{"family_comment":"","value":"","family":"","comment":""},"19":{"family_comment":"","value":"","family":"","comment":""},"20":{"family_comment":"","value":"903","family":"","comment":""}},"banks":{"45":[{"sum_comment_unclear":false,"sum_units":"UAH","sum_foreign_comment":"","sum_foreign_units":"UAH","sum":"2000","sum_foreign_comment_unclear":false,"sum_comment":"","sum_foreign":"","sum_unclear":false,"sum_units_unclear":false,"sum_comment_hidden":false},{"sum_comment_unclear":false,"sum_comment":"","sum_foreign_units":"","sum":"","sum_foreign_comment":"","sum_foreign":"","sum_unclear":false,"sum_units":""},{"sum_units":"","sum_comment":"","sum_foreign_units":"","sum":"","sum_foreign_comment":"","sum_foreign":"","sum_unclear":false}],"46":[{"sum_comment_unclear":false,"sum_comment":"","sum_foreign_units":"UAH","sum":"2000","sum_foreign_comment":"","sum_foreign":"","sum_units":"UAH"}],"47":[{"sum_comment_unclear":false,"sum_comment":"","sum_foreign_units":"UAH","sum_hidden":false,"sum":"","sum_foreign_comment":"","sum_foreign":"","sum_units":"UAH"}],"48":[{"sum_units":"UAH","sum_comment":"","sum_foreign_units":"UAH","sum":"","sum_foreign_comment":"","sum_foreign":""}],"49":[{"sum_units":"UAH","sum_comment":"","sum_foreign_units":"UAH","sum":"","sum_foreign_comment":"","sum_foreign":""},{"sum_comment":"","sum_units":"","sum_foreign":"","sum":"","sum_foreign_comment":""}],"50":[{"sum_units":"UAH","sum_comment":"","sum_foreign_units":"UAH","sum":"","sum_foreign_comment":"","sum_foreign":""}],"51":[{"sum_units":"UAH","sum_comment_unclear":false,"sum_hidden":false,"sum":"","sum_units_unclear":false,"sum_comment":"","sum_foreign_units":"UAH","sum_units_hidden":false,"sum_foreign_comment":"","sum_unclear":false,"sum_foreign":"","sum_comment_hidden":false},{"sum_units":"","sum_comment":"","sum_foreign_units":"","sum":"","sum_foreign_comment":"","sum_foreign":""}],"52":[{"sum_comment_unclear":false,"sum_comment":"","sum_foreign_units":"UAH","sum":"","sum_foreign_comment":"","sum_foreign":"","sum_units":"UAH"},{"sum_units":"","sum_comment":"","sum_foreign_units":"","sum":"","sum_foreign_comment":"","sum_foreign":""}],"53":[{"sum_units":"UAH","sum_comment":"","sum_foreign_units":"UAH","sum_hidden":false,"sum":"","sum_foreign_comment":"","sum_foreign":"","sum_unclear":false},{"sum_comment_unclear":false,"sum_comment":"","sum_foreign_units":"","sum":"","sum_foreign_comment":"","sum_foreign":"","sum_units":""},{"sum_units":"","sum_comment":"","sum_foreign_units":"","sum":"","sum_foreign_comment":"","sum_foreign":""},{"sum_units":"","sum_comment":"","sum_foreign_units":"","sum":"","sum_foreign_comment":"","sum_foreign":""}]},"declaration":{"notfull_lostpages":"","additional_info_text":"","additional_info":"","date":"2015-03-24T00:00:00","notfull":"","url":"http://static.declarations.com.ua/declarations/chosen_ones/mega_batch/starokozhko_volodymyr_petrovych.pdf"},"general":{"family":[{"inn":"","family_name":"Старокожко Т. В. 18. 12. 1974","relations_other":"","relations_hidden":false,"relations_unclear":false,"name_unclear":false,"inn_hidden":false,"name_hidden":false,"relations":"Подружжя"},{"inn":"","family_name":"Старокожко О. В. 24. 07. 2003","relations_other":"","name_unclear":false,"inn_hidden":false,"name_hidden":false,"relations":"Дитина"}],"family_raw":"","name":"Володимир","full_name_suggest":{"input":["Старокожко Володимир Петрович","Володимир Петрович Старокожко","Володимир Старокожко"],"output":"Старокожко Володимир Петрович"},"patronymic":"Петрович","inn_hidden":false,"patronymic_unclear":false,"last_name_hidden":true,"patronymic_hidden":false,"inn":"","inn_unclear":false,"last_name":"Старокожко","full_name":"Старокожко Володимир Петрович","post":{"post_hidden":false,"office":"Загальний місцевий суд","post":"заступник голови хорольського районного суду полтавської області","region":"Полтавська область","office_hidden":false,"office_unclear":false,"region_hidden":false,"post_unclear":false},"addresses":[{"place_city_type_hidden":false,"place_district_hidden":false,"place_address_unclear":true,"place":"","place_city":"","place_city_type_unclear":true,"place_city_type":"","place_city_hidden":false,"place_district":"","place_city_unclear":true,"place_address":"","place_address_hidden":false,"place_hidden":false}],"name_hidden":false,"last_name_unclear":false},"liabilities":{"54":{"sum_comment":"","sum_hidden":false,"sum":"","sum_foreign_comment":"","sum_foreign":"","sum_comment_hidden":false},"55":{"sum_comment":"","sum_hidden":false,"sum":"","sum_foreign_comment":"","sum_foreign":"","sum_foreign_hidden":false},"56":{"sum_comment":"","sum_foreign_comment":"","sum_foreign":"","sum_unclear":false,"sum":""},"57":{"sum_comment_unclear":false,"sum_comment":"","sum_hidden":false,"sum":"","sum_foreign_comment":"","sum_foreign":"","sum_unclear":false,"sum_comment_hidden":false},"58":{"sum_comment":"","sum_hidden":false,"sum":"","sum_foreign_comment":"","sum_foreign":"","sum_unclear":false,"sum_comment_hidden":false},"59":{"sum_comment":"","sum_foreign_comment":"","sum_foreign":"","sum":""},"60":{"sum_comment":"","sum_hidden":false,"sum":"","sum_foreign_comment":"","sum_foreign":"","sum_comment_hidden":false},"61":{"sum_comment":"","sum_foreign_comment":"","sum_foreign":"","sum":""},"62":{"sum_comment":"","sum_foreign_comment":"","sum_foreign":"","sum":""},"63":{"sum_comment":"","sum_foreign_comment":"","sum_foreign":"","sum_unclear":false,"sum":""},"64":{"sum_comment":"","sum_foreign_comment":"","sum_foreign":"","sum_unclear":false,"sum":""}},"intro":{"isnotdeclaration":"","declaration_year":"2014"}}]