[{"id":"vulyk_93_137","ft_src":"2006\nавтопричіп\nПФ-1 фермер\n1500 куб. см., 81 кВт\n2010\nRenault Megane\n6.93\n6.93\n27.3\n180\n180\n27.3\n25.5\n2014\n24865\n234875\n88463\n234875\n63598\nпенсія, стипендія, виплати по народженню дитини\n1500 куб. см., 81 кВт\nRenault Megane\n2010\nавтопричіп\nПФ-1 фермер\n2006\n6.93\n27.3\n25.5\n180\n180\n6.93\n27.3\nТаратін\nПодружжя\nТаратіна А. В. 23. 11. 1978\nДитина\nТаратіна А. В. 16. 08. 1995\nДитина\nТаратіна В. В. 25. 09. 2000\nДитина\nТаратін Г. В. 23. 10. 2013\nТаратін Валентин Олександрович\nВалентин Олександрович Таратін\nВалентин Таратін\nТаратін Валентин Олександрович\nТаратін Валентин Олександрович\nВалентин\nОлександрович\nЧеркаська область\nЗагальний місцевий суд\nсуддя золотоніського міськрайонного суду черкаської області\n24865\n234875\n63598\nпенсія, стипендія, виплати по народженню дитини\n234875\n88463\n2014\nПодружжя\nТаратіна А. В. 23. 11. 1978\nДитина\nТаратіна А. В. 16. 08. 1995\nДитина\nТаратіна В. В. 25. 09. 2000\nТаратін Г. В. 23. 10. 2013\nДитина\nТаратін\nОлександрович\nЧеркаська область\nЗагальний місцевий суд\nсуддя золотоніського міськрайонного суду черкаської області\nТаратін Валентин Олександрович\nТаратін Валентин Олександрович\nВалентин Олександрович Таратін\nВалентин Таратін\nТаратін Валентин Олександрович\nВалентин","estate":{"23":[{"address":"","space_units":"м²","costs_comment":"","space_unclear":false,"region_hidden":true,"space_comment":"","address_hidden":false,"space":"180","space_comment_unclear":false,"costs_rent_comment":"","costs":"","region":"","costs_rent":""}],"24":[{"address":"","space_units":"м²","costs_comment":"","space_unclear":false,"region_hidden":true,"space_comment":"","address_hidden":false,"space":"27.3","space_comment_unclear":false,"costs_rent_comment":"","costs":"","region":"","costs_rent":""}],"25":[{"address":"","space_units":"м²","space_hidden":false,"space_unclear":false,"region_hidden":true,"costs_comment":"","space_comment":"","address_hidden":false,"space":"25.5","costs_rent_comment_unclear":false,"costs_rent_comment":"","costs":"","region":"","costs_rent":""}],"27":[{"costs":"","address":"","space_units":"м²","costs_rent_comment":"","space":"6.93","space_comment":"","region_hidden":true,"costs_comment":"","region":"","address_hidden":false,"costs_rent":""}],"29":[{"costs_property_comment":"","address":"","space_units":"м²","space_unclear":false,"region_hidden":true,"costs_property":"","space_comment":"","address_hidden":true,"space_comment_unclear":false,"costs_rent_comment":"","space":"180","region":"","costs_rent":""}],"30":[{"costs_property_comment":"","address":"","space_units":"м²","space_unclear":false,"region_hidden":true,"costs_property":"","space_comment":"","address_hidden":true,"costs_rent_comment":"","space":"27.3","region":"","costs_rent":""}],"33":[{"costs_property_comment":"","address":"","space_units":"м²","space_hidden":false,"space_comment":"","region_hidden":true,"costs_property":"","region":"","address_hidden":true,"costs_rent_comment":"","space":"6.93","costs_rent":""}]},"vehicle":{"39":[{"sum_comment":"","brand_info":"автопричіп","sum":"","brand_unclear":false,"year":"2006","brand":"ПФ-1 фермер","sum_rent":"","sum_rent_comment":""}],"40":[{"sum_comment":"","brand_info":"1500 куб. см., 81 кВт","sum":"","sum_rent_comment":"","year":"2010","brand":"Renault Megane","sum_rent":"","brand_info_unclear":false}]},"source":"VULYK","income":{"5":{"family":"88463","family_comment":"","comment":"","value_hidden":false,"value_unclear":false,"value":"234875","family_hidden":false,"family_unclear":false},"6":{"family_comment":"","family":"24865","comment":"","value_unclear":false,"family_unclear":false,"value":"234875"},"7":{"source_name_hidden":false,"family_comment":"","comment":"","family":"","comment_hidden":false,"source_name_unclear":false,"value":"","source_name":""},"8":{"family_comment":"","value":"","family":"","comment":""},"9":{"family_comment":"","family":"","comment":"","value_unclear":false,"family_unclear":false,"family_hidden":false,"value":"","family_comment_unclear":false},"10":{"family_comment":"","value":"","family":"","comment":""},"11":{"family_comment":"","value":"","family":"","comment":""},"12":{"family_comment":"","value":"","family":"","comment":""},"13":{"family_comment":"","value":"","family":"","comment":""},"14":{"family_comment":"","value":"","family":"","comment":""},"15":{"family_comment":"","value":"","family":"","comment":""},"16":{"family_comment":"","value":"","family":"","comment":""},"17":{"family_comment":"","value":"","family":"","comment":""},"18":{"family_comment":"","value":"","family":"","comment":""},"19":{"family_comment":"","value":"","family":"","comment":""},"20":{"family_comment":"пенсія, стипендія, виплати по народженню дитини","family":"63598","comment":"","value_unclear":false,"value":"","comment_unclear":false,"family_unclear":false,"family_comment_hidden":false,"family_comment_unclear":false}},"general":{"inn":"","addresses":[{"place_city_type_hidden":false,"place_city_type":"","place_city_hidden":false,"place_hidden":true,"place_district":"","place_district_hidden":false,"place":"","place_address":"","place_address_hidden":false,"place_city":""}],"last_name":"Таратін","full_name":"Таратін Валентин Олександрович","family":[{"inn":"","family_name":"Таратіна А. В. 23. 11. 1978","relations_hidden":false,"name_unclear":false,"relations":"Подружжя","inn_hidden":false,"name_hidden":false,"relations_other":""},{"inn":"","family_name":"Таратіна А. В. 16. 08. 1995","relations_other":"","name_unclear":false,"inn_hidden":false,"name_hidden":false,"relations":"Дитина"},{"inn":"","family_name":"Таратіна В. В. 25. 09. 2000","relations_other":"","name_unclear":false,"inn_hidden":false,"name_hidden":false,"relations":"Дитина"},{"inn":"","family_name":"Таратін Г. В. 23. 10. 2013","relations_other":"","name_hidden":false,"inn_hidden":false,"relations":"Дитина"}],"patronymic":"Олександрович","inn_hidden":true,"name":"Валентин","post":{"office":"Загальний місцевий суд","post":"суддя золотоніського міськрайонного суду черкаської області","candidate":"","office_unclear":false,"region":"Черкаська область","region_unclear":false,"post_unclear":false},"family_raw":"","full_name_suggest":{"input":["Таратін Валентин Олександрович","Валентин Олександрович Таратін","Валентин Таратін"],"output":"Таратін Валентин Олександрович"}},"liabilities":{"54":{"sum_comment":"","sum_foreign_comment":"","sum_foreign":"","sum_hidden":false,"sum":""},"55":{"sum_comment":"","sum_foreign_comment":"","sum_foreign":"","sum":""},"56":{"sum_comment":"","sum_foreign_comment":"","sum_foreign":"","sum":""},"57":{"sum_comment":"","sum_hidden":false,"sum":"","sum_foreign_comment":"","sum_foreign":"","sum_unclear":false,"sum_comment_hidden":false},"58":{"sum_comment_unclear":false,"sum_comment":"","sum_hidden":false,"sum":"","sum_foreign_comment":"","sum_foreign":"","sum_unclear":false},"59":{"sum_comment":"","sum_foreign_comment":"","sum_foreign":"","sum":""},"60":{"sum_comment":"","sum_foreign_comment":"","sum_foreign":"","sum_hidden":false,"sum":""},"61":{"sum_comment":"","sum_foreign_comment":"","sum_foreign":"","sum":""},"62":{"sum_comment":"","sum_foreign_comment":"","sum_foreign":"","sum":""},"63":{"sum_comment":"","sum_foreign_comment":"","sum_foreign":"","sum":""},"64":{"sum_comment":"","sum_foreign_comment":"","sum_foreign":"","sum":""}},"declaration":{"notfull_lostpages":"","additional_info_text":"","additional_info":"","date":"2015-03-30T00:00:00","notfull":"","url":"http://static.declarations.com.ua/declarations/chosen_ones/judges_batch/3583_taratin_valentyn_oleksandrovych.pdf"},"intro":{"isnotdeclaration":"","declaration_year":"2014"}}]