[{"id":"vulyk_94_173","ft_src":"1.2 л\nFord Fiesta\n2012\n2014\n2416\n192188\n12180\nТУ ДСА України в Полтавській області ПП 'Барбус-ЛС' ЦПНЗ соцвиплат у Полтавській області\n3057\n218873\n641\n14505\n1.2 л\nFord Fiesta\n2012\nТУ ДСА України в Полтавській області ПП 'Барбус-ЛС' ЦПНЗ соцвиплат у Полтавській області\n192188\n2416\n14505\n641\n218873\n3057\n12180\nПодружжя\nТатіщев В. О\nДитина\nТатіщева О. В\nДитина\nТатіщева Є. В\nТатіщева Яна Вікторівна\nЯна Вікторівна Татіщева\nЯна Татіщева\nТатіщева Яна Вікторівна\nТатіщева Яна Вікторівна\nЯна\nВікторівна\nЗагальний місцевий суд\nПолтавська область\nсуддя гребінківського районного суду полтавської області\nТатіщева\n9247\n32116\n2014\n9247\n32116\nТатіщев В. О\nПодружжя\nТатіщева О. В\nДитина\nТатіщева Є. В\nДитина\nВікторівна\nТатіщева\nЯна\nТатіщева Яна Вікторівна\nЯна Вікторівна Татіщева\nЯна Татіщева\nТатіщева Яна Вікторівна\nПолтавська область\nЗагальний місцевий суд\nсуддя гребінківського районного суду полтавської області\nТатіщева Яна Вікторівна","vehicle":{"35":[{"year_hidden":false,"brand_info":"1.2 л","sum_rent_comment":"","brand_unclear":false,"brand_hidden":false,"year":"2012","brand":"Ford Fiesta","brand_info_hidden":false,"sum_rent":"","sum_comment":"","year_unclear":false,"brand_info_unclear":false,"sum":""}]},"source":"VULYK","income":{"5":{"family_comment":"","family":"3057","comment":"","value_unclear":false,"family_hidden":false,"value":"218873"},"6":{"family_comment":"","value":"192188","family":"2416","comment":"","value_unclear":false},"7":{"source_name_hidden":false,"family_comment":"","comment":"","family":"","source_name_unclear":false,"value":"","source_name":"ТУ ДСА України в Полтавській області ПП 'Барбус-ЛС' ЦПНЗ соцвиплат у Полтавській області"},"8":{"family_comment":"","value":"","family":"","comment":""},"9":{"family_comment":"","comment_unclear":false,"value":"","family":"","comment":""},"10":{"family_comment":"","value":"12180","family":"","comment":""},"11":{"family_comment":"","value":"","family_unclear":false,"family":"","comment":""},"12":{"family_comment":"","value":"","family":"","comment":""},"13":{"family_comment":"","value":"","family":"","comment":""},"14":{"family_comment":"","value":"","family":"","comment":""},"15":{"family_comment":"","value":"","family":"","comment":""},"16":{"family_comment":"","value":"","family":"","comment":""},"17":{"family_comment":"","value":"","family":"","comment":""},"18":{"family_comment":"","value":"","family":"","comment":""},"19":{"family_comment":"","value":"","family":"","comment":""},"20":{"family_comment":"","comment":"","family":"641","value_unclear":false,"comment_unclear":false,"value":"14505"}},"general":{"family":[{"inn":"","family_name":"Татіщев В. О","relations_hidden":false,"name_unclear":false,"inn_hidden":true,"name_hidden":false,"relations":"Подружжя"},{"inn":"","family_name":"Татіщева О. В","relations_other":"","relations_unclear":false,"name_unclear":false,"inn_hidden":false,"name_hidden":false,"relations":"Дитина"},{"inn":"","family_name":"Татіщева Є. В","relations_other":"","relations_unclear":false,"name_unclear":false,"inn_hidden":false,"name_hidden":false,"relations":"Дитина"}],"family_raw":"","name":"Яна","full_name_suggest":{"input":["Татіщева Яна Вікторівна","Яна Вікторівна Татіщева","Яна Татіщева"],"output":"Татіщева Яна Вікторівна"},"patronymic":"Вікторівна","inn_hidden":true,"addresses":[{"place_city_type_hidden":false,"place_district_hidden":false,"place_city_hidden":false,"place_district":"","place_city_type":"","place_address":"","place":"","place_city":"","place_address_hidden":false,"place_hidden":true}],"patronymic_hidden":false,"inn":"","inn_unclear":false,"last_name":"Татіщева","full_name":"Татіщева Яна Вікторівна","post":{"post_hidden":false,"office":"Загальний місцевий суд","post":"суддя гребінківського районного суду полтавської області","candidate":"","region_unclear":false,"region":"Полтавська область","post_unclear":false,"office_unclear":false}},"liabilities":{"54":{"sum_comment_unclear":false,"sum_comment":"","sum":"","sum_foreign_comment":"","sum_foreign":"","sum_unclear":false,"sum_comment_hidden":false},"55":{"sum_comment":"","sum_foreign_comment":"","sum_foreign":"","sum":""},"56":{"sum_comment":"","sum_foreign_comment":"","sum_foreign":"","sum_unclear":false,"sum":""},"57":{"sum_comment":"","sum_hidden":false,"sum":"32116","sum_foreign_comment":"","sum_foreign":"","sum_unclear":false},"58":{"sum_comment":"","sum_hidden":false,"sum":"9247","sum_foreign_comment":"","sum_foreign":"","sum_unclear":false},"59":{"sum_comment":"","sum_foreign_comment":"","sum_foreign":"","sum":""},"60":{"sum_comment":"","sum_foreign_comment":"","sum_foreign":"","sum":"","sum_comment_hidden":false},"61":{"sum_comment":"","sum_foreign_comment":"","sum_foreign":"","sum":""},"62":{"sum_comment":"","sum_foreign_comment":"","sum_foreign":"","sum_hidden":false,"sum":""},"63":{"sum_comment":"","sum_foreign_comment":"","sum_foreign":"","sum":"","sum_comment_hidden":false},"64":{"sum_comment":"","sum_foreign_comment":"","sum_foreign":"","sum_unclear":false,"sum":""}},"declaration":{"notfull_lostpages":"","additional_info_text":"","additional_info":"","date":"2015-03-30T00:00:00","notfull":"","url":"http://static.declarations.com.ua/declarations/chosen_ones/judges_batch/3819_tatishcheva_iana_viktorivna.pdf"},"intro":{"isnotdeclaration":"","declaration_year":"2014"}},{"id":"vulyk_40_28","declaration":{"notfull_lostpages":"","date":"2014-03-24T00:00:00","notfull":"","url":"http://static.declarations.com.ua/declarations/chosen_ones/mega_batch/tatishcheva_iana_viktorivna.pdf"},"estate":{"23":[{"costs":"","address":"","space_units":"м²","costs_rent_comment":"","space":"","space_comment":"","region_hidden":false,"costs_comment":"","region":"","address_hidden":false,"costs_rent":""},{"costs":"","address":"","space_units":"","costs_rent_comment":"","space":"","space_comment":"","costs_comment":"","region":"","costs_rent":""},{"costs":"","address":"","space_units":"","costs_rent_comment":"","space":"","space_comment":"","costs_comment":"","region":"","costs_rent":""},{"costs":"","address":"","space_units":"","costs_rent_comment":"","space":"","space_comment":"","costs_comment":"","costs_rent":""}]},"vehicle":{"35":[{"sum_comment":"","brand_info_hidden":false,"brand_info":"1.3 л","sum":"","sum_rent_comment":"","year":"2012","brand":"Ford Fiesta","sum_rent":"","brand_info_unclear":false}]},"source":"VULYK","income":{"5":{"family_comment":"","value":"129199","family_unclear":false,"family":"14541","comment":""},"6":{"family_comment":"","value":"98262","family":"14541","comment":"","value_unclear":false},"7":{"family":"","family_comment":"","value":"","comment":"","source_name":"Гребенінківський районий суд Полтавської області, УПСЗН в Ленінському районі Полтавської області,ПП 'Барбус-ЛС'"},"8":{"family_comment":"","value":"","family":"","comment":""},"9":{"family_comment":"","comment":"","family":"","value_unclear":false,"comment_unclear":false,"value":"","family_hidden":false},"10":{"family_comment":"","value":"","family":"","comment":""},"11":{"family_comment":"","value":"","family":"","comment":""},"12":{"family_comment":"","value":"","family":"","comment":""},"13":{"family_comment":"","value":"","family":"","comment":""},"14":{"family_comment":"","value":"","family":"","comment":""},"15":{"family_comment":"","value":"","family":"","comment":""},"16":{"family_comment":"","value":"","family":"","comment":""},"17":{"family_comment":"","value":"","family":"","comment":""},"18":{"family_comment":"","value":"","family":"","comment":""},"19":{"family_comment":"","value":"","family":"","comment":""},"20":{"family_comment":"","family":"","comment":"","value_unclear":false,"comment_hidden":false,"value":"30937"}},"banks":{"45":[{"sum_units":"UAH","sum_comment":"","sum_foreign_units":"UAH","sum_hidden":false,"sum":"","sum_foreign_comment":"","sum_foreign":""},{"sum_units":"","sum_comment":"","sum_foreign_units":"","sum":"","sum_foreign_comment":"","sum_foreign":""},{"sum_units":"","sum_comment":"","sum_foreign_units":"","sum":"","sum_foreign_comment":"","sum_foreign":""}],"46":[{"sum_units":"UAH","sum_comment":"","sum_foreign_units":"UAH","sum":"","sum_foreign_comment":"","sum_foreign":"","sum_unclear":false}],"47":[{"sum_units":"UAH","sum_comment":"","sum_foreign_units":"UAH","sum":"","sum_foreign_comment":"","sum_foreign":""}],"48":[{"sum_units":"UAH","sum_comment":"","sum_foreign_units":"UAH","sum":"","sum_foreign_comment":"","sum_foreign":""}],"49":[{"sum_units":"UAH","sum_comment":"","sum_foreign_units":"UAH","sum":"","sum_foreign_comment":"","sum_foreign":""}],"50":[{"sum_units":"UAH","sum_comment":"","sum_foreign_units":"UAH","sum":"","sum_foreign_comment":"","sum_foreign":""}],"51":[{"sum_units":"UAH","sum_comment":"","sum_foreign_units":"UAH","sum":"","sum_foreign_comment":"","sum_foreign":""}],"52":[{"sum_units":"UAH","sum_comment":"","sum_foreign_units":"UAH","sum":"","sum_foreign_comment":"","sum_foreign":""}],"53":[{"sum_units":"UAH","sum_comment":"","sum_foreign_units":"UAH","sum":"","sum_foreign_comment":"","sum_foreign":""}]},"ft_src":"2012\n1.3 л\nFord Fiesta\n2013\n1.3 л\n2012\nFord Fiesta\nТатіщева\nТатіщева Яна Вікторівна\nЯна Вікторівна Татіщева\nЯна Татіщева\nТатіщева Яна Вікторівна\nЯна\nВікторівна\nТатіщева Яна Вікторівна\nЗагальний місцевий суд\nсуддя гребінківського районного суду полтавської області\nПолтавська область\nПодружжя\nТатіщев В. О\nДитина\nТатіщева О. В\nТатіщева Є. В\nДитина\n21934\n11730\n6796\nГребенінківський районий суд Полтавської області, УПСЗН в Ленінському районі Полтавської області,ПП 'Барбус-ЛС'\n98262\n14541\n30937\n129199\n14541\n2013\n11730\n21934\n6796\nТатіщев В. О\nПодружжя\nТатіщева О. В\nДитина\nТатіщева Є. В\nДитина\nВікторівна\nТатіщева\nсуддя гребінківського районного суду полтавської області\nПолтавська область\nЗагальний місцевий суд\nТатіщева Яна Вікторівна\nТатіщева Яна Вікторівна\nЯна Вікторівна Татіщева\nЯна Татіщева\nТатіщева Яна Вікторівна\nЯна\n14541\n98262\nГребенінківський районий суд Полтавської області, УПСЗН в Ленінському районі Полтавської області,ПП 'Барбус-ЛС'\n14541\n129199\n30937","general":{"inn":"","addresses":[{"place_city_type_hidden":false,"place_city_type":"","place_city_hidden":false,"place_hidden":true,"place_district":"","place_district_hidden":false,"place":"","place_address":"","place_address_hidden":false,"place_city":""}],"last_name":"Татіщева","full_name":"Татіщева Яна Вікторівна","family":[{"inn":"","family_name":"Татіщев В. О","relations_other":"","name_hidden":false,"inn_hidden":false,"relations":"Подружжя"},{"inn":"","family_name":"Татіщева О. В","relations_other":"","name_unclear":false,"inn_hidden":false,"relations":"Дитина"},{"inn":"","family_name":"Татіщева Є. В","inn_hidden":false,"relations":"Дитина"}],"patronymic":"Вікторівна","inn_hidden":true,"name":"Яна","post":{"office":"Загальний місцевий суд","region":"Полтавська область","post":"суддя гребінківського районного суду полтавської області"},"family_raw":"","full_name_suggest":{"input":["Татіщева Яна Вікторівна","Яна Вікторівна Татіщева","Яна Татіщева"],"output":"Татіщева Яна Вікторівна"}},"liabilities":{"54":{"sum_comment":"","sum_foreign_comment":"","sum_foreign":"","sum":"6796"},"55":{"sum_comment":"","sum_foreign_comment":"","sum_foreign":"","sum":""},"56":{"sum_comment":"","sum_foreign_comment":"","sum_foreign":"","sum":""},"57":{"sum_comment":"","sum_hidden":false,"sum":"21934","sum_foreign_comment":"","sum_foreign":"","sum_comment_hidden":false},"58":{"sum_comment":"","sum_hidden":false,"sum":"11730","sum_foreign_comment":"","sum_foreign":"","sum_comment_hidden":false},"59":{"sum_comment":"","sum_foreign_comment":"","sum_foreign":"","sum":""},"60":{"sum_comment":"","sum_foreign_comment":"","sum_foreign":"","sum":""},"61":{"sum_comment":"","sum_foreign_comment":"","sum_foreign":"","sum":""},"62":{"sum_comment":"","sum_foreign_comment":"","sum_foreign":"","sum":""},"63":{"sum_comment":"","sum_foreign_comment":"","sum_foreign":"","sum":""},"64":{"sum_comment":"","sum_foreign_comment":"","sum_foreign":"","sum":""}},"intro":{"declaration_year":"2013"}}]