[{"id":"vulyk_99_55","ft_src":"2007\nSubaru Forester\n1994 куб.см.\n170000\n1998.110 кВт\nMitsubishi Lancer\n2007\n13.64\n76.6\n2015\n118500\n163434\n118500\n383467\nПАТ Полікомбанк м. Чернігів\n220033\n1994 куб.см.\nSubaru Forester\n2007\n170000\n1998.110 кВт\n2007\nMitsubishi Lancer\n2015\nТихоненко\nТихоненко Оксана Михайлівна\nОксана Михайлівна Тихоненко\nОксана Тихоненко\nТихоненко Оксана Михайлівна\nОксана\nМихайлівна\nТихоненко Оксана Михайлівна\nАдміністративний місцевий суд\nсуддя чернігівського окружного адміністративного суду\nЧернігівська область\nПодружжя\nТихоненко Володимир Вікторович\nДитина\nТихоненко Єлизавета Володимирівна\nДитина\nАртюх Данило Євгенович\nТихоненко Софія Володимирівна\nДитина\nПолікомбанк м. Чернігів\n37473\n2922\nПрАТ Поліська страхова компанія\nПолікомбанк м. Чернігів\n66420\n163434\n118500\n220033\nПАТ Полікомбанк м. Чернігів\n383467\n118500\n13.64\n76.6\nПолікомбанк м. Чернігів\n37473\nПолікомбанк м. Чернігів\n66420\nПрАТ Поліська страхова компанія\n2922\nТихоненко Володимир Вікторович\nПодружжя\nТихоненко Єлизавета Володимирівна\nДитина\nАртюх Данило Євгенович\nДитина\nДитина\nТихоненко Софія Володимирівна\nМихайлівна\nТихоненко\nсуддя чернігівського окружного адміністративного суду\nЧернігівська область\nАдміністративний місцевий суд\nТихоненко Оксана Михайлівна\nТихоненко Оксана Михайлівна\nОксана Михайлівна Тихоненко\nОксана Тихоненко\nТихоненко Оксана Михайлівна\nОксана","estate":{"25":[{"address":"","space_units":"м²","space_hidden":false,"space_unclear":false,"region_hidden":true,"costs_comment":"","space_comment":"","address_hidden":false,"space":"76.6","costs_rent_comment":"","costs":"","region":"","costs_rent":""}],"31":[{"costs_property_comment":"","address":"","space_units":"м²","costs_rent_comment":"","space":"13.64","region":"","region_hidden":true,"costs_property":"","space_comment":"","address_hidden":false,"costs_rent":""}]},"vehicle":{"35":[{"sum_comment":"","brand_info":"1994 куб.см.","brand_unclear":false,"sum_rent_comment":"","year":"2007","brand":"Subaru Forester","sum_rent":"","brand_info_unclear":false,"sum":"170000"}],"40":[{"sum_comment":"","brand_info_hidden":false,"sum_rent":"","sum":"","brand_unclear":false,"year":"2007","brand":"Mitsubishi Lancer","brand_info":"1998.110 кВт","sum_rent_comment":"","brand_info_unclear":false}]},"source":"VULYK","income":{"5":{"family_comment":"","family":"118500","comment":"","value_unclear":false,"family_unclear":false,"value":"383467"},"6":{"family_comment":"","family":"118500","comment":"","value_unclear":false,"family_unclear":false,"value":"163434"},"7":{"family":"","family_comment":"","value":"","comment":"","source_name":""},"8":{"family_comment":"","value":"","family":"","comment":""},"9":{"family_comment":"","value":"","family":"","comment":""},"10":{"family_comment":"","value":"","family":"","comment":""},"11":{"family_comment":"","value":"","family":"","comment":""},"12":{"family_comment":"","value":"","family":"","comment":""},"13":{"family_comment":"","value":"","family":"","comment":""},"14":{"family_comment":"","value":"","family":"","comment":""},"15":{"family_comment":"","value":"","family":"","comment":"","value_unclear":false},"16":{"family_comment":"","value":"","family":"","comment":""},"17":{"family_comment":"","value":"","family":"","comment":""},"18":{"family_comment":"","value":"","family":"","comment":""},"19":{"family_comment":"","value":"","family":"","comment":""},"20":{"family_comment":"","family":"","comment":"ПАТ Полікомбанк м. Чернігів","value_unclear":false,"family_unclear":false,"value":"220033","family_comment_unclear":false}},"general":{"inn":"","addresses":[{"place_city_type_hidden":false,"place_city_type":"","place_city_hidden":true,"place_hidden":true,"place_district":"","place_district_hidden":false,"place":"","place_address":"","place_address_hidden":true,"place_city":""}],"last_name":"Тихоненко","full_name":"Тихоненко Оксана Михайлівна","family":[{"inn":"","family_name":"Тихоненко Володимир Вікторович","name_unclear":false,"inn_hidden":true,"name_hidden":true,"relations":"Подружжя"},{"inn":"","family_name":"Тихоненко Єлизавета Володимирівна","relations_other":"","name_unclear":false,"inn_hidden":true,"relations":"Дитина"},{"inn":"","family_name":"Артюх Данило Євгенович","relations_other":"","name_unclear":false,"inn_hidden":true,"name_hidden":false,"relations":"Дитина"},{"inn":"","family_name":"Тихоненко Софія Володимирівна","inn_hidden":true,"relations_other":"","relations":"Дитина"}],"patronymic":"Михайлівна","inn_hidden":true,"name":"Оксана","post":{"office":"Адміністративний місцевий суд","region":"Чернігівська область","post_unclear":false,"post":"суддя чернігівського окружного адміністративного суду"},"family_raw":"","full_name_suggest":{"input":["Тихоненко Оксана Михайлівна","Оксана Михайлівна Тихоненко","Оксана Тихоненко"],"output":"Тихоненко Оксана Михайлівна"}},"liabilities":{"54":{"sum_comment_unclear":false,"sum_comment":"ПрАТ Поліська страхова компанія","sum":"2922","sum_foreign_comment":"","sum_foreign":"","sum_comment_hidden":false},"55":{"sum_comment":"","sum_foreign_comment":"","sum_foreign":"","sum":""},"56":{"sum_comment":"","sum_foreign_comment":"","sum_foreign":"","sum":""},"57":{"sum_comment":"Полікомбанк м. Чернігів","sum_foreign_comment":"","sum_foreign":"","sum":"66420","sum_comment_hidden":false},"58":{"sum_comment":"Полікомбанк м. Чернігів","sum_foreign_comment":"","sum_foreign":"","sum":"37473","sum_comment_hidden":false},"59":{"sum_comment":"","sum":"","sum_foreign_comment":"","sum_foreign":"","sum_unclear":false,"sum_comment_hidden":false},"60":{"sum_comment":"","sum_foreign_comment":"","sum_foreign":"","sum":"","sum_comment_hidden":false},"61":{"sum_comment":"","sum_foreign_comment":"","sum_foreign":"","sum":""},"62":{"sum_comment":"","sum_foreign_comment":"","sum_foreign":"","sum":""},"63":{"sum_comment":"","sum_foreign_comment":"","sum_foreign":"","sum":"","sum_comment_hidden":false},"64":{"sum_comment":"","sum_foreign_comment":"","sum_foreign":"","sum":"","sum_comment_hidden":false}},"declaration":{"notfull_lostpages":"","date":"2016-03-29T00:00:00","notfull":"","url":"http://static.declarations.com.ua/declarations/chosen_ones/judges_batch/604_tykhonenko_oksana_mykhailivna_2015.pdf"},"intro":{"declaration_year":"2015"}},{"id":"vulyk_98_5","ft_src":"об'єм циліндрів 1998 , потужність 1104\n2007\nMitsubishi Lancer\n13.64\n76.6\n2014\n60350\n208581\n60350\n328008\n120000\n27\nоб'єм циліндрів 1998 , потужність 1104\n2007\nMitsubishi Lancer\n2014\nАдміністративний місцевий суд\nсуддя чернігівського окружного адміністративного суду\nЧернігівська область\nТихоненко Оксана Михайлівна\nОксана Михайлівна Тихоненко\nОксана Тихоненко\nТихоненко Оксана Михайлівна\nТихоненко Оксана Михайлівна\nПодружжя\nТихоненко Володимир Вікторович\nДитина\nТихоненко Єлизавета Володимирівна\nДитина\nАртюк Данило Євгенович\nТихоненко Софія Володимирівна\nДитина\nОксана\nТихоненко\nМихайлівна\n2001\nПрАТ Поліська страхова компанія\n199066\n42840 ПАТ Полікомбанк м. Чернігів, 156226 філія Черн. обл. упр. АТ Ощадбанк\n37249\n29346 ПАТ Полікомбанк м. Чернігів, 7903 філія Черн. обл. упр. АТ Ощадбанк\n208581\n60350\n27\n60350\n328008\n120000\n13.64\n76.6\n29346 ПАТ Полікомбанк м. Чернігів, 7903 філія Черн. обл. упр. АТ Ощадбанк\n37249\n42840 ПАТ Полікомбанк м. Чернігів, 156226 філія Черн. обл. упр. АТ Ощадбанк\n199066\nПрАТ Поліська страхова компанія\n2001\nПодружжя\nТихоненко Володимир Вікторович\nДитина\nТихоненко Єлизавета Володимирівна\nАртюк Данило Євгенович\nДитина\nТихоненко Софія Володимирівна\nДитина\nМихайлівна\nТихоненко\nОксана\nТихоненко Оксана Михайлівна\nОксана Михайлівна Тихоненко\nОксана Тихоненко\nТихоненко Оксана Михайлівна\nсуддя чернігівського окружного адміністративного суду\nЧернігівська область\nАдміністративний місцевий суд\nТихоненко Оксана Михайлівна","estate":{"25":[{"address":"","space_units":"м²","costs_comment":"","space_unclear":false,"region_hidden":true,"space_comment":"","address_hidden":false,"costs":"","address_unclear":false,"costs_rent_comment":"","space":"76.6","region":"","costs_rent":""}],"31":[{"costs_property_comment":"","address":"","space_units":"м²","space_comment":"","region_hidden":true,"costs_property":"","region":"","address_hidden":false,"costs_rent_comment":"","space":"13.64","region_unclear":false,"costs_rent":""}]},"vehicle":{"40":[{"sum_comment":"","brand_info":"об'єм циліндрів 1998 , потужність 1104","sum":"","sum_rent_comment":"","year":"2007","brand":"Mitsubishi Lancer","sum_rent":""}]},"source":"VULYK","income":{"5":{"family_comment":"","family":"60350","comment":"","value_unclear":true,"family_unclear":false,"value":"328008"},"6":{"family_comment":"","value":"208581","family":"60350","comment":"","value_unclear":false},"7":{"family":"","family_comment":"","value":"","comment":"","source_name":""},"8":{"family_comment":"","value":"","family":"","comment":""},"9":{"family_comment":"","value":"","family":"","comment":"","value_unclear":false},"10":{"family_comment":"","value":"","family":"","comment":""},"11":{"family_comment":"","value":"","family":"","comment":""},"12":{"family_comment":"","value":"","family":"","comment":""},"13":{"family_comment":"","value":"","family":"","comment":""},"14":{"family_comment":"","value":"","family":"","comment":""},"15":{"family_comment":"","value":"","family":"","comment":""},"16":{"family_comment":"","value":"120000","family":"","comment":""},"17":{"family_comment":"","value":"","family":"","comment":""},"18":{"family_comment":"","value":"","family":"","comment":""},"19":{"family_comment":"","value":"","family":"","comment":""},"20":{"family_comment":"","value":"27","family":"","comment":"","value_unclear":false}},"general":{"family":[{"inn":"","family_name":"Тихоненко Володимир Вікторович","relations_other":"","name_unclear":false,"inn_hidden":true,"name_hidden":true,"relations":"Подружжя"},{"inn":"","family_name":"Тихоненко Єлизавета Володимирівна","relations_other":"","name_unclear":false,"inn_hidden":true,"name_hidden":true,"relations":"Дитина"},{"inn":"","family_name":"Артюк Данило Євгенович","name_unclear":true,"inn_hidden":false,"name_hidden":true,"relations":"Дитина"},{"inn":"","name_hidden":true,"family_name":"Тихоненко Софія Володимирівна","inn_hidden":false,"relations":"Дитина"}],"family_raw":"","name":"Оксана","full_name_suggest":{"input":["Тихоненко Оксана Михайлівна","Оксана Михайлівна Тихоненко","Оксана Тихоненко"],"output":"Тихоненко Оксана Михайлівна"},"patronymic":"Михайлівна","inn_hidden":true,"addresses":[{"place_city_type_hidden":false,"place_city_type":"","place_city_hidden":false,"place_hidden":true,"place_district":"","place_district_hidden":false,"place":"","place_address":"","place_address_hidden":true,"place_city":""}],"last_name_hidden":false,"patronymic_hidden":false,"inn":"","inn_unclear":false,"last_name":"Тихоненко","full_name":"Тихоненко Оксана Михайлівна","post":{"office":"Адміністративний місцевий суд","region":"Чернігівська область","post_unclear":false,"post":"суддя чернігівського окружного адміністративного суду"},"last_name_unclear":false},"liabilities":{"54":{"sum_comment_unclear":false,"sum_comment":"ПрАТ Поліська страхова компанія","sum_hidden":false,"sum":"2001","sum_foreign_comment":"","sum_foreign":"","sum_unclear":false,"sum_comment_hidden":false},"55":{"sum_comment":"","sum_foreign_comment":"","sum_foreign":"","sum":""},"56":{"sum_comment":"","sum_foreign_comment":"","sum_foreign":"","sum_unclear":false,"sum":""},"57":{"sum_comment_unclear":false,"sum_comment":"42840 ПАТ Полікомбанк м. Чернігів, 156226 філія Черн. обл. упр. АТ Ощадбанк","sum_hidden":false,"sum":"199066","sum_foreign_comment":"","sum_foreign":"","sum_unclear":false,"sum_comment_hidden":false},"58":{"sum_comment":"29346 ПАТ Полікомбанк м. Чернігів, 7903 філія Черн. обл. упр. АТ Ощадбанк","sum_hidden":false,"sum":"37249","sum_foreign_comment":"","sum_foreign":"","sum_unclear":false,"sum_comment_hidden":false},"59":{"sum_comment":"","sum_comment_unclear":false,"sum_foreign_comment":"","sum":"","sum_foreign":""},"60":{"sum_comment":"","sum_hidden":false,"sum":"","sum_foreign_comment":"","sum_foreign":"","sum_comment_hidden":false},"61":{"sum_comment":"","sum_foreign_comment":"","sum_foreign":"","sum":""},"62":{"sum_comment":"","sum":"","sum_foreign_comment":"","sum_foreign":"","sum_unclear":false,"sum_comment_hidden":false},"63":{"sum_comment_unclear":false,"sum_comment":"","sum":"","sum_foreign_comment":"","sum_foreign":"","sum_comment_hidden":false},"64":{"sum_comment":"","sum_foreign_comment":"","sum_foreign":"","sum":"","sum_comment_hidden":false}},"declaration":{"date":"2015-03-30T00:00:00","url":"http://static.declarations.com.ua/declarations/chosen_ones/judges_batch/4475_tykhonenko_oksana_mykhailivna.pdf"},"intro":{"declaration_year":"2014"}}]