[{"id":"vulyk_86_75","ft_src":"Донецька область\n1/3 частина\nм. Артемівськ\n68\nм. Красноармійськ\n47\nДонецька область\n2014\n181647.32\n12932\nвиплати по догляду за дитиною\n12932\n181647.32\n181647.32\n12932\nвиплати по догляду за дитиною\n181647.32\n12932\nТокарєв Артем Геннадійович\nАртем Геннадійович Токарєв\nАртем Токарєв\nТокарєв Артем Геннадійович\nТокарєв Артем Геннадійович\nПодружжя\nТокарєва О. Г\nДитина\nТокарєва М. А\nТокарєва А. А\nДитина\nАртем\nТокарєв\nЗагальний місцевий суд\nДонецька область\nсуддя красноармійського міськрайонного суду донецької області\nГеннадійович\nДонецька область\nКрасноармійськ\n68\n1/3 частина\nДонецька область\nм. Артемівськ\n47\nм. Красноармійськ\nДонецька область\n2014\nТокарєва О. Г\nПодружжя\nТокарєва М. А\nДитина\nДитина\nТокарєва А. А\nГеннадійович\nТокарєв\nАртем\nТокарєв Артем Геннадійович\nАртем Геннадійович Токарєв\nАртем Токарєв\nТокарєв Артем Геннадійович\nКрасноармійськ\nДонецька область\nДонецька область\nЗагальний місцевий суд\nсуддя красноармійського міськрайонного суду донецької області\nТокарєв Артем Геннадійович","estate":{"25":[{"address":"м. Красноармійськ","space_units":"м²","space_hidden":false,"space_unclear":false,"region_hidden":false,"costs_comment":"","space_comment":"","address_hidden":true,"costs":"","address_unclear":false,"costs_rent_comment":"","space":"47","region":"Донецька область","costs_rent":""}],"28":[{"address":"м. Артемівськ","space_units":"м²","costs_comment":"","space_comment":"1/3 частина","region_hidden":false,"region":"Донецька область","address_hidden":true,"space":"68","address_unclear":true,"costs_rent_comment":"","costs":"","costs_rent":""}]},"source":"VULYK","income":{"5":{"family_comment":"","value":"181647.32","family":"12932","comment":""},"6":{"family_comment":"","value":"181647.32","family":"","comment":"","family_comment_unclear":false},"7":{"source_name_hidden":false,"family_comment":"","comment":"","family":"","comment_hidden":false,"value":"","source_name":""},"8":{"family_comment":"","value":"","family":"","comment":""},"9":{"family_comment":"","value":"","family":"","comment":""},"10":{"family":"","family_comment":"","comment":"","value_hidden":false,"value_unclear":false,"value":""},"11":{"family_comment":"","value":"","family":"","comment":""},"12":{"family_comment":"","value":"","family":"","comment":""},"13":{"family_comment":"","value":"","family":"","comment":""},"14":{"family_comment":"","value":"","family":"","comment":""},"15":{"family_comment":"виплати по догляду за дитиною","value":"","family":"12932","comment":""},"16":{"family_comment":"","value":"","family":"","comment":""},"17":{"family_comment":"","value":"","family":"","comment":""},"18":{"family_comment":"","value":"","family":"","comment":""},"19":{"family_comment":"","value":"","family":"","comment":""},"20":{"family_comment":"","comment_unclear":false,"value":"","family":"","comment":""}},"general":{"family_raw":"","name":"Артем","full_name_suggest":{"input":["Токарєв Артем Геннадійович","Артем Геннадійович Токарєв","Артем Токарєв"],"output":"Токарєв Артем Геннадійович"},"patronymic":"Геннадійович","inn_hidden":true,"patronymic_unclear":false,"inn":"","inn_unclear":false,"last_name":"Токарєв","full_name":"Токарєв Артем Геннадійович","family":[{"inn":"","family_name":"Токарєва О. Г","relations_other":"","relations_hidden":false,"name_unclear":false,"inn_hidden":true,"name_hidden":false,"relations":"Подружжя"},{"inn":"","family_name":"Токарєва М. А","relations_other":"","name_unclear":false,"inn_hidden":true,"name_hidden":false,"relations":"Дитина"},{"inn":"","name_unclear":false,"family_name":"Токарєва А. А","inn_hidden":false,"relations":"Дитина"}],"post":{"office":"Загальний місцевий суд","post":"суддя красноармійського міськрайонного суду донецької області","candidate":"","region_hidden":false,"region":"Донецька область","office_hidden":false,"post_unclear":false,"office_unclear":false},"addresses":[{"place_city_type":"Місто","place_city_type_hidden":false,"place_district_hidden":false,"place_city_hidden":false,"place_district":"","place_hidden":false,"place_address":"","place":"Донецька область","place_city":"Красноармійськ","place_address_hidden":true,"place_unclear":false}]},"liabilities":{"54":{"sum_comment":"","sum_foreign_comment":"","sum_foreign":"","sum_unclear":false,"sum":""},"55":{"sum_comment":"","sum_foreign_comment":"","sum_foreign":"","sum":""},"56":{"sum_comment":"","sum_foreign_comment":"","sum_foreign":"","sum_hidden":false,"sum":""},"57":{"sum_comment":"","sum_foreign_comment":"","sum_foreign":"","sum_unclear":false,"sum":""},"58":{"sum_comment":"","sum_foreign_comment":"","sum_foreign":"","sum_unclear":false,"sum":""},"59":{"sum_comment":"","sum_foreign_comment":"","sum_foreign":"","sum":""},"60":{"sum_comment":"","sum_foreign_comment":"","sum_foreign":"","sum":"","sum_comment_hidden":false},"61":{"sum_comment":"","sum_foreign_comment":"","sum_foreign":"","sum":""},"62":{"sum_comment":"","sum_foreign_comment":"","sum_foreign":"","sum":""},"63":{"sum_comment":"","sum_foreign_comment":"","sum_foreign":"","sum":""},"64":{"sum_comment":"","sum_foreign_comment":"","sum_foreign":"","sum":""}},"declaration":{"notfull_lostpages":"","additional_info_text":"","additional_info":"","date":"2015-03-15T00:00:00","notfull":"","url":"http://static.declarations.com.ua/declarations/chosen_ones/judges_batch/2778_tokariev_artem_hennadiiovych.pdf"},"intro":{"declaration_year_unclear":false,"declaration_year":"2014"}}]