[{"id":"vulyk_101_35","declaration":{"notfull_lostpages":"","additional_info_text":"","additional_info":"","date":"2016-03-28T00:00:00","notfull":"","url":"http://static.declarations.com.ua/declarations/chosen_ones/judges_batch/699_tolkachenko_oleksandr_oleksandrovych_2015.pdf"},"estate":{"25":[{"address":"","space_units":"м²","space_hidden":false,"space_unclear":false,"region_hidden":true,"costs_comment":"","space_comment":"проживаю, квартира матері","address_hidden":false,"space":"72.7","space_comment_unclear":false,"costs_rent_comment":"","costs":"","region":"","costs_rent":""}],"29":[{"costs_property_comment":"","address":"","space_units":"м²","costs_rent_comment":"","space":"1000","region":"","region_hidden":true,"costs_property":"","space_comment":"","address_hidden":false,"costs_rent":""},{"costs_property_comment":"","address":"","space_units":"м²","costs_rent_comment":"","space":"288","region":"","region_hidden":false,"costs_property":"","space_comment":"","costs_rent":""},{"costs_property_comment":"","address":"","space_units":"м²","costs_rent_comment":"","space":"6923","costs_property":"","space_comment":"","costs_rent":""},{"costs_property_comment":"","address":"","space_units":"м²","costs_rent_comment":"","space":"1500","costs_property":"","space_comment":"","costs_rent":""}],"32":[{"costs_property_comment":"","address":"","space_units":"м²","costs_rent_comment":"","space":"31.6","region":"","region_hidden":true,"costs_property":"","space_comment":"","address_hidden":false,"costs_rent":""}],"34":[{"costs_property_comment":"","address":"","space_units":"м²","space_hidden":true,"space_comment":"літ. А 191,3 кв. м., літ. В-склад, літ. В-маслоцех, літ. Е-склад, літ. Д-вбиральня, літ. З-навіс, літ. Ж-нерозбірливо, літ. Г-трансформатор, №1-криниця","region_hidden":true,"costs_property":"","region":"","address_hidden":false,"address_unclear":true,"space_comment_unclear":true,"costs_rent_comment":"","space":"191.3","costs_rent":""}]},"vehicle":{"40":[{"sum_comment":"","brand_info_hidden":false,"brand_info":"1400 куб. см.","sum":"","sum_rent_comment":"","brand_hidden":false,"brand":"Lancia Delta","sum_rent":"","brand_info_unclear":false,"year":"2008"}]},"source":"VULYK","income":{"5":{"family_comment":"","value":"268516","family":"93000","comment":"","value_unclear":false},"6":{"family_comment":"","family":"93000","comment":"","value_unclear":false,"family_hidden":false,"value":"255032"},"7":{"family_comment":"","comment":"","family":"","source_name_unclear":false,"value":"13483","source_name":"Одеське регіональне відділення Національної школи суддів України Одеський державний університет внутрішніх справ"},"8":{"family_comment":"","value":"","family":"","comment":""},"9":{"family_comment":"","value":"","family":"","comment":""},"10":{"family_comment":"","value":"","family":"","comment":""},"11":{"family_comment":"","comment_unclear":false,"value":"","family":"","comment":""},"12":{"family_comment":"","value":"","family":"","comment":""},"13":{"family_comment":"","value":"","family":"","comment":""},"14":{"family_comment":"","value":"","family":"","comment":""},"15":{"family_comment":"","value":"","family":"","comment":""},"16":{"family_comment":"","value":"","family":"235000","comment":""},"17":{"family_comment":"","value":"","family":"93000","comment":""},"18":{"family_comment":"","value":"","family":"","comment":""},"19":{"family_comment":"","value":"","family":"","comment":""},"20":{"family_comment":"","family":"","comment":"","value_unclear":false,"family_unclear":false,"comment_unclear":false,"value":""}},"banks":{"51":[{"sum_units":"UAH","sum_comment":"Приватбанк","sum_foreign_units":"UAH","sum_hidden":false,"sum":"10000","sum_foreign_comment":"","sum_foreign":"","sum_unclear":false,"sum_comment_hidden":false}]},"ft_src":"1400 куб. см.\nLancia Delta\n2008\nПриватбанк\n10000\n2015\n1400 куб. см.\n2008\nLancia Delta\n10000\nПриватбанк\n2015\nПодружжя\nБайрамова Ірина Григорівна\nДитина\nТолкаченко Марія Олександрівна\nТолкаченко Олександр Олександрович\nОлександр Олександрович Толкаченко\nОлександр Толкаченко\nТолкаченко Олександр Олександрович\nОлександр\nТолкаченко Олександр Олександрович\nОлександрович\nЗагальний апеляційний суд\nсуддя апеляційного суду одеської області\nОдеська область\nТолкаченко\n3000\n50000\n13483\nОдеське регіональне відділення Національної школи суддів України Одеський державний університет внутрішніх справ\n255032\n93000\n93000\n268516\n93000\n235000\n1000\n288\n6923\n1500\nліт. А 191,3 кв. м., літ. В-склад, літ. В-маслоцех, літ. Е-склад, літ. Д-вбиральня, літ. З-навіс, літ. Ж-нерозбірливо, літ. Г-трансформатор, №1-криниця\n191.3\n72.7\nпроживаю, квартира матері\n31.6\n3000\n50000\n1000\n288\n6923\n1500\nліт. А 191,3 кв. м., літ. В-склад, літ. В-маслоцех, літ. Е-склад, літ. Д-вбиральня, літ. З-навіс, літ. Ж-нерозбірливо, літ. Г-трансформатор, №1-криниця\n191.3\n31.6\nпроживаю, квартира матері\n72.7\nБайрамова Ірина Григорівна\nПодружжя\nТолкаченко Марія Олександрівна\nДитина\nОлександр\nОлександрович\nТолкаченко\nТолкаченко Олександр Олександрович\nОлександр Олександрович Толкаченко\nОлександр Толкаченко\nТолкаченко Олександр Олександрович\nсуддя апеляційного суду одеської області\nЗагальний апеляційний суд\nОдеська область\nТолкаченко Олександр Олександрович\n93000\n255032\nОдеське регіональне відділення Національної школи суддів України Одеський державний університет внутрішніх справ\n13483\n93000\n268516\n235000\n93000","general":{"family":[{"inn":"","family_name":"Байрамова Ірина Григорівна","relations_other":"","name_unclear":false,"inn_hidden":true,"name_hidden":true,"relations":"Подружжя"},{"inn":"","family_name":"Толкаченко Марія Олександрівна","relations_other":"","relations_unclear":false,"name_unclear":false,"inn_hidden":true,"name_hidden":false,"relations":"Дитина"}],"family_raw":"","name":"Олександр","full_name_suggest":{"input":["Толкаченко Олександр Олександрович","Олександр Олександрович Толкаченко","Олександр Толкаченко"],"output":"Толкаченко Олександр Олександрович"},"patronymic":"Олександрович","inn_hidden":true,"addresses":[{"place_city_type_hidden":false,"place_city_type":"","place_city_hidden":true,"place_hidden":true,"place_district":"","place_district_hidden":false,"place":"","place_address":"","place_address_hidden":true,"place_city":""}],"patronymic_hidden":false,"inn":"","inn_unclear":false,"last_name":"Толкаченко","full_name":"Толкаченко Олександр Олександрович","post":{"office":"Загальний апеляційний суд","region_unclear":false,"post":"суддя апеляційного суду одеської області","region":"Одеська область","office_unclear":false}},"liabilities":{"54":{"sum_comment_unclear":false,"sum_comment":"","sum_hidden":false,"sum":"","sum_foreign_comment":"","sum_foreign":"","sum_unclear":false,"sum_comment_hidden":false},"55":{"sum_comment":"","sum_foreign_comment":"","sum_foreign":"","sum":""},"56":{"sum_comment":"","sum":"","sum_foreign_comment":"","sum_foreign":"","sum_unclear":false,"sum_comment_hidden":false},"57":{"sum_comment":"","sum_hidden":false,"sum":"","sum_foreign_comment":"","sum_foreign":"","sum_unclear":false,"sum_comment_hidden":false},"58":{"sum_comment_unclear":false,"sum_comment":"","sum_hidden":false,"sum":"","sum_foreign_comment":"","sum_foreign":"","sum_unclear":false,"sum_comment_hidden":false},"59":{"sum_comment":"","sum_foreign_comment":"","sum_foreign":"","sum":""},"60":{"sum_comment":"","sum_hidden":false,"sum":"","sum_foreign_comment":"","sum_foreign":"","sum_unclear":false,"sum_comment_hidden":false},"61":{"sum_comment":"","sum_foreign_comment":"","sum_foreign":"","sum":""},"62":{"sum_comment":"","sum_comment_unclear":false,"sum_foreign_comment":"","sum":"3000","sum_foreign":""},"63":{"sum_comment":"","sum_foreign_comment":"","sum_foreign":"","sum":"50000","sum_comment_hidden":false},"64":{"sum_comment":"","sum_foreign_comment":"","sum_foreign":"","sum":"","sum_comment_hidden":false}},"intro":{"declaration_year":"2015"}},{"id":"vulyk_100_140","declaration":{"notfull_lostpages":"","additional_info_text":"","additional_info":"","date":"2015-03-18T00:00:00","notfull":"","url":"http://static.declarations.com.ua/declarations/chosen_ones/judges_batch/4344_tolkachenko_oleksandr_oleksandrovych.pdf"},"estate":{"29":[{"costs_property_comment":"","address":"","space_units":"га","space_unclear":false,"region_hidden":true,"costs_property":"","space_comment":"","address_hidden":true,"address_unclear":false,"costs_rent_comment":"","space":".1","region_unclear":false,"region":"","costs_rent":""},{"costs_property_comment":"","address":"","space_units":"","space_unclear":true,"region_hidden":false,"costs_property":"","space_comment":"","address_hidden":true,"costs_rent_comment":"","space":"","region":"","costs_rent":""}],"34":[{"costs_property_comment":"","address":"","space_units":"га","costs_rent_comment":"","space":"0.84","region":"","region_hidden":true,"costs_property":"","space_comment":"","address_hidden":true,"costs_rent":""}]},"vehicle":{"40":[{"sum_comment":"","brand_info_hidden":false,"brand_info":"2500 куб. см.","sum":"","sum_rent_comment":"","year":"2008","brand":"Nissan Rogue","sum_rent":"","brand_info_unclear":false}]},"source":"VULYK","income":{"5":{"family_comment":"","family":"","comment":"","value_unclear":false,"family_unclear":false,"value":"275967"},"6":{"family_comment":"","value":"265848","family":"","comment":"","value_unclear":false},"7":{"family_comment":"","comment":"","family":"","value_unclear":false,"value":"10119","source_name":"Одеський державний університет внутрішніх справ (м. Одеса, вул. Успенська, 1"},"8":{"family_comment":"","value":"","family":"","comment":""},"9":{"family_comment":"","family":"","comment":"","value_unclear":false,"family_unclear":false,"value":""},"10":{"family_comment":"","comment_unclear":false,"value":"","family":"","comment":""},"11":{"family_comment":"","value":"","family":"","comment":""},"12":{"family_comment":"","value":"","family":"","comment":""},"13":{"family_comment":"","value":"","family":"","comment":"","value_unclear":false},"14":{"family_comment":"","value":"","family":"","comment":""},"15":{"family_comment":"","value":"","family":"","comment":""},"16":{"family_comment":"","value":"","family_unclear":false,"family":"","comment":""},"17":{"family_comment":"","value":"","family_unclear":false,"family":"","comment":""},"18":{"family_comment":"","value":"","family":"","comment":""},"19":{"family_comment":"","value":"","family":"","comment":""},"20":{"family":"","family_comment":"","comment":"","value_hidden":false,"value_unclear":false,"value":"","comment_unclear":false,"family_unclear":false,"family_hidden":false}},"banks":{"45":[{"sum_comment_unclear":false,"sum_units":"UAH","sum_foreign_comment":"","sum_foreign_units":"UAH","sum":"","sum_comment":"зарплатна картка","sum_foreign":"","sum_unclear":false,"sum_units_unclear":false,"sum_comment_hidden":false}]},"ft_src":"2008\n2500 куб. см.\nNissan Rogue\nзарплатна картка\n2014\nNissan Rogue\n2500 куб. см.\n2008\nзарплатна картка\n.1\n0.84\nПодружжя\nБайрамова Ірина Григорівна\nДитина\nТолкаченко Марія Олександрівна\nОлександрович\nТолкаченко\nТолкаченко Олександр Олександрович\nОлександр Олександрович Толкаченко\nОлександр Толкаченко\nТолкаченко Олександр Олександрович\nТолкаченко Олександр Олександрович\nОлександр\nЗагальний апеляційний суд\nОдеська область\nсуддя апеляційного суду одеської області\n10119\nОдеський державний університет внутрішніх справ (м. Одеса, вул. Успенська, 1\n265848\n275967\n2014\n.1\n0.84\nБайрамова Ірина Григорівна\nПодружжя\nДитина\nТолкаченко Марія Олександрівна\nОлександрович\nТолкаченко\nОдеська область\nЗагальний апеляційний суд\nсуддя апеляційного суду одеської області\nТолкаченко Олександр Олександрович\nТолкаченко Олександр Олександрович\nОлександр Олександрович Толкаченко\nОлександр Толкаченко\nТолкаченко Олександр Олександрович\nОлександр\n265848\nОдеський державний університет внутрішніх справ (м. Одеса, вул. Успенська, 1\n10119\n275967","general":{"inn":"","addresses":[{"place_city_type":"","place_city_type_hidden":false,"place_hidden":true,"place_city_hidden":true,"place_district_hidden":false,"place_district":"","place_city_unclear":false,"place":"","place_city":"","place_address_hidden":true,"place_address":""}],"last_name":"Толкаченко","full_name":"Толкаченко Олександр Олександрович","family":[{"inn":"","family_name":"Байрамова Ірина Григорівна","name_unclear":false,"inn_hidden":true,"name_hidden":true,"relations":"Подружжя"},{"inn":"","family_name":"Толкаченко Марія Олександрівна","relations_other":"","name_unclear":false,"inn_hidden":false,"name_hidden":false,"relations":"Дитина"}],"patronymic":"Олександрович","inn_hidden":true,"name":"Олександр","post":{"post_hidden":false,"office":"Загальний апеляційний суд","post":"суддя апеляційного суду одеської області","office_unclear":false,"region_unclear":false,"region":"Одеська область","post_unclear":false},"family_raw":"","full_name_suggest":{"input":["Толкаченко Олександр Олександрович","Олександр Олександрович Толкаченко","Олександр Толкаченко"],"output":"Толкаченко Олександр Олександрович"}},"liabilities":{"54":{"sum_comment":"","sum":"","sum_foreign_comment":"","sum_foreign":"","sum_unclear":false,"sum_comment_hidden":false},"55":{"sum_comment":"","sum_foreign_comment":"","sum_foreign":"","sum":""},"56":{"sum_comment":"","sum_foreign_comment":"","sum_foreign":"","sum_unclear":false,"sum":""},"57":{"sum_comment_unclear":false,"sum_comment":"","sum":"","sum_foreign_comment":"","sum_foreign":"","sum_unclear":false,"sum_comment_hidden":false},"58":{"sum_comment":"","sum":"","sum_foreign_comment":"","sum_foreign":"","sum_unclear":false,"sum_comment_hidden":false},"59":{"sum_comment":"","sum_foreign_comment":"","sum_foreign":"","sum":""},"60":{"sum_comment":"","sum_foreign_comment":"","sum_foreign":"","sum":"","sum_comment_hidden":false},"61":{"sum_comment":"","sum_foreign_comment":"","sum_foreign":"","sum":""},"62":{"sum_comment":"","sum_foreign_comment":"","sum_foreign":"","sum_unclear":false,"sum":""},"63":{"sum_comment":"","sum_foreign_comment":"","sum_foreign":"","sum":"","sum_comment_hidden":false},"64":{"sum_comment":"","sum_foreign_comment":"","sum_foreign":"","sum":"","sum_comment_hidden":false}},"intro":{"declaration_year":"2014"}},{"ft_src":"Nissan,Rogue\n2008\n1000\nміжрайбаза\n1000\nFALSE\nFALSE\nFALSE\n2013\n247370,72\n3351,12\nОдеський державний університет внутрішніх справ\n7200\n250721,84\n7200\nNissan,Rogue\n2008\nFALSE\nFALSE\n1000\nміжрайбаза\nСуддя апеляційного суду Одеської області\nДружина Байрамова Ірина Григорівна;донька Толкаченко Марія олександрівна\nТолкаченко\nТолкаченко Олександр Олександрович\nОлександр Олександрович Толкаченко\nОлександр Толкаченко\nТолкаченко Олександр Олександрович\nОлександр\nТолкаченко Олександр Олександрович\nЗагальний апеляційний суд\nСуддя\nОдеська область\nОлександрович\nОдеський державний університет внутрішніх справ\n3351,12\n247370,72\n7200\n250721,84\n7200\n1000\n2013\nFALSE\nТолкаченко\nОлександрович\nДружина Байрамова Ірина Григорівна;донька Толкаченко Марія олександрівна\nТолкаченко Олександр Олександрович\nОлександр Олександрович Толкаченко\nОлександр Толкаченко\nТолкаченко Олександр Олександрович\nОлександр\nСуддя апеляційного суду Одеської області\nСуддя\nОдеська область\nЗагальний апеляційний суд\nТолкаченко Олександр Олександрович","estate":{"23":[{"costs":"","address":"","space_units":"","costs_rent_comment":"","space":"","costs_comment":"","costs_rent":"","space_comment":"","region":"","location_raw":""},{"costs":"","address":"","space_units":"","costs_rent_comment":"","space":"","costs_comment":"","costs_rent":"","space_comment":"","region":"","location_raw":""},{"costs":"","address":"","space_units":"","costs_rent_comment":"","space":"","costs_comment":"","costs_rent":"","space_comment":"","region":"","location_raw":""}],"29":[{"costs_property_comment":"","address":"","space_units":"","costs_rent_comment":"","space":"1000","space_comment":"","costs_property":"","region":"","location_raw":"приховано","costs_rent":""}],"34":[{"costs_property_comment":"","address":"","space_units":"","costs_rent_comment":"","space":"","space_comment":"","costs_property":"","region":"","location_raw":"міжрайбаза","costs_rent":""}]},"vehicle":{"40":[{"sum_comment":"","brand_info":"","sum":"","sum_rent_comment":"","year":"2008","brand":"Nissan,Rogue","sum_rent":"","brand_hidden":false}]},"id":"3449","income":{"5":{"family_comment":"","value":"250721,84","family":"7200","comment":""},"6":{"family_comment":"","value":"247370,72","family":"0","comment":""},"7":{"family":"0","family_comment":"","value":"3351,12","comment":"","source_name":"Одеський державний університет внутрішніх справ"},"8":{"family_comment":"","value":"0","family":"0","comment":""},"9":{"family_comment":"","value":"0","family":"0","comment":""},"10":{"family_comment":"","value":"0","family":"0","comment":""},"11":{"family_comment":"","value":"0","family":"0","comment":""},"12":{"family_comment":"","value":"0","family":"0","comment":""},"13":{"family_comment":"","value":"0","family":"0","comment":""},"14":{"family_comment":"","value":"0","family":"0","comment":""},"15":{"family_comment":"","value":"0","family":"0","comment":""},"16":{"family_comment":"","value":"0","family":"0","comment":""},"17":{"family_comment":"","value":"0","family":"0","comment":""},"18":{"family_comment":"","value":"0","family":"0","comment":""},"19":{"family_comment":"","value":"0","family":"0","comment":""},"20":{"family_comment":"","value":"0","family":"7200","comment":""},"21":[{"country_comment":"","uah_equal":"0","country":"0","cur":"0"},{"country_comment":"","uah_equal":"0","country":"0","cur":"0"},{"country_comment":"","uah_equal":"0","country":"0","cur":"0"},{"country_comment":"","uah_equal":"0","country":"0","cur":"0"},{"country_comment":"","uah_equal":"0","country":"0","cur":"0"}],"22":[{"country_comment":"","uah_equal":"0","country":"0","cur":"0"},{"country_comment":"","uah_equal":"0","country":"0","cur":"0"},{"country_comment":"","uah_equal":"0","country":"0","cur":"0"},{"country_comment":"","uah_equal":"0","country":"0","cur":"0"},{"country_comment":"","uah_equal":"0","country":"0","cur":"0"}]},"banks":{"45":[{"sum_units":"UAH","sum_comment":"","sum_foreign_units":"","sum":"","sum_foreign_comment":"","sum_foreign":""},{"sum_units":"USD","sum_comment":"","sum_foreign_units":"","sum":"","sum_foreign_comment":"","sum_foreign":""},{"sum_units":"EUR","sum_comment":"","sum_foreign_units":"","sum":"","sum_foreign_comment":"","sum_foreign":""}],"46":[{"sum_units":"UAH","sum_comment":"","sum_foreign_units":"","sum":"","sum_foreign_comment":"","sum_foreign":""},{"sum_units":"USD","sum_comment":"","sum_foreign_units":"","sum":"","sum_foreign_comment":"","sum_foreign":""},{"sum_units":"EUR","sum_comment":"","sum_foreign_units":"","sum":"","sum_foreign_comment":"","sum_foreign":""}],"47":[{"sum_units":"","sum_comment":"","sum_foreign_units":"","sum":"","sum_foreign_comment":"","sum_foreign":""}],"48":[{"sum_units":"","sum_comment":"","sum_foreign_units":"","sum":"","sum_foreign_comment":"","sum_foreign":""}],"49":[{"sum_units":"","sum_comment":"","sum_foreign_units":"","sum":"","sum_foreign_comment":"","sum_foreign":""}],"50":[{"sum_units":"","sum_comment":"","sum_foreign_units":"","sum":"","sum_foreign_comment":"","sum_foreign":""}],"51":[{"sum_units":"UAH","sum_comment":"","sum_foreign_units":"","sum":"1000","sum_foreign_comment":"","sum_foreign":""},{"sum_units":"USD","sum_comment":"","sum_foreign_units":"","sum":"","sum_foreign_comment":"","sum_foreign":""},{"sum_units":"EUR","sum_comment":"","sum_foreign_units":"","sum":"","sum_foreign_comment":"","sum_foreign":""}],"52":[{"sum_units":"","sum_comment":"","sum_foreign_units":"","sum":"","sum_foreign_comment":"","sum_foreign":""}],"53":[{"sum_units":"","sum_comment":"","sum_foreign_units":"","sum":"","sum_foreign_comment":"","sum_foreign":""}]},"declaration":{"notfull_lostpages":"","additional_info_text":"","additional_info":"FALSE","notfull":"FALSE","url":"http://static.declarations.com.ua/declarations/sudy/apeliatsiini_sudy_oblastei__m.kyieva/odeska/tilkachenko_dec.pdf","needs_scancopy_check":false},"general":{"family_raw":"Дружина Байрамова Ірина Григорівна;донька Толкаченко Марія олександрівна","name":"Олександр","full_name_suggest":{"input":["Толкаченко Олександр Олександрович","Олександр Олександрович Толкаченко","Олександр Толкаченко"],"output":"Толкаченко Олександр Олександрович"},"post_raw":"Суддя апеляційного суду Одеської області","name_unclear":false,"patronymic":"Олександрович","patronymic_unclear":false,"last_name_hidden":false,"patronymic_hidden":false,"inn":"","addresses_raw_hidden":true,"last_name":"Толкаченко","full_name":"Толкаченко Олександр Олександрович","post":{"office":"Загальний апеляційний суд","region":"Одеська область","post":"Суддя"},"addresses_raw":"приховано","name_hidden":false,"last_name_unclear":false},"liabilities":{"54":{"sum_comment":"","sum_foreign_comment":"","sum_foreign":"","sum":""},"55":{"sum_units":"","sum_comment":"","sum_foreign_units":"","sum":"","sum_foreign_comment":"","sum_foreign":""},"56":{"sum_comment":"","sum_foreign_comment":"","sum_foreign":"","sum":""},"57":{"sum_comment":"","sum_foreign_comment":"","sum_foreign":"","sum":""},"58":{"sum_comment":"","sum_foreign_comment":"","sum_foreign":"","sum":""},"59":{"sum_comment":"","sum_foreign_comment":"","sum_foreign":"","sum":""},"60":{"sum_comment":"","sum_foreign_comment":"","sum_foreign":"","sum":""},"61":{"sum_units":"","sum_comment":"","sum_foreign_units":"","sum":"","sum_foreign_comment":"","sum_foreign":""},"62":{"sum_comment":"","sum_foreign_comment":"","sum_foreign":"","sum":""},"63":{"sum_comment":"","sum_units":"","sum_foreign":"","sum":"","sum_foreign_comment":""},"64":{"sum_comment":"","sum_units":"","sum_foreign":"","sum":"","sum_foreign_comment":""}},"intro":{"isnotdeclaration":"FALSE","declaration_year":"2013"}}]