[{"id":"vulyk_88_54","ft_src":"Mercedes-Benz ML 350\n2003\n3438 куб. см.\n211\n172740\n41.5\n2014\n182927.11\n22886.26\n182927.11\n22886.26\n3438 куб. см.\nMercedes-Benz ML 350\n2003\n211\n172740\n41.5\nТурченко Олексій Валерійович\nОлексій Валерійович Турченко\nОлексій Турченко\nТурченко Олексій Валерійович\nОлексій\nПодружжя\nЄвчева М. В\nДитина\nТурченко І. О\nДитина\nТурченко С. О\nТурченко Олексій Валерійович\nТурченко\nЗагальний місцевий суд\nсуддя жовтневого районного суду м. маріуполя донецької області\nДонецька область\nВалерійович\n5250\n9623.41\n182927.11\n22886.26\n182927.11\n22886.26\n2014\n9623.41\n5250\nЄвчева М. В\nПодружжя\nТурченко І. О\nДитина\nТурченко С. О\nДитина\nВалерійович\nТурченко\nОлексій\nТурченко Олексій Валерійович\nОлексій Валерійович Турченко\nОлексій Турченко\nТурченко Олексій Валерійович\nДонецька область\nЗагальний місцевий суд\nсуддя жовтневого районного суду м. маріуполя донецької області\nТурченко Олексій Валерійович","estate":{"23":[{"address":"","space_units":"м²","costs_rent_unclear":false,"costs_comment":"","space_unclear":false,"region_hidden":true,"space_comment":"","address_hidden":true,"costs":"","address_unclear":false,"space_comment_unclear":false,"costs_rent_comment":"","space":"211","region":"","costs_rent":""}],"25":[{"address":"","space_units":"м²","space_hidden":false,"space_unclear":false,"region_hidden":true,"costs_rent_comment":"","space_comment":"","address_hidden":true,"costs":"172740","address_unclear":false,"space_comment_unclear":false,"costs_comment":"","space":"41.5","region":"","costs_rent":""}]},"vehicle":{"35":[{"sum_comment_unclear":false,"sum_comment":"","brand_info":"3438 куб. см.","sum":"","brand_unclear":false,"year":"2003","brand":"Mercedes-Benz ML 350","sum_rent":"","sum_rent_comment":"","brand_hidden":false}]},"source":"VULYK","income":{"5":{"family_comment":"","family":"22886.26","comment":"","value_unclear":false,"family_unclear":false,"value":"182927.11"},"6":{"family_comment":"","family":"","comment":"","value_unclear":false,"family_unclear":false,"value":"182927.11"},"7":{"family":"","family_comment":"","value":"","comment":"","source_name":""},"8":{"family_comment":"","value":"","family":"","comment":""},"9":{"family_comment":"","value":"","family":"","comment":"","family_comment_unclear":false},"10":{"family_comment":"","value":"","family":"","comment":""},"11":{"family_comment":"","value":"","family":"","comment":""},"12":{"family_comment":"","value":"","family":"","comment":""},"13":{"family_comment":"","value":"","family":"","comment":""},"14":{"family_comment":"","value":"","family":"","comment":""},"15":{"family_comment":"","value":"","family":"","comment":""},"16":{"family_comment":"","value":"","family_unclear":false,"family":"","comment":""},"17":{"family_comment":"","value":"","family_unclear":false,"family":"","comment":""},"18":{"family_comment":"","value":"","family":"","comment":""},"19":{"family_comment":"","value":"","family":"","comment":""},"20":{"family_comment":"","value":"","family":"22886.26","comment":""}},"general":{"family":[{"inn":"","family_name":"Євчева М. В","name_unclear":false,"inn_hidden":true,"name_hidden":false,"relations":"Подружжя"},{"inn":"","family_name":"Турченко І. О","relations_other":"","name_unclear":false,"inn_hidden":false,"name_hidden":false,"relations":"Дитина"},{"inn":"","family_name":"Турченко С. О","relations_other":"","name_unclear":false,"inn_hidden":false,"name_hidden":false,"relations":"Дитина"}],"family_raw":"","name":"Олексій","full_name_suggest":{"input":["Турченко Олексій Валерійович","Олексій Валерійович Турченко","Олексій Турченко"],"output":"Турченко Олексій Валерійович"},"patronymic":"Валерійович","inn_hidden":true,"patronymic_unclear":false,"patronymic_hidden":false,"inn":"","addresses":[{"place_city_type_hidden":true,"place_city_type":"","place_city_hidden":true,"place_hidden":true,"place_district":"","place_district_hidden":true,"place":"","place_address":"","place_address_hidden":true,"place_city":""}],"last_name":"Турченко","full_name":"Турченко Олексій Валерійович","post":{"office":"Загальний місцевий суд","post":"суддя жовтневого районного суду м. маріуполя донецької області","candidate":"","region_hidden":false,"region":"Донецька область","office_hidden":false},"last_name_unclear":false},"liabilities":{"54":{"sum_comment":"","sum_comment_unclear":false,"sum_foreign_comment":"","sum":"","sum_foreign":""},"55":{"sum_comment":"","sum_foreign_comment":"","sum_foreign":"","sum":""},"56":{"sum_comment":"","sum_foreign_comment":"","sum_foreign":"","sum":""},"57":{"sum_comment":"","sum_hidden":false,"sum":"5250","sum_foreign_comment":"","sum_foreign":"","sum_unclear":false,"sum_comment_hidden":false},"58":{"sum_comment":"","sum_hidden":false,"sum":"9623.41","sum_foreign_comment":"","sum_foreign":"","sum_comment_hidden":false},"59":{"sum_comment":"","sum_foreign_comment":"","sum_foreign":"","sum":""},"60":{"sum_comment_unclear":false,"sum_comment":"","sum_hidden":false,"sum":"","sum_foreign_comment":"","sum_foreign":"","sum_comment_hidden":false},"61":{"sum_comment":"","sum_foreign_comment":"","sum_foreign":"","sum":""},"62":{"sum_comment":"","sum_foreign_comment":"","sum_foreign":"","sum":""},"63":{"sum_comment":"","sum_foreign_comment":"","sum_foreign":"","sum":""},"64":{"sum_comment":"","sum_foreign_comment":"","sum_foreign":"","sum":""}},"declaration":{"notfull_lostpages":"","additional_info_text":"","additional_info":"","date":"2015-03-20T00:00:00","notfull":"","url":"http://static.declarations.com.ua/declarations/chosen_ones/judges_batch/2957_turchenko_oleksii_valeriiovych.pdf"},"intro":{"isnotdeclaration":"","declaration_year":"2014"}}]