[{"id":"vulyk_97_68","ft_src":"1451 куб. см., 53 кВт , право керування\nВАЗ 21070\n2006\nFord Focus\n1598 куб. см., 73.55 кВт , право керування\n2008\n28\n219\n830\n2035\n219\n2014\n72683\n203118\n83821\n203118\n11138\n1451 куб. см., 53 кВт , право керування\nВАЗ 21070\n2006\n1598 куб. см., 73.55 кВт , право керування\nFord Focus\n2008\n2014\nТуржанський Володимир Васильович\nВолодимир Васильович Туржанський\nВолодимир Туржанський\nТуржанський Володимир Васильович\nВолодимир\nПодружжя\nТуржанська О. А\nДитина\nТуржанська О. В\nІнше\nТуржанська В. В\nДонька дружини\nТуржанський Володимир Васильович\nТуржанський\nЗагальний місцевий суд\nЧернівецька область\nсуддя кельменецького районного суду чернівецької області\nВасильович\n143\n293\n4125\n203118\n72683\n11138\n203118\n83821\n830\n2035\n219\n219\n28\n143\n293\n4125\nПодружжя\nТуржанська О. А\nТуржанська О. В\nДитина\nІнше\nТуржанська В. В\nДонька дружини\nВасильович\nТуржанський\nВолодимир\nТуржанський Володимир Васильович\nВолодимир Васильович Туржанський\nВолодимир Туржанський\nТуржанський Володимир Васильович\nЧернівецька область\nЗагальний місцевий суд\nсуддя кельменецького районного суду чернівецької області\nТуржанський Володимир Васильович","estate":{"24":[{"address":"","space_units":"м²","space_hidden":false,"space_unclear":false,"region_hidden":true,"costs_rent_comment":"","space_comment":"","address_hidden":false,"costs":"","address_unclear":false,"space_comment_unclear":false,"costs_comment":"","space":"219","region_unclear":false,"region":"","costs_rent":""}],"29":[{"costs_property_comment":"","address":"","space_units":"м²","space_unclear":false,"region_hidden":true,"costs_property":"","space_comment":"","address_hidden":false,"address_unclear":false,"space_comment_unclear":false,"costs_rent_comment":"","space":"830","region_unclear":false,"region":"","costs_rent":""},{"costs_property_comment":"","address":"","space_units":"м²","space_comment":"","region_hidden":false,"costs_property":"","region":"","address_hidden":false,"address_unclear":false,"costs_rent_comment":"","space":"2035","costs_rent":""}],"30":[{"costs_property_comment":"","address":"","space_units":"м²","space_comment":"","region_hidden":true,"costs_property":"","region":"","address_hidden":false,"address_unclear":false,"costs_rent_comment":"","space":"219","costs_rent":""}],"33":[{"costs_property_comment":"","address":"","space_units":"м²","space_hidden":false,"space_comment":"","region_hidden":true,"costs_property":"","region":"","address_hidden":false,"costs_rent_comment":"","space":"28","costs_rent":""}]},"vehicle":{"35":[{"year_hidden":false,"brand_info":"1451 куб. см., 53 кВт , право керування","brand_unclear":false,"sum_rent_comment":"","brand_hidden":false,"year":"2006","sum_comment":"","brand_info_hidden":false,"sum_rent":"","brand":"ВАЗ 21070","brand_info_unclear":false,"sum":""}],"40":[{"sum_comment":"","brand_info":"1598 куб. см., 73.55 кВт , право керування","brand_unclear":false,"sum_rent_comment":"","year":"2008","brand":"Ford Focus","sum_rent":"","brand_info_unclear":false,"year_unclear":false,"sum":""}]},"source":"VULYK","income":{"5":{"family_comment":"","value":"203118","family":"83821","comment":""},"6":{"family_comment":"","family":"72683","comment":"","value_unclear":false,"family_unclear":false,"comment_hidden":false,"value":"203118"},"7":{"family":"","family_comment":"","value":"","comment":"","source_name":""},"8":{"family_comment":"","value":"","family":"","comment":""},"9":{"family_comment":"","value":"","family_unclear":false,"family":"","comment":""},"10":{"family_comment":"","value":"","family":"","comment":"","value_unclear":false},"11":{"family_comment":"","value":"","family":"","comment":""},"12":{"family_comment":"","value":"","family":"","comment":""},"13":{"family_comment":"","value":"","family":"","comment":""},"14":{"family_comment":"","value":"","family":"","comment":""},"15":{"family_comment":"","value":"","family":"","comment":""},"16":{"family_comment":"","value":"","family":"","comment":""},"17":{"family_comment":"","value":"","family":"","comment":""},"18":{"family_comment":"","value":"","family":"","comment":""},"19":{"family_comment":"","value":"","family":"","comment":""},"20":{"family_comment":"","comment":"","family":"11138","value_unclear":false,"comment_unclear":false,"value":"","family_hidden":false,"family_comment_unclear":false}},"general":{"family":[{"inn":"","family_name":"Туржанська О. А","relations_other":"","name_unclear":false,"inn_hidden":true,"name_hidden":true,"relations":"Подружжя"},{"inn":"","family_name":"Туржанська О. В","name_unclear":false,"inn_hidden":true,"name_hidden":false,"relations":"Дитина"},{"inn":"","family_name":"Туржанська В. В","relations_other":"Донька дружини","name_unclear":false,"inn_hidden":true,"name_hidden":false,"relations":"Інше"}],"family_raw":"","name":"Володимир","full_name_suggest":{"input":["Туржанський Володимир Васильович","Володимир Васильович Туржанський","Володимир Туржанський"],"output":"Туржанський Володимир Васильович"},"patronymic":"Васильович","inn_hidden":true,"addresses":[{"place_city_type":"","place_city_type_hidden":false,"place_hidden":true,"place_city_hidden":true,"place_district_hidden":false,"place_district":"","place_city_unclear":false,"place":"","place_city":"","place_address_hidden":true,"place_address":""}],"last_name_hidden":false,"patronymic_hidden":false,"inn":"","inn_unclear":false,"last_name":"Туржанський","full_name":"Туржанський Володимир Васильович","post":{"post_hidden":false,"office":"Загальний місцевий суд","post":"суддя кельменецького районного суду чернівецької області","office_unclear":false,"region_unclear":false,"region":"Чернівецька область"},"name_hidden":false},"liabilities":{"54":{"sum_comment_unclear":false,"sum_comment":"","sum_hidden":false,"sum":"","sum_foreign_comment":"","sum_foreign":"","sum_unclear":false,"sum_comment_hidden":false},"55":{"sum_comment":"","sum_foreign_comment":"","sum_foreign":"","sum":""},"56":{"sum_comment":"","sum_foreign_comment":"","sum_foreign":"","sum":""},"57":{"sum_comment_unclear":false,"sum_comment":"","sum_hidden":false,"sum":"","sum_foreign_comment":"","sum_foreign":"","sum_unclear":false,"sum_comment_hidden":false},"58":{"sum_comment_unclear":false,"sum_comment":"","sum_hidden":false,"sum":"","sum_foreign_comment":"","sum_foreign":"","sum_unclear":false,"sum_comment_hidden":false},"59":{"sum_comment":"","sum_foreign_comment":"","sum_foreign":"","sum":""},"60":{"sum_comment_unclear":false,"sum_comment":"","sum_hidden":false,"sum":"293","sum_foreign_comment":"","sum_foreign":"","sum_comment_hidden":false},"61":{"sum_comment":"","sum_foreign_comment":"","sum_foreign":"","sum":""},"62":{"sum_comment":"","sum_foreign_comment":"","sum_foreign":"","sum_unclear":false,"sum":""},"63":{"sum_comment":"","sum_foreign_comment":"","sum_foreign":"","sum_hidden":false,"sum":"4125"},"64":{"sum_comment":"","sum_foreign_comment":"","sum_foreign":"","sum":"143"}},"declaration":{"notfull_lostpages":"","additional_info_text":"","additional_info":"","date":"2015-03-27T00:00:00","notfull":"","url":"http://static.declarations.com.ua/declarations/chosen_ones/judges_batch/3897_turzhanskyi_volodymyr_vasylovych.pdf"},"intro":{"isnotdeclaration":"","declaration_year":"2014"}}]