[{"id":"vulyk_68_47","ft_src":"1497\nЗАЗ Forza\n2011\n1497\nЗАЗ Forza\n2011\n959\nсмт Веселинове, вул. Пирогова, 33\nМиколаївська область\nсмт Веселинове, вул. Пирогова, 33\nМиколаївська область\n187.6\nМиколаївська область\nсмт Веселинове, вул. Пирогова, 33\n952\nсмт Веселинове, вул. Пирогова, 33\nМиколаївська область\n187.6\n2014\n28877\n211864\n28877\n211864\n1497\nЗАЗ Forza\n2011\n1497\n2011\nЗАЗ Forza\n959\nМиколаївська область\nсмт Веселинове, вул. Пирогова, 33\nсмт Веселинове, вул. Пирогова, 33\nМиколаївська область\n952\n187.6\nсмт Веселинове, вул. Пирогова, 33\nМиколаївська область\n187.6\nсмт Веселинове, вул. Пирогова, 33\nМиколаївська область\nПодружжя\nТустановська Ілона Вікторівна\n2922450076\nДитина\nТустановський Денис Андрійович\nДитина\nТустановський Олександр Андрійович\nТустановський Андрій Олександрович\nАндрій Олександрович Тустановський\nАндрій Тустановський\nТустановський Андрій Олександрович\nТустановський Андрій Олександрович\nАндрій\nОлександрович\nЗагальний місцевий суд\nМиколаївська область\nзаступник голови веселинівського районного суду миколаївської області\nТустановський\n1762\n6006\n22725\n15935\n4000\n211864\n28877\n211864\n28877\n2014\n15935\n22725\n6006\n4000\n1762\n2922450076\nПодружжя\nТустановська Ілона Вікторівна\nТустановський Денис Андрійович\nДитина\nТустановський Олександр Андрійович\nДитина\nОлександрович\nТустановський\nАндрій\nТустановський Андрій Олександрович\nАндрій Олександрович Тустановський\nАндрій Тустановський\nТустановський Андрій Олександрович\nМиколаївська область\nЗагальний місцевий суд\nзаступник голови веселинівського районного суду миколаївської області\nТустановський Андрій Олександрович","estate":{"23":[{"address":"смт Веселинове, вул. Пирогова, 33","space_units":"м²","costs_comment":"","region_hidden":false,"space_comment":"","address_hidden":false,"space_comment_hidden":false,"space":"959","costs_rent_comment":"","costs":"","region":"Миколаївська область","costs_rent":""}],"24":[{"address":"смт Веселинове, вул. Пирогова, 33","space_units":"м²","costs_comment":"","space_unclear":false,"region_hidden":false,"space_comment":"","address_hidden":false,"costs":"","costs_rent_comment":"","space":"187.6","region_unclear":false,"region":"Миколаївська область","costs_rent":""}],"29":[{"costs_property_comment":"","costs_property":"","address":"смт Веселинове, вул. Пирогова, 33","space_units":"м²","space_hidden":false,"space_unclear":false,"region_hidden":false,"costs_rent_comment":"","space_comment":"","address_hidden":false,"space_units_unclear":false,"space":"952","region":"Миколаївська область","space_units_hidden":false,"costs_rent":""}],"30":[{"costs_property_comment":"","address":"смт Веселинове, вул. Пирогова, 33","space_units":"м²","space_hidden":false,"space_unclear":false,"region_hidden":false,"costs_property":"","space_comment":"","address_hidden":false,"costs_rent_comment":"","space":"187.6","region":"Миколаївська область","costs_rent":""}]},"vehicle":{"35":[{"brand_info":"1497","sum_rent_comment":"","brand_unclear":false,"year":"2011","brand_hidden":false,"sum_comment":"","brand_info_hidden":false,"sum_rent":"","brand":"ЗАЗ Forza","year_unclear":false,"brand_info_unclear":false,"sum":""}],"40":[{"sum_comment":"","brand_info_hidden":false,"brand_info":"1497","sum":"","sum_rent_comment":"","brand_hidden":false,"brand":"ЗАЗ Forza","sum_rent":"","brand_info_unclear":false,"year":"2011","year_unclear":false}]},"source":"VULYK","income":{"5":{"family_comment":"","value":"211864","family_unclear":false,"family":"28877","comment":""},"6":{"family_comment":"","value":"211864","family_unclear":false,"family":"28877","comment":""},"7":{"family_comment":"","comment":"","family":"","comment_hidden":false,"value":"","source_name":""},"8":{"family_comment":"","value":"","family":"","comment":""},"9":{"family_comment":"","value":"","family":"","comment":""},"10":{"family_comment":"","value":"","family":"","comment":""},"11":{"family_comment":"","value":"","family":"","comment":"","value_unclear":false},"12":{"family_comment":"","value":"","family":"","comment":""},"13":{"family_comment":"","value":"","family":"","comment":""},"14":{"family_comment":"","value":"","family":"","comment":""},"15":{"family_comment":"","value":"","family":"","comment":"","value_unclear":false},"16":{"family_comment":"","value":"","family_unclear":false,"family":"","comment":""},"17":{"family_comment":"","value":"","family":"","comment":""},"18":{"family_comment":"","family_hidden":false,"value":"","family":"","comment":""},"19":{"family_comment":"","value":"","family":"","comment":""},"20":{"family_comment":"","comment":"","family":"","comment_hidden":false,"comment_unclear":false,"value":"","family_comment_hidden":false}},"general":{"family":[{"inn":"2922450076","inn_unclear":false,"family_name":"Тустановська Ілона Вікторівна","relations_hidden":false,"relations_unclear":false,"name_unclear":true,"relations":"Подружжя","inn_hidden":false,"name_hidden":false,"relations_other":""},{"inn":"","inn_unclear":false,"family_name":"Тустановський Денис Андрійович","relations_other":"","relations_hidden":false,"name_unclear":true,"inn_hidden":false,"name_hidden":false,"relations":"Дитина"},{"inn":"","family_name":"Тустановський Олександр Андрійович","relations_other":"","name_unclear":false,"inn_hidden":false,"name_hidden":false,"relations":"Дитина"}],"family_raw":"","name":"Андрій","full_name_suggest":{"input":["Тустановський Андрій Олександрович","Андрій Олександрович Тустановський","Андрій Тустановський"],"output":"Тустановський Андрій Олександрович"},"name_unclear":false,"patronymic":"Олександрович","inn_hidden":true,"addresses":[{"place_city_type_hidden":true,"place_hidden":true,"place_address_unclear":false,"place":"","place_city":"","place_unclear":false,"place_city_type":"","place_city_hidden":true,"place_district":"","place_district_hidden":true,"place_address":"","place_address_hidden":true}],"inn":"","inn_unclear":false,"last_name":"Тустановський","full_name":"Тустановський Андрій Олександрович","post":{"post_hidden":false,"office":"Загальний місцевий суд","post":"заступник голови веселинівського районного суду миколаївської області","region":"Миколаївська область","region_hidden":false,"office_unclear":false,"office_hidden":false,"post_unclear":false,"region_unclear":false},"last_name_unclear":false},"liabilities":{"54":{"sum_comment_unclear":true,"sum_comment":"","sum_hidden":false,"sum":"4000","sum_foreign_comment":"","sum_foreign":"","sum_unclear":false,"sum_comment_hidden":false},"55":{"sum_comment":"","sum_foreign_comment":"","sum_foreign":"","sum_hidden":false,"sum":""},"56":{"sum_comment":"","sum":"","sum_foreign_comment":"","sum_foreign":"","sum_unclear":false,"sum_foreign_hidden":false},"57":{"sum_comment_unclear":true,"sum_comment":"","sum_hidden":false,"sum":"22725","sum_foreign_comment":"","sum_foreign":"","sum_unclear":false,"sum_comment_hidden":false},"58":{"sum_comment":"","sum_hidden":false,"sum":"15935","sum_foreign_comment":"","sum_foreign":"","sum_unclear":false,"sum_comment_hidden":false},"59":{"sum_comment":"","sum_foreign_comment":"","sum_foreign":"","sum":""},"60":{"sum_comment_unclear":false,"sum_comment":"","sum_hidden":false,"sum":"","sum_foreign_comment":"","sum_foreign":"","sum_unclear":false,"sum_comment_hidden":false},"61":{"sum_comment":"","sum_foreign_comment":"","sum_foreign":"","sum_hidden":false,"sum":""},"62":{"sum_comment":"","sum_foreign_comment":"","sum_foreign":"","sum_unclear":false,"sum":""},"63":{"sum_comment":"","sum_hidden":false,"sum":"1762","sum_foreign_comment":"","sum_foreign":"","sum_unclear":false,"sum_comment_hidden":false},"64":{"sum_comment":"","sum_hidden":false,"sum":"6006","sum_foreign_comment":"","sum_foreign":"","sum_comment_hidden":false}},"declaration":{"notfull_lostpages":"","additional_info_text":"","additional_info":"","date":"2015-03-30T00:00:00","notfull":"","url":"http://static.declarations.com.ua/declarations/chosen_ones/mega_batch/tustanovskyi_andrii_oleksandrovych.pdf"},"intro":{"isnotdeclaration":"","declaration_year":"2014"}}]