[{"id":"vulyk_100_28","declaration":{"notfull_lostpages":"","additional_info_text":"","additional_info":"","date":"2015-03-16T00:00:00","notfull":"","url":"http://static.declarations.com.ua/declarations/chosen_ones/judges_batch/4155_vasyltsova_hanna_anatoliivna.pdf"},"estate":{"23":[{"address":"","space_units":"м²","costs_comment":"","space_unclear":false,"region_hidden":true,"space_comment":"для обслуговування житлового будинку","address_hidden":false,"costs":"","address_unclear":false,"space_comment_unclear":false,"costs_comment_unclear":false,"costs_rent_comment":"","space":"600","region":"","costs_rent":""}],"24":[{"address":"","space_units":"м²","costs_comment":"","space_unclear":false,"region_hidden":true,"space_comment":"","address_hidden":false,"space":"72.5","space_comment_unclear":false,"costs_rent_comment":"","costs":"","region":"","costs_rent":""}],"25":[{"address":"","space_units":"м²","costs_comment":"","space_unclear":false,"region_hidden":true,"space_comment":"","address_hidden":false,"costs":"","address_unclear":false,"space_comment_unclear":false,"costs_comment_unclear":false,"costs_rent_comment":"","space":"115","region":"","costs_rent":""}],"29":[{"costs_property_comment":"","address":"","space_units":"м²","space_unclear":false,"region_hidden":true,"costs_property":"","space_comment":"","address_hidden":false,"address_unclear":false,"costs_rent_comment":"","space":"36","region_unclear":false,"region":"","costs_rent":""}],"31":[{"costs_property_comment":"","address":"","space_units":"м²","space_unclear":false,"region_hidden":true,"costs_property":"","space_comment":"","address_hidden":false,"address_unclear":false,"space_comment_unclear":false,"costs_rent_comment":"","space":"115","costs_property_comment_unclear":false,"region_unclear":false,"region":"","costs_rent":""}]},"vehicle":{"35":[{"brand_info":"0.9 л, 67 к. с., 50 кВт , 3928 куб. см.","sum_rent_comment":"","brand_unclear":false,"sum_rent_comment_unclear":false,"brand_hidden":false,"sum_comment":"","brand_info_hidden":false,"sum_rent":"","brand":"Peugeot 107","brand_info_unclear":false,"year":"2012","sum":""},{"sum_comment":"","brand_info_hidden":false,"brand_info":"1200 куб. см., 58 к. с","sum":"","sum_rent_comment":"","year":"2004","brand":"ЗАЗ 1102 Таврия","sum_rent":""}],"40":[{"sum_comment":"","brand_info_hidden":false,"brand_info":"1600 куб. см., 102 к. с., 75 кВт","sum":"","sum_rent_comment":"","year":"2007","brand":"Skoda Octavia","sum_rent":"","brand_info_unclear":false}]},"source":"VULYK","income":{"5":{"family_comment":"","family":"265555","comment":"","value_unclear":false,"family_unclear":false,"value":"218230"},"6":{"family_comment":"","value":"218224","family":"246643","comment":"","value_unclear":false},"7":{"family_comment":"","comment":"","family":"","value_unclear":false,"value":"","source_name":""},"8":{"family_comment":"","value":"","family":"","comment":""},"9":{"family_comment":"ПАТ КБ 'Приватбанк'","family":"133","comment":"ПАТ КБ 'Приватбанк'","value_unclear":false,"family_unclear":false,"value":"6"},"10":{"family_comment":"","comment_unclear":false,"value":"","family":"","comment":""},"11":{"family_comment":"","value":"","family":"","comment":""},"12":{"family_comment":"","value":"","family":"","comment":""},"13":{"family_comment":"","value":"","family":"","comment":"","value_unclear":false},"14":{"family_comment":"","value":"","family":"","comment":""},"15":{"family_comment":"","value":"","family":"","comment":""},"16":{"family_comment":"","value":"","family_unclear":false,"family":"","comment":""},"17":{"family_comment":"","value":"","family_unclear":false,"family":"","comment":""},"18":{"family_comment":"","value":"","family":"","comment":""},"19":{"family_comment":"","value":"","family":"","comment":""},"20":{"family":"18780","family_comment":"пенсія","comment":"","value_hidden":false,"value_unclear":false,"value":"","comment_unclear":false,"family_unclear":false,"family_hidden":false}},"banks":{"45":[{"sum_comment_unclear":false,"sum_units":"UAH","sum_foreign_comment":"","sum_foreign_units":"UAH","sum":"3135","sum_comment":"","sum_foreign":"","sum_unclear":false,"sum_units_unclear":false,"sum_comment_hidden":false}],"46":[{"sum_comment_unclear":false,"sum_comment":"","sum_foreign_units":"UAH","sum":"3135","sum_foreign_comment":"","sum_foreign":"","sum_unclear":false,"sum_units":"UAH"}],"51":[{"sum_comment_unclear":false,"sum_units":"UAH","sum_foreign_comment":"","sum_foreign_units":"UAH","sum":"4244","sum_comment":"","sum_foreign":"","sum_unclear":false,"sum_units_unclear":false,"sum_comment_hidden":false}]},"ft_src":"0.9 л, 67 к. с., 50 кВт , 3928 куб. см.\nPeugeot 107\n2012\n1200 куб. см., 58 к. с\n2004\nЗАЗ 1102 Таврия\n2007\n1600 куб. см., 102 к. с., 75 кВт\nSkoda Octavia\n3135\n4244\n3135\n2014\n0.9 л, 67 к. с., 50 кВт , 3928 куб. см.\nPeugeot 107\n2012\n1200 куб. см., 58 к. с\n2004\nЗАЗ 1102 Таврия\nSkoda Octavia\n1600 куб. см., 102 к. с., 75 кВт\n2007\n3135\n4244\n3135\n600\nдля обслуговування житлового будинку\n36\n72.5\n115\n115\nПодружжя\nВасильцов Олег Володимирович, 28. 09. 1959\nДитина\nГладкіна Аліна Русланівна 02. 10. 2000\nДитина\nВасильцов Артем Олегович 30. 08. 2010\nАнатоліївна\nВасильцова\nВасильцова Ганна Анатоліївна\nГанна Анатоліївна Васильцова\nГанна Васильцова\nВасильцова Ганна Анатоліївна\nВасильцова Ганна Анатоліївна\nГанна\nЗагальний місцевий суд\nЗапорізька область\nсуддя приазовського районного суду запорізької області\n8383\nПАТ Укрсоцбанк, ПАТ КБ Приватбанк\nСК Оранта-Сич\n3580\nПАТ КБ 'Приватбанк'\n4250\n3360\nСК Оранта-Сич\n1\nПАТ КБ 'Приватбанк'\n94\nУкрсоцбанк\n218224\n246643\n18780\nпенсія\n218230\n265555\n6\n133\nПАТ КБ 'Приватбанк'\nПАТ КБ 'Приватбанк'\n2014\nПАТ КБ 'Приватбанк'\n1\nПАТ КБ 'Приватбанк'\n4250\nСК Оранта-Сич\n3580\nСК Оранта-Сич\n3360\nПАТ Укрсоцбанк, ПАТ КБ Приватбанк\n8383\nУкрсоцбанк\n94\n115\n36\n72.5\nдля обслуговування житлового будинку\n600\n115\nВасильцов Олег Володимирович, 28. 09. 1959\nПодружжя\nДитина\nГладкіна Аліна Русланівна 02. 10. 2000\nДитина\nВасильцов Артем Олегович 30. 08. 2010\nАнатоліївна\nВасильцова\nЗапорізька область\nЗагальний місцевий суд\nсуддя приазовського районного суду запорізької області\nВасильцова Ганна Анатоліївна\nВасильцова Ганна Анатоліївна\nГанна Анатоліївна Васильцова\nГанна Васильцова\nВасильцова Ганна Анатоліївна\nГанна\n246643\n218224\n265555\n218230\n133\nПАТ КБ 'Приватбанк'\nПАТ КБ 'Приватбанк'\n6\n18780\nпенсія","general":{"inn":"","addresses":[{"place_city_type":"","place_city_type_hidden":true,"place_hidden":true,"place_city_hidden":true,"place_district_hidden":true,"place_district":"","place_city_unclear":false,"place":"","place_city":"","place_address_hidden":true,"place_address":""}],"last_name":"Васильцова","full_name":"Васильцова Ганна Анатоліївна","family":[{"inn":"","family_name":"Васильцов Олег Володимирович, 28. 09. 1959","name_unclear":false,"inn_hidden":true,"name_hidden":false,"relations":"Подружжя"},{"inn":"","family_name":"Гладкіна Аліна Русланівна 02. 10. 2000","relations_other":"","name_unclear":false,"inn_hidden":true,"name_hidden":false,"relations":"Дитина"},{"inn":"","family_name":"Васильцов Артем Олегович 30. 08. 2010","relations_other":"","name_unclear":false,"inn_hidden":true,"name_hidden":false,"relations":"Дитина"}],"patronymic":"Анатоліївна","inn_hidden":true,"name":"Ганна","post":{"post_hidden":false,"office":"Загальний місцевий суд","post":"суддя приазовського районного суду запорізької області","office_unclear":false,"region_unclear":false,"region":"Запорізька область","post_unclear":false},"family_raw":"","full_name_suggest":{"input":["Васильцова Ганна Анатоліївна","Ганна Анатоліївна Васильцова","Ганна Васильцова"],"output":"Васильцова Ганна Анатоліївна"}},"liabilities":{"54":{"sum_comment":"СК Оранта-Сич","sum":"3580","sum_foreign_comment":"","sum_foreign":"","sum_unclear":false,"sum_comment_hidden":false},"55":{"sum_comment":"","sum_foreign_comment":"","sum_foreign":"","sum":""},"56":{"sum_comment":"","sum_foreign_comment":"","sum_foreign":"","sum_unclear":false,"sum":""},"57":{"sum_comment_unclear":false,"sum_comment":"ПАТ КБ 'Приватбанк'","sum":"4250","sum_foreign_comment":"","sum_foreign":"","sum_unclear":false,"sum_comment_hidden":false},"58":{"sum_comment":"ПАТ КБ 'Приватбанк'","sum":"1","sum_foreign_comment":"","sum_foreign":"","sum_unclear":false,"sum_comment_hidden":false},"59":{"sum_comment":"","sum_foreign_comment":"","sum_foreign":"","sum":""},"60":{"sum_comment":"СК Оранта-Сич","sum_foreign_comment":"","sum_foreign":"","sum":"3360","sum_comment_hidden":false},"61":{"sum_comment":"","sum_foreign_comment":"","sum_foreign":"","sum":""},"62":{"sum_comment":"","sum_foreign_comment":"","sum_foreign":"","sum_unclear":false,"sum":""},"63":{"sum_comment":"ПАТ Укрсоцбанк, ПАТ КБ Приватбанк","sum_foreign_comment":"","sum_foreign":"","sum":"8383","sum_comment_hidden":false},"64":{"sum_comment":"Укрсоцбанк","sum_foreign_comment":"","sum_foreign":"","sum":"94","sum_comment_hidden":false}},"intro":{"declaration_year":"2014"}}]