[{"id":"vulyk_63_190","ft_src":"2008\nDaewoo Lanos\nоб'єм двигуна 1498\n68.7\n2014\n5509\n181499\n17677\n181499\n12168\nоб'єм двигуна 1498\n2008\nDaewoo Lanos\n68.7\nВергопуло Андрій Костянтинович\nАндрій Костянтинович Вергопуло\nАндрій Вергопуло\nВергопуло Андрій Костянтинович\nАндрій\nПодружжя\nВергопуло Катерина Петрівна, 23. 01. 1986\nДитина\nВергопуло Олександра Андріївна, 20. 11. 2009\nДитина\nВергопуло Олексій Андрійович, 31. 05. 2012\nВергопуло Андрій Костянтинович\nВергопуло\nЗагальний місцевий суд\nОдеська область\nсуддя котовського міськрайонного суду одеської області\nКостянтинович\n181499\n5509\n12168\n181499\n17677\n2014\nПодружжя\nВергопуло Катерина Петрівна, 23. 01. 1986\nДитина\nВергопуло Олександра Андріївна, 20. 11. 2009\nДитина\nВергопуло Олексій Андрійович, 31. 05. 2012\nКостянтинович\nВергопуло\nВергопуло Андрій Костянтинович\nАндрій Костянтинович Вергопуло\nАндрій Вергопуло\nВергопуло Андрій Костянтинович\nАндрій\nОдеська область\nсуддя котовського міськрайонного суду одеської області\nЗагальний місцевий суд\nВергопуло Андрій Костянтинович","estate":{"31":[{"costs_property_comment":"","address":"","space_units":"м²","space_hidden":false,"region":"","costs_rent_comment_hidden":false,"costs_property":"","space_comment":"","space_comment_unclear":false,"space_units_unclear":false,"costs_rent_hidden":false,"costs_property_hidden":false,"space_unclear":false,"address_hidden":false,"costs_rent_comment":"","space":"68.7","costs_property_comment_hidden":false,"region_hidden":false,"costs_rent":""}]},"vehicle":{"35":[{"sum_comment":"","brand_info":"об'єм двигуна 1498","brand_unclear":false,"sum_rent_comment":"","year":"2008","brand":"Daewoo Lanos","sum_rent":"","brand_info_unclear":false,"sum":""}]},"source":"VULYK","income":{"5":{"family":"17677","family_comment":"","comment":"","value_hidden":false,"value_unclear":false,"comment_hidden":false,"family_hidden":false,"family_unclear":false,"value":"181499"},"6":{"family_comment":"","family":"5509","comment":"","value_unclear":false,"family_unclear":false,"comment_unclear":false,"value":"181499","family_hidden":false},"7":{"source_name_hidden":false,"family_comment":"","family":"","value_hidden":false,"comment":"","source_name_unclear":false,"value":"","source_name":""},"8":{"family":"","family_comment":"","comment":"","value_hidden":false,"family_hidden":false,"value":""},"9":{"family":"","family_comment":"","comment":"","value_hidden":false,"value_unclear":false,"value":"","family_hidden":false,"family_unclear":false},"10":{"family_comment":"","value":"","family":"","comment":""},"11":{"family_comment":"","value":"","family":"","comment":""},"12":{"family_comment":"","value":"","family":"","comment":""},"13":{"family_comment":"","value":"","family":"","comment":""},"14":{"family_comment":"","value":"","family":"","comment":""},"15":{"family_comment":"","value":"","family":"","comment":""},"16":{"family_comment":"","family":"","comment":"","value_unclear":false,"family_unclear":false,"value":""},"17":{"family_comment":"","value":"","family":"","comment":""},"18":{"family_comment":"","value":"","family":"","comment":""},"19":{"family_comment":"","comment_unclear":false,"value":"","family":"","comment":""},"20":{"family_unclear":false,"family_comment":"","comment":"","family":"12168","value_unclear":false,"value_hidden":false,"comment_hidden":false,"comment_unclear":false,"value":"","family_hidden":false,"family_comment_unclear":false}},"general":{"family":[{"inn":"","inn_unclear":false,"family_name":"Вергопуло Катерина Петрівна, 23. 01. 1986","relations_hidden":false,"relations_unclear":false,"name_unclear":false,"relations":"Подружжя","inn_hidden":false,"name_hidden":false,"relations_other":""},{"inn":"","inn_unclear":false,"family_name":"Вергопуло Олександра Андріївна, 20. 11. 2009","relations_other":"","relations_unclear":false,"name_unclear":false,"inn_hidden":false,"name_hidden":false,"relations":"Дитина"},{"inn":"","inn_unclear":false,"family_name":"Вергопуло Олексій Андрійович, 31. 05. 2012","relations_other":"","name_unclear":false,"inn_hidden":false,"name_hidden":false,"relations":"Дитина"}],"family_raw":"","name":"Андрій","full_name_suggest":{"input":["Вергопуло Андрій Костянтинович","Андрій Костянтинович Вергопуло","Андрій Вергопуло"],"output":"Вергопуло Андрій Костянтинович"},"name_unclear":false,"patronymic":"Костянтинович","inn_hidden":false,"patronymic_unclear":false,"last_name_hidden":false,"inn":"","inn_unclear":false,"last_name":"Вергопуло","full_name":"Вергопуло Андрій Костянтинович","post":{"office":"Загальний місцевий суд","post":"суддя котовського міськрайонного суду одеської області","office_unclear":false,"office_hidden":false,"region":"Одеська область","region_hidden":false,"post_unclear":false,"region_unclear":false},"name_hidden":false,"last_name_unclear":false},"liabilities":{"54":{"sum_comment":"","sum_foreign_comment":"","sum_foreign":"","sum_unclear":false,"sum":""},"55":{"sum_comment":"","sum_foreign_comment":"","sum_foreign":"","sum":""},"56":{"sum_comment":"","sum_foreign_comment":"","sum_foreign":"","sum_unclear":false,"sum":""},"57":{"sum_comment":"","sum":"","sum_foreign_comment":"","sum_foreign":"","sum_unclear":false,"sum_comment_hidden":false},"58":{"sum_comment":"","sum_foreign_comment":"","sum_foreign":"","sum":"","sum_comment_hidden":false},"59":{"sum_comment":"","sum_foreign_comment":"","sum_foreign":"","sum":""},"60":{"sum_comment":"","sum_comment_unclear":false,"sum_foreign_comment":"","sum":"","sum_foreign":""},"61":{"sum_comment":"","sum_foreign_comment":"","sum_foreign":"","sum_unclear":false,"sum":""},"62":{"sum_comment":"","sum_foreign_comment":"","sum_foreign":"","sum_unclear":false,"sum":""},"63":{"sum_comment":"","sum_hidden":false,"sum":"","sum_foreign_comment":"","sum_foreign":"","sum_unclear":false,"sum_comment_hidden":false},"64":{"sum_comment":"","sum_foreign_comment":"","sum_foreign":"","sum":"","sum_comment_hidden":false}},"declaration":{"notfull_lostpages":"","additional_info_text":"","additional_info":"","date":"2015-03-25T00:00:00","notfull":"","url":"http://static.declarations.com.ua/declarations/chosen_ones/mega_batch/verhopulo_andrii_kostiantynovych.pdf"},"intro":{"isnotdeclaration":"","declaration_year_unclear":false,"declaration_year":"2014"}}]