[{"id":"vulyk_109_35","ft_src":"1596, 84\nFord Focus\n2007\n1596, 59.5\n2008\nВАЗ Лада Калина\n1/6 частина\n61.7\n76\n50\n2015\n1596, 84\nFord Focus\n2007\n1596, 59.5\nВАЗ Лада Калина\n2008\n2015\nАндрій\nСергійович\nВороняк Андрій Сергійович\nВороняк Андрій Сергійович\nАндрій Сергійович Вороняк\nАндрій Вороняк\nВороняк Андрій Сергійович\nВороняк\nГосподарський місцевий суд\nВолинська область\nсуддя господарського суду волинської області\n29143\n13344\n1214\n179136\n22575\n201711\n61.7\n1/6 частина\n76\n50\n29143\n13344\n1214\n179136\n201711\n22575\nСергійович\nВороняк\nВолинська область\nГосподарський місцевий суд\nсуддя господарського суду волинської області\nВороняк Андрій Сергійович\nВороняк Андрій Сергійович\nАндрій Сергійович Вороняк\nАндрій Вороняк\nВороняк Андрій Сергійович\nАндрій","estate":{"25":[{"address":"","space_units":"м²","space_hidden":false,"space_unclear":false,"region_hidden":false,"costs_comment":"","space_comment":"1/6 частина","address_hidden":false,"space":"61.7","costs_rent_comment":"","costs":"","region":"","space_units_hidden":false,"costs_rent":""},{"costs":"","address":"","space_units":"м²","costs_rent_comment":"","space":"76","space_comment":"","region_hidden":false,"costs_comment":"","region":"","address_hidden":false,"costs_rent":""}]},"vehicle":{"35":[{"sum_comment_unclear":false,"brand_info":"1596, 84","sum_rent_comment":"","brand_unclear":false,"brand_hidden":false,"year":"2007","sum_comment":"","brand_info_hidden":false,"sum_rent":"","brand":"Ford Focus","year_unclear":false,"brand_info_unclear":false,"sum":""},{"sum_comment":"","brand_info":"1596, 59.5","sum":"","sum_rent_comment":"","year":"2008","brand":"ВАЗ Лада Калина","sum_rent":""}]},"source":"VULYK","income":{"5":{"family_comment":"","value":"201711","family":"","comment":""},"6":{"family_comment":"","value":"179136","family":"","comment":""},"7":{"source_name_hidden":false,"family_comment":"","comment":"","family":"","comment_hidden":false,"value":"","source_name":""},"8":{"family_comment":"","family_hidden":false,"value":"","family":"","comment":""},"9":{"family_comment":"","family":"","comment":"","value_unclear":false,"family_unclear":false,"value":""},"10":{"family_comment":"","value":"","family":"","comment":""},"11":{"family_comment":"","value":"","family":"","comment":""},"12":{"family_comment":"","value":"","family":"","comment":""},"13":{"family_comment":"","value":"","family":"","comment":""},"14":{"family_comment":"","value":"","family":"","comment":""},"15":{"family_comment":"","value":"","family":"","comment":""},"16":{"family_comment":"","value":"","family":"","comment":""},"17":{"family_comment":"","value":"","family":"","comment":""},"18":{"family_comment":"","value":"","family":"","comment":""},"19":{"family_comment":"","value":"","family":"","comment":""},"20":{"family_comment":"","family":"","comment":"","value_unclear":false,"family_hidden":false,"value":"22575"}},"banks":{"45":[{"sum_units":"UAH","sum_comment":"","sum_foreign_units":"UAH","sum":"50","sum_units_hidden":false,"sum_foreign_comment":"","sum_foreign":"","sum_unclear":false,"sum_comment_hidden":false}]},"declaration":{"notfull_lostpages":"","additional_info_text":"","additional_info":"","date":"2016-03-30T00:00:00","notfull":"","url":"http://static.declarations.com.ua/declarations/chosen_ones/judges_batch/2492_voroniak_andrii_serhiiovych_2015.pdf"},"general":{"inn":"","inn_unclear":false,"last_name":"Вороняк","full_name_suggest":{"input":["Вороняк Андрій Сергійович","Андрій Сергійович Вороняк","Андрій Вороняк"],"output":"Вороняк Андрій Сергійович"},"full_name":"Вороняк Андрій Сергійович","patronymic":"Сергійович","family_raw":"","name":"Андрій","name_hidden":false,"post":{"office":"Господарський місцевий суд","post":"суддя господарського суду волинської області","office_unclear":false,"region_hidden":false,"region":"Волинська область","office_hidden":false,"region_unclear":false},"inn_hidden":true},"liabilities":{"54":{"sum_comment":"","sum_hidden":false,"sum":"1214","sum_foreign_comment":"","sum_foreign":"","sum_unclear":false,"sum_comment_hidden":false},"55":{"sum_comment":"","sum_comment_unclear":false,"sum_foreign_comment":"","sum":"","sum_foreign":""},"56":{"sum_comment":"","sum_foreign_comment":"","sum_foreign":"","sum":""},"57":{"sum_comment":"","sum_foreign_comment":"","sum_foreign":"","sum":"13344","sum_comment_hidden":false},"58":{"sum_comment":"","sum_foreign_comment":"","sum_foreign":"","sum":"29143","sum_comment_hidden":false},"59":{"sum_comment":"","sum_foreign_comment":"","sum_foreign":"","sum":""},"60":{"sum_comment":"","sum_foreign_comment":"","sum_foreign":"","sum":""},"61":{"sum_comment":"","sum_foreign_comment":"","sum_foreign":"","sum":""},"62":{"sum_comment":"","sum_foreign_comment":"","sum_foreign":"","sum":""},"63":{"sum_comment":"","sum_foreign_comment":"","sum_foreign":"","sum":""},"64":{"sum_comment":"","sum_foreign_comment":"","sum_foreign":"","sum":""}},"intro":{"isnotdeclaration":"","declaration_year":"2015"}},{"ft_src":"Ford,Focus\n2007\nLada,Kalina\n2008\nВАЗ,2104\n1993\nLada,Kalina\n2008\n61,7\n61,7\n478800\n76\n3402\n50\nTRUE\nВніс все, але є уточнення в Розділі V, сума коштів декларанта та членів сім’ї до кінця не зрозумілі. ;Є ймовірність, що там щось затерто, бо не зрозуміло, чого написано такими маленькими цифрами і дуже зліва.\nFALSE\nFALSE\n2013\n64279\n172430\n42076\n2981\n113274\n377855\n202444\n108041\nЄ10000\nFord,Focus\n2007\nLada,Kalina\n2008\nВАЗ,2104\n1993\nLada,Kalina\n2008\nВніс все, але є уточнення в Розділі V, сума коштів декларанта та членів сім’ї до кінця не зрозумілі. ;Є ймовірність, що там щось затерто, бо не зрозуміло, чого написано такими маленькими цифрами і дуже зліва.\nFALSE\nTRUE\n61,7\n61,7\n478800\n76\nСуддя господарського суду Волиньскої області\nМати - Вороняк Б.О.;Баба - Вороняк К.Т.\nВороняк\nВороняк Андрій Сергійович\nАндрій Сергійович Вороняк\nАндрій Вороняк\nВороняк Андрій Сергійович\nАндрій\nВороняк Андрій Сергійович\nГосподарський місцевий суд\nСуддя\nВолинська область\nСергійович\n1112\n267\n1230\n172430\n64279\n108041\nЄ10000\n202444\n2981\n42076\n377855\n113274\n50\n3402\n2013\nFALSE\n267\n1112\n1230\nВороняк\nСергійович\nМати - Вороняк Б.О.;Баба - Вороняк К.Т.\nВороняк Андрій Сергійович\nАндрій Сергійович Вороняк\nАндрій Вороняк\nВороняк Андрій Сергійович\nАндрій\nСуддя господарського суду Волиньскої області\nСуддя\nВолинська область\nГосподарський місцевий суд\nВороняк Андрій Сергійович","estate":{"23":[{"costs":"","address":"","space_units":"","costs_rent_comment":"","space":"","costs_comment":"","costs_rent":"","space_comment":"","region":"","location_raw":""},{"costs":"","address":"","space_units":"","costs_rent_comment":"","space":"","costs_comment":"","costs_rent":"","space_comment":"","region":"","location_raw":""},{"costs":"","address":"","space_units":"","costs_rent_comment":"","space":"","costs_comment":"","costs_rent":"","space_comment":"","region":"","location_raw":""}],"25":[{"costs":"","address":"","space_units":"","costs_rent_comment":"","space":"61,7","costs_comment":"","costs_rent":"","space_comment":"","region":"","location_raw":""},{"costs":"478800","address":"","space_units":"","costs_rent_comment":"","space":"76","costs_comment":"","costs_rent":"","space_comment":"","region":"","location_raw":""}],"31":[{"costs_property_comment":"","address":"","space_units":"","costs_rent_comment":"","space":"61,7","space_comment":"","costs_property":"","region":"","location_raw":"","costs_rent":""}]},"vehicle":{"35":[{"sum_comment":"","brand_info":"","sum":"","sum_rent_comment":"","year":"2007","brand":"Ford,Focus","sum_rent":"","brand_hidden":false},{"sum_comment":"","brand_info":"","sum":"","sum_rent_comment":"","year":"2008","brand":"Lada,Kalina","sum_rent":"","brand_hidden":false}],"40":[{"sum_comment":"","brand_info":"","sum":"","sum_rent_comment":"","year":"1993","brand":"ВАЗ,2104","sum_rent":"","brand_hidden":false},{"sum_comment":"","brand_info":"","sum":"","sum_rent_comment":"","year":"2008","brand":"Lada,Kalina","sum_rent":"","brand_hidden":false}]},"id":"3538","income":{"5":{"family_comment":"","value":"377855","family":"113274","comment":""},"6":{"family_comment":"","value":"172430","family":"64279","comment":""},"7":{"family":"0","family_comment":"","value":"0","comment":"","source_name":"0"},"8":{"family_comment":"","value":"0","family":"","comment":""},"9":{"family_comment":"","value":"0","family":"","comment":""},"10":{"family_comment":"","value":"0","family":"0","comment":""},"11":{"family_comment":"","value":"0","family":"0","comment":""},"12":{"family_comment":"","value":"0","family":"0","comment":""},"13":{"family_comment":"","value":"0","family":"0","comment":""},"14":{"family_comment":"","value":"0","family":"0","comment":""},"15":{"family_comment":"","value":"2981","family":"42076","comment":""},"16":{"family_comment":"","value":"0","family":"0","comment":""},"17":{"family_comment":"","value":"0","family":"0","comment":""},"18":{"family_comment":"","value":"0","family":"0","comment":""},"19":{"family_comment":"","value":"0","family":"0","comment":""},"20":{"family_comment":"","value":"202444","family":"0","comment":""},"21":[{"country_comment":"","uah_equal":"0","country":"0","cur":"0"},{"country_comment":"","uah_equal":"0","country":"0","cur":"0"},{"country_comment":"","uah_equal":"0","country":"0","cur":"0"},{"country_comment":"","uah_equal":"0","country":"0","cur":"0"},{"country_comment":"","uah_equal":"0","country":"0","cur":"0"}],"22":[{"country_comment":"","uah_equal":"108041","country":"0","cur":"Є10000"},{"country_comment":"","uah_equal":"0","country":"0","cur":"0"},{"country_comment":"","uah_equal":"0","country":"0","cur":"0"},{"country_comment":"","uah_equal":"0","country":"0","cur":"0"},{"country_comment":"","uah_equal":"0","country":"0","cur":"0"}]},"banks":{"45":[{"sum_units":"UAH","sum_comment":"","sum_foreign_units":"","sum":"50","sum_foreign_comment":"","sum_foreign":""},{"sum_units":"USD","sum_comment":"","sum_foreign_units":"","sum":"","sum_foreign_comment":"","sum_foreign":""},{"sum_units":"EUR","sum_comment":"","sum_foreign_units":"","sum":"","sum_foreign_comment":"","sum_foreign":""}],"46":[{"sum_units":"UAH","sum_comment":"","sum_foreign_units":"","sum":"","sum_foreign_comment":"","sum_foreign":""},{"sum_units":"USD","sum_comment":"","sum_foreign_units":"","sum":"","sum_foreign_comment":"","sum_foreign":""},{"sum_units":"EUR","sum_comment":"","sum_foreign_units":"","sum":"","sum_foreign_comment":"","sum_foreign":""}],"47":[{"sum_units":"","sum_comment":"","sum_foreign_units":"","sum":"","sum_foreign_comment":"","sum_foreign":""}],"48":[{"sum_units":"","sum_comment":"","sum_foreign_units":"","sum":"","sum_foreign_comment":"","sum_foreign":""}],"49":[{"sum_units":"","sum_comment":"","sum_foreign_units":"","sum":"","sum_foreign_comment":"","sum_foreign":""}],"50":[{"sum_units":"","sum_comment":"","sum_foreign_units":"","sum":"","sum_foreign_comment":"","sum_foreign":""}],"51":[{"sum_units":"UAH","sum_comment":"","sum_foreign_units":"","sum":"3402","sum_foreign_comment":"","sum_foreign":""},{"sum_units":"USD","sum_comment":"","sum_foreign_units":"","sum":"","sum_foreign_comment":"","sum_foreign":""},{"sum_units":"EUR","sum_comment":"","sum_foreign_units":"","sum":"","sum_foreign_comment":"","sum_foreign":""}],"52":[{"sum_units":"","sum_comment":"","sum_foreign_units":"","sum":"","sum_foreign_comment":"","sum_foreign":""}],"53":[{"sum_units":"","sum_comment":"","sum_foreign_units":"","sum":"","sum_foreign_comment":"","sum_foreign":""}]},"declaration":{"notfull_lostpages":"","additional_info_text":"Вніс все, але є уточнення в Розділі V, сума коштів декларанта та членів сім’ї до кінця не зрозумілі. ;Є ймовірність, що там щось затерто, бо не зрозуміло, чого написано такими маленькими цифрами і дуже зліва.","additional_info":"TRUE","notfull":"FALSE","url":"http://static.declarations.com.ua/declarations/sudy/hospodarski_mistsevi_sudy/volynska_oblast/deklaratsiya_voronyak.pdf","needs_scancopy_check":false},"general":{"family_raw":"Мати - Вороняк Б.О.;Баба - Вороняк К.Т.","name":"Андрій","full_name_suggest":{"input":["Вороняк Андрій Сергійович","Андрій Сергійович Вороняк","Андрій Вороняк"],"output":"Вороняк Андрій Сергійович"},"post_raw":"Суддя господарського суду Волиньскої області","name_unclear":false,"patronymic":"Сергійович","patronymic_unclear":false,"last_name_hidden":false,"patronymic_hidden":false,"inn":"","addresses_raw_hidden":true,"last_name":"Вороняк","full_name":"Вороняк Андрій Сергійович","post":{"office":"Господарський місцевий суд","region":"Волинська область","post":"Суддя"},"addresses_raw":"приховано","name_hidden":false,"last_name_unclear":false},"liabilities":{"54":{"sum_comment":"","sum_foreign_comment":"","sum_foreign":"","sum":"1230"},"55":{"sum_units":"","sum_comment":"","sum_foreign_units":"","sum":"","sum_foreign_comment":"","sum_foreign":""},"56":{"sum_comment":"","sum_foreign_comment":"","sum_foreign":"","sum":""},"57":{"sum_comment":"","sum_foreign_comment":"","sum_foreign":"","sum":"1112"},"58":{"sum_comment":"","sum_foreign_comment":"","sum_foreign":"","sum":"267"},"59":{"sum_comment":"","sum_foreign_comment":"","sum_foreign":"","sum":""},"60":{"sum_comment":"","sum_foreign_comment":"","sum_foreign":"","sum":""},"61":{"sum_units":"","sum_comment":"","sum_foreign_units":"","sum":"","sum_foreign_comment":"","sum_foreign":""},"62":{"sum_comment":"","sum_foreign_comment":"","sum_foreign":"","sum":""},"63":{"sum_comment":"","sum_units":"","sum_foreign":"","sum":"","sum_foreign_comment":""},"64":{"sum_comment":"","sum_units":"","sum_foreign":"","sum":"","sum_foreign_comment":""}},"intro":{"isnotdeclaration":"FALSE","declaration_year":"2013"}}]