{"id":"vulyk_97_124","ft_src":"ВАЗ 2121\n1578 куб. см., 58.8 кВт\n1985\n24.4\nОдеська область\nм. Одеса\nМиколаївська область\nЄланецький р-н\n48.8\nМиколаївська область\n62.2\nМиколаївська область\n20000\n715\n20000\nМиколаївська область\nОвідіопольський р-н\n767\nОдеська область\n178.7\nМиколаївська область\nПриватбанк\n250443\nПриватбанк\n101\n2014\n1578 куб. см., 58.8 кВт\nВАЗ 2121\n1985\n2014\nВжещ Світлана Іванівна\nСвітлана Іванівна Вжещ\nСвітлана Вжещ\nВжещ Світлана Іванівна\nСвітлана\nПодружжя\nКалашніков Є. О. 24. 10. 1978\nДитина\nКалашнікова С. Є. 29. 07. 2008\nДитина\nКалашніков Д. Є. 29. 07. 2013\nВжещ Світлана Іванівна\nВжещ\nЗагальний місцевий суд\nМиколаївська область\nсуддя новобузького районного суду миколаївської області\nІванівна\nМиколаївська область\n55600\n4460\nПриватбанк\n120\nПриватбанк\n131603\n14918\n160873\n131603\n145000\n955\n20000\nМиколаївська область\n767\nОвідіопольський р-н\nОдеська область\n20000\nМиколаївська область\n715\n178.7\nМиколаївська область\n62.2\nМиколаївська область\n24.4\nОдеська область\nм. Одеса\n48.8\nМиколаївська область\nЄланецький р-н\n101\nПриватбанк\n250443\nПриватбанк\nПриватбанк\n4460\nПриватбанк\n120\n131603\n955\n131603\n160873\n145000\n14918\nПодружжя\nКалашніков Є. О. 24. 10. 1978\nКалашнікова С. Є. 29. 07. 2008\nДитина\nДитина\nКалашніков Д. Є. 29. 07. 2013\nІванівна\nВжещ\nСвітлана\nВжещ Світлана Іванівна\nСвітлана Іванівна Вжещ\nСвітлана Вжещ\nВжещ Світлана Іванівна\n55600\nМиколаївська область\nМиколаївська область\nЗагальний місцевий суд\nсуддя новобузького районного суду миколаївської області\nВжещ Світлана Іванівна","estate":{"23":[{"address":"","space_units":"м²","costs_rent_unclear":false,"costs_comment":"","space_unclear":false,"region_hidden":true,"space_comment":"","address_hidden":true,"costs":"","address_unclear":false,"costs_rent_comment":"","space":"20000","region_unclear":false,"region":"Миколаївська область","costs_rent":""},{"address":"Овідіопольський р-н","space_units":"м²","costs_rent_unclear":false,"space_comment":"","region_hidden":false,"costs_comment":"","costs":"","address_unclear":false,"costs_rent_comment":"","space":"767","region_unclear":false,"region":"Одеська область","costs_rent":""}],"24":[{"address":"","space_units":"м²","space_hidden":false,"space_unclear":false,"region_hidden":true,"costs_rent_comment":"","space_comment":"","address_hidden":true,"costs":"","address_unclear":false,"space_comment_unclear":false,"costs_comment":"","space":"178.7","region_unclear":false,"region":"Миколаївська область","costs_rent":""}],"29":[{"costs_property_comment":"","address":"","space_units":"м²","space_unclear":false,"region_hidden":true,"costs_property":"","space_comment":"","address_hidden":true,"address_unclear":false,"space_comment_unclear":false,"costs_rent_comment":"","space":"20000","region_unclear":false,"region":"Миколаївська область","costs_rent":""},{"costs_property_comment":"","address":"","space_units":"м²","space_comment":"","region_hidden":false,"costs_property":"","region":"","address_hidden":true,"address_unclear":false,"costs_rent_comment":"","space":"715","costs_rent":""}],"30":[{"costs_property_comment":"","address":"","space_units":"м²","space_comment":"","region_hidden":false,"costs_property":"","region":"Миколаївська область","address_hidden":true,"address_unclear":false,"costs_rent_comment":"","space":"62.2","costs_rent":""}],"31":[{"costs_property_comment":"","address":"м. Одеса","space_units":"м²","space_hidden":false,"space_unclear":false,"region_hidden":false,"costs_property":"","space_comment":"","address_hidden":true,"space_comment_hidden":false,"costs_rent_comment":"","space":"24.4","region":"Одеська область","costs_rent":""},{"costs_property_comment":"","address":"Єланецький р-н","space_units":"м²","costs_rent_comment":"","space":"48.8","region":"Миколаївська область","costs_property":"","space_comment":"","address_hidden":true,"costs_rent":""}]},"vehicle":{"40":[{"sum_comment":"","brand_info":"1578 куб. см., 58.8 кВт","brand_unclear":false,"sum_rent_comment":"","year":"1985","brand":"ВАЗ 2121","sum_rent":"","brand_info_unclear":false,"year_unclear":false,"sum":""}]},"source":"VULYK","income":{"5":{"family_comment":"","value":"160873","family":"131603","comment":""},"6":{"family_comment":"","family":"131603","comment":"","value_unclear":false,"family_unclear":false,"comment_hidden":false,"value":""},"7":{"family":"","family_comment":"","value":"","comment":"","source_name":""},"8":{"family_comment":"","value":"","family":"","comment":""},"9":{"family_comment":"","value":"","family_unclear":false,"family":"","comment":""},"10":{"family_comment":"","value":"955","family":"","comment":"","value_unclear":false},"11":{"family_comment":"","value":"","family":"","comment":""},"12":{"family_comment":"","value":"","family":"","comment":""},"13":{"family_comment":"","value":"","family":"","comment":""},"14":{"family_comment":"","value":"","family":"","comment":""},"15":{"family_comment":"","value":"","family":"","comment":""},"16":{"family_comment":"","value":"145000","family":"","comment":""},"17":{"family_comment":"","value":"","family":"","comment":""},"18":{"family_comment":"","value":"","family":"","comment":""},"19":{"family_comment":"","value":"","family":"","comment":""},"20":{"family_comment":"","comment":"","family":"","value_unclear":false,"comment_unclear":false,"value":"14918","family_hidden":false,"family_comment_unclear":false}},"banks":{"45":[{"sum_comment_unclear":false,"sum_units":"UAH","sum_foreign_units":"UAH","sum_hidden":false,"sum":"101","sum_foreign_comment":"","sum_comment":"Приватбанк","sum_unclear":false,"sum_foreign":"","sum_comment_hidden":false}],"46":[{"sum_units":"UAH","sum_comment":"Приватбанк","sum_foreign_units":"UAH","sum":"250443","sum_foreign_comment":"","sum_foreign":"","sum_comment_hidden":false}]},"declaration":{"notfull_lostpages":"","additional_info_text":"","additional_info":"","date":"2015-11-05T00:00:00","notfull":"","url":"http://static.declarations.com.ua/declarations/chosen_ones/judges_batch/4026_vzheshch_svitlana_ivanivna.pdf"},"general":{"family":[{"inn":"","family_name":"Калашніков Є. О. 24. 10. 1978","relations_other":"","name_unclear":false,"inn_hidden":true,"name_hidden":false,"relations":"Подружжя"},{"inn":"","family_name":"Калашнікова С. Є. 29. 07. 2008","name_unclear":false,"inn_hidden":false,"name_hidden":false,"relations":"Дитина"},{"inn":"","family_name":"Калашніков Д. Є. 29. 07. 2013","relations_other":"","name_unclear":false,"inn_hidden":true,"name_hidden":false,"relations":"Дитина"}],"family_raw":"","name":"Світлана","full_name_suggest":{"input":["Вжещ Світлана Іванівна","Світлана Іванівна Вжещ","Світлана Вжещ"],"output":"Вжещ Світлана Іванівна"},"patronymic":"Іванівна","inn_hidden":true,"addresses":[{"place_city_type":"","place_city_type_hidden":false,"place_hidden":false,"place_city_hidden":false,"place_district_hidden":false,"place_district":"","place_city_unclear":false,"place":"Миколаївська область","place_city":"","place_address_hidden":true,"place_address":"55600"}],"last_name_hidden":false,"patronymic_hidden":false,"inn":"","inn_unclear":false,"last_name":"Вжещ","full_name":"Вжещ Світлана Іванівна","post":{"post_hidden":false,"office":"Загальний місцевий суд","post":"суддя новобузького районного суду миколаївської області","office_unclear":false,"region_unclear":false,"region":"Миколаївська область"},"name_hidden":false},"liabilities":{"54":{"sum_comment_unclear":false,"sum_comment":"Приватбанк","sum_hidden":false,"sum":"120","sum_foreign_comment":"","sum_foreign":"","sum_unclear":false,"sum_comment_hidden":false},"55":{"sum_comment":"","sum_foreign_comment":"","sum_foreign":"","sum":""},"56":{"sum_comment":"","sum_foreign_comment":"","sum_foreign":"","sum":""},"57":{"sum_comment_unclear":false,"sum_comment":"Приватбанк","sum_hidden":false,"sum":"4460","sum_foreign_comment":"","sum_foreign":"","sum_unclear":false,"sum_comment_hidden":false},"58":{"sum_comment_unclear":false,"sum_comment":"","sum_hidden":false,"sum":"","sum_foreign_comment":"","sum_foreign":"","sum_unclear":false,"sum_comment_hidden":false},"59":{"sum_comment":"","sum_foreign_comment":"","sum_foreign":"","sum":""},"60":{"sum_comment_unclear":false,"sum_comment":"","sum_hidden":false,"sum":"","sum_foreign_comment":"","sum_foreign":"","sum_comment_hidden":false},"61":{"sum_comment":"","sum_foreign_comment":"","sum_foreign":"","sum":""},"62":{"sum_comment":"","sum_foreign_comment":"","sum_foreign":"","sum_unclear":false,"sum":""},"63":{"sum_comment":"","sum_foreign_comment":"","sum_foreign":"","sum_hidden":false,"sum":""},"64":{"sum_comment":"","sum_foreign_comment":"","sum_foreign":"","sum":""}},"intro":{"isnotdeclaration":"","declaration_year":"2014"}}