{"income":{"5":{"family_comment":"","value":"209864.14","family":"13600","comment":""},"6":{"family_comment":"","value":"209864.14","family":"","comment":""},"7":{"value":"","comment_hidden":false,"family_comment":"","source_name":"","family":"","comment":"","source_name_hidden":false},"8":{"family_comment":"","value":"","family_hidden":false,"comment":"","family":""},"9":{"value":"","family_comment":"","value_unclear":false,"family_unclear":false,"family":"","comment":""},"10":{"family_comment":"","value":"","family":"","comment":""},"11":{"family_comment":"","value":"","family":"","comment":""},"12":{"family_comment":"","value":"","family":"","comment":""},"13":{"family_comment":"","value":"","family":"","comment":""},"14":{"family_comment":"","value":"","family":"","comment":""},"15":{"family_comment":"","value":"","family":"","comment":""},"16":{"family_comment":"","value":"","family":"","comment":""},"17":{"family_comment":"","value":"","family":"","comment":""},"18":{"family_comment":"","value":"","family":"","comment":""},"19":{"family_comment":"","value":"","family":"","comment":""},"20":{"value":"","value_unclear":false,"family_hidden":false,"family_comment":"пенсія","family":"13600","comment":""}},"vehicle":{"35":[{"brand_info":"","sum_rent_comment":"","year":"2012","brand_info_hidden":false,"brand_info_unclear":false,"year_unclear":false,"sum_rent":"","sum":"","brand":"Volkswagen Polo","sum_comment":"","sum_comment_unclear":false,"brand_hidden":false,"brand_unclear":false}]},"id":"vulyk_109_103","declaration":{"additional_info_text":"","notfull_lostpages":"","date":"2016-03-24T00:00:00","notfull":"","additional_info":"","url":"http://static.declarations.com.ua/declarations/chosen_ones/judges_batch/2560_nemchenko_liubov_mykolaivna_2015.pdf"},"liabilities":{"54":{"sum_foreign_comment":"","sum":"","sum_comment":"","sum_hidden":false,"sum_comment_hidden":false,"sum_unclear":false,"sum_foreign":""},"55":{"sum_foreign_comment":"","sum":"","sum_comment":"","sum_comment_unclear":false,"sum_foreign":""},"56":{"sum_foreign_comment":"","sum":"","sum_comment":"","sum_foreign":""},"57":{"sum_foreign_comment":"","sum_comment_hidden":false,"sum":"","sum_comment":"","sum_foreign":""},"58":{"sum_foreign_comment":"","sum_comment_hidden":false,"sum":"","sum_comment":"","sum_foreign":""},"59":{"sum_foreign_comment":"","sum":"","sum_comment":"","sum_foreign":""},"60":{"sum_foreign_comment":"","sum":"","sum_comment":"","sum_foreign":""},"61":{"sum_foreign_comment":"","sum":"","sum_comment":"","sum_foreign":""},"62":{"sum_foreign_comment":"","sum":"","sum_comment":"","sum_foreign":""},"63":{"sum_foreign_comment":"","sum":"","sum_comment":"","sum_foreign":""},"64":{"sum_foreign_comment":"","sum":"","sum_comment":"","sum_foreign":""}},"ft_src":"суддя\nХерсонська область\nГосподарський місцевий суд\nЛюбов\nНемченко Ольга Петрівна 20. 02. 1938\nБатьки\nМиколаївна\nНемченко Любов Миколаївна\nЛюбов Миколаївна Немченко\nЛюбов Немченко\nНемченко Любов Миколаївна\nНемченко Любов Миколаївна\nНемченко\nVolkswagen Polo\n2012\n48\n2015\n209864.14\n13600\n209864.14\nпенсія\n13600\nVolkswagen Polo\n2012\n2015\nНемченко Любов Миколаївна\nЛюбов Миколаївна Немченко\nЛюбов Немченко\nНемченко Любов Миколаївна\nЛюбов\nБатьки\nНемченко Ольга Петрівна 20. 02. 1938\nНемченко Любов Миколаївна\nМиколаївна\nГосподарський місцевий суд\nХерсонська область\nсуддя\nНемченко\n209864.14\nпенсія\n13600\n209864.14\n13600\n48\nБатьки\nНемченко Ольга Петрівна 20. 02. 1938\nМиколаївна\nНемченко\nЛюбов\nНемченко Любов Миколаївна\nЛюбов Миколаївна Немченко\nЛюбов Немченко\nНемченко Любов Миколаївна\nХерсонська область\nГосподарський місцевий суд\nсуддя\nНемченко Любов Миколаївна\n2012\nVolkswagen Polo\nпенсія\n13600\n13600\n209864.14\n209864.14\n48\n2015","general":{"name_hidden":false,"name":"Любов","inn":"","family":[{"inn":"","relations":"Батьки","relations_hidden":false,"inn_hidden":true,"relations_other":"","name_hidden":false,"family_name":"Немченко Ольга Петрівна 20. 02. 1938","name_unclear":false}],"patronymic":"Миколаївна","inn_hidden":true,"family_raw":"","inn_unclear":false,"post":{"region_unclear":false,"region":"Херсонська область","post":"суддя","region_hidden":false,"office":"Господарський місцевий суд","office_hidden":false,"office_unclear":false},"full_name":"Немченко Любов Миколаївна","addresses":[{"place_district":"","place_city_hidden":true,"place_city":"","place_city_type_hidden":true,"place_district_hidden":true,"place_city_type":"","place_address_hidden":true,"place_address":"","place_hidden":true,"place":""}],"last_name":"Немченко","full_name_suggest":{"output":"Немченко Любов Миколаївна","input":["Немченко Любов Миколаївна","Любов Миколаївна Немченко","Любов Немченко"]}},"source":"VULYK","estate":{"25":[{"space_unclear":false,"costs":"","costs_comment":"","address_hidden":false,"region_hidden":true,"space_comment":"","space_hidden":false,"space":"48","address":"","region":"","costs_rent_comment":"","space_units":"м²","space_units_hidden":false,"costs_rent":""}]},"intro":{"declaration_year":"2015","isnotdeclaration":""}}