{"income":{"5":{"value":"209547.95","family_comment":"","family_hidden":false,"family_unclear":false,"family":"44424.28","comment":""},"6":{"value":"183699.25","family_comment":"","value_unclear":false,"family_hidden":false,"family_unclear":false,"family":"33934.24","comment":""},"7":{"value":"","family_hidden":false,"value_hidden":false,"family_comment":"","source_name":"","family":"","comment":"","source_name_hidden":false},"8":{"family_comment":"","value":"","family":"","comment":""},"9":{"family_comment":"","value":"","family":"","comment":""},"10":{"family_comment":"","value":"11470","value_unclear":false,"family":"10490.04","comment":""},"11":{"family_comment":"","value":"24","family":"","comment":""},"12":{"family_comment":"","value":"","family":"","comment":""},"13":{"family_comment":"","value":"","family":"","comment":""},"14":{"family_comment":"","value":"","family":"","comment":""},"15":{"family_comment":"","value":"","family":"","comment":""},"16":{"family_comment":"","value":"","family":"","comment":""},"17":{"family_comment":"","value":"","family":"","comment":""},"18":{"family_comment":"","value":"","family":"","comment":""},"19":{"family_comment":"","value":"","family":"","comment":""},"20":{"value":"14354.7","family_comment":"","value_unclear":false,"family_unclear":false,"comment_unclear":false,"comment":"","family":""}},"vehicle":{"40":[{"brand_info":"1600 куб. см.","sum_rent_comment":"","brand":"Daihatsu Terios","sum_comment":"","brand_unclear":false,"year":"2007","brand_info_unclear":false,"year_unclear":false,"sum":"","sum_rent":""}]},"id":"vulyk_74_56","declaration":{"additional_info_text":"","notfull_lostpages":"","date":"2014-12-03T00:00:00","notfull":"","additional_info":"","url":"http://static.declarations.com.ua/declarations/chosen_ones/judges_batch/1725_shaptala_ievhen_iuriiovych.pdf"},"liabilities":{"54":{"sum_foreign_comment":"","sum":"","sum_comment":"","sum_comment_unclear":false,"sum_comment_hidden":false,"sum_foreign":""},"55":{"sum_foreign_comment":"","sum":"","sum_comment":"","sum_hidden":false,"sum_unclear":false,"sum_foreign":""},"56":{"sum_foreign_comment":"","sum":"","sum_comment":"","sum_hidden":false,"sum_unclear":false,"sum_foreign":""},"57":{"sum_foreign_comment":"","sum":"","sum_comment":"","sum_comment_unclear":false,"sum_comment_hidden":false,"sum_foreign":""},"58":{"sum_foreign_comment":"","sum_comment":"","sum":"","sum_comment_hidden":false,"sum_foreign":""},"59":{"sum_foreign_comment":"","sum":"","sum_comment":"","sum_foreign":""},"60":{"sum_foreign_comment":"","sum":"","sum_foreign":"","sum_comment":"","sum_hidden":false},"61":{"sum_foreign_comment":"","sum":"","sum_comment":"","sum_foreign":""},"62":{"sum_foreign_comment":"","sum":"","sum_comment":"","sum_foreign":""},"63":{"sum_foreign_comment":"","sum":"","sum_comment":"","sum_comment_unclear":false,"sum_unclear":false,"sum_foreign":""},"64":{"sum_foreign_comment":"","sum":"","sum_comment":"","sum_comment_unclear":false,"sum_unclear":false,"sum_foreign":""}},"ft_src":"Daihatsu Terios\n1600 куб. см.\n2007\n2013\n33934.24\n183699.25\n24\n10490.04\n11470\n44424.28\n209547.95\n14354.7\n1600 куб. см.\nDaihatsu Terios\n2007\n2013\nАпеляційний господарський суд\nм. Київ\nсуддя київського апеляційного господарського суду\nЮрійович\nШаптала Євген Юрійович\nЄвген Юрійович Шаптала\nЄвген Шаптала\nШаптала Євген Юрійович\nЄвген\nПодружжя\nШаптала О. В\nДитина\nШаптала М. Є\nШаптала Євген Юрійович\nШаптала\n33934.24\n183699.25\n14354.7\n209547.95\n44424.28\n11470\n10490.04\n24\nПодружжя\nШаптала О. В\nДитина\nШаптала М. Є\nЮрійович\nШаптала\nм. Київ\nАпеляційний господарський суд\nсуддя київського апеляційного господарського суду\nШаптала Євген Юрійович\nШаптала Євген Юрійович\nЄвген Юрійович Шаптала\nЄвген Шаптала\nШаптала Євген Юрійович\nЄвген","general":{"inn":"","inn_hidden":false,"last_name":"Шаптала","post":{"region_unclear":false,"post":"суддя київського апеляційного господарського суду","post_hidden":false,"region":"м. Київ","office":"Апеляційний господарський суд","office_unclear":false},"name":"Євген","full_name":"Шаптала Євген Юрійович","family_raw":"","family":[{"inn":"","relations":"Подружжя","relations_other":"","inn_hidden":false,"family_name":"Шаптала О. В","name_hidden":false,"name_unclear":false},{"inn":"","relations":"Дитина","relations_other":"","inn_hidden":false,"family_name":"Шаптала М. Є","name_hidden":false,"name_unclear":false}],"full_name_suggest":{"output":"Шаптала Євген Юрійович","input":["Шаптала Євген Юрійович","Євген Юрійович Шаптала","Євген Шаптала"]},"patronymic":"Юрійович"},"source":"VULYK","intro":{"declaration_year":"2013","isnotdeclaration":"","declaration_year_unclear":false}}