{"income":{"5":{"value":"286741","family_comment":"","value_unclear":false,"family_unclear":false,"family":"107237","comment":""},"6":{"value":"238811","family_comment":"","value_unclear":false,"family_unclear":false,"family":"16031","comment":""},"7":{"family_comment":"","value":"","source_name":"","family":"","comment":""},"8":{"family_comment":"","value":"","family":"","comment":""},"9":{"family_comment":"","value":"17000","family":"60750","comment":""},"10":{"family_comment":"","value":"","family":"","comment":""},"11":{"family_comment":"","value":"","family":"","comment":""},"12":{"family_comment":"","value":"","family":"","comment":""},"13":{"family_comment":"","value":"","family":"","comment":""},"14":{"family_comment":"","value":"","family":"","comment":""},"15":{"family_comment":"","value":"","value_unclear":false,"family":"","comment":""},"16":{"family_comment":"","value":"","family":"","comment":""},"17":{"family_comment":"","value":"","family":"","comment":""},"18":{"family_comment":"","value":"","family":"","comment":""},"19":{"family_comment":"","value":"","family":"13200","comment":""},"20":{"value":"30930","family_comment":"","value_unclear":false,"family_unclear":false,"family":"17256","comment":"","family_comment_unclear":false}},"vehicle":{"35":[{"brand_info":"1800 куб. см.","sum_rent_comment":"","brand":"Skoda Octavia","sum_comment":"","brand_unclear":false,"year":"2008","brand_info_unclear":false,"sum":"","sum_rent":""}]},"id":"vulyk_99_16","banks":{"45":[{"sum_foreign_comment":"","sum":"100000","sum_comment":"","sum_foreign_units":"UAH","sum_comment_hidden":true,"sum_units":"UAH","sum_foreign":""}],"51":[{"sum_foreign_comment":"","sum":"437000","sum_comment":"","sum_comment_unclear":false,"sum_foreign_units":"UAH","sum_comment_hidden":true,"sum_units":"UAH","sum_foreign":""}]},"declaration":{"date":"2016-02-05T00:00:00","notfull":"","notfull_lostpages":"","url":"http://static.declarations.com.ua/declarations/chosen_ones/judges_batch/565_karpovych_volodymyr_dmytrovych_2015.pdf"},"liabilities":{"54":{"sum_foreign_comment":"","sum":"","sum_comment":"","sum_comment_unclear":false,"sum_comment_hidden":false,"sum_foreign":""},"55":{"sum_foreign_comment":"","sum":"","sum_comment":"","sum_foreign":""},"56":{"sum_foreign_comment":"","sum":"","sum_comment":"","sum_foreign":""},"57":{"sum_foreign_comment":"","sum_comment":"","sum":"","sum_comment_hidden":false,"sum_foreign":""},"58":{"sum_foreign_comment":"","sum_comment":"","sum":"","sum_comment_hidden":false,"sum_foreign":""},"59":{"sum_foreign_comment":"","sum":"","sum_comment":"","sum_comment_hidden":false,"sum_unclear":false,"sum_foreign":""},"60":{"sum_foreign_comment":"","sum_comment":"","sum":"","sum_comment_hidden":false,"sum_foreign":""},"61":{"sum_foreign_comment":"","sum":"","sum_comment":"","sum_foreign":""},"62":{"sum_foreign_comment":"","sum":"","sum_comment":"","sum_foreign":""},"63":{"sum_foreign_comment":"","sum_comment":"","sum":"","sum_comment_hidden":false,"sum_foreign":""},"64":{"sum_foreign_comment":"","sum_comment":"","sum":"","sum_comment_hidden":false,"sum_foreign":""}},"ft_src":"2008\nSkoda Octavia\n1800 куб. см.\n437000\n100000\n2015\n1800 куб. см.\nSkoda Octavia\n2008\n100000\n437000\n.1\nм. Яготин\nКиївська область\nКиївська область\n84.7\nм. Яготин\n51\n1/3 від 51 кв. м\nКиївська область\nм. Яготин\nкімната-офіс\n11.3\n51\n1/3 від 51 кв. м\nм. Яготин\nКиївська область\nКарпович\nКарпович Володимир Дмитрович\nВолодимир Дмитрович Карпович\nВолодимир Карпович\nКарпович Володимир Дмитрович\nВолодимир\nДмитрович\nКиївська область\nЯготин\nКарпович Володимир Дмитрович\nЗагальний місцевий суд\nсуддя яготинського районного суду київської області\nКиївська область\nПодружжя\nКарпович В. В\n238811\n16031\n30930\n17256\n286741\n107237\n17000\n60750\n13200\n2015\nКиївська область\n1/3 від 51 кв. м\nм. Яготин\n51\nм. Яготин\n.1\nКиївська область\nкімната-офіс\n11.3\nм. Яготин\n84.7\nКиївська область\n1/3 від 51 кв. м\nм. Яготин\nКиївська область\n51\nКарпович В. В\nПодружжя\nДмитрович\nКиївська область\nЯготин\nКарпович\nсуддя яготинського районного суду київської області\nКиївська область\nЗагальний місцевий суд\nКарпович Володимир Дмитрович\nКарпович Володимир Дмитрович\nВолодимир Дмитрович Карпович\nВолодимир Карпович\nКарпович Володимир Дмитрович\nВолодимир\n16031\n238811\n60750\n17000\n107237\n286741\n13200\n17256\n30930","general":{"inn":"","inn_hidden":true,"last_name":"Карпович","post":{"post_unclear":false,"office":"Загальний місцевий суд","post":"суддя яготинського районного суду київської області","region":"Київська область"},"name":"Володимир","full_name":"Карпович Володимир Дмитрович","family_raw":"","addresses":[{"place_district":"","place_address_hidden":true,"place_city":"Яготин","place_address":"","place_district_hidden":false,"place_city_type":"Місто","place_city_hidden":false,"place_city_type_hidden":false,"place_hidden":false,"place":"Київська область"}],"family":[{"inn":"","relations":"Подружжя","name_hidden":true,"inn_hidden":true,"family_name":"Карпович В. В","name_unclear":false}],"full_name_suggest":{"output":"Карпович Володимир Дмитрович","input":["Карпович Володимир Дмитрович","Володимир Дмитрович Карпович","Володимир Карпович"]},"patronymic":"Дмитрович"},"source":"VULYK","estate":{"23":[{"space_unclear":false,"costs":"","costs_comment":"","address_hidden":true,"region_hidden":false,"space_comment":"","space":".1","address":"м. Яготин","region":"Київська область","costs_rent_comment":"","space_units":"га","costs_rent":""}],"24":[{"costs_rent":"","region":"Київська область","costs":"","costs_rent_comment":"","costs_comment":"","address_hidden":true,"region_hidden":false,"space_comment":"","space_units":"м²","space":"84.7","address":"м. Яготин"}],"25":[{"space_unclear":false,"costs":"","costs_comment":"","address_hidden":true,"region_hidden":false,"space_comment":"1/3 від 51 кв. м","space_hidden":false,"space":"51","address":"м. Яготин","region":"Київська область","costs_rent_comment":"","space_units":"м²","costs_rent":""}],"31":[{"costs_rent":"","region":"Київська область","costs_property":"","costs_rent_comment":"","address_hidden":false,"region_hidden":false,"space_comment":"1/3 від 51 кв. м","costs_property_comment":"","space_units":"м²","space":"51","address":"м. Яготин"}],"34":[{"space_unclear":false,"address_hidden":false,"region_hidden":true,"space_comment":"кімната-офіс","space_hidden":false,"space":"11.3","address":"","region":"","costs_property":"","costs_rent_comment":"","space_units":"м²","costs_property_comment":"","costs_rent":""}]},"intro":{"declaration_year":"2015"}}