{"income":{"5":{"value":"246618","family_comment":"","value_unclear":false,"family_hidden":false,"value_hidden":false,"family_unclear":false,"comment_unclear":false,"comment":"","family":"7390"},"6":{"value":"234001","family_unclear":false,"family_hidden":false,"family_comment":"","family":"","comment":""},"7":{"value":"","family_hidden":false,"value_hidden":false,"family_comment":"","source_name":"","family":"","comment":""},"8":{"family_comment":"","value":"","family":"","comment":""},"9":{"family_comment":"","value":"","value_unclear":false,"family":"","comment":""},"10":{"family_comment":"","family_unclear":false,"value":"12617","family":"","comment":""},"11":{"family_comment":"","value":"","family":"","comment":""},"12":{"family_comment":"","value":"","family":"","comment":""},"13":{"family_comment":"","value":"","family":"","comment":""},"14":{"family_comment":"","value":"","family":"","comment":""},"15":{"family_comment":"","value":"","family":"","comment":""},"16":{"family_comment":"","value":"","family":"","comment":""},"17":{"family_comment":"","value":"","family":"7390","comment":""},"18":{"family_comment":"","value":"","family":"","comment":""},"19":{"family_comment":"","value":"","family":"","comment":""},"20":{"value":"","value_unclear":false,"family_comment":"","comment_unclear":false,"comment":"","family":""}},"vehicle":{"40":[{"brand_info":"800 куб. см.","sum":"","brand":"Daewoo Matiz","sum_comment":"","brand_unclear":true,"year":"2008","brand_info_hidden":false,"brand_info_unclear":false,"sum_rent_comment":"","sum_rent":""}]},"id":"vulyk_71_81","declaration":{"additional_info_text":"","notfull_lostpages":"","date":"2014-03-28T00:00:00","notfull":"","additional_info":"","url":"http://static.declarations.com.ua/declarations/chosen_ones/judges_batch/554_presniakova_anzhelika_anatoliivna.pdf"},"liabilities":{"54":{"sum_foreign_comment":"","sum":"","sum_comment":"","sum_comment_unclear":false,"sum_comment_hidden":false,"sum_unclear":false,"sum_foreign":""},"55":{"sum_foreign_comment":"","sum":"","sum_comment":"","sum_foreign":""},"56":{"sum_foreign_comment":"","sum":"2013","sum_comment":"","sum_comment_unclear":false,"sum_unclear":true,"sum_foreign":""},"57":{"sum_foreign_comment":"","sum":"2912","sum_comment":"","sum_comment_hidden":false,"sum_unclear":false,"sum_foreign":""},"58":{"sum_foreign_comment":"","sum":"8099","sum_comment":"","sum_comment_hidden":false,"sum_unclear":false,"sum_foreign":""},"59":{"sum_foreign_comment":"","sum_comment_hidden":false,"sum":"","sum_comment":"","sum_foreign":""},"60":{"sum_foreign_comment":"","sum_comment_hidden":false,"sum":"1594","sum_comment":"","sum_foreign":""},"61":{"sum_foreign_comment":"","sum":"","sum_comment":"","sum_foreign":""},"62":{"sum_foreign_comment":"","sum":"25423","sum_comment":"","sum_foreign":""},"63":{"sum_foreign_comment":"","sum":"51098","sum_comment":"","sum_unclear":false,"sum_foreign":""},"64":{"sum_foreign_comment":"","sum":"39029","sum_comment":"","sum_unclear":false,"sum_foreign":""}},"ft_src":"2912\n25423\n8099\n51098\n2013\n1594\n39029\nсуддя апеляційного суду донецької області\nДонецька область\nЗагальний апеляційний суд\nАнжеліка\nПресняков О. О\nПодружжя\nАнатоліївна\nПреснякова Анжеліка Анатоліївна\nАнжеліка Анатоліївна Преснякова\nАнжеліка Преснякова\nПреснякова Анжеліка Анатоліївна\nПреснякова Анжеліка Анатоліївна\nПреснякова\n800 куб. см.\nDaewoo Matiz\n2008\n34.7\n1/3 частина\n13.6\n247.6\n1400\n13.6\n2013\n234001\n12617\n7390\n246618\n7390\n800 куб. см.\n2008\nDaewoo Matiz\n34.7\n13.6\n1/3 частина\n247.6\n13.6\n1400\nПодружжя\nПресняков О. О\nПреснякова Анжеліка Анатоліївна\nАнжеліка Анатоліївна Преснякова\nАнжеліка Преснякова\nПреснякова Анжеліка Анатоліївна\nПреснякова Анжеліка Анатоліївна\nАнжеліка\nАнатоліївна\nЗагальний апеляційний суд\nДонецька область\nсуддя апеляційного суду донецької області\nПреснякова\n8099\n2912\n1594\n2013\n25423\n51098\n39029\n234001\n7390\n246618\n7390\n12617\n2013\n8099\n2912\n2013\n25423\n1594\n51098\n39029\nПресняков О. О\nПодружжя\nАнатоліївна\nПреснякова\nАнжеліка\nПреснякова Анжеліка Анатоліївна\nАнжеліка Анатоліївна Преснякова\nАнжеліка Преснякова\nПреснякова Анжеліка Анатоліївна\nДонецька область\nЗагальний апеляційний суд\nсуддя апеляційного суду донецької області\nПреснякова Анжеліка Анатоліївна\nDaewoo Matiz\n800 куб. см.\n2008\n12617\n246618\n7390\n7390\n234001\n1/3 частина\n13.6\n13.6\n34.7\n247.6\n1400\n2013","general":{"inn":"","name":"Анжеліка","family":[{"inn":"","inn_hidden":true,"relations_hidden":false,"family_name":"Пресняков О. О","relations_other":"","relations":"Подружжя","name_hidden":false,"name_unclear":false}],"patronymic":"Анатоліївна","inn_hidden":true,"family_raw":"","inn_unclear":false,"post":{"post_unclear":false,"region_unclear":false,"post":"суддя апеляційного суду донецької області","office":"Загальний апеляційний суд","region":"Донецька область","post_hidden":false,"office_unclear":false},"full_name_suggest":{"output":"Преснякова Анжеліка Анатоліївна","input":["Преснякова Анжеліка Анатоліївна","Анжеліка Анатоліївна Преснякова","Анжеліка Преснякова"]},"full_name":"Преснякова Анжеліка Анатоліївна","addresses":[{"place_district":"","place_unclear":false,"place_city":"","place_city_type_hidden":true,"place_district_hidden":true,"place_city_type":"","place_city_hidden":true,"place_address_hidden":true,"place_address":"","place_hidden":true,"place":""}],"last_name":"Преснякова","patronymic_hidden":false,"last_name_unclear":false,"name_unclear":false},"source":"VULYK","estate":{"25":[{"region_unclear":false,"space_unclear":false,"costs":"","costs_rent_unclear":false,"costs_comment":"","costs_hidden":false,"address_hidden":true,"region_hidden":true,"space_comment":"","space_hidden":false,"space":"13.6","address":"","costs_unclear":false,"region":"","address_unclear":false,"costs_rent_comment":"","costs_rent_hidden":false,"space_comment_unclear":false,"space_units":"м²","costs_rent":""}],"29":[{"space_unclear":false,"address_hidden":true,"region_hidden":true,"space_comment":"","space":"1400","address":"","region":"","costs_property":"","costs_rent_comment":"","space_units":"м²","costs_property_comment":"","costs_rent":""}],"31":[{"space_hidden":false,"costs_property_comment":"","address_hidden":true,"region_hidden":true,"space_comment":"1/3 частина","space":"13.6","address":"","region":"","costs_property":"","costs_rent_comment":"","space_comment_unclear":false,"space_units":"м²","space_units_hidden":false,"costs_rent":""}],"33":[{"space_hidden":false,"address_hidden":true,"region_hidden":true,"space_comment":"","space":"34.7","address":"","region":"","costs_property":"","costs_rent_comment":"","space_comment_hidden":false,"space_units":"м²","costs_property_comment":"","costs_rent":""}],"34":[{"region_unclear":false,"space_hidden":false,"address_hidden":true,"region_hidden":true,"space_comment":"","space":"247.6","address":"","region":"","costs_property":"","costs_rent_comment":"","space_comment_hidden":false,"space_units":"м²","costs_property_comment":"","costs_rent":""}]},"intro":{"declaration_year":"2013","isnotdeclaration":""}}