{"id":"vulyk_100_191","ft_src":"1199 куб. см., 61 кВт\nPeugeot 2008 Allure\n2014\n254724\n1/4 квартири загальною площею 60,7\n60.7\n40.2\n.314\n2014\n218910\n12828\n325917\n12828\nкредит, путівка, пенсія\n107007\n1975\nПортугалія\n100\n1199 куб. см., 61 кВт\nPeugeot 2008 Allure\n2014\n254724\n.314\n40.2\n60.7\n1/4 квартири загальною площею 60,7\nБатьки\nБаргаміна В. О\nДитина\nКравченко Є. В\nМиколаївна\nБаргаміна\nБаргаміна Наталія Миколаївна\nНаталія Миколаївна Баргаміна\nНаталія Баргаміна\nБаргаміна Наталія Миколаївна\nБаргаміна Наталія Миколаївна\nНаталія\nАдміністративний місцевий суд\nЧернігівська область\nсуддя чернігівського окружного адміністративного суду\n14647\nКреді Агріколь Банк\n27604\n946\n218910\n1975\n100\nПортугалія\n107007\n12828\nкредит, путівка, пенсія\n325917\n12828\n2014\n946\nКреді Агріколь Банк\n27604\n14647\nБаргаміна В. О\nБатьки\nДитина\nКравченко Є. В\nМиколаївна\nБаргаміна\nЧернігівська область\nАдміністративний місцевий суд\nсуддя чернігівського окружного адміністративного суду\nБаргаміна Наталія Миколаївна\nБаргаміна Наталія Миколаївна\nНаталія Миколаївна Баргаміна\nНаталія Баргаміна\nБаргаміна Наталія Миколаївна\nНаталія","estate":{"29":[{"costs_property_comment":"","address":"","space_units":"га","space_unclear":false,"region_hidden":true,"costs_property":"","space_comment":"","address_hidden":true,"address_unclear":false,"costs_rent_comment":"","space":".314","region_unclear":false,"region":"","costs_rent":""}],"30":[{"costs_property_comment":"","address":"","space_units":"м²","costs_rent_comment":"","space":"40.2","region":"","region_hidden":true,"costs_property":"","space_comment":"","address_hidden":true,"costs_rent":""}],"31":[{"costs_property_comment":"","address":"","space_units":"м²","space_unclear":false,"region_hidden":true,"costs_property":"","space_comment":"1/4 квартири загальною площею 60,7","address_hidden":true,"address_unclear":false,"space_comment_unclear":false,"costs_rent_comment":"","space":"60.7","costs_property_comment_unclear":false,"region_unclear":false,"region":"","costs_rent":""}]},"vehicle":{"35":[{"brand_info":"1199 куб. см., 61 кВт","sum_rent_comment":"","brand_unclear":false,"sum_rent_comment_unclear":false,"brand_hidden":false,"sum_comment":"","brand_info_hidden":false,"sum_rent":"","brand":"Peugeot 2008 Allure","brand_info_unclear":false,"year":"2014","sum":"254724"}]},"source":"VULYK","income":{"5":{"family_comment":"","family":"12828","comment":"","value_unclear":false,"family_unclear":false,"value":"325917"},"6":{"family_comment":"","value":"218910","family":"","comment":"","value_unclear":false},"7":{"family_comment":"","comment":"","family":"","value_unclear":false,"value":"","source_name":""},"8":{"family_comment":"","value":"","family":"","comment":""},"9":{"family_comment":"","family":"","comment":"","value_unclear":false,"family_unclear":false,"value":""},"10":{"family_comment":"","comment_unclear":false,"value":"","family":"","comment":""},"11":{"family_comment":"","value":"","family":"","comment":""},"12":{"family_comment":"","value":"","family":"","comment":""},"13":{"family_comment":"","value":"","family":"","comment":"","value_unclear":false},"14":{"family_comment":"","value":"","family":"","comment":""},"15":{"family_comment":"","value":"","family":"","comment":""},"16":{"family_comment":"","value":"","family_unclear":false,"family":"","comment":""},"17":{"family_comment":"","value":"","family_unclear":false,"family":"","comment":""},"18":{"family_comment":"","value":"","family":"","comment":""},"19":{"family_comment":"","value":"","family":"","comment":""},"20":{"family":"12828","family_comment":"","comment":"кредит, путівка, пенсія","value_hidden":false,"value_unclear":false,"value":"107007","comment_unclear":false,"family_unclear":false,"family_hidden":false},"22":[{"country_comment":"","uah_equal":"1975","cur":"100","country":"Португалія","cur_units":"EUR"}]},"general":{"inn":"","addresses":[{"place_city_type":"","place_city_type_hidden":false,"place_hidden":true,"place_city_hidden":true,"place_district_hidden":true,"place_district":"","place_city_unclear":false,"place":"","place_city":"","place_address_hidden":true,"place_address":""}],"last_name":"Баргаміна","full_name":"Баргаміна Наталія Миколаївна","family":[{"inn":"","family_name":"Баргаміна В. О","name_unclear":false,"inn_hidden":true,"name_hidden":true,"relations":"Батьки"},{"inn":"","family_name":"Кравченко Є. В","relations_other":"","name_unclear":false,"inn_hidden":false,"name_hidden":false,"relations":"Дитина"}],"patronymic":"Миколаївна","inn_hidden":true,"name":"Наталія","post":{"post_hidden":false,"office":"Адміністративний місцевий суд","post":"суддя чернігівського окружного адміністративного суду","office_unclear":false,"region_unclear":false,"region":"Чернігівська область","post_unclear":false},"family_raw":"","full_name_suggest":{"input":["Баргаміна Наталія Миколаївна","Наталія Миколаївна Баргаміна","Наталія Баргаміна"],"output":"Баргаміна Наталія Миколаївна"}},"liabilities":{"54":{"sum_comment":"","sum":"14647","sum_foreign_comment":"","sum_foreign":"","sum_unclear":false,"sum_comment_hidden":false},"55":{"sum_comment":"","sum_foreign_comment":"","sum_foreign":"","sum":""},"56":{"sum_comment":"","sum_foreign_comment":"","sum_foreign":"","sum_unclear":false,"sum":""},"57":{"sum_comment_unclear":false,"sum_comment":"Креді Агріколь Банк","sum":"27604","sum_foreign_comment":"","sum_foreign":"","sum_unclear":false,"sum_comment_hidden":false},"58":{"sum_comment":"","sum":"946","sum_foreign_comment":"","sum_foreign":"","sum_unclear":false,"sum_comment_hidden":false},"59":{"sum_comment":"","sum_foreign_comment":"","sum_foreign":"","sum":""},"60":{"sum_comment":"","sum_foreign_comment":"","sum_foreign":"","sum":"","sum_comment_hidden":false},"61":{"sum_comment":"","sum_foreign_comment":"","sum_foreign":"","sum":""},"62":{"sum_comment":"","sum_foreign_comment":"","sum_foreign":"","sum_unclear":false,"sum":""},"63":{"sum_comment":"","sum_foreign_comment":"","sum_foreign":"","sum":"","sum_comment_hidden":false},"64":{"sum_comment":"","sum_foreign_comment":"","sum_foreign":"","sum":"","sum_comment_hidden":false}},"declaration":{"notfull_lostpages":"","additional_info_text":"","additional_info":"","date":"2015-03-31T00:00:00","notfull":"","url":"http://static.declarations.com.ua/declarations/chosen_ones/judges_batch/4461_barhamina_nataliia_mykolaivna.pdf"},"intro":{"declaration_year":"2014"}}