{"id":"vulyk_101_3","declaration":{"notfull_lostpages":"","additional_info_text":"","additional_info":"","date":"2016-03-25T00:00:00","notfull":"","url":"http://static.declarations.com.ua/declarations/chosen_ones/judges_batch/662_tsiselskyi_oleh_volodymyrovych_2015.pdf"},"estate":{"31":[{"costs_property_comment":"","address":"м. Одеса","space_units":"м²","space_hidden":false,"space_unclear":true,"region_hidden":false,"costs_property":"","space_comment":"","address_hidden":false,"costs_rent_comment_unclear":false,"costs_rent_comment":"","space":"147.1","region":"Одеська область","costs_rent":""}],"33":[{"costs_property_comment":"","address":"м. Одеса","space_units":"м²","costs_rent_comment":"","space":"18","region":"Одеська область","region_hidden":true,"costs_property":"","space_comment":"","address_hidden":true,"costs_rent":""}]},"vehicle":{"35":[{"sum_comment":"","brand_info_hidden":false,"sum_rent":"","sum":"","brand_unclear":false,"year":"2007","brand":"Honda Accord","brand_info":"2000 куб. см.","sum_rent_comment":"","brand_info_unclear":false,"sum_rent_unclear":false},{"sum_comment":"","brand_info":"1300 куб. см.","sum":"","sum_rent_comment":"","year":"1977","brand":"ВАЗ Жигули 21011","sum_rent":"","brand_info_unclear":false}],"40":[{"sum_comment":"","brand_info_hidden":false,"brand_info":"3700 куб. см.","sum":"","sum_rent_comment":"","brand_hidden":false,"brand":"Acura MDX","sum_rent":"","brand_info_unclear":false,"year":"2008"}]},"source":"VULYK","income":{"5":{"family_comment":"","value":"210627","family":"961658","comment":"","value_unclear":false},"6":{"family_comment":"","family":"12458","comment":"","value_unclear":false,"family_hidden":false,"value":"198447"},"7":{"family_comment":"","comment":"","family":"","source_name_unclear":false,"value":"","source_name":""},"8":{"family_comment":"","value":"","family":"","comment":""},"9":{"family_comment":"","value":"","family":"","comment":""},"10":{"family_comment":"","value":"12180","family":"","comment":""},"11":{"family_comment":"","comment_unclear":false,"value":"","family":"","comment":""},"12":{"family_comment":"","value":"","family":"","comment":""},"13":{"family_comment":"","value":"","family":"","comment":""},"14":{"family_comment":"","value":"","family":"","comment":""},"15":{"family_comment":"","value":"","family":"","comment":""},"16":{"family_comment":"","value":"","family":"","comment":""},"17":{"family_comment":"","value":"","family":"948200","comment":""},"18":{"family_comment":"","value":"","family":"","comment":""},"19":{"family_comment":"","value":"","family":"","comment":""},"20":{"family_comment":"","family":"1000","comment":"","value_unclear":false,"family_unclear":false,"comment_unclear":false,"value":""}},"banks":{"51":[{"sum_units":"UAH","sum_comment":"","sum_foreign_units":"UAH","sum_hidden":false,"sum":"815","sum_foreign_comment":"","sum_foreign":"","sum_unclear":false,"sum_comment_hidden":true}],"53":[{"sum_units":"UAH","sum_comment":"","sum_foreign_units":"UAH","sum":"11000","sum_foreign_comment":"","sum_foreign":"","sum_comment_hidden":false}]},"ft_src":"Honda Accord\n2000 куб. см.\n2007\n1300 куб. см.\n1977\nВАЗ Жигули 21011\n3700 куб. см.\nAcura MDX\n2008\n11000\n815\n2015\nHonda Accord\n2000 куб. см.\n2007\n1300 куб. см.\n1977\nВАЗ Жигули 21011\n3700 куб. см.\n2008\nAcura MDX\n11000\n815\n2015\nПодружжя\nЦісельська О. Е\nДитина\nЦісельська В. О\nДитина\nЦісельський Г. О\nЦісельський Олег Володимирович\nОлег Володимирович Цісельський\nОлег Цісельський\nЦісельський Олег Володимирович\nОлег\nЦісельський Олег Володимирович\nВолодимирович\nГосподарський місцевий суд\nсуддя господарського суду одеської області\nОдеська область\nЦісельський\n5661\n56350\n1620\n4270\n63651\n5067\n198447\n12458\n948200\n1000\n210627\n961658\n12180\n18\nм. Одеса\nОдеська область\n147.1\nОдеська область\nм. Одеса\n5661\n56350\n1620\n4270\n63651\n5067\nм. Одеса\nОдеська область\n147.1\nОдеська область\nм. Одеса\n18\nЦісельська О. Е\nПодружжя\nЦісельська В. О\nДитина\nЦісельський Г. О\nДитина\nОлег\nВолодимирович\nЦісельський\nЦісельський Олег Володимирович\nОлег Володимирович Цісельський\nОлег Цісельський\nЦісельський Олег Володимирович\nсуддя господарського суду одеської області\nГосподарський місцевий суд\nОдеська область\nЦісельський Олег Володимирович\n12458\n198447\n12180\n961658\n210627\n948200\n1000","general":{"family":[{"inn":"","family_name":"Цісельська О. Е","relations_other":"","name_unclear":true,"inn_hidden":true,"name_hidden":true,"relations":"Подружжя"},{"inn":"","family_name":"Цісельська В. О","relations_other":"","relations_unclear":false,"name_unclear":true,"inn_hidden":true,"name_hidden":false,"relations":"Дитина"},{"inn":"","family_name":"Цісельський Г. О","relations_other":"","name_unclear":true,"inn_hidden":false,"name_hidden":false,"relations":"Дитина"}],"family_raw":"","name":"Олег","full_name_suggest":{"input":["Цісельський Олег Володимирович","Олег Володимирович Цісельський","Олег Цісельський"],"output":"Цісельський Олег Володимирович"},"patronymic":"Володимирович","inn_hidden":true,"addresses":[{"place_city_type_hidden":false,"place_city_type":"","place_city_hidden":true,"place_hidden":true,"place_district":"","place_district_hidden":false,"place":"","place_address":"","place_address_hidden":true,"place_city":""}],"patronymic_hidden":false,"inn":"","inn_unclear":false,"last_name":"Цісельський","full_name":"Цісельський Олег Володимирович","post":{"office":"Господарський місцевий суд","region_unclear":false,"post":"суддя господарського суду одеської області","region":"Одеська область","office_unclear":false}},"liabilities":{"54":{"sum_comment_unclear":false,"sum_comment":"","sum_hidden":false,"sum":"1620","sum_foreign_comment":"","sum_foreign":"","sum_unclear":false,"sum_comment_hidden":false},"55":{"sum_comment":"","sum_foreign_comment":"","sum_foreign":"","sum":""},"56":{"sum_comment":"","sum":"","sum_foreign_comment":"","sum_foreign":"","sum_unclear":false,"sum_comment_hidden":false},"57":{"sum_comment":"","sum_hidden":false,"sum":"56350","sum_foreign_comment":"","sum_foreign":"","sum_unclear":false,"sum_comment_hidden":true},"58":{"sum_comment_unclear":false,"sum_comment":"","sum_hidden":false,"sum":"5661","sum_foreign_comment":"","sum_foreign":"","sum_unclear":false,"sum_comment_hidden":true},"59":{"sum_comment":"","sum_foreign_comment":"","sum_foreign":"","sum":""},"60":{"sum_comment":"","sum_hidden":false,"sum":"4270","sum_foreign_comment":"","sum_foreign":"","sum_unclear":false,"sum_comment_hidden":false},"61":{"sum_comment":"","sum_foreign_comment":"","sum_foreign":"","sum":""},"62":{"sum_comment":"","sum_comment_unclear":false,"sum_foreign_comment":"","sum":"","sum_foreign":""},"63":{"sum_comment":"","sum_foreign_comment":"","sum_foreign":"","sum":"63651","sum_comment_hidden":true},"64":{"sum_comment":"","sum_foreign_comment":"","sum_foreign":"","sum":"5067","sum_comment_hidden":true}},"intro":{"declaration_year":"2015"}}