{"income":{"5":{"value":"211022","family_comment":"","value_unclear":false,"family_unclear":false,"family":"900104","comment":""},"6":{"family_comment":"","value":"211022","value_unclear":false,"family":"","comment":""},"7":{"value":"","value_unclear":false,"family_comment":"","source_name":"","family":"","comment":""},"8":{"family_comment":"","value":"","family":"","comment":""},"9":{"value":"","family_comment":"","value_unclear":false,"family_unclear":false,"family":"","comment":""},"10":{"family_comment":"","value":"","comment_unclear":false,"family":"","comment":""},"11":{"family_comment":"","value":"","family":"","comment":""},"12":{"family_comment":"","value":"","family":"","comment":""},"13":{"family_comment":"","value":"","value_unclear":false,"family":"","comment":""},"14":{"family_comment":"","value":"","family":"","comment":""},"15":{"family_comment":"","value":"","family":"","comment":""},"16":{"family_comment":"","family_unclear":false,"value":"","family":"","comment":""},"17":{"family_comment":"","family_unclear":false,"value":"","family":"900104","comment":""},"18":{"family_comment":"","value":"","family":"","comment":""},"19":{"family_comment":"","value":"","family":"","comment":""},"20":{"value":"","family_comment":"","value_unclear":false,"family_hidden":false,"value_hidden":false,"family_unclear":false,"comment_unclear":false,"comment":"","family":""}},"id":"vulyk_100_41","declaration":{"additional_info_text":"","notfull_lostpages":"","date":"2015-03-27T00:00:00","notfull":"","additional_info":"","url":"http://static.declarations.com.ua/declarations/chosen_ones/judges_batch/4209_iukhymuk_ruslan_stepanovych.pdf"},"liabilities":{"54":{"sum_foreign_comment":"","sum":"","sum_comment":"","sum_comment_hidden":false,"sum_unclear":false,"sum_foreign":""},"55":{"sum_foreign_comment":"","sum":"","sum_comment":"","sum_foreign":""},"56":{"sum_foreign_comment":"","sum":"","sum_comment":"","sum_unclear":false,"sum_foreign":""},"57":{"sum_foreign_comment":"","sum":"","sum_comment":"","sum_comment_unclear":false,"sum_comment_hidden":false,"sum_unclear":false,"sum_foreign":""},"58":{"sum_foreign_comment":"","sum":"","sum_comment":"","sum_comment_hidden":false,"sum_unclear":false,"sum_foreign":""},"59":{"sum_foreign_comment":"","sum":"","sum_comment":"","sum_foreign":""},"60":{"sum_foreign_comment":"","sum_comment_hidden":false,"sum":"","sum_comment":"","sum_foreign":""},"61":{"sum_foreign_comment":"","sum":"","sum_comment":"","sum_foreign":""},"62":{"sum_foreign_comment":"","sum":"","sum_comment":"","sum_unclear":false,"sum_foreign":""},"63":{"sum_foreign_comment":"","sum_comment_hidden":false,"sum":"","sum_comment":"","sum_foreign":""},"64":{"sum_foreign_comment":"","sum_comment_hidden":false,"sum":"","sum_comment":"","sum_foreign":""}},"ft_src":"Кремінна\n92900\nЛуганська область\nЮхимук Руслан Степанович\nсуддя сєвєродонецького міського суду луганської області\nЛуганська область\nЗагальний місцевий суд\nРуслан\nЮхимук Т. В\nПодружжя\nЮхимук В. Р\nДитина\nЮхимук М. Р\nДитина\nЮхимук Руслан Степанович\nРуслан Степанович Юхимук\nРуслан Юхимук\nЮхимук Руслан Степанович\nЮхимук\nСтепанович\n211022\n900104\n900104\n211022\nв оренді\nЛуганська область\nм. Сєвєродонецьк\n73.1\nв оренді\nЛуганська область\nм. Кремінна\n684\nЛуганська область\nв оренді\nм. Кремінна\n69\nЛуганська область\nв оренді\nм. Кремінна\n1089\nЛуганська область\nу власності\nм. Кремінна\n.2\nу власності\nЛуганська область\nм. Кремінна\n60.3\nЛуганська область\nу власності\nм. Кремінна\n51.4\nЛуганська область\nу власності\nм. Кремінна\n293.5\nЛуганська область\nу власності\nм. Сєвєродонецьк\n73.1\nЛуганська область\nу власності\nм. Кремінна\n236.6\nЛуганська область\nу власності\nм. Кремінна\n85.3\n2014\n211022\n900104\n211022\n900104\n211022\n900104\n211022\n900104\nПодружжя\nЮхимук Т. В\nДитина\nЮхимук В. Р\nДитина\nЮхимук М. Р\nСтепанович\nЛуганська область\n92900\nКремінна\nЮхимук\nЮхимук Руслан Степанович\nРуслан Степанович Юхимук\nРуслан Юхимук\nЮхимук Руслан Степанович\nЮхимук Руслан Степанович\nРуслан\nЗагальний місцевий суд\nЛуганська область\nсуддя сєвєродонецького міського суду луганської області\nв оренді\nм. Сєвєродонецьк\n73.1\nЛуганська область\nв оренді\nЛуганська область\nм. Кремінна\n684\n69\nв оренді\nм. Кремінна\nЛуганська область\n1089\nв оренді\nЛуганська область\nм. Кремінна\n.2\nу власності\nЛуганська область\nм. Кремінна\n293.5\nу власності\nЛуганська область\nм. Кремінна\n60.3\nу власності\nЛуганська область\nм. Кремінна\nм. Кремінна\n51.4\nу власності\nЛуганська область\n73.1\nу власності\nЛуганська область\nм. Сєвєродонецьк\n236.6\nу власності\nЛуганська область\nм. Кремінна\n85.3\nу власності\nЛуганська область\nм. Кремінна\n2014\nЮхимук Т. В\nПодружжя\nДитина\nЮхимук В. Р\nДитина\nЮхимук М. Р\n92900\nКремінна\nЛуганська область\nСтепанович\nЮхимук\nЛуганська область\nЗагальний місцевий суд\nсуддя сєвєродонецького міського суду луганської області\nЮхимук Руслан Степанович\nЮхимук Руслан Степанович\nРуслан Степанович Юхимук\nРуслан Юхимук\nЮхимук Руслан Степанович\nРуслан\nу власності\nм. Кремінна\nЛуганська область\n60.3\nу власності\nм. Кремінна\nЛуганська область\n51.4\nу власності\nм. Кремінна\nЛуганська область\n293.5\nу власності\nм. Сєвєродонецьк\nЛуганська область\n73.1\nу власності\nм. Кремінна\nЛуганська область\n236.6\nу власності\nм. Кремінна\nЛуганська область\n85.3\nв оренді\nм. Сєвєродонецьк\nЛуганська область\n73.1\nв оренді\nм. Кремінна\nЛуганська область\n684\nв оренді\nм. Кремінна\nЛуганська область\n69\nв оренді\nм. Кремінна\nЛуганська область\n1089\nу власності\nм. Кремінна\nЛуганська область\n.2\n2014","general":{"inn":"","inn_hidden":true,"last_name":"Юхимук","post":{"post_unclear":false,"region_unclear":false,"post":"суддя сєвєродонецького міського суду луганської області","office":"Загальний місцевий суд","region":"Луганська область","post_hidden":false,"office_unclear":false},"name":"Руслан","full_name":"Юхимук Руслан Степанович","family_raw":"","addresses":[{"place_district":"","place_city_hidden":false,"place_city":"Кремінна","place_city_unclear":false,"place_district_hidden":false,"place_city_type":"Місто","place_address_hidden":true,"place_city_type_hidden":false,"place_address":"92900","place_hidden":false,"place":"Луганська область"}],"family":[{"inn_hidden":true,"inn":"","name_hidden":true,"family_name":"Юхимук Т. В","relations":"Подружжя","name_unclear":false},{"inn":"","relations":"Дитина","relations_other":"","inn_hidden":false,"family_name":"Юхимук В. Р","name_hidden":false,"name_unclear":false},{"inn":"","relations":"Дитина","relations_other":"","inn_hidden":false,"family_name":"Юхимук М. Р","name_hidden":false,"name_unclear":false}],"full_name_suggest":{"output":"Юхимук Руслан Степанович","input":["Юхимук Руслан Степанович","Руслан Степанович Юхимук","Руслан Юхимук"]},"patronymic":"Степанович"},"source":"VULYK","estate":{"29":[{"region_unclear":false,"space_unclear":false,"address_hidden":false,"region_hidden":false,"space_comment":"в оренді","space":"73.1","address":"м. Сєвєродонецьк","region":"Луганська область","costs_property":"","costs_rent_comment":"","address_unclear":false,"space_units":"м²","costs_property_comment":"","costs_rent":""},{"space_unclear":false,"address_hidden":true,"region_hidden":false,"space_comment":"в оренді","space":"684","address":"м. Кремінна","region":"Луганська область","costs_property":"","costs_rent_comment":"","space_units":"м²","costs_property_comment":"","costs_rent":""},{"costs_rent":"","region_unclear":true,"region":"Луганська область","costs_property":"","costs_rent_comment":"","space_comment":"в оренді","costs_property_comment":"","space_units":"м²","space":"69","address":"м. Кремінна"},{"costs_rent":"","region":"Луганська область","costs_property":"","costs_rent_comment":"","space_comment":"в оренді","costs_property_comment":"","space_units":"м²","space":"1089","address":"м. Кремінна"},{"costs_rent":"","region":"Луганська область","costs_property":"","costs_rent_comment":"","space_comment":"у власності","costs_property_comment":"","space_units":"га","space":".2","address":"м. Кремінна"}],"30":[{"costs_rent":"","region":"Луганська область","costs_property":"","costs_rent_comment":"","address_hidden":true,"region_hidden":false,"space_comment":"у власності","costs_property_comment":"","space_units":"м²","space":"293.5","address":"м. Кремінна"}],"31":[{"region_unclear":false,"space_unclear":false,"costs_property_comment_unclear":false,"address_hidden":true,"region_hidden":false,"space_comment":"у власності","space":"60.3","address":"м. Кремінна","region":"Луганська область","costs_property":"","costs_rent_comment":"","space_comment_unclear":false,"address_unclear":false,"space_units":"м²","costs_property_comment":"","costs_rent":""},{"costs_rent":"","region_unclear":false,"region":"Луганська область","costs_property":"","costs_rent_comment":"","region_hidden":false,"space_comment":"у власності","costs_property_comment":"","space_units":"м²","space":"51.4","address":"м. Кремінна"}],"34":[{"costs_rent":"","region":"Луганська область","costs_property":"","costs_rent_comment":"","address_hidden":true,"region_hidden":false,"space_comment":"у власності","costs_property_comment":"","space_units":"м²","space":"73.1","address":"м. Сєвєродонецьк"},{"costs_rent":"","region":"Луганська область","costs_property":"","costs_rent_comment":"","space_comment":"у власності","costs_property_comment":"","space_units":"м²","space":"236.6","address":"м. Кремінна"},{"costs_rent":"","region":"Луганська область","costs_property":"","costs_rent_comment":"","space_comment":"у власності","costs_property_comment":"","space_units":"м²","space":"85.3","address":"м. Кремінна"}]},"intro":{"declaration_year":"2014"}}