{"income":{"5":{"value":"199041","family_unclear":false,"family_hidden":false,"family_comment":"","family":"148122","comment":""},"6":{"family_comment":"","value":"198744","family_hidden":false,"comment":"","family":"11250"},"7":{"family_comment":"","value":"","source_name":"","family":"","comment":""},"8":{"family_comment":"","value":"","family":"","comment":""},"9":{"value":"","comment_unclear":false,"family_hidden":false,"family_comment":"","family":"","comment":""},"10":{"family_comment":"","value":"","family":"","comment":""},"11":{"family_comment":"","value":"","family":"","comment":""},"12":{"family_comment":"","value":"","family":"","comment":""},"13":{"family_comment":"","value":"","family":"","comment":""},"14":{"family_comment":"","value":"","family":"","comment":""},"15":{"family_comment":"","value":"","value_unclear":false,"family":"","comment":""},"16":{"family_comment":"","value":"","family":"120000","comment":""},"17":{"family_comment":"","value":"","family":"","comment":""},"18":{"family_comment":"","value":"","family":"","comment":""},"19":{"family_comment":"","value":"","family":"","comment":""},"20":{"value":"297","comment_unclear":false,"comment_hidden":false,"family_hidden":false,"value_hidden":false,"family_comment":"","value_unclear":false,"family":"16872","comment":"","family_comment_hidden":false}},"vehicle":{"35":[{"brand_info":"1600 куб. см.","sum_rent_comment":"","brand":"Nissan TIIDA","sum_comment":"","year":"2013","brand_info_hidden":false,"sum":"224500","sum_rent":""}]},"id":"vulyk_41_63","banks":{"45":[{"sum_foreign_comment":"","sum_units":"UAH","sum_comment":"","sum_foreign_unclear":false,"sum_foreign_units":"UAH","sum_hidden":false,"sum_comment_hidden":false,"sum":"","sum_foreign":""},{"sum_foreign_comment":"","sum_units":"","sum_comment":"","sum_foreign_unclear":false,"sum_foreign_units":"","sum":"","sum_foreign":""}],"46":[{"sum_foreign_comment":"","sum_units":"UAH","sum_comment":"","sum_foreign_units":"UAH","sum_comment_hidden":false,"sum_unclear":false,"sum":"","sum_foreign":""},{"sum_foreign_comment":"","sum_units":"","sum_comment":"","sum_foreign_units":"","sum":"","sum_unclear":false,"sum_foreign":""}],"47":[{"sum_foreign_comment":"","sum_units":"UAH","sum_comment":"","sum_foreign_units":"UAH","sum":"","sum_foreign":""},{"sum_foreign_comment":"","sum_units":"","sum_comment":"","sum_foreign_units":"","sum":"","sum_foreign":""}],"48":[{"sum_foreign_comment":"","sum_units":"UAH","sum_comment":"","sum_foreign_units":"UAH","sum":"","sum_foreign":""}],"49":[{"sum_foreign_comment":"","sum_units":"UAH","sum_comment":"","sum_foreign_units":"UAH","sum":"","sum_foreign":""}],"50":[{"sum_foreign_comment":"","sum_units":"UAH","sum_comment":"","sum_foreign_units":"UAH","sum":"","sum_foreign":""}],"51":[{"sum_foreign_comment":"","sum_units":"UAH","sum_comment":"","sum_hidden":false,"sum_foreign_units":"UAH","sum_comment_hidden":false,"sum_unclear":false,"sum":"282","sum_foreign":""},{"sum_foreign_comment":"","sum_units":"","sum_comment":"","sum_foreign_units":"","sum":"","sum_foreign":""}],"52":[{"sum_foreign_comment":"","sum_units":"UAH","sum_comment":"","sum_foreign_units":"UAH","sum_comment_hidden":false,"sum_unclear":false,"sum":"","sum_foreign":""}],"53":[{"sum_foreign_comment":"","sum_units":"UAH","sum_comment":"","sum_foreign_units":"UAH","sum_comment_hidden":true,"sum":"1500","sum_foreign":""},{"sum_foreign_comment":"","sum_units":"","sum_comment":"","sum_foreign_units":"","sum":"","sum_foreign":""},{"sum_foreign_comment":"","sum_units":"","sum_comment":"","sum_foreign_units":"","sum":"","sum_foreign":""}]},"declaration":{"date":"2015-03-19T00:00:00","additional_info_text":"","additional_info":"","url":"http://static.declarations.com.ua/declarations/chosen_ones/mega_batch/zlatin_stanislav_viktorovych.pdf"},"liabilities":{"54":{"sum_foreign_comment":"","sum_comment_hidden":false,"sum":"","sum_comment":"","sum_foreign":""},"55":{"sum_foreign_comment":"","sum":"","sum_comment":"","sum_foreign":""},"56":{"sum_foreign_comment":"","sum":"","sum_hidden":false,"sum_comment":"","sum_foreign":""},"57":{"sum_foreign_comment":"","sum":"","sum_comment":"","sum_comment_hidden":false,"sum_unclear":false,"sum_foreign":""},"58":{"sum_foreign_comment":"","sum_comment_hidden":false,"sum":"","sum_comment":"","sum_foreign":""},"59":{"sum_foreign_comment":"","sum":"","sum_comment":"","sum_foreign":""},"60":{"sum_foreign_comment":"","sum_comment_hidden":false,"sum":"","sum_comment":"","sum_foreign":""},"61":{"sum_foreign_comment":"","sum":"","sum_comment":"","sum_foreign":""},"62":{"sum_foreign_comment":"","sum":"","sum_comment":"","sum_foreign":""},"63":{"sum_foreign_comment":"","sum":"34645","sum_comment":"сумами 31641 та 3004","sum_comment_hidden":true,"sum_unclear":true,"sum_foreign":""},"64":{"sum_foreign_comment":"","sum_comment_hidden":true,"sum":"2028","sum_comment":"","sum_foreign":""}},"ft_src":"2028\nсумами 31641 та 3004\n34645\nсуддя дніпропетровського окружного адміністративного суду\nДніпропетровська область\nАдміністративний місцевий суд\nСтаніслав\nГерман М. М\nПодружжя\nГерман А. Л\nДитина\nЗлатіна К. С\nДитина\nВікторович\nЗлатін Станіслав Вікторович\nСтаніслав Вікторович Златін\nСтаніслав Златін\nЗлатін Станіслав Вікторович\nЗлатін\nЗлатін Станіслав Вікторович\nДніпропетровськ\nДніпропетровська область\n1600 куб. см.\n224500\n2013\nNissan TIIDA\n282\n1500\n2014\nNissan TIIDA\n1600 куб. см.\n2013\n224500\n282\n1500\n502\nВінницька область\n13.03\nм. Вінниця\nВінницька область\n58\nВінницька область\nм. Вінниця\n17\nм. Дніпропетровськ\nДніпропетровська область\n9.9\nВінницька область\nПодружжя\nГерман М. М\nДитина\nГерман А. Л\nДитина\nЗлатіна К. С\nЗлатін Станіслав Вікторович\nСтаніслав Вікторович Златін\nСтаніслав Златін\nЗлатін Станіслав Вікторович\nЗлатін Станіслав Вікторович\nСтаніслав\nВікторович\nАдміністративний місцевий суд\nсуддя дніпропетровського окружного адміністративного суду\nДніпропетровська область\nЗлатін\nДніпропетровська область\nДніпропетровськ\n34645\nсумами 31641 та 3004\n2028\n198744\n11250\n297\n16872\n199041\n148122\n120000\n2014\n2028\nсумами 31641 та 3004\n34645\nВінницька область\n502\nм. Вінниця\nВінницька область\n13.03\nВінницька область\nм. Вінниця\n58\nВінницька область\n9.9\nм. Дніпропетровськ\n17\nДніпропетровська область\nГерман М. М\nПодружжя\nГерман А. Л\nДитина\nЗлатіна К. С\nДитина\nВікторович\nЗлатін\nСтаніслав\nЗлатін Станіслав Вікторович\nСтаніслав Вікторович Златін\nСтаніслав Златін\nЗлатін Станіслав Вікторович\nДніпропетровська область\nДніпропетровськ\nДніпропетровська область\nсуддя дніпропетровського окружного адміністративного суду\nАдміністративний місцевий суд\nЗлатін Станіслав Вікторович\n11250\n198744\n148122\n199041\n120000\n16872\n297\n224500\nNissan TIIDA\n1600 куб. см.\n2013\n297\n16872\n199041\n148122\n120000\n11250\n198744\nм. Вінниця\nВінницька область\n13.03\nм. Вінниця\nВінницька область\n58\nВінницька область\n502\nм. Дніпропетровськ\nДніпропетровська область\n17\nВінницька область\n9.9\n282\n1500\n2014","general":{"inn":"","name":"Станіслав","family":[{"inn":"","relations":"Подружжя","relations_hidden":false,"inn_hidden":false,"family_name":"Герман М. М","name_hidden":true,"name_unclear":false},{"inn":"","relations":"Дитина","relations_other":"","inn_hidden":false,"family_name":"Герман А. Л","name_hidden":true,"name_unclear":true},{"inn":"","relations":"Дитина","relations_other":"","inn_hidden":false,"family_name":"Златіна К. С","name_hidden":false,"name_unclear":true}],"patronymic":"Вікторович","inn_hidden":true,"family_raw":"","last_name":"Златін","post":{"post_unclear":false,"post":"суддя дніпропетровського окружного адміністративного суду","post_hidden":false,"region":"Дніпропетровська область","region_hidden":false,"office":"Адміністративний місцевий суд","office_hidden":false},"last_name_unclear":false,"full_name":"Златін Станіслав Вікторович","addresses":[{"place_district":"","place_city_hidden":false,"place_city":"Дніпропетровськ","place_city_type_hidden":false,"place_district_hidden":false,"place_city_type":"Місто","place_address_hidden":true,"place_address":"","place_hidden":true,"place":"Дніпропетровська область"}],"patronymic_hidden":false,"full_name_suggest":{"output":"Златін Станіслав Вікторович","input":["Златін Станіслав Вікторович","Станіслав Вікторович Златін","Станіслав Златін"]},"name_unclear":false},"source":"VULYK","estate":{"23":[{"region_unclear":false,"space_unclear":false,"costs":"","costs_comment":"","address_hidden":false,"region_hidden":false,"space_comment":"","space":"","address":"","costs_comment_unclear":false,"region":"","space_units_unclear":false,"space_comment_hidden":false,"space_units":"м²","costs_rent":"","costs_rent_comment":""},{"costs_rent":"","space_unclear":false,"region":"","costs":"","costs_rent_comment":"","costs_comment":"","space_comment":"","space_units":"","space":"","address":""},{"costs_rent":"","region":"","costs":"","costs_rent_comment":"","costs_comment":"","space_comment":"","space_units":"","space":"","address":""}],"25":[{"region_unclear":false,"space_hidden":false,"costs":"","costs_comment":"","address_hidden":true,"region_hidden":false,"space_comment":"","space_unclear":false,"space":"17","address":"м. Дніпропетровськ","costs_comment_unclear":false,"region":"Дніпропетровська область","costs_rent_comment":"","costs_unclear":false,"space_units":"м²","costs_rent":""}],"29":[{"space_unclear":false,"costs_property_comment":"","address_hidden":false,"region_hidden":true,"space_comment":"","space":"502","address":"","region":"Вінницька область","costs_property":"","costs_rent_comment":"","space_units":"м²","space_units_unclear":false,"costs_rent":""}],"31":[{"space_hidden":false,"address_hidden":true,"region_hidden":false,"space_comment":"","space":"13.03","address":"м. Вінниця","region":"Вінницька область","costs_property":"","costs_rent_comment":"","space_comment_unclear":false,"space_units":"м²","costs_property_comment":"","costs_rent":""},{"costs_rent":"","region":"Вінницька область","costs_property":"","costs_rent_comment":"","space_comment_unclear":false,"space_comment":"","costs_property_comment":"","space_units":"м²","space":"58","address":"м. Вінниця"}],"32":[{"space_unclear":false,"address_hidden":true,"region_hidden":false,"space_comment":"","space":"9.9","address":"","region":"Вінницька область","costs_property":"","costs_rent_comment":"","space_units":"м²","costs_property_comment":"","costs_rent":""}]},"intro":{"declaration_year":"2014"}}