{"income":{"5":{"value":"589455","family_comment":"","value_unclear":false,"family_hidden":false,"family_unclear":false,"family":"","comment":""},"6":{"value":"339455","value_unclear":false,"family_hidden":false,"family_comment":"","family":"","comment":""},"7":{"source_name_unclear":false,"value":"","family_hidden":false,"family_comment":"","source_name":"","family":"","comment":"","source_name_hidden":false},"8":{"family_comment":"","value":"","family":"","comment":""},"9":{"family_comment":"","family_unclear":false,"value":"","family":"","comment":""},"10":{"family_comment":"","value":"","family":"","comment":""},"11":{"family_comment":"","value":"","comment_unclear":false,"family":"","comment":""},"12":{"family_comment":"","value":"","family":"","comment":""},"13":{"family_comment":"","value":"","family":"","comment":""},"14":{"family_comment":"","value":"","family":"","comment":""},"15":{"family_comment":"","value":"","family":"","comment":""},"16":{"family_comment":"","value":"","family":"","comment":""},"17":{"family_comment":"","value":"","family":"","comment":"","family_comment_unclear":false},"18":{"family_comment":"","value":"","family":"","comment":""},"19":{"family_comment":"","value":"","comment_unclear":false,"family":"","comment":""},"20":{"value":"250000","family_comment":"","comment_unclear":false,"comment_hidden":false,"family_unclear":false,"family":"","comment":""}},"vehicle":{"35":[{"brand_info":"1997 куб. см.","sum_rent_comment":"","year":"2014","brand_info_hidden":false,"year_unclear":false,"sum_rent":"","sum":"339090","brand":"Ford Mondeo","sum_comment":"","sum_comment_unclear":false,"sum_unclear":false,"brand_unclear":false}]},"id":"vulyk_8_166","banks":{"45":[{"sum_foreign_comment":"","sum_units":"UAH","sum_comment":"","sum_foreign_unclear":false,"sum_foreign_units":"UAH","sum_hidden":false,"sum_comment_hidden":false,"sum_unclear":false,"sum":"","sum_foreign":""},{"sum_foreign_comment":"","sum_units":"","sum_comment":"","sum_hidden":false,"sum_foreign_units":"","sum":"","sum_unclear":false,"sum_foreign":""},{"sum_foreign_comment":"","sum_units":"","sum_comment":"","sum_foreign_units":"","sum":"","sum_unclear":false,"sum_foreign":""},{"sum_foreign_comment":"","sum_units":"","sum_comment":"","sum_foreign_units":"","sum":"","sum_foreign":""}],"46":[{"sum_foreign_comment":"","sum_units":"UAH","sum_comment":"","sum_foreign_comment_hidden":false,"sum_hidden":false,"sum_foreign_units":"UAH","sum_foreign_hidden":false,"sum_comment_hidden":false,"sum_unclear":false,"sum":"","sum_foreign":""}],"47":[{"sum_foreign_comment":"","sum_units":"UAH","sum_comment":"","sum_foreign_units":"UAH","sum_comment_hidden":false,"sum":"","sum_foreign":""}],"48":[{"sum_foreign_comment":"","sum_units":"UAH","sum_comment":"","sum_foreign_units":"UAH","sum":"","sum_foreign":""}],"49":[{"sum_foreign_comment":"","sum_units":"UAH","sum_comment":"","sum_foreign_units":"UAH","sum":"","sum_foreign":""}],"50":[{"sum_foreign_comment":"","sum_units":"UAH","sum_comment":"","sum_foreign_units":"UAH","sum":"","sum_foreign":""}],"51":[{"sum_foreign_comment":"","sum_units":"UAH","sum_comment":"","sum_comment_unclear":false,"sum_hidden":false,"sum_foreign_units":"UAH","sum_comment_hidden":false,"sum_unclear":false,"sum":"","sum_foreign":""},{"sum_foreign_comment":"","sum_units":"","sum_comment":"","sum_hidden":false,"sum_foreign_units":"","sum":"","sum_foreign":""}],"52":[{"sum_foreign_comment":"","sum_units":"UAH","sum_comment":"","sum_comment_unclear":false,"sum_hidden":false,"sum_foreign_units":"UAH","sum_comment_hidden":false,"sum_unclear":false,"sum":"","sum_foreign":""}],"53":[{"sum_foreign_comment":"","sum_units":"UAH","sum_comment":"","sum_foreign_units":"UAH","sum_comment_hidden":false,"sum":"","sum_foreign":""}]},"declaration":{"additional_info_text":"","notfull_lostpages":"","date":"2015-03-25T00:00:00","notfull":"","additional_info":"","url":"http://static.declarations.com.ua/declarations/chosen_ones/batch_16/vilhushynskyi_mykhailo_iosypovych.pdf"},"liabilities":{"54":{"sum_foreign_comment":"","sum_foreign_hidden":false,"sum_comment":"","sum_hidden":false,"sum_comment_hidden":false,"sum":"","sum_foreign":""},"55":{"sum_foreign_comment":"","sum":"","sum_comment":"","sum_foreign":""},"56":{"sum_foreign_comment":"","sum":"","sum_comment":"","sum_unclear":false,"sum_foreign":""},"57":{"sum_foreign_comment":"","sum_comment_hidden":false,"sum":"25000","sum_comment":"","sum_foreign":""},"58":{"sum_foreign_comment":"","sum":"","sum_comment":"","sum_foreign":""},"59":{"sum_foreign_comment":"","sum":"","sum_comment":"","sum_comment_unclear":false,"sum_foreign":""},"60":{"sum_foreign_comment":"","sum_foreign_hidden":false,"sum_comment":"","sum_hidden":false,"sum_comment_hidden":false,"sum":"","sum_foreign":""},"61":{"sum_foreign_comment":"","sum":"","sum_comment":"","sum_foreign":""},"62":{"sum_foreign_comment":"","sum":"","sum_comment":"","sum_foreign":""},"63":{"sum_foreign_comment":"","sum":"","sum_comment":"","sum_foreign":""},"64":{"sum_foreign_comment":"","sum":"","sum_comment":"","sum_foreign":""}},"ft_src":"25000\nсуддя вищого спеціалізованого суду україни з розгляду цивільних і кримінальних справ\nЗагальнодержавний регіон\nВищий спецiалiзований суд України з розгляду цивiльних i кримiнальних справ\nМихайло\nЙосипович\nВільгушинський Михайло Йосипович\nМихайло Йосипович Вільгушинський\nМихайло Вільгушинський\nВільгушинський Михайло Йосипович\nВільгушинський Михайло Йосипович\nВільгушинський\n1997 куб. см.\n339090\nFord Mondeo\n2014\n2014\n1997 куб. см.\n339090\nFord Mondeo\n2014\n3000\n90\nрозпочато будівництво\n82\nВільгушинський Михайло Йосипович\nМихайло Йосипович Вільгушинський\nМихайло Вільгушинський\nВільгушинський Михайло Йосипович\nМихайло\nВільгушинський Михайло Йосипович\nВільгушинський\nВищий спецiалiзований суд України з розгляду цивiльних i кримiнальних справ\nсуддя вищого спеціалізованого суду україни з розгляду цивільних і кримінальних справ\nЗагальнодержавний регіон\nЙосипович\n25000\n339455\n250000\n589455\n2014\n25000\n3000\nрозпочато будівництво\n90\n82\nВільгушинський Михайло Йосипович\nМихайло Йосипович Вільгушинський\nМихайло Вільгушинський\nВільгушинський Михайло Йосипович\nЙосипович\nВільгушинський\nМихайло\nЗагальнодержавний регіон\nсуддя вищого спеціалізованого суду україни з розгляду цивільних і кримінальних справ\nВищий спецiалiзований суд України з розгляду цивiльних i кримiнальних справ\nВільгушинський Михайло Йосипович\n339455\n589455\n250000\n2014\nFord Mondeo\n339090\n1997 куб. см.\n250000\n589455\n339455\n82\n3000\nрозпочато будівництво\n90\n2014","general":{"inn":"","name":"Михайло","patronymic_unclear":false,"last_name_hidden":false,"last_name":"Вільгушинський","patronymic":"Йосипович","inn_hidden":true,"family_raw":"","inn_unclear":false,"post":{"post_unclear":false,"post":"суддя вищого спеціалізованого суду україни з розгляду цивільних і кримінальних справ","post_hidden":false,"region":"Загальнодержавний регіон","region_hidden":false,"office":"Вищий спецiалiзований суд України з розгляду цивiльних i кримiнальних справ","office_hidden":false,"office_unclear":false},"full_name":"Вільгушинський Михайло Йосипович","addresses":[{"place_district":"","place_city_hidden":false,"place_city":"","place_city_type_hidden":false,"place_district_hidden":false,"place_city_type":"","place_address_hidden":false,"place_address":"","place_hidden":true,"place":""}],"full_name_suggest":{"output":"Вільгушинський Михайло Йосипович","input":["Вільгушинський Михайло Йосипович","Михайло Йосипович Вільгушинський","Михайло Вільгушинський"]}},"source":"VULYK","estate":{"23":[{"space_unclear":false,"costs":"","costs_comment":"","address_hidden":false,"region_hidden":true,"space_comment":"","space":"3000","address":"","costs_comment_unclear":false,"region":"","address_unclear":false,"costs_rent_comment":"","space_comment_unclear":false,"space_comment_hidden":false,"space_units":"м²","space_units_hidden":false,"costs_rent":""},{"space_unclear":false,"costs":"","costs_comment":"","address_hidden":false,"region_hidden":false,"space_comment":"","space":"","address":"","region":"","costs_rent_comment":"","space_comment_unclear":false,"space_units":"","costs_rent":""},{"space":"","region":"","costs":"","costs_rent_comment":"","costs_comment":"","space_comment":"","space_units_unclear":false,"space_units":"","costs_rent":"","address":""},{"costs_rent":"","region":"","costs":"","costs_rent_comment":"","costs_comment":"","address_hidden":false,"space_comment":"","space_units":"","space":"","address":""}],"24":[{"space_unclear":false,"costs":"","costs_comment":"","address_hidden":false,"region_hidden":true,"space_comment":"розпочато будівництво","space":"90","address":"","region":"","costs_rent_comment":"","costs_unclear":false,"space_units":"м²","costs_rent":""}],"25":[{"region_unclear":false,"space_unclear":false,"costs":"","costs_comment":"","address_hidden":false,"region_hidden":true,"space_comment":"","space":"82","address":"","costs_comment_unclear":false,"region":"","costs_rent_comment":"","space_comment_unclear":false,"space_units":"м²","costs_rent":""}]},"intro":{"declaration_year":"2014","isnotdeclaration":""}}