{"income":{"5":{"family_comment":"","value":"228425","family":"479020","comment":""},"6":{"family_comment":"","value":"213267","family":"472494","comment":""},"7":{"family_comment":"","value":"","source_name":"","family":"","comment":""},"8":{"family_comment":"","value":"","family":"","comment":""},"9":{"value":"","comment_unclear":false,"family_comment":"","family":"6530","comment":"","family_comment_unclear":false},"10":{"family_comment":"","value":"15158","family":"","comment":""},"11":{"family_comment":"","value":"","family":"","comment":""},"12":{"family_comment":"","value":"","family":"","comment":""},"13":{"family_comment":"","value":"","family":"","comment":""},"14":{"family_comment":"","value":"","family":"","comment":""},"15":{"family_comment":"","value":"","family":"","comment":""},"16":{"family_comment":"","value":"","family":"","comment":""},"17":{"family_comment":"","value":"","family":"","comment":""},"18":{"family_comment":"","value":"","family":"","comment":""},"19":{"value":"","family_comment":"","value_unclear":false,"family_unclear":false,"family":"","comment":""},"20":{"value":"","family_comment":"","value_unclear":false,"comment_hidden":false,"family_comment_hidden":false,"family_unclear":false,"family_comment_unclear":false,"comment_unclear":false,"comment":"","family":""}},"vehicle":{"35":[{"brand_info":"1.6, спільна сумісна власність","sum_rent_comment":"","brand":"Renault Scenic","sum_comment":"","year":"2005","sum_hidden":false,"brand_info_hidden":false,"brand_info_unclear":false,"year_unclear":false,"sum":"","sum_rent":""}],"40":[{"year_hidden":false,"brand_info":"1.6, спільна сумісна власність","sum_rent_comment":"","brand":"Renault Scenic","sum_comment":"","year":"2005","brand_hidden":false,"brand_info_hidden":false,"brand_info_unclear":false,"sum":"","sum_rent":""}]},"id":"vulyk_106_58","banks":{"51":[{"sum_foreign_comment":"","sum_units":"UAH","sum_comment":"","sum_comment_unclear":false,"sum_foreign_comment_hidden":false,"sum_foreign_units":"UAH","sum_comment_hidden":false,"sum":"395026","sum_foreign":""}]},"declaration":{"additional_info_text":"","notfull_lostpages":"","date":"2016-03-31T00:00:00","notfull":"","additional_info":"","url":"http://static.declarations.com.ua/declarations/chosen_ones/judges_batch/2197_hrytsiv_vira_mykolaivna.pdf"},"liabilities":{"54":{"sum_foreign_comment":"","sum":"","sum_comment":"","sum_comment_unclear":false,"sum_hidden":false,"sum_comment_hidden":false,"sum_foreign":""},"55":{"sum_foreign_comment":"","sum":"","sum_hidden":false,"sum_comment":"","sum_foreign":""},"56":{"sum_foreign_comment":"","sum":"","sum_comment":"","sum_hidden":false,"sum_comment_hidden":false,"sum_unclear":false,"sum_foreign":""},"57":{"sum_foreign_comment":"","sum":"","sum_comment":"","sum_hidden":false,"sum_comment_hidden":false,"sum_foreign":""},"58":{"sum_foreign_comment":"","sum":"","sum_comment":"","sum_hidden":false,"sum_comment_hidden":false,"sum_foreign":""},"59":{"sum_foreign_comment":"","sum":"","sum_comment":"","sum_foreign":""},"60":{"sum_foreign_comment":"","sum":"","sum_comment":"","sum_hidden":false,"sum_comment_hidden":false,"sum_foreign":""},"61":{"sum_foreign_comment":"","sum":"","sum_comment":"","sum_foreign":""},"62":{"sum_foreign_comment":"","sum":"","sum_comment":"","sum_comment_hidden":false,"sum_unclear":false,"sum_foreign":""},"63":{"sum_foreign_comment":"","sum":"","sum_comment":"","sum_foreign":""},"64":{"sum_foreign_comment":"","sum":"","sum_comment":"","sum_foreign":""}},"ft_src":"суддя львівського апеляційного господарського суду\nЛьвівська область\nАпеляційний господарський суд\nВіра\nГриців М. І\nПодружжя\nГриців Н. М\nДитина\nГриців Г. М\nДитина\nМиколаївна\nГриців Віра Миколаївна\nВіра Миколаївна Гриців\nВіра Гриців\nГриців Віра Миколаївна\nГриців Віра Миколаївна\nГриців\nRenault Scenic\n1.6, спільна сумісна власність\n2005\n1.6, спільна сумісна власність\nRenault Scenic\n2005\n395026\n2015\n1.6, спільна сумісна власність\n2005\nRenault Scenic\n1.6, спільна сумісна власність\n2005\nRenault Scenic\n395026\n42433\n82\n129\n42433\n82\n42373\n129\n42373\nГриців Віра Миколаївна\nВіра Миколаївна Гриців\nВіра Гриців\nГриців Віра Миколаївна\nГриців Віра Миколаївна\nПодружжя\nГриців М. І\nДитина\nГриців Н. М\nДитина\nГриців Г. М\nВіра\nГриців\nЛьвівська область\nАпеляційний господарський суд\nсуддя львівського апеляційного господарського суду\nМиколаївна\n213267\n472494\n228425\n479020\n6530\n15158\n2015\n42433\n82\n42433\n129\n42373\n82\n42373\n129\nГриців М. І\nПодружжя\nГриців Н. М\nДитина\nГриців Г. М\nДитина\nМиколаївна\nГриців\nВіра\nГриців Віра Миколаївна\nВіра Миколаївна Гриців\nВіра Гриців\nГриців Віра Миколаївна\nЛьвівська область\nАпеляційний господарський суд\nсуддя львівського апеляційного господарського суду\nГриців Віра Миколаївна\n472494\n213267\n6530\n15158\n479020\n228425\n2005\nRenault Scenic\n1.6, спільна сумісна власність\nRenault Scenic\n1.6, спільна сумісна власність\n2005\n6530\n15158\n479020\n228425\n472494\n213267\n42433\n82\n42433\n129\n42373\n82\n42373\n129\n395026\n2015","general":{"inn":"","name":"Віра","inn_unclear":false,"family":[{"inn":"","inn_hidden":true,"relations_unclear":false,"relations_hidden":false,"relations_other":"","relations":"Подружжя","name_hidden":true,"family_name":"Гриців М. І","name_unclear":false},{"inn":"","relations":"Дитина","relations_unclear":false,"family_name":"Гриців Н. М","inn_hidden":false,"relations_other":"","name_hidden":false,"name_unclear":false},{"inn_hidden":false,"inn":"","name_hidden":false,"family_name":"Гриців Г. М","relations":"Дитина","name_unclear":false}],"inn_hidden":true,"family_raw":"","last_name":"Гриців","post":{"region_unclear":false,"region":"Львівська область","post":"суддя львівського апеляційного господарського суду","office":"Апеляційний господарський суд","office_unclear":false,"post_hidden":false},"full_name":"Гриців Віра Миколаївна","addresses":[{"place_district":"","place_city_hidden":true,"place_city":"","place_city_type_hidden":true,"place_district_hidden":true,"place_city_type":"","place_address_hidden":true,"place_address":"","place_hidden":true,"place":""}],"patronymic":"Миколаївна","full_name_suggest":{"output":"Гриців Віра Миколаївна","input":["Гриців Віра Миколаївна","Віра Миколаївна Гриців","Віра Гриців"]},"name_unclear":false},"source":"VULYK","estate":{"25":[{"costs":"","costs_comment":"","address_hidden":true,"region_hidden":true,"space_comment":"42373","space":"82","address":"","region":"","costs_rent_comment":"","space_comment_unclear":false,"space_units":"м²","costs_rent":""},{"space_unclear":false,"costs":"","costs_comment":"","address_hidden":false,"region_hidden":false,"space_comment":"42373","space":"129","address":"","region":"","costs_rent_comment":"","space_comment_unclear":false,"space_units":"м²","costs_rent":""}],"31":[{"space_unclear":false,"address_hidden":true,"region_hidden":true,"space_comment":"42433","space_hidden":false,"space":"82","address":"","region":"","costs_property":"","costs_rent_comment":"","space_comment_unclear":false,"space_units":"м²","costs_property_comment":"","costs_rent":""},{"costs_rent":"","region":"","costs_property":"","costs_rent_comment":"","space_comment_unclear":false,"region_hidden":false,"space_comment":"42433","costs_property_comment":"","space_units":"м²","space":"129","address":""}]},"intro":{"declaration_year":"2015","isnotdeclaration":""}}