{"income":{"5":{"family_comment":"","family_unclear":false,"value":"237152","family":"34293","comment":""},"6":{"family_comment":"","family_unclear":false,"value":"223754","family":"30622","comment":""},"7":{"value":"","comment_hidden":false,"family_comment":"","source_name":"","family":"","comment":""},"8":{"family_comment":"","value":"","family":"","comment":""},"9":{"family_comment":"","value":"","family":"","comment":""},"10":{"family_comment":"","value":"13398","family":"3671","comment":""},"11":{"family_comment":"","value":"","value_unclear":false,"family":"","comment":""},"12":{"family_comment":"","value":"","family":"","comment":""},"13":{"family_comment":"","value":"","family":"","comment":""},"14":{"family_comment":"","value":"","family":"","comment":""},"15":{"family_comment":"","value":"","value_unclear":false,"family":"","comment":""},"16":{"family_comment":"","family_unclear":false,"value":"","family":"","comment":""},"17":{"family_comment":"","value":"","family":"","comment":""},"18":{"family_comment":"","value":"","family_hidden":false,"comment":"","family":""},"19":{"family_comment":"","value":"","family":"","comment":""},"20":{"value":"","comment_unclear":false,"comment_hidden":false,"family_comment":"","family":"","comment":"","family_comment_hidden":false}},"vehicle":{"35":[{"brand_info":"1998 куб. см., 150 к. с","sum_rent_comment":"","year":"2013","brand_info_hidden":false,"brand_info_unclear":false,"year_unclear":false,"sum_rent":"","sum":"","brand":"SsangYong Korando","sum_comment":"","brand_unclear":false,"brand_hidden":false}]},"id":"vulyk_68_116","declaration":{"additional_info_text":"","notfull_lostpages":"","date":"2015-03-03T00:00:00","notfull":"","additional_info":"","url":"http://static.declarations.com.ua/declarations/chosen_ones/mega_batch/onyshkevych_taras_volodymyrovych.pdf"},"liabilities":{"54":{"sum_foreign_comment":"","sum":"215","sum_comment":"двома сумами 120 та 95","sum_comment_unclear":false,"sum_hidden":false,"sum_comment_hidden":false,"sum_unclear":false,"sum_foreign":"120"},"55":{"sum_foreign_comment":"","sum":"","sum_hidden":false,"sum_comment":"","sum_foreign":""},"56":{"sum_foreign_comment":"","sum_foreign_hidden":false,"sum_comment":"","sum":"3221","sum_unclear":false,"sum_foreign":""},"57":{"sum_foreign_comment":"","sum":"","sum_comment":"","sum_comment_unclear":false,"sum_hidden":false,"sum_comment_hidden":false,"sum_unclear":false,"sum_foreign":""},"58":{"sum_foreign_comment":"","sum":"","sum_comment":"","sum_hidden":false,"sum_comment_hidden":false,"sum_unclear":false,"sum_foreign":""},"59":{"sum_foreign_comment":"","sum":"","sum_comment":"","sum_foreign":""},"60":{"sum_foreign_comment":"","sum":"","sum_comment":"","sum_comment_unclear":false,"sum_hidden":false,"sum_comment_hidden":false,"sum_unclear":false,"sum_foreign":""},"61":{"sum_foreign_comment":"","sum":"","sum_hidden":false,"sum_comment":"","sum_foreign":""},"62":{"sum_foreign_comment":"","sum":"","sum_comment":"","sum_unclear":false,"sum_foreign":""},"63":{"sum_foreign_comment":"","sum":"","sum_comment":"","sum_hidden":false,"sum_comment_hidden":false,"sum_unclear":false,"sum_foreign":""},"64":{"sum_foreign_comment":"","sum":"","sum_comment":"","sum_hidden":false,"sum_comment_hidden":false,"sum_foreign":""}},"ft_src":"120\nдвома сумами 120 та 95\n215\n3221\nсуддя львівського апеляційного адміністративного суду\nЛьвівська область\nАпеляційний адміністративний суд\nТарас\nОнишкевич Р. Б\nПодружжя\nОнишкевич І. Т\nДитина\nОнишкевич Я. Т\nДитина\nОнишкевич Ю. Т\nДитина\nВолодимирович\nОнишкевич Тарас Володимирович\nТарас Володимирович Онишкевич\nТарас Онишкевич\nОнишкевич Тарас Володимирович\nОнишкевич Тарас Володимирович\nОнишкевич\n1998 куб. см., 150 к. с\nSsangYong Korando\n2013\n76.4\n19\n108.5\n2014\n30622\n223754\n3671\n13398\n34293\n237152\n1998 куб. см., 150 к. с\nSsangYong Korando\n2013\n19\n76.4\n108.5\nОнишкевич Тарас Володимирович\nТарас Володимирович Онишкевич\nТарас Онишкевич\nОнишкевич Тарас Володимирович\nОнишкевич Тарас Володимирович\nПодружжя\nОнишкевич Р. Б\nДитина\nОнишкевич І. Т\nДитина\nОнишкевич Я. Т\nДитина\nОнишкевич Ю. Т\nТарас\nВолодимирович\nАпеляційний адміністративний суд\nЛьвівська область\nсуддя львівського апеляційного адміністративного суду\nОнишкевич\n3221\n120\n215\nдвома сумами 120 та 95\n223754\n30622\n237152\n34293\n13398\n3671\n2014\n3221\nдвома сумами 120 та 95\n215\n120\nПодружжя\nОнишкевич Р. Б\nОнишкевич І. Т\nДитина\nОнишкевич Я. Т\nДитина\nОнишкевич Ю. Т\nДитина\nВолодимирович\nОнишкевич\nТарас\nОнишкевич Тарас Володимирович\nТарас Володимирович Онишкевич\nТарас Онишкевич\nОнишкевич Тарас Володимирович\nЛьвівська область\nАпеляційний адміністративний суд\nсуддя львівського апеляційного адміністративного суду\nОнишкевич Тарас Володимирович\n2013\nSsangYong Korando\n1998 куб. см., 150 к. с\n3671\n13398\n34293\n237152\n30622\n223754\n76.4\n108.5\n19\n2014","general":{"inn":"","name":"Тарас","inn_unclear":false,"family":[{"inn":"","inn_hidden":false,"relations_unclear":false,"relations_hidden":false,"relations_other":"","relations":"Подружжя","name_hidden":false,"inn_unclear":false,"family_name":"Онишкевич Р. Б","name_unclear":false},{"inn":"","inn_hidden":false,"inn_unclear":false,"relations_hidden":false,"relations_other":"","relations":"Дитина","name_hidden":false,"family_name":"Онишкевич І. Т","name_unclear":false},{"inn":"","relations":"Дитина","relations_other":"","inn_hidden":false,"family_name":"Онишкевич Я. Т","name_hidden":false,"name_unclear":false},{"inn":"","relations":"Дитина","relations_other":"","inn_hidden":false,"family_name":"Онишкевич Ю. Т","name_unclear":false}],"inn_hidden":false,"family_raw":"","last_name":"Онишкевич","post":{"post_unclear":false,"region_unclear":false,"post":"суддя львівського апеляційного адміністративного суду","office":"Апеляційний адміністративний суд","region":"Львівська область","post_hidden":false,"office_hidden":false,"office_unclear":false,"region_hidden":false},"full_name_suggest":{"output":"Онишкевич Тарас Володимирович","input":["Онишкевич Тарас Володимирович","Тарас Володимирович Онишкевич","Тарас Онишкевич"]},"full_name":"Онишкевич Тарас Володимирович","patronymic":"Володимирович","last_name_unclear":false,"name_unclear":false},"source":"VULYK","estate":{"25":[{"space_unclear":false,"costs":"","costs_comment":"","address_hidden":false,"region_hidden":false,"space_comment":"","space_hidden":false,"space":"108.5","address":"","space_comment_unclear":false,"region":"","address_unclear":false,"costs_rent_comment":"","costs_unclear":false,"space_units":"м²","space_units_hidden":false,"costs_rent":""}],"27":[{"costs_rent":"","region":"","costs":"","costs_rent_comment":"","costs_comment":"","address_hidden":false,"region_hidden":false,"space_comment":"","space_units":"м²","space":"19","address":""}],"31":[{"space_unclear":false,"address_hidden":false,"region_hidden":false,"space_comment":"","space_hidden":false,"space":"76.4","address":"","region":"","costs_property":"","costs_rent_comment":"","space_units":"м²","costs_property_comment":"","costs_rent":""}]},"intro":{"declaration_year":"2014","isnotdeclaration":""}}