{"income":{"5":{"value":"201608","family_comment":"","value_unclear":false,"family_unclear":false,"family":"8790","comment":""},"6":{"family_comment":"","value":"200685","value_unclear":false,"family":"8790","comment":""},"7":{"value":"923","value_unclear":false,"family_comment":"","source_name":"Богуславський гуманітарний коледж ім. І. С. Нечуя-Левицького","family":"","comment":""},"8":{"family_comment":"","value":"","family":"","comment":""},"9":{"value":"","family_comment":"","value_unclear":false,"family_unclear":false,"family":"","comment":""},"10":{"family_comment":"","value":"","comment_unclear":false,"family":"","comment":""},"11":{"family_comment":"","value":"","family":"","comment":""},"12":{"family_comment":"","value":"","family":"","comment":""},"13":{"family_comment":"","value":"","value_unclear":false,"family":"","comment":""},"14":{"family_comment":"","value":"","family":"","comment":""},"15":{"family_comment":"","value":"","family":"","comment":""},"16":{"family_comment":"","family_unclear":false,"value":"","family":"","comment":""},"17":{"family_comment":"","family_unclear":false,"value":"","family":"","comment":""},"18":{"family_comment":"","value":"","family":"","comment":""},"19":{"family_comment":"","value":"","family":"","comment":""},"20":{"value":"","family_comment":"","comment_unclear":false,"family_hidden":false,"value_hidden":false,"family_unclear":false,"value_unclear":false,"comment":"","family":""}},"vehicle":{"35":[{"brand_info":"2.4 , 160","sum_rent_comment":"","sum_rent_comment_unclear":false,"year":"2008","brand_info_hidden":false,"brand_info_unclear":false,"sum_rent":"","sum":"","brand":"Mitsubishi","sum_comment":"","brand_unclear":false,"brand_hidden":false}]},"id":"vulyk_100_108","declaration":{"additional_info_text":"","notfull_lostpages":"","date":"2015-03-26T00:00:00","notfull":"","additional_info":"","url":"http://static.declarations.com.ua/declarations/chosen_ones/judges_batch/4312_kikhtenko_serhii_oleksandrovych.pdf"},"liabilities":{"54":{"sum_foreign_comment":"","sum":"","sum_comment":"","sum_comment_hidden":false,"sum_unclear":false,"sum_foreign":""},"55":{"sum_foreign_comment":"","sum":"","sum_comment":"","sum_foreign":""},"56":{"sum_foreign_comment":"","sum":"","sum_comment":"","sum_unclear":false,"sum_foreign":""},"57":{"sum_foreign_comment":"","sum":"","sum_comment":"","sum_comment_unclear":false,"sum_comment_hidden":false,"sum_unclear":false,"sum_foreign":""},"58":{"sum_foreign_comment":"","sum":"","sum_comment":"","sum_comment_hidden":false,"sum_unclear":false,"sum_foreign":""},"59":{"sum_foreign_comment":"","sum":"","sum_comment":"","sum_foreign":""},"60":{"sum_foreign_comment":"","sum_comment":"","sum":"","sum_comment_hidden":false,"sum_foreign":""},"61":{"sum_foreign_comment":"","sum":"","sum_comment":"","sum_foreign":""},"62":{"sum_foreign_comment":"","sum":"","sum_comment":"","sum_unclear":false,"sum_foreign":""},"63":{"sum_foreign_comment":"","sum_comment":"","sum":"","sum_comment_hidden":false,"sum_foreign":""},"64":{"sum_foreign_comment":"","sum_comment":"","sum":"","sum_comment_hidden":false,"sum_foreign":""}},"ft_src":"2.4 , 160\nMitsubishi\n2008\nЧеркаська область\nм. Черкаси\n17.5\nм. Корсунь-Шевченківський\n65\nЧеркаська область\n2014\n8790\n200685\nБогуславський гуманітарний коледж ім. І. С. Нечуя-Левицького\n923\n8790\n201608\n2.4 , 160\nMitsubishi\n2008\n17.5\nЧеркаська область\nм. Черкаси\n65\nЧеркаська область\nм. Корсунь-Шевченківський\nПодружжя\nКіхтенко Тетяна Олександрівна\nДитина\nКіхтенко Кирило Сергійович\nОлександрович\nКиївська область\nБогуслав\nКіхтенко\nКіхтенко Сергій Олександрович\nСергій Олександрович Кіхтенко\nСергій Кіхтенко\nКіхтенко Сергій Олександрович\nКіхтенко Сергій Олександрович\nСергій\nЗагальний місцевий суд\nКиївська область\nсуддя богуславського районного суду київської області\n923\nБогуславський гуманітарний коледж ім. І. С. Нечуя-Левицького\n200685\n8790\n201608\n8790\n2014\nКіхтенко Тетяна Олександрівна\nПодружжя\nДитина\nКіхтенко Кирило Сергійович\nБогуслав\nКиївська область\nОлександрович\nКіхтенко\nКиївська область\nЗагальний місцевий суд\nсуддя богуславського районного суду київської області\nКіхтенко Сергій Олександрович\nКіхтенко Сергій Олександрович\nСергій Олександрович Кіхтенко\nСергій Кіхтенко\nКіхтенко Сергій Олександрович\nСергій","general":{"inn":"","inn_hidden":true,"last_name":"Кіхтенко","post":{"post_unclear":false,"region_unclear":false,"post":"суддя богуславського районного суду київської області","post_hidden":false,"region":"Київська область","office":"Загальний місцевий суд","office_unclear":false},"name":"Сергій","full_name":"Кіхтенко Сергій Олександрович","family_raw":"","addresses":[{"place_district":"","place_address_hidden":true,"place_city":"Богуслав","place_city_unclear":false,"place_district_hidden":false,"place_city_type":"Місто","place_city_hidden":false,"place_city_type_hidden":false,"place_address":"","place_hidden":false,"place":"Київська область"}],"family":[{"inn":"","relations":"Подружжя","name_hidden":true,"inn_hidden":true,"family_name":"Кіхтенко Тетяна Олександрівна","name_unclear":false},{"inn":"","relations":"Дитина","relations_other":"","inn_hidden":true,"family_name":"Кіхтенко Кирило Сергійович","name_hidden":false,"name_unclear":false}],"full_name_suggest":{"output":"Кіхтенко Сергій Олександрович","input":["Кіхтенко Сергій Олександрович","Сергій Олександрович Кіхтенко","Сергій Кіхтенко"]},"patronymic":"Олександрович"},"source":"VULYK","estate":{"25":[{"space_unclear":false,"costs":"","costs_comment":"","address_hidden":true,"region_hidden":false,"space_comment":"","space":"65","address":"м. Корсунь-Шевченківський","costs_comment_unclear":false,"region":"Черкаська область","address_unclear":false,"costs_rent_comment":"","space_comment_unclear":false,"space_units":"м²","costs_rent":""}],"31":[{"region_unclear":false,"space_unclear":false,"costs_property_comment_unclear":false,"address_hidden":true,"region_hidden":false,"space_comment":"","space":"17.5","address":"м. Черкаси","region":"Черкаська область","costs_property":"","costs_rent_comment":"","space_comment_unclear":false,"address_unclear":false,"space_units":"м²","costs_property_comment":"","costs_rent":""}]},"intro":{"declaration_year":"2014"}}