{"income":{"5":{"value":"246602","family_hidden":false,"value_hidden":false,"family_comment":"","family":"22615","comment":""},"6":{"family_comment":"","value":"246602","family":"","comment":""},"7":{"family_comment":"","value":"","source_name":"","family":"","comment":""},"8":{"family_comment":"","value":"","family":"","comment":""},"9":{"family_comment":"","value":"","family":"","comment":""},"10":{"family_comment":"","value":"","family":"","comment":""},"11":{"family_comment":"","value":"","family":"","comment":""},"12":{"family_comment":"","value":"","family":"","comment":""},"13":{"family_comment":"","value":"","family":"","comment":""},"14":{"family_comment":"","value":"","family":"","comment":""},"15":{"family_comment":"","value":"","family":"","comment":""},"16":{"family_comment":"","value":"","family":"","comment":""},"17":{"family_comment":"","value":"","family":"","comment":""},"18":{"family_comment":"","value":"","family":"","comment":""},"19":{"family_comment":"","value":"","family":"","comment":""},"20":{"family_comment":"","value":"","family":"22615","comment":""}},"vehicle":{"40":[{"brand_info":"1.6 л","sum_rent_comment":"","brand":"Nissan TIIDA","sum_comment":"","year":"2012","sum":"","sum_rent":""}]},"id":"vulyk_89_23","declaration":{"date":"2015-03-30T00:00:00","notfull":"","url":"http://static.declarations.com.ua/declarations/chosen_ones/judges_batch/3026_obidniak_vasyl_dmytrovych.pdf","notfull_lostpages":""},"liabilities":{"54":{"sum_foreign_comment":"","sum":"","sum_comment":"","sum_foreign":""},"55":{"sum_foreign_comment":"","sum":"","sum_comment":"","sum_foreign":""},"56":{"sum_foreign_comment":"","sum":"","sum_comment":"","sum_unclear":false,"sum_foreign":""},"57":{"sum_foreign_comment":"","sum":"","sum_comment":"","sum_foreign":""},"58":{"sum_foreign_comment":"","sum":"","sum_comment":"","sum_foreign":""},"59":{"sum_foreign_comment":"","sum":"","sum_comment":"","sum_foreign":""},"60":{"sum_foreign_comment":"","sum":"","sum_comment":"","sum_foreign":""},"61":{"sum_foreign_comment":"","sum":"","sum_comment":"","sum_foreign":""},"62":{"sum_foreign_comment":"","sum":"","sum_comment":"","sum_unclear":false,"sum_foreign":""},"63":{"sum_foreign_comment":"","sum":"","sum_comment":"","sum_foreign":""},"64":{"sum_foreign_comment":"","sum":"","sum_comment":"","sum_foreign":""}},"ft_src":"Коломия\nІвано-Франківська область\nОбідняк Василь Дмитрович\nсуддя коломийського міськрайонного суду івано-франківської області\nІвано-Франківська область\nЗагальний місцевий суд\nВасиль\nОбідняк Н. М. 06. 03. 1983\nПодружжя\nОбідняк Г. В. 18. 03. 2008\nДитина\nОбідняк Н. В. 19. 11. 2009\nДитина\nОбідняк Р. В., 11. 05. 2014\nДитина\nОбідняк Василь Дмитрович\nВасиль Дмитрович Обідняк\nВасиль Обідняк\nОбідняк Василь Дмитрович\nОбідняк\nДмитрович\n1.6 л\n2012\nNissan TIIDA\nІвано-Франківська область\nм. Коломия\n800\n1/4 частина\nм. Коломия\nІвано-Франківська область\n67\n1/3 частина\nм. Коломия\n52\nІвано-Франківська область\n2014\n246602\n22615\n246602\n22615\n1.6 л\nNissan TIIDA\n2012\n2014\nДмитрович\nОбідняк Н. М. 06. 03. 1983\nПодружжя\nДитина\nОбідняк Г. В. 18. 03. 2008\nОбідняк Н. В. 19. 11. 2009\nДитина\nОбідняк Р. В., 11. 05. 2014\nДитина\nОбідняк Василь Дмитрович\nВасиль Дмитрович Обідняк\nВасиль Обідняк\nОбідняк Василь Дмитрович\nОбідняк Василь Дмитрович\nІвано-Франківська область\nКоломия\nВасиль\nОбідняк\nІвано-Франківська область\nсуддя коломийського міськрайонного суду івано-франківської області\nЗагальний місцевий суд\n246602\n22615\n246602\n22615\n800\nІвано-Франківська область\nм. Коломия\n67\n1/4 частина\nм. Коломия\nІвано-Франківська область\n52\n1/3 частина\nІвано-Франківська область\nм. Коломия\nОбідняк Н. М. 06. 03. 1983\nПодружжя\nОбідняк Г. В. 18. 03. 2008\nДитина\nДитина\nОбідняк Н. В. 19. 11. 2009\nОбідняк Р. В., 11. 05. 2014\nДитина\nІвано-Франківська область\nКоломия\nДмитрович\nОбідняк\nсуддя коломийського міськрайонного суду івано-франківської області\nІвано-Франківська область\nЗагальний місцевий суд\nОбідняк Василь Дмитрович\nОбідняк Василь Дмитрович\nВасиль Дмитрович Обідняк\nВасиль Обідняк\nОбідняк Василь Дмитрович\nВасиль\nNissan TIIDA\n1.6 л\n2012\n22615\n246602\n22615\n246602\n1/4 частина\nм. Коломия\nІвано-Франківська область\n67\nм. Коломия\nІвано-Франківська область\n800\n1/3 частина\nм. Коломия\nІвано-Франківська область\n52\n2014","general":{"inn":"","inn_hidden":true,"last_name":"Обідняк","post":{"office":"Загальний місцевий суд","region":"Івано-Франківська область","post":"суддя коломийського міськрайонного суду івано-франківської області"},"name":"Василь","full_name":"Обідняк Василь Дмитрович","family_raw":"","addresses":[{"place_district":"","place_city_hidden":false,"place_city":"Коломия","place_city_type_hidden":false,"place_district_hidden":false,"place_city_type":"Місто","place_address_hidden":true,"place_address":"","place_hidden":false,"place":"Івано-Франківська область"}],"family":[{"inn":"","family_name":"Обідняк Н. М. 06. 03. 1983","relations":"Подружжя","inn_hidden":true,"name_hidden":false},{"inn":"","relations":"Дитина","relations_other":"","inn_hidden":false,"family_name":"Обідняк Г. В. 18. 03. 2008","name_hidden":false,"name_unclear":false},{"inn":"","family_name":"Обідняк Н. В. 19. 11. 2009","relations":"Дитина","inn_hidden":false,"name_unclear":false},{"inn":"","family_name":"Обідняк Р. В., 11. 05. 2014","relations":"Дитина"}],"full_name_suggest":{"output":"Обідняк Василь Дмитрович","input":["Обідняк Василь Дмитрович","Василь Дмитрович Обідняк","Василь Обідняк"]},"patronymic":"Дмитрович"},"source":"VULYK","estate":{"23":[{"costs":"","costs_comment":"","address_hidden":false,"region_hidden":false,"space_comment":"","space":"800","address":"м. Коломия","region":"Івано-Франківська область","address_unclear":false,"costs_rent_comment":"","space_units":"м²","costs_rent":""}],"25":[{"costs":"","costs_comment":"","address_hidden":false,"region_hidden":false,"space_comment":"1/3 частина","space":"52","address":"м. Коломия","region":"Івано-Франківська область","costs_rent_comment":"","space_comment_unclear":false,"space_units":"м²","costs_rent":""}],"31":[{"space_hidden":false,"address_hidden":false,"region_hidden":false,"space_comment":"1/4 частина","space":"67","address":"м. Коломия","region":"Івано-Франківська область","costs_property":"","costs_rent_comment":"","space_units":"м²","costs_property_comment":"","costs_rent":""}]},"intro":{"declaration_year":"2014"}}