{"income":{"5":{"value":"305946","value_unclear":false,"family_hidden":false,"family_comment":"","family":"166634","comment":""},"6":{"family_comment":"","value":"305946","family":"10634","comment":""},"7":{"family_comment":"","value":"","source_name":"","family":"","comment":""},"8":{"family_comment":"","value":"","family":"","comment":""},"9":{"family_comment":"","value":"","family":"","comment":""},"10":{"family_comment":"","value":"","family":"","comment":""},"11":{"family_comment":"","value":"","family_hidden":false,"comment":"","family":""},"12":{"family_comment":"","value":"","family":"","comment":""},"13":{"family_comment":"","value":"","family":"","comment":""},"14":{"family_comment":"","value":"","family":"","comment":""},"15":{"family_comment":"","value":"","family":"","comment":""},"16":{"family_comment":"","value":"","family":"","comment":""},"17":{"family_comment":"","value":"","family":"","comment":"","family_comment_unclear":false},"18":{"family_comment":"","value":"","family":"","comment":""},"19":{"family_comment":"","value":"","family":"156000","comment":""},"20":{"value":"","family_unclear":false,"family_hidden":false,"family_comment":"","family":"","comment":""}},"vehicle":{"40":[{"year_hidden":false,"brand_info":"2354 куб. см.","sum_rent_comment":"","brand":"Honda CR-V","sum_comment":"","year":"2007","brand_hidden":false,"brand_info_unclear":false,"sum":"","sum_rent":""}]},"id":"vulyk_103_13","declaration":{"date":"2016-03-31T00:00:00","additional_info_text":"","additional_info":"","url":"http://static.declarations.com.ua/declarations/chosen_ones/judges_batch/1237_hulko_borys_ivanovych.pdf"},"liabilities":{"54":{"sum_foreign_comment":"","sum_foreign_hidden":false,"sum_comment":"","sum_foreign_comment_hidden":false,"sum_hidden":false,"sum_foreign_comment_unclear":false,"sum_comment_hidden":false,"sum_unclear":false,"sum":"","sum_foreign":""},"55":{"sum_foreign_comment":"","sum":"","sum_comment":"","sum_foreign":""},"56":{"sum_foreign_comment":"","sum":"","sum_comment":"","sum_foreign":""},"57":{"sum_foreign_comment":"","sum_foreign_hidden":false,"sum_comment":"","sum_foreign_comment_hidden":false,"sum_hidden":false,"sum_comment_hidden":false,"sum":"","sum_foreign":""},"58":{"sum_foreign_comment":"","sum_foreign_hidden":false,"sum_comment":"","sum_foreign_comment_hidden":false,"sum_hidden":false,"sum_comment_hidden":false,"sum":"","sum_foreign":""},"59":{"sum_foreign_comment":"","sum_foreign_hidden":false,"sum_comment":"","sum_foreign_comment_hidden":false,"sum_hidden":false,"sum_comment_hidden":false,"sum":"","sum_foreign":""},"60":{"sum_foreign_comment":"","sum":"9180","sum_comment":"","sum_hidden":false,"sum_comment_hidden":true,"sum_foreign":""},"61":{"sum_foreign_comment":"","sum":"","sum_comment":"","sum_foreign":""},"62":{"sum_foreign_comment":"","sum_comment_hidden":false,"sum":"","sum_comment":"","sum_foreign":""},"63":{"sum_foreign_comment":"","sum":"","sum_comment":"","sum_foreign":""},"64":{"sum_foreign_comment":"","sum":"","sum_comment":"","sum_foreign":""}},"ft_src":"9180\nГулько Борис Іванович\nголова вищого спецiалiзованого суду україни з розгляду цивiльних і кримiнальних справ\nЗагальнодержавний регіон\nВищий спеціалізований суд з розгляду цивільних і кримінальних справ\nБорис\nКрижанівська Т. М\nСпільно проживаю\nІнше\nГулько Д. Б\nДитина\nГулько Борис Іванович\nБорис Іванович Гулько\nБорис Гулько\nГулько Борис Іванович\nГулько\nІванович\n2354 куб. см.\nHonda CR-V\n2007\n1800\n37.2\n50.5\n170\n55.2\nпаркомісце\n9.2\n1/4 частина\n45.8\n1/4 частина\n103.45\n2015\n10634\n305946\n166634\n305946\n156000\n2354 куб. см.\n2007\nHonda CR-V\n1800\n55.2\n37.2\n50.5\n170\n9.2\nпаркомісце\n45.8\n1/4 частина\n103.45\n1/4 частина\nГулько\nГулько Борис Іванович\nБорис Іванович Гулько\nБорис Гулько\nГулько Борис Іванович\nГулько Борис Іванович\nІванович\nІнше\nКрижанівська Т. М\nСпільно проживаю\nГулько Д. Б\nДитина\nБорис\nВищий спеціалізований суд з розгляду цивільних і кримінальних справ\nголова вищого спецiалiзованого суду україни з розгляду цивiльних і кримiнальних справ\nЗагальнодержавний регіон\n9180\n305946\n10634\n305946\n166634\n156000\n2015\n9180\nІнше\nКрижанівська Т. М\nСпільно проживаю\nДитина\nГулько Д. Б\nГулько\nІванович\nголова вищого спецiалiзованого суду україни з розгляду цивiльних і кримiнальних справ\nВищий спеціалізований суд з розгляду цивільних і кримінальних справ\nЗагальнодержавний регіон\nГулько Борис Іванович\nГулько Борис Іванович\nБорис Іванович Гулько\nБорис Гулько\nГулько Борис Іванович\nБорис\nHonda CR-V\n2354 куб. см.\n2007\n156000\n305946\n166634\n10634\n305946\n37.2\n50.5\n170\n55.2\nпаркомісце\n9.2\n1/4 частина\n45.8\n1/4 частина\n103.45\n1800\n2015","general":{"inn":"","inn_hidden":true,"last_name":"Гулько","post":{"region":"Загальнодержавний регіон","region_unclear":false,"post":"голова вищого спецiалiзованого суду україни з розгляду цивiльних і кримiнальних справ","office_unclear":false,"office":"Вищий спеціалізований суд з розгляду цивільних і кримінальних справ"},"name":"Борис","full_name":"Гулько Борис Іванович","family_raw":"","addresses":[{"place_district":"","place_city_hidden":true,"place_city":"","place_city_type_hidden":false,"place_district_hidden":false,"place_city_type":"","place_address_hidden":true,"place_address":"","place_hidden":true,"place":""}],"family":[{"inn":"","relations":"Інше","relations_hidden":false,"inn_hidden":true,"relations_other":"Спільно проживаю","name_hidden":true,"family_name":"Крижанівська Т. М","name_unclear":false},{"inn":"","family_name":"Гулько Д. Б","relations":"Дитина","inn_hidden":true,"relations_other":""}],"full_name_suggest":{"output":"Гулько Борис Іванович","input":["Гулько Борис Іванович","Борис Іванович Гулько","Борис Гулько"]},"patronymic":"Іванович"},"source":"VULYK","estate":{"25":[{"costs":"","costs_comment":"","address_hidden":false,"region_hidden":true,"space_comment":"1/4 частина","space":"45.8","address":"","region":"","costs_rent_comment":"","space_comment_unclear":false,"space_comment_hidden":false,"space_units":"м²","costs_rent":""},{"costs_rent":"","region":"","costs":"","costs_rent_comment":"","costs_comment":"","region_hidden":false,"space_comment":"1/4 частина","space_units":"м²","space":"103.45","address":""}],"29":[{"space_hidden":false,"address_hidden":true,"region_hidden":true,"space_comment":"","space":"1800","address":"","region":"","costs_property":"","costs_rent_comment":"","space_units":"м²","costs_property_comment":"","costs_rent":""}],"30":[{"space_unclear":false,"address_hidden":true,"region_hidden":true,"space_comment":"","space_hidden":false,"space":"55.2","address":"","costs_property":"","costs_rent_comment":"","space_units":"м²","costs_property_comment":"","costs_rent":""}],"31":[{"space_hidden":false,"address_hidden":true,"region_hidden":true,"space_comment":"","space":"37.2","address":"","costs_property":"","costs_rent_comment":"","address_unclear":false,"space_units":"м²","costs_property_comment":"","costs_rent":""},{"costs_rent":"","address_hidden":true,"space_hidden":false,"costs_property":"","costs_rent_comment":"","space_comment_unclear":false,"space_comment":"","costs_property_comment":"","space_units":"м²","space":"50.5","address":""},{"costs_rent":"","space_hidden":false,"costs_property":"","costs_rent_comment":"","space_comment_unclear":false,"space_comment":"","costs_property_comment":"","space_units":"м²","space":"170","address":""}],"34":[{"costs_rent":"","space_hidden":false,"costs_property":"","costs_rent_comment":"","address_hidden":false,"region_hidden":true,"space_comment":"паркомісце","costs_property_comment":"","space_units":"м²","space":"9.2","address":""}]},"intro":{"declaration_year":"2015"}}