{"income":{"5":{"family_comment":"","value":"286084","family":"","comment":""},"6":{"value":"283242","family_comment":"","value_unclear":false,"comment_hidden":false,"family_unclear":false,"family":"","comment":""},"7":{"family_comment":"","value":"","source_name":"","family":"","comment":""},"8":{"family_comment":"","value":"","family":"","comment":""},"9":{"family_comment":"","family_unclear":false,"value":"188","family":"","comment":""},"10":{"family_comment":"","value":"","value_unclear":false,"family":"","comment":""},"11":{"family_comment":"","value":"","family":"","comment":""},"12":{"family_comment":"","value":"","family":"","comment":""},"13":{"family_comment":"","value":"","family":"","comment":""},"14":{"family_comment":"","value":"","family":"","comment":""},"15":{"family_comment":"","value":"","family":"","comment":""},"16":{"family_comment":"","value":"","family":"","comment":""},"17":{"family_comment":"","value":"","family":"","comment":""},"18":{"family_comment":"","value":"","family":"","comment":""},"19":{"family_comment":"","value":"2102","family":"","comment":""},"20":{"value":"552","family":"","value_unclear":false,"family_hidden":false,"family_comment":"","comment_unclear":false,"comment":"","family_comment_unclear":false}},"id":"vulyk_97_64","banks":{"47":[{"sum_foreign_comment":"","sum_units":"UAH","sum_comment":"","sum_foreign_units":"UAH","sum_comment_hidden":false,"sum":"500","sum_foreign":""}]},"declaration":{"additional_info_text":"","notfull_lostpages":"","date":"2015-03-27T00:00:00","notfull":"","additional_info":"","url":"http://static.declarations.com.ua/declarations/chosen_ones/judges_batch/3892_khromets_nadiia_stepanivna.pdf"},"liabilities":{"54":{"sum_foreign_comment":"","sum":"280","sum_comment":"","sum_comment_unclear":false,"sum_hidden":false,"sum_comment_hidden":false,"sum_unclear":false,"sum_foreign":""},"55":{"sum_foreign_comment":"","sum":"","sum_comment":"","sum_foreign":""},"56":{"sum_foreign_comment":"","sum":"","sum_comment":"","sum_foreign":""},"57":{"sum_foreign_comment":"","sum":"42055","sum_comment":"","sum_comment_unclear":false,"sum_hidden":false,"sum_comment_hidden":false,"sum_unclear":false,"sum_foreign":""},"58":{"sum_foreign_comment":"","sum":"2812","sum_comment":"","sum_comment_unclear":false,"sum_hidden":false,"sum_comment_hidden":false,"sum_unclear":false,"sum_foreign":""},"59":{"sum_foreign_comment":"","sum":"","sum_comment":"","sum_foreign":""},"60":{"sum_foreign_comment":"","sum":"","sum_comment":"","sum_comment_unclear":false,"sum_hidden":false,"sum_comment_hidden":false,"sum_foreign":""},"61":{"sum_foreign_comment":"","sum":"","sum_comment":"","sum_foreign":""},"62":{"sum_foreign_comment":"","sum":"","sum_comment":"","sum_unclear":false,"sum_foreign":""},"63":{"sum_foreign_comment":"","sum":"","sum_hidden":false,"sum_comment":"","sum_foreign":""},"64":{"sum_foreign_comment":"","sum":"","sum_comment":"","sum_foreign":""}},"ft_src":"42055\n280\n2812\n2137903829\nсуддя апеляційного суду чернігівської області\nЧернігівська область\nЗагальний апеляційний суд\nНадія\nСтепанівна\nХромець Надія Степанівна\nНадія Степанівна Хромець\nНадія Хромець\nХромець Надія Степанівна\nХромець Надія Степанівна\nХромець\n7.3627\n65.9\n50.4\n500\n2014\n2014\nЗагальний апеляційний суд\nЧернігівська область\nсуддя апеляційного суду чернігівської області\nХромець Надія Степанівна\nНадія Степанівна Хромець\nНадія Хромець\nХромець Надія Степанівна\nХромець Надія Степанівна\n2137903829\nНадія\nХромець\nСтепанівна\n2812\n42055\n280\n283242\n552\n286084\n188\n2102\n7.3627\n65.9\n50.4\n500\n2812\n42055\n280\n283242\n188\n286084\n2102\n552\n2137903829\nСтепанівна\nХромець\nНадія\nХромець Надія Степанівна\nНадія Степанівна Хромець\nНадія Хромець\nХромець Надія Степанівна\nЧернігівська область\nЗагальний апеляційний суд\nсуддя апеляційного суду чернігівської області\nХромець Надія Степанівна\n2102\n188\n552\n286084\n283242\n50.4\n7.3627\n65.9\n500\n2014","general":{"name_hidden":false,"name":"Надія","last_name_hidden":false,"inn":"2137903829","last_name":"Хромець","patronymic":"Степанівна","inn_hidden":true,"family_raw":"","inn_unclear":false,"post":{"region_unclear":false,"region":"Чернігівська область","post":"суддя апеляційного суду чернігівської області","office":"Загальний апеляційний суд","office_unclear":false,"post_hidden":false},"full_name":"Хромець Надія Степанівна","addresses":[{"place_district":"","place_city_hidden":true,"place_city":"","place_city_unclear":false,"place_district_hidden":true,"place_city_type":"","place_address_hidden":true,"place_city_type_hidden":true,"place_address":"","place_hidden":true,"place":""}],"patronymic_hidden":false,"full_name_suggest":{"output":"Хромець Надія Степанівна","input":["Хромець Надія Степанівна","Надія Степанівна Хромець","Надія Хромець"]}},"source":"VULYK","estate":{"23":[{"region_unclear":false,"space_unclear":false,"costs":"","costs_rent_unclear":false,"costs_comment":"","address_hidden":true,"region_hidden":true,"space_comment":"","space":"7.3627","address":"","region":"","address_unclear":false,"costs_rent_comment":"","space_units":"га","costs_rent":""}],"24":[{"region_unclear":false,"space_unclear":false,"costs":"","costs_comment":"","address_hidden":true,"region_hidden":true,"space_comment":"","space_hidden":false,"space":"65.9","address":"","region":"","address_unclear":false,"costs_rent_comment":"","space_comment_unclear":false,"space_units":"м²","costs_rent":""}],"25":[{"region_unclear":false,"space_unclear":false,"costs":"","costs_comment":"","address_hidden":true,"region_hidden":true,"space_comment":"","space_hidden":false,"space":"50.4","address":"","region":"","costs_rent_comment":"","space_comment_unclear":false,"space_comment_hidden":false,"space_units":"м²","costs_rent":""}]},"intro":{"declaration_year":"2014","isnotdeclaration":""}}