{"income":{"5":{"family_comment":"","value":"188200.91","family":"","comment":""},"6":{"value":"176020.91","family_comment":"","value_unclear":false,"comment_hidden":false,"family_unclear":false,"family":"","comment":""},"7":{"family_comment":"","value":"","source_name":"","family":"","comment":""},"8":{"family_comment":"","value":"","family":"","comment":""},"9":{"family_comment":"","family_unclear":false,"value":"","family":"","comment":""},"10":{"family_comment":"","value":"12180","value_unclear":false,"family":"","comment":""},"11":{"family_comment":"","value":"","family":"","comment":""},"12":{"family_comment":"","value":"","family":"","comment":""},"13":{"family_comment":"","value":"","family":"","comment":""},"14":{"family_comment":"","value":"","family":"","comment":""},"15":{"family_comment":"","value":"","family":"","comment":""},"16":{"family_comment":"","value":"","family":"","comment":""},"17":{"family_comment":"","value":"","family":"","comment":""},"18":{"family_comment":"","value":"","family":"","comment":""},"19":{"family_comment":"","value":"","family":"","comment":""},"20":{"value":"","family":"","value_unclear":false,"family_hidden":false,"family_comment":"","comment_unclear":false,"comment":"","family_comment_unclear":false}},"id":"vulyk_97_151","declaration":{"additional_info_text":"","notfull_lostpages":"","date":"2015-03-31T00:00:00","notfull":"","additional_info":"","url":"http://static.declarations.com.ua/declarations/chosen_ones/judges_batch/4053_brahina_oleksandra_ievheniivna.pdf"},"liabilities":{"54":{"sum_foreign_comment":"","sum":"","sum_comment":"","sum_comment_unclear":false,"sum_hidden":false,"sum_comment_hidden":false,"sum_unclear":false,"sum_foreign":""},"55":{"sum_foreign_comment":"","sum":"","sum_comment":"","sum_foreign":""},"56":{"sum_foreign_comment":"","sum":"","sum_comment":"","sum_foreign":""},"57":{"sum_foreign_comment":"","sum":"","sum_comment":"","sum_comment_unclear":false,"sum_hidden":false,"sum_comment_hidden":false,"sum_unclear":false,"sum_foreign":""},"58":{"sum_foreign_comment":"","sum":"","sum_comment":"","sum_comment_unclear":false,"sum_hidden":false,"sum_comment_hidden":false,"sum_unclear":false,"sum_foreign":""},"59":{"sum_foreign_comment":"","sum":"","sum_comment":"","sum_foreign":""},"60":{"sum_foreign_comment":"","sum":"","sum_comment":"","sum_comment_unclear":false,"sum_hidden":false,"sum_comment_hidden":false,"sum_foreign":""},"61":{"sum_foreign_comment":"","sum":"","sum_comment":"","sum_foreign":""},"62":{"sum_foreign_comment":"","sum":"","sum_comment":"","sum_unclear":false,"sum_foreign":""},"63":{"sum_foreign_comment":"","sum":"","sum_hidden":false,"sum_comment":"","sum_foreign":""},"64":{"sum_foreign_comment":"","sum":"","sum_comment":"","sum_foreign":""}},"ft_src":"суддя\nКиївська область\nАдміністративний місцевий суд\nОлександра\nЄвгеніївна\nБрагіна Олександра Євгеніївна\nОлександра Євгеніївна Брагіна\nОлександра Брагіна\nБрагіна Олександра Євгеніївна\nБрагіна Олександра Євгеніївна\nБрагіна\n12180\n188200.91\n176020.91\n35\n81\n2014\n176020.91\n12180\n188200.91\n35\n81\nАдміністративний місцевий суд\nКиївська область\nсуддя\nБрагіна Олександра Євгеніївна\nОлександра Євгеніївна Брагіна\nОлександра Брагіна\nБрагіна Олександра Євгеніївна\nБрагіна Олександра Євгеніївна\nОлександра\nБрагіна\nЄвгеніївна\n176020.91\n188200.91\n12180\n2014\nЄвгеніївна\nБрагіна\nОлександра\nБрагіна Олександра Євгеніївна\nОлександра Євгеніївна Брагіна\nОлександра Брагіна\nБрагіна Олександра Євгеніївна\nКиївська область\nАдміністративний місцевий суд\nсуддя\nБрагіна Олександра Євгеніївна\n35\n81\n2014","general":{"name_hidden":false,"name":"Олександра","last_name_hidden":false,"inn":"","last_name":"Брагіна","patronymic":"Євгеніївна","inn_hidden":true,"family_raw":"","inn_unclear":false,"post":{"region_unclear":true,"region":"Київська область","post":"суддя","office":"Адміністративний місцевий суд","office_unclear":true,"post_hidden":false},"full_name":"Брагіна Олександра Євгеніївна","addresses":[{"place_district":"","place_city_hidden":true,"place_city":"","place_city_unclear":false,"place_district_hidden":false,"place_city_type":"","place_address_hidden":true,"place_city_type_hidden":false,"place_address":"","place_hidden":true,"place":""}],"patronymic_hidden":false,"full_name_suggest":{"output":"Брагіна Олександра Євгеніївна","input":["Брагіна Олександра Євгеніївна","Олександра Євгеніївна Брагіна","Олександра Брагіна"]}},"source":"VULYK","estate":{"25":[{"region_unclear":false,"space_unclear":false,"costs":"","costs_comment":"","address_hidden":false,"region_hidden":true,"space_comment":"","space_hidden":false,"space":"35","address":"","region":"","costs_rent_comment":"","space_comment_unclear":false,"space_comment_hidden":false,"space_units":"м²","costs_rent":""},{"space_unclear":false,"costs":"","costs_comment":"","address_hidden":false,"space_comment":"","space":"81","address":"","region":"","costs_rent_comment":"","space_comment_unclear":false,"space_units":"м²","costs_rent":""}]},"intro":{"declaration_year":"2014","isnotdeclaration":""}}