{"income":{"5":{"family_comment":"","family_unclear":false,"value":"174212","family":"","comment":""},"6":{"family_comment":"","value":"174212","value_unclear":false,"family":"","comment":""},"7":{"family_comment":"","value":"","source_name":"","family":"","comment":""},"8":{"family_comment":"","value":"","family":"","comment":""},"9":{"value":"","value_unclear":false,"family_hidden":false,"family_comment":"","comment_unclear":false,"comment":"","family":""},"10":{"family_comment":"","value":"","family":"","comment":""},"11":{"family_comment":"","value":"","family":"","comment":""},"12":{"family_comment":"","value":"","family":"","comment":""},"13":{"family_comment":"","value":"","family":"","comment":""},"14":{"family_comment":"","value":"","family":"","comment":""},"15":{"family_comment":"","value":"","family":"","comment":""},"16":{"family_comment":"","value":"","family":"","comment":""},"17":{"family_comment":"","value":"","family":"","comment":""},"18":{"family_comment":"","value":"","family":"","comment":""},"19":{"family_comment":"","value":"","family":"","comment":""},"20":{"value":"","value_unclear":false,"comment_hidden":false,"family_comment":"","family":"","comment":""}},"id":"vulyk_40_22","banks":{"45":[{"sum_foreign_comment":"","sum_units":"UAH","sum_comment":"","sum_hidden":false,"sum_foreign_units":"UAH","sum":"","sum_foreign":""},{"sum_foreign_comment":"","sum_units":"","sum_comment":"","sum_foreign_units":"","sum":"","sum_foreign":""},{"sum_foreign_comment":"","sum_units":"","sum_comment":"","sum_foreign_units":"","sum":"","sum_foreign":""}],"46":[{"sum_foreign_comment":"","sum_units":"UAH","sum_comment":"","sum_foreign_units":"UAH","sum":"","sum_unclear":false,"sum_foreign":""}],"47":[{"sum_foreign_comment":"","sum_units":"UAH","sum_comment":"","sum_foreign_units":"UAH","sum":"","sum_foreign":""}],"48":[{"sum_foreign_comment":"","sum_units":"UAH","sum_comment":"","sum_foreign_units":"UAH","sum":"","sum_foreign":""}],"49":[{"sum_foreign_comment":"","sum_units":"UAH","sum_comment":"","sum_foreign_units":"UAH","sum":"","sum_foreign":""}],"50":[{"sum_foreign_comment":"","sum_units":"UAH","sum_comment":"","sum_foreign_units":"UAH","sum":"","sum_foreign":""}],"51":[{"sum_foreign_comment":"","sum_units":"UAH","sum_comment":"","sum_foreign_units":"UAH","sum":"","sum_foreign":""}],"52":[{"sum_foreign_comment":"","sum_units":"UAH","sum_comment":"","sum_foreign_units":"UAH","sum":"","sum_foreign":""}],"53":[{"sum_foreign_comment":"","sum_units":"UAH","sum_comment":"","sum_foreign_units":"UAH","sum":"","sum_foreign":""}]},"declaration":{"date":"2015-03-30T00:00:00","notfull":"","url":"http://static.declarations.com.ua/declarations/chosen_ones/mega_batch/semennykov_oleksandr_iuriiovych.pdf","notfull_lostpages":""},"liabilities":{"54":{"sum_foreign_comment":"","sum":"","sum_comment":"","sum_foreign":""},"55":{"sum_foreign_comment":"","sum":"","sum_comment":"","sum_foreign":""},"56":{"sum_foreign_comment":"","sum":"","sum_comment":"","sum_foreign":""},"57":{"sum_foreign_comment":"","sum":"","sum_comment":"","sum_hidden":false,"sum_comment_hidden":false,"sum_foreign":""},"58":{"sum_foreign_comment":"","sum":"","sum_comment":"","sum_hidden":false,"sum_comment_hidden":false,"sum_foreign":""},"59":{"sum_foreign_comment":"","sum":"","sum_comment":"","sum_foreign":""},"60":{"sum_foreign_comment":"","sum":"","sum_comment":"","sum_foreign":""},"61":{"sum_foreign_comment":"","sum":"","sum_comment":"","sum_foreign":""},"62":{"sum_foreign_comment":"","sum":"","sum_comment":"","sum_foreign":""},"63":{"sum_foreign_comment":"","sum":"","sum_comment":"","sum_foreign":""},"64":{"sum_foreign_comment":"","sum":"","sum_comment":"","sum_foreign":""}},"ft_src":"Семенников Олександр Юрійович\nсуддя п'ятихатського районного суду дніпропетровської області\nДніпропетровська область\nЗагальний місцевий суд\nОлександр\nСеменникова В. П., 24. 05. 1977\nПодружжя\nСеменников А. О., 13. 03. 2007\nДитина\nСеменников К. О., 11. 02. 2010\nДитина\nСеменников Олександр Юрійович\nОлександр Юрійович Семенников\nОлександр Семенников\nСеменников Олександр Юрійович\nСеменников\nЮрійович\n174212\n174212\n348\n1/4\n19\n1/4\n19\n2014\n174212\n174212\n2014\nСеменников\nСеменников Олександр Юрійович\nОлександр Юрійович Семенников\nОлександр Семенников\nСеменников Олександр Юрійович\nОлександр\nЮрійович\nСеменников Олександр Юрійович\nЗагальний місцевий суд\nсуддя п'ятихатського районного суду дніпропетровської області\nДніпропетровська область\nПодружжя\nСеменникова В. П., 24. 05. 1977\nДитина\nСеменников А. О., 13. 03. 2007\nСеменников К. О., 11. 02. 2010\nДитина\n174212\n174212\n348\n19\n1/4\n19\n1/4\nСеменникова В. П., 24. 05. 1977\nПодружжя\nСеменников А. О., 13. 03. 2007\nДитина\nСеменников К. О., 11. 02. 2010\nДитина\nЮрійович\nСеменников\nсуддя п'ятихатського районного суду дніпропетровської області\nДніпропетровська область\nЗагальний місцевий суд\nСеменников Олександр Юрійович\nСеменников Олександр Юрійович\nОлександр Юрійович Семенников\nОлександр Семенников\nСеменников Олександр Юрійович\nОлександр\n1/4\n19\n348\n1/4\n19\n2014","general":{"inn":"","inn_hidden":true,"last_name":"Семенников","post":{"office":"Загальний місцевий суд","region":"Дніпропетровська область","post":"суддя п'ятихатського районного суду дніпропетровської області"},"name":"Олександр","full_name":"Семенников Олександр Юрійович","family_raw":"","addresses":[{"place_district":"","place_city_hidden":true,"place_city":"","place_city_type_hidden":true,"place_district_hidden":true,"place_city_type":"","place_address_hidden":true,"place_address":"","place_hidden":true,"place":""}],"family":[{"inn":"","relations":"Подружжя","relations_other":"","inn_hidden":true,"family_name":"Семенникова В. П., 24. 05. 1977","name_hidden":false},{"inn":"","relations":"Дитина","relations_other":"","inn_hidden":false,"family_name":"Семенников А. О., 13. 03. 2007","name_unclear":false},{"inn":"","family_name":"Семенников К. О., 11. 02. 2010","relations":"Дитина","inn_hidden":false}],"full_name_suggest":{"output":"Семенников Олександр Юрійович","input":["Семенников Олександр Юрійович","Олександр Юрійович Семенников","Олександр Семенников"]},"patronymic":"Юрійович"},"source":"VULYK","estate":{"23":[{"costs_rent":"","region":"","costs":"","costs_rent_comment":"","costs_comment":"","address_hidden":true,"region_hidden":true,"space_comment":"","space_units":"м²","space":"348","address":""},{"costs_rent":"","region":"","costs":"","costs_rent_comment":"","costs_comment":"","space_comment":"","space_units":"","space":"","address":""},{"costs_rent":"","region":"","costs":"","costs_rent_comment":"","costs_comment":"","space_comment":"","space_units":"","space":"","address":""},{"costs_rent":"","costs":"","costs_rent_comment":"","costs_comment":"","space_comment":"","space_units":"","space":"","address":""}],"24":[{"costs_rent":"","region":"","costs":"","costs_rent_comment":"","costs_comment":"","address_hidden":true,"region_hidden":true,"space_comment":"1/4","space_units":"м²","space":"19","address":""}],"30":[{"costs_rent":"","region":"","costs_property":"","costs_rent_comment":"","address_hidden":true,"region_hidden":true,"space_comment":"1/4","costs_property_comment":"","space_units":"м²","space":"19","address":""}]},"intro":{"declaration_year":"2014"}}