{"income":{"5":{"family_comment":"","value":"233883.53","family":"","comment":""},"6":{"value":"220393.68","comment_hidden":false,"family_comment":"","family":"","comment":"","family_comment_hidden":false},"7":{"value":"91.85","comment_unclear":false,"family_comment":"","source_name":"Національна школа суддів України","family":"","comment":""},"8":{"family_comment":"","value":"","family":"","comment":""},"9":{"family_comment":"","value":"","family":"","comment":""},"10":{"family_comment":"","value":"13398","family":"","comment":"","family_hidden":false},"11":{"family_comment":"","value":"","family":"","comment":""},"12":{"family_comment":"","value":"","family":"","comment":""},"13":{"family_comment":"","value":"","family":"","comment":""},"14":{"family_comment":"","value":"","family":"","comment":""},"15":{"family_comment":"","value":"","family":"","comment":""},"16":{"family_comment":"","value":"","family":"","comment":""},"17":{"family_comment":"","value":"","family":"","comment":""},"18":{"family_comment":"","value":"","family":"","comment":""},"19":{"family_comment":"","value":"","family":"","comment":""},"20":{"value":"","value_unclear":false,"family_hidden":false,"family_comment":"","family":"","comment":""}},"vehicle":{"35":[{"brand_info":"1.6 л","sum_rent_comment":"","brand":"Chevrolet Lacetti","sum_comment":"","year":"2008","brand_info_unclear":false,"sum":"","sum_rent":""}]},"id":"vulyk_83_46","declaration":{"additional_info_text":"","notfull_lostpages":"","date":"2015-03-27T00:00:00","notfull":"","additional_info":"","url":"http://static.declarations.com.ua/declarations/chosen_ones/judges_batch/2316_chelnyk_olha_ivanivna.pdf"},"liabilities":{"54":{"sum_foreign_comment":"","sum":"","sum_comment":"","sum_foreign":""},"55":{"sum_foreign_comment":"","sum":"","sum_comment":"","sum_foreign":""},"56":{"sum_foreign_comment":"","sum":"20000","sum_comment":"","sum_foreign":""},"57":{"sum_foreign_comment":"","sum":"","sum_comment":"","sum_foreign":""},"58":{"sum_foreign_comment":"","sum":"","sum_comment":"","sum_foreign":""},"59":{"sum_foreign_comment":"","sum":"","sum_comment":"","sum_foreign":""},"60":{"sum_foreign_comment":"","sum":"","sum_comment":"","sum_foreign":""},"61":{"sum_foreign_comment":"","sum":"","sum_comment":"","sum_foreign":""},"62":{"sum_foreign_comment":"","sum":"","sum_comment":"","sum_foreign":""},"63":{"sum_foreign_comment":"","sum":"","sum_comment":"","sum_foreign":""},"64":{"sum_foreign_comment":"","sum":"","sum_comment":"","sum_foreign":""}},"ft_src":"1.6 л\n2008\nChevrolet Lacetti\n6506.56\n65\n2014\n220393.68\n13398\n91.85\nНаціональна школа суддів України\n233883.53\n1.6 л\nChevrolet Lacetti\n2008\n65\n6506.56\nЧельник Ольга Іванівна\nОльга Іванівна Чельник\nОльга Чельник\nЧельник Ольга Іванівна\nОльга\nЧельник Ольга Іванівна\nІванівна\nЗагальний апеляційний суд\nКіровоградська область\nсуддя апеляційного суду кіровоградської області\nЧельник\n20000\n91.85\nНаціональна школа суддів України\n220393.68\n233883.53\n13398\n2014\n20000\nІванівна\nЧельник\nОльга\nЧельник Ольга Іванівна\nОльга Іванівна Чельник\nОльга Чельник\nЧельник Ольга Іванівна\nКіровоградська область\nЗагальний апеляційний суд\nсуддя апеляційного суду кіровоградської області\nЧельник Ольга Іванівна","general":{"inn":"","name":"Ольга","last_name":"Чельник","patronymic":"Іванівна","inn_hidden":true,"family_raw":"","inn_unclear":false,"post":{"post_unclear":false,"post":"суддя апеляційного суду кіровоградської області","candidate":"","region":"Кіровоградська область","office":"Загальний апеляційний суд","office_unclear":false},"full_name_suggest":{"output":"Чельник Ольга Іванівна","input":["Чельник Ольга Іванівна","Ольга Іванівна Чельник","Ольга Чельник"]},"full_name":"Чельник Ольга Іванівна","addresses":[{"place_city_type_unclear":false,"place_city_type_hidden":true,"place_district_hidden":true,"place_city_type":"","place_city_hidden":true,"place_address_unclear":false,"place_address":"","place":"","place_district":"","place_address_hidden":true,"place_hidden":true,"place_city_unclear":false,"place_city":""}],"last_name_unclear":false},"source":"VULYK","estate":{"25":[{"region_unclear":false,"space_hidden":false,"costs":"","costs_comment":"","address_hidden":false,"region_hidden":true,"space_comment":"","space_unclear":false,"space":"65","address":"","region":"","costs_rent_comment":"","space_comment_unclear":false,"space_units":"м²","costs_rent":"6506.56"}]},"intro":{"declaration_year":"2014"}}