{"income":{"5":{"family_comment":"","value":"187237","value_unclear":false,"family":"","comment":""},"6":{"value":"168735","value_unclear":false,"family_hidden":false,"family_comment":"","family":"","comment":""},"7":{"source_name_unclear":false,"value":"","family_comment":"","source_name":"","family":"","comment":""},"8":{"family_comment":"","value":"","family":"","comment":""},"9":{"family_comment":"","value":"476","family":"","comment":""},"10":{"family_comment":"","value":"","family":"","comment":""},"11":{"family_comment":"","value":"","comment_unclear":false,"family":"","comment":""},"12":{"family_comment":"","value":"","family":"","comment":""},"13":{"family_comment":"","value":"","family":"","comment":""},"14":{"family_comment":"","value":"","family":"","comment":""},"15":{"family_comment":"","value":"","family":"","comment":""},"16":{"family_comment":"","value":"","family":"","comment":""},"17":{"family_comment":"","value":"","family":"","comment":""},"18":{"family_comment":"","value":"","family":"","comment":""},"19":{"family_comment":"","value":"","family":"","comment":""},"20":{"value":"18026","family_comment":"","value_unclear":false,"family_unclear":false,"comment_unclear":false,"comment":"","family":""}},"id":"vulyk_101_165","banks":{"45":[{"sum_foreign_comment":"","sum_units":"UAH","sum_comment":"","sum_comment_unclear":false,"sum_hidden":false,"sum_foreign_units":"UAH","sum_comment_hidden":true,"sum_unclear":false,"sum":"260","sum_foreign":""},{"sum_foreign_comment":"","sum_units":"","sum_comment":"","sum":"4377","sum_foreign":""}]},"declaration":{"additional_info_text":"","notfull_lostpages":"","date":"2016-03-31T00:00:00","notfull":"","additional_info":"","url":"http://static.declarations.com.ua/declarations/chosen_ones/judges_batch/880_horokhov_ihor_serhiiovych_2015.pdf"},"liabilities":{"54":{"sum_foreign_comment":"","sum":"120","sum_comment":"","sum_comment_unclear":false,"sum_hidden":true,"sum_comment_hidden":true,"sum_unclear":false,"sum_foreign":""},"55":{"sum_foreign_comment":"","sum":"","sum_comment":"","sum_foreign":""},"56":{"sum_foreign_comment":"","sum":"","sum_comment":"","sum_comment_hidden":false,"sum_unclear":false,"sum_foreign":""},"57":{"sum_foreign_comment":"","sum":"9523","sum_comment":"дві суми 500 та 9023","sum_hidden":true,"sum_comment_hidden":true,"sum_unclear":false,"sum_foreign":""},"58":{"sum_foreign_comment":"","sum":"2472","sum_comment":"","sum_comment_unclear":false,"sum_hidden":true,"sum_comment_hidden":true,"sum_unclear":false,"sum_foreign":""},"59":{"sum_foreign_comment":"","sum":"","sum_comment":"","sum_foreign":""},"60":{"sum_foreign_comment":"","sum":"","sum_comment":"","sum_hidden":false,"sum_comment_hidden":false,"sum_unclear":false,"sum_foreign":""},"61":{"sum_foreign_comment":"","sum":"","sum_comment":"","sum_foreign":""},"62":{"sum_foreign_comment":"","sum":"","sum_comment":"","sum_comment_unclear":false,"sum_foreign":""},"63":{"sum_foreign_comment":"","sum_comment_hidden":false,"sum":"","sum_comment":"","sum_foreign":""},"64":{"sum_foreign_comment":"","sum_comment_hidden":false,"sum":"","sum_comment":"","sum_foreign":""}},"ft_src":"дві суми 500 та 9023\n9523\n120\n2472\nсуддя господарського суду запорізької області\nЗапорізька область\nГосподарський місцевий суд\nІгор\nСергійович\nГорохов Ігор Сергійович\nГорохов\nГорохов Ігор Сергійович\nІгор Сергійович Горохов\nІгор Горохов\nГорохов Ігор Сергійович\n600\n42373\n13\n32\n260\n4377\n2015\n2015\nГорохов Ігор Сергійович\nІгор Сергійович Горохов\nІгор Горохов\nГорохов Ігор Сергійович\nІгор\nГорохов Ігор Сергійович\nГорохов\nГосподарський місцевий суд\nсуддя господарського суду запорізької області\nЗапорізька область\nСергійович\n2472\n9523\nдві суми 500 та 9023\n120\n168735\n18026\n187237\n476\n600\n13\n42373\n32\n260\n4377\n2472\nдві суми 500 та 9023\n9523\n120\n168735\n476\n187237\n18026\nСергійович\nГорохов\nІгор\nГорохов Ігор Сергійович\nІгор Сергійович Горохов\nІгор Горохов\nГорохов Ігор Сергійович\nсуддя господарського суду запорізької області\nГосподарський місцевий суд\nЗапорізька область\nГорохов Ігор Сергійович\n476\n18026\n187237\n168735\n42373\n13\n32\n600\n260\n4377\n2015","general":{"inn":"","name":"Ігор","inn_unclear":false,"patronymic":"Сергійович","inn_hidden":true,"family_raw":"","last_name":"Горохов","post":{"region":"Запорізька область","region_unclear":false,"post":"суддя господарського суду запорізької області","office_unclear":false,"office":"Господарський місцевий суд"},"full_name":"Горохов Ігор Сергійович","addresses":[{"place_district":"","place_city_hidden":true,"place_city":"","place_city_type_hidden":false,"place_district_hidden":false,"place_city_type":"","place_address_hidden":true,"place_address":"","place_hidden":true,"place":""}],"patronymic_hidden":false,"full_name_suggest":{"output":"Горохов Ігор Сергійович","input":["Горохов Ігор Сергійович","Ігор Сергійович Горохов","Ігор Горохов"]}},"source":"VULYK","estate":{"23":[{"space_unclear":false,"costs":"","costs_comment":"","address_hidden":false,"region_hidden":true,"space_comment":"","space_hidden":false,"space":"600","address":"","costs_comment_unclear":false,"region":"","space_units_unclear":false,"space_units":"м²","costs_rent":"","costs_rent_comment":""}],"25":[{"space_unclear":false,"costs":"","costs_comment":"","address_hidden":false,"region_hidden":true,"space_comment":"42373","space_hidden":false,"space":"13","address":"","region":"","costs_rent_comment":"","space_comment_unclear":false,"space_units":"м²","costs_rent":""},{"space_unclear":false,"costs":"","costs_comment":"","space_comment":"","space_hidden":false,"space":"32","address":"","region":"","costs_rent_comment":"","space_comment_unclear":false,"space_units":"м²","costs_rent":""}]},"intro":{"declaration_year":"2015"}}