{"income":{"5":{"value":"224718","family_comment":"","value_unclear":false,"family_hidden":false,"value_hidden":false,"family_unclear":false,"family_comment_hidden":false,"comment":"","family":"18879"},"6":{"value":"224671","family_comment":"","value_unclear":false,"family_hidden":false,"family_unclear":false,"family":"2920","comment":""},"7":{"family_comment":"","value":"","source_name":"","family":"","comment":""},"8":{"family_comment":"","value":"","family":"","comment":""},"9":{"family_comment":"","value":"","family":"59","comment":""},"10":{"family_comment":"","family_unclear":false,"value":"","family":"","comment":""},"11":{"family_comment":"","value":"","family":"","comment":""},"12":{"family_comment":"","value":"","family":"","comment":""},"13":{"family_comment":"","value":"","family":"15900","comment":""},"14":{"family_comment":"","value":"","comment_unclear":false,"family":"","comment":""},"15":{"family_comment":"","value":"","family":"","comment":""},"16":{"family_comment":"","value":"","family":"","comment":""},"17":{"family_comment":"","value":"","family":"","comment":""},"18":{"family_comment":"","value":"","family":"","comment":""},"19":{"family_comment":"","value":"","family":"","comment":""},"20":{"value":"47","family_comment":"","value_unclear":false,"family_unclear":false,"comment_unclear":false,"comment":"","family":""}},"vehicle":{"35":[{"brand_info":"1845 куб. см., 97 кВт","sum_rent_comment":"","brand_info_unclear":false,"year":"2013","sum_rent_unclear":false,"brand_info_hidden":false,"sum_rent_comment_unclear":false,"sum_rent":"","sum":"137000","brand":"Chery Tiggo","sum_comment":"","brand_hidden":false,"sum_rent_comment_hidden":false,"sum_unclear":false}]},"id":"vulyk_35_84","banks":{"45":[{"sum_foreign_comment":"","sum_units":"UAH","sum_comment":"","sum_comment_unclear":false,"sum_hidden":false,"sum_foreign_units":"UAH","sum_comment_hidden":false,"sum_unclear":false,"sum":"3850","sum_foreign":""},{"sum_foreign_comment":"","sum_units":"","sum_comment":"","sum_foreign_units":"","sum":"","sum_foreign":""},{"sum_foreign_comment":"","sum_units":"","sum_comment":"","sum_foreign_units":"","sum":"","sum_foreign":""}],"46":[{"sum_foreign_comment":"","sum_units":"UAH","sum_comment":"","sum_hidden":false,"sum_foreign_units":"UAH","sum_comment_hidden":false,"sum":"","sum_foreign":""},{"sum_foreign_comment":"","sum_units":"","sum_comment":"","sum_foreign_units":"","sum":"","sum_foreign":""}],"47":[{"sum_foreign_comment":"","sum_units":"UAH","sum_comment":"","sum_foreign_units":"UAH","sum":"","sum_foreign":""}],"48":[{"sum_foreign_comment":"","sum_units":"UAH","sum_comment":"","sum_foreign_units":"UAH","sum":"","sum_foreign":""}],"49":[{"sum_foreign_comment":"","sum_units":"UAH","sum_comment":"","sum_hidden":false,"sum_foreign_units":"UAH","sum":"","sum_foreign":""}],"50":[{"sum_foreign_comment":"","sum_units":"UAH","sum_comment":"","sum_foreign_units":"UAH","sum":"","sum_foreign":""}],"51":[{"sum_foreign_comment":"","sum_units":"UAH","sum_comment":"","sum_comment_unclear":false,"sum_foreign_units":"UAH","sum_comment_hidden":false,"sum":"","sum_foreign":""},{"sum_foreign_comment":"","sum_units":"","sum_comment":"","sum_foreign_units":"","sum":"","sum_foreign":""}],"52":[{"sum_foreign_comment":"","sum_units":"UAH","sum_comment":"","sum_foreign_units":"UAH","sum":"","sum_foreign":""}],"53":[{"sum_foreign_comment":"","sum_units":"UAH","sum_comment":"","sum_foreign_units":"UAH","sum":"","sum_foreign":""}]},"declaration":{"additional_info_text":"","notfull_lostpages":"","date":"2015-03-25T00:00:00","notfull":"","additional_info":"","url":"http://static.declarations.com.ua/declarations/chosen_ones/mega_batch/rotaienko_danyila_stepanivna.pdf"},"liabilities":{"54":{"sum_foreign_comment":"","sum":"","sum_comment":"","sum_comment_unclear":false,"sum_hidden":false,"sum_comment_hidden":false,"sum_unclear":false,"sum_foreign":""},"55":{"sum_foreign_comment":"","sum":"","sum_comment":"","sum_foreign":""},"56":{"sum_foreign_comment":"","sum":"","sum_comment":"","sum_unclear":false,"sum_foreign":""},"57":{"sum_foreign_comment":"","sum":"57698","sum_comment":"","sum_comment_unclear":true,"sum_hidden":false,"sum_comment_hidden":true,"sum_unclear":false,"sum_foreign":""},"58":{"sum_foreign_comment":"","sum":"2933","sum_comment":"","sum_hidden":false,"sum_comment_hidden":false,"sum_foreign":""},"59":{"sum_foreign_comment":"","sum":"","sum_comment":"","sum_foreign":""},"60":{"sum_foreign_comment":"","sum_comment_hidden":false,"sum":"288","sum_comment":"","sum_foreign":""},"61":{"sum_foreign_comment":"","sum":"","sum_comment":"","sum_foreign":""},"62":{"sum_foreign_comment":"","sum":"","sum_comment":"","sum_foreign":""},"63":{"sum_foreign_comment":"","sum":"","sum_comment":"","sum_hidden":false,"sum_comment_hidden":false,"sum_foreign":""},"64":{"sum_foreign_comment":"","sum":"","sum_comment":"","sum_hidden":false,"sum_comment_hidden":false,"sum_foreign":""}},"ft_src":"57698\n2933\n288\nМонастирище\nЧеркаська область\nМонастирищенський\nзаступник голови монастирищенського районного суду черкаської області\nЧеркаська область\nЗагальний місцевий суд\nДаниїла\nРотаєнко А. В\nДитина\nСтепанівна\nРотаєнко Даниїла Степанівна\nДаниїла Степанівна Ротаєнко\nДаниїла Ротаєнко\nРотаєнко Даниїла Степанівна\nРотаєнко\nРотаєнко Даниїла Степанівна\n1845 куб. см., 97 кВт\n2013\n137000\nChery Tiggo\n3850\n2014\n1845 куб. см., 97 кВт\nChery Tiggo\n2013\n137000\n3850\n23\nм. Монастирище\nЧеркаська область\n41.4\nЧеркаська область\nм. Монастирище\n20.6\nЧеркаська область\nм. Монастирище\nДитина\nРотаєнко А. В\nРотаєнко Даниїла Степанівна\nДаниїла Степанівна Ротаєнко\nДаниїла Ротаєнко\nРотаєнко Даниїла Степанівна\nРотаєнко Даниїла Степанівна\nДаниїла\nРотаєнко\nзаступник голови монастирищенського районного суду черкаської області\nЗагальний місцевий суд\nЧеркаська область\nСтепанівна\nЧеркаська область\nМонастирище\nМонастирищенський\n57698\n288\n2933\n2920\n224671\n15900\n47\n224718\n18879\n59\n2014\n2933\n57698\n288\nм. Монастирище\n23\nЧеркаська область\nм. Монастирище\nЧеркаська область\n41.4\nм. Монастирище\n20.6\nЧеркаська область\nРотаєнко А. В\nДитина\nСтепанівна\nРотаєнко\nДаниїла\nРотаєнко Даниїла Степанівна\nДаниїла Степанівна Ротаєнко\nДаниїла Ротаєнко\nРотаєнко Даниїла Степанівна\nЧеркаська область\nМонастирище\nМонастирищенський\nЧеркаська область\nЗагальний місцевий суд\nзаступник голови монастирищенського районного суду черкаської області\nРотаєнко Даниїла Степанівна\n2920\n224671\n15900\n18879\n224718\n59\n47\n2013\nChery Tiggo\n137000\n1845 куб. см., 97 кВт\n47\n224718\n18879\n59\n224671\n2920\n15900\nм. Монастирище\nЧеркаська область\n41.4\nм. Монастирище\nЧеркаська область\n23\nм. Монастирище\nЧеркаська область\n20.6\n3850\n2014","general":{"inn":"","name":"Даниїла","patronymic_unclear":false,"last_name_hidden":false,"family":[{"inn":"","inn_hidden":true,"relations_hidden":false,"family_name":"Ротаєнко А. В","relations_other":"","relations":"Дитина","name_hidden":true,"name_unclear":false}],"patronymic":"Степанівна","inn_hidden":true,"family_raw":"","last_name":"Ротаєнко","post":{"post_unclear":false,"region_unclear":false,"post":"заступник голови монастирищенського районного суду черкаської області","candidate":"","office_hidden":false,"region":"Черкаська область","post_hidden":false,"office":"Загальний місцевий суд","office_unclear":false},"last_name_unclear":false,"full_name":"Ротаєнко Даниїла Степанівна","addresses":[{"place_district":"Монастирищенський","place_city_hidden":false,"place_city":"Монастирище","place_city_type_hidden":false,"place_district_hidden":false,"place_city_type":"Місто","place_address_hidden":true,"place_address":"","place_hidden":false,"place":"Черкаська область"}],"full_name_suggest":{"output":"Ротаєнко Даниїла Степанівна","input":["Ротаєнко Даниїла Степанівна","Даниїла Степанівна Ротаєнко","Даниїла Ротаєнко"]}},"source":"VULYK","estate":{"23":[{"space_unclear":false,"costs":"","costs_comment":"","address_hidden":true,"region_hidden":false,"space_comment":"","space":"23","address":"м. Монастирище","region":"Черкаська область","address_unclear":false,"costs_rent_comment":"","space_units":"м²","costs_rent":""},{"space_unclear":false,"costs":"","costs_comment":"","address_hidden":false,"region_hidden":false,"space_comment":"","space":"","address":"","region":"","address_unclear":false,"costs_rent_comment":"","space_units":"","costs_rent":""},{"space":"","region":"","costs":"","costs_rent_comment":"","costs_comment":"","address_unclear":false,"space_comment":"","space_units":"","costs_rent":"","address":""},{"costs_rent":"","costs":"","costs_rent_comment":"","costs_comment":"","space_comment":"","space_units":"","space":"","address":""}],"25":[{"space_unclear":false,"costs":"","costs_comment":"","address_hidden":true,"region_hidden":false,"space_comment":"","space_hidden":false,"space":"20.6","address":"м. Монастирище","region":"Черкаська область","address_unclear":false,"costs_rent_comment":"","space_units":"м²","costs_rent":""}],"31":[{"space_unclear":false,"address_hidden":true,"region_hidden":false,"space_comment":"","space_hidden":false,"space":"41.4","address":"м. Монастирище","region":"Черкаська область","costs_property":"","costs_rent_comment":"","space_units":"м²","costs_property_comment":"","costs_rent":""}]},"intro":{"declaration_year":"2014","isnotdeclaration":"","declaration_year_unclear":false,"declaration_year_hidden":false}}