{"income":{"5":{"value":"193434","value_unclear":false,"value_hidden":false,"family_comment":"","family":"","comment":""},"6":{"value":"188804","family_comment":"","value_unclear":false,"family_unclear":false,"family":"","comment":""},"7":{"source_name_unclear":false,"value":"","family_hidden":false,"family_comment":"","source_name":"","family":"","comment":""},"8":{"family_comment":"","value":"","family":"","comment":""},"9":{"family_comment":"","value":"","family":"","comment":""},"10":{"family_comment":"","value":"","family":"","comment":""},"11":{"family_comment":"","value":"","family":"","comment":""},"12":{"family_comment":"","value":"","family":"","comment":""},"13":{"family_comment":"","value":"","family":"","comment":""},"14":{"family_comment":"","value":"","family":"","comment":""},"15":{"family_comment":"","value":"","family":"","comment":""},"16":{"family_comment":"","value":"","comment_unclear":false,"family":"","comment":""},"17":{"family_comment":"","family_unclear":false,"value":"","family":"","comment":""},"18":{"family_comment":"","value":"","family":"","comment":""},"19":{"value":"","family_hidden":false,"value_hidden":false,"family_comment":"","family":"","comment":""},"20":{"family_comment":"","value":"4630","comment_unclear":false,"family":"","comment":"Допомога на дитину одинокій матері"}},"vehicle":{"35":[{"brand_info":"1800 куб. см., 4710 мм","sum_rent_comment":"","year":"2007","sum_rent_unclear":false,"brand_info_hidden":false,"brand_info_unclear":false,"year_unclear":false,"sum_rent":"","sum":"","brand":"Toyota Avensis","sum_comment":"","sum_comment_unclear":false,"brand_hidden":false,"sum_unclear":false,"brand_unclear":false}],"36":[{"brand_info":"2450 куб. см., 4025 мм","sum_rent_comment":"","brand":"УАЗ 31512","sum_comment":"","year":"1989","sum":"","sum_rent":""}]},"id":"vulyk_67_155","banks":{"45":[{"sum_foreign_comment":"","sum":"370.86","sum_comment":"","sum_comment_unclear":false,"sum_hidden":false,"sum_foreign_units":"UAH","sum_foreign_hidden":false,"sum_units":"UAH","sum_comment_hidden":false,"sum_unclear":false,"sum_foreign":""}]},"declaration":{"additional_info_text":"","notfull_lostpages":"","date":"2015-03-30T00:00:00","notfull":"","additional_info":"","url":"http://static.declarations.com.ua/declarations/chosen_ones/mega_batch/kozlenko_halyna_oleksandrivna.pdf"},"liabilities":{"54":{"sum_foreign_comment":"","sum_foreign_hidden":false,"sum_comment":"","sum_comment_unclear":false,"sum_hidden":false,"sum":"","sum_unclear":false,"sum_foreign":""},"55":{"sum_foreign_comment":"","sum":"","sum_comment":"","sum_foreign":""},"56":{"sum_foreign_comment":"","sum_foreign_hidden":false,"sum_comment":"","sum_hidden":false,"sum":"","sum_unclear":false,"sum_foreign":""},"57":{"sum_foreign_comment":"","sum_foreign_hidden":false,"sum_comment":"","sum_comment_unclear":false,"sum_hidden":false,"sum_comment_hidden":false,"sum_unclear":false,"sum":"6753","sum_foreign":""},"58":{"sum_foreign_comment":"","sum_foreign_hidden":false,"sum_comment":"","sum_comment_unclear":false,"sum_hidden":false,"sum_comment_hidden":false,"sum_unclear":false,"sum":"","sum_foreign":""},"59":{"sum_foreign_comment":"","sum":"","sum_hidden":false,"sum_comment":"","sum_foreign":""},"60":{"sum_foreign_comment":"","sum":"","sum_comment":"","sum_foreign":""},"61":{"sum_foreign_comment":"","sum_foreign_hidden":false,"sum_comment":"","sum_hidden":false,"sum":"","sum_foreign":""},"62":{"sum_foreign_comment":"","sum":"","sum_hidden":false,"sum_comment":"","sum_foreign":""},"63":{"sum_foreign_comment":"","sum":"","sum_comment":"","sum_comment_unclear":false,"sum_hidden":false,"sum_unclear":false,"sum_foreign":""},"64":{"sum_foreign_comment":"","sum":"","sum_comment":"","sum_hidden":false,"sum_unclear":false,"sum_foreign":""}},"ft_src":"6753\nсуддя солом'янського районного суду міста києва\nм. Київ\nЗагальний місцевий суд\nГалина\nКозленко М. О., 18. 05. 2004\nДитина\nОлександрівна\nКозленко Галина Олександрівна\nКозленко\nКозленко Галина Олександрівна\nГалина Олександрівна Козленко\nГалина Козленко\nКозленко Галина Олександрівна\n1800 куб. см., 4710 мм\nToyota Avensis\n2007\n2450 куб. см., 4025 мм\n1989\nУАЗ 31512\n370.86\n2014\n1800 куб. см., 4710 мм\nToyota Avensis\n2007\n2450 куб. см., 4025 мм\nУАЗ 31512\n1989\n370.86\n11.1\n17\nЗагальний місцевий суд\nсуддя солом'янського районного суду міста києва\nм. Київ\nДитина\nКозленко М. О., 18. 05. 2004\nКозленко Галина Олександрівна\nГалина Олександрівна Козленко\nГалина Козленко\nКозленко Галина Олександрівна\nКозленко Галина Олександрівна\nГалина\nКозленко\nОлександрівна\n6753\n188804\nДопомога на дитину одинокій матері\n4630\n193434\n2014\n6753\n11.1\n17\nДитина\nКозленко М. О., 18. 05. 2004\nОлександрівна\nКозленко\nГалина\nКозленко Галина Олександрівна\nГалина Олександрівна Козленко\nГалина Козленко\nКозленко Галина Олександрівна\nм. Київ\nсуддя солом'янського районного суду міста києва\nЗагальний місцевий суд\nКозленко Галина Олександрівна\n188804\n193434\nДопомога на дитину одинокій матері\n4630\n2007\nToyota Avensis\n1800 куб. см., 4710 мм\nУАЗ 31512\n2450 куб. см., 4025 мм\n1989\nДопомога на дитину одинокій матері\n4630\n193434\n188804\n17\n11.1\n370.86\n2014","general":{"inn":"","name":"Галина","patronymic_unclear":false,"last_name_hidden":false,"family":[{"inn":"","inn_hidden":false,"relations_unclear":false,"relations_hidden":false,"relations_other":"","relations":"Дитина","name_hidden":true,"inn_unclear":false,"family_name":"Козленко М. О., 18. 05. 2004","name_unclear":false}],"patronymic":"Олександрівна","inn_hidden":true,"family_raw":"","inn_unclear":false,"post":{"post_unclear":false,"post":"суддя солом'янського районного суду міста києва","post_hidden":false,"region":"м. Київ","region_hidden":false,"office":"Загальний місцевий суд","office_hidden":false,"office_unclear":false},"last_name_unclear":false,"full_name":"Козленко Галина Олександрівна","addresses":[{"place_city_type_hidden":true,"place_district_hidden":true,"place_city_type":"","place_city_hidden":true,"place_address_unclear":false,"place_address":"","place":"","place_district":"","place_unclear":false,"place_city":"","place_city_unclear":false,"place_hidden":true,"place_address_hidden":true,"place_district_unclear":false}],"last_name":"Козленко","full_name_suggest":{"output":"Козленко Галина Олександрівна","input":["Козленко Галина Олександрівна","Галина Олександрівна Козленко","Галина Козленко"]},"name_unclear":false},"source":"VULYK","estate":{"23":[{"space_hidden":false,"costs":"","costs_comment":"","costs_hidden":false,"address_hidden":true,"region_hidden":true,"space_comment":"","space_unclear":false,"space":"11.1","address":"","region":"","address_unclear":false,"space_units_unclear":false,"costs_rent_hidden":false,"space_comment_unclear":false,"space_units":"га","costs_rent":"","costs_rent_comment":""}],"25":[{"space_unclear":false,"costs":"","costs_comment":"","costs_hidden":false,"address_hidden":true,"region_hidden":true,"space_comment":"","space":"17","address":"","region":"","address_unclear":false,"space_units_unclear":false,"space_comment_unclear":false,"space_units":"м²","costs_rent":"","costs_rent_comment":""}]},"intro":{"declaration_year":"2014","isnotdeclaration":"","declaration_year_hidden":false}}