{"income":{"5":{"family_comment":"","value":"254246","family":"46912","comment":""},"6":{"family_comment":"","value":"254246","family":"44612","comment":""},"7":{"value":"","comment_hidden":false,"family_comment":"","source_name":"","family":"","comment":"","source_name_hidden":false},"8":{"family_comment":"","value":"","family_hidden":false,"comment":"","family":""},"9":{"value":"","family_comment":"","value_unclear":false,"family_unclear":false,"family":"","comment":""},"10":{"family_comment":"","value":"","family":"","comment":""},"11":{"family_comment":"","value":"","family":"","comment":""},"12":{"family_comment":"","value":"","family":"","comment":""},"13":{"family_comment":"","value":"","family":"","comment":""},"14":{"family_comment":"","value":"","family":"","comment":""},"15":{"family_comment":"","value":"","family":"","comment":""},"16":{"family_comment":"","value":"","family":"","comment":""},"17":{"family_comment":"","value":"","family":"","comment":""},"18":{"family_comment":"","value":"","family":"","comment":""},"19":{"family_comment":"","value":"","family":"","comment":""},"20":{"value":"","value_unclear":false,"family_hidden":false,"family_comment":"","family":"2300","comment":""},"22":[{"country_hidden":false,"cur":"7000","cur_units":"RUB","uah_equal_hidden":false,"uah_equal":"2700","cur_hidden":false,"country":"Росія","country_comment":""}]},"vehicle":{"35":[{"brand_info":"1.3 , б/у","sum_rent_comment":"","year":"1992","brand_info_hidden":false,"brand_info_unclear":false,"year_unclear":false,"sum_rent":"","sum":"","brand":"ВАЗ 21063","sum_comment":"","sum_comment_unclear":false,"brand_hidden":false,"brand_unclear":false},{"brand_info":"2.4 , б/у","sum_rent_comment":"","brand":"Honda CR-V","sum_comment":"","year":"2008","sum":"","sum_rent":""}]},"id":"vulyk_109_74","declaration":{"additional_info_text":"","notfull_lostpages":"","date":"2016-03-28T00:00:00","notfull":"","additional_info":"","url":"http://static.declarations.com.ua/declarations/chosen_ones/judges_batch/2531_bobrovych_volodymyr_mykolaiovych_2015.pdf"},"liabilities":{"54":{"sum_foreign_comment":"","sum":"","sum_comment":"","sum_hidden":false,"sum_comment_hidden":false,"sum_unclear":false,"sum_foreign":""},"55":{"sum_foreign_comment":"","sum":"","sum_comment":"","sum_comment_unclear":false,"sum_foreign":""},"56":{"sum_foreign_comment":"","sum":"","sum_comment":"","sum_foreign":""},"57":{"sum_foreign_comment":"","sum_comment_hidden":false,"sum":"","sum_comment":"","sum_foreign":""},"58":{"sum_foreign_comment":"","sum_comment_hidden":false,"sum":"","sum_comment":"","sum_foreign":""},"59":{"sum_foreign_comment":"","sum":"","sum_comment":"","sum_foreign":""},"60":{"sum_foreign_comment":"","sum":"","sum_comment":"","sum_foreign":""},"61":{"sum_foreign_comment":"","sum":"","sum_comment":"","sum_foreign":""},"62":{"sum_foreign_comment":"","sum":"","sum_comment":"","sum_foreign":""},"63":{"sum_foreign_comment":"","sum":"","sum_comment":"","sum_foreign":""},"64":{"sum_foreign_comment":"","sum":"","sum_comment":"","sum_foreign":""}},"ft_src":"голова господарського суду житомирської області\nЖитомирська область\nГосподарський місцевий суд\nВолодимир\nБобрович Г. М\nПодружжя\nМиколайович\nБобрович Володимир Миколайович\nБобрович\nБобрович Володимир Миколайович\nВолодимир Миколайович Бобрович\nВолодимир Бобрович\nБобрович Володимир Миколайович\n1.3 , б/у\nВАЗ 21063\n1992\n2.4 , б/у\n2008\nHonda CR-V\n24\n.087\n.25\n52.8\n.374\n3/4 частини від 72  - 54\n72\n1/4 частина від 72 кв. м\n72\n49.5\n2015\n44612\n254246\n46912\n254246\n2300\nРосія\n2700\nRUB\n7000\n1.3 , б/у\nВАЗ 21063\n1992\n2.4 , б/у\nHonda CR-V\n2008\n2015\nПодружжя\nБобрович Г. М\nБобрович Володимир Миколайович\nВолодимир Миколайович Бобрович\nВолодимир Бобрович\nБобрович Володимир Миколайович\nВолодимир\nБобрович Володимир Миколайович\nБобрович\nГосподарський місцевий суд\nЖитомирська область\nголова господарського суду житомирської області\nМиколайович\n254246\n44612\n7000\nРосія\n2700\nRUB\n2300\n254246\n46912\n24\n72\n1/4 частина від 72 кв. м\n49.5\n.374\n.087\n.25\n52.8\n3/4 частини від 72  - 54\n72\nПодружжя\nБобрович Г. М\nВолодимир\nМиколайович\nБобрович\nБобрович Володимир Миколайович\nВолодимир Миколайович Бобрович\nВолодимир Бобрович\nБобрович Володимир Миколайович\nЖитомирська область\nГосподарський місцевий суд\nголова господарського суду житомирської області\nБобрович Володимир Миколайович\n1992\nВАЗ 21063\n1.3 , б/у\nHonda CR-V\n2.4 , б/у\n2008\n2300\n46912\n254246\nРосія\nRUB\n2700\n7000\n44612\n254246\n3/4 частини від 72  - 54\n72\n.374\n52.8\n24\n1/4 частина від 72 кв. м\n72\n49.5\n.087\n.25\n2015","general":{"name_hidden":false,"name":"Володимир","inn":"","inn_unclear":false,"family":[{"inn":"","relations":"Подружжя","relations_hidden":false,"inn_hidden":false,"relations_other":"","name_hidden":false,"family_name":"Бобрович Г. М","name_unclear":false}],"inn_hidden":true,"family_raw":"","last_name":"Бобрович","post":{"region_unclear":false,"region":"Житомирська область","post":"голова господарського суду житомирської області","region_hidden":false,"office":"Господарський місцевий суд","office_hidden":false,"office_unclear":false},"full_name":"Бобрович Володимир Миколайович","patronymic":"Миколайович","full_name_suggest":{"output":"Бобрович Володимир Миколайович","input":["Бобрович Володимир Миколайович","Володимир Миколайович Бобрович","Володимир Бобрович"]}},"source":"VULYK","estate":{"23":[{"space_unclear":false,"costs":"","costs_rent_unclear":false,"costs_comment":"","address_hidden":false,"region_hidden":true,"space_comment":"","space":".374","address":"","region":"","costs_rent_comment":"","space_units":"га","costs_rent":""}],"24":[{"costs_rent":"","region":"","costs":"","costs_rent_comment":"","costs_comment":"","address_hidden":false,"region_hidden":true,"space_comment":"","space_units":"м²","space":"52.8","address":""}],"25":[{"space_unclear":false,"costs":"","costs_comment":"","address_hidden":false,"region_hidden":true,"space_comment":"1/4 частина від 72 кв. м","space_hidden":false,"space":"72","address":"","region":"","costs_rent_comment":"","space_units":"м²","space_units_hidden":false,"costs_rent":""},{"costs_rent":"","region":"","costs":"","costs_rent_comment":"","costs_comment":"","address_hidden":false,"region_hidden":false,"space_comment":"","space_units":"м²","space":"49.5","address":""}],"27":[{"space_unclear":false,"costs":"","costs_rent_unclear":false,"costs_comment":"","address_hidden":false,"region_hidden":true,"space_comment":"","space":"24","address":"","region":"","costs_rent_comment":"","space_units":"м²","costs_rent":""}],"29":[{"space_unclear":false,"address_hidden":true,"region_hidden":true,"space_comment":"","space":".087","address":"","region":"","costs_property":"","costs_rent_comment":"","space_units":"га","costs_property_comment":"","costs_rent":""},{"costs_rent":"","costs_property":"","costs_rent_comment":"","space_comment":"","costs_property_comment":"","space_units":"га","space":".25","address":""}],"30":[{"costs_rent":"","space_hidden":false,"costs_property":"","costs_rent_comment":"","address_hidden":false,"region_hidden":true,"space_comment":"","costs_property_comment":"","space_units":"м²","space":"","address":""}],"31":[{"space_hidden":false,"costs_property_comment":"","address_hidden":true,"region_hidden":true,"space_comment":"3/4 частини від 72  - 54","space":"72","address":"","region":"","costs_property":"","costs_rent_comment":"","space_units":"м²","space_units_hidden":false,"costs_rent":""}]},"intro":{"declaration_year":"2015","isnotdeclaration":""}}