{"income":{"5":{"family_comment":"","value":"216424","family":"16612","comment":""},"6":{"family_comment":"","value":"216424","family":"16612","comment":""},"7":{"value":"","comment_hidden":false,"family_comment":"","source_name":"","family":"","comment":"","source_name_hidden":false},"8":{"family_comment":"","value":"","family_hidden":false,"comment":"","family":""},"9":{"value":"","family_comment":"","value_unclear":false,"family_unclear":false,"family":"","comment":""},"10":{"family_comment":"","value":"","family":"","comment":""},"11":{"family_comment":"","value":"","family":"","comment":""},"12":{"family_comment":"","value":"","family":"","comment":""},"13":{"family_comment":"","value":"","family":"","comment":""},"14":{"family_comment":"","value":"","family":"","comment":""},"15":{"family_comment":"","value":"","family":"","comment":""},"16":{"family_comment":"","value":"","family":"","comment":""},"17":{"family_comment":"","value":"","family":"","comment":""},"18":{"family_comment":"","value":"","family":"","comment":""},"19":{"family_comment":"","value":"","family":"","comment":""},"20":{"value":"","value_unclear":false,"family_hidden":false,"family_comment":"","family":"","comment":""}},"vehicle":{"35":[{"brand_info":"1.9997, 150 к. с, довжина 460 см, д. н. АЕ 1805 СМ, інше право користування","sum_rent_comment":"","year":"2008","brand_info_hidden":false,"brand_info_unclear":false,"year_unclear":false,"sum_rent":"","sum":"","brand":"Honda","sum_comment":"","sum_comment_unclear":false,"brand_hidden":false,"brand_unclear":false}],"40":[{"brand_info":"1.9997, 150 к. с, довжина 460 см, д. н. АЕ 1805 СМ, власність","sum_rent_comment":"","brand":"Honda","sum_comment":"","year":"2008","brand_info_unclear":false,"sum":"","sum_rent":""}]},"id":"vulyk_109_52","declaration":{"additional_info_text":"","notfull_lostpages":"","date":"2016-03-16T00:00:00","notfull":"","additional_info":"","url":"http://static.declarations.com.ua/declarations/chosen_ones/judges_batch/2509_manko_hennadii_valeriiovych_2015.pdf"},"liabilities":{"54":{"sum_foreign_comment":"","sum":"","sum_comment":"","sum_hidden":false,"sum_comment_hidden":false,"sum_unclear":false,"sum_foreign":""},"55":{"sum_foreign_comment":"","sum":"","sum_comment":"","sum_comment_unclear":false,"sum_foreign":""},"56":{"sum_foreign_comment":"","sum":"600","sum_comment":"","sum_foreign":""},"57":{"sum_foreign_comment":"","sum_comment_hidden":false,"sum":"","sum_comment":"","sum_foreign":""},"58":{"sum_foreign_comment":"","sum_comment_hidden":false,"sum":"","sum_comment":"","sum_foreign":""},"59":{"sum_foreign_comment":"","sum":"","sum_comment":"","sum_foreign":""},"60":{"sum_foreign_comment":"","sum":"689","sum_comment":"","sum_foreign":""},"61":{"sum_foreign_comment":"","sum":"","sum_comment":"","sum_foreign":""},"62":{"sum_foreign_comment":"","sum":"12500","sum_comment":"","sum_foreign":""},"63":{"sum_foreign_comment":"","sum":"","sum_comment":"","sum_foreign":""},"64":{"sum_foreign_comment":"","sum":"","sum_comment":"","sum_foreign":""}},"ft_src":"12500\n600\n689\nсуддя господарського суду дніпропетровської області\nДніпропетровська область\nГосподарський місцевий суд\nГеннадій\nГрівковська С. О\nПодружжя\nМанько В. Г\nДитина\nВалерійович\nМанько Геннадій Валерійович\nГеннадій Валерійович Манько\nГеннадій Манько\nМанько Геннадій Валерійович\nМанько Геннадій Валерійович\nМанько\n1.9997, 150 к. с, довжина 460 см, д. н. АЕ 1805 СМ, інше право користування\nHonda\n2008\n1.9997, 150 к. с, довжина 460 см, д. н. АЕ 1805 СМ, власність\n2008\nHonda\n48.3\n600\n27.1\n.0408\n.0469\n.1\n85\n2015\n16612\n216424\n16612\n216424\n1.9997, 150 к. с, довжина 460 см, д. н. АЕ 1805 СМ, інше право користування\nHonda\n2008\n1.9997, 150 к. с, довжина 460 см, д. н. АЕ 1805 СМ, власність\n2008\nHonda\n2015\nМанько Геннадій Валерійович\nГеннадій Валерійович Манько\nГеннадій Манько\nМанько Геннадій Валерійович\nГеннадій\nПодружжя\nГрівковська С. О\nДитина\nМанько В. Г\nМанько Геннадій Валерійович\nВалерійович\nГосподарський місцевий суд\nДніпропетровська область\nсуддя господарського суду дніпропетровської області\nМанько\n689\n600\n12500\n216424\n16612\n216424\n16612\n.0408\n.0469\n.1\n27.1\n600\n48.3\n85\n600\n12500\n689\nПодружжя\nГрівковська С. О\nДитина\nМанько В. Г\nВалерійович\nМанько\nГеннадій\nМанько Геннадій Валерійович\nГеннадій Валерійович Манько\nГеннадій Манько\nМанько Геннадій Валерійович\nДніпропетровська область\nГосподарський місцевий суд\nсуддя господарського суду дніпропетровської області\nМанько Геннадій Валерійович\n2008\nHonda\n1.9997, 150 к. с, довжина 460 см, д. н. АЕ 1805 СМ, інше право користування\n2008\n1.9997, 150 к. с, довжина 460 см, д. н. АЕ 1805 СМ, власність\nHonda\n16612\n216424\n16612\n216424\n48.3\n600\n27.1\n85\n.0408\n.0469\n.1\n2015","general":{"name_hidden":false,"name":"Геннадій","inn":"","family":[{"inn":"","relations":"Подружжя","relations_hidden":false,"inn_hidden":true,"relations_other":"","name_hidden":false,"family_name":"Грівковська С. О","name_unclear":true},{"inn":"","relations":"Дитина","relations_other":"","inn_hidden":false,"family_name":"Манько В. Г","name_hidden":false,"name_unclear":false}],"patronymic":"Валерійович","inn_hidden":true,"family_raw":"","inn_unclear":false,"post":{"region_unclear":false,"region":"Дніпропетровська область","post":"суддя господарського суду дніпропетровської області","region_hidden":false,"office":"Господарський місцевий суд","office_hidden":false,"office_unclear":false},"full_name":"Манько Геннадій Валерійович","addresses":[{"place_district":"","place_city_hidden":true,"place_city":"","place_city_type_hidden":true,"place_district_hidden":true,"place_city_type":"","place_address_hidden":true,"place_address":"","place_hidden":true,"place":""}],"last_name":"Манько","full_name_suggest":{"output":"Манько Геннадій Валерійович","input":["Манько Геннадій Валерійович","Геннадій Валерійович Манько","Геннадій Манько"]}},"source":"VULYK","estate":{"27":[{"space_unclear":false,"costs":"","costs_rent_unclear":true,"costs_comment":"","address_hidden":false,"region_hidden":true,"space_comment":"","space":"27.1","address":"","region":"","costs_rent_comment":"","space_units":"м²","costs_rent":"600"}],"29":[{"space_unclear":false,"address_hidden":true,"region_hidden":true,"space_comment":"","space":".0408","address":"","region":"","costs_property":"","costs_rent_comment":"","space_units":"га","costs_property_comment":"","costs_rent":""},{"costs_rent":"","costs_property":"","costs_rent_comment":"","space_comment":"","costs_property_comment":"","space_units":"га","space":".0469","address":""},{"costs_rent":"","costs_property":"","costs_rent_comment":"","space_comment":"","costs_property_comment":"","space_units":"га","space":".1","address":""}],"31":[{"space_hidden":false,"costs_property_comment":"","address_hidden":true,"region_hidden":true,"space_comment":"","space":"48.3","address":"","region":"","costs_property":"","costs_rent_comment":"","space_units":"м²","space_units_hidden":false,"costs_rent":""}],"32":[{"costs_rent":"","region":"","costs_property":"","costs_rent_comment":"","address_hidden":true,"region_hidden":true,"space_comment":"","costs_property_comment":"","space_units":"м²","space":"85","address":""}]},"intro":{"declaration_year":"2015","isnotdeclaration":""}}