{"income":{"5":{"family_comment":"","value":"252724.68","family":"","comment":""},"6":{"value":"239326.68","comment_hidden":false,"family_comment":"","family":"","comment":"","family_comment_hidden":false},"7":{"value":"","comment_unclear":false,"family_comment":"","source_name":"","family":"","comment":""},"8":{"family_comment":"","value":"","family":"","comment":""},"9":{"family_comment":"","value":"","family":"","comment":""},"10":{"family_comment":"","value":"13398","family_hidden":false,"comment":"","family":""},"11":{"family_comment":"","value":"","family":"","comment":""},"12":{"family_comment":"","value":"","family":"","comment":""},"13":{"family_comment":"","value":"","family":"","comment":""},"14":{"family_comment":"","value":"","family":"","comment":""},"15":{"family_comment":"","value":"","family":"","comment":""},"16":{"family_comment":"","value":"","family":"","comment":""},"17":{"family_comment":"","value":"","family":"","comment":""},"18":{"family_comment":"","value":"","family":"","comment":""},"19":{"family_comment":"","value":"","family":"","comment":""},"20":{"value":"","value_unclear":false,"family_hidden":false,"family_comment":"","family":"","comment":""}},"vehicle":{"35":[{"brand_info":"1.4 л","sum_rent_comment":"","brand":"Hyundai Accent","sum_comment":"","year":"2006","brand_info_unclear":false,"sum":"","sum_rent":""}]},"id":"vulyk_83_35","declaration":{"additional_info_text":"","notfull_lostpages":"","date":"2015-03-19T00:00:00","notfull":"","additional_info":"","url":"http://static.declarations.com.ua/declarations/chosen_ones/judges_batch/2305_petrova_iryna_mykhailivna.pdf"},"liabilities":{"54":{"sum_foreign_comment":"","sum":"","sum_comment":"","sum_foreign":""},"55":{"sum_foreign_comment":"","sum":"","sum_comment":"","sum_foreign":""},"56":{"sum_foreign_comment":"","sum":"","sum_comment":"","sum_foreign":""},"57":{"sum_foreign_comment":"","sum":"129182.41","sum_comment":"","sum_foreign":""},"58":{"sum_foreign_comment":"","sum":"21711.98","sum_comment":"","sum_foreign":""},"59":{"sum_foreign_comment":"","sum":"","sum_comment":"","sum_foreign":""},"60":{"sum_foreign_comment":"","sum":"1647.92","sum_comment":"","sum_foreign":""},"61":{"sum_foreign_comment":"","sum":"","sum_comment":"","sum_foreign":""},"62":{"sum_foreign_comment":"","sum":"","sum_comment":"","sum_foreign":""},"63":{"sum_foreign_comment":"","sum":"","sum_comment":"","sum_foreign":""},"64":{"sum_foreign_comment":"","sum":"","sum_comment":"","sum_foreign":""}},"ft_src":"129182.41\n21711.98\n1647.92\nсуддя апеляційного суду кіровоградської області\nКіровоградська область\nЗагальний апеляційний суд\nІрина\nМихайлівна\nПетрова\nПетрова Ірина Михайлівна\nПетрова Ірина Михайлівна\nІрина Михайлівна Петрова\nІрина Петрова\nПетрова Ірина Михайлівна\n1.4 л\n2006\nHyundai Accent\nне є приватною власністю\n592.8\nоренда\nдоговір оренди від 31. 03. 14\n.0024\n52.6\n56.23\n2014\n239326.68\n13398\n252724.68\n1.4 л\nHyundai Accent\n2006\n592.8\nне є приватною власністю\n.0024\nоренда\nдоговір оренди від 31. 03. 14\n52.6\n56.23\nПетрова Ірина Михайлівна\nІрина Михайлівна Петрова\nІрина Петрова\nПетрова Ірина Михайлівна\nІрина\nПетрова Ірина Михайлівна\nМихайлівна\nЗагальний апеляційний суд\nКіровоградська область\nсуддя апеляційного суду кіровоградської області\nПетрова\n21711.98\n129182.41\n1647.92\n239326.68\n252724.68\n13398\n2014\n21711.98\n129182.41\n1647.92\nМихайлівна\nПетрова\nІрина\nПетрова Ірина Михайлівна\nІрина Михайлівна Петрова\nІрина Петрова\nПетрова Ірина Михайлівна\nКіровоградська область\nЗагальний апеляційний суд\nсуддя апеляційного суду кіровоградської області\nПетрова Ірина Михайлівна\n2006\n1.4 л\nHyundai Accent\n13398\n252724.68\n239326.68\n56.23\n592.8\nне є приватною власністю\nдоговір оренди від 31. 03. 14\nоренда\n.0024\n52.6\n2014","general":{"inn":"","name":"Ірина","inn_unclear":false,"patronymic":"Михайлівна","inn_hidden":true,"family_raw":"","last_name":"Петрова","post":{"post_unclear":false,"post":"суддя апеляційного суду кіровоградської області","candidate":"","region":"Кіровоградська область","office":"Загальний апеляційний суд","office_unclear":false},"last_name_unclear":false,"full_name":"Петрова Ірина Михайлівна","addresses":[{"place_city_type_unclear":false,"place_address":"","place_district_hidden":false,"place_city_type":"","place_address_hidden":false,"place_address_unclear":false,"place_city_type_hidden":false,"place":"","place_district":"","place_city_hidden":false,"place_city":"","place_city_unclear":false,"place_hidden":true}],"full_name_suggest":{"output":"Петрова Ірина Михайлівна","input":["Петрова Ірина Михайлівна","Ірина Михайлівна Петрова","Ірина Петрова"]}},"source":"VULYK","estate":{"23":[{"space_hidden":false,"costs":"","costs_comment":"не є приватною власністю","address_hidden":false,"region_hidden":true,"space_comment":"","space":"592.8","address":"","space_comment_unclear":true,"region":"","address_unclear":false,"costs_rent_comment":"","costs_unclear":false,"costs_comment_hidden":false,"space_units":"м²","costs_rent":""},{"costs":"","costs_comment":"","region_hidden":false,"space_comment":"оренда","space":".0024","address":"","costs_unclear":false,"region":"","address_unclear":false,"costs_rent_comment":"договір оренди від 31. 03. 14","space_comment_unclear":true,"space_units":"га","costs_rent":""}],"24":[{"space_hidden":false,"costs":"","costs_comment":"","address_hidden":false,"region_hidden":true,"space_comment":"","space":"52.6","address":"","region":"","costs_rent_comment":"","space_units":"м²","costs_rent":""}],"25":[{"region_unclear":false,"space_hidden":false,"costs":"","costs_comment":"","address_hidden":false,"region_hidden":true,"space_comment":"","space_unclear":false,"space":"56.23","address":"","region":"","costs_rent_comment":"","space_comment_unclear":false,"space_units":"м²","costs_rent":""}]},"intro":{"declaration_year":"2014"}}