{"id":"vulyk_100_107","ft_src":"м. Богуслав\n.003\nКиївська область\nКиївська область\nБогуславський р-н, с. Медвин\n52.2\nКиївська область\nБогуславський р-н, с. Медвин\n455\n1/4\nКиївська область\nм. Богуслав\n10.47\nКиївська область\n1/3\nм. Богуслав\n17\n1/4\nм. Богуслав\n10.47\nКиївська область\n1/3\nм. Богуслав\n17\nКиївська область\n2014\n239789\n14412\n278968\n14412\n39179\n239789\n39179\n14412\n278968\n14412\nПодружжя\nЯкутюк Т. К\nСтаніславович\nКиївська область\n09700\nБогуслав\nБогуславський\nЯкутюк\nЯкутюк Володимир Станіславович\nВолодимир Станіславович Якутюк\nВолодимир Якутюк\nЯкутюк Володимир Станіславович\nЯкутюк Володимир Станіславович\nВолодимир\nЗагальний місцевий суд\nКиївська область\nзаступник голови богуславського районного суду київської області\n20000\n.003\nКиївська область\nм. Богуслав\nБогуславський р-н, с. Медвин\n455\nКиївська область\n52.2\nКиївська область\nБогуславський р-н, с. Медвин\n10.47\n1/4\nКиївська область\nм. Богуслав\nм. Богуслав\n17\n1/3\nКиївська область\n10.47\n1/4\nКиївська область\nм. Богуслав\nм. Богуслав\n17\n1/3\nКиївська область\n2014\n20000\nЯкутюк Т. К\nПодружжя\n09700\nБогуслав\nКиївська область\nБогуславський\nСтаніславович\nЯкутюк\nКиївська область\nЗагальний місцевий суд\nзаступник голови богуславського районного суду київської області\nЯкутюк Володимир Станіславович\nЯкутюк Володимир Станіславович\nВолодимир Станіславович Якутюк\nВолодимир Якутюк\nЯкутюк Володимир Станіславович\nВолодимир","estate":{"23":[{"address":"м. Богуслав","space_units":"га","costs_comment":"","space_unclear":false,"region_hidden":false,"space_comment":"","address_hidden":true,"costs":"","address_unclear":false,"space_comment_unclear":false,"costs_comment_unclear":false,"costs_rent_comment":"","space":".003","region":"Київська область","costs_rent":""}],"25":[{"address":"м. Богуслав","space_units":"м²","costs_comment":"","space_unclear":false,"region_hidden":false,"space_comment":"1/4","address_hidden":true,"costs":"","address_unclear":false,"space_comment_unclear":false,"costs_comment_unclear":false,"costs_rent_comment":"","space":"10.47","region":"Київська область","costs_rent":""},{"costs":"","address":"м. Богуслав","space_units":"м²","costs_rent_comment":"","space":"17","space_comment":"1/3","region_hidden":false,"costs_comment":"","region":"Київська область","costs_rent":""}],"29":[{"costs_property_comment":"","address":"Богуславський р-н, с. Медвин","space_units":"м²","space_unclear":false,"region_hidden":false,"costs_property":"","space_comment":"","address_hidden":true,"address_unclear":false,"costs_rent_comment":"","space":"455","region_unclear":false,"region":"Київська область","costs_rent":""}],"30":[{"costs_property_comment":"","address":"Богуславський р-н, с. Медвин","space_units":"м²","costs_rent_comment":"","space":"52.2","region":"Київська область","region_hidden":false,"costs_property":"","space_comment":"","address_hidden":true,"costs_rent":""}],"31":[{"costs_property_comment":"","address":"м. Богуслав","space_units":"м²","space_unclear":false,"region_hidden":false,"costs_property":"","space_comment":"1/4","address_hidden":true,"address_unclear":false,"space_comment_unclear":false,"costs_rent_comment":"","space":"10.47","costs_property_comment_unclear":false,"region_unclear":false,"region":"Київська область","costs_rent":""},{"costs_property_comment":"","address":"м. Богуслав","space_units":"м²","costs_rent_comment":"","space":"17","region":"Київська область","region_hidden":false,"costs_property":"","space_comment":"1/3","region_unclear":false,"costs_rent":""}]},"source":"VULYK","income":{"5":{"family_comment":"","family":"14412","comment":"","value_unclear":false,"family_unclear":false,"value":"278968"},"6":{"family_comment":"","value":"239789","family":"","comment":"","value_unclear":false},"7":{"family_comment":"","comment":"","family":"","value_unclear":false,"value":"","source_name":""},"8":{"family_comment":"","value":"","family":"","comment":""},"9":{"family_comment":"","family":"","comment":"","value_unclear":false,"family_unclear":false,"value":""},"10":{"family_comment":"","comment_unclear":false,"value":"","family":"","comment":""},"11":{"family_comment":"","value":"","family":"","comment":""},"12":{"family_comment":"","value":"","family":"","comment":""},"13":{"family_comment":"","value":"","family":"","comment":"","value_unclear":false},"14":{"family_comment":"","value":"","family":"","comment":""},"15":{"family_comment":"","value":"","family":"","comment":""},"16":{"family_comment":"","value":"","family_unclear":false,"family":"","comment":""},"17":{"family_comment":"","value":"","family_unclear":false,"family":"","comment":""},"18":{"family_comment":"","value":"","family":"","comment":""},"19":{"family_comment":"","value":"","family":"","comment":""},"20":{"family":"14412","family_comment":"","comment":"","value_hidden":false,"value_unclear":false,"value":"39179","comment_unclear":false,"family_unclear":false,"family_hidden":false}},"general":{"inn":"","addresses":[{"place_city_type":"Місто","place_city_type_hidden":false,"place_hidden":false,"place_city_hidden":false,"place_district_hidden":false,"place_district":"Богуславський","place_city_unclear":false,"place":"Київська область","place_city":"Богуслав","place_address_hidden":true,"place_address":"09700"}],"last_name":"Якутюк","full_name":"Якутюк Володимир Станіславович","family":[{"inn":"","family_name":"Якутюк Т. К","name_unclear":false,"inn_hidden":true,"name_hidden":true,"relations":"Подружжя"}],"patronymic":"Станіславович","inn_hidden":true,"name":"Володимир","post":{"post_hidden":false,"office":"Загальний місцевий суд","post":"заступник голови богуславського районного суду київської області","office_unclear":false,"region_unclear":false,"region":"Київська область","post_unclear":false},"family_raw":"","full_name_suggest":{"input":["Якутюк Володимир Станіславович","Володимир Станіславович Якутюк","Володимир Якутюк"],"output":"Якутюк Володимир Станіславович"}},"liabilities":{"54":{"sum_comment":"","sum":"","sum_foreign_comment":"","sum_foreign":"","sum_unclear":false,"sum_comment_hidden":false},"55":{"sum_comment":"","sum_foreign_comment":"","sum_foreign":"","sum":""},"56":{"sum_comment":"","sum_foreign_comment":"","sum_foreign":"","sum_unclear":false,"sum":"20000"},"57":{"sum_comment_unclear":false,"sum_comment":"","sum":"","sum_foreign_comment":"","sum_foreign":"","sum_unclear":false,"sum_comment_hidden":false},"58":{"sum_comment":"","sum":"","sum_foreign_comment":"","sum_foreign":"","sum_unclear":false,"sum_comment_hidden":false},"59":{"sum_comment":"","sum_foreign_comment":"","sum_foreign":"","sum":""},"60":{"sum_comment":"","sum_foreign_comment":"","sum_foreign":"","sum":"","sum_comment_hidden":false},"61":{"sum_comment":"","sum_foreign_comment":"","sum_foreign":"","sum":""},"62":{"sum_comment":"","sum_foreign_comment":"","sum_foreign":"","sum_unclear":false,"sum":""},"63":{"sum_comment":"","sum_foreign_comment":"","sum_foreign":"","sum":"","sum_comment_hidden":false},"64":{"sum_comment":"","sum_foreign_comment":"","sum_foreign":"","sum":"","sum_comment_hidden":false}},"declaration":{"notfull_lostpages":"","additional_info_text":"","additional_info":"","date":"2015-03-24T00:00:00","notfull":"","url":"http://static.declarations.com.ua/declarations/chosen_ones/judges_batch/4311_iakutiuk_volodymyr_stanislavovych.pdf"},"intro":{"declaration_year":"2014"}}