{"income":{"5":{"value":"202855","family_comment":"","value_unclear":false,"family_unclear":false,"family":"","comment":""},"6":{"family_comment":"","value":"202855","value_unclear":false,"family":"","comment":""},"7":{"value":"","value_unclear":false,"family_comment":"","source_name":"","family":"","comment":""},"8":{"family_comment":"","value":"","family":"","comment":""},"9":{"value":"","family_comment":"","value_unclear":false,"family_unclear":false,"family":"","comment":""},"10":{"family_comment":"","value":"","comment_unclear":false,"family":"","comment":""},"11":{"family_comment":"","value":"","family":"","comment":""},"12":{"family_comment":"","value":"","family":"","comment":""},"13":{"family_comment":"","value":"","value_unclear":false,"family":"","comment":""},"14":{"family_comment":"","value":"","family":"","comment":""},"15":{"family_comment":"","value":"","family":"","comment":""},"16":{"family_comment":"","family_unclear":false,"value":"","family":"","comment":""},"17":{"family_comment":"","family_unclear":false,"value":"","family":"","comment":""},"18":{"family_comment":"","value":"","family":"","comment":""},"19":{"family_comment":"","value":"","family":"","comment":""},"20":{"value":"","family_comment":"","value_unclear":false,"family_hidden":false,"value_hidden":false,"family_unclear":false,"comment_unclear":false,"comment":"","family":""}},"id":"vulyk_100_36","declaration":{"additional_info_text":"","notfull_lostpages":"","date":"2015-03-27T00:00:00","notfull":"","additional_info":"","url":"http://static.declarations.com.ua/declarations/chosen_ones/judges_batch/4204_kompliektova_tetiana_oleksandrivna.pdf"},"liabilities":{"54":{"sum_foreign_comment":"","sum":"","sum_comment":"","sum_comment_hidden":false,"sum_unclear":false,"sum_foreign":""},"55":{"sum_foreign_comment":"","sum":"","sum_comment":"","sum_foreign":""},"56":{"sum_foreign_comment":"","sum":"","sum_comment":"","sum_unclear":false,"sum_foreign":""},"57":{"sum_foreign_comment":"","sum":"","sum_comment":"","sum_comment_unclear":false,"sum_comment_hidden":false,"sum_unclear":false,"sum_foreign":""},"58":{"sum_foreign_comment":"","sum":"","sum_comment":"","sum_comment_hidden":false,"sum_unclear":false,"sum_foreign":""},"59":{"sum_foreign_comment":"","sum":"","sum_comment":"","sum_foreign":""},"60":{"sum_foreign_comment":"","sum_comment_hidden":false,"sum":"","sum_comment":"","sum_foreign":""},"61":{"sum_foreign_comment":"","sum":"","sum_comment":"","sum_foreign":""},"62":{"sum_foreign_comment":"","sum":"","sum_comment":"","sum_unclear":false,"sum_foreign":""},"63":{"sum_foreign_comment":"","sum_comment_hidden":false,"sum":"","sum_comment":"","sum_foreign":""},"64":{"sum_foreign_comment":"","sum_comment_hidden":false,"sum":"","sum_comment":"","sum_foreign":""}},"ft_src":"Сєвєродонецьк\n93400\nЛуганська область\nКомплєктова Тетяна Олександрівна\nсуддя Сєвєродонецького міського суду луганської області\nЛуганська область\nЗагальний місцевий суд\nТетяна\nКомплєктов І. С\nДитина\nКомплєктова Тетяна Олександрівна\nТетяна Олександрівна Комплєктова\nТетяна Комплєктова\nКомплєктова Тетяна Олександрівна\nКомплєктова\nОлександрівна\n202855\n202855\n2014\n202855\n202855\n202855\n202855\nДитина\nКомплєктов І. С\nОлександрівна\nЛуганська область\n93400\nСєвєродонецьк\nКомплєктова\nКомплєктова Тетяна Олександрівна\nТетяна Олександрівна Комплєктова\nТетяна Комплєктова\nКомплєктова Тетяна Олександрівна\nКомплєктова Тетяна Олександрівна\nТетяна\nЗагальний місцевий суд\nЛуганська область\nсуддя Сєвєродонецького міського суду луганської області\n2014\nКомплєктов І. С\nДитина\n93400\nСєвєродонецьк\nЛуганська область\nОлександрівна\nКомплєктова\nЛуганська область\nЗагальний місцевий суд\nсуддя Сєвєродонецького міського суду луганської області\nКомплєктова Тетяна Олександрівна\nКомплєктова Тетяна Олександрівна\nТетяна Олександрівна Комплєктова\nТетяна Комплєктова\nКомплєктова Тетяна Олександрівна\nТетяна\n2014","general":{"inn":"","inn_hidden":true,"last_name":"Комплєктова","post":{"post_unclear":false,"region_unclear":false,"post":"суддя Сєвєродонецького міського суду луганської області","office":"Загальний місцевий суд","region":"Луганська область","post_hidden":false,"office_unclear":false},"name":"Тетяна","full_name":"Комплєктова Тетяна Олександрівна","family_raw":"","addresses":[{"place_district":"","place_city_hidden":false,"place_city":"Сєвєродонецьк","place_city_unclear":false,"place_district_hidden":false,"place_city_type":"Місто","place_address_hidden":true,"place_city_type_hidden":false,"place_address":"93400","place_hidden":false,"place":"Луганська область"}],"family":[{"inn_hidden":true,"inn":"","name_hidden":true,"family_name":"Комплєктов І. С","relations":"Дитина","name_unclear":false}],"full_name_suggest":{"output":"Комплєктова Тетяна Олександрівна","input":["Комплєктова Тетяна Олександрівна","Тетяна Олександрівна Комплєктова","Тетяна Комплєктова"]},"patronymic":"Олександрівна"},"source":"VULYK","intro":{"declaration_year":"2014"}}