{"income":{"5":{"value":"244386.6","family_comment":"","value_unclear":false,"comment_hidden":false,"family_hidden":false,"value_hidden":false,"family_unclear":false,"family_comment_hidden":false,"comment":"","family":"687.32"},"6":{"value":"244386.6","family_comment":"","value_unclear":false,"family_hidden":false,"family_unclear":false,"family":"","comment":""},"7":{"source_name_unclear":false,"value":"","family_hidden":false,"family_comment":"","source_name":"","family":"","comment":"","source_name_hidden":false},"8":{"family_comment":"","value":"","family":"","comment":""},"9":{"value":"","value_unclear":false,"family_hidden":false,"family_comment":"","family":"","comment":""},"10":{"value":"","value_unclear":false,"family_hidden":false,"value_hidden":false,"family_comment":"","comment_unclear":false,"comment":"","family":"171.4"},"11":{"family_comment":"","value":"","family":"","comment":""},"12":{"family_comment":"","value":"","family":"515.92","comment":""},"13":{"family_comment":"","value":"","family":"","comment":""},"14":{"family_comment":"","value":"","family":"","comment":""},"15":{"family_comment":"","value":"","family_hidden":false,"comment":"","family":""},"16":{"value":"","value_unclear":false,"family_hidden":false,"family_comment":"","family":"","comment":""},"17":{"family_comment":"","value":"","family_hidden":false,"comment":"","family":""},"18":{"family_comment":"","value":"","value_unclear":false,"family":"","comment":""},"19":{"family_comment":"","value":"","family":"","comment":""},"20":{"value":"","family_comment":"","value_unclear":false,"family_hidden":false,"family_unclear":false,"comment_unclear":false,"comment":"","family":""}},"vehicle":{"35":[{"brand_info":"1997 куб. см.","sum_rent_comment":"","brand_info_unclear":true,"year":"2010","sum_rent_unclear":false,"brand_info_hidden":false,"sum_rent_comment_unclear":false,"sum_hidden":false,"sum_rent":"","sum":"","brand":"Honda Accord","sum_comment":"","brand_unclear":false,"brand_hidden":false},{"brand_info":"1390 куб. см.","sum_rent_comment":"","brand":"Volkswagen Golf","sum_comment":"","year":"2011","brand_info_unclear":true,"year_unclear":false,"sum":"120000","sum_rent":""}],"40":[{"year_hidden":false,"brand_info":"1390 куб. см.","sum_rent_comment":"","year":"2011","brand_info_hidden":false,"brand_info_unclear":false,"year_unclear":false,"sum_rent":"","sum":"","brand":"Volkswagen Golf","sum_comment":"","brand_unclear":false,"brand_hidden":false}]},"id":"vulyk_72_305","declaration":{"additional_info_text":"","notfull_lostpages":"","date":"2015-03-31T00:00:00","notfull":"","additional_info":"","url":"http://static.declarations.com.ua/declarations/chosen_ones/epic_batch/melnyk_oleh_volodymyrovych_sud.pdf"},"liabilities":{"54":{"sum_foreign_comment":"","sum":"","sum_comment":"","sum_comment_hidden":false,"sum_unclear":false,"sum_foreign":""},"55":{"sum_foreign_comment":"","sum":"","sum_comment":"","sum_foreign":""},"56":{"sum_foreign_comment":"","sum":"","sum_hidden":false,"sum_comment":"","sum_foreign":""},"57":{"sum_foreign_comment":"","sum":"","sum_comment":"","sum_comment_unclear":false,"sum_hidden":false,"sum_comment_hidden":false,"sum_unclear":false,"sum_foreign":""},"58":{"sum_foreign_comment":"","sum":"","sum_comment":"","sum_comment_unclear":false,"sum_hidden":false,"sum_comment_hidden":false,"sum_unclear":false,"sum_foreign":""},"59":{"sum_foreign_comment":"","sum_foreign_hidden":false,"sum_comment":"","sum_foreign_unclear":false,"sum_comment_hidden":false,"sum":"","sum_foreign":""},"60":{"sum_foreign_comment":"","sum_foreign_hidden":false,"sum_comment":"","sum_hidden":false,"sum":"","sum_foreign":""},"61":{"sum_foreign_comment":"","sum_foreign_hidden":false,"sum_comment":"","sum_hidden":false,"sum":"","sum_foreign":""},"62":{"sum_foreign_comment":"","sum_foreign_hidden":false,"sum_comment":"","sum_hidden":false,"sum":"","sum_foreign":""},"63":{"sum_foreign_comment":"","sum_foreign_hidden":false,"sum_comment":"","sum_comment_unclear":false,"sum_hidden":false,"sum_comment_hidden":false,"sum_unclear":false,"sum":"","sum_foreign":""},"64":{"sum_foreign_comment":"","sum_foreign_hidden":false,"sum_comment":"","sum_hidden":false,"sum":"","sum_foreign":""}},"ft_src":"заступник голови рівненського апеляційного господарського суду\nРівненська область\nАпеляційний господарський суд\nОлег\nПодружжя\nДитина\nДитина\nВолодимирович\nМельник\nМельник Олег Володимирович\nМельник Олег Володимирович\nОлег Володимирович Мельник\nОлег Мельник\nМельник Олег Володимирович\n1997 куб. см.\nHonda Accord\n2010\n2011\n1390 куб. см.\nVolkswagen Golf\n120000\n1390 куб. см.\nVolkswagen Golf\n2011\n105.9\n86.5\n86.5\n2014\n244386.6\n171.4\n687.32\n244386.6\n515.92\n1997 куб. см.\nHonda Accord\n2010\n1390 куб. см.\nVolkswagen Golf\n2011\n120000\n1390 куб. см.\nVolkswagen Golf\n2011\n86.5\n105.9\n86.5\nПодружжя\nДитина\nДитина\nМельник Олег Володимирович\nОлег Володимирович Мельник\nОлег Мельник\nМельник Олег Володимирович\nОлег\nМельник Олег Володимирович\nМельник\nРівненська область\nАпеляційний господарський суд\nзаступник голови рівненського апеляційного господарського суду\nВолодимирович\n244386.6\n515.92\n244386.6\n687.32\n171.4\n2014\nПодружжя\nДитина\nДитина\nВолодимирович\nМельник\nМельник Олег Володимирович\nОлег Володимирович Мельник\nОлег Мельник\nМельник Олег Володимирович\nРівненська область\nАпеляційний господарський суд\nзаступник голови рівненського апеляційного господарського суду\nМельник Олег Володимирович\nОлег\n2010\nHonda Accord\n1997 куб. см.\n2011\n1390 куб. см.\nVolkswagen Golf\n120000\nVolkswagen Golf\n1390 куб. см.\n2011\n171.4\n244386.6\n687.32\n515.92\n244386.6\n105.9\n86.5\n86.5\n2014","general":{"inn":"","name":"Олег","patronymic_unclear":false,"family":[{"inn":"","inn_hidden":true,"relations_unclear":false,"relations_hidden":false,"relations_other":"","relations":"Подружжя","name_hidden":true,"inn_unclear":false,"family_name":"","name_unclear":false},{"inn":"","inn_hidden":false,"relations_hidden":false,"family_name":"","relations_other":"","relations":"Дитина","name_hidden":false,"name_unclear":false},{"inn":"","inn_hidden":false,"relations_hidden":false,"family_name":"","relations_other":"","relations":"Дитина","name_hidden":false,"name_unclear":false}],"patronymic":"Володимирович","inn_hidden":true,"family_raw":"","inn_unclear":false,"post":{"post_unclear":false,"region_unclear":false,"post":"заступник голови рівненського апеляційного господарського суду","candidate":"","office_hidden":false,"region":"Рівненська область","post_hidden":false,"office":"Апеляційний господарський суд","office_unclear":false,"region_hidden":false},"last_name_unclear":false,"full_name":"Мельник Олег Володимирович","addresses":[{"place_city_type_hidden":false,"place_district_hidden":true,"place_city_type":"","place_city_hidden":true,"place_address_unclear":false,"place_address":"","place":"","place_district":"","place_unclear":false,"place_city":"","place_city_unclear":false,"place_hidden":true,"place_address_hidden":true,"place_district_unclear":false}],"last_name":"Мельник","patronymic_hidden":false,"full_name_suggest":{"output":"Мельник Олег Володимирович","input":["Мельник Олег Володимирович","Олег Володимирович Мельник","Олег Мельник"]},"name_unclear":false},"source":"VULYK","estate":{"24":[{"space_hidden":false,"costs":"","costs_comment":"","address_hidden":false,"region_hidden":true,"space_comment":"","space":"86.5","address":"","region":"","address_unclear":false,"costs_rent_comment":"","space_units":"м²","costs_rent":""}],"30":[{"region_unclear":false,"space_unclear":false,"address_hidden":false,"region_hidden":true,"space_comment":"","space_hidden":false,"space":"105.9","address":"","region":"","costs_property":"","costs_rent_comment":"","space_units":"м²","costs_property_comment":"","costs_rent":""},{"costs_rent":"","region":"","costs_property":"","costs_rent_comment":"","address_hidden":false,"region_hidden":false,"space_comment":"","costs_property_comment":"","space_units":"м²","space":"86.5","address":""}]},"intro":{"declaration_year":"2014","isnotdeclaration":"","declaration_year_unclear":false}}