{"income":{"5":{"family_comment":"","value":"226942","family":"157373","comment":""},"6":{"family_comment":"","value":"213570.47","family":"157373","comment":""},"7":{"family_comment":"","value":"","source_name":"","family":"","comment":""},"8":{"family_comment":"","value":"","family":"","comment":""},"9":{"value":"409","comment_unclear":false,"family_comment":"","family":"","comment":"","family_comment_unclear":false},"10":{"family_comment":"","value":"","family":"","comment":""},"11":{"family_comment":"","value":"","family":"","comment":""},"12":{"family_comment":"","value":"","family":"","comment":""},"13":{"family_comment":"","value":"","family":"","comment":""},"14":{"family_comment":"","value":"","family":"","comment":""},"15":{"family_comment":"","value":"","family":"","comment":""},"16":{"family_comment":"","value":"","family":"","comment":""},"17":{"family_comment":"","value":"","family":"","comment":""},"18":{"family_comment":"","value":"","family":"","comment":""},"19":{"value":"","family_comment":"","value_unclear":false,"family_unclear":false,"family":"","comment":""},"20":{"value":"12963","family_comment":"","value_unclear":false,"comment_hidden":false,"family_comment_hidden":false,"family_unclear":false,"family_comment_unclear":false,"comment_unclear":false,"comment":"","family":""}},"vehicle":{"35":[{"brand_info":"1.25","sum_rent_comment":"","brand":"Ford Fiesta","sum_comment":"","year":"2012","sum_hidden":false,"brand_info_hidden":false,"brand_info_unclear":false,"year_unclear":false,"sum":"","sum_rent":""}]},"id":"vulyk_106_95","banks":{"45":[{"sum_foreign_comment":"","sum_units":"UAH","sum_comment":"Приватбанк","sum_foreign_comment_hidden":false,"sum_hidden":false,"sum_foreign_units":"UAH","sum_comment_hidden":false,"sum":"632","sum_foreign":""}]},"declaration":{"additional_info_text":"","notfull_lostpages":"","date":"2016-03-31T00:00:00","notfull":"","additional_info":"","url":"http://static.declarations.com.ua/declarations/chosen_ones/judges_batch/2234_sapalova_tetiana_valentynivna.pdf"},"liabilities":{"54":{"sum_foreign_comment":"","sum":"","sum_comment":"","sum_comment_unclear":false,"sum_hidden":false,"sum_comment_hidden":false,"sum_foreign":""},"55":{"sum_foreign_comment":"","sum":"","sum_hidden":false,"sum_comment":"","sum_foreign":""},"56":{"sum_foreign_comment":"","sum":"7200","sum_comment":"","sum_hidden":false,"sum_comment_hidden":false,"sum_unclear":false,"sum_foreign":""},"57":{"sum_foreign_comment":"","sum":"","sum_comment":"","sum_hidden":false,"sum_comment_hidden":false,"sum_foreign":""},"58":{"sum_foreign_comment":"","sum":"","sum_comment":"","sum_hidden":false,"sum_comment_hidden":false,"sum_foreign":""},"59":{"sum_foreign_comment":"","sum":"","sum_comment":"","sum_foreign":""},"60":{"sum_foreign_comment":"","sum":"","sum_comment":"","sum_hidden":false,"sum_comment_hidden":false,"sum_foreign":""},"61":{"sum_foreign_comment":"","sum":"","sum_comment":"","sum_foreign":""},"62":{"sum_foreign_comment":"","sum":"7200","sum_comment":"","sum_comment_hidden":false,"sum_unclear":false,"sum_foreign":""},"63":{"sum_foreign_comment":"","sum":"","sum_comment":"","sum_foreign":""},"64":{"sum_foreign_comment":"","sum":"","sum_comment":"","sum_foreign":""}},"ft_src":"7200\n7200\nсуддя вінницького апеляційного адміністративного суду\nВінницька область\nАпеляційний адміністративний суд\nТетяна\nКітіцин А. Ю\nПодружжя\nКітіцин А. А\nДитина\nКітіцин Г. А\nДитина\nКітіцина М. В\nІнше\nмати чоловіка\nВалентинівна\nСапальова Тетяна Валентинівна\nТетяна Валентинівна Сапальова\nТетяна Сапальова\nСапальова Тетяна Валентинівна\nСапальова Тетяна Валентинівна\nСапальова\nFord Fiesta\n1.25\n2012\nПриватбанк\n632\n2015\n1.25\n2012\nFord Fiesta\n632\nПриватбанк\n10\n51.1\n51.1\n7200\nСапальова Тетяна Валентинівна\nТетяна Валентинівна Сапальова\nТетяна Сапальова\nСапальова Тетяна Валентинівна\nСапальова Тетяна Валентинівна\nПодружжя\nКітіцин А. Ю\nДитина\nКітіцин А. А\nДитина\nКітіцин Г. А\nІнше\nмати чоловіка\nКітіцина М. В\nТетяна\nСапальова\nВінницька область\nАпеляційний адміністративний суд\nсуддя вінницького апеляційного адміністративного суду\nВалентинівна\n7200\n7200\n213570.47\n157373\n12963\n226942\n157373\n409\n2015\n7200\n7200\n51.1\n10\n7200\n51.1\nКітіцин А. Ю\nПодружжя\nКітіцин А. А\nДитина\nКітіцин Г. А\nДитина\nмати чоловіка\nКітіцина М. В\nІнше\nВалентинівна\nСапальова\nТетяна\nСапальова Тетяна Валентинівна\nТетяна Валентинівна Сапальова\nТетяна Сапальова\nСапальова Тетяна Валентинівна\nВінницька область\nАпеляційний адміністративний суд\nсуддя вінницького апеляційного адміністративного суду\nСапальова Тетяна Валентинівна\n157373\n213570.47\n409\n157373\n226942\n12963\n2012\nFord Fiesta\n1.25\n409\n12963\n157373\n226942\n157373\n213570.47\n51.1\n7200\n51.1\n10\nПриватбанк\n632\n2015","general":{"inn":"","name":"Тетяна","inn_unclear":false,"family":[{"inn":"","inn_hidden":true,"relations_unclear":false,"relations_hidden":false,"relations_other":"","relations":"Подружжя","name_hidden":true,"family_name":"Кітіцин А. Ю","name_unclear":true},{"inn":"","relations":"Дитина","relations_unclear":false,"family_name":"Кітіцин А. А","inn_hidden":false,"relations_other":"","name_hidden":false,"name_unclear":false},{"inn_hidden":false,"inn":"","name_hidden":false,"family_name":"Кітіцин Г. А","relations":"Дитина","name_unclear":false},{"inn":"","relations":"Інше","relations_other":"мати чоловіка","inn_hidden":false,"family_name":"Кітіцина М. В","name_unclear":false}],"inn_hidden":true,"family_raw":"","last_name":"Сапальова","post":{"region_unclear":false,"region":"Вінницька область","post":"суддя вінницького апеляційного адміністративного суду","office":"Апеляційний адміністративний суд","office_unclear":false,"post_hidden":false},"full_name":"Сапальова Тетяна Валентинівна","addresses":[{"place_district":"","place_city_hidden":true,"place_city":"","place_city_type_hidden":true,"place_district_hidden":true,"place_city_type":"","place_address_hidden":true,"place_address":"","place_hidden":true,"place":""}],"patronymic":"Валентинівна","full_name_suggest":{"output":"Сапальова Тетяна Валентинівна","input":["Сапальова Тетяна Валентинівна","Тетяна Валентинівна Сапальова","Тетяна Сапальова"]},"name_unclear":false},"source":"VULYK","estate":{"25":[{"costs":"","costs_comment":"","address_hidden":true,"region_hidden":true,"space_comment":"","space":"51.1","address":"","region":"","costs_rent_comment":"","space_comment_unclear":false,"space_units":"м²","costs_rent":"7200"}],"29":[{"region_unclear":false,"costs_property_comment":"","address_hidden":true,"region_hidden":true,"space_comment":"","space":"10","address":"","costs_rent_comment_unclear":false,"region":"","costs_property":"","costs_rent_comment":"","space_comment_unclear":false,"address_unclear":false,"space_units":"м²","space_units_unclear":true,"costs_rent":""}],"30":[{"space_unclear":false,"address_hidden":true,"region_hidden":true,"space_comment":"","space_hidden":false,"space":"","address":"","region":"","costs_property":"","costs_rent_comment":"","space_comment_unclear":false,"space_units":"м²","costs_property_comment":"","costs_rent":""}],"31":[{"space_unclear":false,"address_hidden":true,"region_hidden":true,"space_comment":"","space_hidden":false,"space":"51.1","address":"","region":"","costs_property":"","costs_rent_comment":"","space_comment_unclear":false,"space_units":"м²","costs_property_comment":"","costs_rent":""}]},"intro":{"declaration_year":"2015","isnotdeclaration":""}}