{"income":{"5":{"family_comment":"","value":"191983","family":"702952","comment":""},"6":{"family_comment":"","value":"191665","family":"135227","comment":""},"7":{"value":"","comment_hidden":false,"family_comment":"","source_name":"","family":"","comment":"","source_name_hidden":false},"8":{"family_comment":"","value":"","family_hidden":false,"comment":"","family":""},"9":{"value":"318","family_comment":"","value_unclear":false,"family_unclear":false,"family":"","comment":""},"10":{"family_comment":"","value":"","family":"12900","comment":""},"11":{"family_comment":"","value":"","family":"554774","comment":""},"12":{"family_comment":"","value":"","family":"","comment":""},"13":{"family_comment":"","value":"","family":"","comment":""},"14":{"family_comment":"","value":"","family":"","comment":""},"15":{"family_comment":"","value":"","family":"","comment":""},"16":{"family_comment":"","value":"","family":"","comment":""},"17":{"family_comment":"","value":"","family":"","comment":""},"18":{"family_comment":"","value":"","family":"","comment":""},"19":{"family_comment":"","value":"","family":"","comment":""},"20":{"value":"","value_unclear":false,"family_hidden":false,"family_comment":"","family":"51","comment":""}},"vehicle":{"40":[{"brand_info":"3498, 183","sum_rent_comment":"","brand":"Nissan Teana","sum_comment":"","year":"2008","brand_info_unclear":false,"sum":"","sum_rent":""}]},"id":"vulyk_109_20","declaration":{"additional_info_text":"","notfull_lostpages":"","date":"2016-03-24T00:00:00","notfull":"","additional_info":"","url":"http://static.declarations.com.ua/declarations/chosen_ones/judges_batch/2477_tvarkovskyi_anatolii_anatoliiovych_2015.pdf"},"liabilities":{"54":{"sum_foreign_comment":"","sum":"","sum_comment":"","sum_hidden":false,"sum_comment_hidden":false,"sum_unclear":false,"sum_foreign":""},"55":{"sum_foreign_comment":"","sum":"","sum_comment":"","sum_comment_unclear":false,"sum_foreign":""},"56":{"sum_foreign_comment":"","sum":"","sum_comment":"","sum_foreign":""},"57":{"sum_foreign_comment":"","sum_comment_hidden":false,"sum":"","sum_comment":"","sum_foreign":""},"58":{"sum_foreign_comment":"","sum_comment_hidden":false,"sum":"","sum_comment":"","sum_foreign":""},"59":{"sum_foreign_comment":"","sum":"","sum_comment":"","sum_foreign":""},"60":{"sum_foreign_comment":"","sum":"","sum_comment":"","sum_foreign":""},"61":{"sum_foreign_comment":"","sum":"","sum_comment":"","sum_foreign":""},"62":{"sum_foreign_comment":"","sum":"","sum_comment":"","sum_foreign":""},"63":{"sum_foreign_comment":"","sum":"","sum_comment":"","sum_foreign":""},"64":{"sum_foreign_comment":"","sum":"","sum_comment":"","sum_foreign":""}},"ft_src":"суддя господарського суду вінницької області\nВінницька область\nГосподарський місцевий суд\nАнатолій\nБошкова Ю. М\nПодружжя\nТварковська Д. А\nДитина\nТварковська Є. А\nДитина\nАнатолійович\nТварковський Анатолій Анатолійович\nТварковський\nТварковський Анатолій Анатолійович\nАнатолій Анатолійович Тварковський\nАнатолій Тварковський\nТварковський Анатолій Анатолійович\n3498, 183\n2008\nNissan Teana\n24\n68.8\n16\n2015\n135227\n191665\n554774\n12900\n702952\n191983\n318\n51\n3498, 183\n2008\nNissan Teana\n2015\nПодружжя\nБошкова Ю. М\nДитина\nТварковська Д. А\nДитина\nТварковська Є. А\nТварковський Анатолій Анатолійович\nАнатолій Анатолійович Тварковський\nАнатолій Тварковський\nТварковський Анатолій Анатолійович\nАнатолій\nТварковський Анатолій Анатолійович\nТварковський\nГосподарський місцевий суд\nВінницька область\nсуддя господарського суду вінницької області\nАнатолійович\n191665\n135227\n51\n191983\n702952\n554774\n12900\n318\n24\n68.8\n16\nПодружжя\nБошкова Ю. М\nДитина\nТварковська Д. А\nДитина\nТварковська Є. А\nАнатолій\nАнатолійович\nТварковський\nТварковський Анатолій Анатолійович\nАнатолій Анатолійович Тварковський\nАнатолій Тварковський\nТварковський Анатолій Анатолійович\nВінницька область\nГосподарський місцевий суд\nсуддя господарського суду вінницької області\nТварковський Анатолій Анатолійович\n2008\n3498, 183\nNissan Teana\n554774\n12900\n51\n702952\n191983\n318\n135227\n191665\n24\n68.8\n16\n2015","general":{"name_hidden":false,"name":"Анатолій","inn":"","inn_unclear":false,"family":[{"inn":"","relations":"Подружжя","relations_hidden":false,"inn_hidden":false,"relations_other":"","name_hidden":false,"family_name":"Бошкова Ю. М","name_unclear":true},{"inn":"","relations":"Дитина","relations_other":"","inn_hidden":false,"family_name":"Тварковська Д. А","name_hidden":false,"name_unclear":false},{"inn":"","relations":"Дитина","relations_other":"","inn_hidden":false,"family_name":"Тварковська Є. А","name_hidden":false,"name_unclear":false}],"inn_hidden":false,"family_raw":"","last_name":"Тварковський","post":{"region_unclear":false,"region":"Вінницька область","post":"суддя господарського суду вінницької області","region_hidden":false,"office":"Господарський місцевий суд","office_hidden":false,"office_unclear":false},"full_name":"Тварковський Анатолій Анатолійович","patronymic":"Анатолійович","full_name_suggest":{"output":"Тварковський Анатолій Анатолійович","input":["Тварковський Анатолій Анатолійович","Анатолій Анатолійович Тварковський","Анатолій Тварковський"]}},"source":"VULYK","estate":{"25":[{"space_unclear":false,"costs":"","costs_comment":"","address_hidden":false,"region_hidden":false,"space_comment":"","space_hidden":false,"space":"16","address":"","region":"","costs_rent_comment":"","space_units":"м²","space_units_hidden":false,"costs_rent":""}],"31":[{"space_hidden":false,"costs_property_comment":"","address_hidden":true,"region_hidden":false,"space_comment":"","space":"24","address":"","region":"","costs_property":"","costs_rent_comment":"","space_units":"м²","space_units_hidden":false,"costs_rent":""},{"costs_rent":"","region":"","costs_property":"","costs_rent_comment":"","space_comment":"","costs_property_comment":"","space_units":"м²","space":"68.8","address":""}]},"intro":{"declaration_year":"2015","isnotdeclaration":""}}