{"income":{"5":{"value":"209667.97","family_comment":"","value_unclear":false,"family_hidden":false,"family_unclear":false,"family":"20400","comment":""},"6":{"family_comment":"","value":"208581.53","family":"20400","comment":""},"7":{"family_comment":"","value":"","source_name":"","family":"","comment":""},"8":{"family_comment":"","value":"","family":"","comment":""},"9":{"family_comment":"","value":"","family":"","comment":""},"10":{"family_comment":"","value":"","value_unclear":false,"family":"","comment":""},"11":{"family_comment":"","value":"","family":"","comment":""},"12":{"family_comment":"","value":"","family":"","comment":""},"13":{"family_comment":"","value":"","family":"","comment":""},"14":{"family_comment":"","value":"","family":"","comment":""},"15":{"family_comment":"","value":"","family":"","comment":""},"16":{"family_comment":"","value":"","family":"","comment":""},"17":{"family_comment":"","value":"","family":"","comment":""},"18":{"family_comment":"","value":"","family":"","comment":""},"19":{"family_comment":"","value":"","family":"","comment":""},"20":{"family_comment":"","value":"1086.44","family":"","comment":""}},"vehicle":{"35":[{"brand_info":"2378 - об'єм","sum":"","brand":"Mitsubishi Outlander","sum_comment":"","brand_unclear":false,"year":"2007","sum_rent_comment":"","sum_rent":""}],"40":[{"year_hidden":false,"brand_info":"1598 - об'єм","sum":"","brand":"Peugeot 308","sum_comment":"","year":"2008","sum_rent_comment":"","sum_rent":""}]},"id":"vulyk_82_34","declaration":{"date":"2015-03-31T00:00:00","additional_info_text":"","additional_info":"","url":"http://static.declarations.com.ua/declarations/chosen_ones/judges_batch/2229_danylenko_vitalii_valeriiovych.pdf"},"liabilities":{"54":{"sum_foreign_comment":"","sum_comment":"","sum":"","sum_comment_hidden":false,"sum_foreign":""},"55":{"sum_foreign_comment":"","sum":"","sum_foreign":"","sum_comment":"","sum_hidden":false},"56":{"sum_foreign_comment":"","sum":"","sum_comment":"","sum_foreign":""},"57":{"sum_foreign_comment":"","sum":"","sum_comment":"","sum_foreign":""},"58":{"sum_foreign_comment":"","sum":"","sum_comment":"","sum_foreign":""},"59":{"sum_foreign_comment":"","sum":"","sum_comment":"","sum_foreign":""},"60":{"sum_foreign_comment":"","sum":"","sum_comment":"","sum_foreign":""},"61":{"sum_foreign_comment":"","sum":"","sum_comment":"","sum_foreign":""},"62":{"sum_foreign_comment":"","sum":"","sum_comment":"","sum_foreign":""},"63":{"sum_foreign_comment":"","sum":"","sum_comment":"","sum_foreign":""},"64":{"sum_foreign_comment":"","sum":"","sum_comment":"","sum_foreign":""}},"ft_src":"2007\n2378 - об'єм\nMitsubishi Outlander\n1598 - об'єм\n2008\nPeugeot 308\n2014\n20400\n208581.53\n20400\n209667.97\n1086.44\n2378 - об'єм\n2007\nMitsubishi Outlander\n1598 - об'єм\n2008\nPeugeot 308\n2014\nДаниленко Віталій Валерійович\nВіталій Валерійович Даниленко\nВіталій Даниленко\nДаниленко Віталій Валерійович\nДаниленко Віталій Валерійович\nВіталій\nДаниленко\nЗагальний місцевий суд\nм. Київ\nсуддя дарницького районного суду м. києва\nВалерійович\n208581.53\n20400\n1086.44\n209667.97\n20400\nВалерійович\nДаниленко\nВіталій\nДаниленко Віталій Валерійович\nВіталій Валерійович Даниленко\nВіталій Даниленко\nДаниленко Віталій Валерійович\nм. Київ\nЗагальний місцевий суд\nсуддя дарницького районного суду м. києва\nДаниленко Віталій Валерійович","general":{"inn":"","name":"Віталій","last_name":"Даниленко","family":[{"inn":"","inn_hidden":true,"relations_hidden":true,"family_name":"","relations_other":"","relations":"","name_hidden":true,"name_unclear":false}],"inn_hidden":true,"family_raw":"","inn_unclear":false,"post":{"post":"суддя дарницького районного суду м. києва","region":"м. Київ","office_hidden":false,"office":"Загальний місцевий суд","office_unclear":false,"post_hidden":false,"region_hidden":false},"full_name_suggest":{"output":"Даниленко Віталій Валерійович","input":["Даниленко Віталій Валерійович","Віталій Валерійович Даниленко","Віталій Даниленко"]},"full_name":"Даниленко Віталій Валерійович","addresses":[{"place_district":"","place_address_hidden":true,"place_city":"","place_address":"","place_district_hidden":true,"place_city_type":"","place_city_hidden":true,"place_city_type_hidden":true,"place_hidden":true,"place":""}],"patronymic":"Валерійович","last_name_unclear":false},"source":"VULYK","intro":{"declaration_year":"2014"}}