{"income":{"5":{"family_comment":"","family_unclear":false,"value":"238220","family":"221720","comment":""},"6":{"family_comment":"","family_unclear":false,"value":"238220","family":"212058","comment":""},"7":{"value":"","comment_hidden":false,"family_comment":"","source_name":"","family":"","comment":""},"8":{"family_comment":"","value":"","family":"","comment":""},"9":{"family_comment":"","value":"","family":"","comment":""},"10":{"family_comment":"","value":"","family":"","comment":""},"11":{"family_comment":"","value":"","value_unclear":false,"family":"","comment":""},"12":{"family_comment":"","value":"","family":"","comment":""},"13":{"family_comment":"","value":"","family":"","comment":""},"14":{"family_comment":"","value":"","family":"","comment":""},"15":{"family_comment":"","value":"","value_unclear":false,"family":"","comment":""},"16":{"family_comment":"","family_unclear":false,"value":"","family":"","comment":""},"17":{"family_comment":"","value":"","family":"","comment":""},"18":{"family_comment":"","value":"","family_hidden":false,"comment":"","family":""},"19":{"family_comment":"","value":"","family":"","comment":""},"20":{"value":"","comment_unclear":false,"comment_hidden":false,"family_comment":"","family":"9663","comment":"","family_comment_hidden":false}},"vehicle":{"35":[{"brand_info":"3456 куб. см.","sum_rent_comment":"","year":"2007","brand_info_hidden":false,"brand_info_unclear":false,"year_unclear":false,"sum_rent":"","sum":"","brand":"Lexus ES 350","sum_comment":"","brand_unclear":false,"brand_hidden":false}],"40":[{"brand_info":"2362 куб. см.","sum_rent_comment":"","brand":"Toyota Camry","sum_comment":"","year":"2004","brand_hidden":false,"brand_info_hidden":false,"brand_info_unclear":false,"year_unclear":false,"sum":"","sum_rent":""}]},"id":"vulyk_68_139","declaration":{"additional_info_text":"","notfull_lostpages":"","date":"2015-02-09T00:00:00","notfull":"","additional_info":"","url":"http://static.declarations.com.ua/declarations/chosen_ones/mega_batch/kovtunenko_olesia_volodymyrivna.pdf"},"liabilities":{"54":{"sum_foreign_comment":"","sum":"","sum_comment":"","sum_comment_unclear":false,"sum_hidden":false,"sum_comment_hidden":false,"sum_unclear":false,"sum_foreign":""},"55":{"sum_foreign_comment":"","sum":"","sum_hidden":false,"sum_comment":"","sum_foreign":""},"56":{"sum_foreign_comment":"","sum_foreign_hidden":false,"sum_comment":"","sum":"","sum_unclear":false,"sum_foreign":""},"57":{"sum_foreign_comment":"","sum":"","sum_comment":"","sum_comment_unclear":false,"sum_hidden":false,"sum_comment_hidden":false,"sum_unclear":false,"sum_foreign":""},"58":{"sum_foreign_comment":"","sum":"","sum_comment":"","sum_hidden":false,"sum_comment_hidden":false,"sum_unclear":false,"sum_foreign":""},"59":{"sum_foreign_comment":"","sum":"","sum_comment":"","sum_foreign":""},"60":{"sum_foreign_comment":"","sum":"","sum_comment":"","sum_comment_unclear":false,"sum_hidden":false,"sum_comment_hidden":false,"sum_unclear":false,"sum_foreign":""},"61":{"sum_foreign_comment":"","sum":"","sum_hidden":false,"sum_comment":"","sum_foreign":""},"62":{"sum_foreign_comment":"","sum":"","sum_comment":"","sum_unclear":false,"sum_foreign":""},"63":{"sum_foreign_comment":"","sum":"","sum_comment":"","sum_hidden":false,"sum_comment_hidden":false,"sum_unclear":false,"sum_foreign":""},"64":{"sum_foreign_comment":"","sum":"","sum_comment":"","sum_hidden":false,"sum_comment_hidden":false,"sum_foreign":""}},"ft_src":"голова орджонікідзевського районного суду міста маріуполя донецької області\nДонецька область\nЗагальний місцевий суд\nОлеся\nКовтуненко В. О\nПодружжя\nКовтуненко О. В\nДитина\nВолодимирівна\nКовтуненко Олеся Володимирівна\nОлеся Володимирівна Ковтуненко\nОлеся Ковтуненко\nКовтуненко Олеся Володимирівна\nКовтуненко Олеся Володимирівна\nКовтуненко\n3456 куб. см.\nLexus ES 350\n2007\n2362 куб. см.\nToyota Camry\n2004\n1/2 частка - 49,35 кв. м\n98.7\n1/2 частка - 49,35 кв. м\n98.7\n2014\n212058\n238220\n221720\n238220\n9663\n3456 куб. см.\nLexus ES 350\n2007\n2362 куб. см.\n2004\nToyota Camry\n98.7\n1/2 частка - 49,35 кв. м\n98.7\n1/2 частка - 49,35 кв. м\nПодружжя\nКовтуненко В. О\nДитина\nКовтуненко О. В\nКовтуненко Олеся Володимирівна\nОлеся Володимирівна Ковтуненко\nОлеся Ковтуненко\nКовтуненко Олеся Володимирівна\nКовтуненко Олеся Володимирівна\nОлеся\nВолодимирівна\nЗагальний місцевий суд\nДонецька область\nголова орджонікідзевського районного суду міста маріуполя донецької області\nКовтуненко\n238220\n212058\n9663\n238220\n221720\n2014\nПодружжя\nКовтуненко В. О\nКовтуненко О. В\nДитина\nВолодимирівна\nКовтуненко\nОлеся\nКовтуненко Олеся Володимирівна\nОлеся Володимирівна Ковтуненко\nОлеся Ковтуненко\nКовтуненко Олеся Володимирівна\nДонецька область\nЗагальний місцевий суд\nголова орджонікідзевського районного суду міста маріуполя донецької області\nКовтуненко Олеся Володимирівна\n2007\nLexus ES 350\n3456 куб. см.\nToyota Camry\n2362 куб. см.\n2004\n9663\n221720\n238220\n212058\n238220\n1/2 частка - 49,35 кв. м\n98.7\n1/2 частка - 49,35 кв. м\n98.7\n2014","general":{"inn":"","name":"Олеся","inn_unclear":false,"family":[{"inn":"","inn_hidden":true,"relations_unclear":false,"relations_hidden":false,"relations_other":"","relations":"Подружжя","name_hidden":false,"inn_unclear":false,"family_name":"Ковтуненко В. О","name_unclear":false},{"inn":"","inn_hidden":false,"inn_unclear":false,"relations_hidden":false,"relations_other":"","relations":"Дитина","name_hidden":false,"family_name":"Ковтуненко О. В","name_unclear":false}],"inn_hidden":true,"family_raw":"","last_name":"Ковтуненко","post":{"post_unclear":false,"region_unclear":false,"post":"голова орджонікідзевського районного суду міста маріуполя донецької області","office":"Загальний місцевий суд","region":"Донецька область","post_hidden":false,"office_hidden":false,"office_unclear":false,"region_hidden":false},"full_name_suggest":{"output":"Ковтуненко Олеся Володимирівна","input":["Ковтуненко Олеся Володимирівна","Олеся Володимирівна Ковтуненко","Олеся Ковтуненко"]},"full_name":"Ковтуненко Олеся Володимирівна","addresses":[{"place_city_type_hidden":false,"place_district_hidden":true,"place_city_type":"","place_city_hidden":true,"place_address_unclear":false,"place_address":"","place_hidden":true,"place":"","place_district":"","place_unclear":false,"place_city":"","place_address_hidden":true}],"patronymic":"Володимирівна","last_name_unclear":false,"name_unclear":false},"source":"VULYK","estate":{"24":[{"region_unclear":false,"space_unclear":false,"costs":"","costs_comment":"","address_hidden":false,"region_hidden":true,"space_comment":"1/2 частка - 49,35 кв. м","space":"98.7","address":"","region":"","costs_rent_comment":"","space_units":"м²","costs_rent":""}],"30":[{"space_unclear":false,"address_hidden":false,"region_hidden":false,"space_comment":"1/2 частка - 49,35 кв. м","space_hidden":false,"space":"98.7","address":"","region":"","costs_property":"","costs_rent_comment":"","space_units":"м²","costs_property_comment":"","costs_rent":""}]},"intro":{"declaration_year":"2014","isnotdeclaration":""}}