{"id":"vulyk_94_85","ft_src":"Уманський р-н\n39677\nЧеркаська область\nУманський р-н\n60580\nЧеркаська область\nЧеркаська область\nУманський р-н\n3200\nЧеркаська область\nУманський р-н\n30877\n2014\n4459\n189339\n10662\n19794\n201070\n4644\n11731\n39677\nЧеркаська область\nУманський р-н\n60580\nЧеркаська область\nУманський р-н\n3200\nЧеркаська область\nУманський р-н\n30877\nЧеркаська область\nУманський р-н\nГончарук Василь Миколайович\nВасиль Миколайович Гончарук\nВасиль Гончарук\nГончарук Василь Миколайович\nГончарук Василь Миколайович\nПодружжя\nГончарук О. І. 11. 01. 1985\nДитина\nГончарук А. В, 30. 12. 2006\nДитина\nГончарук А. В. 10. 11. 2011\nВасиль\nГончарук\nЗагальний місцевий суд\nЧеркаська область\nзаступник голови уманського міськрайонного суду черкаської області\nМиколайович\nЧеркаська область\nУмань\n189339\n4459\n201070\n19794\n10662\n11731\n4644\n2014\nГончарук О. І. 11. 01. 1985\nПодружжя\nГончарук А. В, 30. 12. 2006\nДитина\nГончарук А. В. 10. 11. 2011\nДитина\nМиколайович\nГончарук\nВасиль\nГончарук Василь Миколайович\nВасиль Миколайович Гончарук\nВасиль Гончарук\nГончарук Василь Миколайович\nУмань\nЧеркаська область\nЧеркаська область\nЗагальний місцевий суд\nзаступник голови уманського міськрайонного суду черкаської області\nГончарук Василь Миколайович","estate":{"23":[{"costs":"","address":"Уманський р-н","space_units":"м²","space_hidden":false,"space_unclear":false,"costs_rent_comment_hidden":false,"space_units_unclear":false,"costs_comment":"","address_hidden":false,"costs_rent_hidden":false,"address_unclear":false,"space_comment":"","costs_rent_comment":"","space":"39677","region_unclear":false,"region_hidden":false,"region":"Черкаська область","costs_rent":""},{"address":"Уманський р-н","space_units":"м²","costs_rent_hidden":false,"space_comment":"","costs_rent_comment_hidden":false,"region":"Черкаська область","costs_comment":"","space":"60580","address_unclear":false,"costs_rent_comment":"","costs":"","region_unclear":false,"region_hidden":false,"costs_rent":""}],"29":[{"costs_property_comment":"","address":"Уманський р-н","space_units":"м²","costs_rent_comment":"","space":"3200","region":"Черкаська область","region_hidden":true,"costs_property":"","space_comment":"","address_hidden":true,"costs_rent":""},{"costs_property_comment":"","address":"Уманський р-н","space_units":"м²","costs_rent_comment":"","space":"30877","region":"Черкаська область","region_hidden":false,"costs_property":"","space_comment":"","address_hidden":true,"costs_rent":""}]},"source":"VULYK","income":{"5":{"family_comment":"","family":"19794","comment":"","value_unclear":false,"family_hidden":false,"value":"201070"},"6":{"family_comment":"","value":"189339","family":"4459","comment":"","value_unclear":false},"7":{"source_name_hidden":false,"family_comment":"","comment":"","family":"","source_name_unclear":false,"value":"","source_name":""},"8":{"family_comment":"","value":"","family":"","comment":""},"9":{"family_comment":"","comment_unclear":false,"value":"","family":"","comment":""},"10":{"family_comment":"","value":"","family":"10662","comment":""},"11":{"family_comment":"","value":"","family_unclear":false,"family":"","comment":""},"12":{"family_comment":"","value":"","family":"","comment":""},"13":{"family_comment":"","value":"","family":"","comment":""},"14":{"family_comment":"","value":"","family":"","comment":""},"15":{"family_comment":"","value":"","family":"","comment":""},"16":{"family_comment":"","value":"","family":"","comment":""},"17":{"family_comment":"","value":"","family":"","comment":""},"18":{"family_comment":"","value":"","family":"","comment":""},"19":{"family_comment":"","value":"11731","family":"4644","comment":""},"20":{"family_comment":"","comment":"","family":"","value_unclear":false,"comment_unclear":false,"value":""}},"general":{"family":[{"inn":"","family_name":"Гончарук О. І. 11. 01. 1985","relations_hidden":false,"name_unclear":false,"inn_hidden":true,"name_hidden":false,"relations":"Подружжя"},{"inn":"","family_name":"Гончарук А. В, 30. 12. 2006","relations_other":"","relations_unclear":false,"name_unclear":false,"inn_hidden":false,"name_hidden":false,"relations":"Дитина"},{"inn":"","family_name":"Гончарук А. В. 10. 11. 2011","relations_other":"","relations_unclear":false,"name_unclear":false,"inn_hidden":false,"name_hidden":false,"relations":"Дитина"}],"family_raw":"","name":"Василь","full_name_suggest":{"input":["Гончарук Василь Миколайович","Василь Миколайович Гончарук","Василь Гончарук"],"output":"Гончарук Василь Миколайович"},"patronymic":"Миколайович","inn_hidden":true,"addresses":[{"place_city_type_hidden":false,"place_city_type":"Місто","place_city_hidden":false,"place_hidden":false,"place_district":"","place_district_hidden":false,"place":"Черкаська область","place_city":"Умань","place_address_hidden":false,"place_address":""}],"patronymic_hidden":false,"inn":"","inn_unclear":false,"last_name":"Гончарук","full_name":"Гончарук Василь Миколайович","post":{"post_hidden":false,"office":"Загальний місцевий суд","post":"заступник голови уманського міськрайонного суду черкаської області","candidate":"","region_unclear":false,"region":"Черкаська область","post_unclear":false,"office_unclear":false}},"liabilities":{"54":{"sum_comment_unclear":false,"sum_comment":"","sum":"","sum_foreign_comment":"","sum_foreign":"","sum_unclear":false,"sum_comment_hidden":false},"55":{"sum_comment":"","sum_foreign_comment":"","sum_foreign":"","sum":""},"56":{"sum_comment":"","sum_foreign_comment":"","sum_foreign":"","sum_unclear":false,"sum":""},"57":{"sum_comment":"","sum_hidden":false,"sum":"","sum_foreign_comment":"","sum_foreign":"","sum_unclear":false},"58":{"sum_comment":"","sum_hidden":false,"sum":"","sum_foreign_comment":"","sum_foreign":"","sum_unclear":false},"59":{"sum_comment":"","sum_foreign_comment":"","sum_foreign":"","sum":""},"60":{"sum_comment":"","sum_foreign_comment":"","sum_foreign":"","sum":"","sum_comment_hidden":false},"61":{"sum_comment":"","sum_foreign_comment":"","sum_foreign":"","sum":""},"62":{"sum_comment":"","sum_foreign_comment":"","sum_foreign":"","sum_hidden":false,"sum":""},"63":{"sum_comment":"","sum_foreign_comment":"","sum_foreign":"","sum":"","sum_comment_hidden":false},"64":{"sum_comment":"","sum_foreign_comment":"","sum_foreign":"","sum_unclear":false,"sum":""}},"declaration":{"notfull_lostpages":"","additional_info_text":"","additional_info":"","date":"2015-03-30T00:00:00","notfull":"","url":"http://static.declarations.com.ua/declarations/chosen_ones/judges_batch/3731_honcharuk_vasyl_mykolaiovych.pdf"},"intro":{"isnotdeclaration":"","declaration_year":"2014"}}