{"id":"vulyk_109_81","ft_src":"1598 куб. см., 115 к. с\n2009\nToyota Corolla\n60.8\n2136\n92.1\nПриватбанк\n770\n2015\n1598 куб. см., 115 к. с\n2009\nToyota Corolla\n2015\nПрядко Оксана Василівна\nОксана Василівна Прядко\nОксана Прядко\nПрядко Оксана Василівна\nОксана\nПодружжя\nПрядко С. В\nДитина\nПрядко Н. С\nПрядко Оксана Василівна\nВасилівна\nГосподарський місцевий суд\nЖитомирська область\nсуддя господарського суду житомирської області\nПрядко\n18063\nПрАТ Юпітер Вієнна Іншуранс Груп, страхування життя\n22548\n181692\nПАТ КБ Приватбанк\n18703\n200441\n46\n2136\n60.8\n92.1\n770\nПриватбанк\n18063\nПрАТ Юпітер Вієнна Іншуранс Груп, страхування життя\n22548\n181692\n200441\n46\nПАТ КБ Приватбанк\n18703\nПодружжя\nПрядко С. В\nДитина\nПрядко Н. С\nВасилівна\nПрядко\nОксана\nПрядко Оксана Василівна\nОксана Василівна Прядко\nОксана Прядко\nПрядко Оксана Василівна\nЖитомирська область\nГосподарський місцевий суд\nсуддя господарського суду житомирської області\nПрядко Оксана Василівна","estate":{"25":[{"address":"","space_units":"м²","space_hidden":false,"space_unclear":false,"region_hidden":true,"costs_comment":"","space_comment":"","address_hidden":true,"space":"92.1","costs_rent_comment":"","costs":"","region":"","space_units_hidden":false,"costs_rent":""}],"29":[{"costs_property_comment":"","address":"","space_units":"м²","space_unclear":false,"region_hidden":true,"costs_property":"","space_comment":"","address_hidden":true,"costs_rent_comment":"","space":"2136","region":"","costs_rent":""}],"31":[{"costs_property_comment":"","address":"","space_units":"м²","space_hidden":false,"space_comment":"","region_hidden":true,"costs_property":"","region":"","address_hidden":true,"costs_rent_comment":"","space":"60.8","space_units_hidden":false,"costs_rent":""}]},"vehicle":{"40":[{"sum_comment":"","brand_info":"1598 куб. см., 115 к. с","sum":"","sum_rent_comment":"","year":"2009","brand":"Toyota Corolla","sum_rent":"","brand_info_unclear":false}]},"source":"VULYK","income":{"5":{"family_comment":"","value":"200441","family":"","comment":""},"6":{"family_comment":"","value":"181692","family":"","comment":""},"7":{"source_name_hidden":false,"family_comment":"","comment":"","family":"","comment_hidden":false,"value":"","source_name":""},"8":{"family_comment":"","family_hidden":false,"value":"","family":"","comment":""},"9":{"family_comment":"","family":"","comment":"","value_unclear":false,"family_unclear":false,"value":"46"},"10":{"family_comment":"","value":"","family":"","comment":""},"11":{"family_comment":"","value":"","family":"","comment":""},"12":{"family_comment":"","value":"","family":"","comment":""},"13":{"family_comment":"","value":"","family":"","comment":""},"14":{"family_comment":"","value":"","family":"","comment":""},"15":{"family_comment":"","value":"","family":"","comment":""},"16":{"family_comment":"","value":"","family":"","comment":""},"17":{"family_comment":"","value":"","family":"","comment":""},"18":{"family_comment":"","value":"","family":"","comment":""},"19":{"family_comment":"","value":"","family":"","comment":""},"20":{"family_comment":"","family":"","comment":"ПАТ КБ Приватбанк","value_unclear":false,"family_hidden":false,"value":"18703"}},"banks":{"45":[{"sum_units":"UAH","sum_comment":"Приватбанк","sum_foreign_units":"UAH","sum":"770","sum_units_hidden":false,"sum_foreign_comment":"","sum_foreign":"","sum_unclear":false,"sum_comment_hidden":false}]},"declaration":{"notfull_lostpages":"","additional_info_text":"","additional_info":"","date":"2016-03-31T00:00:00","notfull":"","url":"http://static.declarations.com.ua/declarations/chosen_ones/judges_batch/2538_priadko_oksana_vasylivna_2015.pdf"},"general":{"family_raw":"","name":"Оксана","full_name_suggest":{"input":["Прядко Оксана Василівна","Оксана Василівна Прядко","Оксана Прядко"],"output":"Прядко Оксана Василівна"},"patronymic":"Василівна","inn_hidden":true,"addresses":[{"place_city_type_hidden":true,"place_city_type":"","place_city_hidden":true,"place_hidden":true,"place_district":"","place_district_hidden":true,"place":"","place_address":"","place_address_hidden":true,"place_city":""}],"inn":"","inn_unclear":false,"last_name":"Прядко","full_name":"Прядко Оксана Василівна","family":[{"inn":"","family_name":"Прядко С. В","relations_hidden":false,"name_unclear":false,"relations":"Подружжя","inn_hidden":true,"name_hidden":true,"relations_other":""},{"inn":"","family_name":"Прядко Н. С","relations_other":"","name_unclear":false,"inn_hidden":true,"name_hidden":false,"relations":"Дитина"}],"post":{"office":"Господарський місцевий суд","post":"суддя господарського суду житомирської області","office_unclear":false,"region_hidden":false,"region":"Житомирська область","office_hidden":false,"region_unclear":false},"name_hidden":false},"liabilities":{"54":{"sum_comment":"ПрАТ Юпітер Вієнна Іншуранс Груп, страхування життя","sum_hidden":false,"sum":"22548","sum_foreign_comment":"","sum_foreign":"","sum_unclear":false,"sum_comment_hidden":false},"55":{"sum_comment":"","sum_comment_unclear":false,"sum_foreign_comment":"","sum":"","sum_foreign":""},"56":{"sum_comment":"","sum_foreign_comment":"","sum_foreign":"","sum":""},"57":{"sum_comment":"","sum_foreign_comment":"","sum_foreign":"","sum":"18063","sum_comment_hidden":false},"58":{"sum_comment":"","sum_foreign_comment":"","sum_foreign":"","sum":"","sum_comment_hidden":false},"59":{"sum_comment":"","sum_foreign_comment":"","sum_foreign":"","sum":""},"60":{"sum_comment":"","sum_foreign_comment":"","sum_foreign":"","sum":""},"61":{"sum_comment":"","sum_foreign_comment":"","sum_foreign":"","sum":""},"62":{"sum_comment":"","sum_foreign_comment":"","sum_foreign":"","sum":""},"63":{"sum_comment":"","sum_foreign_comment":"","sum_foreign":"","sum":""},"64":{"sum_comment":"","sum_foreign_comment":"","sum_foreign":"","sum":""}},"intro":{"isnotdeclaration":"","declaration_year":"2015"}}