{"income":{"5":{"value":"179340","family_comment":"","value_unclear":false,"family_unclear":false,"family":"65053","comment":""},"6":{"value":"179340","family_comment":"","value_unclear":false,"family_unclear":false,"family":"57949","comment":""},"7":{"family_comment":"","value":"","source_name":"","family":"","comment":""},"8":{"family_comment":"","value":"","family":"","comment":""},"9":{"family_comment":"","value":"","family":"","comment":"","family_comment_unclear":false},"10":{"family_comment":"","value":"","family":"7104","comment":""},"11":{"family_comment":"","value":"","family":"","comment":""},"12":{"family_comment":"","value":"","family":"","comment":""},"13":{"family_comment":"","value":"","family":"","comment":""},"14":{"family_comment":"","value":"","family":"","comment":""},"15":{"family_comment":"","value":"","family":"","comment":""},"16":{"family_comment":"","family_unclear":false,"value":"","family":"","comment":""},"17":{"family_comment":"","family_unclear":false,"value":"","family":"","comment":""},"18":{"family_comment":"","value":"","family":"","comment":""},"19":{"family_comment":"","value":"","family":"","comment":""},"20":{"family_comment":"","value":"","family":"","comment":""}},"vehicle":{"40":[{"brand_info":"1197 куб. см., 77 кВт","sum_rent_comment":"","brand":"Volkswagen Polo","sum_comment":"","year":"2011","brand_hidden":false,"brand_info_hidden":false,"sum":"","sum_rent":""}]},"id":"vulyk_88_70","declaration":{"additional_info_text":"","notfull_lostpages":"","date":"2015-03-30T00:00:00","notfull":"","additional_info":"","url":"http://static.declarations.com.ua/declarations/chosen_ones/judges_batch/2973_pustovoit_tetiana_valeriivna.pdf"},"liabilities":{"54":{"sum_foreign_comment":"","sum":"","sum_comment":"","sum_comment_unclear":false,"sum_foreign":""},"55":{"sum_foreign_comment":"","sum":"","sum_comment":"","sum_foreign":""},"56":{"sum_foreign_comment":"","sum":"","sum_comment":"","sum_foreign":""},"57":{"sum_foreign_comment":"","sum":"","sum_comment":"","sum_hidden":false,"sum_comment_hidden":false,"sum_unclear":false,"sum_foreign":""},"58":{"sum_foreign_comment":"","sum":"","sum_comment":"","sum_hidden":false,"sum_comment_hidden":false,"sum_foreign":""},"59":{"sum_foreign_comment":"","sum":"","sum_comment":"","sum_foreign":""},"60":{"sum_foreign_comment":"","sum":"","sum_comment":"","sum_comment_unclear":false,"sum_hidden":false,"sum_comment_hidden":false,"sum_foreign":""},"61":{"sum_foreign_comment":"","sum":"","sum_comment":"","sum_foreign":""},"62":{"sum_foreign_comment":"","sum":"","sum_comment":"","sum_foreign":""},"63":{"sum_foreign_comment":"","sum":"","sum_comment":"","sum_foreign":""},"64":{"sum_foreign_comment":"","sum":"","sum_comment":"","sum_foreign":""}},"ft_src":"суддя іллічівського районного суду м. маріуполя донецької області\nДонецька область\nЗагальний місцевий суд\nТетяна\nПустовойт В. К\nПодружжя\nПустовойт В. В\nДитина\nПустовойт Я. В\nДитина\nВалеріївна\nПустовойт Тетяна Валеріївна\nТетяна Валеріївна Пустовойт\nТетяна Пустовойт\nПустовойт Тетяна Валеріївна\nПустовойт\nПустовойт Тетяна Валеріївна\n2011\nVolkswagen Polo\n1197 куб. см., 77 кВт\n40\n2014\n57949\n179340\n7104\n65053\n179340\n1197 куб. см., 77 кВт\n2011\nVolkswagen Polo\n40\nПустовойт Тетяна Валеріївна\nТетяна Валеріївна Пустовойт\nТетяна Пустовойт\nПустовойт Тетяна Валеріївна\nТетяна\nПодружжя\nПустовойт В. К\nДитина\nПустовойт В. В\nДитина\nПустовойт Я. В\nПустовойт Тетяна Валеріївна\nПустовойт\nЗагальний місцевий суд\nсуддя іллічівського районного суду м. маріуполя донецької області\nДонецька область\nВалеріївна\n179340\n57949\n179340\n65053\n7104\n2014\nПустовойт В. К\nПодружжя\nПустовойт В. В\nДитина\nПустовойт Я. В\nДитина\nВалеріївна\nПустовойт\nТетяна\nПустовойт Тетяна Валеріївна\nТетяна Валеріївна Пустовойт\nТетяна Пустовойт\nПустовойт Тетяна Валеріївна\nДонецька область\nЗагальний місцевий суд\nсуддя іллічівського районного суду м. маріуполя донецької області\nПустовойт Тетяна Валеріївна\n2011\nVolkswagen Polo\n1197 куб. см., 77 кВт\n7104\n179340\n65053\n179340\n57949\n40\n2014","general":{"inn":"","name":"Тетяна","patronymic_unclear":false,"family":[{"inn_hidden":true,"inn":"","name_hidden":false,"family_name":"Пустовойт В. К","relations":"Подружжя","name_unclear":false},{"inn":"","relations":"Дитина","relations_other":"","inn_hidden":false,"family_name":"Пустовойт В. В","name_hidden":false,"name_unclear":false},{"inn":"","relations":"Дитина","relations_other":"","inn_hidden":false,"family_name":"Пустовойт Я. В","name_hidden":false,"name_unclear":false}],"patronymic":"Валеріївна","inn_hidden":true,"family_raw":"","last_name":"Пустовойт","post":{"post":"суддя іллічівського районного суду м. маріуполя донецької області","region":"Донецька область","candidate":"","office_hidden":false,"region_hidden":false,"office":"Загальний місцевий суд"},"last_name_unclear":false,"full_name":"Пустовойт Тетяна Валеріївна","addresses":[{"place_district":"","place_city_hidden":true,"place_city":"","place_city_type_hidden":true,"place_district_hidden":true,"place_city_type":"","place_address_hidden":true,"place_address":"","place_hidden":true,"place":""}],"patronymic_hidden":false,"full_name_suggest":{"output":"Пустовойт Тетяна Валеріївна","input":["Пустовойт Тетяна Валеріївна","Тетяна Валеріївна Пустовойт","Тетяна Пустовойт"]}},"source":"VULYK","estate":{"33":[{"costs_rent":"","region":"","costs_property":"","costs_rent_comment":"","address_hidden":true,"region_hidden":true,"space_comment":"","costs_property_comment":"","space_units":"м²","space":"40","address":""}]},"intro":{"declaration_year":"2014","isnotdeclaration":""}}