{"income":{"5":{"value":"178771","family_comment":"","value_unclear":false,"family_unclear":false,"family":"10000","comment":"177271"},"6":{"value":"177271","family_comment":"","value_unclear":false,"family_unclear":false,"family":"","comment":""},"7":{"value":"","value_unclear":false,"family_comment":"","source_name":"","family":"","comment":""},"8":{"family_comment":"","value":"","family":"","comment":""},"9":{"family_comment":"","value":"1500","value_unclear":false,"family":"","comment":""},"10":{"family_comment":"","value":"","comment_unclear":false,"family":"","comment":""},"11":{"family_comment":"","value":"","family":"","comment":""},"12":{"family_comment":"","value":"","family":"","comment":""},"13":{"family_comment":"","value":"","family":"","comment":""},"14":{"family_comment":"","value":"","family":"","comment":""},"15":{"family_comment":"","value":"","family":"","comment":""},"16":{"family_comment":"","value":"","family":"","comment":""},"17":{"family_comment":"","value":"","family":"10000","comment":""},"18":{"family_comment":"","value":"","family":"","comment":""},"19":{"family_comment":"","value":"","family":"","comment":""},"20":{"family_comment":"","value":"","family":"","comment":""}},"vehicle":{"40":[{"brand_info":"OZCF35, 1796 куб. см., 103 кВт","sum_rent_comment":"","year":"2007","brand_info_hidden":false,"brand_info_unclear":false,"sum_rent":"","sum":"","brand":"Opel Vectra","sum_comment":"","sum_comment_unclear":false,"brand_hidden":false,"brand_unclear":false}],"44":[{"brand_info":"мопед, 49 куб. см.","sum_rent_comment":"","brand":"Honda Giorno","sum_comment":"","year":"1996","sum":"","sum_rent":""}]},"id":"vulyk_55_72","banks":{"45":[{"sum_foreign_comment":"","sum_units":"UAH","sum_comment":"","sum_comment_unclear":false,"sum_foreign_units":"UAH","sum_foreign_comment_unclear":false,"sum_units_unclear":false,"sum_comment_hidden":false,"sum_unclear":false,"sum":"","sum_foreign":""},{"sum_foreign_comment":"","sum_units":"","sum_comment":"","sum_comment_unclear":false,"sum_foreign_units":"","sum":"","sum_unclear":false,"sum_foreign":""},{"sum_foreign_comment":"","sum_units":"","sum_comment":"","sum_foreign_units":"","sum":"","sum_unclear":false,"sum_foreign":""}],"46":[{"sum_foreign_comment":"","sum_units":"UAH","sum_comment":"","sum_comment_unclear":false,"sum_foreign_units":"UAH","sum":"","sum_foreign":""}],"47":[{"sum_foreign_comment":"","sum_units":"UAH","sum_comment":"","sum_comment_unclear":false,"sum_hidden":false,"sum_foreign_units":"UAH","sum":"","sum_foreign":""}],"48":[{"sum_foreign_comment":"","sum_units":"UAH","sum_comment":"","sum_foreign_units":"UAH","sum":"","sum_foreign":""}],"49":[{"sum_foreign_comment":"","sum_units":"UAH","sum_comment":"","sum_foreign_units":"UAH","sum":"","sum_foreign":""},{"sum_foreign_comment":"","sum_units":"","sum_comment":"","sum":"","sum_foreign":""}],"50":[{"sum_foreign_comment":"","sum_units":"UAH","sum_comment":"","sum_foreign_units":"UAH","sum":"","sum_foreign":""}],"51":[{"sum_units":"UAH","sum_hidden":false,"sum_units_hidden":false,"sum_foreign":"","sum_foreign_comment":"","sum":"","sum_comment":"","sum_comment_unclear":false,"sum_foreign_units":"UAH","sum_units_unclear":false,"sum_comment_hidden":false,"sum_unclear":false},{"sum_foreign_comment":"","sum_units":"","sum_comment":"","sum_foreign_units":"","sum":"","sum_foreign":""}],"52":[{"sum_foreign_comment":"","sum_units":"UAH","sum_comment":"","sum_comment_unclear":false,"sum_foreign_units":"UAH","sum":"","sum_foreign":""},{"sum_foreign_comment":"","sum_units":"","sum_comment":"","sum_foreign_units":"","sum":"","sum_foreign":""}],"53":[{"sum_foreign_comment":"","sum_units":"UAH","sum_comment":"","sum_hidden":false,"sum_foreign_units":"UAH","sum":"","sum_unclear":false,"sum_foreign":""},{"sum_foreign_comment":"","sum_units":"","sum_comment":"","sum_comment_unclear":false,"sum_foreign_units":"","sum":"","sum_foreign":""},{"sum_foreign_comment":"","sum_units":"","sum_comment":"","sum_foreign_units":"","sum":"","sum_foreign":""},{"sum_foreign_comment":"","sum_units":"","sum_comment":"","sum_foreign_units":"","sum":"","sum_foreign":""}]},"declaration":{"additional_info_text":"","notfull_lostpages":"","date":"2015-03-20T00:00:00","notfull":"","additional_info":"","url":"http://static.declarations.com.ua/declarations/chosen_ones/mega_batch/haidar_iryna_oleksandrivna.pdf"},"liabilities":{"54":{"sum_foreign_comment":"","sum":"","sum_comment":"","sum_hidden":false,"sum_comment_hidden":false,"sum_foreign":""},"55":{"sum_foreign_comment":"","sum_foreign_hidden":false,"sum_comment":"","sum_hidden":false,"sum":"","sum_foreign":""},"56":{"sum_foreign_comment":"","sum":"","sum_comment":"","sum_unclear":false,"sum_foreign":""},"57":{"sum_foreign_comment":"","sum":"","sum_comment":"","sum_comment_unclear":false,"sum_hidden":false,"sum_comment_hidden":false,"sum_unclear":false,"sum_foreign":""},"58":{"sum_foreign_comment":"","sum":"","sum_comment":"","sum_hidden":false,"sum_comment_hidden":false,"sum_unclear":false,"sum_foreign":""},"59":{"sum_foreign_comment":"","sum":"","sum_comment":"","sum_foreign":""},"60":{"sum_foreign_comment":"","sum":"","sum_comment":"","sum_hidden":false,"sum_comment_hidden":false,"sum_foreign":""},"61":{"sum_foreign_comment":"","sum":"","sum_comment":"","sum_foreign":""},"62":{"sum_foreign_comment":"","sum":"","sum_comment":"","sum_foreign":""},"63":{"sum_foreign_comment":"","sum":"","sum_comment":"","sum_unclear":false,"sum_foreign":""},"64":{"sum_foreign_comment":"","sum":"","sum_comment":"","sum_unclear":false,"sum_foreign":""}},"ft_src":"Лозова\n64600\nХарківська область\nсуддя юр'ївського районного суду дніпропетровської області\nДніпропетровська область\nЗагальний місцевий суд\nІрина\nГайдар І. М\nПодружжя\nГайдар М. І\nДитина\nОлександрівна\nГайдар\nГайдар Ірина Олександрівна\nГайдар Ірина Олександрівна\nІрина Олександрівна Гайдар\nІрина Гайдар\nГайдар Ірина Олександрівна\nOZCF35, 1796 куб. см., 103 кВт\nOpel Vectra\n2007\nмопед, 49 куб. см.\n1996\nHonda Giorno\n2014\nOZCF35, 1796 куб. см., 103 кВт\nOpel Vectra\n2007\nмопед, 49 куб. см.\nHonda Giorno\n1996\n982\nм. Лозова\nХарківська область\nм. Лозова\n48.48\nм. Лозова\nХарківська область\n12.88\nХарківська область\nм. Лозова\nПодружжя\nГайдар І. М\nДитина\nГайдар М. І\nГайдар Ірина Олександрівна\nІрина Олександрівна Гайдар\nІрина Гайдар\nГайдар Ірина Олександрівна\nІрина\nГайдар Ірина Олександрівна\nОлександрівна\nЗагальний місцевий суд\nсуддя юр'ївського районного суду дніпропетровської області\nДніпропетровська область\nГайдар\nЛозова\n64600\nХарківська область\n177271\n10000\n178771\n10000\n177271\n1500\n2014\nХарківська область\nм. Лозова\n982\nм. Лозова\nм. Лозова\nХарківська область\n48.48\n12.88\nм. Лозова\nХарківська область\nГайдар І. М\nПодружжя\nГайдар М. І\nДитина\nОлександрівна\nГайдар\nГайдар Ірина Олександрівна\nІрина Олександрівна Гайдар\nІрина Гайдар\nГайдар Ірина Олександрівна\nХарківська область\nЛозова\n64600\nДніпропетровська область\nсуддя юр'ївського районного суду дніпропетровської області\nЗагальний місцевий суд\nГайдар Ірина Олександрівна\nІрина\n177271\n10000\n177271\n178771\n10000\n1500\nHonda Giorno\nмопед, 49 куб. см.\n1996\nOpel Vectra\nOZCF35, 1796 куб. см., 103 кВт\n2007\n177271\n178771\n10000\n10000\n1500\n177271\nм. Лозова\nХарківська область\n48.48\nм. Лозова\nм. Лозова\nХарківська область\n12.88\nм. Лозова\nХарківська область\n982\n2014","general":{"name_hidden":false,"name":"Ірина","patronymic_unclear":false,"last_name_hidden":false,"inn":"","family":[{"inn":"","inn_hidden":false,"relations_unclear":false,"relations_hidden":false,"relations_other":"","relations":"Подружжя","name_hidden":false,"family_name":"Гайдар І. М","name_unclear":false},{"inn":"","relations":"Дитина","relations_other":"","inn_hidden":false,"family_name":"Гайдар М. І","name_hidden":false,"name_unclear":false}],"patronymic":"Олександрівна","inn_hidden":false,"family_raw":"","inn_unclear":false,"post":{"post_unclear":false,"post":"суддя юр'ївського районного суду дніпропетровської області","post_hidden":false,"region":"Дніпропетровська область","region_hidden":false,"office":"Загальний місцевий суд","office_hidden":false,"office_unclear":false},"last_name_unclear":false,"full_name":"Гайдар Ірина Олександрівна","addresses":[{"place_city_type_unclear":false,"place_address":"64600","place_district_hidden":false,"place_city_type":"Місто","place_address_hidden":false,"place_address_unclear":false,"place_city_type_hidden":false,"place":"Харківська область","place_district":"","place_city_hidden":false,"place_city":"Лозова","place_city_unclear":false,"place_hidden":false}],"last_name":"Гайдар","patronymic_hidden":false,"full_name_suggest":{"output":"Гайдар Ірина Олександрівна","input":["Гайдар Ірина Олександрівна","Ірина Олександрівна Гайдар","Ірина Гайдар"]}},"source":"VULYK","estate":{"23":[{"space_hidden":false,"costs":"","costs_comment":"","address_hidden":false,"region_hidden":false,"space_comment":"","space":"982","address":"м. Лозова","region":"Харківська область","address_unclear":false,"costs_rent_comment":"","space_units":"м²","costs_rent":""},{"costs_rent":"","region":"","costs":"","costs_rent_comment":"","costs_comment":"","region_hidden":false,"space_comment":"","space_units":"","space":"","address":""},{"costs_rent":"","region":"","costs":"","costs_rent_comment":"","costs_comment":"","space_comment":"","space_units":"","space":"","address":""},{"costs_rent":"","costs":"","costs_rent_comment":"","costs_comment":"","space_comment":"","space_units":"","space":"","address":""}],"25":[{"region_unclear":false,"space_unclear":false,"costs":"","costs_comment":"","costs_hidden":false,"address_hidden":false,"region_hidden":false,"space_comment":"","space_hidden":false,"space":"12.88","address":"м. Лозова","costs_unclear":false,"region":"Харківська область","address_unclear":false,"costs_rent_comment":"","space_comment_unclear":false,"space_comment_hidden":false,"space_units":"м²","costs_rent":""}],"30":[{"space_unclear":false,"address_hidden":false,"region_hidden":false,"space_comment":"","space":"","address":"м. Лозова","region":"","costs_property":"","costs_rent_comment":"","address_unclear":false,"space_units":"м²","costs_property_comment":"","costs_rent":""}],"31":[{"region_unclear":false,"space_unclear":false,"address_hidden":false,"region_hidden":false,"space_comment":"","space_hidden":false,"space":"48.48","address":"м. Лозова","region":"Харківська область","costs_property":"","space_units_unclear":false,"space_comment_unclear":false,"space_units":"м²","costs_property_comment":"","costs_rent":"","costs_rent_comment":""}]},"intro":{"declaration_year":"2014","isnotdeclaration":""}}