{"income":{"5":{"family_comment":"","family_unclear":false,"value":"129199","family":"14541","comment":""},"6":{"family_comment":"","value":"98262","value_unclear":false,"family":"14541","comment":""},"7":{"family_comment":"","value":"","source_name":"Гребенінківський районий суд Полтавської області, УПСЗН в Ленінському районі Полтавської області,ПП 'Барбус-ЛС'","family":"","comment":""},"8":{"family_comment":"","value":"","family":"","comment":""},"9":{"value":"","value_unclear":false,"family_hidden":false,"family_comment":"","comment_unclear":false,"comment":"","family":""},"10":{"family_comment":"","value":"","family":"","comment":""},"11":{"family_comment":"","value":"","family":"","comment":""},"12":{"family_comment":"","value":"","family":"","comment":""},"13":{"family_comment":"","value":"","family":"","comment":""},"14":{"family_comment":"","value":"","family":"","comment":""},"15":{"family_comment":"","value":"","family":"","comment":""},"16":{"family_comment":"","value":"","family":"","comment":""},"17":{"family_comment":"","value":"","family":"","comment":""},"18":{"family_comment":"","value":"","family":"","comment":""},"19":{"family_comment":"","value":"","family":"","comment":""},"20":{"value":"30937","value_unclear":false,"comment_hidden":false,"family_comment":"","family":"","comment":""}},"vehicle":{"35":[{"brand_info":"1.3 л","sum_rent_comment":"","brand":"Ford Fiesta","sum_comment":"","year":"2012","brand_info_hidden":false,"brand_info_unclear":false,"sum":"","sum_rent":""}]},"id":"vulyk_40_28","banks":{"45":[{"sum_foreign_comment":"","sum_units":"UAH","sum_comment":"","sum_hidden":false,"sum_foreign_units":"UAH","sum":"","sum_foreign":""},{"sum_foreign_comment":"","sum_units":"","sum_comment":"","sum_foreign_units":"","sum":"","sum_foreign":""},{"sum_foreign_comment":"","sum_units":"","sum_comment":"","sum_foreign_units":"","sum":"","sum_foreign":""}],"46":[{"sum_foreign_comment":"","sum_units":"UAH","sum_comment":"","sum_foreign_units":"UAH","sum":"","sum_unclear":false,"sum_foreign":""}],"47":[{"sum_foreign_comment":"","sum_units":"UAH","sum_comment":"","sum_foreign_units":"UAH","sum":"","sum_foreign":""}],"48":[{"sum_foreign_comment":"","sum_units":"UAH","sum_comment":"","sum_foreign_units":"UAH","sum":"","sum_foreign":""}],"49":[{"sum_foreign_comment":"","sum_units":"UAH","sum_comment":"","sum_foreign_units":"UAH","sum":"","sum_foreign":""}],"50":[{"sum_foreign_comment":"","sum_units":"UAH","sum_comment":"","sum_foreign_units":"UAH","sum":"","sum_foreign":""}],"51":[{"sum_foreign_comment":"","sum_units":"UAH","sum_comment":"","sum_foreign_units":"UAH","sum":"","sum_foreign":""}],"52":[{"sum_foreign_comment":"","sum_units":"UAH","sum_comment":"","sum_foreign_units":"UAH","sum":"","sum_foreign":""}],"53":[{"sum_foreign_comment":"","sum_units":"UAH","sum_comment":"","sum_foreign_units":"UAH","sum":"","sum_foreign":""}]},"declaration":{"date":"2014-03-24T00:00:00","notfull":"","url":"http://static.declarations.com.ua/declarations/chosen_ones/mega_batch/tatishcheva_iana_viktorivna.pdf","notfull_lostpages":""},"liabilities":{"54":{"sum_foreign_comment":"","sum":"6796","sum_comment":"","sum_foreign":""},"55":{"sum_foreign_comment":"","sum":"","sum_comment":"","sum_foreign":""},"56":{"sum_foreign_comment":"","sum":"","sum_comment":"","sum_foreign":""},"57":{"sum_foreign_comment":"","sum":"21934","sum_comment":"","sum_hidden":false,"sum_comment_hidden":false,"sum_foreign":""},"58":{"sum_foreign_comment":"","sum":"11730","sum_comment":"","sum_hidden":false,"sum_comment_hidden":false,"sum_foreign":""},"59":{"sum_foreign_comment":"","sum":"","sum_comment":"","sum_foreign":""},"60":{"sum_foreign_comment":"","sum":"","sum_comment":"","sum_foreign":""},"61":{"sum_foreign_comment":"","sum":"","sum_comment":"","sum_foreign":""},"62":{"sum_foreign_comment":"","sum":"","sum_comment":"","sum_foreign":""},"63":{"sum_foreign_comment":"","sum":"","sum_comment":"","sum_foreign":""},"64":{"sum_foreign_comment":"","sum":"","sum_comment":"","sum_foreign":""}},"ft_src":"21934\n6796\n11730\nТатіщева Яна Вікторівна\nсуддя гребінківського районного суду полтавської області\nПолтавська область\nЗагальний місцевий суд\nЯна\nТатіщев В. О\nПодружжя\nТатіщева О. В\nДитина\nТатіщева Є. В\nДитина\nТатіщева Яна Вікторівна\nЯна Вікторівна Татіщева\nЯна Татіщева\nТатіщева Яна Вікторівна\nТатіщева\nВікторівна\n2012\n1.3 л\nFord Fiesta\n2013\n1.3 л\n2012\nFord Fiesta\nТатіщева\nТатіщева Яна Вікторівна\nЯна Вікторівна Татіщева\nЯна Татіщева\nТатіщева Яна Вікторівна\nЯна\nВікторівна\nТатіщева Яна Вікторівна\nЗагальний місцевий суд\nсуддя гребінківського районного суду полтавської області\nПолтавська область\nПодружжя\nТатіщев В. О\nДитина\nТатіщева О. В\nТатіщева Є. В\nДитина\n21934\n11730\n6796\nГребенінківський районий суд Полтавської області, УПСЗН в Ленінському районі Полтавської області,ПП 'Барбус-ЛС'\n98262\n14541\n30937\n129199\n14541\n2013\n11730\n21934\n6796\nТатіщев В. О\nПодружжя\nТатіщева О. В\nДитина\nТатіщева Є. В\nДитина\nВікторівна\nТатіщева\nсуддя гребінківського районного суду полтавської області\nПолтавська область\nЗагальний місцевий суд\nТатіщева Яна Вікторівна\nТатіщева Яна Вікторівна\nЯна Вікторівна Татіщева\nЯна Татіщева\nТатіщева Яна Вікторівна\nЯна\n14541\n98262\nГребенінківський районий суд Полтавської області, УПСЗН в Ленінському районі Полтавської області,ПП 'Барбус-ЛС'\n14541\n129199\n30937\n2012\n1.3 л\nFord Fiesta\n30937\n14541\n129199\nГребенінківський районий суд Полтавської області, УПСЗН в Ленінському районі Полтавської області,ПП 'Барбус-ЛС'\n14541\n98262\n2013","general":{"inn":"","inn_hidden":true,"last_name":"Татіщева","post":{"office":"Загальний місцевий суд","region":"Полтавська область","post":"суддя гребінківського районного суду полтавської області"},"name":"Яна","full_name":"Татіщева Яна Вікторівна","family_raw":"","addresses":[{"place_district":"","place_city_hidden":false,"place_city":"","place_city_type_hidden":false,"place_district_hidden":false,"place_city_type":"","place_address_hidden":false,"place_address":"","place_hidden":true,"place":""}],"family":[{"inn":"","relations":"Подружжя","relations_other":"","inn_hidden":false,"family_name":"Татіщев В. О","name_hidden":false},{"inn":"","relations":"Дитина","relations_other":"","inn_hidden":false,"family_name":"Татіщева О. В","name_unclear":false},{"inn":"","family_name":"Татіщева Є. В","relations":"Дитина","inn_hidden":false}],"full_name_suggest":{"output":"Татіщева Яна Вікторівна","input":["Татіщева Яна Вікторівна","Яна Вікторівна Татіщева","Яна Татіщева"]},"patronymic":"Вікторівна"},"source":"VULYK","estate":{"23":[{"costs_rent":"","region":"","costs":"","costs_rent_comment":"","costs_comment":"","address_hidden":false,"region_hidden":false,"space_comment":"","space_units":"м²","space":"","address":""},{"costs_rent":"","region":"","costs":"","costs_rent_comment":"","costs_comment":"","space_comment":"","space_units":"","space":"","address":""},{"costs_rent":"","region":"","costs":"","costs_rent_comment":"","costs_comment":"","space_comment":"","space_units":"","space":"","address":""},{"costs_rent":"","costs":"","costs_rent_comment":"","costs_comment":"","space_comment":"","space_units":"","space":"","address":""}]},"intro":{"declaration_year":"2013"}}