{"income":{"5":{"family_comment":"","value":"218656.73","family_hidden":false,"comment":"","family":"471683"},"6":{"family_comment":"","value":"205258.73","family_hidden":false,"comment":"","family":"19635"},"7":{"family_comment":"","value":"","source_name":"","family":"","comment":""},"8":{"family_comment":"","value":"","family":"","comment":""},"9":{"family_comment":"","value":"","family":"","comment":""},"10":{"family_comment":"","value":"13398","family":"","comment":""},"11":{"family_comment":"","value":"","family":"","comment":""},"12":{"family_comment":"","value":"","family":"","comment":""},"13":{"family_comment":"","value":"","family":"","comment":""},"14":{"family_comment":"","value":"","family":"","comment":""},"15":{"family_comment":"","value":"","family":"","comment":""},"16":{"family_comment":"","value":"","family":"149000","comment":""},"17":{"family_comment":"","value":"","family":"","comment":""},"18":{"family_comment":"","value":"","family":"","comment":""},"19":{"family_comment":"","value":"","family":"","comment":""},"20":{"family_comment":"","value":"","family":"303048","comment":""}},"vehicle":{"35":[{"brand_info":"2.2 дизель","sum_rent_comment":"","brand":"Hyundai Santa FE","sum_comment":"","year":"2006","brand_info_hidden":false,"sum":"149000","sum_rent":""}],"40":[{"year_hidden":false,"brand_info":"2.5 , бенз","sum_rent_comment":"","brand":"Toyota Camry","sum_comment":"","year":"2014","brand_hidden":false,"brand_info_hidden":false,"sum":"","sum_rent":""}],"44":[{"brand_info":"причіп","sum":"","brand":"Сантей","sum_comment":"","brand_unclear":true,"year":"2013","brand_info_hidden":false,"sum_rent_comment":"","sum_rent":""}]},"id":"vulyk_105_34","declaration":{"date":"2015-03-26T00:00:00","additional_info_text":"","additional_info":"","url":"http://static.declarations.com.ua/declarations/chosen_ones/judges_batch/4609_shaptala_ievhen_iuriiovych.pdf"},"liabilities":{"54":{"sum_foreign_comment":"","sum_comment_hidden":false,"sum":"","sum_comment":"","sum_foreign":""},"55":{"sum_foreign_comment":"","sum":"","sum_comment":"","sum_foreign":""},"56":{"sum_foreign_comment":"","sum":"","sum_comment":"","sum_foreign":""},"57":{"sum_foreign_comment":"","sum":"","sum_comment":"","sum_comment_unclear":false,"sum_comment_hidden":false,"sum_foreign":""},"58":{"sum_foreign_comment":"","sum":"","sum_comment":"","sum_foreign":""},"59":{"sum_foreign_comment":"","sum":"","sum_comment":"","sum_foreign":""},"60":{"sum_foreign_comment":"","sum":"","sum_comment":"","sum_foreign":""},"61":{"sum_foreign_comment":"","sum":"","sum_comment":"","sum_foreign":""},"62":{"sum_foreign_comment":"","sum":"","sum_hidden":false,"sum_comment":"","sum_foreign":""},"63":{"sum_foreign_comment":"","sum":"","sum_comment":"","sum_foreign":""},"64":{"sum_foreign_comment":"","sum":"","sum_comment":"","sum_foreign":""}},"ft_src":"Шаптала Євген Юрійович\nсуддя\nм. Київ\nАпеляційний господарський суд\nЄвген\nШаптала О. В\nПодружжя\nШаптала М. Є\nДитина\nШаптала Євген Юрійович\nЄвген Юрійович Шаптала\nЄвген Шаптала\nШаптала Євген Юрійович\nШаптала\nЮрійович\n2.2 дизель\n149000\n2006\nHyundai Santa FE\n2.5 , бенз\nToyota Camry\n2014\n2013\nСантей\nпричіп\nбезопл\n.12\n2014\n19635\n205258.73\n13398\n471683\n218656.73\n149000\n303048\nHyundai Santa FE\n2.2 дизель\n2006\n149000\n2.5 , бенз\n2014\nToyota Camry\nСантей\nпричіп\n2013\n2014\nсуддя\nАпеляційний господарський суд\nм. Київ\nШаптала\nШаптала Євген Юрійович\nЄвген Юрійович Шаптала\nЄвген Шаптала\nШаптала Євген Юрійович\nШаптала Євген Юрійович\nЄвген\nЮрійович\nПодружжя\nШаптала О. В\nДитина\nШаптала М. Є\n205258.73\n19635\n303048\n218656.73\n471683\n149000\n13398\n.12\nбезопл\nШаптала О. В\nПодружжя\nШаптала М. Є\nДитина\nЮрійович\nШаптала\nм. Київ\nсуддя\nАпеляційний господарський суд\nШаптала Євген Юрійович\nШаптала Євген Юрійович\nЄвген Юрійович Шаптала\nЄвген Шаптала\nШаптала Євген Юрійович\nЄвген\n2013\nСантей\nпричіп\n149000\nHyundai Santa FE\n2.2 дизель\n2006\nToyota Camry\n2.5 , бенз\n2014\n13398\n303048\n471683\n218656.73\n149000\n19635\n205258.73\nбезопл\n.12\n2014","general":{"inn":"","inn_hidden":true,"last_name":"Шаптала","post":{"post_unclear":false,"region_unclear":false,"region":"м. Київ","office_hidden":false,"office":"Апеляційний господарський суд","post":"суддя","office_unclear":true},"name":"Євген","full_name":"Шаптала Євген Юрійович","family_raw":"","addresses":[{"place_district":"","place_city_hidden":true,"place_city":"","place_city_type_hidden":true,"place_district_hidden":true,"place_city_type":"","place_address_hidden":true,"place_address":"","place_hidden":true,"place":""}],"family":[{"inn":"","inn_hidden":true,"relations_hidden":false,"family_name":"Шаптала О. В","relations_other":"","relations":"Подружжя","name_hidden":true,"name_unclear":false},{"inn":"","relations":"Дитина","relations_other":"","inn_hidden":true,"family_name":"Шаптала М. Є","name_hidden":false,"name_unclear":false}],"full_name_suggest":{"output":"Шаптала Євген Юрійович","input":["Шаптала Євген Юрійович","Євген Юрійович Шаптала","Євген Шаптала"]},"patronymic":"Юрійович"},"source":"VULYK","estate":{"23":[{"costs_rent":"","region":"","costs":"","costs_rent_comment":"","costs_comment":"","address_hidden":true,"region_hidden":true,"space_comment":"безопл","space_units":"га","space":".12","address":""}]},"intro":{"declaration_year":"2014"}}