{"income":{"5":{"value":"250621.36","family_comment":"","value_unclear":false,"family_unclear":false,"family":"","comment":""},"6":{"family_comment":"","family_unclear":false,"value":"237223.36","family":"","comment":""},"7":{"source_name_unclear":false,"value":"","family_comment":"","source_name":"","family":"","comment":""},"8":{"family_comment":"","value":"","family":"","comment":""},"9":{"value":"","family_comment":"","comment_hidden":false,"family_unclear":false,"family":"","comment":"","family_comment_hidden":false},"10":{"family_comment":"","value":"13398","family":"","comment":""},"11":{"family_comment":"","value":"","family":"","comment":""},"12":{"family_comment":"","value":"","family":"","comment":""},"13":{"family_comment":"","value":"","family":"","comment":""},"14":{"family_comment":"","value":"","family":"","comment":""},"15":{"family_comment":"","value":"","family":"","comment":""},"16":{"family_comment":"","value":"","family":"","comment":""},"17":{"family_comment":"","value":"","family":"","comment":""},"18":{"family_comment":"","value":"","family":"","comment":""},"19":{"family_comment":"","value":"","family":"","comment":""},"20":{"value":"","value_unclear":false,"comment_hidden":false,"family_comment":"","comment_unclear":false,"comment":"","family":""}},"vehicle":{"35":[{"brand_info":"1493","sum_rent_comment":"","brand":"Honda Civic","sum_comment":"","year":"1996","brand_info_unclear":false,"sum":"","sum_rent":""}]},"id":"vulyk_108_130","declaration":{"additional_info_text":"","notfull_lostpages":"","date":"2016-03-31T00:00:00","notfull":"","additional_info":"","url":"http://static.declarations.com.ua/declarations/chosen_ones/judges_batch/2429_prozorova_maryna_leonidivna_2015.pdf"},"liabilities":{"54":{"sum_foreign_comment":"","sum":"","sum_hidden":false,"sum_comment":"","sum_foreign":""},"55":{"sum_foreign_comment":"","sum":"","sum_comment":"","sum_foreign":""},"56":{"sum_foreign_comment":"","sum":"","sum_comment":"","sum_unclear":false,"sum_foreign":""},"57":{"sum_foreign_comment":"","sum":"","sum_comment":"","sum_hidden":false,"sum_comment_hidden":false,"sum_foreign":""},"58":{"sum_foreign_comment":"","sum_comment_hidden":false,"sum":"","sum_comment":"","sum_foreign":""},"59":{"sum_foreign_comment":"","sum":"","sum_comment":"","sum_unclear":false,"sum_foreign":""},"60":{"sum_foreign_comment":"","sum_comment_hidden":false,"sum":"","sum_comment":"","sum_foreign":""},"61":{"sum_foreign_comment":"","sum_comment_hidden":false,"sum":"","sum_comment":"","sum_foreign":""},"62":{"sum_foreign_comment":"","sum":"","sum_comment":"","sum_foreign":""},"63":{"sum_foreign_comment":"","sum":"","sum_comment":"","sum_hidden":false,"sum_comment_hidden":false,"sum_unclear":false,"sum_foreign":""},"64":{"sum_foreign_comment":"","sum":"","sum_comment":"","sum_comment_hidden":false,"sum_unclear":false,"sum_foreign":""}},"ft_src":"Прозорова Марина Леонідівна\nсуддя апеляційного суду дніпропетровської області\nДніпропетровська область\nЗагальний апеляційний суд\nМарина\nПрозорова Марина Леонідівна\nМарина Леонідівна Прозорова\nМарина Прозорова\nПрозорова Марина Леонідівна\nПрозорова\nЛеонідівна\n1493\n1996\nHonda Civic\n2100\n60\n2015\n237223.36\n13398\n250621.36\n1493\n1996\nHonda Civic\n2015\nЗагальний апеляційний суд\nДніпропетровська область\nсуддя апеляційного суду дніпропетровської області\nПрозорова\nПрозорова Марина Леонідівна\nМарина Леонідівна Прозорова\nМарина Прозорова\nПрозорова Марина Леонідівна\nМарина\nПрозорова Марина Леонідівна\nЛеонідівна\n237223.36\n250621.36\n13398\n2100\n60\nПрозорова\nЛеонідівна\nДніпропетровська область\nсуддя апеляційного суду дніпропетровської області\nЗагальний апеляційний суд\nПрозорова Марина Леонідівна\nПрозорова Марина Леонідівна\nМарина Леонідівна Прозорова\nМарина Прозорова\nПрозорова Марина Леонідівна\nМарина\n1996\n1493\nHonda Civic\n13398\n250621.36\n237223.36\n60\n2100\n2015","general":{"inn":"","family_raw":"","inn_unclear":false,"post":{"post_unclear":false,"post":"суддя апеляційного суду дніпропетровської області","office_hidden":false,"region":"Дніпропетровська область","office":"Загальний апеляційний суд","office_unclear":false},"name":"Марина","full_name":"Прозорова Марина Леонідівна","inn_hidden":true,"addresses":[{"place_city_type_hidden":true,"place_district_hidden":true,"place_city_type":"","place_city_hidden":true,"place_address_unclear":false,"place_address":"","place_hidden":true,"place":"","place_district":"","place_unclear":false,"place_city":"","place_address_hidden":true}],"last_name":"Прозорова","full_name_suggest":{"output":"Прозорова Марина Леонідівна","input":["Прозорова Марина Леонідівна","Марина Леонідівна Прозорова","Марина Прозорова"]},"patronymic":"Леонідівна"},"source":"VULYK","estate":{"23":[{"region_unclear":false,"space_unclear":false,"costs":"","costs_comment":"","address_hidden":true,"region_hidden":true,"space_comment":"","space":"2100","address":"","region":"","address_unclear":false,"space_units_unclear":false,"space_units":"м²","space_units_hidden":false,"costs_rent":"","costs_rent_comment":""}],"25":[{"space_unclear":false,"costs":"","costs_comment":"","address_hidden":true,"region_hidden":true,"space_comment":"","space":"60","address":"","region":"","costs_rent_comment":"","space_comment_unclear":false,"space_units":"м²","space_units_unclear":false,"costs_rent":""}]},"intro":{"declaration_year":"2015","isnotdeclaration":"","declaration_year_hidden":false}}