{"income":{"5":{"value":"207917.6","family_comment":"","value_unclear":false,"family_unclear":false,"family":"","comment":""},"6":{"family_comment":"","value":"207917.6","value_unclear":false,"family":"","comment":""},"7":{"value":"","value_unclear":false,"family_comment":"","source_name":"","family":"","comment":""},"8":{"family_comment":"","value":"","family":"","comment":""},"9":{"value":"","family_comment":"","value_unclear":false,"family_unclear":false,"family":"","comment":""},"10":{"family_comment":"","value":"","comment_unclear":false,"family":"","comment":""},"11":{"family_comment":"","value":"","family":"","comment":""},"12":{"family_comment":"","value":"","family":"","comment":""},"13":{"family_comment":"","value":"","value_unclear":false,"family":"","comment":""},"14":{"family_comment":"","value":"","family":"","comment":""},"15":{"family_comment":"","value":"","family":"","comment":""},"16":{"family_comment":"","family_unclear":false,"value":"","family":"","comment":""},"17":{"family_comment":"","family_unclear":false,"value":"","family":"","comment":""},"18":{"family_comment":"","value":"","family":"","comment":""},"19":{"family_comment":"","value":"","family":"","comment":""},"20":{"value":"","family_comment":"","value_unclear":false,"family_hidden":false,"value_hidden":false,"family_unclear":false,"comment_unclear":false,"comment":"","family":""}},"vehicle":{"35":[{"brand_info":"1499 куб. см., 76, 433.0","sum_rent_comment":"","brand_info_unclear":false,"year":"","brand_info_hidden":false,"sum_rent_comment_unclear":false,"sum_rent":"","sum":"","brand":"ВАЗ 21150","sum_comment":"","brand_unclear":false,"brand_hidden":false}]},"id":"vulyk_100_100","declaration":{"additional_info_text":"","notfull_lostpages":"","date":"2015-03-31T00:00:00","notfull":"","additional_info":"","url":"http://static.declarations.com.ua/declarations/chosen_ones/judges_batch/4300_saloid_nadiia_mykolaivna.pdf"},"liabilities":{"54":{"sum_foreign_comment":"","sum":"","sum_comment":"","sum_comment_hidden":false,"sum_unclear":false,"sum_foreign":""},"55":{"sum_foreign_comment":"","sum":"","sum_comment":"","sum_foreign":""},"56":{"sum_foreign_comment":"","sum":"","sum_comment":"","sum_unclear":false,"sum_foreign":""},"57":{"sum_foreign_comment":"","sum":"","sum_comment":"","sum_comment_unclear":false,"sum_comment_hidden":false,"sum_unclear":false,"sum_foreign":""},"58":{"sum_foreign_comment":"","sum":"","sum_comment":"","sum_comment_hidden":false,"sum_unclear":false,"sum_foreign":""},"59":{"sum_foreign_comment":"","sum":"","sum_comment":"","sum_foreign":""},"60":{"sum_foreign_comment":"","sum_comment_hidden":false,"sum":"","sum_comment":"","sum_foreign":""},"61":{"sum_foreign_comment":"","sum":"","sum_comment":"","sum_foreign":""},"62":{"sum_foreign_comment":"","sum":"","sum_comment":"","sum_unclear":false,"sum_foreign":""},"63":{"sum_foreign_comment":"","sum_comment_hidden":false,"sum":"","sum_comment":"","sum_foreign":""},"64":{"sum_foreign_comment":"","sum_comment_hidden":false,"sum":"","sum_comment":"","sum_foreign":""}},"ft_src":"Миколаївна\nСалоїд Надія Миколаївна\nсуддя хмельницького міськрайонного суду\nХмельницька область\nЗагальний місцевий суд\nНадія\nСалоїд Надія Миколаївна\nНадія Миколаївна Салоїд\nНадія Салоїд\nСалоїд Надія Миколаївна\nСалоїд\n1499 куб. см., 76, 433.0\nВАЗ 21150\n1200\n2500\n65.7\n2014\n207917.6\n207917.6\n1499 куб. см., 76, 433.0\nВАЗ 21150\n1200\n2500\n65.7\nЗагальний місцевий суд\nХмельницька область\nсуддя хмельницького міськрайонного суду\nМиколаївна\nСалоїд Надія Миколаївна\nНадія Миколаївна Салоїд\nНадія Салоїд\nСалоїд Надія Миколаївна\nСалоїд Надія Миколаївна\nНадія\nСалоїд\n207917.6\n207917.6\n2014\nМиколаївна\nСалоїд\nХмельницька область\nЗагальний місцевий суд\nсуддя хмельницького міськрайонного суду\nСалоїд Надія Миколаївна\nСалоїд Надія Миколаївна\nНадія Миколаївна Салоїд\nНадія Салоїд\nСалоїд Надія Миколаївна\nНадія\nВАЗ 21150\n1499 куб. см., 76, 433.0\n207917.6\n207917.6\n65.7\n1200\n2500\n2014","general":{"inn":"","inn_hidden":true,"last_name":"Салоїд","post":{"post_unclear":false,"region_unclear":false,"post":"суддя хмельницького міськрайонного суду","office":"Загальний місцевий суд","region":"Хмельницька область","post_hidden":false,"office_unclear":false},"name":"Надія","full_name":"Салоїд Надія Миколаївна","family_raw":"","addresses":[{"place_district":"","place_city_hidden":true,"place_city":"","place_city_unclear":false,"place_district_hidden":false,"place_city_type":"","place_address_hidden":true,"place_city_type_hidden":false,"place_address":"","place_hidden":true,"place":""}],"full_name_suggest":{"output":"Салоїд Надія Миколаївна","input":["Салоїд Надія Миколаївна","Надія Миколаївна Салоїд","Надія Салоїд"]},"patronymic":"Миколаївна"},"source":"VULYK","estate":{"23":[{"space_unclear":false,"costs":"","costs_comment":"","address_hidden":false,"region_hidden":true,"space_comment":"","space":"1200","address":"","costs_comment_unclear":false,"region":"","address_unclear":false,"costs_rent_comment":"","space_comment_unclear":false,"space_units":"м²","costs_rent":""},{"costs_rent":"","space_unclear":false,"region":"","costs":"","costs_rent_comment":"","costs_comment":"","space_comment":"","space_units":"м²","space":"2500","address":""}],"25":[{"space_unclear":false,"costs":"","costs_comment":"","address_hidden":false,"region_hidden":true,"space_comment":"","space":"65.7","address":"","costs_comment_unclear":false,"region":"","address_unclear":false,"costs_rent_comment":"","space_comment_unclear":false,"space_units":"м²","costs_rent":""}]},"intro":{"declaration_year":"2014"}}