{"id":"vulyk_88_61","ft_src":"причіп легковий В\n2014\nУВН-810083\nHyundai Sonata\n2011\n1998 куб. см., 121 кВт\n2011\nHyundai Sonata\n1998 куб. см., 121 кВт\nм. Дружківка\nДонецька область\n10.425\n2014\n33612\n191321\n9543\n1551\n12180\n44706\n203501\n1998 куб. см., 121 кВт\nHyundai Sonata\n2011\n1998 куб. см., 121 кВт\n2011\nHyundai Sonata\nпричіп легковий В\n2014\nУВН-810083\n10.425\nм. Дружківка\nДонецька область\nЛебеженко Володимир Олександрович\nВолодимир Олександрович Лебеженко\nВолодимир Лебеженко\nЛебеженко Володимир Олександрович\nВолодимир\nПодружжя\nЛебеженко І. А\nДитина\nЛебеженко Б. В\nЛебеженко Володимир Олександрович\nЛебеженко\nЗагальний місцевий суд\nсуддя дружківського міського суду донецької області\nДонецька область\nОлександрович\n84200\nДружківка\nДонецька область\n191321\n33612\n203501\n44706\n9543\n12180\n1551\n2014\nЛебеженко І. А\nПодружжя\nЛебеженко Б. В\nДитина\nОлександрович\nЛебеженко\nВолодимир\nЛебеженко Володимир Олександрович\nВолодимир Олександрович Лебеженко\nВолодимир Лебеженко\nЛебеженко Володимир Олександрович\nДонецька область\nДружківка\n84200\nДонецька область\nЗагальний місцевий суд\nсуддя дружківського міського суду донецької області\nЛебеженко Володимир Олександрович","estate":{"31":[{"costs_property_comment":"","address":"м. Дружківка","space_units":"м²","space_unclear":false,"region_hidden":false,"costs_property":"","space_comment":"","address_hidden":true,"costs_rent_comment":"","space":"10.425","region":"Донецька область","costs_rent":""}]},"vehicle":{"35":[{"sum_comment_unclear":false,"sum_comment":"","brand_info":"1998 куб. см., 121 кВт","sum":"","brand_unclear":false,"year":"2011","brand":"Hyundai Sonata","sum_rent":"","sum_rent_comment":"","brand_hidden":false}],"39":[{"sum_comment":"","brand_info":"причіп легковий В","sum":"","sum_rent_comment":"","year":"2014","brand":"УВН-810083","sum_rent":""}],"40":[{"sum_comment":"","brand_info_hidden":false,"brand_info":"1998 куб. см., 121 кВт","sum":"","sum_rent_comment":"","brand_hidden":false,"brand":"Hyundai Sonata","sum_rent":"","year":"2011"}]},"source":"VULYK","income":{"5":{"family_comment":"","family":"44706","comment":"","value_unclear":false,"family_unclear":false,"value":"203501"},"6":{"family_comment":"","family":"33612","comment":"","value_unclear":false,"family_unclear":false,"value":"191321"},"7":{"family":"","family_comment":"","value":"","comment":"","source_name":""},"8":{"family_comment":"","value":"","family":"","comment":""},"9":{"family_comment":"","value":"","family":"9543","comment":"","family_comment_unclear":false},"10":{"family_comment":"","value":"12180","family":"1551","comment":""},"11":{"family_comment":"","value":"","family":"","comment":""},"12":{"family_comment":"","value":"","family":"","comment":""},"13":{"family_comment":"","value":"","family":"","comment":""},"14":{"family_comment":"","value":"","family":"","comment":""},"15":{"family_comment":"","value":"","family":"","comment":""},"16":{"family_comment":"","value":"","family_unclear":false,"family":"","comment":""},"17":{"family_comment":"","value":"","family_unclear":false,"family":"","comment":""},"18":{"family_comment":"","value":"","family":"","comment":""},"19":{"family_comment":"","value":"","family":"","comment":""},"20":{"family_comment":"","value":"","family":"","comment":""}},"general":{"family":[{"inn":"","family_name":"Лебеженко І. А","name_unclear":false,"inn_hidden":true,"name_hidden":false,"relations":"Подружжя"},{"inn":"","family_name":"Лебеженко Б. В","relations_other":"","name_unclear":false,"inn_hidden":false,"name_hidden":false,"relations":"Дитина"}],"family_raw":"","name":"Володимир","full_name_suggest":{"input":["Лебеженко Володимир Олександрович","Володимир Олександрович Лебеженко","Володимир Лебеженко"],"output":"Лебеженко Володимир Олександрович"},"patronymic":"Олександрович","inn_hidden":true,"patronymic_unclear":false,"patronymic_hidden":false,"inn":"","addresses":[{"place_city_type_hidden":true,"place_city_type":"Місто","place_city_hidden":false,"place_hidden":false,"place_district":"","place_district_hidden":false,"place":"Донецька область","place_address":"84200","place_address_hidden":false,"place_city":"Дружківка"}],"last_name":"Лебеженко","full_name":"Лебеженко Володимир Олександрович","post":{"office":"Загальний місцевий суд","post":"суддя дружківського міського суду донецької області","candidate":"","region_hidden":false,"region":"Донецька область","office_hidden":false},"last_name_unclear":false},"liabilities":{"54":{"sum_comment":"","sum_comment_unclear":false,"sum_foreign_comment":"","sum":"","sum_foreign":""},"55":{"sum_comment":"","sum_foreign_comment":"","sum_foreign":"","sum":""},"56":{"sum_comment":"","sum_foreign_comment":"","sum_foreign":"","sum":""},"57":{"sum_comment":"","sum_hidden":false,"sum":"","sum_foreign_comment":"","sum_foreign":"","sum_unclear":false,"sum_comment_hidden":false},"58":{"sum_comment":"","sum_hidden":false,"sum":"","sum_foreign_comment":"","sum_foreign":"","sum_comment_hidden":false},"59":{"sum_comment":"","sum_foreign_comment":"","sum_foreign":"","sum":""},"60":{"sum_comment_unclear":false,"sum_comment":"","sum_hidden":false,"sum":"","sum_foreign_comment":"","sum_foreign":"","sum_comment_hidden":false},"61":{"sum_comment":"","sum_foreign_comment":"","sum_foreign":"","sum":""},"62":{"sum_comment":"","sum_foreign_comment":"","sum_foreign":"","sum":""},"63":{"sum_comment":"","sum_foreign_comment":"","sum_foreign":"","sum":""},"64":{"sum_comment":"","sum_foreign_comment":"","sum_foreign":"","sum":""}},"declaration":{"notfull_lostpages":"","additional_info_text":"","additional_info":"","date":"2015-03-27T00:00:00","notfull":"","url":"http://static.declarations.com.ua/declarations/chosen_ones/judges_batch/2964_lebezhenko_volodymyr_oleks-vych.pdf"},"intro":{"isnotdeclaration":"","declaration_year":"2014"}}