{"id":"vulyk_92_163","ft_src":"Договір кредиту №607/32-224 АКБ 'Укрсоцбанк' від 12. 12. 07р. 150000 строк 7 років\n2365 куб. см.\nToyota Camry\n2007\n150000\nРішення сесії Червоноградської міськради №601 21. 10. 10 р\n.08\nДоговор купівлі-продажу із регіональним ФДМ, 23. 05. 14\n87949,20\nЛьвівська область\nнежитлове приміщення Договір купівлі-продажу з регіональним відділенням Фонду держ. майна від 23. 05. 14\n39.5\n2014\n220108.08\n12180\n8976\n232288.08\n2365 куб. см.\nToyota Camry\nДоговір кредиту №607/32-224 АКБ 'Укрсоцбанк' від 12. 12. 07р. 150000 строк 7 років\n2007\n150000\n.08\nРішення сесії Червоноградської міськради №601 21. 10. 10 р\nДоговор купівлі-продажу із регіональним ФДМ, 23. 05. 14\n87949,20\nнежитлове приміщення Договір купівлі-продажу з регіональним відділенням Фонду держ. майна від 23. 05. 14\nЛьвівська область\n39.5\nПодружжя\nСемак Тетяна Миколаївна 04. 10. 1974 р. н\nДитина\nРак Богдан Леонідович 15. 03. 1996\nДитина\nРак Максим Леонідович 28. 09. 2001\nРак Леонід Степанович\nЛеонід Степанович Рак\nЛеонід Рак\nРак Леонід Степанович\nРак Леонід Степанович\nЛеонід\nРак\nЗагальний місцевий суд\nсуддя червоноградського міського суду львівської області\nЛьвівська область\nСтепанович\n21428.52\nАКБ 'Укрсоцбанк' в т. ч. проценти\n3120\n220108.08\n232288.08\n8976\n12180\n2014\nАКБ 'Укрсоцбанк' в т. ч. проценти\n21428.52\n3120\nПодружжя\nСемак Тетяна Миколаївна 04. 10. 1974 р. н\nДитина\nРак Богдан Леонідович 15. 03. 1996\nДитина\nРак Максим Леонідович 28. 09. 2001\nСтепанович\nРак\nЛеонід\nРак Леонід Степанович\nЛеонід Степанович Рак\nЛеонід Рак\nРак Леонід Степанович\nЛьвівська область\nЗагальний місцевий суд\nсуддя червоноградського міського суду львівської області\nРак Леонід Степанович","estate":{"23":[{"address":"","space_units":"га","costs_comment":"Рішення сесії Червоноградської міськради №601 21. 10. 10 р","space_unclear":false,"region_hidden":false,"space_comment":"","address_hidden":false,"costs":"","costs_rent_comment":"","space":".08","region_unclear":false,"region":"","costs_rent":""}],"34":[{"costs_property_comment":"Договор купівлі-продажу із регіональним ФДМ, 23. 05. 14","address":"нежитлове приміщення Договір купівлі-продажу з регіональним відділенням Фонду держ. майна від 23. 05. 14","space_units":"м²","space_hidden":false,"space_comment":"","region_hidden":false,"costs_property":"87949,20","region":"Львівська область","address_hidden":false,"costs_rent_comment":"","space":"39.5","costs_rent":""}]},"vehicle":{"35":[{"sum_comment_unclear":false,"brand_info":"2365 куб. см.","sum_rent_comment":"","brand_unclear":false,"brand_hidden":false,"year":"2007","sum_comment":"Договір кредиту №607/32-224 АКБ 'Укрсоцбанк' від 12. 12. 07р. 150000 строк 7 років","brand_info_hidden":false,"sum_rent":"","brand":"Toyota Camry","year_unclear":false,"brand_info_unclear":false,"sum":"150000"}]},"source":"VULYK","income":{"5":{"family_comment":"","family_hidden":false,"value":"232288.08","family":"8976","comment":""},"6":{"family_comment":"","family":"","comment":"","value_unclear":false,"family_hidden":false,"value":"220108.08"},"7":{"family_comment":"","comment":"","family":"","value_unclear":false,"value":"","source_name":""},"8":{"family_comment":"","value":"","family":"","comment":""},"9":{"family_comment":"","value":"","family":"","comment":""},"10":{"family_comment":"","comment":"","family":"","family_unclear":false,"comment_unclear":false,"value":"12180","family_comment_unclear":false},"11":{"family_comment":"","value":"","family":"","comment":"","value_unclear":false},"12":{"family_comment":"","value":"","family":"","comment":""},"13":{"family_comment":"","value":"","family":"","comment":""},"14":{"family_comment":"","value":"","family":"","comment":""},"15":{"family_comment":"","comment":"","family":"","family_unclear":false,"comment_unclear":false,"value":""},"16":{"family_comment":"","value":"","family":"","comment":""},"17":{"family_comment":"","value":"","family":"","comment":""},"18":{"family_comment":"","value":"","family_unclear":false,"family":"","comment":""},"19":{"family_comment":"","value":"","family":"","comment":""},"20":{"family_comment":"","value":"","family_unclear":false,"family":"","comment":""}},"general":{"family_raw":"","name":"Леонід","full_name_suggest":{"input":["Рак Леонід Степанович","Леонід Степанович Рак","Леонід Рак"],"output":"Рак Леонід Степанович"},"patronymic":"Степанович","inn_hidden":true,"patronymic_unclear":false,"inn":"","inn_unclear":false,"last_name":"Рак","full_name":"Рак Леонід Степанович","family":[{"inn":"","inn_unclear":false,"family_name":"Семак Тетяна Миколаївна 04. 10. 1974 р. н","relations_hidden":false,"name_unclear":false,"relations":"Подружжя","inn_hidden":false,"name_hidden":false,"relations_other":""},{"inn":"","inn_unclear":false,"family_name":"Рак Богдан Леонідович 15. 03. 1996","relations_hidden":false,"name_unclear":false,"relations":"Дитина","inn_hidden":false,"name_hidden":false,"relations_other":""},{"inn":"","family_name":"Рак Максим Леонідович 28. 09. 2001","relations_other":"","name_unclear":false,"inn_hidden":false,"relations":"Дитина"}],"post":{"office":"Загальний місцевий суд","post":"суддя червоноградського міського суду львівської області","office_unclear":false,"region_hidden":false,"region":"Львівська область","office_hidden":false,"post_unclear":false},"addresses":[{"place_city_type":"","place_address_unclear":false,"place_city_type_hidden":false,"place_hidden":true,"place_city_hidden":true,"place_district":"","place_district_hidden":false,"place":"","place_city":"","place_address_hidden":true,"place_address":""}]},"liabilities":{"54":{"sum_comment":"","sum_hidden":false,"sum":"","sum_foreign_comment":"","sum_foreign":"","sum_unclear":false},"55":{"sum_comment":"","sum_foreign_comment":"","sum_foreign":"","sum_unclear":false,"sum":""},"56":{"sum_comment_unclear":false,"sum_comment":"","sum_hidden":false,"sum":"","sum_foreign_comment":"","sum_foreign":"","sum_unclear":false},"57":{"sum_comment":"АКБ 'Укрсоцбанк' в т. ч. проценти","sum_hidden":false,"sum":"21428.52","sum_foreign_comment":"","sum_foreign":"","sum_comment_hidden":false},"58":{"sum_comment":"","sum_foreign_comment":"","sum_foreign":"","sum":""},"59":{"sum_comment":"","sum_comment_unclear":false,"sum_foreign_comment":"","sum":"","sum_foreign":""},"60":{"sum_comment":"","sum_foreign_comment":"","sum_foreign":"","sum":""},"61":{"sum_comment":"","sum_foreign_comment":"","sum_foreign":"","sum":""},"62":{"sum_comment_unclear":false,"sum_comment":"","sum_hidden":false,"sum":"3120","sum_foreign_comment":"","sum_foreign":"","sum_unclear":false},"63":{"sum_comment":"","sum_foreign_comment":"","sum_foreign":"","sum":""},"64":{"sum_comment":"","sum_foreign_comment":"","sum_foreign":"","sum":""}},"declaration":{"notfull_lostpages":"","additional_info_text":"","additional_info":"","date":"2015-03-31T00:00:00","notfull":"","url":"http://static.declarations.com.ua/declarations/chosen_ones/judges_batch/3409_rak_leonid_stepanovych.pdf"},"intro":{"isnotdeclaration":"","declaration_year":"2014"}}