{"income":{"5":{"value":"212773","family_comment":"","value_unclear":false,"comment_hidden":false,"family_hidden":false,"value_hidden":false,"family_unclear":false,"family_comment_hidden":false,"comment":"","family":"76794"},"6":{"value":"195941","family_comment":"","value_unclear":false,"family_hidden":false,"family_unclear":false,"family":"76794","comment":""},"7":{"source_name_unclear":false,"value":"","family_hidden":false,"family_comment":"","source_name":"","family":"","comment":"","source_name_hidden":false},"8":{"family_comment":"","value":"","family":"","comment":""},"9":{"value":"","value_unclear":false,"family_hidden":false,"family_comment":"","family":"","comment":""},"10":{"value":"","value_unclear":false,"family_hidden":false,"value_hidden":false,"family_comment":"","comment_unclear":false,"comment":"","family":""},"11":{"family_comment":"","value":"","family":"","comment":""},"12":{"family_comment":"","value":"","family":"","comment":""},"13":{"family_comment":"","value":"","family":"","comment":""},"14":{"family_comment":"","value":"","family":"","comment":""},"15":{"family_comment":"","value":"","family_hidden":false,"comment":"","family":""},"16":{"value":"","value_unclear":false,"family_hidden":false,"family_comment":"","family":"","comment":""},"17":{"family_comment":"","value":"","family_hidden":false,"comment":"","family":""},"18":{"family_comment":"","value":"","value_unclear":false,"family":"","comment":""},"19":{"family_comment":"","value":"","family":"","comment":""},"20":{"value":"16832","family_comment":"","value_unclear":false,"family_hidden":false,"family_unclear":false,"comment_unclear":false,"comment":"","family":""}},"vehicle":{"35":[{"brand_info":"1595 куб. см., 75.02 кВт , 455 см","sum_rent_comment":"","brand_info_unclear":false,"year":"2008","sum_rent_unclear":false,"brand_info_hidden":false,"sum_rent_comment_unclear":false,"sum_hidden":false,"sum_rent":"","sum":"","brand":"Volkswagen Jetta","sum_comment":"","brand_unclear":false,"brand_hidden":false}]},"id":"vulyk_72_115","declaration":{"additional_info_text":"","notfull_lostpages":"","date":"2015-03-23T00:00:00","notfull":"","additional_info":"","url":"http://static.declarations.com.ua/declarations/chosen_ones/epic_batch/lytvynenko_iryna_viktorivna.pdf"},"liabilities":{"54":{"sum_foreign_comment":"","sum":"","sum_comment":"","sum_comment_hidden":false,"sum_unclear":false,"sum_foreign":""},"55":{"sum_foreign_comment":"","sum":"","sum_comment":"","sum_foreign":""},"56":{"sum_foreign_comment":"","sum":"","sum_hidden":false,"sum_comment":"","sum_foreign":""},"57":{"sum_foreign_comment":"","sum":"8439","sum_comment":"","sum_comment_unclear":false,"sum_hidden":false,"sum_comment_hidden":false,"sum_unclear":false,"sum_foreign":""},"58":{"sum_foreign_comment":"","sum":"1","sum_comment":"","sum_comment_unclear":false,"sum_hidden":false,"sum_comment_hidden":false,"sum_unclear":false,"sum_foreign":""},"59":{"sum_foreign_comment":"","sum_foreign_hidden":false,"sum_comment":"","sum_foreign_unclear":false,"sum_comment_hidden":false,"sum":"","sum_foreign":""},"60":{"sum_foreign_comment":"","sum_foreign_hidden":false,"sum_comment":"","sum_hidden":false,"sum":"","sum_foreign":""},"61":{"sum_foreign_comment":"","sum_foreign_hidden":false,"sum_comment":"","sum_hidden":false,"sum":"","sum_foreign":""},"62":{"sum_foreign_comment":"","sum_foreign_hidden":false,"sum_comment":"","sum_hidden":false,"sum":"6113","sum_foreign":""},"63":{"sum_foreign_comment":"","sum_foreign_hidden":false,"sum_comment":"","sum_comment_unclear":false,"sum_hidden":false,"sum_comment_hidden":false,"sum_unclear":false,"sum":"3140","sum_foreign":""},"64":{"sum_foreign_comment":"","sum_foreign_hidden":false,"sum_comment":"","sum_hidden":false,"sum":"","sum_foreign":""}},"ft_src":"8439\n6113\n1\n3140\nЧернігів\nЧернігівська область\nсуддя деснянського районного суду міста чернігова\nЧернігівська область\nЗагальний місцевий суд\nІрина\nЛитвиненко В. В\nПодружжя\nЛитвиненко Є. В\nДитина\nВікторівна\nЛитвиненко\nЛитвиненко Ірина Вікторівна\nЛитвиненко Ірина Вікторівна\nІрина Вікторівна Литвиненко\nІрина Литвиненко\nЛитвиненко Ірина Вікторівна\n1595 куб. см., 75.02 кВт , 455 см\nVolkswagen Jetta\n2008\n47.8\n2014\n76794\n195941\n76794\n212773\n16832\n1595 куб. см., 75.02 кВт , 455 см\nVolkswagen Jetta\n2008\n47.8\nПодружжя\nЛитвиненко В. В\nДитина\nЛитвиненко Є. В\nЛитвиненко Ірина Вікторівна\nІрина Вікторівна Литвиненко\nІрина Литвиненко\nЛитвиненко Ірина Вікторівна\nІрина\nЛитвиненко Ірина Вікторівна\nЛитвиненко\nЧернігівська область\nЗагальний місцевий суд\nсуддя деснянського районного суду міста чернігова\nВікторівна\nЧернігів\nЧернігівська область\n1\n8439\n6113\n3140\n195941\n76794\n16832\n212773\n76794\n2014\n1\n8439\n6113\n3140\nЛитвиненко В. В\nПодружжя\nЛитвиненко Є. В\nДитина\nВікторівна\nЛитвиненко\nЛитвиненко Ірина Вікторівна\nІрина Вікторівна Литвиненко\nІрина Литвиненко\nЛитвиненко Ірина Вікторівна\nЧернігівська область\nЧернігів\nЧернігівська область\nЗагальний місцевий суд\nсуддя деснянського районного суду міста чернігова\nЛитвиненко Ірина Вікторівна\nІрина\n2008\nVolkswagen Jetta\n1595 куб. см., 75.02 кВт , 455 см\n16832\n212773\n76794\n195941\n76794\n47.8\n2014","general":{"inn":"","name":"Ірина","patronymic_unclear":false,"family":[{"inn":"","inn_hidden":false,"relations_unclear":false,"relations_hidden":false,"relations_other":"","relations":"Подружжя","name_hidden":false,"inn_unclear":false,"family_name":"Литвиненко В. В","name_unclear":false},{"inn":"","inn_hidden":false,"relations_hidden":false,"family_name":"Литвиненко Є. В","relations_other":"","relations":"Дитина","name_hidden":false,"name_unclear":false}],"patronymic":"Вікторівна","inn_hidden":false,"family_raw":"","inn_unclear":false,"post":{"post_unclear":false,"region_unclear":false,"post":"суддя деснянського районного суду міста чернігова","candidate":"","office_hidden":false,"region":"Чернігівська область","post_hidden":false,"office":"Загальний місцевий суд","office_unclear":false,"region_hidden":false},"last_name_unclear":false,"full_name":"Литвиненко Ірина Вікторівна","addresses":[{"place_city_type_hidden":false,"place_district_hidden":false,"place_city_type":"Місто","place_city_hidden":false,"place_address_unclear":false,"place_address":"","place":"Чернігівська область","place_district":"","place_unclear":false,"place_city":"Чернігів","place_city_unclear":false,"place_hidden":false,"place_address_hidden":false,"place_district_unclear":false}],"last_name":"Литвиненко","patronymic_hidden":false,"full_name_suggest":{"output":"Литвиненко Ірина Вікторівна","input":["Литвиненко Ірина Вікторівна","Ірина Вікторівна Литвиненко","Ірина Литвиненко"]},"name_unclear":false},"source":"VULYK","estate":{"31":[{"space_unclear":false,"address_hidden":false,"region_hidden":true,"space_comment":"","space_units_hidden":false,"space_hidden":false,"space":"47.8","address":"","region":"","address_unclear":false,"costs_rent_comment":"","costs_property":"","space_units":"м²","costs_property_comment":"","costs_rent":""}]},"intro":{"declaration_year":"2014","isnotdeclaration":"","declaration_year_unclear":false}}