{"income":{"5":{"value":"265638","family_comment":"","family_hidden":false,"value_hidden":false,"family_unclear":false,"family":"387839","comment":""},"6":{"value":"265638","comment_unclear":false,"family_comment":"","family":"229834","comment":"","family_comment_unclear":false},"7":{"family_comment":"","value":"","source_name":"","family":"18005","comment":""},"8":{"family_comment":"","value":"","family":"","comment":""},"9":{"family_comment":"","value":"","family":"","comment":""},"10":{"family_comment":"","value":"","family":"","comment":""},"11":{"family_comment":"","value":"","family":"","comment":"","family_comment_unclear":false},"12":{"family_comment":"","value":"","family":"","comment":""},"13":{"family_comment":"","value":"","family":"","comment":""},"14":{"family_comment":"","value":"","family":"","comment":""},"15":{"family_comment":"","value":"","family":"","comment":""},"16":{"family_comment":"","value":"","family":"140000","comment":""},"17":{"family_comment":"","value":"","family":"","comment":""},"18":{"family_comment":"","value":"","family":"","comment":""},"19":{"family_comment":"","value":"","family":"","comment":"","value_hidden":false},"20":{"family_comment":"","value":"","comment_unclear":false,"family":"","comment":""}},"vehicle":{"40":[{"brand_info":"3498 куб. см., 183 кВт , 486,0 см","sum_rent_comment":"","brand":"Nissan Murano","sum_comment":"","year":"2012","brand_info_unclear":false,"sum":"","sum_rent":""}]},"id":"vulyk_51_8","banks":{"45":[{"sum_foreign_comment":"","sum_units":"UAH","sum_comment":"","sum_comment_unclear":false,"sum_hidden":false,"sum_foreign_units":"UAH","sum_comment_hidden":false,"sum":"8610","sum_foreign":""},{"sum_foreign_comment":"","sum_units":"","sum_comment":"","sum_foreign_units":"","sum":"","sum_foreign":""},{"sum_foreign_comment":"","sum_units":"","sum_comment":"","sum_foreign_units":"","sum":"","sum_foreign":""},{"sum_foreign_comment":"","sum_units":"","sum_comment":"","sum_foreign_units":"","sum":"","sum_foreign":""},{"sum_foreign_comment":"","sum_units":"","sum_comment":"","sum_foreign_units":"","sum":"","sum_unclear":false,"sum_foreign":""}],"46":[{"sum_foreign_comment":"","sum_units":"UAH","sum_comment":"","sum_foreign_units":"UAH","sum":"","sum_foreign":""}],"47":[{"sum_foreign_comment":"","sum_units":"UAH","sum_comment":"","sum_foreign_units":"UAH","sum":"","sum_foreign":""}],"48":[{"sum_foreign_comment":"","sum_units":"UAH","sum_comment":"","sum_foreign_units":"UAH","sum":"","sum_foreign":""}],"49":[{"sum_foreign_comment":"","sum_units":"UAH","sum_comment":"","sum_foreign_units":"UAH","sum":"","sum_foreign":""}],"50":[{"sum_foreign_comment":"","sum_units":"UAH","sum_comment":"","sum_foreign_units":"UAH","sum":"","sum_foreign":""}],"51":[{"sum_foreign_comment":"","sum_units":"UAH","sum_comment":"","sum_foreign_units":"UAH","sum_comment_hidden":false,"sum":"","sum_foreign":""},{"sum_foreign_comment":"","sum_units":"","sum_comment":"","sum_foreign_units":"","sum":"","sum_foreign":""},{"sum_foreign_comment":"","sum_units":"","sum_comment":"","sum_foreign_units":"","sum":"","sum_foreign":""}],"52":[{"sum_foreign_comment":"","sum_units":"UAH","sum_comment":"","sum_foreign_units":"UAH","sum_comment_hidden":false,"sum":"","sum_foreign":""}],"53":[{"sum_foreign_comment":"","sum_units":"UAH","sum_comment":"","sum_foreign_units":"UAH","sum":"","sum_foreign":""}]},"declaration":{"additional_info_text":"","notfull_lostpages":"","date":"2015-03-26T00:00:00","notfull":"","additional_info":"","url":"http://static.declarations.com.ua/declarations/chosen_ones/mega_batch/zaryshniak_halyna_mykolaivna.pdf"},"liabilities":{"54":{"sum_foreign_comment":"","sum_comment_hidden":false,"sum":"","sum_comment":"","sum_foreign":""},"55":{"sum_foreign_comment":"","sum":"","sum_comment":"","sum_foreign":""},"56":{"sum_foreign_comment":"","sum":"","sum_comment":"","sum_foreign":""},"57":{"sum_foreign_comment":"","sum":"","sum_comment":"","sum_hidden":false,"sum_comment_hidden":false,"sum_foreign":""},"58":{"sum_foreign_comment":"","sum_comment_hidden":false,"sum":"","sum_comment":"","sum_foreign":""},"59":{"sum_foreign_comment":"","sum":"","sum_comment":"","sum_foreign":""},"60":{"sum_foreign_comment":"","sum":"","sum_comment":"","sum_foreign":""},"61":{"sum_foreign_comment":"","sum":"","sum_comment":"","sum_foreign":""},"62":{"sum_foreign_comment":"","sum":"","sum_comment":"","sum_foreign":""},"63":{"sum_foreign_comment":"","sum_comment_hidden":false,"sum":"","sum_comment":"","sum_foreign":""},"64":{"sum_foreign_comment":"","sum":"","sum_comment":"","sum_foreign":""}},"ft_src":"Заришняк Галина Миколаївна\nсуддя апеляційного суду м. києва\nм. Київ\nЗагальний апеляційний суд\nГалина\nЗаришняк Анатолій Семенович\nПодружжя\nЗаришняк Галина Миколаївна\nГалина Миколаївна Заришняк\nГалина Заришняк\nЗаришняк Галина Миколаївна\nЗаришняк\nМиколаївна\n3498 куб. см., 183 кВт , 486,0 см\n2012\nNissan Murano\n8610\n2014\n3498 куб. см., 183 кВт , 486,0 см\nNissan Murano\n2012\n8610\n423100\nрозпочато будівництво\n104.5\nдоговір найму\nдоговір найму\n21\n.1175\nбезоплатна приватизація\n.1\n.28\nприблизно 0,28 га\nдоговір дарування\n81.2\n140\nна стадії оформлення\nмашиномісце в підземній автостоянці\n20\nЗаришняк\nЗаришняк Галина Миколаївна\nГалина Миколаївна Заришняк\nГалина Заришняк\nЗаришняк Галина Миколаївна\nГалина\nМиколаївна\nЗаришняк Галина Миколаївна\nЗагальний апеляційний суд\nсуддя апеляційного суду м. києва\nм. Київ\nПодружжя\nЗаришняк Анатолій Семенович\n18005\n265638\n229834\n387839\n265638\n140000\n2014\n423100\nрозпочато будівництво\n.1\nприблизно 0,28 га\n.28\n21\nдоговір дарування\n81.2\nна стадії оформлення\n140\nмашиномісце в підземній автостоянці\n20\nбезоплатна приватизація\n.1175\nдоговір найму\nдоговір найму\n104.5\nЗаришняк Анатолій Семенович\nПодружжя\nМиколаївна\nЗаришняк\nм. Київ\nЗагальний апеляційний суд\nсуддя апеляційного суду м. києва\nЗаришняк Галина Миколаївна\nЗаришняк Галина Миколаївна\nГалина Миколаївна Заришняк\nГалина Заришняк\nЗаришняк Галина Миколаївна\nГалина\n229834\n265638\n18005\n387839\n265638\n140000\n2012\n3498 куб. см., 183 кВт , 486,0 см\nNissan Murano\n265638\n387839\n140000\n18005\n265638\n229834\nдоговір дарування\n81.2\nбезоплатна приватизація\n.1175\nмашиномісце в підземній автостоянці\n20\n423100\nрозпочато будівництво\nна стадії оформлення\n140\n21\nдоговір найму\nдоговір найму\n104.5\n.1\nприблизно 0,28 га\n.28\n8610\n2014","general":{"inn":"","inn_hidden":true,"last_name":"Заришняк","post":{"post":"суддя апеляційного суду м. києва","region":"м. Київ","office_hidden":false,"office":"Загальний апеляційний суд","office_unclear":false,"region_hidden":false},"name":"Галина","full_name":"Заришняк Галина Миколаївна","family_raw":"","addresses":[{"place_district":"","place_city_hidden":true,"place_city":"","place_city_type_hidden":true,"place_district_hidden":true,"place_city_type":"","place_address_hidden":true,"place_address":"","place_hidden":true,"place":""}],"family":[{"inn":"","relations":"Подружжя","relations_other":"","inn_hidden":true,"family_name":"Заришняк Анатолій Семенович","name_hidden":false,"name_unclear":false}],"full_name_suggest":{"output":"Заришняк Галина Миколаївна","input":["Заришняк Галина Миколаївна","Галина Миколаївна Заришняк","Галина Заришняк"]},"patronymic":"Миколаївна"},"source":"VULYK","estate":{"23":[{"costs":"","costs_comment":"","costs_hidden":false,"address_hidden":true,"region_hidden":true,"space_comment":"безоплатна приватизація","space":".1175","address":"","region":"","address_unclear":false,"costs_rent_comment":"","costs_rent_hidden":false,"space_units":"га","costs_rent":""},{"costs":"","costs_comment":"","costs_hidden":false,"region_hidden":false,"space_comment":"","space":"","address":"","region":"","costs_rent_comment":"","costs_rent_hidden":false,"space_units":"","costs_rent":""},{"space":"","region":"","costs":"","costs_rent_comment":"","costs_comment":"","address_unclear":false,"space_comment":"","space_units":"","costs_rent":"","address":""},{"costs_rent":"","region":"","costs":"","costs_rent_comment":"","costs_comment":"","space_comment":"","space_units":"","space":"","address":""}],"25":[{"space_unclear":false,"costs":"","costs_comment":"","costs_hidden":false,"address_hidden":true,"region_hidden":true,"space_comment":"договір найму","space_hidden":false,"space":"104.5","address":"","region":"","address_unclear":false,"costs_rent_comment":"договір найму","space_units":"м²","costs_rent":""}],"26":[{"space_unclear":false,"costs":"","costs_comment":"","address_hidden":true,"region_hidden":true,"space_comment":"","space":"","address":"","region":"","costs_rent_comment":"розпочато будівництво","space_units":"м²","costs_rent":"423100"}],"29":[{"address_hidden":true,"region_hidden":true,"space_comment":"","space":".1","address":"","region":"","costs_property":"","costs_rent_comment":"","address_unclear":false,"space_units":"га","costs_property_comment":"","costs_rent":""},{"costs_rent":"","region":"","costs_property":"","costs_rent_comment":"","address_hidden":false,"region_hidden":false,"space_comment":"приблизно 0,28 га","costs_property_comment":"","space_units":"га","space":".28","address":""}],"30":[{"address_hidden":true,"region_hidden":true,"space_comment":"на стадії оформлення","space":"140","address":"","region":"","costs_property":"","costs_rent_comment":"","space_comment_unclear":false,"space_units":"м²","costs_property_comment":"","costs_rent":""}],"31":[{"space_hidden":false,"costs_property_hidden":false,"address_hidden":true,"region_hidden":true,"space_comment":"договір дарування","space_unclear":false,"space":"81.2","address":"","region":"","address_unclear":false,"costs_rent_comment":"","costs_rent_hidden":false,"costs_property":"","space_units":"м²","costs_property_comment":"","costs_rent":""}],"33":[{"space_hidden":false,"costs_property_comment":"","address_hidden":true,"region_hidden":true,"space_comment":"","space":"21","address":"","region":"","costs_property":"","costs_rent_comment":"","space_units":"м²","space_units_hidden":false,"costs_rent":""}],"34":[{"space_hidden":false,"costs_property_hidden":false,"address_hidden":true,"region_hidden":true,"space_comment":"машиномісце в підземній автостоянці","space":"20","address":"","region":"","costs_property":"","costs_rent_comment":"","costs_rent_hidden":false,"space_units":"м²","costs_property_comment":"","costs_rent":""}]},"intro":{"declaration_year":"2014","isnotdeclaration":""}}