{"id":"vulyk_105_62","declaration":{"additional_info_text":"","additional_info":"","date":"2015-03-12T00:00:00","url":"http://static.declarations.com.ua/declarations/chosen_ones/judges_batch/4637_shapran_viktor_valentynovych.pdf"},"estate":{"25":[{"address":"","space_units":"м²","space_hidden":false,"space_comment":"1/2 від 91,5 кв. м","region_hidden":true,"costs_comment":"","address_hidden":false,"space":"91.5","costs_rent_comment":"","costs":"","region":"","costs_rent":""}],"31":[{"costs_property_comment":"","address":"","space_units":"м²","space_hidden":false,"space_comment":"1/2 від 91,5 кв. м","region_hidden":true,"costs_property":"","region":"","address_hidden":true,"costs_rent_comment":"","space":"91.5","costs_rent":""}]},"vehicle":{"35":[{"sum_comment":"","brand_info_hidden":false,"brand_info":"2972 куб. см.","sum":"","sum_rent_comment":"","year":"2007","brand":"Mitsubishi Pajero","sum_rent":""}]},"source":"VULYK","income":{"5":{"family_comment":"","family_hidden":false,"value":"267656","family":"","comment":""},"6":{"family_comment":"","family_hidden":false,"value":"242039","family":"","comment":""},"7":{"family":"","family_comment":"","value":"","comment":"","source_name":""},"8":{"family_comment":"","value":"","family":"","comment":""},"9":{"family_comment":"","value":"12219","family":"","comment":""},"10":{"family_comment":"","value":"13398","family":"","comment":""},"11":{"family_comment":"","value":"","family":"","comment":""},"12":{"family_comment":"","value":"","family":"","comment":""},"13":{"family_comment":"","value":"","family":"","comment":""},"14":{"family_comment":"","value":"","family":"","comment":""},"15":{"family_comment":"","value":"","family":"","comment":""},"16":{"family_comment":"","value":"","family":"","comment":""},"17":{"family_comment":"","value":"","family":"","comment":""},"18":{"family_comment":"","value":"","family":"","comment":""},"19":{"family_comment":"","value":"","family":"","comment":""},"20":{"family_comment":"","value":"","family":"","comment":""}},"banks":{"45":[{"sum_units":"UAH","sum_comment":"","sum_foreign_units":"UAH","sum":"100000","sum_foreign_comment":"","sum_foreign":"","sum_comment_hidden":true}],"46":[{"sum_units":"UAH","sum_comment":"","sum_foreign_units":"UAH","sum":"100000","sum_foreign_comment":"","sum_foreign":""}]},"ft_src":"2972 куб. см.\n2007\nMitsubishi Pajero\n100000\n100000\n2014\nMitsubishi Pajero\n2972 куб. см.\n2007\n100000\n100000\n2014\nсуддя київського апеляційного господарського суду\nАпеляційний господарський суд\nм. Київ\nШапран\nШапран Віктор Валентинович\nВіктор Валентинович Шапран\nВіктор Шапран\nШапран Віктор Валентинович\nШапран Віктор Валентинович\nВіктор\nВалентинович\nДитина\nШапран А. В\n1055\n242039\n267656\n13398\n12219\n91.5\n1/2 від 91,5 кв. м\n91.5\n1/2 від 91,5 кв. м\n1055\n1/2 від 91,5 кв. м\n91.5\n1/2 від 91,5 кв. м\n91.5\nШапран А. В\nДитина\nВалентинович\nШапран\nм. Київ\nсуддя київського апеляційного господарського суду\nАпеляційний господарський суд\nШапран Віктор Валентинович\nШапран Віктор Валентинович\nВіктор Валентинович Шапран\nВіктор Шапран\nШапран Віктор Валентинович\nВіктор\n242039\n13398\n267656\n12219","general":{"inn":"","addresses":[{"place_city_type_hidden":false,"place_city_type":"","place_city_hidden":true,"place_hidden":true,"place_district":"","place_district_hidden":false,"place":"","place_address":"","place_address_hidden":true,"place_city":""}],"last_name":"Шапран","full_name":"Шапран Віктор Валентинович","family":[{"inn":"","family_name":"Шапран А. В","relations_other":"","relations_hidden":false,"name_unclear":false,"inn_hidden":false,"name_hidden":true,"relations":"Дитина"}],"patronymic":"Валентинович","inn_hidden":true,"name":"Віктор","post":{"office":"Апеляційний господарський суд","post":"суддя київського апеляційного господарського суду","office_unclear":false,"office_hidden":false,"region":"м. Київ","region_unclear":false,"post_unclear":false},"family_raw":"","full_name_suggest":{"input":["Шапран Віктор Валентинович","Віктор Валентинович Шапран","Віктор Шапран"],"output":"Шапран Віктор Валентинович"}},"liabilities":{"54":{"sum_comment":"","sum_foreign_comment":"","sum_foreign":"","sum":"1055","sum_comment_hidden":false},"55":{"sum_comment":"","sum_foreign_comment":"","sum_foreign":"","sum":""},"56":{"sum_comment":"","sum_foreign_comment":"","sum_foreign":"","sum":""},"57":{"sum_comment_unclear":false,"sum_comment":"","sum":"","sum_foreign_comment":"","sum_foreign":"","sum_comment_hidden":false},"58":{"sum_comment":"","sum_foreign_comment":"","sum_foreign":"","sum":""},"59":{"sum_comment":"","sum_foreign_comment":"","sum_foreign":"","sum":""},"60":{"sum_comment":"","sum_foreign_comment":"","sum_foreign":"","sum":""},"61":{"sum_comment":"","sum_foreign_comment":"","sum_foreign":"","sum":""},"62":{"sum_comment":"","sum_foreign_comment":"","sum_foreign":"","sum_hidden":false,"sum":""},"63":{"sum_comment":"","sum_foreign_comment":"","sum_foreign":"","sum":""},"64":{"sum_comment":"","sum_foreign_comment":"","sum_foreign":"","sum":""}},"intro":{"declaration_year":"2014"}}