{"income":{"5":{"family_comment":"","value":"299077.48","family":"80948.18","comment":""},"6":{"family_comment":"","value":"231358.11","family":"56823.94","comment":""},"7":{"family_comment":"","value":"4321.37","source_name":"Донецький Національний університет, м. Вінниця","family":"","comment":""},"8":{"family_comment":"","value":"","family":"","comment":""},"9":{"value":"","comment_unclear":false,"family_comment":"","family":"","comment":"","family_comment_unclear":false},"10":{"family_comment":"","value":"13398","family":"","comment":""},"11":{"family_comment":"","value":"50000","family":"","comment":""},"12":{"family_comment":"","value":"","family":"","comment":""},"13":{"family_comment":"","value":"","family":"","comment":""},"14":{"family_comment":"","value":"","family":"","comment":""},"15":{"family_comment":"","value":"","family":"20233.08","comment":""},"16":{"family_comment":"","value":"","family":"","comment":""},"17":{"family_comment":"","value":"","family":"","comment":""},"18":{"family_comment":"","value":"","family":"","comment":""},"19":{"value":"","family_comment":"","value_unclear":false,"family_unclear":false,"family":"","comment":""},"20":{"value":"","family_comment":"","value_unclear":false,"comment_hidden":false,"family_comment_hidden":false,"family_unclear":false,"family_comment_unclear":false,"comment_unclear":false,"comment":"","family":"591.16"}},"vehicle":{"35":[{"brand_info":"1599 куб. см., 82.38 кВт","sum_rent_comment":"","brand":"Hyundai Accent","sum_comment":"","year":"2008","sum_hidden":false,"brand_info_hidden":false,"brand_info_unclear":false,"year_unclear":false,"sum":"","sum_rent":""}],"40":[{"year_hidden":false,"brand_info":"1390 куб. см., 55.16 кВт","sum_rent_comment":"","brand":"Seat Ibiza","sum_comment":"","year":"2006","brand_hidden":false,"brand_info_hidden":false,"brand_info_unclear":false,"sum":"","sum_rent":""}]},"id":"vulyk_106_99","declaration":{"additional_info_text":"","notfull_lostpages":"","date":"2016-03-28T00:00:00","notfull":"","additional_info":"","url":"http://static.declarations.com.ua/declarations/chosen_ones/judges_batch/2238_sushko_oleh_oleksandrovych.pdf"},"liabilities":{"54":{"sum_foreign_comment":"","sum":"","sum_comment":"","sum_comment_unclear":false,"sum_hidden":false,"sum_comment_hidden":false,"sum_foreign":""},"55":{"sum_foreign_comment":"","sum":"","sum_hidden":false,"sum_comment":"","sum_foreign":""},"56":{"sum_foreign_comment":"","sum":"4500","sum_comment":"","sum_hidden":false,"sum_comment_hidden":false,"sum_unclear":false,"sum_foreign":""},"57":{"sum_foreign_comment":"","sum":"","sum_comment":"","sum_hidden":false,"sum_comment_hidden":false,"sum_foreign":""},"58":{"sum_foreign_comment":"","sum":"","sum_comment":"","sum_hidden":false,"sum_comment_hidden":false,"sum_foreign":""},"59":{"sum_foreign_comment":"","sum":"","sum_comment":"","sum_foreign":""},"60":{"sum_foreign_comment":"","sum":"","sum_comment":"","sum_hidden":false,"sum_comment_hidden":false,"sum_foreign":""},"61":{"sum_foreign_comment":"","sum":"","sum_comment":"","sum_foreign":""},"62":{"sum_foreign_comment":"","sum":"","sum_comment":"","sum_comment_hidden":false,"sum_unclear":false,"sum_foreign":""},"63":{"sum_foreign_comment":"","sum":"","sum_comment":"","sum_foreign":""},"64":{"sum_foreign_comment":"","sum":"","sum_comment":"","sum_foreign":""}},"ft_src":"4500\nсуддя, вінницький апеляційний адміністративний суд, м. вінниця\nВінницька область\nАпеляційний адміністративний суд\nОлег\nСушко М. Д\nПодружжя\nСушко А. О\nДитина\nСушко В. О\nДитина\nОлександрович\nСушко Олег Олександрович\nОлег Олександрович Сушко\nОлег Сушко\nСушко Олег Олександрович\nСушко Олег Олександрович\nСушко\nHyundai Accent\n1599 куб. см., 82.38 кВт\n2008\n1390 куб. см., 55.16 кВт\nSeat Ibiza\n2006\n500\n83.2\n2015\n56823.94\n231358.11\n20233.08\n50000\n13398\n4321.37\nДонецький Національний університет, м. Вінниця\n80948.18\n299077.48\n591.16\n1599 куб. см., 82.38 кВт\n2008\nHyundai Accent\n1390 куб. см., 55.16 кВт\n2006\nSeat Ibiza\n500\n83.2\nСушко Олег Олександрович\nОлег Олександрович Сушко\nОлег Сушко\nСушко Олег Олександрович\nСушко Олег Олександрович\nПодружжя\nСушко М. Д\nДитина\nСушко А. О\nДитина\nСушко В. О\nОлег\nСушко\nВінницька область\nАпеляційний адміністративний суд\nсуддя, вінницький апеляційний адміністративний суд, м. вінниця\nОлександрович\n4500\n4321.37\nДонецький Національний університет, м. Вінниця\n231358.11\n56823.94\n591.16\n20233.08\n299077.48\n80948.18\n13398\n50000\n2015\n4500\nСушко М. Д\nПодружжя\nСушко А. О\nДитина\nСушко В. О\nДитина\nОлександрович\nСушко\nОлег\nСушко Олег Олександрович\nОлег Олександрович Сушко\nОлег Сушко\nСушко Олег Олександрович\nВінницька область\nАпеляційний адміністративний суд\nсуддя, вінницький апеляційний адміністративний суд, м. вінниця\nСушко Олег Олександрович\n2008\nHyundai Accent\n1599 куб. см., 82.38 кВт\nSeat Ibiza\n1390 куб. см., 55.16 кВт\n2006\n50000\n20233.08\n13398\n591.16\n80948.18\n299077.48\nДонецький Національний університет, м. Вінниця\n4321.37\n56823.94\n231358.11\n500\n83.2\n2015","general":{"inn":"","name":"Олег","inn_unclear":false,"family":[{"inn":"","inn_hidden":true,"relations_unclear":false,"relations_hidden":false,"relations_other":"","relations":"Подружжя","name_hidden":true,"family_name":"Сушко М. Д","name_unclear":true},{"inn":"","relations":"Дитина","relations_unclear":false,"family_name":"Сушко А. О","inn_hidden":false,"relations_other":"","name_hidden":false,"name_unclear":false},{"inn_hidden":true,"inn":"","name_hidden":false,"family_name":"Сушко В. О","relations":"Дитина","name_unclear":false}],"inn_hidden":true,"family_raw":"","last_name":"Сушко","post":{"region_unclear":false,"region":"Вінницька область","post":"суддя, вінницький апеляційний адміністративний суд, м. вінниця","office":"Апеляційний адміністративний суд","office_unclear":false,"post_hidden":false},"full_name":"Сушко Олег Олександрович","addresses":[{"place_district":"","place_city_hidden":true,"place_city":"","place_city_type_hidden":true,"place_district_hidden":true,"place_city_type":"","place_address_hidden":true,"place_address":"","place_hidden":true,"place":""}],"patronymic":"Олександрович","full_name_suggest":{"output":"Сушко Олег Олександрович","input":["Сушко Олег Олександрович","Олег Олександрович Сушко","Олег Сушко"]},"name_unclear":false},"source":"VULYK","estate":{"23":[{"region_unclear":false,"space_hidden":false,"costs":"","costs_comment":"","address_hidden":true,"region_hidden":true,"space_comment":"","space_unclear":false,"space":"500","address":"","costs_comment_unclear":false,"costs_rent_comment_unclear":false,"region":"","address_unclear":false,"costs_rent_comment":"","space_comment_unclear":false,"space_comment_hidden":false,"space_units":"м²","costs_rent":""}],"24":[{"space_unclear":false,"costs":"","costs_comment":"","address_hidden":true,"region_hidden":true,"space_comment":"","space_hidden":false,"space":"83.2","address":"","region":"","costs_rent_comment":"","space_comment_unclear":false,"space_comment_hidden":false,"space_units":"м²","costs_rent":""}]},"intro":{"declaration_year":"2015","isnotdeclaration":""}}