{"income":{"5":{"value":"303731","family_comment":"","value_unclear":false,"family_hidden":false,"family_unclear":false,"family":"120865","comment":""},"6":{"value":"256731","family_comment":"","value_unclear":false,"family_unclear":false,"family":"97865","comment":""},"7":{"value":"","family_comment":"","source_name":"","family":"","comment":"","source_name_hidden":false},"8":{"family_comment":"","value":"","family":"","comment":""},"9":{"family_comment":"","value":"","family":"","comment":""},"10":{"value":"","family_hidden":false,"value_hidden":false,"family_comment":"","family":"","comment":""},"11":{"family_comment":"","value":"","family":"","comment":""},"12":{"family_comment":"","value":"","family":"","comment":""},"13":{"family_comment":"","value":"","family":"","comment":""},"14":{"family_comment":"","value":"","family":"","comment":""},"15":{"family_comment":"","value":"","family":"","comment":""},"16":{"family_comment":"","value":"47000","value_unclear":false,"family":"23000","comment":""},"17":{"family_comment":"","value":"","family":"","comment":""},"18":{"family_comment":"","value":"","family":"","comment":""},"19":{"family_comment":"","value":"","family":"","comment":""},"20":{"value":"","family_comment":"","family_unclear":false,"family":"","comment":"","family_comment_unclear":false}},"vehicle":{"35":[{"brand_info":"1798 куб. см., 117.76 кВт свідоцтво про реєстрацію САТ724896","sum_rent_comment":"","brand_info_unclear":false,"year":"2008","brand_info_hidden":true,"sum_rent_comment_unclear":false,"year_unclear":false,"sum_rent":"","sum":"70000","brand":"Volkswagen Passat","sum_comment":"","brand_unclear":false,"brand_hidden":false}]},"id":"vulyk_27_178","banks":{"45":[{"sum_foreign_comment":"","sum":"","sum_comment":"","sum_hidden":false,"sum_foreign_units":"UAH","sum_foreign_hidden":false,"sum_units":"UAH","sum_comment_hidden":false,"sum_units_hidden":false,"sum_foreign":""},{"sum_foreign_comment":"","sum_units":"","sum_comment":"","sum_foreign_units":"","sum_comment_hidden":false,"sum":"","sum_foreign":""}],"46":[{"sum_foreign_comment":"","sum_units":"UAH","sum_comment":"","sum_comment_unclear":false,"sum_hidden":false,"sum_foreign_units":"UAH","sum_comment_hidden":false,"sum":"","sum_foreign":""},{"sum_foreign_comment":"","sum_units":"","sum_comment":"","sum_comment_unclear":false,"sum_foreign_units":"","sum":"","sum_foreign":""}],"47":[{"sum_foreign_comment":"","sum":"","sum_comment":"","sum_hidden":false,"sum_foreign_units":"UAH","sum_foreign_hidden":false,"sum_units":"UAH","sum_comment_hidden":false,"sum_unclear":false,"sum_foreign":"","sum_units_hidden":false}],"48":[{"sum_foreign_comment":"","sum_units":"UAH","sum_comment":"","sum_foreign_units":"UAH","sum":"","sum_foreign":""}],"49":[{"sum_foreign_comment":"","sum_units":"UAH","sum_comment":"","sum_foreign_units":"UAH","sum":"","sum_foreign":""}],"50":[{"sum_foreign_comment":"","sum_units":"UAH","sum_comment":"","sum_foreign_units":"UAH","sum":"","sum_foreign":""}],"51":[{"sum_foreign_comment":"","sum_units":"UAH","sum_units_hidden":false,"sum_comment":"","sum_comment_unclear":false,"sum_hidden":true,"sum_foreign_units":"UAH","sum_comment_hidden":false,"sum_unclear":false,"sum":"1173","sum_foreign":""},{"sum_foreign_comment":"","sum_units":"","sum_comment":"","sum_foreign_units":"","sum_comment_hidden":false,"sum":"","sum_foreign":""}],"52":[{"sum_foreign_comment":"","sum_units":"UAH","sum_comment":"","sum_comment_unclear":false,"sum_units_hidden":false,"sum_foreign_units":"UAH","sum_comment_hidden":false,"sum_unclear":false,"sum":"","sum_foreign":""}],"53":[{"sum_foreign_comment":"","sum_units":"UAH","sum_comment":"","sum_foreign_units":"UAH","sum":"","sum_foreign":""}]},"declaration":{"additional_info_text":"","notfull_lostpages":"","date":"2015-03-05T00:00:00","notfull":"","additional_info":"","url":"http://static.declarations.com.ua/declarations/chosen_ones/mega_batch/kviatkovskyi_anatolii_stepanovych.pdf"},"liabilities":{"54":{"sum_foreign_comment":"","sum_foreign_hidden":false,"sum_comment":"","sum_comment_hidden":false,"sum":"","sum_foreign":""},"55":{"sum_foreign_comment":"","sum":"","sum_comment":"","sum_foreign":""},"56":{"sum_foreign_comment":"","sum":"","sum_comment":"","sum_hidden":false,"sum_unclear":false,"sum_foreign":""},"57":{"sum_foreign_comment":"","sum":"15000","sum_comment":"","sum_hidden":true,"sum_comment_hidden":false,"sum_unclear":false,"sum_foreign":""},"58":{"sum_foreign_comment":"","sum":"238","sum_comment":"","sum_hidden":true,"sum_comment_hidden":false,"sum_unclear":false,"sum_foreign":""},"59":{"sum_foreign_comment":"","sum":"","sum_comment":"","sum_foreign":""},"60":{"sum_foreign_comment":"","sum":"","sum_comment":"","sum_hidden":false,"sum_comment_hidden":false,"sum_foreign":""},"61":{"sum_foreign_comment":"","sum":"","sum_comment":"","sum_foreign":""},"62":{"sum_foreign_comment":"","sum":"","sum_comment":"","sum_foreign":""},"63":{"sum_foreign_comment":"","sum":"","sum_comment":"","sum_hidden":false,"sum_comment_hidden":false,"sum_foreign":""},"64":{"sum_foreign_comment":"","sum":"","sum_comment":"","sum_hidden":false,"sum_comment_hidden":false,"sum_foreign":""}},"ft_src":"15000\n238\nсуддя апеляційного суду рівненської області\nРівненська область\nЗагальний апеляційний суд\nАнатолій\nПодружжя\nСтепанович\nКвятковський\nКвятковський Анатолій Степанович\nКвятковський Анатолій Степанович\nАнатолій Степанович Квятковський\nАнатолій Квятковський\nКвятковський Анатолій Степанович\n1798 куб. см., 117.76 кВт свідоцтво про реєстрацію САТ724896\nVolkswagen Passat\n2008\n70000\n1173\n2014\n1798 куб. см., 117.76 кВт свідоцтво про реєстрацію САТ724896\nVolkswagen Passat\n2008\n70000\n1173\n21.9\n225.6\nу користуванні\n1200\nу користуванні\n2867\nвласність дружини\n1200\nкористувач\n225.6\nкористувач\n55.7\nКвятковський Анатолій Степанович\nАнатолій Степанович Квятковський\nАнатолій Квятковський\nКвятковський Анатолій Степанович\nАнатолій\nПодружжя\nКвятковський Анатолій Степанович\nКвятковський\nЗагальний апеляційний суд\nРівненська область\nсуддя апеляційного суду рівненської області\nСтепанович\n15000\n238\n256731\n97865\n120865\n303731\n47000\n23000\n2014\n238\n15000\n21.9\nвласність дружини\n2867\nкористувач\n1200\nкористувач\n225.6\nу користуванні\n1200\nу користуванні\n225.6\n55.7\nПодружжя\nСтепанович\nКвятковський\nАнатолій\nКвятковський Анатолій Степанович\nАнатолій Степанович Квятковський\nАнатолій Квятковський\nКвятковський Анатолій Степанович\nРівненська область\nЗагальний апеляційний суд\nсуддя апеляційного суду рівненської області\nКвятковський Анатолій Степанович\n97865\n256731\n120865\n303731\n23000\n47000\n2008\nVolkswagen Passat\n70000\n1798 куб. см., 117.76 кВт свідоцтво про реєстрацію САТ724896\n303731\n120865\n23000\n47000\n256731\n97865\n55.7\nу користуванні\n1200\nкористувач\n225.6\n21.9\nу користуванні\n225.6\nвласність дружини\n2867\nкористувач\n1200\n1173\n2014","general":{"name_hidden":false,"name":"Анатолій","patronymic_unclear":false,"inn":"","family":[{"inn":"","inn_hidden":true,"relations_hidden":false,"family_name":"","relations_other":"","relations":"Подружжя","name_hidden":true,"name_unclear":false}],"patronymic":"Степанович","inn_hidden":true,"family_raw":"","inn_unclear":false,"post":{"post_unclear":false,"region_unclear":false,"post":"суддя апеляційного суду рівненської області","office":"Загальний апеляційний суд","region":"Рівненська область","post_hidden":false,"office_unclear":false},"last_name_unclear":false,"full_name":"Квятковський Анатолій Степанович","addresses":[{"place_district":"","place_address_hidden":true,"place_city":"","place_city_type_hidden":true,"place_district_hidden":true,"place_city_type":"","place_city_hidden":true,"place_address_unclear":false,"place_address":"","place_hidden":true,"place":""}],"last_name":"Квятковський","full_name_suggest":{"output":"Квятковський Анатолій Степанович","input":["Квятковський Анатолій Степанович","Анатолій Степанович Квятковський","Анатолій Квятковський"]},"name_unclear":false},"source":"VULYK","estate":{"23":[{"costs":"","costs_comment":"","address_hidden":true,"region_hidden":true,"space_comment":"у користуванні","space":"1200","address":"","region":"","address_unclear":false,"costs_rent_comment":"","costs_rent_comment_hidden":false,"space_units":"м²","space_units_unclear":false,"costs_rent":""},{"costs":"","costs_comment":"","address_hidden":false,"region_hidden":false,"space_comment":"","space":"","address":"","costs_comment_unclear":false,"region":"","costs_rent_comment":"","space_units":"","costs_rent":""},{"costs_rent":"","region":"","costs":"","costs_rent_comment":"","costs_comment":"","space_comment":"","space_units":"","space":"","address":""},{"costs_rent":"","region":"","costs":"","costs_rent_comment":"","costs_comment":"","space_comment":"","space_units":"","space":"","address":""}],"24":[{"space_unclear":false,"costs":"","costs_comment":"","address_hidden":true,"region_hidden":true,"space_comment":"користувач","space":"225.6","address":"","region":"","costs_rent_comment":"","space_units":"м²","costs_rent":""}],"27":[{"space_hidden":false,"costs":"","costs_comment":"","address_hidden":false,"region_hidden":true,"space_comment":"","space":"21.9","address":"","region":"","costs_rent_comment":"","space_units":"м²","costs_rent":""}],"29":[{"space_unclear":false,"costs_property_comment":"","costs_property":"","address_hidden":true,"region_hidden":true,"space_comment":"власність дружини","space":"2867","address":"","costs_property_comment_hidden":true,"region":"","address_unclear":false,"costs_rent_comment":"","space_comment_hidden":false,"space_units":"м²","space_units_unclear":false,"costs_rent":""},{"costs_rent":"","space_unclear":false,"region":"","costs_property":"","costs_rent_comment":"","space_comment":"користувач","costs_property_comment":"","space_units":"м²","space":"1200","address":""}],"30":[{"space_unclear":false,"address_hidden":false,"region_hidden":true,"space_comment":"у користуванні","space":"225.6","address":"","region":"","costs_property":"","costs_rent_comment":"","space_units":"м²","costs_property_comment":"","costs_rent":""}],"31":[{"space_hidden":false,"costs_property":"","address_hidden":false,"region_hidden":true,"space_comment":"","space":"55.7","address":"","region":"","address_unclear":false,"costs_rent_comment":"","space_comment_unclear":false,"costs_rent_comment_hidden":false,"space_units":"м²","costs_property_comment":"","costs_rent":""}]},"intro":{"declaration_year":"2014","isnotdeclaration":"","declaration_year_hidden":false}}