{"id":"vulyk_65_95","ft_src":"1498 куб. см. повна маса 1595 кг\n2004\n1/3 частина\n55200 м. Первомайськ вул. Косіора\n1000\nМиколаївська область\n55200 м. Первомайськ, вул. Желябова\n28\nМиколаївська область\n1/3 частина\n55200 м. Первомайськ вул. Косіора\n93.6\nМиколаївська область\nМиколаївська область\n55200 м. Первомайськ, вул. Грушевського\n62.8\n2014\n216041\n12180\n228349\n128\n1498 куб. см. повна маса 1595 кг\n2004\n1000\n1/3 частина\nМиколаївська область\n55200 м. Первомайськ вул. Косіора\n93.6\n1/3 частина\n55200 м. Первомайськ вул. Косіора\nМиколаївська область\n28\nМиколаївська область\n55200 м. Первомайськ, вул. Желябова\n62.8\nМиколаївська область\n55200 м. Первомайськ, вул. Грушевського\nвул. Грушевського\nМиколаївська область\nПервомайськ\nМаржина Тетяна Валеріївна\nТетяна Валеріївна Маржина\nТетяна Маржина\nМаржина Тетяна Валеріївна\nМаржина Тетяна Валеріївна\nТетяна\nМаржина\nЗагальний місцевий суд\nМиколаївська область\nсуддя первомайського міськрайонного суду миколаївської області\nВалеріївна\n216041\n128\n228349\n12180\n2014\nВалеріївна\nМаржина\nТетяна\nМаржина Тетяна Валеріївна\nТетяна Валеріївна Маржина\nТетяна Маржина\nМаржина Тетяна Валеріївна\nвул. Грушевського\nПервомайськ\nМиколаївська область\nМиколаївська область\nЗагальний місцевий суд\nсуддя первомайського міськрайонного суду миколаївської області\nМаржина Тетяна Валеріївна","estate":{"23":[{"address":"55200 м. Первомайськ вул. Косіора","space_units":"м²","space_hidden":false,"space_unclear":false,"region_hidden":false,"costs_comment":"","space_comment":"1/3 частина","address_hidden":false,"costs":"","address_unclear":false,"costs_rent_comment":"","space":"1000","region":"Миколаївська область","costs_rent":""}],"24":[{"address":"55200 м. Первомайськ вул. Косіора","space_units":"м²","space_hidden":false,"space_unclear":false,"region_hidden":false,"costs_comment":"","space_comment":"1/3 частина","address_hidden":false,"costs":"","address_unclear":false,"costs_rent_comment":"","space":"93.6","region":"Миколаївська область","costs_rent":""}],"25":[{"costs_rent_comment_unclear":false,"address":"55200 м. Первомайськ, вул. Грушевського","space_units":"м²","space_hidden":false,"space_unclear":false,"region_hidden":false,"costs_comment":"","space_comment":"","space_comment_unclear":false,"costs":"","address_unclear":false,"address_hidden":false,"costs_rent_comment":"","space":"62.8","region":"Миколаївська область","space_units_hidden":false,"costs_rent":""}],"27":[{"address":"55200 м. Первомайськ, вул. Желябова","space_units":"м²","space_hidden":false,"space_comment":"","region_hidden":false,"costs_comment":"","address_hidden":false,"space":"28","costs_rent_comment":"","costs":"","region_unclear":false,"region":"Миколаївська область","space_units_hidden":false,"costs_rent":""}]},"vehicle":{"35":[{"brand_info":"1498 куб. см. повна маса 1595 кг","sum_rent_comment":"","brand_unclear":false,"year":"2004","brand_hidden":true,"sum_comment":"","brand_info_hidden":false,"sum_rent":"","brand":"","year_unclear":false,"brand_info_unclear":true,"sum":""}]},"source":"VULYK","income":{"5":{"family":"","family_comment":"","comment":"","value_hidden":false,"value_unclear":false,"value":"228349","family_hidden":false,"family_unclear":false},"6":{"family_comment":"","family":"","value_hidden":false,"comment":"","comment_unclear":false,"value_unclear":false,"value":"216041","family_hidden":false},"7":{"source_name_hidden":false,"family_comment":"","family":"","value_hidden":false,"comment":"","value":"","source_name":""},"8":{"family_comment":"","value":"","family":"","comment":""},"9":{"family_comment":"","comment_unclear":false,"value":"","family":"","comment":""},"10":{"family_comment":"","value":"12180","family":"","comment":"","value_unclear":false},"11":{"family_comment":"","value":"","family":"","comment":""},"12":{"family_comment":"","value":"","family":"","comment":""},"13":{"family_comment":"","value":"","family":"","comment":""},"14":{"family_comment":"","value":"","family":"","comment":""},"15":{"family_comment":"","value":"","family":"","comment":""},"16":{"family_comment":"","value":"","family":"","comment":""},"17":{"family_comment":"","value":"","family":"","comment":""},"18":{"family_comment":"","value":"","family":"","comment":""},"19":{"family":"","family_comment":"","comment":"","value_hidden":false,"value_unclear":false,"comment_hidden":false,"family_hidden":false,"value":"","family_comment_hidden":false},"20":{"family_comment":"","family":"","value_hidden":false,"comment":"","value":"128","comment_unclear":false,"value_unclear":false,"family_unclear":false,"family_hidden":false}},"general":{"family_raw":"","name":"Тетяна","full_name_suggest":{"input":["Маржина Тетяна Валеріївна","Тетяна Валеріївна Маржина","Тетяна Маржина"],"output":"Маржина Тетяна Валеріївна"},"name_unclear":false,"patronymic":"Валеріївна","inn_hidden":true,"addresses":[{"place_city_type":"Місто","place_address_unclear":false,"place_city_type_hidden":false,"place_hidden":false,"place_city_hidden":false,"place_district":"","place_district_hidden":false,"place":"Миколаївська область","place_city":"Первомайськ","place_address_hidden":false,"place_address":"вул. Грушевського"}],"last_name_hidden":false,"patronymic_hidden":false,"inn":"","inn_unclear":false,"last_name":"Маржина","full_name":"Маржина Тетяна Валеріївна","post":{"post_hidden":false,"office":"Загальний місцевий суд","post":"суддя первомайського міськрайонного суду миколаївської області","region":"Миколаївська область","region_hidden":false,"office_unclear":false,"office_hidden":false,"post_unclear":false,"region_unclear":false},"name_hidden":false,"last_name_unclear":false},"liabilities":{"54":{"sum_comment_unclear":false,"sum_comment":"","sum_hidden":false,"sum":"","sum_foreign_comment":"","sum_foreign":"","sum_comment_hidden":false},"55":{"sum_comment":"","sum_foreign_comment":"","sum_foreign":"","sum":""},"56":{"sum_comment":"","sum_foreign_comment":"","sum_foreign":"","sum_unclear":false,"sum":""},"57":{"sum_comment_unclear":false,"sum_comment":"","sum":"","sum_foreign_comment":"","sum_foreign":"","sum_unclear":false},"58":{"sum_comment_unclear":false,"sum_comment":"","sum":"","sum_foreign_comment":"","sum_foreign":"","sum_unclear":false},"59":{"sum_comment":"","sum_foreign_comment":"","sum_foreign":"","sum":""},"60":{"sum_comment":"","sum_comment_unclear":false,"sum_foreign_comment":"","sum":"","sum_foreign":""},"61":{"sum_comment":"","sum_foreign_comment":"","sum_foreign":"","sum":""},"62":{"sum_comment":"","sum_foreign_comment":"","sum_foreign":"","sum":""},"63":{"sum_comment":"","sum_foreign_comment":"","sum_foreign":"","sum":""},"64":{"sum_comment":"","sum_foreign_comment":"","sum_foreign":"","sum_unclear":false,"sum":""}},"declaration":{"notfull_lostpages":"","additional_info_text":"","additional_info":"","date":"2015-03-30T00:00:00","notfull":"","url":"http://static.declarations.com.ua/declarations/chosen_ones/mega_batch/marzhyna_tetiana_valeriivna.pdf"},"intro":{"declaration_year_hidden":false,"isnotdeclaration":"","declaration_year":"2014"}}