{"id":"vulyk_73_11","ft_src":"Hyundai Tucson\n1975 куб. см.\n2008\n2008\nHyundai Tucson\n1975 куб. см.\n27.8\n91.1\n30.3\n1000\n30.3\n91.1\n2013\n65663.95\n247169.53\nАпеляційний суд Тернопільської області, Державна судова адміністрація України, ВЮ 'Українська ліга сприяння розвитку паліативної та хоспісної допомоги'\n65663.95\n252125.53\n4956\n1975 куб. см.\nHyundai Tucson\n2008\n1975 куб. см.\nHyundai Tucson\n2008\n2013\nШевчук Галина Михайлівна\nГалина Михайлівна Шевчук\nГалина Шевчук\nШевчук Галина Михайлівна\nГалина\nПодружжя\nШевчук Д. Н\nШевчук Галина Михайлівна\nМихайлівна\nЗагальний апеляційний суд\nТернопільська область\nсуддя апеляційного суду тернопільської області\nШевчук\n10800\nАпеляційний суд Тернопільської області, Державна судова адміністрація України, ВЮ 'Українська ліга сприяння розвитку паліативної та хоспісної допомоги'\n65663.95\n247169.53\n4956\n252125.53\n65663.95\n27.8\n30.3\n91.1\n30.3\n91.1\n1000\n10800\nПодружжя\nШевчук Д. Н\nМихайлівна\nШевчук\nГалина\nШевчук Галина Михайлівна\nГалина Михайлівна Шевчук\nГалина Шевчук\nШевчук Галина Михайлівна\nТернопільська область\nЗагальний апеляційний суд\nсуддя апеляційного суду тернопільської області\nШевчук Галина Михайлівна","estate":{"25":[{"address":"","space_units":"м²","costs_hidden":false,"space_hidden":false,"space_unclear":false,"region_hidden":true,"costs_rent_comment":"","space_comment":"","address_hidden":false,"space_comment_hidden":false,"costs":"","costs_comment":"","space":"91.1","region":"","costs_rent":""}],"26":[{"address":"","space_units":"м²","costs_comment":"","space_unclear":false,"region_hidden":true,"space_comment":"","address_hidden":false,"costs":"","costs_rent_comment":"","space":"30.3","region":"","costs_rent":""}],"29":[{"costs_property_comment":"","address":"","space_units":"м²","space_unclear":false,"region_hidden":true,"costs_property":"","space_comment":"","address_hidden":false,"costs_rent_comment":"","space":"1000","region":"","costs_rent":""}],"31":[{"costs_property_comment":"","address":"","space_units":"м²","space_unclear":false,"region_hidden":false,"costs_property":"","space_comment":"","address_hidden":false,"costs_rent_comment":"","space":"91.1","region":"","costs_rent":""},{"costs_property_comment":"","address":"","space_units":"м²","costs_rent_comment":"","space":"30.3","space_unclear":false,"region_hidden":false,"costs_property":"","space_comment":"","region":"","costs_rent":""}],"33":[{"costs_property_comment":"","address":"","space_units":"м²","space_hidden":false,"space_comment":"","region_hidden":true,"costs_property":"","region":"","address_hidden":false,"costs_rent_comment":"","space":"27.8","costs_rent":""}]},"vehicle":{"35":[{"brand_info":"1975 куб. см.","sum_comment":"","sum_hidden":false,"brand_unclear":false,"sum_rent_comment":"","year":"2008","brand":"Hyundai Tucson","sum_rent":"","brand_info_unclear":false,"sum":""}],"40":[{"sum_comment":"","brand_info":"1975 куб. см.","brand_unclear":false,"sum_rent_comment":"","year":"2008","brand":"Hyundai Tucson","sum_rent":"","brand_info_unclear":false,"sum":""}]},"source":"VULYK","income":{"5":{"family_comment":"","family":"65663.95","comment":"","comment_hidden":false,"value":"252125.53","family_comment_hidden":false},"6":{"family_comment":"","family":"65663.95","comment":"","comment_hidden":false,"family_hidden":false,"family_unclear":false,"family_comment_hidden":false,"value":"247169.53"},"7":{"source_name_hidden":false,"family_comment":"","comment":"","family":"","comment_hidden":false,"value":"","family_comment_hidden":false,"source_name":"Апеляційний суд Тернопільської області, Державна судова адміністрація України, ВЮ 'Українська ліга сприяння розвитку паліативної та хоспісної допомоги'"},"8":{"family_comment":"","value":"","family":"","comment":""},"9":{"family_comment":"","comment":"","family":"","value_unclear":false,"family_unclear":false,"comment_unclear":false,"value":""},"10":{"family_comment":"","value":"","family_unclear":false,"family":"","comment":""},"11":{"family_comment":"","value":"","family":"","comment":""},"12":{"family_comment":"","value":"","family":"","comment":""},"13":{"family_comment":"","value":"","family":"","comment":""},"14":{"family_comment":"","value":"","family":"","comment":""},"15":{"family_comment":"","comment_unclear":false,"value":"","family":"","comment":""},"16":{"family_comment":"","comment_unclear":false,"value":"","family":"","comment":""},"17":{"family_comment":"","value":"","family":"","comment":""},"18":{"family_comment":"","value":"","family":"","comment":""},"19":{"family_comment":"","value":"","family":"","comment":""},"20":{"family_comment":"","family":"","comment":"","value_unclear":false,"family_unclear":false,"value":"4956","family_comment_hidden":false,"family_comment_unclear":false}},"general":{"family_raw":"","name":"Галина","full_name_suggest":{"input":["Шевчук Галина Михайлівна","Галина Михайлівна Шевчук","Галина Шевчук"],"output":"Шевчук Галина Михайлівна"},"name_unclear":false,"patronymic":"Михайлівна","inn_hidden":true,"inn":"","addresses":[{"place_city_type_hidden":false,"place_city_type":"","place_city_hidden":true,"place_hidden":false,"place_district":"","place_district_hidden":false,"place":"","place_city":"","place_address_hidden":true,"place_address":""}],"last_name":"Шевчук","full_name":"Шевчук Галина Михайлівна","family":[{"inn":"","inn_unclear":false,"family_name":"Шевчук Д. Н","relations_hidden":false,"name_unclear":false,"relations":"Подружжя","inn_hidden":true,"name_hidden":true,"relations_other":""}],"post":{"post_hidden":false,"office":"Загальний апеляційний суд","post":"суддя апеляційного суду тернопільської області","region":"Тернопільська область","region_hidden":false,"office_unclear":false,"office_hidden":false,"post_unclear":false,"region_unclear":false},"last_name_unclear":false},"liabilities":{"54":{"sum_comment_unclear":false,"sum_comment":"","sum_hidden":false,"sum":"","sum_foreign_comment":"","sum_foreign":"","sum_unclear":false,"sum_foreign_hidden":false,"sum_comment_hidden":false},"55":{"sum_comment":"","sum_foreign_comment":"","sum_foreign":"","sum":"","sum_comment_hidden":false},"56":{"sum_comment":"","sum_comment_unclear":false,"sum_foreign_comment":"","sum":"10800","sum_foreign":""},"57":{"sum_comment":"","sum_hidden":false,"sum":"","sum_foreign_comment":"","sum_foreign":"","sum_unclear":false,"sum_comment_hidden":false},"58":{"sum_comment":"","sum_hidden":false,"sum":"","sum_foreign_comment":"","sum_foreign":"","sum_comment_hidden":false},"59":{"sum_comment_unclear":false,"sum_comment":"","sum":"","sum_foreign_comment":"","sum_foreign":"","sum_unclear":false},"60":{"sum_comment":"","sum_hidden":false,"sum":"","sum_foreign_comment":"","sum_foreign":"","sum_unclear":false,"sum_comment_hidden":false},"61":{"sum_comment":"","sum_foreign_comment":"","sum_foreign":"","sum":""},"62":{"sum_comment":"","sum_foreign_comment":"","sum_foreign":"","sum":""},"63":{"sum_comment":"","sum_hidden":false,"sum":"","sum_foreign_comment":"","sum_foreign":"","sum_comment_hidden":false},"64":{"sum_comment":"","sum_foreign_comment":"","sum_foreign":"","sum":""}},"declaration":{"notfull_lostpages":"","additional_info_text":"","additional_info":"","date":"2014-03-28T00:00:00","notfull":"","url":"http://static.declarations.com.ua/declarations/chosen_ones/judges_batch/1476_shevchuk_halyna_mykhailivna.pdf"},"intro":{"declaration_year":"2013"}}