{"income":{"5":{"value":"245663.65","family_comment":"","family_hidden":false,"value_hidden":false,"family_unclear":false,"family":"","comment":""},"6":{"value":"245663.65","comment_unclear":false,"family_comment":"","family":"","comment":"","family_comment_unclear":false},"7":{"family_comment":"","value":"","source_name":"","family":"","comment":""},"8":{"family_comment":"","value":"","family":"","comment":""},"9":{"family_comment":"","value":"","family":"","comment":""},"10":{"family_comment":"","value":"","family":"","comment":""},"11":{"family_comment":"","value":"","family":"","comment":"","family_comment_unclear":false},"12":{"family_comment":"","value":"","family":"","comment":""},"13":{"family_comment":"","value":"","family":"","comment":""},"14":{"family_comment":"","value":"","family":"","comment":""},"15":{"family_comment":"","value":"","family":"","comment":""},"16":{"family_comment":"","value":"","family":"","comment":""},"17":{"family_comment":"","value":"","family":"","comment":""},"18":{"family_comment":"","value":"","family":"","comment":""},"19":{"family_comment":"","value":"","family":"","comment":"","value_hidden":false},"20":{"family_comment":"","value":"","comment_unclear":false,"family":"","comment":""}},"vehicle":{"40":[{"brand_info":"2360 куб. см., 125 кВт , 464,0 см","sum_rent_comment":"","brand":"Mitsubishi Outlander XL","sum_comment":"","year":"2009","brand_info_unclear":false,"sum":"","sum_rent":""}]},"id":"vulyk_51_59","banks":{"45":[{"sum_foreign_comment":"","sum_units":"UAH","sum_comment":"","sum_comment_unclear":false,"sum_hidden":false,"sum_foreign_units":"UAH","sum_comment_hidden":false,"sum":"27000","sum_foreign":""},{"sum_foreign_comment":"","sum_units":"","sum_comment":"","sum_foreign_units":"","sum":"","sum_foreign":""},{"sum_foreign_comment":"","sum_units":"","sum_comment":"","sum_foreign_units":"","sum":"","sum_foreign":""},{"sum_foreign_comment":"","sum_units":"","sum_comment":"","sum_foreign_units":"","sum":"","sum_foreign":""},{"sum_foreign_comment":"","sum_units":"","sum_comment":"","sum_foreign_units":"","sum":"","sum_unclear":false,"sum_foreign":""}],"46":[{"sum_foreign_comment":"","sum_units":"UAH","sum_comment":"","sum_foreign_units":"UAH","sum":"27000","sum_foreign":""}],"47":[{"sum_foreign_comment":"","sum_units":"UAH","sum_comment":"","sum_foreign_units":"UAH","sum":"","sum_foreign":""}],"48":[{"sum_foreign_comment":"","sum_units":"UAH","sum_comment":"","sum_foreign_units":"UAH","sum":"","sum_foreign":""}],"49":[{"sum_foreign_comment":"","sum_units":"UAH","sum_comment":"","sum_foreign_units":"UAH","sum":"","sum_foreign":""}],"50":[{"sum_foreign_comment":"","sum_units":"UAH","sum_comment":"","sum_foreign_units":"UAH","sum":"","sum_foreign":""}],"51":[{"sum_foreign_comment":"","sum_units":"UAH","sum_comment":"","sum_foreign_units":"UAH","sum_comment_hidden":false,"sum":"24000","sum_foreign":""},{"sum_foreign_comment":"","sum_units":"","sum_comment":"","sum_foreign_units":"","sum":"","sum_foreign":""},{"sum_foreign_comment":"","sum_units":"","sum_comment":"","sum_foreign_units":"","sum":"","sum_foreign":""}],"52":[{"sum_foreign_comment":"","sum_units":"UAH","sum_comment":"","sum_foreign_units":"UAH","sum_comment_hidden":false,"sum":"","sum_foreign":""}],"53":[{"sum_foreign_comment":"","sum_units":"UAH","sum_comment":"","sum_foreign_units":"UAH","sum":"","sum_foreign":""}]},"declaration":{"additional_info_text":"","notfull_lostpages":"","date":"2015-03-27T00:00:00","notfull":"","additional_info":"","url":"http://static.declarations.com.ua/declarations/chosen_ones/mega_batch/dziubin_v´yacheslav_viktorovych.pdf"},"liabilities":{"54":{"sum_foreign_comment":"","sum_comment_hidden":false,"sum":"","sum_comment":"","sum_foreign":""},"55":{"sum_foreign_comment":"","sum":"","sum_comment":"","sum_foreign":""},"56":{"sum_foreign_comment":"","sum":"","sum_comment":"","sum_foreign":""},"57":{"sum_foreign_comment":"","sum":"","sum_comment":"","sum_hidden":false,"sum_comment_hidden":false,"sum_foreign":""},"58":{"sum_foreign_comment":"","sum_comment_hidden":false,"sum":"","sum_comment":"","sum_foreign":""},"59":{"sum_foreign_comment":"","sum":"","sum_comment":"","sum_foreign":""},"60":{"sum_foreign_comment":"","sum":"","sum_comment":"","sum_foreign":""},"61":{"sum_foreign_comment":"","sum":"","sum_comment":"","sum_foreign":""},"62":{"sum_foreign_comment":"","sum":"","sum_comment":"","sum_foreign":""},"63":{"sum_foreign_comment":"","sum_comment_hidden":false,"sum":"","sum_comment":"","sum_foreign":""},"64":{"sum_foreign_comment":"","sum":"","sum_comment":"","sum_foreign":""}},"ft_src":"Дзюбін Вячеслав Вікторович\nсуддя апеляційного суду м. києва\nм. Київ\nЗагальний апеляційний суд\nВячеслав\nДзюбіна Л. І\nПодружжя\nДзюбін Вячеслав Вікторович\nВячеслав Вікторович Дзюбін\nВячеслав Дзюбін\nДзюбін Вячеслав Вікторович\nДзюбін\nВікторович\n2360 куб. см., 125 кВт , 464,0 см\n2009\nMitsubishi Outlander XL\n27000\n24000\n27000\n2014\n2360 куб. см., 125 кВт , 464,0 см\nMitsubishi Outlander XL\n2009\n27000\n24000\n27000\n2/3\n57.9\n60.5\n1/2 кв., у 1998 році\n44.6\nу 2014 році, спадщина за законом\nу 2014році, спадщина за законом\nДзюбін\nДзюбін Вячеслав Вікторович\nВячеслав Вікторович Дзюбін\nВячеслав Дзюбін\nДзюбін Вячеслав Вікторович\nВячеслав\nВікторович\nДзюбін Вячеслав Вікторович\nЗагальний апеляційний суд\nсуддя апеляційного суду м. києва\nм. Київ\nПодружжя\nДзюбіна Л. І\n245663.65\n245663.65\n2014\n2/3\n57.9\n1/2 кв., у 1998 році\n60.5\nу 2014році, спадщина за законом\nу 2014 році, спадщина за законом\n44.6\nДзюбіна Л. І\nПодружжя\nВікторович\nДзюбін\nм. Київ\nЗагальний апеляційний суд\nсуддя апеляційного суду м. києва\nДзюбін Вячеслав Вікторович\nДзюбін Вячеслав Вікторович\nВячеслав Вікторович Дзюбін\nВячеслав Дзюбін\nДзюбін Вячеслав Вікторович\nВячеслав\n245663.65\n245663.65\n2009\n2360 куб. см., 125 кВт , 464,0 см\nMitsubishi Outlander XL\n245663.65\n245663.65\n2/3\n57.9\n1/2 кв., у 1998 році\n60.5\nу 2014 році, спадщина за законом\n44.6\nу 2014році, спадщина за законом\n27000\n27000\n24000\n2014","general":{"inn":"","inn_hidden":true,"last_name":"Дзюбін","post":{"post":"суддя апеляційного суду м. києва","region":"м. Київ","office_hidden":false,"office":"Загальний апеляційний суд","office_unclear":false,"region_hidden":false},"name":"Вячеслав","full_name":"Дзюбін Вячеслав Вікторович","family_raw":"","addresses":[{"place_district":"","place_city_hidden":false,"place_city":"","place_city_type_hidden":false,"place_district_hidden":false,"place_city_type":"","place_address_hidden":false,"place_address":"","place_hidden":true,"place":""}],"family":[{"inn":"","relations":"Подружжя","relations_other":"","inn_hidden":false,"family_name":"Дзюбіна Л. І","name_hidden":false,"name_unclear":false}],"full_name_suggest":{"output":"Дзюбін Вячеслав Вікторович","input":["Дзюбін Вячеслав Вікторович","Вячеслав Вікторович Дзюбін","Вячеслав Дзюбін"]},"patronymic":"Вікторович"},"source":"VULYK","estate":{"23":[{"costs":"","costs_comment":"","costs_hidden":false,"address_hidden":false,"region_hidden":false,"space_comment":"","space":"","address":"","region":"","address_unclear":false,"costs_rent_comment":"","costs_rent_hidden":false,"space_units":"м²","costs_rent":""},{"costs":"","costs_comment":"","costs_hidden":false,"region_hidden":false,"space_comment":"","space":"","address":"","region":"","costs_rent_comment":"","costs_rent_hidden":false,"space_units":"","costs_rent":""},{"space":"","region":"","costs":"","costs_rent_comment":"","costs_comment":"","address_unclear":false,"space_comment":"","space_units":"","costs_rent":"","address":""},{"costs_rent":"","region":"","costs":"","costs_rent_comment":"","costs_comment":"","space_comment":"","space_units":"","space":"","address":""}],"25":[{"space_unclear":false,"costs":"","costs_comment":"","costs_hidden":false,"address_hidden":false,"region_hidden":true,"space_comment":"1/2 кв., у 1998 році","space_hidden":false,"space":"60.5","address":"","region":"","address_unclear":false,"costs_rent_comment":"","space_units":"м²","costs_rent":""},{"space_hidden":false,"costs":"","costs_comment":"у 2014році, спадщина за законом","costs_hidden":false,"address_hidden":false,"region_hidden":false,"space_comment":"у 2014 році, спадщина за законом","space":"44.6","address":"","region":"","address_unclear":false,"costs_rent_comment":"","costs_rent_hidden":false,"space_units":"м²","costs_rent":""}],"31":[{"space_hidden":false,"costs_property_hidden":false,"address_hidden":true,"region_hidden":true,"space_comment":"2/3","space_unclear":false,"space":"57.9","address":"","region":"","address_unclear":false,"costs_rent_comment":"","costs_rent_hidden":false,"costs_property":"","space_units":"м²","costs_property_comment":"","costs_rent":""}]},"intro":{"declaration_year":"2014","isnotdeclaration":""}}