{"income":{"5":{"family_comment":"","value":"286882","family":"","comment":""},"6":{"family_comment":"","value":"275561","family":"","comment":""},"7":{"value":"","comment_hidden":false,"value_hidden":false,"family_comment":"","source_name":"","family":"","comment":"","source_name_hidden":false},"8":{"family_comment":"","value":"","family":"","comment":""},"9":{"value":"","comment_hidden":false,"family_comment":"","family":"","comment":"","family_comment_unclear":false},"10":{"family_comment":"","value":"","family":"","comment":""},"11":{"family_comment":"","value":"","comment_hidden":false,"family":"","comment":""},"12":{"family_comment":"","value":"","family":"","comment":""},"13":{"family_comment":"","value":"","family":"","comment":""},"14":{"family_comment":"","value":"","family":"","comment":""},"15":{"family_comment":"","value":"","family":"","comment":""},"16":{"family_comment":"","value":"","family":"","comment":""},"17":{"family_comment":"","value":"","family":"","comment":""},"18":{"family_comment":"","value":"","family":"","comment":""},"19":{"family_comment":"","value":"","family":"","comment":""},"20":{"family_comment":"","value":"11321","comment_hidden":false,"family":"","comment":"пенсія"}},"id":"vulyk_102_115","banks":{"45":[{"sum_foreign_comment":"","sum_units":"UAH","sum_comment":"","sum_comment_unclear":false,"sum_hidden":false,"sum_foreign_units":"UAH","sum_comment_hidden":true,"sum_unclear":false,"sum":"1299","sum_foreign":""}]},"declaration":{"date":"2016-03-30T00:00:00","additional_info_text":"","additional_info":"","url":"http://static.declarations.com.ua/declarations/chosen_ones/judges_batch/1189_kostenko_tetiana_fedorivna.pdf"},"liabilities":{"54":{"sum_foreign_comment":"","sum":"","sum_comment":"","sum_hidden":false,"sum_comment_hidden":false,"sum_foreign":""},"55":{"sum_foreign_comment":"","sum":"","sum_comment":"","sum_foreign":""},"56":{"sum_foreign_comment":"","sum":"","sum_comment":"","sum_foreign":""},"57":{"sum_foreign_comment":"","sum_comment_hidden":false,"sum":"","sum_comment":"","sum_foreign":""},"58":{"sum_foreign_comment":"","sum_comment_hidden":false,"sum":"","sum_comment":"","sum_foreign":""},"59":{"sum_foreign_comment":"","sum_comment_hidden":false,"sum":"","sum_comment":"","sum_foreign":""},"60":{"sum_foreign_comment":"","sum":"","sum_comment":"","sum_hidden":false,"sum_comment_hidden":false,"sum_foreign":""},"61":{"sum_foreign_comment":"","sum":"","sum_comment":"","sum_foreign":""},"62":{"sum_foreign_comment":"","sum":"","sum_comment":"","sum_unclear":false,"sum_foreign":""},"63":{"sum_foreign_comment":"","sum":"","sum_comment":"","sum_hidden":false,"sum_comment_hidden":false,"sum_foreign":""},"64":{"sum_foreign_comment":"","sum_comment_hidden":false,"sum":"","sum_comment":"","sum_foreign":""}},"ft_src":"Костенко Тетяна Федорівна\nФедорівна\nКостенко Тетяна Федорівна\nТетяна Федорівна Костенко\nТетяна Костенко\nКостенко Тетяна Федорівна\nТетяна\nсуддя\nЗагальнодержавний регіон\nВищий господарський суд\nКостенко\n1613\n79\n1299\n2015\n2015\nКостенко Тетяна Федорівна\nТетяна Федорівна Костенко\nТетяна Костенко\nКостенко Тетяна Федорівна\nТетяна\nФедорівна\nКостенко Тетяна Федорівна\nКостенко\nсуддя\nЗагальнодержавний регіон\nВищий господарський суд\n275561\nпенсія\n11321\n286882\n1613\n79\n1299\n275561\n286882\nпенсія\n11321\nФедорівна\nКостенко\nсуддя\nЗагальнодержавний регіон\nВищий господарський суд\nКостенко Тетяна Федорівна\nКостенко Тетяна Федорівна\nТетяна Федорівна Костенко\nТетяна Костенко\nКостенко Тетяна Федорівна\nТетяна\nпенсія\n11321\n286882\n275561\n79\n1613\n1299\n2015","general":{"inn":"","inn_hidden":true,"last_name":"Костенко","post":{"region":"Загальнодержавний регіон","region_unclear":true,"post":"суддя","office_unclear":true,"office":"Вищий господарський суд"},"name":"Тетяна","full_name":"Костенко Тетяна Федорівна","family_raw":"","addresses":[{"place_district":"","place_city_hidden":true,"place_city":"","place_city_type_hidden":false,"place_district_hidden":false,"place_city_type":"","place_address_hidden":true,"place_address":"","place_hidden":true,"place":""}],"patronymic_hidden":false,"full_name_suggest":{"output":"Костенко Тетяна Федорівна","input":["Костенко Тетяна Федорівна","Тетяна Федорівна Костенко","Тетяна Костенко"]},"patronymic":"Федорівна"},"source":"VULYK","estate":{"23":[{"costs":"","costs_comment":"","address_hidden":false,"region_hidden":true,"space_comment":"","space":"1613","address":"","region":"","costs_rent_comment":"","space_comment_unclear":false,"space_units":"м²","space_units_unclear":false,"costs_rent":""}],"25":[{"costs":"","costs_comment":"","address_hidden":false,"region_hidden":true,"space_comment":"","space":"79","address":"","region":"","address_unclear":false,"costs_rent_comment":"","space_units":"м²","costs_rent":""}]},"intro":{"declaration_year":"2015"}}