{"income":{"5":{"value":"327786","family_comment":"","value_unclear":false,"family_hidden":false,"value_hidden":false,"family_unclear":false,"comment_unclear":false,"comment":"","family":"31915"},"6":{"value":"273368","family_unclear":false,"family_hidden":false,"family_comment":"","family":"","comment":""},"7":{"value":"6312","family_hidden":false,"value_hidden":false,"family_comment":"","source_name":"","family":"","comment":""},"8":{"family_comment":"","value":"","family":"","comment":""},"9":{"family_comment":"","value":"100","value_unclear":false,"family":"","comment":""},"10":{"family_comment":"","family_unclear":false,"value":"12617","family":"","comment":""},"11":{"family_comment":"","value":"","family":"","comment":""},"12":{"family_comment":"","value":"","family":"","comment":""},"13":{"family_comment":"","value":"","family":"","comment":""},"14":{"family_comment":"","value":"","family":"","comment":""},"15":{"family_comment":"","value":"","family":"","comment":""},"16":{"family_comment":"","value":"","family":"","comment":""},"17":{"family_comment":"","value":"","family":"","comment":""},"18":{"family_comment":"","value":"","family":"","comment":""},"19":{"family_comment":"","value":"","family":"","comment":""},"20":{"value":"35389","value_unclear":false,"family_comment":"","comment_unclear":false,"comment":"","family":"31915"}},"vehicle":{"40":[{"brand_info":"1598 куб.см.","sum":"","brand":"Toyota Corolla","sum_comment":"","brand_unclear":false,"year":"2008","brand_info_hidden":false,"brand_info_unclear":false,"sum_rent_comment":"","sum_rent":""}]},"id":"vulyk_71_40","banks":{"45":[{"sum_foreign_comment":"","sum_units":"UAH","sum_comment":"","sum_comment_unclear":false,"sum_foreign_units":"UAH","sum_comment_hidden":false,"sum":"2100","sum_foreign":""}],"46":[{"sum_foreign_comment":"","sum_units":"UAH","sum_comment":"","sum_comment_unclear":false,"sum_hidden":false,"sum_foreign_units":"UAH","sum_comment_hidden":false,"sum_unclear":false,"sum":"700","sum_foreign":""}]},"declaration":{"additional_info_text":"","notfull_lostpages":"","date":"2014-03-28T00:00:00","notfull":"","additional_info":"","url":"http://static.declarations.com.ua/declarations/chosen_ones/judges_batch/595_ponomarova_olha_mykhailivna.pdf"},"liabilities":{"54":{"sum_foreign_comment":"","sum":"","sum_comment":"","sum_comment_unclear":false,"sum_comment_hidden":false,"sum_unclear":false,"sum_foreign":""},"55":{"sum_foreign_comment":"","sum":"","sum_comment":"","sum_foreign":""},"56":{"sum_foreign_comment":"","sum":"","sum_comment":"","sum_comment_unclear":false,"sum_unclear":false,"sum_foreign":""},"57":{"sum_foreign_comment":"","sum":"","sum_comment":"","sum_comment_hidden":false,"sum_unclear":false,"sum_foreign":""},"58":{"sum_foreign_comment":"","sum":"","sum_comment":"","sum_comment_hidden":false,"sum_unclear":false,"sum_foreign":""},"59":{"sum_foreign_comment":"","sum_comment_hidden":false,"sum":"","sum_comment":"","sum_foreign":""},"60":{"sum_foreign_comment":"","sum_comment_hidden":false,"sum":"6092","sum_comment":"","sum_foreign":""},"61":{"sum_foreign_comment":"","sum":"","sum_comment":"","sum_foreign":""},"62":{"sum_foreign_comment":"","sum":"","sum_comment":"","sum_foreign":""},"63":{"sum_foreign_comment":"","sum":"","sum_comment":"","sum_unclear":false,"sum_foreign":""},"64":{"sum_foreign_comment":"","sum":"","sum_comment":"","sum_unclear":false,"sum_foreign":""}},"ft_src":"6092\nсуддя апеляційного суду донецької області\nДонецька область\nЗагальний апеляційний суд\nОльга\nПономарьов В. В\nПодружжя\nЛукіна Г. П\nБатьки\nМихайлівна\nПономарьова Ольга Михайлівна\nОльга Михайлівна Пономарьова\nОльга Пономарьова\nПономарьова Ольга Михайлівна\nПономарьова Ольга Михайлівна\nПономарьова\n1598 куб.см.\nToyota Corolla\n2008\n63.72\n35\nприватизована в 1993 році на 3 членів родини\n63.72\n700\n2100\n2013\n1598 куб.см.\n2008\nToyota Corolla\n35\n63.72\n63.72\nприватизована в 1993 році на 3 членів родини\nПодружжя\nПономарьов В. В\nБатьки\nЛукіна Г. П\nПономарьова Ольга Михайлівна\nОльга Михайлівна Пономарьова\nОльга Пономарьова\nПономарьова Ольга Михайлівна\nПономарьова Ольга Михайлівна\nОльга\nМихайлівна\nЗагальний апеляційний суд\nДонецька область\nсуддя апеляційного суду донецької області\nПономарьова\n6092\n6312\n273368\n35389\n31915\n327786\n31915\n100\n12617\n2100\n700\n2013\n6092\n273368\n100\n12617\n6312\n31915\n327786\n31915\n35389\nПономарьов В. В\nПодружжя\nЛукіна Г. П\nБатьки\nМихайлівна\nПономарьова\nОльга\nПономарьова Ольга Михайлівна\nОльга Михайлівна Пономарьова\nОльга Пономарьова\nПономарьова Ольга Михайлівна\nДонецька область\nЗагальний апеляційний суд\nсуддя апеляційного суду донецької області\nПономарьова Ольга Михайлівна\nToyota Corolla\n1598 куб.см.\n2008\n100\n12617\n35389\n31915\n327786\n31915\n6312\n273368\n63.72\n63.72\nприватизована в 1993 році на 3 членів родини\n35\n2100\n700\n2013","general":{"inn":"","name":"Ольга","family":[{"inn":"","inn_hidden":true,"relations_hidden":false,"family_name":"Пономарьов В. В","relations_other":"","relations":"Подружжя","name_hidden":true,"name_unclear":false},{"inn":"","inn_hidden":false,"relations_hidden":false,"family_name":"Лукіна Г. П","relations_other":"","relations":"Батьки","name_hidden":false,"name_unclear":false}],"patronymic":"Михайлівна","inn_hidden":true,"family_raw":"","inn_unclear":false,"post":{"post_unclear":false,"region_unclear":false,"post":"суддя апеляційного суду донецької області","office":"Загальний апеляційний суд","region":"Донецька область","post_hidden":false,"office_unclear":false},"full_name_suggest":{"output":"Пономарьова Ольга Михайлівна","input":["Пономарьова Ольга Михайлівна","Ольга Михайлівна Пономарьова","Ольга Пономарьова"]},"full_name":"Пономарьова Ольга Михайлівна","addresses":[{"place_district":"","place_unclear":false,"place_city":"","place_city_type_hidden":false,"place_district_hidden":false,"place_city_type":"","place_city_hidden":true,"place_address_hidden":true,"place_address":"","place_hidden":true,"place":""}],"last_name":"Пономарьова","patronymic_hidden":false,"last_name_unclear":false,"name_unclear":false},"source":"VULYK","estate":{"25":[{"region_unclear":false,"space_unclear":false,"costs":"","costs_rent_unclear":false,"costs_comment":"","costs_hidden":false,"address_hidden":true,"region_hidden":true,"space_comment":"приватизована в 1993 році на 3 членів родини","space_hidden":false,"space":"63.72","address":"","costs_unclear":false,"region":"","address_unclear":false,"costs_rent_comment":"","costs_rent_hidden":false,"space_comment_unclear":false,"space_units":"м²","costs_rent":""}],"27":[{"space_unclear":false,"costs":"","costs_comment":"","costs_hidden":false,"address_hidden":true,"region_hidden":true,"space_comment":"","space":"35","address":"","region":"","costs_rent_comment":"","costs_comment_hidden":false,"space_units":"м²","costs_rent":""}],"31":[{"space_hidden":false,"costs_property_comment":"","address_hidden":true,"region_hidden":true,"space_comment":"","space":"63.72","address":"","region":"","costs_property":"","costs_rent_comment":"","space_comment_unclear":false,"space_units":"м²","space_units_hidden":false,"costs_rent":""}]},"intro":{"declaration_year":"2013","isnotdeclaration":""}}