{"income":{"5":{"family_comment":"","value":"181215","family":"47702","comment":""},"6":{"value":"169035","comment_hidden":false,"family_comment":"","family":"47702","comment":"","family_comment_hidden":false},"7":{"value":"","comment_unclear":false,"family_comment":"","source_name":"","family":"","comment":""},"8":{"family_comment":"","value":"","family":"","comment":""},"9":{"family_comment":"","value":"","family":"","comment":""},"10":{"family_comment":"","value":"12180","family_hidden":false,"comment":"","family":""},"11":{"family_comment":"","value":"","family":"","comment":""},"12":{"family_comment":"","value":"","family":"","comment":""},"13":{"family_comment":"","value":"","family":"","comment":""},"14":{"family_comment":"","value":"","family":"","comment":""},"15":{"family_comment":"","value":"","family":"","comment":""},"16":{"family_comment":"","value":"","family":"","comment":""},"17":{"family_comment":"","value":"","family":"","comment":""},"18":{"family_comment":"","value":"","family":"","comment":""},"19":{"family_comment":"","value":"","family":"","comment":""},"20":{"value":"","value_unclear":false,"family_hidden":false,"family_comment":"","family":"","comment":""}},"vehicle":{"40":[{"brand_info":"1390 куб. см.","sum_rent_comment":"","brand":"Skoda Roomster","sum_comment":"","year":"2012","brand_info_unclear":false,"sum":"","sum_rent":""}]},"id":"vulyk_83_57","declaration":{"additional_info_text":"","notfull_lostpages":"","date":"2015-03-25T00:00:00","notfull":"","additional_info":"","url":"http://static.declarations.com.ua/declarations/chosen_ones/judges_batch/2327_bohdanova_olena_eduardivna.pdf"},"liabilities":{"54":{"sum_foreign_comment":"","sum":"","sum_comment":"","sum_foreign":""},"55":{"sum_foreign_comment":"","sum":"","sum_comment":"","sum_foreign":""},"56":{"sum_foreign_comment":"","sum":"5853","sum_comment":"","sum_foreign":""},"57":{"sum_foreign_comment":"","sum":"","sum_comment":"","sum_foreign":""},"58":{"sum_foreign_comment":"","sum":"","sum_comment":"","sum_foreign":""},"59":{"sum_foreign_comment":"","sum":"","sum_comment":"","sum_foreign":""},"60":{"sum_foreign_comment":"","sum":"","sum_comment":"","sum_foreign":""},"61":{"sum_foreign_comment":"","sum":"","sum_comment":"","sum_foreign":""},"62":{"sum_foreign_comment":"","sum":"5240","sum_comment":"","sum_foreign":""},"63":{"sum_foreign_comment":"","sum":"","sum_comment":"","sum_foreign":""},"64":{"sum_foreign_comment":"","sum":"","sum_comment":"","sum_foreign":""}},"ft_src":"5240\n5853\nсуддя знам'янського міськрайонного суду кіровоградської області\nКіровоградська область\nЗагальний місцевий суд\nОлена\nБогданов О. М\nПодружжя\nБогданов В. О\nДитина\nЕдуардівна\nБогданова Олена Едуардівна\nОлена Едуардівна Богданова\nОлена Богданова\nБогданова Олена Едуардівна\nБогданова Олена Едуардівна\nБогданова\n1390 куб. см.\n2012\nSkoda Roomster\n65.15\n2014\n47702\n169035\n12180\n47702\n181215\n1390 куб. см.\n2012\nSkoda Roomster\n65.15\nПодружжя\nБогданов О. М\nДитина\nБогданов В. О\nБогданова Олена Едуардівна\nОлена Едуардівна Богданова\nОлена Богданова\nБогданова Олена Едуардівна\nБогданова Олена Едуардівна\nОлена\nЕдуардівна\nЗагальний місцевий суд\nКіровоградська область\nсуддя знам'янського міськрайонного суду кіровоградської області\nБогданова\n5853\n5240\n169035\n47702\n181215\n47702\n12180\n2014\n5853\n5240\nБогданов О. М\nПодружжя\nБогданов В. О\nДитина\nЕдуардівна\nБогданова\nОлена\nБогданова Олена Едуардівна\nОлена Едуардівна Богданова\nОлена Богданова\nБогданова Олена Едуардівна\nКіровоградська область\nЗагальний місцевий суд\nсуддя знам'янського міськрайонного суду кіровоградської області\nБогданова Олена Едуардівна\n2012\n1390 куб. см.\nSkoda Roomster\n12180\n47702\n181215\n169035\n47702\n65.15\n2014","general":{"inn":"","name":"Олена","inn_unclear":false,"family":[{"inn":"","inn_hidden":true,"relations_hidden":false,"family_name":"Богданов О. М","relations_other":"","relations":"Подружжя","name_hidden":false,"name_unclear":false},{"inn":"","relations":"Дитина","relations_other":"","inn_hidden":true,"family_name":"Богданов В. О","name_hidden":false,"name_unclear":false}],"inn_hidden":true,"family_raw":"","last_name":"Богданова","post":{"post_unclear":false,"post":"суддя знам'янського міськрайонного суду кіровоградської області","candidate":"","region":"Кіровоградська область","office":"Загальний місцевий суд","office_unclear":false},"full_name_suggest":{"output":"Богданова Олена Едуардівна","input":["Богданова Олена Едуардівна","Олена Едуардівна Богданова","Олена Богданова"]},"full_name":"Богданова Олена Едуардівна","addresses":[{"place_city_type_unclear":false,"place_address":"","place_district_hidden":true,"place_city_type":"","place_address_hidden":true,"place_address_unclear":false,"place_city_type_hidden":true,"place":"","place_district":"","place_city_hidden":true,"place_city":"","place_city_unclear":false,"place_hidden":true}],"patronymic":"Едуардівна","last_name_unclear":false},"source":"VULYK","estate":{"25":[{"region_unclear":false,"space_hidden":false,"costs":"","costs_comment":"","address_hidden":false,"region_hidden":true,"space_comment":"","space_unclear":false,"space":"65.15","address":"","region":"","costs_rent_comment":"","space_comment_unclear":false,"space_units":"м²","costs_rent":""}]},"intro":{"declaration_year":"2014"}}