{"income":{"5":{"value":"186613","family_comment":"","value_unclear":false,"family":"","value_hidden":false,"family_unclear":false,"comment_unclear":false,"comment":"","family_comment_unclear":false},"6":{"value":"168936","family_comment":"","value_unclear":false,"value_hidden":false,"family_unclear":false,"family":"","comment":""},"7":{"source_name_unclear":false,"value":"","value_hidden":false,"family_comment":"","source_name":"","family":"","comment":"","source_name_hidden":false},"8":{"family_comment":"","value":"","family":"","comment":""},"9":{"family_comment":"","value":"5497","value_unclear":false,"family":"","comment":""},"10":{"family_comment":"","value":"12180","family":"","comment":""},"11":{"family_comment":"","value":"","family":"","comment":""},"12":{"family_comment":"","value":"","family":"","comment":""},"13":{"family_comment":"","value":"","family":"","comment":""},"14":{"family_comment":"","value":"","family":"","comment":""},"15":{"family_comment":"","value":"","family":"","comment":""},"16":{"family_comment":"","value":"","family":"","comment":""},"17":{"family_comment":"","value":"","family":"","comment":""},"18":{"family_comment":"","value":"","family":"","comment":""},"19":{"family_comment":"","value":"","family":"","comment":""},"20":{"value":"","value_unclear":false,"family_comment":"","family":"","comment":"","family_comment_unclear":false}},"id":"vulyk_26_136","banks":{"45":[{"sum_foreign_comment":"","sum_units":"UAH","sum_comment":"","sum_comment_unclear":false,"sum_hidden":false,"sum_foreign_units":"UAH","sum_comment_hidden":false,"sum_unclear":false,"sum":"43983","sum_foreign":""},{"sum_foreign_comment":"","sum_units":"","sum_comment":"","sum_comment_unclear":false,"sum_foreign_units":"","sum":"","sum_foreign":""},{"sum_foreign_comment":"","sum_units":"","sum_comment":"","sum_foreign_units":"","sum":"","sum_foreign":""},{"sum_foreign_comment":"","sum_units":"","sum_comment":"","sum_foreign_units":"","sum":"","sum_foreign":""},{"sum_foreign_comment":"","sum":"","sum_comment":"","sum_foreign":""}],"46":[{"sum_foreign_comment":"","sum_units":"UAH","sum_comment":"","sum_comment_unclear":false,"sum_foreign_units":"UAH","sum_comment_hidden":false,"sum_unclear":false,"sum":"","sum_foreign":""},{"sum_foreign_comment":"","sum_units":"","sum_comment":"","sum_foreign_units":"","sum":"","sum_foreign":""}],"47":[{"sum_foreign_comment":"","sum_units":"UAH","sum_comment":"","sum_comment_unclear":false,"sum_hidden":false,"sum_foreign_units":"UAH","sum":"327","sum_foreign":""}],"48":[{"sum_foreign_comment":"","sum_units":"UAH","sum_comment":"","sum_comment_unclear":false,"sum_hidden":false,"sum_foreign_units":"UAH","sum":"","sum_unclear":false,"sum_foreign":""}],"49":[{"sum_foreign_comment":"","sum_units":"UAH","sum_comment":"","sum_hidden":false,"sum_foreign_units":"UAH","sum":"","sum_foreign_hidden":false,"sum_foreign":""}],"50":[{"sum_foreign_comment":"","sum_units":"UAH","sum_comment":"","sum_foreign_units":"UAH","sum":"","sum_foreign":""}],"51":[{"sum_foreign_comment":"","sum_units":"UAH","sum_comment":"","sum_comment_unclear":false,"sum_hidden":false,"sum_foreign_units":"UAH","sum_comment_hidden":false,"sum":"","sum_foreign":""},{"sum_foreign_comment":"","sum_units":"","sum_comment":"","sum_foreign_units":"","sum":"","sum_foreign":""},{"sum_foreign_comment":"","sum_units":"","sum_comment":"","sum_foreign_units":"","sum":"","sum_foreign":""},{"sum_foreign_comment":"","sum_units":"","sum_comment":"","sum_foreign_units":"","sum":"","sum_foreign":""}],"52":[{"sum_foreign_comment":"","sum_units":"UAH","sum_comment":"","sum_comment_unclear":false,"sum_hidden":false,"sum_foreign_units":"UAH","sum_comment_hidden":false,"sum_unclear":false,"sum":"","sum_foreign":""}],"53":[{"sum_foreign_comment":"","sum_units":"UAH","sum_comment":"","sum_hidden":false,"sum_foreign_units":"UAH","sum_comment_hidden":false,"sum":"","sum_foreign":""},{"sum_foreign_comment":"","sum_units":"","sum_comment":"","sum_foreign_units":"","sum":"","sum_foreign":""},{"sum_foreign_comment":"","sum_units":"","sum_comment":"","sum_foreign_units":"","sum":"","sum_foreign":""},{"sum_foreign_comment":"","sum_units":"","sum_comment":"","sum_foreign_units":"","sum":"","sum_foreign":""},{"sum_foreign_comment":"","sum_units":"","sum_comment":"","sum_foreign_units":"","sum":"","sum_foreign":""}]},"declaration":{"additional_info_text":"","notfull_lostpages":"","date":"2015-03-24T00:00:00","notfull":"","additional_info":"","url":"http://static.declarations.com.ua/declarations/chosen_ones/mega_batch/syvolap_dmytro_serhiiovych.pdf"},"liabilities":{"54":{"sum_foreign_comment":"","sum_foreign_hidden":false,"sum_comment":"","sum_comment_unclear":false,"sum_hidden":false,"sum_comment_hidden":false,"sum":"","sum_foreign":""},"55":{"sum_foreign_comment":"","sum_foreign_hidden":false,"sum_comment":"","sum_hidden":false,"sum":"","sum_foreign":""},"56":{"sum_foreign_comment":"","sum_foreign_hidden":false,"sum_comment":"","sum_hidden":false,"sum":"","sum_foreign":""},"57":{"sum_foreign_comment":"","sum_foreign_hidden":false,"sum_comment":"","sum_comment_unclear":false,"sum_hidden":false,"sum_comment_hidden":false,"sum":"","sum_foreign":""},"58":{"sum_foreign_comment":"","sum_foreign_hidden":false,"sum_comment":"","sum_comment_unclear":false,"sum_hidden":false,"sum_comment_hidden":false,"sum_unclear":false,"sum":"1033","sum_foreign":""},"59":{"sum_foreign_comment":"","sum_foreign_hidden":false,"sum_comment":"","sum_hidden":false,"sum":"","sum_foreign":""},"60":{"sum_foreign_comment":"","sum":"","sum_comment":"","sum_hidden":false,"sum_comment_hidden":false,"sum_foreign":""},"61":{"sum_foreign_comment":"","sum":"","sum_comment":"","sum_foreign":""},"62":{"sum_foreign_comment":"","sum":"","sum_comment":"","sum_foreign":""},"63":{"sum_foreign_comment":"","sum":"","sum_comment":"","sum_comment_unclear":false,"sum_comment_hidden":false,"sum_foreign":""},"64":{"sum_foreign_comment":"","sum":"","sum_comment":"","sum_comment_unclear":false,"sum_comment_hidden":false,"sum_foreign":""}},"ft_src":"1033\nсуддя шишацького районного суду полтавської області\nПолтавська область\nЗагальний місцевий суд\nДмитро\nПодружжя\nДитина\nСергійович\nСиволап Дмитро Сергійович\nДмитро Сергійович Сиволап\nДмитро Сиволап\nСиволап Дмитро Сергійович\nСиволап\nСиволап Дмитро Сергійович\n12180\n186613\n5497\n168936\n327\n43983\nНа праві користування 1/3 частина у спільній власності (упадкована в 2013 р)\n1325\n1/3 частина у спільній власності (успадковано в 2013 р)\n71.7\nуспадкована в 2013 р\n34.1\n1/4 частина у спільній власності (приватиз. в 2000 Р)\n1/4 частина у спільній власності (приватиз. в 2000 р)\n54\n2014\n168936\n12180\n186613\n5497\n43983\n327\n2014\nСиволап Дмитро Сергійович\nДмитро Сергійович Сиволап\nДмитро Сиволап\nСиволап Дмитро Сергійович\nСиволап Дмитро Сергійович\nПодружжя\nДитина\nДмитро\nСергійович\nПолтавська область\nсуддя шишацького районного суду полтавської області\nЗагальний місцевий суд\nСиволап\n1033\n168936\n186613\n12180\n5497\n1325\nНа праві користування 1/3 частина у спільній власності (упадкована в 2013 р)\n71.7\n1/3 частина у спільній власності (успадковано в 2013 р)\n34.1\nуспадкована в 2013 р\n54\n1/4 частина у спільній власності (приватиз. в 2000 р)\n1/4 частина у спільній власності (приватиз. в 2000 Р)\n1033\nПодружжя\nДитина\nСергійович\nСиволап\nДмитро\nСиволап Дмитро Сергійович\nДмитро Сергійович Сиволап\nДмитро Сиволап\nСиволап Дмитро Сергійович\nсуддя шишацького районного суду полтавської області\nПолтавська область\nЗагальний місцевий суд\nСиволап Дмитро Сергійович\n34.1\nуспадкована в 2013 р\n1/4 частина у спільній власності (приватиз. в 2000 р)\n54\n1/4 частина у спільній власності (приватиз. в 2000 Р)\nНа праві користування 1/3 частина у спільній власності (упадкована в 2013 р)\n1325\n71.7\n1/3 частина у спільній власності (успадковано в 2013 р)\n327\n43983\n2014","general":{"inn":"","name":"Дмитро","family":[{"inn":"","inn_hidden":true,"relations_unclear":false,"relations_hidden":false,"relations_other":"","relations":"Подружжя","name_hidden":true,"family_name":"","name_unclear":false},{"inn":"","relations":"Дитина","relations_other":"","inn_hidden":false,"family_name":"","name_hidden":false,"name_unclear":false}],"patronymic":"Сергійович","inn_hidden":true,"family_raw":"","last_name":"Сиволап","post":{"post_unclear":false,"office":"Загальний місцевий суд","post":"суддя шишацького районного суду полтавської області","office_unclear":false,"region":"Полтавська область"},"last_name_unclear":false,"full_name":"Сиволап Дмитро Сергійович","addresses":[{"place_city_type_unclear":false,"place_address":"","place_district_hidden":true,"place_city_type":"","place_address_hidden":true,"place_address_unclear":false,"place_city_type_hidden":true,"place":"","place_district":"","place_unclear":false,"place_city":"","place_city_unclear":false,"place_hidden":true,"place_city_hidden":true,"place_district_unclear":false}],"patronymic_hidden":false,"full_name_suggest":{"output":"Сиволап Дмитро Сергійович","input":["Сиволап Дмитро Сергійович","Дмитро Сергійович Сиволап","Дмитро Сиволап"]}},"source":"VULYK","estate":{"23":[{"region_unclear":false,"space_unclear":false,"costs":"","costs_comment":"","address_hidden":true,"region_hidden":true,"space_comment":"На праві користування 1/3 частина у спільній власності (упадкована в 2013 р)","space":"1325","address":"","region":"","address_unclear":false,"costs_rent_comment":"","space_comment_hidden":false,"space_units":"м²","costs_rent":""},{"costs":"","costs_comment":"","address_hidden":false,"region_hidden":false,"space_comment":"","space":"","address":"","region":"","costs_rent_comment":"","space_comment_hidden":false,"space_units":"","costs_rent":""},{"costs_rent":"","region":"","costs":"","costs_rent_comment":"","costs_comment":"","address_hidden":false,"region_hidden":false,"space_comment":"","space_units":"","space":"","address":""},{"costs_rent":"","costs":"","costs_rent_comment":"","costs_comment":"","space_comment":"","space_units":"","space":"","address":""},{"costs_rent":"","costs":"","costs_rent_comment":"","costs_comment":"","space_comment":"","space_units":"","space":"","address":""},{"costs_rent":"","costs":"","costs_rent_comment":"","costs_comment":"","space_comment":"","space_units":"","space":"","address":""}],"24":[{"space_unclear":false,"costs":"","costs_rent_unclear":false,"costs_comment":"1/3 частина у спільній власності (успадковано в 2013 р)","address_hidden":true,"region_hidden":true,"space_comment":"","space_hidden":false,"space":"71.7","address":"","region":"","costs_rent_comment":"","space_comment_unclear":false,"space_units":"м²","costs_rent":""}],"25":[{"space_unclear":false,"costs":"","costs_comment":"успадкована в 2013 р","costs_hidden":false,"address_hidden":true,"region_hidden":true,"space_comment":"","space":"34.1","address":"","region":"","address_unclear":false,"costs_rent_comment":"","space_comment_unclear":false,"space_comment_hidden":false,"space_units":"м²","costs_rent":""},{"costs":"","costs_comment":"1/4 частина у спільній власності (приватиз. в 2000 Р)","costs_hidden":false,"address_hidden":false,"region_hidden":false,"space_comment":"1/4 частина у спільній власності (приватиз. в 2000 р)","space":"54","address":"","region":"","costs_rent_comment":"","space_units":"м²","costs_rent":""}]},"intro":{"declaration_year":"2014","isnotdeclaration":""}}