{"id":"vulyk_84_36","ft_src":"ЗАЗ TF69403НГ\n1498 куб. см., 86 к. с., 63 кВт , 423.7 см\n2011\nВАЗ 2107\n1498 куб. см., 68 к. с., 50 кВт ,414.5 см\n1999\n1975 куб. см., 142 к. с., 105.9 кВт , 432.5 см\nHyundai Tucson\n2013\nДніпропетровська область\nм. Дніпропетровськ\n83.1\nДніпропетровська область\nм. Дніпропетровськ\n30.3\nДніпропетровська область\nм. Дніпропетровськ\n83.1\n2014\n44829.81\n168915.81\n5672.15\n12180\n62885\n181195.41\n12383.04\nПенсія за віком\n18. 36 донорство, 81. 24 бонус-плюс КБ Приватбанк\n99.6\n1498 куб. см., 86 к. с., 63 кВт , 423.7 см\nЗАЗ TF69403НГ\n2011\nВАЗ 2107\n1498 куб. см., 68 к. с., 50 кВт ,414.5 см\n1999\n1975 куб. см., 142 к. с., 105.9 кВт , 432.5 см\n2013\nHyundai Tucson\n2014\nТаус Максим Марович\nМаксим Марович Таус\nМаксим Таус\nТаус Максим Марович\nМаксим\nПодружжя\nДитина\nБатьки\nТаус Максим Марович\nМарович\nсуддя ленінського районного суду м. дніпропетровська\nЗагальний місцевий суд\nДніпропетровська область\nТаус\nДніпропетровськ\nДніпропетровська область\n168915.81\n44829.81\n99.6\n12383.04\nПенсія за віком\n18. 36 донорство, 81. 24 бонус-плюс КБ Приватбанк\n181195.41\n62885\n12180\n5672.15\n30.3\nм. Дніпропетровськ\nДніпропетровська область\nм. Дніпропетровськ\nДніпропетровська область\n83.1\n83.1\nДніпропетровська область\nм. Дніпропетровськ\nПодружжя\nДитина\nБатьки\nМарович\nТаус\nМаксим\nТаус Максим Марович\nМаксим Марович Таус\nМаксим Таус\nТаус Максим Марович\nДніпропетровська область\nДніпропетровськ\nДніпропетровська область\nсуддя ленінського районного суду м. дніпропетровська\nЗагальний місцевий суд\nТаус Максим Марович","estate":{"25":[{"address":"м. Дніпропетровськ","space_units":"м²","space_hidden":false,"space_comment":"","region_hidden":false,"costs_comment":"","address_hidden":true,"costs":"","address_unclear":false,"costs_rent_comment_unclear":false,"costs_comment_unclear":false,"costs_rent_comment":"","space":"83.1","region_unclear":false,"region":"Дніпропетровська область","costs_rent":""}],"31":[{"costs_property_comment":"","address":"м. Дніпропетровськ","space_units":"м²","space_unclear":false,"region_hidden":false,"costs_property":"","space_comment":"","address_hidden":true,"address_unclear":false,"costs_rent_comment":"","space":"83.1","region":"Дніпропетровська область","costs_rent":""}],"33":[{"costs_property_comment":"","address":"м. Дніпропетровськ","space_units":"м²","costs_rent_comment":"","space":"30.3","region":"Дніпропетровська область","region_hidden":false,"costs_property":"","space_comment":"","address_hidden":true,"costs_rent":""}]},"vehicle":{"35":[{"year_hidden":false,"brand_info":"1498 куб. см., 86 к. с., 63 кВт , 423.7 см","sum_rent_comment":"","brand_unclear":true,"brand_hidden":false,"year":"2011","brand":"ЗАЗ TF69403НГ","brand_info_hidden":false,"sum_rent":"","year_unclear":false,"sum_comment":"","sum_hidden":false,"brand_info_unclear":false,"sum":""}],"40":[{"sum_comment":"","brand_info_hidden":false,"brand_info":"1498 куб. см., 68 к. с., 50 кВт ,414.5 см","sum":"","brand_unclear":false,"brand_hidden":false,"brand":"ВАЗ 2107","sum_rent":"","sum_rent_comment":"","year":"1999","year_unclear":false},{"sum_comment":"","brand_info_hidden":false,"brand_info":"1975 куб. см., 142 к. с., 105.9 кВт , 432.5 см","sum":"","sum_rent_comment":"","brand_hidden":false,"brand":"Hyundai Tucson","sum_rent":"","brand_info_unclear":false,"year":"2013"}]},"source":"VULYK","income":{"5":{"family_comment":"","family":"62885","comment":"","value_unclear":false,"family_unclear":false,"comment_unclear":false,"value":"181195.41"},"6":{"family_comment":"","comment_unclear":false,"value":"168915.81","family":"44829.81","comment":""},"7":{"family":"","family_comment":"","value":"","comment":"","source_name":""},"8":{"family_comment":"","value":"","family":"","comment":""},"9":{"family_comment":"","value":"","family":"","comment":"","value_unclear":false},"10":{"family_comment":"","value":"12180","family":"5672.15","comment":"","value_unclear":false},"11":{"family_comment":"","value":"","family":"","comment":""},"12":{"family_comment":"","value":"","family":"","comment":""},"13":{"family_comment":"","value":"","family":"","comment":""},"14":{"family_comment":"","value":"","family":"","comment":""},"15":{"family_comment":"","value":"","family":"","comment":""},"16":{"family_comment":"","value":"","family":"","comment":""},"17":{"family_comment":"","value":"","family":"","comment":"","value_unclear":false},"18":{"family_comment":"","value":"","family":"","comment":"","value_unclear":false},"19":{"family_comment":"","value":"","family":"","comment":""},"20":{"family_comment":"Пенсія за віком","family":"12383.04","comment":"18. 36 донорство, 81. 24 бонус-плюс КБ Приватбанк","value_unclear":false,"family_unclear":false,"comment_unclear":true,"value":"99.6"}},"general":{"family_raw":"","name":"Максим","full_name_suggest":{"input":["Таус Максим Марович","Максим Марович Таус","Максим Таус"],"output":"Таус Максим Марович"},"patronymic":"Марович","inn_hidden":true,"addresses":[{"place_city_type_hidden":false,"place_district_hidden":false,"place_address_unclear":false,"place":"Дніпропетровська область","place_city":"Дніпропетровськ","place_unclear":false,"place_city_type_unclear":false,"place_city_type":"Місто","place_city_hidden":false,"place_city_unclear":false,"place_district":"","place_district_unclear":false,"place_address":"","place_address_hidden":true,"place_hidden":false}],"inn":"","inn_unclear":false,"last_name":"Таус","full_name":"Таус Максим Марович","family":[{"inn":"","inn_unclear":false,"family_name":"","relations_other":"","relations_hidden":false,"name_unclear":false,"inn_hidden":true,"name_hidden":true,"relations":"Подружжя"},{"inn":"","family_name":"","relations_other":"","name_unclear":false,"inn_hidden":true,"name_hidden":true,"relations":"Дитина"},{"inn":"","family_name":"","relations_other":"","name_unclear":false,"inn_hidden":true,"name_hidden":true,"relations":"Батьки"}],"post":{"post_hidden":false,"office":"Загальний місцевий суд","region_hidden":false,"post":"суддя ленінського районного суду м. дніпропетровська","candidate":"","region_unclear":false,"region":"Дніпропетровська область","office_hidden":false,"post_unclear":false,"office_unclear":false}},"liabilities":{"54":{"sum_comment":"","sum_foreign_comment":"","sum_foreign":"","sum":"","sum_comment_hidden":false},"55":{"sum_comment":"","sum_foreign_comment":"","sum_foreign":"","sum":""},"56":{"sum_comment":"","sum_foreign_comment":"","sum_foreign":"","sum":""},"57":{"sum_comment":"","sum_foreign_comment":"","sum_foreign":"","sum":"","sum_comment_hidden":false},"58":{"sum_comment":"","sum_foreign_comment":"","sum_foreign":"","sum":"","sum_comment_hidden":false},"59":{"sum_comment":"","sum_foreign_comment":"","sum_foreign":"","sum":""},"60":{"sum_comment":"","sum_foreign_comment":"","sum_foreign":"","sum":""},"61":{"sum_comment":"","sum_foreign_comment":"","sum_foreign":"","sum":""},"62":{"sum_comment":"","sum_foreign_comment":"","sum_foreign":"","sum":""},"63":{"sum_comment":"","sum_foreign_comment":"","sum_foreign":"","sum":"","sum_comment_hidden":false},"64":{"sum_comment":"","sum_foreign_comment":"","sum_foreign":"","sum":"","sum_comment_hidden":false}},"declaration":{"notfull_lostpages":"","additional_info_text":"","additional_info":"","date":"2015-03-11T00:00:00","notfull":"","url":"http://static.declarations.com.ua/declarations/chosen_ones/judges_batch/2450_taus_maksym_marovych.pdf"},"intro":{"isnotdeclaration":"","declaration_year_unclear":false,"declaration_year":"2014"}}