{"id":"vulyk_88_56","ft_src":"Костянтинівський р-н, п. Ст. Райськ\nДонецька область\nДонецька область\nм. Константинівка\n44\nм. Дружківка\nДонецька область\n66.51\nДонецька область\nм. Дружківка\n66.51\nДонецька область\nм. Дружківка\n96\nДонецька область\nм. Дружківка\nКостянтинівський р-н, п. Ст. Райськ\nсоток\n27\nДонецька область\nм. Дружківка\nДонецька область\n2014\n241805\n12180\n15746\n449335\n189350\n3158\n6000\n12588\n44\nм. Константинівка\nДонецька область\nм. Дружківка\nДонецька область\n27\nДонецька область\nсоток\nКостянтинівський р-н, п. Ст. Райськ\nКостянтинівський р-н, п. Ст. Райськ\nДонецька область\n66.51\nм. Дружківка\nДонецька область\n66.51\nДонецька область\nм. Дружківка\n96\nм. Дружківка\nДонецька область\nм. Дружківка\nДонецька область\nМолібога Геннадій Вікторович\nГеннадій Вікторович Молібога\nГеннадій Молібога\nМолібога Геннадій Вікторович\nГеннадій\nПодружжя\nМолібога Т. В. 27. 05. 1963\nМолібога Геннадій Вікторович\nМолібога\nЗагальний місцевий суд\nголова дружківського міського суду донецької області\nДонецька область\nВікторович\nДружківка\nДонецька область\n241805\n12588\n3158\n449335\n15746\n189350\n12180\n6000\n2014\nМолібога Т. В. 27. 05. 1963\nПодружжя\nВікторович\nМолібога\nГеннадій\nМолібога Геннадій Вікторович\nГеннадій Вікторович Молібога\nГеннадій Молібога\nМолібога Геннадій Вікторович\nДонецька область\nДружківка\nДонецька область\nЗагальний місцевий суд\nголова дружківського міського суду донецької області\nМолібога Геннадій Вікторович","estate":{"23":[{"address":"Костянтинівський р-н, п. Ст. Райськ","space_units":"соток","costs_rent_unclear":false,"costs_comment":"","space_unclear":false,"region_hidden":false,"space_comment":"","address_hidden":false,"costs":"","address_unclear":false,"space_comment_unclear":false,"costs_rent_comment":"","space":"27","region":"Донецька область","costs_rent":""}],"24":[{"address":"Костянтинівський р-н, п. Ст. Райськ","space_units":"м²","space_hidden":true,"space_unclear":false,"region_hidden":false,"costs_comment":"","space_comment":"","address_hidden":false,"space":"","costs_rent_comment":"","costs":"","region":"Донецька область","costs_rent":""}],"25":[{"address":"м. Дружківка","space_units":"м²","space_hidden":true,"space_unclear":false,"region_hidden":false,"costs_rent_comment":"","space_comment":"","address_hidden":true,"costs":"","address_unclear":false,"space_comment_unclear":false,"costs_comment":"","space":"","region":"Донецька область","costs_rent":""}],"28":[{"address":"м. Константинівка","space_units":"м²","costs_comment":"","space_comment":"","region_hidden":false,"region":"Донецька область","address_hidden":true,"space":"44","address_unclear":false,"costs_rent_comment":"","costs":"","costs_rent":""}],"31":[{"costs_property_comment":"","address":"м. Дружківка","space_units":"м²","space_unclear":false,"region_hidden":false,"costs_property":"","space_comment":"","address_hidden":true,"costs_rent_comment":"","space":"66.51","region":"Донецька область","costs_rent":""},{"costs_property_comment":"","address":"м. Дружківка","space_units":"м²","costs_rent_comment":"","space":"66.51","region":"Донецька область","costs_property":"","space_comment":"","costs_rent":""}],"34":[{"costs_property_comment":"","address":"м. Дружківка","space_units":"м²","costs_rent_comment":"","space":"96","region":"Донецька область","region_hidden":false,"costs_property":"","space_comment":"","address_hidden":true,"costs_rent":""},{"costs_property_comment":"","address":"м. Дружківка","space_units":"м²","costs_rent_comment":"","space_hidden":true,"region":"Донецька область","region_hidden":false,"costs_property":"","space_comment":"","space":"","costs_rent":""}]},"source":"VULYK","income":{"5":{"family_comment":"","family":"15746","comment":"","value_unclear":false,"family_unclear":false,"value":"449335"},"6":{"family_comment":"","family":"","comment":"","value_unclear":false,"family_unclear":false,"value":"241805"},"7":{"family":"","family_comment":"","value":"","comment":"","source_name":""},"8":{"family_comment":"","value":"","family":"","comment":""},"9":{"family_comment":"","value":"","family":"","comment":"","family_comment_unclear":false},"10":{"family_comment":"","value":"12180","family":"","comment":""},"11":{"family_comment":"","value":"","family":"","comment":""},"12":{"family_comment":"","value":"","family":"","comment":""},"13":{"family_comment":"","value":"","family":"","comment":""},"14":{"family_comment":"","value":"","family":"","comment":""},"15":{"family_comment":"","value":"","family":"","comment":""},"16":{"family_comment":"","value":"189350","family_unclear":false,"family":"","comment":""},"17":{"family_comment":"","value":"","family_unclear":false,"family":"3158","comment":""},"18":{"family_comment":"","value":"","family":"","comment":""},"19":{"family_comment":"","value":"6000","family":"","comment":""},"20":{"family_comment":"","value":"","family":"12588","comment":""}},"general":{"family":[{"inn":"","family_name":"Молібога Т. В. 27. 05. 1963","name_unclear":false,"inn_hidden":false,"name_hidden":false,"relations":"Подружжя"}],"family_raw":"","name":"Геннадій","full_name_suggest":{"input":["Молібога Геннадій Вікторович","Геннадій Вікторович Молібога","Геннадій Молібога"],"output":"Молібога Геннадій Вікторович"},"patronymic":"Вікторович","inn_hidden":true,"patronymic_unclear":false,"patronymic_hidden":false,"inn":"","addresses":[{"place_city_type_hidden":false,"place_city_type":"Місто","place_city_hidden":false,"place_hidden":false,"place_district":"","place_district_hidden":false,"place":"Донецька область","place_address":"","place_address_hidden":true,"place_city":"Дружківка"}],"last_name":"Молібога","full_name":"Молібога Геннадій Вікторович","post":{"office":"Загальний місцевий суд","post":"голова дружківського міського суду донецької області","candidate":"","region_hidden":false,"region":"Донецька область","office_hidden":false},"last_name_unclear":false},"liabilities":{"54":{"sum_comment":"","sum_comment_unclear":false,"sum_foreign_comment":"","sum":"","sum_foreign":""},"55":{"sum_comment":"","sum_foreign_comment":"","sum_foreign":"","sum":""},"56":{"sum_comment":"","sum_foreign_comment":"","sum_foreign":"","sum":""},"57":{"sum_comment":"","sum_hidden":false,"sum":"","sum_foreign_comment":"","sum_foreign":"","sum_unclear":false,"sum_comment_hidden":false},"58":{"sum_comment":"","sum_hidden":false,"sum":"","sum_foreign_comment":"","sum_foreign":"","sum_comment_hidden":false},"59":{"sum_comment":"","sum_foreign_comment":"","sum_foreign":"","sum":""},"60":{"sum_comment_unclear":false,"sum_comment":"","sum_hidden":false,"sum":"","sum_foreign_comment":"","sum_foreign":"","sum_comment_hidden":false},"61":{"sum_comment":"","sum_foreign_comment":"","sum_foreign":"","sum":""},"62":{"sum_comment":"","sum_foreign_comment":"","sum_foreign":"","sum":""},"63":{"sum_comment":"","sum_foreign_comment":"","sum_foreign":"","sum":""},"64":{"sum_comment":"","sum_foreign_comment":"","sum_foreign":"","sum":""}},"declaration":{"notfull_lostpages":"","additional_info_text":"","additional_info":"","date":"2015-03-27T00:00:00","notfull":"","url":"http://static.declarations.com.ua/declarations/chosen_ones/judges_batch/2959_moliboha__hennadii__viktorovych.pdf"},"intro":{"isnotdeclaration":"","declaration_year":"2014"}}