{"id":"vulyk_99_108","ft_src":"2004\nТрактор, 490 кг, 118 кВт , 1990 см\nPolaris\n2009\n120 к. с, 2466 см\nHDV-ROD\n2005\nпричіп\nHarley-Davidson V-Rod\n2001\nToyota Land Cruiser L200\n4200 куб. см. 150 кВт 4940 мм\n2777 куб. см. 177 кВт 4751 мм\n2009\nJeep Wrangler\n2003\n85 к. с. 307 см\nBombardier GTX\nГідроцикл, 130 к. с., 272 см\n2006\nBombardier\nОдеська область\n1/3\nм. Одеса\n81\nм. Одеса\n72\nОдеська область\nм. Одеса\nОдеська область\n149\n2015\n56531.03\n166708.1\n965998.03\n166708.1\n909467\n4200 куб. см. 150 кВт 4940 мм\nToyota Land Cruiser L200\n2001\n2777 куб. см. 177 кВт 4751 мм\n2009\nJeep Wrangler\n85 к. с. 307 см\nBombardier GTX\n2003\nГідроцикл, 130 к. с., 272 см\n2006\nBombardier\nТрактор, 490 кг, 118 кВт , 1990 см\nPolaris\n2004\n120 к. с, 2466 см\nHDV-ROD\n2009\nпричіп\nHarley-Davidson V-Rod\n2005\n2015\nРовинський\nРовинський Олександр Юрійович\nОлександр Юрійович Ровинський\nОлександр Ровинський\nРовинський Олександр Юрійович\nОлександр\nЮрійович\nРовинський Олександр Юрійович\nГосподарський місцевий суд\nсуддя господарського суду одеської області\nОдеська область\nПодружжя\nРовинська К. І\nДитина\nРовинська Л. А\nДитина\nРовинська\n166708.1\n56531.03\n909467\n166708.1\n965998.03\nОдеська область\n72\nм. Одеса\n81\n1/3\nОдеська область\nм. Одеса\n149\nм. Одеса\nОдеська область\nРовинська К. І\nПодружжя\nРовинська Л. А\nДитина\nРовинська\nДитина\nЮрійович\nРовинський\nсуддя господарського суду одеської області\nОдеська область\nГосподарський місцевий суд\nРовинський Олександр Юрійович\nРовинський Олександр Юрійович\nОлександр Юрійович Ровинський\nОлександр Ровинський\nРовинський Олександр Юрійович\nОлександр","estate":{"25":[{"address":"м. Одеса","space_units":"м²","space_hidden":false,"space_unclear":false,"region_hidden":false,"costs_comment":"","space_comment":"","address_hidden":true,"space":"149","costs_rent_comment":"","costs":"","region":"Одеська область","costs_rent":""}],"26":[{"costs":"","address":"м. Одеса","space_units":"м²","costs_rent_comment":"","space":"72","space_comment":"","region_hidden":false,"costs_comment":"","region":"Одеська область","address_hidden":true,"costs_rent":""}],"31":[{"costs_property_comment":"","address":"м. Одеса","space_units":"м²","costs_rent_comment":"","space":"81","region":"Одеська область","region_hidden":true,"costs_property":"","space_comment":"1/3","address_hidden":true,"costs_rent":""}]},"vehicle":{"35":[{"sum_comment":"","brand_info":"4200 куб. см. 150 кВт 4940 мм","brand_unclear":false,"sum_rent_comment":"","year":"2001","brand":"Toyota Land Cruiser L200","sum_rent":"","brand_info_unclear":false,"sum":""},{"sum_comment":"","brand_info":"2777 куб. см. 177 кВт 4751 мм","sum":"","sum_rent_comment":"","year":"2009","brand":"Jeep Wrangler","sum_rent":""}],"37":[{"sum_comment":"","brand_info":"85 к. с. 307 см","sum":"","brand_unclear":true,"year":"2003","brand":"Bombardier GTX","sum_rent":"","sum_rent_comment":""},{"sum_comment":"","brand_info":"Гідроцикл, 130 к. с., 272 см","sum":"","sum_rent_comment":"","year":"2006","brand":"Bombardier","sum_rent":""}],"39":[{"sum_comment":"","brand_info":"Трактор, 490 кг, 118 кВт , 1990 см","sum":"","brand_unclear":false,"year":"2004","brand":"Polaris","sum_rent":"","sum_rent_comment":""},{"sum_comment":"","brand_info":"120 к. с, 2466 см","sum":"","brand_unclear":true,"year":"2009","brand":"HDV-ROD","sum_rent":"","sum_rent_comment":""},{"sum_comment":"","brand_info":"причіп","sum":"","brand_unclear":true,"year":"2005","brand":"Harley-Davidson V-Rod","sum_rent":"","sum_rent_comment":""}]},"source":"VULYK","income":{"5":{"family_comment":"","family":"965998.03","comment":"","value_unclear":false,"family_unclear":false,"value":"166708.1"},"6":{"family_comment":"","family":"56531.03","comment":"","value_unclear":false,"family_unclear":false,"value":"166708.1"},"7":{"family":"","family_comment":"","value":"","comment":"","source_name":""},"8":{"family_comment":"","value":"","family":"","comment":""},"9":{"family_comment":"","value":"","family":"","comment":""},"10":{"family_comment":"","value":"","family":"","comment":""},"11":{"family_comment":"","value":"","family":"","comment":""},"12":{"family_comment":"","value":"","family":"","comment":""},"13":{"family_comment":"","value":"","family":"","comment":""},"14":{"family_comment":"","value":"","family":"","comment":""},"15":{"family_comment":"","value":"","family":"","comment":"","value_unclear":false},"16":{"family_comment":"","value":"","family":"","comment":""},"17":{"family_comment":"","value":"","family":"909467","comment":""},"18":{"family_comment":"","value":"","family":"","comment":""},"19":{"family_comment":"","value":"","family":"","comment":""},"20":{"family_comment":"","family":"","comment":"","value_unclear":false,"family_unclear":false,"value":"","family_comment_unclear":false}},"general":{"inn":"","addresses":[{"place_city_type_hidden":false,"place_city_type":"","place_city_hidden":false,"place_hidden":true,"place_district":"","place_district_hidden":false,"place":"","place_address":"","place_address_hidden":true,"place_city":""}],"last_name":"Ровинський","full_name":"Ровинський Олександр Юрійович","family":[{"inn":"","family_name":"Ровинська К. І","name_unclear":false,"inn_hidden":true,"name_hidden":true,"relations":"Подружжя"},{"inn":"","family_name":"Ровинська Л. А","relations_other":"","name_unclear":true,"inn_hidden":true,"relations":"Дитина"},{"inn":"","family_name":"Ровинська","relations_other":"","name_unclear":true,"inn_hidden":true,"name_hidden":true,"relations":"Дитина"}],"patronymic":"Юрійович","inn_hidden":true,"name":"Олександр","post":{"office":"Господарський місцевий суд","region":"Одеська область","post_unclear":false,"post":"суддя господарського суду одеської області"},"family_raw":"","full_name_suggest":{"input":["Ровинський Олександр Юрійович","Олександр Юрійович Ровинський","Олександр Ровинський"],"output":"Ровинський Олександр Юрійович"}},"liabilities":{"54":{"sum_comment_unclear":false,"sum_comment":"","sum":"","sum_foreign_comment":"","sum_foreign":"","sum_comment_hidden":false},"55":{"sum_comment":"","sum_foreign_comment":"","sum_foreign":"","sum":""},"56":{"sum_comment":"","sum_foreign_comment":"","sum_foreign":"","sum":""},"57":{"sum_comment":"","sum_foreign_comment":"","sum_foreign":"","sum":"","sum_comment_hidden":false},"58":{"sum_comment":"","sum_foreign_comment":"","sum_foreign":"","sum":"","sum_comment_hidden":false},"59":{"sum_comment":"","sum":"","sum_foreign_comment":"","sum_foreign":"","sum_unclear":false,"sum_comment_hidden":false},"60":{"sum_comment":"","sum_foreign_comment":"","sum_foreign":"","sum":"","sum_comment_hidden":false},"61":{"sum_comment":"","sum_foreign_comment":"","sum_foreign":"","sum":""},"62":{"sum_comment":"","sum_foreign_comment":"","sum_foreign":"","sum":""},"63":{"sum_comment":"","sum_foreign_comment":"","sum_foreign":"","sum":"","sum_comment_hidden":false},"64":{"sum_comment":"","sum_foreign_comment":"","sum_foreign":"","sum":"","sum_comment_hidden":false}},"declaration":{"notfull_lostpages":"","date":"2016-03-24T00:00:00","notfull":"","url":"http://static.declarations.com.ua/declarations/chosen_ones/judges_batch/657_rovynskyi_oleksandr_iuriiovych_2015.pdf"},"intro":{"declaration_year":"2015"}}