{"income":{"5":{"family_comment":"","value":"279010.16","value_unclear":false,"family":"8861.5","comment":""},"6":{"value":"279010.16","value_unclear":false,"family_hidden":false,"family_comment":"","family":"8861.5","comment":""},"7":{"source_name_unclear":false,"value":"","family_comment":"","source_name":"","family":"","comment":""},"8":{"family_comment":"","value":"","family":"","comment":""},"9":{"family_comment":"","value":"","family":"","comment":""},"10":{"family_comment":"","value":"","family":"","comment":""},"11":{"family_comment":"","value":"","comment_unclear":false,"family":"","comment":""},"12":{"family_comment":"","value":"","family":"","comment":""},"13":{"family_comment":"","value":"","family":"","comment":""},"14":{"family_comment":"","value":"","family":"","comment":""},"15":{"family_comment":"","value":"","family":"","comment":""},"16":{"family_comment":"","value":"","family":"","comment":""},"17":{"family_comment":"","value":"","family":"","comment":""},"18":{"family_comment":"","value":"","family":"","comment":""},"19":{"family_comment":"","value":"","family":"","comment":""},"20":{"value":"","family_comment":"","value_unclear":false,"family_unclear":false,"comment_unclear":false,"comment":"","family":""}},"vehicle":{"35":[{"brand_info":"1.6","sum_rent_comment":"","brand":"Citroen C4","sum_comment":"","brand_unclear":false,"year":"2007","sum_rent_unclear":false,"brand_info_hidden":false,"brand_info_unclear":false,"sum":"124000","sum_rent":""}],"40":[{"brand_info":"3.5","sum_rent_comment":"","brand":"Lexus RX 350","sum_comment":"","year":"2007","brand_hidden":false,"brand_info_hidden":false,"brand_info_unclear":false,"sum":"","sum_rent":""}]},"id":"vulyk_101_194","declaration":{"additional_info_text":"","notfull_lostpages":"","date":"2016-01-19T00:00:00","notfull":"","additional_info":"","url":"http://static.declarations.com.ua/declarations/chosen_ones/judges_batch/909_mikhiienkova_tamara_leonidivna_2015.pdf"},"liabilities":{"54":{"sum_foreign_comment":"","sum":"","sum_comment":"","sum_comment_unclear":false,"sum_hidden":false,"sum_comment_hidden":false,"sum_unclear":false,"sum_foreign":""},"55":{"sum_foreign_comment":"","sum":"","sum_comment":"","sum_foreign":""},"56":{"sum_foreign_comment":"","sum":"","sum_comment":"","sum_comment_hidden":false,"sum_unclear":false,"sum_foreign":""},"57":{"sum_foreign_comment":"","sum":"70476.46","sum_comment":"Погашення основної суми кредиту, дві суми 63000 та 7476,46","sum_hidden":false,"sum_comment_hidden":false,"sum_unclear":false,"sum_foreign":""},"58":{"sum_foreign_comment":"","sum":"","sum_comment":"","sum_comment_unclear":false,"sum_hidden":false,"sum_comment_hidden":false,"sum_unclear":false,"sum_foreign":""},"59":{"sum_foreign_comment":"","sum":"","sum_comment":"","sum_foreign":""},"60":{"sum_foreign_comment":"","sum":"","sum_comment":"","sum_hidden":false,"sum_comment_hidden":false,"sum_unclear":false,"sum_foreign":""},"61":{"sum_foreign_comment":"","sum":"","sum_comment":"","sum_foreign":""},"62":{"sum_foreign_comment":"","sum":"","sum_comment":"","sum_comment_unclear":false,"sum_foreign":""},"63":{"sum_foreign_comment":"","sum_comment_hidden":false,"sum":"","sum_comment":"","sum_foreign":""},"64":{"sum_foreign_comment":"","sum_comment_hidden":false,"sum":"","sum_comment":"","sum_foreign":""}},"ft_src":"Погашення основної суми кредиту, дві суми 63000 та 7476,46\n70476.46\nсуддя броварського міськрайонного суду київської області\nКиївська область\nЗагальний місцевий суд\nТамара\nКосенко Ілля Андрійович\nДитина\nЛеонідівна\nМіхієнкова Тамара Леонідівна\nМіхієнкова\nМіхієнкова Тамара Леонідівна\nТамара Леонідівна Міхієнкова\nТамара Міхієнкова\nМіхієнкова Тамара Леонідівна\nCitroen C4\n1.6\n2007\n124000\n3.5\nLexus RX 350\n2007\n1200\n106\n2015\n8861.5\n279010.16\n8861.5\n279010.16\nCitroen C4\n1.6\n2007\n124000\n3.5\n2007\nLexus RX 350\n2015\nДитина\nКосенко Ілля Андрійович\nМіхієнкова Тамара Леонідівна\nТамара Леонідівна Міхієнкова\nТамара Міхієнкова\nМіхієнкова Тамара Леонідівна\nТамара\nМіхієнкова Тамара Леонідівна\nЛеонідівна\nЗагальний місцевий суд\nсуддя броварського міськрайонного суду київської області\nКиївська область\nМіхієнкова\n70476.46\nПогашення основної суми кредиту, дві суми 63000 та 7476,46\n279010.16\n8861.5\n279010.16\n8861.5\n1200\n106\nПогашення основної суми кредиту, дві суми 63000 та 7476,46\n70476.46\nКосенко Ілля Андрійович\nДитина\nТамара\nЛеонідівна\nМіхієнкова\nМіхієнкова Тамара Леонідівна\nТамара Леонідівна Міхієнкова\nТамара Міхієнкова\nМіхієнкова Тамара Леонідівна\nсуддя броварського міськрайонного суду київської області\nЗагальний місцевий суд\nКиївська область\nМіхієнкова Тамара Леонідівна\n124000\n2007\nCitroen C4\n1.6\nLexus RX 350\n3.5\n2007\n8861.5\n279010.16\n279010.16\n8861.5\n106\n1200\n2015","general":{"inn":"","name":"Тамара","inn_unclear":false,"family":[{"inn":"","relations":"Дитина","relations_other":"","inn_hidden":true,"family_name":"Косенко Ілля Андрійович","name_hidden":true,"name_unclear":false}],"inn_hidden":true,"family_raw":"","last_name":"Міхієнкова","post":{"region":"Київська область","region_unclear":false,"post":"суддя броварського міськрайонного суду київської області","office_unclear":false,"office":"Загальний місцевий суд"},"full_name":"Міхієнкова Тамара Леонідівна","addresses":[{"place_district":"","place_city_hidden":true,"place_city":"","place_city_type_hidden":false,"place_district_hidden":false,"place_city_type":"","place_address_hidden":true,"place_address":"","place_hidden":true,"place":""}],"patronymic":"Леонідівна","patronymic_hidden":false,"full_name_suggest":{"output":"Міхієнкова Тамара Леонідівна","input":["Міхієнкова Тамара Леонідівна","Тамара Леонідівна Міхієнкова","Тамара Міхієнкова"]}},"source":"VULYK","estate":{"23":[{"space_unclear":false,"costs":"","costs_comment":"","address_hidden":false,"region_hidden":true,"space_comment":"","space_hidden":false,"space":"1200","address":"","costs_comment_unclear":false,"region":"","space_units_unclear":false,"space_units":"м²","costs_rent":"","costs_rent_comment":""}],"25":[{"space_unclear":false,"costs":"","costs_comment":"","address_hidden":false,"region_hidden":true,"space_comment":"","space_hidden":false,"space":"106","address":"","region":"","costs_rent_comment":"","space_comment_unclear":false,"space_units":"м²","costs_rent":""}]},"intro":{"declaration_year":"2015"}}