{"income":{"5":{"value":"407223.34","family_comment":"","family_hidden":false,"value_hidden":false,"family_unclear":false,"family":"","comment":""},"6":{"value":"258223.34","comment_unclear":false,"family_comment":"","family":"","comment":"","family_comment_unclear":false},"7":{"family_comment":"","value":"","source_name":"","family":"","comment":""},"8":{"family_comment":"","value":"","family":"","comment":""},"9":{"family_comment":"","value":"","family":"","comment":""},"10":{"family_comment":"","value":"","family":"","comment":""},"11":{"family_comment":"","value":"","family":"","comment":"","family_comment_unclear":false},"12":{"family_comment":"","value":"","family":"","comment":""},"13":{"family_comment":"","value":"","family":"","comment":""},"14":{"family_comment":"","value":"","family":"","comment":""},"15":{"family_comment":"","value":"","family":"","comment":""},"16":{"family_comment":"","value":"149000","family":"","comment":""},"17":{"family_comment":"","value":"","family":"","comment":""},"18":{"family_comment":"","value":"","family":"","comment":""},"19":{"family_comment":"","value":"","family":"","comment":"","value_hidden":false},"20":{"family_comment":"","value":"","comment_unclear":false,"family":"","comment":""}},"vehicle":{"35":[{"brand_info":"2982 куб. см., 173 л. с., 478 см, вибув із володіння у зв'язку з викраденням","sum_rent_comment":"","brand":"Toyota Land Cruiser Prado","sum_comment":"","sum_rent_hidden":false,"year":"2012","sum_hidden":false,"brand_info_hidden":false,"brand_info_unclear":false,"sum":"149000","sum_rent":""}]},"id":"vulyk_51_16","banks":{"45":[{"sum_foreign_comment":"","sum_units":"UAH","sum_comment":"","sum_comment_unclear":false,"sum_hidden":false,"sum_foreign_units":"UAH","sum_comment_hidden":false,"sum":"299.23","sum_foreign":""},{"sum_foreign_comment":"","sum_units":"","sum_comment":"","sum_foreign_units":"","sum":"","sum_foreign":""},{"sum_foreign_comment":"","sum_units":"","sum_comment":"","sum_foreign_units":"","sum":"","sum_foreign":""},{"sum_foreign_comment":"","sum_units":"","sum_comment":"","sum_foreign_units":"","sum":"","sum_foreign":""},{"sum_foreign_comment":"","sum_units":"","sum_comment":"","sum_foreign_units":"","sum":"","sum_unclear":false,"sum_foreign":""}],"46":[{"sum_foreign_comment":"","sum_units":"UAH","sum_comment":"","sum_foreign_units":"UAH","sum":"48077.48","sum_foreign":""}],"47":[{"sum_foreign_comment":"","sum_units":"UAH","sum_comment":"","sum_foreign_units":"UAH","sum":"","sum_foreign":""}],"48":[{"sum_foreign_comment":"","sum_units":"UAH","sum_comment":"","sum_foreign_units":"UAH","sum":"","sum_foreign":""}],"49":[{"sum_foreign_comment":"","sum_units":"UAH","sum_comment":"","sum_foreign_units":"UAH","sum":"","sum_foreign":""}],"50":[{"sum_foreign_comment":"","sum_units":"UAH","sum_comment":"","sum_foreign_units":"UAH","sum":"","sum_foreign":""}],"51":[{"sum_foreign_comment":"","sum_units":"UAH","sum_comment":"","sum_foreign_units":"UAH","sum_comment_hidden":false,"sum":"","sum_foreign":""},{"sum_foreign_comment":"","sum_units":"","sum_comment":"","sum_foreign_units":"","sum":"","sum_foreign":""},{"sum_foreign_comment":"","sum_units":"","sum_comment":"","sum_foreign_units":"","sum":"","sum_foreign":""}],"52":[{"sum_foreign_comment":"","sum_units":"UAH","sum_comment":"","sum_foreign_units":"UAH","sum_comment_hidden":false,"sum":"","sum_foreign":""}],"53":[{"sum_foreign_comment":"","sum_units":"UAH","sum_comment":"","sum_foreign_units":"UAH","sum":"","sum_foreign":""}]},"declaration":{"additional_info_text":"","notfull_lostpages":"","date":"2015-09-11T00:00:00","notfull":"","additional_info":"","url":"http://static.declarations.com.ua/declarations/chosen_ones/mega_batch/kulikova_svitlana_vasylivna.pdf"},"liabilities":{"54":{"sum_foreign_comment":"","sum_comment_hidden":false,"sum":"","sum_comment":"","sum_foreign":""},"55":{"sum_foreign_comment":"","sum":"","sum_comment":"","sum_foreign":""},"56":{"sum_foreign_comment":"","sum":"","sum_comment":"","sum_foreign":""},"57":{"sum_foreign_comment":"","sum":"","sum_comment":"","sum_hidden":false,"sum_comment_hidden":false,"sum_foreign":""},"58":{"sum_foreign_comment":"","sum_comment_hidden":false,"sum":"","sum_comment":"","sum_foreign":""},"59":{"sum_foreign_comment":"","sum":"","sum_comment":"","sum_foreign":""},"60":{"sum_foreign_comment":"","sum":"","sum_comment":"","sum_foreign":""},"61":{"sum_foreign_comment":"","sum":"","sum_comment":"","sum_foreign":""},"62":{"sum_foreign_comment":"","sum":"","sum_comment":"","sum_foreign":""},"63":{"sum_foreign_comment":"","sum_comment_hidden":false,"sum":"","sum_comment":"","sum_foreign":""},"64":{"sum_foreign_comment":"","sum":"","sum_comment":"","sum_foreign":""}},"ft_src":"суддя\nм. Київ\nЗагальний місцевий суд\nКулікова Світлана Василівна\nСвітлана\nКулікова В. А\nДитина\nБовкун Е. Є\nДитина\nКулікова Світлана Василівна\nСвітлана Василівна Кулікова\nСвітлана Кулікова\nКулікова Світлана Василівна\nКулікова\nВасилівна\nToyota Land Cruiser Prado\n2982 куб. см., 173 л. с., 478 см, вибув із володіння у зв'язку з викраденням\n2012\n149000\n48077.48\n299.23\n2014\n2982 куб. см., 173 л. с., 478 см, вибув із володіння у зв'язку з викраденням\n149000\n2012\nToyota Land Cruiser Prado\n299.23\n48077.48\n142.1\n93.2\n10/100 частин, спадщина\n322.1\n28,5/100 частин, спадщина\nКулікова\nКулікова Світлана Василівна\nСвітлана Василівна Кулікова\nСвітлана Кулікова\nКулікова Світлана Василівна\nСвітлана\nВасилівна\nДитина\nКулікова В. А\nДитина\nБовкун Е. Є\nКулікова Світлана Василівна\nЗагальний місцевий суд\nсуддя\nм. Київ\n258223.34\n407223.34\n149000\n2014\n142.1\n10/100 частин, спадщина\n93.2\n28,5/100 частин, спадщина\n322.1\nКулікова В. А\nДитина\nБовкун Е. Є\nДитина\nКулікова\nВасилівна\nм. Київ\nЗагальний місцевий суд\nсуддя\nКулікова Світлана Василівна\nКулікова Світлана Василівна\nСвітлана Василівна Кулікова\nСвітлана Кулікова\nКулікова Світлана Василівна\nСвітлана\n258223.34\n407223.34\n149000\n2012\n149000\nToyota Land Cruiser Prado\n2982 куб. см., 173 л. с., 478 см, вибув із володіння у зв'язку з викраденням\n407223.34\n149000\n258223.34\n142.1\n10/100 частин, спадщина\n93.2\n28,5/100 частин, спадщина\n322.1\n48077.48\n299.23\n2014","general":{"inn":"","inn_hidden":true,"last_name":"Кулікова","post":{"post":"суддя","region":"м. Київ","office_hidden":false,"office":"Загальний місцевий суд","office_unclear":false,"region_hidden":false},"name":"Світлана","full_name":"Кулікова Світлана Василівна","family_raw":"","family":[{"inn":"","relations":"Дитина","relations_other":"","inn_hidden":false,"family_name":"Кулікова В. А","name_hidden":false,"name_unclear":false},{"inn":"","inn_hidden":false,"relations_hidden":false,"family_name":"Бовкун Е. Є","relations_other":"","relations":"Дитина","name_hidden":false,"name_unclear":false}],"full_name_suggest":{"output":"Кулікова Світлана Василівна","input":["Кулікова Світлана Василівна","Світлана Василівна Кулікова","Світлана Кулікова"]},"patronymic":"Василівна"},"source":"VULYK","estate":{"23":[{"costs":"","costs_comment":"","costs_hidden":false,"address_hidden":false,"region_hidden":false,"space_comment":"","space":"","address":"","region":"","address_unclear":false,"costs_rent_comment":"","costs_rent_hidden":false,"space_units":"м²","costs_rent":""},{"costs":"","costs_comment":"","costs_hidden":false,"region_hidden":false,"space_comment":"","space":"","address":"","region":"","costs_rent_comment":"","costs_rent_hidden":false,"space_units":"","costs_rent":""},{"space":"","region":"","costs":"","costs_rent_comment":"","costs_comment":"","address_unclear":false,"space_comment":"","space_units":"","costs_rent":"","address":""},{"costs_rent":"","region":"","costs":"","costs_rent_comment":"","costs_comment":"","space_comment":"","space_units":"","space":"","address":""}],"28":[{"region_unclear":false,"costs":"","costs_comment":"","address_hidden":false,"region_hidden":false,"space_comment":"10/100 частин, спадщина","space":"93.2","address":"","region":"","costs_rent_comment":"","space_units":"м²","costs_rent":""},{"costs_rent":"","region":"","costs":"","costs_rent_comment":"","costs_comment":"","space_comment":"28,5/100 частин, спадщина","space_units":"м²","space":"322.1","address":""}],"31":[{"space_hidden":false,"costs_property_hidden":false,"address_hidden":false,"region_hidden":false,"space_comment":"","space_unclear":false,"space":"142.1","address":"","region":"","address_unclear":false,"costs_rent_comment":"","costs_rent_hidden":false,"costs_property":"","space_units":"м²","costs_property_comment":"","costs_rent":""}]},"intro":{"declaration_year":"2014","isnotdeclaration":""}}