{"income":{"5":{"value":"201949","family_comment":"","value_unclear":false,"family_unclear":false,"family":"527349","comment":""},"6":{"value":"201949","family_comment":"","value_unclear":false,"family_unclear":false,"family":"","comment":""},"7":{"family_comment":"","value":"","source_name":"","family":"","comment":""},"8":{"family_comment":"","value":"","family":"","comment":""},"9":{"family_comment":"","value":"","family":"","comment":""},"10":{"family_comment":"","value":"","family":"","comment":""},"11":{"family_comment":"","value":"","family":"","comment":""},"12":{"family_comment":"","value":"","family":"","comment":""},"13":{"family_comment":"","value":"","family":"","comment":""},"14":{"family_comment":"","value":"","family":"","comment":""},"15":{"family_comment":"","value":"","value_unclear":false,"family":"","comment":""},"16":{"family_comment":"","value":"","family":"382864","comment":""},"17":{"family_comment":"","value":"","family":"3600","comment":""},"18":{"family_comment":"","value":"","family":"","comment":""},"19":{"family_comment":"","value":"","family":"","comment":""},"20":{"value":"","family_comment":"","value_unclear":false,"family_unclear":false,"family":"140885","comment":"","family_comment_unclear":false}},"vehicle":{"40":[{"brand_info":"1968 куб. см. 104 кВт","sum":"","brand":"Volkswagen Tiguan","sum_comment":"","brand_unclear":false,"year":"2015","brand_info_hidden":false,"brand_info_unclear":false,"sum_rent_comment":"","sum_rent":""}]},"id":"vulyk_99_109","banks":{"45":[{"sum_foreign_comment":"","sum_units":"UAH","sum_comment":"","sum_foreign_units":"UAH","sum_comment_hidden":true,"sum":"14930","sum_foreign":""}],"46":[{"sum_foreign_comment":"","sum_units":"UAH","sum_comment":"","sum_foreign_units":"UAH","sum_comment_hidden":false,"sum":"22087","sum_foreign":""}]},"declaration":{"date":"2016-03-30T00:00:00","notfull":"","url":"http://static.declarations.com.ua/declarations/chosen_ones/judges_batch/658_roha_nataliia_vasylivna_2015.pdf","notfull_lostpages":""},"liabilities":{"54":{"sum_foreign_comment":"","sum":"","sum_comment":"","sum_comment_unclear":false,"sum_comment_hidden":false,"sum_foreign":""},"55":{"sum_foreign_comment":"","sum":"","sum_comment":"","sum_foreign":""},"56":{"sum_foreign_comment":"","sum":"","sum_comment":"","sum_foreign":""},"57":{"sum_foreign_comment":"","sum_comment_hidden":false,"sum":"","sum_comment":"","sum_foreign":""},"58":{"sum_foreign_comment":"","sum_comment_hidden":false,"sum":"","sum_comment":"","sum_foreign":""},"59":{"sum_foreign_comment":"","sum":"","sum_comment":"","sum_comment_hidden":false,"sum_unclear":false,"sum_foreign":""},"60":{"sum_foreign_comment":"","sum_comment_hidden":false,"sum":"","sum_comment":"","sum_foreign":""},"61":{"sum_foreign_comment":"","sum":"","sum_comment":"","sum_foreign":""},"62":{"sum_foreign_comment":"","sum":"","sum_comment":"","sum_foreign":""},"63":{"sum_foreign_comment":"","sum_comment_hidden":false,"sum":"","sum_comment":"","sum_foreign":""},"64":{"sum_foreign_comment":"","sum_comment_hidden":false,"sum":"","sum_comment":"","sum_foreign":""}},"ft_src":"Рога Наталія Василівна\nсуддя господарського суду одеської області\nОдеська область\nГосподарський місцевий суд\nНаталія\nРога С. І\nПодружжя\nРога Наталія Василівна\nНаталія Василівна Рога\nНаталія Рога\nРога Наталія Василівна\nРога\nВасилівна\n1968 куб. см. 104 кВт\nVolkswagen Tiguan\n2015\n22087\n14930\n2015\n1968 куб. см. 104 кВт\n2015\nVolkswagen Tiguan\n14930\n22087\n200\nОдеська область\nОвідіопольський р-н, с. Молодіжне\n117\nОдеська область\nм. Одеса\nпаркомісце\nОдеська область\nм. Одеса\n14.4\n70.7\nм. Одеса\nОдеська область\nОдеська область\nспадщина\n70.5\n2/3\nм. Одеса\nРога\nРога Наталія Василівна\nНаталія Василівна Рога\nНаталія Рога\nРога Наталія Василівна\nНаталія\nВасилівна\nРога Наталія Василівна\nГосподарський місцевий суд\nсуддя господарського суду одеської області\nОдеська область\nПодружжя\nРога С. І\n201949\n3600\n140885\n201949\n527349\n382864\n2015\nОдеська область\nОвідіопольський р-н, с. Молодіжне\n200\nОдеська область\nм. Одеса\n117\nпаркомісце\nОдеська область\nм. Одеса\n14.4\nм. Одеса\nОдеська область\n70.7\nспадщина\n2/3\nм. Одеса\n70.5\nОдеська область\nРога С. І\nПодружжя\nВасилівна\nРога\nсуддя господарського суду одеської області\nОдеська область\nГосподарський місцевий суд\nРога Наталія Василівна\nРога Наталія Василівна\nНаталія Василівна Рога\nНаталія Рога\nРога Наталія Василівна\nНаталія\n201949\n527349\n201949\n382864\n3600\n140885\nVolkswagen Tiguan\n1968 куб. см. 104 кВт\n2015\n140885\n201949\n527349\n382864\n3600\n201949\nм. Одеса\nОдеська область\n117\nм. Одеса\nОдеська область\n70.7\n2/3\nм. Одеса\nОдеська область\n70.5\nспадщина\nпаркомісце\nм. Одеса\nОдеська область\n14.4\nОвідіопольський р-н, с. Молодіжне\nОдеська область\n200\n14930\n22087\n2015","general":{"inn":"","inn_hidden":true,"last_name":"Рога","post":{"post_unclear":false,"office":"Господарський місцевий суд","post":"суддя господарського суду одеської області","region":"Одеська область"},"name":"Наталія","full_name":"Рога Наталія Василівна","family_raw":"","addresses":[{"place_district":"","place_city_hidden":true,"place_city":"","place_city_type_hidden":false,"place_district_hidden":false,"place_city_type":"","place_address_hidden":true,"place_address":"","place_hidden":true,"place":""}],"family":[{"inn_hidden":true,"inn":"","name_hidden":true,"family_name":"Рога С. І","relations":"Подружжя","name_unclear":false}],"full_name_suggest":{"output":"Рога Наталія Василівна","input":["Рога Наталія Василівна","Наталія Василівна Рога","Наталія Рога"]},"patronymic":"Василівна"},"source":"VULYK","estate":{"25":[{"space_hidden":false,"costs":"","costs_comment":"","address_hidden":true,"region_hidden":true,"space_comment":"","space_unclear":false,"space":"70.7","address":"м. Одеса","region":"Одеська область","costs_rent_comment":"","space_units":"м²","costs_rent":""},{"costs_rent":"","region":"Одеська область","costs":"","costs_rent_comment":"","costs_comment":"спадщина","address_hidden":false,"space_comment":"2/3","space_units":"м²","space":"70.5","address":"м. Одеса"}],"29":[{"costs_rent":"","region":"Одеська область","costs_property":"","costs_rent_comment":"","address_hidden":true,"region_hidden":false,"space_comment":"","costs_property_comment":"","space_units":"м²","space":"200","address":"Овідіопольський р-н, с. Молодіжне"}],"31":[{"costs_rent":"","region":"Одеська область","costs_property":"","costs_rent_comment":"","address_hidden":true,"region_hidden":false,"space_comment":"","costs_property_comment":"","space_units":"м²","space":"117","address":"м. Одеса"}],"34":[{"space_unclear":false,"address_hidden":true,"region_hidden":false,"space_comment":"паркомісце","space_hidden":false,"space":"14.4","address":"м. Одеса","region":"Одеська область","costs_property":"","costs_rent_comment":"","space_units":"м²","costs_property_comment":"","costs_rent":""}]},"intro":{"declaration_year":"2015"}}