{"income":{"5":{"family_comment":"","value":"363264","family_hidden":false,"comment":"","family":"48295"},"6":{"value":"272020","value_unclear":false,"family_hidden":false,"family_comment":"","family":"42831","comment":""},"7":{"family_comment":"","value":"","source_name":"","family":"","comment":""},"8":{"family_comment":"","value":"","family":"","comment":""},"9":{"family_comment":"","value":"10637","value_unclear":false,"family":"5264","comment":""},"10":{"family_comment":"","value":"","value_unclear":false,"family":"","comment":""},"11":{"family_comment":"","value":"","family":"","comment":""},"12":{"family_comment":"","value":"","family":"","comment":""},"13":{"family_comment":"","value":"","family":"","comment":""},"14":{"family_comment":"","value":"","family":"","comment":""},"15":{"family_comment":"","value":"5607","family":"","comment":""},"16":{"family_comment":"","value":"75000","family":"","comment":"","family_comment_hidden":false},"17":{"family_comment":"","value":"","family_hidden":false,"comment":"","family":""},"18":{"family_comment":"","value":"","family":"","comment":""},"19":{"family_comment":"","value":"","family":"","comment":""},"20":{"value":"","value_unclear":false,"family_comment_hidden":false,"family_comment":"","comment_unclear":false,"comment":"","family":"200"}},"vehicle":{"35":[{"year_hidden":false,"brand_info":"1591 куб. см.","sum_rent_comment":"","year":"2007","brand_info_hidden":false,"brand_info_unclear":false,"year_unclear":false,"sum_rent":"","sum":"45500","brand":"Kia Cerato","sum_comment":"","brand_unclear":false,"brand_hidden":false,"sum_unclear":false}]},"id":"vulyk_42_107","banks":{"45":[{"sum_foreign_comment":"","sum_units":"UAH","sum_comment":"","sum_foreign_comment_hidden":false,"sum_hidden":false,"sum_foreign_units":"UAH","sum_foreign_hidden":false,"sum_comment_hidden":false,"sum_unclear":false,"sum":"23494","sum_foreign":""},{"sum_foreign_comment":"","sum_units":"","sum_comment":"","sum_foreign_units":"","sum":"","sum_foreign":""}],"46":[{"sum_foreign_comment":"","sum_units":"UAH","sum_comment":"","sum_hidden":false,"sum_foreign_units":"UAH","sum_comment_hidden":false,"sum_unclear":false,"sum":"","sum_foreign":""}],"47":[{"sum_foreign_comment":"","sum_units":"UAH","sum_comment":"","sum_comment_unclear":false,"sum_hidden":false,"sum_foreign_units":"UAH","sum":"349","sum_foreign":""},{"sum_foreign_comment":"","sum":"","sum_comment":"","sum_foreign":""}],"48":[{"sum_foreign_comment":"","sum_units":"UAH","sum_comment":"","sum_foreign_units":"UAH","sum":"","sum_foreign":""}],"49":[{"sum_foreign_comment":"","sum_units":"UAH","sum_comment":"","sum_foreign_units":"UAH","sum":"","sum_foreign":""}],"50":[{"sum_foreign_comment":"","sum_units":"UAH","sum_comment":"","sum_foreign_units":"UAH","sum":"","sum_foreign":""}],"51":[{"sum_foreign_comment":"","sum_units":"UAH","sum_comment":"","sum_comment_unclear":false,"sum_hidden":false,"sum_foreign_units":"UAH","sum_comment_hidden":false,"sum":"7420","sum_foreign":""},{"sum_foreign_comment":"","sum_units":"","sum_comment":"","sum_hidden":false,"sum_foreign_units":"","sum":"","sum_units_hidden":false,"sum_foreign":""}],"52":[{"sum_foreign_comment":"","sum_units":"UAH","sum_comment":"","sum_comment_unclear":false,"sum_hidden":false,"sum_foreign_units":"UAH","sum":"238","sum_units_hidden":false,"sum_foreign":""}],"53":[{"sum_foreign_comment":"","sum_units":"UAH","sum_comment":"","sum_foreign_units":"UAH","sum":"","sum_foreign":""}]},"declaration":{"additional_info_text":"","notfull_lostpages":"","date":"2015-03-24T00:00:00","notfull":"","additional_info":"","url":"http://static.declarations.com.ua/declarations/chosen_ones/mega_batch/﻿zadvornyi_oleksandr_leonidovych.pdf"},"liabilities":{"54":{"sum_foreign_comment":"","sum":"","sum_comment":"","sum_foreign_comment_hidden":false,"sum_comment_hidden":false,"sum_foreign":""},"55":{"sum_foreign_comment":"","sum":"","sum_comment":"","sum_foreign":""},"56":{"sum_foreign_comment":"","sum":"","sum_comment":"","sum_foreign":""},"57":{"sum_foreign_comment":"","sum":"","sum_comment":"","sum_comment_unclear":false,"sum_comment_hidden":false,"sum_unclear":false,"sum_foreign":""},"58":{"sum_foreign_comment":"","sum":"","sum_comment":"","sum_foreign_unclear":false,"sum_comment_hidden":false,"sum_unclear":false,"sum_foreign":""},"59":{"sum_foreign_comment":"","sum":"","sum_comment":"","sum_foreign":""},"60":{"sum_foreign_comment":"","sum":"","sum_comment":"","sum_comment_unclear":false,"sum_hidden":false,"sum_comment_hidden":false,"sum_foreign":""},"61":{"sum_foreign_comment":"","sum":"","sum_comment":"","sum_foreign":""},"62":{"sum_foreign_comment":"","sum":"","sum_comment":"","sum_hidden":false,"sum_comment_hidden":false,"sum_foreign":""},"63":{"sum_foreign_comment":"","sum":"","sum_comment":"","sum_comment_hidden":false,"sum_unclear":false,"sum_foreign":""},"64":{"sum_foreign_comment":"","sum":"","sum_comment":"","sum_hidden":false,"sum_comment_hidden":false,"sum_foreign":""}},"ft_src":"Хмельницький\nХмельницька область\nсуддя апеляційного суду хмельницької області\nХмельницька область\nЗагальний апеляційний суд\nОлександр\nЗадворна О. В. 11. 09. 1964\nПодружжя\nЗадворний В. О. 03. 06. 1991\nДитина\nЛеонідович\nЗадворний Олександр Леонідович\nОлександр Леонідович Задворний\nОлександр Задворний\nЗадворний Олександр Леонідович\nЗадворний\nЗадворний Олександр Леонідович\n1591 куб. см.\nKia Cerato\n2007\n45500\n349\n7420\n23494\n238\n2014\n1591 куб. см.\n45500\nKia Cerato\n2007\n23494\n7420\n238\n349\n67.1\n1/4\n66.1\n67.1\n2/4 частини\nм. Хмельницький\nХмельницька область\nПодружжя\nЗадворна О. В. 11. 09. 1964\nДитина\nЗадворний В. О. 03. 06. 1991\nЗадворний Олександр Леонідович\nОлександр Леонідович Задворний\nОлександр Задворний\nЗадворний Олександр Леонідович\nЗадворний Олександр Леонідович\nОлександр\nЗадворний\nсуддя апеляційного суду хмельницької області\nЗагальний апеляційний суд\nХмельницька область\nЛеонідович\nХмельницька область\nХмельницький\n272020\n42831\n200\n5607\n363264\n48295\n75000\n10637\n5264\n2014\n1/4\n67.1\n66.1\n2/4 частини\nм. Хмельницький\nХмельницька область\n67.1\nЗадворна О. В. 11. 09. 1964\nПодружжя\nЗадворний В. О. 03. 06. 1991\nДитина\nЛеонідович\nЗадворний\nОлександр\nЗадворний Олександр Леонідович\nОлександр Леонідович Задворний\nОлександр Задворний\nЗадворний Олександр Леонідович\nХмельницька область\nХмельницький\nХмельницька область\nсуддя апеляційного суду хмельницької області\nЗагальний апеляційний суд\nЗадворний Олександр Леонідович\n42831\n272020\n5607\n48295\n363264\n75000\n5264\n10637\n200\nKia Cerato\n45500\n1591 куб. см.\n2007\n5607\n200\n48295\n363264\n75000\n5264\n10637\n272020\n42831\n1/4\n67.1\n66.1\n2/4 частини\nм. Хмельницький\nХмельницька область\n67.1\n349\n23494\n238\n7420\n2014","general":{"inn":"","name":"Олександр","patronymic_unclear":false,"last_name_hidden":false,"family":[{"inn":"","inn_hidden":true,"relations_hidden":false,"family_name":"Задворна О. В. 11. 09. 1964","relations_other":"","relations":"Подружжя","name_hidden":false,"name_unclear":false},{"inn":"","relations":"Дитина","relations_other":"","inn_hidden":true,"family_name":"Задворний В. О. 03. 06. 1991","name_hidden":false,"name_unclear":false}],"patronymic":"Леонідович","inn_hidden":true,"family_raw":"","last_name":"Задворний","post":{"region_unclear":false,"region":"Хмельницька область","post":"суддя апеляційного суду хмельницької області","office":"Загальний апеляційний суд","office_hidden":false,"region_hidden":false},"last_name_unclear":false,"full_name":"Задворний Олександр Леонідович","addresses":[{"place_district":"","place_city_hidden":false,"place_city":"Хмельницький","place_city_type_hidden":false,"place_district_hidden":false,"place_city_type":"Місто","place_address_hidden":true,"place_address":"","place_hidden":false,"place":"Хмельницька область"}],"full_name_suggest":{"output":"Задворний Олександр Леонідович","input":["Задворний Олександр Леонідович","Олександр Леонідович Задворний","Олександр Задворний"]}},"source":"VULYK","estate":{"23":[{"space_unclear":false,"costs":"","costs_comment":"","address_hidden":false,"region_hidden":false,"space_comment":"","space_hidden":false,"space":"","address":"","region":"","address_unclear":false,"space_units_unclear":false,"space_comment_unclear":false,"space_units":"м²","costs_rent":"","costs_rent_comment":""},{"costs":"","costs_comment":"","address_hidden":false,"region_hidden":false,"space_comment":"","space_units_unclear":false,"address":"","space":"","region":"","costs_rent_comment":"","space_units":"","costs_rent":""},{"costs_rent":"","region":"","costs":"","costs_rent_comment":"","costs_comment":"","space_comment":"","space_units":"","space":"","address":""},{"costs_rent":"","region":"","costs":"","costs_rent_comment":"","costs_comment":"","space_comment":"","space_units":"","space":"","address":""},{"costs_rent":"","region":"","costs":"","costs_rent_comment":"","costs_comment":"","space_comment":"","space_units":"","space":"","address":""},{"costs_rent":"","costs":"","costs_rent_comment":"","costs_comment":"","space_comment":"","space_units":"","space":"","address":""}],"25":[{"space_unclear":false,"costs":"","costs_comment":"","address_hidden":true,"region_hidden":false,"space_comment":"2/4 частини","space_hidden":false,"space":"67.1","address":"м. Хмельницький","region":"Хмельницька область","costs_rent_comment":"","space_comment_unclear":false,"space_units":"м²","costs_rent":""}],"30":[{"space_hidden":false,"address_hidden":true,"region_hidden":false,"space_comment":"","space":"","address":"","region":"","costs_property":"","costs_rent_comment":"","space_units":"м²","costs_property_comment":"","costs_rent":""}],"31":[{"space_hidden":false,"address_hidden":false,"region_hidden":true,"space_comment":"1/4","space":"67.1","address":"","region":"","costs_property":"","costs_rent_comment":"","space_units":"м²","costs_property_comment":"","costs_rent":""},{"costs_rent":"","region":"","costs_property":"","costs_rent_comment":"","region_hidden":false,"space_comment":"","costs_property_comment":"","space_units":"м²","space":"66.1","address":""}]},"intro":{"declaration_year":"2014","isnotdeclaration":""}}