{"id":"vulyk_74_69","ft_src":"2995 куб. см.\nAudi A6\n2011\n1900 куб. см.\n2007\nVolkswagen Jetta\nVolkswagen Touareg\n2967 куб. см.\n2010\n2013\n14923\n221786\n12617\n14923\n234403\n2995 куб. см.\nAudi A6\n2011\n1900 куб. см.\nVolkswagen Jetta\n2007\n2967 куб. см.\nVolkswagen Touareg\n2010\n2013\nАпеляційний господарський суд\nм. Київ\nсуддя київського апеляційного господарського суду\nВолодимирович\nКуксов Володимир Володимирович\nВолодимир Володимирович Куксов\nВолодимир Куксов\nКуксов Володимир Володимирович\nВолодимир\nКуксов Володимир Володимирович\nКуксов\nПодружжя\nКуксова Т. А\n14923\n221786\n234403\n14923\n12617\nПодружжя\nКуксова Т. А\nВолодимирович\nКуксов\nм. Київ\nАпеляційний господарський суд\nсуддя київського апеляційного господарського суду\nКуксов Володимир Володимирович\nКуксов Володимир Володимирович\nВолодимир Володимирович Куксов\nВолодимир Куксов\nКуксов Володимир Володимирович\nВолодимир","vehicle":{"35":[{"brand_info":"2995 куб. см.","sum_rent_comment":"","brand_unclear":false,"year":"2011","brand_hidden":false,"sum_comment":"","brand_info_hidden":false,"sum_rent":"","brand":"Audi A6","year_unclear":false,"brand_info_unclear":false,"sum":""},{"sum_comment":"","brand_info":"1900 куб. см.","sum":"","sum_rent_comment":"","year":"2007","brand":"Volkswagen Jetta","sum_rent":"","brand_info_unclear":false}],"40":[{"sum_comment":"","brand_info":"2967 куб. см.","brand_unclear":false,"sum_rent_comment":"","year":"2010","brand":"Volkswagen Touareg","sum_rent":"","brand_info_unclear":false,"year_unclear":false,"sum":""}]},"source":"VULYK","income":{"5":{"family_comment":"","family":"14923","comment":"","family_unclear":false,"family_hidden":false,"value":"234403"},"6":{"family_comment":"","family":"14923","comment":"","value_unclear":false,"family_unclear":false,"family_hidden":false,"value":"221786"},"7":{"source_name_hidden":false,"family_comment":"","family":"","value_hidden":false,"comment":"","family_hidden":false,"value":"","source_name":""},"8":{"family_comment":"","value":"","family":"","comment":""},"9":{"family_comment":"","value":"","family":"","comment":""},"10":{"family_comment":"","value":"12617","family":"","comment":"","value_unclear":false},"11":{"family_comment":"","value":"","family":"","comment":""},"12":{"family_comment":"","value":"","family":"","comment":""},"13":{"family_comment":"","value":"","family":"","comment":""},"14":{"family_comment":"","value":"","family":"","comment":""},"15":{"family_comment":"","value":"","family":"","comment":""},"16":{"family_comment":"","value":"","family":"","comment":""},"17":{"family_comment":"","value":"","family":"","comment":""},"18":{"family_comment":"","value":"","family":"","comment":""},"19":{"family_comment":"","value":"","family":"","comment":""},"20":{"family_comment":"","comment":"","family":"","value_unclear":false,"family_unclear":false,"comment_unclear":false,"value":""}},"general":{"inn":"","addresses":[{"place_city_type_hidden":false,"place_city_type":"","place_city_hidden":false,"place_hidden":true,"place_district":"","place_district_hidden":false,"place":"","place_address":"","place_address_hidden":false,"place_city":""}],"last_name":"Куксов","full_name":"Куксов Володимир Володимирович","family":[{"inn":"","family_name":"Куксова Т. А","relations_other":"","name_unclear":false,"inn_hidden":false,"name_hidden":false,"relations":"Подружжя"}],"patronymic":"Володимирович","inn_hidden":true,"name":"Володимир","post":{"post_hidden":false,"office":"Апеляційний господарський суд","post":"суддя київського апеляційного господарського суду","office_unclear":false,"region_unclear":false,"region":"м. Київ"},"family_raw":"","full_name_suggest":{"input":["Куксов Володимир Володимирович","Володимир Володимирович Куксов","Володимир Куксов"],"output":"Куксов Володимир Володимирович"}},"liabilities":{"54":{"sum_comment_unclear":false,"sum_comment":"","sum":"","sum_foreign_comment":"","sum_foreign":"","sum_comment_hidden":false},"55":{"sum_comment":"","sum_hidden":false,"sum":"","sum_foreign_comment":"","sum_foreign":"","sum_unclear":false},"56":{"sum_comment":"","sum_hidden":false,"sum":"","sum_foreign_comment":"","sum_foreign":"","sum_unclear":false},"57":{"sum_comment_unclear":false,"sum_comment":"","sum":"","sum_foreign_comment":"","sum_foreign":"","sum_comment_hidden":false},"58":{"sum_comment":"","sum_foreign_comment":"","sum_foreign":"","sum":"","sum_comment_hidden":false},"59":{"sum_comment":"","sum_foreign_comment":"","sum_foreign":"","sum":""},"60":{"sum_comment":"","sum_foreign_comment":"","sum_foreign":"","sum_hidden":false,"sum":""},"61":{"sum_comment":"","sum_foreign_comment":"","sum_foreign":"","sum":""},"62":{"sum_comment":"","sum_foreign_comment":"","sum_foreign":"","sum":""},"63":{"sum_comment_unclear":false,"sum_comment":"","sum":"","sum_foreign_comment":"","sum_foreign":"","sum_unclear":false},"64":{"sum_comment_unclear":false,"sum_comment":"","sum":"","sum_foreign_comment":"","sum_foreign":"","sum_unclear":false}},"declaration":{"notfull_lostpages":"","additional_info_text":"","additional_info":"","date":"2014-03-30T00:00:00","notfull":"","url":"http://static.declarations.com.ua/declarations/chosen_ones/judges_batch/1712_kuksov_volodymyr_volodymyrovych.pdf"},"intro":{"isnotdeclaration":"","declaration_year_unclear":false,"declaration_year":"2013"}}