{"income":{"5":{"value":"374344","family_comment":"","value_unclear":false,"family_hidden":false,"value_hidden":false,"family_unclear":false,"family":"56198","comment":"","family_comment_unclear":false},"6":{"value":"273182","family_comment":"","value_unclear":false,"family_hidden":false,"value_hidden":false,"family_unclear":false,"family":"3014","comment":"","family_comment_unclear":false},"7":{"value":"","family_comment":"","source_name":"","family":"","comment":"","source_name_hidden":false},"8":{"value":"","value_unclear":false,"value_hidden":false,"family_comment":"","family":"","comment":""},"9":{"value":"","family_comment":"","comment_unclear":false,"family_unclear":false,"family":"","comment":""},"10":{"value":"5074","family_comment":"","value_unclear":false,"family_hidden":false,"value_hidden":false,"family_unclear":false,"family":"","comment":"путівка на санаторно-курортне лікування"},"11":{"family_comment":"","value":"","family":"","comment":""},"12":{"family_comment":"","value":"","family":"","comment":""},"13":{"family_comment":"","value":"","family":"","comment":""},"14":{"family_comment":"","value":"","family":"","comment":""},"15":{"value":"","family":"","family_hidden":false,"family_comment":"","family_comment_hidden":false,"comment":"","family_comment_unclear":false},"16":{"value":"","family_comment":"","comment_hidden":false,"family_hidden":false,"family_unclear":false,"family_comment_hidden":false,"comment":"","family":""},"17":{"family_comment":"","value":"","family":"","comment":""},"18":{"value":"","family_unclear":false,"family_hidden":false,"family_comment":"","family":"","comment":""},"19":{"family_comment":"","value":"","family":"","comment":""},"20":{"value":"60738","family_comment":"пенсія","value_unclear":false,"family_comment_hidden":false,"family_hidden":false,"value_hidden":false,"family_unclear":false,"family_comment_unclear":false,"comment_unclear":true,"comment":"пенсія та рішення суду","family":"96087"}},"vehicle":{"35":[{"year_hidden":false,"brand_info":"1600 куб. см., 55 кВт","sum_rent_comment":"","brand_info_unclear":false,"sum_rent_hidden":false,"year":"2007","sum_hidden":false,"brand_info_hidden":false,"sum_rent_comment_unclear":false,"year_unclear":false,"sum_rent":"","sum_rent_unclear":false,"sum":"","brand":"Opel Astra","sum_comment":"","brand_unclear":false,"brand_hidden":false},{"brand_info":"2000 куб. см., 105 кВт","sum_rent_comment":"","brand":"Hyundai Tucson","sum_comment":"","brand_unclear":false,"year":"2011","brand_hidden":false,"brand_info_unclear":false,"sum":"","sum_rent":""}],"40":[{"brand_info":"1700 куб. см., 54.8 кВт","sum_rent_comment":"","year":"1994","brand_info_hidden":false,"brand_info_unclear":false,"year_unclear":false,"sum_rent":"","sum":"","brand":"ВАЗ 2121","sum_comment":"","brand_unclear":false,"brand_hidden":false}]},"id":"vulyk_20_65","banks":{"45":[{"sum_units":"UAH","sum_foreign_unclear":false,"sum_hidden":false,"sum_units_hidden":false,"sum":"","sum_foreign":"","sum_foreign_comment":"","sum_foreign_hidden":false,"sum_comment":"","sum_comment_unclear":false,"sum_foreign_units":"UAH","sum_comment_hidden":false,"sum_unclear":false},{"sum_foreign_comment":"","sum_units":"","sum_comment":"","sum_foreign_units":"","sum":"","sum_foreign":""}],"46":[{"sum_foreign_comment":"","sum_units":"UAH","sum_comment":"","sum_hidden":false,"sum_foreign_units":"UAH","sum_comment_hidden":false,"sum_unclear":false,"sum":"","sum_foreign":""}],"47":[{"sum_units":"UAH","sum_foreign_comment_hidden":false,"sum_hidden":false,"sum_foreign_hidden":false,"sum_foreign":"","sum_foreign_comment":"","sum":"","sum_comment":"","sum_comment_unclear":false,"sum_foreign_units":"UAH","sum_units_unclear":false,"sum_comment_hidden":false,"sum_unclear":false},{"sum_foreign_comment":"","sum_units":"","sum_comment":"","sum_foreign_comment_hidden":false,"sum_hidden":false,"sum_foreign_units":"","sum_comment_hidden":false,"sum_foreign_hidden":false,"sum":"","sum_foreign":""}],"48":[{"sum_foreign_comment":"","sum_units":"UAH","sum_comment":"","sum_foreign_units":"UAH","sum":"","sum_foreign":""}],"49":[{"sum_foreign_comment":"","sum_units":"UAH","sum_comment":"","sum_foreign_units":"UAH","sum":"","sum_foreign":""}],"50":[{"sum_foreign_comment":"","sum_units":"UAH","sum_comment":"","sum_foreign_units":"UAH","sum":"","sum_foreign":""}],"51":[{"sum_foreign_comment":"","sum_units":"UAH","sum_comment":"","sum_comment_unclear":false,"sum_hidden":false,"sum_foreign_units":"UAH","sum_comment_hidden":false,"sum_units_hidden":false,"sum":"1000","sum_foreign":""},{"sum_foreign_comment":"","sum_units":"UAH","sum_comment":"","sum_foreign_units":"UAH","sum":"11773","sum_foreign":""}],"52":[{"sum_foreign_comment":"","sum_units":"UAH","sum_comment":"","sum_comment_unclear":false,"sum_hidden":false,"sum_foreign_units":"UAH","sum_comment_hidden":false,"sum_units_hidden":false,"sum":"","sum_foreign":""}],"53":[{"sum_foreign_comment":"","sum_units":"UAH","sum_comment":"","sum_hidden":false,"sum_foreign_units":"UAH","sum_units_unclear":false,"sum":"","sum_unclear":false,"sum_foreign":""}]},"declaration":{"additional_info_text":"","notfull_lostpages":"","date":"2015-03-27T00:00:00","notfull":"","additional_info":"","url":"http://static.declarations.com.ua/declarations/chosen_ones/mega_batch/malakhova_nataliia_marativna.pdf"},"liabilities":{"54":{"sum_foreign_comment":"","sum":"","sum_comment":"","sum_comment_unclear":false,"sum_hidden":false,"sum_comment_hidden":false,"sum_unclear":false,"sum_foreign":""},"55":{"sum_foreign_comment":"","sum":"","sum_comment":"","sum_foreign":""},"56":{"sum_foreign_comment":"","sum":"","sum_comment":"","sum_unclear":false,"sum_foreign":""},"57":{"sum_foreign_comment":"","sum":"","sum_comment":"","sum_hidden":false,"sum_unclear":false,"sum_foreign":""},"58":{"sum_foreign_comment":"","sum":"","sum_comment":"","sum_hidden":false,"sum_unclear":false,"sum_foreign":""},"59":{"sum_foreign_comment":"","sum":"","sum_comment":"","sum_hidden":false,"sum_unclear":false,"sum_foreign":""},"60":{"sum_foreign_comment":"","sum":"","sum_comment":"","sum_comment_unclear":false,"sum_hidden":false,"sum_comment_hidden":false,"sum_unclear":false,"sum_foreign":""},"61":{"sum_foreign_comment":"","sum":"","sum_hidden":false,"sum_comment":"","sum_foreign":""},"62":{"sum_foreign_comment":"","sum":"","sum_comment":"","sum_foreign":""},"63":{"sum_foreign_comment":"","sum":"","sum_hidden":false,"sum_comment":"","sum_foreign":""},"64":{"sum_foreign_comment":"","sum":"","sum_hidden":false,"sum_comment":"","sum_foreign":""}},"ft_src":"Вереси\nЖитомирський\nЖитомирська область\nСело\nзаступник голови житомирського апеляційного адміністративного суду\nЖитомирська область\nАпеляційний адміністративний суд\nНаталія\nМалахов В. Н\nПодружжя\nАзімова Т. М\nБатьки\nМаратівна\nМалахова\nМалахова Наталія Маратівна\nМалахова Наталія Маратівна\nНаталія Маратівна Малахова\nНаталія Малахова\nМалахова Наталія Маратівна\n1600 куб. см., 55 кВт\nOpel Astra\n2007\nHyundai Tucson\n2000 куб. см., 105 кВт\n2011\n1700 куб. см., 54.8 кВт\nВАЗ 2121\n1994\n1000\n11773\n2014\n1600 куб. см., 55 кВт\nOpel Astra\n2007\n2000 куб. см., 105 кВт\n2011\nHyundai Tucson\n1700 куб. см., 54.8 кВт\nВАЗ 2121\n1994\n1000\n11773\n250\n1/4 земельної ділянки\nс. Вереси\nЖитомирська область\n2/4 земельної ділянки\nс. Вереси\n500\nЖитомирська область\n3100\nс. Ігнатпіль\nЖитомирська область\n44.2\n1/4 житлового будинку\nс. Вереси\nЖитомирська область\n88.4\n2/4 житлового будинку\nс. Вереси\nЖитомирська область\nЖитомирська область\n60\nс. Ігнатпіль\n72\n3 гаражі у гаражному кооперативі\nм. Житомир\nЖитомирська область\nАпеляційний адміністративний суд\nЖитомирська область\nзаступник голови житомирського апеляційного адміністративного суду\nПодружжя\nМалахов В. Н\nБатьки\nАзімова Т. М\nМалахова Наталія Маратівна\nНаталія Маратівна Малахова\nНаталія Малахова\nМалахова Наталія Маратівна\nНаталія\nМалахова Наталія Маратівна\nМалахова\nМаратівна\nСело\nВереси\nЖитомирська область\nЖитомирський\n3014\n273182\nпенсія та рішення суду\nпенсія\n60738\n96087\n56198\n374344\nпутівка на санаторно-курортне лікування\n5074\n2014\n3 гаражі у гаражному кооперативі\nм. Житомир\nЖитомирська область\n72\nЖитомирська область\n1/4 земельної ділянки\nс. Вереси\n250\n2/4 житлового будинку\nс. Вереси\nЖитомирська область\n88.4\nЖитомирська область\nс. Ігнатпіль\n60\n2/4 земельної ділянки\nс. Вереси\nЖитомирська область\n500\nс. Ігнатпіль\nЖитомирська область\n3100\n1/4 житлового будинку\nс. Вереси\n44.2\nЖитомирська область\nПодружжя\nМалахов В. Н\nАзімова Т. М\nБатьки\nМаратівна\nМалахова\nМалахова Наталія Маратівна\nНаталія Маратівна Малахова\nНаталія Малахова\nМалахова Наталія Маратівна\nНаталія\nЖитомирська область\nВереси\nЖитомирський\nСело\nЖитомирська область\nАпеляційний адміністративний суд\nзаступник голови житомирського апеляційного адміністративного суду\nМалахова Наталія Маратівна\n3014\n273182\nпутівка на санаторно-курортне лікування\n5074\n56198\n374344\nпенсія\nпенсія та рішення суду\n96087\n60738\nOpel Astra\n1600 куб. см., 55 кВт\n2007\n2011\n2000 куб. см., 105 кВт\nHyundai Tucson\n1994\nВАЗ 2121\n1700 куб. см., 54.8 кВт\n5074\nпутівка на санаторно-курортне лікування\nпенсія та рішення суду\nпенсія\n60738\n96087\n374344\n56198\n273182\n3014\n2/4 житлового будинку\nс. Вереси\nЖитомирська область\n88.4\nс. Ігнатпіль\nЖитомирська область\n60\nЖитомирська область\n1/4 земельної ділянки\nс. Вереси\n250\n1/4 житлового будинку\nс. Вереси\nЖитомирська область\n44.2\n3 гаражі у гаражному кооперативі\nм. Житомир\nЖитомирська область\n72\nЖитомирська область\n2/4 земельної ділянки\nс. Вереси\n500\nс. Ігнатпіль\nЖитомирська область\n3100\n1000\n11773\n2014","general":{"inn":"","name":"Наталія","patronymic_unclear":false,"last_name_hidden":false,"family":[{"inn":"","inn_hidden":true,"relations_unclear":false,"relations_hidden":false,"relations_other":"","relations":"Подружжя","name_hidden":false,"inn_unclear":false,"family_name":"Малахов В. Н","name_unclear":false},{"inn":"","inn_hidden":false,"inn_unclear":false,"relations_hidden":false,"relations_other":"","relations":"Батьки","name_hidden":false,"family_name":"Азімова Т. М","name_unclear":false}],"patronymic":"Маратівна","inn_hidden":true,"family_raw":"","inn_unclear":false,"post":{"post_unclear":false,"region_unclear":false,"post":"заступник голови житомирського апеляційного адміністративного суду","office":"Апеляційний адміністративний суд","region":"Житомирська область","post_hidden":false,"office_hidden":false,"office_unclear":true,"region_hidden":false},"last_name_unclear":false,"full_name":"Малахова Наталія Маратівна","addresses":[{"place_city_type_unclear":false,"place_address":"","place_district_hidden":false,"place_city_type":"Село","place_address_hidden":false,"place_address_unclear":false,"place_city_type_hidden":false,"place":"Житомирська область","place_district":"Житомирський","place_unclear":false,"place_city":"Вереси","place_city_unclear":false,"place_hidden":false,"place_city_hidden":false,"place_district_unclear":false}],"last_name":"Малахова","patronymic_hidden":false,"full_name_suggest":{"output":"Малахова Наталія Маратівна","input":["Малахова Наталія Маратівна","Наталія Маратівна Малахова","Наталія Малахова"]},"name_unclear":false},"source":"VULYK","estate":{"23":[{"region_unclear":false,"space_hidden":false,"costs":"","costs_comment":"","costs_hidden":false,"address_hidden":false,"region_hidden":false,"space_comment":"1/4 земельної ділянки","space_unclear":false,"space_units_unclear":false,"address":"с. Вереси","region":"Житомирська область","space":"250","costs_rent_hidden":false,"space_units":"м²","space_units_hidden":false,"costs_rent":"","costs_rent_comment":""},{"space_unclear":false,"costs":"","costs_comment":"","address_hidden":false,"region_hidden":false,"space_comment":"","space":"","address":"","region":"","costs_rent_comment":"","space_units":"","costs_rent":""},{"costs_rent":"","region":"","costs":"","costs_rent_comment":"","costs_comment":"","address_hidden":false,"space_comment":"","space_units":"","space":"","address":""},{"costs_rent":"","region":"","costs":"","costs_rent_comment":"","costs_comment":"","address_hidden":false,"space_comment":"","space_units":"","space":"","address":""}],"24":[{"space_unclear":false,"costs":"","costs_comment":"","address_hidden":false,"region_hidden":false,"space_comment":"1/4 житлового будинку","space_hidden":false,"space":"44.2","address":"с. Вереси","region":"Житомирська область","space_units_unclear":false,"space_comment_hidden":false,"space_units":"м²","space_units_hidden":false,"costs_rent":"","costs_rent_comment":""}],"29":[{"region_unclear":false,"space_unclear":false,"address_hidden":false,"region_hidden":false,"space_comment":"2/4 земельної ділянки","space_units_hidden":false,"space_hidden":false,"space":"500","address":"с. Вереси","region":"Житомирська область","costs_property":"","space_units_unclear":false,"space_comment_unclear":false,"space_comment_hidden":false,"space_units":"м²","costs_property_comment":"","costs_rent":"","costs_rent_comment":""},{"region_unclear":true,"space_unclear":false,"address_hidden":false,"region_hidden":false,"space_comment":"","space":"3100","address":"с. Ігнатпіль","region":"Житомирська область","costs_property":"","costs_rent_comment":"","address_unclear":true,"space_units":"м²","costs_property_comment":"","costs_rent":""}],"30":[{"region_unclear":false,"space_unclear":false,"costs_property_comment":"","address_hidden":false,"region_hidden":false,"space_comment":"2/4 житлового будинку","space":"88.4","address":"с. Вереси","region":"Житомирська область","costs_property":"","costs_rent_comment":"","space_comment_unclear":false,"space_units":"м²","space_units_unclear":false,"costs_rent":""},{"costs_rent":"","region_unclear":true,"region":"Житомирська область","costs_property":"","costs_rent_comment":"","region_hidden":false,"space_comment":"","costs_property_comment":"","space_units":"м²","space":"60","address":"с. Ігнатпіль"}],"33":[{"region_unclear":false,"address_hidden":false,"region_hidden":false,"space_comment":"3 гаражі у гаражному кооперативі","space":"72","address":"м. Житомир","region":"Житомирська область","costs_property":"","costs_rent_comment":"","space_units":"м²","costs_property_comment":"","costs_rent":""}]},"intro":{"declaration_year":"2014","isnotdeclaration":"","declaration_year_unclear":false,"declaration_year_hidden":false}}