{"income":{"5":{"value":"362389.6","family_comment":"","value_unclear":false,"family_unclear":false,"family":"","comment":""},"6":{"family_comment":"","value":"240971","value_unclear":false,"family":"","comment":""},"7":{"value":"183.7","value_unclear":false,"family_comment":"","source_name":"Національна школа суддів України Одеське регіональне відділення","family":"","comment":""},"8":{"family_comment":"","value":"","family":"","comment":""},"9":{"value":"","family_comment":"","value_unclear":false,"family_unclear":false,"family":"","comment":""},"10":{"family_comment":"","value":"","comment_unclear":false,"family":"","comment":""},"11":{"family_comment":"","value":"","family":"","comment":""},"12":{"family_comment":"","value":"","family":"","comment":""},"13":{"family_comment":"","value":"","value_unclear":false,"family":"","comment":""},"14":{"family_comment":"","value":"","family":"","comment":""},"15":{"family_comment":"","value":"","family":"","comment":""},"16":{"family_comment":"","family_unclear":false,"value":"80000","family":"","comment":""},"17":{"family_comment":"","family_unclear":false,"value":"","family":"","comment":""},"18":{"family_comment":"","value":"","family":"","comment":""},"19":{"family_comment":"","value":"","family":"","comment":""},"20":{"value":"41233.92","family_comment":"","value_unclear":false,"family_hidden":false,"value_hidden":false,"family_unclear":false,"comment_unclear":false,"comment":"","family":""}},"vehicle":{"35":[{"brand_info":"4000 куб. см.","sum_rent_comment":"","brand_info_unclear":false,"year":"2007","brand_info_hidden":false,"sum_rent_comment_unclear":false,"sum_rent":"","sum":"","brand":"Toyota Prado","sum_comment":"","brand_unclear":false,"brand_hidden":false}]},"id":"vulyk_100_133","declaration":{"additional_info_text":"","notfull_lostpages":"","date":"2015-03-27T00:00:00","notfull":"","additional_info":"","url":"http://static.declarations.com.ua/declarations/chosen_ones/judges_batch/4337_pribylov_vadym_mykhailovych.pdf"},"liabilities":{"54":{"sum_foreign_comment":"","sum":"","sum_comment":"","sum_comment_hidden":false,"sum_unclear":false,"sum_foreign":""},"55":{"sum_foreign_comment":"","sum":"","sum_comment":"","sum_foreign":""},"56":{"sum_foreign_comment":"","sum":"26706.28","sum_comment":"","sum_unclear":false,"sum_foreign":""},"57":{"sum_foreign_comment":"","sum":"","sum_comment":"","sum_comment_unclear":false,"sum_comment_hidden":false,"sum_unclear":false,"sum_foreign":""},"58":{"sum_foreign_comment":"","sum":"","sum_comment":"","sum_comment_hidden":false,"sum_unclear":false,"sum_foreign":""},"59":{"sum_foreign_comment":"","sum":"3900","sum_comment":"","sum_foreign":""},"60":{"sum_foreign_comment":"","sum_comment_hidden":false,"sum":"","sum_comment":"","sum_foreign":""},"61":{"sum_foreign_comment":"","sum":"","sum_comment":"","sum_foreign":""},"62":{"sum_foreign_comment":"","sum":"","sum_comment":"","sum_unclear":false,"sum_foreign":""},"63":{"sum_foreign_comment":"","sum_comment_hidden":false,"sum":"","sum_comment":"","sum_foreign":""},"64":{"sum_foreign_comment":"","sum_comment_hidden":false,"sum":"","sum_comment":"","sum_foreign":""}},"ft_src":"3900\n26706.28\nПрібилов Вадим Михайлович\nсуддя апеляційного суду одеської області\nОдеська область\nЗагальний апеляційний суд\nВадим\nПрібилова Н. М\nПодружжя\nПрібилов Вадим Михайлович\nВадим Михайлович Прібилов\nВадим Прібилов\nПрібилов Вадим Михайлович\nПрібилов\nМихайлович\n4000 куб. см.\nToyota Prado\n2007\n125.3\n1000\n2014\n240971\nНаціональна школа суддів України Одеське регіональне відділення\n183.7\n362389.6\n80000\n41233.92\n4000 куб. см.\nToyota Prado\n2007\n1000\n125.3\nПодружжя\nПрібилова Н. М\nМихайлович\nПрібилов\nПрібилов Вадим Михайлович\nВадим Михайлович Прібилов\nВадим Прібилов\nПрібилов Вадим Михайлович\nПрібилов Вадим Михайлович\nВадим\nЗагальний апеляційний суд\nОдеська область\nсуддя апеляційного суду одеської області\n3900\n26706.28\n183.7\nНаціональна школа суддів України Одеське регіональне відділення\n240971\n41233.92\n362389.6\n80000\n2014\n26706.28\n3900\nПрібилова Н. М\nПодружжя\nМихайлович\nПрібилов\nОдеська область\nЗагальний апеляційний суд\nсуддя апеляційного суду одеської області\nПрібилов Вадим Михайлович\nПрібилов Вадим Михайлович\nВадим Михайлович Прібилов\nВадим Прібилов\nПрібилов Вадим Михайлович\nВадим\n2007\nToyota Prado\n4000 куб. см.\n41233.92\n362389.6\n80000\n183.7\nНаціональна школа суддів України Одеське регіональне відділення\n240971\n125.3\n1000\n2014","general":{"inn":"","inn_hidden":true,"last_name":"Прібилов","post":{"post_unclear":false,"region_unclear":false,"post":"суддя апеляційного суду одеської області","office":"Загальний апеляційний суд","region":"Одеська область","post_hidden":false,"office_unclear":false},"name":"Вадим","full_name":"Прібилов Вадим Михайлович","family_raw":"","addresses":[{"place_district":"","place_city_hidden":true,"place_city":"","place_city_unclear":false,"place_district_hidden":false,"place_city_type":"","place_address_hidden":true,"place_city_type_hidden":false,"place_address":"","place_hidden":true,"place":""}],"family":[{"inn_hidden":true,"inn":"","name_hidden":true,"family_name":"Прібилова Н. М","relations":"Подружжя","name_unclear":false}],"full_name_suggest":{"output":"Прібилов Вадим Михайлович","input":["Прібилов Вадим Михайлович","Вадим Михайлович Прібилов","Вадим Прібилов"]},"patronymic":"Михайлович"},"source":"VULYK","estate":{"29":[{"region_unclear":false,"space_unclear":false,"address_hidden":true,"region_hidden":true,"space_comment":"","space":"1000","address":"","region":"","costs_property":"","costs_rent_comment":"","address_unclear":false,"space_units":"м²","costs_property_comment":"","costs_rent":""}],"30":[{"costs_rent":"","region":"","costs_property":"","costs_rent_comment":"","address_hidden":true,"region_hidden":true,"space_comment":"","costs_property_comment":"","space_units":"м²","space":"125.3","address":""}]},"intro":{"declaration_year":"2014"}}