{"id":"vulyk_103_60","ft_src":"Toyota Venza\n2694 куб. см., 182 к.с., 480.1 см\n2010\n3456 куб. см., 270 к.с., 478.5 см\nToyota Highlander\n2011\n1986\n1479 куб. см., 75 к.с., 425.0 см\nМосквич / АЗЛК 2140\n.24\n540\n1/3 частина квартири\n22.13\n138\n540\n.24\n1/3 частина квартири\n22.13\n138\n2015\n374000\n306937.68\n2374000\n306937.68\n2000000\n2694 куб. см., 182 к.с., 480.1 см\n2010\nToyota Venza\n3456 куб. см., 270 к.с., 478.5 см\n2011\nToyota Highlander\n1479 куб. см., 75 к.с., 425.0 см\n1986\nМосквич / АЗЛК 2140\n540\n22.13\n1/3 частина квартири\n138\n.24\n.24\n540\n1/3 частина квартири\n22.13\n138\nШтелик\nШтелик Світлана Павлівна\nСвітлана Павлівна Штелик\nСвітлана Штелик\nШтелик Світлана Павлівна\nШтелик Світлана Павлівна\nПавлівна\nПодружжя\nШтелик В. М\nСвітлана\nВищий спеціалізований суд з розгляду цивільних і кримінальних справ\nсуддя вищого спецiалiзованого суду україни з розгляду цивiльних і кримiнальних справ\nЗагальнодержавний регіон\n14490\n8800\n306937.68\n374000\n306937.68\n2374000\n2000000\n2015\n8800\n14490\nПодружжя\nШтелик В. М\nШтелик\nПавлівна\nсуддя вищого спецiалiзованого суду україни з розгляду цивiльних і кримiнальних справ\nВищий спеціалізований суд з розгляду цивільних і кримінальних справ\nЗагальнодержавний регіон\nШтелик Світлана Павлівна\nШтелик Світлана Павлівна\nСвітлана Павлівна Штелик\nСвітлана Штелик\nШтелик Світлана Павлівна\nСвітлана","estate":{"23":[{"costs":"","address":"","space_units":"га","costs_rent_comment":"","space":".24","space_comment":"","region_hidden":true,"costs_comment":"","region":"","address_hidden":false,"costs_rent":""}],"24":[{"address":"","space_units":"м²","space_hidden":false,"space_unclear":false,"region_hidden":true,"costs_comment":"","space_comment":"","address_hidden":false,"space":"540","costs_rent_comment":"","costs":"","region":"","costs_rent":""}],"25":[{"address":"","space_units":"м²","costs_comment":"","region_hidden":true,"space_comment":"1/3 частина квартири","address_hidden":false,"space_comment_hidden":false,"space":"22.13","space_comment_unclear":false,"costs_rent_comment":"","costs":"","region":"","costs_rent":""},{"costs":"","address":"","space_units":"м²","costs_rent_comment":"","space":"138","space_comment":"","region_hidden":false,"costs_comment":"","region":"","costs_rent":""}],"29":[{"costs_property_comment":"","address":"","space_units":"м²","space_hidden":false,"space_comment":"","region_hidden":true,"costs_property":"","region":"","address_hidden":true,"costs_rent_comment":"","space":".24","costs_rent":""}],"30":[{"costs_property_comment":"","address":"","space_units":"м²","space_hidden":false,"space_unclear":false,"region_hidden":true,"costs_property":"","space_comment":"","address_hidden":true,"costs_rent_comment":"","space":"540","costs_rent":""}],"31":[{"costs_property_comment":"","address":"","space_units":"м²","space_hidden":false,"region_hidden":true,"costs_property":"","space_comment":"1/3 частина квартири","address_hidden":true,"address_unclear":false,"costs_rent_comment":"","space":"22.13","costs_rent":""},{"address_hidden":true,"costs_property_comment":"","address":"","space_units":"м²","costs_rent_comment":"","space_hidden":false,"costs_property":"","space_comment":"","space":"138","space_comment_unclear":false,"costs_rent":""}]},"vehicle":{"35":[{"sum_comment":"","brand_info_hidden":false,"brand_info":"2694 куб. см., 182 к.с., 480.1 см","sum":"","brand_unclear":false,"brand_hidden":false,"brand":"Toyota Venza","sum_rent":"","brand_info_unclear":false,"sum_rent_comment":"","year":"2010"}],"40":[{"year_hidden":false,"brand_info":"3456 куб. см., 270 к.с., 478.5 см","sum":"","sum_rent_comment":"","brand_hidden":false,"brand":"Toyota Highlander","sum_rent":"","sum_comment":"","year":"2011","brand_info_unclear":false},{"sum_comment":"","brand_info_hidden":false,"brand_info":"1479 куб. см., 75 к.с., 425.0 см","sum":"","sum_rent_comment":"","year":"1986","brand":"Москвич / АЗЛК 2140","sum_rent":"","brand_info_unclear":false}]},"source":"VULYK","income":{"5":{"family_comment":"","family":"2374000","comment":"","value_unclear":false,"family_hidden":false,"value":"306937.68"},"6":{"family_comment":"","value":"306937.68","family":"374000","comment":""},"7":{"family":"","family_comment":"","value":"","comment":"","source_name":""},"8":{"family_comment":"","value":"","family":"","comment":""},"9":{"family_comment":"","value":"","family":"","comment":""},"10":{"family_comment":"","value":"","family":"","comment":""},"11":{"family_comment":"","family_hidden":false,"value":"","family":"","comment":""},"12":{"family_comment":"","value":"","family":"","comment":""},"13":{"family_comment":"","value":"","family":"","comment":""},"14":{"family_comment":"","value":"","family":"","comment":""},"15":{"family_comment":"","value":"","family":"","comment":""},"16":{"family_comment":"","value":"","family":"2000000","comment":""},"17":{"family_comment":"","value":"","family":"","comment":"","family_comment_unclear":false},"18":{"family_comment":"","value":"","family":"","comment":""},"19":{"family_comment":"","value":"","family":"","comment":""},"20":{"family_comment":"","family":"","comment":"","family_unclear":false,"family_hidden":false,"value":""}},"general":{"inn":"","addresses":[{"place_city_type_hidden":false,"place_city_type":"","place_city_hidden":true,"place_hidden":true,"place_district":"","place_district_hidden":false,"place":"","place_city":"","place_address_hidden":true,"place_address":""}],"last_name":"Штелик","full_name":"Штелик Світлана Павлівна","family":[{"inn":"","family_name":"Штелик В. М","relations_hidden":false,"name_unclear":false,"relations":"Подружжя","inn_hidden":true,"name_hidden":true,"relations_other":""}],"patronymic":"Павлівна","inn_hidden":true,"name":"Світлана","post":{"office":"Вищий спеціалізований суд з розгляду цивільних і кримінальних справ","region_unclear":false,"post":"суддя вищого спецiалiзованого суду україни з розгляду цивiльних і кримiнальних справ","region":"Загальнодержавний регіон","office_unclear":false},"family_raw":"","full_name_suggest":{"input":["Штелик Світлана Павлівна","Світлана Павлівна Штелик","Світлана Штелик"],"output":"Штелик Світлана Павлівна"}},"liabilities":{"54":{"sum_foreign_comment_hidden":false,"sum_foreign_comment_unclear":false,"sum_hidden":true,"sum":"8800","sum_foreign_comment":"","sum_comment":"","sum_unclear":false,"sum_foreign":"","sum_comment_hidden":true,"sum_foreign_hidden":false},"55":{"sum_comment":"","sum_foreign_comment":"","sum_foreign":"","sum":""},"56":{"sum_comment":"","sum_foreign_comment":"","sum_foreign":"","sum":""},"57":{"sum_comment":"","sum_hidden":false,"sum":"","sum_foreign_comment":"","sum_foreign":"","sum_comment_hidden":false,"sum_foreign_hidden":false,"sum_foreign_comment_hidden":false},"58":{"sum_comment":"","sum_hidden":false,"sum":"","sum_foreign_comment":"","sum_foreign":"","sum_comment_hidden":false,"sum_foreign_hidden":false,"sum_foreign_comment_hidden":false},"59":{"sum_comment":"","sum_hidden":false,"sum":"","sum_foreign_comment":"","sum_foreign":"","sum_comment_hidden":false,"sum_foreign_hidden":false,"sum_foreign_comment_hidden":false},"60":{"sum_comment":"","sum_hidden":true,"sum":"14490","sum_foreign_comment":"","sum_foreign":"","sum_comment_hidden":true},"61":{"sum_comment":"","sum_foreign_comment":"","sum_foreign":"","sum":""},"62":{"sum_comment":"","sum_foreign_comment":"","sum_foreign":"","sum":"","sum_comment_hidden":false},"63":{"sum_comment":"","sum_foreign_comment":"","sum_foreign":"","sum":""},"64":{"sum_comment":"","sum_foreign_comment":"","sum_foreign":"","sum":""}},"declaration":{"additional_info_text":"","additional_info":"","date":"2016-03-31T00:00:00","url":"http://static.declarations.com.ua/declarations/chosen_ones/judges_batch/1284_shtelyk_svitlana_pavlivna.pdf"},"intro":{"declaration_year":"2015"}}