{"income":{"5":{"value":"291849","family_comment":"","value_unclear":false,"comment_hidden":false,"family_hidden":false,"value_hidden":false,"family_unclear":false,"family":"22274","comment":"255849"},"6":{"value":"","family_comment":"","value_unclear":false,"family_hidden":false,"family_unclear":false,"comment_unclear":false,"comment":"","family":""},"7":{"source_name_unclear":false,"value":"","value_hidden":false,"family_comment":"","source_name":"","family":"","comment":"","source_name_hidden":false},"8":{"value":"","family_hidden":false,"value_hidden":false,"family_comment":"","family":"","comment":""},"9":{"value":"","family_comment":"","value_unclear":false,"family_hidden":false,"value_hidden":false,"family_unclear":false,"family":"","comment":""},"10":{"family_comment":"","value":"","family":"","comment":""},"11":{"family_comment":"","value":"","family":"","comment":""},"12":{"family_comment":"","value":"","family":"","comment":""},"13":{"family_comment":"","value":"","family":"","comment":""},"14":{"family_comment":"","value":"","family":"","comment":""},"15":{"family_comment":"","value":"","family":"","comment":""},"16":{"value":"36000","family_comment":"","value_unclear":false,"family_unclear":false,"family":"","comment":""},"17":{"family_comment":"","value":"","family":"","comment":""},"18":{"family_comment":"","value":"","family":"","comment":""},"19":{"family_comment":"","value":"","comment_unclear":false,"family":"","comment":""},"20":{"value":"","family_comment":"","value_unclear":false,"comment_hidden":false,"family_hidden":false,"family":"22274","value_hidden":false,"family_unclear":false,"comment_unclear":false,"comment":"","family_comment_unclear":false}},"id":"vulyk_63_139","declaration":{"additional_info_text":"","notfull_lostpages":"","date":"2015-03-30T00:00:00","notfull":"","additional_info":"","url":"http://static.declarations.com.ua/declarations/chosen_ones/mega_batch/parkhomenko_oksana_vladyslavivna.pdf"},"liabilities":{"54":{"sum_foreign_comment":"","sum":"","sum_comment":"","sum_unclear":false,"sum_foreign":""},"55":{"sum_foreign_comment":"","sum":"","sum_comment":"","sum_foreign":""},"56":{"sum_foreign_comment":"","sum":"","sum_comment":"","sum_unclear":false,"sum_foreign":""},"57":{"sum_foreign_comment":"","sum":"","sum_comment":"","sum_comment_hidden":false,"sum_unclear":false,"sum_foreign":""},"58":{"sum_foreign_comment":"","sum_comment_hidden":false,"sum":"","sum_comment":"","sum_foreign":""},"59":{"sum_foreign_comment":"","sum":"","sum_comment":"","sum_foreign":""},"60":{"sum_foreign_comment":"","sum":"","sum_comment":"","sum_comment_unclear":false,"sum_foreign":""},"61":{"sum_foreign_comment":"","sum":"","sum_comment":"","sum_unclear":false,"sum_foreign":""},"62":{"sum_foreign_comment":"","sum":"","sum_comment":"","sum_unclear":false,"sum_foreign":""},"63":{"sum_foreign_comment":"","sum":"","sum_comment":"","sum_hidden":false,"sum_comment_hidden":false,"sum_unclear":false,"sum_foreign":""},"64":{"sum_foreign_comment":"","sum_comment_hidden":false,"sum":"","sum_comment":"","sum_foreign":""}},"ft_src":"Ірпінь\n08200\nКиївська область\nсуддя ірпінського міського суду київської області\nКиївська область\nЗагальний місцевий суд\nОксана\nПархоменко\nПодружжя\nВладиславівна\nПархоменко\nПархоменко Оксана Владиславівна\nПархоменко Оксана Владиславівна\nОксана Владиславівна Пархоменко\nОксана Пархоменко\nПархоменко Оксана Владиславівна\n22274\n255849\n291849\n22274\n36000\n1200\nКиївська область\nЧеркаська область\n59\nм. Київ\n43.4\n43.4\nм. Київ\n46.2\nм. Київ\n2014\n22274\n255849\n291849\n36000\n22274\n1200\nКиївська область\n59\nЧеркаська область\n43.4\nм. Київ\n43.4\nм. Київ\n46.2\nм. Київ\nВладиславівна\nПархоменко Оксана Владиславівна\nОксана Владиславівна Пархоменко\nОксана Пархоменко\nПархоменко Оксана Владиславівна\nОксана\nПодружжя\nПархоменко\nПархоменко Оксана Владиславівна\nЗагальний місцевий суд\nКиївська область\nсуддя ірпінського міського суду київської області\nПархоменко\nІрпінь\n08200\nКиївська область\n22274\n291849\n255849\n22274\n36000\n2014\nПодружжя\nПархоменко\nВладиславівна\nПархоменко\nПархоменко Оксана Владиславівна\nОксана Владиславівна Пархоменко\nОксана Пархоменко\nПархоменко Оксана Владиславівна\nОксана\nКиївська область\nІрпінь\n08200\nКиївська область\nсуддя ірпінського міського суду київської області\nЗагальний місцевий суд\nПархоменко Оксана Владиславівна\nм. Київ\n43.4\nЧеркаська область\n59\n43.4\nм. Київ\nм. Київ\n46.2\nКиївська область\n1200\n2014","general":{"name_hidden":false,"name":"Оксана","patronymic_unclear":false,"last_name_hidden":false,"inn":"","family":[{"inn":"","inn_hidden":false,"relations_unclear":false,"relations_hidden":false,"relations_other":"","relations":"Подружжя","name_hidden":false,"inn_unclear":false,"family_name":"Пархоменко","name_unclear":false}],"patronymic":"Владиславівна","inn_hidden":false,"family_raw":"","inn_unclear":false,"post":{"post_unclear":false,"region_unclear":false,"region":"Київська область","office_hidden":false,"region_hidden":false,"post":"суддя ірпінського міського суду київської області","office_unclear":false,"office":"Загальний місцевий суд"},"last_name_unclear":false,"full_name":"Пархоменко Оксана Владиславівна","addresses":[{"place_city_type_unclear":false,"place_address":"08200","place_district_hidden":false,"place_city_type":"Місто","place_address_hidden":false,"place_address_unclear":false,"place_city_type_hidden":false,"place":"Київська область","place_district":"","place_unclear":false,"place_city":"Ірпінь","place_city_unclear":false,"place_hidden":false,"place_city_hidden":false,"place_district_unclear":false}],"last_name":"Пархоменко","full_name_suggest":{"output":"Пархоменко Оксана Владиславівна","input":["Пархоменко Оксана Владиславівна","Оксана Владиславівна Пархоменко","Оксана Пархоменко"]},"name_unclear":false},"source":"VULYK","estate":{"23":[{"space_unclear":false,"costs":"","costs_comment":"","costs_hidden":false,"address_hidden":false,"region_hidden":false,"space_comment":"","space_hidden":false,"space":"1200","address":"","region":"Київська область","space_units_unclear":false,"costs_rent_hidden":false,"space_units":"м²","space_units_hidden":false,"costs_rent":"","costs_rent_comment":""}],"25":[{"region_unclear":false,"space_unclear":false,"costs":"","costs_comment":"","costs_hidden":false,"address_hidden":false,"region_hidden":false,"space_comment":"","space_hidden":false,"space":"43.4","space_units_hidden":false,"region":"м. Київ","address_unclear":false,"costs_rent_comment":"","costs_rent_hidden":false,"space_comment_unclear":false,"costs_rent_comment_hidden":false,"space_units":"м²","address":"","costs_comment_hidden":false,"costs_rent":""},{"costs_rent":"","region":"м. Київ","costs":"","costs_rent_comment":"","costs_comment":"","address_hidden":false,"region_hidden":false,"space_comment":"","space_units":"м²","space":"46.2","address":""}],"30":[{"space_unclear":false,"address_hidden":false,"region_hidden":false,"space_comment":"","space_hidden":false,"space":"59","address":"","region":"Черкаська область","costs_property":"","costs_rent_comment":"","space_units":"м²","costs_property_comment":"","costs_rent":""}],"31":[{"space_unclear":false,"costs_property_hidden":false,"address_hidden":false,"region_hidden":false,"space_comment":"","space_hidden":false,"space":"43.4","address":"","costs_property_comment_hidden":false,"region":"м. Київ","costs_property":"","space_units_unclear":false,"costs_rent_hidden":false,"space_comment_unclear":false,"costs_rent_comment_hidden":false,"space_units":"м²","costs_property_comment":"","costs_rent":"","costs_rent_comment":""}]},"intro":{"declaration_year":"2014","isnotdeclaration":"","declaration_year_unclear":false}}