{"income":{"5":{"family_comment":"","value":"278250","family":"","comment":""},"6":{"family_comment":"","value":"278250","family":"","comment":""},"7":{"value":"","comment_hidden":false,"value_hidden":false,"family_comment":"","source_name":"","family":"","comment":"","source_name_hidden":false},"8":{"family_comment":"","value":"","family":"","comment":""},"9":{"value":"","comment_hidden":false,"family_comment":"","family":"","comment":"","family_comment_unclear":false},"10":{"family_comment":"","value":"","family":"","comment":""},"11":{"family_comment":"","value":"","comment_hidden":false,"family":"","comment":""},"12":{"family_comment":"","value":"","family":"","comment":""},"13":{"family_comment":"","value":"","family":"","comment":""},"14":{"family_comment":"","value":"","family":"","comment":""},"15":{"family_comment":"","value":"","family":"","comment":""},"16":{"family_comment":"","value":"","family":"","comment":""},"17":{"family_comment":"","value":"","family":"","comment":""},"18":{"family_comment":"","value":"","family":"","comment":""},"19":{"family_comment":"","value":"","family":"","comment":""},"20":{"family_comment":"","value":"","comment_hidden":false,"family":"","comment":""}},"id":"vulyk_102_76","declaration":{"date":"2016-03-24T00:00:00","additional_info_text":"","additional_info":"","url":"http://static.declarations.com.ua/declarations/chosen_ones/judges_batch/1150_shvets_viktor_volodymyrovych.pdf"},"liabilities":{"54":{"sum_foreign_comment":"","sum":"","sum_comment":"","sum_hidden":false,"sum_comment_hidden":false,"sum_foreign":""},"55":{"sum_foreign_comment":"","sum":"","sum_comment":"","sum_foreign":""},"56":{"sum_foreign_comment":"","sum":"","sum_comment":"","sum_foreign":""},"57":{"sum_foreign_comment":"","sum_comment_hidden":false,"sum":"","sum_comment":"","sum_foreign":""},"58":{"sum_foreign_comment":"","sum_comment_hidden":false,"sum":"","sum_comment":"","sum_foreign":""},"59":{"sum_foreign_comment":"","sum_comment_hidden":false,"sum":"","sum_comment":"","sum_foreign":""},"60":{"sum_foreign_comment":"","sum":"","sum_comment":"","sum_hidden":false,"sum_comment_hidden":false,"sum_foreign":""},"61":{"sum_foreign_comment":"","sum":"","sum_comment":"","sum_foreign":""},"62":{"sum_foreign_comment":"","sum":"","sum_comment":"","sum_unclear":false,"sum_foreign":""},"63":{"sum_foreign_comment":"","sum":"","sum_comment":"","sum_hidden":false,"sum_comment_hidden":false,"sum_foreign":""},"64":{"sum_foreign_comment":"","sum_comment_hidden":false,"sum":"","sum_comment":"","sum_foreign":""}},"ft_src":"суддя вищого адміністративного суду україни\nЗагальнодержавний регіон\nВищий адміністративний суд\nВіктор\nПодружжя\nВолодимирович\nШвець Віктор Володимирович\nШвець\nШвець Віктор Володимирович\nВіктор Володимирович Швець\nВіктор Швець\nШвець Віктор Володимирович\n278250\n278250\nкористування\n2015\n278250\n278250\nкористування\nШвець Віктор Володимирович\nВіктор Володимирович Швець\nВіктор Швець\nШвець Віктор Володимирович\nШвець Віктор Володимирович\nВіктор\nВолодимирович\nсуддя вищого адміністративного суду україни\nЗагальнодержавний регіон\nВищий адміністративний суд\nШвець\nПодружжя\n278250\n278250\n2015\nПодружжя\nВіктор\nВолодимирович\nШвець\nШвець Віктор Володимирович\nВіктор Володимирович Швець\nВіктор Швець\nШвець Віктор Володимирович\nсуддя вищого адміністративного суду україни\nЗагальнодержавний регіон\nВищий адміністративний суд\nШвець Віктор Володимирович\nкористування\n2015","general":{"inn":"","name":"Віктор","family":[{"inn_hidden":true,"inn":"","name_hidden":true,"family_name":"","relations":"Подружжя","name_unclear":false}],"patronymic":"Володимирович","inn_hidden":true,"family_raw":"","last_name":"Швець","post":{"region":"Загальнодержавний регіон","region_unclear":false,"post":"суддя вищого адміністративного суду україни","office_unclear":false,"office":"Вищий адміністративний суд"},"full_name":"Швець Віктор Володимирович","addresses":[{"place_district":"","place_city_hidden":true,"place_city":"","place_city_type_hidden":false,"place_district_hidden":false,"place_city_type":"","place_address_hidden":true,"place_address":"","place_hidden":true,"place":""}],"patronymic_hidden":false,"full_name_suggest":{"output":"Швець Віктор Володимирович","input":["Швець Віктор Володимирович","Віктор Володимирович Швець","Віктор Швець"]}},"source":"VULYK","estate":{"25":[{"costs":"","costs_comment":"","address_hidden":false,"region_hidden":true,"space_comment":"","space":"","address":"","region":"","address_unclear":false,"costs_rent_comment":"користування","space_units":"м²","costs_rent":""}]},"intro":{"declaration_year":"2015"}}