{"income":{"5":{"value":"245026.11","family_comment":"","value_unclear":false,"family_unclear":false,"family":"","comment":""},"6":{"family_comment":"","family_unclear":false,"value":"232846.11","family":"","comment":""},"7":{"source_name_unclear":false,"value":"","family_comment":"","source_name":"","family":"","comment":""},"8":{"family_comment":"","value":"","family":"","comment":""},"9":{"value":"","family_comment":"","comment_hidden":false,"family_unclear":false,"family":"","comment":"","family_comment_hidden":false},"10":{"family_comment":"","value":"12180","family":"","comment":"12180"},"11":{"family_comment":"","value":"","family":"","comment":""},"12":{"family_comment":"","value":"","family":"","comment":""},"13":{"family_comment":"","value":"","family":"","comment":""},"14":{"family_comment":"","value":"","family":"","comment":""},"15":{"family_comment":"","value":"","family":"","comment":""},"16":{"family_comment":"","value":"","family":"","comment":""},"17":{"family_comment":"","value":"","family":"","comment":""},"18":{"family_comment":"","value":"","family":"","comment":""},"19":{"family_comment":"","value":"","family":"","comment":""},"20":{"value":"","value_unclear":false,"comment_hidden":false,"family_comment":"","comment_unclear":false,"comment":"","family":""}},"vehicle":{"35":[{"brand_info":"3.5 куб.дм, 249","sum_rent_comment":"","brand":"Honda","sum_comment":"","year":"2009","brand_info_unclear":false,"sum":"","sum_rent":""}]},"id":"vulyk_108_142","declaration":{"additional_info_text":"","notfull_lostpages":"","date":"2016-03-16T00:00:00","notfull":"","additional_info":"","url":"http://static.declarations.com.ua/declarations/chosen_ones/judges_batch/2441_antoniuk_oleksandr_andriiovych_2015.pdf"},"liabilities":{"54":{"sum_foreign_comment":"","sum":"","sum_foreign":"","sum_comment":"","sum_hidden":false},"55":{"sum_foreign_comment":"","sum":"","sum_comment":"","sum_foreign":""},"56":{"sum_foreign_comment":"","sum":"","sum_comment":"","sum_unclear":false,"sum_foreign":""},"57":{"sum_foreign_comment":"","sum":"","sum_comment":"","sum_hidden":false,"sum_comment_hidden":false,"sum_foreign":""},"58":{"sum_foreign_comment":"","sum_comment":"","sum":"","sum_comment_hidden":false,"sum_foreign":""},"59":{"sum_foreign_comment":"","sum":"","sum_comment":"","sum_unclear":false,"sum_foreign":""},"60":{"sum_foreign_comment":"","sum_comment":"","sum":"","sum_comment_hidden":false,"sum_foreign":""},"61":{"sum_foreign_comment":"","sum_comment":"","sum":"","sum_comment_hidden":false,"sum_foreign":""},"62":{"sum_foreign_comment":"","sum":"","sum_comment":"","sum_foreign":""},"63":{"sum_foreign_comment":"","sum":"","sum_comment":"","sum_hidden":false,"sum_comment_hidden":false,"sum_unclear":false,"sum_foreign":""},"64":{"sum_foreign_comment":"","sum":"","sum_comment":"","sum_comment_hidden":false,"sum_unclear":false,"sum_foreign":""}},"ft_src":"3.5 куб.дм, 249\n2009\nHonda\nм. Дніпропетровськ\n78\nДніпропетровська область\n2015\n232846.11\n12180\n12180\n245026.11\n3.5 куб.дм, 249\n2009\nHonda\n2015\nЗагальний місцевий суд\nДніпропетровська область\nсуддя жовтневого районного суду м. дніпропетровська\nАнтонюк\nДніпропетровськ\nДніпропетровська область\nАнтонюк Олександр Андрійович\nОлександр Андрійович Антонюк\nОлександр Антонюк\nАнтонюк Олександр Андрійович\nОлександр\nАнтонюк Олександр Андрійович\nАндрійович\n232846.11\n245026.11\n12180\n12180\n78\nм. Дніпропетровськ\nДніпропетровська область\nАнтонюк\nАндрійович\nДніпропетровська область\nДніпропетровськ\nДніпропетровська область\nсуддя жовтневого районного суду м. дніпропетровська\nЗагальний місцевий суд\nАнтонюк Олександр Андрійович\nАнтонюк Олександр Андрійович\nОлександр Андрійович Антонюк\nОлександр Антонюк\nАнтонюк Олександр Андрійович\nОлександр","general":{"inn_hidden":false,"inn":"","inn_unclear":false,"post":{"post_unclear":false,"post":"суддя жовтневого районного суду м. дніпропетровська","office_hidden":false,"region":"Дніпропетровська область","office":"Загальний місцевий суд","office_unclear":false},"name":"Олександр","full_name":"Антонюк Олександр Андрійович","family_raw":"","addresses":[{"place_address":"","place_district_hidden":false,"place_city_type":"Місто","place_city_hidden":false,"place_address_unclear":false,"place_city_type_hidden":false,"place_city":"Дніпропетровськ","place":"Дніпропетровська область","place_district":"","place_unclear":false,"place_hidden":false,"place_address_hidden":false}],"last_name":"Антонюк","full_name_suggest":{"output":"Антонюк Олександр Андрійович","input":["Антонюк Олександр Андрійович","Олександр Андрійович Антонюк","Олександр Антонюк"]},"patronymic":"Андрійович"},"source":"VULYK","estate":{"25":[{"space_unclear":false,"costs":"","costs_comment":"","address_hidden":false,"region_hidden":false,"space_comment":"","space":"78","address":"м. Дніпропетровськ","region":"Дніпропетровська область","costs_rent_comment":"","space_comment_unclear":false,"space_units":"м²","space_units_unclear":false,"costs_rent":""}]},"intro":{"declaration_year":"2015","isnotdeclaration":"","declaration_year_hidden":false}}