{"income":{"5":{"value":"255169.99","family_comment":"","value_unclear":false,"value_hidden":false,"family_unclear":false,"family":"","comment":""},"6":{"value":"241894.23","family_hidden":false,"value_hidden":false,"family_comment":"","family_comment_hidden":false,"comment":"","family":""},"7":{"value":"658.76","value_unclear":false,"family_hidden":false,"value_hidden":false,"family_comment":"","source_name":"","family":"","comment":"","source_name_hidden":false},"8":{"value":"","comment_hidden":false,"family_hidden":false,"value_hidden":false,"family_comment":"","family":"","comment":""},"9":{"value":"","family_comment":"","comment_hidden":false,"family_hidden":false,"value_hidden":false,"family_unclear":false,"family":"","comment":""},"10":{"value":"12617","comment_hidden":false,"family_hidden":false,"value_hidden":false,"family_comment":"","family":"","comment":""},"11":{"value":"","value_unclear":false,"comment_hidden":false,"family_hidden":false,"value_hidden":false,"family_comment":"","family":"","comment":""},"12":{"value":"","comment_hidden":false,"family_hidden":false,"value_hidden":false,"family_comment":"","family":"","comment":""},"13":{"value":"","comment_hidden":false,"family_hidden":false,"value_hidden":false,"family_comment":"","family":"","comment":""},"14":{"value":"","comment_hidden":false,"family_hidden":false,"value_hidden":false,"family_comment":"","family":"","comment":""},"15":{"value":"","comment_hidden":false,"family_hidden":false,"value_hidden":false,"family_comment":"","family":"","comment":""},"16":{"value":"","comment_hidden":false,"family_hidden":false,"value_hidden":false,"family_comment":"","family":"","comment":""},"17":{"value":"","comment_hidden":false,"family_hidden":false,"value_hidden":false,"family_comment":"","family":"","comment":""},"18":{"value":"","value_unclear":false,"comment_hidden":false,"family_hidden":false,"value_hidden":false,"family_comment":"","family":"","comment":""},"19":{"value":"","comment_hidden":false,"family_hidden":false,"value_hidden":false,"family_comment":"","family":"","comment":""},"20":{"value":"","value_unclear":false,"family_comment":"","comment_unclear":false,"comment":"","family":""}},"vehicle":{"35":[{"brand_info":"3998 см, 250 к. с","sum_rent_comment":"","sum_rent_hidden":false,"year":"2008","sum_rent_unclear":false,"brand_info_hidden":false,"brand_info_unclear":false,"year_unclear":false,"sum_hidden":false,"sum_rent":"","sum":"","brand":"Toyota Land Cruiser Prado","sum_comment":"","brand_unclear":false,"sum_rent_comment_hidden":false,"sum_comment_hidden":false,"sum_unclear":false}]},"id":"vulyk_76_180","declaration":{"additional_info_text":"","notfull_lostpages":"","date":"2014-12-18T00:00:00","notfull":"","additional_info":"","url":"http://static.declarations.com.ua/declarations/chosen_ones/judges_batch/381_alkova_svitlana_mykolaivna.pdf"},"liabilities":{"54":{"sum_foreign_comment":"","sum_foreign_hidden":false,"sum_comment":"","sum_hidden":false,"sum_comment_hidden":false,"sum":"","sum_foreign":""},"55":{"sum_foreign_comment":"","sum":"","sum_hidden":false,"sum_comment":"","sum_foreign":""},"56":{"sum_foreign_comment":"","sum":"","sum_comment":"","sum_foreign":""},"57":{"sum_foreign_comment":"","sum_foreign_hidden":false,"sum_comment":"","sum_hidden":false,"sum_comment_hidden":false,"sum_unclear":false,"sum":"","sum_foreign":""},"58":{"sum_foreign_comment":"","sum_foreign_hidden":false,"sum_comment":"","sum_hidden":false,"sum_comment_hidden":false,"sum_unclear":false,"sum":"","sum_foreign":""},"59":{"sum_foreign_comment":"","sum":"","sum_hidden":false,"sum_comment":"","sum_foreign":""},"60":{"sum_foreign_comment":"","sum_foreign_hidden":false,"sum_comment":"","sum_hidden":false,"sum_comment_hidden":false,"sum_unclear":false,"sum":"","sum_foreign":""},"61":{"sum_foreign_comment":"","sum":"","sum_hidden":false,"sum_comment":"","sum_foreign":""},"62":{"sum_foreign_comment":"","sum":"","sum_comment":"","sum_hidden":false,"sum_comment_hidden":false,"sum_foreign":""},"63":{"sum_foreign_comment":"","sum":"","sum_hidden":false,"sum_comment":"","sum_foreign":""},"64":{"sum_foreign_comment":"","sum":"","sum_hidden":false,"sum_comment":"","sum_foreign":""}},"ft_src":"суддя апеляційного суду дніпропетровської області\nДніпропетровська область\nЗагальний апеляційний суд\nСвітлана\nМиколаївна\nАлькова\nАлькова Світлана Миколаївна\nАлькова Світлана Миколаївна\nСвітлана Миколаївна Алькова\nСвітлана Алькова\nАлькова Світлана Миколаївна\n3998 см, 250 к. с\n2008\nToyota Land Cruiser Prado\n200\n.09\n1290.6\n30\n63.4\n8229.57\n2013\n241894.23\n12617\n658.76\n255169.99\n3998 см, 250 к. с\nToyota Land Cruiser Prado\n2008\n.09\n200\n30\n1290.6\n63.4\n8229.57\nАлькова Світлана Миколаївна\nСвітлана Миколаївна Алькова\nСвітлана Алькова\nАлькова Світлана Миколаївна\nАлькова Світлана Миколаївна\nСвітлана\nМиколаївна\nЗагальний апеляційний суд\nсуддя апеляційного суду дніпропетровської області\nДніпропетровська область\nАлькова\n658.76\n241894.23\n255169.99\n12617\n2013\nМиколаївна\nАлькова\nСвітлана\nАлькова Світлана Миколаївна\nСвітлана Миколаївна Алькова\nСвітлана Алькова\nАлькова Світлана Миколаївна\nДніпропетровська область\nсуддя апеляційного суду дніпропетровської області\nЗагальний апеляційний суд\nАлькова Світлана Миколаївна\n2008\nToyota Land Cruiser Prado\n3998 см, 250 к. с\n12617\n255169.99\n658.76\n241894.23\n8229.57\n63.4\n200\n.09\n1290.6\n30\n2013","general":{"inn":"","name":"Світлана","inn_unclear":false,"patronymic":"Миколаївна","inn_hidden":true,"family_raw":"","last_name":"Алькова","post":{"post_unclear":false,"post":"суддя апеляційного суду дніпропетровської області","candidate":"","office_hidden":false,"region":"Дніпропетровська область","office":"Загальний апеляційний суд","office_unclear":false,"region_hidden":false},"last_name_unclear":false,"full_name":"Алькова Світлана Миколаївна","addresses":[{"place_city_type_unclear":false,"place_address":"","place_district_hidden":false,"place_city_type":"","place_city_hidden":false,"place_city_type_hidden":false,"place":"","place_district":"","place_unclear":false,"place_city":"","place_city_unclear":false,"place_hidden":true,"place_address_hidden":false}],"full_name_suggest":{"output":"Алькова Світлана Миколаївна","input":["Алькова Світлана Миколаївна","Світлана Миколаївна Алькова","Світлана Алькова"]},"name_unclear":false},"source":"VULYK","estate":{"23":[{"space_hidden":false,"costs":"","costs_comment":"","address_hidden":false,"region_hidden":true,"space_comment":"","space_unclear":false,"space":".09","address":"","space_comment_unclear":false,"region":"","costs_rent_comment":"","costs_unclear":false,"space_comment_hidden":false,"space_units":"га","costs_rent":"200"}],"25":[{"space_unclear":false,"costs":"","costs_comment":"","address_hidden":false,"region_hidden":true,"space_comment":"","space_hidden":false,"space":"63.4","address":"","region":"","costs_rent_comment":"","space_comment_unclear":false,"space_comment_hidden":false,"space_units":"м²","costs_rent":"8229.57"}],"26":[{"space_hidden":false,"costs":"","costs_comment":"","address_hidden":false,"region_hidden":true,"space_comment":"","space":"30","address":"","region":"","costs_rent_comment":"","space_units":"м²","costs_rent":"1290.6"}]},"intro":{"declaration_year":"2013","isnotdeclaration":"","declaration_year_unclear":false,"declaration_year_hidden":false}}