{"income":{"5":{"value":"247553","value_unclear":false,"family_hidden":false,"value_hidden":false,"family_comment":"","family":"43273","comment":""},"6":{"value":"209983","value_unclear":false,"family_hidden":false,"family_comment":"","family":"","comment":""},"7":{"value":"","comment_hidden":false,"family_comment":"","source_name":"","family":"","comment":"","source_name_hidden":false},"8":{"family_comment":"","value":"","family":"","comment":""},"9":{"family_comment":"","value":"30561","family":"15505","comment":""},"10":{"family_comment":"","family_unclear":false,"value":"","family":"","comment":""},"11":{"family_comment":"","value":"","family":"","comment":""},"12":{"family_comment":"","value":"","family":"6659","comment":""},"13":{"family_comment":"","value":"","family":"","comment":""},"14":{"family_comment":"","value":"","family":"","comment":""},"15":{"family_comment":"","value":"7009","family":"10000","comment":""},"16":{"family_comment":"","value":"","family":"","comment":""},"17":{"family_comment":"","value":"","family":"","comment":""},"18":{"family_comment":"","value":"","family":"","comment":""},"19":{"family_comment":"","value":"","family":"","comment":""},"20":{"value":"","family_comment":"","family_hidden":false,"family_unclear":false,"family":"11109","comment":"","family_comment_unclear":false}},"vehicle":{"35":[{"brand_info":"2494 м3 право власності","sum_rent_comment":"","brand_info_unclear":false,"year":"2012","brand_info_hidden":false,"sum_rent_comment_unclear":false,"sum_rent":"","sum":"","brand":"Toyota Camry","sum_comment":"","sum_comment_unclear":false,"brand_hidden":false,"brand_unclear":false}],"40":[{"brand_info":"2.0 1987 куб. см.","sum_rent_comment":"","brand":"Toyota Rav 4","sum_comment":"","year":"2010","brand_hidden":false,"brand_info_hidden":false,"brand_info_unclear":false,"year_unclear":false,"sum":"","sum_rent":""}]},"id":"vulyk_45_162","banks":{"45":[{"sum_foreign_comment":"","sum_units":"UAH","sum_comment":"","sum_comment_unclear":false,"sum_foreign_units":"UAH","sum_comment_hidden":false,"sum_unclear":false,"sum":"473057","sum_foreign":""},{"sum_foreign_comment":"","sum_units":"","sum_comment":"","sum_foreign_units":"","sum":"","sum_foreign":""}],"46":[{"sum_foreign_comment":"","sum_units":"UAH","sum_comment":"","sum_comment_unclear":false,"sum_foreign_units":"UAH","sum":"","sum_unclear":false,"sum_foreign":""}],"47":[{"sum_foreign_comment":"","sum_units":"UAH","sum_comment":"","sum_foreign_units":"UAH","sum":"","sum_foreign":""}],"48":[{"sum_foreign_comment":"","sum_units":"UAH","sum_comment":"","sum_foreign_units":"UAH","sum":"","sum_foreign":""}],"49":[{"sum_foreign_comment":"","sum_units":"UAH","sum_comment":"","sum_foreign_units":"UAH","sum":"","sum_foreign":""}],"50":[{"sum_foreign_comment":"","sum_units":"UAH","sum_comment":"","sum_foreign_units":"UAH","sum":"","sum_foreign":""}],"51":[{"sum_foreign_comment":"","sum_units":"UAH","sum_comment":"","sum_foreign_units":"UAH","sum_comment_hidden":false,"sum":"200482","sum_foreign":""},{"sum_foreign_comment":"","sum_units":"","sum_comment":"","sum_foreign_units":"","sum":"","sum_foreign":""}],"52":[{"sum_foreign_comment":"","sum_units":"UAH","sum_comment":"","sum_comment_unclear":false,"sum_foreign_units":"UAH","sum":"","sum_unclear":false,"sum_foreign":""}],"53":[{"sum_foreign_comment":"","sum_units":"UAH","sum_comment":"","sum_foreign_comment_hidden":false,"sum_hidden":false,"sum_foreign_units":"UAH","sum_comment_hidden":false,"sum_foreign_hidden":false,"sum":"","sum_foreign":""}]},"declaration":{"additional_info_text":"","notfull_lostpages":"","date":"2015-03-31T00:00:00","notfull":"","additional_info":"","url":"http://static.declarations.com.ua/declarations/chosen_ones/mega_batch/bilousov_serhii_mykolaiovych.pdf"},"liabilities":{"54":{"sum_foreign_comment":"","sum":"16243","sum_comment":"","sum_comment_unclear":false,"sum_comment_hidden":false,"sum_unclear":false,"sum_foreign":""},"55":{"sum_foreign_comment":"","sum":"","sum_comment":"","sum_foreign":""},"56":{"sum_foreign_comment":"","sum":"","sum_comment":"","sum_comment_unclear":false,"sum_unclear":false,"sum_foreign":""},"57":{"sum_foreign_comment":"","sum":"64375","sum_comment":"","sum_comment_unclear":false,"sum_hidden":false,"sum_comment_hidden":false,"sum_foreign":""},"58":{"sum_foreign_comment":"","sum":"","sum_comment":"","sum_comment_unclear":false,"sum_hidden":false,"sum_comment_hidden":false,"sum_foreign":""},"59":{"sum_foreign_comment":"","sum":"","sum_comment":"","sum_foreign":""},"60":{"sum_foreign_comment":"","sum":"8680","sum_comment":"","sum_comment_unclear":false,"sum_comment_hidden":false,"sum_foreign":""},"61":{"sum_foreign_comment":"","sum":"","sum_comment":"","sum_foreign":""},"62":{"sum_foreign_comment":"","sum":"","sum_comment":"","sum_foreign":""},"63":{"sum_foreign_comment":"","sum":"","sum_comment":"","sum_comment_unclear":false,"sum_comment_hidden":false,"sum_unclear":false,"sum_foreign":""},"64":{"sum_foreign_comment":"","sum":"","sum_comment":"","sum_comment_unclear":false,"sum_comment_hidden":false,"sum_unclear":false,"sum_foreign":""}},"ft_src":"64375\n16243\n8680\nзаступник голови господарського суду полтавської області\nПолтавська область\nГосподарський місцевий суд\nСергій\nБілоусова Ж. В\nПодружжя\nБілоусов М. С\nДитина\nБілоусов П. С\nДитина\nБілоусов І. С\nДитина\nМиколайович\nБілоусов Сергій Миколайович\nСергій Миколайович Білоусов\nСергій Білоусов\nБілоусов Сергій Миколайович\nБілоусов Сергій Миколайович\nБілоусов\n2494 м3 право власності\nToyota Camry\n2012\n2.0 1987 куб. см.\nToyota Rav 4\n2010\n200482\n473057\n2014\n2494 м3 право власності\nToyota Camry\n2012\n2.0 1987 куб. см.\n2010\nToyota Rav 4\n473057\n200482\n26\n1500\nправо власності\n20.4\nправо власності\n63.5\nінше право користування\n63.5\nінше право користування\nПодружжя\nБілоусова Ж. В\nДитина\nБілоусов М. С\nДитина\nБілоусов П. С\nБілоусов І. С\nДитина\nБілоусов Сергій Миколайович\nСергій Миколайович Білоусов\nСергій Білоусов\nБілоусов Сергій Миколайович\nБілоусов Сергій Миколайович\nСергій\nБілоусов\nГосподарський місцевий суд\nзаступник голови господарського суду полтавської області\nПолтавська область\nМиколайович\n64375\n8680\n16243\n209983\n6659\n11109\n7009\n10000\n247553\n43273\n30561\n15505\n2014\n64375\n16243\n8680\n26\nправо власності\n20.4\nправо власності\n1500\nінше право користування\n63.5\nінше право користування\n63.5\nБілоусова Ж. В\nПодружжя\nБілоусов М. С\nДитина\nБілоусов П. С\nДитина\nДитина\nБілоусов І. С\nМиколайович\nБілоусов\nСергій\nБілоусов Сергій Миколайович\nСергій Миколайович Білоусов\nСергій Білоусов\nБілоусов Сергій Миколайович\nПолтавська область\nзаступник голови господарського суду полтавської області\nГосподарський місцевий суд\nБілоусов Сергій Миколайович\n209983\n10000\n7009\n43273\n247553\n15505\n30561\n11109\n6659\n2012\nToyota Camry\n2494 м3 право власності\nToyota Rav 4\n2.0 1987 куб. см.\n2010\n10000\n7009\n11109\n247553\n43273\n15505\n30561\n6659\n209983\nінше право користування\n63.5\n26\nправо власності\n20.4\nінше право користування\n63.5\nправо власності\n1500\n473057\n200482\n2014","general":{"inn":"","name":"Сергій","last_name_hidden":false,"family":[{"inn":"","inn_hidden":true,"relations_unclear":false,"relations_hidden":false,"relations_other":"","relations":"Подружжя","name_hidden":false,"family_name":"Білоусова Ж. В","name_unclear":false},{"inn":"","relations":"Дитина","relations_other":"","inn_hidden":false,"family_name":"Білоусов М. С","name_hidden":false,"name_unclear":false},{"inn":"","relations":"Дитина","relations_other":"","inn_hidden":false,"family_name":"Білоусов П. С","name_unclear":false},{"inn":"","family_name":"Білоусов І. С","relations":"Дитина","inn_hidden":false,"relations_other":""}],"patronymic":"Миколайович","inn_hidden":true,"family_raw":"","inn_unclear":false,"post":{"post_unclear":false,"post":"заступник голови господарського суду полтавської області","post_hidden":false,"region":"Полтавська область","region_hidden":false,"office":"Господарський місцевий суд","office_hidden":false,"office_unclear":false},"full_name":"Білоусов Сергій Миколайович","addresses":[{"place_district":"","place_city_hidden":true,"place_city":"","place_city_type_hidden":true,"place_district_hidden":true,"place_city_type":"","place_address_hidden":true,"place_address":"","place_hidden":true,"place":""}],"last_name":"Білоусов","full_name_suggest":{"output":"Білоусов Сергій Миколайович","input":["Білоусов Сергій Миколайович","Сергій Миколайович Білоусов","Сергій Білоусов"]}},"source":"VULYK","estate":{"23":[{"space_unclear":false,"costs":"","costs_comment":"","costs_hidden":false,"address_hidden":false,"region_hidden":true,"space_comment":"","space":"26","address":"","region":"","space_units_unclear":false,"space_units":"м²","costs_rent":"","costs_rent_comment":""},{"costs":"","costs_comment":"","costs_hidden":false,"address_hidden":false,"region_hidden":false,"space_comment":"","space":"","address":"","region":"","costs_rent_comment":"","space_units":"","costs_rent":""},{"costs_rent":"","space_unclear":false,"region":"","costs":"","costs_rent_comment":"","costs_comment":"","address_hidden":false,"space_comment":"","space_units":"","space":"","address":""},{"costs_rent":"","region":"","costs":"","costs_rent_comment":"","costs_comment":"","space_comment":"","space_units":"","space":"","address":""},{"costs_rent":"","region":"","costs":"","costs_rent_comment":"","costs_comment":"","space_comment":"","space_units":"","space":"","address":""},{"costs_rent":"","region":"","costs":"","costs_rent_comment":"","costs_comment":"","space_comment":"","space_units":"","space":"","address":""}],"25":[{"space_unclear":false,"costs":"","costs_comment":"","address_hidden":false,"region_hidden":true,"space_comment":"","space_hidden":false,"space":"63.5","address":"інше право користування","region":"","address_unclear":false,"costs_rent_comment":"","costs_rent_hidden":false,"space_comment_hidden":false,"space_units":"м²","space_units_hidden":false,"costs_rent":""}],"27":[{"costs":"","costs_comment":"","address_hidden":false,"region_hidden":true,"space_comment":"","space":"20.4","address":"право власності","region":"","address_unclear":false,"costs_rent_comment":"","space_units":"м²","costs_rent":""}],"29":[{"space_hidden":false,"costs_property_comment":"","address_hidden":false,"region_hidden":true,"space_comment":"","space":"1500","address":"право власності","region":"","costs_property":"","costs_rent_comment":"","space_units":"м²","space_units_hidden":false,"costs_rent":""}],"31":[{"space_unclear":false,"address_hidden":false,"region_hidden":true,"space_comment":"","space_hidden":false,"space":"63.5","address":"інше право користування","region":"","costs_property":"","costs_rent_comment":"","space_units":"м²","costs_property_comment":"","costs_rent":""}]},"intro":{"declaration_year":"2014","isnotdeclaration":""}}