{"income":{"5":{"family_comment":"","family_unclear":false,"value":"225760","family":"48000","comment":""},"6":{"family_comment":"","family_unclear":false,"value":"212362","family":"","comment":""},"7":{"value":"","comment_hidden":false,"family_comment":"","source_name":"","family":"","comment":""},"8":{"family_comment":"","value":"","family":"","comment":""},"9":{"family_comment":"","value":"19000","family":"","comment":""},"10":{"family_comment":"","value":"13398","family":"","comment":""},"11":{"family_comment":"","value":"","value_unclear":false,"family":"","comment":""},"12":{"family_comment":"","value":"","family":"","comment":""},"13":{"family_comment":"","value":"","family":"","comment":""},"14":{"family_comment":"","value":"","family":"","comment":""},"15":{"family_comment":"","value":"","value_unclear":false,"family":"48000","comment":""},"16":{"family_comment":"","family_unclear":false,"value":"","family":"","comment":""},"17":{"family_comment":"","value":"","family":"","comment":""},"18":{"family_comment":"","value":"","family_hidden":false,"comment":"","family":""},"19":{"family_comment":"","value":"","family":"","comment":""},"20":{"value":"","comment_unclear":false,"comment_hidden":false,"family_comment":"","family":"","comment":"","family_comment_hidden":false}},"vehicle":{"35":[{"brand_info":"2.0, об'єм двигуна 1998 куб. см., 112 кВт","sum_rent_comment":"","year":"2008","brand_info_hidden":false,"brand_info_unclear":false,"year_unclear":false,"sum_rent":"","sum":"","brand":"Mitsubishi Lancer","sum_comment":"свідотцтво про спадщину","brand_unclear":false,"brand_hidden":false}],"40":[{"brand_info":"2.0, об'єм двигуна 1998 куб. см., 112 кВт","sum_rent_comment":"","brand":"Mitsubishi Lancer","sum_comment":"","year":"2008","brand_hidden":false,"brand_info_hidden":false,"brand_info_unclear":false,"year_unclear":false,"sum":"","sum_rent":""}]},"id":"vulyk_68_158","banks":{"45":[{"sum_foreign_comment":"","sum_units":"UAH","sum_units_hidden":false,"sum_comment":"","sum_comment_unclear":false,"sum_hidden":true,"sum_foreign_units":"UAH","sum_comment_hidden":false,"sum_unclear":true,"sum":"533548","sum_foreign":""}]},"declaration":{"additional_info_text":"","notfull_lostpages":"","date":"2015-03-30T00:00:00","notfull":"","additional_info":"","url":"http://static.declarations.com.ua/declarations/chosen_ones/mega_batch/sudova-khomiuk_nataliia_mykhailivna.pdf"},"liabilities":{"54":{"sum_foreign_comment":"","sum":"","sum_comment":"","sum_comment_unclear":false,"sum_hidden":false,"sum_comment_hidden":false,"sum_unclear":false,"sum_foreign":""},"55":{"sum_foreign_comment":"","sum":"","sum_hidden":false,"sum_comment":"","sum_foreign":""},"56":{"sum_foreign_comment":"","sum_foreign_hidden":false,"sum_comment":"","sum":"","sum_unclear":false,"sum_foreign":""},"57":{"sum_foreign_comment":"","sum":"","sum_comment":"","sum_comment_unclear":false,"sum_hidden":false,"sum_comment_hidden":false,"sum_unclear":false,"sum_foreign":""},"58":{"sum_foreign_comment":"","sum":"","sum_comment":"","sum_hidden":false,"sum_comment_hidden":false,"sum_unclear":false,"sum_foreign":""},"59":{"sum_foreign_comment":"","sum":"","sum_comment":"","sum_foreign":""},"60":{"sum_foreign_comment":"","sum":"","sum_comment":"","sum_comment_unclear":false,"sum_hidden":false,"sum_comment_hidden":false,"sum_unclear":false,"sum_foreign":""},"61":{"sum_foreign_comment":"","sum":"","sum_hidden":false,"sum_comment":"","sum_foreign":""},"62":{"sum_foreign_comment":"","sum":"","sum_comment":"","sum_unclear":false,"sum_foreign":""},"63":{"sum_foreign_comment":"","sum":"","sum_comment":"","sum_hidden":false,"sum_comment_hidden":false,"sum_unclear":false,"sum_foreign":""},"64":{"sum_foreign_comment":"","sum":"","sum_comment":"","sum_hidden":false,"sum_comment_hidden":false,"sum_foreign":""}},"ft_src":"суддя львівського апеляційного адміністративного суду\nЛьвівська область\nАпеляційний адміністративний суд\nНаталія\nХомюк Марія-Софія Іванівна\nДитина\nМихайлівна\nСудова-Хомюк Наталія Михайлівна\nНаталія Михайлівна Судова-Хомюк\nНаталія Судова-Хомюк\nСудова-Хомюк Наталія Михайлівна\nСудова-Хомюк Наталія Михайлівна\nСудова-Хомюк\nсвідотцтво про спадщину\n2.0, об'єм двигуна 1998 куб. см., 112 кВт\nMitsubishi Lancer\n2008\n2.0, об'єм двигуна 1998 куб. см., 112 кВт\nMitsubishi Lancer\n2008\n533548\n2014\n2.0, об'єм двигуна 1998 куб. см., 112 кВт\nMitsubishi Lancer\nсвідотцтво про спадщину\n2008\n2.0, об'єм двигуна 1998 куб. см., 112 кВт\n2008\nMitsubishi Lancer\n533548\n58\nсвідоцтво про право на спадщину\n57\n1/2 земельної ділянки, свідотцтво про право на спадщину\n65\n1/2 земельної ділянки, свідотцтво про право на спадщину\n1/2 земельної ділянки\n65\n57\n1/2 земельної ділянки\n147\nсвідоцтво про право на спадщину, 1/2 садового будинку\n147\n1/2 частина садового будинку\nСудова-Хомюк Наталія Михайлівна\nНаталія Михайлівна Судова-Хомюк\nНаталія Судова-Хомюк\nСудова-Хомюк Наталія Михайлівна\nСудова-Хомюк Наталія Михайлівна\nДитина\nХомюк Марія-Софія Іванівна\nНаталія\nМихайлівна\nАпеляційний адміністративний суд\nЛьвівська область\nсуддя львівського апеляційного адміністративного суду\nСудова-Хомюк\n212362\n48000\n225760\n48000\n13398\n19000\n2014\nсвідоцтво про право на спадщину\n58\n1/2 земельної ділянки, свідотцтво про право на спадщину\n57\n1/2 земельної ділянки, свідотцтво про право на спадщину\n65\n1/2 земельної ділянки\n65\n1/2 земельної ділянки\n57\nсвідоцтво про право на спадщину, 1/2 садового будинку\n147\n1/2 частина садового будинку\n147\nДитина\nХомюк Марія-Софія Іванівна\nМихайлівна\nСудова-Хомюк\nНаталія\nСудова-Хомюк Наталія Михайлівна\nНаталія Михайлівна Судова-Хомюк\nНаталія Судова-Хомюк\nСудова-Хомюк Наталія Михайлівна\nЛьвівська область\nАпеляційний адміністративний суд\nсуддя львівського апеляційного адміністративного суду\nСудова-Хомюк Наталія Михайлівна\n212362\n48000\n13398\n48000\n225760\n19000\n2008\nMitsubishi Lancer\nсвідотцтво про спадщину\n2.0, об'єм двигуна 1998 куб. см., 112 кВт\nMitsubishi Lancer\n2.0, об'єм двигуна 1998 куб. см., 112 кВт\n2008\n48000\n13398\n48000\n225760\n19000\n212362\nсвідоцтво про право на спадщину\n58\n1/2 земельної ділянки, свідотцтво про право на спадщину\n57\n1/2 земельної ділянки, свідотцтво про право на спадщину\n65\n1/2 земельної ділянки\n65\n1/2 земельної ділянки\n57\nсвідоцтво про право на спадщину, 1/2 садового будинку\n147\n1/2 частина садового будинку\n147\n533548\n2014","general":{"inn":"","name":"Наталія","inn_unclear":false,"family":[{"inn":"","inn_hidden":false,"relations_unclear":false,"relations_hidden":false,"relations_other":"","relations":"Дитина","name_hidden":false,"inn_unclear":false,"family_name":"Хомюк Марія-Софія Іванівна","name_unclear":false}],"inn_hidden":false,"family_raw":"","last_name":"Судова-Хомюк","post":{"post_unclear":false,"region_unclear":false,"post":"суддя львівського апеляційного адміністративного суду","office":"Апеляційний адміністративний суд","region":"Львівська область","post_hidden":false,"office_hidden":false,"office_unclear":false,"region_hidden":false},"full_name_suggest":{"output":"Судова-Хомюк Наталія Михайлівна","input":["Судова-Хомюк Наталія Михайлівна","Наталія Михайлівна Судова-Хомюк","Наталія Судова-Хомюк"]},"full_name":"Судова-Хомюк Наталія Михайлівна","patronymic":"Михайлівна","last_name_unclear":false,"name_unclear":false},"source":"VULYK","estate":{"23":[{"costs":"","costs_comment":"","address_hidden":false,"region_hidden":true,"space_comment":"свідоцтво про право на спадщину","space":"58","address":"","region":"","costs_rent_comment":"","space_comment_hidden":false,"space_units":"м²","costs_rent":""},{"costs_rent":"","region":"","costs":"","costs_rent_comment":"","costs_comment":"","address_hidden":false,"region_hidden":false,"space_comment":"1/2 земельної ділянки, свідотцтво про право на спадщину","space_units":"м²","space":"57","address":""},{"costs_rent":"","region":"","costs":"","costs_rent_comment":"","costs_comment":"","address_hidden":false,"region_hidden":false,"space_comment":"1/2 земельної ділянки, свідотцтво про право на спадщину","space_units":"м²","space":"65","address":""}],"26":[{"space_unclear":false,"costs":"","costs_comment":"","address_hidden":false,"region_hidden":true,"space_comment":"свідоцтво про право на спадщину, 1/2 садового будинку","space":"147","address":"","region":"","costs_rent_comment":"","space_units":"м²","costs_rent":""},{"costs_rent":"","costs":"","costs_rent_comment":"","costs_comment":"","region_hidden":true,"space_comment":"","space_units":"","space":"","address":""}],"29":[{"space_unclear":false,"address_hidden":true,"region_hidden":true,"space_comment":"1/2 земельної ділянки","space_units_hidden":false,"space_hidden":false,"space":"65","address":"","region":"","costs_property":"","space_units_unclear":false,"space_units":"м²","costs_property_comment":"","costs_rent":"","costs_rent_comment":""},{"space_unclear":false,"region_hidden":false,"space_comment":"1/2 земельної ділянки","space":"57","address":"","region":"","costs_property":"","costs_rent_comment":"","space_comment_hidden":false,"space_units":"м²","costs_property_comment":"","costs_rent":""}],"32":[{"costs_rent":"","region":"","costs_property":"","costs_rent_comment":"","address_hidden":true,"region_hidden":true,"space_comment":"1/2 частина садового будинку","costs_property_comment":"","space_units":"м²","space":"147","address":""}]},"intro":{"declaration_year":"2014","isnotdeclaration":""}}