{"income":{"5":{"value":"176735","family_unclear":false,"family_hidden":false,"family_comment":"","family":"1280","comment":""},"6":{"family_comment":"","value":"176735","family_hidden":false,"comment":"","family":""},"7":{"family_comment":"","value":"","source_name":"","family":"","comment":""},"8":{"family_comment":"","value":"","family":"","comment":""},"9":{"value":"","comment_unclear":false,"family_hidden":false,"family_comment":"","family":"","comment":""},"10":{"family_comment":"","value":"","family":"","comment":""},"11":{"family_comment":"","value":"","family":"","comment":""},"12":{"family_comment":"","value":"","family":"","comment":""},"13":{"family_comment":"","value":"","family":"","comment":""},"14":{"family_comment":"","value":"","family":"","comment":""},"15":{"family_comment":"","value":"","value_unclear":false,"family":"","comment":""},"16":{"family_comment":"","value":"","family":"","comment":""},"17":{"family_comment":"","value":"","family":"","comment":""},"18":{"family_comment":"","value":"","family":"","comment":""},"19":{"family_comment":"","value":"","family":"","comment":""},"20":{"value":"","comment_unclear":false,"comment_hidden":false,"family_hidden":false,"value_hidden":false,"family_comment":"","value_unclear":false,"family":"1280","comment":"","family_comment_hidden":false}},"vehicle":{"35":[{"brand_info":"3471 куб. см.","sum_rent_comment":"","brand":"Honda Accord","sum_comment":"","year":"2007","brand_info_hidden":false,"sum":"","sum_rent":""}],"44":[{"brand_info":"мотоцикл, 250 куб. см.","sum_rent_comment":"","brand":"JL 250","sum_comment":"","year":"2007","sum":"","sum_rent":""}]},"id":"vulyk_41_59","banks":{"45":[{"sum_foreign_comment":"","sum_units":"UAH","sum_comment":"","sum_foreign_unclear":false,"sum_foreign_units":"UAH","sum_hidden":false,"sum_comment_hidden":false,"sum":"","sum_foreign":""},{"sum_foreign_comment":"","sum_units":"","sum_comment":"","sum_foreign_unclear":false,"sum_foreign_units":"","sum":"","sum_foreign":""}],"46":[{"sum_foreign_comment":"","sum_units":"UAH","sum_comment":"","sum_foreign_units":"UAH","sum_comment_hidden":false,"sum_unclear":false,"sum":"","sum_foreign":""},{"sum_foreign_comment":"","sum_units":"","sum_comment":"","sum_foreign_units":"","sum":"","sum_unclear":false,"sum_foreign":""}],"47":[{"sum_foreign_comment":"","sum_units":"UAH","sum_comment":"","sum_foreign_units":"UAH","sum":"","sum_foreign":""},{"sum_foreign_comment":"","sum_units":"","sum_comment":"","sum_foreign_units":"","sum":"","sum_foreign":""}],"48":[{"sum_foreign_comment":"","sum_units":"UAH","sum_comment":"","sum_foreign_units":"UAH","sum":"","sum_foreign":""}],"49":[{"sum_foreign_comment":"","sum_units":"UAH","sum_comment":"","sum_foreign_units":"UAH","sum":"","sum_foreign":""}],"50":[{"sum_foreign_comment":"","sum_units":"UAH","sum_comment":"","sum_foreign_units":"UAH","sum":"","sum_foreign":""}],"51":[{"sum_foreign_comment":"","sum_units":"UAH","sum_comment":"","sum_hidden":false,"sum_foreign_units":"UAH","sum_comment_hidden":false,"sum_unclear":false,"sum":"","sum_foreign":""},{"sum_foreign_comment":"","sum_units":"","sum_comment":"","sum_foreign_units":"","sum":"","sum_foreign":""}],"52":[{"sum_foreign_comment":"","sum_units":"UAH","sum_comment":"","sum_foreign_units":"UAH","sum_comment_hidden":false,"sum_unclear":false,"sum":"","sum_foreign":""}],"53":[{"sum_foreign_comment":"","sum_units":"UAH","sum_comment":"","sum_foreign_units":"UAH","sum_comment_hidden":false,"sum":"","sum_foreign":""},{"sum_foreign_comment":"","sum_units":"","sum_comment":"","sum_foreign_units":"","sum":"","sum_foreign":""},{"sum_foreign_comment":"","sum_units":"","sum_comment":"","sum_foreign_units":"","sum":"","sum_foreign":""}]},"declaration":{"date":"2015-03-27T00:00:00","additional_info_text":"","additional_info":"","url":"http://static.declarations.com.ua/declarations/chosen_ones/mega_batch/dieiev_mykola_vladyslavovych.pdf"},"liabilities":{"54":{"sum_foreign_comment":"","sum_comment_hidden":false,"sum":"","sum_comment":"","sum_foreign":""},"55":{"sum_foreign_comment":"","sum":"","sum_comment":"","sum_foreign":""},"56":{"sum_foreign_comment":"","sum":"","sum_hidden":false,"sum_comment":"","sum_foreign":""},"57":{"sum_foreign_comment":"","sum":"","sum_comment":"","sum_comment_hidden":false,"sum_unclear":false,"sum_foreign":""},"58":{"sum_foreign_comment":"","sum_comment_hidden":false,"sum":"","sum_comment":"","sum_foreign":""},"59":{"sum_foreign_comment":"","sum":"","sum_comment":"","sum_foreign":""},"60":{"sum_foreign_comment":"","sum_comment_hidden":false,"sum":"","sum_comment":"","sum_foreign":""},"61":{"sum_foreign_comment":"","sum":"","sum_comment":"","sum_foreign":""},"62":{"sum_foreign_comment":"","sum":"","sum_comment":"","sum_foreign":""},"63":{"sum_foreign_comment":"","sum":"","sum_comment":"","sum_comment_hidden":false,"sum_unclear":false,"sum_foreign":""},"64":{"sum_foreign_comment":"","sum_comment_hidden":false,"sum":"","sum_comment":"","sum_foreign":""}},"ft_src":"суддя дніпропетровського окружного адміністративного суду\nДніпропетровська область\nАдміністративний місцевий суд\nМикола\nДєєва І. Г\nПодружжя\nДєєва М. М\nДитина\nДєєва С. М\nДитина\nВладиславович\nДєєв Микола Владиславович\nМикола Владиславович Дєєв\nМикола Дєєв\nДєєв Микола Владиславович\nДєєв\nДєєв Микола Владиславович\n3471 куб. см.\n2007\nHonda Accord\nмотоцикл, 250 куб. см.\n2007\nJL 250\n2014\nHonda Accord\n3471 куб. см.\n2007\nмотоцикл, 250 куб. см.\nJL 250\n2007\n1130\nКиївська область\n70\n1/4\nм. Дніпропетровськ\nДніпропетровська область\n66.56\nм. Київ\nПодружжя\nДєєва І. Г\nДитина\nДєєва М. М\nДитина\nДєєва С. М\nДєєв Микола Владиславович\nМикола Владиславович Дєєв\nМикола Дєєв\nДєєв Микола Владиславович\nДєєв Микола Владиславович\nМикола\nВладиславович\nАдміністративний місцевий суд\nсуддя дніпропетровського окружного адміністративного суду\nДніпропетровська область\nДєєв\n176735\n1280\n176735\n1280\n2014\n1130\nКиївська область\n1/4\nм. Дніпропетровськ\nДніпропетровська область\n70\n66.56\nм. Київ\nДєєва І. Г\nПодружжя\nДєєва М. М\nДитина\nДєєва С. М\nДитина\nВладиславович\nДєєв\nМикола\nДєєв Микола Владиславович\nМикола Владиславович Дєєв\nМикола Дєєв\nДєєв Микола Владиславович\nДніпропетровська область\nсуддя дніпропетровського окружного адміністративного суду\nАдміністративний місцевий суд\nДєєв Микола Владиславович\n176735\n1280\n176735\n1280\nJL 250\nмотоцикл, 250 куб. см.\n2007\nHonda Accord\n3471 куб. см.\n2007\n1280\n176735\n1280\n176735\n1/4\nм. Дніпропетровськ\nДніпропетровська область\n70\nКиївська область\n1130\nм. Київ\n66.56\n2014","general":{"inn":"","name":"Микола","family":[{"inn":"","relations":"Подружжя","relations_hidden":false,"inn_hidden":true,"family_name":"Дєєва І. Г","name_hidden":true,"name_unclear":false},{"inn":"","relations":"Дитина","relations_other":"","inn_hidden":true,"family_name":"Дєєва М. М","name_hidden":false,"name_unclear":false},{"inn":"","relations":"Дитина","relations_other":"","inn_hidden":false,"family_name":"Дєєва С. М","name_hidden":false,"name_unclear":false}],"patronymic":"Владиславович","inn_hidden":true,"family_raw":"","last_name":"Дєєв","post":{"post_unclear":false,"post":"суддя дніпропетровського окружного адміністративного суду","post_hidden":false,"region":"Дніпропетровська область","region_hidden":false,"office":"Адміністративний місцевий суд","office_hidden":false},"last_name_unclear":false,"full_name":"Дєєв Микола Владиславович","addresses":[{"place_district":"","place_city_hidden":true,"place_city":"","place_city_type_hidden":true,"place_district_hidden":true,"place_city_type":"","place_address_hidden":true,"place_address":"","place_hidden":true,"place":""}],"patronymic_hidden":false,"full_name_suggest":{"output":"Дєєв Микола Владиславович","input":["Дєєв Микола Владиславович","Микола Владиславович Дєєв","Микола Дєєв"]},"name_unclear":false},"source":"VULYK","estate":{"23":[{"region_unclear":false,"space_unclear":false,"costs":"","costs_comment":"","address_hidden":false,"region_hidden":true,"space_comment":"","space":"1130","address":"","costs_comment_unclear":false,"region":"Київська область","space_units_unclear":false,"space_comment_hidden":false,"space_units":"м²","costs_rent":"","costs_rent_comment":""},{"costs_rent":"","space_unclear":false,"region":"","costs":"","costs_rent_comment":"","costs_comment":"","space_comment":"","space_units":"","space":"","address":""},{"costs_rent":"","region":"","costs":"","costs_rent_comment":"","costs_comment":"","space_comment":"","space_units":"","space":"","address":""}],"25":[{"region_unclear":false,"space_hidden":false,"costs":"","costs_comment":"","address_hidden":false,"region_hidden":true,"space_comment":"","space_unclear":false,"space":"66.56","address":"","costs_comment_unclear":false,"region":"м. Київ","costs_rent_comment":"","costs_unclear":false,"space_units":"м²","costs_rent":""}],"31":[{"space_hidden":false,"address_hidden":false,"region_hidden":false,"space_comment":"1/4","space":"70","address":"м. Дніпропетровськ","region":"Дніпропетровська область","costs_property":"","costs_rent_comment":"","space_comment_unclear":false,"space_units":"м²","costs_property_comment":"","costs_rent":""}]},"intro":{"declaration_year":"2014"}}