{"income":{"5":{"family_comment":"","value":"215574","family":"107004","comment":""},"6":{"family_comment":"","value":"203400","family":"","comment":""},"7":{"value":"","comment_hidden":false,"family_comment":"","source_name":"","family":"","comment":"","source_name_hidden":false},"8":{"family_comment":"","value":"","family":"","comment":"","family_hidden":false},"9":{"value":"24","family_comment":"","value_unclear":false,"family_unclear":false,"family":"4","comment":""},"10":{"family_comment":"","value":"","family":"","comment":""},"11":{"family_comment":"","value":"","family":"","comment":""},"12":{"family_comment":"","value":"","family":"","comment":""},"13":{"family_comment":"","value":"","family":"","comment":""},"14":{"family_comment":"","value":"","family":"","comment":""},"15":{"family_comment":"","value":"","family":"","comment":""},"16":{"family_comment":"","value":"","family":"107000","comment":""},"17":{"family_comment":"","value":"","family":"","comment":""},"18":{"family_comment":"","value":"","family":"","comment":""},"19":{"family_comment":"","value":"","family":"","comment":""},"20":{"value":"12150","value_unclear":false,"family_hidden":false,"family_comment":"","family":"","comment":""}},"vehicle":{"40":[{"brand_info":"3956 куб. см.","sum_rent_comment":"","brand":"Toyota Land Cruiser 120","sum_comment":"","year":"2008","brand_info_unclear":false,"sum":"","sum_rent":""}]},"id":"vulyk_109_51","banks":{"51":[{"sum_foreign_comment":"","sum_unclear":false,"sum":"33","sum_comment":"ПАО 'Банк Кредит Днепр'","sum_foreign_units":"UAH","sum_units":"UAH","sum_comment_hidden":false,"sum_units_hidden":false,"sum_foreign":""}]},"declaration":{"additional_info_text":"","notfull_lostpages":"","date":"2016-03-21T00:00:00","notfull":"","additional_info":"","url":"http://static.declarations.com.ua/declarations/chosen_ones/judges_batch/2508_lipynskyi_oleksandr_viktorovych_2015.pdf"},"liabilities":{"54":{"sum_foreign_comment":"","sum":"","sum_comment":"","sum_hidden":false,"sum_comment_hidden":false,"sum_unclear":false,"sum_foreign":""},"55":{"sum_foreign_comment":"","sum":"","sum_comment":"","sum_comment_unclear":false,"sum_foreign":""},"56":{"sum_foreign_comment":"","sum":"","sum_comment":"","sum_foreign":""},"57":{"sum_foreign_comment":"","sum_comment":"","sum":"","sum_comment_hidden":false,"sum_foreign":""},"58":{"sum_foreign_comment":"","sum_comment":"","sum":"","sum_comment_hidden":false,"sum_foreign":""},"59":{"sum_foreign_comment":"","sum":"","sum_comment":"","sum_foreign":""},"60":{"sum_foreign_comment":"","sum":"","sum_comment":"","sum_foreign":""},"61":{"sum_foreign_comment":"","sum":"","sum_comment":"","sum_foreign":""},"62":{"sum_foreign_comment":"","sum":"","sum_comment":"","sum_foreign":""},"63":{"sum_foreign_comment":"","sum":"","sum_comment":"","sum_foreign":""},"64":{"sum_foreign_comment":"","sum":"","sum_comment":"","sum_foreign":""}},"ft_src":"3956 куб. см.\n2008\nToyota Land Cruiser 120\n520\n520\n168.9\n119.6\nПАО 'Банк Кредит Днепр'\n33\n2015\n3956 куб. см.\n2008\nToyota Land Cruiser 120\n2015\nЛіпинський Олександр Вікторович\nОлександр Вікторович Ліпинський\nОлександр Ліпинський\nЛіпинський Олександр Вікторович\nОлександр\nПодружжя\nЛіпинська Н. М\nДитина\nЛіпинський М. О\nДитина\nЛіпинська Є. О\nЛіпинський Олександр Вікторович\nВікторович\nГосподарський місцевий суд\nДніпропетровська область\nсуддя господарського суду дніпропетровської області\nЛіпинський\n203400\n12150\n215574\n107004\n107000\n24\n4\n520\n520\n168.9\n119.6\n33\nПАО 'Банк Кредит Днепр'\n203400\n107004\n215574\n107000\n4\n24\n12150\nПодружжя\nЛіпинська Н. М\nДитина\nЛіпинський М. О\nДитина\nЛіпинська Є. О\nВікторович\nЛіпинський\nОлександр\nЛіпинський Олександр Вікторович\nОлександр Вікторович Ліпинський\nОлександр Ліпинський\nЛіпинський Олександр Вікторович\nДніпропетровська область\nГосподарський місцевий суд\nсуддя господарського суду дніпропетровської області\nЛіпинський Олександр Вікторович","general":{"name_hidden":false,"name":"Олександр","inn":"","last_name":"Ліпинський","family":[{"inn":"","relations":"Подружжя","relations_hidden":false,"inn_hidden":true,"family_name":"Ліпинська Н. М","relations_other":"","name_hidden":true,"name_unclear":false},{"inn":"","relations":"Дитина","relations_other":"","inn_hidden":false,"family_name":"Ліпинський М. О","name_hidden":false,"name_unclear":false},{"inn":"","relations":"Дитина","relations_other":"","inn_hidden":true,"family_name":"Ліпинська Є. О","name_hidden":false,"name_unclear":false}],"inn_hidden":true,"family_raw":"","inn_unclear":false,"post":{"region_unclear":false,"region":"Дніпропетровська область","post":"суддя господарського суду дніпропетровської області","region_hidden":false,"office":"Господарський місцевий суд","office_hidden":false,"office_unclear":false},"full_name":"Ліпинський Олександр Вікторович","addresses":[{"place_district":"","place_address_hidden":true,"place_city":"","place_address":"","place_district_hidden":true,"place_city_type":"","place_city_hidden":true,"place_city_type_hidden":true,"place_hidden":true,"place":""}],"patronymic":"Вікторович","full_name_suggest":{"output":"Ліпинський Олександр Вікторович","input":["Ліпинський Олександр Вікторович","Олександр Вікторович Ліпинський","Олександр Ліпинський"]}},"source":"VULYK","estate":{"23":[{"space_unclear":false,"costs":"","costs_rent_unclear":false,"costs_comment":"","address_hidden":true,"region_hidden":true,"space_comment":"","space":"520","address":"","region":"","costs_rent_comment":"","space_units":"м²","costs_rent":""}],"29":[{"space_unclear":false,"address_hidden":true,"region_hidden":true,"space_comment":"","space":"520","address":"","region":"","costs_property":"","costs_rent_comment":"","space_units":"м²","costs_property_comment":"","costs_rent":""}],"31":[{"space_hidden":false,"address_hidden":true,"region_hidden":true,"space_comment":"","space":"168.9","space_units_hidden":false,"region":"","costs_property":"","costs_rent_comment":"","space_units":"м²","costs_property_comment":"","costs_rent":"","address":""}],"32":[{"costs_rent":"","region":"","costs_property":"","costs_rent_comment":"","address_hidden":true,"region_hidden":true,"space_comment":"","costs_property_comment":"","space_units":"м²","space":"119.6","address":""}]},"intro":{"declaration_year":"2015","isnotdeclaration":""}}