{"income":{"5":{"family_comment":"","value":"274628","family":"37952","comment":""},"6":{"family_comment":"","value":"274628","family":"","comment":""},"7":{"value":"","comment_hidden":false,"value_hidden":false,"family_comment":"","source_name":"","family":"","comment":"","source_name_hidden":false},"8":{"family_comment":"","value":"","family":"","comment":""},"9":{"value":"","comment_hidden":false,"family_comment":"","family":"","comment":"","family_comment_unclear":false},"10":{"family_comment":"","value":"","family":"","comment":""},"11":{"family_comment":"","value":"","comment_hidden":false,"family":"","comment":""},"12":{"family_comment":"","value":"","family":"","comment":""},"13":{"family_comment":"","value":"","family":"","comment":""},"14":{"family_comment":"","value":"","family":"","comment":""},"15":{"family_comment":"","value":"","family":"","comment":""},"16":{"family_comment":"","value":"","family":"","comment":""},"17":{"family_comment":"","value":"","family":"","comment":""},"18":{"family_comment":"","value":"","family":"","comment":""},"19":{"family_comment":"","value":"","family":"","comment":""},"20":{"family_comment":"військова пенсія","value":"","comment_hidden":false,"family":"37952","comment":""}},"vehicle":{"35":[{"brand_info":"2354","sum_rent_comment":"користування","brand":"Honda CR-V","sum_comment":"","year":"2011","brand_info_unclear":false,"year_unclear":false,"sum":"","sum_rent":""}],"40":[{"brand_info":"2972","sum_rent_comment":"","brand":"Mitsubishi","sum_comment":"","year":"1999","brand_info_unclear":false,"sum":"","sum_rent":""}]},"id":"vulyk_102_92","declaration":{"date":"2016-03-17T00:00:00","additional_info_text":"","additional_info":"","url":"http://static.declarations.com.ua/declarations/chosen_ones/judges_batch/1166_ivanova_larysa_bronislavivna.pdf"},"liabilities":{"54":{"sum_foreign_comment":"","sum":"","sum_comment":"","sum_hidden":false,"sum_comment_hidden":false,"sum_foreign":""},"55":{"sum_foreign_comment":"","sum":"","sum_comment":"","sum_foreign":""},"56":{"sum_foreign_comment":"","sum":"","sum_comment":"","sum_foreign":""},"57":{"sum_foreign_comment":"","sum_comment_hidden":false,"sum":"","sum_comment":"","sum_foreign":""},"58":{"sum_foreign_comment":"","sum_comment_hidden":false,"sum":"","sum_comment":"","sum_foreign":""},"59":{"sum_foreign_comment":"","sum_comment_hidden":false,"sum":"","sum_comment":"","sum_foreign":""},"60":{"sum_foreign_comment":"","sum":"","sum_comment":"","sum_hidden":false,"sum_comment_hidden":false,"sum_foreign":""},"61":{"sum_foreign_comment":"","sum":"","sum_comment":"","sum_foreign":""},"62":{"sum_foreign_comment":"","sum":"","sum_comment":"","sum_unclear":false,"sum_foreign":""},"63":{"sum_foreign_comment":"","sum":"","sum_comment":"","sum_hidden":false,"sum_comment_hidden":false,"sum_foreign":""},"64":{"sum_foreign_comment":"","sum_comment_hidden":false,"sum":"","sum_comment":"","sum_foreign":""}},"ft_src":"суддя вищого господарського суду україни\nЗагальнодержавний регіон\nВищий господарський суд\nЛариса\nІванов В. С\nПодружжя\nБроніславівна\nІванова Лариса Броніславівна\nІванова\nІванова Лариса Броніславівна\nЛариса Броніславівна Іванова\nЛариса Іванова\nІванова Лариса Броніславівна\n2011\n2354\nHonda CR-V\nкористування\n2972\n1999\nMitsubishi\n1000\n1200\n1000\n1000\n1198\n119\n41\n42\n1/2\n28\nдачний, в процесі добудови, без права власності\n409\n1/2\n35\n46.7\n2015\n274628\n37952\n274628\n37952\nвійськова пенсія\n2354\nкористування\nHonda CR-V\n2011\n2972\n1999\nMitsubishi\n2015\nІванова Лариса Броніславівна\nЛариса Броніславівна Іванова\nЛариса Іванова\nІванова Лариса Броніславівна\nІванова Лариса Броніславівна\nЛариса\nБроніславівна\nсуддя вищого господарського суду україни\nЗагальнодержавний регіон\nВищий господарський суд\nІванова\nПодружжя\nІванов В. С\n274628\n37952\nвійськова пенсія\n274628\n37952\n1000\n1200\n1000\n1000\n1198\n119\n41\n42\n28\n1/2\n35\n1/2\n46.7\n409\nдачний, в процесі добудови, без права власності\nІванов В. С\nПодружжя\nЛариса\nБроніславівна\nІванова\nІванова Лариса Броніславівна\nЛариса Броніславівна Іванова\nЛариса Іванова\nІванова Лариса Броніславівна\nсуддя вищого господарського суду україни\nЗагальнодержавний регіон\nВищий господарський суд\nІванова Лариса Броніславівна\nкористування\n2011\n2354\nHonda CR-V\n1999\n2972\nMitsubishi\nвійськова пенсія\n37952\n37952\n274628\n274628\n119\n41\n42\n1/2\n28\n1000\n1200\n1000\n1000\n1198\n1/2\n35\n46.7\nдачний, в процесі добудови, без права власності\n409\n2015","general":{"inn":"","name":"Лариса","family":[{"inn_hidden":true,"inn":"","name_hidden":true,"family_name":"Іванов В. С","relations":"Подружжя","name_unclear":false}],"patronymic":"Броніславівна","inn_hidden":true,"family_raw":"","last_name":"Іванова","post":{"region":"Загальнодержавний регіон","region_unclear":false,"post":"суддя вищого господарського суду україни","office_unclear":false,"office":"Вищий господарський суд"},"full_name":"Іванова Лариса Броніславівна","addresses":[{"place_district":"","place_city_hidden":true,"place_city":"","place_city_type_hidden":false,"place_district_hidden":false,"place_city_type":"","place_address_hidden":true,"place_address":"","place_hidden":true,"place":""}],"patronymic_hidden":false,"full_name_suggest":{"output":"Іванова Лариса Броніславівна","input":["Іванова Лариса Броніславівна","Лариса Броніславівна Іванова","Лариса Іванова"]}},"source":"VULYK","estate":{"23":[{"costs":"","costs_comment":"","address_hidden":false,"region_hidden":true,"space_comment":"","space":"1000","address":"","region":"","costs_rent_comment":"","space_comment_unclear":false,"space_units":"м²","space_units_unclear":false,"costs_rent":""},{"costs_rent":"","region":"","costs":"","costs_rent_comment":"","costs_comment":"","region_hidden":false,"space_comment":"","space_units":"м²","space":"1200","address":""}],"25":[{"costs":"","costs_comment":"","address_hidden":false,"region_hidden":true,"space_comment":"1/2","space":"35","address":"","region":"","address_unclear":false,"costs_rent_comment":"","space_units":"м²","costs_rent":""},{"costs_rent":"","region":"","costs":"","costs_rent_comment":"","costs_comment":"","region_hidden":true,"space_comment":"","space_units":"м²","space":"46.7","address":""}],"29":[{"address_hidden":false,"region_hidden":true,"space_comment":"","space":"1000","address":"","region":"","costs_property":"","costs_rent_comment":"","space_comment_hidden":false,"space_units":"м²","costs_property_comment":"","costs_rent":""},{"costs_rent":"","region":"","costs_property":"","costs_rent_comment":"","address_hidden":false,"region_hidden":false,"space_comment":"","costs_property_comment":"","space_units":"м²","space":"1000","address":""},{"costs_rent":"","costs_property":"","costs_rent_comment":"","space_comment":"","costs_property_comment":"","space_units":"м²","space":"1198","address":""}],"31":[{"costs_rent":"","region":"","costs_property":"","costs_rent_comment":"","address_hidden":false,"region_hidden":true,"space_comment":"","costs_property_comment":"","space_units":"м²","space":"119","address":""},{"costs_rent":"","costs_property":"","costs_rent_comment":"","region_hidden":false,"space_comment":"","costs_property_comment":"","space_units":"м²","space":"41","address":""},{"costs_rent":"","costs_property":"","costs_rent_comment":"","space_comment":"","costs_property_comment":"","space_units":"м²","space":"42","address":""},{"costs_rent":"","costs_property":"","costs_rent_comment":"","space_comment":"1/2","costs_property_comment":"","space_units":"м²","space":"28","address":""}],"32":[{"costs_rent":"","region":"","costs_property":"","costs_rent_comment":"","address_hidden":false,"region_hidden":true,"space_comment":"дачний, в процесі добудови, без права власності","costs_property_comment":"","space_units":"м²","space":"409","address":""}]},"intro":{"declaration_year":"2015"}}