{"income":{"5":{"value":"227197","family_comment":"","value_unclear":false,"family_unclear":false,"family":"196004","comment":""},"6":{"family_comment":"","value":"217890","value_unclear":false,"family":"181350","comment":""},"7":{"value":"","value_unclear":false,"family_comment":"","source_name":"","family":"","comment":""},"8":{"family_comment":"","value":"","family":"","comment":""},"9":{"value":"","family_comment":"","value_unclear":false,"family_unclear":false,"family":"","comment":""},"10":{"family_comment":"","value":"","comment_unclear":false,"family":"","comment":""},"11":{"family_comment":"","value":"","family":"","comment":""},"12":{"family_comment":"","value":"","family":"","comment":""},"13":{"family_comment":"","value":"","value_unclear":false,"family":"","comment":""},"14":{"family_comment":"","value":"","family":"","comment":""},"15":{"family_comment":"","value":"","family":"","comment":""},"16":{"family_comment":"","family_unclear":false,"value":"","family":"10000","comment":""},"17":{"family_comment":"","family_unclear":false,"value":"","family":"","comment":""},"18":{"family_comment":"","value":"","family":"","comment":""},"19":{"family_comment":"","value":"","family":"","comment":""},"20":{"value":"9307","family_comment":"","value_unclear":false,"family_hidden":false,"value_hidden":false,"family_unclear":false,"comment_unclear":false,"comment":"","family":"4654"}},"vehicle":{"35":[{"brand_info":"1690 куб. см., 59 кВт , 1 /2 част., зареєстрована 1/1 част.","sum_rent_comment":"","brand_info_unclear":false,"year":"2007","brand_info_hidden":false,"sum_rent_comment_unclear":false,"sum_rent":"","sum":"","brand":"Chevrolet Niva","sum_comment":"","brand_unclear":false,"brand_hidden":false}],"40":[{"brand_info":"1690 куб. см., 59 кВт , 1 /2 част.","sum_rent_comment":"","brand":"Chevrolet Niva","sum_comment":"","year":"2007","brand_info_hidden":false,"brand_info_unclear":false,"sum":"","sum_rent":""},{"brand_info":"1569 куб. см., 56 кВт","sum_rent_comment":"","brand":"ВАЗ 2106","sum_comment":"","year":"1977","brand_info_hidden":false,"sum":"","sum_rent":""},{"brand_info":"1685 куб. см., 85 кВт , право користування","sum_rent_comment":"право користування","brand":"Kia Sportage","sum_comment":"","year":"2013","sum":"","sum_rent":""}]},"id":"vulyk_100_73","banks":{"47":[{"sum_foreign_comment":"","sum_units":"UAH","sum_comment":"ПрАТ МФПІ 'Нефтьгазпром' м. Харків","sum_comment_unclear":false,"sum_foreign_units":"UAH","sum":"11","sum_unclear":false,"sum_foreign":""}],"51":[{"sum_foreign_comment":"","sum_units":"UAH","sum_comment":"Ощадбанк України","sum_comment_unclear":false,"sum_foreign_units":"UAH","sum_units_unclear":false,"sum_comment_hidden":false,"sum_unclear":false,"sum":"8701","sum_foreign":""}],"52":[{"sum_foreign_comment":"","sum_units":"UAH","sum_comment":"ПАТ 'Лисичанський склозавод 'Пролетарій'","sum_comment_unclear":true,"sum_foreign_units":"UAH","sum":"101950","sum_unclear":false,"sum_foreign":""},{"sum_foreign_comment":"","sum_units":"UAH","sum_comment":"ПрАТ МФПІ 'Нефтьгазпром' м. Харків","sum_comment_unclear":true,"sum":"11","sum_foreign":""}]},"declaration":{"additional_info_text":"","notfull_lostpages":"","date":"2015-03-27T00:00:00","notfull":"","additional_info":"","url":"http://static.declarations.com.ua/declarations/chosen_ones/judges_batch/4273_lyzenko_ilona_vasylivna.pdf"},"liabilities":{"54":{"sum_foreign_comment":"","sum":"","sum_comment":"","sum_comment_hidden":false,"sum_unclear":false,"sum_foreign":""},"55":{"sum_foreign_comment":"","sum":"","sum_comment":"","sum_foreign":""},"56":{"sum_foreign_comment":"","sum":"","sum_comment":"","sum_unclear":false,"sum_foreign":""},"57":{"sum_foreign_comment":"","sum":"","sum_comment":"","sum_comment_unclear":false,"sum_comment_hidden":false,"sum_unclear":false,"sum_foreign":""},"58":{"sum_foreign_comment":"","sum":"","sum_comment":"","sum_comment_hidden":false,"sum_unclear":false,"sum_foreign":""},"59":{"sum_foreign_comment":"","sum":"","sum_comment":"","sum_foreign":""},"60":{"sum_foreign_comment":"","sum_comment_hidden":false,"sum":"","sum_comment":"","sum_foreign":""},"61":{"sum_foreign_comment":"","sum":"","sum_comment":"","sum_foreign":""},"62":{"sum_foreign_comment":"","sum":"","sum_comment":"","sum_unclear":false,"sum_foreign":""},"63":{"sum_foreign_comment":"","sum_comment_hidden":false,"sum":"","sum_comment":"","sum_foreign":""},"64":{"sum_foreign_comment":"","sum_comment_hidden":false,"sum":"","sum_comment":"","sum_foreign":""}},"ft_src":"Попасна\n93300, вул. 60 років Жовтня, буд. 3, кв. 125\nПопаснянський\nЛуганська область\n2822016588\nЛизенко Ілона Василівна\nголова попаснянського районного суду луганської області\nЛуганська область\nЗагальний місцевий суд\nІлона\n2827102914\nЛизенко А. В. 27. 05. 1977\nПодружжя\n3756201369\nЛизенко Д. А. 03. 11. 2002\nДитина\nЛизенко Ілона Василівна\nІлона Василівна Лизенко\nІлона Лизенко\nЛизенко Ілона Василівна\nЛизенко\nВасилівна\n1690 куб. см., 59 кВт , 1 /2 част., зареєстрована 1/1 част.\nChevrolet Niva\n2007\n2007\n1690 куб. см., 59 кВт , 1 /2 част.\nChevrolet Niva\n1569 куб. см., 56 кВт\n1977\nВАЗ 2106\n1685 куб. см., 85 кВт , право користування\n2013\nKia Sportage\nправо користування\nПрАТ МФПІ 'Нефтьгазпром' м. Харків\n11\nПАТ 'Лисичанський склозавод 'Пролетарій'\n101950\nПрАТ МФПІ 'Нефтьгазпром' м. Харків\n11\nОщадбанк України\n8701\n2014\n1690 куб. см., 59 кВт , 1 /2 част., зареєстрована 1/1 част.\nChevrolet Niva\n2007\nChevrolet Niva\n1690 куб. см., 59 кВт , 1 /2 част.\n2007\nВАЗ 2106\n1569 куб. см., 56 кВт\n1977\n1685 куб. см., 85 кВт , право користування\nправо користування\nKia Sportage\n2013\n8701\nОщадбанк України\nПАТ 'Лисичанський склозавод 'Пролетарій'\n101950\n11\nПрАТ МФПІ 'Нефтьгазпром' м. Харків\nПрАТ МФПІ 'Нефтьгазпром' м. Харків\n11\nм. Лисичанськ, вул. Будівельників, 7\n682\nЛуганська область\n67\nЛуганська область\nм. Лисичанськ, вул. Будівельників, 7\n77.3\n1/2 частка\nЛуганська область\nм. Лисичанськ, пр. Леніна, 127, кв. 13\nм. Полтава, пров. Космічний, б. 5, кв. 13\n41.4\n1/6 частка\nПолтавська область\n77.3\n1/2 частина, зареєстрована 1/1 частина\nЛуганська область\nм. Лисичанськ, пр. Леніна, 127, кв. 13\nм. Полтава, пров. Космічний, б. 5, кв. 13\n77780\n41.4\n1/6 частина, зареєстрована 1/3 частина\nПолтавська область\nЛуганська область\n51.2\nправо користування\nм. Попасна, вул. 60 років Жовтня, б.3, кв. 125\nЛуганська область\nм. Лисичанськ, вул. Будівельників, 7\n35.1\nПодружжя\nЛизенко А. В. 27. 05. 1977\n2827102914\nДитина\nЛизенко Д. А. 03. 11. 2002\n3756201369\nВасилівна\nЛуганська область\n93300, вул. 60 років Жовтня, буд. 3, кв. 125\nПопасна\nПопаснянський\nЛизенко\nЛизенко Ілона Василівна\nІлона Василівна Лизенко\nІлона Лизенко\nЛизенко Ілона Василівна\nЛизенко Ілона Василівна\n2822016588\nІлона\nЗагальний місцевий суд\nЛуганська область\nголова попаснянського районного суду луганської області\n217890\n181350\n9307\n4654\n227197\n196004\n10000\n2014\nЛуганська область\nм. Лисичанськ, вул. Будівельників, 7\n35.1\n1/2 частка\nЛуганська область\nм. Лисичанськ, пр. Леніна, 127, кв. 13\n77.3\nПолтавська область\n1/6 частка\nм. Полтава, пров. Космічний, б. 5, кв. 13\n41.4\nЛуганська область\nм. Лисичанськ, вул. Будівельників, 7\n67\nЛуганська область\nм. Лисичанськ, вул. Будівельників, 7\n682\n1/2 частина, зареєстрована 1/1 частина\nм. Лисичанськ, пр. Леніна, 127, кв. 13\n77.3\nЛуганська область\n77780\n1/6 частина, зареєстрована 1/3 частина\nм. Полтава, пров. Космічний, б. 5, кв. 13\n41.4\nПолтавська область\nЛуганська область\nправо користування\nм. Попасна, вул. 60 років Жовтня, б.3, кв. 125\n51.2\n2827102914\nЛизенко А. В. 27. 05. 1977\nПодружжя\n3756201369\nДитина\nЛизенко Д. А. 03. 11. 2002\n2822016588\n93300, вул. 60 років Жовтня, буд. 3, кв. 125\nПопасна\nЛуганська область\nПопаснянський\nВасилівна\nЛизенко\nЛуганська область\nЗагальний місцевий суд\nголова попаснянського районного суду луганської області\nЛизенко Ілона Василівна\nЛизенко Ілона Василівна\nІлона Василівна Лизенко\nІлона Лизенко\nЛизенко Ілона Василівна\nІлона\n181350\n217890\n196004\n227197\n10000\n4654\n9307\n2007\nChevrolet Niva\n1690 куб. см., 59 кВт , 1 /2 част., зареєстрована 1/1 част.\n2007\n1690 куб. см., 59 кВт , 1 /2 част.\nChevrolet Niva\nВАЗ 2106\n1569 куб. см., 56 кВт\n1977\nправо користування\nKia Sportage\n1685 куб. см., 85 кВт , право користування\n2013\n9307\n4654\n227197\n196004\n10000\n181350\n217890\n1/2 частка\nм. Лисичанськ, пр. Леніна, 127, кв. 13\nЛуганська область\n77.3\n1/6 частка\nм. Полтава, пров. Космічний, б. 5, кв. 13\nПолтавська область\n41.4\nм. Лисичанськ, вул. Будівельників, 7\nЛуганська область\n67\nм. Лисичанськ, вул. Будівельників, 7\nЛуганська область\n35.1\n1/2 частина, зареєстрована 1/1 частина\nм. Лисичанськ, пр. Леніна, 127, кв. 13\nЛуганська область\n77.3\n1/6 частина, зареєстрована 1/3 частина\nПолтавська область\n77780\nм. Полтава, пров. Космічний, б. 5, кв. 13\n41.4\nправо користування\nм. Попасна, вул. 60 років Жовтня, б.3, кв. 125\nЛуганська область\n51.2\nм. Лисичанськ, вул. Будівельників, 7\nЛуганська область\n682\nПрАТ МФПІ 'Нефтьгазпром' м. Харків\n11\nОщадбанк України\n8701\nПАТ 'Лисичанський склозавод 'Пролетарій'\n101950\nПрАТ МФПІ 'Нефтьгазпром' м. Харків\n11\n2014","general":{"inn":"2822016588","inn_hidden":false,"last_name":"Лизенко","post":{"post_unclear":false,"region_unclear":false,"post":"голова попаснянського районного суду луганської області","office":"Загальний місцевий суд","region":"Луганська область","post_hidden":false,"office_unclear":false},"name":"Ілона","full_name":"Лизенко Ілона Василівна","family_raw":"","addresses":[{"place_district":"Попаснянський","place_city_hidden":false,"place_city":"Попасна","place_city_unclear":false,"place_district_hidden":false,"place_city_type":"Місто","place_address_hidden":false,"place_city_type_hidden":false,"place_address":"93300, вул. 60 років Жовтня, буд. 3, кв. 125","place_hidden":false,"place":"Луганська область"}],"family":[{"inn_hidden":false,"inn":"2827102914","name_hidden":false,"family_name":"Лизенко А. В. 27. 05. 1977","relations":"Подружжя","name_unclear":false},{"inn":"3756201369","relations":"Дитина","relations_other":"","inn_hidden":false,"family_name":"Лизенко Д. А. 03. 11. 2002","name_hidden":false,"name_unclear":false}],"full_name_suggest":{"output":"Лизенко Ілона Василівна","input":["Лизенко Ілона Василівна","Ілона Василівна Лизенко","Ілона Лизенко"]},"patronymic":"Василівна"},"source":"VULYK","estate":{"25":[{"space_unclear":false,"costs":"","costs_comment":"","address_hidden":false,"region_hidden":false,"space_comment":"1/2 частина, зареєстрована 1/1 частина","space":"77.3","address":"м. Лисичанськ, пр. Леніна, 127, кв. 13","costs_comment_unclear":false,"region":"Луганська область","address_unclear":false,"costs_rent_comment":"","space_comment_unclear":false,"space_units":"м²","costs_rent":""},{"costs_rent":"","region":"Полтавська область","costs":"77780","costs_rent_comment":"","costs_comment":"","region_hidden":false,"space_comment":"1/6 частина, зареєстрована 1/3 частина","space_units":"м²","space":"41.4","address":"м. Полтава, пров. Космічний, б. 5, кв. 13"},{"costs_rent":"","region":"Луганська область","costs":"","costs_rent_comment":"","costs_comment":"","space_comment":"право користування","space_units":"м²","space":"51.2","address":"м. Попасна, вул. 60 років Жовтня, б.3, кв. 125"}],"29":[{"region_unclear":false,"space_unclear":false,"address_hidden":false,"region_hidden":false,"space_comment":"","space":"682","address":"м. Лисичанськ, вул. Будівельників, 7","region":"Луганська область","costs_property":"","costs_rent_comment":"","address_unclear":false,"space_units":"м²","costs_property_comment":"","costs_rent":""}],"30":[{"costs_rent":"","region":"Луганська область","costs_property":"","costs_rent_comment":"","address_hidden":false,"region_hidden":false,"space_comment":"","costs_property_comment":"","space_units":"м²","space":"67","address":"м. Лисичанськ, вул. Будівельників, 7"}],"31":[{"region_unclear":false,"space_unclear":false,"costs_property_comment_unclear":false,"address_hidden":false,"region_hidden":false,"space_comment":"1/2 частка","space":"77.3","address":"м. Лисичанськ, пр. Леніна, 127, кв. 13","region":"Луганська область","costs_property":"","costs_rent_comment":"","space_comment_unclear":false,"address_unclear":false,"space_units":"м²","costs_property_comment":"","costs_rent":""},{"costs_rent":"","region_unclear":false,"region":"Полтавська область","costs_property":"","costs_rent_comment":"","region_hidden":false,"space_comment":"1/6 частка","costs_property_comment":"","space_units":"м²","space":"41.4","address":"м. Полтава, пров. Космічний, б. 5, кв. 13"}],"33":[{"space_unclear":false,"address_hidden":false,"region_hidden":false,"space_comment":"","space":"35.1","address":"м. Лисичанськ, вул. Будівельників, 7","region":"Луганська область","costs_property":"","costs_rent_comment":"","address_unclear":false,"space_units":"м²","costs_property_comment":"","costs_rent":""}]},"intro":{"declaration_year":"2014"}}