{"id":"vulyk_108_153","ft_src":"1998 куб. см.\n2012\nMazda CX-5\nПриведена 51,2 загальна 47,8\nм. Донецьк, Треньова\n51.2\nДонецька область\n2015\n222124\n12180\n235274\n970\n1998 куб. см.\n2012\nMazda CX-5\n2015\nЗагальний місцевий суд\nДніпропетровська область\nсуддя жовтневого районного суду м. дніпропетровська\nБатманова\nБатманова Вікторія Віталіївна\nВікторія Віталіївна Батманова\nВікторія Батманова\nБатманова Вікторія Віталіївна\nВікторія\nБатманова Вікторія Віталіївна\nВіталіївна\n222124\n970\n235274\n12180\n51.2\nПриведена 51,2 загальна 47,8\nм. Донецьк, Треньова\nДонецька область\nБатманова\nВіталіївна\nДніпропетровська область\nсуддя жовтневого районного суду м. дніпропетровська\nЗагальний місцевий суд\nБатманова Вікторія Віталіївна\nБатманова Вікторія Віталіївна\nВікторія Віталіївна Батманова\nВікторія Батманова\nБатманова Вікторія Віталіївна\nВікторія","estate":{"25":[{"address":"м. Донецьк, Треньова","space_units":"м²","costs_comment":"","space_unclear":true,"region_hidden":false,"space_units_unclear":false,"space_comment":"Приведена 51,2 загальна 47,8","address_hidden":false,"costs":"","space_comment_unclear":true,"costs_rent_comment":"","space":"51.2","region":"Донецька область","costs_rent":""}]},"vehicle":{"35":[{"sum_comment":"","brand_info":"1998 куб. см.","sum":"","sum_rent_comment":"","year":"2012","brand":"Mazda CX-5","sum_rent":"","brand_info_unclear":false}]},"source":"VULYK","income":{"5":{"family_comment":"","family":"","comment":"","value_unclear":false,"family_unclear":false,"value":"235274"},"6":{"family_comment":"","value":"222124","family_unclear":false,"family":"","comment":""},"7":{"family_comment":"","comment":"","family":"","source_name_unclear":false,"value":"","source_name":""},"8":{"family_comment":"","value":"","family":"","comment":""},"9":{"family_comment":"","family":"","comment":"","family_unclear":false,"comment_hidden":false,"value":"","family_comment_hidden":false},"10":{"family_comment":"","value":"12180","family":"","comment":""},"11":{"family_comment":"","value":"","family":"","comment":""},"12":{"family_comment":"","value":"","family":"","comment":""},"13":{"family_comment":"","value":"","family":"","comment":""},"14":{"family_comment":"","value":"","family":"","comment":""},"15":{"family_comment":"","value":"","family":"","comment":""},"16":{"family_comment":"","value":"","family":"","comment":""},"17":{"family_comment":"","value":"","family":"","comment":""},"18":{"family_comment":"","value":"","family":"","comment":""},"19":{"family_comment":"","value":"","family":"","comment":""},"20":{"family_comment":"","comment":"","family":"","value_unclear":false,"comment_hidden":false,"comment_unclear":false,"value":"970"}},"general":{"inn":"","inn_unclear":false,"last_name":"Батманова","full_name_suggest":{"input":["Батманова Вікторія Віталіївна","Вікторія Віталіївна Батманова","Вікторія Батманова"],"output":"Батманова Вікторія Віталіївна"},"full_name":"Батманова Вікторія Віталіївна","patronymic":"Віталіївна","inn_hidden":true,"name":"Вікторія","post":{"office":"Загальний місцевий суд","post":"суддя жовтневого районного суду м. дніпропетровська","office_unclear":false,"office_hidden":false,"region":"Дніпропетровська область","post_unclear":false},"family_raw":"","addresses":[{"place_city_type_hidden":false,"place_hidden":true,"place_address_unclear":false,"place":"","place_city":"","place_unclear":false,"place_city_type":"","place_city_hidden":true,"place_district":"","place_district_hidden":false,"place_address":"","place_address_hidden":false}]},"liabilities":{"54":{"sum_comment":"","sum_foreign_comment":"","sum_foreign":"","sum_hidden":false,"sum":""},"55":{"sum_comment":"","sum_foreign_comment":"","sum_foreign":"","sum":""},"56":{"sum_comment":"","sum_foreign_comment":"","sum_foreign":"","sum_unclear":false,"sum":""},"57":{"sum_comment":"","sum_hidden":false,"sum":"","sum_foreign_comment":"","sum_foreign":"","sum_comment_hidden":false},"58":{"sum_comment":"","sum_foreign_comment":"","sum_foreign":"","sum":"","sum_comment_hidden":false},"59":{"sum_comment":"","sum_foreign_comment":"","sum_foreign":"","sum_unclear":false,"sum":""},"60":{"sum_comment":"","sum_foreign_comment":"","sum_foreign":"","sum":"","sum_comment_hidden":false},"61":{"sum_comment":"","sum_foreign_comment":"","sum_foreign":"","sum":"","sum_comment_hidden":false},"62":{"sum_comment":"","sum_foreign_comment":"","sum_foreign":"","sum":""},"63":{"sum_comment":"","sum_hidden":false,"sum":"","sum_foreign_comment":"","sum_foreign":"","sum_unclear":false,"sum_comment_hidden":false},"64":{"sum_comment":"","sum":"","sum_foreign_comment":"","sum_foreign":"","sum_unclear":false,"sum_comment_hidden":false}},"declaration":{"notfull_lostpages":"","additional_info_text":"","additional_info":"","date":"2016-02-15T00:00:00","notfull":"","url":"http://static.declarations.com.ua/declarations/chosen_ones/judges_batch/2452_batmanova_viktoriia_vitaliivna_2015.pdf"},"intro":{"declaration_year_hidden":false,"isnotdeclaration":"","declaration_year":"2015"}}