{"income":{"5":{"family_comment":"","value":"201891","family":"","comment":""},"6":{"value":"189711","family_comment":"","value_unclear":false,"comment_hidden":false,"family_unclear":false,"family":"","comment":""},"7":{"family_comment":"","value":"","source_name":"","family":"","comment":""},"8":{"family_comment":"","value":"","family":"","comment":""},"9":{"family_comment":"","family_unclear":false,"value":"","family":"","comment":""},"10":{"family_comment":"","value":"12180","value_unclear":false,"family":"","comment":"мат. допомога на оздоровлення"},"11":{"family_comment":"","value":"","family":"","comment":""},"12":{"family_comment":"","value":"","family":"","comment":""},"13":{"family_comment":"","value":"","family":"","comment":""},"14":{"family_comment":"","value":"","family":"","comment":""},"15":{"family_comment":"","value":"","family":"","comment":""},"16":{"family_comment":"","value":"","family":"","comment":""},"17":{"family_comment":"","value":"","family":"","comment":""},"18":{"family_comment":"","value":"","family":"","comment":""},"19":{"family_comment":"","value":"","family":"","comment":""},"20":{"value":"","family":"","value_unclear":false,"family_hidden":false,"family_comment":"","comment_unclear":false,"comment":"","family_comment_unclear":false}},"vehicle":{"35":[{"year_hidden":false,"brand_info":"1.8 , 1798","sum_rent_comment":"","year":"2008","brand_info_hidden":false,"brand_info_unclear":false,"sum_rent":"","sum":"","brand":"Volkswagen Passat","sum_comment":"","brand_unclear":false,"brand_hidden":false}]},"id":"vulyk_97_165","banks":{"45":[{"sum_foreign_comment":"","sum_units":"UAH","sum_comment":"","sum_comment_unclear":false,"sum_hidden":true,"sum_foreign_units":"UAH","sum_comment_hidden":true,"sum_unclear":true,"sum":"4468","sum_foreign":""}]},"declaration":{"additional_info_text":"","notfull_lostpages":"","date":"2015-03-31T00:00:00","notfull":"","additional_info":"","url":"http://static.declarations.com.ua/declarations/chosen_ones/judges_batch/4067_spyrydonova_vira_oleksandrivna.pdf"},"liabilities":{"54":{"sum_foreign_comment":"","sum":"120","sum_comment":"","sum_comment_unclear":false,"sum_hidden":true,"sum_comment_hidden":true,"sum_unclear":false,"sum_foreign":""},"55":{"sum_foreign_comment":"","sum":"","sum_comment":"","sum_foreign":""},"56":{"sum_foreign_comment":"","sum":"","sum_comment":"","sum_foreign":""},"57":{"sum_foreign_comment":"","sum":"84974","sum_comment":"","sum_comment_unclear":false,"sum_hidden":true,"sum_comment_hidden":true,"sum_unclear":false,"sum_foreign":""},"58":{"sum_foreign_comment":"","sum":"831","sum_comment":"","sum_comment_unclear":false,"sum_hidden":true,"sum_comment_hidden":true,"sum_unclear":false,"sum_foreign":""},"59":{"sum_foreign_comment":"","sum":"","sum_comment":"","sum_foreign":""},"60":{"sum_foreign_comment":"","sum":"","sum_comment":"","sum_comment_unclear":false,"sum_hidden":false,"sum_comment_hidden":false,"sum_foreign":""},"61":{"sum_foreign_comment":"","sum":"","sum_comment":"","sum_foreign":""},"62":{"sum_foreign_comment":"","sum":"","sum_comment":"","sum_unclear":false,"sum_foreign":""},"63":{"sum_foreign_comment":"","sum":"","sum_hidden":false,"sum_comment":"","sum_foreign":""},"64":{"sum_foreign_comment":"","sum":"","sum_comment":"","sum_foreign":""}},"ft_src":"84974\n120\n831\nсуддя київського окружного адміністративного суду\nКиївська область\nАдміністративний місцевий суд\nВіра\nОлександрівна\nСпиридонова Віра Олександрівна\nВіра Олександрівна Спиридонова\nВіра Спиридонова\nСпиридонова Віра Олександрівна\nСпиридонова Віра Олександрівна\nСпиридонова\n1.8 , 1798\nVolkswagen Passat\n2008\n1024\n1/2 частина від 58,5 кв. м\n58.5\n4468\n2014\n1.8 , 1798\nVolkswagen Passat\n2008\n2014\nАдміністративний місцевий суд\nКиївська область\nсуддя київського окружного адміністративного суду\nСпиридонова Віра Олександрівна\nВіра Олександрівна Спиридонова\nВіра Спиридонова\nСпиридонова Віра Олександрівна\nСпиридонова Віра Олександрівна\nВіра\nСпиридонова\nОлександрівна\n831\n84974\n120\n189711\n201891\nмат. допомога на оздоровлення\n12180\n1024\n58.5\n1/2 частина від 58,5 кв. м\n4468\n831\n84974\n120\n189711\nмат. допомога на оздоровлення\n12180\n201891\nОлександрівна\nСпиридонова\nВіра\nСпиридонова Віра Олександрівна\nВіра Олександрівна Спиридонова\nВіра Спиридонова\nСпиридонова Віра Олександрівна\nКиївська область\nАдміністративний місцевий суд\nсуддя київського окружного адміністративного суду\nСпиридонова Віра Олександрівна\n2008\nVolkswagen Passat\n1.8 , 1798\nмат. допомога на оздоровлення\n12180\n201891\n189711\n1/2 частина від 58,5 кв. м\n58.5\n1024\n4468\n2014","general":{"name_hidden":false,"name":"Віра","last_name_hidden":false,"inn":"","last_name":"Спиридонова","patronymic":"Олександрівна","inn_hidden":true,"family_raw":"","inn_unclear":false,"post":{"region_unclear":false,"region":"Київська область","post":"суддя київського окружного адміністративного суду","office":"Адміністративний місцевий суд","office_unclear":false,"post_hidden":false},"full_name":"Спиридонова Віра Олександрівна","addresses":[{"place_district":"","place_city_hidden":true,"place_city":"","place_city_unclear":false,"place_district_hidden":false,"place_city_type":"","place_address_hidden":true,"place_city_type_hidden":false,"place_address":"","place_hidden":true,"place":""}],"patronymic_hidden":false,"full_name_suggest":{"output":"Спиридонова Віра Олександрівна","input":["Спиридонова Віра Олександрівна","Віра Олександрівна Спиридонова","Віра Спиридонова"]}},"source":"VULYK","estate":{"23":[{"region_unclear":false,"space_unclear":false,"costs":"","costs_rent_unclear":false,"costs_comment":"","address_hidden":false,"region_hidden":true,"space_comment":"","space":"1024","address":"","region":"","address_unclear":false,"costs_rent_comment":"","space_units":"м²","costs_rent":""}],"25":[{"region_unclear":false,"space_unclear":false,"costs":"","costs_comment":"","address_hidden":false,"region_hidden":true,"space_comment":"1/2 частина від 58,5 кв. м","space_hidden":false,"space":"58.5","address":"","region":"","costs_rent_comment":"","space_comment_unclear":false,"space_comment_hidden":false,"space_units":"м²","costs_rent":""}]},"intro":{"declaration_year":"2014","isnotdeclaration":""}}