{"income":{"5":{"value":"890037","family_comment":"","value_unclear":false,"family_hidden":false,"family_unclear":false,"family":"40975","comment":""},"6":{"family_comment":"","value":"447345","family":"10942","comment":""},"7":{"family_comment":"","value":"12659","source_name":"","family":"","comment":""},"8":{"family_comment":"","value":"","family":"","comment":""},"9":{"family_comment":"","value":"","family":"","comment":""},"10":{"family_comment":"","value":"","value_unclear":false,"family":"","comment":""},"11":{"family_comment":"","value":"","family":"","comment":""},"12":{"family_comment":"","value":"","family":"","comment":""},"13":{"family_comment":"","value":"","family":"","comment":""},"14":{"family_comment":"","value":"","family":"","comment":""},"15":{"family_comment":"","value":"","family":"","comment":""},"16":{"family_comment":"","value":"430033","family":"30033","comment":""},"17":{"family_comment":"","value":"","family":"","comment":""},"18":{"family_comment":"","value":"","family":"","comment":""},"19":{"family_comment":"","value":"","family":"","comment":""},"20":{"family_comment":"","value":"","family":"","comment":""}},"vehicle":{"35":[{"brand_info":"1800 куб. см.","sum_rent_comment":"","brand":"Skoda Octavia","sum_comment":"","brand_unclear":false,"year":"1999","sum":"","sum_rent":""}]},"id":"vulyk_82_4","declaration":{"date":"2014-03-19T00:00:00","additional_info_text":"","additional_info":"","url":"http://static.declarations.com.ua/declarations/chosen_ones/judges_batch/2199_hultai_mykhailo_myroslavovych.pdf"},"liabilities":{"54":{"sum_foreign_comment":"","sum_comment_hidden":false,"sum":"","sum_comment":"","sum_foreign":""},"55":{"sum_foreign_comment":"","sum":"","sum_hidden":false,"sum_comment":"","sum_foreign":""},"56":{"sum_foreign_comment":"","sum":"40000","sum_comment":"","sum_foreign":""},"57":{"sum_foreign_comment":"","sum":"","sum_comment":"","sum_foreign":""},"58":{"sum_foreign_comment":"","sum":"","sum_comment":"","sum_foreign":""},"59":{"sum_foreign_comment":"","sum":"","sum_comment":"","sum_foreign":""},"60":{"sum_foreign_comment":"","sum":"","sum_comment":"","sum_foreign":""},"61":{"sum_foreign_comment":"","sum":"","sum_comment":"","sum_foreign":""},"62":{"sum_foreign_comment":"","sum":"","sum_comment":"","sum_foreign":""},"63":{"sum_foreign_comment":"","sum":"","sum_comment":"","sum_foreign":""},"64":{"sum_foreign_comment":"","sum":"","sum_comment":"","sum_foreign":""}},"ft_src":"40000\nсуддя конституційного суду україни\nЗагальнодержавний регіон\nКонституційний Cуд\nМихайло\nФедоренко Т. О\nПодружжя\nГультай О. М\nДитина\nМирославович\nГультай Михайло Мирославович\nМихайло Мирославович Гультай\nМихайло Гультай\nГультай Михайло Мирославович\nГультай Михайло Мирославович\nГультай\n1999\n1800 куб. см.\nSkoda Octavia\n1200\n3274\n175.4\n175.4\n2013\n10942\n447345\n12659\n40975\n890037\n30033\n430033\n1800 куб. см.\n1999\nSkoda Octavia\n2013\nПодружжя\nФедоренко Т. О\nДитина\nГультай О. М\nГультай Михайло Мирославович\nМихайло Мирославович Гультай\nМихайло Гультай\nГультай Михайло Мирославович\nГультай Михайло Мирославович\nМихайло\nГультай\nКонституційний Cуд\nЗагальнодержавний регіон\nсуддя конституційного суду україни\nМирославович\n40000\n12659\n447345\n10942\n890037\n40975\n430033\n30033\n1200\n3274\n175.4\n175.4\n40000\nФедоренко Т. О\nПодружжя\nГультай О. М\nДитина\nМирославович\nГультай\nМихайло\nГультай Михайло Мирославович\nМихайло Мирославович Гультай\nМихайло Гультай\nГультай Михайло Мирославович\nЗагальнодержавний регіон\nКонституційний Cуд\nсуддя конституційного суду україни\nГультай Михайло Мирославович\n1999\n1800 куб. см.\nSkoda Octavia\n890037\n40975\n30033\n430033\n12659\n10942\n447345\n175.4\n1200\n175.4\n3274\n2013","general":{"inn":"","name":"Михайло","inn_unclear":false,"family":[{"inn":"","inn_hidden":true,"relations_hidden":false,"family_name":"Федоренко Т. О","relations_other":"","relations":"Подружжя","name_hidden":true,"name_unclear":false},{"inn":"","relations":"Дитина","relations_other":"","inn_hidden":false,"family_name":"Гультай О. М","name_hidden":false,"name_unclear":false}],"inn_hidden":true,"family_raw":"","last_name":"Гультай","post":{"post":"суддя конституційного суду україни","region":"Загальнодержавний регіон","office_hidden":false,"office":"Конституційний Cуд","office_unclear":false,"post_hidden":false,"region_hidden":false},"full_name_suggest":{"output":"Гультай Михайло Мирославович","input":["Гультай Михайло Мирославович","Михайло Мирославович Гультай","Михайло Гультай"]},"full_name":"Гультай Михайло Мирославович","addresses":[{"place_district":"","place_city_hidden":true,"place_city":"","place_city_type_hidden":false,"place_district_hidden":false,"place_city_type":"","place_address_hidden":false,"place_address":"","place_hidden":true,"place":""}],"patronymic":"Мирославович","last_name_unclear":false},"source":"VULYK","estate":{"23":[{"costs":"","costs_comment":"","address_hidden":false,"region_hidden":true,"space_comment":"","space_units_unclear":false,"address":"","space":"1200","region":"","costs_rent_comment":"","space_units":"м²","costs_rent":""}],"25":[{"space_hidden":false,"costs":"","costs_comment":"","costs_hidden":false,"address_hidden":false,"region_hidden":true,"space_comment":"","space_unclear":false,"space":"175.4","address":"","region":"","costs_rent_comment":"","space_comment_unclear":false,"space_units":"м²","costs_rent":""}],"29":[{"space_units_unclear":false,"address_hidden":false,"region_hidden":true,"space_comment":"","space":"3274","address":"","region":"","costs_property":"","costs_rent_comment":"","space_units":"м²","costs_property_comment":"","costs_rent":""}],"31":[{"space_unclear":false,"address_hidden":false,"region_hidden":true,"space_comment":"","space":"175.4","address":"","region":"","costs_property":"","costs_rent_comment":"","space_comment_unclear":false,"space_units":"м²","costs_property_comment":"","costs_rent":""}]},"intro":{"declaration_year":"2013"}}