{"income":{"5":{"value":"253558","family_comment":"","value_unclear":false,"family_hidden":false,"value_hidden":false,"family_unclear":false,"family":"381620","comment":"","family_comment_unclear":false},"6":{"family_comment":"","family_unclear":false,"value":"221596","family":"1300","comment":""},"7":{"source_name_unclear":false,"value":"","family_comment":"","source_name":"","family":"","comment":"","source_name_hidden":false},"8":{"family_comment":"","value":"","family":"","comment":""},"9":{"family_comment":"","family_unclear":false,"value":"","family":"","comment":""},"10":{"family_comment":"","value":"","family":"","comment":""},"11":{"family_comment":"","value":"","family":"","comment":""},"12":{"family_comment":"","value":"","family":"","comment":""},"13":{"family_comment":"","value":"","family":"","comment":""},"14":{"family_comment":"","value":"","family":"","comment":""},"15":{"family_comment":"","value":"","family":"4456","comment":""},"16":{"value":"","value_unclear":false,"value_hidden":false,"family_comment":"","family":"149980","comment":""},"17":{"family_comment":"","value":"","family":"","comment":""},"18":{"family_comment":"","value":"","family":"","comment":""},"19":{"family_comment":"","value":"","family":"","comment":""},"20":{"value":"31962","family_comment":"","value_unclear":false,"comment_hidden":false,"family_hidden":false,"family":"225884","value_hidden":false,"family_unclear":false,"comment_unclear":false,"comment":"","family_comment_unclear":false}},"vehicle":{"35":[{"year_hidden":true,"brand_info":"","sum_rent_comment":"","sum_rent_hidden":false,"year":"","sum_hidden":false,"brand_info_hidden":false,"brand_info_unclear":false,"year_unclear":true,"sum_rent":"","sum":"","brand":"","sum_comment":"","brand_unclear":false,"brand_hidden":false}],"40":[{"brand_info":"2967 куб. см.","sum":"","brand":"Volkswagen Touareg","sum_comment":"","brand_unclear":false,"year":"2013","brand_hidden":false,"brand_info_hidden":false,"brand_info_unclear":false,"sum_rent_comment":"","sum_rent":""}]},"id":"vulyk_62_9","banks":{"45":[{"sum_units":"UAH","sum_hidden":false,"sum_foreign_units_hidden":false,"sum":"6856","sum_foreign":"","sum_foreign_comment":"","sum_foreign_hidden":false,"sum_comment":"","sum_comment_unclear":false,"sum_foreign_units":"UAH","sum_comment_hidden":false,"sum_unclear":false}],"46":[{"sum_units":"UAH","sum_hidden":true,"sum_foreign_units_hidden":false,"sum":"","sum_foreign":"","sum_foreign_comment":"","sum_foreign_hidden":false,"sum_comment":"","sum_comment_unclear":false,"sum_foreign_units":"UAH","sum_comment_hidden":false,"sum_unclear":false}]},"declaration":{"additional_info_text":"","notfull_lostpages":"","date":"2015-03-28T00:00:00","notfull":"","additional_info":"","url":"http://static.declarations.com.ua/declarations/chosen_ones/mega_batch/kravchenko_kostiantyn_volodymyrovych.pdf"},"liabilities":{"54":{"sum_foreign_comment":"","sum":"330","sum_comment":"","sum_hidden":false,"sum_comment_hidden":false,"sum_foreign":""},"55":{"sum_foreign_comment":"","sum":"","sum_comment":"","sum_hidden":true,"sum_comment_hidden":false,"sum_unclear":false,"sum_foreign":""},"56":{"sum_foreign_comment":"","sum":"","sum_comment":"","sum_hidden":true,"sum_unclear":false,"sum_foreign":""},"57":{"sum_foreign_comment":"","sum":"","sum_comment":"","sum_hidden":true,"sum_comment_hidden":true,"sum_unclear":true,"sum_foreign":""},"58":{"sum_foreign_comment":"","sum_foreign_hidden":true,"sum_comment":"","sum_hidden":false,"sum_comment_hidden":false,"sum_unclear":true,"sum":"385","sum_foreign":""},"59":{"sum_foreign_comment":"","sum":"","sum_comment":"","sum_foreign":""},"60":{"sum_foreign_comment":"","sum_foreign_hidden":true,"sum_comment":"","sum_hidden":false,"sum_comment_hidden":false,"sum_unclear":false,"sum":"324","sum_foreign":""},"61":{"sum_foreign_comment":"","sum_foreign_hidden":true,"sum_comment":"","sum_hidden":true,"sum":"","sum_foreign":""},"62":{"sum_foreign_comment":"","sum":"","sum_comment":"","sum_unclear":false,"sum_foreign":""},"63":{"sum_foreign_comment":"","sum":"","sum_comment":"","sum_hidden":false,"sum_comment_hidden":true,"sum_unclear":true,"sum_foreign":""},"64":{"sum_foreign_comment":"","sum":"140","sum_comment":"","sum_comment_unclear":false,"sum_hidden":false,"sum_comment_hidden":false,"sum_foreign":""}},"ft_src":"330\n140\n385\n324\nсуддя одеського апеляційного адміністративного суду\nОдеська область\nАпеляційний адміністративний суд\nКостянтин\nРусанова Ніна Анатоліївна\nПодружжя\nКравченко Марія Костянтинівна\nДитина\nЯмпольська Олена Миколаївна\nІнше\nТеща\nЯмпольський Юрій Іванович\nІнше\nТесть\nВолодимирович\nКравченко Костянтин Володимирович\nКостянтин Володимирович Кравченко\nКостянтин Кравченко\nКравченко Костянтин Володимирович\nКравченко Костянтин Володимирович\nКравченко\nVolkswagen Touareg\n2967 куб. см.\n2013\n6856\n2014\n2967 куб. см.\n2013\nVolkswagen Touareg\n6856\n600\n1195\n7/8 частин\n200\n96\n7/8 частин\n178\n76\nПодружжя\nРусанова Ніна Анатоліївна\nДитина\nКравченко Марія Костянтинівна\nІнше\nТеща\nЯмпольська Олена Миколаївна\nІнше\nТесть\nЯмпольський Юрій Іванович\nКравченко Костянтин Володимирович\nКостянтин Володимирович Кравченко\nКостянтин Кравченко\nКравченко Костянтин Володимирович\nКравченко Костянтин Володимирович\nКостянтин\nВолодимирович\nАпеляційний адміністративний суд\nсуддя одеського апеляційного адміністративного суду\nОдеська область\nКравченко\n140\n324\n385\n330\n221596\n1300\n31962\n225884\n4456\n253558\n381620\n149980\n2014\n385\n140\n330\n324\n76\n7/8 частин\n96\n178\n600\n7/8 частин\n1195\n200\nПодружжя\nРусанова Ніна Анатоліївна\nКравченко Марія Костянтинівна\nДитина\nТеща\nЯмпольська Олена Миколаївна\nІнше\nТесть\nЯмпольський Юрій Іванович\nІнше\nВолодимирович\nКравченко\nКостянтин\nКравченко Костянтин Володимирович\nКостянтин Володимирович Кравченко\nКостянтин Кравченко\nКравченко Костянтин Володимирович\nОдеська область\nсуддя одеського апеляційного адміністративного суду\nАпеляційний адміністративний суд\nКравченко Костянтин Володимирович\n1300\n221596\n4456\n381620\n253558\n149980\n225884\n31962\nVolkswagen Touareg\n2967 куб. см.\n2013\n4456\n31962\n225884\n253558\n381620\n149980\n1300\n221596\n76\n7/8 частин\n96\n178\n600\n7/8 частин\n1195\n200\n6856\n2014","general":{"inn":"","name":"Костянтин","inn_unclear":false,"family":[{"inn":"","inn_hidden":true,"relations_unclear":false,"relations_hidden":false,"relations_other":"","relations":"Подружжя","name_hidden":false,"inn_unclear":false,"family_name":"Русанова Ніна Анатоліївна","name_unclear":false},{"inn":"","inn_hidden":false,"relations_hidden":false,"family_name":"Кравченко Марія Костянтинівна","relations_other":"","relations":"Дитина","name_hidden":false,"name_unclear":false},{"inn":"","relations":"Інше","relations_other":"Теща","inn_hidden":false,"family_name":"Ямпольська Олена Миколаївна","name_hidden":false,"name_unclear":false},{"inn":"","relations":"Інше","relations_other":"Тесть","inn_hidden":false,"family_name":"Ямпольський Юрій Іванович","name_hidden":false,"name_unclear":false}],"inn_hidden":true,"family_raw":"","last_name":"Кравченко","post":{"post_unclear":false,"post":"суддя одеського апеляційного адміністративного суду","post_hidden":false,"region":"Одеська область","region_hidden":false,"office":"Апеляційний адміністративний суд","office_hidden":false,"office_unclear":false},"full_name_suggest":{"output":"Кравченко Костянтин Володимирович","input":["Кравченко Костянтин Володимирович","Костянтин Володимирович Кравченко","Костянтин Кравченко"]},"full_name":"Кравченко Костянтин Володимирович","addresses":[{"place_city_type_unclear":false,"place_address":"","place_district_hidden":false,"place_city_type":"","place_address_hidden":false,"place_address_unclear":false,"place_city_type_hidden":false,"place":"","place_district":"","place_unclear":false,"place_city":"","place_city_unclear":false,"place_hidden":true,"place_city_hidden":false,"place_district_unclear":false}],"patronymic":"Володимирович","last_name_unclear":false,"name_unclear":false},"source":"VULYK","estate":{"29":[{"region_unclear":false,"space_hidden":false,"address_hidden":false,"region_hidden":true,"space_comment":"","space_unclear":false,"space":"600","address":"","region":"","costs_property":"","costs_rent_comment":"","address_unclear":false,"space_units":"м²","costs_property_comment":"","costs_rent":""},{"region_unclear":false,"space_unclear":false,"address_hidden":false,"region_hidden":false,"space_comment":"7/8 частин","space":"1195","address":"","region":"","costs_property":"","costs_rent_comment":"","space_units":"","costs_property_comment":"","costs_rent":""},{"space_units_unclear":false,"address_hidden":false,"region_hidden":false,"space_comment":"","space":"200","address":"","region":"","costs_property":"","costs_rent_comment":"","space_units":"","costs_property_comment":"","costs_rent":""}],"30":[{"space_hidden":false,"address_hidden":false,"region_hidden":true,"space_comment":"7/8 частин","space_unclear":false,"space":"96","address":"","region":"","costs_property":"","costs_rent_comment":"","space_comment_unclear":false,"address_unclear":false,"space_units":"м²","costs_property_comment":"","costs_rent":""},{"costs_rent":"","space_unclear":false,"region":"","costs_property":"","costs_rent_comment":"","region_hidden":false,"space_comment":"","costs_property_comment":"","space_units":"","space":"178","address":""}],"31":[{"region_unclear":false,"space_hidden":false,"address_hidden":false,"region_hidden":true,"space_comment":"","space_unclear":false,"space":"76","costs_property_unclear":false,"region":"","costs_property":"","costs_rent_comment":"","space_comment_unclear":false,"address_unclear":false,"space_units":"м²","costs_property_comment":"","costs_rent":"","address":""}]},"intro":{"declaration_year":"2014","isnotdeclaration":"","declaration_year_unclear":false,"declaration_year_hidden":false}}