{"income":{"5":{"family_comment":"","family_unclear":false,"value":"162467","family":"1266","comment":""},"6":{"value":"162467","family_comment":"","value_unclear":false,"family_unclear":false,"family":"1266","comment":""},"7":{"value":"","family_comment":"","value_unclear":false,"family_unclear":false,"source_name":"","family":"","comment":"","source_name_hidden":false},"8":{"family_comment":"","value":"","family":"","comment":""},"9":{"family_comment":"","value":"","family":"","comment":""},"10":{"family_comment":"","value":"","value_unclear":false,"family":"","comment":""},"11":{"family_comment":"","value":"","family":"","comment":""},"12":{"family_comment":"","value":"","family":"","comment":""},"13":{"family_comment":"","value":"","family":"","comment":""},"14":{"family_comment":"","value":"","family":"","comment":""},"15":{"family_comment":"","value":"","family":"","comment":""},"16":{"family_comment":"","value":"","family":"","comment":""},"17":{"family_comment":"","value":"","family":"","comment":""},"18":{"family_comment":"","value":"","family":"","comment":""},"19":{"family_comment":"","value":"","family":"","comment":""},"20":{"value":"","value_unclear":false,"comment_hidden":false,"family_comment":"","comment_unclear":false,"comment":"","family":""}},"vehicle":{"35":[{"year_hidden":false,"brand_info":"2.4 л., 160 к.с.","sum_rent_comment":"","year":"2008","brand_info_hidden":false,"year_unclear":false,"sum_rent":"","sum":"","brand":"Mitsubishi","sum_comment":"","brand_unclear":false,"brand_hidden":false,"sum_unclear":false}]},"id":"vulyk_96_31","declaration":{"additional_info_text":"","notfull_lostpages":"","date":"2016-03-29T00:00:00","notfull":"","additional_info":"","url":"http://static.declarations.com.ua/declarations/chosen_ones/judges_batch/245_kikhtenko_serhii_oleksandrovych_2015.pdf"},"liabilities":{"54":{"sum_foreign_comment":"","sum":"","sum_comment":"","sum_hidden":false,"sum_comment_hidden":false,"sum_foreign":""},"55":{"sum_foreign_comment":"","sum":"","sum_comment":"","sum_foreign":""},"56":{"sum_foreign_comment":"","sum":"","sum_comment":"","sum_unclear":false,"sum_foreign":""},"57":{"sum_foreign_comment":"","sum_comment_hidden":false,"sum":"","sum_comment":"","sum_foreign":""},"58":{"sum_foreign_comment":"","sum":"","sum_comment":"","sum_comment_hidden":false,"sum_unclear":false,"sum_foreign":""},"59":{"sum_foreign_comment":"","sum":"","sum_comment":"","sum_foreign":""},"60":{"sum_foreign_comment":"","sum_comment_hidden":false,"sum":"","sum_comment":"","sum_foreign":""},"61":{"sum_foreign_comment":"","sum":"","sum_comment":"","sum_foreign":""},"62":{"sum_foreign_comment":"","sum":"","sum_comment":"","sum_foreign":""},"63":{"sum_foreign_comment":"","sum_comment_hidden":false,"sum":"","sum_comment":"","sum_foreign":""},"64":{"sum_foreign_comment":"","sum_comment_hidden":false,"sum":"","sum_comment":"","sum_foreign":""}},"ft_src":"Богуслав\n09700\nКиївська область\nсуддя богуславського районного суду київської області\nКиївська область\nЗагальний місцевий суд\nСергій\nКіхтенко Тетяна Олександрівна\nПодружжя\nКіхтенко Кирило Сергійович\nДитина\nОлександрович\nКіхтенко Сергій Олександрович\nКіхтенко\nКіхтенко Сергій Олександрович\nСергій Олександрович Кіхтенко\nСергій Кіхтенко\nКіхтенко Сергій Олександрович\n2.4 л., 160 к.с.\nMitsubishi\n2008\nЧеркаська область\nм. Черкаси\n17.5\nм. Корсунь-Шевченківський\n65\nЧеркаська область\n2015\n1266\n162467\n1266\n162467\n2.4 л., 160 к.с.\nMitsubishi\n2008\n2015\nКіхтенко Сергій Олександрович\nСергій Олександрович Кіхтенко\nСергій Кіхтенко\nКіхтенко Сергій Олександрович\nКіхтенко Сергій Олександрович\nСергій\nКіхтенко\nКиївська область\nсуддя богуславського районного суду київської області\nЗагальний місцевий суд\nОлександрович\n09700\nКиївська область\nБогуслав\nПодружжя\nКіхтенко Тетяна Олександрівна\nДитина\nКіхтенко Кирило Сергійович\n1266\n162467\n162467\n1266\nм. Черкаси\nЧеркаська область\n17.5\n65\nм. Корсунь-Шевченківський\nЧеркаська область\nКіхтенко Тетяна Олександрівна\nПодружжя\nДитина\nКіхтенко Кирило Сергійович\nСергій\nОлександрович\nКіхтенко\nКіхтенко Сергій Олександрович\nСергій Олександрович Кіхтенко\nСергій Кіхтенко\nКіхтенко Сергій Олександрович\nКиївська область\nБогуслав\n09700\nсуддя богуславського районного суду київської області\nКиївська область\nЗагальний місцевий суд\nКіхтенко Сергій Олександрович\nMitsubishi\n2.4 л., 160 к.с.\n2008\n1266\n162467\n162467\n1266\nм. Черкаси\nЧеркаська область\n17.5\n65\nм. Корсунь-Шевченківський\nЧеркаська область\n2015","general":{"inn":"","name":"Сергій","family":[{"inn":"","inn_hidden":true,"inn_unclear":false,"relations_hidden":false,"relations_other":"","relations":"Подружжя","name_hidden":true,"family_name":"Кіхтенко Тетяна Олександрівна","name_unclear":false},{"inn":"","relations":"Дитина","relations_other":"","inn_hidden":false,"family_name":"Кіхтенко Кирило Сергійович","name_hidden":false,"name_unclear":false}],"patronymic":"Олександрович","inn_hidden":true,"family_raw":"","last_name":"Кіхтенко","post":{"office":"Загальний місцевий суд","region":"Київська область","office_unclear":false,"post":"суддя богуславського районного суду київської області"},"full_name":"Кіхтенко Сергій Олександрович","addresses":[{"place_district":"","place_city_hidden":false,"place_city":"Богуслав","place_city_type_hidden":false,"place_district_hidden":false,"place_city_type":"Місто","place_address_hidden":true,"place_address":"09700","place_hidden":false,"place":"Київська область"}],"patronymic_hidden":false,"full_name_suggest":{"output":"Кіхтенко Сергій Олександрович","input":["Кіхтенко Сергій Олександрович","Сергій Олександрович Кіхтенко","Сергій Кіхтенко"]}},"source":"VULYK","estate":{"25":[{"space_comment_unclear":false,"space_unclear":false,"costs":"","costs_comment":"","address_hidden":false,"region_hidden":false,"space_comment":"","space_hidden":false,"space":"65","address":"м. Корсунь-Шевченківський","costs_rent_comment_unclear":false,"region":"Черкаська область","address_unclear":false,"costs_rent_comment":"","costs_unclear":false,"space_comment_hidden":false,"space_units":"м²","costs_rent":""}],"31":[{"space_unclear":false,"address_hidden":false,"region_hidden":false,"space_comment":"","space_hidden":false,"space":"17.5","address":"м. Черкаси","region":"Черкаська область","costs_property":"","costs_rent_comment":"","address_unclear":false,"space_units":"м²","costs_property_comment":"","costs_rent":""}]},"intro":{"declaration_year":"2015","isnotdeclaration":""}}