{"income":{"5":{"value":"203604","family_comment":"","value_unclear":false,"family":"70717","family_unclear":false,"comment_unclear":false,"comment":"","family_comment_unclear":false},"6":{"value":"192443","family_comment":"","value_unclear":false,"family_unclear":false,"family":"70717","comment":""},"7":{"source_name_unclear":false,"value":"","value_unclear":false,"family_comment":"","source_name":"","family":"","comment":"","source_name_hidden":false},"8":{"family_comment":"","value":"","family":"","comment":""},"9":{"family_comment":"","value":"8644","family":"","comment":""},"10":{"family_comment":"","value":"","value_unclear":false,"family":"","comment":""},"11":{"value":"","value_unclear":false,"value_hidden":false,"family_comment":"","family":"","comment":""},"12":{"family_comment":"","value":"","family":"","comment":"","value_hidden":false},"13":{"family_comment":"","value":"","family":"","comment":""},"14":{"family_comment":"","value":"","family":"","comment":""},"15":{"family_comment":"","value":"","family":"","comment":""},"16":{"family_comment":"","value":"","family":"","comment":""},"17":{"family_comment":"","value":"","family":"","comment":""},"18":{"family_comment":"","value":"","family":"","comment":""},"19":{"family_comment":"","family_unclear":false,"value":"2517","family":"","comment":""},"20":{"family_comment":"","family_unclear":false,"value":"","family":"","comment":""}},"vehicle":{"35":[{"year_hidden":false,"brand_info":"1.4 л","sum_rent_comment":"","year":"2008","sum_hidden":false,"brand_info_hidden":false,"brand_info_unclear":false,"year_unclear":false,"sum_rent":"","sum":"","brand":"Ford Fusion","sum_comment":"","brand_unclear":false,"brand_hidden":false}]},"id":"vulyk_61_31","banks":{"45":[{"sum_foreign_comment":"","sum_units":"UAH","sum_comment":"","sum_foreign_units":"UAH","sum_comment_hidden":false,"sum_unclear":false,"sum":"90900","sum_foreign":""}],"46":[{"sum_foreign_comment":"","sum_units":"UAH","sum_comment":"","sum_foreign_units":"UAH","sum":"90900","sum_foreign":""}]},"declaration":{"additional_info_text":"","notfull_lostpages":"","date":"2015-03-31T00:00:00","notfull":"","additional_info":"","url":"http://static.declarations.com.ua/declarations/chosen_ones/mega_batch/bessarab_natalia_mykolaivna.pdf"},"liabilities":{"54":{"sum_foreign_comment":"","sum":"","sum_comment":"","sum_comment_unclear":false,"sum_unclear":false,"sum_foreign":""},"55":{"sum_foreign_comment":"","sum":"","sum_comment":"","sum_foreign":""},"56":{"sum_foreign_comment":"","sum":"","sum_comment":"","sum_unclear":false,"sum_foreign":""},"57":{"sum_foreign_comment":"","sum":"","sum_comment":"","sum_comment_hidden":false,"sum_unclear":false,"sum_foreign":""},"58":{"sum_foreign_comment":"","sum":"","sum_comment":"","sum_unclear":false,"sum_foreign":""},"59":{"sum_foreign_comment":"","sum":"","sum_comment":"","sum_foreign":""},"60":{"sum_foreign_comment":"","sum_foreign_hidden":false,"sum_comment":"","sum_hidden":false,"sum":"","sum_foreign":""},"61":{"sum_foreign_comment":"","sum":"","sum_comment":"","sum_foreign":""},"62":{"sum_foreign_comment":"","sum":"","sum_comment":"","sum_unclear":false,"sum_foreign":""},"63":{"sum_foreign_comment":"","sum":"","sum_comment":"","sum_hidden":false,"sum_unclear":false,"sum_foreign":""},"64":{"sum_foreign_comment":"","sum":"","sum_hidden":false,"sum_comment":"","sum_foreign":""}},"ft_src":"суддя вінницького міського суду вінницької області\nВінницька область\nЗагальний місцевий суд\nНаталя\nНечипайло М. О\nДитина\nНечитайло О. Ю\nПодружжя\nМиколаївна\nБессараб Наталя Миколаївна\nНаталя Миколаївна Бессараб\nНаталя Бессараб\nБессараб Наталя Миколаївна\nБессараб Наталя Миколаївна\nБессараб\n1.4 л\nFord Fusion\n2008\n90900\n90900\n2014\n1.4 л\nFord Fusion\n2008\n90900\n90900\n2.3057\n2.172\n1.4021\n.0839\n33.1\nБессараб Наталя Миколаївна\nНаталя Миколаївна Бессараб\nНаталя Бессараб\nБессараб Наталя Миколаївна\nБессараб Наталя Миколаївна\nДитина\nНечипайло М. О\nПодружжя\nНечитайло О. Ю\nНаталя\nМиколаївна\nВінницька область\nЗагальний місцевий суд\nсуддя вінницького міського суду вінницької області\nБессараб\n70717\n192443\n203604\n70717\n8644\n2517\n2014\n2.3057\n2.172\n1.4021\n.0839\n33.1\nНечипайло М. О\nДитина\nНечитайло О. Ю\nПодружжя\nМиколаївна\nБессараб\nНаталя\nБессараб Наталя Миколаївна\nНаталя Миколаївна Бессараб\nНаталя Бессараб\nБессараб Наталя Миколаївна\nВінницька область\nсуддя вінницького міського суду вінницької області\nЗагальний місцевий суд\nБессараб Наталя Миколаївна\n70717\n192443\n70717\n203604\n2517\n8644\nFord Fusion\n1.4 л\n2008\n2517\n203604\n70717\n8644\n192443\n70717\n33.1\n2.3057\n2.172\n1.4021\n.0839\n90900\n90900\n2014","general":{"inn":"","name":"Наталя","patronymic_unclear":false,"family":[{"inn":"","inn_hidden":false,"relations_unclear":false,"relations_hidden":false,"relations_other":"","relations":"Дитина","name_hidden":false,"family_name":"Нечипайло М. О","name_unclear":false},{"inn":"","relations":"Подружжя","relations_other":"","inn_hidden":false,"family_name":"Нечитайло О. Ю","name_hidden":false,"name_unclear":false}],"patronymic":"Миколаївна","inn_hidden":false,"family_raw":"","inn_unclear":false,"post":{"post_unclear":false,"region_unclear":false,"post":"суддя вінницького міського суду вінницької області","office":"Загальний місцевий суд","region":"Вінницька область","post_hidden":false,"office_hidden":false,"region_hidden":false},"full_name_suggest":{"output":"Бессараб Наталя Миколаївна","input":["Бессараб Наталя Миколаївна","Наталя Миколаївна Бессараб","Наталя Бессараб"]},"full_name":"Бессараб Наталя Миколаївна","last_name":"Бессараб","patronymic_hidden":false,"last_name_unclear":false,"name_unclear":false},"source":"VULYK","estate":{"23":[{"region_unclear":false,"space_unclear":false,"costs":"","costs_comment":"","address_hidden":false,"region_hidden":false,"space_comment":"","space":"2.3057","address":"","region":"","address_unclear":false,"costs_rent_comment":"","space_comment_unclear":false,"space_units":"га","space_units_unclear":false,"costs_rent":""},{"costs_rent":"","region":"","costs":"","costs_rent_comment":"","costs_comment":"","address_hidden":false,"region_hidden":false,"space_comment":"","space_units":"га","space":"2.172","address":""},{"costs_rent":"","space_unclear":false,"region":"","costs":"","costs_rent_comment":"","costs_comment":"","space_comment":"","space_units":"га","space":"1.4021","address":""},{"costs_rent":"","region":"","costs":"","costs_rent_comment":"","costs_comment":"","space_comment":"","space_units":"га","space":".0839","address":""}],"25":[{"region_unclear":false,"space_hidden":false,"costs":"","costs_comment":"","address_hidden":false,"region_hidden":false,"space_comment":"","space_unclear":false,"space":"33.1","address":"","costs_comment_unclear":false,"costs_unclear":false,"region":"","address_unclear":false,"costs_rent_comment":"","space_comment_unclear":false,"space_units":"м²","costs_rent":""}]},"intro":{"declaration_year":"2014","isnotdeclaration":"","declaration_year_hidden":false}}