{"income":{"5":{"family_comment":"","value":"208992","value_unclear":false,"family":"36730","comment":""},"6":{"value":"208992","value_unclear":false,"family_hidden":true,"family_comment":"","family":"","comment":""},"7":{"source_name_unclear":false,"value":"","family_comment":"","source_name":"","family":"","comment":""},"8":{"family_comment":"","value":"","family":"","comment":""},"9":{"family_comment":"","value":"","family":"36730","comment":""},"10":{"family_comment":"","value":"","family":"","comment":""},"11":{"family_comment":"","value":"","comment_unclear":false,"family":"","comment":""},"12":{"family_comment":"","value":"","family":"","comment":""},"13":{"family_comment":"","value":"","family":"","comment":""},"14":{"family_comment":"","value":"","family":"","comment":""},"15":{"family_comment":"","value":"","family":"","comment":""},"16":{"family_comment":"","value":"","family":"","comment":""},"17":{"family_comment":"","value":"","family":"","comment":""},"18":{"family_comment":"","value":"","family":"","comment":""},"19":{"family_comment":"","value":"","family":"","comment":""},"20":{"value":"","family_comment":"","value_unclear":false,"family_unclear":false,"comment_unclear":false,"comment":"","family":""}},"vehicle":{"40":[{"brand_info":"3556 куб. см., 249 к. с., 4715 мм, особиста приватна власність","sum":"","brand":"Toyota Land Cruiser Prado","sum_comment":"","year":"2008","brand_hidden":false,"brand_info_hidden":false,"brand_info_unclear":true,"sum_rent_comment":"","sum_rent":""},{"brand_info":"4461 куб. см., 235 к. с., 4950 мм, особиста приватна власність","sum_rent_comment":"","brand":"Toyota Land Cruiser 200","sum_comment":"","year":"2009","brand_info_unclear":true,"sum":"","sum_rent":""}]},"id":"vulyk_101_193","banks":{"51":[{"sum_foreign_comment":"","sum_units":"UAH","sum_comment":"","sum_hidden":false,"sum_foreign_units":"UAH","sum_comment_hidden":true,"sum_unclear":false,"sum":"172760","sum_foreign":""}]},"declaration":{"additional_info_text":"","notfull_lostpages":"","date":"2016-03-31T00:00:00","notfull":"","additional_info":"","url":"http://static.declarations.com.ua/declarations/chosen_ones/judges_batch/908_vasylyshyn_valerii_oleksandrovych_2015.pdf"},"liabilities":{"54":{"sum_foreign_comment":"","sum":"","sum_comment":"","sum_comment_unclear":false,"sum_hidden":false,"sum_comment_hidden":false,"sum_unclear":false,"sum_foreign":""},"55":{"sum_foreign_comment":"","sum":"","sum_comment":"","sum_foreign":""},"56":{"sum_foreign_comment":"","sum":"","sum_comment":"","sum_comment_hidden":false,"sum_unclear":false,"sum_foreign":""},"57":{"sum_foreign_comment":"","sum":"","sum_comment":"","sum_hidden":false,"sum_comment_hidden":false,"sum_unclear":false,"sum_foreign":""},"58":{"sum_foreign_comment":"","sum":"","sum_comment":"","sum_comment_unclear":false,"sum_hidden":false,"sum_comment_hidden":false,"sum_unclear":false,"sum_foreign":""},"59":{"sum_foreign_comment":"","sum":"","sum_comment":"","sum_foreign":""},"60":{"sum_foreign_comment":"","sum":"","sum_comment":"","sum_hidden":false,"sum_comment_hidden":false,"sum_unclear":false,"sum_foreign":""},"61":{"sum_foreign_comment":"","sum":"","sum_comment":"","sum_foreign":""},"62":{"sum_foreign_comment":"","sum":"","sum_comment":"","sum_comment_unclear":false,"sum_foreign":""},"63":{"sum_foreign_comment":"","sum_comment":"","sum":"","sum_comment_hidden":false,"sum_foreign":""},"64":{"sum_foreign_comment":"","sum_comment":"","sum":"","sum_comment_hidden":false,"sum_foreign":""}},"ft_src":"3556 куб. см., 249 к. с., 4715 мм, особиста приватна власність\nToyota Land Cruiser Prado\n2008\n4461 куб. см., 235 к. с., 4950 мм, особиста приватна власність\n2009\nToyota Land Cruiser 200\n172760\n2015\n3556 куб. см., 249 к. с., 4715 мм, особиста приватна власність\n2008\nToyota Land Cruiser Prado\n4461 куб. см., 235 к. с., 4950 мм, особиста приватна власність\nToyota Land Cruiser 200\n2009\n172760\n2264\n1800\n1200\n17\n15.5\n1/3\n65.8\n65.8\n1/3\n85.8\n65.8\n1/3 частина власність\nВасилишин Валерій Олександрович\nВалерій Олександрович Василишин\nВалерій Василишин\nВасилишин Валерій Олександрович\nВалерій\nВасилишин Валерій Олександрович\nОлександрович\nголова броварського міськрайонного суду київської області\nКиївська область\nЗагальний місцевий суд\nВасилишин\nПодружжя\nВасилишина Н. Т\nДитина\nВасилишин Д. В\n208992\n208992\n36730\n36730\n2015\n2264\n1800\n17\n15.5\n1200\n1/3\n65.8\n1/3\n65.8\n85.8\n1/3 частина власність\n65.8\nВасилишина Н. Т\nПодружжя\nВасилишин Д. В\nДитина\nВалерій\nОлександрович\nВасилишин\nВасилишин Валерій Олександрович\nВалерій Олександрович Василишин\nВалерій Василишин\nВасилишин Валерій Олександрович\nголова броварського міськрайонного суду київської області\nКиївська область\nЗагальний місцевий суд\nВасилишин Валерій Олександрович\n208992\n36730\n36730\n208992","general":{"inn":"","name":"Валерій","last_name":"Василишин","family":[{"inn":"","inn_hidden":true,"family_name":"Василишина Н. Т","relations_other":"","relations":"Подружжя","name_hidden":true,"name_unclear":false},{"inn":"","inn_hidden":false,"relations_unclear":false,"family_name":"Василишин Д. В","relations_other":"","relations":"Дитина","name_hidden":false,"name_unclear":false}],"inn_hidden":true,"family_raw":"","inn_unclear":false,"post":{"region":"Київська область","region_unclear":false,"post":"голова броварського міськрайонного суду київської області","office_unclear":false,"office":"Загальний місцевий суд"},"full_name":"Василишин Валерій Олександрович","addresses":[{"place_district":"","place_address_hidden":true,"place_hidden":true,"place_address":"","place_district_hidden":false,"place_city_type":"","place_city_hidden":true,"place_city_type_hidden":false,"place_city":"","place":""}],"patronymic":"Олександрович","patronymic_hidden":false,"full_name_suggest":{"output":"Василишин Валерій Олександрович","input":["Василишин Валерій Олександрович","Валерій Олександрович Василишин","Валерій Василишин"]}},"source":"VULYK","estate":{"23":[{"space_unclear":false,"costs":"","costs_comment":"","address_hidden":false,"region_hidden":true,"space_comment":"","space_hidden":false,"space":"2264","address":"","costs_comment_unclear":false,"region":"","space_units_unclear":false,"space_units":"м²","costs_rent":"","costs_rent_comment":""},{"costs_rent":"","space_unclear":true,"region":"","costs":"","costs_rent_comment":"","costs_comment":"","space_comment":"","space_units":"м²","space":"1800","address":""}],"25":[{"space_unclear":false,"costs":"","costs_comment":"","address_hidden":false,"region_hidden":true,"space_comment":"","space_hidden":false,"space":"85.8","address":"","region":"","costs_rent_comment":"","space_comment_unclear":false,"space_units":"м²","costs_rent":""},{"space_unclear":false,"costs":"","costs_comment":"","space_comment":"1/3 частина власність","space_hidden":false,"space":"65.8","address":"","region":"","costs_rent_comment":"","space_comment_unclear":false,"space_units":"м²","costs_rent":""}],"27":[{"space_hidden":false,"costs":"","costs_comment":"","address_hidden":false,"region_hidden":true,"space_comment":"","space":"17","address":"","region":"","costs_rent_comment":"","space_units":"м²","costs_rent":""},{"costs_rent":"","region":"","costs":"","costs_rent_comment":"","costs_comment":"","space_comment":"","space_units":"м²","space":"15.5","address":""}],"29":[{"costs_rent":"","region":"","costs_property":"","costs_rent_comment":"","address_hidden":false,"region_hidden":true,"space_comment":"","costs_property_comment":"","space_units":"м²","space":"1200","address":""}],"31":[{"space_unclear":false,"address_hidden":false,"region_hidden":true,"space_comment":"1/3","space_hidden":false,"space":"65.8","address":"","costs_rent_comment_unclear":false,"region":"","costs_property":"","costs_rent_comment":"","space_units":"м²","costs_property_comment":"","costs_rent":""},{"costs_rent":"","region":"","costs_property":"","costs_rent_comment":"","space_comment":"1/3","costs_property_comment":"","space_units":"м²","space":"65.8","address":""}]},"intro":{"declaration_year":"2015"}}