{"income":{"5":{"family_comment":"","value":"219212.88","family":"","comment":""},"6":{"value":"202629.42","family_comment":"","value_unclear":false,"comment_hidden":false,"family_unclear":false,"family":"","comment":""},"7":{"family_comment":"","value":"","source_name":"","family":"","comment":""},"8":{"family_comment":"","value":"","family":"","comment":""},"9":{"family_comment":"","family_unclear":false,"value":"","family":"","comment":""},"10":{"family_comment":"","value":"12180","value_unclear":true,"family":"","comment":""},"11":{"family_comment":"","value":"","family":"","comment":""},"12":{"family_comment":"","value":"","family":"","comment":""},"13":{"family_comment":"","value":"","family":"","comment":""},"14":{"family_comment":"","value":"","family":"","comment":""},"15":{"family_comment":"","value":"","family":"","comment":""},"16":{"family_comment":"","value":"","family":"","comment":""},"17":{"family_comment":"","value":"","family":"","comment":""},"18":{"family_comment":"","value":"","family":"","comment":""},"19":{"family_comment":"","value":"","family":"","comment":""},"20":{"value":"4403.46","family":"","value_unclear":false,"family_hidden":false,"family_comment":"","comment_unclear":false,"comment":"","family_comment_unclear":false}},"vehicle":{"35":[{"year_hidden":false,"brand_info":"об'єм циліндрів двигуна 1.332","sum_rent_comment":"","year":"2006","brand_info_hidden":false,"brand_info_unclear":false,"sum_rent":"","sum":"","brand":"Mitsubishi Colt","sum_comment":"","brand_unclear":false,"brand_hidden":false}]},"id":"vulyk_97_182","declaration":{"additional_info_text":"","notfull_lostpages":"","date":"2015-03-24T00:00:00","notfull":"","additional_info":"","url":"http://static.declarations.com.ua/declarations/chosen_ones/judges_batch/4097_ivchenko_tetiana_pavlivna.pdf"},"liabilities":{"54":{"sum_foreign_comment":"","sum":"400.48","sum_comment":"СТ Група ТАС автоцивільний поліс-330,48, ПАТ СК Провідна подорожуючих 70,00","sum_comment_unclear":false,"sum_hidden":false,"sum_comment_hidden":false,"sum_unclear":false,"sum_foreign":""},"55":{"sum_foreign_comment":"","sum":"","sum_comment":"","sum_foreign":""},"56":{"sum_foreign_comment":"","sum":"","sum_comment":"","sum_foreign":""},"57":{"sum_foreign_comment":"","sum":"","sum_comment":"","sum_comment_unclear":false,"sum_hidden":false,"sum_comment_hidden":false,"sum_unclear":false,"sum_foreign":""},"58":{"sum_foreign_comment":"","sum":"","sum_comment":"","sum_comment_unclear":false,"sum_hidden":false,"sum_comment_hidden":false,"sum_unclear":false,"sum_foreign":""},"59":{"sum_foreign_comment":"","sum":"","sum_comment":"","sum_foreign":""},"60":{"sum_foreign_comment":"","sum":"","sum_comment":"","sum_comment_unclear":false,"sum_hidden":false,"sum_comment_hidden":false,"sum_foreign":""},"61":{"sum_foreign_comment":"","sum":"","sum_comment":"","sum_foreign":""},"62":{"sum_foreign_comment":"","sum":"","sum_comment":"","sum_unclear":false,"sum_foreign":""},"63":{"sum_foreign_comment":"","sum":"","sum_hidden":false,"sum_comment":"","sum_foreign":""},"64":{"sum_foreign_comment":"","sum":"","sum_comment":"","sum_foreign":""}},"ft_src":"СТ Група ТАС автоцивільний поліс-330,48, ПАТ СК Провідна подорожуючих 70,00\n400.48\nДніпропетровська область\nсуддя заводського районного суду м. дніпродзержинська дніпропетровської області\nДніпропетровська область\nЗагальний місцевий суд\nТетяна\nІвченко І. П. 31. 03. 08\nДитина\nПавлівна\nІвченко Тетяна Павлівна\nТетяна Павлівна Івченко\nТетяна Івченко\nІвченко Тетяна Павлівна\nІвченко Тетяна Павлівна\nІвченко\nоб'єм циліндрів двигуна 1.332\nMitsubishi Colt\n2006\n48.1\nм. Дніпродзержинськ\nДніпропетровська область\n2014\n202629.42\n12180\n219212.88\n4403.46\nоб'єм циліндрів двигуна 1.332\nMitsubishi Colt\n2006\n2014\nІвченко Тетяна Павлівна\nТетяна Павлівна Івченко\nТетяна Івченко\nІвченко Тетяна Павлівна\nТетяна\nДитина\nІвченко І. П. 31. 03. 08\nІвченко Тетяна Павлівна\nІвченко\nЗагальний місцевий суд\nДніпропетровська область\nсуддя заводського районного суду м. дніпродзержинська дніпропетровської області\nПавлівна\nДніпропетровська область\n400.48\nСТ Група ТАС автоцивільний поліс-330,48, ПАТ СК Провідна подорожуючих 70,00\n202629.42\n4403.46\n219212.88\n12180\n48.1\nм. Дніпродзержинськ\nДніпропетровська область\nСТ Група ТАС автоцивільний поліс-330,48, ПАТ СК Провідна подорожуючих 70,00\n400.48\nДитина\nІвченко І. П. 31. 03. 08\nПавлівна\nІвченко\nТетяна\nІвченко Тетяна Павлівна\nТетяна Павлівна Івченко\nТетяна Івченко\nІвченко Тетяна Павлівна\nДніпропетровська область\nДніпропетровська область\nЗагальний місцевий суд\nсуддя заводського районного суду м. дніпродзержинська дніпропетровської області\nІвченко Тетяна Павлівна\n2006\nMitsubishi Colt\nоб'єм циліндрів двигуна 1.332\n12180\n4403.46\n219212.88\n202629.42\nм. Дніпродзержинськ\nДніпропетровська область\n48.1\n2014","general":{"name_hidden":false,"name":"Тетяна","last_name_hidden":false,"inn":"","family":[{"inn":"","relations":"Дитина","relations_other":"","inn_hidden":true,"family_name":"Івченко І. П. 31. 03. 08","name_hidden":false,"name_unclear":false}],"patronymic":"Павлівна","inn_hidden":true,"family_raw":"","inn_unclear":false,"post":{"region_unclear":false,"region":"Дніпропетровська область","post":"суддя заводського районного суду м. дніпродзержинська дніпропетровської області","office":"Загальний місцевий суд","office_unclear":false,"post_hidden":false},"full_name":"Івченко Тетяна Павлівна","addresses":[{"place_district":"","place_city_hidden":true,"place_city":"","place_city_unclear":false,"place_district_hidden":false,"place_city_type":"","place_address_hidden":true,"place_city_type_hidden":false,"place_address":"","place_hidden":false,"place":"Дніпропетровська область"}],"last_name":"Івченко","patronymic_hidden":false,"full_name_suggest":{"output":"Івченко Тетяна Павлівна","input":["Івченко Тетяна Павлівна","Тетяна Павлівна Івченко","Тетяна Івченко"]}},"source":"VULYK","estate":{"25":[{"region_unclear":false,"space_unclear":false,"costs":"","costs_comment":"","address_hidden":true,"region_hidden":false,"space_comment":"","space_hidden":false,"space":"48.1","address":"м. Дніпродзержинськ","region":"Дніпропетровська область","costs_rent_comment":"","space_comment_unclear":false,"space_comment_hidden":false,"space_units":"м²","costs_rent":""}]},"intro":{"declaration_year":"2014","isnotdeclaration":""}}