{"income":{"5":{"value":"236002.68","family_comment":"","value_unclear":false,"family_unclear":false,"family":"195812","comment":""},"6":{"family_comment":"","value":"219001.55","value_unclear":false,"family":"","comment":""},"7":{"value":"4821.13","value_unclear":false,"family_comment":"","source_name":"Національна школа суддів України, Львівський національний університет імені Івана Франка","family":"","comment":""},"8":{"family_comment":"","value":"","family":"","comment":""},"9":{"value":"","family_comment":"","value_unclear":false,"family_unclear":false,"family":"","comment":""},"10":{"family_comment":"","value":"12180","comment_unclear":false,"family":"","comment":""},"11":{"family_comment":"","value":"","family":"","comment":""},"12":{"family_comment":"","value":"","family":"","comment":""},"13":{"family_comment":"","value":"","value_unclear":false,"family":"","comment":""},"14":{"family_comment":"","value":"","family":"","comment":""},"15":{"family_comment":"","value":"","family":"","comment":""},"16":{"family_comment":"","family_unclear":false,"value":"","family":"","comment":""},"17":{"family_comment":"","family_unclear":false,"value":"","family":"195812","comment":""},"18":{"family_comment":"","value":"","family":"","comment":""},"19":{"family_comment":"","value":"","family":"","comment":""},"20":{"value":"","family_comment":"","comment_unclear":false,"family_hidden":false,"value_hidden":false,"family_unclear":false,"value_unclear":false,"comment":"","family":""}},"vehicle":{"35":[{"brand_info":"1.8 куб. дм, в тимчасовому користуванні","sum_rent_comment":"","sum_rent_comment_unclear":false,"year":"2001","brand_info_hidden":false,"brand_info_unclear":false,"sum_rent":"","sum":"","brand":"Audi A6","sum_comment":"","brand_unclear":false,"brand_hidden":false}],"40":[{"brand_info":"1.8 куб. дм","sum":"","brand":"Audi A6","sum_comment":"","year":"1997","brand_info_hidden":false,"brand_info_unclear":false,"sum_rent_comment":"","sum_rent":""},{"brand_info":"1.6 куб. дм, в тимчасовому користуванні","sum":"","brand":"Volkswagen Golf","sum_comment":"","year":"2008","brand_info_hidden":false,"sum_rent_comment":"","sum_rent":""},{"brand_info":"2.4 куб. дм, в тимчасовому користуванні","sum":"","brand":"Honda CR-V","sum_comment":"","year":"2008","sum_rent_comment":"","sum_rent":""}]},"id":"vulyk_100_64","banks":{"51":[{"sum_foreign_comment":"","sum_unclear":false,"sum":"1635.97","sum_comment":"ПАТ Універсалбанк","sum_comment_unclear":false,"sum_foreign_units":"UAH","sum_units_unclear":false,"sum_comment_hidden":false,"sum_units":"UAH","sum_foreign":""},{"sum_foreign_comment":"","sum":"110.66","sum_comment":"АТ Укрексімбанк","sum_foreign":""}]},"declaration":{"additional_info_text":"","notfull_lostpages":"","date":"2015-03-27T00:00:00","notfull":"","additional_info":"","url":"http://static.declarations.com.ua/declarations/chosen_ones/judges_batch/4233_iurkiv_oleh_romanovych.pdf"},"liabilities":{"54":{"sum_foreign_comment":"","sum":"","sum_comment":"","sum_comment_hidden":false,"sum_unclear":false,"sum_foreign":""},"55":{"sum_foreign_comment":"","sum":"","sum_comment":"","sum_foreign":""},"56":{"sum_foreign_comment":"","sum":"","sum_comment":"","sum_unclear":false,"sum_foreign":""},"57":{"sum_foreign_comment":"","sum":"","sum_comment":"","sum_comment_unclear":false,"sum_comment_hidden":false,"sum_unclear":false,"sum_foreign":""},"58":{"sum_foreign_comment":"","sum":"","sum_comment":"","sum_comment_hidden":false,"sum_unclear":false,"sum_foreign":""},"59":{"sum_foreign_comment":"","sum":"","sum_comment":"","sum_foreign":""},"60":{"sum_foreign_comment":"","sum_comment":"","sum":"","sum_comment_hidden":false,"sum_foreign":""},"61":{"sum_foreign_comment":"","sum":"","sum_comment":"","sum_foreign":""},"62":{"sum_foreign_comment":"","sum":"","sum_comment":"","sum_unclear":false,"sum_foreign":""},"63":{"sum_foreign_comment":"","sum_comment":"","sum":"","sum_comment_hidden":false,"sum_foreign":""},"64":{"sum_foreign_comment":"","sum_comment":"","sum":"","sum_comment_hidden":false,"sum_foreign":""}},"ft_src":"1.8 куб. дм, в тимчасовому користуванні\nAudi A6\n2001\n1997\n1.8 куб. дм\nAudi A6\n1.6 куб. дм, в тимчасовому користуванні\n2008\nVolkswagen Golf\n2.4 куб. дм, в тимчасовому користуванні\n2008\nHonda CR-V\nПАТ Універсалбанк\n1635.97\nАТ Укрексімбанк\n110.66\n2014\n1.8 куб. дм, в тимчасовому користуванні\nAudi A6\n2001\nAudi A6\n1.8 куб. дм\n1997\nVolkswagen Golf\n1.6 куб. дм, в тимчасовому користуванні\n2008\n2.4 куб. дм, в тимчасовому користуванні\nHonda CR-V\n2008\n1635.97\nПАТ Універсалбанк\nАТ Укрексімбанк\n110.66\n16.9\n81\n0,080, 0,088\n.168\n.11\n28.1\n81\n95\n56.9\nПодружжя\nЮрків О. М\nДитина\nЮрків Р. О\nРоманович\nЮрків\nЮрків Олег Романович\nОлег Романович Юрків\nОлег Юрків\nЮрків Олег Романович\nЮрків Олег Романович\nОлег\nЗагальний місцевий суд\nЛьвівська область\nсуддя галицького районного суду м. львова\n4821.13\nНаціональна школа суддів України, Львівський національний університет імені Івана Франка\n219001.55\n195812\n236002.68\n195812\n12180\n2014\n0,080, 0,088\n.168\n.11\n16.9\n28.1\n81\n95\n56.9\n81\nЮрків О. М\nПодружжя\nДитина\nЮрків Р. О\nРоманович\nЮрків\nЛьвівська область\nЗагальний місцевий суд\nсуддя галицького районного суду м. львова\nЮрків Олег Романович\nЮрків Олег Романович\nОлег Романович Юрків\nОлег Юрків\nЮрків Олег Романович\nОлег\n219001.55\n12180\nНаціональна школа суддів України, Львівський національний університет імені Івана Франка\n4821.13\n195812\n236002.68\n195812","general":{"inn":"","inn_hidden":true,"last_name":"Юрків","post":{"post_unclear":false,"region_unclear":false,"post":"суддя галицького районного суду м. львова","post_hidden":false,"region":"Львівська область","office":"Загальний місцевий суд","office_unclear":false},"name":"Олег","full_name":"Юрків Олег Романович","family_raw":"","addresses":[{"place_district":"","place_address_hidden":true,"place_city":"","place_city_unclear":false,"place_district_hidden":false,"place_city_type":"","place_city_hidden":true,"place_city_type_hidden":false,"place_address":"","place_hidden":true,"place":""}],"family":[{"inn":"","relations":"Подружжя","name_hidden":true,"inn_hidden":true,"family_name":"Юрків О. М","name_unclear":false},{"inn":"","relations":"Дитина","relations_other":"","inn_hidden":false,"family_name":"Юрків Р. О","name_hidden":false,"name_unclear":false}],"full_name_suggest":{"output":"Юрків Олег Романович","input":["Юрків Олег Романович","Олег Романович Юрків","Олег Юрків"]},"patronymic":"Романович"},"source":"VULYK","estate":{"25":[{"space_unclear":false,"costs":"","costs_comment":"","address_hidden":false,"region_hidden":true,"space_comment":"","space":"81","address":"","costs_comment_unclear":false,"region":"","address_unclear":false,"costs_rent_comment":"","space_comment_unclear":false,"space_units":"м²","costs_rent":""}],"28":[{"costs_rent":"","region":"","costs":"","costs_rent_comment":"","costs_comment":"","address_hidden":false,"region_hidden":true,"space_comment":"","space_units":"м²","space":"16.9","address":""}],"29":[{"region_unclear":false,"space_unclear":false,"address_hidden":false,"region_hidden":true,"space_comment":"0,080, 0,088","space":".168","address":"","region":"","costs_property":"","costs_rent_comment":"","address_unclear":false,"space_units":"га","costs_property_comment":"","costs_rent":""},{"space_unclear":false,"address_hidden":false,"region_hidden":false,"space_comment":"","space":".11","address":"","region":"","costs_property":"","costs_rent_comment":"","space_units":"га","costs_property_comment":"","costs_rent":""}],"31":[{"region_unclear":false,"space_unclear":false,"costs_property_comment_unclear":false,"address_hidden":false,"region_hidden":true,"space_comment":"","space":"81","address":"","region":"","costs_property":"","costs_rent_comment":"","space_comment_unclear":false,"address_unclear":false,"space_units":"м²","costs_property_comment":"","costs_rent":""},{"costs_rent":"","region_unclear":false,"region":"","costs_property":"","costs_rent_comment":"","region_hidden":false,"space_comment":"","costs_property_comment":"","space_units":"м²","space":"95","address":""}],"33":[{"space_unclear":false,"address_hidden":false,"region_hidden":true,"space_comment":"","space":"28.1","address":"","region":"","costs_property":"","costs_rent_comment":"","address_unclear":false,"space_units":"м²","costs_property_comment":"","costs_rent":""}],"34":[{"costs_rent":"","region":"","costs_property":"","costs_rent_comment":"","address_hidden":false,"region_hidden":true,"space_comment":"","costs_property_comment":"","space_units":"м²","space":"56.9","address":""}]},"intro":{"declaration_year":"2014"}}