{"income":{"5":{"value":"185740","family_comment":"","value_unclear":false,"family_hidden":false,"family_unclear":false,"family":"","comment":""},"6":{"value":"173560","value_unclear":false,"comment_hidden":false,"family_hidden":false,"value_hidden":false,"family_comment":"","family":"","comment":""},"7":{"value":"","family_comment":"","source_name":"","family":"","comment":"","source_name_hidden":false},"8":{"family_comment":"","value":"","family":"","comment":""},"9":{"family_comment":"","value":"","family":"","comment":"","value_hidden":false},"10":{"value":"12180","value_unclear":false,"family_hidden":false,"value_hidden":false,"family_comment":"","family":"","comment":""},"11":{"family_comment":"","value":"","family":"","comment":""},"12":{"family_comment":"","value":"","family":"","comment":""},"13":{"family_comment":"","value":"","comment_hidden":false,"family":"","comment":""},"14":{"value":"","comment_hidden":false,"value_hidden":false,"family_comment":"","family":"","comment":""},"15":{"family_comment":"","value":"","family":"","comment":""},"16":{"family_comment":"","value":"","family":"","comment":"","value_hidden":false},"17":{"family_comment":"","value":"","family":"","comment":""},"18":{"family_comment":"","value":"","family":"","comment":""},"19":{"family_comment":"","value":"","family":"","comment":"","value_hidden":false},"20":{"value":"","family_comment":"","comment_unclear":false,"family_unclear":false,"family":"","comment":""}},"vehicle":{"35":[{"brand_info":"","sum_rent_comment":"","sum_rent_hidden":false,"year":"2010","sum_hidden":false,"brand_info_hidden":false,"brand_info_unclear":false,"sum_rent":"","sum":"79000","brand":"Volkswagen Tiguan","sum_comment":"","sum_rent_comment_hidden":false}]},"id":"vulyk_12_68","banks":{"45":[{"sum_foreign_comment":"","sum":"","sum_comment":"","sum_hidden":false,"sum_foreign_units":"UAH","sum_foreign_hidden":false,"sum_units":"UAH","sum_comment_hidden":false,"sum_unclear":false,"sum_foreign":"","sum_units_hidden":false},{"sum_foreign_comment":"","sum_units":"","sum_comment":"","sum_foreign_units":"","sum":"","sum_foreign":""}],"46":[{"sum_foreign_comment":"","sum_units":"UAH","sum_comment":"","sum_hidden":false,"sum_foreign_units":"UAH","sum":"","sum_foreign_hidden":false,"sum_foreign":""}],"47":[{"sum_foreign_comment":"","sum_units":"UAH","sum_comment":"","sum_comment_unclear":false,"sum_foreign_units":"UAH","sum":"","sum_foreign":""},{"sum_foreign_comment":"","sum_units":"","sum_comment":"","sum_foreign_units":"","sum":"","sum_foreign":""}],"48":[{"sum_foreign_comment":"","sum_units":"UAH","sum_comment":"","sum_foreign_units":"UAH","sum":"","sum_foreign":""}],"49":[{"sum_foreign_comment":"","sum_units":"UAH","sum_comment":"","sum_foreign_units":"UAH","sum":"","sum_foreign":""}],"50":[{"sum_foreign_comment":"","sum_units":"UAH","sum_comment":"","sum_foreign_units":"UAH","sum":"","sum_foreign":""}],"51":[{"sum_foreign_comment":"","sum_units":"UAH","sum_comment":"","sum_hidden":false,"sum_foreign_units":"UAH","sum_comment_hidden":false,"sum_units_hidden":false,"sum":"","sum_foreign":""}],"52":[{"sum_foreign_comment":"","sum_units":"UAH","sum_comment":"","sum_comment_unclear":false,"sum_foreign_units":"UAH","sum":"","sum_foreign":""},{"sum_foreign_comment":"","sum_units":"","sum_comment":"","sum_foreign_units":"","sum":"","sum_foreign":""},{"sum_foreign_comment":"","sum_units":"","sum_comment":"","sum_foreign_units":"","sum":"","sum_foreign":""},{"sum_foreign_comment":"","sum_units":"","sum_comment":"","sum_foreign_units":"","sum":"","sum_foreign":""}],"53":[{"sum_foreign_comment":"","sum_units":"UAH","sum_comment":"","sum_foreign_units":"UAH","sum":"","sum_foreign":""}]},"declaration":{"additional_info_text":"","notfull_lostpages":"","date":"2015-03-25T00:00:00","notfull":"","additional_info":"","url":"http://static.declarations.com.ua/declarations/chosen_ones/mega_batch/demydova_svitlana_oleksandrivna.pdf"},"liabilities":{"54":{"sum_foreign_comment":"","sum":"","sum_comment":"","sum_hidden":false,"sum_comment_hidden":false,"sum_foreign":""},"55":{"sum_foreign_comment":"","sum":"","sum_comment":"","sum_foreign":""},"56":{"sum_foreign_comment":"","sum":"","sum_comment":"","sum_foreign":""},"57":{"sum_foreign_comment":"","sum":"","sum_comment":"","sum_comment_unclear":false,"sum_hidden":false,"sum_comment_hidden":false,"sum_unclear":false,"sum_foreign":""},"58":{"sum_foreign_comment":"","sum":"","sum_comment":"","sum_comment_unclear":false,"sum_hidden":false,"sum_foreign":""},"59":{"sum_foreign_comment":"","sum":"","sum_hidden":false,"sum_comment":"","sum_foreign":""},"60":{"sum_foreign_comment":"","sum":"","sum_comment":"","sum_hidden":false,"sum_comment_hidden":false,"sum_foreign":""},"61":{"sum_foreign_comment":"","sum":"","sum_comment":"","sum_foreign":""},"62":{"sum_foreign_comment":"","sum":"","sum_comment":"","sum_comment_unclear":false,"sum_unclear":false,"sum_foreign":""},"63":{"sum_foreign_comment":"","sum":"","sum_comment":"","sum_comment_unclear":false,"sum_foreign":""},"64":{"sum_foreign_comment":"","sum":"","sum_comment":"","sum_comment_unclear":false,"sum_foreign":""}},"ft_src":"суддя жовтневого районного суду м. дніпропетровська\nДніпропетровська область\nЗагальний місцевий суд\nСвітлана\nОлександрівна\nДемидова\nДемидова Світлана Олександрівна\nДемидова Світлана Олександрівна\nСвітлана Олександрівна Демидова\nСвітлана Демидова\nДемидова Світлана Олександрівна\n79000\nVolkswagen Tiguan\n2010\n2014\n79000\nVolkswagen Tiguan\n2010\n190\nДніпропетровська область\n16\nм. Дніпропетровськ\nДніпропетровська область\n46\nДніпропетровська область\nм. Дніпропетровськ\nДемидова Світлана Олександрівна\nСвітлана Олександрівна Демидова\nСвітлана Демидова\nДемидова Світлана Олександрівна\nСвітлана\nДемидова Світлана Олександрівна\nДемидова\nЗагальний місцевий суд\nсуддя жовтневого районного суду м. дніпропетровська\nДніпропетровська область\nОлександрівна\n173560\n185740\n12180\n2014\n190\nДніпропетровська область\nм. Дніпропетровськ\n16\nДніпропетровська область\nм. Дніпропетровськ\n46\nДніпропетровська область\nДемидова Світлана Олександрівна\nСвітлана Олександрівна Демидова\nСвітлана Демидова\nДемидова Світлана Олександрівна\nОлександрівна\nДемидова\nСвітлана\nДніпропетровська область\nЗагальний місцевий суд\nсуддя жовтневого районного суду м. дніпропетровська\nДемидова Світлана Олександрівна\n173560\n12180\n185740\nVolkswagen Tiguan\n79000\n2010\n12180\n185740\n173560\nм. Дніпропетровськ\nДніпропетровська область\n46\nДніпропетровська область\n190\nм. Дніпропетровськ\nДніпропетровська область\n16\n2014","general":{"inn":"","name":"Світлана","patronymic_unclear":false,"last_name_hidden":false,"inn_unclear":false,"patronymic":"Олександрівна","inn_hidden":false,"family_raw":"","last_name":"Демидова","post":{"post_unclear":false,"post":"суддя жовтневого районного суду м. дніпропетровська","candidate":"","office_hidden":false,"region":"Дніпропетровська область","post_hidden":false,"office":"Загальний місцевий суд","office_unclear":false},"last_name_unclear":false,"full_name":"Демидова Світлана Олександрівна","patronymic_hidden":false,"full_name_suggest":{"output":"Демидова Світлана Олександрівна","input":["Демидова Світлана Олександрівна","Світлана Олександрівна Демидова","Світлана Демидова"]}},"source":"VULYK","estate":{"23":[{"space_unclear":false,"costs":"","costs_comment":"","address_hidden":false,"region_hidden":false,"space_comment":"","space_hidden":false,"space":"190","address":"","costs_comment_unclear":false,"region":"Дніпропетровська область","address_unclear":false,"costs_rent_comment":"","space_units":"м²","costs_rent":""},{"space_unclear":false,"costs":"","costs_comment":"","address_hidden":false,"region_hidden":false,"space_comment":"","space":"","address":"","region":"","costs_rent_comment":"","space_units":"","costs_rent":""},{"space_hidden":false,"costs":"","costs_comment":"","address_hidden":false,"region_hidden":false,"space_comment":"","space":"","address":"","region":"","costs_rent_comment":"","space_units":"","costs_rent":""},{"costs_rent":"","region":"","costs":"","costs_rent_comment":"","costs_comment":"","space_comment":"","space_units":"","space":"","address":""}],"25":[{"region_unclear":false,"space_hidden":false,"costs":"","costs_comment":"","costs_hidden":false,"address_hidden":false,"region_hidden":false,"space_comment":"","space_unclear":false,"space":"46","address":"м. Дніпропетровськ","region":"Дніпропетровська область","address_unclear":false,"costs_rent_comment":"","costs_rent_hidden":false,"space_comment_unclear":false,"space_units":"м²","costs_rent":""}],"27":[{"space_hidden":false,"costs":"","costs_comment":"","address_hidden":false,"region_hidden":false,"space_comment":"","space":"16","address":"м. Дніпропетровськ","region":"Дніпропетровська область","costs_rent_comment":"","space_units":"м²","costs_rent":""}]},"intro":{"declaration_year":"2014","isnotdeclaration":""}}