{"income":{"5":{"value":"195997","family_comment":"","value_unclear":false,"family_hidden":false,"value_hidden":false,"family_unclear":false,"family":"","comment":""},"6":{"value":"179026","family_comment":"","value_unclear":false,"family_hidden":false,"value_hidden":false,"family_unclear":false,"family":"","comment":""},"7":{"source_name_unclear":false,"value":"","comment_hidden":false,"family_hidden":false,"value_hidden":false,"family_comment":"","source_name":"","family":"","comment":"","source_name_hidden":false},"8":{"value":"","family_hidden":false,"value_hidden":false,"family_comment":"","family":"","comment":""},"9":{"value":"4791","family_hidden":false,"value_hidden":false,"family_comment":"","family":"","comment":""},"10":{"family_comment":"","value":"12180","family_hidden":false,"comment":"","family":""},"11":{"value":"","comment_hidden":false,"family_hidden":false,"family_comment":"","family":"","comment":""},"12":{"value":"","family_hidden":false,"value_hidden":false,"family_comment":"","family":"","comment":""},"13":{"value":"","family_hidden":false,"value_hidden":false,"family_comment":"","family":"","comment":""},"14":{"value":"","family_hidden":false,"value_hidden":false,"family_comment":"","family":"","comment":""},"15":{"family_comment":"","value":"","family_hidden":false,"comment":"","family":""},"16":{"value":"","family_hidden":false,"value_hidden":false,"family_comment":"","family":"","comment":""},"17":{"family_comment":"","value":"","family":"","comment":"","value_hidden":false},"18":{"value":"","family_hidden":false,"value_hidden":false,"family_comment":"","family":"","comment":""},"19":{"value":"","family_hidden":false,"value_hidden":false,"family_comment":"","family":"","comment":""},"20":{"value":"","comment_unclear":false,"family_hidden":false,"value_hidden":false,"family_comment":"","family":"","comment":"","family_comment_unclear":false}},"vehicle":{"35":[{"year_hidden":false,"brand_info":"2.0 л","sum_rent_comment":"","sum_rent_hidden":false,"year":"2009","sum_hidden":false,"brand_info_hidden":false,"brand_info_unclear":false,"year_unclear":false,"sum_rent":"","sum_rent_unclear":false,"sum":"","brand":"Mitsubishi Lancer Intense","sum_comment":"","brand_unclear":false,"brand_hidden":false,"sum_unclear":false}]},"id":"vulyk_34_7","banks":{"45":[{"sum_foreign_comment":"","sum_units":"UAH","sum_comment":"","sum_foreign_units":"UAH","sum_comment_hidden":false,"sum_unclear":false,"sum":"6566","sum_foreign":""},{"sum_foreign_comment":"","sum_units":"","sum_comment":"","sum_foreign_units":"","sum_comment_hidden":false,"sum":"","sum_foreign":""}],"46":[{"sum_foreign_comment":"","sum_units":"UAH","sum_comment":"","sum_foreign_units":"UAH","sum_comment_hidden":false,"sum_unclear":false,"sum":"","sum_foreign":""},{"sum_foreign_comment":"","sum_units":"","sum_comment":"","sum_foreign_units":"","sum_comment_hidden":false,"sum":"","sum_foreign":""}],"47":[{"sum_foreign_comment":"","sum_units":"UAH","sum_comment":"","sum_foreign_units":"UAH","sum":"","sum_foreign":""}],"48":[{"sum_foreign_comment":"","sum_units":"UAH","sum_comment":"","sum_foreign_units":"UAH","sum":"","sum_foreign":""}],"49":[{"sum_foreign_comment":"","sum_units":"UAH","sum_comment":"","sum_hidden":false,"sum_foreign_units":"UAH","sum":"","sum_foreign":""}],"50":[{"sum_foreign_comment":"","sum_units":"UAH","sum_comment":"","sum_hidden":false,"sum_foreign_units":"UAH","sum":"","sum_foreign":""}],"51":[{"sum_foreign_comment":"","sum_units":"UAH","sum_comment":"","sum_hidden":false,"sum_foreign_units":"UAH","sum_comment_hidden":false,"sum_unclear":false,"sum":"","sum_foreign":""},{"sum_foreign_comment":"","sum_units":"","sum_comment":"","sum_foreign_units":"","sum_comment_hidden":false,"sum":"","sum_foreign":""}],"52":[{"sum_foreign_comment":"","sum_units":"UAH","sum_comment":"","sum_foreign_units":"UAH","sum":"","sum_foreign":""}],"53":[{"sum_foreign_comment":"","sum_units":"UAH","sum_comment":"","sum_foreign_units":"UAH","sum":"","sum_foreign":""}]},"declaration":{"additional_info_text":"","notfull_lostpages":"","date":"2015-03-04T00:00:00","notfull":"","additional_info":"","url":"http://static.declarations.com.ua/declarations/chosen_ones/mega_batch/tsytsak_viktoriia_liubomyrivna.pdf"},"liabilities":{"54":{"sum_foreign_comment":"","sum_foreign_hidden":false,"sum_comment":"","sum_hidden":false,"sum_comment_hidden":false,"sum":"541","sum_foreign":""},"55":{"sum_foreign_comment":"","sum_foreign_hidden":false,"sum_comment":"","sum_hidden":false,"sum":"","sum_foreign":""},"56":{"sum_foreign_comment":"","sum_foreign_hidden":false,"sum_comment":"","sum":"","sum_unclear":false,"sum_foreign":""},"57":{"sum_foreign_comment":"","sum_foreign_hidden":false,"sum_comment":"","sum_hidden":false,"sum_comment_hidden":false,"sum_unclear":false,"sum":"","sum_foreign":""},"58":{"sum_foreign_comment":"","sum_foreign_hidden":false,"sum_comment":"","sum_hidden":false,"sum_comment_hidden":false,"sum_unclear":false,"sum":"","sum_foreign":""},"59":{"sum_foreign_comment":"","sum_foreign_hidden":false,"sum_comment":"","sum_hidden":false,"sum":"","sum_foreign":""},"60":{"sum_foreign_comment":"","sum_foreign_hidden":false,"sum_comment":"","sum_hidden":false,"sum":"","sum_foreign":""},"61":{"sum_foreign_comment":"","sum_foreign_hidden":false,"sum_comment":"","sum_hidden":false,"sum":"","sum_foreign":""},"62":{"sum_foreign_comment":"","sum_foreign_hidden":false,"sum_comment":"","sum":"","sum_unclear":false,"sum_foreign":""},"63":{"sum_foreign_comment":"","sum_foreign_hidden":false,"sum_comment":"","sum_hidden":false,"sum":"","sum_unclear":false,"sum_foreign":""},"64":{"sum_foreign_comment":"","sum_foreign_hidden":false,"sum_comment":"","sum_comment_unclear":false,"sum_hidden":false,"sum_comment_hidden":false,"sum_unclear":false,"sum":"","sum_foreign":""}},"ft_src":"541\nсуддя новодністровського міського суду чернівецької області\nЧернівецька область\nЗагальний місцевий суд\nВікторія\nЛюбомирівна\nЦицак Вікторія Любомирівна\nВікторія Любомирівна Цицак\nВікторія Цицак\nЦицак Вікторія Любомирівна\nЦицак Вікторія Любомирівна\nЦицак\nЛьвів\nЧернівецька обл, Сокирянський р-н, м Новодністровськ\nЧернівецька область\n2.0 л\nMitsubishi Lancer Intense\n2009\n6566\n2014\n2.0 л\nMitsubishi Lancer Intense\n2009\n6566\n15.1\nЛьвівська область\nм. Львів\nспільна сумісна власність\n86.3\nЛьвівська область\nм. Львів\n64.12\nправо безоплатного користування\nСокирянський район, м. Новодністровськ\nЧернівецька область\nЧернівецька обл, Сокирянський р-н, м Новодністровськ\nЧернівецька область\nЛьвів\nЦицак Вікторія Любомирівна\nВікторія Любомирівна Цицак\nВікторія Цицак\nЦицак Вікторія Любомирівна\nЦицак Вікторія Любомирівна\nВікторія\nЛюбомирівна\nЗагальний місцевий суд\nЧернівецька область\nсуддя новодністровського міського суду чернівецької області\nЦицак\n541\n179026\n195997\n12180\n4791\n2014\n541\nм. Львів\nЛьвівська область\n15.1\nспільна сумісна власність\n86.3\nм. Львів\nЛьвівська область\nправо безоплатного користування\nСокирянський район, м. Новодністровськ\n64.12\nЧернівецька область\nЛюбомирівна\nЦицак\nВікторія\nЦицак Вікторія Любомирівна\nВікторія Любомирівна Цицак\nВікторія Цицак\nЦицак Вікторія Любомирівна\nЧернівецька обл, Сокирянський р-н, м Новодністровськ\nЛьвів\nЧернівецька область\nЧернівецька область\nЗагальний місцевий суд\nсуддя новодністровського міського суду чернівецької області\nЦицак Вікторія Любомирівна\n179026\n12180\n195997\n4791\nMitsubishi Lancer Intense\n2.0 л\n2009\n12180\n195997\n4791\n179026\nспільна сумісна власність\nм. Львів\nЛьвівська область\n86.3\nправо безоплатного користування\nЧернівецька область\nСокирянський район, м. Новодністровськ\n64.12\nм. Львів\nЛьвівська область\n15.1\n6566\n2014","general":{"inn":"","name":"Вікторія","patronymic_unclear":false,"inn_unclear":false,"patronymic":"Любомирівна","inn_hidden":true,"family_raw":"","last_name":"Цицак","post":{"post_unclear":false,"region_unclear":false,"post":"суддя новодністровського міського суду чернівецької області","office":"Загальний місцевий суд","region":"Чернівецька область","post_hidden":false,"office_hidden":false,"office_unclear":false,"region_hidden":false},"full_name_suggest":{"output":"Цицак Вікторія Любомирівна","input":["Цицак Вікторія Любомирівна","Вікторія Любомирівна Цицак","Вікторія Цицак"]},"full_name":"Цицак Вікторія Любомирівна","addresses":[{"place_district":"","place_address_hidden":true,"place_city":"Львів","place_city_type_hidden":false,"place_district_hidden":false,"place_city_type":"Місто","place_city_hidden":false,"place_address_unclear":false,"place_address":"Чернівецька обл, Сокирянський р-н, м Новодністровськ","place_hidden":false,"place":"Чернівецька область"},{"place_district":"","place_address_hidden":true,"place_city":"","place_city_type":"","place_address":"","place":""}],"patronymic_hidden":false,"last_name_unclear":false,"name_unclear":false},"source":"VULYK","estate":{"23":[{"space_unclear":false,"costs":"","costs_comment":"","costs_hidden":false,"address_hidden":false,"region_hidden":false,"space_comment":"","space_hidden":false,"space":"","address":"","region":"","address_unclear":false,"space_units_unclear":false,"costs_rent_hidden":false,"costs_unclear":false,"space_units":"м²","costs_rent":"","costs_rent_comment":""},{"costs_rent":"","region":"","costs":"","costs_rent_comment":"","costs_comment":"","address_hidden":false,"region_hidden":false,"space_comment":"","space_units":"","space":"","address":""},{"costs_rent":"","region":"","costs":"","costs_rent_comment":"","costs_comment":"","space_comment":"","space_units":"","space":"","address":""},{"costs_rent":"","region":"","costs":"","costs_rent_comment":"","costs_comment":"","space_comment":"","space_units":"","space":"","address":""}],"25":[{"region_unclear":false,"space_unclear":false,"costs":"","costs_comment":"","costs_hidden":false,"address_hidden":true,"region_hidden":false,"space_comment":"спільна сумісна власність","space_hidden":false,"space":"86.3","address":"м. Львів","costs_rent_comment_unclear":false,"region":"Львівська область","address_unclear":true,"costs_rent_comment":"","costs_rent_hidden":false,"space_comment_unclear":false,"space_units":"м²","costs_rent":""},{"costs_rent":"","region":"Чернівецька область","costs":"","costs_rent_comment":"","costs_comment":"","address_hidden":true,"region_hidden":false,"space_comment":"право безоплатного користування","space_units":"м²","space":"64.12","address":"Сокирянський район, м. Новодністровськ"}],"27":[{"space_unclear":false,"costs":"","costs_comment":"","costs_hidden":false,"address_hidden":true,"region_hidden":false,"space_comment":"","space_hidden":false,"space":"15.1","address":"м. Львів","region":"Львівська область","costs_rent_comment":"","costs_rent_hidden":false,"space_units":"м²","costs_rent":""}]},"intro":{"declaration_year":"2014","isnotdeclaration":"","declaration_year_unclear":false}}