{"income":{"5":{"value":"259499","family_comment":"","value_unclear":false,"family_hidden":false,"family_unclear":false,"family":"84263","comment":""},"6":{"family_comment":"","value":"259499","family":"83648","comment":""},"7":{"family_comment":"","value":"","source_name":"","family":"","comment":""},"8":{"family_comment":"","value":"","family":"","comment":""},"9":{"family_comment":"","value":"","family":"15","comment":""},"10":{"family_comment":"","value":"","value_unclear":false,"family":"600","comment":""},"11":{"family_comment":"","value":"","family":"","comment":""},"12":{"family_comment":"","value":"","family":"","comment":""},"13":{"family_comment":"","value":"","family":"","comment":""},"14":{"family_comment":"","value":"","family":"","comment":""},"15":{"family_comment":"","value":"","family":"","comment":""},"16":{"family_comment":"","value":"","family":"","comment":""},"17":{"family_comment":"","value":"","family":"","comment":""},"18":{"family_comment":"","value":"","family":"","comment":""},"19":{"family_comment":"","value":"","family":"","comment":""},"20":{"family_comment":"","value":"","family":"","comment":""}},"id":"vulyk_82_44","banks":{"51":[{"sum_foreign_comment":"","sum_units":"UAH","sum_comment":"","sum_hidden":false,"sum_foreign_units":"UAH","sum_comment_hidden":false,"sum_units_hidden":false,"sum":"3512","sum_foreign":""}]},"declaration":{"date":"2015-03-31T00:00:00","additional_info_text":"","additional_info":"","url":"http://static.declarations.com.ua/declarations/chosen_ones/judges_batch/2239_paramonov_mykhailo_leonidovych.pdf"},"liabilities":{"54":{"sum_foreign_comment":"","sum_comment_hidden":false,"sum":"","sum_comment":"","sum_foreign":""},"55":{"sum_foreign_comment":"","sum":"","sum_hidden":false,"sum_comment":"","sum_foreign":""},"56":{"sum_foreign_comment":"","sum":"","sum_comment":"","sum_foreign":""},"57":{"sum_foreign_comment":"","sum":"","sum_comment":"","sum_foreign":""},"58":{"sum_foreign_comment":"","sum":"","sum_comment":"","sum_foreign":""},"59":{"sum_foreign_comment":"","sum":"","sum_comment":"","sum_foreign":""},"60":{"sum_foreign_comment":"","sum":"","sum_comment":"","sum_foreign":""},"61":{"sum_foreign_comment":"","sum":"","sum_comment":"","sum_foreign":""},"62":{"sum_foreign_comment":"","sum":"","sum_comment":"","sum_foreign":""},"63":{"sum_foreign_comment":"","sum":"","sum_comment":"","sum_foreign":""},"64":{"sum_foreign_comment":"","sum":"","sum_comment":"","sum_foreign":""}},"ft_src":"суддя дарницького районного суду м. києва\nм. Київ\nЗагальний місцевий суд\nМихайло\nПодружжя\nДитина\nЛеонідович\nПарамонов Михайло Леонідович\nМихайло Леонідович Парамонов\nМихайло Парамонов\nПарамонов Михайло Леонідович\nПарамонов Михайло Леонідович\nПарамонов\n15\n600\n259499\n84263\n83648\n259499\n3512\n2/4 частини\n58.9\n1/4 частина\n58.9\n2014\n83648\n259499\n15\n600\n84263\n259499\n3512\n2014\nПодружжя\nДитина\nПарамонов Михайло Леонідович\nМихайло Леонідович Парамонов\nМихайло Парамонов\nПарамонов Михайло Леонідович\nПарамонов Михайло Леонідович\nМихайло\nПарамонов\nЗагальний місцевий суд\nм. Київ\nсуддя дарницького районного суду м. києва\nЛеонідович\n259499\n83648\n259499\n84263\n15\n600\n2/4 частини\n58.9\n58.9\n1/4 частина\nПодружжя\nДитина\nЛеонідович\nПарамонов\nМихайло\nПарамонов Михайло Леонідович\nМихайло Леонідович Парамонов\nМихайло Парамонов\nПарамонов Михайло Леонідович\nм. Київ\nЗагальний місцевий суд\nсуддя дарницького районного суду м. києва\nПарамонов Михайло Леонідович\n2/4 частини\n58.9\n1/4 частина\n58.9\n3512\n2014","general":{"inn":"","name":"Михайло","inn_unclear":false,"family":[{"inn":"","inn_hidden":true,"relations_hidden":false,"family_name":"","relations_other":"","relations":"Подружжя","name_hidden":true,"name_unclear":false},{"inn":"","relations":"Дитина","relations_other":"","inn_hidden":false,"family_name":"","name_hidden":true,"name_unclear":false}],"inn_hidden":true,"family_raw":"","last_name":"Парамонов","post":{"post":"суддя дарницького районного суду м. києва","region":"м. Київ","office_hidden":false,"office":"Загальний місцевий суд","office_unclear":false,"post_hidden":false,"region_hidden":false},"full_name_suggest":{"output":"Парамонов Михайло Леонідович","input":["Парамонов Михайло Леонідович","Михайло Леонідович Парамонов","Михайло Парамонов"]},"full_name":"Парамонов Михайло Леонідович","addresses":[{"place_district":"","place_city_hidden":true,"place_city":"","place_city_type_hidden":false,"place_district_hidden":false,"place_city_type":"","place_address_hidden":true,"place_address":"","place_hidden":true,"place":""}],"patronymic":"Леонідович","last_name_unclear":false},"source":"VULYK","estate":{"25":[{"space_hidden":false,"costs":"","costs_comment":"","costs_hidden":false,"address_hidden":false,"region_hidden":true,"space_comment":"1/4 частина","space_unclear":false,"space":"58.9","address":"","region":"","costs_rent_comment":"","space_comment_unclear":false,"space_units":"м²","costs_rent":""}],"31":[{"space_unclear":false,"address_hidden":false,"region_hidden":true,"space_comment":"2/4 частини","space":"58.9","address":"","region":"","costs_property":"","costs_rent_comment":"","space_comment_unclear":false,"space_units":"м²","costs_property_comment":"","costs_rent":""}]},"intro":{"declaration_year":"2014"}}