{"income":{"5":{"value":"263894.04","value_unclear":false,"family_hidden":false,"family_comment":"","family":"64840","comment":""},"6":{"family_comment":"","value":"263894.04","family":"","comment":""},"7":{"family_comment":"","value":"","source_name":"","family":"","comment":""},"8":{"family_comment":"","value":"","family":"","comment":""},"9":{"family_comment":"","value":"","family":"","comment":""},"10":{"family_comment":"","value":"","family":"","comment":""},"11":{"family_comment":"","value":"","family_hidden":false,"comment":"","family":""},"12":{"family_comment":"","value":"","family":"","comment":""},"13":{"family_comment":"","value":"","family":"","comment":""},"14":{"family_comment":"","value":"","family":"","comment":""},"15":{"family_comment":"","value":"","family":"","comment":""},"16":{"family_comment":"","value":"","family":"","comment":""},"17":{"family_comment":"","value":"","family":"4840","comment":"","family_comment_unclear":false},"18":{"family_comment":"","value":"","family":"","comment":""},"19":{"family_comment":"","value":"","family":"60000","comment":""},"20":{"value":"","family_unclear":false,"family_hidden":false,"family_comment":"","family":"","comment":""}},"vehicle":{"35":[{"brand_info":"1968 куб. см., 120 кВт , 525.4 см","sum":"100635","brand":"Volkswagen Amarok","sum_comment":"за договором кредитування","brand_unclear":false,"year":"2012","brand_hidden":false,"brand_info_hidden":false,"brand_info_unclear":false,"sum_rent_comment":"","sum_rent":""}]},"id":"vulyk_103_112","declaration":{"date":"2016-03-31T00:00:00","additional_info_text":"","additional_info":"","url":"http://static.declarations.com.ua/declarations/chosen_ones/judges_batch/1067_serheichuk_oleh_anatoliiovych.pdf"},"liabilities":{"54":{"sum_foreign_comment":"","sum_foreign_hidden":false,"sum_comment":"","sum_foreign_comment_hidden":false,"sum_hidden":false,"sum_foreign_comment_unclear":false,"sum_comment_hidden":false,"sum_unclear":false,"sum":"","sum_foreign":""},"55":{"sum_foreign_comment":"","sum":"","sum_comment":"","sum_foreign":""},"56":{"sum_foreign_comment":"","sum":"","sum_comment":"","sum_foreign":""},"57":{"sum_foreign_comment":"","sum_foreign_hidden":false,"sum_comment":"","sum_foreign_comment_hidden":false,"sum_hidden":false,"sum_comment_hidden":false,"sum":"","sum_foreign":""},"58":{"sum_foreign_comment":"","sum_foreign_hidden":false,"sum_comment":"","sum_foreign_comment_hidden":false,"sum_hidden":false,"sum_comment_hidden":false,"sum":"","sum_foreign":""},"59":{"sum_foreign_comment":"","sum_foreign_hidden":false,"sum_comment":"","sum_foreign_comment_hidden":false,"sum_hidden":false,"sum_comment_hidden":false,"sum":"","sum_foreign":""},"60":{"sum_foreign_comment":"","sum":"","sum_comment":"","sum_hidden":false,"sum_comment_hidden":false,"sum_foreign":""},"61":{"sum_foreign_comment":"","sum":"","sum_comment":"","sum_foreign":""},"62":{"sum_foreign_comment":"","sum_comment_hidden":false,"sum":"","sum_comment":"","sum_foreign":""},"63":{"sum_foreign_comment":"","sum":"","sum_comment":"","sum_foreign":""},"64":{"sum_foreign_comment":"","sum":"","sum_comment":"","sum_foreign":""}},"ft_src":"Сергейчук Олег Анатолійович\nсуддя конституційного суду україни\nЗагальнодержавний регіон\nКонституційний Cуд\nОлег\nСергейчук С. Д\nПодружжя\nСергейчук С. О\nДитина\nСергейчук М. О\nДитина\nСергейчук Олег Анатолійович\nОлег Анатолійович Сергейчук\nОлег Сергейчук\nСергейчук Олег Анатолійович\nСергейчук\nАнатолійович\nза договором кредитування\nVolkswagen Amarok\n100635\n1968 куб. см., 120 кВт , 525.4 см\n2012\n60\n68.8\n59.1\n58.9\n104.5\nдоговор найму житлового приміщення\n2015\n263894.04\n64840\n263894.04\n4840\n60000\n1968 куб. см., 120 кВт , 525.4 см\nза договором кредитування\n2012\n100635\nVolkswagen Amarok\n60\n68.8\n59.1\n58.9\n104.5\nдоговор найму житлового приміщення\nСергейчук\nСергейчук Олег Анатолійович\nОлег Анатолійович Сергейчук\nОлег Сергейчук\nСергейчук Олег Анатолійович\nСергейчук Олег Анатолійович\nАнатолійович\nПодружжя\nСергейчук С. Д\nСергейчук С. О\nДитина\nДитина\nСергейчук М. О\nОлег\nКонституційний Cуд\nсуддя конституційного суду україни\nЗагальнодержавний регіон\n263894.04\n4840\n263894.04\n64840\n60000\n2015\nПодружжя\nСергейчук С. Д\nДитина\nСергейчук С. О\nДитина\nСергейчук М. О\nСергейчук\nАнатолійович\nсуддя конституційного суду україни\nКонституційний Cуд\nЗагальнодержавний регіон\nСергейчук Олег Анатолійович\nСергейчук Олег Анатолійович\nОлег Анатолійович Сергейчук\nОлег Сергейчук\nСергейчук Олег Анатолійович\nОлег\n100635\nза договором кредитування\nVolkswagen Amarok\n1968 куб. см., 120 кВт , 525.4 см\n2012\n60000\n263894.04\n64840\n4840\n263894.04\n60\n68.8\n59.1\nдоговор найму житлового приміщення\n104.5\n58.9\n2015","general":{"inn":"","inn_hidden":true,"last_name":"Сергейчук","post":{"region":"Загальнодержавний регіон","region_unclear":false,"post":"суддя конституційного суду україни","office_unclear":false,"office":"Конституційний Cуд"},"name":"Олег","full_name":"Сергейчук Олег Анатолійович","family_raw":"","addresses":[{"place_district":"","place_city_hidden":true,"place_city":"","place_city_type_hidden":true,"place_district_hidden":true,"place_city_type":"","place_address_hidden":true,"place_address":"","place_hidden":true,"place":""}],"family":[{"inn":"","relations":"Подружжя","relations_hidden":false,"inn_hidden":true,"relations_other":"","name_hidden":true,"family_name":"Сергейчук С. Д","name_unclear":false},{"inn":"","family_name":"Сергейчук С. О","relations":"Дитина","inn_hidden":false,"relations_other":""},{"inn":"","relations":"Дитина","relations_other":"","inn_hidden":false,"family_name":"Сергейчук М. О","name_unclear":false}],"full_name_suggest":{"output":"Сергейчук Олег Анатолійович","input":["Сергейчук Олег Анатолійович","Олег Анатолійович Сергейчук","Олег Сергейчук"]},"patronymic":"Анатолійович"},"source":"VULYK","estate":{"25":[{"costs":"","costs_comment":"","address_hidden":true,"region_hidden":true,"space_comment":"","space":"104.5","address":"","region":"","costs_rent_comment":"договор найму житлового приміщення","space_comment_unclear":false,"space_comment_hidden":false,"space_units":"м²","costs_rent":""}],"31":[{"space_hidden":false,"address_hidden":true,"region_hidden":true,"space_comment":"","space":"60","address":"","costs_property":"","costs_rent_comment":"","address_unclear":false,"space_units":"м²","costs_property_comment":"","costs_rent":""},{"costs_rent":"","address_hidden":false,"space_hidden":false,"costs_property":"","costs_rent_comment":"","space_comment_unclear":false,"space_comment":"","costs_property_comment":"","space_units":"м²","space":"68.8","address":""},{"costs_rent":"","space_hidden":false,"costs_property":"","costs_rent_comment":"","space_comment_unclear":false,"space_comment":"","costs_property_comment":"","space_units":"м²","space":"59.1","address":""}],"34":[{"costs_rent":"","space_hidden":false,"costs_property":"","costs_rent_comment":"","address_hidden":true,"region_hidden":true,"space_comment":"","costs_property_comment":"","space_units":"м²","space":"58.9","address":""}]},"intro":{"declaration_year":"2015"}}