{"income":{"5":{"family_comment":"","family_unclear":false,"value":"209284","family":"46341","comment":""},"6":{"value":"209254","family_comment":"","value_unclear":false,"family_unclear":false,"family":"34363","comment":""},"7":{"value":"","family_comment":"","value_unclear":false,"family_unclear":false,"source_name":"","family":"","comment":"","source_name_hidden":false},"8":{"family_comment":"","value":"","family":"","comment":""},"9":{"family_comment":"","value":"","family":"","comment":""},"10":{"family_comment":"","value":"","value_unclear":false,"family":"","comment":""},"11":{"family_comment":"","value":"","family":"","comment":""},"12":{"family_comment":"","value":"","family":"","comment":""},"13":{"family_comment":"","value":"","family":"","comment":""},"14":{"family_comment":"","value":"","family":"","comment":""},"15":{"family_comment":"","value":"","family":"","comment":""},"16":{"family_comment":"","value":"","family":"","comment":""},"17":{"family_comment":"","value":"","family":"","comment":""},"18":{"family_comment":"","value":"","family":"","comment":""},"19":{"family_comment":"","value":"","family":"","comment":""},"20":{"value":"","value_unclear":false,"comment_hidden":false,"family_comment":"","comment_unclear":false,"comment":"","family":"11977"}},"vehicle":{"40":[{"brand_info":"1799 куб. см.","sum_rent_comment":"","brand":"Chevrolet Lacetti","sum_comment":"","year":"2006","brand_info_hidden":false,"year_unclear":false,"sum":"","sum_rent":""}],"41":[{"brand_info":"2464 куб. см.","sum_rent_comment":"","brand":"ГАЗ 2705-4143 НГ","sum_comment":"","year":"2007","sum":"","sum_rent":""}]},"id":"vulyk_96_75","declaration":{"additional_info_text":"","notfull_lostpages":"","date":"2016-03-28T00:00:00","notfull":"","additional_info":"","url":"http://static.declarations.com.ua/declarations/chosen_ones/judges_batch/289_arkhypenko_anzhelika_viktorivna_2015.pdf"},"liabilities":{"54":{"sum_foreign_comment":"","sum":"","sum_comment":"","sum_hidden":false,"sum_comment_hidden":false,"sum_foreign":""},"55":{"sum_foreign_comment":"","sum":"","sum_comment":"","sum_foreign":""},"56":{"sum_foreign_comment":"","sum":"3520","sum_comment":"","sum_unclear":false,"sum_foreign":""},"57":{"sum_foreign_comment":"","sum_comment_hidden":false,"sum":"","sum_comment":"","sum_foreign":""},"58":{"sum_foreign_comment":"","sum":"","sum_comment":"","sum_comment_hidden":false,"sum_unclear":false,"sum_foreign":""},"59":{"sum_foreign_comment":"","sum":"","sum_comment":"","sum_foreign":""},"60":{"sum_foreign_comment":"","sum_comment_hidden":false,"sum":"","sum_comment":"","sum_foreign":""},"61":{"sum_foreign_comment":"","sum":"","sum_comment":"","sum_foreign":""},"62":{"sum_foreign_comment":"","sum":"69","sum_comment":"","sum_foreign":""},"63":{"sum_foreign_comment":"","sum_comment_hidden":false,"sum":"","sum_comment":"","sum_foreign":""},"64":{"sum_foreign_comment":"","sum_comment_hidden":false,"sum":"","sum_comment":"","sum_foreign":""}},"ft_src":"69\n3520\nПопасна\nвул. О. Кошевого, 18\nЛуганська область\n2519411327\nсуддя попаснянського районного суду луганської області\nЛуганська область\nЗагальний місцевий суд\nАнжеліка\n2505512970\nАрхипенко В. М. 1968\nПодружжя\n3429203042\nАрхипенко О. В., 1993\nДитина\nВікторівна\nАрхипенко Анжеліка Вікторівна\nАрхипенко\nАрхипенко Анжеліка Вікторівна\nАнжеліка Вікторівна Архипенко\nАнжеліка Архипенко\nАрхипенко Анжеліка Вікторівна\n2464 куб. см.\n2007\nГАЗ 2705-4143 НГ\n2006\n1799 куб. см.\nChevrolet Lacetti\nЛуганська область\nм. Попасна, вул. Громової, 17\n.687\nм. Попасна, вул. Кошевого,18\nЛуганська область\n60\nЛуганська область\nм. Попасна, вул. Громової, 17\n17\n.66\nм. Попасна, вул. Кошевого,18\nЛуганська область\nЛуганська область\nм. Попасна, вул. Громової, 17\n52\nЛуганська область\nм. Попасна, вул. Миру, 152/11\n44.6\nм. Сєвєродонецьк, вул. Космонавтів, 29/113\n68.1\nЛуганська область\nУкраїна, м. Попасна, Кошевого, 30/2\n49.5\nЛуганська область\n2015\n34363\n209254\n46341\n209284\n11977\nChevrolet Lacetti\n1799 куб. см.\n2006\n2464 куб. см.\n2007\nГАЗ 2705-4143 НГ\n2015\nАрхипенко Анжеліка Вікторівна\nАнжеліка Вікторівна Архипенко\nАнжеліка Архипенко\nАрхипенко Анжеліка Вікторівна\nАрхипенко Анжеліка Вікторівна\n2519411327\nАнжеліка\nАрхипенко\nЛуганська область\nсуддя попаснянського районного суду луганської області\nЗагальний місцевий суд\nВікторівна\nвул. О. Кошевого, 18\nЛуганська область\nПопасна\nПодружжя\nАрхипенко В. М. 1968\n2505512970\nДитина\nАрхипенко О. В., 1993\n3429203042\n3520\n69\n34363\n209254\n11977\n209284\n46341\n52\nм. Попасна, вул. Громової, 17\nЛуганська область\n68.1\nм. Сєвєродонецьк, вул. Космонавтів, 29/113\nЛуганська область\n49.5\nУкраїна, м. Попасна, Кошевого, 30/2\nЛуганська область\n17\nм. Попасна, вул. Громової, 17\nЛуганська область\n.66\nЛуганська область\nм. Попасна, вул. Кошевого,18\nм. Попасна, вул. Громової, 17\n.687\nЛуганська область\n60\nм. Попасна, вул. Кошевого,18\nЛуганська область\nм. Попасна, вул. Миру, 152/11\nЛуганська область\n44.6\n3520\n69\n2505512970\nАрхипенко В. М. 1968\nПодружжя\n3429203042\nДитина\nАрхипенко О. В., 1993\n2519411327\nАнжеліка\nВікторівна\nАрхипенко\nАрхипенко Анжеліка Вікторівна\nАнжеліка Вікторівна Архипенко\nАнжеліка Архипенко\nАрхипенко Анжеліка Вікторівна\nЛуганська область\nПопасна\nвул. О. Кошевого, 18\nсуддя попаснянського районного суду луганської області\nЛуганська область\nЗагальний місцевий суд\nАрхипенко Анжеліка Вікторівна\nГАЗ 2705-4143 НГ\n2464 куб. см.\n2007\n2006\n1799 куб. см.\nChevrolet Lacetti\n11977\n46341\n209284\n209254\n34363\nм. Попасна, вул. Миру, 152/11\nЛуганська область\n44.6\nм. Попасна, вул. Кошевого,18\nЛуганська область\n.66\nм. Попасна, вул. Кошевого,18\nЛуганська область\n60\nм. Попасна, вул. Громової, 17\nЛуганська область\n52\nм. Попасна, вул. Громової, 17\nЛуганська область\n17\n68.1\nм. Сєвєродонецьк, вул. Космонавтів, 29/113\nЛуганська область\nУкраїна, м. Попасна, Кошевого, 30/2\nЛуганська область\n49.5\nм. Попасна, вул. Громової, 17\nЛуганська область\n.687\n2015","general":{"inn":"2519411327","name":"Анжеліка","family":[{"inn":"2505512970","inn_hidden":false,"inn_unclear":false,"relations_hidden":false,"relations_other":"","relations":"Подружжя","name_hidden":false,"family_name":"Архипенко В. М. 1968","name_unclear":false},{"inn":"3429203042","relations":"Дитина","relations_other":"","inn_hidden":false,"family_name":"Архипенко О. В., 1993","name_hidden":false,"name_unclear":false}],"patronymic":"Вікторівна","inn_hidden":false,"family_raw":"","last_name":"Архипенко","post":{"office":"Загальний місцевий суд","region":"Луганська область","office_unclear":false,"post":"суддя попаснянського районного суду луганської області"},"full_name":"Архипенко Анжеліка Вікторівна","addresses":[{"place_district":"","place_city_hidden":false,"place_city":"Попасна","place_city_type_hidden":false,"place_district_hidden":false,"place_city_type":"Місто","place_address_hidden":false,"place_address":"вул. О. Кошевого, 18","place_hidden":false,"place":"Луганська область"}],"patronymic_hidden":false,"full_name_suggest":{"output":"Архипенко Анжеліка Вікторівна","input":["Архипенко Анжеліка Вікторівна","Анжеліка Вікторівна Архипенко","Анжеліка Архипенко"]}},"source":"VULYK","estate":{"23":[{"region_unclear":false,"space_unclear":false,"costs":"","costs_rent_unclear":false,"costs_comment":"","address_hidden":false,"region_hidden":false,"space_comment":"","space_hidden":false,"space_units_unclear":false,"address":"м. Попасна, вул. Кошевого,18","region":"Луганська область","address_unclear":false,"space":".66","space_comment_unclear":false,"space_units":"га","costs_rent":"","costs_rent_comment":""}],"24":[{"space_unclear":false,"costs":"","costs_comment":"","address_hidden":false,"region_hidden":false,"space_comment":"","space_hidden":false,"space":"60","address":"м. Попасна, вул. Кошевого,18","region":"Луганська область","costs_rent_comment":"","space_comment_unclear":false,"space_units":"м²","costs_rent":""}],"25":[{"space_comment_unclear":false,"space_unclear":false,"costs":"","costs_comment":"","address_hidden":false,"region_hidden":false,"space_comment":"","space_hidden":false,"space":"68.1","address":"м. Сєвєродонецьк, вул. Космонавтів, 29/113","costs_rent_comment_unclear":false,"region":"Луганська область","address_unclear":true,"costs_rent_comment":"","costs_unclear":false,"space_comment_hidden":false,"space_units":"м²","costs_rent":""},{"space_hidden":false,"costs":"","costs_comment":"","address_hidden":false,"region_hidden":false,"space_comment":"","space":"49.5","address":"Україна, м. Попасна, Кошевого, 30/2","region":"Луганська область","address_unclear":true,"costs_rent_comment":"","space_comment_unclear":false,"space_units":"м²","costs_rent":""}],"29":[{"region_unclear":false,"space_unclear":false,"address_hidden":false,"region_hidden":false,"space_comment":"","space":".687","address":"м. Попасна, вул. Громової, 17","region":"Луганська область","costs_property":"","costs_rent_comment":"","address_unclear":false,"space_units":"га","costs_property_comment":"","costs_rent":""}],"30":[{"costs_rent":"","region":"Луганська область","costs_property":"","costs_rent_comment":"","address_hidden":false,"region_hidden":false,"space_comment":"","costs_property_comment":"","space_units":"м²","space":"52","address":"м. Попасна, вул. Громової, 17"}],"31":[{"space_unclear":false,"address_hidden":false,"region_hidden":false,"space_comment":"","space_hidden":false,"space":"44.6","address":"м. Попасна, вул. Миру, 152/11","region":"Луганська область","costs_property":"","costs_rent_comment":"","address_unclear":false,"space_units":"м²","costs_property_comment":"","costs_rent":""}],"33":[{"costs_rent":"","region":"Луганська область","costs_property":"","costs_rent_comment":"","address_hidden":false,"region_hidden":false,"space_comment":"","costs_property_comment":"","space_units":"м²","space":"17","address":"м. Попасна, вул. Громової, 17"}]},"intro":{"declaration_year":"2015","isnotdeclaration":""}}