{"income":{"5":{"value":"366997.95","family_comment":"","value_unclear":false,"family_hidden":false,"value_hidden":false,"family_unclear":false,"family_comment_hidden":false,"comment":"","family":""},"6":{"value":"255164.67","family_comment":"","value_unclear":false,"family_hidden":false,"family_unclear":false,"family":"","comment":""},"7":{"family_comment":"","value":"","source_name":"","family":"","comment":""},"8":{"family_comment":"","value":"","family":"","comment":""},"9":{"family_comment":"","value":"2925","family":"","comment":""},"10":{"family_comment":"","family_unclear":false,"value":"13398","family":"","comment":""},"11":{"family_comment":"","value":"","family":"","comment":""},"12":{"family_comment":"","value":"","family":"","comment":""},"13":{"family_comment":"","value":"","family":"","comment":""},"14":{"family_comment":"","value":"34340.92","comment_unclear":true,"family":"","comment":"кв-ра, зем. діл., вклад, акції"},"15":{"family_comment":"","value":"","family":"","comment":""},"16":{"family_comment":"","value":"","family":"","comment":""},"17":{"family_comment":"","value":"","family":"","comment":""},"18":{"family_comment":"","value":"","family":"","comment":""},"19":{"family_comment":"","value":"","family":"","comment":""},"20":{"value":"61169.4","family_comment":"","value_unclear":false,"family_unclear":false,"comment_unclear":false,"comment":"пенсія","family":""}},"id":"vulyk_35_46","banks":{"45":[{"sum_foreign_comment":"","sum_units":"UAH","sum_comment":"","sum_comment_unclear":false,"sum_hidden":false,"sum_foreign_units":"UAH","sum_comment_hidden":false,"sum_unclear":false,"sum":"117000","sum_foreign":""},{"sum_foreign_comment":"","sum_units":"","sum_comment":"","sum_foreign_units":"","sum":"","sum_foreign":""},{"sum_foreign_comment":"","sum_units":"","sum_comment":"","sum_foreign_units":"","sum":"","sum_foreign":""}],"46":[{"sum_foreign_comment":"","sum_units":"UAH","sum_comment":"","sum_hidden":false,"sum_foreign_units":"UAH","sum_comment_hidden":false,"sum":"57000","sum_foreign":""},{"sum_foreign_comment":"","sum_units":"","sum_comment":"","sum_foreign_units":"","sum":"","sum_foreign":""}],"47":[{"sum_foreign_comment":"","sum_units":"UAH","sum_comment":"","sum_foreign_units":"UAH","sum":"15.75","sum_foreign":""}],"48":[{"sum_foreign_comment":"","sum_units":"UAH","sum_comment":"","sum_foreign_units":"UAH","sum":"15.75","sum_foreign":""}],"49":[{"sum_foreign_comment":"","sum_units":"UAH","sum_comment":"","sum_hidden":false,"sum_foreign_units":"UAH","sum":"","sum_foreign":""}],"50":[{"sum_foreign_comment":"","sum_units":"UAH","sum_comment":"","sum_foreign_units":"UAH","sum":"","sum_foreign":""}],"51":[{"sum_foreign_comment":"","sum_units":"UAH","sum_comment":"","sum_comment_unclear":false,"sum_foreign_units":"UAH","sum_comment_hidden":false,"sum":"","sum_foreign":""},{"sum_foreign_comment":"","sum_units":"","sum_comment":"","sum_foreign_units":"","sum":"","sum_foreign":""}],"52":[{"sum_foreign_comment":"","sum_units":"UAH","sum_comment":"","sum_foreign_units":"UAH","sum":"","sum_foreign":""}],"53":[{"sum_foreign_comment":"","sum_units":"UAH","sum_comment":"","sum_foreign_units":"UAH","sum":"","sum_foreign":""}]},"declaration":{"additional_info_text":"","notfull_lostpages":"","date":"2015-02-10T00:00:00","notfull":"","additional_info":"","url":"http://static.declarations.com.ua/declarations/chosen_ones/mega_batch/zakharova_alla_fedorivna.pdf"},"liabilities":{"54":{"sum_foreign_comment":"","sum":"","sum_comment":"","sum_comment_unclear":false,"sum_hidden":false,"sum_comment_hidden":false,"sum_unclear":false,"sum_foreign":""},"55":{"sum_foreign_comment":"","sum":"","sum_comment":"","sum_foreign":""},"56":{"sum_foreign_comment":"","sum":"4244.8","sum_comment":"","sum_unclear":false,"sum_foreign":""},"57":{"sum_foreign_comment":"","sum":"","sum_comment":"","sum_comment_unclear":false,"sum_hidden":false,"sum_comment_hidden":false,"sum_unclear":false,"sum_foreign":""},"58":{"sum_foreign_comment":"","sum":"","sum_comment":"","sum_hidden":false,"sum_comment_hidden":false,"sum_foreign":""},"59":{"sum_foreign_comment":"","sum":"","sum_comment":"","sum_foreign":""},"60":{"sum_foreign_comment":"","sum_comment_hidden":false,"sum":"","sum_comment":"","sum_foreign":""},"61":{"sum_foreign_comment":"","sum":"","sum_comment":"","sum_foreign":""},"62":{"sum_foreign_comment":"","sum":"","sum_comment":"","sum_foreign":""},"63":{"sum_foreign_comment":"","sum":"","sum_comment":"","sum_hidden":false,"sum_comment_hidden":false,"sum_foreign":""},"64":{"sum_foreign_comment":"","sum":"","sum_comment":"","sum_hidden":false,"sum_comment_hidden":false,"sum_foreign":""}},"ft_src":"4244.8\nсуддя судової палати в цивільних справах апеляційного суду черкаської області\nЧеркаська область\nЗагальний апеляційний суд\nАлла\nФедорівна\nЗахарова Алла Федорівна\nАлла Федорівна Захарова\nАлла Захарова\nЗахарова Алла Федорівна\nЗахарова\nЗахарова Алла Федорівна\nкв-ра, зем. діл., вклад, акції\n34340.92\n13398\nпенсія\n61169.4\n366997.95\n2925\n255164.67\n15.75\n57000\n117000\n15.75\nсело, спадщина\n.25\nспадщина з 2014 р\n73.2\n33.5\n2014\n255164.67\nкв-ра, зем. діл., вклад, акції\n34340.92\n13398\n366997.95\n2925\nпенсія\n61169.4\n117000\n15.75\n15.75\n57000\n2014\nЗахарова Алла Федорівна\nАлла Федорівна Захарова\nАлла Захарова\nЗахарова Алла Федорівна\nАлла\nЗахарова Алла Федорівна\nЗахарова\nсуддя судової палати в цивільних справах апеляційного суду черкаської області\nЗагальний апеляційний суд\nЧеркаська область\nФедорівна\n4244.8\n255164.67\nпенсія\n61169.4\nкв-ра, зем. діл., вклад, акції\n34340.92\n366997.95\n13398\n2925\n.25\nсело, спадщина\n73.2\nспадщина з 2014 р\n33.5\n4244.8\nЗахарова Алла Федорівна\nАлла Федорівна Захарова\nАлла Захарова\nЗахарова Алла Федорівна\nФедорівна\nЗахарова\nАлла\nЧеркаська область\nЗагальний апеляційний суд\nсуддя судової палати в цивільних справах апеляційного суду черкаської області\nЗахарова Алла Федорівна\nспадщина з 2014 р\n73.2\n33.5\nсело, спадщина\n.25\n15.75\n57000\n15.75\n117000\n2014","general":{"inn":"","name":"Алла","patronymic_unclear":false,"last_name_hidden":false,"patronymic":"Федорівна","inn_hidden":true,"family_raw":"","last_name":"Захарова","post":{"post_unclear":false,"region_unclear":false,"post":"суддя судової палати в цивільних справах апеляційного суду черкаської області","candidate":"","office_hidden":false,"region":"Черкаська область","post_hidden":false,"office":"Загальний апеляційний суд","office_unclear":false},"last_name_unclear":false,"full_name":"Захарова Алла Федорівна","addresses":[{"place_district":"","place_city_hidden":true,"place_city":"","place_city_type_hidden":true,"place_district_hidden":true,"place_city_type":"","place_address_hidden":true,"place_address":"","place_hidden":true,"place":""}],"full_name_suggest":{"output":"Захарова Алла Федорівна","input":["Захарова Алла Федорівна","Алла Федорівна Захарова","Алла Захарова"]}},"source":"VULYK","estate":{"23":[{"space_unclear":false,"costs":"","costs_comment":"","address_hidden":true,"region_hidden":true,"space_comment":"село, спадщина","space":".25","address":"","region":"","address_unclear":false,"costs_rent_comment":"","space_units":"га","costs_rent":""},{"space_unclear":false,"costs":"","costs_comment":"","address_hidden":false,"region_hidden":false,"space_comment":"","space":"","address":"","region":"","address_unclear":false,"costs_rent_comment":"","space_units":"","costs_rent":""},{"space":"","region":"","costs":"","costs_rent_comment":"","costs_comment":"","address_unclear":false,"space_comment":"","space_units":"","costs_rent":"","address":""},{"costs_rent":"","costs":"","costs_rent_comment":"","costs_comment":"","space_comment":"","space_units":"","space":"","address":""}],"25":[{"space_unclear":false,"costs":"","costs_comment":"","address_hidden":true,"region_hidden":true,"space_comment":"спадщина з 2014 р","space_hidden":false,"space":"73.2","address":"","region":"","address_unclear":false,"costs_rent_comment":"","space_units":"м²","costs_rent":""},{"costs_rent":"","region":"","costs":"","costs_rent_comment":"","costs_comment":"","region_hidden":false,"space_comment":"","space_units":"м²","space":"33.5","address":""}]},"intro":{"declaration_year":"2014","isnotdeclaration":"","declaration_year_unclear":false,"declaration_year_hidden":false}}