{"income":{"5":{"value":"198181","family_comment":"","value_unclear":false,"family":"37211","family_unclear":false,"comment_unclear":false,"comment":"","family_comment_unclear":false},"6":{"value":"198181","family_comment":"","value_unclear":false,"family_unclear":false,"family":"35566","comment":""},"7":{"source_name_unclear":false,"value":"","value_unclear":false,"family_comment":"","source_name":"","family":"","comment":"","source_name_hidden":false},"8":{"family_comment":"","value":"","family":"","comment":""},"9":{"family_comment":"","value":"","family":"","comment":""},"10":{"family_comment":"","value":"","value_unclear":false,"family":"","comment":""},"11":{"value":"","value_unclear":false,"value_hidden":false,"family_comment":"","family":"","comment":""},"12":{"family_comment":"","value":"","family":"1645","comment":"","value_hidden":false},"13":{"family_comment":"","value":"","family":"","comment":""},"14":{"family_comment":"","value":"","family":"","comment":""},"15":{"family_comment":"","value":"","family":"","comment":""},"16":{"family_comment":"","value":"","family":"","comment":""},"17":{"family_comment":"","value":"","family":"","comment":""},"18":{"family_comment":"","value":"","family":"","comment":""},"19":{"family_comment":"","family_unclear":false,"value":"","family":"","comment":""},"20":{"family_comment":"","family_unclear":false,"value":"","family":"","comment":""}},"vehicle":{"40":[{"brand_info":"1500 куб. см.","sum":"","brand":"ВАЗ 21061","sum_comment":"","brand_unclear":false,"year":"1994","brand_hidden":false,"brand_info_hidden":false,"brand_info_unclear":false,"sum_rent_comment":"","sum_rent":""},{"brand_info":"1591 куб. см.","sum_rent_comment":"","brand":"Kia Cerato","sum_comment":"","brand_unclear":false,"year":"2012","brand_info_unclear":false,"sum":"","sum_rent":""}]},"id":"vulyk_61_21","declaration":{"additional_info_text":"","notfull_lostpages":"","date":"2015-03-27T00:00:00","notfull":"","additional_info":"","url":"http://static.declarations.com.ua/declarations/chosen_ones/mega_batch/trushyna_olha_ivanivna.pdf"},"liabilities":{"54":{"sum_foreign_comment":"","sum":"","sum_comment":"","sum_comment_unclear":false,"sum_unclear":false,"sum_foreign":""},"55":{"sum_foreign_comment":"","sum":"","sum_comment":"","sum_foreign":""},"56":{"sum_foreign_comment":"","sum":"","sum_comment":"","sum_unclear":false,"sum_foreign":""},"57":{"sum_foreign_comment":"","sum":"","sum_comment":"","sum_comment_hidden":false,"sum_unclear":false,"sum_foreign":""},"58":{"sum_foreign_comment":"","sum":"","sum_comment":"","sum_unclear":false,"sum_foreign":""},"59":{"sum_foreign_comment":"","sum":"","sum_comment":"","sum_foreign":""},"60":{"sum_foreign_comment":"","sum_foreign_hidden":false,"sum_comment":"","sum_hidden":false,"sum":"","sum_foreign":""},"61":{"sum_foreign_comment":"","sum":"","sum_comment":"","sum_foreign":""},"62":{"sum_foreign_comment":"","sum":"","sum_comment":"","sum_unclear":false,"sum_foreign":""},"63":{"sum_foreign_comment":"","sum":"","sum_comment":"","sum_hidden":false,"sum_unclear":false,"sum_foreign":""},"64":{"sum_foreign_comment":"","sum":"","sum_hidden":false,"sum_comment":"","sum_foreign":""}},"ft_src":"суддя біляївського районного суду одеської області\nОдеська область\nЗагальний місцевий суд\nОльга\nПодружжя\nДитина\nДитина\nІванівна\nТрушина\nТрушина Ольга Іванівна\nТрушина Ольга Іванівна\nОльга Іванівна Трушина\nОльга Трушина\nТрушина Ольга Іванівна\nВАЗ 21061\n1500 куб. см.\n1994\n2012\nKia Cerato\n1591 куб. см.\n600\n164.7\n1183\n2014\n35566\n198181\n37211\n198181\n1645\n1500 куб. см.\n1994\nВАЗ 21061\n1591 куб. см.\n2012\nKia Cerato\n600\n1183\n164.7\nПодружжя\nДитина\nДитина\nТрушина Ольга Іванівна\nОльга Іванівна Трушина\nОльга Трушина\nТрушина Ольга Іванівна\nОльга\nТрушина Ольга Іванівна\nТрушина\nОдеська область\nЗагальний місцевий суд\nсуддя біляївського районного суду одеської області\nІванівна\n35566\n198181\n1645\n198181\n37211\n2014\nПодружжя\nДитина\nДитина\nІванівна\nТрушина\nТрушина Ольга Іванівна\nОльга Іванівна Трушина\nОльга Трушина\nТрушина Ольга Іванівна\nОдеська область\nсуддя біляївського районного суду одеської області\nЗагальний місцевий суд\nТрушина Ольга Іванівна\nОльга\nВАЗ 21061\n1500 куб. см.\n1994\n2012\n1591 куб. см.\nKia Cerato\n198181\n37211\n1645\n198181\n35566\n164.7\n600\n1183\n2014","general":{"inn":"","name":"Ольга","patronymic_unclear":false,"family":[{"inn":"","inn_hidden":true,"relations_unclear":false,"relations_hidden":false,"relations_other":"","relations":"Подружжя","name_hidden":true,"family_name":"","name_unclear":false},{"inn":"","relations":"Дитина","relations_other":"","inn_hidden":false,"family_name":"","name_hidden":false,"name_unclear":false},{"inn":"","relations":"Дитина","relations_other":"","inn_hidden":false,"family_name":"","name_hidden":false,"name_unclear":false}],"patronymic":"Іванівна","inn_hidden":true,"family_raw":"","inn_unclear":false,"post":{"post_unclear":false,"region_unclear":false,"post":"суддя біляївського районного суду одеської області","office":"Загальний місцевий суд","region":"Одеська область","post_hidden":false,"office_hidden":false,"region_hidden":false},"last_name_unclear":false,"full_name":"Трушина Ольга Іванівна","addresses":[{"place_address":"","place_district_hidden":false,"place_city_type":"","place_city_hidden":true,"place_address_unclear":false,"place_city_type_hidden":false,"place_hidden":true,"place":"","place_district":"","place_address_hidden":true,"place_city":"","place_district_unclear":false}],"last_name":"Трушина","patronymic_hidden":false,"full_name_suggest":{"output":"Трушина Ольга Іванівна","input":["Трушина Ольга Іванівна","Ольга Іванівна Трушина","Ольга Трушина"]},"name_unclear":false},"source":"VULYK","estate":{"23":[{"region_unclear":false,"space_unclear":false,"costs":"","costs_comment":"","address_hidden":true,"region_hidden":true,"space_comment":"","space":"600","address":"","region":"","address_unclear":false,"costs_rent_comment":"","space_comment_unclear":false,"space_units":"м²","space_units_unclear":false,"costs_rent":""}],"29":[{"space_hidden":false,"costs_property":"","address_hidden":true,"region_hidden":true,"space_comment":"","space_units_hidden":false,"space_unclear":false,"space_units_unclear":false,"address":"","region":"","address_unclear":false,"space":"1183","space_comment_hidden":false,"space_units":"м²","costs_property_comment":"","costs_rent":"","costs_rent_comment":""}],"30":[{"space_hidden":false,"costs_property":"","address_hidden":true,"region_hidden":true,"space_comment":"","space_units_hidden":false,"space":"164.7","address":"","region":"","address_unclear":false,"costs_rent_comment":"","space_comment_unclear":false,"space_comment_hidden":false,"space_units":"м²","costs_property_comment":"","costs_rent":""}]},"intro":{"declaration_year":"2014","isnotdeclaration":"","declaration_year_hidden":false}}