{"income":{"5":{"value":"254188.41","family_comment":"","value_unclear":false,"family":"","family_unclear":false,"comment_unclear":false,"comment":"","family_comment_unclear":false},"6":{"value":"254188.41","family_comment":"","value_unclear":false,"family_unclear":false,"family":"","comment":""},"7":{"source_name_unclear":false,"value":"","value_unclear":false,"family_comment":"","source_name":"","family":"","comment":"","source_name_hidden":false},"8":{"family_comment":"","value":"","family":"","comment":""},"9":{"family_comment":"","value":"","family":"","comment":""},"10":{"family_comment":"","value":"","value_unclear":false,"family":"","comment":""},"11":{"value":"","value_unclear":false,"value_hidden":false,"family_comment":"","family":"","comment":""},"12":{"family_comment":"","value":"","family":"","comment":"","value_hidden":false},"13":{"family_comment":"","value":"","family":"","comment":""},"14":{"family_comment":"","value":"","family":"","comment":""},"15":{"family_comment":"","value":"","family":"","comment":""},"16":{"family_comment":"","value":"","family":"","comment":""},"17":{"family_comment":"","value":"","family":"","comment":""},"18":{"family_comment":"","value":"","family":"","comment":""},"19":{"family_comment":"","family_unclear":false,"value":"","family":"","comment":""},"20":{"family_comment":"","family_unclear":false,"value":"","family":"","comment":""}},"vehicle":{"35":[{"year_hidden":false,"brand_info":"1997 куб. см.","sum_rent_comment":"","year":"2007","sum_hidden":false,"brand_info_hidden":false,"brand_info_unclear":false,"year_unclear":false,"sum_rent":"","sum":"","brand":"Mitsubishi Lancer","sum_comment":"","brand_unclear":false,"brand_hidden":false}]},"id":"vulyk_61_65","declaration":{"additional_info_text":"","notfull_lostpages":"","date":"2015-03-25T00:00:00","notfull":"","additional_info":"","url":"http://static.declarations.com.ua/declarations/chosen_ones/mega_batch/kopchynskyi_viktor_ivanovych.pdf"},"liabilities":{"54":{"sum_foreign_comment":"","sum":"","sum_comment":"","sum_comment_unclear":false,"sum_unclear":false,"sum_foreign":""},"55":{"sum_foreign_comment":"","sum":"","sum_comment":"","sum_foreign":""},"56":{"sum_foreign_comment":"","sum":"","sum_comment":"","sum_unclear":false,"sum_foreign":""},"57":{"sum_foreign_comment":"","sum":"","sum_comment":"","sum_comment_hidden":false,"sum_unclear":false,"sum_foreign":""},"58":{"sum_foreign_comment":"","sum":"","sum_comment":"","sum_unclear":false,"sum_foreign":""},"59":{"sum_foreign_comment":"","sum":"","sum_comment":"","sum_foreign":""},"60":{"sum_foreign_comment":"","sum_foreign_hidden":false,"sum_comment":"","sum_hidden":false,"sum":"","sum_foreign":""},"61":{"sum_foreign_comment":"","sum":"","sum_comment":"","sum_foreign":""},"62":{"sum_foreign_comment":"","sum":"4000","sum_comment":"","sum_unclear":false,"sum_foreign":""},"63":{"sum_foreign_comment":"","sum":"","sum_comment":"","sum_hidden":false,"sum_unclear":false,"sum_foreign":""},"64":{"sum_foreign_comment":"","sum":"","sum_hidden":false,"sum_comment":"","sum_foreign":""}},"ft_src":"4000\nсуддя калинівського районного суду вінницької області\nВінницька область\nЗагальний місцевий суд\nВіктор\nКопчинська Л. В\nПодружжя\nІванович\nКопчинський\nКопчинський Віктор Іванович\nКопчинський Віктор Іванович\nВіктор Іванович Копчинський\nВіктор Копчинський\nКопчинський Віктор Іванович\n1997 куб. см.\nMitsubishi Lancer\n2007\n20\n24\n3000\n79\n69\n2014\n254188.41\n254188.41\n1997 куб. см.\nMitsubishi Lancer\n2007\n3000\n24\n79\n69\n20\nПодружжя\nКопчинська Л. В\nКопчинський Віктор Іванович\nВіктор Іванович Копчинський\nВіктор Копчинський\nКопчинський Віктор Іванович\nВіктор\nКопчинський Віктор Іванович\nКопчинський\nВінницька область\nЗагальний місцевий суд\nсуддя калинівського районного суду вінницької області\nІванович\n4000\n254188.41\n254188.41\n2014\n4000\nКопчинська Л. В\nПодружжя\nІванович\nКопчинський\nКопчинський Віктор Іванович\nВіктор Іванович Копчинський\nВіктор Копчинський\nКопчинський Віктор Іванович\nВінницька область\nсуддя калинівського районного суду вінницької області\nЗагальний місцевий суд\nКопчинський Віктор Іванович\nВіктор\nMitsubishi Lancer\n1997 куб. см.\n2007\n254188.41\n254188.41\n69\n79\n3000\n20\n24\n2014","general":{"inn":"","name":"Віктор","patronymic_unclear":false,"family":[{"inn":"","inn_hidden":false,"relations_unclear":false,"relations_hidden":false,"relations_other":"","relations":"Подружжя","name_hidden":false,"family_name":"Копчинська Л. В","name_unclear":false}],"patronymic":"Іванович","inn_hidden":true,"family_raw":"","inn_unclear":false,"post":{"post_unclear":false,"region_unclear":false,"post":"суддя калинівського районного суду вінницької області","office":"Загальний місцевий суд","region":"Вінницька область","post_hidden":false,"office_hidden":false,"region_hidden":false},"last_name_unclear":false,"full_name":"Копчинський Віктор Іванович","addresses":[{"place_address":"","place_district_hidden":false,"place_city_type":"","place_city_hidden":false,"place_address_unclear":false,"place_city_type_hidden":false,"place_hidden":false,"place":"","place_district":"","place_address_hidden":true,"place_city":"","place_district_unclear":false}],"last_name":"Копчинський","patronymic_hidden":false,"full_name_suggest":{"output":"Копчинський Віктор Іванович","input":["Копчинський Віктор Іванович","Віктор Іванович Копчинський","Віктор Копчинський"]},"name_unclear":false},"source":"VULYK","estate":{"25":[{"region_unclear":false,"space_hidden":false,"costs":"","costs_comment":"","address_hidden":false,"region_hidden":true,"space_comment":"","space_unclear":false,"space":"69","address":"","costs_comment_unclear":false,"costs_unclear":false,"region":"","address_unclear":false,"costs_rent_comment":"","space_comment_unclear":false,"space_units":"м²","costs_rent":""}],"27":[{"costs":"","costs_rent_unclear":false,"costs_comment":"","address_hidden":false,"region_hidden":true,"space_comment":"","space":"24","address":"","region":"","address_unclear":false,"costs_rent_comment":"","space_units":"м²","costs_rent":""}],"29":[{"space_hidden":false,"costs_property":"","address_hidden":false,"region_hidden":true,"space_comment":"","space_units_hidden":false,"space_unclear":false,"space_units_unclear":false,"address":"","region":"","address_unclear":false,"space":"3000","space_comment_hidden":false,"space_units":"м²","costs_property_comment":"","costs_rent":"","costs_rent_comment":""}],"30":[{"space_hidden":false,"costs_property":"","address_hidden":false,"region_hidden":true,"space_comment":"","space_units_hidden":false,"space":"79","address":"","region":"","address_unclear":false,"costs_rent_comment":"","space_comment_unclear":false,"space_comment_hidden":false,"space_units":"м²","costs_property_comment":"","costs_rent":""}],"33":[{"space_unclear":false,"address_hidden":false,"region_hidden":true,"space_comment":"","space":"20","address":"","region":"","costs_property":"","costs_rent_comment":"","space_units":"м²","costs_property_comment":"","costs_rent":""}]},"intro":{"declaration_year":"2014","isnotdeclaration":"","declaration_year_hidden":false}}