{"income":{"5":{"value":"242970","value_unclear":false,"value_hidden":false,"family_comment":"","family":"61158","comment":""},"6":{"value":"230790","family_comment":"","value_unclear":false,"family_unclear":false,"family":"39087","comment":""},"7":{"source_name_unclear":false,"value":"","family_hidden":false,"family_comment":"","source_name":"","family":"","comment":""},"8":{"family_comment":"","value":"","family":"","comment":""},"9":{"family_comment":"","value":"","family":"","comment":""},"10":{"family_comment":"","value":"12180","family":"","comment":""},"11":{"family_comment":"","value":"","family":"","comment":""},"12":{"family_comment":"","value":"","family":"","comment":""},"13":{"family_comment":"","value":"","family":"","comment":""},"14":{"family_comment":"","value":"","family":"","comment":""},"15":{"family_comment":"","value":"","family":"","comment":""},"16":{"family_comment":"","value":"","comment_unclear":false,"family":"","comment":""},"17":{"family_comment":"","family_unclear":false,"value":"","family":"","comment":""},"18":{"family_comment":"","value":"","family":"","comment":""},"19":{"value":"","family_hidden":false,"value_hidden":false,"family_comment":"","family":"","comment":""},"20":{"family_comment":"пенсія","value":"","comment_unclear":false,"family":"22071","comment":""}},"id":"vulyk_67_34","banks":{"47":[{"sum_foreign_comment":"","sum":"240","sum_comment":"","sum_comment_unclear":false,"sum_hidden":false,"sum_foreign_units":"UAH","sum_foreign_hidden":false,"sum_units":"UAH","sum_comment_hidden":false,"sum_unclear":false,"sum_foreign":""}]},"declaration":{"additional_info_text":"","notfull_lostpages":"","date":"2015-02-24T00:00:00","notfull":"","additional_info":"","url":"http://static.declarations.com.ua/declarations/chosen_ones/mega_batch/vysotska_halyna_afanasiivna.pdf"},"liabilities":{"54":{"sum_foreign_comment":"","sum_foreign_hidden":false,"sum_comment":"","sum_comment_unclear":false,"sum_hidden":false,"sum":"","sum_unclear":false,"sum_foreign":""},"55":{"sum_foreign_comment":"","sum":"","sum_comment":"","sum_foreign":""},"56":{"sum_foreign_comment":"","sum_foreign_hidden":false,"sum_comment":"","sum_hidden":false,"sum":"","sum_unclear":false,"sum_foreign":""},"57":{"sum_foreign_comment":"","sum_foreign_hidden":false,"sum_comment":"","sum_comment_unclear":false,"sum_hidden":false,"sum_comment_hidden":false,"sum_unclear":false,"sum":"7403","sum_foreign":""},"58":{"sum_foreign_comment":"","sum_foreign_hidden":false,"sum_comment":"","sum_comment_unclear":false,"sum_hidden":false,"sum_comment_hidden":false,"sum_unclear":false,"sum":"96","sum_foreign":""},"59":{"sum_foreign_comment":"","sum":"","sum_hidden":false,"sum_comment":"","sum_foreign":""},"60":{"sum_foreign_comment":"","sum":"","sum_comment":"","sum_foreign":""},"61":{"sum_foreign_comment":"","sum_foreign_hidden":false,"sum_comment":"","sum_hidden":false,"sum":"","sum_foreign":""},"62":{"sum_foreign_comment":"","sum":"","sum_hidden":false,"sum_comment":"","sum_foreign":""},"63":{"sum_foreign_comment":"","sum":"","sum_comment":"","sum_comment_unclear":false,"sum_hidden":false,"sum_unclear":false,"sum_foreign":""},"64":{"sum_foreign_comment":"","sum":"","sum_comment":"","sum_hidden":false,"sum_unclear":false,"sum_foreign":""}},"ft_src":"7403\n96\nсуддя вознесенського міськрайонного суду миколаївської області\nМиколаївська область\nЗагальний місцевий суд\nГалина\nВисоцький Віталій Георгійович\nПодружжя\nШмідт Ірина Віталіївна\nДитина\nАфанасіївна\nВисоцька Галина Афанасіївна\nВисоцька\nВисоцька Галина Афанасіївна\nГалина Афанасіївна Висоцька\nГалина Висоцька\nВисоцька Галина Афанасіївна\n12180\n22071\nпенсія\n242970\n61158\n230790\n39087\n240\n800\n64.9\n2014\n39087\n230790\n12180\n61158\n242970\n22071\nпенсія\n240\n2014\nЗагальний місцевий суд\nсуддя вознесенського міськрайонного суду миколаївської області\nМиколаївська область\nПодружжя\nВисоцький Віталій Георгійович\nДитина\nШмідт Ірина Віталіївна\nВисоцька Галина Афанасіївна\nГалина Афанасіївна Висоцька\nГалина Висоцька\nВисоцька Галина Афанасіївна\nВисоцька Галина Афанасіївна\nГалина\nВисоцька\nАфанасіївна\n7403\n96\n39087\n230790\n22071\nпенсія\n242970\n61158\n12180\n800\n64.9\n96\n7403\nПодружжя\nВисоцький Віталій Георгійович\nДитина\nШмідт Ірина Віталіївна\nАфанасіївна\nВисоцька\nГалина\nВисоцька Галина Афанасіївна\nГалина Афанасіївна Висоцька\nГалина Висоцька\nВисоцька Галина Афанасіївна\nМиколаївська область\nсуддя вознесенського міськрайонного суду миколаївської області\nЗагальний місцевий суд\nВисоцька Галина Афанасіївна\n64.9\n800\n240\n2014","general":{"inn":"","name":"Галина","patronymic_unclear":false,"last_name_hidden":false,"family":[{"inn":"","inn_hidden":true,"relations_unclear":false,"relations_hidden":false,"relations_other":"","relations":"Подружжя","name_hidden":false,"inn_unclear":false,"family_name":"Висоцький Віталій Георгійович","name_unclear":false},{"inn":"","inn_hidden":false,"relations_unclear":false,"relations_hidden":false,"relations_other":"","relations":"Дитина","name_hidden":false,"inn_unclear":false,"family_name":"Шмідт Ірина Віталіївна","name_unclear":false}],"patronymic":"Афанасіївна","inn_hidden":true,"family_raw":"","inn_unclear":false,"post":{"post_unclear":false,"post":"суддя вознесенського міськрайонного суду миколаївської області","post_hidden":false,"region":"Миколаївська область","region_hidden":false,"office":"Загальний місцевий суд","office_hidden":false,"office_unclear":false},"last_name_unclear":false,"full_name":"Висоцька Галина Афанасіївна","addresses":[{"place_city_type_hidden":true,"place_district_hidden":true,"place_city_type":"","place_city_hidden":true,"place_address_unclear":false,"place_address":"","place":"","place_district":"","place_unclear":false,"place_city":"","place_city_unclear":false,"place_hidden":true,"place_address_hidden":true,"place_district_unclear":false}],"last_name":"Висоцька","full_name_suggest":{"output":"Висоцька Галина Афанасіївна","input":["Висоцька Галина Афанасіївна","Галина Афанасіївна Висоцька","Галина Висоцька"]},"name_unclear":false},"source":"VULYK","estate":{"25":[{"space_unclear":false,"costs":"","costs_comment":"","costs_hidden":false,"address_hidden":false,"region_hidden":true,"space_comment":"","space":"64.9","address":"","region":"","address_unclear":false,"space_units_unclear":false,"space_comment_unclear":false,"space_units":"м²","costs_rent":"","costs_rent_comment":""}],"29":[{"region_unclear":false,"space_unclear":false,"address_hidden":false,"region_hidden":true,"space_comment":"","space_units_hidden":false,"space_hidden":false,"space":"800","address":"","region":"","costs_property":"","costs_rent_comment":"","space_units":"м²","costs_property_comment":"","costs_rent":""}]},"intro":{"declaration_year":"2014","isnotdeclaration":"","declaration_year_hidden":false}}