{"income":{"5":{"value":"227691","family_comment":"","value_unclear":false,"family_hidden":false,"value_hidden":false,"family_unclear":false,"comment_unclear":false,"comment":"","family":""},"6":{"value":"227691","family_unclear":false,"family_hidden":false,"family_comment":"","family":"","comment":""},"7":{"value":"","family_hidden":false,"value_hidden":false,"family_comment":"","source_name":"","family":"","comment":""},"8":{"family_comment":"","value":"","family":"","comment":""},"9":{"family_comment":"","value":"","value_unclear":false,"family":"","comment":""},"10":{"family_comment":"","family_unclear":false,"value":"","family":"","comment":""},"11":{"family_comment":"","value":"","family":"","comment":""},"12":{"family_comment":"","value":"","family":"","comment":""},"13":{"family_comment":"","value":"","family":"","comment":""},"14":{"family_comment":"","value":"","family":"","comment":""},"15":{"family_comment":"","value":"","family":"","comment":""},"16":{"family_comment":"","value":"","family":"","comment":""},"17":{"family_comment":"","value":"","family":"","comment":""},"18":{"family_comment":"","value":"","family":"","comment":""},"19":{"family_comment":"","value":"","family":"","comment":""},"20":{"value":"","value_unclear":false,"family_comment":"","comment_unclear":false,"comment":"","family":""}},"id":"vulyk_71_173","declaration":{"additional_info_text":"","notfull_lostpages":"","date":"2014-03-21T00:00:00","notfull":"","additional_info":"","url":"http://static.declarations.com.ua/declarations/chosen_ones/judges_batch/429_lachenkova_oksana_volodymyrivna.pdf"},"liabilities":{"54":{"sum_foreign_comment":"","sum":"","sum_comment":"","sum_comment_unclear":false,"sum_comment_hidden":false,"sum_unclear":false,"sum_foreign":""},"55":{"sum_foreign_comment":"","sum":"","sum_comment":"","sum_foreign":""},"56":{"sum_foreign_comment":"","sum":"","sum_comment":"","sum_comment_unclear":false,"sum_unclear":false,"sum_foreign":""},"57":{"sum_foreign_comment":"","sum":"6000","sum_comment":"","sum_comment_hidden":false,"sum_unclear":false,"sum_foreign":""},"58":{"sum_foreign_comment":"","sum":"4132.43","sum_comment":"","sum_comment_hidden":false,"sum_unclear":false,"sum_foreign":""},"59":{"sum_foreign_comment":"","sum_comment_hidden":false,"sum":"","sum_comment":"","sum_foreign":""},"60":{"sum_foreign_comment":"","sum_comment_hidden":false,"sum":"","sum_comment":"","sum_foreign":""},"61":{"sum_foreign_comment":"","sum":"","sum_comment":"","sum_foreign":""},"62":{"sum_foreign_comment":"","sum":"","sum_comment":"","sum_foreign":""},"63":{"sum_foreign_comment":"","sum":"","sum_comment":"","sum_unclear":false,"sum_foreign":""},"64":{"sum_foreign_comment":"","sum":"","sum_comment":"","sum_unclear":false,"sum_foreign":""}},"ft_src":"6000\n4132.43\nсуддя апеляційного суду дніпропетровської області\nДніпропетровська область\nЗагальний апеляційний суд\nОксана\nЛаченков Ігор\nДитина\nВолодимирівна\nЛаченкова Оксана Володимирівна\nОксана Володимирівна Лаченкова\nОксана Лаченкова\nЛаченкова Оксана Володимирівна\nЛаченкова Оксана Володимирівна\nЛаченкова\n227691\n227691\n43\n2013\n227691\n227691\n227691\n227691\nДитина\nЛаченков Ігор\nЛаченкова Оксана Володимирівна\nОксана Володимирівна Лаченкова\nОксана Лаченкова\nЛаченкова Оксана Володимирівна\nЛаченкова Оксана Володимирівна\nОксана\nВолодимирівна\nЗагальний апеляційний суд\nДніпропетровська область\nсуддя апеляційного суду дніпропетровської області\nЛаченкова\n4132.43\n6000\n43\n2013\n4132.43\n6000\nЛаченков Ігор\nДитина\nВолодимирівна\nЛаченкова\nОксана\nЛаченкова Оксана Володимирівна\nОксана Володимирівна Лаченкова\nОксана Лаченкова\nЛаченкова Оксана Володимирівна\nДніпропетровська область\nЗагальний апеляційний суд\nсуддя апеляційного суду дніпропетровської області\nЛаченкова Оксана Володимирівна\n43\n2013","general":{"inn":"","name":"Оксана","family":[{"inn":"","inn_hidden":true,"relations_hidden":false,"family_name":"Лаченков Ігор","relations_other":"","relations":"Дитина","name_hidden":true,"name_unclear":false}],"patronymic":"Володимирівна","inn_hidden":true,"family_raw":"","inn_unclear":false,"post":{"post_unclear":false,"region_unclear":false,"post":"суддя апеляційного суду дніпропетровської області","office":"Загальний апеляційний суд","region":"Дніпропетровська область","post_hidden":false,"office_unclear":false},"full_name_suggest":{"output":"Лаченкова Оксана Володимирівна","input":["Лаченкова Оксана Володимирівна","Оксана Володимирівна Лаченкова","Оксана Лаченкова"]},"full_name":"Лаченкова Оксана Володимирівна","addresses":[{"place_district":"","place_unclear":false,"place_city":"","place_city_type_hidden":true,"place_district_hidden":true,"place_city_type":"","place_city_hidden":true,"place_address_hidden":true,"place_address":"","place_hidden":true,"place":""}],"last_name":"Лаченкова","patronymic_hidden":false,"last_name_unclear":false,"name_unclear":false},"source":"VULYK","estate":{"25":[{"region_unclear":false,"space_unclear":false,"costs":"","costs_rent_unclear":false,"costs_comment":"","costs_hidden":false,"address_hidden":true,"region_hidden":true,"space_comment":"","space_hidden":false,"space":"43","address":"","costs_unclear":false,"region":"","address_unclear":false,"costs_rent_comment":"","costs_rent_hidden":false,"space_comment_unclear":false,"space_units":"м²","costs_rent":""}]},"intro":{"declaration_year":"2013","isnotdeclaration":""}}