{"income":{"5":{"value":"210490.92","family_comment":"","value_unclear":false,"family_hidden":false,"family_unclear":false,"family":"39633","comment":""},"6":{"family_comment":"","value":"210490.92","family":"16173","comment":""},"7":{"family_comment":"","value":"","source_name":"","family":"","comment":""},"8":{"family_comment":"","value":"","family":"","comment":""},"9":{"family_comment":"","value":"","family":"","comment":""},"10":{"family_comment":"","value":"","value_unclear":false,"family":"","comment":""},"11":{"family_comment":"","value":"","family":"","comment":""},"12":{"family_comment":"","value":"","family":"","comment":""},"13":{"family_comment":"","value":"","family":"","comment":""},"14":{"family_comment":"","value":"","family":"","comment":""},"15":{"family_comment":"","value":"","family":"","comment":""},"16":{"family_comment":"","value":"","family":"","comment":""},"17":{"family_comment":"","value":"","family":"","comment":""},"18":{"family_comment":"","value":"","family":"","comment":""},"19":{"family_comment":"","value":"","family":"","comment":""},"20":{"family_comment":"","value":"","family":"23460","comment":""}},"vehicle":{"35":[{"brand_info":"1998 куб. см. 112 кВт","sum_rent_comment":"","brand":"Toyota Rav 4","sum_comment":"","brand_unclear":false,"year":"2005","sum":"","sum_rent":""}]},"id":"vulyk_82_32","declaration":{"date":"2015-03-30T00:00:00","additional_info_text":"","additional_info":"","url":"http://static.declarations.com.ua/declarations/chosen_ones/judges_batch/2227_zaruba_petro_ivanovych.pdf"},"liabilities":{"54":{"sum_foreign_comment":"","sum_comment_hidden":false,"sum":"","sum_comment":"","sum_foreign":""},"55":{"sum_foreign_comment":"","sum":"","sum_hidden":false,"sum_comment":"","sum_foreign":""},"56":{"sum_foreign_comment":"","sum":"","sum_comment":"","sum_foreign":""},"57":{"sum_foreign_comment":"","sum":"","sum_comment":"","sum_foreign":""},"58":{"sum_foreign_comment":"","sum":"","sum_comment":"","sum_foreign":""},"59":{"sum_foreign_comment":"","sum":"","sum_comment":"","sum_foreign":""},"60":{"sum_foreign_comment":"","sum":"","sum_comment":"","sum_foreign":""},"61":{"sum_foreign_comment":"","sum":"","sum_comment":"","sum_foreign":""},"62":{"sum_foreign_comment":"","sum":"","sum_comment":"","sum_foreign":""},"63":{"sum_foreign_comment":"","sum":"","sum_comment":"","sum_foreign":""},"64":{"sum_foreign_comment":"","sum":"","sum_comment":"","sum_foreign":""}},"ft_src":"заступник голови дарницького районного суду міста києва\nм. Київ\nЗагальний місцевий суд\nПетро\nПодружжя\nДитина\nДитина\nІванович\nЗаруба Петро Іванович\nПетро Іванович Заруба\nПетро Заруба\nЗаруба Петро Іванович\nЗаруба Петро Іванович\nЗаруба\n2005\n1998 куб. см. 112 кВт\nToyota Rav 4\n81\n1/4 частка\n62.6\n2014\n16173\n210490.92\n39633\n210490.92\n23460\n1998 куб. см. 112 кВт\n2005\nToyota Rav 4\n2014\nПодружжя\nДитина\nДитина\nЗаруба Петро Іванович\nПетро Іванович Заруба\nПетро Заруба\nЗаруба Петро Іванович\nЗаруба Петро Іванович\nПетро\nЗаруба\nЗагальний місцевий суд\nм. Київ\nзаступник голови дарницького районного суду міста києва\nІванович\n210490.92\n16173\n23460\n210490.92\n39633\n81\n62.6\n1/4 частка\nПодружжя\nДитина\nДитина\nІванович\nЗаруба\nПетро\nЗаруба Петро Іванович\nПетро Іванович Заруба\nПетро Заруба\nЗаруба Петро Іванович\nм. Київ\nЗагальний місцевий суд\nзаступник голови дарницького районного суду міста києва\nЗаруба Петро Іванович\n2005\n1998 куб. см. 112 кВт\nToyota Rav 4\n23460\n210490.92\n39633\n16173\n210490.92\n81\n1/4 частка\n62.6\n2014","general":{"inn":"","name":"Петро","inn_unclear":false,"family":[{"inn":"","inn_hidden":true,"relations_hidden":false,"family_name":"","relations_other":"","relations":"Подружжя","name_hidden":true,"name_unclear":false},{"inn":"","relations":"Дитина","relations_other":"","inn_hidden":false,"family_name":"","name_hidden":true,"name_unclear":false},{"inn":"","relations":"Дитина","relations_other":"","inn_hidden":false,"family_name":"","name_hidden":true,"name_unclear":false}],"inn_hidden":true,"family_raw":"","last_name":"Заруба","post":{"post":"заступник голови дарницького районного суду міста києва","region":"м. Київ","office_hidden":false,"office":"Загальний місцевий суд","office_unclear":false,"post_hidden":false,"region_hidden":false},"full_name_suggest":{"output":"Заруба Петро Іванович","input":["Заруба Петро Іванович","Петро Іванович Заруба","Петро Заруба"]},"full_name":"Заруба Петро Іванович","addresses":[{"place_district":"","place_city_hidden":true,"place_city":"","place_city_type_hidden":false,"place_district_hidden":false,"place_city_type":"","place_address_hidden":false,"place_address":"","place_hidden":true,"place":""}],"patronymic":"Іванович","last_name_unclear":false},"source":"VULYK","estate":{"25":[{"space_hidden":false,"costs":"","costs_comment":"","costs_hidden":false,"address_hidden":false,"region_hidden":true,"space_comment":"1/4 частка","space_unclear":false,"space":"62.6","address":"","region":"","costs_rent_comment":"","space_comment_unclear":false,"space_units":"м²","costs_rent":""}],"31":[{"space_unclear":false,"address_hidden":false,"region_hidden":true,"space_comment":"","space":"81","address":"","region":"","costs_property":"","costs_rent_comment":"","space_comment_unclear":false,"space_units":"м²","costs_property_comment":"","costs_rent":""}]},"intro":{"declaration_year":"2014"}}