{"income":{"5":{"family_comment":"","value":"244747.41","family_hidden":false,"comment":"","family":"92476.53"},"6":{"value":"232567.41","value_unclear":false,"family_hidden":false,"family_comment":"","family":"79802.35","comment":""},"7":{"value":"","value_unclear":false,"family_comment":"","source_name":"","family":"","comment":""},"8":{"family_comment":"","value":"","family":"","comment":""},"9":{"family_comment":"","value":"","family":"","comment":""},"10":{"value":"12180","family_comment":"","comment_unclear":false,"family_unclear":false,"family":"12774.18","comment":"","family_comment_unclear":false},"11":{"family_comment":"","value":"","value_unclear":false,"family":"","comment":""},"12":{"family_comment":"","value":"","family":"","comment":""},"13":{"family_comment":"","value":"","family":"","comment":""},"14":{"family_comment":"","value":"","family":"","comment":""},"15":{"value":"","family_comment":"","comment_unclear":false,"family_unclear":false,"family":"","comment":""},"16":{"family_comment":"","value":"","family":"","comment":""},"17":{"family_comment":"","value":"","family":"","comment":""},"18":{"family_comment":"","family_unclear":false,"value":"","family":"","comment":""},"19":{"family_comment":"","value":"","family":"","comment":""},"20":{"family_comment":"","family_unclear":false,"value":"","family":"","comment":""}},"vehicle":{"35":[{"brand_info":"1.6 л","sum_rent_comment":"","year":"1996","brand_info_hidden":false,"brand_info_unclear":false,"year_unclear":false,"sum_rent":"","sum":"","brand":"Opel Vectra","sum_comment":"","sum_comment_unclear":false,"brand_hidden":false,"brand_unclear":false}]},"id":"vulyk_92_134","declaration":{"additional_info_text":"","notfull_lostpages":"","date":"2015-03-23T00:00:00","notfull":"","additional_info":"","url":"http://static.declarations.com.ua/declarations/chosen_ones/judges_batch/3382_hotsko_vasyl_ivanovych.pdf"},"liabilities":{"54":{"sum_foreign_comment":"","sum":"","sum_comment":"","sum_hidden":false,"sum_unclear":false,"sum_foreign":""},"55":{"sum_foreign_comment":"","sum":"","sum_comment":"","sum_unclear":false,"sum_foreign":""},"56":{"sum_foreign_comment":"","sum":"60000","sum_comment":"","sum_comment_unclear":false,"sum_hidden":false,"sum_unclear":false,"sum_foreign":""},"57":{"sum_foreign_comment":"","sum":"","sum_comment":"","sum_hidden":false,"sum_comment_hidden":false,"sum_foreign":""},"58":{"sum_foreign_comment":"","sum":"","sum_comment":"","sum_foreign":""},"59":{"sum_foreign_comment":"","sum":"","sum_comment":"","sum_comment_unclear":false,"sum_foreign":""},"60":{"sum_foreign_comment":"","sum":"","sum_comment":"","sum_foreign":""},"61":{"sum_foreign_comment":"","sum":"","sum_comment":"","sum_foreign":""},"62":{"sum_foreign_comment":"","sum":"4000","sum_comment":"","sum_comment_unclear":false,"sum_hidden":false,"sum_unclear":false,"sum_foreign":""},"63":{"sum_foreign_comment":"","sum":"","sum_comment":"","sum_foreign":""},"64":{"sum_foreign_comment":"","sum":"","sum_comment":"","sum_foreign":""}},"ft_src":"4000\n60000\nзаступник голови яворівського районного суду львівської області\nЛьвівська область\nЗагальний місцевий суд\nВасиль\nГоцко Надія Петрівна\nПодружжя\nІванович\nГоцко Василь Іванович\nВасиль Іванович Гоцко\nВасиль Гоцко\nГоцко Василь Іванович\nГоцко Василь Іванович\nГоцко\n1.6 л\nOpel Vectra\n1996\n.0535\n.137\n29.1\n2014\n79802.35\n232567.41\n12774.18\n12180\n92476.53\n244747.41\n1.6 л\nOpel Vectra\n1996\n.0535\n.137\n29.1\nПодружжя\nГоцко Надія Петрівна\nГоцко Василь Іванович\nВасиль Іванович Гоцко\nВасиль Гоцко\nГоцко Василь Іванович\nГоцко Василь Іванович\nВасиль\nГоцко\nЗагальний місцевий суд\nзаступник голови яворівського районного суду львівської області\nЛьвівська область\nІванович\n60000\n4000\n232567.41\n79802.35\n244747.41\n92476.53\n12180\n12774.18\n2014\n60000\n4000\nПодружжя\nГоцко Надія Петрівна\nІванович\nГоцко\nВасиль\nГоцко Василь Іванович\nВасиль Іванович Гоцко\nВасиль Гоцко\nГоцко Василь Іванович\nЛьвівська область\nЗагальний місцевий суд\nзаступник голови яворівського районного суду львівської області\nГоцко Василь Іванович\n1996\nOpel Vectra\n1.6 л\n12180\n12774.18\n92476.53\n244747.41\n232567.41\n79802.35\n29.1\n.0535\n.137\n2014","general":{"inn":"","name":"Василь","patronymic_unclear":false,"family":[{"inn":"","relations":"Подружжя","inn_unclear":false,"relations_hidden":false,"inn_hidden":true,"relations_other":"","name_hidden":true,"family_name":"Гоцко Надія Петрівна","name_unclear":false}],"patronymic":"Іванович","inn_hidden":true,"family_raw":"","inn_unclear":false,"post":{"post_unclear":false,"post":"заступник голови яворівського районного суду львівської області","office_hidden":false,"region":"Львівська область","office":"Загальний місцевий суд","office_unclear":false,"region_hidden":false},"full_name":"Гоцко Василь Іванович","addresses":[{"place_district":"","place_address_hidden":true,"place_city":"","place_city_type_hidden":true,"place_district_hidden":true,"place_city_type":"","place_city_hidden":true,"place_address_unclear":false,"place_address":"","place_hidden":true,"place":""}],"last_name":"Гоцко","full_name_suggest":{"output":"Гоцко Василь Іванович","input":["Гоцко Василь Іванович","Василь Іванович Гоцко","Василь Гоцко"]}},"source":"VULYK","estate":{"23":[{"region_unclear":false,"space_unclear":false,"costs":"","costs_comment":"","address_hidden":true,"region_hidden":true,"space_comment":"","space":".0535","address":"","region":"","costs_rent_comment":"","space_units":"га","costs_rent":""}],"29":[{"space_unclear":false,"space_units_unclear":false,"address_hidden":true,"region_hidden":true,"space_comment":"","space_units_hidden":false,"space":".137","address":"","region":"","costs_property":"","costs_rent_comment":"","space_units":"га","costs_property_comment":"","costs_rent":""}],"31":[{"space_unclear":false,"address_hidden":true,"region_hidden":true,"space_comment":"","space_hidden":false,"space":"29.1","address":"","region":"","costs_property":"","costs_rent_comment":"","address_unclear":false,"space_units":"м²","costs_property_comment":"","costs_rent":""}]},"intro":{"declaration_year":"2014","isnotdeclaration":""}}