{"income":{"5":{"value":"242744","value_unclear":false,"value_hidden":false,"family_comment":"","family":"27222","comment":""},"6":{"value":"242744","family_comment":"","value_unclear":false,"family_unclear":false,"family":"27222","comment":""},"7":{"source_name_unclear":false,"value":"","family_hidden":false,"family_comment":"","source_name":"","family":"","comment":""},"8":{"family_comment":"","value":"","family":"","comment":""},"9":{"family_comment":"","value":"","family":"","comment":""},"10":{"family_comment":"","value":"","family":"","comment":""},"11":{"family_comment":"","value":"","family":"","comment":""},"12":{"family_comment":"","value":"","family":"","comment":""},"13":{"family_comment":"","value":"","family":"","comment":""},"14":{"family_comment":"","value":"","family":"","comment":""},"15":{"family_comment":"","value":"","family":"","comment":""},"16":{"family_comment":"","value":"","comment_unclear":false,"family":"","comment":""},"17":{"family_comment":"","family_unclear":false,"value":"","family":"","comment":""},"18":{"family_comment":"","value":"","family":"","comment":""},"19":{"value":"","family_hidden":false,"value_hidden":false,"family_comment":"","family":"","comment":""},"20":{"family_comment":"","value":"","comment_unclear":false,"family":"","comment":""}},"vehicle":{"40":[{"brand_info":"1498 куб. см.","sum_rent_comment":"","brand":"Chevrolet Aveo","sum_comment":"","brand_unclear":false,"year":"2005","brand_info_unclear":false,"year_unclear":false,"sum":"","sum_rent":""}]},"id":"vulyk_67_77","banks":{"47":[{"sum_foreign_comment":"","sum":"332","sum_comment":"","sum_comment_unclear":false,"sum_hidden":false,"sum_foreign_units":"UAH","sum_foreign_hidden":false,"sum_units":"UAH","sum_comment_hidden":false,"sum_unclear":false,"sum_foreign":""}],"52":[{"sum_foreign_comment":"","sum_units":"UAH","sum_comment":"","sum_foreign_units":"UAH","sum":"664","sum_foreign":""}]},"declaration":{"additional_info_text":"","notfull_lostpages":"","date":"2015-03-25T00:00:00","notfull":"","additional_info":"","url":"http://static.declarations.com.ua/declarations/chosen_ones/mega_batch/sliusarchuk_vasyl_mykhailovych.pdf"},"liabilities":{"54":{"sum_foreign_comment":"","sum_foreign_hidden":false,"sum_comment":"","sum_comment_unclear":false,"sum_hidden":false,"sum":"","sum_unclear":false,"sum_foreign":""},"55":{"sum_foreign_comment":"","sum":"","sum_comment":"","sum_foreign":""},"56":{"sum_foreign_comment":"","sum_foreign_hidden":false,"sum_comment":"","sum_hidden":false,"sum":"","sum_unclear":false,"sum_foreign":""},"57":{"sum_foreign_comment":"","sum_foreign_hidden":false,"sum_comment":"","sum_comment_unclear":false,"sum_hidden":false,"sum_comment_hidden":false,"sum_unclear":false,"sum":"","sum_foreign":""},"58":{"sum_foreign_comment":"","sum_foreign_hidden":false,"sum_comment":"","sum_comment_unclear":false,"sum_hidden":false,"sum_comment_hidden":false,"sum_unclear":false,"sum":"","sum_foreign":""},"59":{"sum_foreign_comment":"","sum":"","sum_hidden":false,"sum_comment":"","sum_foreign":""},"60":{"sum_foreign_comment":"","sum":"","sum_comment":"","sum_foreign":""},"61":{"sum_foreign_comment":"","sum_foreign_hidden":false,"sum_comment":"","sum_hidden":false,"sum":"","sum_foreign":""},"62":{"sum_foreign_comment":"","sum":"","sum_hidden":false,"sum_comment":"","sum_foreign":""},"63":{"sum_foreign_comment":"","sum":"","sum_comment":"","sum_comment_unclear":false,"sum_hidden":false,"sum_unclear":false,"sum_foreign":""},"64":{"sum_foreign_comment":"","sum":"","sum_comment":"","sum_hidden":false,"sum_unclear":false,"sum_foreign":""}},"ft_src":"суддя мукачівського міськрайонного суду закарпатської області\nЗакарпатська область\nЗагальний місцевий суд\nВасиль\nСлюсарчук Т. В\nПодружжя\nСлюсарчук В. В\nДитина\nМихайлович\nСлюсарчук Василь Михайлович\nСлюсарчук\nСлюсарчук Василь Михайлович\nВасиль Михайлович Слюсарчук\nВасиль Слюсарчук\nСлюсарчук Василь Михайлович\n1498 куб. см.\nChevrolet Aveo\n2005\n332\n664\n2014\n1498 куб. см.\n2005\nChevrolet Aveo\n664\n332\n800\n84.1\n84.1\nЗагальний місцевий суд\nсуддя мукачівського міськрайонного суду закарпатської області\nЗакарпатська область\nПодружжя\nСлюсарчук Т. В\nДитина\nСлюсарчук В. В\nСлюсарчук Василь Михайлович\nВасиль Михайлович Слюсарчук\nВасиль Слюсарчук\nСлюсарчук Василь Михайлович\nСлюсарчук Василь Михайлович\nВасиль\nСлюсарчук\nМихайлович\n27222\n242744\n242744\n27222\n2014\n84.1\n800\n84.1\nПодружжя\nСлюсарчук Т. В\nДитина\nСлюсарчук В. В\nМихайлович\nСлюсарчук\nВасиль\nСлюсарчук Василь Михайлович\nВасиль Михайлович Слюсарчук\nВасиль Слюсарчук\nСлюсарчук Василь Михайлович\nЗакарпатська область\nсуддя мукачівського міськрайонного суду закарпатської області\nЗагальний місцевий суд\nСлюсарчук Василь Михайлович\n27222\n242744\n27222\n242744\n2005\n1498 куб. см.\nChevrolet Aveo\n242744\n27222\n242744\n27222\n84.1\n84.1\n800\n332\n664\n2014","general":{"inn":"","name":"Василь","patronymic_unclear":false,"last_name_hidden":false,"family":[{"inn":"","inn_hidden":true,"relations_unclear":false,"relations_hidden":false,"relations_other":"","relations":"Подружжя","name_hidden":true,"inn_unclear":false,"family_name":"Слюсарчук Т. В","name_unclear":false},{"inn":"","inn_hidden":true,"relations_unclear":false,"relations_hidden":false,"relations_other":"","relations":"Дитина","name_hidden":false,"inn_unclear":false,"family_name":"Слюсарчук В. В","name_unclear":false}],"patronymic":"Михайлович","inn_hidden":true,"family_raw":"","inn_unclear":false,"post":{"post_unclear":false,"post":"суддя мукачівського міськрайонного суду закарпатської області","post_hidden":false,"region":"Закарпатська область","region_hidden":false,"office":"Загальний місцевий суд","office_hidden":false,"office_unclear":false},"last_name_unclear":false,"full_name":"Слюсарчук Василь Михайлович","addresses":[{"place_city_type_hidden":true,"place_district_hidden":true,"place_city_type":"","place_city_hidden":true,"place_address_unclear":false,"place_address":"","place":"","place_district":"","place_unclear":false,"place_city":"","place_city_unclear":false,"place_hidden":true,"place_address_hidden":true,"place_district_unclear":false}],"last_name":"Слюсарчук","full_name_suggest":{"output":"Слюсарчук Василь Михайлович","input":["Слюсарчук Василь Михайлович","Василь Михайлович Слюсарчук","Василь Слюсарчук"]},"name_unclear":false},"source":"VULYK","estate":{"25":[{"space_unclear":false,"costs":"","costs_comment":"","costs_hidden":false,"address_hidden":true,"region_hidden":true,"space_comment":"","space":"84.1","address":"","region":"","address_unclear":false,"space_units_unclear":false,"space_comment_unclear":false,"space_units":"м²","costs_rent":"","costs_rent_comment":""}],"29":[{"region_unclear":false,"space_unclear":false,"address_hidden":true,"region_hidden":true,"space_comment":"","space_units_hidden":false,"space_hidden":false,"space":"800","address":"","region":"","costs_property":"","costs_rent_comment":"","space_units":"м²","costs_property_comment":"","costs_rent":""}],"31":[{"space_hidden":false,"address_hidden":true,"region_hidden":true,"space_comment":"","space_unclear":false,"space":"84.1","address":"","region":"","costs_property":"","costs_rent_comment":"","space_comment_unclear":false,"address_unclear":false,"space_units":"м²","costs_property_comment":"","costs_rent":""}]},"intro":{"declaration_year":"2014","isnotdeclaration":"","declaration_year_hidden":false}}