{"income":{"5":{"family_comment":"","value":"171377","value_unclear":false,"family":"","comment":""},"6":{"value":"171377","value_unclear":false,"family_hidden":false,"family_comment":"","family":"","comment":""},"7":{"source_name_unclear":false,"value":"","family_comment":"","source_name":"","family":"","comment":""},"8":{"family_comment":"","value":"","family":"","comment":""},"9":{"family_comment":"","value":"","family":"","comment":""},"10":{"family_comment":"","value":"","family":"","comment":""},"11":{"family_comment":"","value":"","comment_unclear":false,"family":"","comment":""},"12":{"family_comment":"","value":"","family":"","comment":""},"13":{"family_comment":"","value":"","family":"","comment":""},"14":{"family_comment":"","value":"","family":"","comment":""},"15":{"family_comment":"","value":"","family":"","comment":""},"16":{"family_comment":"","value":"","family":"","comment":""},"17":{"family_comment":"","value":"","family":"","comment":""},"18":{"family_comment":"","value":"","family":"","comment":""},"19":{"family_comment":"","value":"","family":"","comment":""},"20":{"value":"","family_comment":"","value_unclear":false,"family_unclear":false,"comment_unclear":false,"comment":"","family":""}},"id":"vulyk_101_146","declaration":{"additional_info_text":"","notfull_lostpages":"","date":"2016-03-16T00:00:00","notfull":"","additional_info":"","url":"http://static.declarations.com.ua/declarations/chosen_ones/judges_batch/861_chernysh_tetiana_oleksandrivna_2015.pdf"},"liabilities":{"54":{"sum_foreign_comment":"","sum":"","sum_comment":"","sum_comment_unclear":false,"sum_hidden":false,"sum_comment_hidden":false,"sum_unclear":false,"sum_foreign":""},"55":{"sum_foreign_comment":"","sum":"","sum_comment":"","sum_foreign":""},"56":{"sum_foreign_comment":"","sum":"","sum_comment":"","sum_comment_hidden":false,"sum_unclear":false,"sum_foreign":""},"57":{"sum_foreign_comment":"","sum":"","sum_comment":"","sum_hidden":false,"sum_comment_hidden":false,"sum_unclear":false,"sum_foreign":""},"58":{"sum_foreign_comment":"","sum":"","sum_comment":"","sum_comment_unclear":false,"sum_hidden":false,"sum_comment_hidden":false,"sum_unclear":false,"sum_foreign":""},"59":{"sum_foreign_comment":"","sum":"","sum_comment":"","sum_foreign":""},"60":{"sum_foreign_comment":"","sum":"","sum_comment":"","sum_hidden":false,"sum_comment_hidden":false,"sum_unclear":false,"sum_foreign":""},"61":{"sum_foreign_comment":"","sum":"","sum_comment":"","sum_foreign":""},"62":{"sum_foreign_comment":"","sum":"","sum_comment":"","sum_comment_unclear":false,"sum_foreign":""},"63":{"sum_foreign_comment":"","sum_comment_hidden":false,"sum":"","sum_comment":"","sum_foreign":""},"64":{"sum_foreign_comment":"","sum_comment_hidden":false,"sum":"","sum_comment":"","sum_foreign":""}},"ft_src":"суддя уманського міськрайонного суду черкаської області\nЧеркаська область\nЗагальний місцевий суд\nТетяна\nВеличко В. О\nДитина\nОлександрівна\nЧерниш Тетяна Олександрівна\nЧерниш\nЧерниш Тетяна Олександрівна\nТетяна Олександрівна Черниш\nТетяна Черниш\nЧерниш Тетяна Олександрівна\n171377\n171377\n57.7\n2015\n171377\n171377\n57.7\nДитина\nВеличко В. О\nЧерниш Тетяна Олександрівна\nТетяна Олександрівна Черниш\nТетяна Черниш\nЧерниш Тетяна Олександрівна\nТетяна\nЧерниш Тетяна Олександрівна\nОлександрівна\nЗагальний місцевий суд\nсуддя уманського міськрайонного суду черкаської області\nЧеркаська область\nЧерниш\n171377\n171377\n2015\nВеличко В. О\nДитина\nТетяна\nОлександрівна\nЧерниш\nЧерниш Тетяна Олександрівна\nТетяна Олександрівна Черниш\nТетяна Черниш\nЧерниш Тетяна Олександрівна\nсуддя уманського міськрайонного суду черкаської області\nЗагальний місцевий суд\nЧеркаська область\nЧерниш Тетяна Олександрівна\n57.7\n2015","general":{"inn":"","name":"Тетяна","inn_unclear":false,"family":[{"inn":"","relations":"Дитина","relations_other":"","inn_hidden":true,"family_name":"Величко В. О","name_hidden":true,"name_unclear":false}],"inn_hidden":true,"family_raw":"","last_name":"Черниш","post":{"region":"Черкаська область","region_unclear":false,"post":"суддя уманського міськрайонного суду черкаської області","office_unclear":false,"office":"Загальний місцевий суд"},"full_name":"Черниш Тетяна Олександрівна","addresses":[{"place_district":"","place_city_hidden":true,"place_city":"","place_city_type_hidden":true,"place_district_hidden":true,"place_city_type":"","place_address_hidden":true,"place_address":"","place_hidden":true,"place":""}],"patronymic":"Олександрівна","patronymic_hidden":false,"full_name_suggest":{"output":"Черниш Тетяна Олександрівна","input":["Черниш Тетяна Олександрівна","Тетяна Олександрівна Черниш","Тетяна Черниш"]}},"source":"VULYK","estate":{"25":[{"space_unclear":false,"costs":"","costs_comment":"","address_hidden":true,"region_hidden":true,"space_comment":"","space_hidden":false,"space":"57.7","address":"","region":"","costs_rent_comment":"","space_comment_unclear":false,"space_units":"м²","costs_rent":""}]},"intro":{"declaration_year":"2015"}}