{"income":{"5":{"value":"343503","family_comment":"","value_unclear":false,"family_hidden":false,"family_unclear":false,"family_comment_unclear":false,"family_comment_hidden":false,"comment":"","family":"25308"},"6":{"value":"263932","family_comment":"","value_unclear":false,"family_hidden":false,"family_unclear":false,"family":"","comment":""},"7":{"value":"3874","comment_unclear":false,"family_comment":"","source_name":"","family_comment_unclear":false,"family":"","comment":"","source_name_hidden":false},"8":{"value":"","comment_unclear":false,"family_comment":"","family":"","comment":"","family_comment_unclear":false},"9":{"family_comment":"","value":"","family":"","comment":""},"10":{"value":"","family_comment":"","value_unclear":false,"family_hidden":false,"family_unclear":false,"family":"","comment":""},"11":{"value":"","family_unclear":false,"family_hidden":false,"family_comment":"","family":"","comment":""},"12":{"value":"","family_unclear":false,"family_hidden":false,"family_comment":"","family":"","comment":""},"13":{"family_comment":"","value":"","family_hidden":false,"comment":"","family":""},"14":{"family_comment":"","value":"","family_hidden":false,"comment":"","family":""},"15":{"family_comment":"","value":"","family_hidden":false,"comment":"","family":""},"16":{"value":"","family_hidden":false,"value_hidden":false,"family_comment":"","family":"","comment":""},"17":{"family_comment":"","value":"","family":"","comment":""},"18":{"value":"","family_comment":"","value_unclear":false,"family_unclear":false,"family":"","comment":""},"19":{"value":"","family_comment":"","value_unclear":false,"family_unclear":false,"comment_unclear":false,"comment":"","family":""},"20":{"value":"75697","family_comment":"","value_unclear":false,"family_unclear":false,"comment_unclear":false,"comment":"","family":"25308"}},"vehicle":{"35":[{"brand_info":"","sum_rent_comment":"","year":"1994","sum_rent_unclear":false,"brand_info_hidden":false,"brand_info_unclear":false,"year_unclear":false,"sum_rent":"","sum":"","brand":"ВАЗ 2121","sum_comment":"","brand_unclear":false,"brand_hidden":false,"sum_unclear":false},{"brand_info":"","sum_rent_comment":"","brand":"Toyota Land Cruiser","sum_comment":"","brand_unclear":false,"year":"2008","sum":"","sum_rent":""}]},"id":"vulyk_21_183","banks":{"45":[{"sum_units":"UAH","sum_hidden":false,"sum_foreign":"","sum_foreign_comment":"","sum":"34775","sum_comment":"","sum_comment_unclear":false,"sum_foreign_units":"UAH","sum_foreign_comment_unclear":false,"sum_units_unclear":false,"sum_comment_hidden":false,"sum_unclear":false},{"sum_foreign_comment":"","sum_units":"","sum_comment":"","sum_foreign_comment_hidden":false,"sum_foreign_unclear":false,"sum_foreign_units":"","sum":"","sum_foreign":""},{"sum_foreign_comment":"","sum_units":"","sum_comment":"","sum_hidden":false,"sum_foreign_units":"","sum_comment_hidden":false,"sum_unclear":false,"sum":"","sum_foreign":""}],"46":[{"sum_foreign_comment":"","sum_units":"UAH","sum_comment":"","sum_comment_unclear":false,"sum_hidden":false,"sum_foreign_units":"UAH","sum":"","sum_unclear":false,"sum_foreign":""}],"47":[{"sum_foreign_comment":"","sum_units":"UAH","sum_comment":"","sum_comment_unclear":false,"sum_foreign_units":"UAH","sum":"","sum_unclear":false,"sum_foreign":""}],"48":[{"sum_foreign_comment":"","sum_units":"UAH","sum_comment":"","sum_foreign_units":"UAH","sum":"","sum_foreign":""}],"49":[{"sum_foreign_comment":"","sum_units":"UAH","sum_comment":"","sum_foreign_units":"UAH","sum":"","sum_foreign":""}],"50":[{"sum_foreign_comment":"","sum_units":"UAH","sum_comment":"","sum_hidden":false,"sum_foreign_units":"UAH","sum":"","sum_foreign":""}],"51":[{"sum_foreign_comment":"","sum_units":"UAH","sum_comment":"","sum_comment_unclear":false,"sum_hidden":false,"sum_foreign_units":"UAH","sum_foreign_comment_unclear":false,"sum_comment_hidden":false,"sum_unclear":false,"sum":"263025","sum_foreign":""},{"sum_foreign_comment":"","sum_units":"USD","sum_comment":"","sum_foreign_unclear":false,"sum_foreign_units":"UAH","sum_hidden":false,"sum_comment_hidden":false,"sum_unclear":false,"sum":"94673","sum_foreign":""},{"sum_foreign_comment":"","sum_units":"","sum_comment":"","sum_foreign_units":"","sum":"","sum_foreign":""}],"52":[{"sum_foreign_comment":"","sum_units":"UAH","sum_comment":"","sum_comment_unclear":false,"sum_hidden":false,"sum_foreign_units":"UAH","sum":"","sum_unclear":false,"sum_foreign":""}],"53":[{"sum_foreign_comment":"","sum_units":"UAH","sum_comment":"","sum_foreign_units":"UAH","sum":"","sum_foreign":""},{"sum_foreign_comment":"","sum_units":"","sum_comment":"","sum_foreign_units":"","sum":"","sum_foreign":""}]},"declaration":{"additional_info_text":"","notfull_lostpages":"","date":"2015-03-31T00:00:00","notfull":"","additional_info":"","url":"http://static.declarations.com.ua/declarations/chosen_ones/mega_batch/sanin_volodymyr_mykolaiovych.pdf"},"liabilities":{"54":{"sum_foreign_comment":"","sum":"855","sum_comment":"","sum_comment_unclear":false,"sum_hidden":false,"sum_foreign":""},"55":{"sum_foreign_comment":"","sum":"","sum_comment":"","sum_foreign":""},"56":{"sum_foreign_comment":"","sum":"13137.96","sum_comment":"","sum_unclear":false,"sum_foreign":""},"57":{"sum_foreign_comment":"","sum":"","sum_comment":"","sum_comment_unclear":false,"sum_hidden":false,"sum_comment_hidden":false,"sum_unclear":false,"sum_foreign":""},"58":{"sum_foreign_comment":"","sum":"","sum_comment":"","sum_comment_unclear":false,"sum_hidden":false,"sum_comment_hidden":false,"sum_unclear":false,"sum_foreign":""},"59":{"sum_foreign_comment":"","sum":"","sum_comment":"","sum_foreign":""},"60":{"sum_foreign_comment":"","sum":"","sum_comment":"","sum_hidden":false,"sum_comment_hidden":false,"sum_foreign":""},"61":{"sum_foreign_comment":"","sum":"","sum_hidden":false,"sum_comment":"","sum_foreign":""},"62":{"sum_foreign_comment":"","sum":"","sum_comment":"","sum_comment_unclear":false,"sum_foreign":""},"63":{"sum_foreign_comment":"","sum":"","sum_comment":"","sum_hidden":false,"sum_unclear":false,"sum_foreign":""},"64":{"sum_foreign_comment":"","sum":"","sum_comment":"","sum_unclear":false,"sum_foreign":""}},"ft_src":"855\n13137.96\nБіла Церква\nголова білоцерківського міськрайонного суду київської області\nКиївська область\nЗагальний місцевий суд\nВолодимир\nСаніна Т. В\nПодружжя\nСанін Д. В\nДитина\nМиколайович\nСанін Володимир Миколайович\nСанін\nСанін Володимир Миколайович\nВолодимир Миколайович Санін\nВолодимир Санін\nСанін Володимир Миколайович\nВАЗ 2121\n1994\n2008\nToyota Land Cruiser\n263025\n94673\n34775\n2014\nВАЗ 2121\n1994\nToyota Land Cruiser\n2008\n34775\n263025\n94673\n.1294\nКиївська область\nБіла Церква\n24\nБіла Церква\nКиївська область\nКиївська область\nБіла Церква\n20\n24\nКиївська область\nБіла Церква\nБіла Церква\n24\nКиївська область\n3/5 частини\nКиївська область\n152.6\n152.6\n1/5 частина\nКиївська область\nБіла Церква\nСанін Володимир Миколайович\nВолодимир Миколайович Санін\nВолодимир Санін\nСанін Володимир Миколайович\nВолодимир\nПодружжя\nСаніна Т. В\nДитина\nСанін Д. В\nСанін Володимир Миколайович\nСанін\nЗагальний місцевий суд\nголова білоцерківського міськрайонного суду київської області\nКиївська область\nМиколайович\nБіла Церква\n13137.96\n855\n3874\n263932\n25308\n75697\n343503\n25308\n2014\n13137.96\n855\nБіла Церква\n.1294\nКиївська область\nБіла Церква\n24\nКиївська область\nБіла Церква\n24\nКиївська область\nБіла Церква\nКиївська область\n24\nКиївська область\nБіла Церква\n20\n3/5 частини\nКиївська область\n152.6\n1/5 частина\nБіла Церква\n152.6\nКиївська область\nПодружжя\nСаніна Т. В\nДитина\nСанін Д. В\nМиколайович\nСанін\nВолодимир\nСанін Володимир Миколайович\nВолодимир Миколайович Санін\nВолодимир Санін\nСанін Володимир Миколайович\nБіла Церква\nКиївська область\nголова білоцерківського міськрайонного суду київської області\nЗагальний місцевий суд\nСанін Володимир Миколайович\n263932\n3874\n25308\n343503\n25308\n75697\n1994\nВАЗ 2121\n2008\nToyota Land Cruiser\n75697\n25308\n343503\n25308\n3874\n263932\n3/5 частини\nКиївська область\n152.6\n.1294\nБіла Церква\nКиївська область\nКиївська область\nБіла Церква\n24\nБіла Церква\nКиївська область\n20\n1/5 частина\nБіла Церква\nКиївська область\n152.6\nБіла Церква\nКиївська область\n24\nКиївська область\nБіла Церква\n24\n34775\n263025\n94673\n2014","general":{"name_hidden":false,"name":"Володимир","last_name_hidden":false,"inn":"","family":[{"inn":"","relations":"Подружжя","relations_unclear":false,"family_name":"Саніна Т. В","inn_hidden":true,"relations_other":"","name_hidden":false,"inn_unclear":false,"name_unclear":false},{"inn":"","relations":"Дитина","relations_unclear":false,"family_name":"Санін Д. В","inn_hidden":true,"relations_other":"","name_hidden":false,"inn_unclear":false,"name_unclear":false}],"patronymic":"Миколайович","inn_hidden":true,"family_raw":"","inn_unclear":false,"post":{"post_unclear":false,"post":"голова білоцерківського міськрайонного суду київської області","post_hidden":false,"region":"Київська область","region_hidden":false,"office":"Загальний місцевий суд","office_hidden":false,"office_unclear":false},"full_name":"Санін Володимир Миколайович","addresses":[{"place_city_type_unclear":false,"place_address":"","place_district_hidden":true,"place_city_type":"Місто","place_address_hidden":true,"place_address_unclear":false,"place_city_type_hidden":false,"place":"","place_district":"","place_unclear":false,"place_city":"Біла Церква","place_city_unclear":false,"place_hidden":true,"place_city_hidden":false,"place_district_unclear":false}],"last_name":"Санін","patronymic_hidden":false,"full_name_suggest":{"output":"Санін Володимир Миколайович","input":["Санін Володимир Миколайович","Володимир Миколайович Санін","Володимир Санін"]},"name_unclear":false},"source":"VULYK","estate":{"23":[{"region_unclear":false,"space_hidden":false,"costs":"","costs_comment":"","costs_hidden":false,"address_hidden":false,"region_hidden":false,"space_comment":"","space_unclear":false,"space_units_unclear":false,"address":"Біла Церква","region":"Київська область","address_unclear":false,"space":".1294","costs_rent_hidden":false,"space_units":"га","costs_rent":"","costs_rent_comment":""},{"costs":"","costs_comment":"","address_hidden":false,"region_hidden":false,"space_comment":"","space":"","address":"","region":"","costs_rent_comment":"","space_comment_unclear":false,"space_comment_hidden":false,"space_units":"","costs_rent":""},{"costs_rent":"","region":"","costs":"","costs_rent_comment":"","costs_comment":"","address_hidden":false,"space_comment":"","space_units":"","space":"","address":""},{"costs_rent":"","region":"","costs":"","costs_rent_comment":"","costs_comment":"","address_hidden":false,"space_comment":"","space_units":"","space":"","address":""},{"costs_rent":"","region":"","costs":"","costs_rent_comment":"","costs_comment":"","space_comment":"","space_units":"","space":"","address":""},{"costs_rent":"","costs":"","costs_rent_comment":"","costs_comment":"","space_comment":"","space_units":"","space":"","address":""}],"25":[{"space_unclear":false,"costs":"","costs_rent_unclear":false,"costs_comment":"","address_hidden":false,"region_hidden":false,"space_comment":"1/5 частина","space_hidden":false,"space":"152.6","address":"Біла Церква","region":"Київська область","address_unclear":false,"costs_rent_comment":"","costs_unclear":false,"space_units":"м²","costs_rent":""}],"27":[{"space_hidden":false,"costs":"","costs_comment":"","costs_hidden":false,"address_hidden":false,"region_hidden":false,"space_comment":"","space":"24","address":"Біла Церква","region":"Київська область","costs_rent_comment":"","costs_rent_hidden":false,"space_units":"м²","costs_rent":""},{"costs_rent":"","region":"Київська область","costs":"","costs_rent_comment":"","costs_comment":"","region_hidden":false,"space_comment":"","space_units":"м²","space":"24","address":"Біла Церква"}],"31":[{"space_unclear":false,"costs_property_hidden":false,"address_hidden":false,"region_hidden":false,"space_comment":"3/5 частини","space_hidden":false,"space":"152.6","address":"","costs_property_comment_hidden":false,"region":"Київська область","costs_property":"","costs_rent_comment":"","costs_rent_hidden":false,"space_comment_unclear":false,"space_units":"м²","costs_property_comment":"","costs_rent":""}],"33":[{"space_hidden":false,"costs_property_hidden":false,"address_hidden":false,"region_hidden":false,"space_comment":"","space_units_hidden":false,"space":"24","address":"Біла Церква","region":"Київська область","address_unclear":false,"space_units_unclear":false,"costs_rent_hidden":false,"costs_property":"","space_units":"м²","costs_property_comment":"","costs_rent":"","costs_rent_comment":""},{"region_unclear":false,"space_units_unclear":false,"region_hidden":false,"space_comment":"","space_units_hidden":false,"space":"20","address":"Біла Церква","region":"Київська область","costs_property":"","costs_rent_comment":"","space_units":"м²","costs_property_comment":"","costs_rent":""}]},"intro":{"declaration_year":"2014","isnotdeclaration":"","declaration_year_unclear":false,"declaration_year_hidden":false}}