{"income":{"5":{"value":"194448","family_comment":"","value_unclear":false,"family":"","family_unclear":false,"comment_unclear":false,"comment":"","family_comment_unclear":false},"6":{"value":"194257","family_comment":"","value_unclear":false,"family_unclear":false,"family":"","comment":""},"7":{"source_name_unclear":false,"value":"","value_unclear":false,"family_comment":"","source_name":"","family":"","comment":"","source_name_hidden":false},"8":{"family_comment":"","value":"","family":"","comment":""},"9":{"family_comment":"","value":"182","family":"","comment":"ПриватБанк, копилка"},"10":{"family_comment":"","value":"","value_unclear":false,"family":"","comment":""},"11":{"value":"","value_unclear":false,"value_hidden":false,"family_comment":"","family":"","comment":""},"12":{"family_comment":"","value":"","family":"","comment":"","value_hidden":false},"13":{"family_comment":"","value":"","family":"","comment":""},"14":{"family_comment":"","value":"","family":"","comment":""},"15":{"family_comment":"","value":"","family":"","comment":""},"16":{"family_comment":"","value":"","family":"","comment":""},"17":{"family_comment":"","value":"","family":"","comment":""},"18":{"family_comment":"","value":"","family":"","comment":""},"19":{"family_comment":"","family_unclear":false,"value":"","family":"","comment":""},"20":{"family_comment":"","family_unclear":false,"value":"9","family":"","comment":""}},"vehicle":{"35":[{"year_hidden":false,"brand_info":"2.0 л","sum_rent_comment":"","year":"2007","sum_hidden":false,"brand_info_hidden":false,"brand_info_unclear":false,"year_unclear":false,"sum_rent":"","sum":"","brand":"Hyundai Coupe","sum_comment":"","brand_unclear":false,"brand_hidden":false}]},"id":"vulyk_61_107","banks":{"45":[{"sum_foreign_comment":"","sum_units":"UAH","sum_comment":"","sum_foreign_units":"UAH","sum_comment_hidden":false,"sum_unclear":false,"sum":"1250","sum_foreign":""}]},"declaration":{"additional_info_text":"","notfull_lostpages":"","date":"2015-03-31T00:00:00","notfull":"","additional_info":"","url":"http://static.declarations.com.ua/declarations/chosen_ones/mega_batch/hrinchuk_oleksandra_petrivna.pdf"},"liabilities":{"54":{"sum_foreign_comment":"","sum":"","sum_comment":"","sum_comment_unclear":false,"sum_unclear":false,"sum_foreign":""},"55":{"sum_foreign_comment":"","sum":"","sum_comment":"","sum_foreign":""},"56":{"sum_foreign_comment":"","sum":"","sum_comment":"","sum_unclear":false,"sum_foreign":""},"57":{"sum_foreign_comment":"","sum":"","sum_comment":"","sum_comment_hidden":false,"sum_unclear":false,"sum_foreign":""},"58":{"sum_foreign_comment":"","sum":"","sum_comment":"","sum_unclear":false,"sum_foreign":""},"59":{"sum_foreign_comment":"","sum":"","sum_comment":"","sum_foreign":""},"60":{"sum_foreign_comment":"","sum_foreign_hidden":false,"sum_comment":"","sum_hidden":false,"sum":"","sum_foreign":""},"61":{"sum_foreign_comment":"","sum":"","sum_comment":"","sum_foreign":""},"62":{"sum_foreign_comment":"","sum":"","sum_comment":"","sum_unclear":false,"sum_foreign":""},"63":{"sum_foreign_comment":"","sum":"","sum_comment":"","sum_hidden":false,"sum_unclear":false,"sum_foreign":""},"64":{"sum_foreign_comment":"","sum":"","sum_hidden":false,"sum_comment":"","sum_foreign":""}},"ft_src":"суддя ленінського районного суду м. харкова\nХарківська область\nЗагальний місцевий суд\nОлександра\nПетрівна\nГрінчук Олександра Петрівна\nОлександра Петрівна Грінчук\nОлександра Грінчук\nГрінчук Олександра Петрівна\nГрінчук Олександра Петрівна\nГрінчук\n2.0 л\nHyundai Coupe\n2007\n1250\n2014\n2.0 л\nHyundai Coupe\n2007\n1250\n.12\n48.7\nГрінчук Олександра Петрівна\nОлександра Петрівна Грінчук\nОлександра Грінчук\nГрінчук Олександра Петрівна\nГрінчук Олександра Петрівна\nОлександра\nПетрівна\nХарківська область\nЗагальний місцевий суд\nсуддя ленінського районного суду м. харкова\nГрінчук\n194257\n9\n194448\n182\nПриватБанк, копилка\n2014\n.12\n48.7\nПетрівна\nГрінчук\nОлександра\nГрінчук Олександра Петрівна\nОлександра Петрівна Грінчук\nОлександра Грінчук\nГрінчук Олександра Петрівна\nХарківська область\nсуддя ленінського районного суду м. харкова\nЗагальний місцевий суд\nГрінчук Олександра Петрівна\n194257\n194448\nПриватБанк, копилка\n182\n9\nHyundai Coupe\n2.0 л\n2007\n9\n194448\nПриватБанк, копилка\n182\n194257\n48.7\n.12\n1250\n2014","general":{"inn":"","name":"Олександра","patronymic_unclear":false,"inn_unclear":false,"patronymic":"Петрівна","inn_hidden":true,"family_raw":"","last_name":"Грінчук","post":{"post_unclear":false,"region_unclear":false,"post":"суддя ленінського районного суду м. харкова","office":"Загальний місцевий суд","region":"Харківська область","post_hidden":false,"office_hidden":false,"region_hidden":false},"full_name_suggest":{"output":"Грінчук Олександра Петрівна","input":["Грінчук Олександра Петрівна","Олександра Петрівна Грінчук","Олександра Грінчук"]},"full_name":"Грінчук Олександра Петрівна","addresses":[{"place_address":"","place_district_hidden":true,"place_city_type":"","place_city_hidden":true,"place_address_unclear":false,"place_city_type_hidden":false,"place_hidden":true,"place":"","place_district":"","place_address_hidden":true,"place_city":"","place_district_unclear":false}],"patronymic_hidden":false,"last_name_unclear":false,"name_unclear":false},"source":"VULYK","estate":{"23":[{"region_unclear":false,"space_unclear":false,"costs":"","costs_comment":"","address_hidden":true,"region_hidden":true,"space_comment":"","space":".12","address":"","region":"","address_unclear":false,"costs_rent_comment":"","space_comment_unclear":false,"space_units":"га","space_units_unclear":false,"costs_rent":""}],"25":[{"region_unclear":false,"space_hidden":false,"costs":"","costs_comment":"","address_hidden":true,"region_hidden":true,"space_comment":"","space_unclear":false,"space":"48.7","address":"","costs_comment_unclear":false,"costs_unclear":false,"region":"","address_unclear":false,"costs_rent_comment":"","space_comment_unclear":false,"space_units":"м²","costs_rent":""}]},"intro":{"declaration_year":"2014","isnotdeclaration":"","declaration_year_hidden":false}}