{"income":{"5":{"value":"218357.08","value_unclear":false,"value_hidden":false,"family_comment":"","family":"","comment":""},"6":{"value":"192547.72","family_comment":"","value_unclear":false,"family_unclear":false,"family":"","comment":""},"7":{"source_name_unclear":false,"value":"","family_hidden":false,"family_comment":"","source_name":"","family":"","comment":""},"8":{"family_comment":"","value":"","family":"","comment":""},"9":{"family_comment":"","value":"59.36","family":"","comment":"48,29+11,07 (%) Дельтабанк"},"10":{"family_comment":"","value":"","family":"","comment":""},"11":{"family_comment":"","value":"","family":"","comment":""},"12":{"family_comment":"","value":"","family":"","comment":""},"13":{"family_comment":"","value":"","family":"","comment":""},"14":{"family_comment":"","value":"","family":"","comment":""},"15":{"family_comment":"","value":"","family":"","comment":""},"16":{"family_comment":"","value":"","comment_unclear":false,"family":"","comment":""},"17":{"family_comment":"","family_unclear":false,"value":"","family":"","comment":""},"18":{"family_comment":"","value":"","family":"","comment":""},"19":{"value":"","family_hidden":false,"value_hidden":false,"family_comment":"","family":"","comment":""},"20":{"family_comment":"","value":"25750","comment_unclear":false,"family":"","comment":"кредит. карта"}},"id":"vulyk_67_181","banks":{"45":[{"sum_foreign_comment":"","sum":"467.66","sum_comment":"","sum_comment_unclear":false,"sum_hidden":false,"sum_foreign_units":"UAH","sum_foreign_hidden":false,"sum_units":"UAH","sum_comment_hidden":false,"sum_unclear":false,"sum_foreign":""}]},"declaration":{"additional_info_text":"","notfull_lostpages":"","date":"2015-03-27T00:00:00","notfull":"","additional_info":"","url":"http://static.declarations.com.ua/declarations/chosen_ones/mega_batch/skral_tetiana_vasylivna.pdf"},"liabilities":{"54":{"sum_foreign_comment":"","sum_foreign_hidden":false,"sum_comment":"","sum_comment_unclear":false,"sum_hidden":false,"sum":"","sum_unclear":false,"sum_foreign":""},"55":{"sum_foreign_comment":"","sum":"","sum_comment":"","sum_foreign":""},"56":{"sum_foreign_comment":"","sum_foreign_hidden":false,"sum_comment":"","sum_hidden":false,"sum":"","sum_unclear":false,"sum_foreign":""},"57":{"sum_foreign_comment":"","sum_foreign_hidden":false,"sum_comment":"","sum_comment_unclear":false,"sum_hidden":false,"sum_comment_hidden":false,"sum_unclear":false,"sum":"8015.91","sum_foreign":""},"58":{"sum_foreign_comment":"","sum_foreign_hidden":false,"sum_comment":"","sum_comment_unclear":false,"sum_hidden":false,"sum_comment_hidden":false,"sum_unclear":false,"sum":"9377.86","sum_foreign":""},"59":{"sum_foreign_comment":"","sum":"","sum_hidden":false,"sum_comment":"","sum_foreign":""},"60":{"sum_foreign_comment":"","sum":"","sum_comment":"","sum_foreign":""},"61":{"sum_foreign_comment":"","sum_foreign_hidden":false,"sum_comment":"","sum_hidden":false,"sum":"","sum_foreign":""},"62":{"sum_foreign_comment":"","sum":"","sum_hidden":false,"sum_comment":"","sum_foreign":""},"63":{"sum_foreign_comment":"","sum":"","sum_comment":"","sum_comment_unclear":false,"sum_hidden":false,"sum_unclear":false,"sum_foreign":""},"64":{"sum_foreign_comment":"","sum":"","sum_comment":"","sum_hidden":false,"sum_unclear":false,"sum_foreign":""}},"ft_src":"8015.91\n9377.86\nсуддя закарпатського окружного адміністративного суду\nЗакарпатська область\nАдміністративний місцевий суд\nТетяна\nСкраль В. В. 05. 11. 1997\nДитина\nСкраль І. В. 11. 12. 1996\nДитина\nВасилівна\nСкраль Тетяна Василівна\nСкраль\nСкраль Тетяна Василівна\nТетяна Василівна Скраль\nТетяна Скраль\nСкраль Тетяна Василівна\nкредит. карта\n25750\n218357.08\n48,29+11,07 (%) Дельтабанк\n59.36\n192547.72\n467.66\n1800\n237.9\n2014\n192547.72\n218357.08\n48,29+11,07 (%) Дельтабанк\n59.36\nкредит. карта\n25750\n467.66\n2014\nАдміністративний місцевий суд\nсуддя закарпатського окружного адміністративного суду\nЗакарпатська область\nДитина\nСкраль В. В. 05. 11. 1997\nДитина\nСкраль І. В. 11. 12. 1996\nСкраль Тетяна Василівна\nТетяна Василівна Скраль\nТетяна Скраль\nСкраль Тетяна Василівна\nСкраль Тетяна Василівна\nТетяна\nСкраль\nВасилівна\n8015.91\n9377.86\n192547.72\nкредит. карта\n25750\n218357.08\n48,29+11,07 (%) Дельтабанк\n59.36\n1800\n237.9\n9377.86\n8015.91\nДитина\nСкраль В. В. 05. 11. 1997\nДитина\nСкраль І. В. 11. 12. 1996\nВасилівна\nСкраль\nТетяна\nСкраль Тетяна Василівна\nТетяна Василівна Скраль\nТетяна Скраль\nСкраль Тетяна Василівна\nЗакарпатська область\nсуддя закарпатського окружного адміністративного суду\nАдміністративний місцевий суд\nСкраль Тетяна Василівна\n1800\n237.9\n467.66\n2014","general":{"inn":"","name":"Тетяна","patronymic_unclear":false,"last_name_hidden":false,"family":[{"inn":"","inn_hidden":false,"relations_unclear":false,"relations_hidden":false,"relations_other":"","relations":"Дитина","name_hidden":false,"inn_unclear":false,"family_name":"Скраль В. В. 05. 11. 1997","name_unclear":false},{"inn":"","inn_hidden":false,"relations_unclear":false,"relations_hidden":false,"relations_other":"","relations":"Дитина","name_hidden":false,"inn_unclear":false,"family_name":"Скраль І. В. 11. 12. 1996","name_unclear":false}],"patronymic":"Василівна","inn_hidden":true,"family_raw":"","inn_unclear":false,"post":{"post_unclear":false,"post":"суддя закарпатського окружного адміністративного суду","post_hidden":false,"region":"Закарпатська область","region_hidden":false,"office":"Адміністративний місцевий суд","office_hidden":false,"office_unclear":false},"last_name_unclear":false,"full_name":"Скраль Тетяна Василівна","addresses":[{"place_city_type_hidden":false,"place_district_hidden":false,"place_city_type":"","place_city_hidden":false,"place_address_unclear":false,"place_address":"","place":"","place_district":"","place_unclear":false,"place_city":"","place_city_unclear":false,"place_hidden":true,"place_address_hidden":false,"place_district_unclear":false}],"last_name":"Скраль","full_name_suggest":{"output":"Скраль Тетяна Василівна","input":["Скраль Тетяна Василівна","Тетяна Василівна Скраль","Тетяна Скраль"]},"name_unclear":false},"source":"VULYK","estate":{"23":[{"space_hidden":false,"costs":"","costs_comment":"","costs_hidden":false,"address_hidden":false,"region_hidden":true,"space_comment":"","space_unclear":false,"space":"1800","address":"","region":"","address_unclear":false,"space_units_unclear":false,"costs_rent_hidden":false,"space_comment_unclear":false,"space_units":"м²","costs_rent":"","costs_rent_comment":""}],"24":[{"space_hidden":false,"costs":"","costs_comment":"","costs_hidden":false,"address_hidden":false,"region_hidden":true,"space_comment":"","space":"237.9","address":"","region":"","costs_rent_comment":"","space_comment_unclear":false,"space_units":"м²","costs_rent":""}]},"intro":{"declaration_year":"2014","isnotdeclaration":"","declaration_year_hidden":false}}