{"income":{"5":{"value":"271871","family_comment":"","value_unclear":false,"family_hidden":false,"family_unclear":false,"family":"9150","comment":""},"6":{"value":"252175","value_unclear":false,"family_hidden":false,"family_comment":"","family":"","comment":""},"7":{"source_name_unclear":false,"value":"250","family_hidden":false,"family_comment":"","source_name":"Товариство з обмеженою відповідальністю 'Діловий клуб управління знаннями'","family":"","comment":"","source_name_hidden":false},"8":{"family_comment":"","value":"","family":"","comment":""},"9":{"family_comment":"","family_unclear":true,"value":"","family":"5550","comment":""},"10":{"family_comment":"","value":"","family":"","comment":""},"11":{"family_comment":"","value":"","comment_unclear":false,"family":"","comment":""},"12":{"family_comment":"","value":"","family":"","comment":""},"13":{"family_comment":"","value":"","family":"","comment":""},"14":{"family_comment":"","value":"","family":"","comment":""},"15":{"family_comment":"","value":"19446","family":"","comment":""},"16":{"family_comment":"","value":"","family":"","comment":""},"17":{"family_comment":"","value":"","family":"","comment":"","family_comment_unclear":false},"18":{"family_comment":"","value":"","family":"","comment":""},"19":{"family_comment":"","value":"","comment_unclear":false,"family":"","comment":""},"20":{"value":"","family_comment":"стипендія","comment_unclear":false,"comment_hidden":false,"family_unclear":false,"family":"3600","comment":""}},"vehicle":{"35":[{"brand_info":"1600 куб. см.","sum_rent_comment":"","year":"2009","brand_info_hidden":false,"year_unclear":false,"sum_rent":"","sum":"","brand":"Toyota Rav 4","sum_comment":"","sum_comment_unclear":false,"sum_unclear":false,"brand_unclear":false}]},"id":"vulyk_8_61","banks":{"45":[{"sum_foreign_comment":"","sum_units":"UAH","sum_comment":"","sum_foreign_unclear":false,"sum_foreign_units":"UAH","sum_hidden":true,"sum_comment_hidden":false,"sum_unclear":false,"sum":"1407","sum_foreign":""},{"sum_foreign_comment":"","sum_units":"","sum_comment":"","sum_hidden":false,"sum_foreign_units":"","sum":"","sum_unclear":false,"sum_foreign":""},{"sum_foreign_comment":"","sum_units":"","sum_comment":"","sum_foreign_units":"","sum":"","sum_unclear":false,"sum_foreign":""},{"sum_foreign_comment":"","sum_units":"","sum_comment":"","sum_foreign_units":"","sum":"","sum_foreign":""}],"46":[{"sum_foreign_comment":"","sum_units":"UAH","sum_comment":"","sum_foreign_comment_hidden":false,"sum_hidden":false,"sum_foreign_units":"UAH","sum_foreign_hidden":false,"sum_comment_hidden":false,"sum_unclear":false,"sum":"","sum_foreign":""}],"47":[{"sum_foreign_comment":"","sum_units":"UAH","sum_comment":"","sum_foreign_units":"UAH","sum_comment_hidden":false,"sum":"","sum_foreign":""}],"48":[{"sum_foreign_comment":"","sum_units":"UAH","sum_comment":"","sum_foreign_units":"UAH","sum":"","sum_foreign":""}],"49":[{"sum_foreign_comment":"","sum_units":"UAH","sum_comment":"","sum_foreign_units":"UAH","sum":"","sum_foreign":""}],"50":[{"sum_foreign_comment":"","sum_units":"UAH","sum_comment":"","sum_foreign_units":"UAH","sum":"","sum_foreign":""}],"51":[{"sum_foreign_comment":"","sum_units":"UAH","sum_comment":"","sum_comment_unclear":false,"sum_hidden":true,"sum_foreign_units":"UAH","sum_comment_hidden":false,"sum_unclear":false,"sum":"380000","sum_foreign":""},{"sum_foreign_comment":"","sum_units":"","sum_comment":"","sum_hidden":false,"sum_foreign_units":"","sum":"","sum_foreign":""}],"52":[{"sum_foreign_comment":"","sum_units":"UAH","sum_comment":"","sum_comment_unclear":false,"sum_hidden":false,"sum_foreign_units":"UAH","sum_comment_hidden":false,"sum_unclear":false,"sum":"","sum_foreign":""}],"53":[{"sum_foreign_comment":"","sum_units":"UAH","sum_comment":"","sum_foreign_units":"UAH","sum_comment_hidden":false,"sum":"","sum_foreign":""}]},"declaration":{"additional_info_text":"","notfull_lostpages":"","date":"2015-03-31T00:00:00","notfull":"","additional_info":"","url":"http://static.declarations.com.ua/declarations/chosen_ones/batch_16/rohach_larysa_ivanivna.pdf"},"liabilities":{"54":{"sum_foreign_comment":"","sum_foreign_hidden":false,"sum_comment":"","sum_hidden":true,"sum_comment_hidden":false,"sum":"15636","sum_foreign":""},"55":{"sum_foreign_comment":"","sum":"","sum_comment":"","sum_foreign":""},"56":{"sum_foreign_comment":"","sum":"7750","sum_comment":"","sum_unclear":true,"sum_foreign":""},"57":{"sum_foreign_comment":"","sum_comment_hidden":false,"sum":"","sum_comment":"","sum_foreign":""},"58":{"sum_foreign_comment":"","sum":"27552","sum_comment":"","sum_foreign":""},"59":{"sum_foreign_comment":"","sum":"","sum_comment":"","sum_comment_unclear":false,"sum_foreign":""},"60":{"sum_foreign_comment":"","sum_foreign_hidden":false,"sum_comment":"","sum_hidden":false,"sum_comment_hidden":false,"sum":"","sum_foreign":""},"61":{"sum_foreign_comment":"","sum":"","sum_comment":"","sum_foreign":""},"62":{"sum_foreign_comment":"","sum":"","sum_comment":"","sum_foreign":""},"63":{"sum_foreign_comment":"","sum":"","sum_comment":"","sum_foreign":""},"64":{"sum_foreign_comment":"","sum":"","sum_comment":"","sum_foreign":""}},"ft_src":"15636\n27552\n7750\nсуддя вищого господарського суду україни\nЗагальнодержавний регіон\nВищий господарський суд\nЛариса\nМоренець В. І\nПодружжя\nМоренець Ю. В\nДитина\nІванівна\nРогач Лариса Іванівна\nЛариса Іванівна Рогач\nЛариса Рогач\nРогач Лариса Іванівна\nРогач Лариса Іванівна\nРогач\n1600 куб. см.\nToyota Rav 4\n2009\n380000\n1407\n2014\n1600 куб. см.\nToyota Rav 4\n2009\n1407\n380000\n72\n36.33\n1/3 від 109 - спільна власність\n1077\n600\n2/3 від 109\n72.67\n33.5\n1/2 від 67\nПодружжя\nМоренець В. І\nДитина\nМоренець Ю. В\nРогач Лариса Іванівна\nЛариса Іванівна Рогач\nЛариса Рогач\nРогач Лариса Іванівна\nРогач Лариса Іванівна\nЛариса\nРогач\nВищий господарський суд\nсуддя вищого господарського суду україни\nЗагальнодержавний регіон\nІванівна\n7750\n27552\n15636\n250\nТовариство з обмеженою відповідальністю 'Діловий клуб управління знаннями'\n252175\n3600\nстипендія\n19446\n9150\n271871\n5550\n2014\n27552\n7750\n15636\n600\n1077\n2/3 від 109\n72.67\n1/2 від 67\n33.5\n72\n1/3 від 109 - спільна власність\n36.33\nМоренець В. І\nПодружжя\nМоренець Ю. В\nДитина\nІванівна\nРогач\nЛариса\nРогач Лариса Іванівна\nЛариса Іванівна Рогач\nЛариса Рогач\nРогач Лариса Іванівна\nЗагальнодержавний регіон\nсуддя вищого господарського суду україни\nВищий господарський суд\nРогач Лариса Іванівна\n252175\n19446\nТовариство з обмеженою відповідальністю 'Діловий клуб управління знаннями'\n250\n9150\n271871\n5550\n3600\nстипендія\n2009\nToyota Rav 4\n1600 куб. см.\n19446\nстипендія\n3600\n271871\n9150\n250\nТовариство з обмеженою відповідальністю 'Діловий клуб управління знаннями'\n5550\n252175\n2/3 від 109\n72.67\n1077\n72\n1/2 від 67\n33.5\n1/3 від 109 - спільна власність\n36.33\n600\n1407\n380000\n2014","general":{"inn":"","name":"Лариса","patronymic_unclear":false,"last_name_hidden":false,"family":[{"inn":"","inn_hidden":false,"relations_hidden":false,"family_name":"Моренець В. І","relations_other":"","relations":"Подружжя","name_hidden":false,"name_unclear":false},{"inn":"","relations":"Дитина","inn_unclear":true,"family_name":"Моренець Ю. В","inn_hidden":true,"relations_other":"","name_hidden":false,"name_unclear":false}],"patronymic":"Іванівна","inn_hidden":true,"family_raw":"","inn_unclear":false,"post":{"post_unclear":false,"post":"суддя вищого господарського суду україни","post_hidden":false,"region":"Загальнодержавний регіон","region_hidden":false,"office":"Вищий господарський суд","office_hidden":false,"office_unclear":false},"full_name":"Рогач Лариса Іванівна","addresses":[{"place_district":"","place_city_hidden":true,"place_city":"","place_city_type_hidden":true,"place_district_hidden":true,"place_city_type":"","place_address_hidden":false,"place_address":"","place_hidden":true,"place":""}],"last_name":"Рогач","full_name_suggest":{"output":"Рогач Лариса Іванівна","input":["Рогач Лариса Іванівна","Лариса Іванівна Рогач","Лариса Рогач"]}},"source":"VULYK","estate":{"23":[{"space_unclear":false,"costs":"","costs_comment":"","address_hidden":false,"region_hidden":true,"space_comment":"","space":"1077","address":"","costs_comment_unclear":false,"region":"","address_unclear":false,"costs_rent_comment":"","space_comment_unclear":false,"space_comment_hidden":false,"space_units":"м²","space_units_hidden":false,"costs_rent":""},{"space_unclear":false,"costs":"","costs_comment":"","address_hidden":false,"region_hidden":false,"space_comment":"","space":"","address":"","region":"","costs_rent_comment":"","space_comment_unclear":false,"space_units":"","costs_rent":""},{"space":"","region":"","costs":"","costs_rent_comment":"","costs_comment":"","space_comment":"","space_units_unclear":false,"space_units":"","costs_rent":"","address":""},{"costs_rent":"","region":"","costs":"","costs_rent_comment":"","costs_comment":"","address_hidden":false,"space_comment":"","space_units":"","space":"","address":""}],"25":[{"region_unclear":false,"space_unclear":false,"costs":"","costs_comment":"","address_hidden":false,"region_hidden":true,"space_comment":"1/3 від 109 - спільна власність","space":"36.33","address":"","costs_comment_unclear":false,"region":"","costs_rent_comment":"","space_comment_unclear":false,"space_units":"м²","costs_rent":""}],"26":[{"costs":"","costs_comment":"","address_hidden":false,"region_hidden":true,"space_comment":"","space":"72","address":"","region":"","costs_rent_comment":"","costs_unclear":false,"space_units":"м²","costs_rent":""}],"29":[{"space_unclear":false,"address_hidden":false,"region_hidden":true,"space_comment":"","space_hidden":false,"space":"600","address":"","region":"","costs_property":"","costs_rent_comment":"","space_units":"м²","costs_property_comment":"","costs_rent":""}],"30":[{"space_unclear":false,"address_hidden":false,"region_hidden":true,"space_comment":"1/2 від 67","space_hidden":false,"space":"33.5","address":"","region":"","costs_property":"","costs_rent_comment":"","space_comment_unclear":false,"space_units":"м²","costs_property_comment":"","costs_rent":""}],"31":[{"space_unclear":false,"address_hidden":false,"region_hidden":true,"space_comment":"2/3 від 109","space_hidden":false,"space":"72.67","address":"","region":"","costs_property":"","costs_rent_comment":"","address_unclear":false,"space_units":"м²","costs_property_comment":"","costs_rent":""}]},"intro":{"declaration_year":"2014","isnotdeclaration":""}}