{"income":{"5":{"value":"181229.73","family_comment":"","family_hidden":false,"value_hidden":false,"family_unclear":false,"family":"","comment":""},"6":{"value":"169049.73","family_unclear":false,"family_hidden":false,"family_comment":"","family":"","comment":""},"7":{"value":"","family_comment":"","source_name":"","family":"","comment":"","source_name_hidden":false},"8":{"family_comment":"","value":"","family":"","comment":""},"9":{"family_comment":"","family_unclear":false,"value":"","family":"","comment":""},"10":{"family_comment":"","value":"12180","family":"","comment":""},"11":{"family_comment":"","value":"","family":"","comment":""},"12":{"family_comment":"","value":"","family":"","comment":""},"13":{"family_comment":"","value":"","family":"","comment":""},"14":{"family_comment":"","value":"","family":"","comment":""},"15":{"family_comment":"","family_unclear":false,"value":"","family":"","comment":""},"16":{"family_comment":"","family_unclear":false,"value":"","family":"","comment":""},"17":{"family_comment":"","value":"","value_unclear":false,"family":"","comment":""},"18":{"family_comment":"","value":"","family":"","comment":""},"19":{"family_comment":"","value":"","family":"","comment":""},"20":{"family_comment":"","value":"","comment_unclear":false,"family":"","comment":""}},"vehicle":{"35":[{"year_hidden":false,"brand_info":"1400 куб. см., 77 кВт , 423.7 см","sum_rent_comment":"тимчасове користування","sum_rent_hidden":false,"year":"2008","sum_hidden":false,"brand_info_hidden":false,"brand_info_unclear":false,"sum_rent":"","sum_rent_unclear":false,"sum":"","brand":"ЗАЗ TF 699","sum_comment":"","brand_unclear":true,"brand_hidden":false}],"40":[{"brand_info":"1400 куб. см., 77 кВт , 423.7 см","sum":"","brand":"ЗАЗ TF 699","sum_comment":"","brand_unclear":true,"year":"2008","brand_hidden":false,"brand_info_hidden":false,"brand_info_unclear":false,"sum_rent_comment":"","sum_rent":""}]},"id":"vulyk_18_16","banks":{"45":[{"sum_units":"UAH","sum_hidden":false,"sum_units_hidden":false,"sum_foreign":"","sum_foreign_comment":"","sum":"","sum_comment":"","sum_comment_unclear":false,"sum_foreign_units":"UAH","sum_units_unclear":false,"sum_comment_hidden":false,"sum_unclear":false}],"46":[{"sum_foreign_comment":"","sum_units":"UAH","sum_comment":"","sum_foreign_units":"UAH","sum":"","sum_foreign":""}],"47":[{"sum_foreign_comment":"","sum_units":"UAH","sum_comment":"","sum_foreign_units":"UAH","sum":"","sum_foreign":""}],"48":[{"sum_foreign_comment":"","sum_units":"UAH","sum_comment":"","sum_foreign_units":"UAH","sum":"","sum_foreign":""}],"49":[{"sum_foreign_comment":"","sum_units":"UAH","sum_comment":"","sum_foreign_units":"UAH","sum":"","sum_foreign":""}],"50":[{"sum_foreign_comment":"","sum_units":"UAH","sum_comment":"","sum_foreign_units":"UAH","sum":"","sum_foreign":""}],"51":[{"sum_foreign_comment":"","sum_units":"UAH","sum_comment":"","sum_hidden":false,"sum_foreign_units":"UAH","sum_units_unclear":false,"sum_comment_hidden":false,"sum_units_hidden":false,"sum":"","sum_foreign":""}],"52":[{"sum_foreign_comment":"","sum_units":"UAH","sum_comment":"","sum_foreign_units":"UAH","sum":"","sum_foreign":""}],"53":[{"sum_foreign_comment":"","sum_units":"UAH","sum_comment":"","sum_foreign_unclear":false,"sum_foreign_units":"UAH","sum":"","sum_foreign_hidden":false,"sum_foreign":""}]},"declaration":{"additional_info_text":"","notfull_lostpages":"","date":"2015-03-17T00:00:00","notfull":"","additional_info":"","url":"http://static.declarations.com.ua/declarations/chosen_ones/mega_batch/semenyshyn_oryslava_zenoviivna.pdf"},"liabilities":{"54":{"sum_foreign_comment":"","sum":"","sum_comment":"","sum_comment_unclear":false,"sum_hidden":false,"sum_comment_hidden":false,"sum_unclear":false,"sum_foreign":""},"55":{"sum_foreign_comment":"","sum":"","sum_comment":"","sum_comment_unclear":false,"sum_hidden":false,"sum_unclear":false,"sum_foreign":""},"56":{"sum_foreign_comment":"","sum":"16000","sum_comment":"","sum_hidden":false,"sum_unclear":false,"sum_foreign":""},"57":{"sum_foreign_comment":"","sum":"15862.99","sum_comment":"","sum_unclear":false,"sum_foreign":""},"58":{"sum_foreign_comment":"","sum":"1211.36","sum_comment":"","sum_unclear":false,"sum_foreign":""},"59":{"sum_foreign_comment":"","sum":"","sum_comment":"","sum_foreign":""},"60":{"sum_foreign_comment":"","sum":"","sum_comment":"","sum_hidden":false,"sum_comment_hidden":false,"sum_unclear":false,"sum_foreign":""},"61":{"sum_foreign_comment":"","sum":"","sum_hidden":false,"sum_comment":"","sum_foreign":""},"62":{"sum_foreign_comment":"","sum":"","sum_hidden":false,"sum_comment":"","sum_foreign":""},"63":{"sum_foreign_comment":"","sum":"2200","sum_hidden":false,"sum_comment":"","sum_foreign":""},"64":{"sum_foreign_comment":"","sum":"30.39","sum_hidden":false,"sum_comment":"","sum_foreign":""}},"ft_src":"15862.99\n30.39\n1211.36\n2200\n16000\nсуддя радехівського районного суду львівської області\nЛьвівська область\nЗагальний місцевий суд\nОрислава\nСеменишин Володимир Павлович, 13. 08. 1976\nПодружжя\nСеменишин Юрій Володимирович, 02. 05. 2001\nДитина\nЗеновіївна\nСеменишин\nСеменишин Орислава Зеновіївна\nСеменишин Орислава Зеновіївна\nОрислава Зеновіївна Семенишин\nОрислава Семенишин\nСеменишин Орислава Зеновіївна\n1400 куб. см., 77 кВт , 423.7 см\nтимчасове користування\nЗАЗ TF 699\n2008\nЗАЗ TF 699\n1400 куб. см., 77 кВт , 423.7 см\n2008\n2014\n1400 куб. см., 77 кВт , 423.7 см\nтимчасове користування\nЗАЗ TF 699\n2008\n1400 куб. см., 77 кВт , 423.7 см\n2008\nЗАЗ TF 699\n55\n1/2 від 110 в користуванні\nСеменишин Орислава Зеновіївна\nОрислава Зеновіївна Семенишин\nОрислава Семенишин\nСеменишин Орислава Зеновіївна\nСеменишин Орислава Зеновіївна\nПодружжя\nСеменишин Володимир Павлович, 13. 08. 1976\nДитина\nСеменишин Юрій Володимирович, 02. 05. 2001\nОрислава\nСеменишин\nЗагальний місцевий суд\nсуддя радехівського районного суду львівської області\nЛьвівська область\nЗеновіївна\n2200\n30.39\n15862.99\n16000\n1211.36\n169049.73\n181229.73\n12180\n2014\n1211.36\n15862.99\n30.39\n16000\n2200\n1/2 від 110 в користуванні\n55\nПодружжя\nСеменишин Володимир Павлович, 13. 08. 1976\nСеменишин Юрій Володимирович, 02. 05. 2001\nДитина\nЗеновіївна\nСеменишин\nОрислава\nСеменишин Орислава Зеновіївна\nОрислава Зеновіївна Семенишин\nОрислава Семенишин\nСеменишин Орислава Зеновіївна\nЛьвівська область\nЗагальний місцевий суд\nсуддя радехівського районного суду львівської області\nСеменишин Орислава Зеновіївна\n169049.73\n12180\n181229.73\nЗАЗ TF 699\nтимчасове користування\n1400 куб. см., 77 кВт , 423.7 см\n2008\nЗАЗ TF 699\n1400 куб. см., 77 кВт , 423.7 см\n2008\n12180\n181229.73\n169049.73\n1/2 від 110 в користуванні\n55\n2014","general":{"inn":"","name":"Орислава","last_name_hidden":false,"family":[{"inn":"","inn_hidden":false,"relations_unclear":false,"relations_hidden":false,"relations_other":"","relations":"Подружжя","name_hidden":false,"inn_unclear":false,"family_name":"Семенишин Володимир Павлович, 13. 08. 1976","name_unclear":false},{"inn":"","inn_hidden":false,"relations_hidden":false,"family_name":"Семенишин Юрій Володимирович, 02. 05. 2001","relations_other":"","relations":"Дитина","name_hidden":false,"name_unclear":false}],"patronymic":"Зеновіївна","inn_hidden":false,"family_raw":"","inn_unclear":false,"post":{"post_unclear":false,"post":"суддя радехівського районного суду львівської області","candidate":"","office_hidden":false,"region":"Львівська область","post_hidden":false,"office":"Загальний місцевий суд","office_unclear":false,"region_hidden":false},"last_name_unclear":false,"full_name":"Семенишин Орислава Зеновіївна","last_name":"Семенишин","full_name_suggest":{"output":"Семенишин Орислава Зеновіївна","input":["Семенишин Орислава Зеновіївна","Орислава Зеновіївна Семенишин","Орислава Семенишин"]}},"source":"VULYK","estate":{"23":[{"space_hidden":false,"costs":"","costs_comment":"","costs_hidden":false,"space_unclear":false,"space_units_unclear":false,"space_units_hidden":false,"costs_comment_unclear":false,"region":"","space_comment_unclear":false,"space_comment_hidden":false,"costs_rent":"","region_unclear":false,"address_hidden":false,"region_hidden":false,"space_comment":"","space":"","address":"","address_unclear":false,"costs_rent_comment":"","costs_rent_hidden":false,"space_units":"м²"},{"costs_rent":"","region":"","costs":"","costs_rent_comment":"","costs_comment":"","region_hidden":false,"space_comment":"","space_units":"","space":"","address":""},{"costs_rent":"","region":"","costs":"","costs_rent_comment":"","costs_comment":"","region_hidden":false,"space_comment":"","space_units":"","space":"","address":""},{"costs_rent":"","costs":"","costs_rent_comment":"","costs_comment":"","region_hidden":false,"space_comment":"","space_units":"","space":"","address":""}],"24":[{"space_hidden":false,"costs":"","costs_comment":"","costs_hidden":false,"address_hidden":false,"region_hidden":true,"space_comment":"1/2 від 110 в користуванні","space":"55","address":"","region":"","costs_rent_comment":"","costs_rent_hidden":false,"space_comment_hidden":false,"space_units":"м²","space_units_hidden":false,"costs_rent":""}]},"intro":{"declaration_year":"2014","isnotdeclaration":"","declaration_year_unclear":false,"declaration_year_hidden":false}}