{"income":{"5":{"value":"313557","family_comment":"","value_unclear":false,"family_unclear":false,"family":"","comment":""},"6":{"value":"229408","family_comment":"","value_unclear":false,"family_unclear":false,"family":"","comment":""},"7":{"family_comment":"","value":"","source_name":"","family":"","comment":""},"8":{"family_comment":"","value":"","family":"","comment":""},"9":{"family_comment":"","value":"","family":"","comment":""},"10":{"family_comment":"","value":"","family":"","comment":""},"11":{"family_comment":"","value":"","family":"","comment":""},"12":{"family_comment":"","value":"","family":"","comment":""},"13":{"family_comment":"","value":"","family":"","comment":""},"14":{"family_comment":"","value":"84149","family":"","comment":""},"15":{"family_comment":"","value":"","value_unclear":false,"family":"","comment":""},"16":{"family_comment":"","value":"","family":"","comment":""},"17":{"family_comment":"","value":"","family":"","comment":""},"18":{"family_comment":"","value":"","family":"","comment":""},"19":{"family_comment":"","value":"","family":"","comment":""},"20":{"value":"","family_comment":"","value_unclear":false,"family_unclear":false,"family":"","comment":"","family_comment_unclear":false}},"id":"vulyk_99_7","declaration":{"date":"2016-03-30T00:00:00","notfull":"","url":"http://static.declarations.com.ua/declarations/chosen_ones/judges_batch/556_ozerov_vitalii_oleksandrovych_2015.pdf","notfull_lostpages":""},"liabilities":{"54":{"sum_foreign_comment":"","sum":"","sum_comment":"","sum_comment_unclear":false,"sum_comment_hidden":false,"sum_foreign":""},"55":{"sum_foreign_comment":"","sum":"","sum_comment":"","sum_foreign":""},"56":{"sum_foreign_comment":"","sum":"","sum_comment":"","sum_foreign":""},"57":{"sum_foreign_comment":"","sum_comment_hidden":false,"sum":"","sum_comment":"","sum_foreign":""},"58":{"sum_foreign_comment":"","sum_comment_hidden":false,"sum":"","sum_comment":"","sum_foreign":""},"59":{"sum_foreign_comment":"","sum":"","sum_comment":"","sum_comment_hidden":false,"sum_unclear":false,"sum_foreign":""},"60":{"sum_foreign_comment":"","sum_comment_hidden":false,"sum":"","sum_comment":"","sum_foreign":""},"61":{"sum_foreign_comment":"","sum":"","sum_comment":"","sum_foreign":""},"62":{"sum_foreign_comment":"","sum":"","sum_comment":"","sum_foreign":""},"63":{"sum_foreign_comment":"","sum_comment_hidden":false,"sum":"","sum_comment":"","sum_foreign":""},"64":{"sum_foreign_comment":"","sum_comment_hidden":false,"sum":"","sum_comment":"","sum_foreign":""}},"ft_src":"Озеров Віталій Олександрович\nсуддя старобільського районного суду луганської області\nЛуганська область\nЗагальний місцевий суд\nВіталій\nОзеров Д. В\nДитина\nОзеров Віталій Олександрович\nВіталій Олександрович Озеров\nВіталій Озеров\nОзеров Віталій Олександрович\nОзеров\nОлександрович\n84149\n313557\n229408\n1000\n1/2\n66.1\n1/2\n66.1\n2015\n229408\n84149\n313557\n229408\n84149\n313557\nОзеров\nОзеров Віталій Олександрович\nВіталій Олександрович Озеров\nВіталій Озеров\nОзеров Віталій Олександрович\nВіталій\nОлександрович\nОзеров Віталій Олександрович\nЗагальний місцевий суд\nсуддя старобільського районного суду луганської області\nЛуганська область\nДитина\nОзеров Д. В\n1000\n66.1\n1/2\n66.1\n1/2\n2015\nОзеров Д. В\nДитина\nОлександрович\nОзеров\nсуддя старобільського районного суду луганської області\nЛуганська область\nЗагальний місцевий суд\nОзеров Віталій Олександрович\nОзеров Віталій Олександрович\nВіталій Олександрович Озеров\nВіталій Озеров\nОзеров Віталій Олександрович\nВіталій\n1/2\n66.1\n1000\n1/2\n66.1\n2015","general":{"inn":"","inn_hidden":true,"last_name":"Озеров","post":{"post_unclear":false,"office":"Загальний місцевий суд","post":"суддя старобільського районного суду луганської області","region":"Луганська область"},"name":"Віталій","full_name":"Озеров Віталій Олександрович","family_raw":"","addresses":[{"place_district":"","place_city_hidden":true,"place_city":"","place_city_type_hidden":false,"place_district_hidden":false,"place_city_type":"","place_address_hidden":true,"place_address":"","place_hidden":true,"place":""}],"family":[{"inn_hidden":true,"inn":"","name_hidden":true,"family_name":"Озеров Д. В","relations":"Дитина","name_unclear":false}],"full_name_suggest":{"output":"Озеров Віталій Олександрович","input":["Озеров Віталій Олександрович","Віталій Олександрович Озеров","Віталій Озеров"]},"patronymic":"Олександрович"},"source":"VULYK","estate":{"23":[{"space_unclear":false,"costs":"","costs_comment":"","address_hidden":false,"region_hidden":true,"space_comment":"","space":"1000","address":"","region":"","costs_rent_comment":"","space_units":"м²","costs_rent":""}],"25":[{"space_hidden":false,"costs":"","costs_comment":"","address_hidden":false,"region_hidden":true,"space_comment":"1/2","space_unclear":false,"space":"66.1","address":"","region":"","costs_rent_comment":"","space_units":"м²","costs_rent":""}],"31":[{"costs_rent":"","region":"","costs_property":"","costs_rent_comment":"","address_hidden":true,"region_hidden":true,"space_comment":"1/2","costs_property_comment":"","space_units":"м²","space":"66.1","address":""}]},"intro":{"declaration_year":"2015"}}