{"income":{"5":{"value":"216261","family_comment":"","value_unclear":false,"family_hidden":false,"value_hidden":false,"family_unclear":false,"family":"","comment":"","family_comment_unclear":false},"6":{"family_comment":"","family_unclear":false,"value":"216261","family":"","comment":""},"7":{"source_name_unclear":false,"value":"","family_comment":"","source_name":"","family":"","comment":"","source_name_hidden":false},"8":{"family_comment":"","value":"","family":"","comment":""},"9":{"family_comment":"","family_unclear":false,"value":"","family":"","comment":""},"10":{"family_comment":"","value":"","family":"","comment":""},"11":{"family_comment":"","value":"","family":"","comment":""},"12":{"family_comment":"","value":"","family":"","comment":""},"13":{"family_comment":"","value":"","family":"","comment":""},"14":{"family_comment":"","value":"","family":"","comment":""},"15":{"family_comment":"","value":"","family":"","comment":""},"16":{"value":"","value_unclear":false,"value_hidden":false,"family_comment":"","family":"","comment":""},"17":{"family_comment":"","value":"","family":"","comment":""},"18":{"family_comment":"","value":"","family":"","comment":""},"19":{"family_comment":"","value":"","family":"","comment":""},"20":{"value":"","family_comment":"","value_unclear":false,"comment_hidden":false,"family_hidden":false,"family":"","value_hidden":false,"family_unclear":false,"comment_unclear":false,"comment":"","family_comment_unclear":false}},"id":"vulyk_62_53","declaration":{"additional_info_text":"","notfull_lostpages":"","date":"2015-03-25T00:00:00","notfull":"","additional_info":"","url":"http://static.declarations.com.ua/declarations/chosen_ones/mega_batch/dudar_oksana_mykhailivna.pdf"},"liabilities":{"54":{"sum_foreign_comment":"","sum":"5912","sum_comment":"","sum_hidden":true,"sum_comment_hidden":false,"sum_foreign":""},"55":{"sum_foreign_comment":"","sum":"","sum_comment":"","sum_hidden":false,"sum_comment_hidden":false,"sum_unclear":false,"sum_foreign":""},"56":{"sum_foreign_comment":"","sum":"","sum_comment":"","sum_hidden":false,"sum_unclear":false,"sum_foreign":""},"57":{"sum_foreign_comment":"","sum":"","sum_comment":"","sum_hidden":false,"sum_comment_hidden":false,"sum_unclear":false,"sum_foreign":""},"58":{"sum_foreign_comment":"","sum_foreign_hidden":false,"sum_comment":"","sum_hidden":false,"sum_comment_hidden":false,"sum_unclear":false,"sum":"","sum_foreign":""},"59":{"sum_foreign_comment":"","sum":"","sum_comment":"","sum_foreign":""},"60":{"sum_foreign_comment":"","sum_foreign_hidden":false,"sum_comment":"","sum_hidden":false,"sum_comment_hidden":false,"sum_unclear":false,"sum":"","sum_foreign":""},"61":{"sum_foreign_comment":"","sum_foreign_hidden":false,"sum_comment":"","sum_hidden":false,"sum":"","sum_foreign":""},"62":{"sum_foreign_comment":"","sum":"","sum_comment":"","sum_unclear":false,"sum_foreign":""},"63":{"sum_foreign_comment":"","sum":"","sum_comment":"","sum_hidden":false,"sum_comment_hidden":false,"sum_unclear":false,"sum_foreign":""},"64":{"sum_foreign_comment":"","sum":"","sum_comment":"","sum_comment_unclear":false,"sum_hidden":false,"sum_comment_hidden":false,"sum_foreign":""}},"ft_src":"5912\nсуддя рівненського окружного адміністративного суду\nРівненська область\nАдміністративний місцевий суд\nОксана\nМихайлівна\nДудар\nДудар Оксана Михайлівна\nДудар Оксана Михайлівна\nОксана Михайлівна Дудар\nОксана Дудар\nДудар Оксана Михайлівна\n216261\n216261\nу користуванні\n11.9\n2014\n216261\n216261\n11.9\nу користуванні\nДудар Оксана Михайлівна\nОксана Михайлівна Дудар\nОксана Дудар\nДудар Оксана Михайлівна\nОксана\nДудар Оксана Михайлівна\nМихайлівна\nАдміністративний місцевий суд\nсуддя рівненського окружного адміністративного суду\nРівненська область\nДудар\n5912\n216261\n216261\n2014\n5912\nОксана\nМихайлівна\nДудар\nДудар Оксана Михайлівна\nОксана Михайлівна Дудар\nОксана Дудар\nДудар Оксана Михайлівна\nРівненська область\nсуддя рівненського окружного адміністративного суду\nАдміністративний місцевий суд\nДудар Оксана Михайлівна\nу користуванні\n11.9\n2014","general":{"inn":"","name":"Оксана","inn_unclear":false,"patronymic":"Михайлівна","inn_hidden":true,"family_raw":"","last_name":"Дудар","post":{"post_unclear":false,"post":"суддя рівненського окружного адміністративного суду","post_hidden":false,"region":"Рівненська область","region_hidden":false,"office":"Адміністративний місцевий суд","office_hidden":false,"office_unclear":false},"last_name_unclear":false,"full_name":"Дудар Оксана Михайлівна","addresses":[{"place_city_type_unclear":false,"place_address":"","place_district_hidden":true,"place_city_type":"","place_address_hidden":false,"place_address_unclear":false,"place_city_type_hidden":false,"place":"","place_district":"","place_unclear":false,"place_city":"","place_city_unclear":false,"place_hidden":true,"place_city_hidden":true,"place_district_unclear":false}],"full_name_suggest":{"output":"Дудар Оксана Михайлівна","input":["Дудар Оксана Михайлівна","Оксана Михайлівна Дудар","Оксана Дудар"]},"name_unclear":false},"source":"VULYK","estate":{"25":[{"region_unclear":false,"space_hidden":false,"costs":"","costs_comment":"","costs_hidden":false,"address_hidden":false,"region_hidden":true,"space_comment":"у користуванні","space_unclear":false,"space":"11.9","address":"","region":"","costs_rent_comment":"","space_units":"м²","costs_rent":""}]},"intro":{"declaration_year":"2014","isnotdeclaration":"","declaration_year_unclear":false,"declaration_year_hidden":false}}