{"income":{"5":{"value":"309812","value_unclear":false,"family_hidden":false,"family_comment":"","family":"15260","comment":""},"6":{"family_comment":"","value":"308279","value_unclear":false,"family":"15260","comment":""},"7":{"source_name_unclear":false,"value":"","family_comment":"","source_name":"","family":"","comment":"","source_name_hidden":false},"8":{"family_comment":"","value":"","family":"","comment":""},"9":{"family_comment":"","value":"466","comment_unclear":false,"family":"","comment":"проценти"},"10":{"family_comment":"","value":"","family":"","comment":""},"11":{"family_comment":"","family_unclear":false,"value":"","family":"","comment":""},"12":{"family_comment":"","value":"","family":"","comment":""},"13":{"family_comment":"","value":"","family":"","comment":""},"14":{"family_comment":"","value":"","family":"","comment":""},"15":{"family_comment":"","value":"","family":"","comment":""},"16":{"family_comment":"","value":"","family":"","comment":""},"17":{"family_comment":"","value":"","family":"","comment":""},"18":{"family_comment":"","value":"","family":"","comment":""},"19":{"family_comment":"","value":"1067","family":"","comment":""},"20":{"value":"","value_unclear":false,"family_comment":"","comment_unclear":false,"comment":"","family":""}},"vehicle":{"35":[{"year_hidden":false,"brand_info":"2488 куб. см.","sum_rent_comment":"","year":"2006","brand_info_hidden":false,"brand_info_unclear":false,"year_unclear":false,"sum_rent":"","sum":"","brand":"Nissan X-Trail","sum_comment":"","brand_unclear":false,"brand_hidden":false}]},"id":"vulyk_94_34","banks":{"45":[{"sum_foreign_comment":"","sum_unclear":false,"sum_units":"UAH","sum_comment":"","sum_hidden":false,"sum_foreign_units":"UAH","sum_units_unclear":false,"sum_comment_hidden":false,"sum_units_hidden":false,"sum":"40331.54","sum_foreign":""}]},"declaration":{"additional_info_text":"","notfull_lostpages":"","date":"2015-03-30T00:00:00","notfull":"","additional_info":"","url":"http://static.declarations.com.ua/declarations/chosen_ones/judges_batch/3680_kobylianskyi_mykola_henrikhovych.pdf"},"liabilities":{"54":{"sum_foreign_comment":"","sum":"","sum_comment":"","sum_comment_unclear":false,"sum_comment_hidden":false,"sum_unclear":false,"sum_foreign":""},"55":{"sum_foreign_comment":"","sum":"","sum_comment":"","sum_foreign":""},"56":{"sum_foreign_comment":"","sum":"","sum_comment":"","sum_unclear":false,"sum_foreign":""},"57":{"sum_foreign_comment":"","sum":"","sum_comment":"","sum_hidden":false,"sum_unclear":false,"sum_foreign":""},"58":{"sum_foreign_comment":"","sum":"","sum_comment":"","sum_hidden":false,"sum_unclear":false,"sum_foreign":""},"59":{"sum_foreign_comment":"","sum":"","sum_comment":"","sum_foreign":""},"60":{"sum_foreign_comment":"","sum_comment_hidden":false,"sum":"","sum_comment":"","sum_foreign":""},"61":{"sum_foreign_comment":"","sum":"","sum_comment":"","sum_foreign":""},"62":{"sum_foreign_comment":"","sum":"","sum_hidden":false,"sum_comment":"","sum_foreign":""},"63":{"sum_foreign_comment":"","sum_comment_hidden":false,"sum":"","sum_comment":"","sum_foreign":""},"64":{"sum_foreign_comment":"","sum":"","sum_comment":"","sum_unclear":false,"sum_foreign":""}},"ft_src":"суддя вищого адміністративного суду україни\nЗагальнодержавний регіон\nВищий адміністративний суд України\nМикола\nПодружжя\nГенріхович\nКобилянський Микола Генріхович\nМикола Генріхович Кобилянський\nМикола Кобилянський\nКобилянський Микола Генріхович\nКобилянський Микола Генріхович\nКобилянський\n2488 куб. см.\nNissan X-Trail\n2006\n340\n1200\nмашиномісце\n12.9\n2400\n2.0032\n.0387\n95\n1/4 частина квартири\n52.6\n105\nне приватизована\n104.9\nне приватизована\n104.9\n1/4 частина\n52.6\n40331.54\n2014\n2488 куб. см.\nNissan X-Trail\n2006\n2014\nПодружжя\nКобилянський Микола Генріхович\nМикола Генріхович Кобилянський\nМикола Кобилянський\nКобилянський Микола Генріхович\nКобилянський Микола Генріхович\nМикола\nГенріхович\nВищий адміністративний суд України\nЗагальнодержавний регіон\nсуддя вищого адміністративного суду україни\nКобилянський\n308279\n15260\n309812\n15260\nпроценти\n466\n1067\n95\n12.9\nмашиномісце\n104.9\nне приватизована\n52.6\n1/4 частина\n2400\n2.0032\n.0387\n340\n1200\n52.6\n1/4 частина квартири\n105\n104.9\nне приватизована\n40331.54\n15260\n308279\n15260\n309812\n1067\nпроценти\n466\nПодружжя\nГенріхович\nКобилянський\nМикола\nКобилянський Микола Генріхович\nМикола Генріхович Кобилянський\nМикола Кобилянський\nКобилянський Микола Генріхович\nЗагальнодержавний регіон\nВищий адміністративний суд України\nсуддя вищого адміністративного суду україни\nКобилянський Микола Генріхович\nNissan X-Trail\n2488 куб. см.\n2006\n1067\n309812\n15260\nпроценти\n466\n15260\n308279\n1/4 частина квартири\n52.6\n105\nне приватизована\n104.9\n2400\n2.0032\n.0387\n95\nмашиномісце\n12.9\nне приватизована\n104.9\n1/4 частина\n52.6\n340\n1200\n40331.54\n2014","general":{"inn":"","name":"Микола","last_name":"Кобилянський","family":[{"inn":"","relations":"Подружжя","relations_hidden":false,"inn_hidden":true,"family_name":"","name_hidden":true,"name_unclear":false}],"inn_hidden":true,"family_raw":"","inn_unclear":false,"post":{"post_unclear":false,"region_unclear":false,"post":"суддя вищого адміністративного суду україни","candidate":"","post_hidden":false,"region":"Загальнодержавний регіон","office":"Вищий адміністративний суд України","office_unclear":false},"full_name":"Кобилянський Микола Генріхович","addresses":[{"place_district":"","place_address_hidden":false,"place_city":"","place_city_type_hidden":false,"place_district_hidden":false,"place_city_type":"","place_city_hidden":false,"place_address":"","place_hidden":true,"place":""}],"patronymic":"Генріхович","patronymic_hidden":false,"full_name_suggest":{"output":"Кобилянський Микола Генріхович","input":["Кобилянський Микола Генріхович","Микола Генріхович Кобилянський","Микола Кобилянський"]}},"source":"VULYK","estate":{"23":[{"region_unclear":false,"space_unclear":false,"costs":"","costs_comment":"","address_hidden":false,"region_hidden":true,"space_comment":"","space_hidden":false,"space":"2400","address":"","region":"","address_unclear":false,"space_units_unclear":false,"costs_rent_hidden":false,"costs_rent_comment_hidden":false,"space_units":"м²","costs_rent":"","costs_rent_comment":""},{"region_unclear":false,"costs":"","costs_comment":"","region_hidden":false,"space_comment":"","space":"2.0032","address":"","region":"","address_unclear":false,"costs_rent_comment":"","costs_rent_hidden":false,"costs_rent_comment_hidden":false,"space_units":"га","costs_rent":""},{"costs_rent":"","region":"","costs":"","costs_rent_comment":"","costs_comment":"","region_hidden":false,"space_comment":"","space_units":"га","space":".0387","address":""}],"25":[{"region_unclear":false,"space_unclear":false,"costs":"","costs_comment":"","address_hidden":false,"region_hidden":true,"space_comment":"не приватизована","space_hidden":false,"space":"104.9","address":"","region":"","address_unclear":false,"costs_rent_comment":"","costs_rent_hidden":false,"space_comment_unclear":false,"costs_rent_comment_hidden":false,"space_units":"м²","costs_rent":""},{"costs_rent":"","region":"","costs":"","costs_rent_comment":"","costs_comment":"","region_hidden":true,"space_comment":"1/4 частина","space_units":"м²","space":"52.6","address":""}],"28":[{"space_hidden":false,"costs":"","costs_comment":"","address_hidden":false,"region_hidden":true,"space_comment":"машиномісце","space":"12.9","address":"","region":"","costs_rent_comment":"","space_units":"м²","costs_rent":""}],"29":[{"costs_rent":"","region":"","costs_property":"","costs_rent_comment":"","address_hidden":true,"region_hidden":true,"space_comment":"","costs_property_comment":"","space_units":"м²","space":"340","address":""},{"costs_rent":"","region":"","costs_property":"","costs_rent_comment":"","address_hidden":true,"region_hidden":false,"space_comment":"","costs_property_comment":"","space_units":"м²","space":"1200","address":""}],"30":[{"space_hidden":false,"address_hidden":true,"region_hidden":true,"space_comment":"","space":"95","address":"","region":"","costs_property":"","costs_rent_comment":"","space_units":"м²","costs_property_comment":"","costs_rent":""}],"31":[{"space_unclear":false,"costs_property_hidden":false,"address_hidden":true,"region_hidden":true,"space_comment":"1/4 частина квартири","space_hidden":false,"space":"52.6","address":"","costs_property_comment_hidden":false,"region":"","costs_property":"","costs_rent_comment":"","costs_rent_hidden":false,"space_comment_unclear":false,"costs_rent_comment_hidden":false,"space_units":"м²","costs_property_comment":"","costs_rent":""},{"costs_rent":"","region":"","costs_property":"","costs_rent_comment":"","address_hidden":true,"region_hidden":false,"space_comment":"","costs_property_comment":"","space_units":"м²","space":"105","address":""},{"costs_rent":"","costs_property":"","costs_rent_comment":"","region_hidden":false,"space_comment":"не приватизована","costs_property_comment":"","space_units":"м²","space":"104.9","address":""}]},"intro":{"declaration_year":"2014","isnotdeclaration":""}}