{"income":{"5":{"family_comment":"","family_unclear":false,"value":"255216","family":"98617","comment":""},"6":{"value":"236984","family_comment":"","value_unclear":false,"family_unclear":false,"family":"93102","comment":""},"7":{"value":"","family_comment":"","value_unclear":false,"family_unclear":false,"source_name":"","family":"","comment":"","source_name_hidden":false},"8":{"family_comment":"","value":"","family":"","comment":""},"9":{"family_comment":"","value":"5832","family":"","comment":""},"10":{"family_comment":"","value":"","value_unclear":false,"family":"5515","comment":""},"11":{"family_comment":"","value":"","family":"","comment":""},"12":{"family_comment":"","value":"","family":"","comment":""},"13":{"family_comment":"","value":"","family":"","comment":""},"14":{"family_comment":"","value":"","family":"","comment":""},"15":{"family_comment":"","value":"","family":"","comment":""},"16":{"family_comment":"","value":"","family":"","comment":""},"17":{"family_comment":"","value":"","family":"","comment":""},"18":{"family_comment":"","value":"","family":"","comment":""},"19":{"family_comment":"","value":"","family":"","comment":""},"20":{"value":"12400","value_unclear":false,"comment_hidden":false,"family_comment":"","comment_unclear":false,"comment":"","family":""}},"vehicle":{"40":[{"brand_info":"2500 куб. см.","sum_rent_comment":"","brand":"Hyundai Terracan","sum_comment":"","year":"2001","brand_info_hidden":false,"year_unclear":true,"sum":"","sum_rent":""},{"brand_info":"1200 куб. см.","sum_rent_comment":"","brand":"Skoda Rapid","sum_comment":"","year":"2013","year_unclear":true,"sum":"","sum_rent":""}]},"id":"vulyk_96_56","banks":{"45":[{"sum_foreign_comment":"","sum_units":"UAH","sum_comment":"","sum_hidden":false,"sum_foreign_units":"UAH","sum_foreign_hidden":false,"sum_comment_hidden":false,"sum_unclear":false,"sum":"100000","sum_foreign":""}],"51":[{"sum_foreign_comment":"","sum_units":"UAH","sum_comment":"","sum_hidden":false,"sum_foreign_units":"UAH","sum_foreign_hidden":false,"sum_comment_hidden":false,"sum_unclear":false,"sum":"193015","sum_foreign":""}]},"declaration":{"additional_info_text":"","notfull_lostpages":"","date":"2016-03-29T00:00:00","notfull":"","additional_info":"","url":"http://static.declarations.com.ua/declarations/chosen_ones/judges_batch/270_horodetska_liudmyla_mykolaivna_2015.pdf"},"liabilities":{"54":{"sum_foreign_comment":"","sum":"","sum_comment":"","sum_hidden":false,"sum_comment_hidden":false,"sum_foreign":""},"55":{"sum_foreign_comment":"","sum":"","sum_comment":"","sum_foreign":""},"56":{"sum_foreign_comment":"","sum":"","sum_comment":"","sum_unclear":false,"sum_foreign":""},"57":{"sum_foreign_comment":"","sum_comment_hidden":false,"sum":"","sum_comment":"","sum_foreign":""},"58":{"sum_foreign_comment":"","sum":"","sum_comment":"","sum_comment_hidden":false,"sum_unclear":false,"sum_foreign":""},"59":{"sum_foreign_comment":"","sum":"","sum_comment":"","sum_foreign":""},"60":{"sum_foreign_comment":"","sum_comment_hidden":false,"sum":"","sum_comment":"","sum_foreign":""},"61":{"sum_foreign_comment":"","sum":"","sum_comment":"","sum_foreign":""},"62":{"sum_foreign_comment":"","sum":"","sum_comment":"","sum_foreign":""},"63":{"sum_foreign_comment":"","sum_comment_hidden":false,"sum":"","sum_comment":"","sum_foreign":""},"64":{"sum_foreign_comment":"","sum_comment_hidden":false,"sum":"","sum_comment":"","sum_foreign":""}},"ft_src":"суддя галицького районного суду м. львова\nЛьвівська область\nЗагальний місцевий суд\nЛюдмила\nГородецький О. М\nПодружжя\nГородецький О. О\nДитина\nМиколаївна\nГородецька Людмила Миколаївна\nГородецька\nГородецька Людмила Миколаївна\nЛюдмила Миколаївна Городецька\nЛюдмила Городецька\nГородецька Людмила Миколаївна\n2001\n2500 куб. см.\nHyundai Terracan\n2013\n1200 куб. см.\nSkoda Rapid\n193015\n100000\n2015\nHyundai Terracan\n2500 куб. см.\n2001\n1200 куб. см.\n2013\nSkoda Rapid\n100000\n193015\n2015\nГородецька Людмила Миколаївна\nЛюдмила Миколаївна Городецька\nЛюдмила Городецька\nГородецька Людмила Миколаївна\nГородецька Людмила Миколаївна\nЛюдмила\nГородецька\nЛьвівська область\nсуддя галицького районного суду м. львова\nЗагальний місцевий суд\nМиколаївна\nПодружжя\nГородецький О. М\nДитина\nГородецький О. О\n93102\n236984\n12400\n255216\n98617\n5832\n5515\n2261\n30\n112.6\nу спільній сумісній власності від 67,7\n22.6\n45\n45\n112.6\n2261\n30\nу спільній сумісній власності від 67,7\n22.6\nГородецький О. М\nПодружжя\nДитина\nГородецький О. О\nЛюдмила\nМиколаївна\nГородецька\nГородецька Людмила Миколаївна\nЛюдмила Миколаївна Городецька\nЛюдмила Городецька\nГородецька Людмила Миколаївна\nсуддя галицького районного суду м. львова\nЛьвівська область\nЗагальний місцевий суд\nГородецька Людмила Миколаївна\n93102\n236984\n5832\n5515\n98617\n255216\n12400\n2001\n2500 куб. см.\nHyundai Terracan\n2013\n1200 куб. см.\nSkoda Rapid\n5832\n5515\n12400\n98617\n255216\n236984\n93102\n112.6\n22.6\nу спільній сумісній власності від 67,7\n2261\n45\n30\n100000\n193015\n2015","general":{"inn":"","name":"Людмила","family":[{"inn":"","inn_hidden":true,"inn_unclear":false,"relations_hidden":false,"relations_other":"","relations":"Подружжя","name_hidden":true,"family_name":"Городецький О. М","name_unclear":false},{"inn":"","relations":"Дитина","relations_other":"","inn_hidden":false,"family_name":"Городецький О. О","name_hidden":false,"name_unclear":false}],"patronymic":"Миколаївна","inn_hidden":true,"family_raw":"","last_name":"Городецька","post":{"office":"Загальний місцевий суд","region":"Львівська область","office_unclear":false,"post":"суддя галицького районного суду м. львова"},"full_name":"Городецька Людмила Миколаївна","addresses":[{"place_district":"","place_city_hidden":true,"place_city":"","place_city_type_hidden":true,"place_district_hidden":true,"place_city_type":"","place_address_hidden":true,"place_address":"","place_hidden":true,"place":""}],"patronymic_hidden":false,"full_name_suggest":{"output":"Городецька Людмила Миколаївна","input":["Городецька Людмила Миколаївна","Людмила Миколаївна Городецька","Людмила Городецька"]}},"source":"VULYK","estate":{"25":[{"space_comment_unclear":true,"space_unclear":false,"costs":"","costs_comment":"","address_hidden":true,"region_hidden":true,"space_comment":"у спільній сумісній власності від 67,7","space_hidden":false,"space":"22.6","address":"","costs_rent_comment_unclear":false,"region":"","address_unclear":false,"costs_rent_comment":"","costs_unclear":false,"space_comment_hidden":false,"space_units":"м²","costs_rent":""}],"29":[{"region_unclear":false,"space_unclear":false,"address_hidden":true,"region_hidden":true,"space_comment":"","space":"2261","address":"","region":"","costs_property":"","costs_rent_comment":"","address_unclear":false,"space_units":"м²","costs_property_comment":"","costs_rent":""}],"31":[{"space_unclear":false,"address_hidden":true,"region_hidden":true,"space_comment":"","space_hidden":false,"space":"112.6","address":"","region":"","costs_property":"","costs_rent_comment":"","address_unclear":false,"space_units":"м²","costs_property_comment":"","costs_rent":""}],"32":[{"costs_rent":"","region":"","costs_property":"","costs_rent_comment":"","address_hidden":true,"region_hidden":true,"space_comment":"","costs_property_comment":"","space_units":"м²","space":"30","address":""}],"33":[{"costs_rent":"","region":"","costs_property":"","costs_rent_comment":"","address_hidden":true,"region_hidden":true,"space_comment":"","costs_property_comment":"","space_units":"м²","space":"45","address":""}]},"intro":{"declaration_year":"2015","isnotdeclaration":""}}