{"income":{"5":{"value":"342989","family_comment":"","comment_unclear":false,"family_unclear":false,"family":"37067","comment":""},"6":{"family_comment":"","value":"230900","family":"36948","comment":""},"7":{"source_name_unclear":false,"value":"","comment_unclear":false,"family_comment":"","source_name":"","family":"97","comment":""},"8":{"family_comment":"","value":"","family":"","comment":""},"9":{"family_comment":"","value":"589","family":"22","comment":""},"10":{"family_comment":"","value":"","family":"","comment":""},"11":{"family_comment":"","value":"","family":"","comment":""},"12":{"family_comment":"","value":"","family":"","comment":""},"13":{"family_comment":"","value":"","family":"","comment":""},"14":{"family_comment":"","value":"","family":"","comment":""},"15":{"family_comment":"","value":"","family":"","comment":""},"16":{"family_comment":"","family_unclear":false,"value":"","family":"","comment":""},"17":{"family_comment":"","value":"","family":"","comment":""},"18":{"family_comment":"","value":"","family":"","comment":""},"19":{"family_comment":"","value":"","family":"","comment":""},"20":{"value":"111500","family_comment":"","comment_unclear":false,"family_unclear":false,"family":"","comment":"","family_comment_unclear":false}},"vehicle":{"35":[{"brand_info":"1390 куб. см.","sum_rent_comment":"","brand":"Renault Megane","sum_comment":"","brand_unclear":false,"year":"2001","brand_info_unclear":false,"sum":"","sum_rent":""}]},"id":"vulyk_107_129","banks":{"45":[{"sum_foreign_comment":"","sum_unclear":false,"sum":"5665","sum_comment":"","sum_comment_unclear":false,"sum_foreign_units":"UAH","sum_comment_hidden":false,"sum_units":"UAH","sum_foreign":""}],"51":[{"sum_foreign_comment":"","sum_unclear":false,"sum":"1856","sum_comment":"Ощадбанк України","sum_comment_unclear":false,"sum_foreign_units":"UAH","sum_units":"UAH","sum_foreign":""}],"52":[{"sum_foreign_comment":"","sum":"2","sum_comment":"ПАТ Нафтохімік Прикарпаття","sum_comment_unclear":true,"sum_foreign_units":"UAH","sum_comment_hidden":false,"sum_units":"UAH","sum_foreign":""}]},"declaration":{"additional_info_text":"","notfull_lostpages":"","date":"2016-03-31T00:00:00","notfull":"","additional_info":"","url":"http://static.declarations.com.ua/declarations/chosen_ones/judges_batch/2108_sarnovskyi_vasyl_iaroslavovych.pdf"},"liabilities":{"54":{"sum_foreign_comment":"","sum":"120","sum_comment":"Приватбанк","sum_comment_unclear":false,"sum_comment_hidden":false,"sum_foreign":""},"55":{"sum_foreign_comment":"","sum":"","sum_comment":"","sum_foreign":""},"56":{"sum_foreign_comment":"","sum":"","sum_comment":"","sum_unclear":false,"sum_foreign":""},"57":{"sum_foreign_comment":"","sum":"67935","sum_comment":"","sum_comment_unclear":false,"sum_foreign":""},"58":{"sum_foreign_comment":"","sum":"1556","sum_comment":"","sum_comment_unclear":false,"sum_unclear":false,"sum_foreign":""},"59":{"sum_foreign_comment":"","sum":"","sum_comment":"","sum_unclear":false,"sum_foreign":""},"60":{"sum_foreign_comment":"","sum":"","sum_comment":"","sum_comment_unclear":false,"sum_comment_hidden":false,"sum_foreign":""},"61":{"sum_foreign_comment":"","sum":"","sum_comment":"","sum_foreign":""},"62":{"sum_foreign_comment":"","sum":"","sum_comment":"","sum_foreign":""},"63":{"sum_foreign_comment":"","sum":"","sum_comment":"","sum_foreign":""},"64":{"sum_foreign_comment":"","sum":"","sum_comment":"","sum_foreign":""}},"ft_src":"2001\nRenault Megane\n1390 куб. см.\nПАТ Нафтохімік Прикарпаття\n2\nОщадбанк України\n1856\n5665\n2015\n1390 куб. см.\n2001\nRenault Megane\n5665\n1856\nОщадбанк України\n2\nПАТ Нафтохімік Прикарпаття\n2015\nСарновський\nПодружжя\nСарновська Н. В\nДитина\nСарновська Т. В\nСарновський Василь Ярославович\nВасиль Ярославович Сарновський\nВасиль Сарновський\nСарновський Василь Ярославович\nВасиль\nЯрославович\nСарновський Василь Ярославович\nЗагальний апеляційний суд\nсуддя апеляційного суду тернопільської області\nТернопільська область\n67935\nПриватбанк\n120\n1556\n97\n230900\n36948\n111500\n342989\n37067\n589\n22\n.092\n32120\n.1\n.08\nінше право користування\n19.7\n19.7\nінше право користування\n1556\n67935\nПриватбанк\n120\n.092\n32120\n.1\n.08\nінше право користування\n19.7\nінше право користування\n19.7\nСарновська Н. В\nПодружжя\nСарновська Т. В\nДитина\nСарновський\nЯрославович\nсуддя апеляційного суду тернопільської області\nТернопільська область\nЗагальний апеляційний суд\nСарновський Василь Ярославович\nСарновський Василь Ярославович\nВасиль Ярославович Сарновський\nВасиль Сарновський\nСарновський Василь Ярославович\nВасиль\n36948\n230900\n22\n589\n97\n37067\n342989\n111500","general":{"inn_hidden":true,"inn":"","last_name":"Сарновський","post":{"post_unclear":false,"office":"Загальний апеляційний суд","post":"суддя апеляційного суду тернопільської області","region":"Тернопільська область"},"name":"Василь","full_name":"Сарновський Василь Ярославович","family_raw":"","addresses":[{"place_district":"","place_address_hidden":false,"place_city":"","place_address":"","place_district_hidden":true,"place_city_type":"","place_city_hidden":false,"place_city_type_hidden":false,"place_hidden":true,"place":""}],"family":[{"inn":"","inn_hidden":true,"family_name":"Сарновська Н. В","relations_other":"","relations":"Подружжя","name_hidden":false,"name_unclear":false},{"inn":"","inn_hidden":false,"family_name":"Сарновська Т. В","relations_other":"","relations":"Дитина","name_hidden":false,"name_unclear":false}],"full_name_suggest":{"output":"Сарновський Василь Ярославович","input":["Сарновський Василь Ярославович","Василь Ярославович Сарновський","Василь Сарновський"]},"patronymic":"Ярославович"},"source":"VULYK","estate":{"23":[{"costs":"","costs_comment":"","address_hidden":false,"region_hidden":true,"space_comment":"","space":".092","address":"","region":"","costs_rent_comment":"","space_comment_unclear":false,"space_comment_hidden":false,"space_units":"га","costs_rent":""},{"costs_rent":"","region":"","costs":"32120","costs_rent_comment":"","costs_comment":"","address_hidden":false,"region_hidden":false,"space_comment":"","space_units":"га","space":".1","address":""}],"25":[{"space_unclear":false,"costs":"","costs_comment":"","address_hidden":false,"region_hidden":true,"space_comment":"інше право користування","space_hidden":false,"space":"19.7","address":"","region":"","costs_rent_comment":"","space_units":"м²","costs_rent":""}],"29":[{"address_hidden":true,"region_hidden":true,"space_comment":"","space":".08","address":"","region":"","costs_property":"","costs_rent_comment":"","costs_rent_hidden":false,"space_units":"га","costs_property_comment":"","costs_rent":""}],"31":[{"space_unclear":false,"address_hidden":true,"region_hidden":true,"space_comment":"інше право користування","space_hidden":false,"space":"19.7","address":"","region":"","costs_property":"","costs_rent_comment":"","space_comment_unclear":false,"space_units":"м²","costs_property_comment":"","costs_rent":""}]},"intro":{"declaration_year":"2015","isnotdeclaration":""}}