{"income":{"5":{"family_comment":"","family_unclear":false,"value":"179775","family":"57671","comment":""},"6":{"family_comment":"","family_unclear":false,"value":"179775","family":"57536","comment":""},"7":{"value":"","comment_hidden":false,"family_comment":"","source_name":"","family":"","comment":""},"8":{"family_comment":"","value":"","family":"","comment":""},"9":{"family_comment":"","value":"","family":"32","comment":""},"10":{"family_comment":"","value":"","family":"","comment":""},"11":{"family_comment":"","value":"","value_unclear":false,"family":"103","comment":""},"12":{"family_comment":"","value":"","family":"","comment":""},"13":{"family_comment":"","value":"","family":"","comment":""},"14":{"family_comment":"","value":"","family":"","comment":""},"15":{"family_comment":"","value":"","value_unclear":false,"family":"","comment":""},"16":{"family_comment":"","family_unclear":false,"value":"","family":"","comment":""},"17":{"family_comment":"","value":"","family":"","comment":""},"18":{"family_comment":"","value":"","family_hidden":false,"comment":"","family":""},"19":{"family_comment":"","value":"","family":"","comment":""},"20":{"value":"","comment_unclear":false,"comment_hidden":false,"family_comment":"","family":"","comment":"","family_comment_hidden":false}},"vehicle":{"35":[{"brand_info":"1.4 , 5 dr, 1399 куб. см.","sum_rent_comment":"","year":"2010","brand_info_hidden":false,"brand_info_unclear":false,"year_unclear":false,"sum_rent":"","sum":"","brand":"Hyundai Getz","sum_comment":"","brand_unclear":false,"brand_hidden":false}],"40":[{"brand_info":"1595 куб. см.","sum_rent_comment":"","brand":"Volkswagen Golf","sum_comment":"","year":"2008","brand_hidden":false,"brand_info_hidden":false,"brand_info_unclear":false,"year_unclear":false,"sum":"","sum_rent":""}]},"id":"vulyk_68_175","banks":{"51":[{"sum_foreign_comment":"","sum_units":"UAH","sum_comment":"","sum_hidden":false,"sum_foreign_units":"UAH","sum_comment_hidden":false,"sum":"518","sum_foreign":""}]},"declaration":{"additional_info_text":"","notfull_lostpages":"","date":"2015-02-09T00:00:00","notfull":"","additional_info":"","url":"http://static.declarations.com.ua/declarations/chosen_ones/mega_batch/shcherbina_artem_valentynovych.pdf"},"liabilities":{"54":{"sum_foreign_comment":"","sum":"","sum_comment":"","sum_comment_unclear":false,"sum_hidden":false,"sum_comment_hidden":false,"sum_unclear":false,"sum_foreign":""},"55":{"sum_foreign_comment":"","sum":"","sum_hidden":false,"sum_comment":"","sum_foreign":""},"56":{"sum_foreign_comment":"","sum_foreign_hidden":false,"sum_comment":"","sum":"","sum_unclear":false,"sum_foreign":""},"57":{"sum_foreign_comment":"","sum":"","sum_comment":"","sum_comment_unclear":false,"sum_hidden":false,"sum_comment_hidden":false,"sum_unclear":false,"sum_foreign":""},"58":{"sum_foreign_comment":"","sum":"","sum_comment":"","sum_hidden":false,"sum_comment_hidden":false,"sum_unclear":false,"sum_foreign":""},"59":{"sum_foreign_comment":"","sum":"","sum_comment":"","sum_foreign":""},"60":{"sum_foreign_comment":"","sum":"","sum_comment":"","sum_comment_unclear":false,"sum_hidden":false,"sum_comment_hidden":false,"sum_unclear":false,"sum_foreign":""},"61":{"sum_foreign_comment":"","sum":"","sum_hidden":false,"sum_comment":"","sum_foreign":""},"62":{"sum_foreign_comment":"","sum":"","sum_comment":"","sum_unclear":false,"sum_foreign":""},"63":{"sum_foreign_comment":"","sum":"","sum_comment":"","sum_hidden":false,"sum_comment_hidden":false,"sum_unclear":false,"sum_foreign":""},"64":{"sum_foreign_comment":"","sum":"","sum_comment":"","sum_hidden":false,"sum_comment_hidden":false,"sum_foreign":""}},"ft_src":"суддя орджонікідзевського районного суду м. маріуполя донецької області\nДонецька область\nЗагальний місцевий суд\nАртем\nЩербіна О. А\nПодружжя\nЩербіна А. А\nДитина\nВалентинович\nЩербіна Артем Валентинович\nАртем Валентинович Щербіна\nАртем Щербіна\nЩербіна Артем Валентинович\nЩербіна Артем Валентинович\nЩербіна\n1.4 , 5 dr, 1399 куб. см.\nHyundai Getz\n2010\n1595 куб. см.\nVolkswagen Golf\n2008\n518\n2014\n1.4 , 5 dr, 1399 куб. см.\nHyundai Getz\n2010\n1595 куб. см.\n2008\nVolkswagen Golf\n518\n28\n31.61\n22.37\n1/3 частини, або 22,37\nЩербіна Артем Валентинович\nАртем Валентинович Щербіна\nАртем Щербіна\nЩербіна Артем Валентинович\nЩербіна Артем Валентинович\nПодружжя\nЩербіна О. А\nДитина\nЩербіна А. А\nАртем\nВалентинович\nЗагальний місцевий суд\nДонецька область\nсуддя орджонікідзевського районного суду м. маріуполя донецької області\nЩербіна\n179775\n57536\n179775\n57671\n103\n32\n2014\n31.61\n28\n1/3 частини, або 22,37\n22.37\nПодружжя\nЩербіна О. А\nЩербіна А. А\nДитина\nВалентинович\nЩербіна\nАртем\nЩербіна Артем Валентинович\nАртем Валентинович Щербіна\nАртем Щербіна\nЩербіна Артем Валентинович\nДонецька область\nЗагальний місцевий суд\nсуддя орджонікідзевського районного суду м. маріуполя донецької області\nЩербіна Артем Валентинович\n57536\n179775\n103\n57671\n179775\n32\n2010\nHyundai Getz\n1.4 , 5 dr, 1399 куб. см.\nVolkswagen Golf\n1595 куб. см.\n2008\n103\n57671\n179775\n32\n57536\n179775\n31.61\n22.37\n1/3 частини, або 22,37\n28\n518\n2014","general":{"inn":"","name":"Артем","inn_unclear":false,"family":[{"inn":"","inn_hidden":false,"relations_unclear":false,"relations_hidden":false,"relations_other":"","relations":"Подружжя","name_hidden":false,"inn_unclear":false,"family_name":"Щербіна О. А","name_unclear":false},{"inn":"","inn_hidden":false,"inn_unclear":false,"relations_hidden":true,"relations_other":"","relations":"Дитина","name_hidden":false,"family_name":"Щербіна А. А","name_unclear":false}],"inn_hidden":false,"family_raw":"","last_name":"Щербіна","post":{"post_unclear":false,"region_unclear":false,"post":"суддя орджонікідзевського районного суду м. маріуполя донецької області","office":"Загальний місцевий суд","region":"Донецька область","post_hidden":false,"office_hidden":false,"office_unclear":false,"region_hidden":false},"full_name_suggest":{"output":"Щербіна Артем Валентинович","input":["Щербіна Артем Валентинович","Артем Валентинович Щербіна","Артем Щербіна"]},"full_name":"Щербіна Артем Валентинович","patronymic":"Валентинович","last_name_unclear":false,"name_unclear":false},"source":"VULYK","estate":{"25":[{"space_unclear":false,"costs":"","costs_comment":"","address_hidden":false,"region_hidden":true,"space_comment":"1/3 частини, або 22,37","space_hidden":false,"space":"22.37","address":"","space_comment_unclear":false,"region":"","address_unclear":false,"costs_rent_comment":"","costs_unclear":false,"space_units":"м²","space_units_hidden":false,"costs_rent":""}],"31":[{"space_unclear":false,"address_hidden":true,"region_hidden":false,"space_comment":"","space_hidden":false,"space":"31.61","address":"","region":"","costs_property":"","costs_rent_comment":"","space_units":"м²","costs_property_comment":"","costs_rent":""}],"33":[{"space_unclear":false,"address_hidden":true,"region_hidden":false,"space_comment":"","space":"28","address":"","region":"","costs_property":"","costs_rent_comment":"","space_comment_unclear":false,"space_units":"м²","costs_property_comment":"","costs_rent":""}]},"intro":{"declaration_year":"2014","isnotdeclaration":""}}