{"income":{"5":{"value":"185000","family_comment":"","value_unclear":false,"family_hidden":false,"value_hidden":false,"family_unclear":false,"comment_unclear":false,"comment":"","family":"10500"},"6":{"value":"167819","family_comment":"","value_unclear":false,"family_hidden":false,"value_hidden":false,"family_unclear":false,"comment_unclear":false,"comment":"","family":""},"7":{"source_name_unclear":false,"value":"5001","family_comment":"","source_name":"Миколаївський інститут права Національного університету 'Одеська юридична академія'","family":"","comment":""},"8":{"family_comment":"","value":"","family":"","comment":""},"9":{"value":"","value_unclear":false,"comment_hidden":false,"family_comment":"","comment_unclear":false,"comment":"","family":""},"10":{"value":"12180","comment_unclear":false,"value_hidden":false,"family_comment":"","family":"","comment":""},"11":{"family_comment":"","value":"","family":"","comment":""},"12":{"family_comment":"","value":"","family":"","comment":""},"13":{"family_comment":"","value":"","family":"","comment":""},"14":{"family_comment":"","value":"","family":"","comment":""},"15":{"family_comment":"","value":"","family":"","comment":""},"16":{"family_comment":"","value":"","family":"","comment":""},"17":{"family_comment":"","value":"","family":"","comment":""},"18":{"value":"","family_hidden":false,"value_hidden":false,"family_comment":"","family":"","comment":""},"19":{"family_comment":"","value":"","family":"","comment":""},"20":{"value":"","family_comment":"","value_unclear":false,"family_hidden":false,"value_hidden":false,"family_unclear":false,"family":"10500","comment":""}},"vehicle":{"35":[{"year_hidden":false,"brand_info":"2100 куб. см, 90 к. с. , 400.0 см","sum_rent_comment":"","year":"1992","brand_info_unclear":false,"year_unclear":false,"sum_rent":"","sum":"","brand":"Peugeot 605","sum_comment":"","brand_unclear":false,"brand_hidden":false}]},"id":"vulyk_66_41","banks":{"45":[{"sum_foreign_comment":"","sum_units":"UAH","sum_units_hidden":false,"sum_comment":"","sum_comment_unclear":false,"sum_hidden":false,"sum_foreign_units":"UAH","sum_comment_hidden":false,"sum_unclear":false,"sum":"4134","sum_foreign":""}]},"declaration":{"additional_info_text":"","notfull_lostpages":"","date":"2015-03-25T00:00:00","notfull":"","additional_info":"","url":"http://static.declarations.com.ua/declarations/chosen_ones/mega_batch/voinarivskyi_mykola_mykolaiovych.pdf"},"liabilities":{"54":{"sum_foreign_comment":"","sum":"","sum_comment":"","sum_comment_unclear":false,"sum_comment_hidden":false,"sum_unclear":false,"sum_foreign":""},"55":{"sum_foreign_comment":"","sum":"","sum_comment":"","sum_foreign":""},"56":{"sum_foreign_comment":"","sum_foreign_hidden":false,"sum_comment":"","sum_hidden":false,"sum_comment_hidden":false,"sum":"","sum_foreign":""},"57":{"sum_foreign_comment":"","sum":"","sum_comment":"","sum_comment_unclear":false,"sum_hidden":false,"sum_comment_hidden":false,"sum_unclear":false,"sum_foreign":""},"58":{"sum_foreign_comment":"","sum":"","sum_comment":"","sum_comment_unclear":false,"sum_unclear":false,"sum_foreign":""},"59":{"sum_foreign_comment":"","sum_foreign_hidden":false,"sum_comment":"","sum_comment_unclear":false,"sum_hidden":false,"sum":"","sum_foreign":""},"60":{"sum_foreign_comment":"","sum":"","sum_comment":"","sum_comment_unclear":false,"sum_foreign":""},"61":{"sum_foreign_comment":"","sum":"","sum_comment":"","sum_foreign":""},"62":{"sum_foreign_comment":"","sum_foreign_hidden":false,"sum_comment":"","sum_hidden":false,"sum":"","sum_unclear":false,"sum_foreign":""},"63":{"sum_foreign_comment":"","sum":"","sum_comment":"","sum_comment_unclear":false,"sum_comment_hidden":false,"sum_unclear":false,"sum_foreign":""},"64":{"sum_foreign_comment":"","sum":"","sum_comment":"","sum_comment_unclear":false,"sum_foreign":""}},"ft_src":"суддя миколаївського районного суду миколаївської області\nМиколаївська область\nЗагальний місцевий суд\nМикола\nВойнарівська С. В. 22. 04. 1983\nПодружжя\nВойнарівський Р. М. 07. 03. 2013\nДитина\nМиколайович\nВойнарівський Микола Миколайович\nМикола Миколайович Войнарівський\nМикола Войнарівський\nВойнарівський Микола Миколайович\nВойнарівський Микола Миколайович\nВойнарівський\n2100 куб. см, 90 к. с. , 400.0 см\nPeugeot 605\n1992\n4134\n2014\n167819\n12180\nМиколаївський інститут права Національного університету 'Одеська юридична академія'\n5001\n10500\n185000\n10500\n2100 куб. см, 90 к. с. , 400.0 см\nPeugeot 605\n1992\n4134\n2014\nЗагальний місцевий суд\nсуддя миколаївського районного суду миколаївської області\nМиколаївська область\nПодружжя\nВойнарівська С. В. 22. 04. 1983\nДитина\nВойнарівський Р. М. 07. 03. 2013\nВойнарівський Микола Миколайович\nМикола Миколайович Войнарівський\nМикола Войнарівський\nВойнарівський Микола Миколайович\nВойнарівський Микола Миколайович\nМикола\nВойнарівський\nМиколайович\n5001\nМиколаївський інститут права Національного університету 'Одеська юридична академія'\n167819\n10500\n185000\n10500\n12180\nВойнарівська С. В. 22. 04. 1983\nПодружжя\nВойнарівський Р. М. 07. 03. 2013\nДитина\nМиколайович\nВойнарівський\nМикола\nВойнарівський Микола Миколайович\nМикола Миколайович Войнарівський\nМикола Войнарівський\nВойнарівський Микола Миколайович\nМиколаївська область\nсуддя миколаївського районного суду миколаївської області\nЗагальний місцевий суд\nВойнарівський Микола Миколайович\nPeugeot 605\n2100 куб. см, 90 к. с. , 400.0 см\n1992\n12180\n10500\n185000\n10500\n5001\nМиколаївський інститут права Національного університету 'Одеська юридична академія'\n167819\n4134\n2014","general":{"inn":"","name":"Микола","last_name_hidden":false,"family":[{"inn":"","inn_hidden":true,"relations_hidden":false,"family_name":"Войнарівська С. В. 22. 04. 1983","relations_other":"","relations":"Подружжя","name_hidden":false,"name_unclear":false},{"inn":"","inn_hidden":false,"relations_unclear":false,"relations_hidden":false,"relations_other":"","relations":"Дитина","name_hidden":false,"family_name":"Войнарівський Р. М. 07. 03. 2013","name_unclear":true}],"patronymic":"Миколайович","inn_hidden":true,"family_raw":"","inn_unclear":false,"post":{"post_unclear":false,"post":"суддя миколаївського районного суду миколаївської області","candidate":"","office_hidden":false,"region":"Миколаївська область","office":"Загальний місцевий суд","office_unclear":false},"full_name_suggest":{"output":"Войнарівський Микола Миколайович","input":["Войнарівський Микола Миколайович","Микола Миколайович Войнарівський","Микола Войнарівський"]},"full_name":"Войнарівський Микола Миколайович","addresses":[{"place_city_type_unclear":false,"place_address":"","place_district_hidden":false,"place_city_type":"","place_address_hidden":true,"place_address_unclear":false,"place_city_type_hidden":false,"place":"","place_district":"","place_unclear":false,"place_city":"","place_city_unclear":false,"place_hidden":true,"place_city_hidden":false,"place_district_unclear":false}],"last_name":"Войнарівський","last_name_unclear":false},"source":"VULYK","intro":{"declaration_year":"2014","isnotdeclaration":"","declaration_year_unclear":false}}