{"income":{"5":{"value":"312707","family_comment":"","value_unclear":false,"value_hidden":false,"family_unclear":false,"family":"","comment":""},"6":{"value":"296920","family_hidden":false,"value_hidden":false,"family_comment":"","family_comment_hidden":false,"comment":"","family":""},"7":{"value":"","value_unclear":false,"family_hidden":false,"value_hidden":false,"family_comment":"","source_name":"","family":"","comment":"","source_name_hidden":false},"8":{"value":"","comment_hidden":false,"family_hidden":false,"value_hidden":false,"family_comment":"","family":"","comment":""},"9":{"value":"2023","family_comment":"","comment_hidden":false,"family_hidden":false,"value_hidden":false,"family_unclear":false,"family":"","comment":""},"10":{"value":"13764","comment_hidden":false,"family_hidden":false,"value_hidden":false,"family_comment":"","family":"","comment":""},"11":{"value":"","value_unclear":false,"comment_hidden":false,"family_hidden":false,"value_hidden":false,"family_comment":"","family":"","comment":""},"12":{"value":"","comment_hidden":false,"family_hidden":false,"value_hidden":false,"family_comment":"","family":"","comment":""},"13":{"value":"","comment_hidden":false,"family_hidden":false,"value_hidden":false,"family_comment":"","family":"","comment":""},"14":{"value":"","comment_hidden":false,"family_hidden":false,"value_hidden":false,"family_comment":"","family":"","comment":""},"15":{"value":"","comment_hidden":false,"family_hidden":false,"value_hidden":false,"family_comment":"","family":"","comment":""},"16":{"value":"","comment_hidden":false,"family_hidden":false,"value_hidden":false,"family_comment":"","family":"","comment":""},"17":{"value":"","comment_hidden":false,"family_hidden":false,"value_hidden":false,"family_comment":"","family":"","comment":""},"18":{"value":"","value_unclear":false,"comment_hidden":false,"family_hidden":false,"value_hidden":false,"family_comment":"","family":"","comment":""},"19":{"value":"","comment_hidden":false,"family_hidden":false,"value_hidden":false,"family_comment":"","family":"","comment":""},"20":{"value":"","value_unclear":false,"family_comment":"","comment_unclear":false,"comment":"","family":""}},"vehicle":{"35":[{"brand_info":"2.362","sum_rent_comment":"","sum_rent_hidden":true,"year":"2008","sum_rent_unclear":true,"brand_info_hidden":true,"brand_info_unclear":true,"year_unclear":false,"sum_hidden":true,"sum_rent":"","sum":"","brand":"Toyota Camry","sum_comment":"","brand_unclear":false,"sum_rent_comment_hidden":false,"sum_comment_hidden":false,"sum_unclear":true}]},"id":"vulyk_76_13","banks":{"45":[{"sum_units":"UAH","sum_foreign":"","sum_hidden":false,"sum":"10060","sum_units_hidden":false,"sum_foreign_comment":"","sum_foreign_hidden":false,"sum_comment":"","sum_foreign_units":"UAH","sum_units_unclear":false,"sum_comment_hidden":false,"sum_unclear":false}]},"declaration":{"additional_info_text":"","notfull":"1","additional_info":"","notfull_lostpages":"п.п. 2,4,7-8,11-24,26-34,36-44,46-64, рік, дата заповнення декларації, підпис","url":"http://static.declarations.com.ua/declarations/chosen_ones/judges_batch/214_myroshnychenko_stanislav_volodymyrovych.pdf"},"liabilities":{"54":{"sum_foreign_comment":"","sum_foreign_hidden":false,"sum_comment":"","sum_hidden":false,"sum_comment_hidden":false,"sum":"","sum_foreign":""},"55":{"sum_foreign_comment":"","sum":"","sum_hidden":false,"sum_comment":"","sum_foreign":""},"56":{"sum_foreign_comment":"","sum":"","sum_comment":"","sum_foreign":""},"57":{"sum_foreign_comment":"","sum_foreign_hidden":false,"sum_comment":"","sum_hidden":false,"sum_comment_hidden":false,"sum_unclear":false,"sum":"","sum_foreign":""},"58":{"sum_foreign_comment":"","sum_foreign_hidden":false,"sum_comment":"","sum_hidden":false,"sum_comment_hidden":false,"sum_unclear":false,"sum":"","sum_foreign":""},"59":{"sum_foreign_comment":"","sum":"","sum_hidden":false,"sum_comment":"","sum_foreign":""},"60":{"sum_foreign_comment":"","sum_foreign_hidden":false,"sum_comment":"","sum_hidden":false,"sum_comment_hidden":false,"sum_unclear":false,"sum":"","sum_foreign":""},"61":{"sum_foreign_comment":"","sum":"","sum_hidden":false,"sum_comment":"","sum_foreign":""},"62":{"sum_foreign_comment":"","sum":"","sum_comment":"","sum_hidden":false,"sum_comment_hidden":false,"sum_foreign":""},"63":{"sum_foreign_comment":"","sum":"","sum_hidden":false,"sum_comment":"","sum_foreign":""},"64":{"sum_foreign_comment":"","sum":"","sum_hidden":false,"sum_comment":"","sum_foreign":""}},"ft_src":"1\nп.п. 2,4,7-8,11-24,26-34,36-44,46-64, рік, дата заповнення декларації, підпис\nсуддя вищого господарського суду україни\nЗагальнодержавний регіон\nВищий господарський суд\nСтаніслав\nВолодимирович\nМирошниченко\nМирошниченко Станіслав Володимирович\nМирошниченко Станіслав Володимирович\nСтаніслав Володимирович Мирошниченко\nСтаніслав Мирошниченко\nМирошниченко Станіслав Володимирович\n2.362\n2008\nToyota Camry\n53\n10060\nп.п. 2,4,7-8,11-24,26-34,36-44,46-64, рік, дата заповнення декларації, підпис\n1\n2013\n2.362\nToyota Camry\n2008\n1\nп.п. 2,4,7-8,11-24,26-34,36-44,46-64, рік, дата заповнення декларації, підпис\n53\nМирошниченко Станіслав Володимирович\nСтаніслав Володимирович Мирошниченко\nСтаніслав Мирошниченко\nМирошниченко Станіслав Володимирович\nМирошниченко Станіслав Володимирович\nСтаніслав\nВолодимирович\nВищий господарський суд\nсуддя вищого господарського суду україни\nЗагальнодержавний регіон\nМирошниченко\n296920\n312707\n2023\n13764\n10060\n2013\n296920\n2023\n13764\n312707\nВолодимирович\nМирошниченко\nСтаніслав\nМирошниченко Станіслав Володимирович\nСтаніслав Володимирович Мирошниченко\nСтаніслав Мирошниченко\nМирошниченко Станіслав Володимирович\nЗагальнодержавний регіон\nсуддя вищого господарського суду україни\nВищий господарський суд\nМирошниченко Станіслав Володимирович\n2008\nToyota Camry\n2.362\n2023\n13764\n312707\n296920\n53\n10060\n2013","general":{"inn":"","name":"Станіслав","inn_unclear":true,"patronymic":"Володимирович","inn_hidden":true,"family_raw":"","last_name":"Мирошниченко","post":{"post_unclear":false,"post":"суддя вищого господарського суду україни","candidate":"","office_hidden":false,"region":"Загальнодержавний регіон","office":"Вищий господарський суд","office_unclear":false,"region_hidden":true},"last_name_unclear":false,"full_name":"Мирошниченко Станіслав Володимирович","addresses":[{"place_city_type_unclear":false,"place_address":"","place_district_hidden":true,"place_city_type":"","place_city_hidden":true,"place_city_type_hidden":true,"place":"","place_district":"","place_unclear":false,"place_city":"","place_city_unclear":false,"place_hidden":true,"place_address_hidden":true}],"full_name_suggest":{"output":"Мирошниченко Станіслав Володимирович","input":["Мирошниченко Станіслав Володимирович","Станіслав Володимирович Мирошниченко","Станіслав Мирошниченко"]},"name_unclear":false},"source":"VULYK","estate":{"25":[{"space_unclear":false,"costs":"","costs_comment":"","address_hidden":true,"region_hidden":true,"space_comment":"","space_hidden":false,"space":"53","address":"","region":"","costs_rent_comment":"","space_comment_unclear":false,"space_comment_hidden":false,"space_units":"м²","costs_rent":""}]},"intro":{"declaration_year":"2013","isnotdeclaration":"","declaration_year_unclear":false,"declaration_year_hidden":false}}