{"income":{"5":{"value":"294675","comment_hidden":false,"family_comment":"","family":"20559","comment":"","family_comment_hidden":false},"6":{"value":"289509","family_comment":"","comment_hidden":false,"family_hidden":false,"family_unclear":false,"family_comment_hidden":false,"comment":"","family":"3767"},"7":{"value":"","comment_hidden":false,"family_comment_hidden":false,"family_comment":"","source_name":"","family":"","comment":"","source_name_hidden":false},"8":{"family_comment":"","value":"","family":"","comment":""},"9":{"value":"","family_comment":"","value_unclear":false,"family_unclear":false,"comment_unclear":false,"comment":"","family":""},"10":{"family_comment":"","family_unclear":false,"value":"","family":"","comment":""},"11":{"family_comment":"","value":"","family":"","comment":""},"12":{"family_comment":"","value":"","family":"","comment":""},"13":{"family_comment":"","value":"","family":"","comment":""},"14":{"family_comment":"","value":"","family":"","comment":""},"15":{"family_comment":"","value":"","comment_unclear":false,"family":"","comment":""},"16":{"family_comment":"","value":"","comment_unclear":false,"family":"","comment":""},"17":{"family_comment":"","value":"","family":"","comment":""},"18":{"family_comment":"","value":"","family":"","comment":""},"19":{"family_comment":"","value":"","family":"","comment":""},"20":{"value":"5166","family_comment":"пенсія","value_unclear":false,"family_unclear":false,"family_comment_unclear":false,"family_comment_hidden":false,"comment":"путівка","family":"16792"}},"vehicle":{"35":[{"brand_info":"1300 куб. см.","sum_rent_comment":"","brand":"ВАЗ 2108","sum_comment":"","brand_unclear":false,"year":"1991","sum_hidden":false,"brand_info_unclear":false,"sum":"","sum_rent":""}]},"id":"vulyk_73_48","banks":{"52":[{"sum_foreign_comment":"","sum_units":"UAH","sum_comment":"","sum_hidden":false,"sum_foreign_units":"UAH","sum_comment_hidden":true,"sum_foreign_hidden":true,"sum":"871","sum_foreign":""}]},"declaration":{"additional_info_text":"","notfull_lostpages":"","date":"2014-03-24T00:00:00","notfull":"","additional_info":"","url":"http://static.declarations.com.ua/declarations/chosen_ones/judges_batch/1391_savchenko_hryhorii_ivanovych.pdf"},"liabilities":{"54":{"sum_foreign_comment":"","sum_foreign_hidden":false,"sum_comment":"","sum_comment_unclear":false,"sum_hidden":false,"sum_comment_hidden":false,"sum_unclear":false,"sum":"","sum_foreign":""},"55":{"sum_foreign_comment":"","sum_comment_hidden":false,"sum":"","sum_comment":"","sum_foreign":""},"56":{"sum_foreign_comment":"","sum":"","sum_comment":"","sum_comment_unclear":false,"sum_foreign":""},"57":{"sum_foreign_comment":"","sum":"","sum_comment":"","sum_hidden":false,"sum_comment_hidden":false,"sum_unclear":false,"sum_foreign":""},"58":{"sum_foreign_comment":"","sum":"","sum_comment":"","sum_hidden":false,"sum_comment_hidden":false,"sum_foreign":""},"59":{"sum_foreign_comment":"","sum":"","sum_comment":"","sum_comment_unclear":false,"sum_unclear":false,"sum_foreign":""},"60":{"sum_foreign_comment":"","sum":"","sum_comment":"","sum_hidden":false,"sum_comment_hidden":false,"sum_unclear":false,"sum_foreign":""},"61":{"sum_foreign_comment":"","sum":"","sum_comment":"","sum_foreign":""},"62":{"sum_foreign_comment":"","sum":"","sum_comment":"","sum_foreign":""},"63":{"sum_foreign_comment":"","sum":"","sum_comment":"","sum_hidden":false,"sum_comment_hidden":false,"sum_foreign":""},"64":{"sum_foreign_comment":"","sum":"","sum_comment":"","sum_foreign":""}},"ft_src":"секретар судової палати (суддя) рівненського апеляційного господарського суду\nРівненська область\nАпеляційний господарський суд\nГригорій\nПодружжя\nДитина\nІванович\nСавченко Григорій Іванович\nГригорій Іванович Савченко\nГригорій Савченко\nСавченко Григорій Іванович\nСавченко\nСавченко Григорій Іванович\nВАЗ 2108\n1300 куб. см.\n1991\n18\n1000\nлітня кухня\n64\nнежитлове приміщення\n54\nнезавершене будівництво\n1500\nу спільній власності із членами сім'ї\n62.3\n62.3\nу спільній власності із членами сім'ї\n871\n2013\n1300 куб. см.\nВАЗ 2108\n1991\n2013\nСавченко Григорій Іванович\nГригорій Іванович Савченко\nГригорій Савченко\nСавченко Григорій Іванович\nГригорій\nПодружжя\nДитина\nСавченко Григорій Іванович\nІванович\nАпеляційний господарський суд\nРівненська область\nсекретар судової палати (суддя) рівненського апеляційного господарського суду\nСавченко\n3767\n289509\nпутівка\n16792\nпенсія\n5166\n294675\n20559\n18\n64\nлітня кухня\nнежитлове приміщення\n54\nнезавершене будівництво\n62.3\nу спільній власності із членами сім'ї\n1500\n1000\nу спільній власності із членами сім'ї\n62.3\n871\n3767\n289509\n20559\n294675\n16792\nпенсія\nпутівка\n5166\nПодружжя\nДитина\nІванович\nСавченко\nГригорій\nСавченко Григорій Іванович\nГригорій Іванович Савченко\nГригорій Савченко\nСавченко Григорій Іванович\nРівненська область\nАпеляційний господарський суд\nсекретар судової палати (суддя) рівненського апеляційного господарського суду\nСавченко Григорій Іванович\n1991\n1300 куб. см.\nВАЗ 2108\nпенсія\n5166\nпутівка\n16792\n294675\n20559\n289509\n3767\nу спільній власності із членами сім'ї\n62.3\n1500\n18\nлітня кухня\n64\nнежитлове приміщення\n54\nнезавершене будівництво\nу спільній власності із членами сім'ї\n62.3\n1000\n871\n2013","general":{"inn":"","name":"Григорій","family":[{"inn":"","relations":"Подружжя","inn_unclear":false,"relations_hidden":false,"inn_hidden":true,"relations_other":"","name_hidden":true,"family_name":"","name_unclear":false},{"inn":"","relations":"Дитина","inn_unclear":false,"family_name":"","inn_hidden":false,"relations_other":"","name_hidden":false,"name_unclear":false}],"patronymic":"Іванович","inn_hidden":true,"family_raw":"","last_name":"Савченко","post":{"post_unclear":false,"region_unclear":false,"post":"секретар судової палати (суддя) рівненського апеляційного господарського суду","office":"Апеляційний господарський суд","region":"Рівненська область","post_hidden":false,"office_hidden":false,"office_unclear":false,"region_hidden":false},"last_name_unclear":false,"full_name":"Савченко Григорій Іванович","addresses":[{"place_district":"","place_city_hidden":true,"place_city":"","place_city_type_hidden":true,"place_district_hidden":true,"place_city_type":"","place_address_hidden":true,"place_address":"","place_hidden":true,"place":""}],"full_name_suggest":{"output":"Савченко Григорій Іванович","input":["Савченко Григорій Іванович","Григорій Іванович Савченко","Григорій Савченко"]},"name_unclear":false},"source":"VULYK","estate":{"23":[{"space_hidden":false,"costs":"","costs_comment":"","costs_hidden":false,"address_hidden":false,"region_hidden":true,"space_comment":"","space_unclear":false,"space":"1500","address":"","region":"","space_units_unclear":false,"costs_unclear":false,"space_units":"м²","costs_rent":"","costs_rent_comment":""}],"25":[{"space_unclear":false,"costs":"","costs_comment":"","costs_hidden":false,"address_hidden":false,"region_hidden":true,"space_comment":"","space_hidden":false,"space":"62.3","address":"у спільній власності із членами сім'ї","region":"","costs_rent_comment":"","space_comment_hidden":false,"space_units":"м²","costs_rent":""}],"27":[{"space_unclear":false,"costs":"","costs_comment":"","costs_hidden":false,"address_hidden":false,"region_hidden":true,"space_comment":"","space":"18","address":"","region":"","costs_rent_comment":"","space_units":"м²","costs_rent":""}],"28":[{"costs":"","costs_comment":"","costs_hidden":false,"address_hidden":false,"region_hidden":true,"space_comment":"","space":"64","address":"літня кухня","region":"","address_unclear":true,"costs_rent_comment":"","space_units":"м²","costs_rent":""},{"space":"54","region":"","costs":"","costs_rent_comment":"","costs_comment":"","region_hidden":false,"address_unclear":true,"space_comment":"","space_units":"м²","costs_rent":"","address":"нежитлове приміщення"},{"costs_rent":"","region":"","costs":"","costs_rent_comment":"","costs_comment":"","space_comment":"","space_units":"м²","space":"","address":"незавершене будівництво"},{"costs_rent":"","region":"","costs":"","costs_rent_comment":"","costs_comment":"","address_hidden":true,"region_hidden":true,"space_comment":"","space_units":"","space":"","address":""}],"29":[{"space_unclear":false,"address_hidden":false,"region_hidden":true,"space_comment":"","space":"1000","address":"","region":"","costs_property":"","costs_rent_comment":"","space_units":"м²","costs_property_comment":"","costs_rent":""}],"31":[{"space_unclear":false,"address_hidden":false,"region_hidden":true,"space_comment":"","space":"62.3","address":"у спільній власності із членами сім'ї","region":"","costs_property":"","costs_rent_comment":"","space_units":"м²","costs_property_comment":"","costs_rent":""}]},"intro":{"declaration_year":"2013"}}