{"income":{"5":{"family_comment":"","value":"260737","family":"129806","comment":"","family_hidden":false},"6":{"family_comment":"","value":"247339","family":"24000","comment":"","family_hidden":false},"7":{"family_comment":"","value":"","source_name":"Київський транспортний університет","family":"67716","comment":""},"8":{"family_comment":"","value":"","family":"","comment":""},"9":{"family_comment":"","value":"","family":"","comment":""},"10":{"family_comment":"","value":"13398","family":"","comment":""},"11":{"family_comment":"","value":"","family":"","comment":""},"12":{"family_comment":"","value":"","family":"","comment":""},"13":{"family_comment":"","value":"","family":"","comment":""},"14":{"family_comment":"","value":"","family":"","comment":""},"15":{"family_comment":"","value":"","family":"","comment":""},"16":{"family_comment":"","value":"","family":"","comment":""},"17":{"family_comment":"","value":"","family":"","comment":""},"18":{"family_comment":"","value":"","family":"","comment":""},"19":{"family_comment":"","value":"","family":"","comment":""},"20":{"family_comment":"","value":"","family":"38090","comment":""}},"vehicle":{"35":[{"brand_info":"1.8 Т","sum":"","brand":"Audi A4","sum_comment":"","year":"2007","brand_info_hidden":false,"sum_rent_comment":"","sum_rent":""}]},"id":"vulyk_105_40","declaration":{"date":"2015-03-24T00:00:00","additional_info_text":"","additional_info":"","url":"http://static.declarations.com.ua/declarations/chosen_ones/judges_batch/4615_dykunska_svitlana_iaroslavivna.pdf"},"liabilities":{"54":{"sum_foreign_comment":"","sum_comment":"","sum":"10000","sum_comment_hidden":false,"sum_foreign":""},"55":{"sum_foreign_comment":"","sum":"","sum_comment":"","sum_foreign":""},"56":{"sum_foreign_comment":"","sum":"","sum_comment":"","sum_foreign":""},"57":{"sum_foreign_comment":"","sum":"","sum_comment":"","sum_comment_unclear":false,"sum_comment_hidden":false,"sum_foreign":""},"58":{"sum_foreign_comment":"","sum":"","sum_comment":"","sum_foreign":""},"59":{"sum_foreign_comment":"","sum":"","sum_comment":"","sum_foreign":""},"60":{"sum_foreign_comment":"","sum":"","sum_comment":"","sum_foreign":""},"61":{"sum_foreign_comment":"","sum":"","sum_comment":"","sum_foreign":""},"62":{"sum_foreign_comment":"","sum":"","sum_foreign":"","sum_comment":"","sum_hidden":false},"63":{"sum_foreign_comment":"","sum":"","sum_comment":"","sum_foreign":""},"64":{"sum_foreign_comment":"","sum":"","sum_comment":"","sum_foreign":""}},"ft_src":"1.8 Т\n2007\nAudi A4\n87.89\n1320\n512\n81.5\n73.5\n120\n2014\n24000\n247339\n13398\n67716\nКиївський транспортний університет\n129806\n260737\n38090\nAudi A4\n1.8 Т\n2007\n2014\nсуддя київського апеляційного господарського суду\nАпеляційний господарський суд\nм. Київ\nДикунська\nДикунська Світлана Ярославівна\nСвітлана Ярославівна Дикунська\nСвітлана Дикунська\nДикунська Світлана Ярославівна\nДикунська Світлана Ярославівна\nСвітлана\nЯрославівна\nПодружжя\nЯрослав Ю. Ю\nДитина\nЯрослав С. Ю\n10000\n67716\nКиївський транспортний університет\n247339\n24000\n38090\n260737\n129806\n13398\n1320\n512\n81.5\n87.89\n73.5\n120\n10000\nЯрослав Ю. Ю\nПодружжя\nЯрослав С. Ю\nДитина\nЯрославівна\nДикунська\nм. Київ\nсуддя київського апеляційного господарського суду\nАпеляційний господарський суд\nДикунська Світлана Ярославівна\nДикунська Світлана Ярославівна\nСвітлана Ярославівна Дикунська\nСвітлана Дикунська\nДикунська Світлана Ярославівна\nСвітлана","general":{"inn":"","inn_hidden":true,"last_name":"Дикунська","post":{"post_unclear":false,"region_unclear":false,"post":"суддя київського апеляційного господарського суду","office_hidden":false,"region":"м. Київ","office":"Апеляційний господарський суд","office_unclear":false},"name":"Світлана","full_name":"Дикунська Світлана Ярославівна","family_raw":"","addresses":[{"place_district":"","place_address_hidden":true,"place_city":"","place_address":"","place_district_hidden":true,"place_city_type":"","place_city_hidden":true,"place_city_type_hidden":false,"place_hidden":true,"place":""}],"family":[{"inn":"","inn_hidden":true,"relations_hidden":false,"family_name":"Ярослав Ю. Ю","relations_other":"","relations":"Подружжя","name_hidden":false,"name_unclear":false},{"inn":"","inn_hidden":false,"family_name":"Ярослав С. Ю","relations_other":"","relations":"Дитина","name_hidden":false,"name_unclear":false}],"full_name_suggest":{"output":"Дикунська Світлана Ярославівна","input":["Дикунська Світлана Ярославівна","Світлана Ярославівна Дикунська","Світлана Дикунська"]},"patronymic":"Ярославівна"},"source":"VULYK","estate":{"23":[{"costs_rent":"","region":"","costs":"","costs_rent_comment":"","costs_comment":"","address_hidden":true,"region_hidden":true,"space_comment":"","space_units":"м²","space":"1320","address":""},{"costs_rent":"","region":"","costs":"","costs_rent_comment":"","costs_comment":"","address_hidden":false,"region_hidden":false,"space_comment":"","space_units":"м²","space":"512","address":""}],"24":[{"space_hidden":false,"costs":"","costs_comment":"","address_hidden":true,"region_hidden":true,"space_comment":"","space":"81.5","address":"","region":"","costs_rent_comment":"","space_units":"м²","costs_rent":""}],"25":[{"space_hidden":false,"costs":"","costs_comment":"","address_hidden":true,"region_hidden":true,"space_comment":"","space":"120","address":"","region":"","costs_rent_comment":"","space_units":"м²","costs_rent":""}],"26":[{"costs_rent":"","region":"","costs":"","costs_rent_comment":"","costs_comment":"","address_hidden":true,"region_hidden":true,"space_comment":"","space_units":"м²","space":"87.89","address":""}],"31":[{"space_hidden":false,"address_hidden":true,"region_hidden":true,"space_comment":"","space":"73.5","address":"","region":"","costs_property":"","costs_rent_comment":"","space_units":"м²","costs_property_comment":"","costs_rent":""}]},"intro":{"declaration_year":"2014"}}