{"income":{"5":{"value":"223015.63","family_comment":"","value_unclear":false,"family_hidden":false,"value_hidden":false,"family_unclear":false,"family":"","comment":""},"6":{"value":"223015.63","value_unclear":false,"family_hidden":false,"value_hidden":false,"family_comment":"","comment_unclear":false,"comment":"","family":""},"7":{"value":"","value_hidden":false,"family_comment":"","source_name":"","family":"","comment":"","source_name_hidden":false},"8":{"family_comment":"","value":"","family":"","comment":""},"9":{"family_comment":"","value":"","comment_unclear":false,"family":"","comment":""},"10":{"family_comment":"","value":"","value_unclear":false,"family":"","comment":""},"11":{"family_comment":"","value":"","family":"","comment":""},"12":{"family_comment":"","value":"","family":"","comment":""},"13":{"family_comment":"","value":"","family":"","comment":""},"14":{"family_comment":"","value":"","family":"","comment":""},"15":{"family_comment":"","value":"","family":"","comment":""},"16":{"family_comment":"","value":"","family":"","comment":""},"17":{"family_comment":"","value":"","family":"","comment":""},"18":{"family_comment":"","value":"","family":"","comment":""},"19":{"value":"","value_unclear":false,"comment_hidden":false,"family_hidden":false,"value_hidden":false,"family_comment":"","family_comment_hidden":false,"comment":"","family":""},"20":{"value":"","family_comment":"","value_unclear":false,"family_hidden":false,"value_hidden":false,"family_unclear":false,"comment_unclear":false,"comment":"","family":""}},"id":"vulyk_65_92","declaration":{"additional_info_text":"","notfull_lostpages":"","date":"2015-03-26T00:00:00","notfull":"","additional_info":"","url":"http://static.declarations.com.ua/declarations/chosen_ones/mega_batch/serebriakova_tetiana_valeriivna.pdf"},"liabilities":{"54":{"sum_foreign_comment":"","sum":"60","sum_comment":"","sum_comment_unclear":false,"sum_hidden":false,"sum_comment_hidden":false,"sum_foreign":""},"55":{"sum_foreign_comment":"","sum":"","sum_comment":"","sum_foreign":""},"56":{"sum_foreign_comment":"","sum":"","sum_comment":"","sum_unclear":false,"sum_foreign":""},"57":{"sum_foreign_comment":"","sum":"","sum_comment":"","sum_comment_unclear":false,"sum_unclear":false,"sum_foreign":""},"58":{"sum_foreign_comment":"","sum":"","sum_comment":"","sum_comment_unclear":false,"sum_unclear":false,"sum_foreign":""},"59":{"sum_foreign_comment":"","sum":"","sum_comment":"","sum_foreign":""},"60":{"sum_foreign_comment":"","sum":"","sum_comment":"","sum_comment_unclear":false,"sum_foreign":""},"61":{"sum_foreign_comment":"","sum":"","sum_comment":"","sum_foreign":""},"62":{"sum_foreign_comment":"","sum":"","sum_comment":"","sum_foreign":""},"63":{"sum_foreign_comment":"","sum":"","sum_comment":"","sum_foreign":""},"64":{"sum_foreign_comment":"","sum":"","sum_comment":"","sum_unclear":false,"sum_foreign":""}},"ft_src":"60\nсуддя апеляційного суду миколаївської області\nМиколаївська область\nЗагальний апеляційний суд\nТетяна\nТяпаєв О. В. 30 листопада 1979 р. н\nПодружжя\nТяпаєва К. О. 17 вересня 2008 р. н\nДитина\nВалеріївна\nСеребрякова\nСеребрякова Тетяна Валеріївна\nСеребрякова Тетяна Валеріївна\nТетяна Валеріївна Серебрякова\nТетяна Серебрякова\nСеребрякова Тетяна Валеріївна\n223015.63\n223015.63\n66.2\n69.1\n2014\n223015.63\n223015.63\n66.2\n69.1\nЗагальний апеляційний суд\nМиколаївська область\nсуддя апеляційного суду миколаївської області\nСеребрякова Тетяна Валеріївна\nТетяна Валеріївна Серебрякова\nТетяна Серебрякова\nСеребрякова Тетяна Валеріївна\nТетяна\nПодружжя\nТяпаєв О. В. 30 листопада 1979 р. н\nДитина\nТяпаєва К. О. 17 вересня 2008 р. н\nСеребрякова Тетяна Валеріївна\nСеребрякова\nВалеріївна\n60\n223015.63\n223015.63\n2014\n60\nТяпаєв О. В. 30 листопада 1979 р. н\nПодружжя\nДитина\nТяпаєва К. О. 17 вересня 2008 р. н\nВалеріївна\nСеребрякова\nТетяна\nСеребрякова Тетяна Валеріївна\nТетяна Валеріївна Серебрякова\nТетяна Серебрякова\nСеребрякова Тетяна Валеріївна\nМиколаївська область\nЗагальний апеляційний суд\nсуддя апеляційного суду миколаївської області\nСеребрякова Тетяна Валеріївна\n66.2\n69.1\n2014","general":{"name_hidden":false,"name":"Тетяна","last_name_hidden":false,"inn":"","family":[{"inn":"","inn_hidden":true,"inn_unclear":false,"relations_hidden":false,"relations_other":"","relations":"Подружжя","name_hidden":false,"family_name":"Тяпаєв О. В. 30 листопада 1979 р. н","name_unclear":false},{"inn":"","inn_hidden":false,"relations_unclear":false,"relations_hidden":false,"relations_other":"","relations":"Дитина","name_hidden":false,"inn_unclear":false,"family_name":"Тяпаєва К. О. 17 вересня 2008 р. н","name_unclear":false}],"patronymic":"Валеріївна","inn_hidden":true,"family_raw":"","inn_unclear":false,"post":{"post_unclear":false,"region_unclear":false,"post":"суддя апеляційного суду миколаївської області","office":"Загальний апеляційний суд","region":"Миколаївська область","post_hidden":false,"office_hidden":false,"office_unclear":false,"region_hidden":false},"last_name_unclear":false,"full_name":"Серебрякова Тетяна Валеріївна","addresses":[{"place_district":"","place_address_hidden":true,"place_city":"","place_city_type_hidden":false,"place_district_hidden":true,"place_city_type":"","place_city_hidden":true,"place_address_unclear":false,"place_address":"","place_hidden":false,"place":""}],"last_name":"Серебрякова","patronymic_hidden":false,"full_name_suggest":{"output":"Серебрякова Тетяна Валеріївна","input":["Серебрякова Тетяна Валеріївна","Тетяна Валеріївна Серебрякова","Тетяна Серебрякова"]},"name_unclear":false},"source":"VULYK","estate":{"25":[{"space_unclear":false,"costs":"","costs_comment":"","address_hidden":false,"region_hidden":false,"space_comment":"","space_hidden":false,"space":"69.1","address":"","costs_rent_comment_unclear":false,"region":"","address_unclear":false,"costs_rent_comment":"","space_comment_unclear":false,"space_units":"м²","space_units_hidden":false,"costs_rent":""}],"31":[{"space_unclear":false,"address_hidden":false,"region_hidden":false,"space_comment":"","space":"66.2","address":"","region":"","costs_property":"","costs_rent_comment":"","space_comment_unclear":false,"space_units":"м²","costs_property_comment":"","costs_rent":""}]},"intro":{"declaration_year":"2014","isnotdeclaration":"","declaration_year_hidden":false}}