{"income":{"5":{"value":"330788.68","value_unclear":false,"value_hidden":false,"family_comment":"","family":"","comment":""},"6":{"value":"273061.47","family_comment":"","value_unclear":false,"family_unclear":false,"family":"","comment":""},"7":{"source_name_unclear":false,"value":"","family_hidden":false,"family_comment":"","source_name":"","family":"","comment":""},"8":{"family_comment":"","value":"","family":"","comment":""},"9":{"family_comment":"","value":"","family":"","comment":""},"10":{"family_comment":"","value":"","family":"","comment":""},"11":{"family_comment":"","value":"","family":"","comment":""},"12":{"family_comment":"","value":"","family":"","comment":""},"13":{"family_comment":"","value":"","family":"","comment":""},"14":{"family_comment":"","value":"","family":"","comment":""},"15":{"family_comment":"","value":"","family":"","comment":""},"16":{"family_comment":"","value":"","comment_unclear":false,"family":"","comment":""},"17":{"family_comment":"","family_unclear":false,"value":"","family":"","comment":""},"18":{"family_comment":"","value":"","family":"","comment":""},"19":{"value":"","family_hidden":false,"value_hidden":false,"family_comment":"","family":"","comment":""},"20":{"family_comment":"","value":"57726.36","comment_unclear":true,"family":"","comment":"пенсія за віком"}},"vehicle":{"35":[{"brand_info":"4650 мм, 188 к.с., 2656 куб. см.","sum_rent_comment":"","year":"2006","sum_rent_unclear":false,"brand_info_hidden":true,"brand_info_unclear":false,"year_unclear":false,"sum_rent":"","sum":"","brand":"Hyundai Santa FE","sum_comment":"","sum_comment_unclear":false,"brand_hidden":false,"sum_unclear":false,"brand_unclear":false}]},"id":"vulyk_67_175","declaration":{"additional_info_text":"","notfull_lostpages":"","date":"2015-03-30T00:00:00","notfull":"","additional_info":"","url":"http://static.declarations.com.ua/declarations/chosen_ones/mega_batch/zakharova_alla_serhiivna.pdf"},"liabilities":{"54":{"sum_foreign_comment":"","sum_foreign_hidden":false,"sum_comment":"","sum_comment_unclear":false,"sum_hidden":false,"sum":"","sum_unclear":false,"sum_foreign":""},"55":{"sum_foreign_comment":"","sum":"","sum_comment":"","sum_foreign":""},"56":{"sum_foreign_comment":"","sum_foreign_hidden":false,"sum_comment":"","sum_hidden":false,"sum":"","sum_unclear":false,"sum_foreign":""},"57":{"sum_foreign_comment":"","sum_foreign_hidden":false,"sum_comment":"","sum_comment_unclear":false,"sum_hidden":false,"sum_comment_hidden":false,"sum_unclear":false,"sum":"","sum_foreign":""},"58":{"sum_foreign_comment":"","sum_foreign_hidden":false,"sum_comment":"","sum_comment_unclear":false,"sum_hidden":false,"sum_comment_hidden":false,"sum_unclear":false,"sum":"","sum_foreign":""},"59":{"sum_foreign_comment":"","sum":"","sum_hidden":false,"sum_comment":"","sum_foreign":""},"60":{"sum_foreign_comment":"","sum":"","sum_comment":"","sum_foreign":""},"61":{"sum_foreign_comment":"","sum_foreign_hidden":false,"sum_comment":"","sum_hidden":false,"sum":"","sum_foreign":""},"62":{"sum_foreign_comment":"","sum":"","sum_hidden":false,"sum_comment":"","sum_foreign":""},"63":{"sum_foreign_comment":"","sum":"","sum_comment":"","sum_comment_unclear":false,"sum_hidden":false,"sum_unclear":false,"sum_foreign":""},"64":{"sum_foreign_comment":"","sum":"","sum_comment":"","sum_hidden":false,"sum_unclear":false,"sum_foreign":""}},"ft_src":"суддя солом'янського районного суду міста києва\nм. Київ\nЗагальний місцевий суд\nАлла\nСергіївна\nЗахарова\nЗахарова Алла Сергіївна\nЗахарова Алла Сергіївна\nАлла Сергіївна Захарова\nАлла Захарова\nЗахарова Алла Сергіївна\n4650 мм, 188 к.с., 2656 куб. см.\nHyundai Santa FE\n2006\n.3301\n2/3\n69.3\n2014\n273061.47\n330788.68\nпенсія за віком\n57726.36\n4650 мм, 188 к.с., 2656 куб. см.\nHyundai Santa FE\n2006\n.3301\n69.3\n2/3\nЗагальний місцевий суд\nсуддя солом'янського районного суду міста києва\nм. Київ\nЗахарова Алла Сергіївна\nАлла Сергіївна Захарова\nАлла Захарова\nЗахарова Алла Сергіївна\nАлла\nЗахарова Алла Сергіївна\nЗахарова\nСергіївна\n273061.47\nпенсія за віком\n57726.36\n330788.68\n2014\nЗахарова Алла Сергіївна\nАлла Сергіївна Захарова\nАлла Захарова\nЗахарова Алла Сергіївна\nСергіївна\nЗахарова\nм. Київ\nсуддя солом'янського районного суду міста києва\nЗагальний місцевий суд\nЗахарова Алла Сергіївна\nАлла\n2006\nHyundai Santa FE\n4650 мм, 188 к.с., 2656 куб. см.\nпенсія за віком\n57726.36\n330788.68\n273061.47\n2/3\n69.3\n.3301\n2014","general":{"inn":"","name":"Алла","patronymic_unclear":false,"last_name_hidden":false,"inn_unclear":false,"patronymic":"Сергіївна","inn_hidden":true,"family_raw":"","last_name":"Захарова","post":{"post_unclear":false,"post":"суддя солом'янського районного суду міста києва","post_hidden":false,"region":"м. Київ","region_hidden":false,"office":"Загальний місцевий суд","office_hidden":false,"office_unclear":false},"last_name_unclear":false,"full_name":"Захарова Алла Сергіївна","addresses":[{"place_city_type_hidden":true,"place_district_hidden":true,"place_city_type":"","place_city_hidden":true,"place_address_unclear":false,"place_address":"","place":"","place_district":"","place_unclear":false,"place_city":"","place_city_unclear":false,"place_hidden":true,"place_address_hidden":true,"place_district_unclear":false}],"full_name_suggest":{"output":"Захарова Алла Сергіївна","input":["Захарова Алла Сергіївна","Алла Сергіївна Захарова","Алла Захарова"]},"name_unclear":false},"source":"VULYK","estate":{"23":[{"space_hidden":false,"costs":"","costs_comment":"","costs_hidden":false,"address_hidden":false,"region_hidden":true,"space_comment":"","space_unclear":false,"space":".3301","address":"","region":"","address_unclear":false,"space_units_unclear":false,"costs_rent_hidden":false,"space_comment_unclear":false,"space_units":"га","costs_rent":"","costs_rent_comment":""}],"25":[{"space_unclear":false,"costs":"","costs_comment":"","costs_hidden":false,"address_hidden":false,"region_hidden":true,"space_comment":"2/3","space":"69.3","address":"","region":"","address_unclear":false,"space_units_unclear":false,"space_comment_unclear":false,"space_units":"м²","costs_rent":"","costs_rent_comment":""}]},"intro":{"declaration_year":"2014","isnotdeclaration":"","declaration_year_hidden":false}}