{"income":{"5":{"value":"263207","family_hidden":false,"value_hidden":false,"family_comment":"","family":"","comment":""},"6":{"family_comment":"","value":"247872","family":"","comment":""},"7":{"family_comment":"","value":"367","source_name":"Національна школа суддів України","family":"","comment":""},"8":{"family_comment":"","value":"","family":"","comment":""},"9":{"family_comment":"","value":"","family":"","comment":""},"10":{"family_comment":"","value":"","family":"","comment":""},"11":{"family_comment":"","value":"","family":"","comment":""},"12":{"family_comment":"","value":"","family":"","comment":""},"13":{"family_comment":"","value":"","family":"","comment":""},"14":{"family_comment":"","value":"","family":"","comment":""},"15":{"family_comment":"","value":"","family":"","comment":""},"16":{"family_comment":"","value":"","family":"","comment":""},"17":{"family_comment":"","value":"","family":"","comment":""},"18":{"family_comment":"","value":"","family":"","comment":""},"19":{"family_comment":"","value":"","family":"","comment":""},"20":{"family_comment":"","value":"14968","family":"","comment":""}},"vehicle":{"40":[{"brand_info":"1499 куб. см., 80 кВт","sum":"","brand":"Mitsubishi Lancer","sum_comment":"","year":"2008","sum_rent_comment":"","sum_rent":""}]},"id":"vulyk_89_11","declaration":{"date":"2015-03-26T00:00:00","notfull":"","notfull_lostpages":"","url":"http://static.declarations.com.ua/declarations/chosen_ones/judges_batch/3014_sivachenko_ihor_viktorovych.pdf"},"liabilities":{"54":{"sum_foreign_comment":"","sum":"","sum_comment":"","sum_foreign":""},"55":{"sum_foreign_comment":"","sum":"","sum_comment":"","sum_foreign":""},"56":{"sum_foreign_comment":"","sum":"","sum_comment":"","sum_unclear":false,"sum_foreign":""},"57":{"sum_foreign_comment":"","sum":"","sum_comment":"","sum_foreign":""},"58":{"sum_foreign_comment":"","sum":"","sum_comment":"","sum_foreign":""},"59":{"sum_foreign_comment":"","sum":"","sum_comment":"","sum_foreign":""},"60":{"sum_foreign_comment":"","sum":"","sum_comment":"","sum_foreign":""},"61":{"sum_foreign_comment":"","sum":"","sum_comment":"","sum_foreign":""},"62":{"sum_foreign_comment":"","sum":"","sum_comment":"","sum_unclear":false,"sum_foreign":""},"63":{"sum_foreign_comment":"","sum":"","sum_comment":"","sum_foreign":""},"64":{"sum_foreign_comment":"","sum":"","sum_comment":"","sum_foreign":""}},"ft_src":"1499 куб. см., 80 кВт\n2008\nMitsubishi Lancer\n43.9\n66.5\n2014\n247872\n367\nНаціональна школа суддів України\n263207\n14968\n1499 куб. см., 80 кВт\nMitsubishi Lancer\n2008\n2014\nВікторович\nСіваченко С. В\nПодружжя\nДитина\nСіваченко В. І\nСіваченко Ігор Вікторович\nІгор Вікторович Сіваченко\nІгор Сіваченко\nСіваченко Ігор Вікторович\nСіваченко Ігор Вікторович\nІгор\nСіваченко\nДонецька область\nсуддя донецького апеляційного адміністративного суду\nАпеляційний адміністративний суд\n367\nНаціональна школа суддів України\n247872\n14968\n263207\n43.9\n66.5\nСіваченко С. В\nПодружжя\nСіваченко В. І\nДитина\nВікторович\nСіваченко\nсуддя донецького апеляційного адміністративного суду\nДонецька область\nАпеляційний адміністративний суд\nСіваченко Ігор Вікторович\nСіваченко Ігор Вікторович\nІгор Вікторович Сіваченко\nІгор Сіваченко\nСіваченко Ігор Вікторович\nІгор","general":{"inn":"","inn_hidden":true,"last_name":"Сіваченко","post":{"office":"Апеляційний адміністративний суд","region":"Донецька область","post":"суддя донецького апеляційного адміністративного суду"},"name":"Ігор","full_name":"Сіваченко Ігор Вікторович","family_raw":"","addresses":[{"place_district":"","place_address_hidden":false,"place_city":"","place_address":"","place_district_hidden":true,"place_city_type":"","place_city_hidden":true,"place_city_type_hidden":false,"place_hidden":true,"place":""}],"family":[{"inn":"","inn_hidden":true,"relations":"Подружжя","family_name":"Сіваченко С. В","name_hidden":false},{"inn":"","inn_hidden":false,"family_name":"Сіваченко В. І","relations_other":"","relations":"Дитина","name_hidden":false,"name_unclear":false}],"full_name_suggest":{"output":"Сіваченко Ігор Вікторович","input":["Сіваченко Ігор Вікторович","Ігор Вікторович Сіваченко","Ігор Сіваченко"]},"patronymic":"Вікторович"},"source":"VULYK","estate":{"25":[{"costs":"","costs_comment":"","address_hidden":true,"region_hidden":true,"space_comment":"","space":"66.5","address":"","region":"","costs_rent_comment":"","space_comment_unclear":false,"space_units":"м²","costs_rent":""}],"31":[{"space_hidden":false,"address_hidden":true,"region_hidden":true,"space_comment":"","space":"43.9","address":"","region":"","costs_property":"","costs_rent_comment":"","space_units":"м²","costs_property_comment":"","costs_rent":""}]},"intro":{"declaration_year":"2014"}}