{"income":{"5":{"family_comment":"","value":"257095","family":"51218","comment":""},"6":{"family_comment":"","value":"257095","family":"51218","comment":""},"7":{"family_comment":"","value":"","source_name":"","family":"","comment":""},"8":{"family_comment":"","value":"","family":"","comment":""},"9":{"value":"","comment_unclear":false,"family_comment":"","family":"","comment":"","family_comment_unclear":false},"10":{"family_comment":"","value":"","family":"","comment":""},"11":{"family_comment":"","value":"","family":"","comment":""},"12":{"family_comment":"","value":"","family":"","comment":""},"13":{"family_comment":"","value":"","family":"","comment":""},"14":{"family_comment":"","value":"","family":"","comment":""},"15":{"family_comment":"","value":"","family":"","comment":""},"16":{"family_comment":"","value":"","family":"","comment":""},"17":{"family_comment":"","value":"","family":"","comment":""},"18":{"family_comment":"","value":"","family":"","comment":""},"19":{"value":"","family_comment":"","value_unclear":false,"family_unclear":false,"family":"","comment":""},"20":{"value":"","family_comment":"","value_unclear":false,"comment_hidden":false,"family_comment_hidden":false,"family_unclear":false,"family_comment_unclear":false,"comment_unclear":false,"comment":"","family":""}},"vehicle":{"35":[{"brand_info":"2378 куб. см.","sum_rent_comment":"","brand":"Mitsubishi Outlander","sum_comment":"","year":"2008","sum_hidden":false,"brand_info_hidden":false,"brand_info_unclear":false,"year_unclear":false,"sum":"","sum_rent":""}]},"id":"vulyk_106_10","banks":{"45":[{"sum_foreign_comment":"","sum_units":"UAH","sum_comment":"Приватбанк - депозит 'Копілка' закритий 28. 03. 2016","sum_foreign_comment_hidden":false,"sum_hidden":false,"sum_foreign_units":"UAH","sum_comment_hidden":false,"sum":"73.35","sum_foreign":""}]},"declaration":{"additional_info_text":"","notfull_lostpages":"","date":"2016-03-28T00:00:00","notfull":"","additional_info":"","url":"http://static.declarations.com.ua/declarations/chosen_ones/judges_batch/2149_fanda_volodymyr_petrovych.pdf"},"liabilities":{"54":{"sum_foreign_comment":"","sum":"120","sum_comment":"Приватбанк, страхування квартири","sum_comment_unclear":false,"sum_hidden":false,"sum_comment_hidden":false,"sum_foreign":""},"55":{"sum_foreign_comment":"","sum":"","sum_hidden":false,"sum_comment":"","sum_foreign":""},"56":{"sum_foreign_comment":"","sum":"","sum_comment":"","sum_hidden":false,"sum_comment_hidden":false,"sum_unclear":false,"sum_foreign":""},"57":{"sum_foreign_comment":"","sum":"","sum_comment":"","sum_hidden":false,"sum_comment_hidden":false,"sum_foreign":""},"58":{"sum_foreign_comment":"","sum":"","sum_comment":"","sum_hidden":false,"sum_comment_hidden":false,"sum_foreign":""},"59":{"sum_foreign_comment":"","sum":"","sum_comment":"","sum_foreign":""},"60":{"sum_foreign_comment":"","sum":"","sum_comment":"","sum_hidden":false,"sum_comment_hidden":false,"sum_foreign":""},"61":{"sum_foreign_comment":"","sum":"","sum_comment":"","sum_foreign":""},"62":{"sum_foreign_comment":"","sum":"","sum_comment":"","sum_comment_hidden":false,"sum_unclear":false,"sum_foreign":""},"63":{"sum_foreign_comment":"","sum":"","sum_comment":"","sum_foreign":""},"64":{"sum_foreign_comment":"","sum":"","sum_comment":"","sum_foreign":""}},"ft_src":"Приватбанк, страхування квартири\n120\nсуддя апеляційного суду хмельницької області\nХмельницька область\nЗагальний апеляційний суд\nВолодимир\nПіхурець І. В\nДитина\nПіхурець А. П\nІнше\nзять\nПіхурець Т. А\nПетрович\nФанда Володимир Петрович\nВолодимир Петрович Фанда\nВолодимир Фанда\nФанда Володимир Петрович\nФанда Володимир Петрович\nФанда\nMitsubishi Outlander\n2378 куб. см.\n2008\nПриватбанк - депозит 'Копілка' закритий 28. 03. 2016\n73.35\n2015\n2378 куб. см.\n2008\nMitsubishi Outlander\n73.35\nПриватбанк - депозит 'Копілка' закритий 28. 03. 2016\n69\nФанда Володимир Петрович\nВолодимир Петрович Фанда\nВолодимир Фанда\nФанда Володимир Петрович\nФанда Володимир Петрович\nДитина\nПіхурець І. В\nІнше\nзять\nПіхурець А. П\nПіхурець Т. А\nВолодимир\nФанда\nХмельницька область\nЗагальний апеляційний суд\nсуддя апеляційного суду хмельницької області\nПетрович\nПриватбанк, страхування квартири\n120\n257095\n51218\n257095\n51218\n2015\nПриватбанк, страхування квартири\n120\n69\nПіхурець І. В\nДитина\nзять\nПіхурець А. П\nІнше\nПіхурець Т. А\nПетрович\nФанда\nВолодимир\nФанда Володимир Петрович\nВолодимир Петрович Фанда\nВолодимир Фанда\nФанда Володимир Петрович\nХмельницька область\nЗагальний апеляційний суд\nсуддя апеляційного суду хмельницької області\nФанда Володимир Петрович\n51218\n257095\n51218\n257095\n2008\nMitsubishi Outlander\n2378 куб. см.\n51218\n257095\n51218\n257095\n69\nПриватбанк - депозит 'Копілка' закритий 28. 03. 2016\n73.35\n2015","general":{"inn":"","name":"Володимир","inn_unclear":false,"family":[{"inn":"","inn_hidden":true,"relations_unclear":false,"relations_hidden":false,"relations_other":"","relations":"Дитина","name_hidden":false,"family_name":"Піхурець І. В","name_unclear":false},{"inn":"","relations":"Інше","relations_unclear":false,"family_name":"Піхурець А. П","inn_hidden":true,"relations_other":"зять","name_hidden":false,"name_unclear":false},{"inn_hidden":false,"inn":"","name_hidden":false,"family_name":"Піхурець Т. А","relations":"","name_unclear":false}],"inn_hidden":true,"family_raw":"","last_name":"Фанда","post":{"region_unclear":false,"region":"Хмельницька область","post":"суддя апеляційного суду хмельницької області","office":"Загальний апеляційний суд","office_unclear":false,"post_hidden":false},"full_name":"Фанда Володимир Петрович","addresses":[{"place_district":"","place_city_hidden":false,"place_city":"","place_city_type_hidden":false,"place_district_hidden":false,"place_city_type":"","place_address_hidden":false,"place_address":"","place_hidden":true,"place":""}],"patronymic":"Петрович","full_name_suggest":{"output":"Фанда Володимир Петрович","input":["Фанда Володимир Петрович","Володимир Петрович Фанда","Володимир Фанда"]},"name_unclear":false},"source":"VULYK","estate":{"25":[{"costs":"","costs_comment":"","address_hidden":false,"region_hidden":true,"space_comment":"","space":"69","address":"","region":"","costs_rent_comment":"","space_comment_unclear":false,"space_units":"м²","costs_rent":""}]},"intro":{"declaration_year":"2015","isnotdeclaration":""}}