{"income":{"5":{"family_comment":"","value":"265637","family":"5942","comment":""},"6":{"family_comment":"","value":"246393","family":"","comment":"","family_comment_unclear":false},"7":{"value":"","comment_hidden":false,"family_comment":"","source_name":"","family":"","comment":"","source_name_hidden":false},"8":{"family_comment":"","value":"","family":"","comment":""},"9":{"family_comment":"","value":"5846","family":"5942","comment":""},"10":{"value":"13398","value_unclear":false,"value_hidden":false,"family_comment":"","family":"","comment":""},"11":{"family_comment":"","value":"","family":"","comment":""},"12":{"family_comment":"","value":"","family":"","comment":""},"13":{"family_comment":"","value":"","family":"","comment":""},"14":{"family_comment":"","value":"","family":"","comment":""},"15":{"family_comment":"","value":"","family":"","comment":""},"16":{"family_comment":"","value":"","family":"","comment":""},"17":{"family_comment":"","value":"","family":"","comment":""},"18":{"family_comment":"","value":"","family":"","comment":""},"19":{"family_comment":"","value":"","family":"","comment":""},"20":{"family_comment":"","value":"","comment_unclear":false,"family":"","comment":""}},"id":"vulyk_86_42","banks":{"45":[{"sum_foreign_comment":"","sum_units":"UAH","sum_comment":"","sum_foreign_units":"UAH","sum_comment_hidden":true,"sum_unclear":false,"sum":"125860","sum_foreign":""}],"51":[{"sum_foreign_comment":"","sum_units":"UAH","sum_comment":"","sum_foreign_units":"UAH","sum_comment_hidden":false,"sum":"272380","sum_foreign":""}]},"declaration":{"additional_info_text":"","notfull_lostpages":"","date":"2015-03-24T00:00:00","notfull":"","additional_info":"","url":"http://static.declarations.com.ua/declarations/chosen_ones/judges_batch/2745_novosiadla_valentyna_mykolaivna.pdf"},"liabilities":{"54":{"sum_foreign_comment":"","sum":"","sum_comment":"","sum_unclear":false,"sum_foreign":""},"55":{"sum_foreign_comment":"","sum":"","sum_comment":"","sum_foreign":""},"56":{"sum_foreign_comment":"","sum":"","sum_hidden":false,"sum_comment":"","sum_foreign":""},"57":{"sum_foreign_comment":"","sum":"","sum_comment":"","sum_unclear":false,"sum_foreign":""},"58":{"sum_foreign_comment":"","sum":"","sum_comment":"","sum_unclear":false,"sum_foreign":""},"59":{"sum_foreign_comment":"","sum":"","sum_comment":"","sum_foreign":""},"60":{"sum_foreign_comment":"","sum_comment_hidden":false,"sum":"","sum_comment":"","sum_foreign":""},"61":{"sum_foreign_comment":"","sum":"","sum_comment":"","sum_foreign":""},"62":{"sum_foreign_comment":"","sum":"","sum_comment":"","sum_foreign":""},"63":{"sum_foreign_comment":"","sum":"","sum_comment":"","sum_foreign":""},"64":{"sum_foreign_comment":"","sum":"","sum_comment":"","sum_foreign":""}},"ft_src":"суддя апеляційного суду донецької області\nДонецька область\nЗагальний апеляційний суд\nВалентина\nБухштейн Павло Шулімович\nПодружжя\nМиколаївна\nНовосядла Валентина Миколаївна\nВалентина Миколаївна Новосядла\nВалентина Новосядла\nНовосядла Валентина Миколаївна\nНовосядла Валентина Миколаївна\nНовосядла\n39.8\n68.8\n272380\n125860\n2014\n2014\nНовосядла Валентина Миколаївна\nВалентина Миколаївна Новосядла\nВалентина Новосядла\nНовосядла Валентина Миколаївна\nНовосядла Валентина Миколаївна\nПодружжя\nБухштейн Павло Шулімович\nВалентина\nНовосядла\nЗагальний апеляційний суд\nДонецька область\nсуддя апеляційного суду донецької області\nМиколаївна\n246393\n265637\n5942\n5846\n5942\n13398\n39.8\n68.8\n125860\n272380\n246393\n5942\n5846\n13398\n5942\n265637\nБухштейн Павло Шулімович\nПодружжя\nМиколаївна\nНовосядла\nВалентина\nНовосядла Валентина Миколаївна\nВалентина Миколаївна Новосядла\nВалентина Новосядла\nНовосядла Валентина Миколаївна\nДонецька область\nЗагальний апеляційний суд\nсуддя апеляційного суду донецької області\nНовосядла Валентина Миколаївна\n5942\n5846\n13398\n5942\n265637\n246393\n39.8\n68.8\n125860\n272380\n2014","general":{"inn":"","name":"Валентина","patronymic_unclear":false,"family":[{"inn":"","inn_hidden":true,"relations_hidden":false,"family_name":"Бухштейн Павло Шулімович","relations_other":"","relations":"Подружжя","name_hidden":false,"name_unclear":true}],"patronymic":"Миколаївна","inn_hidden":true,"family_raw":"","inn_unclear":false,"post":{"post_unclear":false,"post":"суддя апеляційного суду донецької області","candidate":"","office_hidden":false,"region":"Донецька область","office":"Загальний апеляційний суд","office_unclear":false,"region_hidden":false},"full_name":"Новосядла Валентина Миколаївна","addresses":[{"place_district":"","place_unclear":false,"place_city":"","place_city_type_hidden":false,"place_district_hidden":false,"place_city_type":"","place_city_hidden":true,"place_address_hidden":false,"place_address":"","place_hidden":true,"place":""}],"last_name":"Новосядла","full_name_suggest":{"output":"Новосядла Валентина Миколаївна","input":["Новосядла Валентина Миколаївна","Валентина Миколаївна Новосядла","Валентина Новосядла"]}},"source":"VULYK","estate":{"31":[{"space_unclear":false,"address_hidden":true,"region_hidden":true,"space_comment":"","space_hidden":false,"space":"39.8","address":"","region":"","costs_property":"","costs_rent_comment":"","space_units":"м²","costs_property_comment":"","costs_rent":""},{"costs_rent":"","region":"","costs_property":"","costs_rent_comment":"","space_comment":"","costs_property_comment":"","space_units":"м²","space":"68.8","address":""}]},"intro":{"declaration_year":"2014","declaration_year_unclear":false}}