{"income":{"5":{"family_comment":"","family_unclear":false,"value":"368669","family":"183624","comment":""},"6":{"family_comment":"","value":"253137","value_unclear":false,"family":"183624","comment":""},"7":{"family_comment":"","value":"","source_name":"","family":"","comment":""},"8":{"family_comment":"","value":"","family":"","comment":""},"9":{"value":"","value_unclear":false,"family_hidden":false,"family_comment":"","comment_unclear":false,"comment":"","family":""},"10":{"family_comment":"","value":"","family":"","comment":""},"11":{"family_comment":"","value":"","family":"","comment":""},"12":{"family_comment":"","value":"","family":"","comment":""},"13":{"family_comment":"","value":"","family":"","comment":""},"14":{"family_comment":"","value":"","family":"","comment":""},"15":{"family_comment":"","value":"","family":"","comment":""},"16":{"family_comment":"","value":"115532","family":"","comment":""},"17":{"family_comment":"","value":"","family":"","comment":""},"18":{"family_comment":"","value":"","family":"","comment":""},"19":{"family_comment":"","value":"","family":"","comment":""},"20":{"value":"","value_unclear":false,"comment_hidden":false,"family_comment":"","family":"","comment":""}},"vehicle":{"35":[{"brand_info":"1984 куб. см.","sum_rent_comment":"довір","brand":"Audi A6","sum_comment":"","year":"1995","brand_info_hidden":false,"brand_info_unclear":false,"sum":"","sum_rent":""},{"brand_info":"1100 куб. см.","sum_rent_comment":"довір","brand":"ВАЗ 21011","sum_comment":"","year":"1982","sum":"","sum_rent":""}]},"id":"vulyk_40_7","banks":{"45":[{"sum_foreign_comment":"","sum_units":"UAH","sum_comment":"","sum_hidden":false,"sum_foreign_units":"UAH","sum":"3713","sum_foreign":""},{"sum_foreign_comment":"","sum_units":"","sum_comment":"","sum_foreign_units":"","sum":"","sum_foreign":""},{"sum_foreign_comment":"","sum_units":"","sum_comment":"","sum_foreign_units":"","sum":"","sum_foreign":""}],"46":[{"sum_foreign_comment":"","sum_units":"UAH","sum_comment":"","sum_foreign_units":"UAH","sum":"","sum_unclear":false,"sum_foreign":""}],"47":[{"sum_foreign_comment":"","sum_units":"UAH","sum_comment":"","sum_foreign_units":"UAH","sum":"","sum_foreign":""}],"48":[{"sum_foreign_comment":"","sum_units":"UAH","sum_comment":"","sum_foreign_units":"UAH","sum":"","sum_foreign":""}],"49":[{"sum_foreign_comment":"","sum_units":"UAH","sum_comment":"","sum_foreign_units":"UAH","sum":"","sum_foreign":""}],"50":[{"sum_foreign_comment":"","sum_units":"UAH","sum_comment":"","sum_foreign_units":"UAH","sum":"","sum_foreign":""}],"51":[{"sum_foreign_comment":"","sum_units":"UAH","sum_comment":"","sum_foreign_units":"UAH","sum":"","sum_foreign":""}],"52":[{"sum_foreign_comment":"","sum_units":"UAH","sum_comment":"","sum_foreign_units":"UAH","sum":"","sum_foreign":""}],"53":[{"sum_foreign_comment":"","sum_units":"UAH","sum_comment":"","sum_foreign_units":"UAH","sum":"","sum_foreign":""}]},"declaration":{"date":"2015-03-27T00:00:00","notfull":"","url":"http://static.declarations.com.ua/declarations/chosen_ones/mega_batch/osnach_serhii_vladylenovych.pdf","notfull_lostpages":""},"liabilities":{"54":{"sum_foreign_comment":"","sum":"","sum_comment":"","sum_foreign":""},"55":{"sum_foreign_comment":"","sum":"","sum_comment":"","sum_foreign":""},"56":{"sum_foreign_comment":"","sum":"","sum_comment":"","sum_foreign":""},"57":{"sum_foreign_comment":"","sum":"","sum_comment":"","sum_hidden":false,"sum_comment_hidden":false,"sum_foreign":""},"58":{"sum_foreign_comment":"","sum":"","sum_comment":"","sum_hidden":false,"sum_comment_hidden":false,"sum_foreign":""},"59":{"sum_foreign_comment":"","sum":"","sum_comment":"","sum_foreign":""},"60":{"sum_foreign_comment":"","sum":"","sum_comment":"","sum_foreign":""},"61":{"sum_foreign_comment":"","sum":"","sum_comment":"","sum_foreign":""},"62":{"sum_foreign_comment":"","sum":"","sum_comment":"","sum_foreign":""},"63":{"sum_foreign_comment":"","sum":"","sum_comment":"","sum_foreign":""},"64":{"sum_foreign_comment":"","sum":"","sum_comment":"","sum_foreign":""}},"ft_src":"Оснач Сергій Владиленович\nзаступник голови ямпільського районного суду\nСумська область\nЗагальний місцевий суд\nСергій\nОснач Ю. І\nПодружжя\nОснач А. С\nДитина\nОснач С. С\nДитина\nОснач Сергій Владиленович\nСергій Владиленович Оснач\nСергій Оснач\nОснач Сергій Владиленович\nОснач\nВладиленович\n1995\n1984 куб. см.\nAudi A6\nдовір\n1100 куб. см.\n1982\nВАЗ 21011\nдовір\n3713\n2014\n1984 куб. см.\nдовір\n1995\nAudi A6\n1100 куб. см.\nдовір\nВАЗ 21011\n1982\n3713\n200\n35\n43\n52\n59\n19\nОснач\nОснач Сергій Владиленович\nСергій Владиленович Оснач\nСергій Оснач\nОснач Сергій Владиленович\nСергій\nВладиленович\nОснач Сергій Владиленович\nЗагальний місцевий суд\nзаступник голови ямпільського районного суду\nСумська область\nПодружжя\nОснач Ю. І\nДитина\nОснач А. С\nОснач С. С\nДитина\n253137\n183624\n368669\n183624\n115532\n2014\n200\n35\n43\n52\n59\n19\nОснач Ю. І\nПодружжя\nОснач А. С\nДитина\nОснач С. С\nДитина\nВладиленович\nОснач\nзаступник голови ямпільського районного суду\nСумська область\nЗагальний місцевий суд\nОснач Сергій Владиленович\nОснач Сергій Владиленович\nСергій Владиленович Оснач\nСергій Оснач\nОснач Сергій Владиленович\nСергій\n183624\n253137\n183624\n368669\n115532\nдовір\n1995\n1984 куб. см.\nAudi A6\nдовір\nВАЗ 21011\n1100 куб. см.\n1982\n183624\n368669\n115532\n183624\n253137\n43\n52\n59\n200\n19\n35\n3713\n2014","general":{"inn":"","inn_hidden":true,"last_name":"Оснач","post":{"office":"Загальний місцевий суд","region":"Сумська область","post":"заступник голови ямпільського районного суду"},"name":"Сергій","full_name":"Оснач Сергій Владиленович","family_raw":"","addresses":[{"place_district":"","place_city_hidden":true,"place_city":"","place_city_type_hidden":true,"place_district_hidden":true,"place_city_type":"","place_address_hidden":true,"place_address":"","place_hidden":true,"place":""}],"family":[{"inn":"","relations":"Подружжя","relations_other":"","inn_hidden":true,"family_name":"Оснач Ю. І","name_hidden":true},{"inn":"","relations":"Дитина","relations_other":"","inn_hidden":false,"family_name":"Оснач А. С","name_unclear":false},{"inn":"","family_name":"Оснач С. С","relations":"Дитина","inn_hidden":false}],"full_name_suggest":{"output":"Оснач Сергій Владиленович","input":["Оснач Сергій Владиленович","Сергій Владиленович Оснач","Сергій Оснач"]},"patronymic":"Владиленович"},"source":"VULYK","estate":{"23":[{"costs_rent":"","region":"","costs":"","costs_rent_comment":"","costs_comment":"","address_hidden":true,"region_hidden":true,"space_comment":"","space_units":"м²","space":"200","address":""},{"costs_rent":"","region":"","costs":"","costs_rent_comment":"","costs_comment":"","space_comment":"","space_units":"","space":"","address":""},{"costs_rent":"","region":"","costs":"","costs_rent_comment":"","costs_comment":"","space_comment":"","space_units":"","space":"","address":""},{"costs_rent":"","costs":"","costs_rent_comment":"","costs_comment":"","space_comment":"","space_units":"","space":"","address":""}],"25":[{"costs_rent":"","region":"","costs":"","costs_rent_comment":"","costs_comment":"","address_hidden":true,"region_hidden":true,"space_comment":"","space_units":"м²","space":"19","address":""}],"27":[{"costs_rent":"","region":"","costs":"","costs_rent_comment":"","costs_comment":"","address_hidden":true,"region_hidden":true,"space_comment":"","space_units":"м²","space":"35","address":""}],"31":[{"space_hidden":false,"address_hidden":true,"region_hidden":true,"space_comment":"","space":"43","address":"","region":"","costs_property":"","costs_rent_comment":"","space_units":"м²","costs_property_comment":"","costs_rent":""},{"costs_rent":"","region":"","costs_property":"","costs_rent_comment":"","space_comment":"","costs_property_comment":"","space_units":"м²","space":"52","address":""},{"costs_rent":"","costs_property":"","costs_rent_comment":"","space_comment":"","costs_property_comment":"","space_units":"м²","space":"59","address":""}]},"intro":{"declaration_year":"2014"}}