{"id":"vulyk_109_23","ft_src":"3456 куб. см.\nToyota Highlander\n2013\n1798 куб. см.\n2010\nMitsubishi ASX\n1/2 спільної сумісної власності\n1098\n1/2 спільної сумісної власності\n1098\n1/2 спільної сумісної власності, незавершене будівництво\n172.9\nофісне приміщення нотар. контори\n115.9\n1/2 спільної сумісної власності, незавершене будівництво\n172.9\n833\n429\n2015\n3456 куб. см.\nToyota Highlander\n2013\n1798 куб. см.\n2010\nMitsubishi ASX\n2015\nПодружжя\nШум І. О\nШум Микола Сергійович\nМикола Сергійович Шум\nМикола Шум\nШум Микола Сергійович\nМикола\nШум Микола Сергійович\nШум\nГосподарський місцевий суд\nВолинська область\nголова господарського суду волинської області\nСергійович\nдві суми 9075 та 542. Погашення основної суми позики та процентів за позикою. Користування коштами зарплатної картки Універсальна\n9617\nдві суми 108102 та 608935. Погашення основної суми позики та процентів за позикою. Користування коштами зарплатної картки Універсальна\n717037\nФінансові зобов'язання членів сім'ї декларанта - зі слів члена сім'ї\n2268\n249256\n38331\nзалишки по зарплатній карті 'Універсальна'\n95\n754\n251619\n39087\nсумма одержаного доходу члена сім'ї-зі слів члена сім'ї\n1.6\n1098\n1/2 спільної сумісної власності\n1/2 спільної сумісної власності\n1098\n172.9\n1/2 спільної сумісної власності, незавершене будівництво\n172.9\n1/2 спільної сумісної власності, незавершене будівництво\n115.9\nофісне приміщення нотар. контори\n429\n833\nдві суми 9075 та 542. Погашення основної суми позики та процентів за позикою. Користування коштами зарплатної картки Універсальна\n9617\nдві суми 108102 та 608935. Погашення основної суми позики та процентів за позикою. Користування коштами зарплатної картки Універсальна\n717037\nФінансові зобов'язання членів сім'ї декларанта - зі слів члена сім'ї\n249256\n754\n2268\n39087\nсумма одержаного доходу члена сім'ї-зі слів члена сім'ї\n251619\n38331\n1.6\nзалишки по зарплатній карті 'Універсальна'\n95\nПодружжя\nШум І. О\nМикола\nСергійович\nШум\nШум Микола Сергійович\nМикола Сергійович Шум\nМикола Шум\nШум Микола Сергійович\nВолинська область\nГосподарський місцевий суд\nголова господарського суду волинської області\nШум Микола Сергійович","estate":{"23":[{"address":"","space_units":"м²","costs_rent_unclear":false,"costs_comment":"","space_unclear":false,"region_hidden":true,"space_comment":"1/2 спільної сумісної власності","address_hidden":false,"costs":"","costs_rent_comment":"","space":"1098","region":"","costs_rent":""}],"24":[{"costs":"","address":"","space_units":"м²","costs_rent_comment":"","space":"172.9","space_comment":"1/2 спільної сумісної власності, незавершене будівництво","region_hidden":false,"costs_comment":"","region":"","address_hidden":false,"costs_rent":""}],"29":[{"costs_property_comment":"","address":"","space_units":"м²","space_unclear":false,"region_hidden":false,"costs_property":"","space_comment":"1/2 спільної сумісної власності","address_hidden":true,"costs_rent_comment":"","space":"1098","region":"","costs_rent":""}],"30":[{"costs_property_comment":"","address":"","space_units":"м²","costs_rent_comment":"","space_hidden":false,"region_hidden":false,"costs_property":"","space_comment":"1/2 спільної сумісної власності, незавершене будівництво","space":"172.9","address_hidden":true,"costs_rent":""}],"34":[{"costs_property_comment":"","address":"","space_units":"м²","costs_rent_comment":"","space":"115.9","region_hidden":false,"costs_property":"","space_comment":"офісне приміщення нотар. контори","address_hidden":true,"costs_rent":""}]},"vehicle":{"35":[{"sum_comment_unclear":false,"brand_info":"3456 куб. см.","sum_rent_comment":"","brand_unclear":false,"brand_hidden":false,"year":"2013","sum_comment":"","brand_info_hidden":false,"sum_rent":"","brand":"Toyota Highlander","year_unclear":false,"brand_info_unclear":false,"sum":""}],"40":[{"sum_comment":"","brand_info":"1798 куб. см.","sum":"","sum_rent_comment":"","year":"2010","brand":"Mitsubishi ASX","sum_rent":"","brand_info_unclear":false}]},"source":"VULYK","income":{"5":{"family_comment":"сумма одержаного доходу члена сім'ї-зі слів члена сім'ї","value":"251619","family":"39087","comment":""},"6":{"family_comment":"","value":"249256","family":"","comment":""},"7":{"source_name_hidden":false,"family_comment":"","comment":"","family":"","comment_hidden":false,"value":"2268","source_name":""},"8":{"family_comment":"","family_hidden":false,"value":"","family":"","comment":""},"9":{"family_comment":"","family":"1.6","comment":"","value_unclear":false,"family_unclear":false,"value":""},"10":{"family_comment":"","value":"","family":"","comment":""},"11":{"family_comment":"","value":"","family":"","comment":""},"12":{"family_comment":"","value":"","family":"","comment":""},"13":{"family_comment":"","value":"","family":"","comment":""},"14":{"family_comment":"","value":"","family":"","comment":""},"15":{"family_comment":"","value":"","family":"754","comment":""},"16":{"family_comment":"","value":"","family":"","comment":""},"17":{"family_comment":"","value":"","family":"38331","comment":""},"18":{"family_comment":"","value":"","family":"","comment":""},"19":{"family_comment":"","value":"","family":"","comment":""},"20":{"family_comment":"","family":"","comment":"залишки по зарплатній карті 'Універсальна'","value_unclear":false,"family_hidden":false,"value":"95"}},"banks":{"45":[{"sum_units":"UAH","sum_comment":"","sum_foreign_units":"UAH","sum":"429","sum_units_hidden":false,"sum_foreign_comment":"","sum_foreign":"","sum_unclear":false,"sum_comment_hidden":false}],"51":[{"sum_units":"UAH","sum_comment":"","sum_foreign_units":"UAH","sum":"833","sum_units_hidden":false,"sum_foreign_comment":"","sum_foreign":"","sum_unclear":false,"sum_comment_hidden":false}]},"declaration":{"notfull_lostpages":"","additional_info_text":"","additional_info":"","date":"2016-03-31T00:00:00","notfull":"","url":"http://static.declarations.com.ua/declarations/chosen_ones/judges_batch/2480_shum_mykola_serhiiovych_2015.pdf"},"general":{"family_raw":"","name":"Микола","full_name_suggest":{"input":["Шум Микола Сергійович","Микола Сергійович Шум","Микола Шум"],"output":"Шум Микола Сергійович"},"patronymic":"Сергійович","inn_hidden":true,"inn":"","inn_unclear":false,"last_name":"Шум","full_name":"Шум Микола Сергійович","family":[{"inn":"","family_name":"Шум І. О","relations_hidden":false,"name_unclear":false,"relations":"Подружжя","inn_hidden":true,"name_hidden":false,"relations_other":""}],"post":{"office":"Господарський місцевий суд","post":"голова господарського суду волинської області","office_unclear":false,"region_hidden":false,"region":"Волинська область","office_hidden":false,"region_unclear":false},"name_hidden":false},"liabilities":{"54":{"sum_comment":"","sum_hidden":false,"sum":"","sum_foreign_comment":"","sum_foreign":"","sum_unclear":false,"sum_comment_hidden":false},"55":{"sum_comment":"","sum_comment_unclear":false,"sum_foreign_comment":"","sum":"","sum_foreign":""},"56":{"sum_comment":"","sum_foreign_comment":"","sum_foreign":"","sum":""},"57":{"sum_comment":"дві суми 108102 та 608935. Погашення основної суми позики та процентів за позикою. Користування коштами зарплатної картки Універсальна","sum_foreign_comment":"","sum_foreign":"","sum":"717037","sum_comment_hidden":false},"58":{"sum_comment":"дві суми 9075 та 542. Погашення основної суми позики та процентів за позикою. Користування коштами зарплатної картки Універсальна","sum_foreign_comment":"","sum_foreign":"","sum":"9617","sum_comment_hidden":false},"59":{"sum_comment":"","sum_foreign_comment":"","sum_foreign":"","sum":""},"60":{"sum_comment":"Фінансові зобов'язання членів сім'ї декларанта - зі слів члена сім'ї","sum_foreign_comment":"","sum_foreign":"","sum":""},"61":{"sum_comment":"","sum_foreign_comment":"","sum_foreign":"","sum":""},"62":{"sum_comment":"","sum_foreign_comment":"","sum_foreign":"","sum":""},"63":{"sum_comment":"","sum_foreign_comment":"","sum_foreign":"","sum":""},"64":{"sum_comment":"","sum_foreign_comment":"","sum_foreign":"","sum":""}},"intro":{"isnotdeclaration":"","declaration_year":"2015"}}