{"income":{"5":{"value":"250655","family_comment":"","value_unclear":false,"family_unclear":false,"family":"101480","comment":""},"6":{"value":"226766","family_comment":"","value_unclear":false,"family_unclear":false,"family":"94476","comment":""},"7":{"family_comment":"","value":"","source_name":"","family":"","comment":""},"8":{"family_comment":"","value":"","family":"","comment":""},"9":{"family_comment":"","value":"","family":"1478","comment":""},"10":{"family_comment":"","value":"12180","family":"","comment":""},"11":{"family_comment":"","value":"","family":"","comment":""},"12":{"family_comment":"","value":"","family":"","comment":""},"13":{"family_comment":"","value":"","family":"","comment":""},"14":{"family_comment":"","value":"","family":"","comment":""},"15":{"family_comment":"","value":"11709","value_unclear":false,"family":"2226","comment":""},"16":{"family_comment":"","value":"","family":"","comment":""},"17":{"family_comment":"","value":"","family":"","comment":""},"18":{"family_comment":"","value":"","family":"","comment":""},"19":{"family_comment":"","value":"","family":"","comment":""},"20":{"value":"","family_comment":"","value_unclear":false,"family_unclear":false,"family":"3300","comment":"","family_comment_unclear":false}},"vehicle":{"35":[{"brand_info":"1.8 дм3","sum_rent_comment":"","brand":"Volkswagen","sum_comment":"","brand_unclear":false,"year":"1998","brand_info_unclear":false,"sum":"","sum_rent":""}],"40":[{"brand_info":"1.6 дм3","sum":"","brand":"Suzuki SX4","sum_comment":"","brand_unclear":false,"year":"2014","brand_info_hidden":false,"brand_info_unclear":false,"sum_rent_comment":"","sum_rent":""}]},"id":"vulyk_99_27","banks":{"51":[{"sum_foreign_comment":"","sum_units":"UAH","sum_comment":"","sum_comment_unclear":false,"sum_foreign_units":"UAH","sum_comment_hidden":false,"sum":"14463","sum_foreign":""}]},"declaration":{"date":"2016-03-28T00:00:00","notfull":"","url":"http://static.declarations.com.ua/declarations/chosen_ones/judges_batch/576_voievidko_iaroslav_ivanovych_2015.pdf","notfull_lostpages":""},"liabilities":{"54":{"sum_foreign_comment":"","sum":"","sum_comment":"","sum_comment_unclear":false,"sum_comment_hidden":false,"sum_foreign":""},"55":{"sum_foreign_comment":"","sum":"","sum_comment":"","sum_foreign":""},"56":{"sum_foreign_comment":"","sum":"","sum_comment":"","sum_foreign":""},"57":{"sum_foreign_comment":"","sum_comment_hidden":false,"sum":"","sum_comment":"","sum_foreign":""},"58":{"sum_foreign_comment":"","sum_comment_hidden":false,"sum":"","sum_comment":"","sum_foreign":""},"59":{"sum_foreign_comment":"","sum":"","sum_comment":"","sum_comment_hidden":false,"sum_unclear":false,"sum_foreign":""},"60":{"sum_foreign_comment":"","sum_comment_hidden":false,"sum":"12500","sum_comment":"","sum_foreign":""},"61":{"sum_foreign_comment":"","sum":"","sum_comment":"","sum_foreign":""},"62":{"sum_foreign_comment":"","sum":"","sum_comment":"","sum_foreign":""},"63":{"sum_foreign_comment":"","sum_comment_hidden":false,"sum":"","sum_comment":"","sum_foreign":""},"64":{"sum_foreign_comment":"","sum_comment_hidden":false,"sum":"","sum_comment":"","sum_foreign":""}},"ft_src":"12500\nВоєвідко Ярослав Іванович\nсуддя кам'янець-подільського міськрайонного суду хмельницької області\nХмельницька область\nЗагальний місцевий суд\nЯрослав\nВоєвідко А. М\nПодружжя\nВоєвідко Я. Я\nДитина\nВоєвідко Ярослав Іванович\nЯрослав Іванович Воєвідко\nЯрослав Воєвідко\nВоєвідко Ярослав Іванович\nВоєвідко\nІванович\n1998\nVolkswagen\n1.8 дм3\n1.6 дм3\nSuzuki SX4\n2014\n14463\n2015\n1.8 дм3\nVolkswagen\n1998\n1.6 дм3\n2014\nSuzuki SX4\n14463\n873\n56\nВказано: приблизно\n300\n56\nВоєвідко\nВоєвідко Ярослав Іванович\nЯрослав Іванович Воєвідко\nЯрослав Воєвідко\nВоєвідко Ярослав Іванович\nЯрослав\nІванович\nВоєвідко Ярослав Іванович\nЗагальний місцевий суд\nсуддя кам'янець-подільського міськрайонного суду хмельницької області\nХмельницька область\nПодружжя\nВоєвідко А. М\nДитина\nВоєвідко Я. Я\n12500\n226766\n94476\n3300\n11709\n2226\n250655\n101480\n1478\n12180\n2015\n12500\n873\n56\nВказано: приблизно\n300\n56\nВоєвідко А. М\nПодружжя\nВоєвідко Я. Я\nДитина\nІванович\nВоєвідко\nсуддя кам'янець-подільського міськрайонного суду хмельницької області\nХмельницька область\nЗагальний місцевий суд\nВоєвідко Ярослав Іванович\nВоєвідко Ярослав Іванович\nЯрослав Іванович Воєвідко\nЯрослав Воєвідко\nВоєвідко Ярослав Іванович\nЯрослав\n94476\n226766\n2226\n11709\n1478\n12180\n101480\n250655\n3300\n1998\n1.8 дм3\nVolkswagen\nSuzuki SX4\n1.6 дм3\n2014\n2226\n11709\n1478\n12180\n3300\n250655\n101480\n226766\n94476\n56\n56\nВказано: приблизно\n300\n873\n14463\n2015","general":{"inn":"","inn_hidden":true,"last_name":"Воєвідко","post":{"post_unclear":true,"office":"Загальний місцевий суд","post":"суддя кам'янець-подільського міськрайонного суду хмельницької області","region":"Хмельницька область"},"name":"Ярослав","full_name":"Воєвідко Ярослав Іванович","family_raw":"","addresses":[{"place_district":"","place_city_hidden":true,"place_city":"","place_city_type_hidden":false,"place_district_hidden":false,"place_city_type":"","place_address_hidden":true,"place_address":"","place_hidden":true,"place":""}],"family":[{"inn_hidden":true,"inn":"","name_hidden":true,"family_name":"Воєвідко А. М","relations":"Подружжя","name_unclear":true},{"inn":"","relations":"Дитина","relations_other":"","inn_hidden":true,"family_name":"Воєвідко Я. Я","name_unclear":true}],"full_name_suggest":{"output":"Воєвідко Ярослав Іванович","input":["Воєвідко Ярослав Іванович","Ярослав Іванович Воєвідко","Ярослав Воєвідко"]},"patronymic":"Іванович"},"source":"VULYK","estate":{"25":[{"space_hidden":false,"costs":"","costs_comment":"","address_hidden":false,"region_hidden":true,"space_comment":"","space_unclear":false,"space":"56","address":"","region":"","costs_rent_comment":"","space_units":"м²","costs_rent":""}],"29":[{"costs_rent":"","region":"","costs_property":"","costs_rent_comment":"","address_hidden":false,"region_hidden":true,"space_comment":"","costs_property_comment":"","space_units":"м²","space":"873","address":""}],"31":[{"costs_rent":"","region":"","costs_property":"","costs_rent_comment":"","address_hidden":false,"region_hidden":true,"space_comment":"","costs_property_comment":"","space_units":"м²","space":"56","address":""}],"34":[{"space_unclear":false,"address_hidden":false,"region_hidden":true,"space_comment":"Вказано: приблизно","space_hidden":false,"space":"300","address":"","region":"","costs_property":"","costs_rent_comment":"","space_units":"м²","costs_property_comment":"","costs_rent":""}]},"intro":{"declaration_year":"2015"}}