{"id":"vulyk_100_29","ft_src":"1798 куб. см., 89 кВт\nChevrolet Lacetti\n2008\n100000\nПриватбанк\n11431\n2014\n49094\n181537\n49094\n197273\n31\nкредити ПАТ Укрссибанк, ПАТ КБ Приватбанк\n15705\n1798 куб. см., 89 кВт\nChevrolet Lacetti\n2008\n100000\nПриватбанк\n11431\n2014\nПодружжя\nДіденко Т. Ю. 05. 04. 1993\nВолодимирович\nДіденко\nДіденко Євген Володимирович\nЄвген Володимирович Діденко\nЄвген Діденко\nДіденко Євген Володимирович\nДіденко Євген Володимирович\nЄвген\nЗагальний місцевий суд\nЗапорізька область\nсуддя приазовського районного суду запорізької області\n10706 Приватбанк, 1200 Укрсиббанк\n11906\n467\nПриватбанк\n181537\n49094\n15705\nкредити ПАТ Укрссибанк, ПАТ КБ Приватбанк\n197273\n49094\n31\nПриватбанк\n467\n10706 Приватбанк, 1200 Укрсиббанк\n11906\nДіденко Т. Ю. 05. 04. 1993\nПодружжя\nВолодимирович\nДіденко\nЗапорізька область\nЗагальний місцевий суд\nсуддя приазовського районного суду запорізької області\nДіденко Євген Володимирович\nДіденко Євген Володимирович\nЄвген Володимирович Діденко\nЄвген Діденко\nДіденко Євген Володимирович\nЄвген","vehicle":{"35":[{"brand_info":"1798 куб. см., 89 кВт","sum_rent_comment":"","brand_unclear":false,"sum_rent_comment_unclear":false,"brand_hidden":false,"sum_comment":"","brand_info_hidden":false,"sum_rent":"","brand":"Chevrolet Lacetti","brand_info_unclear":false,"year":"2008","sum":"100000"}]},"source":"VULYK","income":{"5":{"family_comment":"","family":"49094","comment":"","value_unclear":false,"family_unclear":false,"value":"197273"},"6":{"family_comment":"","value":"181537","family":"49094","comment":"","value_unclear":false},"7":{"family_comment":"","comment":"","family":"","value_unclear":false,"value":"","source_name":""},"8":{"family_comment":"","value":"","family":"","comment":""},"9":{"family_comment":"","family":"","comment":"","value_unclear":false,"family_unclear":false,"value":"31"},"10":{"family_comment":"","comment_unclear":false,"value":"","family":"","comment":""},"11":{"family_comment":"","value":"","family":"","comment":""},"12":{"family_comment":"","value":"","family":"","comment":""},"13":{"family_comment":"","value":"","family":"","comment":"","value_unclear":false},"14":{"family_comment":"","value":"","family":"","comment":""},"15":{"family_comment":"","value":"","family":"","comment":""},"16":{"family_comment":"","value":"","family_unclear":false,"family":"","comment":""},"17":{"family_comment":"","value":"","family_unclear":false,"family":"","comment":""},"18":{"family_comment":"","value":"","family":"","comment":""},"19":{"family_comment":"","value":"","family":"","comment":""},"20":{"family":"","family_comment":"","comment":"кредити ПАТ Укрссибанк, ПАТ КБ Приватбанк","value_hidden":false,"value_unclear":false,"value":"15705","comment_unclear":true,"family_unclear":false,"family_hidden":false}},"banks":{"45":[{"sum_comment_unclear":false,"sum_units":"UAH","sum_foreign_comment":"","sum_foreign_units":"UAH","sum":"11431","sum_comment":"Приватбанк","sum_foreign":"","sum_unclear":false,"sum_units_unclear":false,"sum_comment_hidden":false}]},"declaration":{"notfull_lostpages":"","additional_info_text":"","additional_info":"","date":"2015-03-30T00:00:00","notfull":"","url":"http://static.declarations.com.ua/declarations/chosen_ones/judges_batch/4156_didenko_ievhen_volodymyrovych.pdf"},"general":{"inn":"","addresses":[{"place_city_type":"","place_city_type_hidden":true,"place_hidden":true,"place_city_hidden":true,"place_district_hidden":true,"place_district":"","place_city_unclear":false,"place":"","place_city":"","place_address_hidden":true,"place_address":""}],"last_name":"Діденко","full_name":"Діденко Євген Володимирович","family":[{"inn":"","family_name":"Діденко Т. Ю. 05. 04. 1993","name_unclear":false,"inn_hidden":true,"name_hidden":false,"relations":"Подружжя"}],"patronymic":"Володимирович","inn_hidden":true,"name":"Євген","post":{"post_hidden":false,"office":"Загальний місцевий суд","post":"суддя приазовського районного суду запорізької області","office_unclear":false,"region_unclear":false,"region":"Запорізька область","post_unclear":false},"family_raw":"","full_name_suggest":{"input":["Діденко Євген Володимирович","Євген Володимирович Діденко","Євген Діденко"],"output":"Діденко Євген Володимирович"}},"liabilities":{"54":{"sum_comment":"","sum":"","sum_foreign_comment":"","sum_foreign":"","sum_unclear":false,"sum_comment_hidden":false},"55":{"sum_comment":"","sum_foreign_comment":"","sum_foreign":"","sum":""},"56":{"sum_comment":"","sum_foreign_comment":"","sum_foreign":"","sum_unclear":false,"sum":""},"57":{"sum_comment_unclear":true,"sum_comment":"10706 Приватбанк, 1200 Укрсиббанк","sum":"11906","sum_foreign_comment":"","sum_foreign":"","sum_unclear":true,"sum_comment_hidden":false},"58":{"sum_comment":"Приватбанк","sum":"467","sum_foreign_comment":"","sum_foreign":"","sum_unclear":false,"sum_comment_hidden":false},"59":{"sum_comment":"","sum_foreign_comment":"","sum_foreign":"","sum":""},"60":{"sum_comment":"","sum_foreign_comment":"","sum_foreign":"","sum":"","sum_comment_hidden":false},"61":{"sum_comment":"","sum_foreign_comment":"","sum_foreign":"","sum":""},"62":{"sum_comment":"","sum_foreign_comment":"","sum_foreign":"","sum_unclear":false,"sum":""},"63":{"sum_comment":"","sum_foreign_comment":"","sum_foreign":"","sum":"","sum_comment_hidden":false},"64":{"sum_comment":"","sum_foreign_comment":"","sum_foreign":"","sum":"","sum_comment_hidden":false}},"intro":{"declaration_year":"2014"}}