{"income":{"5":{"value":"340607","value_unclear":false,"family_hidden":false,"family_comment":"","family":"","comment":""},"6":{"family_comment":"","value":"300261","family":"","comment":""},"7":{"family_comment":"","value":"21545","source_name":"Київська державна академія водного транспорту ім. гетьмана П. Конашевича-Сагайдачного","family":"","comment":""},"8":{"family_comment":"","value":"","family":"","comment":""},"9":{"family_comment":"","value":"18801","family":"","comment":""},"10":{"family_comment":"","value":"","family":"","comment":""},"11":{"family_comment":"","value":"","family_hidden":false,"comment":"","family":""},"12":{"family_comment":"","value":"","family":"","comment":""},"13":{"family_comment":"","value":"","family":"","comment":""},"14":{"family_comment":"","value":"","family":"","comment":""},"15":{"family_comment":"","value":"","family":"","comment":""},"16":{"family_comment":"","value":"","family":"","comment":""},"17":{"family_comment":"","value":"","family":"","comment":"","family_comment_unclear":false},"18":{"family_comment":"","value":"","family":"","comment":""},"19":{"family_comment":"","value":"","family":"","comment":""},"20":{"value":"","family_unclear":false,"family_hidden":false,"family_comment":"","family":"","comment":""}},"id":"vulyk_103_116","banks":{"45":[{"sum_foreign_comment":"","sum_units":"UAH","sum_comment":"","sum_hidden":false,"sum_foreign_units":"UAH","sum_comment_hidden":true,"sum_unclear":false,"sum":"555","sum_foreign":""}]},"declaration":{"date":"2016-03-15T00:00:00","additional_info_text":"","additional_info":"","url":"http://static.declarations.com.ua/declarations/chosen_ones/judges_batch/1071_shaptala_natalia_kostiantynivna.pdf"},"liabilities":{"54":{"sum_foreign_comment":"","sum_foreign_hidden":false,"sum_comment":"","sum_foreign_comment_hidden":false,"sum_hidden":false,"sum_foreign_comment_unclear":false,"sum_comment_hidden":false,"sum_unclear":false,"sum":"","sum_foreign":""},"55":{"sum_foreign_comment":"","sum":"","sum_comment":"","sum_foreign":""},"56":{"sum_foreign_comment":"","sum":"","sum_comment":"","sum_foreign":""},"57":{"sum_foreign_comment":"","sum_foreign_hidden":false,"sum_comment":"","sum_foreign_comment_hidden":false,"sum_hidden":false,"sum_comment_hidden":false,"sum":"","sum_foreign":""},"58":{"sum_foreign_comment":"","sum_foreign_hidden":false,"sum_comment":"","sum_foreign_comment_hidden":false,"sum_hidden":false,"sum_comment_hidden":false,"sum":"","sum_foreign":""},"59":{"sum_foreign_comment":"","sum_foreign_hidden":false,"sum_comment":"","sum_foreign_comment_hidden":false,"sum_hidden":false,"sum_comment_hidden":false,"sum":"","sum_foreign":""},"60":{"sum_foreign_comment":"","sum":"","sum_comment":"","sum_hidden":false,"sum_comment_hidden":false,"sum_foreign":""},"61":{"sum_foreign_comment":"","sum":"","sum_comment":"","sum_foreign":""},"62":{"sum_foreign_comment":"","sum_comment_hidden":false,"sum":"","sum_comment":"","sum_foreign":""},"63":{"sum_foreign_comment":"","sum":"","sum_comment":"","sum_foreign":""},"64":{"sum_foreign_comment":"","sum":"","sum_comment":"","sum_foreign":""}},"ft_src":"Шаптала Наталя Костянтинівна\nсуддя конституційного суду україни\nЗагальнодержавний регіон\nКонституційний Cуд\nНаталя\nШаптала Наталя Костянтинівна\nНаталя Костянтинівна Шаптала\nНаталя Шаптала\nШаптала Наталя Костянтинівна\nШаптала\nКостянтинівна\n1/2 частина складає 49,0 кв. м\n98\n555\n2015\n98\n1/2 частина складає 49,0 кв. м\nШаптала Наталя Костянтинівна\nНаталя Костянтинівна Шаптала\nНаталя Шаптала\nШаптала Наталя Костянтинівна\nШаптала Наталя Костянтинівна\nКостянтинівна\nНаталя\nШаптала\nКонституційний Cуд\nсуддя конституційного суду україни\nЗагальнодержавний регіон\nКиївська державна академія водного транспорту ім. гетьмана П. Конашевича-Сагайдачного\n21545\n300261\n340607\n18801\n555\n2015\n300261\n18801\n21545\nКиївська державна академія водного транспорту ім. гетьмана П. Конашевича-Сагайдачного\n340607\nШаптала\nКостянтинівна\nсуддя конституційного суду україни\nКонституційний Cуд\nЗагальнодержавний регіон\nШаптала Наталя Костянтинівна\nШаптала Наталя Костянтинівна\nНаталя Костянтинівна Шаптала\nНаталя Шаптала\nШаптала Наталя Костянтинівна\nНаталя\n18801\n340607\nКиївська державна академія водного транспорту ім. гетьмана П. Конашевича-Сагайдачного\n21545\n300261\n1/2 частина складає 49,0 кв. м\n98\n555\n2015","general":{"inn":"","inn_hidden":true,"last_name":"Шаптала","post":{"region":"Загальнодержавний регіон","region_unclear":false,"post":"суддя конституційного суду україни","office_unclear":false,"office":"Конституційний Cуд"},"name":"Наталя","full_name":"Шаптала Наталя Костянтинівна","family_raw":"","addresses":[{"place_district":"","place_city_hidden":true,"place_city":"","place_city_type_hidden":false,"place_district_hidden":false,"place_city_type":"","place_address_hidden":true,"place_address":"","place_hidden":true,"place":""}],"full_name_suggest":{"output":"Шаптала Наталя Костянтинівна","input":["Шаптала Наталя Костянтинівна","Наталя Костянтинівна Шаптала","Наталя Шаптала"]},"patronymic":"Костянтинівна"},"source":"VULYK","estate":{"25":[{"costs":"","costs_comment":"","address_hidden":false,"region_hidden":true,"space_comment":"1/2 частина складає 49,0 кв. м","space":"98","address":"","region":"","costs_rent_comment":"","space_comment_unclear":false,"space_comment_hidden":false,"space_units":"м²","costs_rent":""}]},"intro":{"declaration_year":"2015"}}