{"income":{"5":{"value":"208908.5","family_comment":"","value_unclear":false,"family_unclear":false,"family":"49713.33","comment":""},"6":{"family_comment":"","value":"196728.5","value_unclear":false,"family":"46943.33","comment":""},"7":{"value":"","value_unclear":false,"family_comment":"","source_name":"","family":"","comment":""},"8":{"family_comment":"","value":"","family":"","comment":""},"9":{"value":"","family_comment":"","value_unclear":false,"family_unclear":false,"family":"","comment":""},"10":{"family_comment":"","value":"12180","comment_unclear":false,"family":"2770","comment":""},"11":{"family_comment":"","value":"","family":"","comment":""},"12":{"family_comment":"","value":"","family":"","comment":""},"13":{"family_comment":"","value":"","value_unclear":false,"family":"","comment":""},"14":{"family_comment":"","value":"","family":"","comment":""},"15":{"family_comment":"","value":"","family":"","comment":""},"16":{"family_comment":"","family_unclear":false,"value":"","family":"","comment":""},"17":{"family_comment":"","family_unclear":false,"value":"","family":"","comment":""},"18":{"family_comment":"","value":"","family":"","comment":""},"19":{"family_comment":"","value":"","family":"","comment":""},"20":{"value":"","family_comment":"","value_unclear":false,"family_hidden":false,"value_hidden":false,"family_unclear":false,"comment_unclear":false,"comment":"","family":""}},"vehicle":{"35":[{"brand_info":"4700","sum_rent_comment":"","brand_info_unclear":false,"year":"2001","brand_info_hidden":false,"sum_rent_comment_unclear":false,"sum_rent":"","sum":"","brand":"Toyota Land Cruiser 100","sum_comment":"","brand_unclear":false,"brand_hidden":false}],"39":[{"brand_info":"мопед, 49","sum":"","brand":"Yamaha Aprio","sum_comment":"","brand_unclear":false,"year":"1993","brand_hidden":false,"sum_rent_comment":"","sum_rent":""}],"40":[{"brand_info":"2000","sum_rent_comment":"","brand":"Toyota Rav 4","sum_comment":"","year":"2002","brand_info_hidden":false,"brand_info_unclear":false,"sum":"","sum_rent":""}]},"id":"vulyk_100_70","declaration":{"additional_info_text":"","notfull_lostpages":"","date":"2015-02-17T00:00:00","notfull":"","additional_info":"","url":"http://static.declarations.com.ua/declarations/chosen_ones/judges_batch/4269_kovalenko_konstiantyn_viktorovych.pdf"},"liabilities":{"54":{"sum_foreign_comment":"","sum":"","sum_comment":"","sum_comment_hidden":false,"sum_unclear":false,"sum_foreign":""},"55":{"sum_foreign_comment":"","sum":"","sum_comment":"","sum_foreign":""},"56":{"sum_foreign_comment":"","sum":"","sum_comment":"","sum_unclear":false,"sum_foreign":""},"57":{"sum_foreign_comment":"","sum":"","sum_comment":"","sum_comment_unclear":false,"sum_comment_hidden":false,"sum_unclear":false,"sum_foreign":""},"58":{"sum_foreign_comment":"","sum":"","sum_comment":"","sum_comment_hidden":false,"sum_unclear":false,"sum_foreign":""},"59":{"sum_foreign_comment":"","sum":"","sum_comment":"","sum_foreign":""},"60":{"sum_foreign_comment":"","sum_comment_hidden":false,"sum":"","sum_comment":"","sum_foreign":""},"61":{"sum_foreign_comment":"","sum":"","sum_comment":"","sum_foreign":""},"62":{"sum_foreign_comment":"","sum":"","sum_comment":"","sum_unclear":false,"sum_foreign":""},"63":{"sum_foreign_comment":"","sum_comment_hidden":false,"sum":"","sum_comment":"","sum_foreign":""},"64":{"sum_foreign_comment":"","sum_comment_hidden":false,"sum":"","sum_comment":"","sum_foreign":""}},"ft_src":"Коваленко Костянтин Вікторович\nсуддя баришівського районного суду київської області\nКиївська область\nЗагальний місцевий суд\nКостянтин\nКоваленко О. В. 27. 04. 1971\nПодружжя\nКоваленко Д. К. 02. 01. 1990\nДитина\nКоваленко Костянтин Вікторович\nКостянтин Вікторович Коваленко\nКостянтин Коваленко\nКоваленко Костянтин Вікторович\nКоваленко\nВікторович\nYamaha Aprio\nмопед, 49\n1993\n4700\nToyota Land Cruiser 100\n2001\n2002\n2000\nToyota Rav 4\n.029\n51\n109\n107\n2014\n46943.33\n196728.5\n2770\n12180\n49713.33\n208908.5\n4700\nToyota Land Cruiser 100\n2001\nToyota Rav 4\n2000\n2002\nмопед, 49\n1993\nYamaha Aprio\n.029\n109\n51\n107\nПодружжя\nКоваленко О. В. 27. 04. 1971\nДитина\nКоваленко Д. К. 02. 01. 1990\nВікторович\nКоваленко\nКоваленко Костянтин Вікторович\nКостянтин Вікторович Коваленко\nКостянтин Коваленко\nКоваленко Костянтин Вікторович\nКоваленко Костянтин Вікторович\nКостянтин\nЗагальний місцевий суд\nКиївська область\nсуддя баришівського районного суду київської області\n196728.5\n46943.33\n208908.5\n49713.33\n12180\n2770\n2014\nКоваленко О. В. 27. 04. 1971\nПодружжя\nДитина\nКоваленко Д. К. 02. 01. 1990\nВікторович\nКоваленко\nКиївська область\nЗагальний місцевий суд\nсуддя баришівського районного суду київської області\nКоваленко Костянтин Вікторович\nКоваленко Костянтин Вікторович\nКостянтин Вікторович Коваленко\nКостянтин Коваленко\nКоваленко Костянтин Вікторович\nКостянтин\nYamaha Aprio\nмопед, 49\n1993\n2001\nToyota Land Cruiser 100\n4700\n2002\n2000\nToyota Rav 4\n2770\n12180\n208908.5\n49713.33\n46943.33\n196728.5\n.029\n109\n107\n51\n2014","general":{"inn":"","inn_hidden":true,"last_name":"Коваленко","post":{"post_unclear":false,"region_unclear":false,"post":"суддя баришівського районного суду київської області","office":"Загальний місцевий суд","region":"Київська область","post_hidden":false,"office_unclear":false},"name":"Костянтин","full_name":"Коваленко Костянтин Вікторович","family_raw":"","addresses":[{"place_district":"","place_city_hidden":true,"place_city":"","place_city_unclear":false,"place_district_hidden":true,"place_city_type":"","place_address_hidden":true,"place_city_type_hidden":false,"place_address":"","place_hidden":true,"place":""}],"family":[{"inn_hidden":true,"inn":"","name_hidden":false,"family_name":"Коваленко О. В. 27. 04. 1971","relations":"Подружжя","name_unclear":false},{"inn":"","relations":"Дитина","relations_other":"","inn_hidden":false,"family_name":"Коваленко Д. К. 02. 01. 1990","name_hidden":false,"name_unclear":false}],"full_name_suggest":{"output":"Коваленко Костянтин Вікторович","input":["Коваленко Костянтин Вікторович","Костянтин Вікторович Коваленко","Костянтин Коваленко"]},"patronymic":"Вікторович"},"source":"VULYK","estate":{"23":[{"space_unclear":false,"costs":"","costs_comment":"","address_hidden":true,"region_hidden":true,"space_comment":"","space":".029","address":"","costs_comment_unclear":false,"region":"","address_unclear":false,"costs_rent_comment":"","space_comment_unclear":false,"space_units":"га","costs_rent":""}],"24":[{"space_unclear":false,"costs":"","costs_comment":"","address_hidden":true,"region_hidden":true,"space_comment":"","space":"109","address":"","region":"","costs_rent_comment":"","space_comment_unclear":false,"space_units":"м²","costs_rent":""}],"27":[{"space_unclear":false,"costs":"","costs_comment":"","address_hidden":true,"region_hidden":true,"space_comment":"","space":"51","address":"","region":"","address_unclear":false,"costs_rent_comment":"","space_units":"м²","costs_rent":""}],"28":[{"costs_rent":"","region":"","costs":"","costs_rent_comment":"","costs_comment":"","address_hidden":true,"region_hidden":true,"space_comment":"","space_units":"м²","space":"107","address":""}]},"intro":{"declaration_year":"2014"}}