{"income":{"5":{"value":"564088","value_unclear":false,"family_hidden":false,"family_comment":"","family":"46320","comment":""},"6":{"family_comment":"","value":"298588","family":"","comment":""},"7":{"family_comment":"","value":"","source_name":"","family":"","comment":""},"8":{"family_comment":"","value":"","family":"","comment":""},"9":{"family_comment":"","value":"","family":"","comment":""},"10":{"family_comment":"","value":"","family":"","comment":""},"11":{"family_comment":"","value":"","family_hidden":false,"comment":"","family":""},"12":{"family_comment":"","value":"","family":"","comment":""},"13":{"family_comment":"","value":"","family":"","comment":""},"14":{"family_comment":"","value":"","family":"","comment":""},"15":{"family_comment":"","value":"","family":"","comment":""},"16":{"family_comment":"","value":"240000","family":"","comment":""},"17":{"family_comment":"","value":"","family":"","comment":"","family_comment_unclear":false},"18":{"family_comment":"","value":"","family":"","comment":""},"19":{"family_comment":"","value":"","family":"","comment":""},"20":{"value":"25500","family_unclear":false,"family_hidden":false,"family_comment":"","family":"46320","comment":""}},"vehicle":{"35":[{"brand_info":"2000 куб. см., 4.8 м","sum":"","brand":"Hyundai Sonata","sum_comment":"","brand_unclear":false,"year":"2009","brand_hidden":false,"brand_info_hidden":false,"brand_info_unclear":false,"sum_rent_comment":"","sum_rent":""},{"brand_info":"2000 куб. см., 4.74 м","sum_rent_comment":"","brand":"Volvo XC60","sum_comment":"","year":"2014","sum":"872943","sum_rent":""}]},"id":"vulyk_103_76","banks":{"45":[{"sum_foreign_comment":"","sum_units":"UAH","sum_comment":"","sum_hidden":false,"sum_foreign_units":"UAH","sum_comment_hidden":true,"sum_unclear":false,"sum":"301018","sum_foreign":""}],"46":[{"sum_foreign_comment":"","sum_units":"UAH","sum_comment":"","sum_hidden":false,"sum_foreign_units":"UAH","sum_comment_hidden":true,"sum":"52602","sum_foreign":""}]},"declaration":{"date":"2016-03-28T00:00:00","additional_info_text":"","additional_info":"","url":"http://static.declarations.com.ua/declarations/chosen_ones/judges_batch/1300_kulbaba_vasyl_mykolaiovych.pdf"},"liabilities":{"54":{"sum_foreign_comment":"","sum_foreign_hidden":false,"sum_comment":"","sum_foreign_comment_hidden":false,"sum_hidden":false,"sum_foreign_comment_unclear":false,"sum_comment_hidden":false,"sum_unclear":false,"sum":"","sum_foreign":""},"55":{"sum_foreign_comment":"","sum":"","sum_comment":"","sum_foreign":""},"56":{"sum_foreign_comment":"","sum":"","sum_comment":"","sum_foreign":""},"57":{"sum_foreign_comment":"","sum_foreign_hidden":false,"sum_comment":"","sum_foreign_comment_hidden":false,"sum_hidden":false,"sum_comment_hidden":false,"sum":"","sum_foreign":""},"58":{"sum_foreign_comment":"","sum_foreign_hidden":false,"sum_comment":"","sum_foreign_comment_hidden":false,"sum_hidden":false,"sum_comment_hidden":false,"sum":"","sum_foreign":""},"59":{"sum_foreign_comment":"","sum_foreign_hidden":false,"sum_comment":"","sum_foreign_comment_hidden":false,"sum_hidden":false,"sum_comment_hidden":false,"sum":"","sum_foreign":""},"60":{"sum_foreign_comment":"","sum":"","sum_comment":"","sum_hidden":false,"sum_comment_hidden":false,"sum_foreign":""},"61":{"sum_foreign_comment":"","sum":"","sum_comment":"","sum_foreign":""},"62":{"sum_foreign_comment":"","sum_comment_hidden":false,"sum":"","sum_comment":"","sum_foreign":""},"63":{"sum_foreign_comment":"","sum":"","sum_comment":"","sum_foreign":""},"64":{"sum_foreign_comment":"","sum":"","sum_comment":"","sum_foreign":""}},"ft_src":"Кульбаба Василь Миколайович\nсуддя вищого спецiалiзованого суду україни з розгляду цивiльних і кримiнальних справ\nЗагальнодержавний регіон\nВищий спеціалізований суд з розгляду цивільних і кримінальних справ\nВасиль\nКульбаба Любов Іванівна\nПодружжя\nВорона Галина Павлівна\nмати дружини\nІнше\nКульбаба Василь Миколайович\nВасиль Миколайович Кульбаба\nВасиль Кульбаба\nКульбаба Василь Миколайович\nКульбаба\nМиколайович\nHyundai Sonata\n2000 куб. см., 4.8 м\n2009\n2000 куб. см., 4.74 м\n872943\n2014\nVolvo XC60\n1050\nу користуванні\n.25\nземельний пай\n3.19\n1000\n50.2\nнежитлове приміщення\n20.75\n83.7\n1/2\n98.2\n1/4\n79.5\n83.7\n1/2\n98.2\n1/4\n79.5\n52602\n301018\n2015\n2000 куб. см., 4.8 м\n2009\nHyundai Sonata\n2000 куб. см., 4.74 м\n2014\n872943\nVolvo XC60\n50.2\n83.7\n98.2\n1/2\n79.5\n1/4\n1000\n1050\n.25\nу користуванні\n3.19\nземельний пай\n83.7\n98.2\n1/2\n79.5\n1/4\n20.75\nнежитлове приміщення\nКульбаба\nКульбаба Василь Миколайович\nВасиль Миколайович Кульбаба\nВасиль Кульбаба\nКульбаба Василь Миколайович\nКульбаба Василь Миколайович\nМиколайович\nПодружжя\nКульбаба Любов Іванівна\nВорона Галина Павлівна\nІнше\nмати дружини\nВасиль\nВищий спеціалізований суд з розгляду цивільних і кримінальних справ\nсуддя вищого спецiалiзованого суду україни з розгляду цивiльних і кримiнальних справ\nЗагальнодержавний регіон\n298588\n25500\n46320\n564088\n46320\n240000\n301018\n52602\n2015\n298588\n46320\n564088\n240000\n46320\n25500\nПодружжя\nКульбаба Любов Іванівна\nІнше\nмати дружини\nВорона Галина Павлівна\nКульбаба\nМиколайович\nсуддя вищого спецiалiзованого суду україни з розгляду цивiльних і кримiнальних справ\nВищий спеціалізований суд з розгляду цивільних і кримінальних справ\nЗагальнодержавний регіон\nКульбаба Василь Миколайович\nКульбаба Василь Миколайович\nВасиль Миколайович Кульбаба\nВасиль Кульбаба\nКульбаба Василь Миколайович\nВасиль\nHyundai Sonata\n2000 куб. см., 4.8 м\n2009\n872943\nVolvo XC60\n2000 куб. см., 4.74 м\n2014\n25500\n46320\n564088\n46320\n240000\n298588\n83.7\n1/2\n98.2\n1/4\n79.5\n1000\n83.7\n1/2\n98.2\n1/4\n79.5\n50.2\nнежитлове приміщення\n20.75\n1050\nу користуванні\n.25\nземельний пай\n3.19\n301018\n52602\n2015","general":{"inn":"","inn_hidden":true,"last_name":"Кульбаба","post":{"region":"Загальнодержавний регіон","region_unclear":false,"post":"суддя вищого спецiалiзованого суду україни з розгляду цивiльних і кримiнальних справ","office_unclear":false,"office":"Вищий спеціалізований суд з розгляду цивільних і кримінальних справ"},"name":"Василь","full_name":"Кульбаба Василь Миколайович","family_raw":"","addresses":[{"place_district":"","place_city_hidden":true,"place_city":"","place_city_type_hidden":false,"place_district_hidden":true,"place_city_type":"","place_address_hidden":true,"place_address":"","place_hidden":true,"place":""}],"family":[{"inn":"","relations":"Подружжя","relations_hidden":false,"inn_hidden":true,"relations_other":"","name_hidden":true,"family_name":"Кульбаба Любов Іванівна","name_unclear":false},{"inn":"","family_name":"Ворона Галина Павлівна","relations":"Інше","inn_hidden":true,"relations_other":"мати дружини"}],"full_name_suggest":{"output":"Кульбаба Василь Миколайович","input":["Кульбаба Василь Миколайович","Василь Миколайович Кульбаба","Василь Кульбаба"]},"patronymic":"Миколайович"},"source":"VULYK","estate":{"23":[{"costs_rent":"","region":"","costs":"","costs_rent_comment":"","costs_comment":"","address_hidden":true,"region_hidden":true,"space_comment":"","space_units":"м²","space":"1000","address":""}],"25":[{"costs":"","costs_comment":"","address_hidden":true,"region_hidden":true,"space_comment":"","space":"83.7","address":"","region":"","costs_rent_comment":"","space_comment_unclear":false,"space_comment_hidden":false,"space_units":"м²","costs_rent":""},{"costs_rent":"","region":"","costs":"","costs_rent_comment":"","costs_comment":"","region_hidden":false,"space_comment":"1/2","space_units":"м²","space":"98.2","address":""},{"costs_rent":"","region":"","costs":"","costs_rent_comment":"","costs_comment":"","space_comment":"1/4","space_units":"м²","space":"79.5","address":""}],"29":[{"space_hidden":false,"address_hidden":true,"region_hidden":true,"space_comment":"","space":"1050","address":"","region":"","costs_property":"","costs_rent_comment":"","space_units":"м²","costs_property_comment":"","costs_rent":""},{"costs_rent":"","costs_property":"","costs_rent_comment":"","space_comment":"у користуванні","costs_property_comment":"","space_units":"га","space":".25","address":""},{"costs_rent":"","space_unclear":false,"costs_property":"","costs_rent_comment":"","space_comment":"земельний пай","costs_property_comment":"","space_units":"га","space":"3.19","address":""}],"30":[{"space_unclear":false,"address_hidden":true,"region_hidden":true,"space_comment":"","space_hidden":false,"space":"50.2","address":"","costs_property":"","costs_rent_comment":"","space_units":"м²","costs_property_comment":"","costs_rent":""}],"31":[{"space_hidden":false,"address_hidden":true,"region_hidden":true,"space_comment":"","space":"83.7","address":"","costs_property":"","costs_rent_comment":"","address_unclear":false,"space_units":"м²","costs_property_comment":"","costs_rent":""},{"costs_rent":"","address_hidden":false,"space_hidden":false,"costs_property":"","costs_rent_comment":"","space_comment_unclear":false,"space_comment":"1/2","costs_property_comment":"","space_units":"м²","space":"98.2","address":""},{"costs_rent":"","space_hidden":false,"costs_property":"","costs_rent_comment":"","space_comment_unclear":false,"space_comment":"1/4","costs_property_comment":"","space_units":"м²","space":"79.5","address":""}],"34":[{"costs_rent":"","space_hidden":false,"costs_property":"","costs_rent_comment":"","address_hidden":true,"region_hidden":true,"space_comment":"","costs_property_comment":"","space_units":"м²","space":"20.75","address":"нежитлове приміщення"}]},"intro":{"declaration_year":"2015"}}