{"income":{"5":{"value":"210626.09","comment_hidden":false,"family_comment":"","family":"45745","comment":"","family_comment_hidden":false},"6":{"value":"210578.15","family_comment":"","comment_hidden":false,"family_hidden":false,"family_unclear":true,"family_comment_hidden":false,"comment":"","family":"24430"},"7":{"value":"","comment_hidden":false,"family_comment_hidden":false,"family_comment":"","source_name":"","family":"","comment":"","source_name_hidden":false},"8":{"family_comment":"","value":"","family":"","comment":""},"9":{"value":"","family_comment":"","value_unclear":false,"family_unclear":false,"comment_unclear":false,"comment":"","family":""},"10":{"family_comment":"допомога по вагітності та пологах","family_unclear":true,"value":"","family":"7092","comment":""},"11":{"family_comment":"","value":"","family":"","comment":""},"12":{"family_comment":"","value":"","family":"","comment":""},"13":{"family_comment":"","value":"","family":"","comment":""},"14":{"family_comment":"","value":"","family":"","comment":""},"15":{"family_comment":"","value":"","comment_unclear":false,"family":"","comment":""},"16":{"family_comment":"","value":"","comment_unclear":false,"family":"","comment":""},"17":{"family_comment":"","value":"","family":"","comment":""},"18":{"family_comment":"","value":"","family":"","comment":""},"19":{"family_comment":"","value":"","family":"","comment":""},"20":{"value":"47.94","family_comment":"","value_unclear":true,"family_unclear":true,"family_comment_unclear":false,"family_comment_hidden":false,"comment":"","family":"14223"}},"id":"vulyk_73_31","banks":{"53":[{"sum_foreign_comment":"","sum_units":"UAH","sum_comment":"","sum_foreign_units":"UAH","sum":"7029,59","sum_foreign":""}]},"declaration":{"additional_info_text":"","notfull_lostpages":"","date":"2014-11-28T00:00:00","notfull":"","additional_info":"","url":"http://static.declarations.com.ua/declarations/chosen_ones/judges_batch/1408_ohorodnik_kostiantyn_mykhailovych.pdf"},"liabilities":{"54":{"sum_foreign_comment":"","sum_foreign_hidden":false,"sum_comment":"","sum_comment_unclear":false,"sum_hidden":false,"sum_comment_hidden":false,"sum_unclear":false,"sum":"","sum_foreign":""},"55":{"sum_foreign_comment":"","sum_comment_hidden":false,"sum":"","sum_comment":"","sum_foreign":""},"56":{"sum_foreign_comment":"","sum":"7500","sum_comment":"","sum_comment_unclear":false,"sum_foreign":""},"57":{"sum_foreign_comment":"","sum":"","sum_comment":"","sum_hidden":false,"sum_comment_hidden":false,"sum_unclear":false,"sum_foreign":""},"58":{"sum_foreign_comment":"","sum":"","sum_comment":"","sum_hidden":false,"sum_comment_hidden":false,"sum_foreign":""},"59":{"sum_foreign_comment":"","sum":"","sum_comment":"","sum_comment_unclear":false,"sum_unclear":false,"sum_foreign":""},"60":{"sum_foreign_comment":"","sum":"","sum_comment":"","sum_hidden":false,"sum_comment_hidden":false,"sum_unclear":false,"sum_foreign":""},"61":{"sum_foreign_comment":"","sum":"","sum_comment":"","sum_foreign":""},"62":{"sum_foreign_comment":"","sum":"","sum_comment":"","sum_foreign":""},"63":{"sum_foreign_comment":"","sum":"","sum_comment":"","sum_hidden":false,"sum_comment_hidden":false,"sum_foreign":""},"64":{"sum_foreign_comment":"","sum":"","sum_comment":"","sum_foreign":""}},"ft_src":"7500\nсуддя рівненського апеляційного господарського суду\nРівненська область\nАпеляційний господарський суд\nКостянтин\nПодружжя\nСин\nДитина\nДонька\nДитина\nМихайлович\nОгороднік Костянтин Михайлович\nКостянтин Михайлович Огороднік\nКостянтин Огороднік\nОгороднік Костянтин Михайлович\nОгороднік\nОгороднік Костянтин Михайлович\n96\n7029,59\n2013\n2013\nОгороднік Костянтин Михайлович\nКостянтин Михайлович Огороднік\nКостянтин Огороднік\nОгороднік Костянтин Михайлович\nКостянтин\nПодружжя\nДитина\nСин\nДитина\nДонька\nОгороднік Костянтин Михайлович\nМихайлович\nАпеляційний господарський суд\nРівненська область\nсуддя рівненського апеляційного господарського суду\nОгороднік\n7500\n24430\n210578.15\n14223\n47.94\n210626.09\n45745\n7092\nдопомога по вагітності та пологах\n96\n7029,59\n7500\n24430\n210578.15\n7092\nдопомога по вагітності та пологах\n45745\n210626.09\n14223\n47.94\nПодружжя\nДитина\nСин\nДитина\nДонька\nМихайлович\nОгороднік\nКостянтин\nОгороднік Костянтин Михайлович\nКостянтин Михайлович Огороднік\nКостянтин Огороднік\nОгороднік Костянтин Михайлович\nРівненська область\nАпеляційний господарський суд\nсуддя рівненського апеляційного господарського суду\nОгороднік Костянтин Михайлович\nдопомога по вагітності та пологах\n7092\n47.94\n14223\n210626.09\n45745\n210578.15\n24430\n96\n7029,59\n2013","general":{"inn":"","name":"Костянтин","family":[{"inn":"","relations":"Подружжя","inn_unclear":false,"relations_hidden":false,"inn_hidden":true,"relations_other":"","name_hidden":true,"family_name":"","name_unclear":false},{"inn":"","relations":"Дитина","inn_unclear":false,"family_name":"","inn_hidden":true,"relations_other":"Син","name_hidden":false,"name_unclear":false},{"inn":"","relations":"Дитина","relations_other":"Донька","inn_hidden":true,"family_name":"","name_hidden":false,"name_unclear":false}],"patronymic":"Михайлович","inn_hidden":true,"family_raw":"","last_name":"Огороднік","post":{"post_unclear":false,"region_unclear":false,"post":"суддя рівненського апеляційного господарського суду","office":"Апеляційний господарський суд","region":"Рівненська область","post_hidden":false,"office_hidden":false,"office_unclear":false,"region_hidden":false},"last_name_unclear":false,"full_name":"Огороднік Костянтин Михайлович","addresses":[{"place_district":"","place_city_hidden":true,"place_city":"","place_city_type_hidden":true,"place_district_hidden":true,"place_city_type":"","place_address_hidden":true,"place_address":"","place_hidden":true,"place":""}],"full_name_suggest":{"output":"Огороднік Костянтин Михайлович","input":["Огороднік Костянтин Михайлович","Костянтин Михайлович Огороднік","Костянтин Огороднік"]},"name_unclear":false},"source":"VULYK","estate":{"25":[{"space_unclear":false,"costs":"","costs_comment":"","costs_hidden":false,"address_hidden":true,"region_hidden":true,"space_comment":"","space_hidden":false,"space":"96","address":"","region":"","costs_rent_comment":"","space_comment_hidden":false,"space_units":"м²","costs_rent":""}]},"intro":{"declaration_year":"2013"}}