{"income":{"5":{"family_comment":"","value":"284458","value_unclear":false,"family":"","comment":""},"6":{"value":"284458","value_unclear":false,"family_hidden":false,"family_comment":"","family":"","comment":""},"7":{"source_name_unclear":false,"value":"","family_comment":"","source_name":"","family":"","comment":""},"8":{"family_comment":"","value":"","family":"","comment":""},"9":{"family_comment":"","value":"","family":"","comment":""},"10":{"family_comment":"","value":"","family":"","comment":""},"11":{"family_comment":"","value":"","comment_unclear":false,"family":"","comment":""},"12":{"family_comment":"","value":"","family":"","comment":""},"13":{"family_comment":"","value":"","family":"","comment":""},"14":{"family_comment":"","value":"","family":"","comment":""},"15":{"family_comment":"","value":"","family":"","comment":""},"16":{"family_comment":"","value":"","family":"","comment":""},"17":{"family_comment":"","value":"","family":"","comment":""},"18":{"family_comment":"","value":"","family":"","comment":""},"19":{"family_comment":"","value":"","family":"","comment":""},"20":{"value":"","family_comment":"","value_unclear":false,"family_unclear":false,"comment_unclear":false,"comment":"","family":""}},"vehicle":{"35":[{"brand_info":"1968 куб. см., 103 кВт , 443 см","sum":"549700","brand":"Volkswagen Tiguan","sum_comment":"в т. ч. кредит","brand_unclear":false,"year":"2014","sum_rent_unclear":false,"brand_info_hidden":false,"brand_info_unclear":false,"sum_rent_comment":"","sum_rent":""}],"40":[{"brand_info":"1968 куб. см., 103 кВт , 443 см","sum":"","brand":"Volkswagen Tiguan","sum_comment":"","year":"2014","brand_hidden":false,"brand_info_hidden":false,"brand_info_unclear":false,"sum_rent_comment":"користування","sum_rent":""}]},"id":"vulyk_101_8","declaration":{"additional_info_text":"","notfull_lostpages":"","date":"2016-03-18T00:00:00","notfull":"","additional_info":"","url":"http://static.declarations.com.ua/declarations/chosen_ones/judges_batch/667_kolesnikov_hryhorii_iakovlevych_2015.pdf"},"liabilities":{"54":{"sum_foreign_comment":"","sum":"49874","sum_comment":"","sum_comment_unclear":false,"sum_hidden":false,"sum_comment_hidden":false,"sum_unclear":false,"sum_foreign":""},"55":{"sum_foreign_comment":"","sum":"","sum_comment":"","sum_foreign":""},"56":{"sum_foreign_comment":"","sum":"","sum_comment":"","sum_comment_hidden":false,"sum_unclear":false,"sum_foreign":""},"57":{"sum_foreign_comment":"","sum":"60645","sum_comment":"","sum_hidden":false,"sum_comment_hidden":false,"sum_unclear":false,"sum_foreign":""},"58":{"sum_foreign_comment":"","sum":"75500","sum_comment":"","sum_comment_unclear":false,"sum_hidden":false,"sum_comment_hidden":false,"sum_unclear":false,"sum_foreign":""},"59":{"sum_foreign_comment":"","sum":"","sum_comment":"","sum_foreign":""},"60":{"sum_foreign_comment":"","sum":"","sum_comment":"","sum_hidden":false,"sum_comment_hidden":false,"sum_unclear":false,"sum_foreign":""},"61":{"sum_foreign_comment":"","sum":"","sum_comment":"","sum_foreign":""},"62":{"sum_foreign_comment":"","sum":"","sum_comment":"","sum_comment_unclear":false,"sum_foreign":""},"63":{"sum_foreign_comment":"","sum_comment":"","sum":"","sum_comment_hidden":false,"sum_foreign":""},"64":{"sum_foreign_comment":"","sum_comment":"","sum":"","sum_comment_hidden":false,"sum_foreign":""}},"ft_src":"в т. ч. кредит\nVolkswagen Tiguan\n1968 куб. см., 103 кВт , 443 см\n2014\n549700\nкористування\n1968 куб. см., 103 кВт , 443 см\nVolkswagen Tiguan\n2014\nбезоплатна передача у власність\nбезоплатно передана у власність\n901\n645\n1000\n100\n34.7\n2015\n284458\n284458\n1968 куб. см., 103 кВт , 443 см\nв т. ч. кредит\n2014\n549700\nVolkswagen Tiguan\n1968 куб. см., 103 кВт , 443 см\nкористування\n2014\nVolkswagen Tiguan\n901\nбезоплатно передана у власність\nбезоплатна передача у власність\n645\n1000\n100\n34.7\nКолесніков Григорій Яковлевич\nГригорій Яковлевич Колесніков\nГригорій Колесніков\nКолесніков Григорій Яковлевич\nГригорій\nКолесніков Григорій Яковлевич\nЯковлевич\nголова апеляційного суду одеської області\nОдеська область\nЗагальний апеляційний суд\nКолесніков\nДитина\nКолеснікова А. Г\n49874\n60645\n75500\n284458\n284458\n2015\n75500\n60645\n49874\nКолеснікова А. Г\nДитина\nГригорій\nЯковлевич\nКолесніков\nКолесніков Григорій Яковлевич\nГригорій Яковлевич Колесніков\nГригорій Колесніков\nКолесніков Григорій Яковлевич\nголова апеляційного суду одеської області\nОдеська область\nЗагальний апеляційний суд\nКолесніков Григорій Яковлевич","general":{"inn":"","name":"Григорій","last_name":"Колесніков","family":[{"inn":"","inn_hidden":true,"family_name":"Колеснікова А. Г","relations_other":"","relations":"Дитина","name_hidden":true,"name_unclear":false}],"inn_hidden":true,"family_raw":"","inn_unclear":false,"post":{"region":"Одеська область","region_unclear":false,"post":"голова апеляційного суду одеської області","office_unclear":false,"office":"Загальний апеляційний суд"},"full_name":"Колесніков Григорій Яковлевич","addresses":[{"place_district":"","place_address_hidden":true,"place_hidden":true,"place_address":"","place_district_hidden":false,"place_city_type":"","place_city_hidden":true,"place_city_type_hidden":false,"place_city":"","place":""}],"patronymic":"Яковлевич","patronymic_hidden":false,"full_name_suggest":{"output":"Колесніков Григорій Яковлевич","input":["Колесніков Григорій Яковлевич","Григорій Яковлевич Колесніков","Григорій Колесніков"]}},"source":"VULYK","estate":{"23":[{"space_unclear":false,"costs":"","costs_comment":"безоплатна передача у власність","address_hidden":false,"region_hidden":true,"space_comment":"безоплатно передана у власність","space_hidden":false,"space":"901","address":"","costs_comment_unclear":false,"region":"","space_units_unclear":false,"space_units":"м²","costs_rent":"","costs_rent_comment":""},{"costs_rent":"645","space_unclear":false,"region":"","costs":"","costs_rent_comment":"","costs_comment":"","space_comment":"","space_units":"м²","space":"1000","address":""}],"25":[{"space_unclear":false,"costs":"","costs_comment":"","address_hidden":false,"region_hidden":true,"space_comment":"","space_hidden":false,"space":"100","address":"","region":"","costs_rent_comment":"","space_comment_unclear":false,"space_units":"м²","costs_rent":""},{"space_unclear":false,"costs":"","costs_comment":"","space_comment":"","space_hidden":false,"space":"34.7","address":"","region":"","costs_rent_comment":"","space_comment_unclear":false,"space_units":"м²","costs_rent":""}]},"intro":{"declaration_year":"2015"}}