{"income":{"5":{"value":"269809.39","family_comment":"","value_unclear":false,"family_hidden":false,"family_unclear":false,"family":"184495.17","comment":""},"6":{"value":"265662.02","family_comment":"","value_unclear":false,"family_unclear":false,"family":"151335.9","comment":""},"7":{"value":"","family_comment":"","source_name":"","family":"","comment":"","source_name_hidden":false},"8":{"family_comment":"","value":"","family":"","comment":""},"9":{"family_comment":"","value":"4147.37","family":"33159.27","comment":""},"10":{"value":"","family_hidden":false,"value_hidden":false,"family_comment":"","family":"","comment":""},"11":{"family_comment":"","value":"","family":"","comment":"Нагрудний знак ДСА України 'Знак пошани'. Вартість невідома"},"12":{"family_comment":"","value":"","family":"","comment":""},"13":{"family_comment":"","value":"","family":"","comment":""},"14":{"family_comment":"","value":"","family":"","comment":""},"15":{"family_comment":"","value":"","family":"","comment":""},"16":{"family_comment":"","value":"","value_unclear":false,"family":"","comment":""},"17":{"family_comment":"","value":"","family":"","comment":""},"18":{"family_comment":"","value":"","family":"","comment":""},"19":{"family_comment":"","value":"","family":"","comment":""},"20":{"value":"","family_comment":"","family_unclear":false,"family":"","comment":"","family_comment_unclear":false}},"vehicle":{"35":[{"brand_info":"1248 куб. см., дизель, 70 кВт (95 к. с","sum_rent_comment":"","brand_info_unclear":false,"year":"2012","brand_info_hidden":false,"sum_rent_comment_unclear":false,"year_unclear":false,"sum_rent":"","sum":"","brand":"Opel Astra","sum_comment":"","brand_unclear":false,"brand_hidden":false}],"40":[{"brand_info":"1461 куб. см., дизель, 63 кВт (86 к. с) 1/2 частина","sum_rent_comment":"","brand":"Renault Kangoo","sum_comment":"","brand_unclear":false,"year":"2010","brand_hidden":false,"brand_info_hidden":false,"year_unclear":false,"sum":"","sum_rent":""}]},"id":"vulyk_27_160","banks":{"45":[{"sum_foreign_comment":"","sum":"31721.7","sum_comment":"","sum_hidden":false,"sum_foreign_units":"UAH","sum_foreign_hidden":false,"sum_units":"UAH","sum_comment_hidden":false,"sum_units_hidden":false,"sum_foreign":""},{"sum_foreign_comment":"","sum_units":"","sum_comment":"","sum_foreign_units":"","sum_comment_hidden":false,"sum":"","sum_foreign":""}],"46":[{"sum_foreign_comment":"","sum_units":"UAH","sum_comment":"","sum_comment_unclear":false,"sum_hidden":false,"sum_foreign_units":"UAH","sum_comment_hidden":false,"sum":"38568.2","sum_foreign":""},{"sum_foreign_comment":"","sum_units":"","sum_comment":"","sum_comment_unclear":false,"sum_foreign_units":"","sum":"","sum_foreign":""}],"47":[{"sum_foreign_comment":"","sum":"15","sum_comment":"","sum_hidden":false,"sum_foreign_units":"UAH","sum_foreign_hidden":false,"sum_units":"UAH","sum_comment_hidden":false,"sum_unclear":false,"sum_foreign":"","sum_units_hidden":false}],"48":[{"sum_foreign_comment":"","sum_units":"UAH","sum_comment":"","sum_foreign_units":"UAH","sum":"","sum_foreign":""}],"49":[{"sum_foreign_comment":"","sum_units":"UAH","sum_comment":"","sum_foreign_units":"UAH","sum":"","sum_foreign":""}],"50":[{"sum_foreign_comment":"","sum_units":"UAH","sum_comment":"","sum_foreign_units":"UAH","sum":"","sum_foreign":""}],"51":[{"sum_foreign_comment":"","sum_units":"UAH","sum_units_hidden":true,"sum_comment":"","sum_comment_unclear":false,"sum_hidden":false,"sum_foreign_units":"UAH","sum_comment_hidden":true,"sum_unclear":false,"sum":"475603","sum_foreign":""},{"sum_foreign_comment":"","sum_units":"","sum_comment":"","sum_foreign_units":"","sum_comment_hidden":false,"sum":"","sum_foreign":""}],"52":[{"sum_foreign_comment":"","sum_units":"UAH","sum_comment":"","sum_comment_unclear":false,"sum_units_hidden":true,"sum_foreign_units":"UAH","sum_comment_hidden":true,"sum_unclear":false,"sum":"30","sum_foreign":""}],"53":[{"sum_foreign_comment":"","sum_units":"UAH","sum_comment":"","sum_foreign_units":"UAH","sum":"","sum_foreign":""}]},"declaration":{"additional_info_text":"","notfull_lostpages":"","date":"2015-03-03T00:00:00","notfull":"","additional_info":"","url":"http://static.declarations.com.ua/declarations/chosen_ones/mega_batch/butsiak_zenovii_ivanovych.pdf"},"liabilities":{"54":{"sum_foreign_comment":"","sum_foreign_hidden":false,"sum_comment":"","sum_comment_hidden":false,"sum":"","sum_foreign":""},"55":{"sum_foreign_comment":"","sum":"","sum_comment":"","sum_foreign":""},"56":{"sum_foreign_comment":"","sum":"","sum_comment":"","sum_hidden":false,"sum_unclear":false,"sum_foreign":""},"57":{"sum_foreign_comment":"","sum":"","sum_comment":"","sum_hidden":false,"sum_comment_hidden":false,"sum_unclear":false,"sum_foreign":""},"58":{"sum_foreign_comment":"","sum":"","sum_comment":"","sum_hidden":false,"sum_comment_hidden":false,"sum_unclear":false,"sum_foreign":""},"59":{"sum_foreign_comment":"","sum":"","sum_comment":"","sum_foreign":""},"60":{"sum_foreign_comment":"","sum":"","sum_comment":"","sum_hidden":false,"sum_comment_hidden":false,"sum_foreign":""},"61":{"sum_foreign_comment":"","sum":"","sum_comment":"","sum_foreign":""},"62":{"sum_foreign_comment":"","sum":"","sum_comment":"","sum_foreign":""},"63":{"sum_foreign_comment":"","sum":"","sum_comment":"","sum_hidden":false,"sum_comment_hidden":false,"sum_foreign":""},"64":{"sum_foreign_comment":"","sum":"","sum_comment":"","sum_hidden":false,"sum_comment_hidden":false,"sum_foreign":""}},"ft_src":"суддя апеляційного суду рівненської області\nРівненська область\nЗагальний апеляційний суд\nЗеновій\nПодружжя\nДитина\nІванович\nБуцяк\nБуцяк Зеновій Іванович\nБуцяк Зеновій Іванович\nЗеновій Іванович Буцяк\nЗеновій Буцяк\nБуцяк Зеновій Іванович\n1248 куб. см., дизель, 70 кВт (95 к. с\nOpel Astra\n2012\nRenault Kangoo\n1461 куб. см., дизель, 63 кВт (86 к. с) 1/2 частина\n2010\n15\n38568.2\n475603\n31721.7\n30\n2014\n1248 куб. см., дизель, 70 кВт (95 к. с\nOpel Astra\n2012\n1461 куб. см., дизель, 63 кВт (86 к. с) 1/2 частина\n2010\nRenault Kangoo\n31721.7\n475603\n30\n15\n38568.2\n900\nдачна / приватизована у 1997 р\n1000\n55.5\nзбудована у 90-х роках\n29.4\nприватизована\n33.1\nБуцяк Зеновій Іванович\nЗеновій Іванович Буцяк\nЗеновій Буцяк\nБуцяк Зеновій Іванович\nЗеновій\nПодружжя\nДитина\nБуцяк Зеновій Іванович\nБуцяк\nЗагальний апеляційний суд\nРівненська область\nсуддя апеляційного суду рівненської області\nІванович\n265662.02\n151335.9\n184495.17\n269809.39\nНагрудний знак ДСА України 'Знак пошани'. Вартість невідома\n4147.37\n33159.27\n2014\nприватизована\n29.4\n33.1\n1000\nдачна / приватизована у 1997 р\n900\nзбудована у 90-х роках\n55.5\nПодружжя\nДитина\nІванович\nБуцяк\nЗеновій\nБуцяк Зеновій Іванович\nЗеновій Іванович Буцяк\nЗеновій Буцяк\nБуцяк Зеновій Іванович\nРівненська область\nЗагальний апеляційний суд\nсуддя апеляційного суду рівненської області\nБуцяк Зеновій Іванович\n151335.9\n265662.02\nНагрудний знак ДСА України 'Знак пошани'. Вартість невідома\n184495.17\n269809.39\n33159.27\n4147.37\n2012\nOpel Astra\n1248 куб. см., дизель, 70 кВт (95 к. с\n2010\nRenault Kangoo\n1461 куб. см., дизель, 63 кВт (86 к. с) 1/2 частина\nНагрудний знак ДСА України 'Знак пошани'. Вартість невідома\n269809.39\n184495.17\n33159.27\n4147.37\n265662.02\n151335.9\nприватизована\n29.4\n33.1\nдачна / приватизована у 1997 р\n900\nзбудована у 90-х роках\n55.5\n1000\n15\n38568.2\n31721.7\n30\n475603\n2014","general":{"name_hidden":false,"name":"Зеновій","patronymic_unclear":false,"inn":"","family":[{"inn":"","inn_hidden":true,"relations_hidden":false,"family_name":"","relations_other":"","relations":"Подружжя","name_hidden":true,"name_unclear":false},{"inn":"","relations":"Дитина","relations_other":"","inn_hidden":false,"family_name":"","name_hidden":false,"name_unclear":false}],"patronymic":"Іванович","inn_hidden":true,"family_raw":"","inn_unclear":false,"post":{"post_unclear":false,"region_unclear":false,"post":"суддя апеляційного суду рівненської області","office":"Загальний апеляційний суд","region":"Рівненська область","post_hidden":false,"office_unclear":false},"last_name_unclear":false,"full_name":"Буцяк Зеновій Іванович","addresses":[{"place_district":"","place_address_hidden":true,"place_city":"","place_city_type_hidden":true,"place_district_hidden":true,"place_city_type":"","place_city_hidden":true,"place_address_unclear":false,"place_address":"","place_hidden":true,"place":""}],"last_name":"Буцяк","full_name_suggest":{"output":"Буцяк Зеновій Іванович","input":["Буцяк Зеновій Іванович","Зеновій Іванович Буцяк","Зеновій Буцяк"]},"name_unclear":false},"source":"VULYK","estate":{"23":[{"costs":"","costs_comment":"","address_hidden":true,"region_hidden":true,"space_comment":"дачна / приватизована у 1997 р","space":"900","address":"","region":"","address_unclear":false,"costs_rent_comment":"","costs_rent_comment_hidden":false,"space_units":"м²","space_units_unclear":false,"costs_rent":""},{"costs":"","costs_comment":"","address_hidden":false,"region_hidden":false,"space_comment":"","space":"","address":"","costs_comment_unclear":false,"region":"","costs_rent_comment":"","space_units":"","costs_rent":""},{"costs_rent":"","region":"","costs":"","costs_rent_comment":"","costs_comment":"","space_comment":"","space_units":"","space":"","address":""},{"costs_rent":"","region":"","costs":"","costs_rent_comment":"","costs_comment":"","space_comment":"","space_units":"","space":"","address":""}],"26":[{"costs_rent":"","region":"","costs":"","costs_rent_comment":"","costs_comment":"","address_hidden":true,"region_hidden":true,"space_comment":"збудована у 90-х роках","space_units":"м²","space":"55.5","address":""}],"29":[{"space_unclear":false,"costs_property_comment":"","costs_property":"","address_hidden":true,"region_hidden":true,"space_comment":"","space":"1000","address":"","costs_property_comment_hidden":false,"region":"","address_unclear":false,"costs_rent_comment":"","space_comment_hidden":true,"space_units":"м²","space_units_unclear":false,"costs_rent":""}],"31":[{"space_hidden":false,"costs_property":"","address_hidden":true,"region_hidden":true,"space_comment":"приватизована","space":"29.4","address":"","region":"","address_unclear":false,"costs_rent_comment":"","space_comment_unclear":false,"costs_rent_comment_hidden":false,"space_units":"м²","costs_property_comment":"","costs_rent":""},{"costs_rent":"","region":"","costs_property":"","costs_rent_comment":"","region_hidden":false,"space_comment":"","costs_property_comment":"","space_units":"м²","space":"33.1","address":""}]},"intro":{"declaration_year":"2014","isnotdeclaration":"","declaration_year_hidden":false}}