{"income":{"5":{"value":"251557","family_comment":"","value_unclear":false,"comment_hidden":false,"family_hidden":false,"value_hidden":false,"family_unclear":false,"family":"392254","comment":""},"6":{"value":"251557","family_comment":"","value_unclear":false,"family_hidden":false,"family_unclear":false,"comment_unclear":false,"comment":"","family":"13990"},"7":{"source_name_unclear":false,"value":"","value_hidden":false,"family_comment":"","source_name":"","family":"","comment":"","source_name_hidden":false},"8":{"value":"","family_hidden":false,"value_hidden":false,"family_comment":"","family":"","comment":""},"9":{"value":"","family_comment":"","value_unclear":false,"family_hidden":false,"value_hidden":false,"family_unclear":false,"family":"","comment":""},"10":{"family_comment":"","value":"","family":"","comment":""},"11":{"family_comment":"","value":"","family":"150015","comment":""},"12":{"family_comment":"","value":"","family":"","comment":""},"13":{"family_comment":"","value":"","family":"","comment":""},"14":{"family_comment":"","value":"","family":"143875","comment":""},"15":{"family_comment":"","value":"","family":"","comment":""},"16":{"value":"","family_comment":"","value_unclear":false,"family_unclear":false,"family":"84374","comment":""},"17":{"family_comment":"","value":"","family":"","comment":""},"18":{"family_comment":"","value":"","family":"","comment":""},"19":{"family_comment":"","value":"","comment_unclear":false,"family":"","comment":""},"20":{"value":"","family_comment":"","value_unclear":false,"comment_hidden":false,"family_hidden":false,"family":"","value_hidden":false,"family_unclear":false,"comment_unclear":false,"comment":"","family_comment_unclear":false}},"vehicle":{"35":[{"brand_info":"об'єм циліндрів 1086 , потужність 47.81","sum_rent_comment":"","brand":"Hyundai T10","sum_comment":"","brand_unclear":false,"year":"2012","brand_info_unclear":false,"sum":"","sum_rent":""}]},"id":"vulyk_63_187","banks":{"45":[{"sum_foreign_comment":"","sum_units":"UAH","sum_comment":"","sum_foreign_unclear":false,"sum_foreign_units":"UAH","sum_foreign_hidden":false,"sum_hidden":false,"sum_comment_hidden":false,"sum_unclear":false,"sum":"9511","sum_foreign":""}],"47":[{"sum_foreign_comment":"","sum_units":"UAH","sum_comment":"","sum_foreign_units":"UAH","sum":"11","sum_foreign":""}],"51":[{"sum_foreign_comment":"","sum_units":"UAH","sum_comment":"","sum_foreign_unclear":false,"sum_foreign_units":"UAH","sum_foreign_hidden":false,"sum_hidden":false,"sum_comment_hidden":false,"sum_unclear":false,"sum":"1603","sum_foreign":""}]},"declaration":{"additional_info_text":"","notfull_lostpages":"","date":"2014-03-17T00:00:00","notfull":"","additional_info":"","url":"http://static.declarations.com.ua/declarations/chosen_ones/mega_batch/denysenko_nataliia_oleksandrivna.pdf"},"liabilities":{"54":{"sum_foreign_comment":"","sum":"","sum_comment":"","sum_unclear":false,"sum_foreign":""},"55":{"sum_foreign_comment":"","sum":"","sum_comment":"","sum_foreign":""},"56":{"sum_foreign_comment":"","sum":"","sum_comment":"","sum_unclear":false,"sum_foreign":""},"57":{"sum_foreign_comment":"","sum":"","sum_comment":"","sum_comment_hidden":false,"sum_unclear":false,"sum_foreign":""},"58":{"sum_foreign_comment":"","sum_comment_hidden":false,"sum":"","sum_comment":"","sum_foreign":""},"59":{"sum_foreign_comment":"","sum":"","sum_comment":"","sum_foreign":""},"60":{"sum_foreign_comment":"","sum":"","sum_comment":"","sum_comment_unclear":false,"sum_foreign":""},"61":{"sum_foreign_comment":"","sum":"","sum_comment":"","sum_unclear":false,"sum_foreign":""},"62":{"sum_foreign_comment":"","sum":"","sum_comment":"","sum_unclear":false,"sum_foreign":""},"63":{"sum_foreign_comment":"","sum":"","sum_comment":"","sum_hidden":false,"sum_comment_hidden":false,"sum_unclear":false,"sum_foreign":""},"64":{"sum_foreign_comment":"","sum_comment_hidden":false,"sum":"","sum_comment":"","sum_foreign":""}},"ft_src":"в. о. заступника голови згурівського районного суду київської області\nКиївська область\nЗагальний місцевий суд\nНаталія\nДенисенко Юлія Віталіївна\nОлександрівна\nДенисенко\nДенисенко Наталія Олександрівна\nДенисенко Наталія Олександрівна\nНаталія Олександрівна Денисенко\nНаталія Денисенко\nДенисенко Наталія Олександрівна\n2012\nHyundai T10\nоб'єм циліндрів 1086 , потужність 47.81\n11\n1603\n9511\n2013\nоб'єм циліндрів 1086 , потужність 47.81\n2012\nHyundai T10\n9511\n1603\n11\n50.4\n58\n45.6\n2861\nДенисенко Наталія Олександрівна\nНаталія Олександрівна Денисенко\nНаталія Денисенко\nДенисенко Наталія Олександрівна\nНаталія\nДенисенко Юлія Віталіївна\nДенисенко Наталія Олександрівна\nДенисенко\nЗагальний місцевий суд\nКиївська область\nв. о. заступника голови згурівського районного суду київської області\nОлександрівна\n251557\n13990\n143875\n251557\n392254\n84374\n150015\n2013\n50.4\n45.6\n58\n2861\nДенисенко Юлія Віталіївна\nОлександрівна\nДенисенко\nДенисенко Наталія Олександрівна\nНаталія Олександрівна Денисенко\nНаталія Денисенко\nДенисенко Наталія Олександрівна\nНаталія\nКиївська область\nв. о. заступника голови згурівського районного суду київської області\nЗагальний місцевий суд\nДенисенко Наталія Олександрівна\n13990\n251557\n143875\n150015\n392254\n251557\n84374\n2012\nоб'єм циліндрів 1086 , потужність 47.81\nHyundai T10\n150015\n143875\n251557\n392254\n84374\n251557\n13990\n45.6\n58\n50.4\n2861\n11\n9511\n1603\n2013","general":{"name_hidden":false,"name":"Наталія","patronymic_unclear":false,"last_name_hidden":false,"inn":"","family":[{"inn":"","inn_hidden":true,"relations_unclear":false,"relations_hidden":false,"relations_other":"","relations":"","name_hidden":false,"inn_unclear":false,"family_name":"Денисенко Юлія Віталіївна","name_unclear":false}],"patronymic":"Олександрівна","inn_hidden":true,"family_raw":"","inn_unclear":false,"post":{"post_unclear":false,"region_unclear":false,"region":"Київська область","office_hidden":false,"region_hidden":false,"post":"в. о. заступника голови згурівського районного суду київської області","office_unclear":false,"office":"Загальний місцевий суд"},"last_name_unclear":false,"full_name":"Денисенко Наталія Олександрівна","last_name":"Денисенко","full_name_suggest":{"output":"Денисенко Наталія Олександрівна","input":["Денисенко Наталія Олександрівна","Наталія Олександрівна Денисенко","Наталія Денисенко"]},"name_unclear":false},"source":"VULYK","estate":{"29":[{"space_hidden":false,"costs_property_comment":"","address_hidden":false,"region_hidden":false,"space_comment":"","space_unclear":false,"space":"2861","address":"","region":"","costs_property":"","costs_rent_comment":"","address_unclear":false,"space_units":"м²","space_units_unclear":false,"costs_rent":""}],"30":[{"space_unclear":false,"address_hidden":false,"region_hidden":false,"space_comment":"","space_hidden":false,"space":"58","address":"","region":"","costs_property":"","costs_rent_comment":"","space_units":"м²","costs_property_comment":"","costs_rent":""}],"31":[{"space_unclear":false,"costs_property_hidden":false,"address_hidden":false,"region_hidden":false,"space_comment":"","space_hidden":false,"space":"45.6","address":"","costs_property_comment_hidden":false,"region":"","costs_property":"","space_units_unclear":false,"costs_rent_hidden":false,"space_comment_unclear":false,"costs_rent_comment_hidden":false,"space_units":"м²","costs_property_comment":"","costs_rent":"","costs_rent_comment":""}],"33":[{"space_hidden":false,"address_hidden":false,"region_hidden":false,"space_comment":"","space":"50.4","address":"","region":"","costs_property":"","costs_rent_comment":"","space_units":"м²","costs_property_comment":"","costs_rent":""}]},"intro":{"declaration_year":"2013","isnotdeclaration":"","declaration_year_unclear":false}}