{"income":{"5":{"family_comment":"","family_unclear":false,"value":"179119","family":"28689","comment":""},"6":{"family_comment":"","family_unclear":false,"value":"179119","family":"28689","comment":""},"7":{"value":"","comment_hidden":false,"family_comment":"","source_name":"","family":"","comment":""},"8":{"family_comment":"","value":"","family":"","comment":""},"9":{"family_comment":"","value":"","family":"","comment":""},"10":{"family_comment":"","value":"","family":"","comment":""},"11":{"family_comment":"","value":"","value_unclear":false,"family":"","comment":""},"12":{"family_comment":"","value":"","family":"","comment":""},"13":{"family_comment":"","value":"","family":"","comment":""},"14":{"family_comment":"","value":"","family":"","comment":""},"15":{"family_comment":"","value":"","value_unclear":false,"family":"","comment":""},"16":{"family_comment":"","family_unclear":false,"value":"","family":"","comment":""},"17":{"family_comment":"","value":"","family":"","comment":""},"18":{"family_comment":"","value":"","family_hidden":false,"comment":"","family":""},"19":{"family_comment":"","value":"","family":"","comment":""},"20":{"value":"","comment_unclear":false,"comment_hidden":false,"family_comment":"","family":"","comment":"","family_comment_hidden":false}},"id":"vulyk_68_143","banks":{"45":[{"sum_foreign_comment":"","sum_units":"UAH","sum_units_hidden":false,"sum_comment":"","sum_comment_unclear":false,"sum_hidden":false,"sum_foreign_units":"UAH","sum_comment_hidden":false,"sum_unclear":false,"sum":"100000","sum_foreign":""}],"46":[{"sum_foreign_comment":"","sum_units":"UAH","sum_comment":"","sum_foreign_units":"UAH","sum":"20000","sum_foreign":""}]},"declaration":{"additional_info_text":"","notfull_lostpages":"","date":"2015-02-09T00:00:00","notfull":"","additional_info":"","url":"http://static.declarations.com.ua/declarations/chosen_ones/mega_batch/kozlov_dmytro_oleksandrovych.pdf"},"liabilities":{"54":{"sum_foreign_comment":"","sum":"","sum_comment":"","sum_comment_unclear":false,"sum_hidden":false,"sum_comment_hidden":false,"sum_unclear":false,"sum_foreign":""},"55":{"sum_foreign_comment":"","sum":"","sum_hidden":false,"sum_comment":"","sum_foreign":""},"56":{"sum_foreign_comment":"","sum_foreign_hidden":false,"sum_comment":"","sum":"","sum_unclear":false,"sum_foreign":""},"57":{"sum_foreign_comment":"","sum":"","sum_comment":"","sum_comment_unclear":false,"sum_hidden":false,"sum_comment_hidden":false,"sum_unclear":false,"sum_foreign":""},"58":{"sum_foreign_comment":"","sum":"","sum_comment":"","sum_hidden":false,"sum_comment_hidden":false,"sum_unclear":false,"sum_foreign":""},"59":{"sum_foreign_comment":"","sum":"","sum_comment":"","sum_foreign":""},"60":{"sum_foreign_comment":"","sum":"","sum_comment":"","sum_comment_unclear":false,"sum_hidden":false,"sum_comment_hidden":false,"sum_unclear":false,"sum_foreign":""},"61":{"sum_foreign_comment":"","sum":"","sum_hidden":false,"sum_comment":"","sum_foreign":""},"62":{"sum_foreign_comment":"","sum":"","sum_comment":"","sum_unclear":false,"sum_foreign":""},"63":{"sum_foreign_comment":"","sum":"","sum_comment":"","sum_hidden":false,"sum_comment_hidden":false,"sum_unclear":false,"sum_foreign":""},"64":{"sum_foreign_comment":"","sum":"","sum_comment":"","sum_hidden":false,"sum_comment_hidden":false,"sum_foreign":""}},"ft_src":"суддя орджонікідзевського районного суду м. маріуполя донецької області\nДонецька область\nЗагальний місцевий суд\nДмитро\nКозлова В. В\nПодружжя\nОлександрович\nКозлов Дмитро Олександрович\nДмитро Олександрович Козлов\nДмитро Козлов\nКозлов Дмитро Олександрович\nКозлов Дмитро Олександрович\nКозлов\n28689\n179119\n28689\n179119\n20000\n100000\n2014\n28689\n179119\n28689\n179119\n100000\n20000\n179119\n28689\n179119\n28689\nПодружжя\nКозлова В. В\nКозлов Дмитро Олександрович\nДмитро Олександрович Козлов\nДмитро Козлов\nКозлов Дмитро Олександрович\nКозлов Дмитро Олександрович\nДмитро\nОлександрович\nЗагальний місцевий суд\nДонецька область\nсуддя орджонікідзевського районного суду м. маріуполя донецької області\nКозлов\n2014\nПодружжя\nКозлова В. В\nОлександрович\nКозлов\nДмитро\nКозлов Дмитро Олександрович\nДмитро Олександрович Козлов\nДмитро Козлов\nКозлов Дмитро Олександрович\nДонецька область\nЗагальний місцевий суд\nсуддя орджонікідзевського районного суду м. маріуполя донецької області\nКозлов Дмитро Олександрович\n100000\n20000\n2014","general":{"inn":"","name":"Дмитро","inn_unclear":false,"family":[{"inn":"","inn_hidden":true,"relations_unclear":false,"relations_hidden":false,"relations_other":"","relations":"Подружжя","name_hidden":true,"inn_unclear":false,"family_name":"Козлова В. В","name_unclear":false}],"inn_hidden":true,"family_raw":"","last_name":"Козлов","post":{"post_unclear":false,"region_unclear":false,"post":"суддя орджонікідзевського районного суду м. маріуполя донецької області","office":"Загальний місцевий суд","region":"Донецька область","post_hidden":false,"office_hidden":false,"office_unclear":true,"region_hidden":false},"full_name_suggest":{"output":"Козлов Дмитро Олександрович","input":["Козлов Дмитро Олександрович","Дмитро Олександрович Козлов","Дмитро Козлов"]},"full_name":"Козлов Дмитро Олександрович","addresses":[{"place_city_type_hidden":true,"place_district_hidden":true,"place_city_type":"","place_city_hidden":true,"place_address_unclear":false,"place_address":"","place_hidden":true,"place":"","place_district":"","place_unclear":false,"place_city":"","place_address_hidden":true}],"patronymic":"Олександрович","last_name_unclear":false,"name_unclear":false},"source":"VULYK","intro":{"declaration_year":"2014","isnotdeclaration":""}}