{"income":{"5":{"value":"202186","family_comment":"","value_unclear":false,"family_hidden":false,"value_hidden":false,"family_unclear":false,"family":"15000","comment":"","family_comment_unclear":false},"6":{"value":"","family_comment":"","value_unclear":false,"comment_hidden":false,"family_hidden":false,"value_hidden":false,"family_unclear":false,"family":"15000","comment":""},"7":{"value":"","value_hidden":false,"family_comment":"","source_name":"","family":"","comment":"","source_name_hidden":false},"8":{"family_comment":"","value":"","family":"","comment":""},"9":{"value":"","comment_hidden":false,"value_hidden":false,"family_comment":"","family":"","comment":""},"10":{"value":"","value_unclear":false,"value_hidden":false,"family_comment":"","family":"","comment":""},"11":{"family_comment":"","value":"","family":"","comment":""},"12":{"family_comment":"","value":"","family":"","comment":""},"13":{"family_comment":"","value":"","family_hidden":false,"comment":"","family":""},"14":{"family_comment":"","value":"","family":"","comment":""},"15":{"family_comment":"","family_unclear":false,"value":"","family":"","comment":""},"16":{"family_comment":"","value":"","value_unclear":false,"family":"","comment":""},"17":{"family_comment":"","value":"","family":"","comment":""},"18":{"family_comment":"","value":"","family":"","comment":""},"19":{"family_comment":"","value":"","comment_unclear":false,"family":"","comment":""},"20":{"value":"","comment_unclear":false,"family_hidden":false,"value_hidden":false,"family_comment":"","family":"","comment":""}},"vehicle":{"35":[{"year_hidden":false,"brand_info":"2500 куб.см","sum_rent_comment":"","brand_info_unclear":false,"sum_rent_hidden":false,"year":"2012","sum_hidden":false,"brand_info_hidden":false,"sum_rent_comment_unclear":false,"year_unclear":false,"sum_rent":"","sum":"310000","brand":"Toyota Camry","sum_comment":"","sum_comment_unclear":false,"brand_hidden":false,"sum_unclear":false,"brand_unclear":false}]},"id":"vulyk_64_137","declaration":{"additional_info_text":"","notfull_lostpages":"","date":"2015-03-27T00:00:00","notfull":"","additional_info":"","url":"http://static.declarations.com.ua/declarations/chosen_ones/mega_batch/handzii_dmytro_mykolaiovych.pdf"},"liabilities":{"54":{"sum_foreign_comment":"","sum":"","sum_comment":"","sum_foreign_comment_hidden":false,"sum_hidden":false,"sum_comment_hidden":false,"sum_unclear":false,"sum_foreign":""},"55":{"sum_foreign_comment":"","sum":"","sum_comment":"","sum_comment_unclear":false,"sum_foreign":""},"56":{"sum_foreign_comment":"","sum":"","sum_comment":"","sum_unclear":false,"sum_foreign":""},"57":{"sum_foreign_comment":"","sum":"","sum_comment":"","sum_hidden":false,"sum_unclear":false,"sum_foreign":""},"58":{"sum_foreign_comment":"","sum":"","sum_comment":"","sum_unclear":false,"sum_foreign":""},"59":{"sum_foreign_comment":"","sum":"","sum_comment":"","sum_comment_unclear":false,"sum_comment_hidden":false,"sum_unclear":false,"sum_foreign":""},"60":{"sum_foreign_comment":"","sum":"","sum_comment":"","sum_foreign":""},"61":{"sum_foreign_comment":"","sum":"","sum_comment":"","sum_foreign":""},"62":{"sum_foreign_comment":"","sum":"","sum_comment":"","sum_unclear":false,"sum_foreign":""},"63":{"sum_foreign_comment":"","sum":"","sum_comment":"","sum_unclear":false,"sum_foreign":""},"64":{"sum_foreign_comment":"","sum":"","sum_comment":"","sum_comment_unclear":false,"sum_unclear":false,"sum_foreign":""}},"ft_src":"суддя овідіопольського районного суду одеської області\nОдеська область\nЗагальний місцевий суд\nДмитро\nГандзiй Ганна Олександрiвна\nПодружжя\nМиколайович\nГандзій Дмитро Миколайович\nГандзій\nГандзій Дмитро Миколайович\nДмитро Миколайович Гандзій\nДмитро Гандзій\nГандзій Дмитро Миколайович\n2500 куб.см\nToyota Camry\n2012\n310000\n144\n2014\n15000\n15000\n202186\n2500 куб.см\n310000\nToyota Camry\n2012\n144\nЗагальний місцевий суд\nОдеська область\nсуддя овідіопольського районного суду одеської області\nПодружжя\nГандзiй Ганна Олександрiвна\nГандзій Дмитро Миколайович\nДмитро Миколайович Гандзій\nДмитро Гандзій\nГандзій Дмитро Миколайович\nГандзій Дмитро Миколайович\nДмитро\nГандзій\nМиколайович\n15000\n202186\n15000\n2014\nПодружжя\nГандзiй Ганна Олександрiвна\nМиколайович\nГандзій\nДмитро\nГандзій Дмитро Миколайович\nДмитро Миколайович Гандзій\nДмитро Гандзій\nГандзій Дмитро Миколайович\nОдеська область\nЗагальний місцевий суд\nсуддя овідіопольського районного суду одеської області\nГандзій Дмитро Миколайович\nToyota Camry\n310000\n2500 куб.см\n2012\n202186\n15000\n15000\n144\n2014","general":{"inn":"","name":"Дмитро","last_name_hidden":false,"family":[{"inn":"","inn_hidden":true,"relations_unclear":false,"relations_hidden":false,"relations_other":"","relations":"Подружжя","name_hidden":false,"inn_unclear":false,"family_name":"Гандзiй Ганна Олександрiвна","name_unclear":false}],"patronymic":"Миколайович","inn_hidden":true,"family_raw":"","inn_unclear":false,"post":{"post_unclear":false,"post":"суддя овідіопольського районного суду одеської області","candidate":"","office_hidden":false,"region":"Одеська область","post_hidden":false,"office":"Загальний місцевий суд","office_unclear":false,"region_hidden":false},"last_name_unclear":false,"full_name":"Гандзій Дмитро Миколайович","addresses":[{"place_city_type_unclear":false,"place_address":"","place_district_hidden":false,"place_city_type":"","place_city_hidden":false,"place_city_type_hidden":false,"place":"","place_district":"","place_unclear":false,"place_city":"","place_city_unclear":false,"place_hidden":true,"place_address_hidden":false}],"last_name":"Гандзій","patronymic_hidden":false,"full_name_suggest":{"output":"Гандзій Дмитро Миколайович","input":["Гандзій Дмитро Миколайович","Дмитро Миколайович Гандзій","Дмитро Гандзій"]},"name_unclear":false},"source":"VULYK","estate":{"25":[{"region_unclear":false,"space_unclear":false,"costs":"","costs_rent_unclear":false,"costs_comment":"","costs_hidden":false,"address_hidden":false,"region_hidden":true,"space_comment":"","space_hidden":false,"space":"144","space_units_hidden":false,"costs_rent_comment_unclear":false,"region":"","costs_rent_comment":"","costs_rent_hidden":false,"space_comment_unclear":false,"space_units":"м²","address":"","costs_rent":"","costs_unclear":false}]},"intro":{"declaration_year":"2014","isnotdeclaration":"","declaration_year_unclear":false,"declaration_year_hidden":false}}