{"income":{"5":{"family_comment":"","family_unclear":false,"value":"290331","family":"22978","comment":""},"6":{"family_comment":"","family_unclear":false,"value":"","family":"20542","comment":""},"7":{"value":"","comment_hidden":false,"family_comment":"","source_name":"","family":"","comment":""},"8":{"family_comment":"","value":"","family":"","comment":""},"9":{"family_comment":"","value":"","family":"","comment":""},"10":{"family_comment":"","value":"","family":"2436","comment":""},"11":{"family_comment":"","value":"","value_unclear":false,"family":"","comment":""},"12":{"family_comment":"","value":"","family":"","comment":""},"13":{"family_comment":"","value":"","family":"","comment":""},"14":{"family_comment":"","value":"","family":"","comment":""},"15":{"family_comment":"","value":"","value_unclear":false,"family":"","comment":""},"16":{"family_comment":"","family_unclear":false,"value":"","family":"","comment":""},"17":{"family_comment":"","value":"","family":"","comment":""},"18":{"family_comment":"","value":"","family":"","comment":"","family_hidden":false},"19":{"family_comment":"","value":"","family":"","comment":""},"20":{"value":"","comment_unclear":false,"comment_hidden":false,"family_comment":"","family":"","comment":"","family_comment_hidden":false}},"vehicle":{"35":[{"brand_info":"1.4 куб. дм., 1450 кВт , 420.0 см","sum_rent_comment":"","year":"2006","brand_info_hidden":false,"brand_info_unclear":false,"year_unclear":false,"sum_rent":"","sum":"","brand":"Dacia Logan","sum_comment":"","brand_unclear":false,"brand_hidden":false}],"36":[{"brand_info":"2.5 куб. дм., 2600 кВт , 560.0 см","sum":"","brand":"ГАЗ 2752 Соболь","sum_comment":"","year":"2007","sum_rent_comment":"","sum_rent":""}]},"id":"vulyk_68_179","declaration":{"additional_info_text":"","notfull_lostpages":"","date":"2015-03-18T00:00:00","notfull":"","additional_info":"","url":"http://static.declarations.com.ua/declarations/chosen_ones/mega_batch/molchanov_viktor_andriiovych.pdf"},"liabilities":{"54":{"sum_foreign_comment":"","sum":"530","sum_comment":"","sum_comment_unclear":false,"sum_hidden":false,"sum_comment_hidden":false,"sum_unclear":false,"sum_foreign":""},"55":{"sum_foreign_comment":"","sum":"","sum_foreign":"","sum_comment":"","sum_hidden":false},"56":{"sum_foreign_comment":"","sum":"","sum_comment":"","sum_foreign":"","sum_foreign_hidden":false,"sum_unclear":false},"57":{"sum_foreign_comment":"","sum":"171000","sum_comment":"","sum_comment_unclear":false,"sum_hidden":false,"sum_comment_hidden":false,"sum_unclear":false,"sum_foreign":""},"58":{"sum_foreign_comment":"","sum":"","sum_comment":"","sum_hidden":false,"sum_comment_hidden":false,"sum_unclear":false,"sum_foreign":""},"59":{"sum_foreign_comment":"","sum":"","sum_comment":"","sum_foreign":""},"60":{"sum_foreign_comment":"","sum":"","sum_comment":"","sum_comment_unclear":false,"sum_hidden":false,"sum_comment_hidden":false,"sum_unclear":false,"sum_foreign":""},"61":{"sum_foreign_comment":"","sum":"","sum_foreign":"","sum_comment":"","sum_hidden":false},"62":{"sum_foreign_comment":"","sum":"","sum_comment":"","sum_unclear":false,"sum_foreign":""},"63":{"sum_foreign_comment":"","sum":"9960","sum_comment":"","sum_hidden":false,"sum_comment_hidden":false,"sum_unclear":false,"sum_foreign":""},"64":{"sum_foreign_comment":"","sum":"","sum_comment":"","sum_hidden":false,"sum_comment_hidden":false,"sum_foreign":""}},"ft_src":"1.4 куб. дм., 1450 кВт , 420.0 см\nDacia Logan\n2006\n2.5 куб. дм., 2600 кВт , 560.0 см\n2007\nГАЗ 2752 Соболь\nм. Краматорськ\nДонецька область\n26\nс. Софіївка, Олександрівський району\nДонецька область\n39\nДонецька область\nОлександрівський район\n1\n2\nОлександрівський р-н\nДонецька область\n1/2 частина житловогу будинку. Молчанов Евгеній Вікторович\nс. Софіївка, Олександрівского р-ну\nДонецька область\n57\n2014\n20542\n2436\n22978\n290331\n1.4 куб. дм., 1450 кВт , 420.0 см\nDacia Logan\n2006\n2.5 куб. дм., 2600 кВт , 560.0 см\nГАЗ 2752 Соболь\n2007\n2\nДонецька область\nОлександрівський р-н\nОлександрівський район\nДонецька область\n1\n57\n1/2 частина житловогу будинку. Молчанов Евгеній Вікторович\nс. Софіївка, Олександрівского р-ну\nДонецька область\n39\nс. Софіївка, Олександрівський району\nДонецька область\n26\nм. Краматорськ\nДонецька область\nПодружжя\nМолчанова Олена Тарасівна, 04. 07. 1961\nМолчанов Віктор Андрійович\nВіктор Андрійович Молчанов\nВіктор Молчанов\nМолчанов Віктор Андрійович\nМолчанов Віктор Андрійович\nВіктор\nАндрійович\nЗагальний місцевий суд\nДонецька область\nзаступник голови олександрівського районного суду донецької області\nМолчанов\nСело\nСофіївка\n84000\nДонецька область\nОлександрівський\n9960\n171000\n530\n20542\n290331\n22978\n2436\n2014\n171000\n530\n9960\nПодружжя\nМолчанова Олена Тарасівна, 04. 07. 1961\nАндрійович\nМолчанов\nВіктор\nМолчанов Віктор Андрійович\nВіктор Андрійович Молчанов\nВіктор Молчанов\nМолчанов Віктор Андрійович\nДонецька область\nСофіївка\nОлександрівський\nСело\n84000\nДонецька область\nЗагальний місцевий суд\nзаступник голови олександрівського районного суду донецької області\nМолчанов Віктор Андрійович","general":{"inn":"","name":"Віктор","last_name":"Молчанов","family":[{"inn":"","inn_hidden":true,"relations_unclear":false,"relations_hidden":false,"relations_other":"","relations":"Подружжя","name_hidden":false,"inn_unclear":false,"family_name":"Молчанова Олена Тарасівна, 04. 07. 1961","name_unclear":false}],"inn_hidden":true,"family_raw":"","inn_unclear":false,"post":{"post_unclear":false,"region_unclear":false,"post":"заступник голови олександрівського районного суду донецької області","post_hidden":false,"region":"Донецька область","region_hidden":false,"office":"Загальний місцевий суд","office_hidden":false,"office_unclear":false},"full_name_suggest":{"output":"Молчанов Віктор Андрійович","input":["Молчанов Віктор Андрійович","Віктор Андрійович Молчанов","Віктор Молчанов"]},"full_name":"Молчанов Віктор Андрійович","addresses":[{"place_address":"84000","place_district_hidden":false,"place_city_type":"Село","place_city_hidden":false,"place_address_unclear":false,"place_city_type_hidden":false,"place_city":"Софіївка","place":"Донецька область","place_district":"Олександрівський","place_unclear":false,"place_hidden":false,"place_address_hidden":true}],"patronymic":"Андрійович","last_name_unclear":false,"name_unclear":false},"source":"VULYK","estate":{"23":[{"costs":"","costs_comment":"","address_hidden":false,"region_hidden":false,"space_comment":"","space":"2","address":"Олександрівський р-н","region":"Донецька область","costs_rent_comment":"","space_comment_hidden":false,"space_units":"га","costs_rent":""}],"24":[{"region_unclear":false,"space_unclear":false,"costs":"","costs_comment":"","address_hidden":false,"region_hidden":false,"space_comment":"1/2 частина житловогу будинку. Молчанов Евгеній Вікторович","space":"57","address":"с. Софіївка, Олександрівского р-ну","region":"Донецька область","costs_rent_comment":"","space_units":"м²","costs_rent":""}],"29":[{"space_unclear":false,"costs_property_comment":"","address_hidden":false,"region_hidden":false,"space_comment":"","space_hidden":false,"space":"1","address":"Олександрівський район","region":"Донецька область","costs_property":"","space_units_unclear":false,"space_units":"га","space_units_hidden":false,"costs_rent":"","costs_rent_comment":""}],"30":[{"space_unclear":false,"address_hidden":false,"region_hidden":false,"space_comment":"","space_hidden":false,"space":"39","address":"с. Софіївка, Олександрівський району","region":"Донецька область","costs_property":"","costs_rent_comment":"","space_units":"м²","costs_property_comment":"","costs_rent":""}],"31":[{"space_unclear":false,"address_hidden":false,"region_hidden":false,"space_comment":"","space_hidden":false,"space":"26","address":"м. Краматорськ","region":"Донецька область","costs_property":"","costs_rent_comment":"","space_units":"м²","costs_property_comment":"","costs_rent":""}]},"intro":{"declaration_year":"2014","isnotdeclaration":""}}