{"income":{"5":{"value":"319015","family_unclear":false,"family_hidden":false,"family_comment":"","family":"24000","comment":""},"6":{"value":"256615","family_comment":"","value_unclear":false,"family_hidden":false,"family_unclear":false,"family":"9000","comment":""},"7":{"value":"","family_hidden":false,"value_hidden":false,"family_comment":"","source_name":"","family":"","comment":"","source_name_hidden":false},"8":{"family_comment":"","value":"","family":"","comment":""},"9":{"family_comment":"","value":"","family":"","comment":""},"10":{"family_comment":"","value":"","value_unclear":false,"family":"","comment":""},"11":{"family_comment":"","value":"","family":"","comment":""},"12":{"family_comment":"","value":"","family":"","comment":""},"13":{"family_comment":"","value":"","family":"","comment":""},"14":{"family_comment":"","value":"","family":"","comment":""},"15":{"family_comment":"","value":"","family":"","comment":""},"16":{"family_comment":"","value":"","family":"","comment":""},"17":{"family_comment":"","value":"","family":"","comment":""},"18":{"family_comment":"","value":"","family":"","comment":""},"19":{"family_comment":"","value":"","family":"","comment":""},"20":{"value":"62400","family_comment":"","value_unclear":false,"family_unclear":false,"comment_unclear":false,"comment":"","family":"15000"}},"id":"vulyk_74_148","banks":{"45":[{"sum_foreign_comment":"","sum":"160000","sum_comment":"","sum_comment_unclear":false,"sum_hidden":false,"sum_foreign_units":"UAH","sum_foreign_hidden":false,"sum_units":"UAH","sum_comment_hidden":false,"sum_unclear":false,"sum_foreign":""}],"51":[{"sum_foreign_comment":"","sum":"160000","sum_comment":"","sum_comment_unclear":false,"sum_hidden":false,"sum_foreign_units":"UAH","sum_foreign_hidden":false,"sum_units":"UAH","sum_comment_hidden":false,"sum_unclear":false,"sum_foreign":""}]},"declaration":{"additional_info_text":"","notfull_lostpages":"","date":"2014-03-27T00:00:00","notfull":"","additional_info":"","url":"http://static.declarations.com.ua/declarations/chosen_ones/judges_batch/1545_hlinin_borys_viktorovych.pdf"},"liabilities":{"54":{"sum_foreign_comment":"","sum":"","sum_comment":"","sum_comment_unclear":false,"sum_comment_hidden":false,"sum_foreign":""},"55":{"sum_foreign_comment":"","sum":"","sum_comment":"","sum_hidden":false,"sum_unclear":false,"sum_foreign":""},"56":{"sum_foreign_comment":"","sum":"","sum_comment":"","sum_hidden":false,"sum_unclear":false,"sum_foreign":""},"57":{"sum_foreign_comment":"","sum":"","sum_comment":"","sum_comment_unclear":false,"sum_comment_hidden":false,"sum_foreign":""},"58":{"sum_foreign_comment":"","sum_comment_hidden":false,"sum":"","sum_comment":"","sum_foreign":""},"59":{"sum_foreign_comment":"","sum":"","sum_comment":"","sum_foreign":""},"60":{"sum_foreign_comment":"","sum":"","sum_hidden":false,"sum_comment":"","sum_foreign":""},"61":{"sum_foreign_comment":"","sum":"","sum_comment":"","sum_foreign":""},"62":{"sum_foreign_comment":"","sum":"","sum_comment":"","sum_foreign":""},"63":{"sum_foreign_comment":"","sum":"","sum_comment":"","sum_comment_unclear":false,"sum_unclear":false,"sum_foreign":""},"64":{"sum_foreign_comment":"","sum":"","sum_comment":"","sum_comment_unclear":false,"sum_unclear":false,"sum_foreign":""}},"ft_src":"суддя апеляційного суду харківської області\nХарківська область\nЗагальний апеляційний суд\nГлінін Борис Вікторович\nГлінін\nБорис\nКрижанівська-глініна Л. О\nПодружжя\nРезвухіна О. Б\nДитина\nГлінін Борис Вікторович\nБорис Вікторович Глінін\nБорис Глінін\nГлінін Борис Вікторович\nВікторович\n600\n1000\n1500\n48\n63\n35\n40\n64.6\n160000\n160000\n2013\n2013\nЗагальний апеляційний суд\nХарківська область\nсуддя апеляційного суду харківської області\nВікторович\nГлінін Борис Вікторович\nБорис Вікторович Глінін\nБорис Глінін\nГлінін Борис Вікторович\nБорис\nПодружжя\nКрижанівська-глініна Л. О\nДитина\nРезвухіна О. Б\nГлінін Борис Вікторович\nГлінін\n9000\n256615\n62400\n15000\n319015\n24000\n1500\n600\n1000\n63\n35\n40\n48\n64.6\n160000\n160000\n9000\n256615\n24000\n319015\n15000\n62400\nПодружжя\nКрижанівська-глініна Л. О\nДитина\nРезвухіна О. Б\nВікторович\nГлінін\nХарківська область\nЗагальний апеляційний суд\nсуддя апеляційного суду харківської області\nГлінін Борис Вікторович\nГлінін Борис Вікторович\nБорис Вікторович Глінін\nБорис Глінін\nГлінін Борис Вікторович\nБорис\n62400\n15000\n319015\n24000\n256615\n9000\n63\n35\n40\n1500\n48\n64.6\n600\n1000\n160000\n160000\n2013","general":{"inn":"","family_raw":"","last_name":"Глінін","post":{"region_unclear":false,"region":"Харківська область","post":"суддя апеляційного суду харківської області","office":"Загальний апеляційний суд","office_unclear":false,"post_hidden":false},"name":"Борис","full_name":"Глінін Борис Вікторович","inn_hidden":false,"family":[{"inn":"","relations":"Подружжя","relations_other":"","inn_hidden":false,"family_name":"Крижанівська-глініна Л. О","name_hidden":false,"name_unclear":false},{"inn":"","relations":"Дитина","relations_other":"","inn_hidden":false,"family_name":"Резвухіна О. Б","name_hidden":false,"name_unclear":false}],"full_name_suggest":{"output":"Глінін Борис Вікторович","input":["Глінін Борис Вікторович","Борис Вікторович Глінін","Борис Глінін"]},"patronymic":"Вікторович"},"source":"VULYK","estate":{"23":[{"space_hidden":false,"costs":"","costs_comment":"","address_hidden":false,"region_hidden":false,"space_comment":"","space_unclear":false,"space":"1500","address":"","region":"","space_units_unclear":false,"space_comment_unclear":false,"space_units":"м²","costs_rent":"","costs_rent_comment":""}],"25":[{"space_hidden":false,"costs":"","costs_comment":"","address_hidden":false,"region_hidden":false,"space_comment":"","space_unclear":false,"space":"64.6","address":"","region":"","costs_rent_comment":"","space_units":"м²","costs_rent":""}],"29":[{"costs_rent":"","region":"","costs_property":"","costs_rent_comment":"","address_hidden":false,"region_hidden":false,"space_comment":"","costs_property_comment":"","space_units":"м²","space":"600","address":""},{"costs_rent":"","region":"","costs_property":"","costs_rent_comment":"","region_hidden":false,"space_comment":"","costs_property_comment":"","space_units":"м²","space":"1000","address":""}],"31":[{"space_unclear":false,"address_hidden":false,"region_hidden":false,"space_comment":"","space":"63","address":"","region":"","costs_property":"","costs_rent_comment":"","address_unclear":false,"space_units":"м²","costs_property_comment":"","costs_rent":""},{"space_unclear":false,"address_hidden":false,"region_hidden":false,"space_comment":"","space":"35","address":"","region":"","costs_property":"","costs_rent_comment":"","space_units":"м²","costs_property_comment":"","costs_rent":""},{"costs_rent":"","region":"","costs_property":"","costs_rent_comment":"","space_comment":"","costs_property_comment":"","space_units":"м²","space":"40","address":""}],"34":[{"costs_rent":"","region":"","costs_property":"","costs_rent_comment":"","address_hidden":false,"region_hidden":false,"space_comment":"","costs_property_comment":"","space_units":"м²","space":"48","address":""}]},"intro":{"declaration_year":"2013","isnotdeclaration":"","declaration_year_unclear":false}}