{"income":{"5":{"value":"488664","family_comment":"","value_unclear":false,"family_hidden":false,"value_hidden":false,"family_unclear":false,"comment_unclear":false,"comment":"","family":""},"6":{"value":"250491","family_comment":"","value_unclear":false,"family_hidden":false,"value_hidden":false,"family_unclear":false,"comment_unclear":false,"comment":"","family":""},"7":{"source_name_unclear":false,"value":"710","family_comment":"","source_name":"","family":"","comment":""},"8":{"family_comment":"","value":"","family":"","comment":""},"9":{"value":"31","value_unclear":false,"comment_hidden":false,"family_comment":"","comment_unclear":false,"comment":"","family":""},"10":{"value":"","comment_unclear":false,"value_hidden":false,"family_comment":"","family":"","comment":""},"11":{"family_comment":"","value":"","family":"","comment":""},"12":{"family_comment":"","value":"","family":"","comment":""},"13":{"family_comment":"","value":"","family":"","comment":""},"14":{"family_comment":"","value":"","family":"","comment":""},"15":{"family_comment":"","value":"","family":"","comment":""},"16":{"family_comment":"","value":"237432","family":"","comment":""},"17":{"family_comment":"","value":"","family":"","comment":""},"18":{"value":"","family_hidden":false,"value_hidden":false,"family_comment":"","family":"","comment":""},"19":{"family_comment":"","value":"","family":"","comment":""},"20":{"value":"","family_comment":"","value_unclear":false,"family_hidden":false,"value_hidden":false,"family_unclear":false,"family":"","comment":""}},"vehicle":{"35":[{"year_hidden":false,"brand_info":"1.6","sum_rent_comment":"","year":"2013","brand_info_unclear":false,"year_unclear":false,"sum_rent":"28000","sum":"","brand":"Toyota Corolla","sum_comment":"","brand_unclear":true,"brand_hidden":false}]},"id":"vulyk_66_195","banks":{"45":[{"sum_foreign_comment":"","sum_units":"UAH","sum_units_hidden":false,"sum_comment":"","sum_comment_unclear":true,"sum_hidden":false,"sum_foreign_units":"UAH","sum_comment_hidden":false,"sum_unclear":false,"sum":"50000","sum_foreign":""}],"46":[{"sum_foreign_comment":"","sum_units":"UAH","sum_comment":"","sum_foreign_units":"UAH","sum":"50000","sum_foreign":""}]},"declaration":{"additional_info_text":"","notfull_lostpages":"","date":"2015-03-30T00:00:00","notfull":"","additional_info":"","url":"http://static.declarations.com.ua/declarations/chosen_ones/mega_batch/biletska_liudmyla_mykolaivna.pdf"},"liabilities":{"54":{"sum_foreign_comment":"","sum":"2904","sum_comment":"","sum_comment_unclear":false,"sum_comment_hidden":false,"sum_unclear":false,"sum_foreign":""},"55":{"sum_foreign_comment":"","sum":"","sum_comment":"","sum_foreign":""},"56":{"sum_foreign_comment":"","sum_foreign_hidden":false,"sum_comment":"","sum_hidden":false,"sum_comment_hidden":false,"sum":"92000","sum_foreign":""},"57":{"sum_foreign_comment":"","sum":"","sum_comment":"","sum_comment_unclear":false,"sum_hidden":false,"sum_comment_hidden":false,"sum_unclear":false,"sum_foreign":""},"58":{"sum_foreign_comment":"","sum":"","sum_comment":"","sum_comment_unclear":false,"sum_unclear":false,"sum_foreign":""},"59":{"sum_foreign_comment":"","sum_foreign_hidden":false,"sum_comment":"","sum_comment_unclear":false,"sum_hidden":false,"sum":"","sum_foreign":""},"60":{"sum_foreign_comment":"","sum":"","sum_comment":"","sum_comment_unclear":false,"sum_foreign":""},"61":{"sum_foreign_comment":"","sum":"","sum_comment":"","sum_foreign":""},"62":{"sum_foreign_comment":"","sum_foreign_hidden":false,"sum_comment":"","sum_hidden":false,"sum":"","sum_unclear":false,"sum_foreign":""},"63":{"sum_foreign_comment":"","sum":"","sum_comment":"","sum_comment_unclear":false,"sum_comment_hidden":false,"sum_unclear":false,"sum_foreign":""},"64":{"sum_foreign_comment":"","sum":"","sum_comment":"","sum_comment_unclear":false,"sum_foreign":""}},"ft_src":"2904\n92000\nсуддя дніпропетровського апеляційного господарського суду\nДніпропетровська область\nАпеляційний господарський суд\nЛюдмила\nМиколаївна\nБілецька Людмила Миколаївна\nЛюдмила Миколаївна Білецька\nЛюдмила Білецька\nБілецька Людмила Миколаївна\nБілецька Людмила Миколаївна\nБілецька\n1.6\nToyota Corolla\n2013\n28000\n50000\n50000\n2014\n1.6\n28000\nToyota Corolla\n2013\n50000\n50000\n47\n64000\nБілецька Людмила Миколаївна\nЛюдмила Миколаївна Білецька\nЛюдмила Білецька\nБілецька Людмила Миколаївна\nЛюдмила\nБілецька Людмила Миколаївна\nБілецька\nАпеляційний господарський суд\nсуддя дніпропетровського апеляційного господарського суду\nДніпропетровська область\nМиколаївна\n92000\n2904\n710\n250491\n488664\n237432\n31\n2014\n92000\n2904\n64000\n47\nМиколаївна\nБілецька\nЛюдмила\nБілецька Людмила Миколаївна\nЛюдмила Миколаївна Білецька\nЛюдмила Білецька\nБілецька Людмила Миколаївна\nДніпропетровська область\nсуддя дніпропетровського апеляційного господарського суду\nАпеляційний господарський суд\nБілецька Людмила Миколаївна\n250491\n710\n488664\n237432\n31\n28000\nToyota Corolla\n1.6\n2013\n488664\n237432\n710\n31\n250491\n47\n64000\n50000\n50000\n2014","general":{"inn":"","name":"Людмила","last_name_hidden":false,"last_name":"Білецька","patronymic":"Миколаївна","inn_hidden":true,"family_raw":"","inn_unclear":false,"post":{"post_unclear":false,"post":"суддя дніпропетровського апеляційного господарського суду","candidate":"","office_hidden":false,"region":"Дніпропетровська область","office":"Апеляційний господарський суд","office_unclear":false},"full_name_suggest":{"output":"Білецька Людмила Миколаївна","input":["Білецька Людмила Миколаївна","Людмила Миколаївна Білецька","Людмила Білецька"]},"full_name":"Білецька Людмила Миколаївна","addresses":[{"place_city_type_unclear":false,"place_address":"","place_district_hidden":false,"place_city_type":"","place_address_hidden":true,"place_address_unclear":false,"place_city_type_hidden":false,"place":"","place_district":"","place_unclear":false,"place_city":"","place_city_unclear":false,"place_hidden":true,"place_city_hidden":false,"place_district_unclear":false}],"last_name_unclear":false},"source":"VULYK","estate":{"24":[{"space_unclear":false,"costs":"","costs_comment":"","costs_hidden":false,"address_hidden":false,"region_hidden":true,"space_comment":"","space_hidden":false,"space":"","address":"","region":"","address_unclear":false,"costs_rent_comment":"","costs_rent_hidden":false,"space_comment_unclear":false,"space_units":"м²","costs_rent":""}],"25":[{"region_unclear":false,"space_hidden":false,"costs":"","costs_comment":"","costs_hidden":false,"address_hidden":false,"region_hidden":true,"space_comment":"","space_unclear":false,"space":"47","space_units_hidden":false,"region":"","address_unclear":false,"costs_rent_comment":"","space_comment_unclear":false,"space_units":"м²","address":"","costs_rent":"64000"}]},"intro":{"declaration_year":"2014","isnotdeclaration":"","declaration_year_unclear":false}}