{"income":{"5":{"family_comment":"","value":"223335.12","family":"","comment":""},"6":{"family_comment":"","value":"223335.12","value_unclear":false,"family":"","comment":""},"7":{"value":"","family_comment":"","source_name":"","family":"","comment":"","source_name_hidden":false},"8":{"family_comment":"","value":"","family":"","comment":""},"9":{"family_comment":"","value":"","family":"","comment":""},"10":{"family_comment":"","value":"","family":"","comment":""},"11":{"family_comment":"","value":"","comment_hidden":false,"family":"","comment":""},"12":{"family_comment":"","value":"","family":"","comment":""},"13":{"family_comment":"","value":"","family":"","comment":""},"14":{"family_comment":"","value":"","family":"","comment":""},"15":{"value":"","family_comment":"","value_unclear":false,"family_unclear":false,"family":"","comment":""},"16":{"family_comment":"","value":"","family":"","comment":""},"17":{"family_comment":"","value":"","family":"","comment":""},"18":{"family_comment":"","value":"","family":"","comment":""},"19":{"family_comment":"","value":"","family":"","comment":""},"20":{"family_comment":"","value":"","comment_unclear":false,"family":"","comment":""}},"vehicle":{"35":[{"brand_info":"1.8 куб. см., 148 кВт","sum_rent_comment":"","brand":"Honda Civic SD","sum_comment":"","year":"2008","brand_hidden":false,"brand_info_unclear":false,"sum":"","sum_rent":""}]},"id":"vulyk_104_89","banks":{"45":[{"sum_foreign_comment":"","sum_units":"UAH","sum_comment":"","sum_hidden":false,"sum_foreign_units":"UAH","sum_foreign_hidden":false,"sum_comment_hidden":false,"sum_unclear":false,"sum":"1953","sum_foreign":""}]},"declaration":{"date":"2016-03-24T00:00:00","additional_info_text":"","additional_info":"","url":"http://static.declarations.com.ua/declarations/chosen_ones/judges_batch/1887_matviienko_iuliia_oleksandrivna_2015.pdf"},"liabilities":{"54":{"sum_foreign_comment":"","sum_foreign_hidden":false,"sum_comment":"","sum_hidden":false,"sum_comment_hidden":false,"sum_unclear":false,"sum":"","sum_foreign":""},"55":{"sum_foreign_comment":"","sum":"","sum_comment":"","sum_foreign":""},"56":{"sum_foreign_comment":"","sum":"","sum_comment":"","sum_unclear":false,"sum_foreign":""},"57":{"sum_foreign_comment":"","sum_foreign_hidden":false,"sum_comment":"","sum_comment_unclear":false,"sum_comment_hidden":false,"sum":"","sum_foreign":""},"58":{"sum_foreign_comment":"","sum":"","sum_comment":"","sum_unclear":false,"sum_foreign":""},"59":{"sum_foreign_comment":"","sum":"","sum_comment":"","sum_foreign":""},"60":{"sum_foreign_comment":"","sum_foreign_hidden":false,"sum_comment":"","sum_comment_hidden":false,"sum":"","sum_foreign":""},"61":{"sum_foreign_comment":"","sum":"","sum_comment":"","sum_foreign":""},"62":{"sum_foreign_comment":"","sum":"","sum_comment":"","sum_foreign":""},"63":{"sum_foreign_comment":"","sum":"","sum_comment":"","sum_foreign":""},"64":{"sum_foreign_comment":"","sum":"","sum_comment":"","sum_foreign":""}},"ft_src":"Матвієнко Юлія Олександрівна\nсуддя апеляційного суду київської області\nКиївська область\nЗагальний апеляційний суд\nЮлія\nМатвієнко Валерія Олександрівна, 30. 12. 1999\nДитина\nМатвієнко Юлія Олександрівна\nЮлія Олександрівна Матвієнко\nЮлія Матвієнко\nМатвієнко Юлія Олександрівна\nМатвієнко\nОлександрівна\n2008\nHonda Civic SD\n1.8 куб. см., 148 кВт\n1953\n2015\n1.8 куб. см., 148 кВт\nHonda Civic SD\n2008\n1953\n2015\nДитина\nМатвієнко Валерія Олександрівна, 30. 12. 1999\nМатвієнко\nМатвієнко Юлія Олександрівна\nЮлія Олександрівна Матвієнко\nЮлія Матвієнко\nМатвієнко Юлія Олександрівна\nМатвієнко Юлія Олександрівна\nЮлія\nОлександрівна\nЗагальний апеляційний суд\nсуддя апеляційного суду київської області\nКиївська область\n223335.12\n223335.12\n1000\n68\n68\n1000\n68\n68\nДитина\nМатвієнко Валерія Олександрівна, 30. 12. 1999\nОлександрівна\nМатвієнко\nсуддя апеляційного суду київської області\nЗагальний апеляційний суд\nКиївська область\nМатвієнко Юлія Олександрівна\nМатвієнко Юлія Олександрівна\nЮлія Олександрівна Матвієнко\nЮлія Матвієнко\nМатвієнко Юлія Олександрівна\nЮлія\n223335.12\n223335.12\n2008\n1.8 куб. см., 148 кВт\nHonda Civic SD\n223335.12\n223335.12\n68\n1000\n68\n1953\n2015","general":{"inn":"","inn_hidden":true,"last_name":"Матвієнко","post":{"region":"Київська область","region_unclear":false,"post":"суддя апеляційного суду київської області","office_unclear":false,"office":"Загальний апеляційний суд"},"name":"Юлія","full_name":"Матвієнко Юлія Олександрівна","family_raw":"","addresses":[{"place_district":"","place_city_hidden":true,"place_city":"","place_city_type_hidden":false,"place_district_hidden":false,"place_city_type":"","place_address_hidden":true,"place_address":"","place_hidden":true,"place":""}],"family":[{"inn":"","relations":"Дитина","relations_other":"","inn_hidden":true,"family_name":"Матвієнко Валерія Олександрівна, 30. 12. 1999","name_hidden":false,"name_unclear":false}],"full_name_suggest":{"output":"Матвієнко Юлія Олександрівна","input":["Матвієнко Юлія Олександрівна","Юлія Олександрівна Матвієнко","Юлія Матвієнко"]},"patronymic":"Олександрівна"},"source":"VULYK","estate":{"23":[{"space_hidden":false,"costs":"","costs_comment":"","address_hidden":false,"region_hidden":true,"space_comment":"","space":"1000","address":"","region":"","costs_rent_comment":"","space_comment_unclear":false,"space_units":"м²","costs_rent":""}],"25":[{"costs":"","costs_comment":"","address_hidden":false,"region_hidden":true,"space_comment":"","space":"68","address":"","costs_unclear":false,"region":"","costs_rent_comment":"","space_comment_unclear":false,"space_units":"м²","costs_rent":""}],"31":[{"space_unclear":false,"address_hidden":false,"region_hidden":true,"space_comment":"","space_hidden":false,"space":"68","address":"","region":"","costs_property":"","costs_rent_comment":"","space_units":"м²","costs_property_comment":"","costs_rent":""}]},"intro":{"declaration_year":"2015","isnotdeclaration":""}}