{"income":{"5":{"family_comment":"","value":"180195","family":"889880","comment":""},"6":{"value":"180195","family_comment":"","value_unclear":false,"comment_hidden":false,"family_unclear":false,"family":"24000","comment":""},"7":{"family_comment":"","value":"","source_name":"","family":"","comment":""},"8":{"family_comment":"","value":"","family":"","comment":""},"9":{"family_comment":"","family_unclear":false,"value":"","family":"","comment":""},"10":{"family_comment":"","value":"","value_unclear":false,"family":"","comment":""},"11":{"family_comment":"","value":"","family":"","comment":""},"12":{"family_comment":"","value":"","family":"","comment":""},"13":{"family_comment":"","value":"","family":"","comment":""},"14":{"family_comment":"","value":"","family":"","comment":""},"15":{"family_comment":"","value":"","family":"","comment":""},"16":{"family_comment":"","value":"","family":"140000","comment":""},"17":{"family_comment":"","value":"","family":"720800","comment":""},"18":{"family_comment":"","value":"","family":"","comment":""},"19":{"family_comment":"","value":"","family":"","comment":""},"20":{"value":"","family":"5080","value_unclear":false,"family_hidden":false,"family_comment":"","comment_unclear":false,"comment":"","family_comment_unclear":false}},"vehicle":{"35":[{"year_hidden":false,"brand_info":"2.4","sum_rent_comment":"","year":"","brand_info_hidden":false,"brand_info_unclear":false,"sum_rent":"","sum":"","brand":"ГАЗ 24","sum_comment":"","brand_unclear":false,"brand_hidden":false},{"brand_info":"керування","sum_rent_comment":"","brand":"Toyota Land Cruiser","sum_comment":"","brand_unclear":false,"year":"","brand_info_hidden":true,"brand_info_unclear":false,"year_unclear":false,"sum":"","sum_rent":""},{"brand_info":"2.97, керування","sum_rent_comment":"","brand":"BMW X5","sum_comment":"","year":"2005","sum":"","sum_rent":""},{"brand_info":"2.7, керування","sum_rent_comment":"","brand":"Hyundai Tucson","sum_comment":"","year":"2008","sum":"","sum_rent":""}],"40":[{"brand_info":"2.97","sum_rent_comment":"","brand":"BMW X5","sum_comment":"","brand_unclear":false,"year":"2005","brand_info_unclear":false,"year_unclear":false,"sum":"","sum_rent":""},{"brand_info":"2.7","sum_rent_comment":"","brand":"Hyundai Tucson","sum_comment":"","year":"2005","sum":"","sum_rent":""},{"brand_info":"6.2","sum_rent_comment":"","brand":"Mercedes-Benz","sum_comment":"","year":"2008","sum":"","sum_rent":""},{"brand_info":"","sum_rent_comment":"","brand":"Toyota Land Cruiser","sum_comment":"","year":"2014","brand_info_hidden":true,"sum":"","sum_rent":""}]},"id":"vulyk_97_103","banks":{"51":[{"sum_foreign_comment":"","sum_units":"UAH","sum_comment":"","sum_comment_unclear":false,"sum_hidden":false,"sum_foreign_units":"UAH","sum_comment_hidden":true,"sum_unclear":false,"sum":"5","sum_foreign":""}],"53":[{"sum_foreign_comment":"","sum_units":"UAH","sum_comment":"","sum_foreign_units":"UAH","sum_comment_hidden":false,"sum":"19200","sum_foreign":""}]},"declaration":{"additional_info_text":"","notfull_lostpages":"","date":"2015-03-31T00:00:00","notfull":"","additional_info":"","url":"http://static.declarations.com.ua/declarations/chosen_ones/judges_batch/4004_izovitova-vakim_olena_vasylivna.pdf"},"liabilities":{"54":{"sum_foreign_comment":"","sum":"","sum_comment":"","sum_comment_unclear":false,"sum_hidden":false,"sum_comment_hidden":false,"sum_unclear":false,"sum_foreign":""},"55":{"sum_foreign_comment":"","sum":"","sum_comment":"","sum_foreign":""},"56":{"sum_foreign_comment":"","sum":"","sum_comment":"","sum_foreign":""},"57":{"sum_foreign_comment":"","sum":"","sum_comment":"","sum_comment_unclear":false,"sum_hidden":false,"sum_comment_hidden":false,"sum_unclear":false,"sum_foreign":""},"58":{"sum_foreign_comment":"","sum":"","sum_comment":"","sum_comment_unclear":false,"sum_hidden":false,"sum_comment_hidden":false,"sum_unclear":false,"sum_foreign":""},"59":{"sum_foreign_comment":"","sum":"","sum_comment":"","sum_foreign":""},"60":{"sum_foreign_comment":"","sum":"","sum_comment":"","sum_comment_unclear":false,"sum_hidden":false,"sum_comment_hidden":false,"sum_foreign":""},"61":{"sum_foreign_comment":"","sum":"","sum_comment":"","sum_foreign":""},"62":{"sum_foreign_comment":"","sum":"","sum_comment":"","sum_unclear":false,"sum_foreign":""},"63":{"sum_foreign_comment":"","sum":"","sum_hidden":false,"sum_comment":"","sum_foreign":""},"64":{"sum_foreign_comment":"","sum":"","sum_comment":"","sum_foreign":""}},"ft_src":"Київ\n02097\nм. Київ\nсуддя харківського окружного адміністративного суду\nХарківська область\nАдміністративний місцевий суд\nОлена\nВакім Е. Ю\nПодружжя\nВакім В. Е\nДитина\nВакім Е. Е\nДитина\nВасилівна\nІзовітова-Вакім Олена Василівна\nОлена Василівна Ізовітова-Вакім\nОлена Ізовітова-Вакім\nІзовітова-Вакім Олена Василівна\nІзовітова-Вакім Олена Василівна\nІзовітова-Вакім\n2.4\nГАЗ 24\nToyota Land Cruiser\nкерування\n2.97, керування\n2005\nBMW X5\n2.7, керування\n2008\nHyundai Tucson\nBMW X5\n2.97\n2005\n2.7\n2005\nHyundai Tucson\n6.2\n2008\nMercedes-Benz\n2014\nToyota Land Cruiser\nХарківський р-н, с. Покотилівка\n60.5\nХарківська область\n17.3\nм. Київ\nХарківський р-н, с. Покотилівка\nХарківська область\n60.5\nХарківський р-н, с. Покотилівка\n155.6\nХарківська область\nХарківська область\nХарківський р-н, с. Покотилівка\n158.4\nХарківський р-н, с. Покотилівка\nХарківська область\n1300\nХарківський р-н, с. Покотилівка\n1300\nХарківська область\nХарківський р-н, с. Покотилівка\nХарківська область\n155.6\nХарківська область\nХарківський р-н, с. Покотилівка\n158.4\nм. Харків\nХарківська область\n138\nХарківська область\nм. Харків\n866.16\nЛіван, Бейрут\n212\n89\nм. Київ\n160.4\nм. Київ\n140/300 часток\nм. Харків\n69.7\nХарківська область\nкористування\nм.Київ\n89\nм. Київ\n19200\n5\n2014\n2.4\nГАЗ 24\nToyota Land Cruiser\nкерування\n2.97, керування\n2005\nBMW X5\n2.7, керування\n2008\nHyundai Tucson\n2.97\nBMW X5\n2005\n2.7\n2005\nHyundai Tucson\n6.2\n2008\nMercedes-Benz\n2014\nToyota Land Cruiser\n2014\nІзовітова-Вакім Олена Василівна\nОлена Василівна Ізовітова-Вакім\nОлена Ізовітова-Вакім\nІзовітова-Вакім Олена Василівна\nОлена\nПодружжя\nВакім Е. Ю\nДитина\nВакім В. Е\nДитина\nВакім Е. Е\nІзовітова-Вакім Олена Василівна\nІзовітова-Вакім\nАдміністративний місцевий суд\nХарківська область\nсуддя харківського окружного адміністративного суду\nВасилівна\nм. Київ\n02097\nКиїв\n180195\n24000\n720800\n5080\n180195\n889880\n140000\n60.5\nХарківська область\nХарківський р-н, с. Покотилівка\nм. Київ\n17.3\n155.6\nХарківська область\nХарківський р-н, с. Покотилівка\n158.4\nХарківська область\nХарківський р-н, с. Покотилівка\n160.4\nм. Київ\n69.7\n140/300 часток\nХарківська область\nм. Харків\nм. Київ\n89\nкористування\nм.Київ\n1300\nХарківська область\nХарківський р-н, с. Покотилівка\n1300\nХарківський р-н, с. Покотилівка\nХарківська область\n60.5\nХарківська область\nХарківський р-н, с. Покотилівка\n155.6\nХарківська область\nХарківський р-н, с. Покотилівка\n158.4\nХарківська область\nХарківський р-н, с. Покотилівка\n89\nм. Київ\n138\nХарківська область\nм. Харків\n866.16\nХарківська область\nм. Харків\n212\nЛіван, Бейрут\n19200\n5\n24000\n180195\n889880\n180195\n140000\n720800\n5080\nПодружжя\nВакім Е. Ю\nВакім В. Е\nДитина\nДитина\nВакім Е. Е\nВасилівна\nІзовітова-Вакім\nОлена\nІзовітова-Вакім Олена Василівна\nОлена Василівна Ізовітова-Вакім\nОлена Ізовітова-Вакім\nІзовітова-Вакім Олена Василівна\n02097\nКиїв\nм. Київ\nХарківська область\nАдміністративний місцевий суд\nсуддя харківського окружного адміністративного суду\nІзовітова-Вакім Олена Василівна\nГАЗ 24\n2.4\nToyota Land Cruiser\nкерування\nBMW X5\n2.97, керування\n2005\nHyundai Tucson\n2.7, керування\n2008\n2005\n2.97\nBMW X5\nHyundai Tucson\n2.7\n2005\nMercedes-Benz\n6.2\n2008\nToyota Land Cruiser\n2014\n5080\n889880\n180195\n140000\n720800\n180195\n24000\nм. Київ\n89\nХарківський р-н, с. Покотилівка\nХарківська область\n1300\nХарківський р-н, с. Покотилівка\nХарківська область\n155.6\nХарківський р-н, с. Покотилівка\nХарківська область\n158.4\nм. Харків\nХарківська область\n138\nм. Харків\nХарківська область\n866.16\nЛіван, Бейрут\n212\nХарківський р-н, с. Покотилівка\nХарківська область\n60.5\nм. Київ\n17.3\nХарківський р-н, с. Покотилівка\nХарківська область\n155.6\nХарківський р-н, с. Покотилівка\nХарківська область\n158.4\nХарківський р-н, с. Покотилівка\nХарківська область\n60.5\nм. Київ\n160.4\n140/300 часток\nм. Харків\nХарківська область\n69.7\nкористування\nм.Київ\nм. Київ\n89\nХарківський р-н, с. Покотилівка\nХарківська область\n1300\n5\n19200\n2014","general":{"name_hidden":false,"name":"Олена","last_name_hidden":false,"inn":"","family":[{"inn":"","relations":"Подружжя","relations_other":"","inn_hidden":true,"family_name":"Вакім Е. Ю","name_hidden":true,"name_unclear":false},{"inn_hidden":true,"inn":"","name_hidden":false,"family_name":"Вакім В. Е","relations":"Дитина","name_unclear":false},{"inn":"","relations":"Дитина","relations_other":"","inn_hidden":true,"family_name":"Вакім Е. Е","name_hidden":false,"name_unclear":false}],"patronymic":"Василівна","inn_hidden":true,"family_raw":"","inn_unclear":false,"post":{"region_unclear":false,"region":"Харківська область","post":"суддя харківського окружного адміністративного суду","office":"Адміністративний місцевий суд","office_unclear":false,"post_hidden":false},"full_name":"Ізовітова-Вакім Олена Василівна","addresses":[{"place_district":"","place_city_hidden":false,"place_city":"Київ","place_city_unclear":false,"place_district_hidden":false,"place_city_type":"Місто","place_address_hidden":true,"place_city_type_hidden":false,"place_address":"02097","place_hidden":false,"place":"м. Київ"}],"last_name":"Ізовітова-Вакім","patronymic_hidden":false,"full_name_suggest":{"output":"Ізовітова-Вакім Олена Василівна","input":["Ізовітова-Вакім Олена Василівна","Олена Василівна Ізовітова-Вакім","Олена Ізовітова-Вакім"]}},"source":"VULYK","estate":{"23":[{"region_unclear":false,"space_unclear":false,"costs":"","costs_rent_unclear":false,"costs_comment":"","address_hidden":true,"region_hidden":false,"space_comment":"","space":"1300","address":"Харківський р-н, с. Покотилівка","region":"Харківська область","address_unclear":false,"costs_rent_comment":"","space_units":"м²","costs_rent":""}],"24":[{"region_unclear":false,"space_unclear":false,"costs":"","costs_comment":"","address_hidden":true,"region_hidden":false,"space_comment":"","space_hidden":false,"space":"155.6","address":"Харківський р-н, с. Покотилівка","region":"Харківська область","address_unclear":false,"costs_rent_comment":"","space_comment_unclear":false,"space_units":"м²","costs_rent":""},{"costs_rent":"","space_unclear":false,"region":"Харківська область","costs":"","costs_rent_comment":"","costs_comment":"","region_hidden":false,"space_comment":"","space_units":"м²","space":"158.4","address":"Харківський р-н, с. Покотилівка"}],"25":[{"region_unclear":false,"space_unclear":false,"costs":"","costs_comment":"","address_hidden":false,"region_hidden":false,"space_comment":"","space_hidden":false,"space":"160.4","address":"","region":"м. Київ","costs_rent_comment":"","space_comment_unclear":false,"space_comment_hidden":false,"space_units":"м²","costs_rent":""},{"space_unclear":false,"costs":"","costs_comment":"","address_hidden":true,"space_comment":"140/300 часток","space":"69.7","address":"м. Харків","region":"Харківська область","costs_rent_comment":"","space_comment_unclear":false,"space_units":"м²","costs_rent":""},{"costs_rent":"","region":"м. Київ","costs":"","costs_rent_comment":"","costs_comment":"","address_hidden":true,"space_comment":"користування","space_units":"м²","space":"89","address":"м.Київ"}],"27":[{"region_unclear":false,"costs":"","costs_comment":"","address_hidden":false,"region_hidden":false,"space_comment":"","space":"60.5","address":"Харківський р-н, с. Покотилівка","region":"Харківська область","costs_rent_comment":"","space_units":"м²","costs_rent":""},{"costs_rent":"","region":"м. Київ","costs":"","costs_rent_comment":"","costs_comment":"","address_hidden":true,"space_comment":"","space_units":"м²","space":"17.3","address":""}],"29":[{"region_unclear":false,"space_unclear":false,"address_hidden":true,"region_hidden":false,"space_comment":"","space":"1300","address":"Харківський р-н, с. Покотилівка","region":"Харківська область","costs_property":"","costs_rent_comment":"","space_comment_unclear":false,"address_unclear":false,"space_units":"м²","costs_property_comment":"","costs_rent":""}],"30":[{"address_hidden":true,"region_hidden":false,"space_comment":"","space":"155.6","address":"Харківський р-н, с. Покотилівка","region":"Харківська область","costs_property":"","costs_rent_comment":"","address_unclear":false,"space_units":"м²","costs_property_comment":"","costs_rent":""},{"costs_rent":"","region":"Харківська область","costs_property":"","costs_rent_comment":"","space_comment":"","costs_property_comment":"","space_units":"м²","space":"158.4","address":"Харківський р-н, с. Покотилівка"}],"31":[{"space_unclear":false,"address_hidden":true,"region_hidden":false,"space_comment":"","space_hidden":false,"space":"89","address":"","region":"м. Київ","costs_property":"","costs_rent_comment":"","space_comment_hidden":false,"space_units":"м²","costs_property_comment":"","costs_rent":""}],"33":[{"space_hidden":false,"address_hidden":true,"region_hidden":false,"space_comment":"","space":"60.5","address":"Харківський р-н, с. Покотилівка","region":"Харківська область","costs_property":"","costs_rent_comment":"","space_units":"м²","costs_property_comment":"","costs_rent":""}],"34":[{"space_hidden":false,"address_hidden":true,"region_hidden":false,"space_comment":"","space":"138","address":"м. Харків","region":"Харківська область","costs_property":"","costs_rent_comment":"","space_units":"м²","costs_property_comment":"","costs_rent":""},{"costs_rent":"","region":"Харківська область","costs_property":"","costs_rent_comment":"","address_hidden":false,"space_comment":"","costs_property_comment":"","space_units":"м²","space":"866.16","address":"м. Харків"},{"costs_rent":"","region":"","costs_property":"","costs_rent_comment":"","address_hidden":false,"space_comment":"","costs_property_comment":"","space_units":"м²","space":"212","address":"Ліван, Бейрут"}]},"intro":{"declaration_year":"2014","isnotdeclaration":""}}