{"income":{"5":{"family_comment":"","value":"226436","family":"132160","comment":""},"6":{"family_comment":"","value":"210328","family":"86101","comment":"","family_hidden":false},"7":{"family_comment":"","value":"2710","source_name":"Національна школа суддів України","family":"","comment":""},"8":{"family_comment":"","value":"","family":"","comment":""},"9":{"value":"","value_unclear":false,"family_hidden":false,"family_comment":"","family":"","comment":""},"10":{"value":"13398","family_comment":"","family_hidden":false,"value_hidden":false,"family_unclear":false,"family":"","comment":""},"11":{"family_comment":"","value":"","family":"","comment":""},"12":{"family_comment":"","value":"","family":"","comment":""},"13":{"family_comment":"","value":"","family":"","comment":""},"14":{"family_comment":"","value":"","family":"","comment":""},"15":{"family_comment":"","value":"","family":"","comment":""},"16":{"family_comment":"","value":"","family":"","comment":""},"17":{"family_comment":"","value":"","family":"","comment":""},"18":{"family_comment":"","value":"","family":"","comment":""},"19":{"family_comment":"","value":"","family":"","comment":""},"20":{"value":"","comment_unclear":false,"family_comment":"","family":"46059","comment":"","family_comment_unclear":false}},"vehicle":{"40":[{"brand_info":"2362 куб. см.","sum_rent_comment":"","brand":"Toyota Camry","sum_comment":"","year":"2006","brand_info_unclear":false,"sum":"","sum_rent":""}]},"id":"vulyk_75_6","declaration":{"additional_info_text":"","notfull_lostpages":"3, 6, 8","date":"2015-06-09T00:00:00","notfull":"1","additional_info":"","url":"http://static.declarations.com.ua/declarations/chosen_ones/judges_batch/1929_dibrova_halyna_ivanivna.pdf"},"liabilities":{"54":{"sum_foreign_comment":"","sum":"","sum_comment":"","sum_foreign":""},"55":{"sum_foreign_comment":"","sum":"","sum_comment":"","sum_foreign":""},"56":{"sum_foreign_comment":"","sum":"4882","sum_comment":"","sum_foreign":""},"57":{"sum_foreign_comment":"","sum":"","sum_comment":"","sum_foreign":""},"58":{"sum_foreign_comment":"","sum":"","sum_comment":"","sum_foreign":""},"59":{"sum_foreign_comment":"","sum":"","sum_comment":"","sum_comment_unclear":false,"sum_unclear":false,"sum_foreign":""},"60":{"sum_foreign_comment":"","sum":"","sum_comment":"","sum_foreign":""},"61":{"sum_foreign_comment":"","sum":"","sum_comment":"","sum_foreign":""},"62":{"sum_foreign_comment":"","sum":"","sum_comment":"","sum_unclear":false,"sum_foreign":""},"63":{"sum_foreign_comment":"","sum":"","sum_comment":"","sum_foreign":""},"64":{"sum_foreign_comment":"","sum":"","sum_comment":"","sum_foreign":""}},"ft_src":"2362 куб. см.\n2006\nToyota Camry\nспільна власність\n60.4\nспільна власність\n60.4\n3, 6, 8\n1\n2014\n86101\n210328\n13398\n2710\nНаціональна школа суддів України\n132160\n226436\n46059\n2362 куб. см.\n2006\nToyota Camry\n3, 6, 8\n1\n2014\nДіброва\nІванівна\nПодружжя\nЧорний І. П\nДитина\nДіброва А. І. В звязку із переміщенням з тимчасово окупованої території в м. Київ Київської області з жовтня 2014 року спільно не проживає, спільного побуту не має\nДіброва Галина Іванівна\nГалина Іванівна Діброва\nГалина Діброва\nДіброва Галина Іванівна\nГалина\nДіброва Галина Іванівна\nАпеляційний господарський суд\nсуддя одеського апеляційного господарського суду\nОдеська область\n4882\n2710\nНаціональна школа суддів України\n210328\n86101\n46059\n226436\n132160\n13398\n60.4\nспільна власність\n60.4\nспільна власність\n4882\nЧорний І. П\nПодружжя\nДіброва А. І. В звязку із переміщенням з тимчасово окупованої території в м. Київ Київської області з жовтня 2014 року спільно не проживає, спільного побуту не має\nДитина\nДіброва\nІванівна\nсуддя одеського апеляційного господарського суду\nОдеська область\nАпеляційний господарський суд\nДіброва Галина Іванівна\nДіброва Галина Іванівна\nГалина Іванівна Діброва\nГалина Діброва\nДіброва Галина Іванівна\nГалина","general":{"inn_hidden":true,"inn":"","last_name":"Діброва","post":{"office":"Апеляційний господарський суд","region":"Одеська область","post":"суддя одеського апеляційного господарського суду"},"name":"Галина","full_name":"Діброва Галина Іванівна","family_raw":"","addresses":[{"place_district":"","place_address_hidden":true,"place_hidden":true,"place_address":"","place_district_hidden":true,"place_city_type":"","place_city_hidden":true,"place_city_type_hidden":false,"place_city":"","place":""}],"family":[{"inn":"","inn_hidden":false,"relations_hidden":false,"family_name":"Чорний І. П","relations_other":"","relations":"Подружжя","name_hidden":false,"name_unclear":false},{"inn":"","inn_hidden":false,"family_name":"Діброва А. І. В звязку із переміщенням з тимчасово окупованої території в м. Київ Київської області з жовтня 2014 року спільно не проживає, спільного побуту не має","relations_other":"","relations":"Дитина","name_hidden":false,"name_unclear":false}],"full_name_suggest":{"output":"Діброва Галина Іванівна","input":["Діброва Галина Іванівна","Галина Іванівна Діброва","Галина Діброва"]},"patronymic":"Іванівна"},"source":"VULYK","estate":{"25":[{"space_unclear":false,"costs":"","costs_comment":"","address_hidden":false,"region_hidden":true,"space_comment":"спільна власність","space_hidden":false,"space":"60.4","address":"","region":"","costs_rent_comment":"","space_units":"м²","costs_rent":""}],"31":[{"space_unclear":false,"address_hidden":false,"region_hidden":true,"space_comment":"спільна власність","space":"60.4","address":"","region":"","costs_property":"","costs_rent_comment":"","space_units":"м²","costs_property_comment":"","costs_rent":""}]},"intro":{"declaration_year":"2014","isnotdeclaration":""}}