{"income":{"5":{"family_comment":"","value":"167402","value_unclear":false,"family":"294191","comment":""},"6":{"value":"167402","value_unclear":false,"family_hidden":false,"family_comment":"","family":"47738","comment":""},"7":{"source_name_unclear":false,"value":"","family_comment":"","source_name":"","family":"","comment":""},"8":{"family_comment":"","value":"","family":"","comment":""},"9":{"family_comment":"","value":"","family":"","comment":""},"10":{"family_comment":"","value":"","family":"","comment":""},"11":{"family_comment":"","value":"","comment_unclear":false,"family":"","comment":""},"12":{"family_comment":"","value":"","family":"","comment":""},"13":{"family_comment":"","value":"","family":"","comment":""},"14":{"family_comment":"","value":"","family":"","comment":""},"15":{"family_comment":"","value":"","family":"","comment":""},"16":{"family_comment":"","value":"","family":"197000","comment":""},"17":{"family_comment":"","value":"","family":"","comment":""},"18":{"family_comment":"","value":"","family":"","comment":""},"19":{"family_comment":"","value":"","family":"","comment":""},"20":{"value":"","family_comment":"","value_unclear":false,"family_unclear":false,"comment_unclear":false,"comment":"","family":"49453"}},"vehicle":{"35":[{"brand_info":"2698 куб. см.","sum_rent_comment":"","brand":"Toyota Prado","sum_comment":"","brand_unclear":false,"year":"2006","sum_rent_unclear":false,"brand_info_hidden":false,"brand_info_unclear":false,"sum":"","sum_rent":""}],"40":[{"brand_info":"1598 куб. см.","sum_rent_comment":"","brand":"Toyota Corolla","sum_comment":"","year":"2008","brand_hidden":false,"brand_info_hidden":false,"brand_info_unclear":false,"sum":"","sum_rent":""}]},"id":"vulyk_101_135","banks":{"53":[{"sum_foreign_comment":"","sum_units":"UAH","sum_comment":"","sum_foreign_units":"UAH","sum_comment_hidden":false,"sum":"23316","sum_foreign":""}]},"declaration":{"additional_info_text":"","notfull_lostpages":"","date":"2016-03-30T00:00:00","notfull":"","additional_info":"","url":"http://static.declarations.com.ua/declarations/chosen_ones/judges_batch/850_kotormus_taras_ihorovych_2015.pdf"},"liabilities":{"54":{"sum_foreign_comment":"","sum":"","sum_comment":"","sum_comment_unclear":false,"sum_hidden":false,"sum_comment_hidden":false,"sum_unclear":false,"sum_foreign":""},"55":{"sum_foreign_comment":"","sum":"","sum_comment":"","sum_foreign":""},"56":{"sum_foreign_comment":"","sum":"","sum_comment":"","sum_comment_hidden":false,"sum_unclear":false,"sum_foreign":""},"57":{"sum_foreign_comment":"","sum":"","sum_comment":"","sum_hidden":false,"sum_comment_hidden":false,"sum_unclear":false,"sum_foreign":""},"58":{"sum_foreign_comment":"","sum":"","sum_comment":"","sum_comment_unclear":false,"sum_hidden":false,"sum_comment_hidden":false,"sum_unclear":false,"sum_foreign":""},"59":{"sum_foreign_comment":"","sum":"","sum_comment":"","sum_foreign":""},"60":{"sum_foreign_comment":"","sum":"","sum_comment":"","sum_hidden":false,"sum_comment_hidden":false,"sum_unclear":false,"sum_foreign":""},"61":{"sum_foreign_comment":"","sum":"","sum_comment":"","sum_foreign":""},"62":{"sum_foreign_comment":"","sum":"","sum_comment":"","sum_comment_unclear":false,"sum_foreign":""},"63":{"sum_foreign_comment":"","sum_comment_hidden":false,"sum":"","sum_comment":"","sum_foreign":""},"64":{"sum_foreign_comment":"","sum_comment_hidden":false,"sum":"","sum_comment":"","sum_foreign":""}},"ft_src":"суддя кам'янка-бузького районного суду львівської області\nЛьвівська область\nЗагальний місцевий суд\nТарас\nЛевицька Г. С\nПодружжя\nКотормус Д. Т\nДитина\nКотормус А. Т\nДитина\nКотормус І. М\nБатьки\nКотормус С. М\nБатьки\nЛевицька Л. Л\nІнше\nТеща\nІгорович\nКотормус Тарас Ігорович\nКотормус\nКотормус Тарас Ігорович\nТарас Ігорович Котормус\nТарас Котормус\nКотормус Тарас Ігорович\nToyota Prado\n2698 куб. см.\n2006\n1598 куб. см.\nToyota Corolla\n2008\n23316\n2015\nToyota Prado\n2698 куб. см.\n2006\n1598 куб. см.\n2008\nToyota Corolla\n23316\n2015\nПодружжя\nЛевицька Г. С\nДитина\nКотормус Д. Т\nДитина\nКотормус А. Т\nКотормус І. М\nБатьки\nКотормус С. М\nБатьки\nЛевицька Л. Л\nІнше\nТеща\nКотормус Тарас Ігорович\nТарас Ігорович Котормус\nТарас Котормус\nКотормус Тарас Ігорович\nТарас\nКотормус Тарас Ігорович\nІгорович\nЗагальний місцевий суд\nсуддя кам'янка-бузького районного суду львівської області\nЛьвівська область\nКотормус\n167402\n47738\n49453\n167402\n294191\n197000\n.3\nЛьвівська область\nДрогобицький р-н, с. Доброгостів\n.0155\nДрогобицький р-н, с. Доброгостів\nЛьвівська область\n196.2\nДрогобицький р-н, с. Доброгостів\nЛьвівська область\n70.6\nЛьвівська область\nм. Львів\n40.2\nм. Львів\nЛьвівська область\nм. Львів\nЛьвівська область\n22.8\nЛьвівська область\nДрогобицький р-н, с. Доброгостів\n.3\nЛьвівська область\nДрогобицький р-н, с. Доброгостів\n.0155\nм. Львів\nЛьвівська область\n70.6\nЛьвівська область\nм. Львів\n40.2\nЛьвівська область\nДрогобицький р-н, с. Доброгостів\n196.2\nЛьвівська область\nм. Львів\n22.8\nЛевицька Г. С\nПодружжя\nКотормус Д. Т\nДитина\nКотормус А. Т\nДитина\nКотормус І. М\nБатьки\nКотормус С. М\nБатьки\nІнше\nТеща\nЛевицька Л. Л\nТарас\nІгорович\nКотормус\nКотормус Тарас Ігорович\nТарас Ігорович Котормус\nТарас Котормус\nКотормус Тарас Ігорович\nсуддя кам'янка-бузького районного суду львівської області\nЗагальний місцевий суд\nЛьвівська область\nКотормус Тарас Ігорович\n47738\n167402\n294191\n167402\n197000\n49453\n2006\nToyota Prado\n2698 куб. см.\nToyota Corolla\n1598 куб. см.\n2008\n49453\n294191\n167402\n197000\n167402\n47738\nм. Львів\nЛьвівська область\n70.6\nм. Львів\nЛьвівська область\n40.2\nДрогобицький р-н, с. Доброгостів\nЛьвівська область\n196.2\nм. Львів\nЛьвівська область\n22.8\nДрогобицький р-н, с. Доброгостів\nЛьвівська область\n.3\nДрогобицький р-н, с. Доброгостів\nЛьвівська область\n.0155\n23316\n2015","general":{"inn":"","name":"Тарас","inn_unclear":false,"family":[{"inn":"","relations":"Подружжя","relations_other":"","inn_hidden":true,"family_name":"Левицька Г. С","name_hidden":true,"name_unclear":false},{"inn":"","relations":"Дитина","relations_unclear":false,"family_name":"Котормус Д. Т","inn_hidden":true,"relations_other":"","name_hidden":false,"name_unclear":false},{"inn":"","relations":"Дитина","relations_other":"","inn_hidden":true,"family_name":"Котормус А. Т","name_hidden":false,"name_unclear":false},{"inn":"","family_name":"Котормус І. М","relations":"Батьки","inn_hidden":true},{"inn":"","family_name":"Котормус С. М","relations":"Батьки"},{"inn":"","family_name":"Левицька Л. Л","relations":"Інше","relations_other":"Теща"}],"inn_hidden":true,"family_raw":"","last_name":"Котормус","post":{"region":"Львівська область","region_unclear":false,"post":"суддя кам'янка-бузького районного суду львівської області","office_unclear":false,"office":"Загальний місцевий суд"},"full_name":"Котормус Тарас Ігорович","addresses":[{"place_district":"","place_city_hidden":true,"place_city":"","place_city_type_hidden":false,"place_district_hidden":false,"place_city_type":"","place_address_hidden":true,"place_address":"","place_hidden":true,"place":""}],"patronymic":"Ігорович","patronymic_hidden":false,"full_name_suggest":{"output":"Котормус Тарас Ігорович","input":["Котормус Тарас Ігорович","Тарас Ігорович Котормус","Тарас Котормус"]}},"source":"VULYK","estate":{"29":[{"costs_rent":"","region":"Львівська область","costs_property":"","costs_rent_comment":"","address_hidden":true,"region_hidden":false,"space_comment":"","costs_property_comment":"","space_units":"га","space":".3","address":"Дрогобицький р-н, с. Доброгостів"},{"costs_rent":"","region":"Львівська область","costs_property":"","costs_rent_comment":"","region_hidden":true,"space_comment":"","costs_property_comment":"","space_units":"га","space":".0155","address":"Дрогобицький р-н, с. Доброгостів"}],"30":[{"costs_rent":"","region":"Львівська область","costs_property":"","costs_rent_comment":"","address_hidden":true,"region_hidden":false,"space_comment":"","costs_property_comment":"","space_units":"м²","space":"196.2","address":"Дрогобицький р-н, с. Доброгостів"}],"31":[{"space_unclear":false,"address_hidden":true,"region_hidden":false,"space_comment":"","space_hidden":false,"space":"70.6","address":"м. Львів","costs_rent_comment_unclear":false,"region":"Львівська область","costs_property":"","costs_rent_comment":"","space_units":"м²","costs_property_comment":"","costs_rent":""},{"costs_rent":"","region":"Львівська область","costs_property":"","costs_rent_comment":"","space_comment":"","costs_property_comment":"","space_units":"м²","space":"40.2","address":"м. Львів"}],"34":[{"space_hidden":false,"address_hidden":true,"region_hidden":false,"space_comment":"","space":"22.8","address":"м. Львів","region":"Львівська область","costs_property":"","costs_rent_comment":"","space_comment_unclear":false,"address_unclear":false,"space_units":"м²","costs_property_comment":"","costs_rent":""}]},"intro":{"declaration_year":"2015"}}