{"income":{"5":{"value":"309664","family_comment":"","value_unclear":false,"family_unclear":false,"family":"","comment":""},"6":{"value":"259579","family_comment":"","value_unclear":false,"family_unclear":false,"family":"","comment":""},"7":{"family_comment":"","value":"","source_name":"","family":"","comment":""},"8":{"family_comment":"","value":"","family":"","comment":""},"9":{"family_comment":"","value":"17150","family":"","comment":"","family_comment_unclear":false},"10":{"family_comment":"","value":"","family":"","comment":""},"11":{"family_comment":"","value":"","family":"","comment":""},"12":{"family_comment":"","value":"","family":"","comment":""},"13":{"family_comment":"","value":"","family":"","comment":""},"14":{"family_comment":"","value":"","family":"","comment":""},"15":{"family_comment":"","value":"","family":"","comment":""},"16":{"family_comment":"","family_unclear":false,"value":"","family":"","comment":""},"17":{"family_comment":"","family_unclear":false,"value":"","family":"","comment":""},"18":{"family_comment":"","value":"","family":"","comment":""},"19":{"family_comment":"","value":"","family":"","comment":""},"20":{"family_comment":"","value":"32935","family":"","comment":""}},"id":"vulyk_88_100","banks":{"45":[{"sum_foreign_comment":"","sum_units":"UAH","sum_comment":"","sum_comment_unclear":false,"sum_hidden":true,"sum_foreign_units":"UAH","sum_comment_hidden":true,"sum":"143442","sum_foreign":""}],"46":[{"sum_foreign_comment":"","sum_units":"UAH","sum_comment":"","sum_foreign_units":"UAH","sum":"130000","sum_foreign":""}],"47":[{"sum_foreign_comment":"","sum_units":"UAH","sum_comment":"","sum_hidden":true,"sum_foreign_units":"UAH","sum_comment_hidden":true,"sum":"60","sum_foreign":""}]},"declaration":{"additional_info_text":"","notfull_lostpages":"","date":"2015-03-26T00:00:00","notfull":"","additional_info":"","url":"http://static.declarations.com.ua/declarations/chosen_ones/judges_batch/3003_arabei_tetiana_heorhiivna.pdf"},"liabilities":{"54":{"sum_foreign_comment":"","sum":"","sum_comment":"","sum_comment_unclear":false,"sum_foreign":""},"55":{"sum_foreign_comment":"","sum":"","sum_comment":"","sum_foreign":""},"56":{"sum_foreign_comment":"","sum":"","sum_comment":"","sum_foreign":""},"57":{"sum_foreign_comment":"","sum":"","sum_comment":"","sum_hidden":false,"sum_comment_hidden":false,"sum_unclear":false,"sum_foreign":""},"58":{"sum_foreign_comment":"","sum":"","sum_comment":"","sum_hidden":false,"sum_comment_hidden":false,"sum_foreign":""},"59":{"sum_foreign_comment":"","sum":"","sum_comment":"","sum_foreign":""},"60":{"sum_foreign_comment":"","sum":"","sum_comment":"","sum_comment_unclear":false,"sum_hidden":false,"sum_comment_hidden":false,"sum_foreign":""},"61":{"sum_foreign_comment":"","sum":"","sum_comment":"","sum_foreign":""},"62":{"sum_foreign_comment":"","sum":"","sum_comment":"","sum_foreign":""},"63":{"sum_foreign_comment":"","sum":"","sum_comment":"","sum_foreign":""},"64":{"sum_foreign_comment":"","sum":"","sum_comment":"","sum_foreign":""}},"ft_src":"суддя донецького апеляційного адміністративного суду\nДонецька область\nАпеляційний адміністративний суд\nТетяна\nГеоргіївна\nАрабей Тетяна Георгіївна\nТетяна Георгіївна Арабей\nТетяна Арабей\nАрабей Тетяна Георгіївна\nАрабей\nАрабей Тетяна Георгіївна\n224\n35.5\n46.9\n130000\n60\n143442\n2014\n2014\nАрабей Тетяна Георгіївна\nТетяна Георгіївна Арабей\nТетяна Арабей\nАрабей Тетяна Георгіївна\nАрабей Тетяна Георгіївна\nТетяна\nАрабей\nАпеляційний адміністративний суд\nсуддя донецького апеляційного адміністративного суду\nДонецька область\nГеоргіївна\n259579\n32935\n309664\n17150\n224\n35.5\n46.9\n143442\n130000\n60\n259579\n17150\n309664\n32935\nГеоргіївна\nАрабей\nТетяна\nАрабей Тетяна Георгіївна\nТетяна Георгіївна Арабей\nТетяна Арабей\nАрабей Тетяна Георгіївна\nДонецька область\nАпеляційний адміністративний суд\nсуддя донецького апеляційного адміністративного суду\nАрабей Тетяна Георгіївна\n17150\n32935\n309664\n259579\n46.9\n224\n35.5\n60\n143442\n130000\n2014","general":{"inn":"","name":"Тетяна","patronymic_unclear":false,"patronymic":"Георгіївна","inn_hidden":true,"family_raw":"","last_name":"Арабей","post":{"post":"суддя донецького апеляційного адміністративного суду","region":"Донецька область","candidate":"","office_hidden":false,"region_hidden":false,"office":"Апеляційний адміністративний суд"},"last_name_unclear":false,"full_name":"Арабей Тетяна Георгіївна","addresses":[{"place_district":"","place_city_hidden":true,"place_city":"","place_city_type_hidden":true,"place_district_hidden":true,"place_city_type":"","place_address_hidden":true,"place_address":"","place_hidden":true,"place":""}],"patronymic_hidden":false,"full_name_suggest":{"output":"Арабей Тетяна Георгіївна","input":["Арабей Тетяна Георгіївна","Тетяна Георгіївна Арабей","Тетяна Арабей"]}},"source":"VULYK","estate":{"23":[{"space_unclear":false,"costs":"","costs_rent_unclear":false,"costs_comment":"","address_hidden":true,"region_hidden":true,"space_comment":"","space":"224","address":"","region":"","address_unclear":false,"costs_rent_comment":"","space_comment_unclear":false,"space_units":"м²","costs_rent":""}],"24":[{"space_hidden":false,"costs":"","costs_comment":"","address_hidden":true,"region_hidden":true,"space_comment":"","space_unclear":false,"space":"35.5","address":"","region":"","costs_rent_comment":"","space_units":"м²","costs_rent":""}],"25":[{"space_unclear":false,"costs":"","costs_comment":"","address_hidden":true,"region_hidden":true,"space_comment":"","space_hidden":false,"space":"46.9","address":"","region":"","address_unclear":false,"costs_rent_comment":"","space_comment_unclear":false,"space_units":"м²","costs_rent":""}]},"intro":{"declaration_year":"2014","isnotdeclaration":""}}