{"income":{"5":{"family_comment":"","value":"231360.3","family":"27748.45","comment":""},"6":{"family_comment":"","value":"230089.33","value_unclear":false,"family":"1112.46","comment":""},"7":{"value":"","family_comment":"","source_name":"","family":"","comment":"","source_name_hidden":false},"8":{"family_comment":"","value":"","family":"","comment":""},"9":{"family_comment":"","value":"1270.97","family":"13917.81","comment":""},"10":{"family_comment":"","value":"","family":"","comment":""},"11":{"family_comment":"","value":"","comment_hidden":false,"family":"","comment":""},"12":{"family_comment":"","value":"","family":"","comment":""},"13":{"family_comment":"","value":"","family":"","comment":""},"14":{"family_comment":"","value":"","family":"","comment":""},"15":{"value":"","family_comment":"","value_unclear":false,"family_unclear":false,"family":"4037.54","comment":""},"16":{"family_comment":"","value":"","family":"","comment":""},"17":{"family_comment":"","value":"","family":"","comment":""},"18":{"family_comment":"","value":"","family":"","comment":""},"19":{"family_comment":"","value":"","family":"8680.64","comment":""},"20":{"family_comment":"","value":"","comment_unclear":false,"family":"","comment":""}},"vehicle":{"40":[{"brand_info":"2354 об'єм двигуна, 4574 довжина, 166 к. с потужність","sum_rent_comment":"","brand":"Honda","sum_comment":"","year":"2010","brand_hidden":true,"brand_info_hidden":false,"brand_info_unclear":false,"sum":"","sum_rent":""}]},"id":"vulyk_104_80","banks":{"51":[{"sum_foreign_comment":"","sum_foreign_hidden":false,"sum_comment":"","sum_comment_unclear":false,"sum_hidden":false,"sum_foreign_units":"UAH","sum_foreign_comment_unclear":false,"sum_comment_hidden":false,"sum_units":"UAH","sum":"200000","sum_foreign":""}]},"declaration":{"date":"2016-03-30T00:00:00","additional_info_text":"","additional_info":"","url":"http://static.declarations.com.ua/declarations/chosen_ones/judges_batch/1878_hul_v’yacheslav_volodymyrovych_2015.pdf"},"liabilities":{"54":{"sum_foreign_comment":"","sum_foreign_hidden":false,"sum_comment":"","sum_hidden":false,"sum_comment_hidden":false,"sum_unclear":false,"sum":"","sum_foreign":""},"55":{"sum_foreign_comment":"","sum":"","sum_comment":"","sum_foreign":""},"56":{"sum_foreign_comment":"","sum":"1900","sum_comment":"","sum_unclear":false,"sum_foreign":""},"57":{"sum_foreign_comment":"","sum_foreign_hidden":false,"sum_comment":"","sum_comment_unclear":false,"sum_comment_hidden":false,"sum":"","sum_foreign":""},"58":{"sum_foreign_comment":"","sum":"","sum_comment":"","sum_unclear":false,"sum_foreign":""},"59":{"sum_foreign_comment":"","sum":"","sum_comment":"","sum_foreign":""},"60":{"sum_foreign_comment":"","sum_foreign_hidden":false,"sum_comment":"","sum_comment_hidden":false,"sum":"","sum_foreign":""},"61":{"sum_foreign_comment":"","sum":"","sum_comment":"","sum_foreign":""},"62":{"sum_foreign_comment":"","sum":"","sum_comment":"","sum_foreign":""},"63":{"sum_foreign_comment":"","sum":"","sum_comment":"","sum_foreign":""},"64":{"sum_foreign_comment":"","sum":"","sum_comment":"","sum_foreign":""}},"ft_src":"1900\nГуль В'ячеслав Володимирович\nсуддя апеляційного суду київської області\nКиївська область\nЗагальний апеляційний суд\nВ'ячеслав\nГуль К. О. 04. 10. 1985\nПодружжя\nГуль Т. В. 11. 10. 2010\nДитина\nГуль А. В. 02. 06. 2012\nДитина\nГуль В'ячеслав Володимирович\nВ'ячеслав Володимирович Гуль\nВ'ячеслав Гуль\nГуль В'ячеслав Володимирович\nГуль\nВолодимирович\nHonda\n2354 об'єм двигуна, 4574 довжина, 166 к. с потужність\n2010\n200000\n2015\nHonda\n2354 об'єм двигуна, 4574 довжина, 166 к. с потужність\n2010\n200000\n2015\nПодружжя\nГуль К. О. 04. 10. 1985\nДитина\nГуль Т. В. 11. 10. 2010\nДитина\nГуль А. В. 02. 06. 2012\nГуль\nГуль В'ячеслав Володимирович\nВ'ячеслав Володимирович Гуль\nВ'ячеслав Гуль\nГуль В'ячеслав Володимирович\nГуль В'ячеслав Володимирович\nВ'ячеслав\nВолодимирович\nЗагальний апеляційний суд\nсуддя апеляційного суду київської області\nКиївська область\n1900\n230089.33\n1112.46\n4037.54\n231360.3\n27748.45\n1270.97\n13917.81\n8680.64\nбезкоштовна приватизація\nбезкоштовна приватизація\n1/3 частина\n1900\nбезкоштовна приватизація\nбезкоштовна приватизація\n1/3 частина\nПодружжя\nГуль К. О. 04. 10. 1985\nДитина\nГуль Т. В. 11. 10. 2010\nГуль А. В. 02. 06. 2012\nДитина\nВолодимирович\nГуль\nсуддя апеляційного суду київської області\nЗагальний апеляційний суд\nКиївська область\nГуль В'ячеслав Володимирович\nГуль В'ячеслав Володимирович\nВ'ячеслав Володимирович Гуль\nВ'ячеслав Гуль\nГуль В'ячеслав Володимирович\nВ'ячеслав\n1112.46\n230089.33\n4037.54\n13917.81\n1270.97\n27748.45\n231360.3\n8680.64\nHonda\n2354 об'єм двигуна, 4574 довжина, 166 к. с потужність\n2010\n8680.64\n4037.54\n13917.81\n1270.97\n27748.45\n231360.3\n1112.46\n230089.33\n1/3 частина\nбезкоштовна приватизація\nбезкоштовна приватизація\n200000\n2015","general":{"inn":"","inn_hidden":true,"last_name":"Гуль","post":{"region":"Київська область","region_unclear":false,"post":"суддя апеляційного суду київської області","office_unclear":false,"office":"Загальний апеляційний суд"},"name":"В'ячеслав","full_name":"Гуль В'ячеслав Володимирович","family_raw":"","addresses":[{"place_district":"","place_city_hidden":true,"place_city":"","place_city_type_hidden":true,"place_district_hidden":true,"place_city_type":"","place_address_hidden":true,"place_address":"","place_hidden":true,"place":""}],"family":[{"inn":"","relations":"Подружжя","relations_other":"","inn_hidden":true,"family_name":"Гуль К. О. 04. 10. 1985","name_hidden":false,"name_unclear":false},{"inn":"","relations":"Дитина","relations_other":"","inn_hidden":true,"family_name":"Гуль Т. В. 11. 10. 2010","name_hidden":false,"name_unclear":false},{"inn":"","relations":"Дитина","relations_other":"","inn_hidden":true,"family_name":"Гуль А. В. 02. 06. 2012","name_unclear":false}],"full_name_suggest":{"output":"Гуль В'ячеслав Володимирович","input":["Гуль В'ячеслав Володимирович","В'ячеслав Володимирович Гуль","В'ячеслав Гуль"]},"patronymic":"Володимирович"},"source":"VULYK","estate":{"23":[{"space_hidden":true,"costs":"","costs_comment":"безкоштовна приватизація","address_hidden":true,"region_hidden":true,"space_comment":"безкоштовна приватизація","space":"","address":"","region":"","costs_rent_comment":"","space_comment_unclear":false,"space_units":"м²","costs_rent":""}],"31":[{"space_unclear":false,"address_hidden":true,"region_hidden":true,"space_comment":"1/3 частина","space_hidden":true,"space":"","address":"","region":"","costs_property":"","costs_rent_comment":"","space_units":"м²","costs_property_comment":"","costs_rent":""}]},"intro":{"declaration_year":"2015","isnotdeclaration":""}}