{"income":{"5":{"value":"202997","family_comment":"","value_unclear":false,"family_unclear":false,"family":"15180","comment":""},"6":{"family_comment":"","value":"202997","value_unclear":false,"family":"4000","comment":""},"7":{"value":"","value_unclear":false,"family_comment":"","source_name":"","family":"","comment":""},"8":{"family_comment":"","value":"","family":"","comment":""},"9":{"value":"","family_comment":"","value_unclear":false,"family_unclear":false,"family":"","comment":""},"10":{"family_comment":"","value":"","comment_unclear":false,"family":"","comment":""},"11":{"family_comment":"","value":"","family":"","comment":""},"12":{"family_comment":"","value":"","family":"","comment":""},"13":{"family_comment":"","value":"","value_unclear":false,"family":"","comment":""},"14":{"family_comment":"","value":"","family":"","comment":""},"15":{"family_comment":"","value":"","family":"","comment":""},"16":{"family_comment":"","family_unclear":false,"value":"","family":"","comment":""},"17":{"family_comment":"","family_unclear":false,"value":"","family":"","comment":""},"18":{"family_comment":"","value":"","family":"","comment":""},"19":{"family_comment":"","value":"","family":"","comment":""},"20":{"value":"","family_comment":"","value_unclear":false,"family_hidden":false,"value_hidden":false,"family_unclear":false,"comment_unclear":false,"comment":"","family":"11180"}},"vehicle":{"35":[{"brand_info":"2360, 125 кВт , 466.5 см","sum_rent_comment":"у користуванні був","brand_info_unclear":false,"year":"2008","brand_info_hidden":false,"sum_rent_comment_unclear":false,"sum_rent":"","sum":"","brand":"Mitsubishi Outlander","sum_comment":"","brand_unclear":false,"brand_hidden":false}],"39":[{"brand_info":"причіп","sum":"","brand":"Турист","sum_comment":"","brand_unclear":true,"year":"2010","brand_hidden":false,"sum_rent_comment":"","sum_rent":""}]},"id":"vulyk_100_171","declaration":{"additional_info_text":"","notfull_lostpages":"","date":"2015-03-27T00:00:00","notfull":"","additional_info":"","url":"http://static.declarations.com.ua/declarations/chosen_ones/judges_batch/4441_drach_ivan_volodymyrovych.pdf"},"liabilities":{"54":{"sum_foreign_comment":"","sum":"130","sum_comment":"","sum_comment_hidden":false,"sum_unclear":false,"sum_foreign":""},"55":{"sum_foreign_comment":"","sum":"","sum_comment":"","sum_foreign":""},"56":{"sum_foreign_comment":"","sum":"","sum_comment":"","sum_unclear":false,"sum_foreign":""},"57":{"sum_foreign_comment":"","sum":"22329","sum_comment":"","sum_comment_unclear":false,"sum_comment_hidden":false,"sum_unclear":false,"sum_foreign":""},"58":{"sum_foreign_comment":"","sum":"2323","sum_comment":"","sum_comment_hidden":false,"sum_unclear":false,"sum_foreign":""},"59":{"sum_foreign_comment":"","sum":"","sum_comment":"","sum_foreign":""},"60":{"sum_foreign_comment":"","sum_comment_hidden":false,"sum":"","sum_comment":"","sum_foreign":""},"61":{"sum_foreign_comment":"","sum":"","sum_comment":"","sum_foreign":""},"62":{"sum_foreign_comment":"","sum":"","sum_comment":"","sum_unclear":false,"sum_foreign":""},"63":{"sum_foreign_comment":"","sum_comment_hidden":false,"sum":"","sum_comment":"","sum_foreign":""},"64":{"sum_foreign_comment":"","sum_comment_hidden":false,"sum":"","sum_comment":"","sum_foreign":""}},"ft_src":"22329\n130\n2323\nДрач Іван Володимирович\nсуддя кам'янець-подільського міськрайонного суду\nХмельницька область\nЗагальний місцевий суд\nІван\nДрач В. Л\nПодружжя\nДрач В. І\nДитина\nДрач Б. І\nДитина\nДрач Іван Володимирович\nІван Володимирович Драч\nІван Драч\nДрач Іван Володимирович\nДрач\nВолодимирович\nТурист\nпричіп\n2010\n2360, 125 кВт , 466.5 см\nу користуванні був\nMitsubishi Outlander\n2008\n1316\n40.3\n83.7\nналежить 1/4\n77.6\n417.3\n73.2\n37\n2014\n4000\n202997\n15180\n202997\n11180\n2360, 125 кВт , 466.5 см\nMitsubishi Outlander\nу користуванні був\n2008\nпричіп\n2010\nТурист\n417.3\n37\n1316\n40.3\n83.7\n77.6\nналежить 1/4\n73.2\nПодружжя\nДрач В. Л\nДитина\nДрач В. І\nДитина\nДрач Б. І\nВолодимирович\nДрач\nДрач Іван Володимирович\nІван Володимирович Драч\nІван Драч\nДрач Іван Володимирович\nДрач Іван Володимирович\nІван\nЗагальний місцевий суд\nХмельницька область\nсуддя кам'янець-подільського міськрайонного суду\n130\n22329\n2323\n202997\n4000\n11180\n202997\n15180\n2014\n2323\n22329\n130\nДрач В. Л\nПодружжя\nДитина\nДрач В. І\nДитина\nДрач Б. І\nВолодимирович\nДрач\nХмельницька область\nЗагальний місцевий суд\nсуддя кам'янець-подільського міськрайонного суду\nДрач Іван Володимирович\nДрач Іван Володимирович\nІван Володимирович Драч\nІван Драч\nДрач Іван Володимирович\nІван\nТурист\nпричіп\n2010\n2008\nMitsubishi Outlander\nу користуванні був\n2360, 125 кВт , 466.5 см\n11180\n202997\n15180\n4000\n202997\n83.7\nналежить 1/4\n77.6\n37\n417.3\n40.3\n73.2\n1316\n2014","general":{"inn":"","inn_hidden":true,"last_name":"Драч","post":{"post_unclear":false,"region_unclear":false,"post":"суддя кам'янець-подільського міськрайонного суду","office":"Загальний місцевий суд","region":"Хмельницька область","post_hidden":false,"office_unclear":false},"name":"Іван","full_name":"Драч Іван Володимирович","family_raw":"","addresses":[{"place_district":"","place_city_hidden":true,"place_city":"","place_city_unclear":false,"place_district_hidden":false,"place_city_type":"","place_address_hidden":true,"place_city_type_hidden":false,"place_address":"","place_hidden":true,"place":""}],"family":[{"inn_hidden":true,"inn":"","name_hidden":true,"family_name":"Драч В. Л","relations":"Подружжя","name_unclear":false},{"inn":"","relations":"Дитина","relations_other":"","inn_hidden":true,"family_name":"Драч В. І","name_hidden":false,"name_unclear":false},{"inn":"","relations":"Дитина","relations_other":"","inn_hidden":true,"family_name":"Драч Б. І","name_hidden":false,"name_unclear":false}],"full_name_suggest":{"output":"Драч Іван Володимирович","input":["Драч Іван Володимирович","Іван Володимирович Драч","Іван Драч"]},"patronymic":"Володимирович"},"source":"VULYK","estate":{"25":[{"space_unclear":false,"costs":"","costs_comment":"","address_hidden":false,"region_hidden":true,"space_comment":"","space":"37","address":"","costs_comment_unclear":false,"region":"","address_unclear":false,"costs_rent_comment":"","space_comment_unclear":false,"space_units":"м²","costs_rent":""}],"29":[{"region_unclear":false,"space_unclear":true,"address_hidden":true,"region_hidden":true,"space_comment":"","space":"1316","address":"","region":"","costs_property":"","costs_rent_comment":"","address_unclear":false,"space_units":"м²","costs_property_comment":"","costs_rent":""}],"30":[{"costs_rent":"","region":"","costs_property":"","costs_rent_comment":"","address_hidden":true,"region_hidden":true,"space_comment":"","costs_property_comment":"","space_units":"м²","space":"417.3","address":""}],"31":[{"region_unclear":false,"space_unclear":false,"costs_property_comment_unclear":false,"address_hidden":true,"region_hidden":true,"space_comment":"","space":"83.7","address":"","region":"","costs_property":"","costs_rent_comment":"","space_comment_unclear":false,"address_unclear":false,"space_units":"м²","costs_property_comment":"","costs_rent":""},{"costs_rent":"","region_unclear":false,"region":"","costs_property":"","costs_rent_comment":"","region_hidden":false,"space_comment":"належить 1/4","costs_property_comment":"","space_units":"м²","space":"77.6","address":""}],"33":[{"space_unclear":false,"address_hidden":true,"region_hidden":true,"space_comment":"","space":"40.3","address":"","region":"","costs_property":"","costs_rent_comment":"","address_unclear":false,"space_units":"м²","costs_property_comment":"","costs_rent":""}],"34":[{"costs_rent":"","region":"","costs_property":"","costs_rent_comment":"","address_hidden":true,"region_hidden":true,"space_comment":"","costs_property_comment":"","space_units":"м²","space":"73.2","address":""}]},"intro":{"declaration_year":"2014"}}