{"income":{"5":{"value":"276092","comment_hidden":false,"family_comment":"","family":"","comment":"","family_comment_hidden":false},"6":{"value":"276092","family_comment":"","comment_hidden":false,"family_hidden":false,"family_unclear":false,"family_comment_hidden":false,"comment":"","family":""},"7":{"value":"","comment_hidden":false,"family_comment_hidden":false,"family_comment":"","source_name":"","family":"","comment":"","source_name_hidden":false},"8":{"family_comment":"","value":"","family":"","comment":""},"9":{"value":"","family_comment":"","value_unclear":false,"family_unclear":false,"comment_unclear":false,"comment":"","family":""},"10":{"family_comment":"","family_unclear":false,"value":"","family":"","comment":""},"11":{"family_comment":"","value":"","family":"","comment":""},"12":{"family_comment":"","value":"","family":"","comment":""},"13":{"family_comment":"","value":"","family":"","comment":""},"14":{"family_comment":"","value":"","family":"","comment":""},"15":{"family_comment":"","value":"","comment_unclear":false,"family":"","comment":""},"16":{"family_comment":"","value":"","comment_unclear":false,"family":"","comment":""},"17":{"family_comment":"","value":"","family":"","comment":""},"18":{"family_comment":"","value":"","family":"","comment":""},"19":{"family_comment":"","value":"","family":"","comment":""},"20":{"value":"","family_comment":"","value_unclear":false,"family_unclear":false,"family_comment_unclear":false,"family_comment_hidden":false,"comment":"","family":""}},"vehicle":{"35":[{"brand_info":"1998 куб.см., 156 к. с","sum_rent_comment":"","brand":"Toyota Rav 4","sum_comment":"","brand_unclear":false,"year":"2008","sum_hidden":false,"brand_info_unclear":false,"sum":"","sum_rent":""},{"brand_info":"1500 куб.см., 86 к. с","sum_rent_comment":"оренда","brand":"ВАЗ 21083","sum_comment":"","year":"1986","brand_info_unclear":false,"sum":"","sum_rent":"6000"},{"brand_info":"1500 куб.см., 86 к. с","sum_rent_comment":"оренда","brand":"ВАЗ-2108","sum_comment":"","year":"1991","sum":"","sum_rent":"6000"}]},"id":"vulyk_73_78","declaration":{"additional_info_text":"","notfull_lostpages":"","date":"2014-12-10T00:00:00","notfull":"","additional_info":"","url":"http://static.declarations.com.ua/declarations/chosen_ones/judges_batch/1326_zhekov_volodymyr_ivanovych.pdf"},"liabilities":{"54":{"sum_foreign_comment":"","sum_foreign_hidden":false,"sum_comment":"","sum_comment_unclear":false,"sum_hidden":false,"sum_comment_hidden":false,"sum_unclear":false,"sum":"","sum_foreign":""},"55":{"sum_foreign_comment":"","sum_comment_hidden":false,"sum":"","sum_comment":"","sum_foreign":""},"56":{"sum_foreign_comment":"","sum":"","sum_comment":"","sum_comment_unclear":false,"sum_foreign":""},"57":{"sum_foreign_comment":"","sum":"","sum_comment":"","sum_hidden":false,"sum_comment_hidden":false,"sum_unclear":false,"sum_foreign":""},"58":{"sum_foreign_comment":"","sum":"","sum_comment":"","sum_hidden":false,"sum_comment_hidden":false,"sum_foreign":""},"59":{"sum_foreign_comment":"","sum":"","sum_comment":"","sum_comment_unclear":false,"sum_unclear":false,"sum_foreign":""},"60":{"sum_foreign_comment":"","sum":"","sum_comment":"","sum_hidden":false,"sum_comment_hidden":false,"sum_unclear":false,"sum_foreign":""},"61":{"sum_foreign_comment":"","sum":"","sum_comment":"","sum_foreign":""},"62":{"sum_foreign_comment":"","sum":"","sum_comment":"","sum_foreign":""},"63":{"sum_foreign_comment":"","sum":"","sum_comment":"","sum_hidden":false,"sum_comment_hidden":false,"sum_foreign":""},"64":{"sum_foreign_comment":"","sum":"","sum_comment":"","sum_foreign":""}},"ft_src":"суддя одеського апеляційного господарського суду\nОдеська область\nАпеляційний господарський суд\nЖеков Володимир Іванович\nВолодимир\nЖеков Володимир Іванович\nВолодимир Іванович Жеков\nВолодимир Жеков\nЖеков Володимир Іванович\nЖеков\nІванович\nToyota Rav 4\n1998 куб.см., 156 к. с\n2008\n1500 куб.см., 86 к. с\n1986\nВАЗ 21083\nоренда\n6000\n1500 куб.см., 86 к. с\n1991\nВАЗ-2108\nоренда\n6000\n14.4\n14.4\n42\n102\n2013\n276092\n276092\n1998 куб.см., 156 к. с\nToyota Rav 4\n2008\n1500 куб.см., 86 к. с\nоренда\n1986\n6000\nВАЗ 21083\n1500 куб.см., 86 к. с\nоренда\n1991\n6000\nВАЗ-2108\n2013\nАпеляційний господарський суд\nОдеська область\nсуддя одеського апеляційного господарського суду\nІванович\nЖеков Володимир Іванович\nВолодимир Іванович Жеков\nВолодимир Жеков\nЖеков Володимир Іванович\nЖеков Володимир Іванович\nВолодимир\nЖеков\n276092\n276092\n14.4\n14.4\n42\n102\nЖеков\nІванович\nОдеська область\nАпеляційний господарський суд\nсуддя одеського апеляційного господарського суду\nЖеков Володимир Іванович\nЖеков Володимир Іванович\nВолодимир Іванович Жеков\nВолодимир Жеков\nЖеков Володимир Іванович\nВолодимир\n2008\n1998 куб.см., 156 к. с\nToyota Rav 4\nоренда\n1986\n1500 куб.см., 86 к. с\nВАЗ 21083\n6000\nоренда\n6000\nВАЗ-2108\n1500 куб.см., 86 к. с\n1991\n276092\n276092\n42\n102\n14.4\n14.4\n2013","general":{"inn":"","family_raw":"","last_name":"Жеков","post":{"post_unclear":false,"region_unclear":false,"post":"суддя одеського апеляційного господарського суду","office":"Апеляційний господарський суд","region":"Одеська область","post_hidden":false,"office_hidden":false,"office_unclear":false,"region_hidden":false},"name":"Володимир","full_name":"Жеков Володимир Іванович","inn_hidden":false,"name_unclear":false,"last_name_unclear":false,"full_name_suggest":{"output":"Жеков Володимир Іванович","input":["Жеков Володимир Іванович","Володимир Іванович Жеков","Володимир Жеков"]},"patronymic":"Іванович"},"source":"VULYK","estate":{"25":[{"space_unclear":false,"costs":"","costs_comment":"","costs_hidden":false,"address_hidden":false,"region_hidden":false,"space_comment":"","space_hidden":false,"space":"42","address":"","region":"","costs_rent_comment":"","space_comment_hidden":false,"space_units":"м²","costs_rent":""},{"space_unclear":false,"costs":"","costs_comment":"","address_hidden":false,"region_hidden":false,"space_comment":"","space":"102","address":"","region":"","costs_rent_comment":"","space_comment_unclear":false,"space_units":"м²","costs_rent":""}],"28":[{"costs":"","costs_comment":"","costs_hidden":false,"address_hidden":false,"region_hidden":false,"space_comment":"","space":"14.4","address":"","region":"","address_unclear":false,"costs_rent_comment":"","space_units":"м²","costs_rent":""},{"space":"14.4","region":"","costs":"","costs_rent_comment":"","costs_comment":"","region_hidden":false,"address_unclear":false,"space_comment":"","space_units":"м²","costs_rent":"","address":""}]},"intro":{"declaration_year":"2013"}}