{"income":{"5":{"value":"285775.65","family_comment":"","value_unclear":false,"family_hidden":false,"value_hidden":false,"family_unclear":false,"family":"15561.36","comment":""},"6":{"value":"219782.88","value_unclear":false,"value_hidden":false,"family_comment":"","family":"","comment":""},"7":{"family_comment":"","value":"","source_name":"","family":"","comment":""},"8":{"family_comment":"","value":"","family":"","comment":""},"9":{"family_comment":"","value":"","family":"","comment":""},"10":{"value":"13398","family_comment":"","value_unclear":false,"family_unclear":false,"family":"","comment":""},"11":{"family_comment":"","value":"","family":"","comment":""},"12":{"family_comment":"","value":"","family":"","comment":""},"13":{"family_comment":"","value":"","family":"","comment":""},"14":{"family_comment":"","value":"","value_unclear":false,"family":"","comment":""},"15":{"family_comment":"","value":"","family":"","comment":""},"16":{"family_comment":"","value":"","family":"","comment":""},"17":{"family_comment":"","value":"","family":"","comment":""},"18":{"family_comment":"","value":"","family":"","comment":""},"19":{"family_comment":"","value":"","family":"","comment":"","family_comment_unclear":false},"20":{"value":"52594.77","value_unclear":false,"family_comment":"пенсія","comment_unclear":false,"comment":"пенсія","family":"15561.36"}},"id":"vulyk_60_196","banks":{"45":[{"sum_foreign_comment":"","sum_units":"UAH","sum_comment":"","sum_comment_unclear":false,"sum_foreign_units":"UAH","sum":"","sum_unclear":false,"sum_foreign":""}],"46":[{"sum_foreign_comment":"","sum_units":"UAH","sum_comment":"","sum_foreign_units":"UAH","sum":"","sum_foreign":""}],"47":[{"sum_foreign_comment":"","sum_units":"UAH","sum_comment":"","sum_foreign_units":"UAH","sum":"","sum_foreign":""}],"48":[{"sum_foreign_comment":"","sum_units":"UAH","sum_comment":"","sum_foreign_units":"UAH","sum":"","sum_foreign":""}],"49":[{"sum_foreign_comment":"","sum_units":"UAH","sum_comment":"","sum_foreign_units":"UAH","sum":"","sum_foreign":""}],"50":[{"sum_foreign_comment":"","sum_units":"UAH","sum_comment":"","sum_foreign_units":"UAH","sum":"","sum_foreign":""}],"51":[{"sum_foreign_comment":"","sum_units":"UAH","sum_comment":"","sum_foreign_units":"UAH","sum":"4000","sum_unclear":false,"sum_foreign":""}],"52":[{"sum_foreign_comment":"","sum_units":"UAH","sum_comment":"","sum_foreign_units":"UAH","sum":"","sum_foreign":""}],"53":[{"sum_foreign_comment":"","sum_units":"UAH","sum_comment":"","sum_foreign_units":"UAH","sum":"","sum_foreign":""}]},"declaration":{"additional_info_text":"","notfull_lostpages":"","date":"2015-03-27T00:00:00","notfull":"","additional_info":"","url":"http://static.declarations.com.ua/declarations/chosen_ones/mega_batch/yevstaf_ieva_tetiana_anatoliivna.pdf"},"liabilities":{"54":{"sum_foreign_comment":"","sum":"","sum_comment":"","sum_foreign":""},"55":{"sum_foreign_comment":"","sum":"","sum_comment":"","sum_foreign":""},"56":{"sum_foreign_comment":"","sum":"","sum_comment":"","sum_foreign":""},"57":{"sum_foreign_comment":"","sum":"","sum_comment":"","sum_unclear":false,"sum_foreign":""},"58":{"sum_foreign_comment":"","sum":"","sum_comment":"","sum_foreign":""},"59":{"sum_foreign_comment":"","sum":"","sum_comment":"","sum_foreign":""},"60":{"sum_foreign_comment":"","sum":"","sum_comment":"","sum_foreign":""},"61":{"sum_foreign_comment":"","sum":"","sum_comment":"","sum_foreign":""},"62":{"sum_foreign_comment":"","sum":"","sum_comment":"","sum_comment_unclear":false,"sum_unclear":false,"sum_foreign":""},"63":{"sum_foreign_comment":"","sum":"","sum_comment":"","sum_foreign":""},"64":{"sum_foreign_comment":"","sum":"","sum_comment":"","sum_foreign":""}},"ft_src":"суддя апеляційного суду житомирської області\nЖитомирська область\nЗагальний апеляційний суд\nТетяна\nБатьки\nАнатоліївна\nЄвстаф'єва\nЄвстаф'єва Тетяна Анатоліївна\nЄвстаф'єва Тетяна Анатоліївна\nТетяна Анатоліївна Євстаф'єва\nТетяна Євстаф'єва\nЄвстаф'єва Тетяна Анатоліївна\n13398\nпенсія\n52594.77\n15561.36\nпенсія\n285775.65\n15561.36\n219782.88\n4000\nм. Бердичів\nЖитомирська область\n55.5\nм. Бердичів\nЖитомирська область\n50.1\n2014\n219782.88\n13398\n15561.36\n285775.65\nпенсія\nпенсія\n15561.36\n52594.77\n4000\n2014\nЄвстаф'єва Тетяна Анатоліївна\nТетяна Анатоліївна Євстаф'єва\nТетяна Євстаф'єва\nЄвстаф'єва Тетяна Анатоліївна\nЄвстаф'єва Тетяна Анатоліївна\nБатьки\nТетяна\nАнатоліївна\nсуддя апеляційного суду житомирської області\nЖитомирська область\nЗагальний апеляційний суд\nЄвстаф'єва\n219782.88\n52594.77\nпенсія\nпенсія\n15561.36\n15561.36\n285775.65\n13398\n55.5\nЖитомирська область\nм. Бердичів\n50.1\nм. Бердичів\nЖитомирська область\nБатьки\nТетяна\nАнатоліївна\nЄвстаф'єва\nЄвстаф'єва Тетяна Анатоліївна\nТетяна Анатоліївна Євстаф'єва\nТетяна Євстаф'єва\nЄвстаф'єва Тетяна Анатоліївна\nсуддя апеляційного суду житомирської області\nЖитомирська область\nЗагальний апеляційний суд\nЄвстаф'єва Тетяна Анатоліївна\nм. Бердичів\nЖитомирська область\n55.5\nм. Бердичів\nЖитомирська область\n50.1\n4000\n2014","general":{"inn":"","name":"Тетяна","family":[{"inn":"","inn_hidden":true,"relations_hidden":false,"family_name":"","relations_other":"","relations":"Батьки","name_hidden":true,"name_unclear":false}],"patronymic":"Анатоліївна","inn_hidden":true,"family_raw":"","last_name":"Євстаф'єва","post":{"post_unclear":false,"post_hidden":false,"post":"суддя апеляційного суду житомирської області","region":"Житомирська область","office":"Загальний апеляційний суд"},"last_name_unclear":false,"full_name":"Євстаф'єва Тетяна Анатоліївна","addresses":[{"place_district":"","place_city_hidden":true,"place_city":"","place_city_type_hidden":false,"place_district_hidden":true,"place_city_type":"","place_address_hidden":false,"place_address":"","place_hidden":true,"place":""}],"full_name_suggest":{"output":"Євстаф'єва Тетяна Анатоліївна","input":["Євстаф'єва Тетяна Анатоліївна","Тетяна Анатоліївна Євстаф'єва","Тетяна Євстаф'єва"]}},"source":"VULYK","estate":{"23":[{"space_unclear":false,"costs":"","costs_comment":"","address_hidden":false,"region_hidden":false,"space_comment":"","space_hidden":false,"space":"","address":"","region":"","address_unclear":false,"costs_rent_comment":"","space_units":"м²","costs_rent":""},{"space_unclear":false,"costs":"","costs_comment":"","address_hidden":false,"space_comment":"","space":"","address":"","region":"","address_unclear":false,"costs_rent_comment":"","space_units":"","costs_rent":""},{"costs_rent":"","space_unclear":false,"region":"","costs":"","costs_rent_comment":"","costs_comment":"","space_comment":"","space_units":"","space":"","address":""},{"costs_rent":"","region":"","costs":"","costs_rent_comment":"","costs_comment":"","space_comment":"","space_units":"","space":"","address":""}],"25":[{"space_unclear":false,"costs":"","costs_comment":"","address_hidden":true,"region_hidden":false,"space_comment":"","space_hidden":false,"space":"50.1","address":"м. Бердичів","region":"Житомирська область","costs_rent_comment":"","space_comment_unclear":false,"space_units":"м²","costs_rent":""}],"30":[{"space_unclear":false,"address_hidden":true,"region_hidden":false,"space_comment":"","space_hidden":false,"space":"55.5","address":"м. Бердичів","region":"Житомирська область","costs_property":"","costs_rent_comment":"","space_units":"м²","costs_property_comment":"","costs_rent":""}]},"intro":{"declaration_year":"2014","isnotdeclaration":"","declaration_year_unclear":false}}