{"income":{"5":{"family_comment":"","family_unclear":false,"value":"253603.21","family":"","comment":""},"6":{"family_comment":"","family_unclear":false,"value":"208303.73","family":"","comment":""},"7":{"value":"","comment_hidden":false,"family_comment":"","source_name":"","family":"","comment":""},"8":{"family_comment":"","value":"","family":"","comment":""},"9":{"family_comment":"","value":"","family":"","comment":""},"10":{"family_comment":"","value":"13398","family":"","comment":""},"11":{"family_comment":"","value":"","value_unclear":false,"family":"","comment":""},"12":{"family_comment":"","value":"","family":"","comment":""},"13":{"family_comment":"","value":"","family":"","comment":""},"14":{"family_comment":"","value":"","family":"","comment":""},"15":{"family_comment":"","value":"31901.48","value_unclear":false,"family":"","comment":""},"16":{"family_comment":"","family_unclear":false,"value":"","family":"","comment":""},"17":{"family_comment":"","value":"","family":"","comment":""},"18":{"family_comment":"","value":"","family_hidden":false,"comment":"","family":""},"19":{"family_comment":"","value":"","family":"","comment":""},"20":{"value":"","comment_unclear":false,"comment_hidden":false,"family_comment":"","family":"","comment":"","family_comment_hidden":false}},"id":"vulyk_68_94","declaration":{"additional_info_text":"","notfull_lostpages":"","date":"2015-03-31T00:00:00","notfull":"","additional_info":"","url":"http://static.declarations.com.ua/declarations/chosen_ones/mega_batch/zvarych_oksana_volodymyrivna.pdf"},"liabilities":{"54":{"sum_foreign_comment":"","sum":"","sum_comment":"","sum_comment_unclear":false,"sum_hidden":false,"sum_comment_hidden":false,"sum_unclear":false,"sum_foreign":""},"55":{"sum_foreign_comment":"","sum":"","sum_hidden":false,"sum_comment":"","sum_foreign":""},"56":{"sum_foreign_comment":"","sum_foreign_hidden":false,"sum_comment":"","sum":"16293.44","sum_unclear":false,"sum_foreign":""},"57":{"sum_foreign_comment":"","sum":"","sum_comment":"","sum_comment_unclear":false,"sum_hidden":false,"sum_comment_hidden":false,"sum_unclear":false,"sum_foreign":""},"58":{"sum_foreign_comment":"","sum":"","sum_comment":"","sum_hidden":false,"sum_comment_hidden":false,"sum_unclear":false,"sum_foreign":""},"59":{"sum_foreign_comment":"","sum":"","sum_comment":"","sum_foreign":""},"60":{"sum_foreign_comment":"","sum":"","sum_comment":"","sum_comment_unclear":false,"sum_hidden":false,"sum_comment_hidden":false,"sum_unclear":false,"sum_foreign":""},"61":{"sum_foreign_comment":"","sum":"","sum_hidden":false,"sum_comment":"","sum_foreign":""},"62":{"sum_foreign_comment":"","sum":"16293.44","sum_comment":"","sum_unclear":false,"sum_foreign":""},"63":{"sum_foreign_comment":"","sum":"","sum_comment":"","sum_hidden":false,"sum_comment_hidden":false,"sum_unclear":false,"sum_foreign":""},"64":{"sum_foreign_comment":"","sum":"","sum_comment":"","sum_hidden":false,"sum_comment_hidden":false,"sum_foreign":""}},"ft_src":"16293.44\n16293.44\nсуддя\nЛьвівська область\nАпеляційний господарський суд\nОксана\nЗварич Ігор Степанович\nПодружжя\nЗварич Іванна Ігорівна\nДитина\nВолодимирівна\nЗварич Оксана Володимирівна\nОксана Володимирівна Зварич\nОксана Зварич\nЗварич Оксана Володимирівна\nЗварич Оксана Володимирівна\nЗварич\n31901.48\n13398\n253603.21\n208303.73\n16.8\n16.8\nу спільній сумісній власності\n318.7\nу спільній сумісній власності\n.242\nу спільній сумісній власності\n.242\nу спільній сумісній власності\n318.7\n+120 мансарда, у спільній сумісній власності\n120\n+120 мансарда, у спільній сумісній власності\n120\n2014\n208303.73\n31901.48\n13398\n253603.21\n16.8\n318.7\nу спільній сумісній власності\n120\n+120 мансарда, у спільній сумісній власності\nу спільній сумісній власності\n.242\n.242\nу спільній сумісній власності\n16.8\n318.7\nу спільній сумісній власності\n120\n+120 мансарда, у спільній сумісній власності\nЗварич Оксана Володимирівна\nОксана Володимирівна Зварич\nОксана Зварич\nЗварич Оксана Володимирівна\nЗварич Оксана Володимирівна\nПодружжя\nЗварич Ігор Степанович\nДитина\nЗварич Іванна Ігорівна\nОксана\nВолодимирівна\nАпеляційний господарський суд\nЛьвівська область\nсуддя\nЗварич\n16293.44\n16293.44\n208303.73\n31901.48\n253603.21\n13398\n2014\n16293.44\n16293.44\nПодружжя\nЗварич Ігор Степанович\nЗварич Іванна Ігорівна\nДитина\nВолодимирівна\nЗварич\nОксана\nЗварич Оксана Володимирівна\nОксана Володимирівна Зварич\nОксана Зварич\nЗварич Оксана Володимирівна\nЛьвівська область\nАпеляційний господарський суд\nсуддя\nЗварич Оксана Володимирівна\n+120 мансарда, у спільній сумісній власності\n120\nу спільній сумісній власності\n.242\nу спільній сумісній власності\n318.7\n16.8\nу спільній сумісній власності\n318.7\n16.8\n120\n+120 мансарда, у спільній сумісній власності\nу спільній сумісній власності\n.242\n2014","general":{"inn":"","name":"Оксана","inn_unclear":false,"family":[{"inn":"","inn_hidden":false,"relations_unclear":false,"relations_hidden":false,"relations_other":"","relations":"Подружжя","name_hidden":false,"inn_unclear":false,"family_name":"Зварич Ігор Степанович","name_unclear":false},{"inn":"","inn_hidden":false,"inn_unclear":false,"relations_hidden":false,"relations_other":"","relations":"Дитина","name_hidden":false,"family_name":"Зварич Іванна Ігорівна","name_unclear":false}],"inn_hidden":false,"family_raw":"","last_name":"Зварич","post":{"post_unclear":false,"region_unclear":false,"post":"суддя","office":"Апеляційний господарський суд","region":"Львівська область","post_hidden":false,"office_hidden":false,"office_unclear":false,"region_hidden":false},"full_name_suggest":{"output":"Зварич Оксана Володимирівна","input":["Зварич Оксана Володимирівна","Оксана Володимирівна Зварич","Оксана Зварич"]},"full_name":"Зварич Оксана Володимирівна","patronymic":"Володимирівна","last_name_unclear":false,"name_unclear":false},"source":"VULYK","estate":{"23":[{"costs":"","costs_comment":"","address_hidden":false,"region_hidden":false,"space_comment":"у спільній сумісній власності","space":".242","address":"","region":"","costs_rent_comment":"","space_comment_hidden":false,"space_units":"га","costs_rent":""}],"24":[{"region_unclear":false,"space_unclear":false,"costs":"","costs_comment":"","address_hidden":false,"region_hidden":false,"space_comment":"у спільній сумісній власності","space":"318.7","address":"","region":"","costs_rent_comment":"","space_units":"м²","costs_rent":""}],"25":[{"space_unclear":false,"costs":"","costs_comment":"","address_hidden":false,"region_hidden":false,"space_comment":"+120 мансарда, у спільній сумісній власності","space_hidden":false,"space":"120","address":"","space_comment_unclear":false,"region":"","address_unclear":false,"costs_rent_comment":"","costs_unclear":false,"space_units":"м²","space_units_hidden":false,"costs_rent":""}],"27":[{"costs_rent":"","region":"","costs":"","costs_rent_comment":"","costs_comment":"","address_hidden":false,"region_hidden":false,"space_comment":"","space_units":"м²","space":"16.8","address":""}],"29":[{"space_unclear":false,"address_hidden":false,"region_hidden":false,"space_comment":"у спільній сумісній власності","space_units_hidden":false,"space_hidden":false,"space":".242","address":"","region":"","costs_property":"","space_units_unclear":false,"space_units":"га","costs_property_comment":"","costs_rent":"","costs_rent_comment":""}],"30":[{"space_unclear":false,"address_hidden":false,"region_hidden":false,"space_comment":"у спільній сумісній власності","space_hidden":false,"space":"318.7","address":"","region":"","costs_property":"","costs_rent_comment":"","space_units":"м²","costs_property_comment":"","costs_rent":""}],"31":[{"space_unclear":false,"address_hidden":false,"region_hidden":false,"space_comment":"+120 мансарда, у спільній сумісній власності","space_hidden":false,"space":"120","address":"","region":"","costs_property":"","costs_rent_comment":"","space_units":"м²","costs_property_comment":"","costs_rent":""}],"33":[{"space_unclear":false,"address_hidden":false,"region_hidden":false,"space_comment":"","space":"16.8","address":"","region":"","costs_property":"","costs_rent_comment":"","space_comment_unclear":false,"space_units":"м²","costs_property_comment":"","costs_rent":""}]},"intro":{"declaration_year":"2014","isnotdeclaration":""}}