{"income":{"5":{"family_comment":"","value":"246044.64","family":"","comment":""},"6":{"family_comment":"","value":"229235.04","family":"","comment":"","family_comment_unclear":false},"7":{"value":"","comment_hidden":false,"family_comment":"","source_name":"","family":"","comment":"","source_name_hidden":false},"8":{"family_comment":"","value":"","family":"","comment":""},"9":{"family_comment":"","value":"","family":"","comment":""},"10":{"value":"12180","value_unclear":false,"value_hidden":false,"family_comment":"","family":"","comment":""},"11":{"family_comment":"","value":"","family":"","comment":""},"12":{"family_comment":"","value":"","family":"","comment":""},"13":{"family_comment":"","value":"4629.6","family":"","comment":""},"14":{"family_comment":"","value":"","family":"","comment":""},"15":{"family_comment":"","value":"","family":"","comment":""},"16":{"family_comment":"","value":"","family":"","comment":""},"17":{"family_comment":"","value":"","family":"","comment":""},"18":{"family_comment":"","value":"","family":"","comment":""},"19":{"family_comment":"","value":"","family":"","comment":""},"20":{"family_comment":"","value":"","comment_unclear":false,"family":"","comment":""}},"id":"vulyk_86_71","declaration":{"additional_info_text":"","notfull_lostpages":"","date":"2015-03-16T00:00:00","notfull":"","additional_info":"","url":"http://static.declarations.com.ua/declarations/chosen_ones/judges_batch/2774_fil_olena_ievhenivna.pdf"},"liabilities":{"54":{"sum_foreign_comment":"","sum":"","sum_comment":"","sum_unclear":false,"sum_foreign":""},"55":{"sum_foreign_comment":"","sum":"","sum_comment":"","sum_foreign":""},"56":{"sum_foreign_comment":"","sum":"8014","sum_hidden":false,"sum_comment":"","sum_foreign":""},"57":{"sum_foreign_comment":"","sum":"","sum_comment":"","sum_unclear":false,"sum_foreign":""},"58":{"sum_foreign_comment":"","sum":"","sum_comment":"","sum_unclear":false,"sum_foreign":""},"59":{"sum_foreign_comment":"","sum":"13500","sum_comment":"","sum_foreign":""},"60":{"sum_foreign_comment":"","sum_comment_hidden":false,"sum":"","sum_comment":"","sum_foreign":""},"61":{"sum_foreign_comment":"","sum":"","sum_comment":"","sum_foreign":""},"62":{"sum_foreign_comment":"","sum":"","sum_comment":"","sum_foreign":""},"63":{"sum_foreign_comment":"","sum":"","sum_comment":"","sum_foreign":""},"64":{"sum_foreign_comment":"","sum":"","sum_comment":"","sum_foreign":""}},"ft_src":"13500\n8014\nКрасноармійськ\nДонецька область\nсуддя красноармійського міськрайонного суду донецької області\nДонецька область\nЗагальний місцевий суд\nОлена\nФіль К. Д\nДитина\nЄвгенівна\nФіль Олена Євгенівна\nОлена Євгенівна Філь\nОлена Філь\nФіль Олена Євгенівна\nФіль Олена Євгенівна\nФіль\n12180\n246044.64\n229235.04\n4629.6\nм. Красноармійськ\n.035\nДонецька область\nДонецька область\nм. Красноармійськ\n66.4\nм. Красноармійськ\n57.9\nДонецька область\n2014\n229235.04\n4629.6\n12180\n246044.64\n229235.04\n4629.6\n246044.64\n12180\nФіль Олена Євгенівна\nОлена Євгенівна Філь\nОлена Філь\nФіль Олена Євгенівна\nФіль Олена Євгенівна\nДитина\nФіль К. Д\nОлена\nФіль\nЗагальний місцевий суд\nДонецька область\nсуддя красноармійського міськрайонного суду донецької області\nЄвгенівна\nДонецька область\nКрасноармійськ\n13500\n8014\n.035\nДонецька область\nм. Красноармійськ\n66.4\nДонецька область\nм. Красноармійськ\n57.9\nм. Красноармійськ\nДонецька область\n2014\n8014\n13500\nФіль К. Д\nДитина\nЄвгенівна\nФіль\nОлена\nФіль Олена Євгенівна\nОлена Євгенівна Філь\nОлена Філь\nФіль Олена Євгенівна\nКрасноармійськ\nДонецька область\nДонецька область\nЗагальний місцевий суд\nсуддя красноармійського міськрайонного суду донецької області\nФіль Олена Євгенівна\nм. Красноармійськ\nДонецька область\n57.9\nм. Красноармійськ\nДонецька область\n.035\nм. Красноармійськ\nДонецька область\n66.4\n2014","general":{"inn":"","name":"Олена","patronymic_unclear":false,"family":[{"inn":"","inn_hidden":true,"relations_hidden":false,"family_name":"Філь К. Д","relations_other":"","relations":"Дитина","name_hidden":false,"name_unclear":false}],"patronymic":"Євгенівна","inn_hidden":true,"family_raw":"","inn_unclear":false,"post":{"post_unclear":false,"post":"суддя красноармійського міськрайонного суду донецької області","candidate":"","office_hidden":false,"region":"Донецька область","office":"Загальний місцевий суд","office_unclear":true,"region_hidden":false},"full_name":"Філь Олена Євгенівна","addresses":[{"place_district":"","place_unclear":false,"place_city":"Красноармійськ","place_city_type_hidden":false,"place_district_hidden":false,"place_city_type":"Місто","place_city_hidden":false,"place_address_hidden":true,"place_address":"","place_hidden":false,"place":"Донецька область"}],"last_name":"Філь","full_name_suggest":{"output":"Філь Олена Євгенівна","input":["Філь Олена Євгенівна","Олена Євгенівна Філь","Олена Філь"]}},"source":"VULYK","estate":{"23":[{"costs":"","costs_comment":"","address_hidden":true,"region_hidden":false,"space_comment":"","space":".035","address":"м. Красноармійськ","region":"Донецька область","address_unclear":false,"costs_rent_comment":"","space_units":"га","costs_rent":""}],"24":[{"costs":"","costs_comment":"","address_hidden":true,"region_hidden":false,"space_comment":"","space":"66.4","address":"м. Красноармійськ","region":"Донецька область","address_unclear":false,"costs_rent_comment":"","space_units":"м²","costs_rent":""}],"25":[{"space_unclear":false,"costs":"","costs_comment":"","address_hidden":true,"region_hidden":false,"space_comment":"","space_hidden":false,"space":"57.9","address":"м. Красноармійськ","region":"Донецька область","address_unclear":false,"costs_rent_comment":"","space_units":"м²","costs_rent":""}]},"intro":{"declaration_year":"2014","declaration_year_unclear":false}}