{"income":{"5":{"family_comment":"","value":"328870","value_unclear":false,"family":"48391","comment":""},"6":{"family_comment":"","value":"287101","value_unclear":false,"family":"","comment":""},"7":{"source_name_unclear":false,"value":"28005","family_hidden":false,"value_hidden":false,"family_comment":"","source_name":"Національний технічний університет України 'Київський політехнічний інститут'","family":"","comment":"","source_name_hidden":false},"8":{"value":"","family_hidden":false,"value_hidden":false,"family_comment":"","family":"","comment":""},"9":{"value":"","value_unclear":false,"value_hidden":false,"family_comment":"","comment_unclear":false,"comment":"","family":""},"10":{"value":"13764","family_hidden":false,"value_hidden":false,"family_comment":"","family":"","comment":""},"11":{"value":"","family_hidden":false,"value_hidden":false,"family_comment":"","family":"","comment":""},"12":{"value":"","family_hidden":false,"value_hidden":false,"family_comment":"","family":"","comment":""},"13":{"value":"","family_hidden":false,"value_hidden":false,"family_comment":"","family":"","comment":""},"14":{"value":"","family_hidden":false,"value_hidden":false,"family_comment":"","family":"","comment":""},"15":{"value":"","family_hidden":false,"value_hidden":false,"family_comment":"","family":"","comment":""},"16":{"value":"","family_hidden":false,"value_hidden":false,"family_comment":"","family":"","comment":""},"17":{"value":"","family_hidden":false,"value_hidden":false,"family_comment":"","family":"","comment":""},"18":{"value":"","comment_unclear":false,"family_hidden":false,"value_hidden":false,"family_comment":"","family":"","comment":""},"19":{"value":"","family_hidden":false,"value_hidden":false,"family_comment":"","family":"","comment":""},"20":{"value":"","value_unclear":false,"family_hidden":false,"value_hidden":false,"family_comment":"пенсія військовослужбовця","comment_unclear":false,"comment":"","family":"48391"}},"vehicle":{"35":[{"brand_info":"1598","sum_rent_comment":"","sum_rent_hidden":false,"year":"2005","sum_hidden":false,"brand_info_unclear":false,"sum_rent":"","sum":"","brand":"Skoda Octavia","sum_comment":"","brand_unclear":false,"sum_rent_comment_hidden":false,"sum_comment_hidden":false,"sum_unclear":false}],"40":[{"brand_info":"1699","sum":"","brand":"Mercedes-Benz B 170","sum_comment":"","brand_unclear":false,"year":"2008","brand_hidden":false,"brand_info_hidden":false,"brand_info_unclear":false,"sum_rent_comment":"","sum_rent":""}],"44":[{"brand_info":"бортовий","sum":"","brand":"автопричіп до легкового автомобіля","sum_comment":"","year":"2009","brand_hidden":false,"sum_rent_comment":"","sum_rent":""}]},"id":"vulyk_53_93","declaration":{"additional_info_text":"Декларація не є цілісною, склеєна лише з заповнених пунктів, підпис та дата заповнення відсутні. Відсутні пункти 2, 8-9, 11-19, 21-22, 24, 26-28, 30-32, 34, 36-39, 41-43, 45-64","notfull":"1","additional_info":"1","notfull_lostpages":"подано лише окремі частини декларації (витяги окремих позицій з окремих розділів","url":"http://static.declarations.com.ua/declarations/chosen_ones/judges_batch/153_shevchuk_svitlana_rostyslavivna.pdf"},"liabilities":{"54":{"sum_foreign_comment":"","sum":"","sum_comment":"","sum_hidden":false,"sum_foreign_comment_unclear":false,"sum_comment_hidden":false,"sum_foreign_hidden":false,"sum_foreign":""},"55":{"sum_foreign_comment":"","sum":"","sum_foreign":"","sum_comment":"","sum_hidden":false},"56":{"sum_foreign_comment":"","sum":"","sum_comment":"","sum_foreign":""},"57":{"sum_foreign_comment":"","sum":"","sum_comment":"","sum_hidden":false,"sum_comment_hidden":false,"sum_foreign_hidden":false,"sum_foreign":""},"58":{"sum_foreign_comment":"","sum":"","sum_comment":"","sum_hidden":false,"sum_comment_hidden":false,"sum_foreign":""},"59":{"sum_foreign_comment":"","sum":"","sum_comment":"","sum_hidden":false,"sum_foreign_hidden":false,"sum_foreign":""},"60":{"sum_foreign_comment":"","sum":"","sum_comment":"","sum_comment_unclear":false,"sum_hidden":false,"sum_comment_hidden":false,"sum_foreign":""},"61":{"sum_foreign_comment":"","sum":"","sum_foreign":"","sum_comment":"","sum_hidden":false},"62":{"sum_foreign_comment":"","sum_unclear":false,"sum":"","sum_comment":"","sum_comment_hidden":false,"sum_foreign_hidden":false,"sum_foreign":""},"63":{"sum_foreign_comment":"","sum":"","sum_comment":"","sum_hidden":false,"sum_comment_hidden":false,"sum_foreign_hidden":false,"sum_foreign":""},"64":{"sum_foreign_comment":"","sum":"","sum_comment":"","sum_hidden":false,"sum_comment_hidden":false,"sum_foreign":""}},"ft_src":"Skoda Octavia\n1598\n2005\nMercedes-Benz B 170\n1699\n2008\n2009\nбортовий\nавтопричіп до легкового автомобіля\nмашиномісце\n19.6\n2825\n1324\n1324\nземельний пай\n38602\n52\nподано лише окремі частини декларації (витяги окремих позицій з окремих розділів\n1\n1\nДекларація не є цілісною, склеєна лише з заповнених пунктів, підпис та дата заповнення відсутні. Відсутні пункти 2, 8-9, 11-19, 21-22, 24, 26-28, 30-32, 34, 36-39, 41-43, 45-64\n2013\n287101\n13764\nНаціональний технічний університет України 'Київський політехнічний інститут'\n28005\n48391\n328870\nпенсія військовослужбовця\n48391\n1598\nSkoda Octavia\n2005\n1699\n2008\nMercedes-Benz B 170\nбортовий\nавтопричіп до легкового автомобіля\n2009\nДекларація не є цілісною, склеєна лише з заповнених пунктів, підпис та дата заповнення відсутні. Відсутні пункти 2, 8-9, 11-19, 21-22, 24, 26-28, 30-32, 34, 36-39, 41-43, 45-64\n1\n1\nподано лише окремі частини декларації (витяги окремих позицій з окремих розділів\n2013\nПодружжя\nЛевчук А. С\nШевчук Світлана Ростиславівна\nСвітлана Ростиславівна Шевчук\nСвітлана Шевчук\nШевчук Світлана Ростиславівна\nСвітлана\nШевчук Світлана Ростиславівна\nРостиславівна\nсуддя вищого господарського суду україни\nВищий господарський суд\nЗагальнодержавний регіон\nШевчук\n28005\nНаціональний технічний університет України 'Київський політехнічний інститут'\n287101\nпенсія військовослужбовця\n48391\n328870\n48391\n13764\n2825\n1324\n19.6\nмашиномісце\n52\n1324\nземельний пай\n38602\nПодружжя\nЛевчук А. С\nСвітлана\nРостиславівна\nШевчук\nШевчук Світлана Ростиславівна\nСвітлана Ростиславівна Шевчук\nСвітлана Шевчук\nШевчук Світлана Ростиславівна\nЗагальнодержавний регіон\nВищий господарський суд\nсуддя вищого господарського суду україни\nШевчук Світлана Ростиславівна","general":{"inn":"","name":"Світлана","last_name":"Шевчук","family":[{"inn":"","relations":"Подружжя","inn_unclear":false,"relations_hidden":false,"inn_hidden":true,"family_name":"Левчук А. С","relations_other":"","name_hidden":false,"name_unclear":false}],"inn_hidden":true,"family_raw":"","inn_unclear":false,"post":{"post":"суддя вищого господарського суду україни","region":"Загальнодержавний регіон","candidate":"","post_hidden":false,"office":"Вищий господарський суд","office_hidden":false,"region_hidden":false},"full_name_suggest":{"output":"Шевчук Світлана Ростиславівна","input":["Шевчук Світлана Ростиславівна","Світлана Ростиславівна Шевчук","Світлана Шевчук"]},"full_name":"Шевчук Світлана Ростиславівна","addresses":[{"place_city_type_unclear":false,"place_city_type_hidden":true,"place_district_hidden":true,"place_city_type":"","place_address_hidden":true,"place_address_unclear":false,"place_address":"","place":"","place_district":"","place_unclear":false,"place_hidden":true,"place_city_unclear":false,"place_city_hidden":true,"place_city":"","place_district_unclear":false}],"patronymic":"Ростиславівна","last_name_unclear":false,"name_unclear":false},"source":"VULYK","estate":{"23":[{"region_unclear":false,"space_hidden":false,"costs_comment_hidden":false,"costs_comment":"","costs_hidden":false,"address_hidden":false,"region_hidden":true,"space_comment":"","space_unclear":false,"space_units_unclear":false,"address":"","costs_comment_unclear":false,"region":"","address_unclear":false,"space":"2825","costs_rent_hidden":false,"costs":"","costs_rent_comment_hidden":false,"space_units":"м²","costs_rent":"","costs_rent_comment":""},{"space_unclear":false,"costs":"","costs_comment":"","costs_hidden":false,"address_hidden":false,"region_hidden":false,"space_comment":"","space":"1324","address":"","region":"","costs_rent_comment":"","costs_rent_hidden":false,"space_units":"м²","costs_rent":""}],"25":[{"region_unclear":false,"space_unclear":false,"costs":"","costs_comment":"","costs_hidden":false,"address_hidden":false,"region_hidden":true,"space_comment":"","space":"52","address":"","costs_rent_comment_unclear":false,"region":"","costs_rent_comment":"","costs_rent_hidden":false,"space_comment_unclear":false,"costs_rent_comment_hidden":false,"space_units":"м²","costs_comment_hidden":false,"costs_rent":"","costs_unclear":false}],"29":[{"space_hidden":false,"costs_property_hidden":false,"address_hidden":false,"region_hidden":true,"space_comment":"","space_unclear":false,"space":"1324","address":"","region":"","costs_property":"","costs_rent_comment":"","costs_rent_hidden":false,"space_comment_hidden":false,"space_units":"м²","costs_property_comment":"","costs_rent":""},{"space_unclear":false,"region_hidden":false,"space_comment":"земельний пай","space":"38602","address":"","region":"","costs_property":"","costs_rent_comment":"","space_comment_unclear":true,"space_units":"м²","costs_property_comment":"","costs_rent":""}],"33":[{"region_unclear":true,"space_hidden":false,"costs_property_comment":"","costs_property_hidden":false,"address_hidden":false,"region_hidden":true,"space_comment":"машиномісце","space":"19.6","address":"","region":"","costs_property":"","costs_rent_comment":"","costs_rent_hidden":false,"space_units":"м²","space_units_hidden":false,"costs_rent":""}]},"intro":{"declaration_year":"2013","isnotdeclaration":"","declaration_year_unclear":false,"declaration_year_hidden":false}}