{"income":{"5":{"value":"208436.73","value_unclear":false,"value_hidden":false,"family_comment":"","family":"","comment":""},"6":{"value":"184744.49","family_comment":"","value_unclear":false,"family_unclear":false,"family":"","comment":""},"7":{"source_name_unclear":false,"value":"","family_hidden":false,"family_comment":"","source_name":"","family":"","comment":""},"8":{"family_comment":"","value":"","family":"","comment":""},"9":{"family_comment":"","value":"12421.37","family":"","comment":"банківські %"},"10":{"family_comment":"","value":"","family":"","comment":""},"11":{"family_comment":"","value":"","family":"","comment":""},"12":{"family_comment":"","value":"","family":"","comment":""},"13":{"family_comment":"","value":"11270.87","family":"","comment":""},"14":{"family_comment":"","value":"","family":"","comment":""},"15":{"family_comment":"","value":"","family":"","comment":""},"16":{"family_comment":"","value":"","comment_unclear":false,"family":"","comment":""},"17":{"family_comment":"","family_unclear":false,"value":"","family":"","comment":""},"18":{"family_comment":"","value":"","family":"","comment":""},"19":{"value":"","family_hidden":false,"value_hidden":false,"family_comment":"","family":"","comment":""},"20":{"family_comment":"","value":"","comment_unclear":false,"family":"","comment":""}},"id":"vulyk_67_166","banks":{"45":[{"sum_foreign_comment":"","sum":"82755.69","sum_comment":"","sum_comment_unclear":false,"sum_hidden":false,"sum_foreign_units":"UAH","sum_foreign_hidden":false,"sum_units":"UAH","sum_comment_hidden":false,"sum_unclear":false,"sum_foreign":""}],"46":[{"sum_foreign_comment":"","sum_units":"UAH","sum_comment":"","sum_foreign_units":"UAH","sum":"49290.33","sum_foreign":""}]},"declaration":{"additional_info_text":"","notfull_lostpages":"","date":"2015-03-30T00:00:00","notfull":"","additional_info":"","url":"http://static.declarations.com.ua/declarations/chosen_ones/mega_batch/kozachok_iryna_serhiivna.pdf"},"liabilities":{"54":{"sum_foreign_comment":"","sum_foreign_hidden":false,"sum_comment":"","sum_comment_unclear":false,"sum_hidden":false,"sum":"","sum_unclear":false,"sum_foreign":""},"55":{"sum_foreign_comment":"","sum":"","sum_comment":"","sum_foreign":""},"56":{"sum_foreign_comment":"","sum_foreign_hidden":false,"sum_comment":"","sum_hidden":false,"sum":"","sum_unclear":false,"sum_foreign":""},"57":{"sum_foreign_comment":"","sum_foreign_hidden":false,"sum_comment":"","sum_comment_unclear":false,"sum_hidden":false,"sum_comment_hidden":false,"sum_unclear":false,"sum":"","sum_foreign":""},"58":{"sum_foreign_comment":"","sum_foreign_hidden":false,"sum_comment":"","sum_comment_unclear":false,"sum_hidden":false,"sum_comment_hidden":false,"sum_unclear":false,"sum":"","sum_foreign":""},"59":{"sum_foreign_comment":"","sum":"","sum_hidden":false,"sum_comment":"","sum_foreign":""},"60":{"sum_foreign_comment":"","sum":"","sum_comment":"","sum_foreign":""},"61":{"sum_foreign_comment":"","sum_foreign_hidden":false,"sum_comment":"","sum_hidden":false,"sum":"","sum_foreign":""},"62":{"sum_foreign_comment":"","sum":"","sum_hidden":false,"sum_comment":"","sum_foreign":""},"63":{"sum_foreign_comment":"","sum":"","sum_comment":"","sum_comment_unclear":false,"sum_hidden":false,"sum_unclear":false,"sum_foreign":""},"64":{"sum_foreign_comment":"","sum":"","sum_comment":"","sum_hidden":false,"sum_unclear":false,"sum_foreign":""}},"ft_src":"суддя хмельницького окружного адміністративного суду\nХмельницька область\nАдміністративний місцевий суд\nІрина\nКозачок П. В\nДитина\nСергіївна\nКозачок Ірина Сергіївна\nКозачок\nКозачок Ірина Сергіївна\nІрина Сергіївна Козачок\nІрина Козачок\nКозачок Ірина Сергіївна\n208436.73\nбанківські %\n12421.37\n184744.49\n11270.87\n49290.33\n82755.69\n2014\n184744.49\n11270.87\n208436.73\nбанківські %\n12421.37\n82755.69\n49290.33\n184744.49\n11270.87\n208436.73\nбанківські %\n12421.37\nАдміністративний місцевий суд\nсуддя хмельницького окружного адміністративного суду\nХмельницька область\nДитина\nКозачок П. В\nКозачок Ірина Сергіївна\nІрина Сергіївна Козачок\nІрина Козачок\nКозачок Ірина Сергіївна\nКозачок Ірина Сергіївна\nІрина\nКозачок\nСергіївна\n2014\nДитина\nКозачок П. В\nСергіївна\nКозачок\nІрина\nКозачок Ірина Сергіївна\nІрина Сергіївна Козачок\nІрина Козачок\nКозачок Ірина Сергіївна\nХмельницька область\nсуддя хмельницького окружного адміністративного суду\nАдміністративний місцевий суд\nКозачок Ірина Сергіївна\n82755.69\n49290.33\n2014","general":{"inn":"","name":"Ірина","patronymic_unclear":false,"last_name_hidden":false,"family":[{"inn":"","inn_hidden":false,"relations_unclear":false,"relations_hidden":false,"relations_other":"","relations":"Дитина","name_hidden":false,"inn_unclear":false,"family_name":"Козачок П. В","name_unclear":false}],"patronymic":"Сергіївна","inn_hidden":true,"family_raw":"","inn_unclear":false,"post":{"post_unclear":false,"post":"суддя хмельницького окружного адміністративного суду","post_hidden":false,"region":"Хмельницька область","region_hidden":false,"office":"Адміністративний місцевий суд","office_hidden":false,"office_unclear":false},"last_name_unclear":false,"full_name":"Козачок Ірина Сергіївна","addresses":[{"place_city_type_hidden":false,"place_district_hidden":false,"place_city_type":"","place_city_hidden":false,"place_address_unclear":false,"place_address":"","place":"","place_district":"","place_unclear":false,"place_city":"","place_city_unclear":false,"place_hidden":false,"place_address_hidden":true,"place_district_unclear":false}],"last_name":"Козачок","full_name_suggest":{"output":"Козачок Ірина Сергіївна","input":["Козачок Ірина Сергіївна","Ірина Сергіївна Козачок","Ірина Козачок"]},"name_unclear":false},"source":"VULYK","intro":{"declaration_year":"2014","isnotdeclaration":"","declaration_year_hidden":false}}