{"income":{"5":{"value":"257780","family_comment":"","family_hidden":false,"value_hidden":false,"family_unclear":false,"family":"169189","comment":""},"6":{"value":"257780","comment_unclear":false,"family_comment":"","family":"168209","comment":"","family_comment_unclear":false},"7":{"family_comment":"","value":"","source_name":"","family":"","comment":""},"8":{"family_comment":"","value":"","family":"","comment":""},"9":{"family_comment":"","value":"","family":"","comment":""},"10":{"family_comment":"","value":"","family":"","comment":""},"11":{"family_comment":"","value":"","family":"210","comment":"","family_comment_unclear":false},"12":{"family_comment":"","value":"","family":"","comment":""},"13":{"family_comment":"","value":"","family":"","comment":""},"14":{"family_comment":"","value":"","family":"","comment":""},"15":{"family_comment":"","value":"","family":"","comment":""},"16":{"family_comment":"","value":"","family":"","comment":""},"17":{"family_comment":"","value":"","family":"","comment":""},"18":{"family_comment":"","value":"","family":"","comment":""},"19":{"family_comment":"","value":"","family":"","comment":"","value_hidden":false},"20":{"family_comment":"","value":"","comment_unclear":false,"family":"770","comment":""}},"vehicle":{"35":[{"brand_info":"3000 куб. см., потужність 176","sum_rent_comment":"","brand":"Volkswagen Touareg","sum_comment":"","sum_rent_hidden":false,"year":"","sum_hidden":false,"brand_info_hidden":false,"brand_info_unclear":false,"sum":"","sum_rent":""},{"brand_info":"1500 куб. см., потужність 75","sum_rent_comment":"","brand":"Mitsubishi Lancer","sum_comment":"","year":"","sum":"","sum_rent":""}],"39":[{"brand_info":"Причіп легковий","sum":"","brand":"","sum_comment":"","brand_unclear":false,"year":"2003","brand_hidden":true,"sum_rent_comment":"","sum_rent":""},{"brand_info":"Причіп легковий","sum_rent_comment":"","brand":"","sum_comment":"","year":"2013","sum":"","sum_rent":""}],"40":[{"brand_info":"1968 куб. см., потужність 102","sum_rent_comment":"","brand":"Volkswagen Passat","sum_comment":"","year":"2013","brand_info_unclear":false,"sum":"","sum_rent":""}]},"id":"vulyk_51_40","banks":{"45":[{"sum_foreign_comment":"","sum_units":"UAH","sum_comment":"","sum_comment_unclear":false,"sum_hidden":false,"sum_foreign_units":"UAH","sum_comment_hidden":false,"sum":"34829.27","sum_foreign":""},{"sum_foreign_comment":"","sum_units":"","sum_comment":"","sum_foreign_units":"","sum":"","sum_foreign":""},{"sum_foreign_comment":"","sum_units":"","sum_comment":"","sum_foreign_units":"","sum":"","sum_foreign":""},{"sum_foreign_comment":"","sum_units":"","sum_comment":"","sum_foreign_units":"","sum":"","sum_foreign":""},{"sum_foreign_comment":"","sum_units":"","sum_comment":"","sum_foreign_units":"","sum":"","sum_unclear":false,"sum_foreign":""}],"46":[{"sum_foreign_comment":"","sum_units":"UAH","sum_comment":"","sum_foreign_units":"UAH","sum":"","sum_foreign":""}],"47":[{"sum_foreign_comment":"","sum_units":"UAH","sum_comment":"","sum_foreign_units":"UAH","sum":"","sum_foreign":""}],"48":[{"sum_foreign_comment":"","sum_units":"UAH","sum_comment":"","sum_foreign_units":"UAH","sum":"","sum_foreign":""}],"49":[{"sum_foreign_comment":"","sum_units":"UAH","sum_comment":"","sum_foreign_units":"UAH","sum":"","sum_foreign":""}],"50":[{"sum_foreign_comment":"","sum_units":"UAH","sum_comment":"","sum_foreign_units":"UAH","sum":"","sum_foreign":""}],"51":[{"sum_foreign_comment":"","sum_units":"UAH","sum_comment":"","sum_foreign_units":"UAH","sum_comment_hidden":false,"sum":"31253.89","sum_foreign":""},{"sum_foreign_comment":"","sum_units":"","sum_comment":"","sum_foreign_units":"","sum":"","sum_foreign":""},{"sum_foreign_comment":"","sum_units":"","sum_comment":"","sum_foreign_units":"","sum":"","sum_foreign":""}],"52":[{"sum_foreign_comment":"","sum_units":"UAH","sum_comment":"","sum_foreign_units":"UAH","sum_comment_hidden":false,"sum":"","sum_foreign":""}],"53":[{"sum_foreign_comment":"","sum_units":"UAH","sum_comment":"","sum_foreign_units":"UAH","sum":"","sum_foreign":""}]},"declaration":{"additional_info_text":"","notfull_lostpages":"","date":"2015-03-25T00:00:00","notfull":"","additional_info":"","url":"http://static.declarations.com.ua/declarations/chosen_ones/mega_batch/stryzheus_anatolii_mykolaiovych.pdf"},"liabilities":{"54":{"sum_foreign_comment":"","sum_comment_hidden":false,"sum":"","sum_comment":"","sum_foreign":""},"55":{"sum_foreign_comment":"","sum":"","sum_comment":"","sum_foreign":""},"56":{"sum_foreign_comment":"","sum":"","sum_comment":"","sum_foreign":""},"57":{"sum_foreign_comment":"","sum":"","sum_comment":"","sum_hidden":false,"sum_comment_hidden":false,"sum_foreign":""},"58":{"sum_foreign_comment":"","sum_comment_hidden":false,"sum":"","sum_comment":"","sum_foreign":""},"59":{"sum_foreign_comment":"","sum":"","sum_comment":"","sum_foreign":""},"60":{"sum_foreign_comment":"","sum":"","sum_comment":"","sum_foreign":""},"61":{"sum_foreign_comment":"","sum":"","sum_comment":"","sum_foreign":""},"62":{"sum_foreign_comment":"","sum":"","sum_comment":"","sum_foreign":""},"63":{"sum_foreign_comment":"","sum_comment_hidden":false,"sum":"","sum_comment":"","sum_foreign":""},"64":{"sum_foreign_comment":"","sum":"","sum_comment":"","sum_foreign":""}},"ft_src":"Стрижеус Анатолій Миколайович\nсуддя апеляційного суду м. києва\nм. Київ\nЗагальний апеляційний суд\nАнатолій\nСтрижеус Л. С\nПодружжя\nСтрижеус Д. А\nДитина\nСтрижеус В. А\nДитина\nСтрижеус Анатолій Миколайович\nАнатолій Миколайович Стрижеус\nАнатолій Стрижеус\nСтрижеус Анатолій Миколайович\nСтрижеус\nМиколайович\nПричіп легковий\n2003\nПричіп легковий\n2013\nVolkswagen Touareg\n3000 куб. см., потужність 176\n1500 куб. см., потужність 75\nMitsubishi Lancer\n1968 куб. см., потужність 102\n2013\nVolkswagen Passat\n31253.89\n34829.27\n2014\n3000 куб. см., потужність 176\nVolkswagen Touareg\n1500 куб. см., потужність 75\nMitsubishi Lancer\n1968 куб. см., потужність 102\nVolkswagen Passat\n2013\nПричіп легковий\n2003\nПричіп легковий\n2013\n34829.27\n31253.89\n29.8\n41.4\nСтрижеус\nСтрижеус Анатолій Миколайович\nАнатолій Миколайович Стрижеус\nАнатолій Стрижеус\nСтрижеус Анатолій Миколайович\nАнатолій\nМиколайович\nСтрижеус Анатолій Миколайович\nЗагальний апеляційний суд\nсуддя апеляційного суду м. києва\nм. Київ\nПодружжя\nСтрижеус Л. С\nДитина\nСтрижеус Д. А\nДитина\nСтрижеус В. А\n257780\n168209\n770\n169189\n257780\n210\n2014\n29.8\n41.4\nСтрижеус Л. С\nПодружжя\nСтрижеус Д. А\nДитина\nСтрижеус В. А\nДитина\nМиколайович\nСтрижеус\nм. Київ\nЗагальний апеляційний суд\nсуддя апеляційного суду м. києва\nСтрижеус Анатолій Миколайович\nСтрижеус Анатолій Миколайович\nАнатолій Миколайович Стрижеус\nАнатолій Стрижеус\nСтрижеус Анатолій Миколайович\nАнатолій\n168209\n257780\n210\n169189\n257780\n770\nПричіп легковий\n2003\nПричіп легковий\n2013\nVolkswagen Touareg\n3000 куб. см., потужність 176\nMitsubishi Lancer\n1500 куб. см., потужність 75\n2013\n1968 куб. см., потужність 102\nVolkswagen Passat\n210\n770\n257780\n169189\n257780\n168209\n29.8\n41.4\n34829.27\n31253.89\n2014","general":{"inn":"","inn_hidden":true,"last_name":"Стрижеус","post":{"post":"суддя апеляційного суду м. києва","region":"м. Київ","office_hidden":false,"office":"Загальний апеляційний суд","office_unclear":false,"region_hidden":false},"name":"Анатолій","full_name":"Стрижеус Анатолій Миколайович","family_raw":"","addresses":[{"place_district":"","place_city_hidden":true,"place_city":"","place_city_type_hidden":true,"place_district_hidden":true,"place_city_type":"","place_address_hidden":true,"place_address":"","place_hidden":true,"place":""}],"family":[{"inn":"","relations":"Подружжя","relations_other":"","inn_hidden":true,"family_name":"Стрижеус Л. С","name_hidden":false,"name_unclear":false},{"inn":"","inn_hidden":false,"relations_hidden":false,"family_name":"Стрижеус Д. А","relations_other":"","relations":"Дитина","name_hidden":false,"name_unclear":false},{"inn":"","relations":"Дитина","relations_other":"","inn_hidden":false,"family_name":"Стрижеус В. А","name_hidden":false,"name_unclear":false}],"full_name_suggest":{"output":"Стрижеус Анатолій Миколайович","input":["Стрижеус Анатолій Миколайович","Анатолій Миколайович Стрижеус","Анатолій Стрижеус"]},"patronymic":"Миколайович"},"source":"VULYK","estate":{"23":[{"costs":"","costs_comment":"","costs_hidden":false,"address_hidden":false,"region_hidden":false,"space_comment":"","space":"","address":"","region":"","address_unclear":false,"costs_rent_comment":"","costs_rent_hidden":false,"space_units":"м²","costs_rent":""},{"costs":"","costs_comment":"","costs_hidden":false,"region_hidden":false,"space_comment":"","space":"","address":"","region":"","costs_rent_comment":"","costs_rent_hidden":false,"space_units":"","costs_rent":""},{"space":"","region":"","costs":"","costs_rent_comment":"","costs_comment":"","address_unclear":false,"space_comment":"","space_units":"","costs_rent":"","address":""},{"costs_rent":"","region":"","costs":"","costs_rent_comment":"","costs_comment":"","space_comment":"","space_units":"","space":"","address":""}],"25":[{"space_unclear":false,"costs":"","costs_comment":"","costs_hidden":false,"address_hidden":true,"region_hidden":true,"space_comment":"","space_hidden":false,"space":"41.4","address":"","region":"","address_unclear":false,"costs_rent_comment":"","space_units":"м²","costs_rent":""}],"31":[{"space_hidden":false,"costs_property_hidden":false,"address_hidden":false,"region_hidden":false,"space_comment":"","space_unclear":false,"space":"29.8","address":"","region":"","address_unclear":false,"costs_rent_comment":"","costs_rent_hidden":false,"costs_property":"","space_units":"м²","costs_property_comment":"","costs_rent":""}]},"intro":{"declaration_year":"2014","isnotdeclaration":""}}