{"income":{"5":{"value":"251374.38","family_comment":"","value_unclear":false,"family_hidden":false,"value_hidden":false,"family_unclear":false,"family_comment_hidden":false,"comment":"","family":"8500"},"6":{"value":"237976.38","family_comment":"стипендія","value_unclear":false,"family_hidden":false,"family_unclear":false,"family":"8500","comment":""},"7":{"family_comment":"","value":"","source_name":"","family":"","comment":""},"8":{"family_comment":"","value":"","family":"","comment":""},"9":{"family_comment":"","value":"","family":"","comment":""},"10":{"family_comment":"","family_unclear":false,"value":"13398","family":"","comment":""},"11":{"family_comment":"","value":"","family":"","comment":""},"12":{"family_comment":"","value":"","family":"","comment":""},"13":{"family_comment":"","value":"","family":"","comment":""},"14":{"family_comment":"","value":"","comment_unclear":false,"family":"","comment":""},"15":{"family_comment":"","value":"","family":"","comment":""},"16":{"family_comment":"","value":"","family":"","comment":""},"17":{"family_comment":"","value":"","family":"","comment":""},"18":{"family_comment":"","value":"","family":"","comment":""},"19":{"family_comment":"","value":"","family":"","comment":""},"20":{"value":"","family_comment":"","value_unclear":false,"family_unclear":false,"comment_unclear":false,"comment":"","family":""}},"vehicle":{"35":[{"brand_info":"легковий комбі-В, об'єм двиг.1388","sum_rent_comment":"","brand_info_unclear":false,"year":"2007","sum_rent_unclear":false,"brand_info_hidden":false,"sum_rent_comment_unclear":false,"sum_rent":"","sum":"","brand":"Ford Fiesta GT","sum_comment":"","brand_hidden":false,"sum_rent_comment_hidden":false,"sum_unclear":false}]},"id":"vulyk_35_47","banks":{"45":[{"sum_foreign_comment":"","sum_units":"UAH","sum_comment":"","sum_comment_unclear":false,"sum_hidden":false,"sum_foreign_units":"UAH","sum_comment_hidden":false,"sum_unclear":false,"sum":"","sum_foreign":""},{"sum_foreign_comment":"","sum_units":"","sum_comment":"","sum_foreign_units":"","sum":"","sum_foreign":""},{"sum_foreign_comment":"","sum_units":"","sum_comment":"","sum_foreign_units":"","sum":"","sum_foreign":""}],"46":[{"sum_foreign_comment":"","sum_units":"UAH","sum_comment":"","sum_hidden":false,"sum_foreign_units":"UAH","sum_comment_hidden":false,"sum":"","sum_foreign":""},{"sum_foreign_comment":"","sum_units":"","sum_comment":"","sum_foreign_units":"","sum":"","sum_foreign":""}],"47":[{"sum_foreign_comment":"","sum_units":"UAH","sum_comment":"","sum_foreign_units":"UAH","sum":"","sum_foreign":""}],"48":[{"sum_foreign_comment":"","sum_units":"UAH","sum_comment":"","sum_foreign_units":"UAH","sum":"","sum_foreign":""}],"49":[{"sum_foreign_comment":"","sum_units":"UAH","sum_comment":"","sum_hidden":false,"sum_foreign_units":"UAH","sum":"","sum_foreign":""}],"50":[{"sum_foreign_comment":"","sum_units":"UAH","sum_comment":"","sum_foreign_units":"UAH","sum":"","sum_foreign":""}],"51":[{"sum_foreign_comment":"","sum_units":"UAH","sum_comment":"","sum_comment_unclear":false,"sum_foreign_units":"UAH","sum_comment_hidden":false,"sum":"","sum_foreign":""},{"sum_foreign_comment":"","sum_units":"","sum_comment":"","sum_foreign_units":"","sum":"","sum_foreign":""}],"52":[{"sum_foreign_comment":"","sum_units":"UAH","sum_comment":"","sum_foreign_units":"UAH","sum":"","sum_foreign":""}],"53":[{"sum_foreign_comment":"","sum_units":"UAH","sum_comment":"","sum_foreign_units":"UAH","sum":"","sum_foreign":""}]},"declaration":{"additional_info_text":"","notfull_lostpages":"","date":"2015-01-31T00:00:00","notfull":"","additional_info":"","url":"http://static.declarations.com.ua/declarations/chosen_ones/mega_batch/karpenko_oksana_volodymyrivna.pdf"},"liabilities":{"54":{"sum_foreign_comment":"","sum":"","sum_comment":"","sum_comment_unclear":false,"sum_hidden":false,"sum_comment_hidden":false,"sum_unclear":false,"sum_foreign":""},"55":{"sum_foreign_comment":"","sum":"","sum_comment":"","sum_foreign":""},"56":{"sum_foreign_comment":"","sum":"13500","sum_comment":"","sum_unclear":false,"sum_foreign":""},"57":{"sum_foreign_comment":"","sum":"","sum_comment":"","sum_comment_unclear":false,"sum_hidden":false,"sum_comment_hidden":false,"sum_unclear":false,"sum_foreign":""},"58":{"sum_foreign_comment":"","sum":"","sum_comment":"","sum_hidden":false,"sum_comment_hidden":false,"sum_foreign":""},"59":{"sum_foreign_comment":"","sum":"","sum_comment":"","sum_foreign":""},"60":{"sum_foreign_comment":"","sum_comment_hidden":false,"sum":"","sum_comment":"","sum_foreign":""},"61":{"sum_foreign_comment":"","sum":"","sum_comment":"","sum_foreign":""},"62":{"sum_foreign_comment":"","sum":"","sum_comment":"","sum_foreign":""},"63":{"sum_foreign_comment":"","sum":"","sum_comment":"","sum_hidden":false,"sum_comment_hidden":false,"sum_foreign":""},"64":{"sum_foreign_comment":"","sum":"","sum_comment":"","sum_hidden":false,"sum_comment_hidden":false,"sum_foreign":""}},"ft_src":"13500\nсуддя апеляційного суду черкаської області\nЧеркаська область\nЗагальний апеляційний суд\nОксана\nКарпенко А. В. 28. 04. 1993 р. н\nДитина\nКарпенко Е. Ю. 11. 07. 2006 р. н\nДитина\nВолодимирівна\nКарпенко Оксана Володимирівна\nОксана Володимирівна Карпенко\nОксана Карпенко\nКарпенко Оксана Володимирівна\nКарпенко\nКарпенко Оксана Володимирівна\nлегковий комбі-В, об'єм двиг.1388\n2007\nFord Fiesta GT\n2014\nлегковий комбі-В, об'єм двиг.1388\nFord Fiesta GT\n2007\nприватизація\n28.9\n1/2 частина\n34.8\n28.9\n1/2 частина\nприватизація\nДитина\nКарпенко А. В. 28. 04. 1993 р. н\nДитина\nКарпенко Е. Ю. 11. 07. 2006 р. н\nКарпенко Оксана Володимирівна\nОксана Володимирівна Карпенко\nОксана Карпенко\nКарпенко Оксана Володимирівна\nКарпенко Оксана Володимирівна\nОксана\nКарпенко\nсуддя апеляційного суду черкаської області\nЗагальний апеляційний суд\nЧеркаська область\nВолодимирівна\n13500\n8500\nстипендія\n237976.38\n251374.38\n8500\n13398\n2014\n13500\nприватизація\n1/2 частина\n28.9\n34.8\nприватизація\n1/2 частина\n28.9\nКарпенко А. В. 28. 04. 1993 р. н\nДитина\nКарпенко Е. Ю. 11. 07. 2006 р. н\nДитина\nВолодимирівна\nКарпенко\nОксана\nКарпенко Оксана Володимирівна\nОксана Володимирівна Карпенко\nОксана Карпенко\nКарпенко Оксана Володимирівна\nЧеркаська область\nЗагальний апеляційний суд\nсуддя апеляційного суду черкаської області\nКарпенко Оксана Володимирівна\n8500\nстипендія\n237976.38\n13398\n8500\n251374.38\n2007\nFord Fiesta GT\nлегковий комбі-В, об'єм двиг.1388\n13398\n251374.38\n8500\nстипендія\n237976.38\n8500\n1/2 частина\nприватизація\n28.9\n34.8\n1/2 частина\n28.9\nприватизація\n2014","general":{"inn":"","name":"Оксана","patronymic_unclear":false,"last_name_hidden":false,"family":[{"inn":"","inn_hidden":true,"relations_hidden":false,"family_name":"Карпенко А. В. 28. 04. 1993 р. н","relations_other":"","relations":"Дитина","name_hidden":false,"name_unclear":false},{"inn":"","relations":"Дитина","relations_other":"","inn_hidden":true,"family_name":"Карпенко Е. Ю. 11. 07. 2006 р. н","name_hidden":false,"name_unclear":false}],"patronymic":"Володимирівна","inn_hidden":true,"family_raw":"","last_name":"Карпенко","post":{"post_unclear":false,"region_unclear":false,"post":"суддя апеляційного суду черкаської області","candidate":"","office_hidden":false,"region":"Черкаська область","post_hidden":false,"office":"Загальний апеляційний суд","office_unclear":false},"last_name_unclear":false,"full_name":"Карпенко Оксана Володимирівна","addresses":[{"place_district":"","place_city_hidden":true,"place_city":"","place_city_type_hidden":true,"place_district_hidden":true,"place_city_type":"","place_address_hidden":true,"place_address":"","place_hidden":true,"place":""}],"full_name_suggest":{"output":"Карпенко Оксана Володимирівна","input":["Карпенко Оксана Володимирівна","Оксана Володимирівна Карпенко","Оксана Карпенко"]}},"source":"VULYK","estate":{"23":[{"space_unclear":false,"costs":"","costs_comment":"","address_hidden":false,"region_hidden":false,"space_comment":"","space":"","address":"","region":"","address_unclear":false,"costs_rent_comment":"","space_units":"м²","costs_rent":""},{"space_unclear":false,"costs":"","costs_comment":"","address_hidden":false,"region_hidden":false,"space_comment":"","space":"","address":"","region":"","address_unclear":false,"costs_rent_comment":"","space_units":"","costs_rent":""},{"space":"","region":"","costs":"","costs_rent_comment":"","costs_comment":"","address_unclear":false,"space_comment":"","space_units":"","costs_rent":"","address":""},{"costs_rent":"","costs":"","costs_rent_comment":"","costs_comment":"","space_comment":"","space_units":"","space":"","address":""}],"25":[{"space_unclear":false,"costs":"","costs_comment":"приватизація","address_hidden":true,"region_hidden":true,"space_comment":"1/2 частина","space_hidden":false,"space":"28.9","address":"","region":"","address_unclear":false,"costs_rent_comment":"","space_units":"м²","costs_rent":""}],"31":[{"space_unclear":false,"address_hidden":true,"region_hidden":true,"space_comment":"1/2 частина","space_hidden":false,"space":"28.9","address":"","region":"","costs_property":"","costs_rent_comment":"","space_units":"м²","costs_property_comment":"приватизація","costs_rent":""},{"costs_rent":"","region":"","costs_property":"","costs_rent_comment":"","region_hidden":false,"space_comment":"","costs_property_comment":"","space_units":"м²","space":"34.8","address":""}]},"intro":{"declaration_year":"2014","isnotdeclaration":"","declaration_year_unclear":false,"declaration_year_hidden":false}}