{"id":"vulyk_108_150","ft_src":"легковий причіп, у власності\n2014\nКреон\n2461 куб. см, у власності\n2007\nVolkswagen Transporter\nвантажопасажирський 2148 куб. см, маю право керувати на підставі довіреності\n2007\nMercedes-Benz Sprinter 313\nДніпропетровська область\n454\nм. Дніпродзержинськ\nДніпропетровська область\n41\nм. Дніпропетровськ\n16.4\nДніпропетровська область\n2015\n22768\n153368\n1474\n12180\nНаціональна школа суддів України\nНаціональна школа суддів України\n1788\n24242\n301220\n133878 - кредитна картка Приватбанк, 6 - % Приватбанк\n133884\n2461 куб. см, у власності\n2007\nVolkswagen Transporter\nлегковий причіп, у власності\n2014\nКреон\nвантажопасажирський 2148 куб. см, маю право керувати на підставі довіреності\n2007\nMercedes-Benz Sprinter 313\n2015\nФедоріщев Сергій Сергійович\nСергій Сергійович Федоріщев\nСергій Федоріщев\nФедоріщев Сергій Сергійович\nСергій\nПодружжя\nФедоріщева К. А\nДитина\nФедоріщева Д. С\nФедоріщев Сергій Сергійович\nСергійович\nЗагальний місцевий суд\nДніпропетровська область\nсуддя жовтневого районного суду м. дніпропетровська\nФедоріщев\nДніпропетровськ\nДніпропетровська область\n133878\nКредитна карта Приватбанк\n120\nПриватбанк - страхування здоров'я\n1788\nНаціональна школа суддів України\nНаціональна школа суддів України\n153368\n22768\n133884\n133878 - кредитна картка Приватбанк, 6 - % Приватбанк\n301220\n24242\n12180\n1474\n454\nДніпропетровська область\n16.4\nм. Дніпропетровськ\nДніпропетровська область\n41\nм. Дніпродзержинськ\nДніпропетровська область\nКредитна карта Приватбанк\n133878\nПриватбанк - страхування здоров'я\n120\nПодружжя\nФедоріщева К. А\nДитина\nФедоріщева Д. С\nСергійович\nФедоріщев\nСергій\nФедоріщев Сергій Сергійович\nСергій Сергійович Федоріщев\nСергій Федоріщев\nФедоріщев Сергій Сергійович\nДніпропетровська область\nДніпропетровськ\nДніпропетровська область\nсуддя жовтневого районного суду м. дніпропетровська\nЗагальний місцевий суд\nФедоріщев Сергій Сергійович","estate":{"25":[{"address":"м. Дніпропетровськ","space_units":"м²","costs_comment":"","space_unclear":false,"region_hidden":false,"space_units_unclear":false,"space_comment":"","address_hidden":true,"costs":"","space_comment_unclear":false,"costs_rent_comment":"","space":"16.4","region":"Дніпропетровська область","costs_rent":""}],"29":[{"costs_property_comment":"","address":"","space_units":"м²","space_unclear":false,"region_hidden":false,"costs_property":"","space_comment":"","address_hidden":true,"costs_rent_comment":"","space":"454","region":"Дніпропетровська область","costs_rent":""}],"32":[{"costs_property_comment":"","address":"м. Дніпродзержинськ","space_units":"м²","space_unclear":false,"region_hidden":false,"costs_property":"","space_comment":"","address_hidden":true,"costs_rent_comment":"","space":"41","region":"Дніпропетровська область","costs_rent":""}]},"vehicle":{"35":[{"sum_comment":"","brand_info":"2461 куб. см, у власності","sum":"","sum_rent_comment":"","year":"2007","brand":"Volkswagen Transporter","sum_rent":"","brand_info_unclear":false}],"36":[{"sum_comment":"","brand_info":"вантажопасажирський 2148 куб. см, маю право керувати на підставі довіреності","sum":"","sum_rent_comment":"","year":"2007","brand":"Mercedes-Benz Sprinter 313","sum_rent":""}],"39":[{"sum_comment":"","brand_info":"легковий причіп, у власності","sum":"","sum_rent_comment":"","year":"2014","brand":"Креон","sum_rent":""}]},"source":"VULYK","income":{"5":{"family_comment":"","family":"24242","comment":"","value_unclear":false,"family_unclear":false,"value":"301220"},"6":{"family_comment":"","value":"153368","family_unclear":false,"family":"22768","comment":""},"7":{"family_comment":"","comment":"Національна школа суддів України","family":"","source_name_unclear":true,"value":"1788","source_name":"Національна школа суддів України"},"8":{"family_comment":"","value":"","family":"","comment":""},"9":{"family_comment":"","family":"","comment":"","family_unclear":false,"comment_hidden":false,"value":"","family_comment_hidden":false},"10":{"family_comment":"","value":"12180","family":"1474","comment":""},"11":{"family_comment":"","value":"","family":"","comment":""},"12":{"family_comment":"","value":"","family":"","comment":""},"13":{"family_comment":"","value":"","family":"","comment":""},"14":{"family_comment":"","value":"","family":"","comment":""},"15":{"family_comment":"","value":"","family":"","comment":""},"16":{"family_comment":"","value":"","family":"","comment":""},"17":{"family_comment":"","value":"","family":"","comment":""},"18":{"family_comment":"","value":"","family":"","comment":""},"19":{"family_comment":"","value":"","family":"","comment":""},"20":{"family_comment":"","comment":"133878 - кредитна картка Приватбанк, 6 - % Приватбанк","family":"","value_unclear":false,"comment_hidden":false,"comment_unclear":false,"value":"133884"}},"general":{"family_raw":"","name":"Сергій","full_name_suggest":{"input":["Федоріщев Сергій Сергійович","Сергій Сергійович Федоріщев","Сергій Федоріщев"],"output":"Федоріщев Сергій Сергійович"},"patronymic":"Сергійович","inn_hidden":true,"addresses":[{"place_city_type_hidden":false,"place_hidden":false,"place_address_unclear":true,"place":"Дніпропетровська область","place_city":"Дніпропетровськ","place_unclear":false,"place_city_type":"Місто","place_city_hidden":false,"place_district":"","place_district_hidden":false,"place_address":"","place_address_hidden":true}],"inn":"","inn_unclear":true,"last_name":"Федоріщев","full_name":"Федоріщев Сергій Сергійович","family":[{"inn":"","inn_unclear":true,"family_name":"Федоріщева К. А","relations_hidden":false,"name_unclear":false,"relations":"Подружжя","inn_hidden":true,"name_hidden":false,"relations_other":""},{"inn":"","family_name":"Федоріщева Д. С","relations_other":"","name_unclear":false,"inn_hidden":false,"name_hidden":false,"relations":"Дитина"}],"post":{"office":"Загальний місцевий суд","post":"суддя жовтневого районного суду м. дніпропетровська","office_unclear":false,"office_hidden":false,"region":"Дніпропетровська область","post_unclear":false}},"liabilities":{"54":{"sum_comment":"Приватбанк - страхування здоров'я","sum_foreign_comment":"","sum_foreign":"","sum_hidden":false,"sum":"120"},"55":{"sum_comment":"","sum_foreign_comment":"","sum_foreign":"","sum":""},"56":{"sum_comment":"","sum_foreign_comment":"","sum_foreign":"","sum_unclear":false,"sum":""},"57":{"sum_comment":"Кредитна карта Приватбанк","sum_hidden":false,"sum":"133878","sum_foreign_comment":"","sum_foreign":"","sum_comment_hidden":false},"58":{"sum_comment":"","sum_foreign_comment":"","sum_foreign":"","sum":"","sum_comment_hidden":false},"59":{"sum_comment":"","sum_foreign_comment":"","sum_foreign":"","sum_unclear":false,"sum":""},"60":{"sum_comment":"","sum_foreign_comment":"","sum_foreign":"","sum":"","sum_comment_hidden":false},"61":{"sum_comment":"","sum_foreign_comment":"","sum_foreign":"","sum":"","sum_comment_hidden":false},"62":{"sum_comment":"","sum_foreign_comment":"","sum_foreign":"","sum":""},"63":{"sum_comment":"","sum_hidden":false,"sum":"","sum_foreign_comment":"","sum_foreign":"","sum_unclear":false,"sum_comment_hidden":false},"64":{"sum_comment":"","sum":"","sum_foreign_comment":"","sum_foreign":"","sum_unclear":false,"sum_comment_hidden":false}},"declaration":{"notfull_lostpages":"","additional_info_text":"","additional_info":"","date":"2016-03-31T00:00:00","notfull":"","url":"http://static.declarations.com.ua/declarations/chosen_ones/judges_batch/2449_fedorishchev_serhii_serhiiovych_2015.pdf"},"intro":{"declaration_year_hidden":false,"isnotdeclaration":"","declaration_year":"2015"}}