{"income":{"5":{"value":"205238","family_comment":"","value_unclear":false,"family_hidden":false,"value_hidden":false,"family_unclear":false,"family":"17112","comment":"","family_comment_unclear":false},"6":{"value":"202365","family_comment":"","value_unclear":false,"comment_hidden":false,"family_hidden":false,"value_hidden":false,"family_unclear":false,"family":"","comment":""},"7":{"value":"","value_hidden":false,"family_comment":"","source_name":"","family":"","comment":"","source_name_hidden":false},"8":{"family_comment":"","value":"","family":"","comment":""},"9":{"value":"","comment_hidden":false,"value_hidden":false,"family_comment":"","family":"","comment":""},"10":{"value":"","value_unclear":false,"value_hidden":false,"family_comment":"","family":"","comment":""},"11":{"family_comment":"","value":"","family":"","comment":""},"12":{"family_comment":"","value":"","family":"","comment":""},"13":{"family_comment":"","value":"","family_hidden":false,"comment":"","family":""},"14":{"family_comment":"","value":"","family":"","comment":""},"15":{"family_comment":"","family_unclear":false,"value":"","family":"","comment":""},"16":{"family_comment":"","value":"","value_unclear":false,"family":"","comment":""},"17":{"family_comment":"","value":"","family":"","comment":""},"18":{"family_comment":"","value":"","family":"","comment":""},"19":{"family_comment":"","value":"","comment_unclear":false,"family":"","comment":""},"20":{"value":"2873","comment_unclear":false,"family_hidden":false,"value_hidden":false,"family_comment":"","family":"17112","comment":""}},"vehicle":{"40":[{"year_hidden":false,"brand_info":"1997 куб. см., 114 кВт , 457 см","sum_rent_comment":"","year":"2012","brand_info_hidden":false,"brand_info_unclear":false,"sum_rent":"","sum":"","brand":"Honda CR-V","sum_comment":"","brand_unclear":false,"brand_hidden":false}]},"id":"vulyk_64_147","banks":{"49":[{"sum_foreign_comment":"","sum_units":"UAH","sum_comment":"","sum_foreign_units":"UAH","sum_comment_hidden":false,"sum":"10.49","sum_foreign":""}],"51":[{"sum_foreign_comment":"","sum_units":"UAH","sum_comment":"","sum_comment_unclear":false,"sum_foreign_units":"UAH","sum_comment_hidden":false,"sum_unclear":false,"sum":"1580","sum_foreign":""}]},"declaration":{"additional_info_text":"","notfull_lostpages":"","date":"2015-03-18T00:00:00","notfull":"","additional_info":"","url":"http://static.declarations.com.ua/declarations/chosen_ones/mega_batch/sahun_andrii_vasylovych.pdf"},"liabilities":{"54":{"sum_foreign_comment":"","sum":"","sum_comment":"","sum_foreign_comment_hidden":false,"sum_hidden":false,"sum_comment_hidden":false,"sum_unclear":false,"sum_foreign":""},"55":{"sum_foreign_comment":"","sum":"","sum_comment":"","sum_comment_unclear":false,"sum_foreign":""},"56":{"sum_foreign_comment":"","sum":"","sum_comment":"","sum_unclear":false,"sum_foreign":""},"57":{"sum_foreign_comment":"","sum":"","sum_comment":"","sum_hidden":false,"sum_unclear":false,"sum_foreign":""},"58":{"sum_foreign_comment":"","sum":"","sum_comment":"","sum_unclear":false,"sum_foreign":""},"59":{"sum_foreign_comment":"","sum":"","sum_comment":"","sum_comment_unclear":false,"sum_comment_hidden":false,"sum_unclear":false,"sum_foreign":""},"60":{"sum_foreign_comment":"","sum":"","sum_comment":"","sum_foreign":""},"61":{"sum_foreign_comment":"","sum":"","sum_comment":"","sum_foreign":""},"62":{"sum_foreign_comment":"","sum":"","sum_comment":"","sum_unclear":false,"sum_foreign":""},"63":{"sum_foreign_comment":"","sum":"","sum_comment":"","sum_unclear":false,"sum_foreign":""},"64":{"sum_foreign_comment":"","sum":"","sum_comment":"","sum_comment_unclear":false,"sum_unclear":false,"sum_foreign":""}},"ft_src":"суддя\nКіровоградська область\nАдміністративний місцевий суд\nАндрій\nСагун Н. Г\nПодружжя\nСагун І. А\nДитина\nСагун Т. А\nДитина\nСагун О. А\nДитина\nВасильович\nСагун Андрій Васильович\nАндрій Васильович Сагун\nАндрій Сагун\nСагун Андрій Васильович\nСагун Андрій Васильович\nСагун\n1997 куб. см., 114 кВт , 457 см\nHonda CR-V\n2012\n10.49\n1580\n2014\n1997 куб. см., 114 кВт , 457 см\nHonda CR-V\n2012\n1580\n10.49\nвласність\n1021\n10\nвласність\n86\nвласність\n86\nкористування\nСагун Андрій Васильович\nАндрій Васильович Сагун\nАндрій Сагун\nСагун Андрій Васильович\nСагун Андрій Васильович\nПодружжя\nСагун Н. Г\nДитина\nСагун І. А\nДитина\nСагун Т. А\nСагун О. А\nДитина\nАндрій\nСагун\nАдміністративний місцевий суд\nКіровоградська область\nсуддя\nВасильович\n202365\n2873\n17112\n205238\n17112\n2014\n1021\nвласність\nвласність\n10\n86\nвласність\nкористування\n86\nПодружжя\nСагун Н. Г\nДитина\nСагун І. А\nСагун Т. А\nДитина\nДитина\nСагун О. А\nВасильович\nСагун\nАндрій\nСагун Андрій Васильович\nАндрій Васильович Сагун\nАндрій Сагун\nСагун Андрій Васильович\nКіровоградська область\nАдміністративний місцевий суд\nсуддя\nСагун Андрій Васильович\n202365\n17112\n205238\n17112\n2873\n2012\nHonda CR-V\n1997 куб. см., 114 кВт , 457 см\n2873\n17112\n205238\n17112\n202365\nвласність\n86\nвласність\n1021\n86\nкористування\nвласність\n10\n10.49\n1580\n2014","general":{"inn":"","name":"Андрій","last_name_hidden":false,"family":[{"inn":"","inn_hidden":false,"relations_unclear":false,"relations_hidden":false,"relations_other":"","relations":"Подружжя","name_hidden":false,"inn_unclear":false,"family_name":"Сагун Н. Г","name_unclear":false},{"inn":"","inn_hidden":false,"relations_unclear":false,"relations_hidden":false,"relations_other":"","relations":"Дитина","name_hidden":false,"family_name":"Сагун І. А","name_unclear":false},{"inn":"","relations":"Дитина","relations_other":"","inn_hidden":false,"family_name":"Сагун Т. А","name_hidden":false,"name_unclear":false},{"inn":"","family_name":"Сагун О. А","relations":"Дитина","relations_other":"","name_hidden":false}],"patronymic":"Васильович","inn_hidden":false,"family_raw":"","inn_unclear":false,"post":{"post_unclear":false,"post":"суддя","candidate":"","office_hidden":false,"region":"Кіровоградська область","post_hidden":false,"office":"Адміністративний місцевий суд","office_unclear":false,"region_hidden":false},"full_name_suggest":{"output":"Сагун Андрій Васильович","input":["Сагун Андрій Васильович","Андрій Васильович Сагун","Андрій Сагун"]},"full_name":"Сагун Андрій Васильович","last_name":"Сагун","patronymic_hidden":false,"last_name_unclear":false,"name_unclear":false},"source":"VULYK","estate":{"23":[{"space_unclear":false,"costs":"","costs_rent_unclear":false,"costs_comment":"","costs_hidden":false,"space_hidden":false,"space_units_unclear":false,"space_units_hidden":false,"costs_unclear":false,"region":"","space_comment_unclear":false,"space_comment_hidden":false,"costs_rent":"","region_unclear":false,"costs_rent_comment_unclear":false,"address_hidden":false,"region_hidden":false,"space_comment":"власність","space":"1021","address":"","address_unclear":false,"costs_rent_comment":"","costs_rent_hidden":false,"space_units":"м²"}],"25":[{"region_unclear":false,"space_unclear":false,"costs":"","costs_rent_unclear":false,"costs_comment":"","costs_hidden":false,"address_hidden":false,"region_hidden":false,"space_comment":"користування","space_hidden":false,"space":"86","space_units_hidden":false,"costs_rent_comment_unclear":false,"region":"","costs_rent_comment":"","costs_rent_hidden":false,"space_comment_unclear":false,"space_units":"м²","address":"","costs_rent":"","costs_unclear":false}],"27":[{"space_unclear":false,"costs":"","costs_comment":"","costs_hidden":false,"address_hidden":false,"region_hidden":false,"space_comment":"власність","space_hidden":false,"space":"10","address":"","region":"","address_unclear":false,"costs_rent_comment":"","costs_rent_hidden":false,"space_units":"м²","costs_rent":""}],"31":[{"region_unclear":false,"address_hidden":false,"region_hidden":false,"space_comment":"","space":"86","address":"власність","region":"","costs_property":"","costs_rent_comment":"","space_comment_hidden":false,"space_units":"м²","costs_property_comment":"","costs_rent":""}]},"intro":{"declaration_year":"2014","isnotdeclaration":"","declaration_year_unclear":false,"declaration_year_hidden":false}}