{"income":{"5":{"value":"217199","family_comment":"","value_unclear":false,"family_unclear":false,"family":"82300","comment":""},"6":{"value":"205019","family_comment":"","value_unclear":false,"family_unclear":false,"family":"82300","comment":""},"7":{"value":"","value_unclear":false,"family_comment":"","source_name":"","family":"","comment":""},"8":{"family_comment":"","value":"","family":"","comment":""},"9":{"family_comment":"","value":"","value_unclear":false,"family":"","comment":""},"10":{"family_comment":"","value":"12180","comment_unclear":false,"family":"","comment":""},"11":{"family_comment":"","value":"","family":"","comment":""},"12":{"family_comment":"","value":"","family":"","comment":""},"13":{"family_comment":"","value":"","family":"","comment":""},"14":{"family_comment":"","value":"","family":"","comment":""},"15":{"family_comment":"","value":"","family":"","comment":""},"16":{"family_comment":"","value":"","family":"","comment":""},"17":{"family_comment":"","value":"","family":"","comment":""},"18":{"family_comment":"","value":"","family":"","comment":""},"19":{"family_comment":"","value":"","family":"","comment":""},"20":{"family_comment":"","value":"","family":"","comment":""}},"vehicle":{"39":[{"brand_info":"Мотоцикл, 347.6","sum_rent_comment":"","brand":"ІЖ-Ю-5","sum_comment":"","year":"1989","year_unclear":true,"sum":"","sum_rent":""}]},"id":"vulyk_55_172","banks":{"45":[{"sum_foreign_comment":"","sum_units":"UAH","sum_comment":"","sum_comment_unclear":false,"sum_foreign_units":"UAH","sum_foreign_comment_unclear":false,"sum_units_unclear":false,"sum_comment_hidden":false,"sum_unclear":false,"sum":"","sum_foreign":""},{"sum_foreign_comment":"","sum_units":"","sum_comment":"","sum_comment_unclear":false,"sum_foreign_units":"","sum":"","sum_unclear":false,"sum_foreign":""},{"sum_foreign_comment":"","sum_units":"","sum_comment":"","sum_foreign_units":"","sum":"","sum_unclear":false,"sum_foreign":""}],"46":[{"sum_foreign_comment":"","sum_units":"UAH","sum_comment":"","sum_comment_unclear":false,"sum_foreign_units":"UAH","sum":"","sum_foreign":""}],"47":[{"sum_foreign_comment":"","sum_units":"UAH","sum_comment":"","sum_comment_unclear":false,"sum_hidden":false,"sum_foreign_units":"UAH","sum":"","sum_foreign":""}],"48":[{"sum_foreign_comment":"","sum_units":"UAH","sum_comment":"","sum_foreign_units":"UAH","sum":"","sum_foreign":""}],"49":[{"sum_foreign_comment":"","sum_units":"UAH","sum_comment":"","sum_foreign_units":"UAH","sum":"","sum_foreign":""},{"sum_foreign_comment":"","sum_units":"","sum_comment":"","sum":"","sum_foreign":""}],"50":[{"sum_foreign_comment":"","sum_units":"UAH","sum_comment":"","sum_foreign_units":"UAH","sum":"","sum_foreign":""}],"51":[{"sum_units":"UAH","sum_hidden":false,"sum_units_hidden":false,"sum_foreign":"","sum_foreign_comment":"","sum":"","sum_comment":"","sum_comment_unclear":false,"sum_foreign_units":"UAH","sum_units_unclear":false,"sum_comment_hidden":false,"sum_unclear":false},{"sum_foreign_comment":"","sum_units":"","sum_comment":"","sum_foreign_units":"","sum":"","sum_foreign":""}],"52":[{"sum_foreign_comment":"","sum_units":"UAH","sum_comment":"","sum_comment_unclear":false,"sum_foreign_units":"UAH","sum":"","sum_foreign":""},{"sum_foreign_comment":"","sum_units":"","sum_comment":"","sum_foreign_units":"","sum":"","sum_foreign":""}],"53":[{"sum_foreign_comment":"","sum_units":"UAH","sum_comment":"","sum_hidden":false,"sum_foreign_units":"UAH","sum":"","sum_unclear":false,"sum_foreign":""},{"sum_foreign_comment":"","sum_units":"","sum_comment":"","sum_comment_unclear":false,"sum_foreign_units":"","sum":"","sum_foreign":""},{"sum_foreign_comment":"","sum_units":"","sum_comment":"","sum_foreign_units":"","sum":"","sum_foreign":""},{"sum_foreign_comment":"","sum_units":"","sum_comment":"","sum_foreign_units":"","sum":"","sum_foreign":""}]},"declaration":{"additional_info_text":"","notfull_lostpages":"","date":"2015-03-19T00:00:00","notfull":"","additional_info":"","url":"http://static.declarations.com.ua/declarations/chosen_ones/mega_batch/holovin_valerii_oleksandrovych.pdf"},"liabilities":{"54":{"sum_foreign_comment":"","sum":"","sum_comment":"","sum_hidden":false,"sum_comment_hidden":false,"sum_foreign":""},"55":{"sum_foreign_comment":"","sum_foreign_hidden":false,"sum_comment":"","sum_hidden":false,"sum":"","sum_foreign":""},"56":{"sum_foreign_comment":"","sum":"","sum_comment":"","sum_unclear":false,"sum_foreign":""},"57":{"sum_foreign_comment":"","sum":"","sum_comment":"","sum_comment_unclear":false,"sum_hidden":false,"sum_comment_hidden":false,"sum_unclear":false,"sum_foreign":""},"58":{"sum_foreign_comment":"","sum":"","sum_comment":"","sum_hidden":false,"sum_comment_hidden":false,"sum_unclear":false,"sum_foreign":""},"59":{"sum_foreign_comment":"","sum":"","sum_comment":"","sum_foreign":""},"60":{"sum_foreign_comment":"","sum":"","sum_comment":"","sum_hidden":false,"sum_comment_hidden":false,"sum_foreign":""},"61":{"sum_foreign_comment":"","sum":"","sum_comment":"","sum_foreign":""},"62":{"sum_foreign_comment":"","sum":"","sum_comment":"","sum_foreign":""},"63":{"sum_foreign_comment":"","sum":"","sum_comment":"","sum_unclear":false,"sum_foreign":""},"64":{"sum_foreign_comment":"","sum":"","sum_comment":"","sum_unclear":false,"sum_foreign":""}},"ft_src":"Павлоград\nДніпропетровська область\nзаступник голови павлоградського міськрайонного суду дніпропетровської області\nДніпропетровська область\nЗагальний місцевий суд\nВалерій\nГоловіна Л. А\nПодружжя\nГоловін А. В. 2009 р. н\nДитина\nОлександрович\nГоловін\nГоловін Валерій Олександрович\nГоловін Валерій Олександрович\nВалерій Олександрович Головін\nВалерій Головін\nГоловін Валерій Олександрович\n1989\nМотоцикл, 347.6\nІЖ-Ю-5\n2014\nМотоцикл, 347.6\nІЖ-Ю-5\n1989\n28\nДніпропетровська область\nм. Павлоград\n31.9\nДніпропетровська область\nм. Тернівка\n64.2\nм. Тернівка\nДніпропетровська область\n72.3\nДніпропетровська область\nм. Павлоград\n34.2\nДніпропетровська область\nм. Тернівка\n49.6\nм. Тернівка\nДніпропетровська область\nПодружжя\nГоловіна Л. А\nДитина\nГоловін А. В. 2009 р. н\nГоловін Валерій Олександрович\nВалерій Олександрович Головін\nВалерій Головін\nГоловін Валерій Олександрович\nВалерій\nГоловін Валерій Олександрович\nОлександрович\nЗагальний місцевий суд\nзаступник голови павлоградського міськрайонного суду дніпропетровської області\nДніпропетровська область\nГоловін\nПавлоград\nДніпропетровська область\n205019\n82300\n217199\n82300\n12180\n2014\nм. Тернівка\n31.9\nДніпропетровська область\nм. Павлоград\nДніпропетровська область\n28\nм. Тернівка\nДніпропетровська область\n64.2\n72.3\nм. Павлоград\nДніпропетровська область\nм. Тернівка\n34.2\nДніпропетровська область\nм. Тернівка\n49.6\nДніпропетровська область\nГоловіна Л. А\nПодружжя\nГоловін А. В. 2009 р. н\nДитина\nОлександрович\nГоловін\nГоловін Валерій Олександрович\nВалерій Олександрович Головін\nВалерій Головін\nГоловін Валерій Олександрович\nДніпропетровська область\nПавлоград\nДніпропетровська область\nзаступник голови павлоградського міськрайонного суду дніпропетровської області\nЗагальний місцевий суд\nГоловін Валерій Олександрович\nВалерій\n82300\n205019\n12180\n82300\n217199\n1989\nМотоцикл, 347.6\nІЖ-Ю-5\n12180\n217199\n82300\n205019\n82300\nм. Тернівка\nДніпропетровська область\n64.2\nм. Павлоград\nДніпропетровська область\n28\nм. Павлоград\nДніпропетровська область\n72.3\nм. Тернівка\nДніпропетровська область\n34.2\nм. Тернівка\nДніпропетровська область\n49.6\nм. Тернівка\nДніпропетровська область\n31.9\n2014","general":{"name_hidden":false,"name":"Валерій","patronymic_unclear":false,"last_name_hidden":false,"inn":"","family":[{"inn":"","inn_hidden":true,"relations_unclear":false,"relations_hidden":false,"relations_other":"","relations":"Подружжя","name_hidden":false,"family_name":"Головіна Л. А","name_unclear":false},{"inn":"","relations":"Дитина","relations_other":"","inn_hidden":false,"family_name":"Головін А. В. 2009 р. н","name_hidden":false,"name_unclear":false}],"patronymic":"Олександрович","inn_hidden":true,"family_raw":"","inn_unclear":false,"post":{"post_unclear":false,"post":"заступник голови павлоградського міськрайонного суду дніпропетровської області","post_hidden":true,"region":"Дніпропетровська область","region_hidden":false,"office":"Загальний місцевий суд","office_hidden":false,"office_unclear":false},"last_name_unclear":false,"full_name":"Головін Валерій Олександрович","addresses":[{"place_city_type_unclear":false,"place_address":"","place_district_hidden":false,"place_city_type":"Місто","place_address_hidden":false,"place_address_unclear":false,"place_city_type_hidden":false,"place":"Дніпропетровська область","place_district":"","place_city_hidden":false,"place_city":"Павлоград","place_city_unclear":false,"place_hidden":false}],"last_name":"Головін","patronymic_hidden":false,"full_name_suggest":{"output":"Головін Валерій Олександрович","input":["Головін Валерій Олександрович","Валерій Олександрович Головін","Валерій Головін"]}},"source":"VULYK","estate":{"23":[{"space_hidden":false,"costs":"","costs_comment":"","address_hidden":false,"region_hidden":false,"space_comment":"","space":"","address":"","region":"","address_unclear":false,"costs_rent_comment":"","space_units":"м²","costs_rent":""},{"costs_rent":"","region":"","costs":"","costs_rent_comment":"","costs_comment":"","region_hidden":false,"space_comment":"","space_units":"","space":"","address":""},{"costs_rent":"","region":"","costs":"","costs_rent_comment":"","costs_comment":"","space_comment":"","space_units":"","space":"","address":""},{"costs_rent":"","costs":"","costs_rent_comment":"","costs_comment":"","space_comment":"","space_units":"","space":"","address":""}],"25":[{"region_unclear":false,"space_unclear":false,"costs":"","costs_comment":"","costs_hidden":false,"address_hidden":true,"region_hidden":false,"space_comment":"","space_hidden":false,"space":"72.3","address":"м. Павлоград","costs_unclear":false,"region":"Дніпропетровська область","address_unclear":false,"costs_rent_comment":"","space_comment_unclear":false,"space_comment_hidden":false,"space_units":"м²","costs_rent":""},{"space_unclear":false,"costs":"","costs_comment":"","address_hidden":true,"region_hidden":false,"space_comment":"","space":"34.2","address":"м. Тернівка","region":"Дніпропетровська область","address_unclear":false,"costs_rent_comment":"","space_comment_unclear":false,"space_units":"м²","costs_rent":""},{"space_hidden":false,"costs":"","costs_comment":"","address_hidden":true,"region_hidden":false,"space_comment":"","space":"49.6","address":"м. Тернівка","region":"Дніпропетровська область","costs_rent_comment":"","space_units":"м²","costs_rent":""}],"27":[{"space_unclear":false,"costs":"","costs_comment":"","address_hidden":false,"region_hidden":false,"space_comment":"","space":"31.9","address":"м. Тернівка","region":"Дніпропетровська область","costs_rent_comment":"","space_units":"м²","space_units_hidden":false,"costs_rent":""}],"31":[{"region_unclear":false,"space_unclear":false,"address_hidden":false,"region_hidden":false,"space_comment":"","space_hidden":false,"space":"64.2","address":"м. Тернівка","region":"Дніпропетровська область","costs_property":"","space_units_unclear":false,"space_comment_unclear":false,"space_units":"м²","costs_property_comment":"","costs_rent":"","costs_rent_comment":""}],"33":[{"space_unclear":false,"address_hidden":false,"region_hidden":false,"space_comment":"","space":"28","address":"м. Павлоград","region":"Дніпропетровська область","costs_property":"","costs_rent_comment":"","space_units":"м²","costs_property_comment":"","costs_rent":""}]},"intro":{"declaration_year":"2014","isnotdeclaration":""}}