{"id":"vulyk_97_141","ft_src":"1.5 л\nChevrolet Aveo\n2006\nЛозівський р-н, с Катеринівка\nХарківська область\n20000\nм. Лозова\nХарківська область\n1345\n30.9\nХарківська область\nм. Лозова\nХарківська область\nм. Лозова\n40.5\nм. Лозова\nХарківська область\n30\nс. Катеринівка, Лозівського р-ну\n10000\nХарківська область\nс. Домаха, Лозова, вул. Чкалова,12\n2500\nХарківська область\nс. Домаха, Лозова, вул. Чкалова,12\n48.4\nХарківська область\n7475.74\n20064.14\n52304.53\n2014\n1.5 л\nChevrolet Aveo\n2006\n2014\nСмірнова Наталія Андріївна\nНаталія Андріївна Смірнова\nНаталія Смірнова\nСмірнова Наталія Андріївна\nНаталія\nПодружжя\nСмірнов С. О\nСмірнова Наталія Андріївна\nСмірнова\nЗагальний місцевий суд\nХарківська область\nсуддя лозівського міськрайонного суду харківської області\nАндріївна\nХарківська область\n64600\nЛозова\n209913.99\n15000\nУПФУ\n42127.08\n254695.64\n15095.01\n2654.57\nРайфайзен банк Аваль, Приватбанк, Ощадбанк\n95.01\n10000\nс. Катеринівка, Лозівського р-ну\nХарківська область\n2500\nс. Домаха, Лозова, вул. Чкалова,12\nХарківська область\n20000\nХарківська область\nЛозівський р-н, с Катеринівка\n1345\nХарківська область\nм. Лозова\n48.4\nХарківська область\nс. Домаха, Лозова, вул. Чкалова,12\n30.9\nХарківська область\nм. Лозова\n40.5\nХарківська область\nм. Лозова\n30\nХарківська область\nм. Лозова\n52304.53\n20064.14\n7475.74\n15000\n209913.99\n95.01\nРайфайзен банк Аваль, Приватбанк, Ощадбанк\n2654.57\n15095.01\n254695.64\nУПФУ\n42127.08\nПодружжя\nСмірнов С. О\nАндріївна\nСмірнова\nНаталія\nСмірнова Наталія Андріївна\nНаталія Андріївна Смірнова\nНаталія Смірнова\nСмірнова Наталія Андріївна\n64600\nЛозова\nХарківська область\nХарківська область\nЗагальний місцевий суд\nсуддя лозівського міськрайонного суду харківської області\nСмірнова Наталія Андріївна","estate":{"23":[{"address":"с. Катеринівка, Лозівського р-ну","space_units":"м²","costs_rent_unclear":false,"costs_comment":"","space_unclear":false,"region_hidden":false,"space_comment":"","address_hidden":false,"costs":"","address_unclear":false,"costs_rent_comment":"","space":"10000","region_unclear":false,"region":"Харківська область","costs_rent":""},{"address":"с. Домаха, Лозова, вул. Чкалова,12","space_units":"м²","costs_rent_unclear":false,"space_comment":"","region_hidden":false,"costs_comment":"","costs":"","address_unclear":false,"costs_rent_comment":"","space":"2500","region_unclear":false,"region":"Харківська область","costs_rent":""}],"24":[{"address":"с. Домаха, Лозова, вул. Чкалова,12","space_units":"м²","space_hidden":false,"space_unclear":false,"region_hidden":false,"costs_rent_comment":"","space_comment":"","address_hidden":false,"costs":"","address_unclear":false,"space_comment_unclear":false,"costs_comment":"","space":"48.4","region_unclear":false,"region":"Харківська область","costs_rent":""}],"29":[{"costs_property_comment":"","address":"Лозівський р-н, с Катеринівка","space_units":"м²","space_unclear":false,"region_hidden":false,"costs_property":"","space_comment":"","address_hidden":false,"address_unclear":false,"space_comment_unclear":false,"costs_rent_comment":"","space":"20000","region_unclear":false,"region":"Харківська область","costs_rent":""},{"costs_property_comment":"","address":"м. Лозова","space_units":"м²","space_comment":"","region_hidden":false,"costs_property":"","region":"Харківська область","address_hidden":true,"address_unclear":false,"costs_rent_comment":"","space":"1345","costs_rent":""}],"31":[{"costs_property_comment":"","address":"м. Лозова","space_units":"м²","space_hidden":false,"space_unclear":false,"region_hidden":false,"costs_property":"","space_comment":"","address_hidden":true,"space_comment_hidden":false,"costs_rent_comment":"","space":"30.9","region":"Харківська область","costs_rent":""},{"costs_property_comment":"","address":"м. Лозова","space_units":"м²","costs_rent_comment":"","space":"40.5","region":"Харківська область","costs_property":"","space_comment":"","address_hidden":false,"costs_rent":""}],"33":[{"costs_property_comment":"","address":"м. Лозова","space_units":"м²","space_hidden":false,"space_comment":"","region_hidden":false,"costs_property":"","region":"Харківська область","address_hidden":true,"costs_rent_comment":"","space":"30","costs_rent":""}]},"vehicle":{"35":[{"year_hidden":false,"brand_info":"1.5 л","brand_unclear":false,"sum_rent_comment":"","brand_hidden":false,"year":"2006","sum_comment":"","brand_info_hidden":false,"sum_rent":"","brand":"Chevrolet Aveo","brand_info_unclear":false,"sum":""}]},"source":"VULYK","income":{"5":{"family_comment":"","value":"254695.64","family":"15095.01","comment":""},"6":{"family_comment":"","family":"15000","comment":"","value_unclear":false,"family_unclear":false,"comment_hidden":false,"value":"209913.99"},"7":{"family":"","family_comment":"","value":"","comment":"","source_name":""},"8":{"family_comment":"","value":"","family":"","comment":""},"9":{"family_comment":"","value":"2654.57","family_unclear":false,"family":"95.01","comment":"Райфайзен банк Аваль, Приватбанк, Ощадбанк"},"10":{"family_comment":"","value":"","family":"","comment":"","value_unclear":false},"11":{"family_comment":"","value":"","family":"","comment":""},"12":{"family_comment":"","value":"","family":"","comment":""},"13":{"family_comment":"","value":"","family":"","comment":""},"14":{"family_comment":"","value":"","family":"","comment":""},"15":{"family_comment":"","value":"","family":"","comment":""},"16":{"family_comment":"","value":"","family":"","comment":""},"17":{"family_comment":"","value":"","family":"","comment":""},"18":{"family_comment":"","value":"","family":"","comment":""},"19":{"family_comment":"","value":"","family":"","comment":""},"20":{"family_comment":"","comment":"УПФУ","family":"","value_unclear":false,"comment_unclear":false,"value":"42127.08","family_hidden":false,"family_comment_unclear":false}},"banks":{"45":[{"sum_comment_unclear":false,"sum_units":"UAH","sum_foreign_units":"UAH","sum_hidden":false,"sum":"52304.53","sum_foreign_comment":"","sum_comment":"","sum_unclear":false,"sum_foreign":"","sum_comment_hidden":false}],"46":[{"sum_units":"UAH","sum_comment":"","sum_foreign_units":"UAH","sum":"7475.74","sum_foreign_comment":"","sum_foreign":"","sum_comment_hidden":false}],"51":[{"sum_comment_unclear":false,"sum_units":"UAH","sum_foreign_units":"UAH","sum_hidden":false,"sum":"20064.14","sum_foreign_comment":"","sum_comment":"","sum_unclear":false,"sum_foreign":"","sum_comment_hidden":false}]},"declaration":{"notfull_lostpages":"","additional_info_text":"","additional_info":"","date":"2015-03-27T00:00:00","notfull":"","url":"http://static.declarations.com.ua/declarations/chosen_ones/judges_batch/4043_smirnova_nataliia_andriivna.pdf"},"general":{"family":[{"inn":"","family_name":"Смірнов С. О","relations_other":"","name_unclear":false,"inn_hidden":true,"name_hidden":true,"relations":"Подружжя"}],"family_raw":"","name":"Наталія","full_name_suggest":{"input":["Смірнова Наталія Андріївна","Наталія Андріївна Смірнова","Наталія Смірнова"],"output":"Смірнова Наталія Андріївна"},"patronymic":"Андріївна","inn_hidden":true,"addresses":[{"place_city_type":"Місто","place_city_type_hidden":false,"place_hidden":false,"place_city_hidden":false,"place_district_hidden":false,"place_district":"","place_city_unclear":false,"place":"Харківська область","place_city":"Лозова","place_address_hidden":true,"place_address":"64600"}],"last_name_hidden":false,"patronymic_hidden":false,"inn":"","inn_unclear":false,"last_name":"Смірнова","full_name":"Смірнова Наталія Андріївна","post":{"post_hidden":false,"office":"Загальний місцевий суд","post":"суддя лозівського міськрайонного суду харківської області","office_unclear":false,"region_unclear":false,"region":"Харківська область"},"name_hidden":false},"liabilities":{"54":{"sum_comment_unclear":false,"sum_comment":"","sum_hidden":false,"sum":"","sum_foreign_comment":"","sum_foreign":"","sum_unclear":false,"sum_comment_hidden":false},"55":{"sum_comment":"","sum_foreign_comment":"","sum_foreign":"","sum":""},"56":{"sum_comment":"","sum_foreign_comment":"","sum_foreign":"","sum":""},"57":{"sum_comment_unclear":false,"sum_comment":"","sum_hidden":false,"sum":"","sum_foreign_comment":"","sum_foreign":"","sum_unclear":false,"sum_comment_hidden":false},"58":{"sum_comment_unclear":false,"sum_comment":"","sum_hidden":false,"sum":"","sum_foreign_comment":"","sum_foreign":"","sum_unclear":false,"sum_comment_hidden":false},"59":{"sum_comment":"","sum_foreign_comment":"","sum_foreign":"","sum":""},"60":{"sum_comment_unclear":false,"sum_comment":"","sum_hidden":false,"sum":"","sum_foreign_comment":"","sum_foreign":"","sum_comment_hidden":false},"61":{"sum_comment":"","sum_foreign_comment":"","sum_foreign":"","sum":""},"62":{"sum_comment":"","sum_foreign_comment":"","sum_foreign":"","sum_unclear":false,"sum":""},"63":{"sum_comment":"","sum_foreign_comment":"","sum_foreign":"","sum_hidden":false,"sum":""},"64":{"sum_comment":"","sum_foreign_comment":"","sum_foreign":"","sum":""}},"intro":{"isnotdeclaration":"","declaration_year":"2014"}}