{"income":{"5":{"value":"303255.54","value_unclear":false,"comment_hidden":false,"family_comment":"","family":"14278","comment":""},"6":{"family_comment":"","value":"257657.83","family":"","comment":"","value_hidden":false},"7":{"family_comment":"","value":"","source_name":"","family":"","comment":""},"8":{"family_comment":"","value":"","family":"","comment":""},"9":{"family_comment":"","value":"","comment_hidden":false,"family":"","comment":""},"10":{"family_comment":"","value":"","family":"","comment":""},"11":{"family_comment":"","value":"","family":"","comment":""},"12":{"family_comment":"","value":"","family":"","comment":""},"13":{"family_comment":"","value":"","family":"","comment":""},"14":{"family_comment":"","value":"","family":"","comment":""},"15":{"family_comment":"","value":"","family":"","comment":"","family_comment_hidden":false},"16":{"family_comment":"","value":"","family":"","comment":""},"17":{"family_comment":"","value":"","family":"","comment":""},"18":{"family_comment":"","value":"","family":"","comment":"","value_hidden":false},"19":{"family_comment":"","value":"","family":"","comment":""},"20":{"family_comment":"","value":"45597.71","family":"14278","comment":"","family_comment_unclear":false}},"vehicle":{"35":[{"brand_info":"1999 куб. см., 150 к. с","sum_rent_comment":"","brand":"Mazda 6","sum_comment":"","year":"2006","sum":"95916","sum_rent":""}]},"id":"vulyk_78_16","banks":{"49":[{"sum_foreign_comment":"","sum_foreign_hidden":true,"sum_comment":"","sum_foreign_units":"UAH","sum_units":"UAH","sum":"","sum_foreign":""}],"50":[{"sum_foreign_comment":"","sum_foreign_hidden":true,"sum_comment":"","sum_foreign_units":"UAH","sum_units":"UAH","sum":"","sum_foreign":""}]},"declaration":{"additional_info_text":"","notfull_lostpages":"","date":"2015-03-24T00:00:00","notfull":"","additional_info":"","url":"http://static.declarations.com.ua/declarations/chosen_ones/judges_batch/2083_vasylenko_vasyl_vasylovych.pdf"},"liabilities":{"54":{"sum_foreign_comment":"","sum_foreign_hidden":false,"sum_comment":"","sum_comment_unclear":false,"sum_hidden":false,"sum_comment_hidden":false,"sum":"","sum_foreign":""},"55":{"sum_foreign_comment":"","sum":"","sum_comment":"","sum_foreign":""},"56":{"sum_foreign_comment":"","sum":"7000","sum_comment":"","sum_foreign":""},"57":{"sum_foreign_comment":"","sum":"","sum_comment":"","sum_foreign":""},"58":{"sum_foreign_comment":"","sum":"","sum_comment":"","sum_unclear":false,"sum_foreign":""},"59":{"sum_foreign_comment":"","sum":"","sum_comment":"","sum_foreign":""},"60":{"sum_foreign_comment":"","sum":"","sum_comment":"","sum_comment_unclear":false,"sum_comment_hidden":false,"sum_foreign":""},"61":{"sum_foreign_comment":"","sum":"","sum_comment":"","sum_foreign":""},"62":{"sum_foreign_comment":"","sum":"","sum_hidden":false,"sum_comment":"","sum_foreign":""},"63":{"sum_foreign_comment":"","sum_foreign_hidden":false,"sum_comment":"","sum":"","sum_unclear":false,"sum_foreign":""},"64":{"sum_foreign_comment":"","sum_foreign_hidden":false,"sum_comment":"","sum_hidden":false,"sum":"","sum_foreign":""}},"ft_src":"7000\nсуддя черкаського районного суду черкаської області\nЧеркаська область\nЗагальний місцевий суд\nВасиль\nВасиленко О. Г\nПодружжя\nВасильович\nВасиленко Василь Васильович\nВасиль Васильович Василенко\nВасиль Василенко\nВасиленко Василь Васильович\nВасиленко\nВасиленко Василь Васильович\n1999 куб. см., 150 к. с\n95916\n2006\nMazda 6\n.1\n.15\n.5\n121\n2014\n1999 куб. см., 150 к. с\n2006\n95916\nMazda 6\n2014\nПодружжя\nВасиленко О. Г\nВасиленко Василь Васильович\nВасиль Васильович Василенко\nВасиль Василенко\nВасиленко Василь Васильович\nВасиленко Василь Васильович\nВасиль\nВасильович\nЗагальний місцевий суд\nсуддя черкаського районного суду черкаської області\nЧеркаська область\nВасиленко\n7000\n257657.83\n45597.71\n14278\n303255.54\n14278\n.1\n.15\n.5\n121\n7000\n257657.83\n14278\n303255.54\n14278\n45597.71\nПодружжя\nВасиленко О. Г\nВасильович\nВасиленко\nВасиль\nВасиленко Василь Васильович\nВасиль Васильович Василенко\nВасиль Василенко\nВасиленко Василь Васильович\nЧеркаська область\nсуддя черкаського районного суду черкаської області\nЗагальний місцевий суд\nВасиленко Василь Васильович\n95916\nMazda 6\n1999 куб. см., 150 к. с\n2006\n14278\n45597.71\n303255.54\n14278\n257657.83\n.1\n121\n.15\n.5\n2014","general":{"inn":"","name":"Василь","family":[{"inn":"","relations":"Подружжя","relations_other":"","inn_hidden":true,"family_name":"Василенко О. Г","name_hidden":true,"name_unclear":false}],"patronymic":"Васильович","inn_hidden":true,"family_raw":"","last_name":"Василенко","post":{"post_unclear":false,"post":"суддя черкаського районного суду черкаської області","post_hidden":false,"region":"Черкаська область","region_hidden":false,"office":"Загальний місцевий суд","office_hidden":false},"last_name_unclear":false,"full_name":"Василенко Василь Васильович","addresses":[{"place_district":"","place_city_hidden":true,"place_city":"","place_city_type_hidden":true,"place_district_hidden":true,"place_city_type":"","place_address_hidden":true,"place_address":"","place_hidden":true,"place":""}],"full_name_suggest":{"output":"Василенко Василь Васильович","input":["Василенко Василь Васильович","Василь Васильович Василенко","Василь Василенко"]},"name_unclear":false},"source":"VULYK","estate":{"23":[{"costs_rent":"","region":"","costs":"","costs_rent_comment":"","costs_comment":"","address_hidden":true,"region_hidden":true,"space_comment":"","space_units":"га","space":".1","address":""}],"24":[{"costs_rent":"","region":"","costs":"","costs_rent_comment":"","costs_comment":"","address_hidden":true,"region_hidden":true,"space_comment":"","space_units":"м²","space":"121","address":""}],"29":[{"space_unclear":false,"address_hidden":false,"region_hidden":true,"space_comment":"","space":".15","address":"","region":"","costs_property":"","costs_rent_comment":"","space_units":"га","costs_property_comment":"","costs_rent":""},{"costs_rent":"","region":"","costs_property":"","costs_rent_comment":"","address_hidden":false,"space_comment":"","costs_property_comment":"","space_units":"га","space":".5","address":""}]},"intro":{"declaration_year":"2014"}}