{"income":{"5":{"value":"186073","family_comment":"","value_unclear":false,"family_unclear":false,"family":"","comment":""},"6":{"value":"179734","family_comment":"","value_unclear":false,"family_unclear":false,"family":"","comment":""},"7":{"family_comment":"","value":"","source_name":"","family":"","comment":""},"8":{"family_comment":"","value":"","family":"","comment":""},"9":{"family_comment":"","value":"26","value_unclear":false,"family":"","comment":""},"10":{"family_comment":"","value":"","value_unclear":false,"family":"","comment":""},"11":{"family_comment":"","value":"","family":"","comment":""},"12":{"family_comment":"","value":"","family":"","comment":""},"13":{"family_comment":"","value":"5146","value_unclear":false,"family":"","comment":""},"14":{"family_comment":"","value":"","family":"","comment":""},"15":{"family_comment":"","value":"","family":"","comment":""},"16":{"family_comment":"","value":"","family":"","comment":""},"17":{"family_comment":"","value":"","family":"","comment":""},"18":{"family_comment":"","value":"","family":"","comment":""},"19":{"family_comment":"","value":"","family":"","comment":""},"20":{"family_comment":"","family_unclear":false,"value":"1167","family":"","comment":""}},"id":"vulyk_85_52","declaration":{"additional_info_text":"","notfull_lostpages":"","date":"2015-03-30T00:00:00","notfull":"","additional_info":"","url":"http://static.declarations.com.ua/declarations/chosen_ones/judges_batch/2655_troianova_olena_viktorivna.pdf"},"liabilities":{"54":{"sum_foreign_comment":"","sum":"","sum_comment":"","sum_comment_unclear":false,"sum_foreign":""},"55":{"sum_foreign_comment":"","sum":"","sum_comment":"","sum_foreign":""},"56":{"sum_foreign_comment":"","sum":"","sum_comment":"","sum_unclear":false,"sum_foreign":""},"57":{"sum_foreign_comment":"","sum":"","sum_comment":"","sum_foreign":""},"58":{"sum_foreign_comment":"","sum_comment_hidden":false,"sum":"","sum_comment":"","sum_foreign":""},"59":{"sum_foreign_comment":"","sum":"","sum_comment":"","sum_foreign":""},"60":{"sum_foreign_comment":"","sum":"","sum_comment":"","sum_foreign":""},"61":{"sum_foreign_comment":"","sum":"","sum_comment":"","sum_foreign":""},"62":{"sum_foreign_comment":"","sum":"","sum_comment":"","sum_unclear":false,"sum_foreign":""},"63":{"sum_foreign_comment":"","sum":"","sum_comment":"","sum_unclear":false,"sum_foreign":""},"64":{"sum_foreign_comment":"","sum":"","sum_comment":"","sum_foreign":""}},"ft_src":"суддя донецького окружного адміністративного суду\nДонецька область\nАдміністративний місцевий суд\nОлена\nДитина\nВікторівна\nТроянова Олена Вікторівна\nОлена Вікторівна Троянова\nОлена Троянова\nТроянова Олена Вікторівна\nТроянова\nТроянова Олена Вікторівна\n26\n1167\n186073\n179734\n5146\n2014\n179734\n5146\n26\n186073\n1167\n179734\n5146\n1167\n186073\n26\nТроянова Олена Вікторівна\nОлена Вікторівна Троянова\nОлена Троянова\nТроянова Олена Вікторівна\nОлена\nДитина\nТроянова Олена Вікторівна\nТроянова\nАдміністративний місцевий суд\nсуддя донецького окружного адміністративного суду\nДонецька область\nВікторівна\n2014\nДитина\nВікторівна\nТроянова\nОлена\nТроянова Олена Вікторівна\nОлена Вікторівна Троянова\nОлена Троянова\nТроянова Олена Вікторівна\nсуддя донецького окружного адміністративного суду\nДонецька область\nАдміністративний місцевий суд\nТроянова Олена Вікторівна\n2014","general":{"inn":"","name":"Олена","last_name_hidden":false,"family":[{"inn":"","inn_hidden":true,"relations_unclear":false,"relations_hidden":false,"relations_other":"","relations":"Дитина","name_hidden":true,"family_name":"","name_unclear":false}],"patronymic":"Вікторівна","inn_hidden":true,"family_raw":"","last_name":"Троянова","post":{"post_unclear":false,"post_hidden":false,"post":"суддя донецького окружного адміністративного суду","region":"Донецька область","office":"Адміністративний місцевий суд"},"last_name_unclear":false,"full_name":"Троянова Олена Вікторівна","addresses":[{"place_district":"","place_city_hidden":false,"place_city":"","place_city_type_hidden":false,"place_district_hidden":false,"place_city_type":"","place_address_hidden":true,"place_address":"","place_hidden":true,"place":""}],"full_name_suggest":{"output":"Троянова Олена Вікторівна","input":["Троянова Олена Вікторівна","Олена Вікторівна Троянова","Олена Троянова"]}},"source":"VULYK","intro":{"declaration_year":"2014","isnotdeclaration":""}}