{"id":"vulyk_63_174","ft_src":"2013\nVolkswagen Touran\n1980.81\n264400\n1989\n1073\nІЖ-2715\n1478 куб.см., 67к.с.\nсмт Іршанськ\n18\nЖитомирська область\nЖитомирська обл. смт Іршанськ\n18\nЖитомирська область\nсмт. Володимир-Волинський, вул. Рози Люксембург, 18\nЖитомирська область\n95\nсмт. Іршанськ, вул. Гагаріна, 1, кв. 16\nЖитомирська область\n46\n2374\nЖитомирська обл смт Іршанськ вул. Гагаріна 1 кв 16\n46\nЖитомирська область\n2014\n56927\n239077\n19080\n30915\n1806\n12180\n77813\n282172\n1980.81\n2013\n264400\nVolkswagen Touran\n1478 куб.см., 67к.с.\n1989\n1073\nІЖ-2715\n18\nЖитомирська область\nЖитомирська обл. смт Іршанськ\n18\nсмт Іршанськ\nЖитомирська область\n95\nсмт. Володимир-Волинський, вул. Рози Люксембург, 18\nЖитомирська область\n46\nЖитомирська область\nсмт. Іршанськ, вул. Гагаріна, 1, кв. 16\n46\nЖитомирська область\n2374\nЖитомирська обл смт Іршанськ вул. Гагаріна 1 кв 16\nЛеонович\nМельник Микола Леонович\nМикола Леонович Мельник\nМикола Мельник\nМельник Микола Леонович\nМикола\nПодружжя\nМельник В. В., 24. 01. 1960\nМельник Микола Леонович\nЗагальний місцевий суд\nЖитомирська область\nсуддя володарсько-волинського районного суду житомирської області\nМельник\nЖитомирська область\nВолодарсько-Волинський\n11456\n4185\n239077\n56927\n30915\n19080\n282172\n77813\n12180\n1806\n2014\n11456\n4185\nПодружжя\nМельник В. В., 24. 01. 1960\nЛеонович\nМельник\nМельник Микола Леонович\nМикола Леонович Мельник\nМикола Мельник\nМельник Микола Леонович\nМикола\nЖитомирська область\nВолодарсько-Волинський\nЖитомирська область\nсуддя володарсько-волинського районного суду житомирської області\nЗагальний місцевий суд\nМельник Микола Леонович","estate":{"23":[{"costs":"","address":"Житомирська обл. смт Іршанськ","space_units":"м²","costs_hidden":false,"space_hidden":false,"space_unclear":false,"region_hidden":false,"space_units_unclear":false,"costs_comment":"","address_hidden":false,"costs_rent_hidden":false,"space_comment":"","costs_rent_comment":"","space":"18","region":"Житомирська область","space_units_hidden":false,"costs_rent":""}],"25":[{"space":"46","address":"Житомирська обл смт Іршанськ вул. Гагаріна 1 кв 16","costs_comment":"","space_units":"м²","costs_hidden":false,"costs_rent_hidden":false,"space_unclear":false,"costs_rent_comment_hidden":false,"space_comment":"","space_comment_unclear":false,"space_hidden":false,"address_unclear":false,"space_units_hidden":false,"address_hidden":false,"costs_rent_comment":"","costs":"","region_hidden":false,"region_unclear":false,"region":"Житомирська область","costs_comment_hidden":false,"costs_rent":"2374"}],"27":[{"address":"смт Іршанськ","space_units":"м²","costs_hidden":false,"costs_rent_hidden":false,"space_unclear":false,"region_hidden":false,"costs_comment":"","costs_rent_comment_hidden":false,"address_hidden":false,"costs":"","address_unclear":false,"space_comment":"","costs_rent_comment":"","space":"18","region":"Житомирська область","costs_comment_hidden":false,"costs_rent":""}],"30":[{"costs_property_comment":"","address":"смт. Володимир-Волинський, вул. Рози Люксембург, 18","space_units":"м²","space_hidden":false,"space_unclear":false,"region_hidden":false,"costs_property":"","space_comment":"","address_hidden":false,"costs_rent_comment":"","space":"95","region":"Житомирська область","costs_rent":""}],"31":[{"costs_property_comment":"","address":"смт. Іршанськ, вул. Гагаріна, 1, кв. 16","space_units":"м²","space_hidden":false,"region":"Житомирська область","costs_rent_comment_hidden":false,"costs_property":"","space_comment":"","space_comment_unclear":false,"space_units_unclear":false,"costs_rent_hidden":false,"costs_property_hidden":false,"space_unclear":false,"address_hidden":false,"costs_rent_comment":"","space":"46","costs_property_comment_hidden":false,"region_hidden":false,"costs_rent":""}]},"vehicle":{"35":[{"sum_comment":"","brand_info":"1980.81","brand_unclear":false,"sum_rent_comment":"","year":"2013","brand":"Volkswagen Touran","sum_rent":"","brand_info_unclear":false,"sum":"264400"}],"36":[{"sum_comment":"","brand_info_hidden":false,"sum_rent":"","sum":"1073","brand_unclear":false,"year":"1989","brand":"ІЖ-2715","brand_info":"1478 куб.см., 67к.с.","sum_rent_comment":""}]},"source":"VULYK","income":{"5":{"family":"77813","family_comment":"","comment":"","value_hidden":false,"value_unclear":false,"comment_hidden":false,"family_hidden":false,"family_unclear":false,"value":"282172"},"6":{"family_comment":"","family":"56927","comment":"","value_unclear":false,"family_unclear":false,"comment_unclear":false,"value":"239077","family_hidden":false},"7":{"source_name_hidden":false,"family_comment":"","family":"","value_hidden":false,"comment":"","source_name_unclear":false,"value":"","source_name":""},"8":{"family":"","family_comment":"","comment":"","value_hidden":false,"family_hidden":false,"value":""},"9":{"family":"","family_comment":"","comment":"","value_hidden":false,"value_unclear":false,"value":"","family_hidden":false,"family_unclear":false},"10":{"family_comment":"","value":"12180","family":"1806","comment":""},"11":{"family_comment":"","value":"","family":"","comment":""},"12":{"family_comment":"","value":"","family":"","comment":""},"13":{"family_comment":"","value":"","family":"","comment":""},"14":{"family_comment":"","value":"","family":"","comment":""},"15":{"family_comment":"","value":"30915","family":"19080","comment":""},"16":{"family_comment":"","family":"","comment":"","value_unclear":false,"family_unclear":false,"value":""},"17":{"family_comment":"","value":"","family":"","comment":""},"18":{"family_comment":"","value":"","family":"","comment":""},"19":{"family_comment":"","comment_unclear":false,"value":"","family":"","comment":""},"20":{"family_unclear":false,"family_comment":"","comment":"","family":"","value_unclear":false,"value_hidden":false,"comment_hidden":false,"comment_unclear":false,"value":"","family_hidden":false,"family_comment_unclear":false}},"general":{"family":[{"inn":"","inn_unclear":false,"family_name":"Мельник В. В., 24. 01. 1960","relations_hidden":false,"relations_unclear":false,"name_unclear":false,"relations":"Подружжя","inn_hidden":true,"name_hidden":false,"relations_other":""}],"family_raw":"","name":"Микола","full_name_suggest":{"input":["Мельник Микола Леонович","Микола Леонович Мельник","Микола Мельник"],"output":"Мельник Микола Леонович"},"name_unclear":false,"patronymic":"Леонович","inn_hidden":false,"patronymic_unclear":false,"last_name_hidden":false,"inn":"","inn_unclear":true,"last_name":"Мельник","full_name":"Мельник Микола Леонович","post":{"office":"Загальний місцевий суд","post":"суддя володарсько-волинського районного суду житомирської області","office_unclear":false,"office_hidden":false,"region":"Житомирська область","region_hidden":false,"post_unclear":false,"region_unclear":false},"addresses":[{"place_city_type_hidden":false,"place_district_hidden":false,"place_address_unclear":false,"place":"Житомирська область","place_city":"","place_unclear":false,"place_city_type_unclear":false,"place_city_type":"","place_city_hidden":true,"place_city_unclear":false,"place_district":"Володарсько-Волинський","place_district_unclear":false,"place_address":"","place_address_hidden":false,"place_hidden":false}],"name_hidden":false,"last_name_unclear":false},"liabilities":{"54":{"sum_comment":"","sum_foreign_comment":"","sum_foreign":"","sum_unclear":false,"sum":""},"55":{"sum_comment":"","sum_foreign_comment":"","sum_foreign":"","sum":""},"56":{"sum_comment":"","sum_foreign_comment":"","sum_foreign":"","sum_unclear":false,"sum":"11456"},"57":{"sum_comment":"","sum":"","sum_foreign_comment":"","sum_foreign":"","sum_unclear":false,"sum_comment_hidden":false},"58":{"sum_comment":"","sum_foreign_comment":"","sum_foreign":"","sum":"","sum_comment_hidden":false},"59":{"sum_comment":"","sum_foreign_comment":"","sum_foreign":"","sum":""},"60":{"sum_comment":"","sum_comment_unclear":false,"sum_foreign_comment":"","sum":"","sum_foreign":""},"61":{"sum_comment":"","sum_foreign_comment":"","sum_foreign":"","sum_unclear":false,"sum":""},"62":{"sum_comment":"","sum_foreign_comment":"","sum_foreign":"","sum_unclear":false,"sum":"4185"},"63":{"sum_comment":"","sum_hidden":false,"sum":"","sum_foreign_comment":"","sum_foreign":"","sum_unclear":false,"sum_comment_hidden":false},"64":{"sum_comment":"","sum_foreign_comment":"","sum_foreign":"","sum":"","sum_comment_hidden":false}},"declaration":{"notfull_lostpages":"","additional_info_text":"","additional_info":"","date":"2015-03-20T00:00:00","notfull":"","url":"http://static.declarations.com.ua/declarations/chosen_ones/mega_batch/melnyk_mykola_leonovych.pdf"},"intro":{"isnotdeclaration":"","declaration_year_unclear":false,"declaration_year":"2014"}}