{"income":{"5":{"value":"337899","family_comment":"","value_unclear":false,"family_hidden":false,"value_hidden":false,"family_unclear":false,"family":"23715","comment":""},"6":{"value":"195899","value_unclear":false,"family_hidden":false,"value_hidden":false,"family_comment":"","comment_unclear":false,"comment":"","family":"23715"},"7":{"value":"","value_hidden":false,"family_comment":"","source_name":"","family":"","comment":"","source_name_hidden":false},"8":{"family_comment":"","value":"","family":"","comment":""},"9":{"family_comment":"","value":"","comment_unclear":false,"family":"","comment":""},"10":{"family_comment":"","value":"","value_unclear":false,"family":"","comment":""},"11":{"family_comment":"","value":"","family":"","comment":""},"12":{"family_comment":"","value":"","family":"","comment":""},"13":{"family_comment":"","value":"","family":"","comment":""},"14":{"family_comment":"","value":"","family":"","comment":""},"15":{"family_comment":"","value":"","family":"","comment":""},"16":{"family_comment":"","value":"142000","family":"","comment":""},"17":{"family_comment":"","value":"","family":"","comment":""},"18":{"family_comment":"","value":"","family":"","comment":""},"19":{"value":"","value_unclear":false,"comment_hidden":false,"family_hidden":false,"value_hidden":false,"family_comment":"","family_comment_hidden":false,"comment":"","family":""},"20":{"value":"","family_comment":"","value_unclear":false,"family_hidden":false,"value_hidden":false,"family_unclear":false,"comment_unclear":false,"comment":"","family":""}},"vehicle":{"40":[{"brand_info":"2.5 куб. см.","sum_rent_comment":"","brand":"Nissan X-Trail","sum_comment":"","brand_unclear":false,"year":"2008","brand_hidden":false,"brand_info_unclear":false,"year_unclear":false,"sum":"","sum_rent":""}]},"id":"vulyk_65_197","declaration":{"additional_info_text":"","notfull_lostpages":"","date":"2015-03-19T00:00:00","notfull":"","additional_info":"","url":"http://static.declarations.com.ua/declarations/chosen_ones/mega_batch/halytskyi_vitalii_valentynovych.pdf"},"liabilities":{"54":{"sum_foreign_comment":"","sum":"","sum_comment":"","sum_comment_unclear":false,"sum_hidden":false,"sum_comment_hidden":false,"sum_foreign":""},"55":{"sum_foreign_comment":"","sum":"","sum_comment":"","sum_foreign":""},"56":{"sum_foreign_comment":"","sum":"","sum_comment":"","sum_unclear":false,"sum_foreign":""},"57":{"sum_foreign_comment":"","sum":"","sum_comment":"","sum_comment_unclear":false,"sum_unclear":false,"sum_foreign":""},"58":{"sum_foreign_comment":"","sum":"","sum_comment":"","sum_comment_unclear":false,"sum_unclear":false,"sum_foreign":""},"59":{"sum_foreign_comment":"","sum":"","sum_comment":"","sum_foreign":""},"60":{"sum_foreign_comment":"","sum":"","sum_comment":"","sum_comment_unclear":false,"sum_foreign":""},"61":{"sum_foreign_comment":"","sum":"","sum_comment":"","sum_foreign":""},"62":{"sum_foreign_comment":"","sum":"","sum_comment":"","sum_foreign":""},"63":{"sum_foreign_comment":"","sum":"","sum_comment":"","sum_foreign":""},"64":{"sum_foreign_comment":"","sum":"","sum_comment":"","sum_unclear":false,"sum_foreign":""}},"ft_src":"голова вільшанського районного суду кіровоградської області\nКіровоградська область\nЗагальний місцевий суд\nВіталій\nГалицька А. Г\nПодружжя\nГалицька З. В\nДитина\nВалентинович\nГалицький\nГалицький Віталій Валентинович\nГалицький Віталій Валентинович\nВіталій Валентинович Галицький\nВіталій Галицький\nГалицький Віталій Валентинович\nNissan X-Trail\n2.5 куб. см.\n2008\n56.91\n2014\n23715\n195899\n23715\n337899\n142000\n2.5 куб. см.\n2008\nNissan X-Trail\n56.91\nЗагальний місцевий суд\nКіровоградська область\nголова вільшанського районного суду кіровоградської області\nГалицький Віталій Валентинович\nВіталій Валентинович Галицький\nВіталій Галицький\nГалицький Віталій Валентинович\nВіталій\nПодружжя\nГалицька А. Г\nДитина\nГалицька З. В\nГалицький Віталій Валентинович\nГалицький\nВалентинович\n195899\n23715\n337899\n23715\n142000\n2014\nГалицька А. Г\nПодружжя\nДитина\nГалицька З. В\nВалентинович\nГалицький\nВіталій\nГалицький Віталій Валентинович\nВіталій Валентинович Галицький\nВіталій Галицький\nГалицький Віталій Валентинович\nКіровоградська область\nЗагальний місцевий суд\nголова вільшанського районного суду кіровоградської області\nГалицький Віталій Валентинович\n2008\nNissan X-Trail\n2.5 куб. см.\n337899\n23715\n142000\n195899\n23715\n56.91\n2014","general":{"name_hidden":false,"name":"Віталій","last_name_hidden":false,"inn":"","family":[{"inn":"","inn_hidden":true,"inn_unclear":false,"relations_hidden":false,"relations_other":"","relations":"Подружжя","name_hidden":true,"family_name":"Галицька А. Г","name_unclear":false},{"inn":"","inn_hidden":true,"relations_unclear":false,"relations_hidden":false,"relations_other":"","relations":"Дитина","name_hidden":false,"inn_unclear":false,"family_name":"Галицька З. В","name_unclear":false}],"patronymic":"Валентинович","inn_hidden":true,"family_raw":"","inn_unclear":false,"post":{"post_unclear":false,"region_unclear":false,"post":"голова вільшанського районного суду кіровоградської області","office":"Загальний місцевий суд","region":"Кіровоградська область","post_hidden":false,"office_hidden":false,"office_unclear":false,"region_hidden":false},"last_name_unclear":false,"full_name":"Галицький Віталій Валентинович","addresses":[{"place_district":"","place_address_hidden":true,"place_city":"","place_city_type_hidden":true,"place_district_hidden":true,"place_city_type":"","place_city_hidden":true,"place_address_unclear":false,"place_address":"","place_hidden":true,"place":""}],"last_name":"Галицький","patronymic_hidden":false,"full_name_suggest":{"output":"Галицький Віталій Валентинович","input":["Галицький Віталій Валентинович","Віталій Валентинович Галицький","Віталій Галицький"]},"name_unclear":false},"source":"VULYK","estate":{"31":[{"space_unclear":false,"address_hidden":false,"region_hidden":true,"space_comment":"","space":"56.91","address":"","region":"","costs_property":"","costs_rent_comment":"","space_comment_unclear":false,"space_units":"м²","costs_property_comment":"","costs_rent":""}]},"intro":{"declaration_year":"2014","isnotdeclaration":"","declaration_year_hidden":false}}