{"income":{"5":{"value":"15792","value_unclear":false,"value_hidden":false,"family_comment":"","family":"17463","comment":""},"6":{"value":"","family_comment":"","value_unclear":false,"family_unclear":false,"family":"15753","comment":""},"7":{"source_name_unclear":false,"value":"","family_hidden":false,"family_comment":"","source_name":"","family":"","comment":""},"8":{"family_comment":"","value":"","family":"","comment":""},"9":{"family_comment":"","value":"","family":"","comment":""},"10":{"family_comment":"","value":"","family":"1710","comment":""},"11":{"family_comment":"","value":"","family":"","comment":""},"12":{"family_comment":"","value":"","family":"","comment":""},"13":{"family_comment":"","value":"","family":"","comment":""},"14":{"family_comment":"","value":"","family":"","comment":""},"15":{"family_comment":"","value":"","family":"","comment":""},"16":{"family_comment":"","value":"","comment_unclear":false,"family":"","comment":""},"17":{"family_comment":"","family_unclear":false,"value":"","family":"","comment":""},"18":{"family_comment":"","value":"","family":"","comment":""},"19":{"value":"","family_hidden":false,"value_hidden":false,"family_comment":"","family":"","comment":""},"20":{"family_comment":"","value":"15792","comment_unclear":false,"family":"","comment":"допомога по догляду за дитиною до 3-х років"}},"vehicle":{"40":[{"brand_info":"1600 куб. см.","sum_rent_comment":"","brand":"Mitsubishi Lancer","sum_comment":"","brand_unclear":false,"year":"2008","brand_info_unclear":false,"year_unclear":false,"sum":"","sum_rent":""}]},"id":"vulyk_67_5","declaration":{"additional_info_text":"","notfull_lostpages":"","date":"2015-03-30T00:00:00","notfull":"","additional_info":"","url":"http://static.declarations.com.ua/declarations/chosen_ones/mega_batch/mozolevska_olena_mykolaivna.pdf"},"liabilities":{"54":{"sum_foreign_comment":"","sum_foreign_hidden":false,"sum_comment":"","sum_comment_unclear":false,"sum_hidden":false,"sum":"","sum_unclear":false,"sum_foreign":""},"55":{"sum_foreign_comment":"","sum":"","sum_comment":"","sum_foreign":""},"56":{"sum_foreign_comment":"","sum_foreign_hidden":false,"sum_comment":"","sum_hidden":false,"sum":"","sum_unclear":false,"sum_foreign":""},"57":{"sum_foreign_comment":"","sum_foreign_hidden":false,"sum_comment":"","sum_comment_unclear":false,"sum_hidden":false,"sum_comment_hidden":false,"sum_unclear":false,"sum":"","sum_foreign":""},"58":{"sum_foreign_comment":"","sum_foreign_hidden":false,"sum_comment":"","sum_comment_unclear":false,"sum_hidden":false,"sum_comment_hidden":false,"sum_unclear":false,"sum":"","sum_foreign":""},"59":{"sum_foreign_comment":"","sum":"","sum_hidden":false,"sum_comment":"","sum_foreign":""},"60":{"sum_foreign_comment":"","sum":"","sum_comment":"","sum_foreign":""},"61":{"sum_foreign_comment":"","sum_foreign_hidden":false,"sum_comment":"","sum_hidden":false,"sum":"","sum_foreign":""},"62":{"sum_foreign_comment":"","sum":"","sum_hidden":false,"sum_comment":"","sum_foreign":""},"63":{"sum_foreign_comment":"","sum":"","sum_comment":"","sum_comment_unclear":false,"sum_hidden":false,"sum_unclear":false,"sum_foreign":""},"64":{"sum_foreign_comment":"","sum":"","sum_comment":"","sum_hidden":false,"sum_unclear":false,"sum_foreign":""}},"ft_src":"суддя солом'янського районного суду міста києва\nм. Київ\nЗагальний місцевий суд\nОлена\nМозолевський О. В., 07. 02. 1983\nПодружжя\nЛук'янець Д. Р., 22. 01. 2000\nДитина\nМозолевський М. О., 19. 03. 2012\nДитина\nМиколаївна\nМозолевська Олена Миколаївна\nМозолевська\nМозолевська Олена Миколаївна\nОлена Миколаївна Мозолевська\nОлена Мозолевська\nМозолевська Олена Миколаївна\n1600 куб. см.\nMitsubishi Lancer\n2008\n1/3 частина\n60\nкористування\n22\n2014\n15753\n1710\n17463\n15792\nдопомога по догляду за дитиною до 3-х років\n15792\n1600 куб. см.\n2008\nMitsubishi Lancer\n60\n1/3 частина\n22\nкористування\nЗагальний місцевий суд\nсуддя солом'янського районного суду міста києва\nм. Київ\nПодружжя\nМозолевський О. В., 07. 02. 1983\nДитина\nЛук'янець Д. Р., 22. 01. 2000\nДитина\nМозолевський М. О., 19. 03. 2012\nМозолевська Олена Миколаївна\nОлена Миколаївна Мозолевська\nОлена Мозолевська\nМозолевська Олена Миколаївна\nМозолевська Олена Миколаївна\nОлена\nМозолевська\nМиколаївна\n15753\nдопомога по догляду за дитиною до 3-х років\n15792\n15792\n17463\n1710\n2014\nПодружжя\nМозолевський О. В., 07. 02. 1983\nДитина\nЛук'янець Д. Р., 22. 01. 2000\nМозолевський М. О., 19. 03. 2012\nДитина\nМиколаївна\nМозолевська\nОлена\nМозолевська Олена Миколаївна\nОлена Миколаївна Мозолевська\nОлена Мозолевська\nМозолевська Олена Миколаївна\nм. Київ\nсуддя солом'янського районного суду міста києва\nЗагальний місцевий суд\nМозолевська Олена Миколаївна\n2008\n1600 куб. см.\nMitsubishi Lancer\n1710\nдопомога по догляду за дитиною до 3-х років\n15792\n15792\n17463\n15753\n1/3 частина\n60\nкористування\n22\n2014","general":{"inn":"","name":"Олена","patronymic_unclear":false,"last_name_hidden":false,"family":[{"inn":"","inn_hidden":true,"relations_unclear":false,"relations_hidden":false,"relations_other":"","relations":"Подружжя","name_hidden":false,"inn_unclear":false,"family_name":"Мозолевський О. В., 07. 02. 1983","name_unclear":false},{"inn":"","inn_hidden":true,"relations_unclear":false,"relations_hidden":false,"relations_other":"","relations":"Дитина","name_hidden":true,"inn_unclear":false,"family_name":"Лук'янець Д. Р., 22. 01. 2000","name_unclear":false},{"inn":"","relations":"Дитина","relations_unclear":false,"family_name":"Мозолевський М. О., 19. 03. 2012","inn_hidden":true,"relations_other":"","name_hidden":false,"name_unclear":false}],"patronymic":"Миколаївна","inn_hidden":true,"family_raw":"","inn_unclear":false,"post":{"post_unclear":false,"post":"суддя солом'янського районного суду міста києва","post_hidden":false,"region":"м. Київ","region_hidden":false,"office":"Загальний місцевий суд","office_hidden":false,"office_unclear":false},"last_name_unclear":false,"full_name":"Мозолевська Олена Миколаївна","addresses":[{"place_city_type_hidden":true,"place_district_hidden":true,"place_city_type":"","place_city_hidden":true,"place_address_unclear":false,"place_address":"","place":"","place_district":"","place_unclear":false,"place_city":"","place_city_unclear":false,"place_hidden":true,"place_address_hidden":true,"place_district_unclear":false}],"last_name":"Мозолевська","full_name_suggest":{"output":"Мозолевська Олена Миколаївна","input":["Мозолевська Олена Миколаївна","Олена Миколаївна Мозолевська","Олена Мозолевська"]},"name_unclear":false},"source":"VULYK","estate":{"25":[{"space_unclear":false,"costs":"","costs_comment":"","costs_hidden":false,"address_hidden":true,"region_hidden":true,"space_comment":"користування","space":"22","address":"","region":"","address_unclear":false,"space_units_unclear":false,"space_comment_unclear":false,"space_units":"м²","costs_rent":"","costs_rent_comment":""}],"31":[{"space_hidden":false,"address_hidden":true,"region_hidden":true,"space_comment":"1/3 частина","space_unclear":false,"space":"60","address":"","region":"","costs_property":"","costs_rent_comment":"","space_comment_unclear":false,"address_unclear":false,"space_units":"м²","costs_property_comment":"","costs_rent":""}]},"intro":{"declaration_year":"2014","isnotdeclaration":"","declaration_year_hidden":false}}