{"income":{"5":{"value":"241371","family_comment":"","comment_unclear":false,"family_unclear":false,"family":"46047","comment":""},"6":{"family_comment":"","value":"241371","family":"45104","comment":""},"7":{"source_name_unclear":false,"value":"","comment_unclear":false,"family_comment":"","source_name":"","family":"","comment":""},"8":{"family_comment":"","value":"","family":"","comment":""},"9":{"family_comment":"","value":"","family":"","comment":""},"10":{"family_comment":"","value":"","family":"","comment":""},"11":{"family_comment":"","value":"","family":"","comment":""},"12":{"family_comment":"","value":"","family":"","comment":""},"13":{"family_comment":"","value":"","family":"","comment":""},"14":{"family_comment":"","value":"","family":"","comment":""},"15":{"family_comment":"","value":"","family":"","comment":""},"16":{"family_comment":"","family_unclear":false,"value":"","family":"","comment":""},"17":{"family_comment":"","value":"","family":"","comment":""},"18":{"family_comment":"","value":"","family":"","comment":""},"19":{"family_comment":"","value":"","family":"","comment":""},"20":{"value":"","family_comment":"","comment_unclear":false,"family_unclear":false,"family":"943","comment":"","family_comment_unclear":false}},"id":"vulyk_107_53","banks":{"45":[{"sum_foreign_comment":"","sum_units":"UAH","sum_comment":"","sum_comment_unclear":false,"sum_foreign_units":"UAH","sum_comment_hidden":true,"sum_unclear":false,"sum":"891","sum_foreign":""}]},"declaration":{"additional_info_text":"","notfull_lostpages":"","date":"2016-03-25T00:00:00","notfull":"","additional_info":"","url":"http://static.declarations.com.ua/declarations/chosen_ones/judges_batch/2032_ieremeichuk_serhii_volodymyrovych.pdf"},"liabilities":{"54":{"sum_foreign_comment":"","sum":"","sum_comment":"","sum_comment_unclear":false,"sum_comment_hidden":false,"sum_foreign":""},"55":{"sum_foreign_comment":"","sum":"","sum_comment":"","sum_foreign":""},"56":{"sum_foreign_comment":"","sum":"","sum_comment":"","sum_unclear":false,"sum_foreign":""},"57":{"sum_foreign_comment":"","sum":"","sum_comment":"","sum_comment_unclear":false,"sum_foreign":""},"58":{"sum_foreign_comment":"","sum":"","sum_comment":"","sum_comment_unclear":false,"sum_unclear":false,"sum_foreign":""},"59":{"sum_foreign_comment":"","sum":"","sum_comment":"","sum_unclear":false,"sum_foreign":""},"60":{"sum_foreign_comment":"","sum":"","sum_comment":"","sum_comment_unclear":false,"sum_comment_hidden":false,"sum_foreign":""},"61":{"sum_foreign_comment":"","sum":"","sum_comment":"","sum_foreign":""},"62":{"sum_foreign_comment":"","sum":"","sum_comment":"","sum_foreign":""},"63":{"sum_foreign_comment":"","sum":"","sum_comment":"","sum_foreign":""},"64":{"sum_foreign_comment":"","sum":"","sum_comment":"","sum_foreign":""}},"ft_src":"Єремейчук Сергій Володимирович\nсуддя апеляційного суду рівненської області\nРівненська область\nЗагальний апеляційний суд\nСергій\nЄремейчук Л. С\nПодружжя\nЄремейчук Я. С\nДитина\nЄремейчук Сергій Володимирович\nСергій Володимирович Єремейчук\nСергій Єремейчук\nЄремейчук Сергій Володимирович\nЄремейчук\nВолодимирович\n943\n241371\n46047\n45104\n241371\n891\nспадок\n29700\n1980\n1382\n61.8\n2015\n45104\n241371\n46047\n241371\n943\n891\n2015\nЄремейчук\nПодружжя\nЄремейчук Л. С\nДитина\nЄремейчук Я. С\nЄремейчук Сергій Володимирович\nСергій Володимирович Єремейчук\nСергій Єремейчук\nЄремейчук Сергій Володимирович\nСергій\nВолодимирович\nЄремейчук Сергій Володимирович\nЗагальний апеляційний суд\nсуддя апеляційного суду рівненської області\nРівненська область\n241371\n45104\n943\n241371\n46047\n29700\nспадок\n1980\n1382\n61.8\nЄремейчук Л. С\nПодружжя\nЄремейчук Я. С\nДитина\nЄремейчук\nВолодимирович\nсуддя апеляційного суду рівненської області\nРівненська область\nЗагальний апеляційний суд\nЄремейчук Сергій Володимирович\nЄремейчук Сергій Володимирович\nСергій Володимирович Єремейчук\nСергій Єремейчук\nЄремейчук Сергій Володимирович\nСергій\n61.8\nспадок\n29700\n1980\n1382\n891\n2015","general":{"inn":"","inn_hidden":true,"last_name":"Єремейчук","post":{"post_unclear":false,"office":"Загальний апеляційний суд","post":"суддя апеляційного суду рівненської області","region":"Рівненська область"},"name":"Сергій","full_name":"Єремейчук Сергій Володимирович","family_raw":"","addresses":[{"place_district":"","place_city_hidden":true,"place_city":"","place_city_type_hidden":false,"place_district_hidden":true,"place_city_type":"","place_address_hidden":true,"place_address":"","place_hidden":true,"place":""}],"family":[{"inn":"","relations":"Подружжя","relations_other":"","inn_hidden":true,"family_name":"Єремейчук Л. С","name_hidden":true,"name_unclear":false},{"inn":"","relations":"Дитина","relations_other":"","inn_hidden":true,"family_name":"Єремейчук Я. С","name_hidden":false,"name_unclear":false}],"full_name_suggest":{"output":"Єремейчук Сергій Володимирович","input":["Єремейчук Сергій Володимирович","Сергій Володимирович Єремейчук","Сергій Єремейчук"]},"patronymic":"Володимирович"},"source":"VULYK","estate":{"23":[{"costs":"","costs_comment":"","address_hidden":true,"region_hidden":true,"space_comment":"спадок","space":"29700","address":"","region":"","costs_rent_comment":"","space_comment_unclear":false,"space_comment_hidden":false,"space_units":"м²","costs_rent":""},{"costs_rent":"","region":"","costs":"","costs_rent_comment":"","costs_comment":"","address_hidden":false,"region_hidden":false,"space_comment":"","space_units":"м²","space":"1980","address":""}],"29":[{"address_hidden":true,"region_hidden":true,"space_comment":"","space":"1382","address":"","region":"","costs_property":"","costs_rent_comment":"","costs_rent_hidden":false,"space_units":"м²","costs_property_comment":"","costs_rent":""}],"31":[{"space_unclear":false,"address_hidden":true,"region_hidden":true,"space_comment":"","space_hidden":false,"space":"61.8","address":"","region":"","costs_property":"","costs_rent_comment":"","space_comment_unclear":false,"space_units":"м²","costs_property_comment":"","costs_rent":""}]},"intro":{"declaration_year":"2015","isnotdeclaration":""}}