{"income":{"5":{"value":"225383","family_comment":"","value_unclear":false,"family_hidden":false,"value_hidden":false,"family_unclear":false,"comment_unclear":false,"comment":"","family":"392000"},"6":{"value":"225383","family_unclear":false,"family_hidden":false,"family_comment":"","family":"","comment":""},"7":{"value":"","family_hidden":false,"value_hidden":false,"family_comment":"","source_name":"","family":"","comment":""},"8":{"family_comment":"","value":"","family":"","comment":""},"9":{"family_comment":"","value":"","value_unclear":false,"family":"","comment":""},"10":{"family_comment":"","family_unclear":false,"value":"","family":"","comment":""},"11":{"family_comment":"","value":"","family":"","comment":""},"12":{"family_comment":"","value":"","family":"","comment":""},"13":{"family_comment":"","value":"","family":"","comment":""},"14":{"family_comment":"","value":"","family":"","comment":""},"15":{"family_comment":"","value":"","family":"","comment":""},"16":{"family_comment":"","value":"","family":"","comment":""},"17":{"family_comment":"","value":"","family":"392000","comment":""},"18":{"family_comment":"","value":"","family":"","comment":""},"19":{"family_comment":"","value":"","family":"","comment":""},"20":{"value":"","value_unclear":false,"family_comment":"","comment_unclear":false,"comment":"","family":""}},"id":"vulyk_71_148","banks":{"51":[{"sum_foreign_comment":"","sum_units":"UAH","sum_comment":"","sum_comment_unclear":false,"sum_foreign_units":"UAH","sum_comment_hidden":false,"sum_unclear":false,"sum":"95971","sum_foreign":""}],"53":[{"sum_foreign_comment":"","sum_units":"UAH","sum_comment":"","sum_foreign_units":"UAH","sum":"172650","sum_foreign":""}]},"declaration":{"additional_info_text":"","notfull_lostpages":"","date":"2014-12-11T00:00:00","notfull":"","additional_info":"","url":"http://static.declarations.com.ua/declarations/chosen_ones/judges_batch/454_mazhara_svitlana_borysivna.pdf"},"liabilities":{"54":{"sum_foreign_comment":"","sum":"","sum_comment":"","sum_comment_unclear":false,"sum_comment_hidden":false,"sum_unclear":false,"sum_foreign":""},"55":{"sum_foreign_comment":"","sum":"","sum_comment":"","sum_foreign":""},"56":{"sum_foreign_comment":"","sum":"","sum_comment":"","sum_comment_unclear":false,"sum_unclear":false,"sum_foreign":""},"57":{"sum_foreign_comment":"","sum":"","sum_comment":"","sum_comment_hidden":false,"sum_unclear":false,"sum_foreign":""},"58":{"sum_foreign_comment":"","sum":"","sum_comment":"","sum_comment_hidden":false,"sum_unclear":false,"sum_foreign":""},"59":{"sum_foreign_comment":"","sum_comment_hidden":false,"sum":"","sum_comment":"","sum_foreign":""},"60":{"sum_foreign_comment":"","sum_comment_hidden":false,"sum":"","sum_comment":"","sum_foreign":""},"61":{"sum_foreign_comment":"","sum":"","sum_comment":"","sum_foreign":""},"62":{"sum_foreign_comment":"","sum":"","sum_comment":"","sum_foreign":""},"63":{"sum_foreign_comment":"","sum":"","sum_comment":"","sum_unclear":false,"sum_foreign":""},"64":{"sum_foreign_comment":"","sum":"","sum_comment":"","sum_unclear":false,"sum_foreign":""}},"ft_src":"суддя апеляційного суду дніпропетровської області\nДніпропетровська область\nЗагальний апеляційний суд\nСвітлана\nМажара В. М\nПодружжя\nМажара М. В\nДитина\nМажара К. В\nДитина\nМажара О. В\nДитина\nБорисівна\nМажара Світлана Борисівна\nСвітлана Борисівна Мажара\nСвітлана Мажара\nМажара Світлана Борисівна\nМажара Світлана Борисівна\nМажара\n85\n172650\n95971\n2013\n85\nПодружжя\nМажара В. М\nДитина\nМажара М. В\nДитина\nМажара К. В\nМажара О. В\nДитина\nМажара Світлана Борисівна\nСвітлана Борисівна Мажара\nСвітлана Мажара\nМажара Світлана Борисівна\nМажара Світлана Борисівна\nСвітлана\nБорисівна\nЗагальний апеляційний суд\nДніпропетровська область\nсуддя апеляційного суду дніпропетровської області\nМажара\n225383\n392000\n225383\n392000\n172650\n95971\n2013\n225383\n392000\n225383\n392000\nМажара В. М\nПодружжя\nМажара М. В\nДитина\nМажара К. В\nДитина\nДитина\nМажара О. В\nБорисівна\nМажара\nСвітлана\nМажара Світлана Борисівна\nСвітлана Борисівна Мажара\nСвітлана Мажара\nМажара Світлана Борисівна\nДніпропетровська область\nЗагальний апеляційний суд\nсуддя апеляційного суду дніпропетровської області\nМажара Світлана Борисівна\n225383\n392000\n392000\n225383\n85\n95971\n172650\n2013","general":{"inn":"","name":"Світлана","family":[{"inn":"","inn_hidden":false,"relations_hidden":false,"family_name":"Мажара В. М","relations_other":"","relations":"Подружжя","name_hidden":false,"name_unclear":false},{"inn":"","inn_hidden":false,"relations_hidden":false,"family_name":"Мажара М. В","relations_other":"","relations":"Дитина","name_hidden":false,"name_unclear":false},{"inn":"","relations":"Дитина","relations_other":"","inn_hidden":false,"family_name":"Мажара К. В","name_unclear":false},{"inn":"","family_name":"Мажара О. В","relations":"Дитина","inn_hidden":false,"relations_other":""}],"patronymic":"Борисівна","inn_hidden":true,"family_raw":"","inn_unclear":false,"post":{"post_unclear":false,"region_unclear":false,"post":"суддя апеляційного суду дніпропетровської області","office":"Загальний апеляційний суд","region":"Дніпропетровська область","post_hidden":false,"office_unclear":false},"full_name_suggest":{"output":"Мажара Світлана Борисівна","input":["Мажара Світлана Борисівна","Світлана Борисівна Мажара","Світлана Мажара"]},"full_name":"Мажара Світлана Борисівна","addresses":[{"place_district":"","place_unclear":false,"place_city":"","place_city_type_hidden":true,"place_district_hidden":true,"place_city_type":"","place_city_hidden":true,"place_address_hidden":true,"place_address":"","place_hidden":true,"place":""}],"last_name":"Мажара","patronymic_hidden":false,"last_name_unclear":false,"name_unclear":false},"source":"VULYK","estate":{"25":[{"region_unclear":false,"space_unclear":false,"costs":"","costs_rent_unclear":false,"costs_comment":"","costs_hidden":false,"address_hidden":false,"region_hidden":true,"space_comment":"","space_hidden":false,"space":"85","address":"","costs_unclear":false,"region":"","address_unclear":false,"costs_rent_comment":"","costs_rent_hidden":false,"space_comment_unclear":false,"space_units":"м²","costs_rent":""}],"26":[{"space_unclear":false,"costs":"","costs_comment":"","address_hidden":false,"region_hidden":true,"space_comment":"","space":"","address":"","region":"","address_unclear":false,"costs_rent_comment":"","space_comment_unclear":false,"space_units":"м²","costs_rent":""}]},"intro":{"declaration_year":"2013","isnotdeclaration":""}}