{"income":{"5":{"value":"167035","family_comment":"","value_unclear":false,"family_unclear":false,"family":"16158","comment":""},"6":{"value":"167035","family_comment":"","value_unclear":false,"family_unclear":false,"family":"","comment":""},"7":{"family_comment":"","value":"","source_name":"","family":"","comment":""},"8":{"family_comment":"","value":"","family":"","comment":""},"9":{"family_comment":"","value":"","family":"","comment":""},"10":{"family_comment":"","value":"","family":"","comment":""},"11":{"family_comment":"","value":"","family":"","comment":""},"12":{"family_comment":"","value":"","family":"","comment":""},"13":{"family_comment":"","value":"","family":"","comment":""},"14":{"family_comment":"","value":"","family":"","comment":""},"15":{"family_comment":"","value":"","value_unclear":false,"family":"","comment":""},"16":{"family_comment":"","value":"","family":"","comment":""},"17":{"family_comment":"","value":"","family":"","comment":""},"18":{"family_comment":"","value":"","family":"","comment":""},"19":{"family_comment":"","value":"","family":"","comment":""},"20":{"value":"","family_comment":"пенсія, субсидія","value_unclear":false,"family_unclear":false,"family":"16158","comment":"","family_comment_unclear":false},"21":[{"cur":"100","cur_units":"EUR","country":"Португалія","uah_equal":"2420","country_comment":""}],"22":[{"cur":"100","cur_units":"EUR","country":"Португалія","uah_equal":"2524","country_comment":""}]},"vehicle":{"35":[{"brand_info":"1199 куб. см., 61 кВт","sum_rent_comment":"","brand":"Peugeot 2008 Allure","sum_comment":"","brand_unclear":false,"year":"2014","brand_info_unclear":false,"sum":"","sum_rent":""}]},"id":"vulyk_99_44","declaration":{"date":"2016-03-30T00:00:00","notfull":"","notfull_lostpages":"","url":"http://static.declarations.com.ua/declarations/chosen_ones/judges_batch/593_barhamina_nataliia_mykolaivna_2015.pdf"},"liabilities":{"54":{"sum_foreign_comment":"","sum":"","sum_comment":"","sum_comment_unclear":false,"sum_comment_hidden":false,"sum_foreign":""},"55":{"sum_foreign_comment":"","sum":"","sum_comment":"","sum_foreign":""},"56":{"sum_foreign_comment":"","sum":"","sum_comment":"","sum_foreign":""},"57":{"sum_foreign_comment":"","sum_comment":"Креді Агріколь Банк індекс Банк","sum":"75957","sum_comment_hidden":false,"sum_foreign":""},"58":{"sum_foreign_comment":"","sum_comment":"","sum":"684","sum_comment_hidden":false,"sum_foreign":""},"59":{"sum_foreign_comment":"","sum":"","sum_comment":"","sum_comment_hidden":false,"sum_unclear":false,"sum_foreign":""},"60":{"sum_foreign_comment":"","sum_comment":"","sum":"","sum_comment_hidden":false,"sum_foreign":""},"61":{"sum_foreign_comment":"","sum":"","sum_comment":"","sum_foreign":""},"62":{"sum_foreign_comment":"","sum":"","sum_comment":"","sum_foreign":""},"63":{"sum_foreign_comment":"","sum_comment":"","sum":"","sum_comment_hidden":false,"sum_foreign":""},"64":{"sum_foreign_comment":"","sum_comment":"","sum":"","sum_comment_hidden":false,"sum_foreign":""}},"ft_src":"2014\nPeugeot 2008 Allure\n1199 куб. см., 61 кВт\n1/4\n60.7\n40.2\n3140\n2015\n167035\n2420\nПортугалія\n100\n16158\n167035\nпенсія, субсидія\n16158\n2524\nПортугалія\n100\n1199 куб. см., 61 кВт\nPeugeot 2008 Allure\n2014\n2015\nБаргаміна\nБаргаміна Наталія Миколаївна\nНаталія Миколаївна Баргаміна\nНаталія Баргаміна\nБаргаміна Наталія Миколаївна\nНаталія\nМиколаївна\nБаргаміна Наталія Миколаївна\nАдміністративний місцевий суд\nсуддя чернігівського окружного адміністративного суду\nЧернігівська область\nБатьки\nБаргаміна В. О\nДитина\nКравченко Є. В\n684\nКреді Агріколь Банк індекс Банк\n75957\n167035\n2524\n100\nПортугалія\nпенсія, субсидія\n16158\n2420\n100\nПортугалія\n167035\n16158\n3140\n40.2\n60.7\n1/4\n684\nКреді Агріколь Банк індекс Банк\n75957\nБаргаміна В. О\nБатьки\nКравченко Є. В\nДитина\nМиколаївна\nБаргаміна\nсуддя чернігівського окружного адміністративного суду\nЧернігівська область\nАдміністративний місцевий суд\nБаргаміна Наталія Миколаївна\nБаргаміна Наталія Миколаївна\nНаталія Миколаївна Баргаміна\nНаталія Баргаміна\nБаргаміна Наталія Миколаївна\nНаталія","general":{"inn":"","inn_hidden":true,"last_name":"Баргаміна","post":{"post_unclear":false,"office":"Адміністративний місцевий суд","post":"суддя чернігівського окружного адміністративного суду","region":"Чернігівська область"},"name":"Наталія","full_name":"Баргаміна Наталія Миколаївна","family_raw":"","addresses":[{"place_district":"","place_address_hidden":true,"place_city":"","place_address":"","place_district_hidden":true,"place_city_type":"","place_city_hidden":true,"place_city_type_hidden":true,"place_hidden":true,"place":""}],"family":[{"inn":"","relations":"Батьки","name_hidden":true,"inn_hidden":true,"family_name":"Баргаміна В. О","name_unclear":false},{"inn":"","inn_hidden":false,"family_name":"Кравченко Є. В","relations_other":"","relations":"Дитина","name_unclear":false}],"full_name_suggest":{"output":"Баргаміна Наталія Миколаївна","input":["Баргаміна Наталія Миколаївна","Наталія Миколаївна Баргаміна","Наталія Баргаміна"]},"patronymic":"Миколаївна"},"source":"VULYK","estate":{"29":[{"costs_rent":"","region":"","costs_property":"","costs_rent_comment":"","address_hidden":true,"region_hidden":true,"space_comment":"","costs_property_comment":"","space_units":"м²","space":"3140","address":""}],"30":[{"costs_rent":"","region":"","costs_property":"","costs_rent_comment":"","address_hidden":true,"region_hidden":true,"space_comment":"","costs_property_comment":"","space_units":"м²","space":"40.2","address":""}],"31":[{"costs_rent":"","region":"","costs_property":"","costs_rent_comment":"","address_hidden":true,"region_hidden":true,"space_comment":"1/4","costs_property_comment":"","space_units":"м²","space":"60.7","address":""}]},"intro":{"declaration_year":"2015"}}