{"income":{"5":{"value":"204486.39","family_comment":"","family_hidden":false,"value_hidden":false,"family_unclear":false,"family":"27259.89","comment":""},"6":{"value":"204486.39","value_unclear":false,"comment_hidden":true,"family_hidden":false,"value_hidden":false,"family_comment":"","family_comment_hidden":false,"comment":"","family":""},"7":{"source_name_unclear":false,"value":"","family_comment":"","source_name":"","family":"","comment":"","source_name_hidden":false},"8":{"family_comment":"","value":"","comment_hidden":false,"family":"","comment":""},"9":{"value":"","family_hidden":false,"value_hidden":false,"family_comment":"","family":"","comment":""},"10":{"value":"","comment_hidden":false,"family_hidden":false,"value_hidden":false,"family_comment":"","family_comment_hidden":false,"comment":"","family":""},"11":{"family_comment":"","value":"","family_hidden":false,"comment":"","family":""},"12":{"family_comment":"","value":"","family_hidden":false,"comment":"","family":""},"13":{"family_comment":"","value":"","family":"","comment":""},"14":{"family_comment":"","value":"","family":"","comment":""},"15":{"value":"","comment_hidden":false,"family_comment":"","family":"","comment":"","family_comment_hidden":false},"16":{"family_comment":"","family_unclear":false,"value":"","family":"","comment":""},"17":{"family_comment":"","value":"","family":"","comment":""},"18":{"family_comment":"","value":"","family":"","comment":""},"19":{"family_comment":"","value":"","family":"","comment":""},"20":{"value":"","family_comment":"","comment_unclear":false,"family_hidden":false,"family_unclear":false,"family":"27259.89","comment":""}},"id":"vulyk_77_35","declaration":{"additional_info_text":"","notfull_lostpages":"","date":"2015-03-04T00:00:00","notfull":"","additional_info":"","url":"http://static.declarations.com.ua/declarations/chosen_ones/judges_batch/1944_hetman_vadym_volodymyrovych.pdf"},"liabilities":{"54":{"sum_foreign_comment":"","sum":"","sum_comment":"","sum_comment_unclear":false,"sum_foreign":""},"55":{"sum_foreign_comment":"","sum":"","sum_comment":"","sum_foreign":""},"56":{"sum_foreign_comment":"","sum":"","sum_comment":"","sum_unclear":false,"sum_foreign":""},"57":{"sum_foreign_comment":"","sum":"","sum_comment":"","sum_foreign":""},"58":{"sum_foreign_comment":"","sum":"","sum_comment":"","sum_foreign":""},"59":{"sum_foreign_comment":"","sum":"","sum_comment":"","sum_foreign":""},"60":{"sum_foreign_comment":"","sum":"","sum_comment":"","sum_foreign":""},"61":{"sum_foreign_comment":"","sum":"","sum_comment":"","sum_foreign":""},"62":{"sum_foreign_comment":"","sum":"","sum_hidden":false,"sum_comment":"","sum_foreign":""},"63":{"sum_foreign_comment":"","sum":"","sum_comment":"","sum_foreign":""},"64":{"sum_foreign_comment":"","sum":"","sum_comment":"","sum_foreign":""}},"ft_src":"суддя конотопського міськрайонного суду сумської області\nСумська область\nЗагальний місцевий суд\nВадим\nГетьман А. В\nПодружжя\nГетьман Б. В\nДитина\nГетьман К. В\nДитина\nВолодимирович\nГетьман Вадим Володимирович\nВадим Володимирович Гетьман\nВадим Гетьман\nГетьман Вадим Володимирович\nГетьман Вадим Володимирович\nГетьман\n27259.89\n204486.39\n27259.89\n204486.39\n2014\n204486.39\n27259.89\n204486.39\n27259.89\n204486.39\n27259.89\n204486.39\n27259.89\nГетьман Вадим Володимирович\nВадим Володимирович Гетьман\nВадим Гетьман\nГетьман Вадим Володимирович\nВадим\nПодружжя\nГетьман А. В\nДитина\nГетьман Б. В\nДитина\nГетьман К. В\nГетьман Вадим Володимирович\nГетьман\nЗагальний місцевий суд\nсуддя конотопського міськрайонного суду сумської області\nСумська область\nВолодимирович\n2014\nПодружжя\nГетьман А. В\nДитина\nГетьман Б. В\nДитина\nГетьман К. В\nВолодимирович\nГетьман\nВадим\nГетьман Вадим Володимирович\nВадим Володимирович Гетьман\nВадим Гетьман\nГетьман Вадим Володимирович\nсуддя конотопського міськрайонного суду сумської області\nСумська область\nЗагальний місцевий суд\nГетьман Вадим Володимирович\n2014","general":{"inn":"","name":"Вадим","inn_unclear":false,"family":[{"inn":"","relations":"Подружжя","inn_unclear":false,"relations_hidden":false,"inn_hidden":true,"relations_other":"","name_hidden":true,"family_name":"Гетьман А. В","name_unclear":false},{"inn":"","relations":"Дитина","relations_other":"","inn_hidden":false,"family_name":"Гетьман Б. В","name_hidden":false,"name_unclear":false},{"inn":"","relations":"Дитина","relations_other":"","inn_hidden":false,"family_name":"Гетьман К. В","name_hidden":false,"name_unclear":false}],"inn_hidden":true,"family_raw":"","last_name":"Гетьман","post":{"office":"Загальний місцевий суд","region":"Сумська область","post":"суддя конотопського міськрайонного суду сумської області"},"full_name_suggest":{"output":"Гетьман Вадим Володимирович","input":["Гетьман Вадим Володимирович","Вадим Володимирович Гетьман","Вадим Гетьман"]},"full_name":"Гетьман Вадим Володимирович","addresses":[{"place_city_type_hidden":false,"place_district_hidden":false,"place_city_type":"","place_city_hidden":false,"place_address_unclear":false,"place_address":"","place":"","place_district":"","place_unclear":false,"place_city":"","place_city_unclear":false,"place_hidden":true,"place_address_hidden":false,"place_district_unclear":false}],"patronymic":"Володимирович","last_name_unclear":false},"source":"VULYK","intro":{"declaration_year":"2014","isnotdeclaration":"","declaration_year_unclear":false}}