{"income":{"5":{"value":"255479","family_comment":"","value_unclear":false,"family_hidden":false,"value_hidden":false,"family_unclear":false,"family":"43571","comment":""},"6":{"value":"255479","value_unclear":false,"family_hidden":false,"value_hidden":false,"family_comment":"","comment_unclear":false,"comment":"","family":""},"7":{"value":"","value_hidden":false,"family_comment":"","source_name":"","family":"","comment":"","source_name_hidden":false},"8":{"family_comment":"","value":"","family":"","comment":""},"9":{"family_comment":"","value":"5","comment_unclear":false,"family":"","comment":""},"10":{"family_comment":"","value":"","value_unclear":false,"family":"","comment":""},"11":{"family_comment":"","value":"","family":"","comment":""},"12":{"family_comment":"","value":"","family":"","comment":""},"13":{"family_comment":"","value":"","family":"","comment":""},"14":{"family_comment":"","value":"","family":"","comment":""},"15":{"family_comment":"","value":"","family":"","comment":""},"16":{"family_comment":"","value":"","family":"","comment":""},"17":{"family_comment":"","value":"","family":"","comment":""},"18":{"family_comment":"","value":"","family":"","comment":""},"19":{"value":"","value_unclear":false,"comment_hidden":false,"family_hidden":false,"value_hidden":false,"family_comment":"","family_comment_hidden":false,"comment":"","family":""},"20":{"value":"","family_comment":"","value_unclear":false,"family_hidden":false,"value_hidden":false,"family_unclear":false,"comment_unclear":false,"comment":"","family":"43571"}},"vehicle":{"40":[{"brand_info":"1500 куб. см.","sum_rent_comment":"","brand":"","sum_comment":"","brand_unclear":false,"year":"2005","brand_hidden":true,"brand_info_unclear":false,"year_unclear":false,"sum":"","sum_rent":""}]},"id":"vulyk_65_88","declaration":{"additional_info_text":"","notfull_lostpages":"","date":"2015-03-30T00:00:00","notfull":"","additional_info":"","url":"http://static.declarations.com.ua/declarations/chosen_ones/mega_batch/litvinenko_tetiana_iakivna.pdf"},"liabilities":{"54":{"sum_foreign_comment":"","sum":"","sum_comment":"","sum_comment_unclear":false,"sum_hidden":false,"sum_comment_hidden":false,"sum_foreign":""},"55":{"sum_foreign_comment":"","sum":"","sum_comment":"","sum_foreign":""},"56":{"sum_foreign_comment":"","sum":"","sum_comment":"","sum_unclear":false,"sum_foreign":""},"57":{"sum_foreign_comment":"","sum":"","sum_comment":"","sum_comment_unclear":false,"sum_unclear":false,"sum_foreign":""},"58":{"sum_foreign_comment":"","sum":"","sum_comment":"","sum_comment_unclear":false,"sum_unclear":false,"sum_foreign":""},"59":{"sum_foreign_comment":"","sum":"","sum_comment":"","sum_foreign":""},"60":{"sum_foreign_comment":"","sum":"","sum_comment":"","sum_comment_unclear":false,"sum_foreign":""},"61":{"sum_foreign_comment":"","sum":"","sum_comment":"","sum_foreign":""},"62":{"sum_foreign_comment":"","sum":"","sum_comment":"","sum_foreign":""},"63":{"sum_foreign_comment":"","sum":"","sum_comment":"","sum_foreign":""},"64":{"sum_foreign_comment":"","sum":"","sum_comment":"","sum_unclear":false,"sum_foreign":""}},"ft_src":"Грушівка\nМиколаївська область\nПервомайський\nСело\nсуддя первомайського міськрайонного суду миколаївської області\nМиколаївська область\nЗагальний місцевий суд\nТетяна\nЧоловік 31. 03. 1960 р\nПодружжя\nЯківна\nЛітвіненко\nЛітвіненко Тетяна Яківна\nЛітвіненко Тетяна Яківна\nТетяна Яківна Літвіненко\nТетяна Літвіненко\nЛітвіненко Тетяна Яківна\n1500 куб. см.\n2005\nм. Первомайськ, ОКСП\n505\nМиколаївська область\nПервомайський р-н, с. Грушівка, вул. Крилова\nМиколаївська область\n207.4\nМиколаївська область\nПервомайський р-н, с. Грушівка, вул. Крилова\n1000\nМиколаївська область\nм. Первомайськ, вул. Рожева\n34\nм. Первомайськ, вул. Рожева\nМиколаївська область\n33.05\nВінницька область\nм. Вінниця, вул. Червоноармійська\n36.3\nм. Первомайськ\nМиколаївська область\n33.05\n2014\n255479\n43571\n255479\n5\n43571\n1500 куб. см.\n2005\n505\nМиколаївська область\nм. Первомайськ, ОКСП\n1000\nМиколаївська область\nПервомайський р-н, с. Грушівка, вул. Крилова\n34\nм. Первомайськ, вул. Рожева\nМиколаївська область\n207.4\nМиколаївська область\nПервомайський р-н, с. Грушівка, вул. Крилова\n33.05\nМиколаївська область\nм. Первомайськ, вул. Рожева\n36.3\nВінницька область\nм. Вінниця, вул. Червоноармійська\n33.05\nм. Первомайськ\nМиколаївська область\nЗагальний місцевий суд\nМиколаївська область\nсуддя первомайського міськрайонного суду миколаївської області\nЛітвіненко Тетяна Яківна\nТетяна Яківна Літвіненко\nТетяна Літвіненко\nЛітвіненко Тетяна Яківна\nТетяна\nПодружжя\nЧоловік 31. 03. 1960 р\nЛітвіненко Тетяна Яківна\nЛітвіненко\nЯківна\nСело\nМиколаївська область\nГрушівка\nПервомайський\n255479\n43571\n255479\n43571\n5\n2014\nЧоловік 31. 03. 1960 р\nПодружжя\nЯківна\nЛітвіненко\nТетяна\nЛітвіненко Тетяна Яківна\nТетяна Яківна Літвіненко\nТетяна Літвіненко\nЛітвіненко Тетяна Яківна\nСело\nГрушівка\nМиколаївська область\nПервомайський\nМиколаївська область\nЗагальний місцевий суд\nсуддя первомайського міськрайонного суду миколаївської області\nЛітвіненко Тетяна Яківна\n2005\n1500 куб. см.\n43571\n255479\n43571\n5\n255479\nм. Первомайськ, вул. Рожева\nМиколаївська область\n33.05\nПервомайський р-н, с. Грушівка, вул. Крилова\nМиколаївська область\n207.4\nМиколаївська область\nПервомайський р-н, с. Грушівка, вул. Крилова\n1000\nм. Первомайськ, вул. Рожева\nМиколаївська область\n34\n36.3\nВінницька область\nм. Вінниця, вул. Червоноармійська\nм. Первомайськ\nМиколаївська область\n33.05\nм. Первомайськ, ОКСП\nМиколаївська область\n505\n2014","general":{"name_hidden":false,"name":"Тетяна","last_name_hidden":false,"inn":"","family":[{"inn":"","inn_hidden":true,"inn_unclear":false,"relations_hidden":false,"relations_other":"","relations":"Подружжя","name_hidden":true,"family_name":"Чоловік 31. 03. 1960 р","name_unclear":false}],"patronymic":"Яківна","inn_hidden":true,"family_raw":"","inn_unclear":false,"post":{"post_unclear":false,"region_unclear":false,"post":"суддя первомайського міськрайонного суду миколаївської області","office":"Загальний місцевий суд","region":"Миколаївська область","post_hidden":false,"office_hidden":false,"office_unclear":false,"region_hidden":false},"last_name_unclear":false,"full_name":"Літвіненко Тетяна Яківна","addresses":[{"place_district":"Первомайський","place_address_hidden":true,"place_city":"Грушівка","place_city_type_hidden":false,"place_district_hidden":false,"place_city_type":"Село","place_city_hidden":false,"place_address_unclear":false,"place_address":"","place_hidden":false,"place":"Миколаївська область"}],"last_name":"Літвіненко","patronymic_hidden":false,"full_name_suggest":{"output":"Літвіненко Тетяна Яківна","input":["Літвіненко Тетяна Яківна","Тетяна Яківна Літвіненко","Тетяна Літвіненко"]},"name_unclear":false},"source":"VULYK","estate":{"23":[{"space_unclear":false,"costs":"","costs_comment":"","address_hidden":true,"region_hidden":false,"space_comment":"","space_hidden":false,"space":"505","address":"м. Первомайськ, ОКСП","region":"Миколаївська область","address_unclear":false,"costs_rent_comment":"","space_units":"м²","costs_rent":""}],"25":[{"space_unclear":false,"costs":"","costs_comment":"","address_hidden":true,"region_hidden":false,"space_comment":"","space_hidden":false,"space":"36.3","address":"м. Вінниця, вул. Червоноармійська","costs_rent_comment_unclear":false,"region":"Вінницька область","address_unclear":false,"costs_rent_comment":"","space_comment_unclear":false,"space_units":"м²","space_units_hidden":false,"costs_rent":""},{"space_hidden":false,"costs":"","costs_comment":"","address_hidden":false,"region_hidden":false,"space_comment":"","space_unclear":false,"space":"33.05","address":"м. Первомайськ","region":"Миколаївська область","costs_rent_comment":"","space_units":"м²","costs_rent":""}],"29":[{"space_unclear":false,"address_hidden":false,"region_hidden":false,"space_comment":"","space_units_hidden":false,"space":"1000","address":"Первомайський р-н, с. Грушівка, вул. Крилова","region":"Миколаївська область","address_unclear":false,"costs_rent_comment":"","costs_property":"","space_units":"м²","costs_property_comment":"","costs_rent":""},{"costs_rent":"","region":"Миколаївська область","costs_property":"","costs_rent_comment":"","address_hidden":false,"region_hidden":false,"space_comment":"","costs_property_comment":"","space_units":"м²","space":"34","address":"м. Первомайськ, вул. Рожева"}],"30":[{"address_hidden":false,"region_hidden":false,"space_comment":"","space":"207.4","address":"Первомайський р-н, с. Грушівка, вул. Крилова","region":"Миколаївська область","costs_property":"","costs_rent_comment":"","space_comment_unclear":false,"address_unclear":true,"space_units":"м²","costs_property_comment":"","costs_rent":""}],"31":[{"space_unclear":false,"address_hidden":false,"region_hidden":false,"space_comment":"","space":"33.05","address":"м. Первомайськ, вул. Рожева","region":"Миколаївська область","costs_property":"","costs_rent_comment":"","space_comment_unclear":false,"space_units":"м²","costs_property_comment":"","costs_rent":""}]},"intro":{"declaration_year":"2014","isnotdeclaration":"","declaration_year_hidden":false}}