{"income":{"5":{"family_comment":"","value":"183773","family":"","comment":""},"6":{"value":"183773","family_comment":"","value_unclear":false,"comment_hidden":false,"family_unclear":false,"family":"","comment":""},"7":{"family_comment":"","value":"","source_name":"","family":"","comment":""},"8":{"family_comment":"","value":"","family":"","comment":""},"9":{"family_comment":"","family_unclear":false,"value":"","family":"","comment":""},"10":{"family_comment":"","value":"","value_unclear":false,"family":"","comment":""},"11":{"family_comment":"","value":"","family":"","comment":""},"12":{"family_comment":"","value":"","family":"","comment":""},"13":{"family_comment":"","value":"","family":"","comment":""},"14":{"family_comment":"","value":"","family":"","comment":""},"15":{"family_comment":"","value":"","family":"","comment":""},"16":{"family_comment":"","value":"","family":"","comment":""},"17":{"family_comment":"","value":"","family":"","comment":""},"18":{"family_comment":"","value":"","family":"","comment":""},"19":{"family_comment":"","value":"","family":"","comment":""},"20":{"value":"","family":"","value_unclear":false,"family_hidden":false,"family_comment":"","comment_unclear":false,"comment":"","family_comment_unclear":false}},"id":"vulyk_97_110","declaration":{"additional_info_text":"","notfull_lostpages":"","date":"2015-03-26T00:00:00","notfull":"","additional_info":"","url":"http://static.declarations.com.ua/declarations/chosen_ones/judges_batch/4011_sahaidak_valerii_viktorovych.pdf"},"liabilities":{"54":{"sum_foreign_comment":"","sum":"","sum_comment":"","sum_comment_unclear":false,"sum_hidden":false,"sum_comment_hidden":false,"sum_unclear":false,"sum_foreign":""},"55":{"sum_foreign_comment":"","sum":"","sum_comment":"","sum_foreign":""},"56":{"sum_foreign_comment":"","sum":"","sum_comment":"","sum_foreign":""},"57":{"sum_foreign_comment":"","sum":"","sum_comment":"","sum_comment_unclear":false,"sum_hidden":false,"sum_comment_hidden":false,"sum_unclear":false,"sum_foreign":""},"58":{"sum_foreign_comment":"","sum":"","sum_comment":"","sum_comment_unclear":false,"sum_hidden":false,"sum_comment_hidden":false,"sum_unclear":false,"sum_foreign":""},"59":{"sum_foreign_comment":"","sum":"","sum_comment":"","sum_foreign":""},"60":{"sum_foreign_comment":"","sum":"","sum_comment":"","sum_comment_unclear":false,"sum_hidden":false,"sum_comment_hidden":false,"sum_foreign":""},"61":{"sum_foreign_comment":"","sum":"","sum_comment":"","sum_foreign":""},"62":{"sum_foreign_comment":"","sum":"","sum_comment":"","sum_unclear":false,"sum_foreign":""},"63":{"sum_foreign_comment":"","sum":"","sum_hidden":false,"sum_comment":"","sum_foreign":""},"64":{"sum_foreign_comment":"","sum":"","sum_comment":"","sum_foreign":""}},"ft_src":"Харків\n61124\nХарківська область\nсуддя харківського окружного адміністративного суду\nХарківська область\nАдміністративний місцевий суд\nВалерій\nВікторович\nСагайдак Валерій Вікторович\nВалерій Вікторович Сагайдак\nВалерій Сагайдак\nСагайдак Валерій Вікторович\nСагайдак Валерій Вікторович\nСагайдак\n183773\n183773\n75\nм. Харків\nХарківська область\n2014\n183773\n183773\n75\nм. Харків\nХарківська область\nАдміністративний місцевий суд\nХарківська область\nсуддя харківського окружного адміністративного суду\nСагайдак Валерій Вікторович\nВалерій Вікторович Сагайдак\nВалерій Сагайдак\nСагайдак Валерій Вікторович\nСагайдак Валерій Вікторович\nВалерій\nСагайдак\nВікторович\nХарківська область\n61124\nХарків\n183773\n183773\n2014\nВікторович\nСагайдак\nВалерій\nСагайдак Валерій Вікторович\nВалерій Вікторович Сагайдак\nВалерій Сагайдак\nСагайдак Валерій Вікторович\n61124\nХарків\nХарківська область\nХарківська область\nАдміністративний місцевий суд\nсуддя харківського окружного адміністративного суду\nСагайдак Валерій Вікторович\nм. Харків\nХарківська область\n75\n2014","general":{"name_hidden":false,"name":"Валерій","last_name_hidden":false,"inn":"","last_name":"Сагайдак","patronymic":"Вікторович","inn_hidden":true,"family_raw":"","inn_unclear":false,"post":{"region_unclear":false,"region":"Харківська область","post":"суддя харківського окружного адміністративного суду","office":"Адміністративний місцевий суд","office_unclear":false,"post_hidden":false},"full_name":"Сагайдак Валерій Вікторович","addresses":[{"place_district":"","place_city_hidden":false,"place_city":"Харків","place_city_unclear":false,"place_district_hidden":false,"place_city_type":"Місто","place_address_hidden":true,"place_city_type_hidden":false,"place_address":"61124","place_hidden":false,"place":"Харківська область"}],"patronymic_hidden":false,"full_name_suggest":{"output":"Сагайдак Валерій Вікторович","input":["Сагайдак Валерій Вікторович","Валерій Вікторович Сагайдак","Валерій Сагайдак"]}},"source":"VULYK","estate":{"25":[{"region_unclear":false,"space_unclear":false,"costs":"","costs_comment":"","address_hidden":true,"region_hidden":false,"space_comment":"","space_hidden":false,"space":"75","address":"м. Харків","region":"Харківська область","costs_rent_comment":"","space_comment_unclear":false,"space_comment_hidden":false,"space_units":"м²","costs_rent":""}]},"intro":{"declaration_year":"2014","isnotdeclaration":""}}