{"id":"vulyk_103_36","ft_src":"Mitsubishi Pajero\n3\n2007\n2001\nбез держ. реєстрації\n21.7\n1200\nнезавершене будівництво, одноповерхова дерев'яна коробка без вікон і двірей з огорожею\nмашиномісце\n13.1\nтрансформаторна підстанція КТП 10/04 Кв\n1/2\n17.85\n1/2\n40.95\n1/2\n61.5\n1/2\n61.5\n1/2\n40.95\n3651\n2943\n2015\n3\n2007\nMitsubishi Pajero\nнезавершене будівництво, одноповерхова дерев'яна коробка без вікон і двірей з огорожею\n21.7\nбез держ. реєстрації\n61.5\n1/2\n40.95\n1/2\n1200\n2001\n1/2\n17.85\n40.95\n1/2\n61.5\n1/2\n13.1\nмашиномісце\nтрансформаторна підстанція КТП 10/04 Кв\nКоротун\nКоротун Вадим Михайлович\nВадим Михайлович Коротун\nВадим Коротун\nКоротун Вадим Михайлович\nКоротун Вадим Михайлович\nМихайлович\nПодружжя\nКоротун О. М\nКоротун М. В\nДитина\nДитина\nКоротун В. В\nВадим\nВищий спеціалізований суд з розгляду цивільних і кримінальних справ\nсуддя вссу з розгляду цивiльних і кримiнальних справ\nЗагальнодержавний регіон\n15692\n283173\n227835\nв т. ч. допомога на дитину 5200\n27322\n895\nІталія\n22122\nне зазначено\nOTHER\n1000\n1000\n632023\n289849\n347850\n18000\n2943\n3651\n2015\n227835\n283173\n1000\n1000\n15692\n289849\n632023\n347850\n18000\nв т. ч. допомога на дитину 5200\n27322\nІталія\n895\nOTHER\n22122\nне зазначено\nПодружжя\nКоротун О. М\nДитина\nКоротун М. В\nДитина\nКоротун В. В\nКоротун\nМихайлович\nсуддя вссу з розгляду цивiльних і кримiнальних справ\nВищий спеціалізований суд з розгляду цивільних і кримінальних справ\nЗагальнодержавний регіон\nКоротун Вадим Михайлович\nКоротун Вадим Михайлович\nВадим Михайлович Коротун\nВадим Коротун\nКоротун Вадим Михайлович\nВадим","estate":{"23":[{"costs":"","address":"","space_units":"м²","costs_rent_comment":"","space":"1200","space_comment":"","region_hidden":true,"costs_comment":"","region":"","address_hidden":false,"costs_rent":""}],"25":[{"address":"","space_units":"м²","costs_comment":"","region_hidden":true,"space_comment":"1/2","address_hidden":false,"space_comment_hidden":false,"space":"61.5","space_comment_unclear":false,"costs_rent_comment":"","costs":"","region":"","costs_rent":""},{"costs":"","address":"","space_units":"м²","costs_rent_comment":"","space":"40.95","space_comment":"1/2","region_hidden":false,"costs_comment":"","region":"","costs_rent":""}],"28":[{"address":"","space_units":"м²","space_hidden":false,"space_unclear":false,"region_hidden":true,"costs_comment":"","space_comment":"без держ. реєстрації","address_hidden":false,"space":"21.7","costs_rent_comment":"","costs":"","region":"","costs_rent":""}],"29":[{"costs_property_comment":"","address":"","space_units":"м²","space_hidden":false,"space_comment":"","region_hidden":true,"costs_property":"","region":"","address_hidden":true,"costs_rent_comment":"","space":"2001","costs_rent":""}],"30":[{"costs_property_comment":"","address":"незавершене будівництво, одноповерхова дерев'яна коробка без вікон і двірей з огорожею","space_units":"м²","space_hidden":true,"space_unclear":false,"region_hidden":true,"costs_property":"","space_comment":"","address_hidden":true,"costs_rent_comment":"","space":"","costs_rent":""}],"31":[{"costs_property_comment":"","address":"","space_units":"м²","space_hidden":false,"region_hidden":true,"costs_property":"","space_comment":"1/2","address_hidden":true,"address_unclear":false,"costs_rent_comment":"","space":"17.85","costs_rent":""},{"address_hidden":true,"costs_property_comment":"","address":"","space_units":"м²","costs_rent_comment":"","space_hidden":false,"costs_property":"","space_comment":"1/2","space":"40.95","space_comment_unclear":false,"costs_rent":""},{"costs_property_comment":"","address":"","space_units":"м²","costs_rent_comment":"","space_hidden":false,"costs_property":"","space_comment":"1/2","space":"61.5","space_comment_unclear":false,"costs_rent":""}],"34":[{"costs_property_comment":"","address":"","space_units":"м²","costs_rent_comment":"","space_hidden":false,"region_hidden":true,"costs_property":"","space_comment":"машиномісце","space":"13.1","address_hidden":true,"costs_rent":""},{"costs_property_comment":"","address":"","space_units":"","costs_rent_comment":"","space":"","costs_property":"","space_comment":"трансформаторна підстанція КТП 10/04 Кв","costs_rent":""}]},"vehicle":{"35":[{"sum_comment":"","brand_info_hidden":false,"brand_info":"3","sum":"","brand_unclear":false,"brand_hidden":false,"brand":"Mitsubishi Pajero","sum_rent":"","brand_info_unclear":false,"sum_rent_comment":"","year":"2007"}]},"source":"VULYK","income":{"5":{"family_comment":"","family":"289849","comment":"","value_unclear":false,"family_hidden":false,"value":"632023"},"6":{"family_comment":"","value":"283173","family":"227835","comment":""},"7":{"family":"15692","family_comment":"","value":"","comment":"","source_name":""},"8":{"family_comment":"","value":"","family":"","comment":""},"9":{"family_comment":"","value":"","family":"","comment":""},"10":{"family_comment":"","value":"","family":"","comment":""},"11":{"family_comment":"","family_hidden":false,"value":"","family":"","comment":""},"12":{"family_comment":"","value":"","family":"","comment":""},"13":{"family_comment":"","value":"","family":"","comment":""},"14":{"family_comment":"","value":"","family":"","comment":""},"15":{"family_comment":"","value":"","family":"","comment":""},"16":{"family_comment":"","value":"347850","family":"","comment":""},"17":{"family_comment":"","value":"","family":"","comment":"","family_comment_unclear":false},"18":{"family_comment":"","value":"1000","family":"1000","comment":""},"19":{"family_comment":"","value":"","family":"18000","comment":""},"20":{"family_comment":"в т. ч. допомога на дитину 5200","family":"27322","comment":"","family_unclear":false,"family_hidden":false,"value":""},"22":[{"country_comment":"","uah_equal":"22122","cur":"895","cur_units":"OTHER","country":"Італія","cur_units_other":"не зазначено"}]},"banks":{"45":[{"sum_units":"UAH","sum_comment":"","sum_foreign_units":"UAH","sum_hidden":false,"sum":"2943","sum_foreign_comment":"","sum_foreign":"","sum_unclear":false,"sum_comment_hidden":true}],"51":[{"sum_units":"UAH","sum_comment":"","sum_foreign_units":"UAH","sum_hidden":false,"sum":"3651","sum_foreign_comment_hidden":false,"sum_foreign_comment":"","sum_foreign":"","sum_foreign_hidden":false,"sum_comment_hidden":true}]},"declaration":{"additional_info_text":"","additional_info":"","date":"2016-03-31T00:00:00","url":"http://static.declarations.com.ua/declarations/chosen_ones/judges_batch/1260_korotun_vadym_mykhailovych.pdf"},"general":{"inn":"","addresses":[{"place_city_type_hidden":false,"place_city_type":"","place_city_hidden":true,"place_hidden":true,"place_district":"","place_district_hidden":false,"place":"","place_city":"","place_address_hidden":true,"place_address":""}],"last_name":"Коротун","full_name":"Коротун Вадим Михайлович","family":[{"inn":"","family_name":"Коротун О. М","relations_hidden":false,"name_unclear":false,"relations":"Подружжя","inn_hidden":true,"name_hidden":true,"relations_other":""},{"inn":"","family_name":"Коротун М. В","inn_hidden":true,"relations_other":"","relations":"Дитина"},{"inn":"","family_name":"Коротун В. В","relations_other":"","name_unclear":false,"inn_hidden":false,"relations":"Дитина"}],"patronymic":"Михайлович","inn_hidden":true,"name":"Вадим","post":{"office":"Вищий спеціалізований суд з розгляду цивільних і кримінальних справ","region_unclear":false,"post":"суддя вссу з розгляду цивiльних і кримiнальних справ","region":"Загальнодержавний регіон","office_unclear":false},"family_raw":"","full_name_suggest":{"input":["Коротун Вадим Михайлович","Вадим Михайлович Коротун","Вадим Коротун"],"output":"Коротун Вадим Михайлович"}},"liabilities":{"54":{"sum_foreign_comment_hidden":false,"sum_foreign_comment_unclear":false,"sum_hidden":false,"sum":"","sum_foreign_comment":"","sum_comment":"","sum_unclear":false,"sum_foreign":"","sum_comment_hidden":false,"sum_foreign_hidden":false},"55":{"sum_comment":"","sum_foreign_comment":"","sum_foreign":"","sum":""},"56":{"sum_comment":"","sum_foreign_comment":"","sum_foreign":"","sum":""},"57":{"sum_comment":"","sum_hidden":false,"sum":"","sum_foreign_comment":"","sum_foreign":"","sum_comment_hidden":false,"sum_foreign_hidden":false,"sum_foreign_comment_hidden":false},"58":{"sum_comment":"","sum_hidden":false,"sum":"","sum_foreign_comment":"","sum_foreign":"","sum_comment_hidden":false,"sum_foreign_hidden":false,"sum_foreign_comment_hidden":false},"59":{"sum_comment":"","sum_hidden":false,"sum":"","sum_foreign_comment":"","sum_foreign":"","sum_comment_hidden":false,"sum_foreign_hidden":false,"sum_foreign_comment_hidden":false},"60":{"sum_comment":"","sum_hidden":false,"sum":"","sum_foreign_comment":"","sum_foreign":"","sum_comment_hidden":false},"61":{"sum_comment":"","sum_foreign_comment":"","sum_foreign":"","sum":""},"62":{"sum_comment":"","sum_foreign_comment":"","sum_foreign":"","sum":"","sum_comment_hidden":false},"63":{"sum_comment":"","sum_foreign_comment":"","sum_foreign":"","sum":""},"64":{"sum_comment":"","sum_foreign_comment":"","sum_foreign":"","sum":""}},"intro":{"declaration_year":"2015"}}