{"income":{"5":{"value":"311595","value_unclear":false,"family_hidden":false,"family_comment":"","family":"","comment":""},"6":{"family_comment":"","value":"311595","family":"","comment":""},"7":{"family_comment":"","value":"","source_name":"","family":"","comment":""},"8":{"family_comment":"","value":"","family":"","comment":""},"9":{"family_comment":"","value":"","family":"","comment":""},"10":{"family_comment":"","value":"","family":"","comment":""},"11":{"family_comment":"","value":"","family_hidden":false,"comment":"","family":""},"12":{"family_comment":"","value":"","family":"","comment":""},"13":{"family_comment":"","value":"","family":"","comment":""},"14":{"family_comment":"","value":"","family":"","comment":""},"15":{"family_comment":"","value":"","family":"","comment":""},"16":{"family_comment":"","value":"","family":"","comment":""},"17":{"family_comment":"","value":"","family":"","comment":"","family_comment_unclear":false},"18":{"family_comment":"","value":"","family":"","comment":""},"19":{"family_comment":"","value":"","family":"","comment":""},"20":{"value":"","family_unclear":false,"family_hidden":false,"family_comment":"","family":"","comment":""}},"vehicle":{"35":[{"brand_info":"3000 куб. см., 225 кВт","sum":"","brand":"Volkswagen Touareg","sum_comment":"","brand_unclear":false,"year":"2007","brand_hidden":false,"brand_info_hidden":false,"brand_info_unclear":false,"sum_rent_comment":"","sum_rent":""},{"brand_info":"1800 куб. см., 80 кВт","sum_rent_comment":"","brand":"Opel","sum_comment":"","year":"2002","sum":"","sum_rent":""},{"brand_info":"1600 куб. см., 70 кВт","sum_rent_comment":"","brand":"ВАЗ 2121 Нива","sum_comment":"","year":"1991","sum":"","sum_rent":""}]},"id":"vulyk_103_111","declaration":{"date":"2016-03-11T00:00:00","additional_info_text":"","additional_info":"","url":"http://static.declarations.com.ua/declarations/chosen_ones/judges_batch/1066_sas_serhii_volodymyrovych.pdf"},"liabilities":{"54":{"sum_foreign_comment":"","sum_foreign_hidden":false,"sum_comment":"","sum_foreign_comment_hidden":false,"sum_hidden":false,"sum_foreign_comment_unclear":false,"sum_comment_hidden":false,"sum_unclear":false,"sum":"","sum_foreign":""},"55":{"sum_foreign_comment":"","sum":"","sum_comment":"","sum_foreign":""},"56":{"sum_foreign_comment":"","sum":"","sum_comment":"","sum_foreign":""},"57":{"sum_foreign_comment":"","sum_foreign_hidden":false,"sum_comment":"","sum_foreign_comment_hidden":false,"sum_hidden":false,"sum_comment_hidden":false,"sum":"","sum_foreign":""},"58":{"sum_foreign_comment":"","sum_foreign_hidden":false,"sum_comment":"","sum_foreign_comment_hidden":false,"sum_hidden":false,"sum_comment_hidden":false,"sum":"","sum_foreign":""},"59":{"sum_foreign_comment":"","sum_foreign_hidden":false,"sum_comment":"","sum_foreign_comment_hidden":false,"sum_hidden":false,"sum_comment_hidden":false,"sum":"","sum_foreign":""},"60":{"sum_foreign_comment":"","sum":"","sum_comment":"","sum_hidden":false,"sum_comment_hidden":false,"sum_foreign":""},"61":{"sum_foreign_comment":"","sum":"","sum_comment":"","sum_foreign":""},"62":{"sum_foreign_comment":"","sum_comment_hidden":false,"sum":"","sum_comment":"","sum_foreign":""},"63":{"sum_foreign_comment":"","sum":"","sum_comment":"","sum_foreign":""},"64":{"sum_foreign_comment":"","sum":"","sum_comment":"","sum_foreign":""}},"ft_src":"Сас Сергій Володимирович\nсуддя конституційного суду україни\nЗагальнодержавний регіон\nКонституційний Cуд\nСергій\nСас Г. Л\nПодружжя\nСас Сергій Володимирович\nСергій Володимирович Сас\nСергій Сас\nСас Сергій Володимирович\nСас\nВолодимирович\nVolkswagen Touareg\n3000 куб. см., 225 кВт\n2007\n1800 куб. см., 80 кВт\n2002\nOpel\n1600 куб. см., 70 кВт\n1991\nВАЗ 2121 Нива\n18\nКіровоградська область\n25300\n100\n18\n28900\nКіровоградська область\nКіровоградська область\n18250\n1200\nКиївська область\n1000\nКиївська область\n20.8\n17.75\n17.75\n111.2\n2015\n311595\n311595\n3000 куб. см., 225 кВт\n2007\nVolkswagen Touareg\n1800 куб. см., 80 кВт\n2002\nOpel\n1600 куб. см., 70 кВт\n1991\nВАЗ 2121 Нива\n18\n18\n17.75\n111.2\n28900\nКіровоградська область\n18250\nКіровоградська область\n1200\nКиївська область\n1000\nКиївська область\nКіровоградська область\n25300\n100\n17.75\n20.8\nСас\nСас Сергій Володимирович\nСергій Володимирович Сас\nСергій Сас\nСас Сергій Володимирович\nСас Сергій Володимирович\nВолодимирович\nПодружжя\nСас Г. Л\nСергій\nКонституційний Cуд\nсуддя конституційного суду україни\nЗагальнодержавний регіон\n311595\n311595\n2015\nПодружжя\nСас Г. Л\nСас\nВолодимирович\nсуддя конституційного суду україни\nКонституційний Cуд\nЗагальнодержавний регіон\nСас Сергій Володимирович\nСас Сергій Володимирович\nСергій Володимирович Сас\nСергій Сас\nСас Сергій Володимирович\nСергій\nVolkswagen Touareg\n3000 куб. см., 225 кВт\n2007\nOpel\n1800 куб. см., 80 кВт\n2002\nВАЗ 2121 Нива\n1600 куб. см., 70 кВт\n1991\n311595\n311595\n17.75\nКіровоградська область\n28900\nКіровоградська область\n18250\nКиївська область\n1200\nКиївська область\n1000\n100\n20.8\n18\n18\n17.75\n111.2\nКіровоградська область\n25300\n2015","general":{"inn":"","inn_hidden":true,"last_name":"Сас","post":{"region":"Загальнодержавний регіон","region_unclear":false,"post":"суддя конституційного суду україни","office_unclear":false,"office":"Конституційний Cуд"},"name":"Сергій","full_name":"Сас Сергій Володимирович","family_raw":"","addresses":[{"place_district":"","place_city_hidden":true,"place_city":"","place_city_type_hidden":false,"place_district_hidden":false,"place_city_type":"","place_address_hidden":true,"place_address":"","place_hidden":true,"place":""}],"family":[{"inn":"","relations":"Подружжя","relations_hidden":false,"inn_hidden":true,"relations_other":"","name_hidden":true,"family_name":"Сас Г. Л","name_unclear":false}],"full_name_suggest":{"output":"Сас Сергій Володимирович","input":["Сас Сергій Володимирович","Сергій Володимирович Сас","Сергій Сас"]},"patronymic":"Володимирович"},"source":"VULYK","estate":{"23":[{"costs_rent":"","region":"Кіровоградська область","costs":"","costs_rent_comment":"","costs_comment":"","address_hidden":true,"region_hidden":false,"space_comment":"","space_units":"м²","space":"28900","address":""},{"space":"18250","region":"Кіровоградська область","costs":"","costs_rent_comment":"","costs_comment":"","space_comment_unclear":false,"region_hidden":false,"space_comment":"","space_units":"м²","costs_rent":"","address":""},{"costs_rent":"","region":"Київська область","costs":"","costs_rent_comment":"","costs_comment":"","space_comment":"","space_units":"м²","space":"1200","address":""},{"costs_rent":"","region":"Київська область","costs":"","costs_rent_comment":"","costs_comment":"","space_comment":"","space_units":"м²","space":"1000","address":""}],"24":[{"space_hidden":false,"costs":"","costs_comment":"","address_hidden":false,"region_hidden":true,"space_comment":"","space_unclear":false,"space":"100","address":"","region":"","costs_rent_comment":"","space_units":"м²","costs_rent":""}],"25":[{"costs":"","costs_comment":"","address_hidden":false,"region_hidden":true,"space_comment":"","space":"17.75","address":"","region":"","costs_rent_comment":"","space_comment_unclear":false,"space_comment_hidden":false,"space_units":"м²","costs_rent":""},{"costs_rent":"","region":"","costs":"","costs_rent_comment":"","costs_comment":"","region_hidden":false,"space_comment":"","space_units":"м²","space":"111.2","address":""}],"27":[{"costs_rent":"","region":"","costs":"","costs_rent_comment":"","costs_comment":"","address_hidden":false,"region_hidden":true,"space_comment":"","space_units":"м²","space":"18","address":""}],"28":[{"space_hidden":false,"costs":"","costs_comment":"","address_hidden":false,"region_hidden":true,"space_comment":"","space_unclear":false,"space":"18","address":"","region":"","costs_rent_comment":"","space_units":"м²","costs_rent":""}],"29":[{"space_hidden":false,"address_hidden":true,"region_hidden":false,"space_comment":"","space":"25300","address":"","region":"Кіровоградська область","costs_property":"","costs_rent_comment":"","space_units":"м²","costs_property_comment":"","costs_rent":""}],"31":[{"space_hidden":false,"address_hidden":true,"region_hidden":true,"space_comment":"","space":"17.75","address":"","costs_property":"","costs_rent_comment":"","address_unclear":false,"space_units":"м²","costs_property_comment":"","costs_rent":""}],"34":[{"costs_rent":"","space_hidden":false,"costs_property":"","costs_rent_comment":"","address_hidden":true,"region_hidden":true,"space_comment":"","costs_property_comment":"","space_units":"м²","space":"20.8","address":""}]},"intro":{"declaration_year":"2015"}}