{"income":{"5":{"value":"185011","family_comment":"","value_unclear":false,"family_hidden":false,"value_hidden":false,"family_unclear":false,"family":"97964","comment":""},"6":{"value":"178498","family_comment":"","value_unclear":false,"family_hidden":false,"family_unclear":false,"family":"88043","comment":""},"7":{"value":"","family_hidden":false,"value_hidden":false,"family_comment":"","source_name":"","family":"","comment":"","source_name_hidden":false},"8":{"value":"","family_hidden":false,"value_hidden":false,"family_comment":"","family":"","comment":""},"9":{"value":"6573","family_hidden":false,"value_hidden":false,"family_comment":"","family":"9921","comment":"за депозитними рахунками"},"10":{"value":"","family_comment":"","value_unclear":false,"family_hidden":false,"value_hidden":false,"family_unclear":false,"family_comment_hidden":false,"comment":"","family":""},"11":{"value":"","comment_hidden":false,"family_hidden":false,"value_hidden":false,"family_comment":"","family_comment_hidden":false,"comment":"67/100 часток за договором дарування","family":""},"12":{"value":"","comment_hidden":false,"family_hidden":false,"value_hidden":false,"family_comment":"","family_comment_hidden":false,"comment":"","family":""},"13":{"value":"","comment_hidden":false,"family_hidden":false,"value_hidden":false,"family_comment":"","family_comment_hidden":false,"comment":"","family":""},"14":{"value":"","comment_unclear":false,"comment_hidden":false,"family_hidden":false,"value_hidden":false,"family_comment":"","family":"","comment":"","family_comment_hidden":false},"15":{"value":"","comment_hidden":false,"family_hidden":false,"value_hidden":false,"family_comment":"","family_comment_hidden":false,"comment":"","family":""},"16":{"value":"","comment_hidden":false,"family_hidden":false,"value_hidden":false,"family_comment":"","family_comment_hidden":false,"comment":"","family":""},"17":{"value":"","comment_hidden":false,"family_hidden":false,"value_hidden":false,"family_comment":"","family_comment_hidden":false,"comment":"","family":""},"18":{"value":"","comment_hidden":false,"family_hidden":false,"value_hidden":false,"family_comment":"","family_comment_hidden":false,"comment":"","family":""},"19":{"value":"","comment_hidden":false,"family_hidden":false,"value_hidden":false,"family_comment":"","family_comment_hidden":false,"comment":"","family":""},"20":{"value":"","value_unclear":false,"comment_hidden":false,"family_hidden":false,"value_hidden":false,"family_comment":"","family_comment_hidden":false,"comment":"","family":""}},"vehicle":{"35":[{"year_hidden":false,"brand_info":"1984 куб. см., 225 к. с., 463 см","sum_rent_comment":"","brand_info_unclear":false,"year":"2013","sum_hidden":false,"sum_rent_comment_unclear":false,"year_unclear":false,"sum_rent":"","sum":"","brand":"Audi Q5","sum_comment":"","brand_unclear":false,"brand_hidden":false,"sum_unclear":false}],"40":[{"brand_info":"1596 куб. см., 102 к. с., 431 см","sum":"","brand":"Audi A3 sportback","sum_comment":"","brand_unclear":false,"year":"2007","brand_hidden":false,"brand_info_hidden":false,"brand_info_unclear":false,"sum_rent_comment":"","sum_rent":""}]},"id":"vulyk_15_191","banks":{"45":[{"sum_foreign_comment":"","sum_units":"UAH","sum_comment":"","sum_comment_unclear":false,"sum_hidden":false,"sum_foreign_units":"UAH","sum":"","sum_unclear":false,"sum_foreign":""},{"sum_foreign_comment":"","sum_units":"","sum_comment":"","sum_foreign_units":"","sum":"","sum_foreign":""}],"46":[{"sum_foreign_comment":"","sum_units":"UAH","sum_comment":"","sum_hidden":false,"sum_foreign_units":"UAH","sum":"","sum_foreign":""}],"47":[{"sum_foreign_comment":"","sum_units":"UAH","sum_comment":"","sum_foreign_units":"UAH","sum":"","sum_foreign":""}],"48":[{"sum_foreign_comment":"","sum_units":"UAH","sum_comment":"","sum_foreign_units":"UAH","sum":"","sum_foreign":""}],"49":[{"sum_foreign_comment":"","sum_units":"UAH","sum_comment":"","sum_foreign_units":"UAH","sum":"","sum_foreign":""}],"50":[{"sum_foreign_comment":"","sum_units":"UAH","sum_comment":"","sum_foreign_units":"UAH","sum":"","sum_foreign":""}],"51":[{"sum_foreign_comment":"","sum_units":"UAH","sum_comment":"","sum_hidden":false,"sum_foreign_units":"UAH","sum":"","sum_foreign":""},{"sum_foreign_comment":"","sum_units":"","sum_comment":"","sum_foreign_units":"","sum":"","sum_unclear":false,"sum_foreign":""}],"52":[{"sum_foreign_comment":"","sum_units":"UAH","sum_comment":"","sum_foreign_units":"UAH","sum":"","sum_foreign":""}],"53":[{"sum_foreign_comment":"","sum_units":"UAH","sum_comment":"","sum_foreign_units":"UAH","sum":"","sum_foreign":""}]},"declaration":{"additional_info_text":"","notfull_lostpages":"","date":"2015-03-31T00:00:00","notfull":"","additional_info":"","url":"http://static.declarations.com.ua/declarations/chosen_ones/mega_batch/ovsiannikov_vladyslav_serhiiovych.pdf"},"liabilities":{"54":{"sum_foreign_comment":"","sum":"","sum_comment":"","sum_foreign":""},"55":{"sum_foreign_comment":"","sum":"","sum_comment":"","sum_foreign":""},"56":{"sum_foreign_comment":"","sum":"","sum_comment":"","sum_comment_unclear":false,"sum_foreign":""},"57":{"sum_foreign_comment":"","sum":"","sum_comment":"","sum_foreign":""},"58":{"sum_foreign_comment":"","sum":"","sum_comment":"","sum_unclear":false,"sum_foreign":""},"59":{"sum_foreign_comment":"","sum":"","sum_comment":"","sum_foreign":""},"60":{"sum_foreign_comment":"","sum":"","sum_comment":"","sum_comment_unclear":false,"sum_foreign":""},"61":{"sum_foreign_comment":"","sum":"","sum_comment":"","sum_foreign":""},"62":{"sum_foreign_comment":"","sum":"","sum_comment":"","sum_foreign":""},"63":{"sum_foreign_comment":"","sum":"","sum_comment":"","sum_foreign":""},"64":{"sum_foreign_comment":"","sum":"","sum_comment":"","sum_unclear":false,"sum_foreign":""}},"ft_src":"суддя дергачівського районного суду харківської області\nХарківська область\nЗагальний місцевий суд\nВладислав\nОвсяннікова О. О\nПодружжя\nОвсянніков І. В\nДитина\nСергійович\nОвсянніков Владислав Сергійович\nВладислав Сергійович Овсянніков\nВладислав Овсянніков\nОвсянніков Владислав Сергійович\nОвсянніков Владислав Сергійович\nОвсянніков\n1984 куб. см., 225 к. с., 463 см\nAudi Q5\n2013\nAudi A3 sportback\n1596 куб. см., 102 к. с., 431 см\n2007\n2014\n1984 куб. см., 225 к. с., 463 см\nAudi Q5\n2013\nAudi A3 sportback\n1596 куб. см., 102 к. с., 431 см\n2007\n32.4\n139.6\n98.2\n67\n67/100 частина за договором дарування\n.1\n139.6\n1/2 частина\n25.6\n1/2 частина\nОвсянніков Владислав Сергійович\nВладислав Сергійович Овсянніков\nВладислав Овсянніков\nОвсянніков Владислав Сергійович\nОвсянніков Владислав Сергійович\nПодружжя\nОвсяннікова О. О\nДитина\nОвсянніков І. В\nВладислав\nСергійович\nЗагальний місцевий суд\nХарківська область\nсуддя дергачівського районного суду харківської області\nОвсянніков\n88043\n178498\n185011\n97964\n67/100 часток за договором дарування\nза депозитними рахунками\n6573\n9921\n2014\n.1\n32.4\n1/2 частина\n25.6\n1/2 частина\n139.6\n139.6\n98.2\n67/100 частина за договором дарування\n67\nОвсяннікова О. О\nПодружжя\nОвсянніков І. В\nДитина\nСергійович\nОвсянніков\nВладислав\nОвсянніков Владислав Сергійович\nВладислав Сергійович Овсянніков\nВладислав Овсянніков\nОвсянніков Владислав Сергійович\nХарківська область\nЗагальний місцевий суд\nсуддя дергачівського районного суду харківської області\nОвсянніков Владислав Сергійович\n88043\n178498\n67/100 часток за договором дарування\n97964\n185011\n9921\nза депозитними рахунками\n6573\n2013\nAudi Q5\n1984 куб. см., 225 к. с., 463 см\nAudi A3 sportback\n1596 куб. см., 102 к. с., 431 см\n2007\n67/100 часток за договором дарування\n185011\n97964\n6573\n9921\nза депозитними рахунками\n178498\n88043\n1/2 частина\n139.6\n139.6\n98.2\n67/100 частина за договором дарування\n67\n32.4\n1/2 частина\n25.6\n.1\n2014","general":{"inn":"","name":"Владислав","patronymic_unclear":false,"family":[{"inn":"","inn_hidden":false,"relations_unclear":false,"relations_hidden":false,"relations_other":"","relations":"Подружжя","name_hidden":false,"family_name":"Овсяннікова О. О","name_unclear":false},{"inn":"","relations":"Дитина","relations_other":"","inn_hidden":false,"family_name":"Овсянніков І. В","name_hidden":false,"name_unclear":false}],"patronymic":"Сергійович","inn_hidden":false,"family_raw":"","inn_unclear":false,"post":{"post_unclear":false,"region_unclear":false,"post":"суддя дергачівського районного суду харківської області","office":"Загальний місцевий суд","region":"Харківська область","post_hidden":false,"office_hidden":false,"office_unclear":false,"region_hidden":false},"full_name_suggest":{"output":"Овсянніков Владислав Сергійович","input":["Овсянніков Владислав Сергійович","Владислав Сергійович Овсянніков","Владислав Овсянніков"]},"full_name":"Овсянніков Владислав Сергійович","last_name":"Овсянніков","last_name_unclear":false,"name_unclear":false},"source":"VULYK","estate":{"23":[{"space_unclear":false,"costs":"","costs_comment":"","costs_hidden":false,"address_hidden":false,"region_hidden":false,"space_comment":"","space":"","address":"","region":"","address_unclear":false,"costs_rent_comment":"","costs_rent_hidden":false,"space_comment_unclear":false,"space_units":"м²","costs_rent":""},{"costs_rent":"","region":"","costs":"","costs_rent_comment":"","costs_comment":"","address_hidden":false,"region_hidden":false,"space_comment":"","space_units":"","space":"","address":""},{"costs_rent":"","address_hidden":false,"costs":"","costs_rent_comment":"","costs_comment":"","space_comment_unclear":false,"space_comment":"","space_units":"","space":"","address":""}],"25":[{"space_unclear":false,"costs":"","costs_comment":"","costs_hidden":false,"address_hidden":false,"region_hidden":false,"space_comment":"","space_hidden":false,"space":"139.6","address":"","region":"","address_unclear":false,"costs_rent_comment":"","costs_rent_hidden":false,"space_comment_unclear":false,"space_units":"м²","costs_rent":""},{"space":"98.2","region":"","costs":"","costs_rent_comment":"","costs_comment":"","region_hidden":false,"address_unclear":false,"space_comment":"","space_units":"м²","costs_rent":"","address":""},{"costs_rent":"","region":"","costs":"","costs_rent_comment":"","costs_comment":"","space_comment":"67/100 частина за договором дарування","space_units":"м²","space":"67","address":""}],"28":[{"costs":"","costs_comment":"","address_hidden":false,"region_hidden":false,"space_comment":"","space":"32.4","address":"","costs_rent_comment_unclear":false,"region":"","costs_rent_comment":"","space_comment_unclear":false,"space_units":"м²","costs_rent":""}],"29":[{"region_unclear":false,"space_hidden":false,"address_hidden":false,"region_hidden":false,"space_comment":"","space_units_hidden":false,"space_unclear":false,"space":".1","address":"","region":"","address_unclear":false,"space_units_unclear":false,"costs_property":"","space_units":"га","costs_property_comment":"","costs_rent":"","costs_rent_comment":""}],"31":[{"space_hidden":false,"costs_property_hidden":false,"address_hidden":false,"region_hidden":false,"space_comment":"1/2 частина","space":"139.6","address":"","region":"","address_unclear":false,"costs_rent_comment":"","costs_rent_hidden":false,"costs_property":"","space_units":"м²","costs_property_comment":"","costs_rent":""}],"34":[{"costs_property_hidden":false,"address_hidden":false,"region_hidden":false,"space_comment":"1/2 частина","space":"25.6","address":"","region":"","address_unclear":false,"costs_rent_comment":"","costs_rent_hidden":false,"costs_property":"","space_units":"м²","costs_property_comment":"","costs_rent":""}]},"intro":{"declaration_year":"2014","declaration_year_unclear":false}}