{"income":{"5":{"value":"291065","family_comment":"","value_unclear":false,"comment_hidden":false,"family_hidden":false,"value_hidden":false,"family_unclear":true,"family":"68757","comment":""},"6":{"value":"257768","family_comment":"","value_unclear":true,"family_hidden":false,"family_unclear":false,"comment_unclear":false,"comment":"","family":"42960"},"7":{"source_name_unclear":false,"value":"","value_hidden":false,"family_comment":"","source_name":"","family":"","comment":"","source_name_hidden":false},"8":{"value":"","family_hidden":false,"value_hidden":false,"family_comment":"","family":"","comment":""},"9":{"value":"","family_comment":"","value_unclear":false,"family_hidden":false,"value_hidden":false,"family_unclear":false,"family":"","comment":""},"10":{"family_comment":"","value":"","family":"","comment":""},"11":{"family_comment":"","value":"","family":"","comment":""},"12":{"family_comment":"","value":"","family":"","comment":""},"13":{"family_comment":"","value":"","family":"","comment":""},"14":{"family_comment":"","value":"","family":"","comment":""},"15":{"family_comment":"","value":"","family":"","comment":""},"16":{"value":"","family_comment":"","value_unclear":false,"family_unclear":false,"family":"","comment":""},"17":{"family_comment":"","value":"","family":"","comment":""},"18":{"family_comment":"","value":"","family":"","comment":""},"19":{"family_comment":"","value":"","comment_unclear":false,"family":"","comment":""},"20":{"value":"33297","family_comment":"","value_unclear":false,"comment_hidden":false,"family_hidden":false,"family":"25797","value_hidden":false,"family_unclear":true,"comment_unclear":false,"comment":"","family_comment_unclear":false}},"vehicle":{"40":[{"brand_info":"1.6 л","sum_rent_comment":"","brand":"Шевроле Такума","sum_comment":"","brand_unclear":true,"year":"2006","brand_info_unclear":true,"year_unclear":false,"sum":"","sum_rent":""}]},"id":"vulyk_63_114","declaration":{"additional_info_text":"","notfull_lostpages":"","date":"2015-03-26T00:00:00","notfull":"","additional_info":"","url":"http://static.declarations.com.ua/declarations/chosen_ones/mega_batch/mashkina_vira_valentynivna.pdf"},"liabilities":{"54":{"sum_foreign_comment":"","sum":"","sum_comment":"","sum_unclear":false,"sum_foreign":""},"55":{"sum_foreign_comment":"","sum":"","sum_comment":"","sum_foreign":""},"56":{"sum_foreign_comment":"","sum":"","sum_comment":"","sum_unclear":false,"sum_foreign":""},"57":{"sum_foreign_comment":"","sum":"","sum_comment":"","sum_comment_hidden":false,"sum_unclear":false,"sum_foreign":""},"58":{"sum_foreign_comment":"","sum_comment_hidden":false,"sum":"","sum_comment":"","sum_foreign":""},"59":{"sum_foreign_comment":"","sum":"","sum_comment":"","sum_foreign":""},"60":{"sum_foreign_comment":"","sum":"","sum_comment":"","sum_comment_unclear":false,"sum_foreign":""},"61":{"sum_foreign_comment":"","sum":"","sum_comment":"","sum_unclear":false,"sum_foreign":""},"62":{"sum_foreign_comment":"","sum":"","sum_comment":"","sum_unclear":false,"sum_foreign":""},"63":{"sum_foreign_comment":"","sum":"","sum_comment":"","sum_hidden":false,"sum_comment_hidden":false,"sum_unclear":false,"sum_foreign":""},"64":{"sum_foreign_comment":"","sum_comment_hidden":false,"sum":"","sum_comment":"","sum_foreign":""}},"ft_src":"Біла Церква\nКиївська область\nголова сквирського районного суду київської області\nКиївська область\nЗагальний місцевий суд\nВіра\nМашкін В. М\nПодружжя\nВалентинівна\nМашкіна\nМашкіна Віра Валентинівна\nМашкіна Віра Валентинівна\nВіра Валентинівна Машкіна\nВіра Машкіна\nМашкіна Віра Валентинівна\n1.6 л\nШевроле Такума\n2006\nСквирський р-н\n103.6\nКиївська область\n58.5\n2014\n42960\n257768\n68757\n291065\n25797\n33297\n1.6 л\n2006\nШевроле Такума\n103.6\nКиївська область\nСквирський р-н\n58.5\nВалентинівна\nМашкіна Віра Валентинівна\nВіра Валентинівна Машкіна\nВіра Машкіна\nМашкіна Віра Валентинівна\nВіра\nПодружжя\nМашкін В. М\nМашкіна Віра Валентинівна\nЗагальний місцевий суд\nКиївська область\nголова сквирського районного суду київської області\nМашкіна\nБіла Церква\nКиївська область\n257768\n42960\n33297\n25797\n291065\n68757\n2014\nПодружжя\nМашкін В. М\nВалентинівна\nМашкіна\nМашкіна Віра Валентинівна\nВіра Валентинівна Машкіна\nВіра Машкіна\nМашкіна Віра Валентинівна\nВіра\nКиївська область\nБіла Церква\nКиївська область\nголова сквирського районного суду київської області\nЗагальний місцевий суд\nМашкіна Віра Валентинівна\n2006\n1.6 л\nШевроле Такума\n33297\n25797\n291065\n68757\n257768\n42960\nСквирський р-н\nКиївська область\n103.6\n58.5\n2014","general":{"name_hidden":false,"name":"Віра","patronymic_unclear":false,"last_name_hidden":false,"inn":"","family":[{"inn":"","inn_hidden":false,"relations_unclear":false,"relations_hidden":false,"relations_other":"","relations":"Подружжя","name_hidden":false,"inn_unclear":false,"family_name":"Машкін В. М","name_unclear":true}],"patronymic":"Валентинівна","inn_hidden":false,"family_raw":"","inn_unclear":false,"post":{"post_unclear":false,"region_unclear":false,"region":"Київська область","office_hidden":false,"region_hidden":false,"post":"голова сквирського районного суду київської області","office_unclear":false,"office":"Загальний місцевий суд"},"last_name_unclear":false,"full_name":"Машкіна Віра Валентинівна","addresses":[{"place_city_type_unclear":false,"place_address":"","place_district_hidden":false,"place_city_type":"Місто","place_address_hidden":false,"place_address_unclear":false,"place_city_type_hidden":false,"place":"Київська область","place_district":"","place_unclear":false,"place_city":"Біла Церква","place_city_unclear":false,"place_hidden":false,"place_city_hidden":false,"place_district_unclear":false}],"last_name":"Машкіна","full_name_suggest":{"output":"Машкіна Віра Валентинівна","input":["Машкіна Віра Валентинівна","Віра Валентинівна Машкіна","Віра Машкіна"]},"name_unclear":false},"source":"VULYK","estate":{"24":[{"region_unclear":false,"space_unclear":false,"costs":"","costs_comment":"","address_hidden":true,"region_hidden":false,"space_comment":"","space":"103.6","address":"Сквирський р-н","region":"Київська область","address_unclear":true,"space_units_unclear":false,"space_units":"м²","costs_rent":"","costs_rent_comment":""},{"costs_rent":"","space_unclear":true,"region":"","costs":"","costs_rent_comment":"","costs_comment":"","space_comment":"","space_units":"м²","space":"58.5","address":""}]},"intro":{"declaration_year":"2014","isnotdeclaration":"","declaration_year_unclear":false}}