{"income":{"5":{"value":"","family_unclear":false,"family_hidden":false,"family_comment":"","family":"","comment":""},"6":{"value":"","family_comment":"","value_unclear":false,"family_hidden":false,"family_unclear":false,"family":"","comment":""},"7":{"value":"","family_hidden":false,"value_hidden":false,"family_comment":"","source_name":"","family":"","comment":"","source_name_hidden":false},"8":{"family_comment":"","value":"","family":"","comment":""},"9":{"family_comment":"","value":"","family":"","comment":""},"10":{"family_comment":"","value":"","value_unclear":false,"family":"","comment":""},"11":{"family_comment":"","value":"","family":"","comment":""},"12":{"family_comment":"","value":"","family":"","comment":""},"13":{"family_comment":"","value":"","family":"","comment":""},"14":{"family_comment":"","value":"","family":"","comment":""},"15":{"family_comment":"","value":"","family":"","comment":""},"16":{"family_comment":"","value":"","family":"","comment":""},"17":{"family_comment":"","value":"","family":"","comment":""},"18":{"family_comment":"","value":"","family":"","comment":""},"19":{"family_comment":"","value":"","family":"","comment":""},"20":{"value":"","family_comment":"","value_unclear":false,"family_unclear":false,"comment_unclear":false,"comment":"","family":""}},"vehicle":{"35":[{"brand_info":"998 куб. см.","sum_rent_comment":"","year":"2013","brand_info_hidden":false,"brand_info_unclear":false,"year_unclear":false,"sum_rent":"","sum":"160000","brand":"Ford B-Max","sum_comment":"","brand_unclear":false,"brand_hidden":false}]},"id":"vulyk_74_149","declaration":{"additional_info_text":"","notfull_lostpages":"2","date":"2014-03-28T00:00:00","notfull":"1","additional_info":"","url":"http://static.declarations.com.ua/declarations/chosen_ones/judges_batch/1544_vynohradova_olena_pavlivna.pdf"},"liabilities":{"54":{"sum_foreign_comment":"","sum":"","sum_comment":"","sum_comment_unclear":false,"sum_comment_hidden":false,"sum_foreign":""},"55":{"sum_foreign_comment":"","sum":"","sum_comment":"","sum_hidden":false,"sum_unclear":false,"sum_foreign":""},"56":{"sum_foreign_comment":"","sum":"12000","sum_comment":"","sum_hidden":false,"sum_unclear":false,"sum_foreign":""},"57":{"sum_foreign_comment":"","sum":"31200","sum_comment":"","sum_comment_unclear":false,"sum_comment_hidden":false,"sum_foreign":""},"58":{"sum_foreign_comment":"","sum_comment_hidden":false,"sum":"","sum_comment":"","sum_foreign":""},"59":{"sum_foreign_comment":"","sum":"","sum_comment":"","sum_foreign":""},"60":{"sum_foreign_comment":"","sum":"","sum_hidden":false,"sum_comment":"","sum_foreign":""},"61":{"sum_foreign_comment":"","sum":"","sum_comment":"","sum_foreign":""},"62":{"sum_foreign_comment":"","sum":"","sum_comment":"","sum_foreign":""},"63":{"sum_foreign_comment":"","sum":"","sum_comment":"","sum_comment_unclear":false,"sum_unclear":false,"sum_foreign":""},"64":{"sum_foreign_comment":"","sum":"","sum_comment":"","sum_comment_unclear":false,"sum_unclear":false,"sum_foreign":""}},"ft_src":"31200\n12000\n1\n2\nХарків\nХарківська область\nПавлівна\nВиноградова Олена Павлівна\nсуддя апеляційного суду харківської області\nХарківська область\nЗагальний апеляційний суд\nОлена\nВиноградова Олена Павлівна\nОлена Павлівна Виноградова\nОлена Виноградова\nВиноградова Олена Павлівна\nВиноградова\n998 куб. см.\n160000\nFord B-Max\n2013\nм. Харків\nХарківська область\nм. Харків\nХарківська область\n2\n1\n2013\n998 куб. см.\n160000\nFord B-Max\n2013\n2\n1\n2013\nЗагальний апеляційний суд\nХарківська область\nсуддя апеляційного суду харківської області\nПавлівна\nВиноградова Олена Павлівна\nОлена Павлівна Виноградова\nОлена Виноградова\nВиноградова Олена Павлівна\nОлена\nХарківська область\nХарків\nВиноградова Олена Павлівна\nВиноградова\n31200\n12000\nХарківська область\nм. Харків\nХарківська область\nм. Харків\n31200\n12000\nПавлівна\nХарківська область\nХарків\nВиноградова\nХарківська область\nЗагальний апеляційний суд\nсуддя апеляційного суду харківської області\nВиноградова Олена Павлівна\nВиноградова Олена Павлівна\nОлена Павлівна Виноградова\nОлена Виноградова\nВиноградова Олена Павлівна\nОлена\nFord B-Max\n160000\n998 куб. см.\n2013\nм. Харків\nХарківська область\nм. Харків\nХарківська область\n2013","general":{"inn":"","inn_hidden":true,"last_name":"Виноградова","post":{"region_unclear":false,"region":"Харківська область","post":"суддя апеляційного суду харківської області","office":"Загальний апеляційний суд","office_unclear":false,"post_hidden":false},"name":"Олена","full_name":"Виноградова Олена Павлівна","family_raw":"","addresses":[{"place_district":"","place_city_hidden":false,"place_city":"Харків","place_city_type_hidden":false,"place_district_hidden":true,"place_city_type":"Місто","place_address_hidden":true,"place_address":"","place_hidden":true,"place":"Харківська область"}],"full_name_suggest":{"output":"Виноградова Олена Павлівна","input":["Виноградова Олена Павлівна","Олена Павлівна Виноградова","Олена Виноградова"]},"patronymic":"Павлівна"},"source":"VULYK","estate":{"23":[{"space_hidden":true,"costs":"","costs_comment":"","address_hidden":true,"region_hidden":false,"space_comment":"","space_unclear":false,"space":"","address":"м. Харків","region":"Харківська область","space_units_unclear":false,"space_comment_unclear":false,"space_units":"м²","costs_rent":"","costs_rent_comment":""}],"24":[{"region_unclear":false,"space_hidden":true,"costs":"","costs_comment":"","address_hidden":true,"region_hidden":false,"space_comment":"","space":"","address":"м. Харків","region":"Харківська область","space_units_unclear":false,"space_units":"м²","costs_rent":"","costs_rent_comment":""}]},"intro":{"declaration_year":"2013","isnotdeclaration":"","declaration_year_unclear":false}}