{"income":{"5":{"value":"206974.8","family_comment":"","value_unclear":false,"family_hidden":false,"value_hidden":false,"family_unclear":false,"family":"","comment":"","family_comment_unclear":false},"6":{"value":"194794.8","family_comment":"","value_unclear":false,"comment_hidden":false,"family_hidden":false,"value_hidden":false,"family_unclear":false,"family":"","comment":""},"7":{"value":"","value_hidden":false,"family_comment":"","source_name":"","family":"","comment":"","source_name_hidden":false},"8":{"family_comment":"","value":"","family":"","comment":""},"9":{"value":"","comment_hidden":false,"value_hidden":false,"family_comment":"","family":"","comment":""},"10":{"value":"12180","value_unclear":false,"value_hidden":false,"family_comment":"","family":"","comment":""},"11":{"family_comment":"","value":"","family":"","comment":""},"12":{"family_comment":"","value":"","family":"","comment":""},"13":{"family_comment":"","value":"","family_hidden":false,"comment":"","family":""},"14":{"family_comment":"","value":"","family":"","comment":""},"15":{"family_comment":"","family_unclear":false,"value":"","family":"","comment":""},"16":{"family_comment":"","value":"","value_unclear":false,"family":"","comment":""},"17":{"family_comment":"","value":"","family":"","comment":""},"18":{"family_comment":"","value":"","family":"","comment":""},"19":{"family_comment":"","value":"","comment_unclear":false,"family":"","comment":""},"20":{"value":"","comment_unclear":false,"family_hidden":false,"value_hidden":false,"family_comment":"","family":"","comment":""}},"vehicle":{"35":[{"year_hidden":false,"brand_info":"1595 куб. см., 75 кВт , 457.2 см","sum_rent_comment":"","brand_info_unclear":false,"sum_rent_hidden":false,"year":"2009","sum_hidden":false,"brand_info_hidden":false,"sum_rent_comment_unclear":false,"year_unclear":false,"sum_rent":"","sum":"","brand":"Skoda Octavia","sum_comment":"","sum_comment_unclear":false,"brand_hidden":false,"sum_unclear":false,"brand_unclear":false}]},"id":"vulyk_64_110","declaration":{"additional_info_text":"","notfull_lostpages":"","date":"2015-03-30T00:00:00","notfull":"","additional_info":"","url":"http://static.declarations.com.ua/declarations/chosen_ones/mega_batch/borets_ievhen_oleksandrovych.pdf"},"liabilities":{"54":{"sum_foreign_comment":"","sum":"","sum_comment":"","sum_foreign_comment_hidden":false,"sum_hidden":false,"sum_comment_hidden":false,"sum_unclear":false,"sum_foreign":""},"55":{"sum_foreign_comment":"","sum":"","sum_comment":"","sum_comment_unclear":false,"sum_foreign":""},"56":{"sum_foreign_comment":"","sum":"","sum_comment":"","sum_unclear":false,"sum_foreign":""},"57":{"sum_foreign_comment":"","sum":"","sum_comment":"","sum_hidden":false,"sum_unclear":false,"sum_foreign":""},"58":{"sum_foreign_comment":"","sum":"","sum_comment":"","sum_unclear":false,"sum_foreign":""},"59":{"sum_foreign_comment":"","sum":"","sum_comment":"","sum_comment_unclear":false,"sum_comment_hidden":false,"sum_unclear":false,"sum_foreign":""},"60":{"sum_foreign_comment":"","sum":"","sum_comment":"","sum_foreign":""},"61":{"sum_foreign_comment":"","sum":"","sum_comment":"","sum_foreign":""},"62":{"sum_foreign_comment":"","sum":"","sum_comment":"","sum_unclear":false,"sum_foreign":""},"63":{"sum_foreign_comment":"","sum":"","sum_comment":"","sum_unclear":false,"sum_foreign":""},"64":{"sum_foreign_comment":"","sum":"","sum_comment":"","sum_comment_unclear":false,"sum_unclear":false,"sum_foreign":""}},"ft_src":"заступник голови бориспільського міськрайонного суду київської області\nКиївська область\nЗагальний місцевий суд\nЄвген\nБурмістенко Наталія Олексіївна\nПодружжя\nОлександрович\nБорець Євген Олександрович\nБорець\nБорець Євген Олександрович\nЄвген Олександрович Борець\nЄвген Борець\nБорець Євген Олександрович\n1595 куб. см., 75 кВт , 457.2 см\nSkoda Octavia\n2009\n56\n2014\n194794.8\n12180\n206974.8\n1595 куб. см., 75 кВт , 457.2 см\nSkoda Octavia\n2009\n56\nЗагальний місцевий суд\nКиївська область\nзаступник голови бориспільського міськрайонного суду київської області\nПодружжя\nБурмістенко Наталія Олексіївна\nБорець Євген Олександрович\nЄвген Олександрович Борець\nЄвген Борець\nБорець Євген Олександрович\nБорець Євген Олександрович\nЄвген\nБорець\nОлександрович\n194794.8\n206974.8\n12180\n2014\nПодружжя\nБурмістенко Наталія Олексіївна\nОлександрович\nБорець\nЄвген\nБорець Євген Олександрович\nЄвген Олександрович Борець\nЄвген Борець\nБорець Євген Олександрович\nКиївська область\nЗагальний місцевий суд\nзаступник голови бориспільського міськрайонного суду київської області\nБорець Євген Олександрович\nSkoda Octavia\n1595 куб. см., 75 кВт , 457.2 см\n2009\n12180\n206974.8\n194794.8\n56\n2014","general":{"inn":"","name":"Євген","last_name_hidden":false,"family":[{"inn":"","inn_hidden":true,"relations_unclear":false,"relations_hidden":false,"relations_other":"","relations":"Подружжя","name_hidden":false,"inn_unclear":false,"family_name":"Бурмістенко Наталія Олексіївна","name_unclear":true}],"patronymic":"Олександрович","inn_hidden":true,"family_raw":"","inn_unclear":false,"post":{"post_unclear":false,"post":"заступник голови бориспільського міськрайонного суду київської області","candidate":"","office_hidden":false,"region":"Київська область","post_hidden":false,"office":"Загальний місцевий суд","office_unclear":false,"region_hidden":false},"last_name_unclear":false,"full_name":"Борець Євген Олександрович","addresses":[{"place_city_type_unclear":false,"place_address":"","place_district_hidden":true,"place_city_type":"","place_city_hidden":true,"place_city_type_hidden":true,"place":"","place_district":"","place_unclear":false,"place_city":"","place_city_unclear":false,"place_hidden":true,"place_address_hidden":true}],"last_name":"Борець","patronymic_hidden":false,"full_name_suggest":{"output":"Борець Євген Олександрович","input":["Борець Євген Олександрович","Євген Олександрович Борець","Євген Борець"]},"name_unclear":false},"source":"VULYK","estate":{"31":[{"region_unclear":false,"address_hidden":false,"region_hidden":false,"space_comment":"","space":"56","address":"","region":"","costs_property":"","costs_rent_comment":"","space_comment_hidden":false,"space_units":"м²","costs_property_comment":"","costs_rent":""}]},"intro":{"declaration_year":"2014","isnotdeclaration":"","declaration_year_unclear":false,"declaration_year_hidden":false}}