{"income":{"5":{"value":"184169","value_unclear":false,"value_hidden":false,"family_comment":"","family":"","comment":""},"6":{"value":"184169","family_comment":"","value_unclear":false,"family_unclear":false,"family":"","comment":""},"7":{"source_name_unclear":false,"value":"","family_hidden":false,"family_comment":"","source_name":"","family":"","comment":""},"8":{"family_comment":"","value":"","family":"","comment":""},"9":{"family_comment":"","value":"","family":"","comment":""},"10":{"family_comment":"","value":"","family":"","comment":""},"11":{"family_comment":"","value":"","family":"","comment":""},"12":{"family_comment":"","value":"","family":"","comment":""},"13":{"family_comment":"","value":"","family":"","comment":""},"14":{"family_comment":"","value":"","family":"","comment":""},"15":{"family_comment":"","value":"","family":"","comment":""},"16":{"family_comment":"","value":"","comment_unclear":false,"family":"","comment":""},"17":{"family_comment":"","family_unclear":false,"value":"","family":"","comment":""},"18":{"family_comment":"","value":"","family":"","comment":""},"19":{"value":"","family_hidden":false,"value_hidden":false,"family_comment":"","family":"","comment":""},"20":{"family_comment":"","value":"","comment_unclear":false,"family":"","comment":""}},"vehicle":{"35":[{"brand_info":"1329 куб. см.","sum_rent_comment":"","year":"2012","sum_rent_unclear":false,"brand_info_hidden":false,"brand_info_unclear":false,"year_unclear":false,"sum_rent":"","sum":"","brand":"Toyota Yaris","sum_comment":"","sum_comment_unclear":false,"brand_hidden":false,"sum_unclear":false,"brand_unclear":false}]},"id":"vulyk_67_30","declaration":{"additional_info_text":"","notfull_lostpages":"","date":"2015-03-30T00:00:00","notfull":"","additional_info":"","url":"http://static.declarations.com.ua/declarations/chosen_ones/mega_batch/horbatovska_svitlana_anatoliivna.pdf"},"liabilities":{"54":{"sum_foreign_comment":"","sum_foreign_hidden":false,"sum_comment":"","sum_comment_unclear":false,"sum_hidden":false,"sum":"","sum_unclear":false,"sum_foreign":""},"55":{"sum_foreign_comment":"","sum":"","sum_comment":"","sum_foreign":""},"56":{"sum_foreign_comment":"","sum_foreign_hidden":false,"sum_comment":"","sum_hidden":false,"sum":"","sum_unclear":false,"sum_foreign":""},"57":{"sum_foreign_comment":"","sum_foreign_hidden":false,"sum_comment":"","sum_comment_unclear":false,"sum_hidden":false,"sum_comment_hidden":false,"sum_unclear":false,"sum":"","sum_foreign":""},"58":{"sum_foreign_comment":"","sum_foreign_hidden":false,"sum_comment":"","sum_comment_unclear":false,"sum_hidden":false,"sum_comment_hidden":false,"sum_unclear":false,"sum":"","sum_foreign":""},"59":{"sum_foreign_comment":"","sum":"","sum_hidden":false,"sum_comment":"","sum_foreign":""},"60":{"sum_foreign_comment":"","sum":"","sum_comment":"","sum_foreign":""},"61":{"sum_foreign_comment":"","sum_foreign_hidden":false,"sum_comment":"","sum_hidden":false,"sum":"","sum_foreign":""},"62":{"sum_foreign_comment":"","sum":"","sum_hidden":false,"sum_comment":"","sum_foreign":""},"63":{"sum_foreign_comment":"","sum":"","sum_comment":"","sum_comment_unclear":false,"sum_hidden":false,"sum_unclear":false,"sum_foreign":""},"64":{"sum_foreign_comment":"","sum":"","sum_comment":"","sum_hidden":false,"sum_unclear":false,"sum_foreign":""}},"ft_src":"суддя солом'янського районного суду міста києва\nм. Київ\nЗагальний місцевий суд\nСвітлана\nГорбатовська А. А., 14. 04. 2009\nДитина\nАнатоліївна\nГорбатовська Світлана Анатоліївна\nГорбатовська\nГорбатовська Світлана Анатоліївна\nСвітлана Анатоліївна Горбатовська\nСвітлана Горбатовська\nГорбатовська Світлана Анатоліївна\n1329 куб. см.\nToyota Yaris\n2012\n41.06\n2014\n184169\n184169\n1329 куб. см.\nToyota Yaris\n2012\n41.06\nЗагальний місцевий суд\nсуддя солом'янського районного суду міста києва\nм. Київ\nДитина\nГорбатовська А. А., 14. 04. 2009\nГорбатовська Світлана Анатоліївна\nСвітлана Анатоліївна Горбатовська\nСвітлана Горбатовська\nГорбатовська Світлана Анатоліївна\nГорбатовська Світлана Анатоліївна\nСвітлана\nГорбатовська\nАнатоліївна\n184169\n184169\n2014\nДитина\nГорбатовська А. А., 14. 04. 2009\nАнатоліївна\nГорбатовська\nСвітлана\nГорбатовська Світлана Анатоліївна\nСвітлана Анатоліївна Горбатовська\nСвітлана Горбатовська\nГорбатовська Світлана Анатоліївна\nм. Київ\nсуддя солом'янського районного суду міста києва\nЗагальний місцевий суд\nГорбатовська Світлана Анатоліївна\n2012\nToyota Yaris\n1329 куб. см.\n184169\n184169\n41.06\n2014","general":{"inn":"","name":"Світлана","patronymic_unclear":false,"last_name_hidden":false,"family":[{"inn":"","inn_hidden":false,"relations_unclear":false,"relations_hidden":false,"relations_other":"","relations":"Дитина","name_hidden":false,"inn_unclear":false,"family_name":"Горбатовська А. А., 14. 04. 2009","name_unclear":false}],"patronymic":"Анатоліївна","inn_hidden":true,"family_raw":"","inn_unclear":false,"post":{"post_unclear":false,"post":"суддя солом'янського районного суду міста києва","post_hidden":false,"region":"м. Київ","region_hidden":false,"office":"Загальний місцевий суд","office_hidden":false,"office_unclear":false},"last_name_unclear":false,"full_name":"Горбатовська Світлана Анатоліївна","addresses":[{"place_city_type_hidden":true,"place_district_hidden":true,"place_city_type":"","place_city_hidden":true,"place_address_unclear":false,"place_address":"","place":"","place_district":"","place_unclear":false,"place_city":"","place_city_unclear":false,"place_hidden":true,"place_address_hidden":true,"place_district_unclear":false}],"last_name":"Горбатовська","full_name_suggest":{"output":"Горбатовська Світлана Анатоліївна","input":["Горбатовська Світлана Анатоліївна","Світлана Анатоліївна Горбатовська","Світлана Горбатовська"]},"name_unclear":false},"source":"VULYK","estate":{"25":[{"space_unclear":false,"costs":"","costs_comment":"","costs_hidden":false,"address_hidden":true,"region_hidden":true,"space_comment":"","space":"41.06","address":"","region":"","address_unclear":false,"space_units_unclear":false,"space_comment_unclear":false,"space_units":"м²","costs_rent":"","costs_rent_comment":""}]},"intro":{"declaration_year":"2014","isnotdeclaration":"","declaration_year_hidden":false}}