{"income":{"5":{"value":"182165","family_unclear":false,"family_hidden":false,"family_comment":"","family":"45335","comment":""},"6":{"family_comment":"","value":"182001","family_hidden":false,"comment":"","family":"45265"},"7":{"family_comment":"","value":"","source_name":"","family":"","comment":""},"8":{"family_comment":"","value":"","family":"","comment":""},"9":{"value":"","comment_unclear":false,"family_hidden":false,"family_comment":"","family":"","comment":""},"10":{"family_comment":"","value":"","family":"","comment":""},"11":{"family_comment":"","value":"","family":"","comment":""},"12":{"family_comment":"","value":"","family":"","comment":""},"13":{"family_comment":"","value":"","family":"","comment":""},"14":{"family_comment":"","value":"","family":"","comment":""},"15":{"family_comment":"","value":"","value_unclear":false,"family":"","comment":""},"16":{"family_comment":"","value":"","family":"","comment":""},"17":{"family_comment":"","value":"","family":"","comment":""},"18":{"family_comment":"","value":"","family":"","comment":""},"19":{"family_comment":"","value":"","family":"","comment":""},"20":{"value":"164","comment_unclear":false,"comment_hidden":false,"family_hidden":false,"value_hidden":false,"family_comment":"","value_unclear":false,"family":"70","comment":"","family_comment_hidden":false}},"vehicle":{"35":[{"brand_info":"об'єм двигуна 1994","sum_rent_comment":"право керування","brand":"Subaru Legacy","sum_comment":"","year":"2008","brand_info_hidden":false,"sum":"","sum_rent":""}]},"id":"vulyk_41_81","banks":{"45":[{"sum_foreign_comment":"","sum_units":"UAH","sum_comment":"","sum_foreign_unclear":false,"sum_foreign_units":"UAH","sum_hidden":false,"sum_comment_hidden":false,"sum":"","sum_foreign":""},{"sum_foreign_comment":"","sum_units":"","sum_comment":"","sum_foreign_unclear":false,"sum_foreign_units":"","sum":"","sum_foreign":""}],"46":[{"sum_foreign_comment":"","sum_units":"UAH","sum_comment":"","sum_foreign_units":"UAH","sum_comment_hidden":false,"sum_unclear":false,"sum":"","sum_foreign":""},{"sum_foreign_comment":"","sum_units":"","sum_comment":"","sum_foreign_units":"","sum":"","sum_unclear":false,"sum_foreign":""}],"47":[{"sum_foreign_comment":"","sum_units":"UAH","sum_comment":"","sum_foreign_units":"UAH","sum":"","sum_foreign":""},{"sum_foreign_comment":"","sum_units":"","sum_comment":"","sum_foreign_units":"","sum":"","sum_foreign":""}],"48":[{"sum_foreign_comment":"","sum_units":"UAH","sum_comment":"","sum_foreign_units":"UAH","sum":"","sum_foreign":""}],"49":[{"sum_foreign_comment":"","sum_units":"UAH","sum_comment":"","sum_foreign_units":"UAH","sum":"","sum_foreign":""}],"50":[{"sum_foreign_comment":"","sum_units":"UAH","sum_comment":"","sum_foreign_units":"UAH","sum":"","sum_foreign":""}],"51":[{"sum_foreign_comment":"","sum_units":"UAH","sum_comment":"","sum_hidden":false,"sum_foreign_units":"UAH","sum_comment_hidden":false,"sum_unclear":false,"sum":"","sum_foreign":""},{"sum_foreign_comment":"","sum_units":"","sum_comment":"","sum_foreign_units":"","sum":"","sum_foreign":""}],"52":[{"sum_foreign_comment":"","sum_units":"UAH","sum_comment":"","sum_foreign_units":"UAH","sum_comment_hidden":false,"sum_unclear":false,"sum":"","sum_foreign":""}],"53":[{"sum_foreign_comment":"","sum_units":"UAH","sum_comment":"","sum_foreign_units":"UAH","sum_comment_hidden":false,"sum":"","sum_foreign":""},{"sum_foreign_comment":"","sum_units":"","sum_comment":"","sum_foreign_units":"","sum":"","sum_foreign":""},{"sum_foreign_comment":"","sum_units":"","sum_comment":"","sum_foreign_units":"","sum":"","sum_foreign":""}]},"declaration":{"date":"2015-03-31T00:00:00","additional_info_text":"","additional_info":"","url":"http://static.declarations.com.ua/declarations/chosen_ones/mega_batch/prudnyk_serhii_volodymyrovych.pdf"},"liabilities":{"54":{"sum_foreign_comment":"","sum_comment_hidden":false,"sum":"","sum_comment":"","sum_foreign":""},"55":{"sum_foreign_comment":"","sum":"","sum_comment":"","sum_foreign":""},"56":{"sum_foreign_comment":"","sum":"","sum_hidden":false,"sum_comment":"","sum_foreign":""},"57":{"sum_foreign_comment":"","sum":"","sum_comment":"","sum_comment_hidden":false,"sum_unclear":false,"sum_foreign":""},"58":{"sum_foreign_comment":"","sum_comment_hidden":false,"sum":"","sum_comment":"","sum_foreign":""},"59":{"sum_foreign_comment":"","sum":"","sum_comment":"","sum_foreign":""},"60":{"sum_foreign_comment":"","sum_comment_hidden":false,"sum":"","sum_comment":"","sum_foreign":""},"61":{"sum_foreign_comment":"","sum":"","sum_comment":"","sum_foreign":""},"62":{"sum_foreign_comment":"","sum":"","sum_comment":"","sum_foreign":""},"63":{"sum_foreign_comment":"","sum":"","sum_comment":"","sum_comment_hidden":false,"sum_unclear":false,"sum_foreign":""},"64":{"sum_foreign_comment":"","sum_comment_hidden":false,"sum":"","sum_comment":"","sum_foreign":""}},"ft_src":"суддя дніпропетровського окружного адміністративного суду\nДніпропетровська область\nАдміністративний місцевий суд\nСергій\nПрудник Ю. В\nПодружжя\nПрудник М. С\nДитина\nВолодимирович\nПрудник Сергій Володимирович\nСергій Володимирович Прудник\nСергій Прудник\nПрудник Сергій Володимирович\nПрудник\nПрудник Сергій Володимирович\nоб'єм двигуна 1994\n2008\nSubaru Legacy\nправо керування\n2014\nSubaru Legacy\nоб'єм двигуна 1994\nправо керування\n2008\n.0645\nДніпропетровська область\n207.5\nм. Кривий Ріг\nДніпропетровська область\n70\n1/4 частина\nм. Кривий Ріг\nДніпропетровська область\n70.5\n1/2 частина\nм. Кривий Ріг\nДніпропетровська область\nПодружжя\nПрудник Ю. В\nДитина\nПрудник М. С\nПрудник Сергій Володимирович\nСергій Володимирович Прудник\nСергій Прудник\nПрудник Сергій Володимирович\nПрудник Сергій Володимирович\nСергій\nВолодимирович\nАдміністративний місцевий суд\nсуддя дніпропетровського окружного адміністративного суду\nДніпропетровська область\nПрудник\n182001\n45265\n164\n70\n182165\n45335\n2014\n.0645\nДніпропетровська область\n1/4 частина\nм. Кривий Ріг\nДніпропетровська область\n70\nм. Кривий Ріг\nДніпропетровська область\n207.5\n1/2 частина\nм. Кривий Ріг\n70.5\nДніпропетровська область\nПрудник Ю. В\nПодружжя\nПрудник М. С\nДитина\nВолодимирович\nПрудник\nСергій\nПрудник Сергій Володимирович\nСергій Володимирович Прудник\nСергій Прудник\nПрудник Сергій Володимирович\nДніпропетровська область\nсуддя дніпропетровського окружного адміністративного суду\nАдміністративний місцевий суд\nПрудник Сергій Володимирович\n45265\n182001\n45335\n182165\n70\n164\nправо керування\nSubaru Legacy\nоб'єм двигуна 1994\n2008\n164\n70\n182165\n45335\n45265\n182001\n1/4 частина\nм. Кривий Ріг\nДніпропетровська область\n70\nДніпропетровська область\n.0645\nм. Кривий Ріг\nДніпропетровська область\n207.5\n1/2 частина\nм. Кривий Ріг\nДніпропетровська область\n70.5\n2014","general":{"inn":"","name":"Сергій","family":[{"inn":"","relations":"Подружжя","relations_hidden":false,"inn_hidden":true,"family_name":"Прудник Ю. В","name_hidden":true,"name_unclear":false},{"inn":"","relations":"Дитина","relations_other":"","inn_hidden":false,"family_name":"Прудник М. С","name_hidden":false,"name_unclear":false}],"patronymic":"Володимирович","inn_hidden":true,"family_raw":"","last_name":"Прудник","post":{"post_unclear":false,"post":"суддя дніпропетровського окружного адміністративного суду","post_hidden":false,"region":"Дніпропетровська область","region_hidden":false,"office":"Адміністративний місцевий суд","office_hidden":false},"last_name_unclear":false,"full_name":"Прудник Сергій Володимирович","addresses":[{"place_district":"","place_city_hidden":true,"place_city":"","place_city_type_hidden":false,"place_district_hidden":true,"place_city_type":"","place_address_hidden":false,"place_address":"","place_hidden":true,"place":""}],"patronymic_hidden":false,"full_name_suggest":{"output":"Прудник Сергій Володимирович","input":["Прудник Сергій Володимирович","Сергій Володимирович Прудник","Сергій Прудник"]},"name_unclear":false},"source":"VULYK","estate":{"23":[{"region_unclear":false,"space_unclear":false,"costs":"","costs_comment":"","address_hidden":true,"region_hidden":false,"space_comment":"","space":".0645","address":"","costs_comment_unclear":false,"region":"Дніпропетровська область","space_units_unclear":false,"space_comment_hidden":false,"space_units":"га","costs_rent":"","costs_rent_comment":""},{"costs_rent":"","space_unclear":false,"region":"","costs":"","costs_rent_comment":"","costs_comment":"","space_comment":"","space_units":"","space":"","address":""},{"costs_rent":"","region":"","costs":"","costs_rent_comment":"","costs_comment":"","space_comment":"","space_units":"","space":"","address":""}],"24":[{"region_unclear":false,"space_unclear":false,"costs":"","costs_comment":"","address_hidden":true,"region_hidden":false,"space_comment":"","space":"207.5","address":"м. Кривий Ріг","region":"Дніпропетровська область","costs_rent_comment":"","space_units":"м²","costs_rent":""}],"25":[{"region_unclear":false,"space_hidden":false,"costs":"","costs_comment":"","address_hidden":true,"region_hidden":false,"space_comment":"1/2 частина","space_unclear":false,"space":"70.5","address":"м. Кривий Ріг","costs_comment_unclear":false,"region":"Дніпропетровська область","costs_rent_comment":"","costs_unclear":false,"space_units":"м²","costs_rent":""}],"31":[{"space_hidden":false,"address_hidden":true,"region_hidden":false,"space_comment":"1/4 частина","space":"70","address":"м. Кривий Ріг","region":"Дніпропетровська область","costs_property":"","costs_rent_comment":"","space_comment_unclear":false,"space_units":"м²","costs_property_comment":"","costs_rent":""}]},"intro":{"declaration_year":"2014"}}