{"id":"vulyk_79_32","ft_src":"2005\nЗАЗ 1102 Таврия\n11021840, 1 .3 куб. дм., власність\n2008\n2.0 куб. см, право керувати\nHyundai Tucson\nвласність\n28\nвласність\n47\nкористування\n70\n2014\n209981\nпроценти на залишок зарплатної картки\n452\n13398\n257376\nпенсія\n33545\nЗАЗ 1102 Таврия\n11021840, 1 .3 куб. дм., власність\n2005\n2.0 куб. см, право керувати\nHyundai Tucson\n2008\n28\nвласність\nвласність\n47\n70\nкористування\nАпеляційний адміністративний суд\nДніпропетровська область\nсуддя дніпропетровського апеляційного адміністративного суду\nБогданенко Ігор Юрійович\nІгор Юрійович Богданенко\nІгор Богданенко\nБогданенко Ігор Юрійович\nІгор\nБогданенко Ігор Юрійович\nБогданенко\nЮрійович\n209981\n33545\nпенсія\n257376\n452\nпроценти на залишок зарплатної картки\n13398\n2014\nЮрійович\nБогданенко\nІгор\nБогданенко Ігор Юрійович\nІгор Юрійович Богданенко\nІгор Богданенко\nБогданенко Ігор Юрійович\nДніпропетровська область\nАпеляційний адміністративний суд\nсуддя дніпропетровського апеляційного адміністративного суду\nБогданенко Ігор Юрійович","estate":{"25":[{"costs_unclear":false,"address":"","space_units":"м²","costs_rent_unclear":false,"space_hidden":false,"space_unclear":false,"region_hidden":true,"costs_rent_comment":"","space_comment":"власність","address_hidden":true,"costs":"","costs_rent_comment_unclear":false,"costs_comment":"","space":"47","region":"","costs_rent":""},{"address":"","space_units":"м²","costs_hidden":false,"space_hidden":false,"space_comment":"користування","region_hidden":false,"costs_comment":"","space":"70","costs_rent_hidden":false,"costs_rent_comment":"","costs":"","region":"","costs_rent":""}],"27":[{"costs":"","address":"","space_units":"м²","costs_rent_comment":"","space":"28","space_comment":"власність","region_hidden":true,"costs_comment":"","region":"","address_hidden":true,"costs_rent":""}]},"vehicle":{"35":[{"sum_comment":"","brand_info_hidden":false,"sum_rent":"","sum":"","brand_unclear":false,"year":"2005","brand":"ЗАЗ 1102 Таврия","brand_info":"11021840, 1 .3 куб. дм., власність","sum_rent_comment":""},{"sum_comment":"","brand_info":"2.0 куб. см, право керувати","sum":"","brand_unclear":false,"year":"2008","brand":"Hyundai Tucson","sum_rent":"","sum_rent_comment":""}]},"source":"VULYK","income":{"5":{"family":"","family_comment":"","comment":"","value_hidden":false,"value_unclear":false,"comment_hidden":false,"family_hidden":false,"value":"257376"},"6":{"family":"","family_comment":"","comment":"","value_hidden":false,"value_unclear":false,"comment_hidden":false,"family_hidden":false,"value":"209981","family_comment_hidden":false},"7":{"family":"","family_comment":"","value":"","comment":"","source_name":""},"8":{"family_comment":"","value":"","family":"","comment":""},"9":{"family_comment":"","value":"452","family":"","comment":"проценти на залишок зарплатної картки"},"10":{"family_comment":"","family":"","comment":"","value_unclear":false,"family_hidden":false,"value":"13398"},"11":{"family_comment":"","value":"","family":"","comment":""},"12":{"family_comment":"","value":"","family":"","comment":""},"13":{"family_comment":"","value":"","family":"","comment":""},"14":{"family_comment":"","value":"","family":"","comment":""},"15":{"family_comment":"","comment_unclear":false,"value":"","family":"","comment":""},"16":{"family_comment":"","value":"","family":"","comment":""},"17":{"family_comment":"","value":"","family":"","comment":""},"18":{"family_comment":"","value":"","family":"","comment":""},"19":{"family_comment":"","value":"","family":"","comment":""},"20":{"family_comment":"","value":"33545","family":"","comment":"пенсія","family_comment_hidden":false}},"general":{"family_raw":"","name":"Ігор","full_name_suggest":{"input":["Богданенко Ігор Юрійович","Ігор Юрійович Богданенко","Ігор Богданенко"],"output":"Богданенко Ігор Юрійович"},"patronymic":"Юрійович","inn_hidden":true,"addresses":[{"place_city_type_hidden":true,"place_city_type":"","place_city_hidden":true,"place_hidden":true,"place_district":"","place_district_hidden":true,"place":"","place_address":"","place_address_hidden":true,"place_city":""}],"last_name_hidden":false,"inn":"","inn_unclear":false,"last_name":"Богданенко","full_name":"Богданенко Ігор Юрійович","post":{"post_hidden":false,"office":"Апеляційний адміністративний суд","post":"суддя дніпропетровського апеляційного адміністративного суду","region":"Дніпропетровська область","region_hidden":false,"office_unclear":false,"office_hidden":false,"post_unclear":false}},"liabilities":{"54":{"sum_comment":"","sum_foreign_comment":"","sum_foreign":"","sum":"","sum_comment_hidden":false},"55":{"sum_comment":"","sum_foreign_comment":"","sum_foreign":"","sum":""},"56":{"sum_comment":"","sum_foreign_comment":"","sum_foreign":"","sum_hidden":false,"sum":""},"57":{"sum_comment_unclear":false,"sum_comment":"","sum_hidden":false,"sum":"","sum_foreign_comment":"","sum_foreign":"","sum_comment_hidden":false},"58":{"sum_comment_unclear":false,"sum_comment":"","sum_hidden":false,"sum":"","sum_foreign_comment":"","sum_foreign":"","sum_unclear":false,"sum_comment_hidden":false},"59":{"sum_comment":"","sum_foreign_comment":"","sum_foreign":"","sum":""},"60":{"sum_comment":"","sum_foreign_comment":"","sum_foreign":"","sum":"","sum_comment_hidden":false},"61":{"sum_comment":"","sum_foreign_comment":"","sum_foreign":"","sum":""},"62":{"sum_comment":"","sum_foreign_comment":"","sum_foreign":"","sum":""},"63":{"sum_comment":"","sum_foreign_comment":"","sum_foreign":"","sum_unclear":false,"sum":""},"64":{"sum_comment":"","sum_foreign_comment":"","sum_foreign":"","sum_unclear":false,"sum":""}},"declaration":{"additional_info_text":"","additional_info":"","date":"2015-03-31T00:00:00","url":"http://static.declarations.com.ua/declarations/chosen_ones/judges_batch/2037_bohdanenko_ihor_iuriiovych.pdf"},"intro":{"declaration_year":"2014"}}