{"income":{"5":{"value":"204673.6","family_comment":"","value_unclear":false,"family":"4920","family_unclear":false,"comment_unclear":false,"comment":"","family_comment_unclear":false},"6":{"value":"192493.6","family_comment":"","value_unclear":false,"family_unclear":false,"family":"4920","comment":""},"7":{"source_name_unclear":false,"value":"","value_unclear":false,"family_comment":"","source_name":"","family":"","comment":"","source_name_hidden":true},"8":{"family_comment":"","value":"","family":"","comment":""},"9":{"family_comment":"","value":"","family":"","comment":""},"10":{"family_comment":"","value":"12180","value_unclear":false,"family":"","comment":""},"11":{"value":"","value_unclear":false,"value_hidden":false,"family_comment":"","family":"","comment":""},"12":{"family_comment":"","value":"","family":"","comment":"","value_hidden":false},"13":{"family_comment":"","value":"","family":"","comment":""},"14":{"family_comment":"","value":"","family":"","comment":""},"15":{"family_comment":"","value":"","family":"","comment":""},"16":{"family_comment":"","value":"","family":"","comment":""},"17":{"family_comment":"","value":"","family":"","comment":""},"18":{"family_comment":"","value":"","family":"","comment":""},"19":{"family_comment":"","family_unclear":false,"value":"","family":"","comment":""},"20":{"family_comment":"","family_unclear":false,"value":"","family":"","comment":""}},"vehicle":{"40":[{"brand_info":"","sum":"","brand":"","sum_comment":"","brand_unclear":false,"year":"1999","brand_hidden":true,"brand_info_hidden":true,"brand_info_unclear":false,"sum_rent_comment":"","sum_rent":""}]},"id":"vulyk_61_32","declaration":{"additional_info_text":"","notfull_lostpages":"","date":"2015-03-31T00:00:00","notfull":"","additional_info":"","url":"http://static.declarations.com.ua/declarations/chosen_ones/mega_batch/shyshkin_oleksii_volodymyrovych.pdf"},"liabilities":{"54":{"sum_foreign_comment":"","sum":"","sum_comment":"","sum_comment_unclear":false,"sum_unclear":false,"sum_foreign":""},"55":{"sum_foreign_comment":"","sum":"","sum_comment":"","sum_foreign":""},"56":{"sum_foreign_comment":"","sum":"","sum_comment":"","sum_unclear":false,"sum_foreign":""},"57":{"sum_foreign_comment":"","sum":"","sum_comment":"","sum_comment_hidden":false,"sum_unclear":false,"sum_foreign":""},"58":{"sum_foreign_comment":"","sum":"","sum_comment":"","sum_unclear":false,"sum_foreign":""},"59":{"sum_foreign_comment":"","sum":"","sum_comment":"","sum_foreign":""},"60":{"sum_foreign_comment":"","sum_foreign_hidden":false,"sum_comment":"","sum_hidden":false,"sum":"","sum_foreign":""},"61":{"sum_foreign_comment":"","sum":"","sum_comment":"","sum_foreign":""},"62":{"sum_foreign_comment":"","sum":"","sum_comment":"","sum_unclear":false,"sum_foreign":""},"63":{"sum_foreign_comment":"","sum":"","sum_comment":"","sum_hidden":false,"sum_unclear":false,"sum_foreign":""},"64":{"sum_foreign_comment":"","sum":"","sum_hidden":false,"sum_comment":"","sum_foreign":""}},"ft_src":"суддя дзержинського районного суду м. харкова\nХарківська область\nЗагальний місцевий суд\nОлексій\nШишкіна Н. О\nПодружжя\nШишкін Д. О\nДитина\nВолодимирович\nШишкін\nШишкін Олексій Володимирович\nШишкін Олексій Володимирович\nОлексій Володимирович Шишкін\nОлексій Шишкін\nШишкін Олексій Володимирович\n1999\n60.7\n65.2\n2014\n4920\n192493.6\n12180\n4920\n204673.6\n1999\n60.7\n65.2\nПодружжя\nШишкіна Н. О\nДитина\nШишкін Д. О\nШишкін Олексій Володимирович\nОлексій Володимирович Шишкін\nОлексій Шишкін\nШишкін Олексій Володимирович\nОлексій\nШишкін Олексій Володимирович\nШишкін\nХарківська область\nЗагальний місцевий суд\nсуддя дзержинського районного суду м. харкова\nВолодимирович\n4920\n192493.6\n204673.6\n4920\n12180\n2014\nШишкіна Н. О\nПодружжя\nШишкін Д. О\nДитина\nВолодимирович\nШишкін\nШишкін Олексій Володимирович\nОлексій Володимирович Шишкін\nОлексій Шишкін\nШишкін Олексій Володимирович\nХарківська область\nсуддя дзержинського районного суду м. харкова\nЗагальний місцевий суд\nШишкін Олексій Володимирович\nОлексій\n1999\n12180\n204673.6\n4920\n192493.6\n4920\n60.7\n65.2\n2014","general":{"inn":"","name":"Олексій","patronymic_unclear":false,"family":[{"inn":"","inn_hidden":true,"relations_unclear":false,"relations_hidden":false,"relations_other":"","relations":"Подружжя","name_hidden":false,"family_name":"Шишкіна Н. О","name_unclear":false},{"inn":"","relations":"Дитина","relations_other":"","inn_hidden":false,"family_name":"Шишкін Д. О","name_hidden":false,"name_unclear":false}],"patronymic":"Володимирович","inn_hidden":true,"family_raw":"","inn_unclear":false,"post":{"post_unclear":false,"region_unclear":false,"post":"суддя дзержинського районного суду м. харкова","office":"Загальний місцевий суд","region":"Харківська область","post_hidden":false,"office_hidden":false,"region_hidden":false},"last_name_unclear":false,"full_name":"Шишкін Олексій Володимирович","addresses":[{"place_address":"","place_district_hidden":true,"place_city_type":"","place_city_hidden":true,"place_address_unclear":false,"place_city_type_hidden":true,"place_hidden":true,"place":"","place_district":"","place_address_hidden":true,"place_city":"","place_district_unclear":false}],"last_name":"Шишкін","patronymic_hidden":false,"full_name_suggest":{"output":"Шишкін Олексій Володимирович","input":["Шишкін Олексій Володимирович","Олексій Володимирович Шишкін","Олексій Шишкін"]},"name_unclear":false},"source":"VULYK","estate":{"25":[{"region_unclear":false,"space_hidden":false,"costs":"","costs_comment":"","address_hidden":false,"region_hidden":true,"space_comment":"","space_unclear":false,"space":"65.2","address":"","costs_comment_unclear":false,"costs_unclear":false,"region":"","address_unclear":false,"costs_rent_comment":"","space_comment_unclear":false,"space_units":"м²","costs_rent":""}],"31":[{"space_unclear":false,"address_hidden":true,"region_hidden":true,"space_comment":"","space_hidden":false,"space":"60.7","address":"","region":"","costs_property":"","costs_rent_comment":"","space_comment_unclear":false,"space_units":"м²","costs_property_comment":"","costs_rent":""}],"32":[{"space_hidden":false,"address_hidden":false,"region_hidden":true,"space_comment":"","space":"","address":"","region":"","costs_property":"","costs_rent_comment":"","space_units":"м²","costs_property_comment":"","costs_rent":""}]},"intro":{"declaration_year":"2014","isnotdeclaration":"","declaration_year_hidden":false}}