{"income":{"5":{"value":"301122","value_unclear":false,"family_hidden":false,"family_comment":"","family":"79756","comment":""},"6":{"family_comment":"","value":"301122","family":"","comment":""},"7":{"family_comment":"","value":"","source_name":"","family":"","comment":""},"8":{"family_comment":"","value":"","family":"","comment":""},"9":{"family_comment":"","value":"","family":"","comment":""},"10":{"family_comment":"","value":"","family":"","comment":""},"11":{"family_comment":"","value":"","family":"","comment":"","family_hidden":false},"12":{"family_comment":"","value":"","family":"","comment":""},"13":{"family_comment":"","value":"","family":"","comment":""},"14":{"family_comment":"","value":"","family":"","comment":""},"15":{"family_comment":"","value":"","family":"36942","comment":""},"16":{"family_comment":"","value":"","family":"","comment":""},"17":{"family_comment":"","value":"","family":"","comment":"","family_comment_unclear":false},"18":{"family_comment":"","value":"","family":"","comment":""},"19":{"family_comment":"","value":"","family":"","comment":""},"20":{"value":"","family_comment":"пенсія за віком","family_hidden":false,"family_unclear":false,"family":"42814","comment":""}},"vehicle":{"40":[{"year_hidden":false,"brand_info":"Легковий універсал В, 2675, 185","sum":"","brand":"Toyota Venza","sum_comment":"","year":"2012","brand_hidden":false,"brand_info_unclear":false,"sum_rent_comment":"","sum_rent":""}]},"id":"vulyk_103_19","declaration":{"date":"2016-03-24T00:00:00","additional_info_text":"","additional_info":"","url":"http://static.declarations.com.ua/declarations/chosen_ones/judges_batch/1243_vysotska_valentyna_stepanivna.pdf"},"liabilities":{"54":{"sum_foreign_comment":"","sum_unclear":false,"sum":"","sum_comment":"","sum_foreign_comment_hidden":false,"sum_hidden":false,"sum_foreign_comment_unclear":false,"sum_comment_hidden":false,"sum_foreign_hidden":false,"sum_foreign":""},"55":{"sum_foreign_comment":"","sum":"","sum_comment":"","sum_foreign":""},"56":{"sum_foreign_comment":"","sum":"","sum_comment":"","sum_foreign":""},"57":{"sum_foreign_comment":"","sum":"","sum_comment":"","sum_foreign_comment_hidden":false,"sum_hidden":false,"sum_comment_hidden":false,"sum_foreign_hidden":false,"sum_foreign":""},"58":{"sum_foreign_comment":"","sum":"","sum_comment":"","sum_foreign_comment_hidden":false,"sum_hidden":false,"sum_comment_hidden":false,"sum_foreign_hidden":false,"sum_foreign":""},"59":{"sum_foreign_comment":"","sum":"","sum_comment":"","sum_foreign_comment_hidden":false,"sum_hidden":false,"sum_comment_hidden":false,"sum_foreign_hidden":false,"sum_foreign":""},"60":{"sum_foreign_comment":"","sum":"","sum_comment":"","sum_hidden":false,"sum_comment_hidden":false,"sum_foreign":""},"61":{"sum_foreign_comment":"","sum":"","sum_comment":"","sum_foreign":""},"62":{"sum_foreign_comment":"","sum_comment":"","sum":"","sum_comment_hidden":false,"sum_foreign":""},"63":{"sum_foreign_comment":"","sum":"","sum_comment":"","sum_foreign":""},"64":{"sum_foreign_comment":"","sum":"","sum_comment":"","sum_foreign":""}},"ft_src":"Легковий універсал В, 2675, 185\nToyota Venza\n2012\n750\n18.2\nкористування\n83.1\n83.1\nкористування\n2015\n301122\n36942\n79756\n301122\nпенсія за віком\n42814\nЛегковий універсал В, 2675, 185\n2012\nToyota Venza\n750\n18.2\n83.1\nкористування\n83.1\nкористування\nВисоцька\nВисоцька Валентина Степанівна\nВалентина Степанівна Висоцька\nВалентина Висоцька\nВисоцька Валентина Степанівна\nВисоцька Валентина Степанівна\nСтепанівна\nПодружжя\nВисоцький М. М\nВалентина\nВищий спеціалізований суд з розгляду цивільних і кримінальних справ\nсуддя вищого спецiалiзованого суду україни з розгляду цивiльних і кримiнальних справ\nЗагальнодержавний регіон\n301122\nпенсія за віком\n42814\n36942\n301122\n79756\n2015\nПодружжя\nВисоцький М. М\nВисоцька\nСтепанівна\nсуддя вищого спецiалiзованого суду україни з розгляду цивiльних і кримiнальних справ\nВищий спеціалізований суд з розгляду цивільних і кримінальних справ\nЗагальнодержавний регіон\nВисоцька Валентина Степанівна\nВисоцька Валентина Степанівна\nВалентина Степанівна Висоцька\nВалентина Висоцька\nВисоцька Валентина Степанівна\nВалентина","general":{"inn_hidden":true,"inn":"","last_name":"Висоцька","post":{"region":"Загальнодержавний регіон","office":"Вищий спеціалізований суд з розгляду цивільних і кримінальних справ","post":"суддя вищого спецiалiзованого суду україни з розгляду цивiльних і кримiнальних справ","office_unclear":false,"region_unclear":false},"name":"Валентина","full_name":"Висоцька Валентина Степанівна","family_raw":"","addresses":[{"place_district":"","place_address_hidden":true,"place_city":"","place_address":"","place_district_hidden":false,"place_city_type":"","place_city_hidden":true,"place_city_type_hidden":false,"place_hidden":true,"place":""}],"family":[{"inn":"","relations":"Подружжя","relations_hidden":false,"inn_hidden":true,"family_name":"Висоцький М. М","relations_other":"","name_hidden":true,"name_unclear":false}],"full_name_suggest":{"output":"Висоцька Валентина Степанівна","input":["Висоцька Валентина Степанівна","Валентина Степанівна Висоцька","Валентина Висоцька"]},"patronymic":"Степанівна"},"source":"VULYK","estate":{"23":[{"costs_rent":"","region":"","costs":"","costs_rent_comment":"","costs_comment":"","address_hidden":false,"region_hidden":true,"space_comment":"","space_units":"м²","space":"750","address":""}],"25":[{"costs":"","costs_comment":"","address_hidden":false,"region_hidden":true,"space_comment":"","space":"83.1","address":"","region":"","costs_rent_comment":"користування","space_comment_unclear":false,"space_comment_hidden":false,"space_units":"м²","costs_rent":""}],"31":[{"space_hidden":false,"address_hidden":false,"region_hidden":true,"space_comment":"","space":"83.1","address":"","costs_property":"","costs_rent_comment":"користування","address_unclear":false,"space_units":"м²","costs_property_comment":"","costs_rent":""}],"33":[{"costs_rent":"","space_hidden":false,"costs_property":"","costs_rent_comment":"","region_hidden":true,"space_comment":"","costs_property_comment":"","space_units":"м²","space":"18.2","address":""}]},"intro":{"declaration_year":"2015"}}