{"income":{"5":{"value":"258397","value_unclear":false,"family_hidden":false,"family_comment":"","family":"343848","comment":""},"6":{"family_comment":"","value":"258397","family":"","comment":""},"7":{"family_comment":"","value":"","source_name":"","family":"","comment":""},"8":{"family_comment":"","value":"","family":"","comment":""},"9":{"family_comment":"","value":"","family":"","comment":""},"10":{"family_comment":"","value":"","family":"","comment":""},"11":{"family_comment":"","value":"","family_hidden":false,"comment":"","family":""},"12":{"family_comment":"","value":"","family":"","comment":""},"13":{"family_comment":"","value":"","family":"","comment":""},"14":{"family_comment":"","value":"","family":"","comment":""},"15":{"family_comment":"","value":"","family":"","comment":""},"16":{"family_comment":"","value":"","family":"","comment":""},"17":{"family_comment":"","value":"","family":"","comment":"","family_comment_unclear":false},"18":{"family_comment":"","value":"","family":"","comment":""},"19":{"family_comment":"","value":"","family":"","comment":""},"20":{"value":"","family_unclear":false,"family_hidden":false,"family_comment":"","family":"343848","comment":""}},"vehicle":{"35":[{"brand_info":"2","sum":"","brand":"Volkswagen Tiguan","sum_comment":"","brand_unclear":false,"year":"2010","brand_hidden":false,"brand_info_hidden":false,"brand_info_unclear":false,"sum_rent_comment":"","sum_rent":""}]},"id":"vulyk_103_51","declaration":{"date":"2016-03-29T00:00:00","additional_info_text":"","additional_info":"","url":"http://static.declarations.com.ua/declarations/chosen_ones/judges_batch/1275_popovych_olena_viktorivna.pdf"},"liabilities":{"54":{"sum_foreign_comment":"","sum_foreign_hidden":false,"sum_comment":"","sum_foreign_comment_hidden":false,"sum_hidden":false,"sum_foreign_comment_unclear":false,"sum_comment_hidden":true,"sum_unclear":false,"sum":"20187.39","sum_foreign":""},"55":{"sum_foreign_comment":"","sum":"","sum_comment":"","sum_foreign":""},"56":{"sum_foreign_comment":"","sum":"","sum_comment":"","sum_foreign":""},"57":{"sum_foreign_comment":"","sum_foreign_hidden":false,"sum_comment":"","sum_foreign_comment_hidden":false,"sum_hidden":false,"sum_comment_hidden":false,"sum":"","sum_foreign":""},"58":{"sum_foreign_comment":"","sum_foreign_hidden":false,"sum_comment":"","sum_foreign_comment_hidden":false,"sum_hidden":false,"sum_comment_hidden":false,"sum":"","sum_foreign":""},"59":{"sum_foreign_comment":"","sum_foreign_hidden":false,"sum_comment":"","sum_foreign_comment_hidden":false,"sum_hidden":false,"sum_comment_hidden":false,"sum":"","sum_foreign":""},"60":{"sum_foreign_comment":"","sum":"","sum_comment":"","sum_hidden":false,"sum_comment_hidden":false,"sum_foreign":""},"61":{"sum_foreign_comment":"","sum":"","sum_comment":"","sum_foreign":""},"62":{"sum_foreign_comment":"","sum_comment_hidden":false,"sum":"","sum_comment":"","sum_foreign":""},"63":{"sum_foreign_comment":"","sum":"","sum_comment":"","sum_foreign":""},"64":{"sum_foreign_comment":"","sum":"","sum_comment":"","sum_foreign":""}},"ft_src":"20187.39\nПопович Олена Вікторівна\nсуддя вищого спецiалiзованого суду україни з розгляду цивiльних і кримiнальних справ\nЗагальнодержавний регіон\nВищий спеціалізований суд з розгляду цивільних і кримінальних справ\nОлена\nПилипчук П. П\nПодружжя\nПилипчук О. П\nДитина\nПопович Олена Вікторівна\nОлена Вікторівна Попович\nОлена Попович\nПопович Олена Вікторівна\nПопович\nВікторівна\nVolkswagen Tiguan\n2\n2010\n82\n1000\n133\n2015\n258397\n343848\n258397\n343848\n2\n2010\nVolkswagen Tiguan\n1000\n82\n133\nПопович\nПопович Олена Вікторівна\nОлена Вікторівна Попович\nОлена Попович\nПопович Олена Вікторівна\nПопович Олена Вікторівна\nВікторівна\nПодружжя\nПилипчук П. П\nПилипчук О. П\nДитина\nОлена\nВищий спеціалізований суд з розгляду цивільних і кримінальних справ\nсуддя вищого спецiалiзованого суду україни з розгляду цивiльних і кримiнальних справ\nЗагальнодержавний регіон\n20187.39\n258397\n343848\n258397\n343848\n2015\n20187.39\nПодружжя\nПилипчук П. П\nДитина\nПилипчук О. П\nПопович\nВікторівна\nсуддя вищого спецiалiзованого суду україни з розгляду цивiльних і кримiнальних справ\nВищий спеціалізований суд з розгляду цивільних і кримінальних справ\nЗагальнодержавний регіон\nПопович Олена Вікторівна\nПопович Олена Вікторівна\nОлена Вікторівна Попович\nОлена Попович\nПопович Олена Вікторівна\nОлена\nVolkswagen Tiguan\n2\n2010\n343848\n258397\n343848\n258397\n82\n133\n1000\n2015","general":{"inn":"","inn_hidden":true,"last_name":"Попович","post":{"region":"Загальнодержавний регіон","region_unclear":false,"post":"суддя вищого спецiалiзованого суду україни з розгляду цивiльних і кримiнальних справ","office_unclear":false,"office":"Вищий спеціалізований суд з розгляду цивільних і кримінальних справ"},"name":"Олена","full_name":"Попович Олена Вікторівна","family_raw":"","addresses":[{"place_district":"","place_city_hidden":true,"place_city":"","place_city_type_hidden":false,"place_district_hidden":false,"place_city_type":"","place_address_hidden":true,"place_address":"","place_hidden":true,"place":""}],"family":[{"inn":"","relations":"Подружжя","relations_hidden":false,"inn_hidden":true,"relations_other":"","name_hidden":true,"family_name":"Пилипчук П. П","name_unclear":false},{"inn":"","family_name":"Пилипчук О. П","relations":"Дитина","inn_hidden":false,"relations_other":""}],"full_name_suggest":{"output":"Попович Олена Вікторівна","input":["Попович Олена Вікторівна","Олена Вікторівна Попович","Олена Попович"]},"patronymic":"Вікторівна"},"source":"VULYK","estate":{"25":[{"costs":"","costs_comment":"","address_hidden":false,"region_hidden":true,"space_comment":"","space":"133","address":"","region":"","costs_rent_comment":"","space_comment_unclear":false,"space_comment_hidden":false,"space_units":"м²","costs_rent":""}],"29":[{"space_hidden":false,"address_hidden":false,"region_hidden":true,"space_comment":"","space":"1000","address":"","region":"","costs_property":"","costs_rent_comment":"","space_units":"м²","costs_property_comment":"","costs_rent":""}],"31":[{"space_hidden":false,"address_hidden":false,"region_hidden":true,"space_comment":"","space":"82","address":"","costs_property":"","costs_rent_comment":"","address_unclear":false,"space_units":"м²","costs_property_comment":"","costs_rent":""}]},"intro":{"declaration_year":"2015"}}