{"income":{"5":{"value":"217180","value_unclear":false,"comment_hidden":false,"family_comment":"","family":"15384","comment":""},"6":{"family_comment":"","value":"217180","family":"4984","comment":"","value_hidden":false},"7":{"family_comment":"","value":"","source_name":"","family":"","comment":""},"8":{"family_comment":"","value":"","family":"","comment":""},"9":{"family_comment":"","value":"","comment_hidden":false,"family":"","comment":""},"10":{"family_comment":"","value":"","family":"","comment":""},"11":{"family_comment":"","value":"","family":"","comment":""},"12":{"family_comment":"","value":"","family":"","comment":""},"13":{"family_comment":"","value":"","family":"","comment":""},"14":{"family_comment":"","value":"","family":"","comment":""},"15":{"family_comment":"","value":"","family":"","comment":"","family_comment_hidden":false},"16":{"family_comment":"","value":"","family":"","comment":""},"17":{"family_comment":"","value":"","family":"","comment":""},"18":{"family_comment":"","value":"","family":"","comment":"","value_hidden":false},"19":{"family_comment":"","value":"","family":"","comment":""},"20":{"family_comment":"","value":"","family":"10400","comment":"","family_comment_unclear":false}},"vehicle":{"35":[{"brand_info":"1595 куб. см., 75 кВт","sum_rent_comment":"","brand":"Skoda Octavia A5","sum_comment":"","year":"2007","sum":"","sum_rent":""}]},"id":"vulyk_78_23","declaration":{"additional_info_text":"","notfull_lostpages":"","date":"2015-03-30T00:00:00","notfull":"","additional_info":"","url":"http://static.declarations.com.ua/declarations/chosen_ones/judges_batch/2090_hrushko_oleksandr_petrovych.pdf"},"liabilities":{"54":{"sum_foreign_comment":"","sum_foreign_hidden":false,"sum_comment":"","sum_comment_unclear":false,"sum_hidden":false,"sum_comment_hidden":false,"sum":"","sum_foreign":""},"55":{"sum_foreign_comment":"","sum":"","sum_comment":"","sum_foreign":""},"56":{"sum_foreign_comment":"","sum":"","sum_comment":"","sum_foreign":""},"57":{"sum_foreign_comment":"","sum":"","sum_comment":"","sum_foreign":""},"58":{"sum_foreign_comment":"","sum":"","sum_comment":"","sum_unclear":false,"sum_foreign":""},"59":{"sum_foreign_comment":"","sum":"","sum_comment":"","sum_foreign":""},"60":{"sum_foreign_comment":"","sum":"","sum_comment":"","sum_comment_unclear":false,"sum_comment_hidden":false,"sum_foreign":""},"61":{"sum_foreign_comment":"","sum":"","sum_comment":"","sum_foreign":""},"62":{"sum_foreign_comment":"","sum":"","sum_hidden":false,"sum_comment":"","sum_foreign":""},"63":{"sum_foreign_comment":"","sum_foreign_hidden":false,"sum_comment":"","sum":"","sum_unclear":false,"sum_foreign":""},"64":{"sum_foreign_comment":"","sum_foreign_hidden":false,"sum_comment":"","sum_hidden":false,"sum":"","sum_foreign":""}},"ft_src":"суддя, заступник голови коропського районного суду чернігівської області\nЧернігівська область\nЗагальний місцевий суд\nОлександр\nГрушко Т. А., 21. 01. 1985 р. н\nПодружжя\nГрушко О. О., 15. 11. 2007 р. н\nДитина\nГрушко Т. О., 30. 08. 2011 р. н\nДитина\nПетрович\nГрушко Олександр Петрович\nОлександр Петрович Грушко\nОлександр Грушко\nГрушко Олександр Петрович\nГрушко\nГрушко Олександр Петрович\nКороп\nСМТ\n16200\nЧернігівська область\n1595 куб. см., 75 кВт\n2007\nSkoda Octavia A5\n1/3 будинку\nЧернігівська область\nМенський р-н, смт. Березна\n50.6\nЧернігівська область\nсмт. Короп\n72.1\n2014\n4984\n217180\n15384\n217180\n10400\n1595 куб. см., 75 кВт\n2007\nSkoda Octavia A5\n2014\nПодружжя\nГрушко Т. А., 21. 01. 1985 р. н\nДитина\nГрушко О. О., 15. 11. 2007 р. н\nДитина\nГрушко Т. О., 30. 08. 2011 р. н\nГрушко Олександр Петрович\nОлександр Петрович Грушко\nОлександр Грушко\nГрушко Олександр Петрович\nГрушко Олександр Петрович\nОлександр\nПетрович\nЗагальний місцевий суд\nсуддя, заступник голови коропського районного суду чернігівської області\nЧернігівська область\nГрушко\nСМТ\n16200\nЧернігівська область\nКороп\n217180\n4984\n10400\n217180\n15384\n1/3 будинку\nМенський р-н, смт. Березна\nЧернігівська область\n50.6\n72.1\nЧернігівська область\nсмт. Короп\nПодружжя\nГрушко Т. А., 21. 01. 1985 р. н\nДитина\nГрушко О. О., 15. 11. 2007 р. н\nДитина\nГрушко Т. О., 30. 08. 2011 р. н\nПетрович\nГрушко\nОлександр\nГрушко Олександр Петрович\nОлександр Петрович Грушко\nОлександр Грушко\nГрушко Олександр Петрович\nСМТ\nЧернігівська область\nКороп\n16200\nЧернігівська область\nсуддя, заступник голови коропського районного суду чернігівської області\nЗагальний місцевий суд\nГрушко Олександр Петрович\nSkoda Octavia A5\n1595 куб. см., 75 кВт\n2007\n10400\n217180\n15384\n4984\n217180\n1/3 будинку\nМенський р-н, смт. Березна\nЧернігівська область\n50.6\nсмт. Короп\nЧернігівська область\n72.1\n2014","general":{"inn":"","name":"Олександр","family":[{"inn":"","relations":"Подружжя","relations_other":"","inn_hidden":true,"family_name":"Грушко Т. А., 21. 01. 1985 р. н","name_hidden":false,"name_unclear":false},{"inn":"","relations":"Дитина","relations_other":"","inn_hidden":false,"family_name":"Грушко О. О., 15. 11. 2007 р. н","name_hidden":false,"name_unclear":false},{"inn":"","relations":"Дитина","relations_other":"","inn_hidden":false,"family_name":"Грушко Т. О., 30. 08. 2011 р. н","name_unclear":false}],"patronymic":"Петрович","inn_hidden":true,"family_raw":"","last_name":"Грушко","post":{"post_unclear":false,"post":"суддя, заступник голови коропського районного суду чернігівської області","post_hidden":false,"region":"Чернігівська область","region_hidden":false,"office":"Загальний місцевий суд","office_hidden":false},"last_name_unclear":false,"full_name":"Грушко Олександр Петрович","addresses":[{"place_district":"","place_city_hidden":false,"place_city":"Короп","place_city_type_hidden":false,"place_district_hidden":false,"place_city_type":"СМТ","place_address_hidden":true,"place_address":"16200","place_hidden":true,"place":"Чернігівська область"}],"full_name_suggest":{"output":"Грушко Олександр Петрович","input":["Грушко Олександр Петрович","Олександр Петрович Грушко","Олександр Грушко"]},"name_unclear":false},"source":"VULYK","estate":{"25":[{"space_hidden":false,"costs":"","costs_comment":"","address_hidden":false,"region_hidden":false,"space_comment":"","space":"72.1","address":"смт. Короп","region":"Чернігівська область","address_unclear":false,"costs_rent_comment":"","space_units":"м²","costs_rent":""}],"30":[{"space_hidden":false,"address_hidden":false,"region_hidden":false,"space_comment":"1/3 будинку","space":"50.6","address":"Менський р-н, смт. Березна","region":"Чернігівська область","costs_property":"","costs_rent_comment":"","space_units":"м²","costs_property_comment":"","costs_rent":""}]},"intro":{"declaration_year":"2014"}}