{"income":{"5":{"value":"300407","family_comment":"","comment_unclear":false,"family_unclear":false,"family":"","comment":""},"6":{"family_comment":"","value":"275966","family":"","comment":""},"7":{"source_name_unclear":false,"value":"","comment_unclear":false,"family_comment":"","source_name":"","family":"","comment":""},"8":{"family_comment":"","value":"","family":"","comment":""},"9":{"family_comment":"","value":"","family":"","comment":""},"10":{"family_comment":"","value":"","family":"","comment":""},"11":{"family_comment":"","value":"","family":"","comment":""},"12":{"family_comment":"","value":"","family":"","comment":""},"13":{"family_comment":"","value":"","family":"","comment":""},"14":{"family_comment":"","value":"","family":"","comment":""},"15":{"family_comment":"","value":"","family":"","comment":""},"16":{"family_comment":"","family_unclear":false,"value":"","family":"","comment":""},"17":{"family_comment":"","value":"","family":"","comment":""},"18":{"family_comment":"","value":"","family":"","comment":""},"19":{"family_comment":"","value":"","family":"","comment":""},"20":{"value":"24441","family_comment":"","comment_unclear":false,"family_unclear":false,"family":"","comment":"","family_comment_unclear":false}},"id":"vulyk_107_124","declaration":{"additional_info_text":"","notfull_lostpages":"","date":"2016-03-24T00:00:00","notfull":"","additional_info":"","url":"http://static.declarations.com.ua/declarations/chosen_ones/judges_batch/2103_kostruba_halyna_ivanivna.pdf"},"liabilities":{"54":{"sum_foreign_comment":"","sum":"","sum_comment":"","sum_comment_unclear":false,"sum_comment_hidden":false,"sum_foreign":""},"55":{"sum_foreign_comment":"","sum":"","sum_comment":"","sum_foreign":""},"56":{"sum_foreign_comment":"","sum":"","sum_comment":"","sum_unclear":false,"sum_foreign":""},"57":{"sum_foreign_comment":"","sum":"60000","sum_comment":"","sum_comment_unclear":false,"sum_foreign":""},"58":{"sum_foreign_comment":"","sum":"12000","sum_comment":"","sum_comment_unclear":false,"sum_unclear":false,"sum_foreign":""},"59":{"sum_foreign_comment":"","sum":"","sum_comment":"","sum_unclear":false,"sum_foreign":""},"60":{"sum_foreign_comment":"","sum":"","sum_comment":"","sum_comment_unclear":false,"sum_comment_hidden":false,"sum_foreign":""},"61":{"sum_foreign_comment":"","sum":"","sum_comment":"","sum_foreign":""},"62":{"sum_foreign_comment":"","sum":"","sum_comment":"","sum_foreign":""},"63":{"sum_foreign_comment":"","sum":"","sum_comment":"","sum_foreign":""},"64":{"sum_foreign_comment":"","sum":"","sum_comment":"","sum_foreign":""}},"ft_src":"60000\n12000\nКоструба Галина Іванівна\nсуддя апеляційного суду тернопільської області\nТернопільська область\nЗагальний апеляційний суд\nГалина\nКоструба Галина Іванівна\nГалина Іванівна Коструба\nГалина Коструба\nКоструба Галина Іванівна\nКоструба\nІванівна\n24441\n300407\n275966\n2015\n275966\n300407\n24441\n275966\n24441\n300407\nКоструба\nКоструба Галина Іванівна\nГалина Іванівна Коструба\nГалина Коструба\nКоструба Галина Іванівна\nГалина\nІванівна\nКоструба Галина Іванівна\nЗагальний апеляційний суд\nсуддя апеляційного суду тернопільської області\nТернопільська область\n60000\n12000\n2015\n12000\n60000\nКоструба\nІванівна\nсуддя апеляційного суду тернопільської області\nТернопільська область\nЗагальний апеляційний суд\nКоструба Галина Іванівна\nКоструба Галина Іванівна\nГалина Іванівна Коструба\nГалина Коструба\nКоструба Галина Іванівна\nГалина\n2015","general":{"inn":"","inn_hidden":true,"last_name":"Коструба","post":{"post_unclear":false,"office":"Загальний апеляційний суд","post":"суддя апеляційного суду тернопільської області","region":"Тернопільська область"},"name":"Галина","full_name":"Коструба Галина Іванівна","family_raw":"","addresses":[{"place_district":"","place_city_hidden":true,"place_city":"","place_city_type_hidden":true,"place_district_hidden":true,"place_city_type":"","place_address_hidden":true,"place_address":"","place_hidden":true,"place":""}],"full_name_suggest":{"output":"Коструба Галина Іванівна","input":["Коструба Галина Іванівна","Галина Іванівна Коструба","Галина Коструба"]},"patronymic":"Іванівна"},"source":"VULYK","intro":{"declaration_year":"2015","isnotdeclaration":""}}