{"income":{"5":{"value":"258619","value_unclear":false,"family_hidden":false,"family_comment":"","family":"","comment":""},"6":{"family_comment":"","value":"243963","value_unclear":false,"family":"","comment":""},"7":{"source_name_unclear":false,"value":"","family_comment":"","source_name":"","family":"","comment":"","source_name_hidden":false},"8":{"family_comment":"","value":"","family":"","comment":""},"9":{"family_comment":"","value":"16","comment_unclear":false,"family":"","comment":""},"10":{"family_comment":"","value":"14616","family":"","comment":""},"11":{"family_comment":"","family_unclear":false,"value":"24","family":"","comment":""},"12":{"family_comment":"","value":"","family":"","comment":""},"13":{"family_comment":"","value":"","family":"","comment":""},"14":{"family_comment":"","value":"","family":"","comment":""},"15":{"family_comment":"","value":"","family":"","comment":""},"16":{"family_comment":"","value":"","family":"","comment":""},"17":{"family_comment":"","value":"","family":"","comment":""},"18":{"family_comment":"","value":"","family":"","comment":""},"19":{"family_comment":"","value":"","family":"","comment":""},"20":{"value":"","value_unclear":false,"family_comment":"","comment_unclear":false,"comment":"","family":""}},"id":"vulyk_94_33","banks":{"45":[{"sum_foreign_comment":"","sum_unclear":false,"sum_units":"UAH","sum_comment":"","sum_hidden":false,"sum_foreign_units":"UAH","sum_units_unclear":false,"sum_comment_hidden":true,"sum_units_hidden":false,"sum":"87","sum_foreign":""}]},"declaration":{"additional_info_text":"","notfull_lostpages":"","date":"2015-03-31T00:00:00","notfull":"","additional_info":"","url":"http://static.declarations.com.ua/declarations/chosen_ones/judges_batch/3679_ivanenko_iana_leonidivna.pdf"},"liabilities":{"54":{"sum_foreign_comment":"","sum":"","sum_comment":"","sum_comment_unclear":false,"sum_comment_hidden":false,"sum_unclear":false,"sum_foreign":""},"55":{"sum_foreign_comment":"","sum":"","sum_comment":"","sum_foreign":""},"56":{"sum_foreign_comment":"","sum":"","sum_comment":"","sum_unclear":false,"sum_foreign":""},"57":{"sum_foreign_comment":"","sum":"","sum_comment":"","sum_hidden":false,"sum_unclear":false,"sum_foreign":""},"58":{"sum_foreign_comment":"","sum":"","sum_comment":"","sum_hidden":false,"sum_unclear":false,"sum_foreign":""},"59":{"sum_foreign_comment":"","sum":"","sum_comment":"","sum_foreign":""},"60":{"sum_foreign_comment":"","sum_comment_hidden":false,"sum":"","sum_comment":"","sum_foreign":""},"61":{"sum_foreign_comment":"","sum":"","sum_comment":"","sum_foreign":""},"62":{"sum_foreign_comment":"","sum":"","sum_hidden":false,"sum_comment":"","sum_foreign":""},"63":{"sum_foreign_comment":"","sum_comment_hidden":false,"sum":"","sum_comment":"","sum_foreign":""},"64":{"sum_foreign_comment":"","sum":"","sum_comment":"","sum_unclear":false,"sum_foreign":""}},"ft_src":"суддя вищого адміністративного суду україни\nЗагальнодержавний регіон\nВищий адміністративний суд України\nЯна\nДитина\nЛеонідівна\nІваненко Яна Леонідівна\nЯна Леонідівна Іваненко\nЯна Іваненко\nІваненко Яна Леонідівна\nІваненко Яна Леонідівна\nІваненко\n.15\n272.9\nкористування\n142\n87\n2014\n2014\nДитина\nІваненко Яна Леонідівна\nЯна Леонідівна Іваненко\nЯна Іваненко\nІваненко Яна Леонідівна\nІваненко Яна Леонідівна\nЯна\nЛеонідівна\nВищий адміністративний суд України\nЗагальнодержавний регіон\nсуддя вищого адміністративного суду україни\nІваненко\n243963\n258619\n24\n14616\n16\n.15\n272.9\n142\nкористування\n87\n243963\n24\n14616\n258619\n16\nДитина\nЛеонідівна\nІваненко\nЯна\nІваненко Яна Леонідівна\nЯна Леонідівна Іваненко\nЯна Іваненко\nІваненко Яна Леонідівна\nЗагальнодержавний регіон\nВищий адміністративний суд України\nсуддя вищого адміністративного суду україни\nІваненко Яна Леонідівна\n24\n14616\n258619\n16\n243963\nкористування\n142\n.15\n272.9\n87\n2014","general":{"inn":"","name":"Яна","last_name":"Іваненко","family":[{"inn":"","relations":"Дитина","relations_hidden":false,"inn_hidden":true,"family_name":"","name_hidden":true,"name_unclear":false}],"inn_hidden":true,"family_raw":"","inn_unclear":false,"post":{"post_unclear":false,"region_unclear":false,"post":"суддя вищого адміністративного суду україни","candidate":"","post_hidden":false,"region":"Загальнодержавний регіон","office":"Вищий адміністративний суд України","office_unclear":false},"full_name":"Іваненко Яна Леонідівна","addresses":[{"place_district":"","place_address_hidden":true,"place_city":"","place_city_type_hidden":true,"place_district_hidden":true,"place_city_type":"","place_city_hidden":false,"place_address":"","place_hidden":true,"place":""}],"patronymic":"Леонідівна","patronymic_hidden":false,"full_name_suggest":{"output":"Іваненко Яна Леонідівна","input":["Іваненко Яна Леонідівна","Яна Леонідівна Іваненко","Яна Іваненко"]}},"source":"VULYK","estate":{"23":[{"region_unclear":false,"space_unclear":false,"costs":"","costs_comment":"","address_hidden":false,"region_hidden":true,"space_comment":"","space_hidden":false,"space":".15","address":"","region":"","address_unclear":false,"space_units_unclear":false,"costs_rent_hidden":false,"costs_rent_comment_hidden":false,"space_units":"га","costs_rent":"","costs_rent_comment":""}],"24":[{"space_unclear":false,"costs":"","costs_comment":"","address_hidden":false,"region_hidden":true,"space_comment":"","space_hidden":false,"space":"272.9","address":"","region":"","costs_rent_comment":"","costs_rent_hidden":false,"costs_rent_comment_hidden":false,"space_units":"м²","costs_rent":""}],"25":[{"region_unclear":false,"space_unclear":false,"costs":"","costs_comment":"","address_hidden":false,"region_hidden":true,"space_comment":"користування","space_hidden":false,"space":"142","address":"","region":"","address_unclear":false,"costs_rent_comment":"","costs_rent_hidden":false,"space_comment_unclear":false,"costs_rent_comment_hidden":false,"space_units":"м²","costs_rent":""}]},"intro":{"declaration_year":"2014","isnotdeclaration":""}}