{"income":{"5":{"family_comment":"","value":"202970.23","family":"313670","comment":""},"6":{"family_comment":"","value":"190790.23","family":"","comment":""},"7":{"value":"","comment_hidden":false,"family_comment":"","source_name":"","family":"","comment":"","source_name_hidden":false},"8":{"family_comment":"","value":"","family_hidden":false,"comment":"","family":""},"9":{"value":"","family_comment":"","value_unclear":false,"family_unclear":false,"family":"","comment":""},"10":{"family_comment":"","value":"12180","family":"9600","comment":""},"11":{"family_comment":"","value":"","family":"","comment":""},"12":{"family_comment":"","value":"","family":"","comment":""},"13":{"family_comment":"","value":"","family":"","comment":""},"14":{"family_comment":"","value":"","family":"300002","comment":""},"15":{"family_comment":"","value":"","family":"","comment":""},"16":{"family_comment":"","value":"","family":"","comment":""},"17":{"family_comment":"","value":"","family":"","comment":""},"18":{"family_comment":"","value":"","family":"","comment":""},"19":{"family_comment":"","value":"","family":"","comment":""},"20":{"value":"","value_unclear":false,"family_hidden":false,"family_comment":"допомога на поховання","family":"4070","comment":""}},"vehicle":{"35":[{"brand_info":"об'єм двигуна 2.7","sum_rent_comment":"","year":"2008","brand_info_hidden":false,"brand_info_unclear":false,"year_unclear":true,"sum_rent":"","sum":"","brand":"Mercedes ML","sum_comment":"","sum_comment_unclear":false,"brand_hidden":false,"brand_unclear":false}],"40":[{"brand_info":"об'єм 1.6","sum_rent_comment":"","brand":"Renault Logan","sum_comment":"","year":"2011","brand_info_unclear":false,"sum":"","sum_rent":""}]},"id":"vulyk_109_118","declaration":{"additional_info_text":"","notfull_lostpages":"","date":"2016-03-17T00:00:00","notfull":"","additional_info":"","url":"http://static.declarations.com.ua/declarations/chosen_ones/judges_batch/2575_zaverukha_serhii_volodymyrovych_2015.pdf"},"liabilities":{"54":{"sum_foreign_comment":"","sum":"900","sum_comment":"","sum_hidden":false,"sum_comment_hidden":false,"sum_unclear":false,"sum_foreign":""},"55":{"sum_foreign_comment":"","sum":"","sum_comment":"","sum_comment_unclear":false,"sum_foreign":""},"56":{"sum_foreign_comment":"","sum":"6700","sum_comment":"","sum_foreign":""},"57":{"sum_foreign_comment":"","sum_comment_hidden":false,"sum":"","sum_comment":"","sum_foreign":""},"58":{"sum_foreign_comment":"","sum_comment_hidden":false,"sum":"","sum_comment":"","sum_foreign":""},"59":{"sum_foreign_comment":"","sum":"","sum_comment":"","sum_foreign":""},"60":{"sum_foreign_comment":"","sum":"700","sum_comment":"","sum_foreign":""},"61":{"sum_foreign_comment":"","sum":"","sum_comment":"","sum_foreign":""},"62":{"sum_foreign_comment":"","sum":"7200","sum_comment":"","sum_foreign":""},"63":{"sum_foreign_comment":"","sum":"","sum_comment":"","sum_foreign":""},"64":{"sum_foreign_comment":"","sum":"","sum_comment":"","sum_foreign":""}},"ft_src":"7200\n900\n6700\n700\nсуддя господарського суду хмельницької області\nХмельницька область\nГосподарський місцевий суд\nСергій\nЗаверуха Тетяна Миколаївна\nПодружжя\nЗаверуха Валерія Сергіївна\nДитина\nЗаверуха Анна Сергіївна\nДитина\nВолодимирович\nЗаверуха Сергій Володимирович\nЗаверуха\nЗаверуха Сергій Володимирович\nСергій Володимирович Заверуха\nСергій Заверуха\nЗаверуха Сергій Володимирович\nоб'єм двигуна 2.7\nMercedes ML\n2008\nоб'єм 1.6\n2011\nRenault Logan\n34.1\n19.4\n.0919\n.0589\n22.8\n20.7\n.0021\n51.8\n39.1\n1/4 частина приватизованої квартири\n48.8\n2015\n190790.23\n300002\n9600\n12180\n313670\n202970.23\nдопомога на поховання\n4070\nоб'єм двигуна 2.7\nMercedes ML\n2008\nоб'єм 1.6\n2011\nRenault Logan\n2015\nПодружжя\nЗаверуха Тетяна Миколаївна\nДитина\nЗаверуха Валерія Сергіївна\nДитина\nЗаверуха Анна Сергіївна\nЗаверуха Сергій Володимирович\nСергій Володимирович Заверуха\nСергій Заверуха\nЗаверуха Сергій Володимирович\nСергій\nЗаверуха Сергій Володимирович\nЗаверуха\nГосподарський місцевий суд\nХмельницька область\nсуддя господарського суду хмельницької області\nВолодимирович\n900\n700\n6700\n7200\n190790.23\nдопомога на поховання\n4070\n300002\n202970.23\n313670\n12180\n9600\n34.1\n19.4\n48.8\n1/4 частина приватизованої квартири\n20.7\n.0021\n.0919\n.0589\n51.8\n39.1\n22.8\n900\n6700\n7200\n700\nПодружжя\nЗаверуха Тетяна Миколаївна\nДитина\nЗаверуха Валерія Сергіївна\nДитина\nЗаверуха Анна Сергіївна\nСергій\nВолодимирович\nЗаверуха\nЗаверуха Сергій Володимирович\nСергій Володимирович Заверуха\nСергій Заверуха\nЗаверуха Сергій Володимирович\nХмельницька область\nГосподарський місцевий суд\nсуддя господарського суду хмельницької області\nЗаверуха Сергій Володимирович\n2008\nMercedes ML\nоб'єм двигуна 2.7\n2011\nоб'єм 1.6\nRenault Logan\n300002\n9600\n12180\nдопомога на поховання\n4070\n313670\n202970.23\n190790.23\n51.8\n39.1\n.0021\n22.8\n34.1\n19.4\n20.7\n1/4 частина приватизованої квартири\n48.8\n.0919\n.0589\n2015","general":{"name_hidden":false,"name":"Сергій","inn":"","inn_unclear":false,"family":[{"inn":"","relations":"Подружжя","relations_hidden":false,"inn_hidden":false,"relations_other":"","name_hidden":false,"family_name":"Заверуха Тетяна Миколаївна","name_unclear":false},{"inn":"","relations":"Дитина","relations_other":"","inn_hidden":false,"family_name":"Заверуха Валерія Сергіївна","name_hidden":false,"name_unclear":false},{"inn":"","relations":"Дитина","relations_other":"","inn_hidden":false,"family_name":"Заверуха Анна Сергіївна","name_hidden":false,"name_unclear":false}],"inn_hidden":false,"family_raw":"","last_name":"Заверуха","post":{"region_unclear":false,"region":"Хмельницька область","post":"суддя господарського суду хмельницької області","region_hidden":false,"office":"Господарський місцевий суд","office_hidden":false,"office_unclear":false},"full_name":"Заверуха Сергій Володимирович","patronymic":"Володимирович","full_name_suggest":{"output":"Заверуха Сергій Володимирович","input":["Заверуха Сергій Володимирович","Сергій Володимирович Заверуха","Сергій Заверуха"]}},"source":"VULYK","estate":{"23":[{"space_unclear":false,"costs":"","costs_rent_unclear":false,"costs_comment":"","address_hidden":false,"region_hidden":false,"space_comment":"","space":".0021","address":"","region":"","costs_rent_comment":"","space_units":"га","costs_rent":""}],"25":[{"space_unclear":false,"costs":"","costs_comment":"","address_hidden":false,"region_hidden":false,"space_comment":"1/4 частина приватизованої квартири","space_hidden":false,"space":"48.8","address":"","region":"","costs_rent_comment":"","space_units":"м²","space_units_hidden":false,"costs_rent":""}],"27":[{"space_unclear":false,"costs":"","costs_rent_unclear":false,"costs_comment":"","address_hidden":false,"region_hidden":false,"space_comment":"","space":"34.1","address":"","region":"","costs_rent_comment":"","space_units":"м²","costs_rent":""},{"costs_rent":"","space_unclear":false,"region":"","costs":"","costs_rent_comment":"","costs_comment":"","region_hidden":false,"space_comment":"","space_units":"м²","space":"19.4","address":""}],"29":[{"space_unclear":false,"address_hidden":true,"region_hidden":false,"space_comment":"","space":".0919","address":"","region":"","costs_property":"","costs_rent_comment":"","space_units":"га","costs_property_comment":"","costs_rent":""},{"costs_rent":"","costs_property":"","costs_rent_comment":"","space_comment":"","costs_property_comment":"","space_units":"га","space":".0589","address":""}],"31":[{"space_hidden":false,"costs_property_comment":"","address_hidden":true,"region_hidden":false,"space_comment":"","space":"51.8","address":"","region":"","costs_property":"","costs_rent_comment":"","space_units":"м²","space_units_hidden":false,"costs_rent":""},{"costs_rent":"","region":"","costs_property":"","costs_rent_comment":"","space_comment":"","costs_property_comment":"","space_units":"м²","space":"39.1","address":""}],"32":[{"costs_rent":"","region":"","costs_property":"","costs_rent_comment":"","address_hidden":true,"region_hidden":false,"space_comment":"","costs_property_comment":"","space_units":"м²","space":"22.8","address":""}],"33":[{"costs_rent":"","costs_property":"","costs_rent_comment":"","address_hidden":true,"region_hidden":false,"space_comment":"","costs_property_comment":"","space_units":"м²","space":"20.7","address":""}]},"intro":{"declaration_year":"2015","isnotdeclaration":""}}