{"income":{"5":{"family_comment":"","value":"260961","family":"12301","comment":""},"6":{"family_comment":"","value":"244287","family":"","comment":"","family_hidden":false},"7":{"family_comment":"","value":"","source_name":"","family":"","comment":""},"8":{"family_comment":"","value":"","family":"","comment":""},"9":{"value":"","value_unclear":false,"family_hidden":false,"family_comment":"","family":"","comment":""},"10":{"value":"12617","family_comment":"","family_hidden":false,"value_hidden":false,"family_unclear":false,"family":"","comment":""},"11":{"family_comment":"","value":"","family":"","comment":""},"12":{"family_comment":"","value":"","family":"","comment":""},"13":{"family_comment":"","value":"","family":"","comment":""},"14":{"family_comment":"","value":"","family":"","comment":""},"15":{"family_comment":"","value":"4057","family":"","comment":""},"16":{"family_comment":"","value":"","family":"","comment":""},"17":{"family_comment":"","value":"","family":"","comment":""},"18":{"family_comment":"","value":"","family":"","comment":""},"19":{"family_comment":"","value":"","family":"","comment":""},"20":{"value":"","comment_unclear":false,"family_comment":"пенсія","family":"12301","comment":"","family_comment_unclear":false}},"vehicle":{"35":[{"brand_info":"3456 куб. см.","sum":"","brand":"Toyota Highlander","sum_comment":"","brand_unclear":false,"year":"2012","brand_hidden":false,"brand_info_unclear":false,"sum_rent_comment":"","sum_rent":"","sum_unclear":false}]},"id":"vulyk_75_141","banks":{"51":[{"sum_foreign_comment":"","sum":"120","sum_comment":"","sum_foreign_units":"UAH","sum_units":"UAH","sum_foreign":""},{"sum_foreign_comment":"","sum_units":"UAH","sum_comment":"","sum":"3700","sum_foreign":""}]},"declaration":{"additional_info_text":"Пункт 54. Добровільне страхування 30142 грн., з них: 28384 грн. Аска, 1758грн. Оранта. Пункт 57. Погашення основної суми позики (кредиту) : 170535 грн., з них: 80102грн. ПУМБ, 53620 грн. БРР, 36813 грн. ПУМБ","notfull_lostpages":"","date":"2014-03-28T00:00:00","notfull":"","additional_info":"1","url":"http://static.declarations.com.ua/declarations/chosen_ones/judges_batch/1794_melnychuk_volodymyr_petrovych.pdf"},"liabilities":{"54":{"sum_foreign_comment":"","sum":"30142","sum_comment":"","sum_foreign":""},"55":{"sum_foreign_comment":"","sum":"","sum_comment":"","sum_foreign":""},"56":{"sum_foreign_comment":"","sum":"","sum_comment":"","sum_foreign":""},"57":{"sum_foreign_comment":"","sum":"133722","sum_comment":"","sum_foreign":""},"58":{"sum_foreign_comment":"","sum":"36813","sum_comment":"","sum_foreign":""},"59":{"sum_foreign_comment":"","sum":"","sum_comment":"","sum_comment_unclear":false,"sum_unclear":false,"sum_foreign":""},"60":{"sum_foreign_comment":"","sum":"","sum_comment":"","sum_foreign":""},"61":{"sum_foreign_comment":"","sum":"","sum_comment":"","sum_foreign":""},"62":{"sum_foreign_comment":"","sum":"","sum_comment":"","sum_unclear":false,"sum_foreign":""},"63":{"sum_foreign_comment":"","sum":"","sum_comment":"","sum_foreign":""},"64":{"sum_foreign_comment":"","sum":"","sum_comment":"","sum_foreign":""}},"ft_src":"Toyota Highlander\n3456 куб. см.\n2012\n120\n3700\n1\nПункт 54. Добровільне страхування 30142 грн., з них: 28384 грн. Аска, 1758грн. Оранта. Пункт 57. Погашення основної суми позики (кредиту) : 170535 грн., з них: 80102грн. ПУМБ, 53620 грн. БРР, 36813 грн. ПУМБ\n2013\n3456 куб. см.\n2012\nToyota Highlander\nПункт 54. Добровільне страхування 30142 грн., з них: 28384 грн. Аска, 1758грн. Оранта. Пункт 57. Погашення основної суми позики (кредиту) : 170535 грн., з них: 80102грн. ПУМБ, 53620 грн. БРР, 36813 грн. ПУМБ\n1\n120\n3700\n2013\nМельничук\nПетрович\nПодружжя\nМельничук М. І\nМельничук Володимир Петрович\nВолодимир Петрович Мельничук\nВолодимир Мельничук\nМельничук Володимир Петрович\nВолодимир\nМельничук Володимир Петрович\nАпеляційний адміністративний суд\nсуддя київського апеляційного адміністративного суду\nм. Київ\n36813\n30142\n133722\n244287\nпенсія\n12301\n4057\n260961\n12301\n12617\n1900\n26\n1/4\n281.9\n36813\n133722\n30142\n281.9\n1/4\n26\n1900\nМельничук М. І\nПодружжя\nМельничук\nПетрович\nсуддя київського апеляційного адміністративного суду\nм. Київ\nАпеляційний адміністративний суд\nМельничук Володимир Петрович\nМельничук Володимир Петрович\nВолодимир Петрович Мельничук\nВолодимир Мельничук\nМельничук Володимир Петрович\nВолодимир\n244287\n4057\n12617\n12301\n260961\nпенсія\n12301","general":{"inn_hidden":true,"inn":"","last_name":"Мельничук","post":{"office":"Апеляційний адміністративний суд","region":"м. Київ","post":"суддя київського апеляційного адміністративного суду"},"name":"Володимир","full_name":"Мельничук Володимир Петрович","family_raw":"","addresses":[{"place_district":"","place_address_hidden":false,"place_hidden":true,"place_address":"","place_district_hidden":false,"place_city_type":"","place_city_hidden":false,"place_city_type_hidden":false,"place_city":"","place":""}],"family":[{"inn":"","inn_hidden":false,"relations_hidden":false,"family_name":"Мельничук М. І","relations_other":"","relations":"Подружжя","name_hidden":false,"name_unclear":false}],"full_name_suggest":{"output":"Мельничук Володимир Петрович","input":["Мельничук Володимир Петрович","Володимир Петрович Мельничук","Володимир Мельничук"]},"patronymic":"Петрович"},"source":"VULYK","estate":{"25":[{"space_unclear":false,"costs":"","costs_comment":"","address_hidden":false,"region_hidden":true,"space_comment":"","space_hidden":true,"space":"","address":"","region":"","costs_rent_comment":"","space_units":"м²","costs_rent":""}],"29":[{"space_units_unclear":false,"address_hidden":false,"region_hidden":true,"space_comment":"","space":"1900","address":"","region":"","costs_property":"","costs_rent_comment":"","space_units":"м²","costs_property_comment":"","costs_rent":""}],"30":[{"costs_rent":"","region":"","costs_property":"","costs_rent_comment":"","region_hidden":true,"space_comment":"1/4","costs_property_comment":"","space_units":"м²","space":"26","address":""}],"31":[{"space_unclear":false,"address_hidden":false,"region_hidden":true,"space_comment":"","space":"281.9","address":"","region":"","costs_property":"","costs_rent_comment":"","space_units":"м²","costs_property_comment":"","costs_rent":""}]},"intro":{"declaration_year":"2013","isnotdeclaration":""}}