{"income":{"5":{"family_comment":"","value":"555580","family":"9482","comment":""},"6":{"family_comment":"","value":"231319","value_unclear":false,"family":"9482","comment":""},"7":{"value":"","family_comment":"","source_name":"","family":"","comment":"","source_name_hidden":false},"8":{"family_comment":"","value":"","family":"","comment":""},"9":{"family_comment":"","value":"","family":"","comment":""},"10":{"family_comment":"","value":"","family":"","comment":""},"11":{"family_comment":"","value":"","comment_hidden":false,"family":"","comment":""},"12":{"family_comment":"","value":"","family":"","comment":""},"13":{"family_comment":"","value":"","family":"","comment":""},"14":{"family_comment":"","value":"","family":"","comment":""},"15":{"value":"15976","family_comment":"","value_unclear":false,"family_unclear":false,"family":"","comment":""},"16":{"family_comment":"","value":"308285","family":"","comment":""},"17":{"family_comment":"","value":"","family":"","comment":""},"18":{"family_comment":"","value":"","family":"","comment":""},"19":{"family_comment":"","value":"","family":"","comment":""},"20":{"family_comment":"","value":"","comment_unclear":false,"family":"","comment":""}},"vehicle":{"35":[{"brand_info":"2.0 ТДІ","sum_rent_comment":"","brand":"Volkswagen Tiguan","sum_comment":"","year":"2015","brand_hidden":false,"brand_info_unclear":false,"sum":"986406","sum_rent":""}]},"id":"vulyk_104_43","declaration":{"date":"2016-03-31T00:00:00","additional_info_text":"","additional_info":"","url":"http://static.declarations.com.ua/declarations/chosen_ones/judges_batch/1841_kropyvna_liudmyla_volodymyrivna_2015.pdf"},"liabilities":{"54":{"sum_foreign_comment":"","sum_foreign_hidden":false,"sum_comment":"","sum_hidden":false,"sum_comment_hidden":true,"sum_unclear":false,"sum":"39061","sum_foreign":""},"55":{"sum_foreign_comment":"","sum":"","sum_comment":"","sum_foreign":""},"56":{"sum_foreign_comment":"","sum":"","sum_comment":"","sum_unclear":false,"sum_foreign":""},"57":{"sum_foreign_comment":"","sum_foreign_hidden":false,"sum_comment":"","sum_comment_unclear":false,"sum_comment_hidden":false,"sum":"","sum_foreign":""},"58":{"sum_foreign_comment":"","sum":"","sum_comment":"","sum_unclear":false,"sum_foreign":""},"59":{"sum_foreign_comment":"","sum":"","sum_comment":"","sum_foreign":""},"60":{"sum_foreign_comment":"","sum_foreign_hidden":false,"sum_comment":"","sum_comment_hidden":false,"sum":"","sum_foreign":""},"61":{"sum_foreign_comment":"","sum":"","sum_comment":"","sum_foreign":""},"62":{"sum_foreign_comment":"","sum":"","sum_comment":"","sum_foreign":""},"63":{"sum_foreign_comment":"","sum":"","sum_comment":"","sum_foreign":""},"64":{"sum_foreign_comment":"","sum":"","sum_comment":"","sum_foreign":""}},"ft_src":"39061\nКропивна Людмила Володимирівна\nсуддя київського апеляційного господарського суду\nм. Київ\nАпеляційний господарський суд\nЛюдмила\nКрапівной А. С\nДитина\nКропивна Людмила Володимирівна\nЛюдмила Володимирівна Кропивна\nЛюдмила Кропивна\nКропивна Людмила Володимирівна\nКропивна\nВолодимирівна\n2015\nVolkswagen Tiguan\n2.0 ТДІ\n986406\n1/4 частина від 82,8\n82.8\n23\n1/4 від 129\n129\n2015\n9482\n231319\n15976\n9482\n555580\n308285\n2.0 ТДІ\n986406\nVolkswagen Tiguan\n2015\n2015\nДитина\nКрапівной А. С\nКропивна\nКропивна Людмила Володимирівна\nЛюдмила Володимирівна Кропивна\nЛюдмила Кропивна\nКропивна Людмила Володимирівна\nКропивна Людмила Володимирівна\nЛюдмила\nВолодимирівна\nАпеляційний господарський суд\nсуддя київського апеляційного господарського суду\nм. Київ\n39061\n231319\n9482\n15976\n555580\n9482\n308285\n82.8\n1/4 частина від 82,8\n23\n129\n1/4 від 129\n39061\nДитина\nКрапівной А. С\nВолодимирівна\nКропивна\nсуддя київського апеляційного господарського суду\nАпеляційний господарський суд\nм. Київ\nКропивна Людмила Володимирівна\nКропивна Людмила Володимирівна\nЛюдмила Володимирівна Кропивна\nЛюдмила Кропивна\nКропивна Людмила Володимирівна\nЛюдмила\n2015\n2.0 ТДІ\nVolkswagen Tiguan\n986406\n15976\n9482\n555580\n308285\n9482\n231319\n1/4 частина від 82,8\n82.8\n1/4 від 129\n23\n129\n2015","general":{"inn":"","inn_hidden":true,"last_name":"Кропивна","post":{"region":"м. Київ","region_unclear":false,"post":"суддя київського апеляційного господарського суду","office_unclear":false,"office":"Апеляційний господарський суд"},"name":"Людмила","full_name":"Кропивна Людмила Володимирівна","family_raw":"","addresses":[{"place_district":"","place_city_hidden":true,"place_city":"","place_city_type_hidden":false,"place_district_hidden":false,"place_city_type":"","place_address_hidden":true,"place_address":"","place_hidden":true,"place":""}],"family":[{"inn":"","relations":"Дитина","relations_other":"","inn_hidden":true,"family_name":"Крапівной А. С","name_hidden":true,"name_unclear":false}],"full_name_suggest":{"output":"Кропивна Людмила Володимирівна","input":["Кропивна Людмила Володимирівна","Людмила Володимирівна Кропивна","Людмила Кропивна"]},"patronymic":"Володимирівна"},"source":"VULYK","estate":{"25":[{"costs":"","costs_comment":"","address_hidden":false,"region_hidden":true,"space_comment":"1/4 частина від 82,8","space":"82.8","address":"","costs_unclear":false,"region":"","costs_rent_comment":"","space_comment_unclear":false,"space_units":"м²","costs_rent":""},{"costs_rent":"","space_comment_unclear":false,"region":"","costs":"23","costs_rent_comment":"","costs_comment":"","costs_unclear":true,"space_comment":"1/4 від 129","space_units":"м²","space":"129","address":""}]},"intro":{"declaration_year":"2015","isnotdeclaration":""}}