{"income":{"5":{"value":"198626","family_comment":"","value_unclear":false,"family_unclear":false,"comment_unclear":false,"comment":"","family":""},"6":{"family_comment":"","value":"186446","comment_unclear":false,"family":"","comment":""},"7":{"family_comment":"","value":"","source_name":"","family":"","comment":""},"8":{"family_comment":"","value":"","family":"","comment":""},"9":{"family_comment":"","value":"","value_unclear":false,"family":"","comment":""},"10":{"family_comment":"","value":"12180","value_unclear":false,"family":"","comment":""},"11":{"family_comment":"","value":"","family":"","comment":""},"12":{"family_comment":"","value":"","family":"","comment":""},"13":{"family_comment":"","value":"","family":"","comment":""},"14":{"family_comment":"","value":"","family":"","comment":""},"15":{"family_comment":"","value":"","family":"","comment":""},"16":{"family_comment":"","value":"","family":"","comment":""},"17":{"family_comment":"","value":"","value_unclear":false,"family":"","comment":""},"18":{"family_comment":"","value":"","value_unclear":false,"family":"","comment":""},"19":{"family_comment":"","value":"","family":"","comment":""},"20":{"value":"","family_comment":"","value_unclear":false,"family_unclear":false,"comment_unclear":false,"comment":"","family":""}},"vehicle":{"35":[{"year_hidden":false,"brand_info":"немає інформації","sum_rent_comment":"","year":"2011","sum_hidden":false,"brand_info_hidden":true,"brand_info_unclear":false,"year_unclear":false,"sum_rent":"","sum":"","brand":"немає інформації","sum_comment":"","brand_unclear":false,"brand_hidden":true}]},"id":"vulyk_84_171","declaration":{"additional_info_text":"","notfull_lostpages":"","date":"2015-03-26T00:00:00","notfull":"","additional_info":"","url":"http://static.declarations.com.ua/declarations/chosen_ones/judges_batch/2585_bobrova_iryna_viacheslavivna.pdf"},"liabilities":{"54":{"sum_foreign_comment":"","sum_comment_hidden":false,"sum":"","sum_comment":"","sum_foreign":""},"55":{"sum_foreign_comment":"","sum":"","sum_comment":"","sum_foreign":""},"56":{"sum_foreign_comment":"","sum":"15400","sum_comment":"","sum_foreign":""},"57":{"sum_foreign_comment":"","sum_comment_hidden":false,"sum":"5000","sum_comment":"","sum_foreign":""},"58":{"sum_foreign_comment":"","sum_comment_hidden":false,"sum":"3400","sum_comment":"","sum_foreign":""},"59":{"sum_foreign_comment":"","sum":"10000","sum_comment":"","sum_foreign":""},"60":{"sum_foreign_comment":"","sum":"","sum_comment":"","sum_foreign":""},"61":{"sum_foreign_comment":"","sum":"","sum_comment":"","sum_foreign":""},"62":{"sum_foreign_comment":"","sum":"","sum_comment":"","sum_foreign":""},"63":{"sum_foreign_comment":"","sum_comment_hidden":false,"sum":"","sum_comment":"","sum_foreign":""},"64":{"sum_foreign_comment":"","sum_comment_hidden":false,"sum":"","sum_comment":"","sum_foreign":""}},"ft_src":"10000\n5000\n3400\n15400\nсуддя заводського районного суду м. миколаєва\nМиколаївська область\nЗагальний місцевий суд\nІрина\nБобров В. О. 20. 11. 1998\nДитина\nБоброва С. О., 13. 05. 2006\nДитина\nВячеславівна\nБоброва Ірина Вячеславівна\nІрина Вячеславівна Боброва\nІрина Боброва\nБоброва Ірина Вячеславівна\nБоброва Ірина Вячеславівна\nБоброва\nнемає інформації\nнемає інформації\n2011\n52.9\n2014\n186446\n12180\n198626\nнемає інформації\nнемає інформації\n2011\n2014\nБоброва Ірина Вячеславівна\nІрина Вячеславівна Боброва\nІрина Боброва\nБоброва Ірина Вячеславівна\nІрина\nДитина\nБобров В. О. 20. 11. 1998\nДитина\nБоброва С. О., 13. 05. 2006\nБоброва Ірина Вячеславівна\nВячеславівна\nсуддя заводського районного суду м. миколаєва\nЗагальний місцевий суд\nМиколаївська область\nБоброва\n10000\n3400\n5000\n15400\n186446\n198626\n12180\n52.9\n3400\n5000\n15400\n10000\nБобров В. О. 20. 11. 1998\nДитина\nБоброва С. О., 13. 05. 2006\nДитина\nВячеславівна\nБоброва\nІрина\nБоброва Ірина Вячеславівна\nІрина Вячеславівна Боброва\nІрина Боброва\nБоброва Ірина Вячеславівна\nМиколаївська область\nсуддя заводського районного суду м. миколаєва\nЗагальний місцевий суд\nБоброва Ірина Вячеславівна\nнемає інформації\nнемає інформації\n2011\n12180\n198626\n186446\n52.9\n2014","general":{"inn":"","name":"Ірина","inn_unclear":false,"family":[{"inn":"","inn_hidden":true,"inn_unclear":false,"relations_hidden":false,"relations_other":"","relations":"Дитина","name_hidden":false,"family_name":"Бобров В. О. 20. 11. 1998","name_unclear":false},{"inn":"","relations":"Дитина","relations_other":"","inn_hidden":true,"family_name":"Боброва С. О., 13. 05. 2006","name_hidden":false,"name_unclear":false}],"inn_hidden":true,"family_raw":"","last_name":"Боброва","post":{"post_unclear":false,"region_unclear":false,"post":"суддя заводського районного суду м. миколаєва","candidate":"","office_hidden":false,"region":"Миколаївська область","post_hidden":false,"office":"Загальний місцевий суд","office_unclear":false,"region_hidden":false},"full_name":"Боброва Ірина Вячеславівна","addresses":[{"place_city_type_unclear":false,"place_address":"","place_district_hidden":true,"place_city_type":"","place_address_hidden":true,"place_address_unclear":false,"place_city_type_hidden":true,"place":"","place_district":"","place_unclear":false,"place_city":"","place_city_unclear":false,"place_hidden":true,"place_city_hidden":true,"place_district_unclear":false}],"patronymic":"Вячеславівна","full_name_suggest":{"output":"Боброва Ірина Вячеславівна","input":["Боброва Ірина Вячеславівна","Ірина Вячеславівна Боброва","Ірина Боброва"]}},"source":"VULYK","estate":{"25":[{"region_unclear":false,"space_hidden":false,"costs":"","costs_comment":"","address_hidden":false,"region_hidden":true,"space_comment":"","space":"52.9","address":"","costs_comment_unclear":false,"costs_rent_comment_unclear":false,"region":"","address_unclear":false,"costs_rent_comment":"","space_units":"м²","costs_rent":""}]},"intro":{"declaration_year":"2014","isnotdeclaration":"","declaration_year_unclear":false}}