{"id":"vulyk_92_73","ft_src":"1800 куб. см.\nвласність\nVolkswagen Passat\n2012\n1800 куб. см.\nVolkswagen Passat\n2012\nвласність\nм. Харків\n53.5\nХарківська область\nХарківська область\nм. Харків\n1000\nХарківська область\nЗміївський р-н\n2013\nХарківська область\nЗміївський р-н\n1617\nвласність\nм. Харків\nХарківська область\n370\nХарківська область\nм. Харків\n53.5\nм. Харків\n1000\nХарківська область\nЗміївський р-н\n2013\nХарківська область\nЗміївський р-н\n1617\nХарківська область\nХарківська область\nм. Харків\n370\nХарківська область\nм. Харків\n61.2\n2014\n234094\n223066\n303013\n223066\n68919\n1800 куб. см.\nVolkswagen Passat\nвласність\n2012\n1800 куб. см.\nVolkswagen Passat\n2012\n53.5\nХарківська область\nвласність\nм. Харків\nХарківська область\nм. Харків\n370\n53.5\nм. Харків\nХарківська область\n1000\nХарківська область\nм. Харків\n2013\nЗміївський р-н\nХарківська область\nХарківська область\n1617\nЗміївський р-н\n1000\nм. Харків\nХарківська область\nЗміївський р-н\nХарківська область\n2013\n1617\nХарківська область\nЗміївський р-н\n370\nвласність\nм. Харків\nХарківська область\nХарківська область\nм. Харків\n61.2\nПодружжя\nМар'єнко Л. М\nДитина\nШабельнікова Є. С\nБатьки\nШабельнікова Н. П\nШабельніков Сергій Кузьмич\nСергій Кузьмич Шабельніков\nСергій Шабельніков\nШабельніков Сергій Кузьмич\nШабельніков Сергій Кузьмич\nСергій\nШабельніков\nЗагальний апеляційний суд\nсуддя апеляційного суду харківської області\nХарківська область\nКузьмич\n63012\nПриватбанк, кредитна картка\n223066\n234094\n68919\n223066\n303013\n2014\nПриватбанк, кредитна картка\n63012\nПодружжя\nМар'єнко Л. М\nДитина\nШабельнікова Є. С\nБатьки\nШабельнікова Н. П\nКузьмич\nШабельніков\nСергій\nШабельніков Сергій Кузьмич\nСергій Кузьмич Шабельніков\nСергій Шабельніков\nШабельніков Сергій Кузьмич\nХарківська область\nЗагальний апеляційний суд\nсуддя апеляційного суду харківської області\nШабельніков Сергій Кузьмич","estate":{"23":[{"address":"м. Харків","space_units":"м²","costs_comment":"","space_unclear":false,"region_hidden":true,"space_comment":"","address_hidden":false,"costs":"","costs_rent_comment":"","space":"1000","region_unclear":false,"region":"Харківська область","costs_rent":""},{"address":"Зміївський р-н","space_units":"м²","space_hidden":false,"space_unclear":false,"region_hidden":false,"costs_comment":"","space_comment":"","space":"2013","address_unclear":false,"costs_rent_comment":"","costs":"","region":"Харківська область","costs_rent":""},{"costs":"","address":"Зміївський р-н","space_units":"м²","costs_rent_comment":"","space":"1617","space_comment":"","region_hidden":false,"costs_comment":"","region":"Харківська область","costs_rent":""}],"24":[{"address":"м. Харків","space_units":"м²","costs_comment":"власність","space_hidden":false,"space_unclear":false,"region_hidden":false,"costs_rent_comment":"","space_comment":"","address_hidden":true,"space":"370","space_units_unclear":false,"costs":"","region":"Харківська область","space_units_hidden":false,"costs_rent":""}],"27":[{"address":"м. Харків","space_units":"м²","space_hidden":false,"space_unclear":false,"region_hidden":false,"costs_comment":"власність","space_comment":"","address_hidden":true,"costs":"","address_unclear":false,"costs_rent_comment":"","space":"53.5","region":"Харківська область","costs_rent":""}],"29":[{"costs_property_comment":"","costs_property":"","address":"м. Харків","space_units":"м²","space_unclear":false,"region_hidden":true,"space_units_unclear":false,"space_comment":"","address_hidden":false,"costs_rent_comment":"","space":"1000","region":"Харківська область","space_units_hidden":false,"costs_rent":""},{"costs_property_comment":"","address":"Зміївський р-н","space_units":"м²","space_comment":"","region_hidden":false,"costs_property":"","region":"Харківська область","address_hidden":true,"address_unclear":false,"costs_rent_comment":"","space":"2013","costs_rent":""},{"costs_property_comment":"","address":"Зміївський р-н","space_units":"м²","costs_rent_comment":"","space":"1617","region":"Харківська область","region_hidden":true,"costs_property":"","space_comment":"","costs_rent":""}],"30":[{"costs_property_comment":"","address":"м. Харків","space_units":"м²","space_hidden":false,"space_unclear":false,"region_hidden":false,"costs_property":"","space_comment":"","address_hidden":true,"address_unclear":false,"costs_rent_comment":"","space":"370","region":"Харківська область","costs_rent":""}],"31":[{"costs_property_comment":"","address":"м. Харків","space_units":"м²","space_hidden":false,"space_unclear":false,"region_hidden":false,"costs_property":"","space_comment":"","address_hidden":true,"address_unclear":false,"costs_rent_comment":"","space":"61.2","region":"Харківська область","costs_rent":""}],"33":[{"costs_property_comment":"","address":"м. Харків","space_units":"м²","costs_rent_comment":"","space":"53.5","region":"Харківська область","region_hidden":false,"costs_property":"","space_comment":"","address_hidden":true,"costs_rent":""}]},"vehicle":{"35":[{"sum_comment_unclear":false,"brand_info":"1800 куб. см.","sum_rent_comment":"власність","brand_unclear":false,"brand_hidden":false,"year":"2012","sum_comment":"","brand_info_hidden":false,"sum_rent":"","brand":"Volkswagen Passat","year_unclear":false,"brand_info_unclear":false,"sum":""}],"40":[{"sum_comment_unclear":false,"year_hidden":false,"brand_info":"1800 куб. см.","sum":"","sum_rent_comment":"","brand_hidden":false,"year":"2012","brand":"Volkswagen Passat","brand_info_hidden":false,"sum_rent":"","sum_comment":"","year_unclear":false}]},"source":"VULYK","income":{"5":{"family_comment":"","family_hidden":false,"value":"223066","family":"303013","comment":""},"6":{"family_comment":"","family":"234094","comment":"","value_unclear":false,"family_hidden":false,"value":"223066"},"7":{"family_comment":"","comment":"","family":"","value_unclear":false,"value":"","source_name":""},"8":{"family_comment":"","value":"","family":"","comment":""},"9":{"family_comment":"","value":"","family":"","comment":""},"10":{"family_comment":"","comment":"","family":"","family_unclear":false,"comment_unclear":false,"value":"","family_comment_unclear":false},"11":{"family_comment":"","value":"","family":"","comment":"","value_unclear":false},"12":{"family_comment":"","value":"","family":"","comment":""},"13":{"family_comment":"","value":"","family":"","comment":""},"14":{"family_comment":"","value":"","family":"","comment":""},"15":{"family_comment":"","comment":"","family":"","family_unclear":false,"comment_unclear":false,"value":""},"16":{"family_comment":"","value":"","family":"","comment":""},"17":{"family_comment":"","value":"","family":"","comment":""},"18":{"family_comment":"","value":"","family_unclear":false,"family":"","comment":""},"19":{"family_comment":"","value":"","family":"","comment":""},"20":{"family_comment":"","value":"","family_unclear":false,"family":"68919","comment":""}},"general":{"family_raw":"","name":"Сергій","full_name_suggest":{"input":["Шабельніков Сергій Кузьмич","Сергій Кузьмич Шабельніков","Сергій Шабельніков"],"output":"Шабельніков Сергій Кузьмич"},"patronymic":"Кузьмич","inn_hidden":true,"patronymic_unclear":false,"inn":"","inn_unclear":false,"last_name":"Шабельніков","full_name":"Шабельніков Сергій Кузьмич","family":[{"inn":"","inn_unclear":false,"family_name":"Мар'єнко Л. М","relations_hidden":false,"name_unclear":false,"relations":"Подружжя","inn_hidden":true,"name_hidden":false,"relations_other":""},{"inn":"","inn_unclear":false,"family_name":"Шабельнікова Є. С","relations_hidden":false,"name_unclear":false,"relations":"Дитина","inn_hidden":false,"name_hidden":false,"relations_other":""},{"inn":"","family_name":"Шабельнікова Н. П","relations_other":"","name_unclear":false,"inn_hidden":true,"relations":"Батьки"}],"post":{"office":"Загальний апеляційний суд","post":"суддя апеляційного суду харківської області","office_unclear":false,"region_hidden":false,"region":"Харківська область","office_hidden":false,"post_unclear":false},"addresses":[{"place_city_type":"","place_address_unclear":false,"place_city_type_hidden":true,"place_hidden":true,"place_city_hidden":true,"place_district":"","place_district_hidden":true,"place":"","place_city":"","place_address_hidden":true,"place_address":""}]},"liabilities":{"54":{"sum_comment":"","sum_hidden":false,"sum":"","sum_foreign_comment":"","sum_foreign":"","sum_unclear":false},"55":{"sum_comment":"","sum_foreign_comment":"","sum_foreign":"","sum_unclear":false,"sum":""},"56":{"sum_comment_unclear":false,"sum_comment":"","sum_hidden":false,"sum":"","sum_foreign_comment":"","sum_foreign":"","sum_unclear":false},"57":{"sum_comment":"","sum_hidden":false,"sum":"","sum_foreign_comment":"","sum_foreign":"","sum_comment_hidden":false},"58":{"sum_comment":"","sum_foreign_comment":"","sum_foreign":"","sum":""},"59":{"sum_comment":"","sum_comment_unclear":false,"sum_foreign_comment":"","sum":"","sum_foreign":""},"60":{"sum_comment":"","sum_foreign_comment":"","sum_foreign":"","sum":""},"61":{"sum_comment":"","sum_foreign_comment":"","sum_foreign":"","sum":""},"62":{"sum_comment_unclear":false,"sum_comment":"","sum_hidden":false,"sum":"","sum_foreign_comment":"","sum_foreign":"","sum_unclear":false},"63":{"sum_comment":"Приватбанк, кредитна картка","sum_foreign_comment":"","sum_foreign":"","sum":"63012"},"64":{"sum_comment":"","sum_foreign_comment":"","sum_foreign":"","sum":""}},"declaration":{"notfull_lostpages":"","additional_info_text":"","additional_info":"","date":"2015-03-31T00:00:00","notfull":"","url":"http://static.declarations.com.ua/declarations/chosen_ones/judges_batch/3321_shabelnikov_serhii_kuzmych.pdf"},"intro":{"isnotdeclaration":"","declaration_year":"2014"}}