{"income":{"5":{"value":"181205.67","family_comment":"","value_unclear":false,"family_hidden":false,"family_unclear":false,"family":"18781.86","comment":""},"6":{"family_comment":"","value":"181205.67","family":"18781.86","comment":""},"7":{"family_comment":"","value":"","source_name":"","family":"","comment":""},"8":{"family_comment":"","value":"","family":"","comment":""},"9":{"family_comment":"","value":"","family":"","comment":""},"10":{"family_comment":"","value":"","value_unclear":false,"family":"","comment":""},"11":{"family_comment":"","value":"","family":"","comment":""},"12":{"family_comment":"","value":"","family":"","comment":""},"13":{"family_comment":"","value":"","family":"","comment":""},"14":{"family_comment":"","value":"","family":"","comment":""},"15":{"family_comment":"","value":"","family":"","comment":""},"16":{"family_comment":"","value":"","family":"","comment":""},"17":{"family_comment":"","value":"","family":"","comment":""},"18":{"family_comment":"","value":"","family":"","comment":""},"19":{"family_comment":"","value":"","family":"","comment":""},"20":{"family_comment":"","value":"","family":"","comment":""}},"vehicle":{"35":[{"brand_info":"3498 куб. см.","sum_rent_comment":"","brand":"Mercedes-Benz ML 350","sum_comment":"","brand_unclear":false,"year":"2007","sum":"","sum_rent":""}]},"id":"vulyk_82_42","declaration":{"date":"2015-03-30T00:00:00","additional_info_text":"","additional_info":"","url":"http://static.declarations.com.ua/declarations/chosen_ones/judges_batch/2237_luzhetska_olena_romanivna.pdf"},"liabilities":{"54":{"sum_foreign_comment":"","sum_comment_hidden":false,"sum":"","sum_comment":"","sum_foreign":""},"55":{"sum_foreign_comment":"","sum":"","sum_hidden":false,"sum_comment":"","sum_foreign":""},"56":{"sum_foreign_comment":"","sum":"20000","sum_comment":"","sum_foreign":""},"57":{"sum_foreign_comment":"","sum":"","sum_comment":"","sum_foreign":""},"58":{"sum_foreign_comment":"","sum":"","sum_comment":"","sum_foreign":""},"59":{"sum_foreign_comment":"","sum":"","sum_comment":"","sum_foreign":""},"60":{"sum_foreign_comment":"","sum":"","sum_comment":"","sum_foreign":""},"61":{"sum_foreign_comment":"","sum":"","sum_comment":"","sum_foreign":""},"62":{"sum_foreign_comment":"","sum":"","sum_comment":"","sum_foreign":""},"63":{"sum_foreign_comment":"","sum":"","sum_comment":"","sum_foreign":""},"64":{"sum_foreign_comment":"","sum":"","sum_comment":"","sum_foreign":""}},"ft_src":"20000\nсуддя дарницького районного суду міста києва\nм. Київ\nЗагальний місцевий суд\nОлена\nПодружжя\nДитина\nДитина\nРоманівна\nЛужецька Олена Романівна\nОлена Романівна Лужецька\nОлена Лужецька\nЛужецька Олена Романівна\nЛужецька Олена Романівна\nЛужецька\n2007\n3498 куб. см.\nMercedes-Benz ML 350\n2000\n24.9\n218\n128.3\n2014\n18781.86\n181205.67\n18781.86\n181205.67\n3498 куб. см.\n2007\nMercedes-Benz ML 350\n2014\nПодружжя\nДитина\nДитина\nЛужецька Олена Романівна\nОлена Романівна Лужецька\nОлена Лужецька\nЛужецька Олена Романівна\nЛужецька Олена Романівна\nОлена\nЛужецька\nЗагальний місцевий суд\nм. Київ\nсуддя дарницького районного суду міста києва\nРоманівна\n20000\n181205.67\n18781.86\n181205.67\n18781.86\n2000\n24.9\n218\n128.3\n20000\nПодружжя\nДитина\nДитина\nРоманівна\nЛужецька\nОлена\nЛужецька Олена Романівна\nОлена Романівна Лужецька\nОлена Лужецька\nЛужецька Олена Романівна\nм. Київ\nЗагальний місцевий суд\nсуддя дарницького районного суду міста києва\nЛужецька Олена Романівна\n2007\n3498 куб. см.\nMercedes-Benz ML 350\n181205.67\n18781.86\n18781.86\n181205.67\n218\n2000\n128.3\n24.9\n2014","general":{"inn":"","name":"Олена","inn_unclear":false,"family":[{"inn":"","inn_hidden":true,"relations_hidden":false,"family_name":"","relations_other":"","relations":"Подружжя","name_hidden":true,"name_unclear":false},{"inn":"","relations":"Дитина","relations_other":"","inn_hidden":false,"family_name":"","name_hidden":true,"name_unclear":false},{"inn":"","relations":"Дитина","relations_other":"","inn_hidden":false,"family_name":"","name_hidden":true,"name_unclear":false}],"inn_hidden":true,"family_raw":"","last_name":"Лужецька","post":{"post":"суддя дарницького районного суду міста києва","region":"м. Київ","office_hidden":false,"office":"Загальний місцевий суд","office_unclear":false,"post_hidden":false,"region_hidden":false},"full_name_suggest":{"output":"Лужецька Олена Романівна","input":["Лужецька Олена Романівна","Олена Романівна Лужецька","Олена Лужецька"]},"full_name":"Лужецька Олена Романівна","addresses":[{"place_district":"","place_city_hidden":true,"place_city":"","place_city_type_hidden":false,"place_district_hidden":true,"place_city_type":"","place_address_hidden":true,"place_address":"","place_hidden":true,"place":""}],"patronymic":"Романівна","last_name_unclear":false},"source":"VULYK","estate":{"23":[{"costs":"","costs_comment":"","address_hidden":false,"region_hidden":true,"space_comment":"","space_units_unclear":false,"address":"","space":"2000","region":"","costs_rent_comment":"","space_units":"м²","costs_rent":""}],"25":[{"space_hidden":false,"costs":"","costs_comment":"","costs_hidden":false,"address_hidden":false,"region_hidden":true,"space_comment":"","space_unclear":true,"space":"128.3","address":"","region":"","costs_rent_comment":"","space_comment_unclear":false,"space_units":"м²","costs_rent":""}],"27":[{"costs_rent":"","region":"","costs":"","costs_rent_comment":"","costs_comment":"","address_hidden":false,"region_hidden":true,"space_comment":"","space_units":"м²","space":"24.9","address":""}],"31":[{"space_unclear":true,"address_hidden":true,"region_hidden":true,"space_comment":"","space":"218","address":"","region":"","costs_property":"","costs_rent_comment":"","space_comment_unclear":false,"space_units":"м²","costs_property_comment":"","costs_rent":""}]},"intro":{"declaration_year":"2014"}}