{"income":{"5":{"value":"262784","family_comment":"","value_unclear":false,"family":"40399","value_hidden":false,"family_unclear":false,"comment_unclear":false,"comment":"","family_comment_unclear":false},"6":{"value":"250604","family_comment":"","value_unclear":false,"value_hidden":false,"family_unclear":false,"family":"36489","comment":""},"7":{"source_name_unclear":false,"value":"","value_hidden":false,"family_comment":"","source_name":"","family":"","comment":"","source_name_hidden":false},"8":{"family_comment":"","value":"","family":"","comment":""},"9":{"family_comment":"","value":"","value_unclear":false,"family":"","comment":""},"10":{"family_comment":"","value":"12180","family":"3910","comment":""},"11":{"family_comment":"","value":"","family":"","comment":""},"12":{"family_comment":"","value":"","family":"","comment":""},"13":{"family_comment":"","value":"","family":"","comment":""},"14":{"family_comment":"","value":"","family":"","comment":""},"15":{"family_comment":"","value":"","family":"","comment":""},"16":{"family_comment":"","value":"","family":"341533","comment":""},"17":{"family_comment":"","value":"","family":"","comment":""},"18":{"family_comment":"","value":"","family":"","comment":""},"19":{"family_comment":"","value":"","family":"","comment":""},"20":{"value":"12184","value_unclear":false,"family_comment":"","family":"15533","comment":"","family_comment_unclear":false}},"vehicle":{"35":[{"brand_info":"1781 куб. см.","sum_rent_comment":"","brand_info_unclear":false,"year":"2004","sum_rent_unclear":false,"sum_rent_comment_unclear":false,"sum_rent":"","sum":"","brand":"Audi A4","sum_comment":"","sum_comment_unclear":false,"sum_unclear":false,"brand_unclear":false}],"40":[{"brand_info":"1600 куб. см.","sum_rent_comment":"","brand":"ВАЗ 2110","sum_comment":"","year":"2007","brand_info_hidden":false,"brand_info_unclear":false,"sum":"","sum_rent":""}],"44":[{"brand_info":"мопед А1.49 куб. см.","sum_rent_comment":"","brand":"Honda Lead","sum_comment":"","year":"1998","brand_info_unclear":true,"sum":"","sum_rent":""}]},"id":"vulyk_26_104","banks":{"45":[{"sum_foreign_comment":"","sum_units":"UAH","sum_comment":"","sum_comment_unclear":false,"sum_hidden":false,"sum_foreign_units":"UAH","sum_comment_hidden":false,"sum_unclear":false,"sum":"3522","sum_foreign":""},{"sum_foreign_comment":"","sum_units":"","sum_comment":"","sum_comment_unclear":false,"sum_foreign_units":"","sum":"","sum_foreign":""},{"sum_foreign_comment":"","sum_units":"","sum_comment":"","sum_foreign_units":"","sum":"","sum_foreign":""},{"sum_foreign_comment":"","sum_units":"","sum_comment":"","sum_foreign_units":"","sum":"","sum_foreign":""},{"sum_foreign_comment":"","sum":"","sum_comment":"","sum_foreign":""}],"46":[{"sum_foreign_comment":"","sum_units":"UAH","sum_comment":"","sum_comment_unclear":false,"sum_foreign_units":"UAH","sum_comment_hidden":false,"sum_unclear":false,"sum":"","sum_foreign":""},{"sum_foreign_comment":"","sum_units":"","sum_comment":"","sum_foreign_units":"","sum":"","sum_foreign":""}],"47":[{"sum_foreign_comment":"","sum_units":"UAH","sum_comment":"","sum_comment_unclear":false,"sum_hidden":false,"sum_foreign_units":"UAH","sum":"","sum_foreign":""}],"48":[{"sum_foreign_comment":"","sum_units":"UAH","sum_comment":"","sum_comment_unclear":false,"sum_hidden":false,"sum_foreign_units":"UAH","sum":"","sum_unclear":false,"sum_foreign":""}],"49":[{"sum_foreign_comment":"","sum_units":"UAH","sum_comment":"","sum_hidden":false,"sum_foreign_units":"UAH","sum":"","sum_foreign_hidden":false,"sum_foreign":""}],"50":[{"sum_foreign_comment":"","sum_units":"UAH","sum_comment":"","sum_foreign_units":"UAH","sum":"","sum_foreign":""}],"51":[{"sum_foreign_comment":"","sum_units":"UAH","sum_comment":"","sum_comment_unclear":false,"sum_hidden":false,"sum_foreign_units":"UAH","sum_comment_hidden":false,"sum":"8783","sum_foreign":""},{"sum_foreign_comment":"","sum_units":"","sum_comment":"","sum_foreign_units":"","sum":"","sum_foreign":""},{"sum_foreign_comment":"","sum_units":"","sum_comment":"","sum_foreign_units":"","sum":"","sum_foreign":""},{"sum_foreign_comment":"","sum_units":"","sum_comment":"","sum_foreign_units":"","sum":"","sum_foreign":""}],"52":[{"sum_foreign_comment":"","sum_units":"UAH","sum_comment":"","sum_comment_unclear":false,"sum_hidden":false,"sum_foreign_units":"UAH","sum_comment_hidden":false,"sum_unclear":false,"sum":"","sum_foreign":""}],"53":[{"sum_foreign_comment":"","sum_units":"UAH","sum_comment":"","sum_hidden":false,"sum_foreign_units":"UAH","sum_comment_hidden":false,"sum":"","sum_foreign":""},{"sum_foreign_comment":"","sum_units":"","sum_comment":"","sum_foreign_units":"","sum":"","sum_foreign":""},{"sum_foreign_comment":"","sum_units":"","sum_comment":"","sum_foreign_units":"","sum":"","sum_foreign":""},{"sum_foreign_comment":"","sum_units":"","sum_comment":"","sum_foreign_units":"","sum":"","sum_foreign":""},{"sum_foreign_comment":"","sum_units":"","sum_comment":"","sum_foreign_units":"","sum":"","sum_foreign":""}]},"declaration":{"additional_info_text":"","notfull_lostpages":"","date":"2015-02-09T00:00:00","notfull":"","additional_info":"","url":"http://static.declarations.com.ua/declarations/chosen_ones/mega_batch/zhmurko_pavlo_iakovych.pdf"},"liabilities":{"54":{"sum_foreign_comment":"","sum_foreign_hidden":false,"sum_comment":"","sum_comment_unclear":false,"sum_hidden":false,"sum_comment_hidden":false,"sum":"193","sum_foreign":""},"55":{"sum_foreign_comment":"","sum_foreign_hidden":false,"sum_comment":"","sum_hidden":false,"sum":"","sum_foreign":""},"56":{"sum_foreign_comment":"","sum_foreign_hidden":false,"sum_comment":"","sum_hidden":false,"sum":"","sum_foreign":""},"57":{"sum_foreign_comment":"","sum_foreign_hidden":false,"sum_comment":"","sum_comment_unclear":false,"sum_hidden":false,"sum_comment_hidden":false,"sum":"","sum_foreign":""},"58":{"sum_foreign_comment":"","sum_foreign_hidden":false,"sum_comment":"","sum_comment_unclear":false,"sum_hidden":false,"sum_comment_hidden":false,"sum_unclear":false,"sum":"","sum_foreign":""},"59":{"sum_foreign_comment":"","sum_foreign_hidden":false,"sum_comment":"","sum_hidden":false,"sum":"","sum_foreign":""},"60":{"sum_foreign_comment":"","sum":"","sum_comment":"","sum_hidden":false,"sum_comment_hidden":false,"sum_foreign":""},"61":{"sum_foreign_comment":"","sum":"","sum_comment":"","sum_foreign":""},"62":{"sum_foreign_comment":"","sum":"","sum_comment":"","sum_foreign":""},"63":{"sum_foreign_comment":"","sum":"","sum_comment":"","sum_comment_unclear":false,"sum_comment_hidden":false,"sum_foreign":""},"64":{"sum_foreign_comment":"","sum":"","sum_comment":"","sum_comment_unclear":false,"sum_comment_hidden":false,"sum_foreign":""}},"ft_src":"193\nКарлівка\n39500\nПолтавська область\nголова карлівського районного суду полтавської області\nПолтавська область\nЗагальний місцевий суд\nПавло\nЖмурко Т. М\nПодружжя\nЯкович\nЖмурко Павло Якович\nПавло Якович Жмурко\nПавло Жмурко\nЖмурко Павло Якович\nЖмурко\nЖмурко Павло Якович\n1781 куб. см.\nAudi A4\n2004\n2007\n1600 куб. см.\nВАЗ 2110\nмопед А1.49 куб. см.\n1998\nHonda Lead\n8783\n3522\n2014\n1781 куб. см.\nAudi A4\n2004\n1600 куб. см.\n2007\nВАЗ 2110\nмопед А1.49 куб. см.\nHonda Lead\n1998\n3522\n8783\n.0036\nПолтавська область\nм. Карлівка\n.0024\nм. Карлівка\nПолтавська область\n55.8\nПолтавська область\nм. Карлівка\nПолтавська область\n85.4\nм. Полтава\n66.2\nПолтавська область\nм. Карлівка\nЖмурко Павло Якович\nПавло Якович Жмурко\nПавло Жмурко\nЖмурко Павло Якович\nЖмурко Павло Якович\nПодружжя\nЖмурко Т. М\nПавло\nЯкович\nПолтавська область\nголова карлівського районного суду полтавської області\nЗагальний місцевий суд\nЖмурко\nКарлівка\n39500\nПолтавська область\n193\n36489\n250604\n12184\n15533\n262784\n40399\n341533\n12180\n3910\n2014\n193\nм. Карлівка\n.0036\nПолтавська область\n.0024\nм. Карлівка\nПолтавська область\nПолтавська область\nм. Карлівка\n55.8\nПолтавська область\nм. Полтава\n85.4\nм. Карлівка\n66.2\nПолтавська область\nЖмурко Т. М\nПодружжя\nЯкович\nЖмурко\nПавло\nЖмурко Павло Якович\nПавло Якович Жмурко\nПавло Жмурко\nЖмурко Павло Якович\nПолтавська область\nКарлівка\n39500\nголова карлівського районного суду полтавської області\nПолтавська область\nЗагальний місцевий суд\nЖмурко Павло Якович\n36489\n250604\n3910\n12180\n40399\n262784\n341533\n15533\n12184\n1998\nмопед А1.49 куб. см.\nHonda Lead\n2004\nAudi A4\n1781 куб. см.\n2007\n1600 куб. см.\nВАЗ 2110\n3910\n12180\n12184\n15533\n262784\n40399\n341533\n250604\n36489\nм. Полтава\nПолтавська область\n85.4\nм. Карлівка\nПолтавська область\n.0036\nм. Карлівка\nПолтавська область\n.0024\nм. Карлівка\nПолтавська область\n66.2\nм. Карлівка\nПолтавська область\n55.8\n3522\n8783\n2014","general":{"inn":"","name":"Павло","family":[{"inn":"","inn_hidden":true,"relations_unclear":false,"relations_hidden":false,"relations_other":"","relations":"Подружжя","name_hidden":false,"family_name":"Жмурко Т. М","name_unclear":true}],"patronymic":"Якович","inn_hidden":true,"family_raw":"","last_name":"Жмурко","post":{"post_unclear":false,"office":"Загальний місцевий суд","post":"голова карлівського районного суду полтавської області","office_unclear":false,"region":"Полтавська область"},"last_name_unclear":false,"full_name":"Жмурко Павло Якович","addresses":[{"place_city_type_unclear":false,"place_address":"39500","place_district_hidden":false,"place_city_type":"Місто","place_address_hidden":true,"place_address_unclear":false,"place_city_type_hidden":false,"place":"Полтавська область","place_district":"","place_unclear":false,"place_city":"Карлівка","place_city_unclear":false,"place_hidden":false,"place_city_hidden":false,"place_district_unclear":false}],"patronymic_hidden":false,"full_name_suggest":{"output":"Жмурко Павло Якович","input":["Жмурко Павло Якович","Павло Якович Жмурко","Павло Жмурко"]}},"source":"VULYK","estate":{"23":[{"region_unclear":false,"space_unclear":false,"costs":"","costs_comment":"","address_hidden":false,"region_hidden":false,"space_comment":"","space":".0036","address":"м. Карлівка","region":"Полтавська область","address_unclear":true,"costs_rent_comment":"","space_comment_hidden":false,"space_units":"га","costs_rent":""},{"costs":"","costs_comment":"","address_hidden":false,"region_hidden":false,"space_comment":"","space":".0024","address":"м. Карлівка","region":"Полтавська область","costs_rent_comment":"","space_comment_hidden":true,"space_units":"га","costs_rent":""},{"costs_rent":"","region":"","costs":"","costs_rent_comment":"","costs_comment":"","address_hidden":false,"region_hidden":false,"space_comment":"","space_units":"","space":"","address":""},{"costs_rent":"","costs":"","costs_rent_comment":"","costs_comment":"","space_comment":"","space_units":"","space":"","address":""},{"costs_rent":"","costs":"","costs_rent_comment":"","costs_comment":"","space_comment":"","space_units":"","space":"","address":""},{"costs_rent":"","costs":"","costs_rent_comment":"","costs_comment":"","space_comment":"","space_units":"","space":"","address":""}],"25":[{"space_unclear":false,"costs":"","costs_comment":"","costs_hidden":false,"address_hidden":true,"region_hidden":false,"space_comment":"","space":"66.2","address":"м. Карлівка","region":"Полтавська область","address_unclear":false,"costs_rent_comment":"","space_comment_unclear":false,"space_comment_hidden":false,"space_units":"м²","costs_rent":""}],"27":[{"costs":"","costs_comment":"","address_hidden":true,"region_hidden":false,"space_comment":"","space":"55.8","address":"м. Карлівка","region":"Полтавська область","address_unclear":false,"costs_rent_comment":"","space_units":"м²","costs_rent":""}],"31":[{"region_unclear":false,"space_hidden":false,"address_hidden":true,"region_hidden":false,"space_comment":"","space_unclear":false,"space":"85.4","address":"м. Полтава","region":"Полтавська область","costs_property":"","costs_rent_comment":"","space_comment_unclear":false,"space_units":"м²","costs_property_comment":"","costs_rent":""}]},"intro":{"declaration_year":"2014","isnotdeclaration":""}}