{"income":{"5":{"family_comment":"","value":"206066","family":"","comment":""},"6":{"family_comment":"","value":"193881","family":"","comment":""},"7":{"value":"","comment_hidden":false,"family_comment":"","source_name":"","family":"","comment":"","source_name_hidden":false},"8":{"family_comment":"","value":"","family_hidden":false,"comment":"","family":""},"9":{"value":"5","family_comment":"","value_unclear":false,"family_unclear":false,"family":"","comment":""},"10":{"family_comment":"","value":"12180","family":"","comment":""},"11":{"family_comment":"","value":"","family":"","comment":""},"12":{"family_comment":"","value":"","family":"","comment":""},"13":{"family_comment":"","value":"","family":"","comment":""},"14":{"family_comment":"","value":"","family":"","comment":""},"15":{"family_comment":"","value":"","family":"","comment":""},"16":{"family_comment":"","value":"","family":"","comment":""},"17":{"family_comment":"","value":"","family":"","comment":""},"18":{"family_comment":"","value":"","family":"","comment":""},"19":{"family_comment":"","value":"","family":"","comment":""},"20":{"value":"","value_unclear":false,"family_hidden":false,"family_comment":"","family":"","comment":""}},"vehicle":{"35":[{"brand_info":"2231 куб. см, право користування","sum_rent_comment":"","year":"2013","brand_info_hidden":false,"brand_info_unclear":false,"year_unclear":false,"sum_rent":"","sum":"","brand":"Toyota Rav 4","sum_comment":"","sum_comment_unclear":false,"brand_hidden":false,"brand_unclear":false}]},"id":"vulyk_109_145","banks":{"45":[{"sum_foreign_comment":"","sum_unclear":false,"sum_units":"UAH","sum_comment":"","sum_foreign_units":"UAH","sum_comment_hidden":false,"sum_units_hidden":false,"sum":"128","sum_foreign":""}]},"declaration":{"additional_info_text":"","notfull_lostpages":"","date":"2016-03-09T00:00:00","notfull":"","additional_info":"","url":"http://static.declarations.com.ua/declarations/chosen_ones/judges_batch/2602_shvets_mykola_vasylovych_2015.pdf"},"liabilities":{"54":{"sum_foreign_comment":"","sum":"","sum_comment":"","sum_hidden":false,"sum_comment_hidden":false,"sum_unclear":false,"sum_foreign":""},"55":{"sum_foreign_comment":"","sum":"","sum_comment":"","sum_comment_unclear":false,"sum_foreign":""},"56":{"sum_foreign_comment":"","sum":"","sum_comment":"","sum_foreign":""},"57":{"sum_foreign_comment":"","sum_comment_hidden":false,"sum":"","sum_comment":"","sum_foreign":""},"58":{"sum_foreign_comment":"","sum_comment_hidden":false,"sum":"","sum_comment":"","sum_foreign":""},"59":{"sum_foreign_comment":"","sum":"","sum_comment":"","sum_foreign":""},"60":{"sum_foreign_comment":"","sum":"","sum_comment":"","sum_foreign":""},"61":{"sum_foreign_comment":"","sum":"","sum_comment":"","sum_foreign":""},"62":{"sum_foreign_comment":"","sum":"","sum_comment":"","sum_foreign":""},"63":{"sum_foreign_comment":"","sum":"","sum_comment":"","sum_foreign":""},"64":{"sum_foreign_comment":"","sum":"","sum_comment":"","sum_foreign":""}},"ft_src":"суддя господарського суду чернівецької області\nЧернівецька область\nГосподарський місцевий суд\nМикола\nВасильович\nШвець Микола Васильович\nМикола Васильович Швець\nМикола Швець\nШвець Микола Васильович\nШвець Микола Васильович\nШвець\n2231 куб. см, право користування\nToyota Rav 4\n2013\n90.6\n128\n2015\n2231 куб. см, право користування\nToyota Rav 4\n2013\n2015\nШвець Микола Васильович\nМикола Васильович Швець\nМикола Швець\nШвець Микола Васильович\nШвець Микола Васильович\nМикола\nШвець\nГосподарський місцевий суд\nЧернівецька область\nсуддя господарського суду чернівецької області\nВасильович\n193881\n206066\n12180\n5\n90.6\n128\n193881\n12180\n206066\n5\nВасильович\nШвець\nМикола\nШвець Микола Васильович\nМикола Васильович Швець\nМикола Швець\nШвець Микола Васильович\nЧернівецька область\nГосподарський місцевий суд\nсуддя господарського суду чернівецької області\nШвець Микола Васильович\n2013\nToyota Rav 4\n2231 куб. см, право користування\n12180\n206066\n5\n193881\n90.6\n128\n2015","general":{"name_hidden":false,"name":"Микола","inn":"","inn_unclear":false,"patronymic":"Васильович","inn_hidden":true,"family_raw":"","last_name":"Швець","post":{"region_unclear":false,"region":"Чернівецька область","post":"суддя господарського суду чернівецької області","region_hidden":false,"office":"Господарський місцевий суд","office_hidden":false,"office_unclear":false},"full_name":"Швець Микола Васильович","addresses":[{"place_district":"","place_city_hidden":true,"place_city":"","place_city_type_hidden":false,"place_district_hidden":false,"place_city_type":"","place_address_hidden":true,"place_address":"","place_hidden":true,"place":""}],"full_name_suggest":{"output":"Швець Микола Васильович","input":["Швець Микола Васильович","Микола Васильович Швець","Микола Швець"]}},"source":"VULYK","estate":{"25":[{"space_unclear":false,"costs":"","costs_comment":"","address_hidden":true,"region_hidden":false,"space_comment":"","space_hidden":false,"space":"90.6","address":"","region":"","costs_rent_comment":"","space_units":"м²","space_units_hidden":false,"costs_rent":""}]},"intro":{"declaration_year":"2015","isnotdeclaration":""}}