{"id":"vulyk_109_72","ft_src":"2008\nKawasaki\nER 650 A8 F, мотоцикл, дв. 649 куб. см.\nдв. 1998 куб. см.\nHyundai Sonata\n2008\nмотоцикл, дв. 223 куб. см.\n2003\nHonda FTR\n196.9\n496\n2015\n80141\n224739\n20000\n350\n111097\n224787\n48\n10606\nдв. 1998 куб. см.\nHyundai Sonata\n2008\nER 650 A8 F, мотоцикл, дв. 649 куб. см.\n2008\nKawasaki\nмотоцикл, дв. 223 куб. см.\n2003\nHonda FTR\n2015\nЮзіков Станіслав Георгійович\nСтаніслав Георгійович Юзіков\nСтаніслав Юзіков\nЮзіков Станіслав Георгійович\nСтаніслав\nПодружжя\nЮзікова Н. С\nДитина\nЮзіков Г. С\nДитина\nЮзіков М. С\nЮзіков Станіслав Георгійович\nГеоргійович\nГосподарський місцевий суд\nДніпропетровська область\nсуддя господарського суду дніпропетровської області\nЮзіков\n80000\n224739\n80141\n10606\n224787\n111097\n20000\n350\n48\n496\n196.9\n80000\nПодружжя\nЮзікова Н. С\nДитина\nЮзіков Г. С\nДитина\nЮзіков М. С\nГеоргійович\nЮзіков\nСтаніслав\nЮзіков Станіслав Георгійович\nСтаніслав Георгійович Юзіков\nСтаніслав Юзіков\nЮзіков Станіслав Георгійович\nДніпропетровська область\nГосподарський місцевий суд\nсуддя господарського суду дніпропетровської області\nЮзіков Станіслав Георгійович","estate":{"29":[{"costs_property_comment":"","address":"","space_units":"м²","space_unclear":false,"region_hidden":true,"costs_property":"","space_comment":"","address_hidden":true,"costs_rent_comment":"","space":"496","region":"","costs_rent":""}],"30":[{"costs_property_comment":"","address":"","space_units":"м²","costs_rent_comment":"","space_hidden":false,"region_hidden":true,"costs_property":"","space_comment":"","space":"196.9","address_hidden":true,"costs_rent":""}]},"vehicle":{"35":[{"sum_comment_unclear":false,"brand_info":"дв. 1998 куб. см.","sum_rent_comment":"","brand_unclear":false,"brand_hidden":false,"year":"2008","sum_comment":"","brand_info_hidden":false,"sum_rent":"","brand":"Hyundai Sonata","year_unclear":false,"brand_info_unclear":false,"sum":""}],"39":[{"sum_comment":"","brand_info_hidden":false,"brand_info":"ER 650 A8 F, мотоцикл, дв. 649 куб. см.","sum":"","sum_rent_comment":"","brand_hidden":false,"brand":"Kawasaki","sum_rent":"","year":"2008"}],"44":[{"sum_comment":"","brand_info":"мотоцикл, дв. 223 куб. см.","sum":"","sum_rent_comment":"","year":"2003","brand":"Honda FTR","sum_rent":""}]},"source":"VULYK","income":{"5":{"family_comment":"","value":"224787","family":"111097","comment":""},"6":{"family_comment":"","value":"224739","family":"80141","comment":""},"7":{"source_name_hidden":false,"family_comment":"","comment":"","family":"","comment_hidden":false,"value":"","source_name":""},"8":{"family_comment":"","family_hidden":false,"value":"","family":"","comment":""},"9":{"family_comment":"","family":"","comment":"","value_unclear":false,"family_unclear":false,"value":"48"},"10":{"family_comment":"","value":"","family":"350","comment":""},"11":{"family_comment":"","value":"","family":"20000","comment":""},"12":{"family_comment":"","value":"","family":"","comment":""},"13":{"family_comment":"","value":"","family":"","comment":""},"14":{"family_comment":"","value":"","family":"","comment":""},"15":{"family_comment":"","value":"","family":"","comment":""},"16":{"family_comment":"","value":"","family":"","comment":""},"17":{"family_comment":"","value":"","family":"","comment":""},"18":{"family_comment":"","value":"","family":"","comment":""},"19":{"family_comment":"","value":"","family":"","comment":""},"20":{"family_comment":"","family":"10606","comment":"","value_unclear":false,"family_hidden":false,"value":""}},"general":{"family_raw":"","name":"Станіслав","full_name_suggest":{"input":["Юзіков Станіслав Георгійович","Станіслав Георгійович Юзіков","Станіслав Юзіков"],"output":"Юзіков Станіслав Георгійович"},"patronymic":"Георгійович","inn_hidden":true,"addresses":[{"place_city_type_hidden":true,"place_city_type":"","place_city_hidden":true,"place_hidden":true,"place_district":"","place_district_hidden":true,"place":"","place_address":"","place_address_hidden":true,"place_city":""}],"inn":"","inn_unclear":false,"last_name":"Юзіков","full_name":"Юзіков Станіслав Георгійович","family":[{"inn":"","family_name":"Юзікова Н. С","relations_hidden":false,"name_unclear":false,"relations":"Подружжя","inn_hidden":true,"name_hidden":true,"relations_other":""},{"inn":"","family_name":"Юзіков Г. С","relations_other":"","name_unclear":false,"inn_hidden":false,"name_hidden":false,"relations":"Дитина"},{"inn":"","family_name":"Юзіков М. С","relations_other":"","name_unclear":false,"inn_hidden":false,"name_hidden":false,"relations":"Дитина"}],"post":{"office":"Господарський місцевий суд","post":"суддя господарського суду дніпропетровської області","office_unclear":false,"region_hidden":false,"region":"Дніпропетровська область","office_hidden":false,"region_unclear":false},"name_hidden":false},"liabilities":{"54":{"sum_comment":"","sum_hidden":false,"sum":"","sum_foreign_comment":"","sum_foreign":"","sum_unclear":false,"sum_comment_hidden":false},"55":{"sum_comment":"","sum_comment_unclear":false,"sum_foreign_comment":"","sum":"","sum_foreign":""},"56":{"sum_comment":"","sum_foreign_comment":"","sum_foreign":"","sum":""},"57":{"sum_comment":"","sum_foreign_comment":"","sum_foreign":"","sum":"","sum_comment_hidden":false},"58":{"sum_comment":"","sum_foreign_comment":"","sum_foreign":"","sum":"","sum_comment_hidden":false},"59":{"sum_comment":"","sum_foreign_comment":"","sum_foreign":"","sum":""},"60":{"sum_comment":"","sum_foreign_comment":"","sum_foreign":"","sum":""},"61":{"sum_comment":"","sum_foreign_comment":"","sum_foreign":"","sum":""},"62":{"sum_comment":"","sum_foreign_comment":"","sum_foreign":"","sum":""},"63":{"sum_comment":"","sum_foreign_comment":"","sum_foreign":"","sum":"80000"},"64":{"sum_comment":"","sum_foreign_comment":"","sum_foreign":"","sum":""}},"declaration":{"notfull_lostpages":"","additional_info_text":"","additional_info":"","date":"2016-03-31T00:00:00","notfull":"","url":"http://static.declarations.com.ua/declarations/chosen_ones/judges_batch/2529_iuzikov_stanislav_heorhiiovych_2015.pdf"},"intro":{"isnotdeclaration":"","declaration_year":"2015"}}