{"income":{"5":{"value":"369193.73","family_comment":"","value_unclear":false,"comment_hidden":false,"family_hidden":false,"value_hidden":false,"family_unclear":false,"family":"57598.58","comment":""},"6":{"value":"243133.73","family_comment":"","value_unclear":false,"family_hidden":false,"family_unclear":false,"comment_unclear":false,"comment":"","family":"41064.18"},"7":{"source_name_unclear":false,"value":"","value_hidden":false,"family_comment":"","source_name":"","family":"","comment":"","source_name_hidden":false},"8":{"value":"","family_hidden":false,"value_hidden":false,"family_comment":"","family":"","comment":""},"9":{"value":"","family_comment":"","value_unclear":false,"family_hidden":false,"value_hidden":false,"family_unclear":false,"family":"","comment":""},"10":{"family_comment":"","value":"12180","family":"5146.4","comment":""},"11":{"family_comment":"","value":"","family":"","comment":""},"12":{"family_comment":"","value":"","family":"","comment":""},"13":{"family_comment":"","value":"","family":"","comment":""},"14":{"family_comment":"","value":"","family":"","comment":""},"15":{"family_comment":"","value":"","family":"","comment":""},"16":{"value":"","family_comment":"","value_unclear":false,"family_unclear":false,"family":"","comment":""},"17":{"family_comment":"","value":"","family":"","comment":""},"18":{"family_comment":"","value":"","family":"","comment":""},"19":{"family_comment":"","value":"","comment_unclear":false,"family":"","comment":""},"20":{"value":"113880","family_comment":"","value_unclear":false,"comment_hidden":false,"family_hidden":false,"family":"11388","value_hidden":false,"family_unclear":false,"comment_unclear":false,"comment":"","family_comment_unclear":false}},"vehicle":{"35":[{"brand_info":"","sum_rent_comment":"","brand":"","sum_comment":"","brand_unclear":false,"year":"","brand_info_unclear":true,"sum":"","sum_rent":""}],"40":[{"brand_info":"1300 куб.см.","sum_rent_comment":"","brand":"Wartburg 1. 3","sum_comment":"","brand_unclear":true,"year":"1990","brand_info_unclear":true,"year_unclear":false,"sum":"","sum_rent":""}]},"id":"vulyk_63_2","banks":{"48":[{"sum_foreign_comment":"","sum_units":"UAH","sum_comment":"","sum_foreign_units":"UAH","sum":"","sum_units_hidden":true,"sum_foreign":""}]},"declaration":{"additional_info_text":"","notfull_lostpages":"","date":"2013-03-17T00:00:00","notfull":"","additional_info":"","url":"http://static.declarations.com.ua/declarations/chosen_ones/mega_batch/slobodeniuk_nataliia_ievhenivna.pdf"},"liabilities":{"54":{"sum_foreign_comment":"","sum":"","sum_comment":"","sum_unclear":false,"sum_foreign":""},"55":{"sum_foreign_comment":"","sum":"","sum_comment":"","sum_foreign":""},"56":{"sum_foreign_comment":"","sum":"","sum_comment":"","sum_unclear":false,"sum_foreign":""},"57":{"sum_foreign_comment":"","sum":"","sum_comment":"","sum_comment_hidden":false,"sum_unclear":false,"sum_foreign":""},"58":{"sum_foreign_comment":"","sum_comment_hidden":false,"sum":"","sum_comment":"","sum_foreign":""},"59":{"sum_foreign_comment":"","sum":"","sum_comment":"","sum_foreign":""},"60":{"sum_foreign_comment":"","sum":"","sum_comment":"","sum_comment_unclear":false,"sum_foreign":""},"61":{"sum_foreign_comment":"","sum":"","sum_comment":"","sum_unclear":false,"sum_foreign":""},"62":{"sum_foreign_comment":"","sum":"","sum_comment":"","sum_unclear":false,"sum_foreign":""},"63":{"sum_foreign_comment":"","sum":"","sum_comment":"","sum_hidden":false,"sum_comment_hidden":false,"sum_unclear":false,"sum_foreign":""},"64":{"sum_foreign_comment":"","sum_comment_hidden":false,"sum":"","sum_comment":"","sum_foreign":""}},"ft_src":"суддя черняхівського районного суду житомирської області\nЖитомирська область\nЗагальний місцевий суд\nНаталія\nДитина\nЄвгенівна\nСлободенюк\nСлободенюк Наталія Євгенівна\nСлободенюк Наталія Євгенівна\nНаталія Євгенівна Слободенюк\nНаталія Слободенюк\nСлободенюк Наталія Євгенівна\n1300 куб.см.\nWartburg 1. 3\n1990\n2014\n1300 куб.см.\n1990\nWartburg 1. 3\n1200\nЖитомирська область\nсмт. Черняхів\n1350\nсмт. Черняхів\nЖитомирська область\n159.9\nЖитомирська область\nсмт. Черняхів\nЄвгенівна\nСлободенюк Наталія Євгенівна\nНаталія Євгенівна Слободенюк\nНаталія Слободенюк\nСлободенюк Наталія Євгенівна\nНаталія\nДитина\nСлободенюк Наталія Євгенівна\nЗагальний місцевий суд\nЖитомирська область\nсуддя черняхівського районного суду житомирської області\nСлободенюк\n243133.73\n41064.18\n113880\n11388\n369193.73\n57598.58\n12180\n5146.4\n2014\nсмт. Черняхів\n1200\nЖитомирська область\nЖитомирська область\nсмт. Черняхів\n1350\nсмт. Черняхів\n159.9\nЖитомирська область\nДитина\nЄвгенівна\nСлободенюк\nСлободенюк Наталія Євгенівна\nНаталія Євгенівна Слободенюк\nНаталія Слободенюк\nСлободенюк Наталія Євгенівна\nНаталія\nЖитомирська область\nсуддя черняхівського районного суду житомирської області\nЗагальний місцевий суд\nСлободенюк Наталія Євгенівна\n41064.18\n243133.73\n5146.4\n12180\n57598.58\n369193.73\n11388\n113880\n1990\n1300 куб.см.\nWartburg 1. 3\n5146.4\n12180\n113880\n11388\n369193.73\n57598.58\n243133.73\n41064.18\nЖитомирська область\nсмт. Черняхів\n1200\nсмт. Черняхів\nЖитомирська область\n159.9\nсмт. Черняхів\nЖитомирська область\n1350\n2014","general":{"name_hidden":false,"name":"Наталія","patronymic_unclear":false,"last_name_hidden":false,"inn":"","family":[{"inn":"","inn_hidden":true,"relations_unclear":false,"relations_hidden":false,"relations_other":"","relations":"Дитина","name_hidden":true,"inn_unclear":false,"family_name":"","name_unclear":false}],"patronymic":"Євгенівна","inn_hidden":true,"family_raw":"","inn_unclear":false,"post":{"post_unclear":false,"region_unclear":false,"region":"Житомирська область","office_hidden":false,"region_hidden":false,"post":"суддя черняхівського районного суду житомирської області","office_unclear":true,"office":"Загальний місцевий суд"},"last_name_unclear":true,"full_name":"Слободенюк Наталія Євгенівна","addresses":[{"place_city_type_unclear":false,"place_address":"","place_district_hidden":true,"place_city_type":"","place_address_hidden":true,"place_address_unclear":false,"place_city_type_hidden":true,"place":"","place_district":"","place_unclear":false,"place_city":"","place_city_unclear":false,"place_hidden":true,"place_city_hidden":true,"place_district_unclear":false}],"last_name":"Слободенюк","full_name_suggest":{"output":"Слободенюк Наталія Євгенівна","input":["Слободенюк Наталія Євгенівна","Наталія Євгенівна Слободенюк","Наталія Слободенюк"]},"name_unclear":false},"source":"VULYK","estate":{"23":[{"space_unclear":false,"costs":"","costs_comment":"","costs_hidden":false,"address_hidden":true,"region_hidden":false,"space_comment":"","space_hidden":false,"space":"1200","address":"смт. Черняхів","region":"Житомирська область","space_units_unclear":false,"costs_rent_hidden":false,"space_units":"м²","space_units_hidden":false,"costs_rent":"","costs_rent_comment":""}],"24":[{"region_unclear":false,"space_unclear":false,"costs":"","costs_comment":"","address_hidden":false,"region_hidden":false,"space_comment":"","space":"159.9","address":"смт. Черняхів","region":"Житомирська область","address_unclear":false,"space_units_unclear":false,"space_units":"м²","costs_rent":"","costs_rent_comment":""}],"29":[{"space_hidden":false,"costs_property_comment":"","address_hidden":true,"region_hidden":false,"space_comment":"","space_unclear":false,"space":"1350","address":"смт. Черняхів","region":"Житомирська область","costs_property":"","costs_rent_comment":"","address_unclear":false,"space_units":"м²","space_units_unclear":false,"costs_rent":""}]},"intro":{"declaration_year":"2014","isnotdeclaration":"","declaration_year_unclear":true}}