{"income":{"5":{"value":"212058","family_comment":"","value_unclear":false,"family_unclear":false,"family":"247883","comment":""},"6":{"value":"212058","family_comment":"","value_unclear":false,"family_unclear":false,"family":"238220","comment":""},"7":{"family_comment":"","value":"","source_name":"","family":"","comment":""},"8":{"family_comment":"","value":"","family":"","comment":""},"9":{"family_comment":"","value":"","family":"","comment":"","family_comment_unclear":false},"10":{"family_comment":"","value":"","family":"","comment":""},"11":{"family_comment":"","value":"","family":"","comment":""},"12":{"family_comment":"","value":"","family":"","comment":""},"13":{"family_comment":"","value":"","family":"","comment":""},"14":{"family_comment":"","value":"","family":"","comment":""},"15":{"family_comment":"","value":"","family":"","comment":""},"16":{"family_comment":"","family_unclear":false,"value":"","family":"","comment":""},"17":{"family_comment":"","family_unclear":false,"value":"","family":"","comment":""},"18":{"family_comment":"","value":"","family":"","comment":""},"19":{"family_comment":"","value":"","family":"","comment":""},"20":{"family_comment":"","value":"","family":"9663","comment":""}},"vehicle":{"35":[{"brand_info":"2362 куб. см.","sum":"","brand":"Toyota Camry","sum_comment":"","sum_comment_unclear":false,"year":"2004","brand_hidden":false,"sum_rent_comment":"","sum_rent":"","brand_unclear":false}],"40":[{"brand_info":"3456 куб. см.","sum":"","brand":"Lexus ES 350","sum_comment":"","year":"2007","brand_hidden":false,"brand_info_hidden":false,"sum_rent_comment":"","sum_rent":""}]},"id":"vulyk_88_44","declaration":{"additional_info_text":"","notfull_lostpages":"","date":"2015-03-30T00:00:00","notfull":"","additional_info":"","url":"http://static.declarations.com.ua/declarations/chosen_ones/judges_batch/2947_kovtunenko_vadym_oleksiiovych.pdf"},"liabilities":{"54":{"sum_foreign_comment":"","sum":"","sum_comment":"","sum_comment_unclear":false,"sum_foreign":""},"55":{"sum_foreign_comment":"","sum":"","sum_comment":"","sum_foreign":""},"56":{"sum_foreign_comment":"","sum":"","sum_comment":"","sum_foreign":""},"57":{"sum_foreign_comment":"","sum":"","sum_comment":"","sum_hidden":false,"sum_comment_hidden":false,"sum_unclear":false,"sum_foreign":""},"58":{"sum_foreign_comment":"","sum":"","sum_comment":"","sum_hidden":false,"sum_comment_hidden":false,"sum_foreign":""},"59":{"sum_foreign_comment":"","sum":"","sum_comment":"","sum_foreign":""},"60":{"sum_foreign_comment":"","sum":"","sum_comment":"","sum_comment_unclear":false,"sum_hidden":false,"sum_comment_hidden":false,"sum_foreign":""},"61":{"sum_foreign_comment":"","sum":"","sum_comment":"","sum_foreign":""},"62":{"sum_foreign_comment":"","sum":"","sum_comment":"","sum_foreign":""},"63":{"sum_foreign_comment":"","sum":"","sum_comment":"","sum_foreign":""},"64":{"sum_foreign_comment":"","sum":"","sum_comment":"","sum_foreign":""}},"ft_src":"Toyota Camry\n2004\n2362 куб. см.\n2007\nLexus ES 350\n3456 куб. см.\n98.7\n2014\n238220\n212058\n247883\n212058\n9663\n2362 куб. см.\nToyota Camry\n2004\n3456 куб. см.\n2007\nLexus ES 350\n98.7\nКовтуненко Вадим Олексійович\nВадим Олексійович Ковтуненко\nВадим Ковтуненко\nКовтуненко Вадим Олексійович\nВадим\nПодружжя\nКовтуненко О. В\nДитина\nКовтуненко О. В\nКовтуненко Вадим Олексійович\nКовтуненко\nЗагальний місцевий суд\nсуддя жовтневого районного суду м. маріуполя донецької області\nДонецька область\nОлексійович\n212058\n238220\n9663\n212058\n247883\n2014\nКовтуненко О. В\nПодружжя\nКовтуненко О. В\nДитина\nОлексійович\nКовтуненко\nВадим\nКовтуненко Вадим Олексійович\nВадим Олексійович Ковтуненко\nВадим Ковтуненко\nКовтуненко Вадим Олексійович\nДонецька область\nЗагальний місцевий суд\nсуддя жовтневого районного суду м. маріуполя донецької області\nКовтуненко Вадим Олексійович","general":{"inn":"","name":"Вадим","patronymic_unclear":false,"family":[{"inn":"","relations":"Подружжя","name_hidden":false,"inn_hidden":true,"family_name":"Ковтуненко О. В","name_unclear":false},{"inn":"","inn_hidden":false,"family_name":"Ковтуненко О. В","relations_other":"","relations":"Дитина","name_hidden":false,"name_unclear":false}],"patronymic":"Олексійович","inn_hidden":true,"family_raw":"","last_name":"Ковтуненко","post":{"post":"суддя жовтневого районного суду м. маріуполя донецької області","region":"Донецька область","candidate":"","office":"Загальний місцевий суд","region_hidden":false,"office_hidden":false},"full_name_suggest":{"output":"Ковтуненко Вадим Олексійович","input":["Ковтуненко Вадим Олексійович","Вадим Олексійович Ковтуненко","Вадим Ковтуненко"]},"full_name":"Ковтуненко Вадим Олексійович","addresses":[{"place_district":"","place_address_hidden":false,"place_city":"","place_address":"","place_district_hidden":false,"place_city_type":"","place_city_hidden":false,"place_city_type_hidden":false,"place_hidden":true,"place":""}],"patronymic_hidden":false,"last_name_unclear":false},"source":"VULYK","estate":{"30":[{"address_hidden":false,"region_hidden":true,"space_comment":"","space":"98.7","address":"","region":"","costs_property":"","costs_rent_comment":"","address_unclear":false,"space_units":"м²","costs_property_comment":"","costs_rent":""}]},"intro":{"declaration_year":"2014","isnotdeclaration":""}}