{"income":{"5":{"family_comment":"","value":"205553","family":"24325","comment":""},"6":{"family_comment":"","value":"193373","family":"24000","comment":"","family_comment_unclear":false},"7":{"value":"","comment_hidden":false,"family_comment":"","source_name":"","family":"","comment":"","source_name_hidden":false},"8":{"family_comment":"","value":"","family":"","comment":""},"9":{"family_comment":"","value":"","family":"","comment":""},"10":{"value":"12180","value_unclear":false,"value_hidden":false,"family_comment":"","family":"","comment":""},"11":{"family_comment":"","value":"","family":"","comment":""},"12":{"family_comment":"","value":"","family":"","comment":""},"13":{"family_comment":"","value":"","family":"","comment":""},"14":{"family_comment":"","value":"","family":"","comment":""},"15":{"family_comment":"","value":"","family":"","comment":""},"16":{"family_comment":"","value":"","family":"","comment":""},"17":{"family_comment":"","value":"","family":"","comment":""},"18":{"family_comment":"","value":"","family":"","comment":""},"19":{"family_comment":"","value":"","family":"","comment":""},"20":{"family_comment":"","value":"","comment_unclear":false,"family":"325","comment":""}},"vehicle":{"40":[{"brand_info":"1480","sum":"","brand":"Москвич / АЗЛК 21412","sum_comment":"","brand_unclear":false,"year":"1991","sum_rent_comment":"","sum_rent":""},{"brand_info":"1480","sum":"","brand":"Москвич / АЗЛК 21412","sum_comment":"","year":"1989","sum_rent_comment":"","sum_rent":""}]},"id":"vulyk_86_73","declaration":{"additional_info_text":"","notfull_lostpages":"","date":"2015-03-18T00:00:00","notfull":"","additional_info":"","url":"http://static.declarations.com.ua/declarations/chosen_ones/judges_batch/2776_kornieieva_inessa_viktorivna.pdf"},"liabilities":{"54":{"sum_foreign_comment":"","sum":"","sum_comment":"","sum_unclear":false,"sum_foreign":""},"55":{"sum_foreign_comment":"","sum":"","sum_comment":"","sum_foreign":""},"56":{"sum_foreign_comment":"","sum":"6364","sum_foreign":"","sum_comment":"","sum_hidden":false},"57":{"sum_foreign_comment":"","sum":"10814","sum_comment":"","sum_unclear":false,"sum_foreign":""},"58":{"sum_foreign_comment":"","sum":"16136","sum_comment":"","sum_unclear":false,"sum_foreign":""},"59":{"sum_foreign_comment":"","sum":"","sum_comment":"","sum_foreign":""},"60":{"sum_foreign_comment":"","sum_comment":"","sum":"110","sum_comment_hidden":false,"sum_foreign":""},"61":{"sum_foreign_comment":"","sum":"","sum_comment":"","sum_foreign":""},"62":{"sum_foreign_comment":"","sum":"","sum_comment":"","sum_foreign":""},"63":{"sum_foreign_comment":"","sum":"20449","sum_comment":"","sum_foreign":""},"64":{"sum_foreign_comment":"","sum":"7761","sum_comment":"","sum_foreign":""}},"ft_src":"1991\n1480\nМосквич / АЗЛК 21412\n1480\n1989\nМосквич / АЗЛК 21412\nм. Красноармійськ\n652\nДонецька область\nДонецька область\nм. Красноармійськ\n177.9\n2014\n24000\n193373\n12180\n24325\n205553\n325\n1480\nМосквич / АЗЛК 21412\n1991\n1480\nМосквич / АЗЛК 21412\n1989\n2014\nКорнєєва Інесса Вікторівна\nІнесса Вікторівна Корнєєва\nІнесса Корнєєва\nКорнєєва Інесса Вікторівна\nКорнєєва Інесса Вікторівна\nПодружжя\nСекірін О. В\nДитина\nСекірін Б. О\nДубіна Т. В\nДитина\nДубіна Н. Д\nІнесса\nКорнєєва\nЗагальний місцевий суд\nДонецька область\nсуддя красноармійського міськрайонного суду донецької області\nВікторівна\nДонецька область\nКрасноармійськ\nКрасноармійський\n16136\n7761\n20449\n110\n6364\n10814\n193373\n24000\n325\n205553\n24325\n12180\n652\nДонецька область\nм. Красноармійськ\n177.9\nДонецька область\nм. Красноармійськ\n16136\n7761\n6364\n10814\n110\n20449\nСекірін О. В\nПодружжя\nСекірін Б. О\nДитина\nДитина\nДубіна Т. В\nДубіна Н. Д\nВікторівна\nКорнєєва\nІнесса\nКорнєєва Інесса Вікторівна\nІнесса Вікторівна Корнєєва\nІнесса Корнєєва\nКорнєєва Інесса Вікторівна\nКрасноармійськ\nДонецька область\nКрасноармійський\nДонецька область\nЗагальний місцевий суд\nсуддя красноармійського міськрайонного суду донецької області\nКорнєєва Інесса Вікторівна","general":{"inn":"","name":"Інесса","patronymic_unclear":false,"last_name":"Корнєєва","family":[{"inn":"","inn_hidden":true,"relations_hidden":false,"family_name":"Секірін О. В","relations_other":"","relations":"Подружжя","name_hidden":false,"name_unclear":false},{"inn":"","inn_hidden":false,"family_name":"Секірін Б. О","relations_other":"","relations":"Дитина","name_hidden":false,"name_unclear":false},{"inn":"","inn_hidden":false,"relations":"Дитина","name_unclear":false,"family_name":"Дубіна Т. В"},{"inn":"","family_name":"Дубіна Н. Д","relations":"","name_unclear":false}],"inn_hidden":true,"family_raw":"","inn_unclear":false,"post":{"post_unclear":false,"post":"суддя красноармійського міськрайонного суду донецької області","candidate":"","office_hidden":false,"region":"Донецька область","region_hidden":false,"office":"Загальний місцевий суд","office_unclear":false},"full_name":"Корнєєва Інесса Вікторівна","addresses":[{"place_district":"Красноармійський","place_address_hidden":true,"place_city":"Красноармійськ","place_address":"","place_district_hidden":false,"place_city_type":"Місто","place_unclear":false,"place_city_hidden":false,"place_city_type_hidden":false,"place_hidden":false,"place":"Донецька область"}],"patronymic":"Вікторівна","full_name_suggest":{"output":"Корнєєва Інесса Вікторівна","input":["Корнєєва Інесса Вікторівна","Інесса Вікторівна Корнєєва","Інесса Корнєєва"]}},"source":"VULYK","estate":{"23":[{"costs":"","costs_comment":"","address_hidden":false,"region_hidden":false,"space_comment":"","space":"652","address":"м. Красноармійськ","region":"Донецька область","address_unclear":false,"costs_rent_comment":"","space_units":"м²","costs_rent":""}],"24":[{"costs":"","costs_comment":"","address_hidden":false,"region_hidden":false,"space_comment":"","space":"177.9","address":"м. Красноармійськ","region":"Донецька область","address_unclear":false,"costs_rent_comment":"","space_units":"м²","costs_rent":""}]},"intro":{"declaration_year":"2014","declaration_year_unclear":false}}