{"income":{"5":{"value":"253032","family_unclear":false,"family_hidden":false,"family_comment":"","family":"46026","comment":""},"6":{"value":"239887","family_comment":"","value_unclear":false,"family_hidden":false,"family_unclear":false,"family":"","comment":""},"7":{"value":"368","family_hidden":false,"value_hidden":false,"family_comment":"","source_name":"","family":"","comment":"","source_name_hidden":false},"8":{"family_comment":"","value":"","family":"","comment":""},"9":{"family_comment":"","value":"31","family":"62","comment":""},"10":{"family_comment":"","value":"12617","value_unclear":false,"family":"","comment":""},"11":{"family_comment":"","value":"128","family":"","comment":""},"12":{"family_comment":"","value":"","family":"","comment":""},"13":{"family_comment":"","value":"","family":"","comment":""},"14":{"family_comment":"","value":"","family":"","comment":""},"15":{"family_comment":"","value":"","family":"","comment":""},"16":{"family_comment":"","value":"","family":"","comment":""},"17":{"family_comment":"","value":"","family":"","comment":""},"18":{"family_comment":"","value":"","family":"","comment":""},"19":{"family_comment":"","value":"","family":"","comment":""},"20":{"value":"","family_comment":"","value_unclear":false,"family_unclear":false,"comment_unclear":false,"comment":"","family":""}},"vehicle":{"35":[{"brand_info":"1300 куб. см., 70 к.с., 430 см","sum_rent_comment":"","year":"2005","brand_info_hidden":false,"brand_info_unclear":false,"year_unclear":false,"sum_rent":"","sum":"","brand":"Daewoo Sens","sum_comment":"","brand_unclear":false,"brand_hidden":false}],"40":[{"brand_info":"1998 куб. см., користування","sum_rent_comment":"","brand":"Toyota Rav 4","sum_comment":"","brand_unclear":false,"year":"2008","brand_info_unclear":false,"year_unclear":false,"sum":"","sum_rent":""}]},"id":"vulyk_74_91","declaration":{"additional_info_text":"","notfull_lostpages":"","date":"2014-03-14T00:00:00","notfull":"","additional_info":"","url":"http://static.declarations.com.ua/declarations/chosen_ones/judges_batch/1602_sirenko_olha_ivanivna.pdf"},"liabilities":{"54":{"sum_foreign_comment":"","sum":"","sum_comment":"","sum_comment_unclear":false,"sum_comment_hidden":false,"sum_foreign":""},"55":{"sum_foreign_comment":"","sum":"","sum_comment":"","sum_hidden":false,"sum_unclear":false,"sum_foreign":""},"56":{"sum_foreign_comment":"","sum":"","sum_comment":"","sum_hidden":false,"sum_unclear":false,"sum_foreign":""},"57":{"sum_foreign_comment":"","sum":"","sum_comment":"","sum_comment_unclear":false,"sum_comment_hidden":false,"sum_foreign":""},"58":{"sum_foreign_comment":"","sum_comment_hidden":false,"sum":"","sum_comment":"","sum_foreign":""},"59":{"sum_foreign_comment":"","sum":"","sum_comment":"","sum_foreign":""},"60":{"sum_foreign_comment":"","sum":"","sum_hidden":false,"sum_comment":"","sum_foreign":""},"61":{"sum_foreign_comment":"","sum":"","sum_comment":"","sum_foreign":""},"62":{"sum_foreign_comment":"","sum":"","sum_comment":"","sum_foreign":""},"63":{"sum_foreign_comment":"","sum":"","sum_comment":"","sum_comment_unclear":false,"sum_unclear":false,"sum_foreign":""},"64":{"sum_foreign_comment":"","sum":"","sum_comment":"","sum_comment_unclear":false,"sum_unclear":false,"sum_foreign":""}},"ft_src":"Сіренко Ольга Іванівна\nсуддя харківського апеляційного адміністративного суду\nХарківська область\nАпеляційний адміністративний суд\nОльга\nПодружжя\nСіренко Ольга Іванівна\nОльга Іванівна Сіренко\nОльга Сіренко\nСіренко Ольга Іванівна\nСіренко\nІванівна\n1300 куб. см., 70 к.с., 430 см\nDaewoo Sens\n2005\nToyota Rav 4\n1998 куб. см., користування\n2008\n.1\n31%\n.14\n148\n50.8\n2013\n239887\n62\n31\n128\n12617\n368\n46026\n253032\n1300 куб. см., 70 к.с., 430 см\nDaewoo Sens\n2005\n1998 куб. см., користування\nToyota Rav 4\n2008\n2013\nАпеляційний адміністративний суд\nХарківська область\nсуддя харківського апеляційного адміністративного суду\nІванівна\nСіренко Ольга Іванівна\nОльга Іванівна Сіренко\nОльга Сіренко\nСіренко Ольга Іванівна\nОльга\nСіренко Ольга Іванівна\nСіренко\nПодружжя\n368\n239887\n253032\n46026\n31\n62\n12617\n128\n148\n50.8\n.14\n.1\n31%\nПодружжя\nІванівна\nСіренко\nХарківська область\nАпеляційний адміністративний суд\nсуддя харківського апеляційного адміністративного суду\nСіренко Ольга Іванівна\nСіренко Ольга Іванівна\nОльга Іванівна Сіренко\nОльга Сіренко\nСіренко Ольга Іванівна\nОльга\nDaewoo Sens\n1300 куб. см., 70 к.с., 430 см\n2005\n2008\n1998 куб. см., користування\nToyota Rav 4\n128\n62\n31\n12617\n253032\n46026\n368\n239887\n50.8\n.14\n31%\n148\n.1\n2013","general":{"inn":"","inn_hidden":true,"last_name":"Сіренко","post":{"region_unclear":false,"region":"Харківська область","post":"суддя харківського апеляційного адміністративного суду","office":"Апеляційний адміністративний суд","office_unclear":false,"post_hidden":false},"name":"Ольга","full_name":"Сіренко Ольга Іванівна","family_raw":"","addresses":[{"place_district":"","place_city_hidden":true,"place_city":"","place_city_type_hidden":true,"place_district_hidden":true,"place_city_type":"","place_address_hidden":true,"place_address":"","place_hidden":true,"place":""}],"family":[{"inn":"","relations":"Подружжя","relations_other":"","inn_hidden":true,"family_name":"","name_hidden":true,"name_unclear":false}],"full_name_suggest":{"output":"Сіренко Ольга Іванівна","input":["Сіренко Ольга Іванівна","Ольга Іванівна Сіренко","Ольга Сіренко"]},"patronymic":"Іванівна"},"source":"VULYK","estate":{"23":[{"space_hidden":false,"costs":"","costs_comment":"","address_hidden":true,"region_hidden":true,"space_comment":"","space_unclear":false,"space":".14","address":"","region":"","space_units_unclear":false,"space_comment_unclear":false,"space_units":"га","costs_rent":"","costs_rent_comment":""}],"24":[{"region_unclear":false,"space_hidden":false,"costs":"","costs_comment":"","address_hidden":true,"region_hidden":true,"space_comment":"31%","space":"","address":"","region":"","space_units_unclear":true,"space_units":"м²","costs_rent":"","costs_rent_comment":""}],"25":[{"space_hidden":false,"costs":"","costs_comment":"","address_hidden":true,"region_hidden":true,"space_comment":"","space_unclear":false,"space":"50.8","address":"","region":"","costs_rent_comment":"","space_units":"м²","costs_rent":""}],"28":[{"costs":"","costs_comment":"","address_hidden":true,"region_hidden":true,"space_comment":"","space":"","address":"","region":"","address_unclear":false,"costs_rent_comment":"","space_units":"м²","costs_rent":""}],"29":[{"costs_rent":"","region":"","costs_property":"","costs_rent_comment":"","address_hidden":true,"region_hidden":true,"space_comment":"","costs_property_comment":"","space_units":"га","space":".1","address":""}],"30":[{"space_unclear":false,"address_hidden":true,"region_hidden":true,"space_comment":"","space":"148","address":"","region":"","costs_property":"","costs_rent_comment":"","space_comment_unclear":false,"address_unclear":false,"space_units":"м²","costs_property_comment":"","costs_rent":""}]},"intro":{"declaration_year":"2013","isnotdeclaration":"","declaration_year_unclear":false}}