{"id":"vulyk_95_28","ft_src":"Toyota Camry\n3500 куб. см.\n2009\n2010\n5461 куб. см.\nMercedes-Benz GL 550\nінше право користування\nToyota Camry\n3500 куб. см.\n2009\n5461 куб. см.\n2010\nMercedes-Benz GL 550\nХарківська область\nХарків\n20\nм. Харків\n20\nХарківська область\nХарківська область\nХарків\n27.3\nХарківська область\nХарків, підземна автостоянка\n23.6\nм. Харків\n14.2\nХарківська область\nХарківська область\nХарків\n78\nХарківська область\nХарківський р-н, смт. Високий\n918\nХарківський р-он, Русько-Тишківський\n120\nХарківська область\nХарківська область\nХарківський р-н, смт. Високий\n91.1\nЛьох\nХарківська область\nм. Харків\n27.7\nХарківська область\nПідвал\nм. Харків\n121\n121\nХарківська область\nм. Харків\n187.2\nХарківська область\nм. Харків\n105.6\nХарківська область\nХарків\n82.3\nХарків\n146.2\nХарківська область\n1589\n45391\n1589\n2015\nToyota Camry\n3500 куб. см.\n2009\n5461 куб. см.\nінше право користування\nMercedes-Benz GL 550\n2010\nToyota Camry\n3500 куб. см.\n2009\n5461 куб. см.\n2010\nMercedes-Benz GL 550\n2015\nВадимович\nПодружжя\nТацій Лариса Василівна\nДитина\nТацій Василь Владиславович\nЄгупенко Владислав Вадимович\nВладислав Вадимович Єгупенко\nВладислав Єгупенко\nЄгупенко Владислав Вадимович\nВладислав\nХарків\n61024, зареєстровний 61002, м. Харків\nХарківська область\nЄгупенко Владислав Вадимович\nЄгупенко\nАдміністративний місцевий суд\nсуддя харківського окружного адміністративного суду\nХарківська область\nНаціональний юридичний університет ім. Я. Мудрого\n4574\n159302\n225829\n26204\nпенсія та виплати учаснику ліквідації аварії на ЧАЕС\n185506\n230403\n20\nХарків\nХарківська область\n20\nм. Харків\nХарківська область\nХарківський р-н, смт. Високий\nХарківська область\n91.1\n14.2\nм. Харків\nХарківська область\n146.2\nХарків\nХарківська область\nХарків\nХарківська область\n78\nХарківський р-н, смт. Високий\nХарківська область\n918\n120\nХарківський р-он, Русько-Тишківський\nХарківська область\n27.3\nХарківська область\nХарків\n23.6\nХарків, підземна автостоянка\nХарківська область\nм. Харків\nХарківська область\n187.2\nм. Харків\nХарківська область\n105.6\n82.3\nХарків\nХарківська область\nЛьох\nм. Харків\nХарківська область\n27.7\n121\nПідвал\nХарківська область\nм. Харків\n121\n1589\n45391\n1589\n225829\n159302\nНаціональний юридичний університет ім. Я. Мудрого\n4574\n230403\n185506\nпенсія та виплати учаснику ліквідації аварії на ЧАЕС\n26204\nТацій Лариса Василівна\nПодружжя\nТацій Василь Владиславович\nДитина\nХарківська область\nХарків\n61024, зареєстровний 61002, м. Харків\nВадимович\nЄгупенко\nХарківська область\nАдміністративний місцевий суд\nсуддя харківського окружного адміністративного суду\nЄгупенко Владислав Вадимович\nЄгупенко Владислав Вадимович\nВладислав Вадимович Єгупенко\nВладислав Єгупенко\nЄгупенко Владислав Вадимович\nВладислав","estate":{"23":[{"address":"Харківський р-он, Русько-Тишківський","space_units":"м²","costs_comment":"","space_unclear":false,"costs_comment_hidden":false,"region":"Харківська область","address_hidden":true,"space":"120","address_unclear":false,"space_comment":"","costs_rent_comment":"","costs":"","region_unclear":false,"region_hidden":false,"costs_rent":""}],"25":[{"address":"Харків","space_units":"м²","space_hidden":false,"space_unclear":false,"region_hidden":false,"costs_rent_comment":"","space_comment":"","address_hidden":true,"costs":"","address_unclear":false,"space_comment_unclear":false,"costs_comment":"","space":"146.2","region":"Харківська область","costs_rent":""}],"27":[{"address":"Харків","space_units":"м²","costs_comment":"","space_comment":"","region_hidden":false,"region":"Харківська область","address_hidden":true,"space":"20","address_unclear":false,"costs_rent_comment":"","costs":"","costs_rent":""},{"costs":"","address":"м. Харків","space_units":"м²","costs_rent_comment":"","space":"20","space_comment":"","costs_comment":"","region":"Харківська область","address_hidden":true,"costs_rent":""}],"28":[{"address":"м. Харків","space_units":"м²","costs_comment":"","space_unclear":false,"region_hidden":false,"space_comment":"","address_hidden":false,"costs":"","address_unclear":false,"costs_rent_comment":"","space":"14.2","region":"Харківська область","costs_rent":""}],"29":[{"costs_property_comment":"","address":"Харків","space_units":"м²","space_unclear":false,"region_hidden":false,"costs_property":"","space_comment":"","address_hidden":true,"address_unclear":false,"costs_rent_comment":"","space":"78","region_unclear":false,"region":"Харківська область","costs_rent":""},{"costs_property_comment":"","address":"Харківський р-н, смт. Високий","space_units":"м²","space_comment":"","region_hidden":false,"costs_property":"","region":"Харківська область","address_hidden":false,"address_unclear":false,"costs_rent_comment":"","space":"918","costs_rent":""}],"30":[{"costs_property_comment":"","address":"Харківський р-н, смт. Високий","space_units":"м²","space_unclear":false,"region_hidden":false,"costs_property":"","space_comment":"","address_hidden":false,"address_unclear":false,"costs_rent_comment":"","space":"91.1","region":"Харківська область","costs_rent":""}],"31":[{"costs_property_comment":"","address":"м. Харків","space_units":"м²","space_unclear":false,"region_hidden":false,"costs_property":"","space_comment":"","address_hidden":true,"space_comment_unclear":false,"costs_rent_comment":"","space":"187.2","region":"Харківська область","costs_rent":""},{"costs_property_comment":"","address":"м. Харків","space_units":"м²","space_comment":"","region_hidden":false,"costs_property":"","region":"Харківська область","address_hidden":true,"space_comment_unclear":false,"costs_rent_comment":"","space":"105.6","costs_rent":""},{"costs_property_comment":"","address":"Харків","space_units":"м²","costs_rent_comment":"","space":"82.3","region":"Харківська область","costs_property":"","space_comment":"","address_hidden":true,"costs_rent":""}],"33":[{"costs_property_comment":"","address":"Харків","space_units":"м²","costs_rent_comment":"","space":"27.3","region":"Харківська область","region_hidden":false,"costs_property":"","space_comment":"","address_hidden":false,"costs_rent":""},{"costs_property_comment":"","address":"Харків, підземна автостоянка","space_units":"м²","costs_rent_comment":"","space":"23.6","region":"Харківська область","costs_property":"","space_comment":"","address_hidden":true,"costs_rent":""}],"34":[{"costs_property_comment":"","address":"м. Харків","space_units":"м²","space_unclear":false,"region_hidden":false,"costs_property":"","space_comment":"Льох","address_hidden":true,"address_unclear":false,"costs_rent_comment":"","space":"27.7","region":"Харківська область","costs_rent":""},{"costs_property_comment":"","address":"м. Харків","space_units":"м²","costs_rent_comment":"","space":"121","region":"Харківська область","region_hidden":false,"costs_property":"","space_comment":"Підвал","costs_rent":""},{"costs_property_comment":"","address":"","costs_rent_comment":"","space":"121","region":"","costs_property":"","space_comment":"","costs_rent":""}]},"vehicle":{"35":[{"sum_comment":"","brand_info_hidden":false,"brand_info":"3500 куб. см.","sum":"","brand_unclear":false,"brand_hidden":false,"brand":"Toyota Camry","sum_rent":"","sum_rent_comment":"","year":"2009","brand_info_unclear":false},{"sum_comment":"","brand_info":"5461 куб. см.","sum":"","brand_unclear":false,"year":"2010","brand":"Mercedes-Benz GL 550","sum_rent":"","sum_rent_comment":"інше право користування"}],"40":[{"sum_comment":"","brand_info_hidden":false,"brand_info":"3500 куб. см.","sum":"","brand_unclear":false,"brand_hidden":false,"brand":"Toyota Camry","sum_rent":"","sum_rent_comment":"","year":"2009","brand_info_unclear":false},{"sum_comment":"","brand_info":"5461 куб. см.","sum":"","sum_rent_comment":"","year":"2010","brand":"Mercedes-Benz GL 550","sum_rent":""}]},"source":"VULYK","income":{"5":{"family_comment":"","value":"185506","family_unclear":false,"family":"230403","comment":""},"6":{"family_comment":"","family":"225829","comment":"","value_unclear":false,"family_unclear":false,"value":"159302"},"7":{"source_name_hidden":false,"family_comment":"","comment":"","family":"4574","source_name_unclear":false,"value":"","source_name":"Національний юридичний університет ім. Я. Мудрого"},"8":{"family_comment":"","value":"","family":"","comment":""},"9":{"family_comment":"","value":"","family_unclear":false,"family":"","comment":""},"10":{"family_comment":"","value":"","family":"","comment":""},"11":{"family_comment":"","value":"","family":"","comment":""},"12":{"family_comment":"","value":"","family":"","comment":""},"13":{"family_comment":"","value":"","family":"","comment":""},"14":{"family_comment":"","value":"","family":"","comment":""},"15":{"family_comment":"","value":"","family":"","comment":""},"16":{"family_comment":"","value":"","family_unclear":false,"family":"","comment":""},"17":{"family_comment":"","value":"","family_unclear":false,"family":"","comment":""},"18":{"family_comment":"","value":"","family":"","comment":""},"19":{"family_comment":"","value":"","family":"","comment":""},"20":{"family_comment":"","comment_unclear":false,"value":"26204","family":"","comment":"пенсія та виплати учаснику ліквідації аварії на ЧАЕС"}},"banks":{"45":[{"sum_units":"UAH","sum_comment_unclear":false,"sum_foreign_units_hidden":false,"sum_hidden":false,"sum":"1589","sum_foreign":"","sum_foreign_hidden":false,"sum_foreign_comment":"","sum_foreign_units":"UAH","sum_comment_hidden":false,"sum_units_hidden":false,"sum_comment":"","sum_foreign_comment_hidden":false}],"46":[{"sum_units":"UAH","sum_comment":"","sum_foreign_units_hidden":false,"sum_foreign_units":"UAH","sum":"1589","sum_units_hidden":false,"sum_foreign_comment":"","sum_foreign":"","sum_foreign_hidden":false,"sum_comment_hidden":false}],"51":[{"sum_units":"UAH","sum_foreign_units_hidden":false,"sum_hidden":false,"sum":"45391","sum_foreign":"","sum_foreign_hidden":false,"sum_comment":"","sum_foreign_units":"UAH","sum_comment_hidden":false,"sum_foreign_comment":"","sum_unclear":false,"sum_foreign_comment_hidden":false}]},"declaration":{"notfull_lostpages":"","additional_info_text":"","additional_info":"","date":"2016-03-24T00:00:00","notfull":"","url":"http://static.declarations.com.ua/declarations/chosen_ones/judges_batch/29_iehupenko_vladyslav_vadymovych.pdf"},"general":{"inn":"","addresses":[{"place_city_type_hidden":false,"place_district_hidden":false,"place_address_unclear":false,"place":"Харківська область","place_city":"Харків","place_city_type":"Місто","place_city_hidden":false,"place_district":"","place_city_unclear":false,"place_address":"61024, зареєстровний 61002, м. Харків","place_address_hidden":true,"place_hidden":false}],"last_name":"Єгупенко","full_name":"Єгупенко Владислав Вадимович","family":[{"inn":"","inn_unclear":false,"family_name":"Тацій Лариса Василівна","relations_other":"","relations_hidden":false,"name_unclear":false,"inn_hidden":true,"name_hidden":true,"relations":"Подружжя"},{"inn":"","inn_unclear":false,"family_name":"Тацій Василь Владиславович","relations_other":"","relations_hidden":false,"name_unclear":false,"inn_hidden":false,"name_hidden":false,"relations":"Дитина"}],"patronymic":"Вадимович","inn_hidden":true,"name":"Владислав","post":{"office":"Адміністративний місцевий суд","post":"суддя харківського окружного адміністративного суду","candidate":"","office_unclear":false,"region":"Харківська область","office_hidden":false},"family_raw":"","full_name_suggest":{"input":["Єгупенко Владислав Вадимович","Владислав Вадимович Єгупенко","Владислав Єгупенко"],"output":"Єгупенко Владислав Вадимович"}},"liabilities":{"54":{"sum_comment":"","sum_hidden":false,"sum":"","sum_foreign_comment":"","sum_foreign":"","sum_unclear":false,"sum_comment_hidden":false},"55":{"sum_comment":"","sum_foreign_comment":"","sum_foreign":"","sum":""},"56":{"sum_comment":"","sum_foreign_comment":"","sum_foreign":"","sum":""},"57":{"sum_comment":"","sum_hidden":false,"sum":"","sum_foreign_comment":"","sum_foreign":"","sum_unclear":false,"sum_comment_hidden":false},"58":{"sum_comment":"","sum_hidden":false,"sum":"","sum_foreign_comment":"","sum_foreign":"","sum_unclear":false,"sum_comment_hidden":false},"59":{"sum_comment":"","sum_foreign_comment":"","sum_foreign":"","sum":""},"60":{"sum_comment":"","sum_hidden":false,"sum":"","sum_foreign_comment":"","sum_foreign":"","sum_comment_hidden":false},"61":{"sum_comment":"","sum_foreign_comment":"","sum_foreign":"","sum":""},"62":{"sum_comment":"","sum_foreign_comment":"","sum_foreign":"","sum_unclear":false,"sum":""},"63":{"sum_comment":"","sum_foreign_comment":"","sum_foreign":"","sum_unclear":false,"sum":""},"64":{"sum_comment":"","sum_foreign_comment":"","sum_foreign":"","sum":""}},"intro":{"isnotdeclaration":"","declaration_year":"2015"}}