{"income":{"5":{"value":"262968","family_comment":"","value_unclear":false,"family":"","family_unclear":false,"comment_unclear":false,"comment":"","family_comment_unclear":false},"6":{"value":"231406","family_comment":"","value_unclear":false,"family_unclear":false,"family":"","comment":""},"7":{"source_name_unclear":false,"value":"","value_unclear":false,"family_comment":"","source_name":"","family":"","comment":"","source_name_hidden":false},"8":{"family_comment":"","value":"","family":"","comment":""},"9":{"family_comment":"","value":"","family":"","comment":""},"10":{"family_comment":"","value":"","value_unclear":false,"family":"","comment":""},"11":{"value":"","value_unclear":false,"value_hidden":false,"family_comment":"","family":"","comment":""},"12":{"family_comment":"","value":"","family":"","comment":"","value_hidden":false},"13":{"family_comment":"","value":"","family":"","comment":""},"14":{"family_comment":"","value":"","family":"","comment":""},"15":{"family_comment":"","value":"27757","family":"","comment":""},"16":{"family_comment":"","value":"","family":"","comment":""},"17":{"family_comment":"","value":"","family":"","comment":""},"18":{"family_comment":"","value":"","family":"","comment":""},"19":{"family_comment":"","family_unclear":false,"value":"","family":"","comment":""},"20":{"family_comment":"","family_unclear":false,"value":"3805","family":"","comment":""}},"id":"vulyk_61_112","declaration":{"additional_info_text":"","notfull_lostpages":"","date":"2015-03-31T00:00:00","notfull":"","additional_info":"","url":"http://static.declarations.com.ua/declarations/chosen_ones/mega_batch/hrymailo_anzhelika_mykhailivna.pdf"},"liabilities":{"54":{"sum_foreign_comment":"","sum":"","sum_comment":"","sum_comment_unclear":false,"sum_unclear":false,"sum_foreign":""},"55":{"sum_foreign_comment":"","sum":"","sum_comment":"","sum_foreign":""},"56":{"sum_foreign_comment":"","sum":"","sum_comment":"","sum_unclear":false,"sum_foreign":""},"57":{"sum_foreign_comment":"","sum":"","sum_comment":"","sum_comment_hidden":false,"sum_unclear":false,"sum_foreign":""},"58":{"sum_foreign_comment":"","sum":"","sum_comment":"","sum_unclear":false,"sum_foreign":""},"59":{"sum_foreign_comment":"","sum":"","sum_comment":"","sum_foreign":""},"60":{"sum_foreign_comment":"","sum_foreign_hidden":false,"sum_comment":"","sum_hidden":false,"sum":"","sum_foreign":""},"61":{"sum_foreign_comment":"","sum":"","sum_comment":"","sum_foreign":""},"62":{"sum_foreign_comment":"","sum":"","sum_comment":"","sum_unclear":false,"sum_foreign":""},"63":{"sum_foreign_comment":"","sum":"","sum_comment":"","sum_hidden":false,"sum_unclear":false,"sum_foreign":""},"64":{"sum_foreign_comment":"","sum":"","sum_hidden":false,"sum_comment":"","sum_foreign":""}},"ft_src":"суддя ленінського районного суду м. харкова\nХарківська область\nЗагальний місцевий суд\nАнжеліка\nГримайло А. С\nДитина\nМихайлівна\nГримайло Анжеліка Михайлівна\nАнжеліка Михайлівна Гримайло\nАнжеліка Гримайло\nГримайло Анжеліка Михайлівна\nГримайло Анжеліка Михайлівна\nГримайло\n27757\n3805\n262968\n231406\n.6\n25\n115\n88\n2014\n231406\n27757\n262968\n3805\n.6\n25\n115\n88\nГримайло Анжеліка Михайлівна\nАнжеліка Михайлівна Гримайло\nАнжеліка Гримайло\nГримайло Анжеліка Михайлівна\nГримайло Анжеліка Михайлівна\nДитина\nГримайло А. С\nАнжеліка\nМихайлівна\nХарківська область\nЗагальний місцевий суд\nсуддя ленінського районного суду м. харкова\nГримайло\n231406\n3805\n27757\n262968\n2014\nГримайло А. С\nДитина\nМихайлівна\nГримайло\nАнжеліка\nГримайло Анжеліка Михайлівна\nАнжеліка Михайлівна Гримайло\nАнжеліка Гримайло\nГримайло Анжеліка Михайлівна\nХарківська область\nсуддя ленінського районного суду м. харкова\nЗагальний місцевий суд\nГримайло Анжеліка Михайлівна\n115\n88\n.6\n25\n2014","general":{"inn":"","name":"Анжеліка","patronymic_unclear":false,"family":[{"inn":"","inn_hidden":false,"relations_unclear":false,"relations_hidden":false,"relations_other":"","relations":"Дитина","name_hidden":false,"family_name":"Гримайло А. С","name_unclear":false}],"patronymic":"Михайлівна","inn_hidden":false,"family_raw":"","inn_unclear":false,"post":{"post_unclear":false,"region_unclear":false,"post":"суддя ленінського районного суду м. харкова","office":"Загальний місцевий суд","region":"Харківська область","post_hidden":false,"office_hidden":false,"region_hidden":false},"full_name_suggest":{"output":"Гримайло Анжеліка Михайлівна","input":["Гримайло Анжеліка Михайлівна","Анжеліка Михайлівна Гримайло","Анжеліка Гримайло"]},"full_name":"Гримайло Анжеліка Михайлівна","last_name":"Гримайло","patronymic_hidden":false,"last_name_unclear":false,"name_unclear":false},"source":"VULYK","estate":{"23":[{"region_unclear":false,"space_unclear":false,"costs":"","costs_comment":"","address_hidden":false,"region_hidden":false,"space_comment":"","space":".6","address":"","region":"","address_unclear":false,"costs_rent_comment":"","space_comment_unclear":false,"space_units":"га","space_units_unclear":false,"costs_rent":""}],"25":[{"region_unclear":false,"space_hidden":false,"costs":"","costs_comment":"","address_hidden":false,"region_hidden":false,"space_comment":"","space_unclear":false,"space":"115","address":"","costs_comment_unclear":false,"costs_unclear":false,"region":"","address_unclear":false,"costs_rent_comment":"","space_comment_unclear":false,"space_units":"м²","costs_rent":""},{"region_unclear":false,"costs":"","costs_comment":"","address_hidden":false,"space_comment":"","space":"88","address":"","costs_unclear":false,"region":"","costs_rent_comment":"","space_comment_unclear":false,"space_units":"м²","costs_rent":""}],"27":[{"costs":"","costs_rent_unclear":false,"costs_comment":"","address_hidden":false,"region_hidden":false,"space_comment":"","space":"25","address":"","region":"","address_unclear":false,"costs_rent_comment":"","space_units":"м²","costs_rent":""}]},"intro":{"declaration_year":"2014","isnotdeclaration":"","declaration_year_hidden":false}}