{"income":{"5":{"family_comment":"","value":"17820","family_hidden":false,"comment":"","family":"95073.29"},"6":{"value":"","value_unclear":false,"family_hidden":false,"family_comment":"","family":"93573.29","comment":""},"7":{"value":"","value_unclear":false,"family_comment":"","source_name":"","family":"","comment":""},"8":{"family_comment":"","value":"","family":"","comment":""},"9":{"family_comment":"","value":"","family":"1500","comment":""},"10":{"value":"","family_comment":"","comment_unclear":false,"family_unclear":false,"family":"","comment":"","family_comment_unclear":false},"11":{"family_comment":"","value":"","value_unclear":false,"family":"","comment":""},"12":{"family_comment":"","value":"","family":"","comment":""},"13":{"family_comment":"","value":"","family":"","comment":""},"14":{"family_comment":"","value":"","family":"","comment":""},"15":{"value":"","family_comment":"","comment_unclear":false,"family_unclear":false,"family":"","comment":""},"16":{"family_comment":"","value":"","family":"","comment":""},"17":{"family_comment":"","value":"","family":"","comment":""},"18":{"family_comment":"","family_unclear":false,"value":"","family":"","comment":""},"19":{"family_comment":"","value":"","family":"","comment":""},"20":{"family_comment":"","family_unclear":false,"value":"17820","family":"","comment":""}},"vehicle":{"40":[{"year_hidden":false,"brand_info":"2445 куб. см.","sum_rent_comment":"","year":"1994","brand_info_hidden":false,"year_unclear":false,"sum_rent":"","sum":"","brand":"УАЗ","sum_comment":"","sum_comment_unclear":false,"brand_hidden":false},{"brand_info":"1630 куб. см.","sum_rent_comment":"","brand":"ВАЗ","sum_comment":"","year":"2009","sum":"","sum_rent":""}]},"id":"vulyk_92_145","banks":{"47":[{"sum_foreign_comment":"","sum_units":"UAH","sum_comment":"","sum_comment_unclear":false,"sum_foreign_units":"UAH","sum":"9","sum_foreign":""}],"49":[{"sum_foreign_comment":"","sum_units":"UAH","sum_comment":"","sum_foreign_units":"UAH","sum":"9000","sum_unclear":true,"sum_foreign":""}],"52":[{"sum_foreign_comment":"","sum_units":"UAH","sum_comment":"","sum_hidden":false,"sum_foreign_units":"UAH","sum":"1000","sum_foreign":""}]},"declaration":{"additional_info_text":"","notfull_lostpages":"","date":"2015-03-27T00:00:00","notfull":"","additional_info":"","url":"http://static.declarations.com.ua/declarations/chosen_ones/judges_batch/3393_dobosh_nataliia_bohdanivna.pdf"},"liabilities":{"54":{"sum_foreign_comment":"","sum":"","sum_comment":"","sum_hidden":false,"sum_unclear":false,"sum_foreign":""},"55":{"sum_foreign_comment":"","sum":"","sum_comment":"","sum_unclear":false,"sum_foreign":""},"56":{"sum_foreign_comment":"","sum":"5600","sum_comment":"","sum_comment_unclear":false,"sum_hidden":false,"sum_unclear":false,"sum_foreign":""},"57":{"sum_foreign_comment":"","sum":"","sum_comment":"","sum_hidden":false,"sum_comment_hidden":false,"sum_foreign":""},"58":{"sum_foreign_comment":"","sum":"","sum_comment":"","sum_foreign":""},"59":{"sum_foreign_comment":"","sum":"","sum_comment":"","sum_comment_unclear":false,"sum_foreign":""},"60":{"sum_foreign_comment":"","sum":"","sum_comment":"","sum_foreign":""},"61":{"sum_foreign_comment":"","sum":"","sum_comment":"","sum_foreign":""},"62":{"sum_foreign_comment":"","sum":"10000","sum_comment":"","sum_comment_unclear":false,"sum_hidden":false,"sum_unclear":false,"sum_foreign":""},"63":{"sum_foreign_comment":"","sum":"","sum_comment":"","sum_foreign":""},"64":{"sum_foreign_comment":"","sum":"","sum_comment":"","sum_foreign":""}},"ft_src":"10000\n5600\nсуддя пустомитівського районного суду львівської області\nЛьвівська область\nЗагальний місцевий суд\nНаталія\nЛещук Д. Р\nПодружжя\nЛещук Р. Д\nДитина\nЛещук Б. Д\nДитина\nЛещук А. Д\nДитина\nБогданівна\nДобош Наталія Богданівна\nНаталія Богданівна Добош\nНаталія Добош\nДобош Наталія Богданівна\nДобош Наталія Богданівна\nДобош\n2445 куб. см.\nУАЗ\n1994\n1630 куб. см.\n2009\nВАЗ\n600\n869\n55\n264\n21\n1/4\n18.77\n9\n9000\n1000\n2014\n2445 куб. см.\nУАЗ\n1994\n1630 куб. см.\nВАЗ\n2009\n21\n18.77\n1/4\n869\n600\n55\n264\nПодружжя\nЛещук Д. Р\nДитина\nЛещук Р. Д\nДитина\nЛещук Б. Д\nДитина\nЛещук А. Д\nДобош Наталія Богданівна\nНаталія Богданівна Добош\nНаталія Добош\nДобош Наталія Богданівна\nДобош Наталія Богданівна\nНаталія\nДобош\nЗагальний місцевий суд\nсуддя пустомитівського районного суду львівської області\nЛьвівська область\nБогданівна\n5600\n10000\n93573.29\n17820\n17820\n95073.29\n1500\n9\n9000\n1000\n2014\n5600\n10000\n93573.29\n1500\n95073.29\n17820\n17820\nПодружжя\nЛещук Д. Р\nДитина\nЛещук Р. Д\nДитина\nЛещук Б. Д\nДитина\nЛещук А. Д\nБогданівна\nДобош\nНаталія\nДобош Наталія Богданівна\nНаталія Богданівна Добош\nНаталія Добош\nДобош Наталія Богданівна\nЛьвівська область\nЗагальний місцевий суд\nсуддя пустомитівського районного суду львівської області\nДобош Наталія Богданівна\nУАЗ\n2445 куб. см.\n1994\nВАЗ\n1630 куб. см.\n2009\n1500\n17820\n95073.29\n17820\n93573.29\n55\n869\n21\n264\n1/4\n18.77\n600\n9\n9000\n1000\n2014","general":{"inn":"","name":"Наталія","patronymic_unclear":false,"family":[{"inn":"","relations":"Подружжя","inn_unclear":false,"relations_hidden":false,"inn_hidden":true,"relations_other":"","name_hidden":false,"family_name":"Лещук Д. Р","name_unclear":false},{"inn":"","relations":"Дитина","inn_unclear":false,"relations_hidden":false,"inn_hidden":false,"relations_other":"","name_hidden":false,"family_name":"Лещук Р. Д","name_unclear":false},{"inn":"","relations":"Дитина","relations_other":"","inn_hidden":false,"family_name":"Лещук Б. Д","name_unclear":false},{"inn":"","relations":"Дитина","relations_other":"","inn_hidden":false,"family_name":"Лещук А. Д","name_unclear":false}],"patronymic":"Богданівна","inn_hidden":true,"family_raw":"","inn_unclear":false,"post":{"post_unclear":false,"post":"суддя пустомитівського районного суду львівської області","office_hidden":false,"region":"Львівська область","office":"Загальний місцевий суд","office_unclear":false,"region_hidden":false},"full_name":"Добош Наталія Богданівна","addresses":[{"place_district":"","place_address_hidden":true,"place_city":"","place_city_type_hidden":false,"place_district_hidden":false,"place_city_type":"","place_city_hidden":true,"place_address_unclear":false,"place_address":"","place_hidden":true,"place":""}],"last_name":"Добош","full_name_suggest":{"output":"Добош Наталія Богданівна","input":["Добош Наталія Богданівна","Наталія Богданівна Добош","Наталія Добош"]}},"source":"VULYK","estate":{"23":[{"region_unclear":false,"space_unclear":false,"costs":"","costs_comment":"","address_hidden":false,"region_hidden":true,"space_comment":"","space":"869","address":"","region":"","costs_rent_comment":"","space_units":"м²","costs_rent":""}],"25":[{"space_hidden":false,"costs":"","costs_comment":"","address_hidden":false,"region_hidden":true,"space_comment":"1/4","space":"18.77","address":"","region":"","address_unclear":false,"costs_rent_comment":"","space_comment_unclear":false,"space_units":"м²","costs_rent":""}],"26":[{"costs_rent":"","region":"","costs":"","costs_rent_comment":"","costs_comment":"","address_hidden":false,"region_hidden":true,"space_comment":"","space_units":"м²","space":"21","address":""}],"29":[{"space_unclear":false,"space_units_unclear":false,"address_hidden":false,"region_hidden":true,"space_comment":"","space_units_hidden":false,"space":"600","address":"","region":"","costs_property":"","costs_rent_comment":"","space_units":"м²","costs_property_comment":"","costs_rent":""}],"30":[{"space_unclear":false,"address_hidden":false,"region_hidden":true,"space_comment":"","space_hidden":false,"space":"264","address":"","region":"","costs_property":"","costs_rent_comment":"","address_unclear":false,"space_units":"м²","costs_property_comment":"","costs_rent":""}],"31":[{"space_unclear":false,"address_hidden":false,"region_hidden":true,"space_comment":"","space_hidden":false,"space":"55","address":"","region":"","costs_property":"","costs_rent_comment":"","address_unclear":false,"space_units":"м²","costs_property_comment":"","costs_rent":""}]},"intro":{"declaration_year":"2014","isnotdeclaration":""}}