{"income":{"5":{"value":"364446.74","family_comment":"","value_unclear":false,"family_hidden":false,"value_hidden":false,"family_unclear":false,"family":"300273.69","comment":""},"6":{"value":"278660.1","family_comment":"","value_unclear":false,"family_unclear":false,"family":"","comment":""},"7":{"source_name_unclear":false,"value":"3566.84","comment_hidden":false,"family_comment":"","source_name":"Львівський національний університет ім. Франка","family":"","comment":"","source_name_hidden":false},"8":{"family_comment":"","value":"","family":"","comment":""},"9":{"value":"9037.2","family_comment":"","value_unclear":false,"family_hidden":false,"family_unclear":false,"family":"","comment":"","family_comment_unclear":false},"10":{"family_comment":"","value":"","family":"","comment":""},"11":{"family_comment":"","value":"","family":"","comment":""},"12":{"family_comment":"","value":"","family":"","comment":""},"13":{"family_comment":"","value":"","family":"","comment":""},"14":{"family_comment":"","value":"","family":"68932","comment":""},"15":{"family_comment":"","value":"","family":"","comment":""},"16":{"family_comment":"","value":"","family":"","comment":""},"17":{"family_comment":"","value":"","family":"170932","comment":""},"18":{"family_comment":"","value":"","family":"","comment":""},"19":{"family_comment":"","value":"","family":"","comment":""},"20":{"value":"73182.6","family_comment":"пенсія","value_unclear":false,"family_comment_hidden":false,"family_unclear":false,"family_comment_unclear":false,"comment_unclear":false,"comment":"пенсія","family":"60409.69"}},"vehicle":{"35":[{"year_hidden":true,"brand_info":"","sum_rent_comment":"","year":"","brand_info_hidden":false,"brand_info_unclear":false,"sum_rent":"","sum":"","brand":"","sum_comment":"","brand_unclear":false,"brand_hidden":true}],"40":[{"brand_info":"3.2 л","sum_rent_comment":"","brand":"Mitsubishi","sum_comment":"","year":"2007","brand_info_unclear":false,"sum":"","sum_rent":""}]},"id":"vulyk_93_31","declaration":{"additional_info_text":"","notfull_lostpages":"","date":"2015-03-30T00:00:00","notfull":"","additional_info":"","url":"http://static.declarations.com.ua/declarations/chosen_ones/judges_batch/3477_tertychnyi_vitalii_hryhorovych.pdf"},"liabilities":{"54":{"sum_foreign_comment":"","sum":"","sum_hidden":false,"sum_comment":"","sum_foreign":""},"55":{"sum_foreign_comment":"","sum":"","sum_comment":"","sum_foreign":""},"56":{"sum_foreign_comment":"","sum":"","sum_comment":"","sum_foreign":""},"57":{"sum_foreign_comment":"","sum":"","sum_comment":"","sum_hidden":false,"sum_comment_hidden":false,"sum_unclear":false,"sum_foreign":""},"58":{"sum_foreign_comment":"","sum":"","sum_comment":"","sum_comment_unclear":false,"sum_hidden":false,"sum_unclear":false,"sum_foreign":""},"59":{"sum_foreign_comment":"","sum":"","sum_comment":"","sum_foreign":""},"60":{"sum_foreign_comment":"","sum":"","sum_hidden":false,"sum_comment":"","sum_foreign":""},"61":{"sum_foreign_comment":"","sum":"","sum_comment":"","sum_foreign":""},"62":{"sum_foreign_comment":"","sum":"","sum_comment":"","sum_foreign":""},"63":{"sum_foreign_comment":"","sum":"","sum_comment":"","sum_foreign":""},"64":{"sum_foreign_comment":"","sum":"","sum_comment":"","sum_foreign":""}},"ft_src":"Тертичний Віталій Григорович\nголова львівського окружного адміністративного суду\nЛьвівська область\nАдміністративний місцевий суд\nВіталій\nТертична Н. І\nПодружжя\nТертичний Віталій Григорович\nВіталій Григорович Тертичний\nВіталій Тертичний\nТертичний Віталій Григорович\nТертичний\nГригорович\n3.2 л\n2007\nMitsubishi\n16.7\n800\n1260\nдля садівництва\n880\n103\n82\n2014\n278660.1\n68932\n9037.2\nЛьвівський національний університет ім. Франка\n3566.84\n300273.69\n364446.74\n170932\n60409.69\nпенсія\n73182.6\nпенсія\n3.2 л\nMitsubishi\n2007\n800\n1260\n880\nдля садівництва\n103\n82\n16.7\nТертичний\nПодружжя\nТертична Н. І\nТертичний Віталій Григорович\nВіталій Григорович Тертичний\nВіталій Тертичний\nТертичний Віталій Григорович\nТертичний Віталій Григорович\nВіталій\nГригорович\nЛьвівська область\nАдміністративний місцевий суд\nголова львівського окружного адміністративного суду\n3566.84\nЛьвівський національний університет ім. Франка\n278660.1\n170932\n60409.69\n73182.6\nпенсія\nпенсія\n68932\n364446.74\n300273.69\n9037.2\n2014\nПодружжя\nТертична Н. І\nТертичний\nГригорович\nЛьвівська область\nАдміністративний місцевий суд\nголова львівського окружного адміністративного суду\nТертичний Віталій Григорович\nТертичний Віталій Григорович\nВіталій Григорович Тертичний\nВіталій Тертичний\nТертичний Віталій Григорович\nВіталій\n2007\n3.2 л\nMitsubishi\n9037.2\n68932\nпенсія\n73182.6\nпенсія\n60409.69\n364446.74\n300273.69\n3566.84\nЛьвівський національний університет ім. Франка\n170932\n278660.1\n103\n800\n16.7\n82\n1260\nдля садівництва\n880\n2014","general":{"inn":"","inn_hidden":true,"last_name":"Тертичний","post":{"post_unclear":false,"region_unclear":false,"region":"Львівська область","candidate":"","post":"голова львівського окружного адміністративного суду","office":"Адміністративний місцевий суд","office_unclear":false},"name":"Віталій","full_name":"Тертичний Віталій Григорович","family_raw":"","addresses":[{"place_district":"","place_city_hidden":true,"place_city":"","place_city_type_hidden":true,"place_district_hidden":true,"place_city_type":"","place_address_hidden":true,"place_address":"","place_hidden":true,"place":""}],"family":[{"inn":"","relations":"Подружжя","relations_hidden":false,"inn_hidden":true,"relations_other":"","name_hidden":true,"family_name":"Тертична Н. І","name_unclear":false}],"full_name_suggest":{"output":"Тертичний Віталій Григорович","input":["Тертичний Віталій Григорович","Віталій Григорович Тертичний","Віталій Тертичний"]},"patronymic":"Григорович"},"source":"VULYK","estate":{"23":[{"space_unclear":false,"costs":"","costs_comment":"","address_hidden":true,"region_hidden":true,"space_comment":"","space":"800","address":"","region":"","costs_rent_comment":"","space_comment_unclear":false,"space_units":"м²","costs_rent":""}],"25":[{"space_hidden":false,"costs":"","costs_comment":"","address_hidden":true,"region_hidden":true,"space_comment":"","space_unclear":false,"space":"82","address":"","costs_rent_comment_unclear":false,"region":"","costs_rent_comment":"","space_units":"м²","costs_rent":""}],"29":[{"space_unclear":false,"address_hidden":true,"region_hidden":true,"space_comment":"","space":"1260","address":"","region":"","costs_property":"","costs_rent_comment":"","space_comment_unclear":false,"space_units":"м²","costs_property_comment":"","costs_rent":""},{"costs_rent":"","region":"","costs_property":"","costs_rent_comment":"","region_hidden":false,"space_comment":"для садівництва","costs_property_comment":"","space_units":"м²","space":"880","address":""}],"31":[{"space_hidden":false,"address_hidden":true,"region_hidden":true,"space_comment":"","space":"103","address":"","region":"","costs_property":"","costs_rent_comment":"","space_comment_unclear":false,"space_units":"м²","costs_property_comment":"","costs_rent":""}],"33":[{"space_hidden":false,"address_hidden":true,"region_hidden":true,"space_comment":"","space":"16.7","address":"","region":"","costs_property":"","costs_rent_comment":"","space_units":"м²","costs_property_comment":"","costs_rent":""}]},"intro":{"declaration_year":"2014","isnotdeclaration":""}}