{"income":{"5":{"value":"521159","family_comment":"","value_unclear":true,"family_unclear":false,"family":"","comment":""},"6":{"family_comment":"","family_unclear":false,"value":"268841","family":"","comment":""},"7":{"source_name_unclear":false,"value":"","family_comment":"","source_name":"","family":"","comment":""},"8":{"family_comment":"","value":"","family":"","comment":""},"9":{"value":"","family_comment":"","comment_hidden":false,"family_unclear":false,"family":"","comment":"","family_comment_hidden":false},"10":{"family_comment":"","value":"","family":"","comment":""},"11":{"family_comment":"","value":"","family":"","comment":""},"12":{"family_comment":"","value":"","family":"","comment":""},"13":{"family_comment":"","value":"","family":"","comment":""},"14":{"family_comment":"","value":"","family":"","comment":""},"15":{"family_comment":"","value":"","family":"","comment":""},"16":{"family_comment":"","value":"240000","family":"","comment":""},"17":{"family_comment":"","value":"","family":"","comment":""},"18":{"family_comment":"","value":"","family":"","comment":""},"19":{"family_comment":"","value":"","family":"","comment":""},"20":{"value":"12318","value_unclear":false,"comment_hidden":false,"family_comment":"","comment_unclear":false,"comment":"пенсія","family":""}},"id":"vulyk_108_137","declaration":{"additional_info_text":"","notfull_lostpages":"","date":"2016-03-25T00:00:00","notfull":"","additional_info":"","url":"http://static.declarations.com.ua/declarations/chosen_ones/judges_batch/2436_sokolan_nataliia_oleksandrivna_2015.pdf"},"liabilities":{"54":{"sum_foreign_comment":"","sum":"","sum_hidden":false,"sum_comment":"","sum_foreign":""},"55":{"sum_foreign_comment":"","sum":"","sum_comment":"","sum_foreign":""},"56":{"sum_foreign_comment":"","sum":"","sum_comment":"","sum_unclear":false,"sum_foreign":""},"57":{"sum_foreign_comment":"","sum":"","sum_comment":"","sum_hidden":false,"sum_comment_hidden":false,"sum_foreign":""},"58":{"sum_foreign_comment":"","sum_comment_hidden":false,"sum":"","sum_comment":"","sum_foreign":""},"59":{"sum_foreign_comment":"","sum":"","sum_comment":"","sum_unclear":false,"sum_foreign":""},"60":{"sum_foreign_comment":"","sum_comment_hidden":false,"sum":"","sum_comment":"","sum_foreign":""},"61":{"sum_foreign_comment":"","sum_comment_hidden":false,"sum":"","sum_comment":"","sum_foreign":""},"62":{"sum_foreign_comment":"","sum":"","sum_comment":"","sum_foreign":""},"63":{"sum_foreign_comment":"","sum":"","sum_comment":"","sum_hidden":false,"sum_comment_hidden":false,"sum_unclear":false,"sum_foreign":""},"64":{"sum_foreign_comment":"","sum":"","sum_comment":"","sum_comment_hidden":false,"sum_unclear":false,"sum_foreign":""}},"ft_src":"Соколан Наталія Олександрівна\nсуддя апеляційного суду дніпропетровської області\nДніпропетровська область\nЗагальний апеляційний суд\nНаталія\nСоколан Наталія Олександрівна\nНаталія Олександрівна Соколан\nНаталія Соколан\nСоколан Наталія Олександрівна\nСоколан\nОлександрівна\n12318\nпенсія\n521159\n240000\n268841\n.0685\n68.6\n35.3\n61.3\n2015\n268841\n521159\n240000\nпенсія\n12318\n.0685\n68.6\n35.3\n61.3\nЗагальний апеляційний суд\nДніпропетровська область\nсуддя апеляційного суду дніпропетровської області\nСоколан\nСоколан Наталія Олександрівна\nНаталія Олександрівна Соколан\nНаталія Соколан\nСоколан Наталія Олександрівна\nНаталія\nСоколан Наталія Олександрівна\nОлександрівна\n268841\n12318\nпенсія\n521159\n240000\n2015\nСоколан\nОлександрівна\nДніпропетровська область\nсуддя апеляційного суду дніпропетровської області\nЗагальний апеляційний суд\nСоколан Наталія Олександрівна\nСоколан Наталія Олександрівна\nНаталія Олександрівна Соколан\nНаталія Соколан\nСоколан Наталія Олександрівна\nНаталія\n35.3\n61.3\n.0685\n68.6\n2015","general":{"inn":"","family_raw":"","inn_unclear":false,"post":{"post_unclear":false,"post":"суддя апеляційного суду дніпропетровської області","office_hidden":false,"region":"Дніпропетровська область","office":"Загальний апеляційний суд","office_unclear":false},"name":"Наталія","full_name":"Соколан Наталія Олександрівна","inn_hidden":true,"addresses":[{"place_city_type_hidden":true,"place_district_hidden":true,"place_city_type":"","place_city_hidden":true,"place_address_unclear":false,"place_address":"","place_hidden":true,"place":"","place_district":"","place_unclear":false,"place_city":"","place_address_hidden":true}],"last_name":"Соколан","full_name_suggest":{"output":"Соколан Наталія Олександрівна","input":["Соколан Наталія Олександрівна","Наталія Олександрівна Соколан","Наталія Соколан"]},"patronymic":"Олександрівна"},"source":"VULYK","estate":{"23":[{"region_unclear":false,"space_unclear":false,"costs":"","costs_comment":"","address_hidden":true,"region_hidden":true,"space_comment":"","space":".0685","address":"","region":"","address_unclear":false,"space_units_unclear":false,"space_units":"га","space_units_hidden":false,"costs_rent":"","costs_rent_comment":""}],"25":[{"space_unclear":false,"costs":"","costs_comment":"","address_hidden":true,"region_hidden":true,"space_comment":"","space":"35.3","address":"","region":"","costs_rent_comment":"","space_comment_unclear":false,"space_units":"м²","space_units_unclear":false,"costs_rent":""},{"costs_rent":"","region":"","costs":"","costs_rent_comment":"","costs_comment":"","address_hidden":false,"region_hidden":false,"space_comment":"","space_units":"м²","space":"61.3","address":""}],"26":[{"space_hidden":false,"costs":"","costs_comment":"","address_hidden":true,"region_hidden":true,"space_comment":"","space":"68.6","address":"","region":"","costs_rent_comment":"","space_units":"м²","costs_rent":""}]},"intro":{"declaration_year":"2015","isnotdeclaration":"","declaration_year_hidden":false}}