{"income":{"5":{"value":"187195","family_comment":"","value_unclear":false,"family_unclear":false,"family":"28055","comment":""},"6":{"family_comment":"","value":"170561","family":"9852","comment":""},"7":{"source_name_unclear":false,"value":"","family_hidden":false,"value_hidden":false,"family_comment":"","source_name":"","family":"","comment":"","source_name_hidden":false},"8":{"value":"","family_hidden":false,"value_hidden":false,"family_comment":"","family":"","comment":""},"9":{"value":"112","comment_hidden":false,"family_hidden":false,"value_hidden":false,"family_comment":"","family":"","comment":""},"10":{"family_comment":"","value":"12180","family":"","comment":""},"11":{"value":"","family_hidden":false,"value_hidden":false,"family_comment":"","family":"","comment":""},"12":{"family_comment":"","value":"","family":"","comment":"","value_hidden":false},"13":{"family_comment":"","value":"","family":"","comment":"","value_hidden":false},"14":{"family_comment":"","value":"","family":"","comment":"","value_hidden":false},"15":{"family_comment":"","value":"","family":"","comment":"","value_hidden":false},"16":{"family_comment":"","value":"","family":"","comment":"","value_hidden":false},"17":{"family_comment":"","value":"","family":"","comment":"","value_hidden":false},"18":{"family_comment":"","value":"","family":"","comment":"","value_hidden":false},"19":{"family_comment":"","value":"","family":"","comment":"","value_hidden":false},"20":{"value":"4342","family_comment":"","value_unclear":false,"family":"18203","family_unclear":false,"comment_unclear":false,"comment":"","family_comment_unclear":false}},"vehicle":{"35":[{"brand_info":"1560 куб. см.","sum_rent_comment":"","brand":"Peugeot Partner","sum_comment":"","sum_comment_unclear":false,"year":"2007","brand_hidden":false,"brand_info_unclear":false,"sum":"","sum_rent":"","sum_rent_unclear":false}]},"id":"vulyk_33_176","banks":{"45":[{"sum_foreign_comment":"","sum_units":"UAH","sum_comment":"","sum_hidden":false,"sum_foreign_units":"UAH","sum_comment_hidden":false,"sum":"2392","sum_foreign":""},{"sum_foreign_comment":"","sum_units":"","sum_comment":"","sum_foreign_units":"","sum":"","sum_foreign":""},{"sum_foreign_comment":"","sum_units":"","sum_comment":"","sum_foreign_units":"","sum":"","sum_foreign":""}],"46":[{"sum_foreign_comment":"","sum_units":"UAH","sum_comment":"","sum_foreign_units":"UAH","sum_comment_hidden":false,"sum":"1442","sum_foreign":""}],"47":[{"sum_foreign_comment":"","sum_units":"UAH","sum_comment":"","sum_comment_unclear":false,"sum_foreign_units":"UAH","sum":"","sum_foreign":""}],"48":[{"sum_foreign_comment":"","sum_units":"UAH","sum_comment":"","sum_foreign_units":"UAH","sum":"","sum_foreign":""}],"49":[{"sum_foreign_comment":"","sum_units":"UAH","sum_comment":"","sum_foreign_units":"UAH","sum":"","sum_foreign":""}],"50":[{"sum_foreign_comment":"","sum_units":"UAH","sum_comment":"","sum_foreign_units":"UAH","sum":"","sum_foreign":""}],"51":[{"sum_foreign_comment":"","sum_units":"UAH","sum_comment":"","sum_hidden":false,"sum_foreign_units":"UAH","sum_comment_hidden":false,"sum":"","sum_foreign":""},{"sum_foreign_comment":"","sum_units":"","sum_comment":"","sum_foreign_units":"","sum":"","sum_foreign":""},{"sum_foreign_comment":"","sum":"","sum_comment":"","sum_foreign":""}],"52":[{"sum_foreign_comment":"","sum_units":"UAH","sum_comment":"","sum_foreign_units":"UAH","sum_comment_hidden":false,"sum":"","sum_foreign":""}],"53":[{"sum_foreign_comment":"","sum_units":"UAH","sum_comment":"","sum_comment_unclear":false,"sum_foreign_units":"UAH","sum":"","sum_foreign":""}]},"declaration":{"additional_info_text":"","notfull_lostpages":"","date":"2015-03-16T00:00:00","notfull":"","additional_info":"","url":"http://static.declarations.com.ua/declarations/chosen_ones/mega_batch/tsurkan_vitalii_vasylovych.pdf"},"liabilities":{"54":{"sum_foreign_comment":"","sum":"120","sum_hidden":false,"sum_comment":"","sum_foreign":""},"55":{"sum_foreign_comment":"","sum":"","sum_comment":"","sum_foreign":""},"56":{"sum_foreign_comment":"","sum":"4800","sum_comment":"","sum_foreign":""},"57":{"sum_foreign_comment":"","sum_foreign_hidden":false,"sum_comment":"","sum_hidden":false,"sum_comment_hidden":false,"sum":"4343","sum_foreign":""},"58":{"sum_foreign_comment":"","sum_foreign_hidden":false,"sum_comment":"","sum_hidden":false,"sum_comment_hidden":false,"sum":"","sum_foreign":""},"59":{"sum_foreign_comment":"","sum":"","sum_comment":"","sum_unclear":false,"sum_foreign":""},"60":{"sum_foreign_comment":"","sum":"","sum_comment":"","sum_foreign":""},"61":{"sum_foreign_comment":"","sum":"","sum_comment":"","sum_foreign":""},"62":{"sum_foreign_comment":"","sum":"","sum_comment":"","sum_unclear":false,"sum_foreign":""},"63":{"sum_foreign_comment":"","sum":"","sum_comment":"","sum_foreign":""},"64":{"sum_foreign_comment":"","sum":"","sum_comment":"","sum_foreign":""}},"ft_src":"4343\n120\n4800\nсуддя глибоцького районного суду чернівецької області\nЧернівецька область\nЗагальний місцевий суд\nВіталій\nЦуркан А. Л., 24. 05. 1986\nПодружжя\nЦуркан О. В., 17. 03. 2014\nДитина\nВасильович\nЦуркан\nЦуркан Віталій Васильович\nЦуркан Віталій Васильович\nВіталій Васильович Цуркан\nВіталій Цуркан\nЦуркан Віталій Васильович\nPeugeot Partner\n1560 куб. см.\n2007\n1442\n2392\n2014\n1560 куб. см.\n2007\nPeugeot Partner\n2392\n1442\n42.2\nУ власності, 1/2 частко\n42.2\nу власності 1/2 частка\nЦуркан Віталій Васильович\nВіталій Васильович Цуркан\nВіталій Цуркан\nЦуркан Віталій Васильович\nЦуркан Віталій Васильович\nПодружжя\nЦуркан А. Л., 24. 05. 1986\nДитина\nЦуркан О. В., 17. 03. 2014\nВіталій\nВасильович\nЗагальний місцевий суд\nсуддя глибоцького районного суду чернівецької області\nЧернівецька область\nЦуркан\n4343\n4800\n120\n170561\n9852\n4342\n18203\n187195\n28055\n12180\n112\n2014\n4343\n4800\n120\nУ власності, 1/2 частко\n42.2\nу власності 1/2 частка\n42.2\nЦуркан А. Л., 24. 05. 1986\nПодружжя\nЦуркан О. В., 17. 03. 2014\nДитина\nВіталій\nВасильович\nЦуркан\nЦуркан Віталій Васильович\nВіталій Васильович Цуркан\nВіталій Цуркан\nЦуркан Віталій Васильович\nЧернівецька область\nсуддя глибоцького районного суду чернівецької області\nЗагальний місцевий суд\nЦуркан Віталій Васильович\n9852\n170561\n12180\n28055\n187195\n112\n18203\n4342\n2007\n1560 куб. см.\nPeugeot Partner\n12180\n4342\n18203\n187195\n28055\n112\n9852\n170561\nУ власності, 1/2 частко\n42.2\nу власності 1/2 частка\n42.2\n1442\n2392\n2014","general":{"inn":"","name":"Віталій","family":[{"inn":"","inn_hidden":true,"relations_hidden":false,"family_name":"Цуркан А. Л., 24. 05. 1986","relations_other":"","relations":"Подружжя","name_hidden":false,"name_unclear":false},{"inn":"","relations":"Дитина","relations_other":"","inn_hidden":false,"family_name":"Цуркан О. В., 17. 03. 2014","name_hidden":false,"name_unclear":false}],"patronymic":"Васильович","inn_hidden":true,"family_raw":"","last_name":"Цуркан","post":{"post_unclear":false,"post":"суддя глибоцького районного суду чернівецької області","candidate":"","office_hidden":false,"region":"Чернівецька область","post_hidden":false,"office":"Загальний місцевий суд","region_hidden":false},"last_name_unclear":false,"full_name":"Цуркан Віталій Васильович","addresses":[{"place_district":"","place_city_hidden":true,"place_city":"","place_city_type_hidden":true,"place_district_hidden":true,"place_city_type":"","place_address_hidden":true,"place_address":"","place_hidden":true,"place":""}],"full_name_suggest":{"output":"Цуркан Віталій Васильович","input":["Цуркан Віталій Васильович","Віталій Васильович Цуркан","Віталій Цуркан"]}},"source":"VULYK","estate":{"23":[{"space_unclear":false,"costs":"","costs_comment":"","address_hidden":false,"region_hidden":false,"space_comment":"","space_hidden":false,"space":"","address":"","region":"","space_units_unclear":false,"space_units":"м²","costs_rent":"","costs_rent_comment":""},{"costs":"","costs_rent_unclear":false,"costs_comment":"","address_hidden":false,"region_hidden":false,"space_comment":"","space":"","address":"","region":"","address_unclear":false,"space_units_unclear":false,"space_units":"","costs_rent":"","costs_rent_comment":""},{"region_unclear":false,"costs":"","costs_comment":"","address_hidden":false,"region_hidden":false,"space_comment":"","space":"","address":"","region":"","address_unclear":false,"costs_rent_comment":"","space_units":"","costs_rent":""},{"costs_rent":"","region":"","costs":"","costs_rent_comment":"","costs_comment":"","address_hidden":false,"region_hidden":false,"space_comment":"","space_units":"","space":"","address":""},{"costs_rent":"","region":"","costs":"","costs_rent_comment":"","costs_comment":"","space_comment":"","space_units":"","space":"","address":""}],"25":[{"space_unclear":false,"costs":"","costs_comment":"","costs_hidden":false,"address_hidden":true,"region_hidden":true,"space_comment":"у власності 1/2 частка","space_hidden":false,"space":"42.2","address":"","region":"","costs_rent_comment":"","space_units":"м²","costs_rent":""}],"31":[{"space_unclear":false,"address_hidden":true,"region_hidden":true,"space_comment":"У власності, 1/2 частко","space":"42.2","address":"","region":"","costs_property":"","costs_rent_comment":"","space_comment_unclear":false,"space_units":"м²","costs_property_comment":"","costs_rent":""}]},"intro":{"declaration_year":"2014"}}