{"income":{"5":{"value":"200638","family_comment":"","value_unclear":false,"family_hidden":false,"value_hidden":false,"family_unclear":false,"family":"371810","comment":""},"6":{"value":"200638","family_comment":"","value_unclear":false,"family_unclear":false,"family":"","comment":""},"7":{"source_name_unclear":false,"value":"","comment_hidden":false,"family_comment":"","source_name":"","family":"","comment":"","source_name_hidden":false},"8":{"family_comment":"","value":"","family":"","comment":""},"9":{"value":"","family_comment":"","value_unclear":false,"family_hidden":false,"family_unclear":false,"family":"61061","comment":"","family_comment_unclear":false},"10":{"family_comment":"","value":"","family":"","comment":""},"11":{"family_comment":"","value":"","family":"","comment":""},"12":{"family_comment":"","value":"","family":"","comment":""},"13":{"family_comment":"","value":"","family":"","comment":""},"14":{"family_comment":"","value":"","family":"","comment":""},"15":{"family_comment":"","value":"","family":"","comment":""},"16":{"family_comment":"","value":"","family":"","comment":""},"17":{"family_comment":"","value":"","family":"310749","comment":""},"18":{"family_comment":"","value":"","family":"","comment":""},"19":{"family_comment":"","value":"","family":"","comment":""},"20":{"value":"","family_comment":"","value_unclear":false,"family_comment_hidden":false,"family_unclear":false,"family_comment_unclear":false,"comment_unclear":false,"comment":"","family":""}},"vehicle":{"35":[{"year_hidden":false,"brand_info":"3456 куб. см., 276 кВт","sum_rent_comment":"","year":"2008","brand_info_hidden":false,"brand_info_unclear":false,"sum_rent":"","sum":"","brand":"Lexus RX 350","sum_comment":"","brand_unclear":false,"brand_hidden":false}],"40":[{"brand_info":"1984 куб. см., 155 кВт","sum_rent_comment":"","brand":"Volkswagen Passat B7","sum_comment":"","year":"2012","brand_info_unclear":false,"sum":"","sum_rent":""}]},"id":"vulyk_93_4","declaration":{"additional_info_text":"","notfull_lostpages":"","date":"2015-03-30T00:00:00","notfull":"","additional_info":"","url":"http://static.declarations.com.ua/declarations/chosen_ones/judges_batch/3450_d_iachenko_tetiana_hennadiivna.pdf"},"liabilities":{"54":{"sum_foreign_comment":"","sum":"","sum_hidden":false,"sum_comment":"","sum_foreign":""},"55":{"sum_foreign_comment":"","sum":"","sum_comment":"","sum_foreign":""},"56":{"sum_foreign_comment":"","sum":"","sum_comment":"","sum_foreign":""},"57":{"sum_foreign_comment":"","sum":"","sum_comment":"","sum_hidden":false,"sum_comment_hidden":false,"sum_unclear":false,"sum_foreign":""},"58":{"sum_foreign_comment":"","sum":"","sum_comment":"","sum_comment_unclear":false,"sum_hidden":false,"sum_unclear":false,"sum_foreign":""},"59":{"sum_foreign_comment":"","sum":"","sum_comment":"","sum_foreign":""},"60":{"sum_foreign_comment":"","sum":"2799","sum_hidden":false,"sum_comment":"","sum_foreign":""},"61":{"sum_foreign_comment":"","sum":"","sum_comment":"","sum_foreign":""},"62":{"sum_foreign_comment":"","sum":"","sum_comment":"","sum_foreign":""},"63":{"sum_foreign_comment":"","sum":"","sum_comment":"","sum_foreign":""},"64":{"sum_foreign_comment":"","sum":"","sum_comment":"","sum_foreign":""}},"ft_src":"2799\nД'яченко Тетяна Геннадіївна\nсуддя господарського суду одеської області\nОдеська область\nГосподарський місцевий суд\nТетяна\nДідур С. Д\nПодружжя\nДідур М. С\nДитина\nД'яченко Тетяна Геннадіївна\nТетяна Геннадіївна Д'яченко\nТетяна Д'яченко\nД'яченко Тетяна Геннадіївна\nД'яченко\nГеннадіївна\n3456 куб. см., 276 кВт\nLexus RX 350\n2008\n1984 куб. см., 155 кВт\n2012\nVolkswagen Passat B7\n121.1\n2014\n200638\n61061\n371810\n200638\n310749\n3456 куб. см., 276 кВт\nLexus RX 350\n2008\n1984 куб. см., 155 кВт\nVolkswagen Passat B7\n2012\n121.1\nД'яченко\nПодружжя\nДідур С. Д\nДитина\nДідур М. С\nД'яченко Тетяна Геннадіївна\nТетяна Геннадіївна Д'яченко\nТетяна Д'яченко\nД'яченко Тетяна Геннадіївна\nД'яченко Тетяна Геннадіївна\nТетяна\nГеннадіївна\nОдеська область\nГосподарський місцевий суд\nсуддя господарського суду одеської області\n2799\n200638\n310749\n200638\n371810\n61061\n2014\n2799\nПодружжя\nДідур С. Д\nДитина\nДідур М. С\nД'яченко\nГеннадіївна\nОдеська область\nГосподарський місцевий суд\nсуддя господарського суду одеської області\nД'яченко Тетяна Геннадіївна\nД'яченко Тетяна Геннадіївна\nТетяна Геннадіївна Д'яченко\nТетяна Д'яченко\nД'яченко Тетяна Геннадіївна\nТетяна\nLexus RX 350\n3456 куб. см., 276 кВт\n2008\n2012\n1984 куб. см., 155 кВт\nVolkswagen Passat B7\n61061\n200638\n371810\n310749\n200638\n121.1\n2014","general":{"inn":"","inn_hidden":true,"last_name":"Д'яченко","post":{"post_unclear":false,"region_unclear":false,"region":"Одеська область","candidate":"","post":"суддя господарського суду одеської області","office":"Господарський місцевий суд","office_unclear":false},"name":"Тетяна","full_name":"Д'яченко Тетяна Геннадіївна","family_raw":"","addresses":[{"place_district":"","place_city_hidden":true,"place_city":"","place_city_type_hidden":true,"place_district_hidden":true,"place_city_type":"","place_address_hidden":true,"place_address":"","place_hidden":true,"place":""}],"family":[{"inn":"","relations":"Подружжя","relations_hidden":false,"inn_hidden":true,"relations_other":"","name_hidden":true,"family_name":"Дідур С. Д","name_unclear":false},{"inn":"","relations":"Дитина","relations_other":"","inn_hidden":false,"family_name":"Дідур М. С","name_hidden":false,"name_unclear":false}],"full_name_suggest":{"output":"Д'яченко Тетяна Геннадіївна","input":["Д'яченко Тетяна Геннадіївна","Тетяна Геннадіївна Д'яченко","Тетяна Д'яченко"]},"patronymic":"Геннадіївна"},"source":"VULYK","estate":{"25":[{"space_hidden":false,"costs":"","costs_comment":"","address_hidden":true,"region_hidden":true,"space_comment":"","space_unclear":false,"space":"121.1","address":"","costs_rent_comment_unclear":false,"region":"","costs_rent_comment":"","space_units":"м²","costs_rent":""}]},"intro":{"declaration_year":"2014","isnotdeclaration":""}}