{"income":{"5":{"value":"178699","family_comment":"","value_unclear":false,"family_unclear":false,"family":"","comment":""},"6":{"family_comment":"","value":"178699","value_unclear":false,"family":"","comment":""},"7":{"value":"","value_unclear":false,"family_comment":"","source_name":"","family":"","comment":""},"8":{"family_comment":"","value":"","family":"","comment":""},"9":{"value":"","family_comment":"","value_unclear":false,"family_unclear":false,"family":"","comment":""},"10":{"family_comment":"","value":"","comment_unclear":false,"family":"","comment":""},"11":{"family_comment":"","value":"","family":"","comment":""},"12":{"family_comment":"","value":"","family":"","comment":""},"13":{"family_comment":"","value":"","value_unclear":false,"family":"","comment":""},"14":{"family_comment":"","value":"","family":"","comment":""},"15":{"family_comment":"","value":"","family":"","comment":""},"16":{"family_comment":"","family_unclear":false,"value":"","family":"","comment":""},"17":{"family_comment":"","family_unclear":false,"value":"","family":"","comment":""},"18":{"family_comment":"","value":"","family":"","comment":""},"19":{"family_comment":"","value":"","family":"","comment":""},"20":{"value":"","family_comment":"","value_unclear":false,"family_hidden":false,"value_hidden":false,"family_unclear":false,"comment_unclear":false,"comment":"","family":""}},"id":"vulyk_100_93","declaration":{"additional_info_text":"","notfull_lostpages":"","date":"2015-03-20T00:00:00","notfull":"","additional_info":"","url":"http://static.declarations.com.ua/declarations/chosen_ones/judges_batch/4293_navrotskyi_volodymyr_anatoliiovych.pdf"},"liabilities":{"54":{"sum_foreign_comment":"","sum":"","sum_comment":"","sum_comment_hidden":false,"sum_unclear":false,"sum_foreign":""},"55":{"sum_foreign_comment":"","sum":"","sum_comment":"","sum_foreign":""},"56":{"sum_foreign_comment":"","sum":"","sum_comment":"","sum_unclear":false,"sum_foreign":""},"57":{"sum_foreign_comment":"","sum":"","sum_comment":"","sum_comment_unclear":false,"sum_comment_hidden":false,"sum_unclear":false,"sum_foreign":""},"58":{"sum_foreign_comment":"","sum":"","sum_comment":"","sum_comment_hidden":false,"sum_unclear":false,"sum_foreign":""},"59":{"sum_foreign_comment":"","sum":"","sum_comment":"","sum_foreign":""},"60":{"sum_foreign_comment":"","sum_comment_hidden":false,"sum":"","sum_comment":"","sum_foreign":""},"61":{"sum_foreign_comment":"","sum":"","sum_comment":"","sum_foreign":""},"62":{"sum_foreign_comment":"","sum":"","sum_comment":"","sum_unclear":false,"sum_foreign":""},"63":{"sum_foreign_comment":"","sum_comment_hidden":false,"sum":"","sum_comment":"","sum_foreign":""},"64":{"sum_foreign_comment":"","sum_comment_hidden":false,"sum":"","sum_comment":"","sum_foreign":""}},"ft_src":"Навроцький Володимир Анатолійович\nсуддя хмельницького міськрайонного суду\nХмельницька область\nЗагальний місцевий суд\nВолодимир\nНавроцька Д. В. 20. 10. 2002\nДитина\nНавроцький Володимир Анатолійович\nВолодимир Анатолійович Навроцький\nВолодимир Навроцький\nНавроцький Володимир Анатолійович\nНавроцький\nАнатолійович\n178699\n178699\n.12\n2014\n178699\n178699\n178699\n178699\nДитина\nНавроцька Д. В. 20. 10. 2002\nАнатолійович\nНавроцький\nНавроцький Володимир Анатолійович\nВолодимир Анатолійович Навроцький\nВолодимир Навроцький\nНавроцький Володимир Анатолійович\nНавроцький Володимир Анатолійович\nВолодимир\nЗагальний місцевий суд\nХмельницька область\nсуддя хмельницького міськрайонного суду\n.12\n2014\nНавроцька Д. В. 20. 10. 2002\nДитина\nАнатолійович\nНавроцький\nХмельницька область\nЗагальний місцевий суд\nсуддя хмельницького міськрайонного суду\nНавроцький Володимир Анатолійович\nНавроцький Володимир Анатолійович\nВолодимир Анатолійович Навроцький\nВолодимир Навроцький\nНавроцький Володимир Анатолійович\nВолодимир\n.12\n2014","general":{"inn":"","inn_hidden":true,"last_name":"Навроцький","post":{"post_unclear":false,"region_unclear":false,"post":"суддя хмельницького міськрайонного суду","office":"Загальний місцевий суд","region":"Хмельницька область","post_hidden":false,"office_unclear":false},"name":"Володимир","full_name":"Навроцький Володимир Анатолійович","family_raw":"","addresses":[{"place_district":"","place_city_hidden":true,"place_city":"","place_city_unclear":false,"place_district_hidden":false,"place_city_type":"","place_address_hidden":true,"place_city_type_hidden":false,"place_address":"","place_hidden":true,"place":""}],"family":[{"inn_hidden":true,"inn":"","name_hidden":false,"family_name":"Навроцька Д. В. 20. 10. 2002","relations":"Дитина","name_unclear":false}],"full_name_suggest":{"output":"Навроцький Володимир Анатолійович","input":["Навроцький Володимир Анатолійович","Володимир Анатолійович Навроцький","Володимир Навроцький"]},"patronymic":"Анатолійович"},"source":"VULYK","estate":{"23":[{"space_unclear":false,"costs":"","costs_comment":"","address_hidden":false,"region_hidden":true,"space_comment":"","space":".12","address":"","costs_comment_unclear":false,"region":"","address_unclear":false,"costs_rent_comment":"","space_comment_unclear":false,"space_units":"га","costs_rent":""}]},"intro":{"declaration_year":"2014"}}