{"income":{"5":{"value":"233759","family_comment":"","value_unclear":false,"family":"39280","family_unclear":false,"comment_unclear":false,"comment":"","family_comment_unclear":false},"6":{"value":"233759","family_comment":"","value_unclear":false,"family_unclear":false,"family":"39280","comment":""},"7":{"source_name_unclear":false,"value":"","value_unclear":false,"family_comment":"","source_name":"","family":"","comment":"","source_name_hidden":false},"8":{"family_comment":"","value":"","family":"","comment":""},"9":{"family_comment":"","value":"","family":"","comment":""},"10":{"family_comment":"","value":"","value_unclear":false,"family":"","comment":""},"11":{"value":"","value_unclear":false,"value_hidden":false,"family_comment":"","family":"","comment":""},"12":{"family_comment":"","value":"","family":"","comment":"","value_hidden":false},"13":{"family_comment":"","value":"","family":"","comment":""},"14":{"family_comment":"","value":"","family":"","comment":""},"15":{"family_comment":"","value":"","family":"","comment":""},"16":{"family_comment":"","value":"","family":"","comment":""},"17":{"family_comment":"","value":"","family":"","comment":""},"18":{"family_comment":"","value":"","family":"","comment":""},"19":{"family_comment":"","family_unclear":false,"value":"","family":"","comment":""},"20":{"family_comment":"","family_unclear":false,"value":"","family":"","comment":""}},"id":"vulyk_61_66","declaration":{"additional_info_text":"","notfull_lostpages":"","date":"2015-03-25T00:00:00","notfull":"","additional_info":"","url":"http://static.declarations.com.ua/declarations/chosen_ones/mega_batch/korol_oleksandr_pavlovych.pdf"},"liabilities":{"54":{"sum_foreign_comment":"","sum":"","sum_comment":"","sum_comment_unclear":false,"sum_unclear":false,"sum_foreign":""},"55":{"sum_foreign_comment":"","sum":"","sum_comment":"","sum_foreign":""},"56":{"sum_foreign_comment":"","sum":"","sum_comment":"","sum_unclear":false,"sum_foreign":""},"57":{"sum_foreign_comment":"","sum":"","sum_comment":"","sum_comment_hidden":false,"sum_unclear":false,"sum_foreign":""},"58":{"sum_foreign_comment":"","sum":"","sum_comment":"","sum_unclear":false,"sum_foreign":""},"59":{"sum_foreign_comment":"","sum":"","sum_comment":"","sum_foreign":""},"60":{"sum_foreign_comment":"","sum_foreign_hidden":true,"sum_comment":"","sum_hidden":true,"sum":"","sum_foreign":""},"61":{"sum_foreign_comment":"","sum":"","sum_comment":"","sum_foreign":""},"62":{"sum_foreign_comment":"","sum":"","sum_comment":"","sum_unclear":false,"sum_foreign":""},"63":{"sum_foreign_comment":"","sum":"","sum_comment":"","sum_hidden":false,"sum_unclear":false,"sum_foreign":""},"64":{"sum_foreign_comment":"","sum":"","sum_hidden":false,"sum_comment":"","sum_foreign":""}},"ft_src":"суддя вінницького міського суду вінницької області\nВінницька область\nЗагальний місцевий суд\nОлександр\nКороль С. С\nПодружжя\nКороль М. О\nДитина\nПавлович\nКороль\nКороль Олександр Павлович\nКороль Олександр Павлович\nОлександр Павлович Король\nОлександр Король\nКороль Олександр Павлович\n233759\n39280\n233759\n39280\n2014\n39280\n233759\n39280\n233759\n39280\n233759\n233759\n39280\nПодружжя\nКороль С. С\nДитина\nКороль М. О\nКороль Олександр Павлович\nОлександр Павлович Король\nОлександр Король\nКороль Олександр Павлович\nОлександр\nКороль Олександр Павлович\nКороль\nВінницька область\nЗагальний місцевий суд\nсуддя вінницького міського суду вінницької області\nПавлович\n2014\nКороль С. С\nПодружжя\nКороль М. О\nДитина\nПавлович\nКороль\nКороль Олександр Павлович\nОлександр Павлович Король\nОлександр Король\nКороль Олександр Павлович\nВінницька область\nсуддя вінницького міського суду вінницької області\nЗагальний місцевий суд\nКороль Олександр Павлович\nОлександр\n2014","general":{"inn":"","name":"Олександр","patronymic_unclear":false,"family":[{"inn":"","inn_hidden":true,"relations_unclear":false,"relations_hidden":false,"relations_other":"","relations":"Подружжя","name_hidden":true,"family_name":"Король С. С","name_unclear":false},{"inn":"","relations":"Дитина","relations_other":"","inn_hidden":true,"family_name":"Король М. О","name_hidden":false,"name_unclear":false}],"patronymic":"Павлович","inn_hidden":true,"family_raw":"","inn_unclear":false,"post":{"post_unclear":false,"region_unclear":false,"post":"суддя вінницького міського суду вінницької області","office":"Загальний місцевий суд","region":"Вінницька область","post_hidden":false,"office_hidden":false,"region_hidden":false},"last_name_unclear":false,"full_name":"Король Олександр Павлович","addresses":[{"place_address":"","place_district_hidden":true,"place_city_type":"","place_city_hidden":true,"place_address_unclear":false,"place_city_type_hidden":true,"place_hidden":true,"place":"","place_district":"","place_address_hidden":true,"place_city":"","place_district_unclear":false}],"last_name":"Король","patronymic_hidden":false,"full_name_suggest":{"output":"Король Олександр Павлович","input":["Король Олександр Павлович","Олександр Павлович Король","Олександр Король"]},"name_unclear":false},"source":"VULYK","intro":{"declaration_year":"2014","isnotdeclaration":"","declaration_year_hidden":false}}