{"income":{"5":{"value":"209916.64","comment_hidden":false,"family_comment":"","family":"18609","comment":"","family_comment_hidden":false},"6":{"value":"195663.87","family_comment":"","comment_hidden":false,"family_hidden":false,"family_unclear":false,"family_comment_hidden":false,"comment":"","family":""},"7":{"value":"","comment_hidden":false,"family_comment_hidden":false,"family_comment":"","source_name":"","family":"","comment":"","source_name_hidden":false},"8":{"family_comment":"","value":"","family":"","comment":""},"9":{"value":"73.26","family_comment":"","value_unclear":false,"family_unclear":false,"comment_unclear":false,"comment":"","family":""},"10":{"family_comment":"","family_unclear":false,"value":"12617","family":"18609","comment":""},"11":{"family_comment":"","value":"","family":"","comment":""},"12":{"family_comment":"","value":"","family":"","comment":""},"13":{"family_comment":"","value":"","family":"","comment":""},"14":{"family_comment":"","value":"","family":"","comment":""},"15":{"family_comment":"","value":"1562.51","comment_unclear":false,"family":"","comment":""},"16":{"family_comment":"","value":"","comment_unclear":false,"family":"","comment":""},"17":{"family_comment":"","value":"","family":"","comment":""},"18":{"family_comment":"","value":"","family":"","comment":""},"19":{"family_comment":"","value":"","family":"","comment":""},"20":{"value":"","family_comment":"","value_unclear":false,"family_unclear":false,"family_comment_unclear":false,"family_comment_hidden":false,"comment":"","family":""}},"vehicle":{"35":[{"brand_info":"3000 куб. см.","sum_rent_comment":"","brand":"Mercedes E280","sum_comment":"","brand_unclear":false,"year":"2007","sum_hidden":false,"brand_info_unclear":false,"sum":"","sum_rent":""}]},"id":"vulyk_73_147","declaration":{"additional_info_text":"","notfull_lostpages":"","date":"2014-03-21T00:00:00","notfull":"","additional_info":"","url":"http://static.declarations.com.ua/declarations/chosen_ones/judges_batch/1130_zhelik_maksym_borysovych.pdf"},"liabilities":{"54":{"sum_foreign_comment":"","sum_foreign_hidden":false,"sum_comment":"","sum_comment_unclear":false,"sum_hidden":false,"sum_comment_hidden":false,"sum_unclear":false,"sum":"","sum_foreign":""},"55":{"sum_foreign_comment":"","sum_comment_hidden":false,"sum":"","sum_comment":"","sum_foreign":""},"56":{"sum_foreign_comment":"","sum":"","sum_comment":"","sum_comment_unclear":false,"sum_foreign":""},"57":{"sum_foreign_comment":"","sum":"","sum_comment":"","sum_hidden":false,"sum_comment_hidden":false,"sum_unclear":false,"sum_foreign":""},"58":{"sum_foreign_comment":"","sum":"","sum_comment":"","sum_hidden":false,"sum_comment_hidden":false,"sum_foreign":""},"59":{"sum_foreign_comment":"","sum":"","sum_comment":"","sum_comment_unclear":false,"sum_unclear":false,"sum_foreign":""},"60":{"sum_foreign_comment":"","sum":"","sum_comment":"","sum_hidden":false,"sum_comment_hidden":false,"sum_unclear":false,"sum_foreign":""},"61":{"sum_foreign_comment":"","sum":"","sum_comment":"","sum_foreign":""},"62":{"sum_foreign_comment":"","sum":"","sum_comment":"","sum_foreign":""},"63":{"sum_foreign_comment":"","sum":"","sum_comment":"","sum_hidden":false,"sum_comment_hidden":false,"sum_foreign":""},"64":{"sum_foreign_comment":"","sum":"","sum_comment":"","sum_foreign":""}},"ft_src":"суддя львівського апеляційного господарського суду\nЛьвівська область\nАпеляційний господарський суд\nМаксим\nЖелік Олександра Мирославівна\nПодружжя\nЖелік Борис Максимович\nДитина\nЖелік Роман Максимович\nДитина\nЖелік Юстина Максимівна\nДитина\nБорисович\nЖелік Максим Борисович\nМаксим Борисович Желік\nМаксим Желік\nЖелік Максим Борисович\nЖелік\nЖелік Максим Борисович\nMercedes E280\n3000 куб. см.\n2007\n.0812\n2013\n195663.87\n1562.51\n73.26\n18609\n12617\n18609\n209916.64\n3000 куб. см.\nMercedes E280\n2007\n2013\nЖелік Максим Борисович\nМаксим Борисович Желік\nМаксим Желік\nЖелік Максим Борисович\nМаксим\nПодружжя\nЖелік Олександра Мирославівна\nДитина\nЖелік Борис Максимович\nДитина\nЖелік Роман Максимович\nЖелік Юстина Максимівна\nДитина\nЖелік Максим Борисович\nБорисович\nАпеляційний господарський суд\nЛьвівська область\nсуддя львівського апеляційного господарського суду\nЖелік\n195663.87\n1562.51\n209916.64\n18609\n73.26\n12617\n18609\n.0812\nПодружжя\nЖелік Олександра Мирославівна\nДитина\nЖелік Борис Максимович\nДитина\nЖелік Роман Максимович\nДитина\nЖелік Юстина Максимівна\nБорисович\nЖелік\nМаксим\nЖелік Максим Борисович\nМаксим Борисович Желік\nМаксим Желік\nЖелік Максим Борисович\nЛьвівська область\nАпеляційний господарський суд\nсуддя львівського апеляційного господарського суду\nЖелік Максим Борисович\n2007\n3000 куб. см.\nMercedes E280\n1562.51\n73.26\n18609\n12617\n209916.64\n18609\n195663.87\n.0812\n2013","general":{"inn":"","name":"Максим","family":[{"inn":"","relations":"Подружжя","inn_unclear":false,"relations_hidden":false,"inn_hidden":true,"relations_other":"","name_hidden":false,"family_name":"Желік Олександра Мирославівна","name_unclear":false},{"inn":"","relations":"Дитина","inn_unclear":false,"family_name":"Желік Борис Максимович","inn_hidden":false,"relations_other":"","name_hidden":false,"name_unclear":false},{"inn":"","relations":"Дитина","relations_other":"","inn_hidden":false,"family_name":"Желік Роман Максимович","name_hidden":false,"name_unclear":false},{"inn":"","family_name":"Желік Юстина Максимівна","relations":"Дитина","inn_hidden":false,"relations_other":""}],"patronymic":"Борисович","inn_hidden":true,"family_raw":"","last_name":"Желік","post":{"post_unclear":false,"region_unclear":false,"post":"суддя львівського апеляційного господарського суду","office":"Апеляційний господарський суд","region":"Львівська область","post_hidden":false,"office_hidden":false,"office_unclear":false,"region_hidden":false},"last_name_unclear":false,"full_name":"Желік Максим Борисович","addresses":[{"place_district":"","place_city_hidden":true,"place_city":"","place_city_type_hidden":false,"place_district_hidden":false,"place_city_type":"","place_address_hidden":false,"place_address":"","place_hidden":true,"place":""}],"full_name_suggest":{"output":"Желік Максим Борисович","input":["Желік Максим Борисович","Максим Борисович Желік","Максим Желік"]},"name_unclear":false},"source":"VULYK","estate":{"23":[{"space_hidden":false,"costs":"","costs_comment":"","costs_hidden":false,"address_hidden":false,"region_hidden":true,"space_comment":"","space_unclear":false,"space":".0812","address":"","region":"","space_units_unclear":false,"costs_unclear":false,"space_units":"га","costs_rent":"","costs_rent_comment":""}]},"intro":{"declaration_year":"2013"}}