{"income":{"5":{"family_comment":"","value":"250730","family":"","comment":""},"6":{"family_comment":"","value":"235365","family_hidden":false,"comment":"","family":""},"7":{"family_comment":"","value":"","source_name":"","family":"","comment":""},"8":{"family_comment":"","value":"","family":"","comment":""},"9":{"value":"22","value_unclear":false,"family_hidden":false,"family_comment":"","family":"","comment":""},"10":{"value":"13398","family_comment":"","family_hidden":false,"value_hidden":false,"family_unclear":false,"family":"","comment":""},"11":{"family_comment":"","value":"","family":"","comment":""},"12":{"family_comment":"","value":"","family":"","comment":""},"13":{"family_comment":"","value":"","family":"","comment":""},"14":{"family_comment":"","value":"","family":"","comment":""},"15":{"family_comment":"","value":"","family":"","comment":""},"16":{"family_comment":"","value":"","family":"","comment":""},"17":{"family_comment":"","value":"","family":"","comment":""},"18":{"family_comment":"","value":"","family":"","comment":""},"19":{"family_comment":"","value":"","family":"","comment":""},"20":{"value":"1945","comment_unclear":false,"family_comment":"","family":"","comment":"","family_comment_unclear":false}},"id":"vulyk_75_5","declaration":{"additional_info_text":"","notfull_lostpages":"3 (розділ ІІ Б), 5 (розділ ІІІ Б), 6, 7, 8 (розділ IV, V)","date":"2015-05-13T00:00:00","notfull":"1","additional_info":"","url":"http://static.declarations.com.ua/declarations/chosen_ones/judges_batch/1930_pryntsevska_nataliia_mykolaivna.pdf"},"liabilities":{"54":{"sum_foreign_comment":"","sum":"","sum_comment":"","sum_foreign":""},"55":{"sum_foreign_comment":"","sum":"","sum_comment":"","sum_foreign":""},"56":{"sum_foreign_comment":"","sum":"","sum_comment":"","sum_foreign":""},"57":{"sum_foreign_comment":"","sum":"","sum_comment":"","sum_foreign":""},"58":{"sum_foreign_comment":"","sum":"","sum_comment":"","sum_foreign":""},"59":{"sum_foreign_comment":"","sum":"","sum_comment":"","sum_comment_unclear":false,"sum_unclear":false,"sum_foreign":""},"60":{"sum_foreign_comment":"","sum":"","sum_comment":"","sum_foreign":""},"61":{"sum_foreign_comment":"","sum":"","sum_comment":"","sum_foreign":""},"62":{"sum_foreign_comment":"","sum":"","sum_comment":"","sum_unclear":false,"sum_foreign":""},"63":{"sum_foreign_comment":"","sum":"","sum_comment":"","sum_foreign":""},"64":{"sum_foreign_comment":"","sum":"","sum_comment":"","sum_foreign":""}},"ft_src":"1\n3 (розділ ІІ Б), 5 (розділ ІІІ Б), 6, 7, 8 (розділ IV, V)\nПринцевська Наталія Миколаївна\nсуддя одеського апеляційного господарського суду\nОдеська область\nАпеляційний господарський суд\nНаталія\nКатранжи Андрій Дмитрович\nДитина\nПринцевська Наталія Миколаївна\nНаталія Миколаївна Принцевська\nНаталія Принцевська\nПринцевська Наталія Миколаївна\nПринцевська\nМиколаївна\n22\n13398\n1945\n250730\n235365\nу власності\n35.8\nзареєстрована\n51.7\nперебувала на час АТО\n59.3\n3 (розділ ІІ Б), 5 (розділ ІІІ Б), 6, 7, 8 (розділ IV, V)\n1\n2014\n235365\n22\n13398\n250730\n1945\n3 (розділ ІІ Б), 5 (розділ ІІІ Б), 6, 7, 8 (розділ IV, V)\n1\n2014\nПринцевська\nМиколаївна\nДитина\nКатранжи Андрій Дмитрович\nПринцевська Наталія Миколаївна\nНаталія Миколаївна Принцевська\nНаталія Принцевська\nПринцевська Наталія Миколаївна\nНаталія\nПринцевська Наталія Миколаївна\nАпеляційний господарський суд\nсуддя одеського апеляційного господарського суду\nОдеська область\n235365\n1945\n250730\n22\n13398\n35.8\nу власності\n51.7\nзареєстрована\n59.3\nперебувала на час АТО\nКатранжи Андрій Дмитрович\nДитина\nПринцевська\nМиколаївна\nсуддя одеського апеляційного господарського суду\nОдеська область\nАпеляційний господарський суд\nПринцевська Наталія Миколаївна\nПринцевська Наталія Миколаївна\nНаталія Миколаївна Принцевська\nНаталія Принцевська\nПринцевська Наталія Миколаївна\nНаталія\nу власності\n35.8\nзареєстрована\n51.7\nперебувала на час АТО\n59.3\n2014","general":{"inn":"","inn_hidden":true,"last_name":"Принцевська","post":{"office":"Апеляційний господарський суд","region":"Одеська область","post":"суддя одеського апеляційного господарського суду"},"name":"Наталія","full_name":"Принцевська Наталія Миколаївна","family_raw":"","addresses":[{"place_district":"","place_address_hidden":true,"place_city":"","place_city_type_hidden":true,"place_district_hidden":true,"place_city_type":"","place_city_hidden":true,"place_address":"","place_hidden":true,"place":""}],"family":[{"inn":"","inn_hidden":false,"relations_hidden":false,"family_name":"Катранжи Андрій Дмитрович","relations_other":"","relations":"Дитина","name_hidden":true,"name_unclear":false}],"full_name_suggest":{"output":"Принцевська Наталія Миколаївна","input":["Принцевська Наталія Миколаївна","Наталія Миколаївна Принцевська","Наталія Принцевська"]},"patronymic":"Миколаївна"},"source":"VULYK","estate":{"25":[{"space_hidden":false,"costs":"","costs_comment":"","address_hidden":true,"region_hidden":true,"space_comment":"у власності","space_unclear":false,"space":"35.8","address":"","region":"","costs_rent_comment":"","space_units":"м²","costs_rent":""},{"costs_rent":"","space_unclear":false,"region":"","costs":"","costs_rent_comment":"","costs_comment":"","region_hidden":true,"space_comment":"зареєстрована","space_units":"м²","space":"51.7","address":""},{"costs_rent":"","region":"","costs":"","costs_rent_comment":"","costs_comment":"","region_hidden":true,"space_comment":"перебувала на час АТО","space_units":"м²","space":"59.3","address":""}],"26":[{"costs_rent":"","region":"","costs":"","costs_rent_comment":"","costs_comment":"","address_hidden":true,"region_hidden":false,"space_comment":"","space_units":"м²","space":"","address":""}]},"intro":{"declaration_year":"2014","isnotdeclaration":""}}