{"income":{"5":{"family_comment":"","value":"303960","family_hidden":false,"comment":"","family":"43629"},"6":{"value":"249000","value_unclear":false,"family_hidden":false,"family_comment":"","family":"43629","comment":""},"7":{"value":"","value_unclear":false,"family_comment":"","source_name":"","family":"","comment":""},"8":{"family_comment":"","value":"","family":"","comment":""},"9":{"family_comment":"","value":"","family":"","comment":""},"10":{"value":"","family_comment":"","comment_unclear":false,"family_unclear":false,"family":"","comment":"","family_comment_unclear":false},"11":{"family_comment":"","value":"","value_unclear":false,"family":"","comment":""},"12":{"family_comment":"","value":"","family":"","comment":""},"13":{"family_comment":"","value":"","family":"","comment":""},"14":{"family_comment":"","value":"","family":"","comment":""},"15":{"value":"","family_comment":"","comment_unclear":false,"family_unclear":false,"family":"","comment":""},"16":{"family_comment":"","value":"","family":"","comment":""},"17":{"family_comment":"","value":"","family":"","comment":""},"18":{"family_comment":"","family_unclear":false,"value":"","family":"","comment":""},"19":{"family_comment":"","value":"","family":"","comment":""},"20":{"family_comment":"","family_unclear":false,"value":"54960","family":"","comment":""}},"vehicle":{"35":[{"brand_info":"1400 куб. см.","sum_rent_comment":"","year":"2008","brand_info_hidden":false,"brand_info_unclear":false,"year_unclear":false,"sum_rent":"","sum":"","brand":"Opel Astra","sum_comment":"","sum_comment_unclear":false,"brand_hidden":false,"brand_unclear":false},{"brand_info":"1600 куб. см.","sum_rent_comment":"","brand":"Nissan TIIDA","sum_comment":"","brand_unclear":false,"year":"2012","sum":"","sum_rent":""}]},"id":"vulyk_92_66","declaration":{"additional_info_text":"","notfull_lostpages":"","date":"2015-03-31T00:00:00","notfull":"","additional_info":"","url":"http://static.declarations.com.ua/declarations/chosen_ones/judges_batch/3314_protasov_volodymyr_illich.pdf"},"liabilities":{"54":{"sum_foreign_comment":"","sum":"","sum_comment":"","sum_hidden":false,"sum_unclear":false,"sum_foreign":""},"55":{"sum_foreign_comment":"","sum":"","sum_comment":"","sum_unclear":false,"sum_foreign":""},"56":{"sum_foreign_comment":"","sum":"","sum_comment":"","sum_comment_unclear":false,"sum_hidden":false,"sum_unclear":false,"sum_foreign":""},"57":{"sum_foreign_comment":"","sum":"","sum_comment":"","sum_hidden":false,"sum_comment_hidden":false,"sum_foreign":""},"58":{"sum_foreign_comment":"","sum":"","sum_comment":"","sum_foreign":""},"59":{"sum_foreign_comment":"","sum":"","sum_comment":"","sum_comment_unclear":false,"sum_foreign":""},"60":{"sum_foreign_comment":"","sum":"","sum_comment":"","sum_foreign":""},"61":{"sum_foreign_comment":"","sum":"","sum_comment":"","sum_foreign":""},"62":{"sum_foreign_comment":"","sum":"","sum_comment":"","sum_comment_unclear":false,"sum_hidden":false,"sum_unclear":false,"sum_foreign":""},"63":{"sum_foreign_comment":"","sum":"","sum_comment":"","sum_foreign":""},"64":{"sum_foreign_comment":"","sum":"","sum_comment":"","sum_foreign":""}},"ft_src":"суддя апеляційного суду харківської області\nХарківська область\nЗагальний апеляційний суд\nВолодимир\nПротасов А. В\nДитина\nІлліч\nПротасов Володимир Ілліч\nВолодимир Ілліч Протасов\nВолодимир Протасов\nПротасов Володимир Ілліч\nПротасов Володимир Ілліч\nПротасов\n1400 куб. см.\nOpel Astra\n2008\n2012\n1600 куб. см.\nNissan TIIDA\n1200\nХарківська область\nХарківська область\nм. Харків\n72\n1/2\nм. Харків\n72\nХарківська область\n1/2\nм. Харків\n78\nХарківська область\n2014\n43629\n249000\n43629\n303960\n54960\n1400 куб. см.\nOpel Astra\n2008\n1600 куб. см.\nNissan TIIDA\n2012\n1200\nХарківська область\nХарківська область\nм. Харків\n72\n72\n1/2\nХарківська область\nм. Харків\nм. Харків\n78\n1/2\nХарківська область\nДитина\nПротасов А. В\nПротасов Володимир Ілліч\nВолодимир Ілліч Протасов\nВолодимир Протасов\nПротасов Володимир Ілліч\nПротасов Володимир Ілліч\nВолодимир\nПротасов\nЗагальний апеляційний суд\nсуддя апеляційного суду харківської області\nХарківська область\nІлліч\n249000\n43629\n54960\n303960\n43629\n2014\nДитина\nПротасов А. В\nІлліч\nПротасов\nВолодимир\nПротасов Володимир Ілліч\nВолодимир Ілліч Протасов\nВолодимир Протасов\nПротасов Володимир Ілліч\nХарківська область\nЗагальний апеляційний суд\nсуддя апеляційного суду харківської області\nПротасов Володимир Ілліч\n2008\nOpel Astra\n1400 куб. см.\n2012\n1600 куб. см.\nNissan TIIDA\n54960\n43629\n303960\n249000\n43629\nм. Харків\nХарківська область\n72\nХарківська область\n1200\n1/2\nм. Харків\nХарківська область\n72\n1/2\nХарківська область\nм. Харків\n78\n2014","general":{"inn":"","name":"Володимир","patronymic_unclear":false,"family":[{"inn":"","relations":"Дитина","inn_unclear":false,"relations_hidden":false,"inn_hidden":true,"relations_other":"","name_hidden":true,"family_name":"Протасов А. В","name_unclear":false}],"patronymic":"Ілліч","inn_hidden":true,"family_raw":"","inn_unclear":false,"post":{"post_unclear":false,"post":"суддя апеляційного суду харківської області","office_hidden":false,"region":"Харківська область","office":"Загальний апеляційний суд","office_unclear":false,"region_hidden":false},"full_name":"Протасов Володимир Ілліч","addresses":[{"place_district":"","place_address_hidden":true,"place_city":"","place_city_type_hidden":false,"place_district_hidden":true,"place_city_type":"","place_city_hidden":false,"place_address_unclear":false,"place_address":"","place_hidden":true,"place":""}],"last_name":"Протасов","full_name_suggest":{"output":"Протасов Володимир Ілліч","input":["Протасов Володимир Ілліч","Володимир Ілліч Протасов","Володимир Протасов"]}},"source":"VULYK","estate":{"23":[{"region_unclear":false,"space_unclear":false,"costs":"","costs_comment":"","address_hidden":true,"region_hidden":false,"space_comment":"","space":"1200","address":"","region":"Харківська область","costs_rent_comment":"","space_units":"м²","costs_rent":""}],"24":[{"space_unclear":false,"costs":"","costs_comment":"","address_hidden":true,"region_hidden":false,"space_comment":"","space_hidden":false,"space":"","address":"","region":"","space_units_unclear":false,"space_units":"м²","space_units_hidden":false,"costs_rent":"","costs_rent_comment":""}],"25":[{"space_hidden":false,"costs":"","costs_comment":"","address_hidden":false,"region_hidden":false,"space_comment":"1/2","space":"72","address":"м. Харків","region":"Харківська область","address_unclear":false,"costs_rent_comment":"","space_comment_unclear":true,"space_units":"м²","costs_rent":""},{"costs_rent":"","region":"Харківська область","costs":"","costs_rent_comment":"","costs_comment":"","address_hidden":false,"region_hidden":false,"space_comment":"1/2","space_units":"м²","space":"78","address":"м. Харків"}],"31":[{"space_unclear":false,"address_hidden":true,"region_hidden":false,"space_comment":"","space_hidden":false,"space":"72","address":"м. Харків","region":"Харківська область","costs_property":"","costs_rent_comment":"","address_unclear":false,"space_units":"м²","costs_property_comment":"","costs_rent":""}]},"intro":{"declaration_year":"2014","isnotdeclaration":""}}