{"income":{"5":{"family_comment":"","value":"291631","value_unclear":false,"family":"17102","comment":""},"6":{"value":"270111","value_unclear":false,"family_hidden":false,"family_comment":"","family":"","comment":""},"7":{"source_name_unclear":false,"value":"","family_comment":"","source_name":"","family":"","comment":""},"8":{"family_comment":"","value":"","family":"","comment":""},"9":{"family_comment":"","value":"","family":"1863","comment":""},"10":{"family_comment":"","value":"","family":"","comment":""},"11":{"family_comment":"","value":"","comment_unclear":false,"family":"","comment":""},"12":{"family_comment":"","value":"","family":"","comment":""},"13":{"family_comment":"","value":"","family":"","comment":""},"14":{"family_comment":"","value":"","family":"","comment":""},"15":{"family_comment":"","value":"","family":"","comment":""},"16":{"family_comment":"","value":"","family":"","comment":""},"17":{"family_comment":"","value":"","family":"","comment":""},"18":{"family_comment":"","value":"","family":"","comment":""},"19":{"family_comment":"","value":"2352","family":"","comment":""},"20":{"value":"19168","family_comment":"пенсія","value_unclear":false,"family_unclear":false,"comment_unclear":false,"comment":"пенсія","family":"15239"}},"vehicle":{"35":[{"brand_info":"2.4 куб. дм","sum_rent_comment":"","brand":"Toyota Camry","sum_comment":"","brand_unclear":false,"year":"2008","sum_rent_unclear":false,"brand_info_hidden":false,"brand_info_unclear":false,"sum":"","sum_rent":""}]},"id":"vulyk_101_32","banks":{"51":[{"sum_foreign_comment":"","sum_units":"UAH","sum_comment":"Приватбанк","sum_hidden":false,"sum_foreign_units":"UAH","sum_comment_hidden":false,"sum_unclear":false,"sum":"125000","sum_foreign":""}]},"declaration":{"additional_info_text":"","notfull_lostpages":"","date":"2016-03-31T00:00:00","notfull":"","additional_info":"","url":"http://static.declarations.com.ua/declarations/chosen_ones/judges_batch/696_senator_leonid_ivanovych_2015.pdf"},"liabilities":{"54":{"sum_foreign_comment":"","sum":"","sum_comment":"","sum_comment_unclear":false,"sum_hidden":false,"sum_comment_hidden":false,"sum_unclear":false,"sum_foreign":""},"55":{"sum_foreign_comment":"","sum":"","sum_comment":"","sum_foreign":""},"56":{"sum_foreign_comment":"","sum":"","sum_comment":"","sum_comment_hidden":false,"sum_unclear":false,"sum_foreign":""},"57":{"sum_foreign_comment":"","sum":"","sum_comment":"","sum_hidden":false,"sum_comment_hidden":false,"sum_unclear":false,"sum_foreign":""},"58":{"sum_foreign_comment":"","sum":"","sum_comment":"","sum_comment_unclear":false,"sum_hidden":false,"sum_comment_hidden":false,"sum_unclear":false,"sum_foreign":""},"59":{"sum_foreign_comment":"","sum":"","sum_comment":"","sum_foreign":""},"60":{"sum_foreign_comment":"","sum":"","sum_comment":"","sum_hidden":false,"sum_comment_hidden":false,"sum_unclear":false,"sum_foreign":""},"61":{"sum_foreign_comment":"","sum":"","sum_comment":"","sum_foreign":""},"62":{"sum_foreign_comment":"","sum":"","sum_comment":"","sum_comment_unclear":false,"sum_foreign":""},"63":{"sum_foreign_comment":"","sum_comment_hidden":false,"sum":"","sum_comment":"","sum_foreign":""},"64":{"sum_foreign_comment":"","sum_comment_hidden":false,"sum":"","sum_comment":"","sum_foreign":""}},"ft_src":"суддя апеляційного суду одеської області\nОдеська область\nЗагальний апеляційний суд\nЛеонід\nКіліянчук Ніна Миколаївна\nПодружжя\nІванович\nСенатор Леонід Іванович\nСенатор\nСенатор Леонід Іванович\nЛеонід Іванович Сенатор\nЛеонід Сенатор\nСенатор Леонід Іванович\nToyota Camry\n2.4 куб. дм\n2008\nПриватбанк\n125000\n2015\n2.4 куб. дм\n2008\nToyota Camry\n125000\nПриватбанк\n3.19\n36\n71\nСенатор Леонід Іванович\nЛеонід Іванович Сенатор\nЛеонід Сенатор\nСенатор Леонід Іванович\nЛеонід\nСенатор Леонід Іванович\nІванович\nсуддя апеляційного суду одеської області\nОдеська область\nЗагальний апеляційний суд\nСенатор\nПодружжя\nКіліянчук Ніна Миколаївна\n270111\n19168\nпенсія\nпенсія\n15239\n291631\n17102\n1863\n2352\n2015\n3.19\n36\n71\nКіліянчук Ніна Миколаївна\nПодружжя\nЛеонід\nІванович\nСенатор\nСенатор Леонід Іванович\nЛеонід Іванович Сенатор\nЛеонід Сенатор\nСенатор Леонід Іванович\nсуддя апеляційного суду одеської області\nОдеська область\nЗагальний апеляційний суд\nСенатор Леонід Іванович\n270111\n1863\n17102\n291631\n2352\nпенсія\nпенсія\n15239\n19168\n2008\nToyota Camry\n2.4 куб. дм\n2352\n1863\nпенсія\nпенсія\n19168\n15239\n17102\n291631\n270111\n71\n3.19\n36\nПриватбанк\n125000\n2015","general":{"inn":"","name":"Леонід","inn_unclear":false,"family":[{"inn":"","relations":"Подружжя","relations_other":"","inn_hidden":true,"family_name":"Кіліянчук Ніна Миколаївна","name_hidden":true,"name_unclear":false}],"inn_hidden":true,"family_raw":"","last_name":"Сенатор","post":{"region":"Одеська область","region_unclear":false,"post":"суддя апеляційного суду одеської області","office_unclear":false,"office":"Загальний апеляційний суд"},"full_name":"Сенатор Леонід Іванович","addresses":[{"place_district":"","place_address_hidden":true,"place_city":"","place_city_type_hidden":false,"place_district_hidden":false,"place_city_type":"","place_city_hidden":true,"place_address":"","place_hidden":true,"place":""}],"patronymic":"Іванович","patronymic_hidden":false,"full_name_suggest":{"output":"Сенатор Леонід Іванович","input":["Сенатор Леонід Іванович","Леонід Іванович Сенатор","Леонід Сенатор"]}},"source":"VULYK","estate":{"23":[{"space_unclear":false,"costs":"","costs_comment":"","address_hidden":false,"region_hidden":true,"space_comment":"","space_hidden":false,"space":"3.19","address":"","costs_comment_unclear":false,"region":"","space_units_unclear":false,"space_units":"га","costs_rent":"","costs_rent_comment":""}],"25":[{"space_unclear":false,"costs":"","costs_comment":"","address_hidden":false,"region_hidden":true,"space_comment":"","space_hidden":false,"space":"71","address":"","region":"","costs_rent_comment":"","space_comment_unclear":false,"space_units":"м²","costs_rent":""}],"27":[{"space_hidden":false,"costs":"","costs_comment":"","address_hidden":false,"region_hidden":true,"space_comment":"","space":"36","address":"","region":"","costs_rent_comment":"","space_units":"м²","costs_rent":""}]},"intro":{"declaration_year":"2015"}}