{"income":{"5":{"value":"652783","family_comment":"","value_unclear":false,"family_hidden":false,"value_hidden":false,"family_unclear":false,"comment_unclear":false,"comment":"","family":"18509"},"6":{"value":"240894","family_comment":"","family_hidden":false,"family_unclear":false,"family":"","comment":""},"7":{"value":"","family_hidden":false,"value_hidden":false,"family_comment":"","source_name":"","family":"","comment":""},"8":{"family_comment":"","value":"","family":"","comment":""},"9":{"family_comment":"","value":"","value_unclear":false,"family":"","comment":""},"10":{"family_comment":"","family_unclear":false,"value":"","family":"","comment":""},"11":{"family_comment":"","value":"","family":"","comment":""},"12":{"family_comment":"","value":"","family":"","comment":""},"13":{"family_comment":"","value":"","family":"","comment":""},"14":{"family_comment":"","value":"168779","family":"","comment":""},"15":{"family_comment":"","value":"","family":"","comment":""},"16":{"family_comment":"","value":"243110","family":"","comment":""},"17":{"family_comment":"","value":"","family":"15589","comment":""},"18":{"family_comment":"","value":"","family":"","comment":""},"19":{"family_comment":"","value":"","family":"","comment":""},"20":{"value":"","value_unclear":false,"family_comment":"","comment_unclear":false,"comment":"","family":"2920"}},"vehicle":{"35":[{"brand_info":"1798 куб. см.","sum_rent_comment":"","year":"2013","sum_rent_unclear":false,"brand_info_unclear":false,"year_unclear":false,"sum_rent":"","sum":"231705","brand":"Mitsubishi ASX","sum_comment":"","brand_unclear":false,"sum_unclear":false}]},"id":"vulyk_71_142","declaration":{"additional_info_text":"","notfull_lostpages":"","date":"2014-03-24T00:00:00","notfull":"","additional_info":"","url":"http://static.declarations.com.ua/declarations/chosen_ones/judges_batch/460_barylska_alla_petrivna.pdf"},"liabilities":{"54":{"sum_foreign_comment":"","sum":"15524","sum_comment":"","sum_comment_unclear":false,"sum_comment_hidden":false,"sum_unclear":false,"sum_foreign":""},"55":{"sum_foreign_comment":"","sum":"","sum_comment":"","sum_foreign":""},"56":{"sum_foreign_comment":"","sum":"","sum_comment":"","sum_comment_unclear":false,"sum_unclear":false,"sum_foreign":""},"57":{"sum_foreign_comment":"","sum":"73328","sum_comment":"","sum_comment_hidden":false,"sum_unclear":false,"sum_foreign":""},"58":{"sum_foreign_comment":"","sum":"18659","sum_comment":"","sum_comment_hidden":false,"sum_unclear":false,"sum_foreign":""},"59":{"sum_foreign_comment":"","sum_comment":"","sum":"","sum_comment_hidden":false,"sum_foreign":""},"60":{"sum_foreign_comment":"","sum_comment":"","sum":"","sum_comment_hidden":false,"sum_foreign":""},"61":{"sum_foreign_comment":"","sum":"","sum_comment":"","sum_foreign":""},"62":{"sum_foreign_comment":"","sum":"","sum_comment":"","sum_foreign":""},"63":{"sum_foreign_comment":"","sum":"","sum_comment":"","sum_unclear":false,"sum_foreign":""},"64":{"sum_foreign_comment":"","sum":"","sum_comment":"","sum_unclear":false,"sum_foreign":""}},"ft_src":"1798 куб. см.\nMitsubishi ASX\n2013\n231705\n62\n48.1\n2013\n240894\n168779\n18509\n652783\n243110\n15589\n2920\n1798 куб. см.\nMitsubishi ASX\n2013\n231705\n62\n48.1\nПодружжя\nКозлов Анатолій Володимирович\nДитина\nКозлова Валентина Анатоліївна\nБарильська Алла Петрівна\nАлла Петрівна Барильська\nАлла Барильська\nБарильська Алла Петрівна\nБарильська Алла Петрівна\nАлла\nПетрівна\nЗагальний апеляційний суд\nДніпропетровська область\nсуддя апеляційного суду дніпропетровської області\nБарильська\n18659\n15524\n73328\n240894\n2920\n15589\n168779\n652783\n18509\n243110\n2013\n18659\n73328\n15524\nКозлов Анатолій Володимирович\nПодружжя\nКозлова Валентина Анатоліївна\nДитина\nПетрівна\nБарильська\nАлла\nБарильська Алла Петрівна\nАлла Петрівна Барильська\nАлла Барильська\nБарильська Алла Петрівна\nДніпропетровська область\nЗагальний апеляційний суд\nсуддя апеляційного суду дніпропетровської області\nБарильська Алла Петрівна","general":{"inn":"","name":"Алла","last_name":"Барильська","family":[{"inn":"","inn_hidden":false,"relations_hidden":false,"family_name":"Козлов Анатолій Володимирович","relations_other":"","relations":"Подружжя","name_hidden":false,"name_unclear":false},{"inn":"","inn_hidden":false,"relations_hidden":false,"family_name":"Козлова Валентина Анатоліївна","relations_other":"","relations":"Дитина","name_hidden":false,"name_unclear":false}],"inn_hidden":false,"family_raw":"","inn_unclear":false,"post":{"post_unclear":false,"region_unclear":false,"post":"суддя апеляційного суду дніпропетровської області","post_hidden":false,"region":"Дніпропетровська область","office":"Загальний апеляційний суд","office_unclear":false},"full_name_suggest":{"output":"Барильська Алла Петрівна","input":["Барильська Алла Петрівна","Алла Петрівна Барильська","Алла Барильська"]},"full_name":"Барильська Алла Петрівна","patronymic":"Петрівна","patronymic_hidden":false,"last_name_unclear":false,"name_unclear":false},"source":"VULYK","estate":{"25":[{"region_unclear":false,"space_unclear":false,"costs":"","costs_rent_unclear":false,"costs_comment":"","costs_hidden":false,"address_hidden":false,"region_hidden":true,"space_comment":"","space_hidden":false,"space":"62","address":"","space_comment_unclear":false,"region":"","address_unclear":false,"costs_rent_comment":"","costs_rent_hidden":false,"costs_unclear":false,"space_units":"м²","costs_rent":""},{"costs":"","costs_comment":"","costs_hidden":false,"address_hidden":false,"region_hidden":false,"space_comment":"","space":"48.1","address":"","region":"","costs_rent_comment":"","space_units":"м²","costs_rent":""}]},"intro":{"declaration_year":"2013","isnotdeclaration":""}}