{"income":{"5":{"value":"225004","family_comment":"","value_unclear":false,"family":"","family_unclear":false,"comment_unclear":false,"comment":"","family_comment_unclear":false},"6":{"value":"225004","family_comment":"","value_unclear":false,"family_unclear":false,"family":"","comment":""},"7":{"source_name_unclear":false,"value":"","value_unclear":false,"family_comment":"","source_name":"","family":"","comment":"","source_name_hidden":false},"8":{"family_comment":"","value":"","family":"","comment":""},"9":{"family_comment":"","value":"","family":"","comment":""},"10":{"family_comment":"","value":"","value_unclear":false,"family":"","comment":""},"11":{"value":"","value_unclear":false,"value_hidden":false,"family_comment":"","family":"","comment":""},"12":{"family_comment":"","value":"","family":"","comment":"","value_hidden":false},"13":{"family_comment":"","value":"","family":"","comment":""},"14":{"family_comment":"","value":"","family":"","comment":""},"15":{"family_comment":"","value":"","family":"","comment":""},"16":{"family_comment":"","value":"","family":"","comment":""},"17":{"family_comment":"","value":"","family":"","comment":""},"18":{"family_comment":"","value":"","family":"","comment":""},"19":{"family_comment":"","family_unclear":false,"value":"","family":"","comment":""},"20":{"family_comment":"","family_unclear":false,"value":"","family":"","comment":""}},"id":"vulyk_61_168","declaration":{"additional_info_text":"","notfull_lostpages":"","date":"2015-03-16T00:00:00","notfull":"","additional_info":"","url":"http://static.declarations.com.ua/declarations/chosen_ones/mega_batch/dovhotko_tetiana_mykolaivna.pdf"},"liabilities":{"54":{"sum_foreign_comment":"","sum":"","sum_comment":"","sum_comment_unclear":false,"sum_unclear":false,"sum_foreign":""},"55":{"sum_foreign_comment":"","sum":"","sum_comment":"","sum_foreign":""},"56":{"sum_foreign_comment":"","sum":"","sum_comment":"","sum_unclear":false,"sum_foreign":""},"57":{"sum_foreign_comment":"","sum":"","sum_comment":"","sum_comment_hidden":false,"sum_unclear":false,"sum_foreign":""},"58":{"sum_foreign_comment":"","sum":"","sum_comment":"","sum_unclear":false,"sum_foreign":""},"59":{"sum_foreign_comment":"","sum":"","sum_comment":"","sum_foreign":""},"60":{"sum_foreign_comment":"","sum_foreign_hidden":false,"sum_comment":"","sum_hidden":false,"sum":"","sum_foreign":""},"61":{"sum_foreign_comment":"","sum":"","sum_comment":"","sum_foreign":""},"62":{"sum_foreign_comment":"","sum":"","sum_comment":"","sum_unclear":false,"sum_foreign":""},"63":{"sum_foreign_comment":"","sum":"","sum_comment":"","sum_hidden":false,"sum_unclear":false,"sum_foreign":""},"64":{"sum_foreign_comment":"","sum":"","sum_hidden":false,"sum_comment":"","sum_foreign":""}},"ft_src":"Харків\nХарківська область\nзаступник голови московського районного суду міста харкова\nХарківська область\nЗагальний місцевий суд\nТетяна\nДовготько В. В\nДитина\nДовготько М. В\nДитина\nМиколаївна\nДовготько\nДовготько Тетяна Миколаївна\nДовготько Тетяна Миколаївна\nТетяна Миколаївна Довготько\nТетяна Довготько\nДовготько Тетяна Миколаївна\n225004\n225004\nХарківська область\nХарківський р-н\n43.5\n2014\n225004\n225004\n43.5\nХарківський р-н\nХарківська область\nДитина\nДовготько В. В\nДитина\nДовготько М. В\nДовготько Тетяна Миколаївна\nТетяна Миколаївна Довготько\nТетяна Довготько\nДовготько Тетяна Миколаївна\nТетяна\nДовготько Тетяна Миколаївна\nДовготько\nХарківська область\nЗагальний місцевий суд\nзаступник голови московського районного суду міста харкова\nМиколаївна\nХарків\nХарківська область\n225004\n225004\n2014\nДовготько В. В\nДитина\nДовготько М. В\nДитина\nМиколаївна\nДовготько\nДовготько Тетяна Миколаївна\nТетяна Миколаївна Довготько\nТетяна Довготько\nДовготько Тетяна Миколаївна\nХарківська область\nХарків\nХарківська область\nзаступник голови московського районного суду міста харкова\nЗагальний місцевий суд\nДовготько Тетяна Миколаївна\nТетяна\nХарківський р-н\nХарківська область\n43.5\n2014","general":{"inn":"","name":"Тетяна","patronymic_unclear":false,"family":[{"inn":"","inn_hidden":false,"relations_unclear":false,"relations_hidden":false,"relations_other":"","relations":"Дитина","name_hidden":false,"family_name":"Довготько В. В","name_unclear":false},{"inn":"","relations":"Дитина","relations_other":"","inn_hidden":false,"family_name":"Довготько М. В","name_hidden":false,"name_unclear":false}],"patronymic":"Миколаївна","inn_hidden":true,"family_raw":"","inn_unclear":false,"post":{"post_unclear":false,"region_unclear":false,"post":"заступник голови московського районного суду міста харкова","office":"Загальний місцевий суд","region":"Харківська область","post_hidden":false,"office_hidden":false,"region_hidden":false},"last_name_unclear":false,"full_name":"Довготько Тетяна Миколаївна","addresses":[{"place_address":"","place_district_hidden":false,"place_city_type":"Місто","place_city_hidden":false,"place_address_unclear":false,"place_city_type_hidden":false,"place_hidden":false,"place":"Харківська область","place_district":"","place_address_hidden":false,"place_city":"Харків","place_district_unclear":false}],"last_name":"Довготько","patronymic_hidden":false,"full_name_suggest":{"output":"Довготько Тетяна Миколаївна","input":["Довготько Тетяна Миколаївна","Тетяна Миколаївна Довготько","Тетяна Довготько"]},"name_unclear":false},"source":"VULYK","estate":{"25":[{"region_unclear":false,"space_hidden":false,"costs":"","costs_comment":"","address_hidden":false,"region_hidden":false,"space_comment":"","space_unclear":false,"space":"43.5","address":"Харківський р-н","costs_comment_unclear":false,"costs_unclear":false,"region":"Харківська область","address_unclear":false,"costs_rent_comment":"","space_comment_unclear":false,"space_units":"м²","costs_rent":""}]},"intro":{"declaration_year":"2014","isnotdeclaration":"","declaration_year_hidden":false}}