{"income":{"5":{"family_comment":"","value":"258092","family":"7690","comment":""},"6":{"value":"244582","family_comment":"","value_unclear":false,"comment_hidden":false,"family_unclear":false,"family":"7690","comment":""},"7":{"family_comment":"","value":"","source_name":"","family":"","comment":""},"8":{"family_comment":"","value":"","family":"","comment":""},"9":{"family_comment":"","family_unclear":false,"value":"","family":"","comment":""},"10":{"family_comment":"","value":"","value_unclear":false,"family":"","comment":""},"11":{"family_comment":"","value":"","family":"","comment":""},"12":{"family_comment":"","value":"","family":"","comment":""},"13":{"family_comment":"","value":"","family":"","comment":""},"14":{"family_comment":"","value":"","family":"","comment":""},"15":{"family_comment":"","value":"","family":"","comment":""},"16":{"family_comment":"","value":"","family":"","comment":""},"17":{"family_comment":"","value":"","family":"","comment":""},"18":{"family_comment":"","value":"","family":"","comment":""},"19":{"family_comment":"","value":"","family":"","comment":""},"20":{"value":"","family":"","value_unclear":false,"family_hidden":false,"family_comment":"","comment_unclear":false,"comment":"","family_comment_unclear":false}},"id":"vulyk_97_30","declaration":{"additional_info_text":"","notfull_lostpages":"","date":"2015-03-20T00:00:00","notfull":"","additional_info":"","url":"http://static.declarations.com.ua/declarations/chosen_ones/judges_batch/3858_vorontsova_svitlana_viktorivna.pdf"},"liabilities":{"54":{"sum_foreign_comment":"","sum":"","sum_comment":"","sum_comment_unclear":false,"sum_hidden":false,"sum_comment_hidden":false,"sum_unclear":false,"sum_foreign":""},"55":{"sum_foreign_comment":"","sum":"","sum_comment":"","sum_foreign":""},"56":{"sum_foreign_comment":"","sum":"","sum_comment":"","sum_foreign":""},"57":{"sum_foreign_comment":"","sum":"","sum_comment":"","sum_comment_unclear":false,"sum_hidden":false,"sum_comment_hidden":false,"sum_unclear":false,"sum_foreign":""},"58":{"sum_foreign_comment":"","sum":"","sum_comment":"","sum_comment_unclear":false,"sum_hidden":false,"sum_comment_hidden":false,"sum_unclear":false,"sum_foreign":""},"59":{"sum_foreign_comment":"","sum":"","sum_comment":"","sum_foreign":""},"60":{"sum_foreign_comment":"","sum":"","sum_comment":"","sum_comment_unclear":false,"sum_hidden":false,"sum_comment_hidden":false,"sum_foreign":""},"61":{"sum_foreign_comment":"","sum":"","sum_comment":"","sum_foreign":""},"62":{"sum_foreign_comment":"","sum":"","sum_comment":"","sum_unclear":false,"sum_foreign":""},"63":{"sum_foreign_comment":"","sum":"","sum_hidden":false,"sum_comment":"","sum_foreign":""},"64":{"sum_foreign_comment":"","sum":"","sum_comment":"","sum_foreign":""}},"ft_src":"суддя апеляційного суду чернігівської області\nЧернігівська область\nЗагальний апеляційний суд\nСвітлана\nВоронцова Вероніка Олексіївна, 28. 05. 1994\nДитина\nВікторівна\nВоронцова Світлана Вікторівна\nСвітлана Вікторівна Воронцова\nСвітлана Воронцова\nВоронцова Світлана Вікторівна\nВоронцова Світлана Вікторівна\nВоронцова\n7690\n258092\n244582\n7690\n100\n50\n44.7\nдоговір найму\n2014\n7690\n244582\n7690\n258092\n100\n50\n44.7\nдоговір найму\nВоронцова Світлана Вікторівна\nСвітлана Вікторівна Воронцова\nСвітлана Воронцова\nВоронцова Світлана Вікторівна\nСвітлана\nДитина\nВоронцова Вероніка Олексіївна, 28. 05. 1994\nВоронцова Світлана Вікторівна\nВоронцова\nЗагальний апеляційний суд\nЧернігівська область\nсуддя апеляційного суду чернігівської області\nВікторівна\n244582\n7690\n258092\n7690\n2014\nДитина\nВоронцова Вероніка Олексіївна, 28. 05. 1994\nВікторівна\nВоронцова\nСвітлана\nВоронцова Світлана Вікторівна\nСвітлана Вікторівна Воронцова\nСвітлана Воронцова\nВоронцова Світлана Вікторівна\nЧернігівська область\nЗагальний апеляційний суд\nсуддя апеляційного суду чернігівської області\nВоронцова Світлана Вікторівна\nдоговір найму\n44.7\n100\n50\n2014","general":{"name_hidden":false,"name":"Світлана","last_name_hidden":false,"inn":"","family":[{"inn":"","relations":"Дитина","relations_other":"","inn_hidden":true,"family_name":"Воронцова Вероніка Олексіївна, 28. 05. 1994","name_hidden":false,"name_unclear":false}],"patronymic":"Вікторівна","inn_hidden":true,"family_raw":"","inn_unclear":false,"post":{"region_unclear":false,"region":"Чернігівська область","post":"суддя апеляційного суду чернігівської області","office":"Загальний апеляційний суд","office_unclear":false,"post_hidden":false},"full_name":"Воронцова Світлана Вікторівна","addresses":[{"place_district":"","place_city_hidden":true,"place_city":"","place_city_unclear":false,"place_district_hidden":true,"place_city_type":"","place_address_hidden":true,"place_city_type_hidden":true,"place_address":"","place_hidden":true,"place":""}],"last_name":"Воронцова","patronymic_hidden":false,"full_name_suggest":{"output":"Воронцова Світлана Вікторівна","input":["Воронцова Світлана Вікторівна","Світлана Вікторівна Воронцова","Світлана Воронцова"]}},"source":"VULYK","estate":{"23":[{"region_unclear":false,"space_unclear":false,"costs":"","costs_rent_unclear":false,"costs_comment":"","address_hidden":true,"region_hidden":true,"space_comment":"","space":"100","address":"","region":"","address_unclear":false,"costs_rent_comment":"","space_units":"м²","costs_rent":""},{"region_unclear":false,"costs":"","costs_rent_unclear":false,"costs_comment":"","region_hidden":false,"space_comment":"","space":"50","address":"","region":"","address_unclear":false,"costs_rent_comment":"","space_units":"м²","costs_rent":""}],"25":[{"region_unclear":false,"space_unclear":false,"costs":"","costs_comment":"","address_hidden":true,"region_hidden":true,"space_comment":"","space_hidden":false,"space":"44.7","address":"","region":"","costs_rent_comment":"договір найму","space_comment_unclear":false,"space_comment_hidden":false,"space_units":"м²","costs_rent":""}]},"intro":{"declaration_year":"2014","isnotdeclaration":""}}