{"income":{"5":{"family_comment":"","value":"388514","value_unclear":false,"family":"","comment":""},"6":{"value":"240093","value_unclear":false,"family_hidden":false,"family_comment":"","family":"","comment":""},"7":{"source_name_unclear":false,"value":"","family_comment":"","source_name":"","family":"","comment":""},"8":{"family_comment":"","value":"","family":"","comment":""},"9":{"family_comment":"","value":"","family":"","comment":""},"10":{"family_comment":"","value":"","family":"","comment":""},"11":{"family_comment":"","value":"","comment_unclear":false,"family":"","comment":""},"12":{"family_comment":"","value":"","family":"","comment":""},"13":{"family_comment":"","value":"","family":"","comment":""},"14":{"family_comment":"","value":"","family":"","comment":""},"15":{"family_comment":"","value":"9971","family":"","comment":""},"16":{"family_comment":"","value":"138450","family":"","comment":""},"17":{"family_comment":"","value":"","family":"","comment":""},"18":{"family_comment":"","value":"","family":"","comment":""},"19":{"family_comment":"","value":"","family":"","comment":""},"20":{"value":"","family_comment":"","value_unclear":false,"family_unclear":false,"comment_unclear":false,"comment":"","family":""}},"vehicle":{"35":[{"brand_info":"1.6","sum_rent_comment":"","brand":"Skoda Octavia","sum_comment":"","brand_unclear":false,"year":"2005","sum_rent_unclear":false,"brand_info_hidden":false,"brand_info_unclear":false,"sum":"","sum_rent":""},{"brand_info":"1.4","sum_rent_comment":"","brand":"Hyundai i20","sum_comment":"","year":"2010","brand_info_unclear":false,"sum":"","sum_rent":""}]},"id":"vulyk_101_181","declaration":{"additional_info_text":"","notfull_lostpages":"","date":"2016-03-31T00:00:00","notfull":"","additional_info":"","url":"http://static.declarations.com.ua/declarations/chosen_ones/judges_batch/896_popova_iryna_anatoliivna_2015.pdf"},"liabilities":{"54":{"sum_foreign_comment":"","sum":"15834","sum_comment":"","sum_comment_unclear":false,"sum_hidden":false,"sum_comment_hidden":false,"sum_unclear":false,"sum_foreign":""},"55":{"sum_foreign_comment":"","sum":"","sum_comment":"","sum_foreign":""},"56":{"sum_foreign_comment":"","sum":"","sum_comment":"","sum_comment_hidden":false,"sum_unclear":false,"sum_foreign":""},"57":{"sum_foreign_comment":"","sum":"","sum_comment":"","sum_hidden":false,"sum_comment_hidden":false,"sum_unclear":false,"sum_foreign":""},"58":{"sum_foreign_comment":"","sum":"","sum_comment":"","sum_comment_unclear":false,"sum_hidden":false,"sum_comment_hidden":false,"sum_unclear":false,"sum_foreign":""},"59":{"sum_foreign_comment":"","sum":"","sum_comment":"","sum_foreign":""},"60":{"sum_foreign_comment":"","sum":"","sum_comment":"","sum_hidden":false,"sum_comment_hidden":false,"sum_unclear":false,"sum_foreign":""},"61":{"sum_foreign_comment":"","sum":"","sum_comment":"","sum_foreign":""},"62":{"sum_foreign_comment":"","sum":"","sum_comment":"","sum_comment_unclear":false,"sum_foreign":""},"63":{"sum_foreign_comment":"","sum_comment_hidden":false,"sum":"","sum_comment":"","sum_foreign":""},"64":{"sum_foreign_comment":"","sum_comment_hidden":false,"sum":"","sum_comment":"","sum_foreign":""}},"ft_src":"15834\nсуддя господарського суду запорізької області\nЗапорізька область\nГосподарський місцевий суд\nІрина\nОринянський І. Б\nДитина\nАнатоліївна\nПопова Ірина Анатоліївна\nПопова\nПопова Ірина Анатоліївна\nІрина Анатоліївна Попова\nІрина Попова\nПопова Ірина Анатоліївна\nSkoda Octavia\n1.6\n2005\n1.4\n2010\nHyundai i20\n2/3 частини\n66.85\n1/2 частина. Спадщина\n33\n1/2 частина\n33\n1/3 частина. Приват.\n66.85\n2015\n240093\n9971\n388514\n138450\n1.6\n2005\nSkoda Octavia\n1.4\n2010\nHyundai i20\n33\n1/2 частина. Спадщина\n2/3 частини\n66.85\n66.85\n1/3 частина. Приват.\n33\n1/2 частина\nПопова Ірина Анатоліївна\nІрина Анатоліївна Попова\nІрина Попова\nПопова Ірина Анатоліївна\nІрина\nПопова Ірина Анатоліївна\nАнатоліївна\nсуддя господарського суду запорізької області\nЗапорізька область\nГосподарський місцевий суд\nПопова\nДитина\nОринянський І. Б\n15834\n240093\n9971\n388514\n138450\n2015\n15834\nОринянський І. Б\nДитина\nІрина\nАнатоліївна\nПопова\nПопова Ірина Анатоліївна\nІрина Анатоліївна Попова\nІрина Попова\nПопова Ірина Анатоліївна\nсуддя господарського суду запорізької області\nЗапорізька область\nГосподарський місцевий суд\nПопова Ірина Анатоліївна\n2005\nSkoda Octavia\n1.6\n2010\n1.4\nHyundai i20\n9971\n388514\n138450\n240093\n2/3 частини\n66.85\n1/3 частина. Приват.\n66.85\n1/2 частина. Спадщина\n33\n1/2 частина\n33\n2015","general":{"inn":"","name":"Ірина","inn_unclear":false,"family":[{"inn":"","relations":"Дитина","relations_other":"","inn_hidden":true,"family_name":"Оринянський І. Б","name_hidden":true,"name_unclear":false}],"inn_hidden":true,"family_raw":"","last_name":"Попова","post":{"region":"Запорізька область","region_unclear":false,"post":"суддя господарського суду запорізької області","office_unclear":false,"office":"Господарський місцевий суд"},"full_name":"Попова Ірина Анатоліївна","addresses":[{"place_district":"","place_address_hidden":true,"place_city":"","place_city_type_hidden":false,"place_district_hidden":false,"place_city_type":"","place_city_hidden":true,"place_address":"","place_hidden":true,"place":""}],"patronymic":"Анатоліївна","patronymic_hidden":false,"full_name_suggest":{"output":"Попова Ірина Анатоліївна","input":["Попова Ірина Анатоліївна","Ірина Анатоліївна Попова","Ірина Попова"]}},"source":"VULYK","estate":{"25":[{"space_unclear":false,"costs":"","costs_comment":"","address_hidden":false,"region_hidden":true,"space_comment":"1/3 частина. Приват.","space_hidden":false,"space":"66.85","address":"","region":"","costs_rent_comment":"","space_comment_unclear":false,"space_units":"м²","costs_rent":""}],"26":[{"costs_rent":"","region":"","costs":"","costs_rent_comment":"","costs_comment":"","address_hidden":false,"region_hidden":true,"space_comment":"1/2 частина. Спадщина","space_units":"м²","space":"33","address":""}],"31":[{"space_unclear":false,"address_hidden":true,"region_hidden":true,"space_comment":"2/3 частини","space_hidden":false,"space":"66.85","address":"","costs_rent_comment_unclear":false,"region":"","costs_property":"","costs_rent_comment":"","space_units":"м²","costs_property_comment":"","costs_rent":""}],"32":[{"costs_rent":"","region":"","costs_property":"","costs_rent_comment":"","address_hidden":true,"region_hidden":true,"space_comment":"1/2 частина","costs_property_comment":"","space_units":"м²","space":"33","address":""}]},"intro":{"declaration_year":"2015"}}