{"id":"vulyk_73_146","ft_src":"У спільній сумісній власності\n16.8\nу спільній сумісній власності\n16.8\nУ спільній сумісній власності\n318.7\nУ спільній сумісній власності\n.242\nУ спільній сумісній власності\n.242\nУ спільній сумісній власності\n318.7\nУ спільній сумісній власності\n120\nмансарда у спільній сумісній власності\n120\nУ спільній сумісній власності\n120\nмансарда У спільній сумісній власності\n120\n2013\n193768.75\n57019.17\n32.85\n12617\n263437.77\n193768.75\n57019.17\n263437.77\n32.85\n12617\nЗварич Оксана Володимирівна\nОксана Володимирівна Зварич\nОксана Зварич\nЗварич Оксана Володимирівна\nОксана\nПодружжя\nЗварич Ігор Степанович\nДитина\nЗварич Іванна Ігорівна\nЗварич Оксана Володимирівна\nВолодимирівна\nАпеляційний господарський суд\nЛьвівська область\nсуддя львівського апеляційного господарського суду\nЗварич\n14653\n14653\n16.8\nУ спільній сумісній власності\n318.7\nУ спільній сумісній власності\n120\nУ спільній сумісній власності\n120\nмансарда У спільній сумісній власності\nУ спільній сумісній власності\n.242\n.242\nУ спільній сумісній власності\n16.8\nу спільній сумісній власності\n318.7\nУ спільній сумісній власності\nУ спільній сумісній власності\n120\n120\nмансарда у спільній сумісній власності\n2013\n14653\n14653\nПодружжя\nЗварич Ігор Степанович\nДитина\nЗварич Іванна Ігорівна\nВолодимирівна\nЗварич\nОксана\nЗварич Оксана Володимирівна\nОксана Володимирівна Зварич\nОксана Зварич\nЗварич Оксана Володимирівна\nЛьвівська область\nАпеляційний господарський суд\nсуддя львівського апеляційного господарського суду\nЗварич Оксана Володимирівна","estate":{"23":[{"costs_unclear":false,"address":"","space_units":"га","costs_hidden":false,"space_hidden":false,"space_unclear":false,"region_hidden":true,"space_units_unclear":false,"costs_comment":"","address_hidden":false,"space":".242","space_comment":"У спільній сумісній власності","costs_rent_comment":"","costs":"","region":"","costs_rent":""}],"24":[{"address":"","space_units":"м²","costs_hidden":false,"costs_comment":"","space_unclear":false,"region_hidden":true,"space_units_unclear":false,"space_comment":"У спільній сумісній власності","space_comment_unclear":false,"space_comment_hidden":false,"costs":"","address_hidden":false,"costs_rent_comment":"","space":"318.7","region":"","costs_rent":""}],"25":[{"address":"","space_units":"м²","costs_hidden":false,"space_hidden":false,"space_unclear":false,"region_hidden":true,"costs_rent_comment":"","space_comment":"У спільній сумісній власності","address_hidden":false,"space_comment_hidden":false,"costs":"","costs_comment":"","space":"120","region":"","costs_rent":""},{"address":"","space_units":"м²","costs_comment":"","space_unclear":false,"region_hidden":true,"space_comment":"мансарда У спільній сумісній власності","address_hidden":false,"space":"120","space_comment_unclear":false,"costs_rent_comment":"","costs":"","region":"","costs_rent":""}],"27":[{"address":"","space_units":"м²","costs_hidden":false,"costs_comment":"","space_unclear":false,"region_hidden":true,"space_comment":"У спільній сумісній власності","address_hidden":false,"costs":"","costs_rent_comment":"","space":"16.8","region":"","costs_rent":""}],"29":[{"costs_property_comment":"","address":"","space_units":"га","space_unclear":false,"region_hidden":true,"costs_property":"","space_comment":"У спільній сумісній власності","address_hidden":false,"costs_rent_comment":"","space":".242","region":"","costs_rent":""}],"30":[{"costs_property_comment":"","address":"","space_units":"м²","space_hidden":false,"space_unclear":false,"region_hidden":true,"costs_property":"","space_comment":"У спільній сумісній власності","address_hidden":false,"space_comment_unclear":false,"costs_rent_comment":"","space":"318.7","region":"","costs_rent":""}],"31":[{"costs_property_comment":"","address":"","space_units":"м²","space_unclear":false,"region_hidden":true,"costs_property":"","space_comment":"У спільній сумісній власності","address_hidden":false,"costs_rent_comment":"","space":"120","region":"","costs_rent":""},{"costs_property_comment":"","address":"","space_units":"м²","costs_rent_comment":"","space":"120","space_unclear":false,"region_hidden":true,"costs_property":"","space_comment":"мансарда у спільній сумісній власності","region":"","costs_rent":""}],"33":[{"costs_property_comment":"","address":"","space_units":"м²","space_hidden":false,"space_comment":"у спільній сумісній власності","region_hidden":true,"costs_property":"","region":"","address_hidden":false,"costs_rent_comment":"","space":"16.8","costs_rent":""}]},"source":"VULYK","income":{"5":{"family_comment":"","family":"","comment":"","comment_hidden":false,"value":"263437.77","family_comment_hidden":false},"6":{"family_comment":"","family":"","comment":"","comment_hidden":false,"family_hidden":false,"family_unclear":false,"family_comment_hidden":false,"value":"193768.75"},"7":{"source_name_hidden":false,"family_comment":"","comment":"","family":"","comment_hidden":false,"value":"","family_comment_hidden":false,"source_name":""},"8":{"family_comment":"","value":"","family":"","comment":""},"9":{"family_comment":"","comment":"","family":"","value_unclear":false,"family_unclear":false,"comment_unclear":false,"value":"32.85"},"10":{"family_comment":"","value":"12617","family_unclear":false,"family":"","comment":""},"11":{"family_comment":"","value":"","family":"","comment":""},"12":{"family_comment":"","value":"","family":"","comment":""},"13":{"family_comment":"","value":"","family":"","comment":""},"14":{"family_comment":"","value":"","family":"","comment":""},"15":{"family_comment":"","comment_unclear":false,"value":"57019.17","family":"","comment":""},"16":{"family_comment":"","comment_unclear":false,"value":"","family":"","comment":""},"17":{"family_comment":"","value":"","family":"","comment":""},"18":{"family_comment":"","value":"","family":"","comment":""},"19":{"family_comment":"","value":"","family":"","comment":""},"20":{"family_comment":"","family":"","comment":"","value_unclear":false,"family_unclear":false,"value":"","family_comment_hidden":false,"family_comment_unclear":false}},"general":{"family_raw":"","name":"Оксана","full_name_suggest":{"input":["Зварич Оксана Володимирівна","Оксана Володимирівна Зварич","Оксана Зварич"],"output":"Зварич Оксана Володимирівна"},"name_unclear":false,"patronymic":"Володимирівна","inn_hidden":true,"inn":"","addresses":[{"place_city_type_hidden":true,"place_city_type":"","place_city_hidden":true,"place_hidden":true,"place_district":"","place_district_hidden":true,"place":"","place_city":"","place_address_hidden":true,"place_address":""}],"last_name":"Зварич","full_name":"Зварич Оксана Володимирівна","family":[{"inn":"","inn_unclear":false,"family_name":"Зварич Ігор Степанович","relations_hidden":false,"name_unclear":false,"relations":"Подружжя","inn_hidden":true,"name_hidden":false,"relations_other":""},{"inn":"","inn_unclear":false,"family_name":"Зварич Іванна Ігорівна","relations_other":"","name_unclear":false,"inn_hidden":true,"name_hidden":false,"relations":"Дитина"}],"post":{"post_hidden":false,"office":"Апеляційний господарський суд","post":"суддя львівського апеляційного господарського суду","region":"Львівська область","region_hidden":false,"office_unclear":false,"office_hidden":false,"post_unclear":false,"region_unclear":false},"last_name_unclear":false},"liabilities":{"54":{"sum_comment_unclear":false,"sum_comment":"","sum_hidden":false,"sum":"","sum_foreign_comment":"","sum_foreign":"","sum_unclear":false,"sum_foreign_hidden":false,"sum_comment_hidden":false},"55":{"sum_comment":"","sum_foreign_comment":"","sum_foreign":"","sum":"","sum_comment_hidden":false},"56":{"sum_comment":"","sum_comment_unclear":false,"sum_foreign_comment":"","sum":"14653","sum_foreign":""},"57":{"sum_comment":"","sum_hidden":false,"sum":"","sum_foreign_comment":"","sum_foreign":"","sum_unclear":false,"sum_comment_hidden":false},"58":{"sum_comment":"","sum_hidden":false,"sum":"","sum_foreign_comment":"","sum_foreign":"","sum_comment_hidden":false},"59":{"sum_comment_unclear":false,"sum_comment":"","sum":"","sum_foreign_comment":"","sum_foreign":"","sum_unclear":false},"60":{"sum_comment":"","sum_hidden":false,"sum":"","sum_foreign_comment":"","sum_foreign":"","sum_unclear":false,"sum_comment_hidden":false},"61":{"sum_comment":"","sum_foreign_comment":"","sum_foreign":"","sum":""},"62":{"sum_comment":"","sum_foreign_comment":"","sum_foreign":"","sum":"14653"},"63":{"sum_comment":"","sum_hidden":false,"sum":"","sum_foreign_comment":"","sum_foreign":"","sum_comment_hidden":false},"64":{"sum_comment":"","sum_foreign_comment":"","sum_foreign":"","sum":""}},"declaration":{"notfull_lostpages":"","additional_info_text":"","additional_info":"","date":"2014-03-31T00:00:00","notfull":"","url":"http://static.declarations.com.ua/declarations/chosen_ones/judges_batch/1131_zvarych_oksana_volodymyrivna.pdf"},"intro":{"declaration_year":"2013"}}