{"income":{"5":{"value":"235850.6","value_unclear":false,"comment_hidden":false,"family_comment":"","family":"18400","comment":""},"6":{"family_comment":"","value":"223670.6","family":"8200","comment":"","value_hidden":false},"7":{"family_comment":"","value":"","source_name":"","family":"","comment":""},"8":{"family_comment":"","value":"","family":"","comment":""},"9":{"family_comment":"","value":"","comment_hidden":false,"family":"","comment":""},"10":{"family_comment":"","value":"12180","family":"","comment":""},"11":{"family_comment":"","value":"","family":"","comment":""},"12":{"family_comment":"","value":"","family":"","comment":""},"13":{"family_comment":"","value":"","family":"","comment":""},"14":{"family_comment":"","value":"","family":"","comment":""},"15":{"family_comment":"","value":"","family":"10200","comment":"","family_comment_hidden":false},"16":{"family_comment":"","value":"","family":"","comment":""},"17":{"family_comment":"","value":"","family":"","comment":""},"18":{"family_comment":"","value":"","family":"","comment":"","value_hidden":false},"19":{"family_comment":"","value":"","family":"","comment":""},"20":{"family_comment":"","value":"","family":"","comment":"","family_comment_unclear":false}},"vehicle":{"40":[{"brand_info":"1690 куб. см.","sum":"","brand":"ВАЗ 21213","sum_comment":"","year":"2004","brand_info_hidden":false,"sum_rent_comment":"","sum_rent":""}]},"id":"vulyk_78_22","declaration":{"additional_info_text":"","notfull_lostpages":"","date":"2015-03-30T00:00:00","notfull":"","additional_info":"","url":"http://static.declarations.com.ua/declarations/chosen_ones/judges_batch/2089_korziuk_tetiana_petrivna.pdf"},"liabilities":{"54":{"sum_foreign_comment":"","sum":"","sum_comment":"","sum_comment_unclear":false,"sum_hidden":false,"sum_comment_hidden":false,"sum_foreign_hidden":false,"sum_foreign":""},"55":{"sum_foreign_comment":"","sum":"","sum_comment":"","sum_foreign":""},"56":{"sum_foreign_comment":"","sum":"","sum_comment":"","sum_foreign":""},"57":{"sum_foreign_comment":"","sum":"","sum_comment":"","sum_foreign":""},"58":{"sum_foreign_comment":"","sum":"","sum_comment":"","sum_unclear":false,"sum_foreign":""},"59":{"sum_foreign_comment":"","sum":"","sum_comment":"","sum_foreign":""},"60":{"sum_foreign_comment":"","sum":"","sum_comment":"","sum_comment_unclear":false,"sum_comment_hidden":false,"sum_foreign":""},"61":{"sum_foreign_comment":"","sum":"","sum_comment":"","sum_foreign":""},"62":{"sum_foreign_comment":"","sum":"","sum_foreign":"","sum_comment":"","sum_hidden":false},"63":{"sum_foreign_comment":"","sum":"","sum_comment":"","sum_foreign":"","sum_foreign_hidden":false,"sum_unclear":false},"64":{"sum_foreign_comment":"","sum":"","sum_comment":"","sum_hidden":false,"sum_foreign_hidden":false,"sum_foreign":""}},"ft_src":"1690 куб. см.\n2004\nВАЗ 21213\n1/2\nКоропський р-н, смт. Короп\n24\nЧернігівська область\nЧернігівська область\n1/2 частина\nКоропський р-н, смт. Короп\n24\n1/2\nКоропський р-н\n88.2\nЧернігівська область\n1/2 частина\nКоропський р-н, смт. Короп (господарська будівля\n40.5\nЧернігівська область\nКоропський р-н\nЧернігівська область\n24600\nКоропський р-н\n20000\nЧернігівська область\n1/2 частина\nЧернігівська область\nКоропський р-н\n88.2\nЧернігівська область\n1/2 частина господарської будівлі\nКоропський р-н\n40.5\n2014\n8200\n223670.6\n10200\n12180\n18400\n235850.6\n1690 куб. см.\n2004\nВАЗ 21213\n2014\nПодружжя\nКорзюк В. М. 26. 11. 1955\nКорзюк Тетяна Петрівна\nТетяна Петрівна Корзюк\nТетяна Корзюк\nКорзюк Тетяна Петрівна\nКорзюк Тетяна Петрівна\nТетяна\nПетрівна\nЗагальний місцевий суд\nсуддя коропського районного суду чернігівської області\nЧернігівська область\nКорзюк\nСМТ\nЧернігівська область\nКороп\nКоропський\n223670.6\n8200\n10200\n235850.6\n18400\n12180\n24\n1/2\nЧернігівська область\nКоропський р-н, смт. Короп\n1/2 частина\nКоропський р-н\nЧернігівська область\n88.2\nЧернігівська область\n40.5\n1/2 частина\nКоропський р-н, смт. Короп (господарська будівля\n24600\nЧернігівська область\nКоропський р-н\nКоропський р-н\n20000\nЧернігівська область\n24\n1/2 частина\nЧернігівська область\nКоропський р-н, смт. Короп\nЧернігівська область\n88.2\n1/2\nКоропський р-н\n40.5\n1/2 частина господарської будівлі\nКоропський р-н\nЧернігівська область\nПодружжя\nКорзюк В. М. 26. 11. 1955\nПетрівна\nКорзюк\nТетяна\nКорзюк Тетяна Петрівна\nТетяна Петрівна Корзюк\nТетяна Корзюк\nКорзюк Тетяна Петрівна\nСМТ\nЧернігівська область\nКороп\nКоропський\nЧернігівська область\nсуддя коропського районного суду чернігівської області\nЗагальний місцевий суд\nКорзюк Тетяна Петрівна","general":{"inn":"","name":"Тетяна","family":[{"inn":"","relations":"Подружжя","relations_other":"","inn_hidden":true,"family_name":"Корзюк В. М. 26. 11. 1955","name_hidden":false,"name_unclear":false}],"patronymic":"Петрівна","inn_hidden":true,"family_raw":"","last_name":"Корзюк","post":{"post_unclear":false,"post":"суддя коропського районного суду чернігівської області","post_hidden":false,"region":"Чернігівська область","region_hidden":false,"office":"Загальний місцевий суд","office_hidden":false},"full_name_suggest":{"output":"Корзюк Тетяна Петрівна","input":["Корзюк Тетяна Петрівна","Тетяна Петрівна Корзюк","Тетяна Корзюк"]},"full_name":"Корзюк Тетяна Петрівна","addresses":[{"place_district":"Коропський","place_address_hidden":true,"place_city":"Короп","place_address":"","place_district_hidden":false,"place_city_type":"СМТ","place_city_hidden":false,"place_city_type_hidden":false,"place_hidden":false,"place":"Чернігівська область"}],"last_name_unclear":false,"name_unclear":false},"source":"VULYK","estate":{"23":[{"costs_rent":"","region":"Чернігівська область","costs":"","costs_rent_comment":"","costs_comment":"","address_hidden":false,"region_hidden":false,"space_comment":"","space_units":"м²","space":"20000","address":"Коропський р-н"}],"24":[{"costs_rent":"","region":"Чернігівська область","costs":"","costs_rent_comment":"","costs_comment":"","address_hidden":false,"region_hidden":false,"space_comment":"1/2","space_units":"м²","space":"88.2","address":"Коропський р-н"}],"27":[{"space_hidden":false,"costs":"","costs_comment":"","costs_hidden":false,"address_hidden":false,"region_hidden":false,"space_comment":"1/2","space":"24","address":"Коропський р-н, смт. Короп","region":"Чернігівська область","costs_rent_comment":"","costs_rent_hidden":false,"space_comment_hidden":false,"space_units":"м²","costs_rent":""}],"28":[{"costs_rent":"","region":"Чернігівська область","costs":"","costs_rent_comment":"","costs_comment":"","address_hidden":false,"region_hidden":false,"space_comment":"1/2 частина","space_units":"м²","space":"40.5","address":"Коропський р-н, смт. Короп (господарська будівля"}],"29":[{"space_unclear":false,"address_hidden":false,"region_hidden":false,"space_comment":"","space":"24600","address":"Коропський р-н","region":"Чернігівська область","costs_property":"","costs_rent_comment":"","space_units":"м²","costs_property_comment":"","costs_rent":""}],"30":[{"space_hidden":false,"address_hidden":false,"region_hidden":false,"space_comment":"1/2 частина","space":"88.2","address":"Коропський р-н","region":"Чернігівська область","costs_property":"","costs_rent_comment":"","space_units":"м²","costs_property_comment":"","costs_rent":""}],"33":[{"costs_rent":"","region":"Чернігівська область","costs_property":"","costs_rent_comment":"","space_comment":"1/2 частина","costs_property_comment":"","space_units":"м²","space":"24","address":"Коропський р-н, смт. Короп"}],"34":[{"costs_rent":"","region":"Чернігівська область","costs_property":"","costs_rent_comment":"","address_hidden":false,"region_hidden":false,"space_comment":"1/2 частина господарської будівлі","costs_property_comment":"","space_units":"м²","space":"40.5","address":"Коропський р-н"}]},"intro":{"declaration_year":"2014"}}