{"income":{"5":{"value":"231375.96","value_unclear":false,"family_hidden":false,"family_comment":"","family":"","comment":""},"6":{"family_comment":"","value":"231375.96","value_unclear":false,"family":"","comment":""},"7":{"source_name_unclear":false,"value":"","family_comment":"","source_name":"","family":"","comment":"","source_name_hidden":false},"8":{"family_comment":"","value":"","family":"","comment":""},"9":{"family_comment":"","value":"","comment_unclear":false,"family":"","comment":""},"10":{"family_comment":"","value":"","family":"","comment":""},"11":{"family_comment":"","family_unclear":false,"value":"","family":"","comment":""},"12":{"family_comment":"","value":"","family":"","comment":""},"13":{"family_comment":"","value":"","family":"","comment":""},"14":{"family_comment":"","value":"","family":"","comment":""},"15":{"family_comment":"","value":"","family":"","comment":""},"16":{"family_comment":"","value":"","family":"","comment":""},"17":{"family_comment":"","value":"","family":"","comment":""},"18":{"family_comment":"","value":"","family":"","comment":""},"19":{"family_comment":"","value":"","family":"","comment":""},"20":{"value":"","value_unclear":false,"family_comment":"","comment_unclear":false,"comment":"","family":""}},"id":"vulyk_94_171","declaration":{"additional_info_text":"","notfull_lostpages":"","date":"2015-02-19T00:00:00","notfull":"","additional_info":"","url":"http://static.declarations.com.ua/declarations/chosen_ones/judges_batch/3817_tordiia_eteri_nuhzarivna.pdf"},"liabilities":{"54":{"sum_foreign_comment":"","sum":"","sum_comment":"","sum_comment_unclear":false,"sum_comment_hidden":false,"sum_unclear":false,"sum_foreign":""},"55":{"sum_foreign_comment":"","sum":"","sum_comment":"","sum_foreign":""},"56":{"sum_foreign_comment":"","sum":"","sum_comment":"","sum_unclear":false,"sum_foreign":""},"57":{"sum_foreign_comment":"","sum":"14605.46","sum_comment":"","sum_hidden":false,"sum_unclear":false,"sum_foreign":""},"58":{"sum_foreign_comment":"","sum":"","sum_comment":"","sum_hidden":false,"sum_unclear":false,"sum_foreign":""},"59":{"sum_foreign_comment":"","sum":"","sum_comment":"","sum_foreign":""},"60":{"sum_foreign_comment":"","sum_comment_hidden":false,"sum":"","sum_comment":"","sum_foreign":""},"61":{"sum_foreign_comment":"","sum":"","sum_comment":"","sum_foreign":""},"62":{"sum_foreign_comment":"","sum":"","sum_hidden":false,"sum_comment":"","sum_foreign":""},"63":{"sum_foreign_comment":"","sum_comment_hidden":false,"sum":"","sum_comment":"","sum_foreign":""},"64":{"sum_foreign_comment":"","sum":"","sum_comment":"","sum_unclear":false,"sum_foreign":""}},"ft_src":"14605.46\nсуддя шевченківського районного суду харківської області\nХарківська область\nЗагальний місцевий суд\nЕтері\nТордія Діана\nДитина\nНугзарівна\nТордія Етері Нугзарівна\nЕтері Нугзарівна Тордія\nЕтері Тордія\nТордія Етері Нугзарівна\nТордія Етері Нугзарівна\nТордія\n231375.96\n231375.96\nсоток\n10\n34\n43\n68\n2014\n231375.96\n231375.96\n10\nсоток\n43\n34\n68\nТордія Етері Нугзарівна\nЕтері Нугзарівна Тордія\nЕтері Тордія\nТордія Етері Нугзарівна\nТордія Етері Нугзарівна\nДитина\nТордія Діана\nЕтері\nТордія\nЗагальний місцевий суд\nХарківська область\nсуддя шевченківського районного суду харківської області\nНугзарівна\n14605.46\n231375.96\n231375.96\n2014\n14605.46\nТордія Діана\nДитина\nНугзарівна\nТордія\nЕтері\nТордія Етері Нугзарівна\nЕтері Нугзарівна Тордія\nЕтері Тордія\nТордія Етері Нугзарівна\nХарківська область\nЗагальний місцевий суд\nсуддя шевченківського районного суду харківської області\nТордія Етері Нугзарівна\n34\nсоток\n10\n43\n68\n2014","general":{"inn":"","name":"Етері","last_name":"Тордія","family":[{"inn":"","relations":"Дитина","relations_hidden":false,"inn_hidden":true,"family_name":"Тордія Діана","name_hidden":false,"name_unclear":false}],"inn_hidden":true,"family_raw":"","inn_unclear":false,"post":{"post_unclear":false,"region_unclear":false,"post":"суддя шевченківського районного суду харківської області","candidate":"","post_hidden":false,"region":"Харківська область","office":"Загальний місцевий суд","office_unclear":false},"full_name":"Тордія Етері Нугзарівна","addresses":[{"place_district":"","place_city_hidden":false,"place_city":"","place_city_type_hidden":false,"place_district_hidden":false,"place_city_type":"","place_address_hidden":false,"place_address":"","place_hidden":true,"place":""}],"patronymic":"Нугзарівна","patronymic_hidden":false,"full_name_suggest":{"output":"Тордія Етері Нугзарівна","input":["Тордія Етері Нугзарівна","Етері Нугзарівна Тордія","Етері Тордія"]}},"source":"VULYK","estate":{"23":[{"region_unclear":false,"space_unclear":true,"costs":"","costs_comment":"","address_hidden":false,"region_hidden":true,"space_comment":"","space_hidden":false,"space":"10","address":"","region":"","address_unclear":false,"space_units_unclear":true,"costs_rent_hidden":false,"costs_rent_comment_hidden":false,"space_units":"соток","costs_rent":"","costs_rent_comment":""}],"25":[{"region_unclear":false,"space_unclear":false,"costs":"","costs_comment":"","address_hidden":false,"region_hidden":true,"space_comment":"","space_hidden":false,"space":"68","address":"","region":"","address_unclear":false,"costs_rent_comment":"","costs_rent_hidden":false,"space_comment_unclear":false,"costs_rent_comment_hidden":false,"space_units":"м²","costs_rent":""}],"26":[{"costs_rent":"","region":"","costs":"","costs_rent_comment":"","costs_comment":"","address_hidden":false,"region_hidden":true,"space_comment":"","space_units":"м²","space":"43","address":""}],"31":[{"space_unclear":false,"costs_property_hidden":false,"address_hidden":true,"region_hidden":true,"space_comment":"","space_hidden":false,"space":"34","address":"","costs_property_comment_hidden":false,"region":"","costs_property":"","costs_rent_comment":"","costs_rent_hidden":false,"space_comment_unclear":false,"costs_rent_comment_hidden":false,"space_units":"м²","costs_property_comment":"","costs_rent":""}]},"intro":{"declaration_year":"2014","isnotdeclaration":""}}