{"income":{"5":{"value":"164742","family_comment":"","value_unclear":false,"family_unclear":false,"family":"","comment":""},"6":{"family_comment":"","value":"164742","value_unclear":false,"family":"","comment":""},"7":{"family_comment":"","value":"","source_name":"","family":"","comment":""},"8":{"family_comment":"","value":"","family":"","comment":""},"9":{"family_comment":"","value":"","value_unclear":false,"family":"","comment":""},"10":{"family_comment":"","value":"","family":"","comment":""},"11":{"family_comment":"","value":"","family":"","comment":""},"12":{"family_comment":"","value":"","family":"","comment":""},"13":{"family_comment":"","value":"","family":"","comment":""},"14":{"family_comment":"","value":"","family":"","comment":""},"15":{"family_comment":"","value":"","family":"","comment":""},"16":{"family_comment":"","value":"","family":"","comment":""},"17":{"family_comment":"","value":"","family":"","comment":""},"18":{"family_comment":"","value":"","family":"","comment":""},"19":{"family_comment":"","value":"","family":"","comment":""},"20":{"family_comment":"","value":"","value_unclear":false,"family":"","comment":""}},"id":"vulyk_98_51","declaration":{"date":"2015-03-30T00:00:00","url":"http://static.declarations.com.ua/declarations/chosen_ones/judges_batch/4548_davydenko_iryna_viktorivna.pdf"},"liabilities":{"54":{"sum_foreign_comment":"","sum":"","sum_comment":"","sum_comment_unclear":false,"sum_hidden":false,"sum_comment_hidden":false,"sum_unclear":false,"sum_foreign":""},"55":{"sum_foreign_comment":"","sum":"","sum_comment":"","sum_foreign":""},"56":{"sum_foreign_comment":"","sum":"","sum_comment":"","sum_unclear":false,"sum_foreign":""},"57":{"sum_foreign_comment":"","sum":"","sum_comment":"","sum_comment_unclear":false,"sum_hidden":false,"sum_comment_hidden":false,"sum_unclear":false,"sum_foreign":""},"58":{"sum_foreign_comment":"","sum":"","sum_comment":"","sum_hidden":false,"sum_comment_hidden":false,"sum_unclear":false,"sum_foreign":""},"59":{"sum_foreign_comment":"","sum":"","sum_comment":"","sum_comment_unclear":false,"sum_foreign":""},"60":{"sum_foreign_comment":"","sum":"","sum_comment":"","sum_hidden":false,"sum_comment_hidden":false,"sum_foreign":""},"61":{"sum_foreign_comment":"","sum":"","sum_comment":"","sum_foreign":""},"62":{"sum_foreign_comment":"","sum":"","sum_comment":"","sum_comment_hidden":false,"sum_unclear":false,"sum_foreign":""},"63":{"sum_foreign_comment":"","sum":"","sum_comment":"","sum_comment_unclear":false,"sum_comment_hidden":false,"sum_foreign":""},"64":{"sum_foreign_comment":"","sum_comment_hidden":false,"sum":"","sum_comment":"","sum_foreign":""}},"ft_src":"суддя господарського суду запорізької області\nЗапорізька область\nГосподарський місцевий суд\nІрина\nВікторівна\nДавиденко Ірина Вікторівна\nІрина Вікторівна Давиденко\nІрина Давиденко\nДавиденко Ірина Вікторівна\nДавиденко Ірина Вікторівна\nДавиденко\n164742\n164742\n.2421\n21.87\n30.13\n34.15\n2014\n164742\n164742\n164742\n164742\nГосподарський місцевий суд\nсуддя господарського суду запорізької області\nЗапорізька область\nДавиденко Ірина Вікторівна\nІрина Вікторівна Давиденко\nІрина Давиденко\nДавиденко Ірина Вікторівна\nДавиденко Ірина Вікторівна\nІрина\nДавиденко\nВікторівна\n.2421\n21.87\n30.13\n34.15\n2014\nВікторівна\nДавиденко\nІрина\nДавиденко Ірина Вікторівна\nІрина Вікторівна Давиденко\nІрина Давиденко\nДавиденко Ірина Вікторівна\nсуддя господарського суду запорізької області\nЗапорізька область\nГосподарський місцевий суд\nДавиденко Ірина Вікторівна\n21.87\n30.13\n34.15\n.2421\n2014","general":{"inn":"","name":"Ірина","last_name_hidden":false,"last_name":"Давиденко","patronymic":"Вікторівна","inn_hidden":true,"family_raw":"","inn_unclear":false,"post":{"post_unclear":false,"office":"Господарський місцевий суд","post":"суддя господарського суду запорізької області","region":"Запорізька область"},"full_name_suggest":{"output":"Давиденко Ірина Вікторівна","input":["Давиденко Ірина Вікторівна","Ірина Вікторівна Давиденко","Ірина Давиденко"]},"full_name":"Давиденко Ірина Вікторівна","addresses":[{"place_district":"","place_city_hidden":true,"place_city":"","place_city_type_hidden":true,"place_district_hidden":true,"place_city_type":"","place_address_hidden":true,"place_address":"","place_hidden":true,"place":""}],"patronymic_hidden":false,"last_name_unclear":false},"source":"VULYK","estate":{"23":[{"space_unclear":false,"costs":"","costs_comment":"","address_hidden":true,"region_hidden":true,"space_comment":"","space":".2421","address":"","region":"","costs_rent_comment":"","space_units":"га","costs_rent":""}],"25":[{"space_unclear":false,"costs":"","costs_comment":"","address_hidden":true,"region_hidden":true,"space_comment":"","space":"21.87","address":"","region":"","address_unclear":false,"costs_rent_comment":"","space_units":"м²","costs_rent":""},{"costs_rent":"","region":"","costs":"","costs_rent_comment":"","costs_comment":"","space_comment":"","space_units":"м²","space":"30.13","address":""},{"costs_rent":"","region":"","costs":"","costs_rent_comment":"","costs_comment":"","space_comment":"","space_units":"м²","space":"34.15","address":""}]},"intro":{"declaration_year":"2014"}}