{"id":"vulyk_77_59","ft_src":"2003\nVolkswagen Passat\n1781 куб. см.\n2014\n19423.6\n63648.4\n2449.03\n21872.63\n63648.4\n1781 куб. см.\n2003\nVolkswagen Passat\n2014\nКрамар Сергій Іванович\nСергій Іванович Крамар\nСергій Крамар\nКрамар Сергій Іванович\nСергій\nПодружжя\nКрамар І. В\nКрамар Сергій Іванович\nКрамар\nМіністерство внутрішніх справ\nзаступник начальника жовтневого рв умвс україни в миколаївській області - начальник кримінальної міліції\nМиколаївська область\nІванович\n63648.4\n19423.6\n2449.03\n63648.4\n21872.63\nПодружжя\nКрамар І. В\nІванович\nКрамар\nСергій\nКрамар Сергій Іванович\nСергій Іванович Крамар\nСергій Крамар\nКрамар Сергій Іванович\nзаступник начальника жовтневого рв умвс україни в миколаївській області - начальник кримінальної міліції\nМиколаївська область\nМіністерство внутрішніх справ\nКрамар Сергій Іванович","vehicle":{"40":[{"sum_comment":"","brand_info":"1781 куб. см.","sum":"","sum_rent_comment":"","brand_hidden":false,"brand":"Volkswagen Passat","sum_rent":"","year_hidden":false,"year":"2003"}]},"source":"VULYK","income":{"5":{"family":"21872.63","family_comment":"","comment":"","value_hidden":false,"value":"63648.4","family_hidden":false,"family_unclear":false},"6":{"family":"19423.6","family_comment":"","comment":"","value_hidden":false,"value_unclear":false,"comment_hidden":false,"family_hidden":false,"value":"63648.4","family_comment_hidden":false},"7":{"source_name_hidden":false,"family_comment":"","comment":"","family":"","source_name_unclear":false,"value":"","source_name":""},"8":{"family_comment":"","value":"","family":"","comment":"","comment_hidden":false},"9":{"family":"","family_comment":"","comment":"","value_hidden":false,"family_hidden":false,"value":""},"10":{"family":"","family_comment":"","comment":"","value_hidden":false,"comment_hidden":false,"family_hidden":false,"value":"","family_comment_hidden":false},"11":{"family_comment":"","family_hidden":false,"value":"","family":"","comment":""},"12":{"family_comment":"","family_hidden":false,"value":"","family":"","comment":""},"13":{"family_comment":"","value":"","family":"","comment":""},"14":{"family_comment":"","value":"","family":"","comment":""},"15":{"family_comment":"","family":"2449.03","comment":"","comment_hidden":false,"value":"","family_comment_hidden":false},"16":{"family_comment":"","value":"","family_unclear":false,"family":"","comment":""},"17":{"family_comment":"","value":"","family":"","comment":""},"18":{"family_comment":"","value":"","family":"","comment":""},"19":{"family_comment":"","value":"","family":"","comment":""},"20":{"family_comment":"","comment":"","family":"","family_unclear":false,"comment_unclear":false,"value":"","family_hidden":false}},"general":{"family_raw":"","name":"Сергій","full_name_suggest":{"input":["Крамар Сергій Іванович","Сергій Іванович Крамар","Сергій Крамар"],"output":"Крамар Сергій Іванович"},"patronymic":"Іванович","inn_hidden":false,"addresses":[{"place_city_type_hidden":false,"place_district_hidden":false,"place_address_unclear":false,"place":"","place_city":"","place_unclear":false,"place_city_type":"","place_city_hidden":false,"place_city_unclear":false,"place_district":"","place_district_unclear":false,"place_address":"","place_address_hidden":true,"place_hidden":true}],"inn":"","inn_unclear":false,"last_name":"Крамар","full_name":"Крамар Сергій Іванович","family":[{"inn":"","inn_unclear":false,"family_name":"Крамар І. В","relations_hidden":false,"name_unclear":false,"relations":"Подружжя","inn_hidden":false,"name_hidden":false,"relations_other":""}],"post":{"office":"Міністерство внутрішніх справ","region":"Миколаївська область","post":"заступник начальника жовтневого рв умвс україни в миколаївській області - начальник кримінальної міліції"},"last_name_unclear":false},"liabilities":{"54":{"sum_comment":"","sum_comment_unclear":false,"sum_foreign_comment":"","sum":"","sum_foreign":""},"55":{"sum_comment":"","sum_foreign_comment":"","sum_foreign":"","sum":""},"56":{"sum_comment":"","sum_foreign_comment":"","sum_foreign":"","sum_unclear":false,"sum":""},"57":{"sum_comment":"","sum_foreign_comment":"","sum_foreign":"","sum":""},"58":{"sum_comment":"","sum_foreign_comment":"","sum_foreign":"","sum":""},"59":{"sum_comment":"","sum_foreign_comment":"","sum_foreign":"","sum":""},"60":{"sum_comment":"","sum_foreign_comment":"","sum_foreign":"","sum":""},"61":{"sum_comment":"","sum_foreign_comment":"","sum_foreign":"","sum":""},"62":{"sum_comment":"","sum_foreign_comment":"","sum_foreign":"","sum_hidden":false,"sum":""},"63":{"sum_comment":"","sum_foreign_comment":"","sum_foreign":"","sum":""},"64":{"sum_comment":"","sum_foreign_comment":"","sum_foreign":"","sum":""}},"declaration":{"notfull_lostpages":"","additional_info_text":"","additional_info":"","date":"2015-02-09T00:00:00","notfull":"","url":"http://static.declarations.com.ua/declarations/chosen_ones/judges_batch/1993_kramar_serhii_ivanovych.pdf"},"intro":{"isnotdeclaration":"","declaration_year_unclear":false,"declaration_year":"2014"}}