{"income":{"5":{"value":"300246","family_comment":"","comment_unclear":false,"family_unclear":false,"family":"20227","comment":""},"6":{"family_comment":"","value":"273633","family":"20227","comment":""},"7":{"source_name_unclear":false,"value":"","comment_unclear":false,"family_comment":"","source_name":"","family":"","comment":""},"8":{"family_comment":"","value":"","family":"","comment":""},"9":{"family_comment":"","value":"20329","family":"","comment":""},"10":{"family_comment":"","value":"","family":"","comment":""},"11":{"family_comment":"","value":"","family":"","comment":""},"12":{"family_comment":"","value":"","family":"","comment":""},"13":{"family_comment":"","value":"","family":"","comment":""},"14":{"family_comment":"","value":"","family":"","comment":""},"15":{"family_comment":"","value":"","family":"","comment":""},"16":{"family_comment":"","family_unclear":false,"value":"","family":"","comment":""},"17":{"family_comment":"","value":"","family":"","comment":""},"18":{"family_comment":"","value":"","family":"","comment":""},"19":{"family_comment":"","value":"4455","family":"","comment":""},"20":{"value":"1629","family_comment":"","comment_unclear":false,"family_unclear":false,"family":"","comment":"","family_comment_unclear":false}},"id":"vulyk_107_66","banks":{"45":[{"sum_foreign_comment":"","sum_units":"UAH","sum_comment":"","sum_comment_unclear":false,"sum_foreign_units":"UAH","sum_comment_hidden":false,"sum_unclear":false,"sum":"101290","sum_foreign":""}]},"declaration":{"additional_info_text":"","notfull_lostpages":"","date":"2016-03-29T00:00:00","notfull":"","additional_info":"","url":"http://static.declarations.com.ua/declarations/chosen_ones/judges_batch/2045_demchenko_mykola_oleksandrovych.pdf"},"liabilities":{"54":{"sum_foreign_comment":"","sum":"","sum_comment":"","sum_comment_unclear":false,"sum_comment_hidden":false,"sum_foreign":""},"55":{"sum_foreign_comment":"","sum":"","sum_comment":"","sum_foreign":""},"56":{"sum_foreign_comment":"","sum":"","sum_comment":"","sum_unclear":false,"sum_foreign":""},"57":{"sum_foreign_comment":"","sum":"","sum_comment":"","sum_comment_unclear":false,"sum_foreign":""},"58":{"sum_foreign_comment":"","sum":"","sum_comment":"","sum_comment_unclear":false,"sum_unclear":false,"sum_foreign":""},"59":{"sum_foreign_comment":"","sum":"","sum_comment":"","sum_unclear":false,"sum_foreign":""},"60":{"sum_foreign_comment":"","sum":"","sum_comment":"","sum_comment_unclear":false,"sum_comment_hidden":false,"sum_foreign":""},"61":{"sum_foreign_comment":"","sum":"","sum_comment":"","sum_foreign":""},"62":{"sum_foreign_comment":"","sum":"","sum_comment":"","sum_foreign":""},"63":{"sum_foreign_comment":"","sum":"","sum_comment":"","sum_foreign":""},"64":{"sum_foreign_comment":"","sum":"","sum_comment":"","sum_foreign":""}},"ft_src":"Демченко Микола Олександрович\nсуддя апеляційного суду сумської області\nСумська область\nЗагальний апеляційний суд\nМикола\nДемченко (Баштова) Л. О\nПодружжя\nДемченко Д. М\nДитина\nДемченко Т. М\nДитина\nДемченко Микола Олександрович\nМикола Олександрович Демченко\nМикола Демченко\nДемченко Микола Олександрович\nДемченко\nОлександрович\n4455\n20329\n1629\n300246\n20227\n20227\n273633\n101290\n3446\n0.1842\n0.1444\n65.4\n87.6\n68.09\n2015\n20227\n273633\n20329\n20227\n300246\n4455\n1629\n101290\n2015\nДемченко\nПодружжя\nДемченко (Баштова) Л. О\nДитина\nДемченко Д. М\nДитина\nДемченко Т. М\nДемченко Микола Олександрович\nМикола Олександрович Демченко\nМикола Демченко\nДемченко Микола Олександрович\nМикола\nОлександрович\nДемченко Микола Олександрович\nЗагальний апеляційний суд\nсуддя апеляційного суду сумської області\nСумська область\n273633\n20227\n1629\n300246\n20227\n20329\n4455\n3446\n0.1842\n0.1444\n87.6\n65.4\n68.09\nДемченко (Баштова) Л. О\nПодружжя\nДемченко Д. М\nДитина\nДемченко Т. М\nДитина\nДемченко\nОлександрович\nсуддя апеляційного суду сумської області\nСумська область\nЗагальний апеляційний суд\nДемченко Микола Олександрович\nДемченко Микола Олександрович\nМикола Олександрович Демченко\nМикола Демченко\nДемченко Микола Олександрович\nМикола\n65.4\n3446\n0.1842\n0.1444\n87.6\n68.09\n101290\n2015","general":{"inn":"","inn_hidden":true,"last_name":"Демченко","post":{"post_unclear":false,"office":"Загальний апеляційний суд","post":"суддя апеляційного суду сумської області","region":"Сумська область"},"name":"Микола","full_name":"Демченко Микола Олександрович","family_raw":"","addresses":[{"place_district":"","place_city_hidden":true,"place_city":"","place_city_type_hidden":false,"place_district_hidden":true,"place_city_type":"","place_address_hidden":true,"place_address":"","place_hidden":true,"place":""}],"family":[{"inn":"","relations":"Подружжя","relations_other":"","inn_hidden":true,"family_name":"Демченко (Баштова) Л. О","name_hidden":true,"name_unclear":false},{"inn":"","relations":"Дитина","relations_other":"","inn_hidden":false,"family_name":"Демченко Д. М","name_hidden":false,"name_unclear":false},{"inn":"","relations":"Дитина","relations_other":"","inn_hidden":false,"family_name":"Демченко Т. М","name_hidden":false,"name_unclear":false}],"full_name_suggest":{"output":"Демченко Микола Олександрович","input":["Демченко Микола Олександрович","Микола Олександрович Демченко","Микола Демченко"]},"patronymic":"Олександрович"},"source":"VULYK","estate":{"23":[{"costs":"","costs_comment":"","address_hidden":true,"region_hidden":true,"space_comment":"","space":"3446","address":"","region":"","costs_rent_comment":"","space_comment_unclear":false,"space_comment_hidden":false,"space_units":"м²","costs_rent":""},{"costs_rent":"","region":"","costs":"","costs_rent_comment":"","costs_comment":"","address_hidden":false,"region_hidden":false,"space_comment":"","space_units":"га","space":"0.1842","address":""},{"costs_rent":"","region":"","costs":"","costs_rent_comment":"","costs_comment":"","space_comment":"","space_units":"га","space":"0.1444","address":""}],"24":[{"space_hidden":false,"costs":"","costs_comment":"","address_hidden":true,"region_hidden":true,"space_comment":"","space":"87.6","address":"","region":"","costs_rent_comment":"","space_units":"м²","costs_rent":""}],"25":[{"space_hidden":false,"costs":"","costs_comment":"","address_hidden":true,"region_hidden":true,"space_comment":"","space_unclear":false,"space":"68.09","address":"","region":"","costs_rent_comment":"","space_units":"м²","costs_rent":""}],"31":[{"space_unclear":false,"address_hidden":true,"region_hidden":true,"space_comment":"","space_hidden":false,"space":"65.4","address":"","region":"","costs_property":"","costs_rent_comment":"","space_comment_unclear":false,"space_units":"м²","costs_property_comment":"","costs_rent":""}]},"intro":{"declaration_year":"2015","isnotdeclaration":""}}