{"income":{"5":{"family_comment":"","value":"267077.89","family":"","comment":""},"6":{"family_comment":"","value":"246850.76","family":"","comment":""},"7":{"family_comment":"","value":"","source_name":"","family":"","comment":""},"8":{"family_comment":"","value":"","family":"","comment":""},"9":{"value":"","comment_unclear":false,"family_comment":"","family":"","comment":"","family_comment_unclear":false},"10":{"family_comment":"","value":"13398","family":"","comment":""},"11":{"family_comment":"","value":"","family":"","comment":""},"12":{"family_comment":"","value":"","family":"","comment":""},"13":{"family_comment":"","value":"","family":"","comment":""},"14":{"family_comment":"","value":"","family":"","comment":""},"15":{"family_comment":"","value":"859.13","family":"","comment":""},"16":{"family_comment":"","value":"","family":"","comment":""},"17":{"family_comment":"","value":"","family":"","comment":""},"18":{"family_comment":"","value":"","family":"","comment":""},"19":{"value":"","family_comment":"","value_unclear":false,"family_unclear":false,"family":"","comment":""},"20":{"value":"5970","family_comment":"","value_unclear":false,"comment_hidden":false,"family_comment_hidden":false,"family_unclear":false,"family_comment_unclear":false,"comment_unclear":false,"comment":"військова пенсія","family":""}},"vehicle":{"35":[{"brand_info":"2496 куб. см.,керує за довіреністю","sum_rent_comment":"","brand":"Nissan Teana","sum_comment":"","year":"2010","sum_hidden":false,"brand_info_hidden":false,"brand_info_unclear":false,"year_unclear":false,"sum":"","sum_rent":""}]},"id":"vulyk_106_52","declaration":{"additional_info_text":"","notfull_lostpages":"","date":"2016-03-29T00:00:00","notfull":"","additional_info":"","url":"http://static.declarations.com.ua/declarations/chosen_ones/judges_batch/2191_plotnitskyi_borys_dmytrovych.pdf"},"liabilities":{"54":{"sum_foreign_comment":"","sum":"22220","sum_comment":"","sum_comment_unclear":false,"sum_hidden":false,"sum_comment_hidden":false,"sum_foreign":""},"55":{"sum_foreign_comment":"","sum":"","sum_hidden":false,"sum_comment":"","sum_foreign":""},"56":{"sum_foreign_comment":"","sum":"11448.18","sum_comment":"","sum_hidden":false,"sum_comment_hidden":false,"sum_unclear":false,"sum_foreign":""},"57":{"sum_foreign_comment":"","sum":"","sum_comment":"","sum_hidden":false,"sum_comment_hidden":false,"sum_foreign":""},"58":{"sum_foreign_comment":"","sum":"","sum_comment":"","sum_hidden":false,"sum_comment_hidden":false,"sum_foreign":""},"59":{"sum_foreign_comment":"","sum":"","sum_comment":"","sum_foreign":""},"60":{"sum_foreign_comment":"","sum":"","sum_comment":"","sum_hidden":false,"sum_comment_hidden":false,"sum_foreign":""},"61":{"sum_foreign_comment":"","sum":"","sum_comment":"","sum_foreign":""},"62":{"sum_foreign_comment":"","sum":"","sum_comment":"","sum_comment_hidden":false,"sum_unclear":false,"sum_foreign":""},"63":{"sum_foreign_comment":"","sum":"","sum_comment":"","sum_foreign":""},"64":{"sum_foreign_comment":"","sum":"","sum_comment":"","sum_foreign":""}},"ft_src":"22220\n11448.18\nголова львівського апеляційного господарського суду\nЛьвівська область\nАпеляційний господарський суд\nБорис\nПлотніцька І. А\nПодружжя\nДмитрович\nПлотніцький Борис Дмитрович\nБорис Дмитрович Плотніцький\nБорис Плотніцький\nПлотніцький Борис Дмитрович\nПлотніцький Борис Дмитрович\nПлотніцький\nNissan Teana\n2496 куб. см.,керує за довіреністю\n2010\n1453\nпай спадщина\n7044\n40.6\n1000\n188.3\n13.7\n112.8\n49\n30\n2015\n246850.76\n859.13\n13398\n267077.89\nвійськова пенсія\n5970\n2496 куб. см.,керує за довіреністю\n2010\nNissan Teana\n188.3\n30\n40.6\n1000\n1453\n7044\nпай спадщина\n112.8\n49\n13.7\nПлотніцький Борис Дмитрович\nБорис Дмитрович Плотніцький\nБорис Плотніцький\nПлотніцький Борис Дмитрович\nПлотніцький Борис Дмитрович\nПодружжя\nПлотніцька І. А\nБорис\nПлотніцький\nЛьвівська область\nАпеляційний господарський суд\nголова львівського апеляційного господарського суду\nДмитрович\n22220\n11448.18\n246850.76\n5970\nвійськова пенсія\n859.13\n267077.89\n13398\n2015\n22220\n11448.18\nПлотніцька І. А\nПодружжя\nДмитрович\nПлотніцький\nБорис\nПлотніцький Борис Дмитрович\nБорис Дмитрович Плотніцький\nБорис Плотніцький\nПлотніцький Борис Дмитрович\nЛьвівська область\nАпеляційний господарський суд\nголова львівського апеляційного господарського суду\nПлотніцький Борис Дмитрович\n2010\nNissan Teana\n2496 куб. см.,керує за довіреністю\n859.13\n13398\n5970\nвійськова пенсія\n267077.89\n246850.76\n112.8\n49\n1000\n13.7\n188.3\n40.6\n30\n1453\nпай спадщина\n7044\n2015","general":{"inn":"","name":"Борис","inn_unclear":false,"family":[{"inn":"","inn_hidden":false,"relations_unclear":false,"relations_hidden":false,"relations_other":"","relations":"Подружжя","name_hidden":false,"family_name":"Плотніцька І. А","name_unclear":false}],"inn_hidden":true,"family_raw":"","last_name":"Плотніцький","post":{"region_unclear":false,"region":"Львівська область","post":"голова львівського апеляційного господарського суду","office":"Апеляційний господарський суд","office_unclear":false,"post_hidden":false},"full_name":"Плотніцький Борис Дмитрович","addresses":[{"place_district":"","place_city_hidden":false,"place_city":"","place_city_type_hidden":false,"place_district_hidden":false,"place_city_type":"","place_address_hidden":false,"place_address":"","place_hidden":true,"place":""}],"patronymic":"Дмитрович","full_name_suggest":{"output":"Плотніцький Борис Дмитрович","input":["Плотніцький Борис Дмитрович","Борис Дмитрович Плотніцький","Борис Плотніцький"]},"name_unclear":false},"source":"VULYK","estate":{"23":[{"region_unclear":false,"space_hidden":false,"costs":"","costs_comment":"","address_hidden":false,"region_hidden":true,"space_comment":"","space_unclear":false,"space":"1000","address":"","costs_comment_unclear":false,"costs_rent_comment_unclear":false,"region":"","address_unclear":false,"costs_rent_comment":"","space_comment_unclear":false,"space_comment_hidden":false,"space_units":"м²","costs_rent":""}],"25":[{"costs":"","costs_comment":"","address_hidden":false,"region_hidden":true,"space_comment":"","space":"30","address":"","region":"","costs_rent_comment":"","space_comment_unclear":false,"space_units":"м²","costs_rent":""}],"29":[{"region_unclear":false,"costs_property_comment":"","address_hidden":true,"region_hidden":true,"space_comment":"","space":"1453","address":"","costs_rent_comment_unclear":false,"region":"","costs_property":"","costs_rent_comment":"","space_comment_unclear":false,"address_unclear":false,"space_units":"м²","space_units_unclear":false,"costs_rent":""},{"costs_rent":"","region":"","costs_property":"","costs_rent_comment":"","address_hidden":true,"region_hidden":false,"space_comment":"пай спадщина","costs_property_comment":"","space_units":"м²","space":"7044","address":""}],"30":[{"space_unclear":false,"address_hidden":false,"region_hidden":true,"space_comment":"","space_hidden":false,"space":"188.3","address":"","region":"","costs_property":"","costs_rent_comment":"","space_comment_unclear":false,"space_units":"м²","costs_property_comment":"","costs_rent":""}],"31":[{"space_unclear":false,"address_hidden":true,"region_hidden":false,"space_comment":"","space_hidden":false,"space":"112.8","address":"","region":"","costs_property":"","costs_rent_comment":"","space_comment_unclear":false,"space_units":"м²","costs_property_comment":"","costs_rent":""},{"costs_rent":"","region":"","costs_property":"","costs_rent_comment":"","space_comment_unclear":false,"region_hidden":false,"space_comment":"","costs_property_comment":"","space_units":"м²","space":"49","address":""}],"33":[{"space_hidden":false,"address_hidden":true,"region_hidden":true,"space_comment":"","space":"40.6","address":"","region":"","costs_property":"","costs_rent_comment":"","space_comment_unclear":false,"space_units":"м²","costs_property_comment":"","costs_rent":""}],"34":[{"costs_rent":"","costs_property":"","costs_rent_comment":"","address_hidden":true,"region_hidden":true,"space_comment":"","costs_property_comment":"","space_units":"м²","space":"13.7","address":""}]},"intro":{"declaration_year":"2015","isnotdeclaration":""}}