{"income":{"5":{"family_comment":"","value":"270481","family":"","comment":""},"6":{"family_comment":"","value":"257925","family":"","comment":""},"7":{"family_comment":"","value":"406","source_name":"ДРВ НШСУ","family":"","comment":""},"8":{"family_comment":"","value":"","family":"","comment":""},"9":{"value":"","comment_unclear":false,"family_comment":"","family":"","comment":"","family_comment_unclear":false},"10":{"family_comment":"","value":"","family":"","comment":""},"11":{"family_comment":"","value":"","family":"","comment":""},"12":{"family_comment":"","value":"","family":"","comment":""},"13":{"family_comment":"","value":"","family":"","comment":""},"14":{"family_comment":"","value":"","family":"","comment":""},"15":{"family_comment":"","value":"","family":"","comment":""},"16":{"family_comment":"","value":"","family":"","comment":""},"17":{"family_comment":"","value":"","family":"","comment":""},"18":{"family_comment":"","value":"","family":"","comment":""},"19":{"value":"","family_comment":"","value_unclear":false,"family_unclear":false,"family":"","comment":""},"20":{"value":"12150","family_comment":"","comment_unclear":false,"comment_hidden":false,"family_unclear":false,"value_unclear":false,"family_comment_unclear":false,"family_comment_hidden":false,"comment":"","family":""}},"vehicle":{"35":[{"brand_info":"1.7","sum":"","brand":"Mitsubishi ASX","sum_comment":"","year":"2012","sum_hidden":false,"brand_info_hidden":false,"brand_info_unclear":false,"year_unclear":false,"sum_rent_comment":"","sum_rent":""}]},"id":"vulyk_106_119","declaration":{"additional_info_text":"","notfull_lostpages":"","date":"2016-03-30T00:00:00","notfull":"","additional_info":"","url":"http://static.declarations.com.ua/declarations/chosen_ones/judges_batch/2258_olefirenko_nataliia_anatoliivna.pdf"},"liabilities":{"54":{"sum_foreign_comment":"","sum":"","sum_comment":"","sum_comment_unclear":false,"sum_hidden":false,"sum_comment_hidden":false,"sum_foreign":""},"55":{"sum_foreign_comment":"","sum":"","sum_foreign":"","sum_comment":"","sum_hidden":false},"56":{"sum_foreign_comment":"","sum":"","sum_comment":"","sum_hidden":false,"sum_comment_hidden":false,"sum_unclear":false,"sum_foreign":""},"57":{"sum_foreign_comment":"","sum":"","sum_comment":"","sum_hidden":false,"sum_comment_hidden":false,"sum_foreign":""},"58":{"sum_foreign_comment":"","sum":"42541","sum_comment":"","sum_hidden":false,"sum_comment_hidden":false,"sum_foreign":""},"59":{"sum_foreign_comment":"","sum":"","sum_comment":"","sum_foreign":""},"60":{"sum_foreign_comment":"","sum":"","sum_comment":"","sum_hidden":false,"sum_comment_hidden":false,"sum_foreign":""},"61":{"sum_foreign_comment":"","sum":"","sum_comment":"","sum_foreign":""},"62":{"sum_foreign_comment":"","sum":"","sum_comment":"","sum_comment_hidden":false,"sum_unclear":false,"sum_foreign":""},"63":{"sum_foreign_comment":"","sum":"","sum_comment":"","sum_foreign":""},"64":{"sum_foreign_comment":"","sum":"","sum_comment":"","sum_foreign":""}},"ft_src":"Mitsubishi ASX\n1.7\n2012\n54.75\n2015\n257925\n406\nДРВ НШСУ\n270481\n12150\n1.7\n2012\nMitsubishi ASX\n54.75\nОлефіренко Наталія Анатоліївна\nНаталія Анатоліївна Олефіренко\nНаталія Олефіренко\nОлефіренко Наталія Анатоліївна\nОлефіренко Наталія Анатоліївна\nДитина\nОлефіренко Є. Я\nДитина\nБєляєва М. А\nНаталія\nОлефіренко\nДніпропетровська область\nАпеляційний адміністративний суд\nсуддя дніпропетровського апеляційного адміністративного суду\nАнатоліївна\n42541\n406\nДРВ НШСУ\n257925\n12150\n270481\n2015\n42541\nОлефіренко Є. Я\nДитина\nБєляєва М. А\nДитина\nАнатоліївна\nОлефіренко\nНаталія\nОлефіренко Наталія Анатоліївна\nНаталія Анатоліївна Олефіренко\nНаталія Олефіренко\nОлефіренко Наталія Анатоліївна\nДніпропетровська область\nАпеляційний адміністративний суд\nсуддя дніпропетровського апеляційного адміністративного суду\nОлефіренко Наталія Анатоліївна","general":{"inn":"","name":"Наталія","last_name":"Олефіренко","family":[{"inn":"","inn_hidden":false,"relations_unclear":false,"relations_hidden":false,"relations_other":"","relations":"Дитина","name_hidden":true,"family_name":"Олефіренко Є. Я","name_unclear":false},{"inn":"","inn_hidden":false,"relations_unclear":false,"family_name":"Бєляєва М. А","relations_other":"","relations":"Дитина","name_hidden":false,"name_unclear":false}],"inn_hidden":true,"family_raw":"","inn_unclear":false,"post":{"region_unclear":false,"post":"суддя дніпропетровського апеляційного адміністративного суду","post_hidden":false,"region":"Дніпропетровська область","office":"Апеляційний адміністративний суд","office_unclear":false},"full_name":"Олефіренко Наталія Анатоліївна","addresses":[{"place_district":"","place_address_hidden":false,"place_city":"","place_address":"","place_district_hidden":false,"place_city_type":"","place_city_hidden":false,"place_city_type_hidden":false,"place_hidden":true,"place":""}],"patronymic":"Анатоліївна","full_name_suggest":{"output":"Олефіренко Наталія Анатоліївна","input":["Олефіренко Наталія Анатоліївна","Наталія Анатоліївна Олефіренко","Наталія Олефіренко"]},"name_unclear":false},"source":"VULYK","estate":{"25":[{"costs":"","costs_comment":"","address_hidden":true,"region_hidden":true,"space_comment":"","space":"54.75","address":"","region":"","costs_rent_comment":"","space_comment_unclear":false,"space_units":"м²","costs_rent":""}]},"intro":{"declaration_year":"2015","isnotdeclaration":""}}