{"income":{"5":{"value":"217739","family_comment":"","value_unclear":false,"family_unclear":false,"family":"","comment":""},"6":{"family_comment":"","family_unclear":false,"value":"217739","family":"","comment":""},"7":{"source_name_unclear":false,"value":"","family_comment":"","source_name":"","family":"","comment":""},"8":{"family_comment":"","value":"","family":"","comment":""},"9":{"value":"","family_comment":"","comment_hidden":false,"family_unclear":false,"family":"","comment":"","family_comment_hidden":false},"10":{"family_comment":"","value":"","family":"","comment":""},"11":{"family_comment":"","value":"","family":"","comment":""},"12":{"family_comment":"","value":"","family":"","comment":""},"13":{"family_comment":"","value":"","family":"","comment":""},"14":{"family_comment":"","value":"","family":"","comment":""},"15":{"family_comment":"","value":"","family":"","comment":""},"16":{"family_comment":"","value":"","family":"","comment":""},"17":{"family_comment":"","value":"","family":"","comment":""},"18":{"family_comment":"","value":"","family":"","comment":""},"19":{"family_comment":"","value":"","family":"","comment":""},"20":{"value":"","value_unclear":false,"comment_hidden":false,"family_comment":"","comment_unclear":false,"comment":"","family":""}},"vehicle":{"35":[{"brand_info":"седан, 1598","sum_rent_comment":"","brand":"Mazda 3","sum_comment":"","year":"2013","brand_info_unclear":false,"sum":"","sum_rent":""}]},"id":"vulyk_108_97","declaration":{"additional_info_text":"","notfull_lostpages":"","date":"2016-03-31T00:00:00","notfull":"","additional_info":"","url":"http://static.declarations.com.ua/declarations/chosen_ones/judges_batch/2396_karataieva_liudmyla_oleksiivna_2015.pdf"},"liabilities":{"54":{"sum_foreign_comment":"","sum":"13177","sum_hidden":false,"sum_comment":"","sum_foreign":""},"55":{"sum_foreign_comment":"","sum":"","sum_comment":"","sum_foreign":""},"56":{"sum_foreign_comment":"","sum":"","sum_comment":"","sum_unclear":false,"sum_foreign":""},"57":{"sum_foreign_comment":"","sum":"","sum_comment":"","sum_hidden":false,"sum_comment_hidden":false,"sum_foreign":""},"58":{"sum_foreign_comment":"","sum_comment_hidden":false,"sum":"","sum_comment":"","sum_foreign":""},"59":{"sum_foreign_comment":"","sum":"","sum_comment":"","sum_unclear":false,"sum_foreign":""},"60":{"sum_foreign_comment":"","sum_comment_hidden":false,"sum":"","sum_comment":"","sum_foreign":""},"61":{"sum_foreign_comment":"","sum_comment_hidden":false,"sum":"","sum_comment":"","sum_foreign":""},"62":{"sum_foreign_comment":"","sum":"","sum_comment":"","sum_foreign":""},"63":{"sum_foreign_comment":"","sum":"","sum_comment":"","sum_hidden":false,"sum_comment_hidden":false,"sum_unclear":false,"sum_foreign":""},"64":{"sum_foreign_comment":"","sum":"","sum_comment":"","sum_comment_hidden":false,"sum_unclear":false,"sum_foreign":""}},"ft_src":"13177\nКаратаєва Людмила Олексіївна\nсуддя апеляційного суду дніпропетровської області\nДніпропетровська область\nЗагальний апеляційний суд\nЛюдмила\nКаратаєва Людмила Олексіївна\nЛюдмила Олексіївна Каратаєва\nЛюдмила Каратаєва\nКаратаєва Людмила Олексіївна\nКаратаєва\nОлексіївна\nседан, 1598\n2013\nMazda 3\n709\n159\n2015\n217739\n217739\nседан, 1598\n2013\nMazda 3\n2015\nЗагальний апеляційний суд\nДніпропетровська область\nсуддя апеляційного суду дніпропетровської області\nКаратаєва\nКаратаєва Людмила Олексіївна\nЛюдмила Олексіївна Каратаєва\nЛюдмила Каратаєва\nКаратаєва Людмила Олексіївна\nЛюдмила\nКаратаєва Людмила Олексіївна\nОлексіївна\n13177\n217739\n217739\n709\n159\n13177\nКаратаєва\nОлексіївна\nДніпропетровська область\nсуддя апеляційного суду дніпропетровської області\nЗагальний апеляційний суд\nКаратаєва Людмила Олексіївна\nКаратаєва Людмила Олексіївна\nЛюдмила Олексіївна Каратаєва\nЛюдмила Каратаєва\nКаратаєва Людмила Олексіївна\nЛюдмила\n2013\nседан, 1598\nMazda 3\n217739\n217739\n709\n159\n2015","general":{"inn":"","family_raw":"","inn_unclear":false,"post":{"post_unclear":false,"post":"суддя апеляційного суду дніпропетровської області","office_hidden":false,"region":"Дніпропетровська область","office":"Загальний апеляційний суд","office_unclear":false},"name":"Людмила","full_name":"Каратаєва Людмила Олексіївна","inn_hidden":true,"addresses":[{"place_city_type_hidden":false,"place_district_hidden":false,"place_city_type":"","place_city_hidden":false,"place_address_unclear":false,"place_address":"","place_hidden":true,"place":"","place_district":"","place_unclear":false,"place_city":"","place_address_hidden":false}],"last_name":"Каратаєва","full_name_suggest":{"output":"Каратаєва Людмила Олексіївна","input":["Каратаєва Людмила Олексіївна","Людмила Олексіївна Каратаєва","Людмила Каратаєва"]},"patronymic":"Олексіївна"},"source":"VULYK","estate":{"23":[{"region_unclear":false,"space_unclear":false,"costs":"","costs_comment":"","address_hidden":false,"region_hidden":true,"space_comment":"","space":"709","address":"","region":"","address_unclear":false,"space_units_unclear":false,"space_units":"м²","space_units_hidden":false,"costs_rent":"","costs_rent_comment":""}],"24":[{"space_hidden":false,"costs":"","costs_comment":"","address_hidden":false,"region_hidden":true,"space_comment":"","space":"159","address":"","region":"","costs_rent_comment":"","space_units":"м²","costs_rent":""}]},"intro":{"declaration_year":"2015","isnotdeclaration":"","declaration_year_hidden":false}}