{"income":{"5":{"family_comment":"","value":"177445.75","value_unclear":false,"family":"","comment":""},"6":{"value":"177445.75","value_unclear":false,"family_hidden":false,"family_comment":"","family":"","comment":""},"7":{"source_name_unclear":false,"value":"","family_comment":"","source_name":"","family":"","comment":""},"8":{"family_comment":"","value":"","family":"","comment":""},"9":{"family_comment":"","value":"","family":"","comment":""},"10":{"family_comment":"","value":"","family":"","comment":""},"11":{"family_comment":"","value":"","comment_unclear":false,"family":"","comment":""},"12":{"family_comment":"","value":"","family":"","comment":""},"13":{"family_comment":"","value":"","family":"","comment":""},"14":{"family_comment":"","value":"","family":"","comment":""},"15":{"family_comment":"","value":"","family":"","comment":""},"16":{"family_comment":"","value":"","family":"","comment":""},"17":{"family_comment":"","value":"","family":"","comment":""},"18":{"family_comment":"","value":"","family":"","comment":""},"19":{"family_comment":"","value":"","family":"","comment":""},"20":{"value":"","family_comment":"","value_unclear":false,"family_unclear":false,"comment_unclear":false,"comment":"","family":""}},"vehicle":{"35":[{"brand_info":"2393 куб. см.","sum_rent_comment":"","brand":"Suzuki Grand Vitara","sum_comment":"","brand_unclear":false,"year":"2008","sum_rent_unclear":false,"brand_info_hidden":false,"brand_info_unclear":false,"sum":"","sum_rent":""}]},"id":"vulyk_101_4","declaration":{"additional_info_text":"","notfull_lostpages":"","date":"2016-03-30T00:00:00","notfull":"","additional_info":"","url":"http://static.declarations.com.ua/declarations/chosen_ones/judges_batch/663_sharatov_iurii_anatoliiovych_2015.pdf"},"liabilities":{"54":{"sum_foreign_comment":"","sum":"","sum_comment":"","sum_comment_unclear":false,"sum_hidden":false,"sum_comment_hidden":false,"sum_unclear":false,"sum_foreign":""},"55":{"sum_foreign_comment":"","sum":"","sum_comment":"","sum_foreign":""},"56":{"sum_foreign_comment":"","sum":"18000","sum_comment":"","sum_comment_hidden":false,"sum_unclear":false,"sum_foreign":""},"57":{"sum_foreign_comment":"","sum":"2872.27","sum_comment":"","sum_hidden":false,"sum_comment_hidden":false,"sum_unclear":false,"sum_foreign":""},"58":{"sum_foreign_comment":"","sum":"144.08","sum_comment":"","sum_comment_unclear":false,"sum_hidden":false,"sum_comment_hidden":false,"sum_unclear":false,"sum_foreign":""},"59":{"sum_foreign_comment":"","sum":"","sum_comment":"","sum_foreign":""},"60":{"sum_foreign_comment":"","sum":"","sum_comment":"","sum_hidden":false,"sum_comment_hidden":false,"sum_unclear":false,"sum_foreign":""},"61":{"sum_foreign_comment":"","sum":"","sum_comment":"","sum_foreign":""},"62":{"sum_foreign_comment":"","sum":"","sum_comment":"","sum_comment_unclear":false,"sum_foreign":""},"63":{"sum_foreign_comment":"","sum_comment_hidden":false,"sum":"","sum_comment":"","sum_foreign":""},"64":{"sum_foreign_comment":"","sum_comment_hidden":false,"sum":"","sum_comment":"","sum_foreign":""}},"ft_src":"2872.27\n144.08\n18000\nсуддя господарського суду одеської області\nОдеська область\nГосподарський місцевий суд\nЮрій\nШаратова Юлія Анатоліївна\nПодружжя\nШаратов Костянтин Юрійович\nДитина\nШаратова Олександра Юріївна\nДитина\nАнатолійович\nШаратов Юрій Анатолійович\nШаратов\nШаратов Юрій Анатолійович\nЮрій Анатолійович Шаратов\nЮрій Шаратов\nШаратов Юрій Анатолійович\nSuzuki Grand Vitara\n2393 куб. см.\n2008\nОдеська область\nм. Одеса\n80.3\nОдеська область\nм. Одеса\n44\nм. Сімферополь\nКримська Автономна Республіка\n56.3\nм. Одеса\n80.3\n12000\n44\n2015\n177445.75\n177445.75\n2393 куб. см.\n2008\nSuzuki Grand Vitara\nОдеська область\nм. Одеса\n80.3\n44\nОдеська область\nм. Одеса\n56.3\nм. Сімферополь\nКримська Автономна Республіка\n80.3\nм. Одеса\n12000\n44\nШаратов Юрій Анатолійович\nЮрій Анатолійович Шаратов\nЮрій Шаратов\nШаратов Юрій Анатолійович\nЮрій\nШаратов Юрій Анатолійович\nАнатолійович\nсуддя господарського суду одеської області\nОдеська область\nГосподарський місцевий суд\nШаратов\nПодружжя\nШаратова Юлія Анатоліївна\nДитина\nШаратов Костянтин Юрійович\nДитина\nШаратова Олександра Юріївна\n2872.27\n18000\n144.08\n177445.75\n177445.75\n2015\n144.08\n2872.27\n18000\nШаратова Юлія Анатоліївна\nПодружжя\nШаратов Костянтин Юрійович\nДитина\nШаратова Олександра Юріївна\nДитина\nЮрій\nАнатолійович\nШаратов\nШаратов Юрій Анатолійович\nЮрій Анатолійович Шаратов\nЮрій Шаратов\nШаратов Юрій Анатолійович\nсуддя господарського суду одеської області\nОдеська область\nГосподарський місцевий суд\nШаратов Юрій Анатолійович\n2008\nSuzuki Grand Vitara\n2393 куб. см.\n177445.75\n177445.75\nм. Одеса\nОдеська область\n80.3\nм. Одеса\nОдеська область\n44\nм. Сімферополь\nКримська Автономна Республіка\n56.3\nм. Одеса\n80.3\n12000\n44\n2015","general":{"inn":"","name":"Юрій","inn_unclear":false,"family":[{"inn":"","relations":"Подружжя","relations_other":"","inn_hidden":true,"family_name":"Шаратова Юлія Анатоліївна","name_hidden":true,"name_unclear":false},{"inn":"","relations":"Дитина","relations_unclear":false,"family_name":"Шаратов Костянтин Юрійович","inn_hidden":true,"relations_other":"","name_hidden":false,"name_unclear":false},{"inn":"","relations":"Дитина","relations_other":"","inn_hidden":true,"family_name":"Шаратова Олександра Юріївна","name_hidden":false,"name_unclear":false}],"inn_hidden":true,"family_raw":"","last_name":"Шаратов","post":{"region":"Одеська область","region_unclear":false,"post":"суддя господарського суду одеської області","office_unclear":false,"office":"Господарський місцевий суд"},"full_name":"Шаратов Юрій Анатолійович","addresses":[{"place_district":"","place_address_hidden":true,"place_city":"","place_city_type_hidden":false,"place_district_hidden":false,"place_city_type":"","place_city_hidden":true,"place_address":"","place_hidden":true,"place":""}],"patronymic":"Анатолійович","patronymic_hidden":false,"full_name_suggest":{"output":"Шаратов Юрій Анатолійович","input":["Шаратов Юрій Анатолійович","Юрій Анатолійович Шаратов","Юрій Шаратов"]}},"source":"VULYK","estate":{"25":[{"space_unclear":false,"costs":"","costs_comment":"","address_hidden":false,"region_hidden":false,"space_comment":"","space_hidden":false,"space":"56.3","address":"м. Сімферополь","region":"Кримська Автономна Республіка","costs_rent_comment":"","space_comment_unclear":false,"space_units":"м²","costs_rent":""},{"space_unclear":false,"costs":"","costs_comment":"","space_comment":"","space_hidden":false,"space":"80.3","address":"м. Одеса","region":"","costs_rent_comment":"","space_comment_unclear":false,"space_units":"м²","costs_rent":""},{"costs_rent":"12000","region":"","costs":"","costs_rent_comment":"","costs_comment":"","space_comment":"","space_units":"м²","space":"44","address":""}],"31":[{"space_unclear":false,"address_hidden":true,"region_hidden":false,"space_comment":"","space_hidden":false,"space":"80.3","address":"м. Одеса","costs_rent_comment_unclear":false,"region":"Одеська область","costs_property":"","costs_rent_comment":"","space_units":"м²","costs_property_comment":"","costs_rent":""},{"costs_rent":"","region":"Одеська область","costs_property":"","costs_rent_comment":"","space_comment":"","costs_property_comment":"","space_units":"м²","space":"44","address":"м. Одеса"}]},"intro":{"declaration_year":"2015"}}