{"income":{"5":{"family_comment":"","value":"282483","family":"25617","comment":""},"6":{"family_comment":"","value":"245839","value_unclear":false,"family":"","comment":""},"7":{"value":"","family_comment":"","source_name":"","family":"","comment":"","source_name_hidden":false},"8":{"family_comment":"","value":"","family":"","comment":""},"9":{"family_comment":"","value":"","family":"","comment":""},"10":{"family_comment":"","value":"13398","family":"","comment":""},"11":{"family_comment":"","value":"","comment_hidden":false,"family":"","comment":""},"12":{"family_comment":"","value":"","family":"","comment":""},"13":{"family_comment":"","value":"","family":"","comment":""},"14":{"family_comment":"","value":"23246","family":"","comment":""},"15":{"value":"","family_comment":"","value_unclear":false,"family_unclear":false,"family":"","comment":""},"16":{"family_comment":"","value":"","family":"","comment":""},"17":{"family_comment":"","value":"","family":"","comment":""},"18":{"family_comment":"","value":"","family":"","comment":""},"19":{"family_comment":"","value":"","family":"","comment":""},"20":{"family_comment":"","value":"","comment_unclear":false,"family":"","comment":""}},"vehicle":{"35":[{"brand_info":"1452 куб. см.","sum_rent_comment":"","brand":"ВАЗ 2107","sum_comment":"","year":"2003","brand_hidden":false,"brand_info_unclear":false,"sum":"","sum_rent":""},{"brand_info":"1598 куб. см.","sum":"","brand":"Toyota Auris","sum_comment":"","year":"2008","sum_rent_comment":"","sum_rent":"","sum_unclear":false}]},"id":"vulyk_104_151","declaration":{"date":"2016-03-30T00:00:00","additional_info_text":"","additional_info":"","url":"http://static.declarations.com.ua/declarations/chosen_ones/judges_batch/1949_dukovskyi_oleksandr_leontiiovych_2015.pdf"},"liabilities":{"54":{"sum_foreign_comment":"","sum_foreign_hidden":false,"sum_comment":"","sum_hidden":false,"sum_comment_hidden":false,"sum_unclear":false,"sum":"","sum_foreign":""},"55":{"sum_foreign_comment":"","sum":"","sum_comment":"","sum_foreign":""},"56":{"sum_foreign_comment":"","sum":"","sum_comment":"","sum_unclear":false,"sum_foreign":""},"57":{"sum_foreign_comment":"","sum_foreign_hidden":false,"sum_comment":"","sum_comment_unclear":false,"sum_comment_hidden":false,"sum":"","sum_foreign":""},"58":{"sum_foreign_comment":"","sum":"","sum_comment":"","sum_unclear":false,"sum_foreign":""},"59":{"sum_foreign_comment":"","sum":"","sum_comment":"","sum_foreign":""},"60":{"sum_foreign_comment":"","sum_foreign_hidden":false,"sum_comment":"","sum_comment_hidden":false,"sum":"","sum_foreign":""},"61":{"sum_foreign_comment":"","sum":"","sum_comment":"","sum_foreign":""},"62":{"sum_foreign_comment":"","sum":"","sum_comment":"","sum_foreign":""},"63":{"sum_foreign_comment":"","sum":"","sum_comment":"","sum_foreign":""},"64":{"sum_foreign_comment":"","sum":"","sum_comment":"","sum_foreign":""}},"ft_src":"Дуковський Олександр Леонтійович\nсуддя апеляційного суду кіровоградської області\nКіровоградська область\nЗагальний апеляційний суд\nОлександр\nДуковська Т. М\nПодружжя\nДуковський А. О\nДитина\nДуковський Олександр Леонтійович\nОлександр Леонтійович Дуковський\nОлександр Дуковський\nДуковський Олександр Леонтійович\nДуковський\nЛеонтійович\n2003\nВАЗ 2107\n1452 куб. см.\n1598 куб. см.\n2008\nToyota Auris\n39.12\n19.56\n2015\n245839\n23246\n13398\n25617\n282483\n1452 куб. см.\nВАЗ 2107\n2003\n1598 куб. см.\nToyota Auris\n2008\n2015\nПодружжя\nДуковська Т. М\nДитина\nДуковський А. О\nДуковський\nДуковський Олександр Леонтійович\nОлександр Леонтійович Дуковський\nОлександр Дуковський\nДуковський Олександр Леонтійович\nДуковський Олександр Леонтійович\nОлександр\nЛеонтійович\nЗагальний апеляційний суд\nсуддя апеляційного суду кіровоградської області\nКіровоградська область\n245839\n23246\n282483\n25617\n13398\n39.12\n19.56\nПодружжя\nДуковська Т. М\nДитина\nДуковський А. О\nЛеонтійович\nДуковський\nсуддя апеляційного суду кіровоградської області\nЗагальний апеляційний суд\nКіровоградська область\nДуковський Олександр Леонтійович\nДуковський Олександр Леонтійович\nОлександр Леонтійович Дуковський\nОлександр Дуковський\nДуковський Олександр Леонтійович\nОлександр\n2003\n1452 куб. см.\nВАЗ 2107\nToyota Auris\n1598 куб. см.\n2008\n23246\n13398\n25617\n282483\n245839\n39.12\n19.56\n2015","general":{"inn":"","inn_hidden":true,"last_name":"Дуковський","post":{"region":"Кіровоградська область","region_unclear":false,"post":"суддя апеляційного суду кіровоградської області","office_unclear":false,"office":"Загальний апеляційний суд"},"name":"Олександр","full_name":"Дуковський Олександр Леонтійович","family_raw":"","addresses":[{"place_district":"","place_city_hidden":true,"place_city":"","place_city_type_hidden":false,"place_district_hidden":false,"place_city_type":"","place_address_hidden":true,"place_address":"","place_hidden":true,"place":""}],"family":[{"inn":"","relations":"Подружжя","relations_other":"","inn_hidden":true,"family_name":"Дуковська Т. М","name_hidden":true,"name_unclear":false},{"inn":"","relations":"Дитина","relations_other":"","inn_hidden":false,"family_name":"Дуковський А. О","name_hidden":false,"name_unclear":false}],"full_name_suggest":{"output":"Дуковський Олександр Леонтійович","input":["Дуковський Олександр Леонтійович","Олександр Леонтійович Дуковський","Олександр Дуковський"]},"patronymic":"Леонтійович"},"source":"VULYK","estate":{"25":[{"costs":"","costs_comment":"","address_hidden":false,"region_hidden":true,"space_comment":"","space":"19.56","address":"","costs_unclear":false,"region":"","costs_rent_comment":"","space_comment_unclear":false,"space_units":"м²","costs_rent":""}],"31":[{"space_unclear":false,"address_hidden":false,"region_hidden":true,"space_comment":"","space_hidden":false,"space":"39.12","address":"","region":"","costs_property":"","costs_rent_comment":"","space_units":"м²","costs_property_comment":"","costs_rent":""}]},"intro":{"declaration_year":"2015","isnotdeclaration":""}}