{"income":{"5":{"family_comment":"","value":"241539","family":"22935","comment":""},"6":{"family_comment":"","value":"231539","family":"","comment":""},"7":{"family_comment":"","value":"","source_name":"","family":"","comment":""},"8":{"family_comment":"","value":"","family":"","comment":""},"9":{"value":"","comment_unclear":false,"family_comment":"","family":"","comment":"","family_comment_unclear":false},"10":{"family_comment":"","value":"","family":"","comment":""},"11":{"family_comment":"","value":"","family":"","comment":""},"12":{"family_comment":"","value":"","family":"","comment":""},"13":{"family_comment":"","value":"","family":"","comment":""},"14":{"family_comment":"","value":"","family":"","comment":""},"15":{"family_comment":"","value":"","family":"","comment":""},"16":{"family_comment":"","value":"10000","family":"","comment":""},"17":{"family_comment":"","value":"","family":"","comment":""},"18":{"family_comment":"","value":"","family":"","comment":""},"19":{"value":"","family_comment":"","value_unclear":false,"family_unclear":false,"family":"","comment":""},"20":{"value":"","family_comment":"пенсія","value_unclear":false,"comment_hidden":false,"family_comment_hidden":false,"family_unclear":false,"family_comment_unclear":false,"comment_unclear":false,"comment":"","family":"22935"}},"vehicle":{"40":[{"year_hidden":false,"brand_info":"1799 куб. см., 89.8 кВт","sum_rent_comment":"","brand":"Mercedes-Benz C180","sum_comment":"","year":"1995","brand_hidden":false,"brand_info_hidden":false,"brand_info_unclear":false,"sum":"","sum_rent":""},{"brand_info":"1600 куб. см., 55.2 кВт","sum_rent_comment":"","brand":"Volkswagen Golf","sum_comment":"","year":"1992","brand_info_hidden":false,"sum":"","sum_rent":""}]},"id":"vulyk_106_8","banks":{"45":[{"sum_foreign_comment":"","sum_units":"UAH","sum_comment":"Ощадбанк України","sum_foreign_comment_hidden":false,"sum_hidden":false,"sum_foreign_units":"UAH","sum_comment_hidden":false,"sum":"2471","sum_foreign":""}],"53":[{"sum_foreign_comment":"","sum_units":"UAH","sum_comment":"","sum_foreign_units":"UAH","sum":"15000","sum_foreign":""}]},"declaration":{"additional_info_text":"","notfull_lostpages":"","date":"2016-03-30T00:00:00","notfull":"","additional_info":"","url":"http://static.declarations.com.ua/declarations/chosen_ones/judges_batch/2147_spiridonova_tetiana_viktorivna.pdf"},"liabilities":{"54":{"sum_foreign_comment":"","sum":"","sum_comment":"","sum_comment_unclear":false,"sum_hidden":false,"sum_comment_hidden":false,"sum_foreign":""},"55":{"sum_foreign_comment":"","sum":"","sum_hidden":false,"sum_comment":"","sum_foreign":""},"56":{"sum_foreign_comment":"","sum":"","sum_comment":"","sum_hidden":false,"sum_comment_hidden":false,"sum_unclear":false,"sum_foreign":""},"57":{"sum_foreign_comment":"","sum":"","sum_comment":"","sum_hidden":false,"sum_comment_hidden":false,"sum_foreign":""},"58":{"sum_foreign_comment":"","sum":"","sum_comment":"","sum_hidden":false,"sum_comment_hidden":false,"sum_foreign":""},"59":{"sum_foreign_comment":"","sum":"","sum_comment":"","sum_foreign":""},"60":{"sum_foreign_comment":"","sum":"","sum_comment":"","sum_hidden":false,"sum_comment_hidden":false,"sum_foreign":""},"61":{"sum_foreign_comment":"","sum":"","sum_comment":"","sum_foreign":""},"62":{"sum_foreign_comment":"","sum":"","sum_comment":"","sum_comment_hidden":false,"sum_unclear":false,"sum_foreign":""},"63":{"sum_foreign_comment":"","sum":"","sum_comment":"","sum_foreign":""},"64":{"sum_foreign_comment":"","sum":"","sum_comment":"","sum_foreign":""}},"ft_src":"суддя апеляційного суду хмельницької області\nХмельницька область\nЗагальний апеляційний суд\nТетяна\nТихонюк Я. П\nПодружжя\nТихонюк В. Я\nДитина\nВікторівна\nСпірідонова Тетяна Вікторівна\nТетяна Вікторівна Спірідонова\nТетяна Спірідонова\nСпірідонова Тетяна Вікторівна\nСпірідонова Тетяна Вікторівна\nСпірідонова\n1799 куб. см., 89.8 кВт\nMercedes-Benz C180\n1995\n1600 куб. см., 55.2 кВт\n1992\nVolkswagen Golf\n15000\nОщадбанк України\n2471\n2015\n1799 куб. см., 89.8 кВт\n1995\nMercedes-Benz C180\nVolkswagen Golf\n1600 куб. см., 55.2 кВт\n1992\n15000\n2471\nОщадбанк України\n48.7\n21\n1200\n1000\n2500\n714\n20000\n80.1\n329.1\nСпірідонова Тетяна Вікторівна\nТетяна Вікторівна Спірідонова\nТетяна Спірідонова\nСпірідонова Тетяна Вікторівна\nСпірідонова Тетяна Вікторівна\nПодружжя\nТихонюк Я. П\nДитина\nТихонюк В. Я\nТетяна\nСпірідонова\nХмельницька область\nЗагальний апеляційний суд\nсуддя апеляційного суду хмельницької області\nВікторівна\n231539\n22935\nпенсія\n241539\n22935\n10000\n2015\n2500\n714\n20000\n1200\n1000\n21\n80.1\n329.1\n48.7\nТихонюк Я. П\nПодружжя\nТихонюк В. Я\nДитина\nВікторівна\nСпірідонова\nТетяна\nСпірідонова Тетяна Вікторівна\nТетяна Вікторівна Спірідонова\nТетяна Спірідонова\nСпірідонова Тетяна Вікторівна\nХмельницька область\nЗагальний апеляційний суд\nсуддя апеляційного суду хмельницької області\nСпірідонова Тетяна Вікторівна\n231539\n22935\n241539\n10000\n22935\nпенсія\nMercedes-Benz C180\n1799 куб. см., 89.8 кВт\n1995\nVolkswagen Golf\n1600 куб. см., 55.2 кВт\n1992\nпенсія\n22935\n22935\n241539\n10000\n231539\n80.1\n1200\n1000\n329.1\n21\n48.7\n2500\n714\n20000\nОщадбанк України\n2471\n15000\n2015","general":{"inn":"","name":"Тетяна","inn_unclear":false,"family":[{"inn":"","inn_hidden":true,"relations_unclear":false,"relations_hidden":false,"relations_other":"","relations":"Подружжя","name_hidden":true,"family_name":"Тихонюк Я. П","name_unclear":true},{"inn":"","relations":"Дитина","relations_unclear":false,"family_name":"Тихонюк В. Я","inn_hidden":false,"relations_other":"","name_hidden":false,"name_unclear":false}],"inn_hidden":true,"family_raw":"","last_name":"Спірідонова","post":{"region_unclear":false,"region":"Хмельницька область","post":"суддя апеляційного суду хмельницької області","office":"Загальний апеляційний суд","office_unclear":false,"post_hidden":false},"full_name":"Спірідонова Тетяна Вікторівна","addresses":[{"place_district":"","place_city_hidden":true,"place_city":"","place_city_type_hidden":true,"place_district_hidden":true,"place_city_type":"","place_address_hidden":true,"place_address":"","place_hidden":true,"place":""}],"patronymic":"Вікторівна","full_name_suggest":{"output":"Спірідонова Тетяна Вікторівна","input":["Спірідонова Тетяна Вікторівна","Тетяна Вікторівна Спірідонова","Тетяна Спірідонова"]},"name_unclear":false},"source":"VULYK","estate":{"23":[{"region_unclear":false,"space_hidden":false,"costs":"","costs_comment":"","address_hidden":true,"region_hidden":true,"space_comment":"","space_unclear":false,"space":"1200","address":"","costs_comment_unclear":false,"costs_rent_comment_unclear":false,"region":"","address_unclear":false,"costs_rent_comment":"","space_comment_unclear":false,"space_comment_hidden":false,"space_units":"м²","costs_rent":""},{"space_unclear":false,"costs":"","costs_comment":"","address_hidden":false,"region_hidden":false,"space_comment":"","space":"1000","address":"","costs_comment_unclear":false,"region":"","address_unclear":false,"costs_rent_comment":"","space_units":"м²","costs_rent":""}],"25":[{"costs":"","costs_comment":"","address_hidden":false,"region_hidden":true,"space_comment":"","space":"48.7","address":"","region":"","costs_rent_comment":"","space_comment_unclear":false,"space_units":"м²","costs_rent":""}],"26":[{"costs_rent":"","region":"","costs":"","costs_rent_comment":"","costs_comment":"","address_hidden":true,"region_hidden":true,"space_comment":"","space_units":"м²","space":"","address":""}],"29":[{"region_unclear":false,"costs_property_comment":"","address_hidden":true,"region_hidden":true,"space_comment":"","space":"2500","address":"","costs_rent_comment_unclear":false,"region":"","costs_property":"","costs_rent_comment":"","space_comment_unclear":false,"address_unclear":false,"space_units":"м²","space_units_unclear":false,"costs_rent":""},{"costs_rent":"","region":"","costs_property":"","costs_rent_comment":"","address_hidden":true,"region_hidden":false,"space_comment":"","costs_property_comment":"","space_units":"м²","space":"714","address":""},{"costs_rent":"","region":"","costs_property":"","costs_rent_comment":"","address_hidden":true,"region_hidden":false,"space_comment":"","costs_property_comment":"","space_units":"м²","space":"20000","address":""}],"31":[{"space_unclear":false,"address_hidden":true,"region_hidden":true,"space_comment":"","space_hidden":false,"space":"80.1","address":"","region":"","costs_property":"","costs_rent_comment":"","space_comment_unclear":false,"space_units":"м²","costs_property_comment":"","costs_rent":""}],"33":[{"space_hidden":false,"address_hidden":true,"region_hidden":true,"space_comment":"","space":"21","address":"","region":"","costs_property":"","costs_rent_comment":"","space_comment_unclear":false,"space_units":"м²","costs_property_comment":"","costs_rent":""}],"34":[{"costs_rent":"","costs_property":"","costs_rent_comment":"","address_hidden":true,"region_hidden":true,"space_comment":"","costs_property_comment":"","space_units":"м²","space":"329.1","address":""}]},"intro":{"declaration_year":"2015","isnotdeclaration":""}}