{"income":{"5":{"value":"240315.32","family_comment":"","value_unclear":false,"family_hidden":false,"value_hidden":false,"family_unclear":false,"family":"15698.39","comment":""},"6":{"value":"228135.32","family_comment":"","value_unclear":false,"family_unclear":false,"family":"15698.39","comment":""},"7":{"source_name_unclear":false,"value":"","comment_hidden":false,"family_comment":"","source_name":"","family":"","comment":"","source_name_hidden":false},"8":{"family_comment":"","value":"","family":"","comment":""},"9":{"value":"","family_comment":"","value_unclear":false,"family_hidden":false,"family_unclear":false,"family":"","comment":"","family_comment_unclear":false},"10":{"family_comment":"","value":"12180","family":"","comment":""},"11":{"family_comment":"","value":"","family":"","comment":""},"12":{"family_comment":"","value":"","family":"","comment":""},"13":{"family_comment":"","value":"","family":"","comment":""},"14":{"family_comment":"","value":"","family":"","comment":""},"15":{"family_comment":"","value":"","family":"","comment":""},"16":{"family_comment":"","value":"","family":"","comment":""},"17":{"family_comment":"","value":"","family":"","comment":""},"18":{"family_comment":"","value":"","family":"","comment":""},"19":{"family_comment":"","value":"","family":"","comment":""},"20":{"value":"","family_comment":"","value_unclear":false,"family_comment_hidden":false,"family_unclear":false,"family_comment_unclear":false,"comment_unclear":false,"comment":"","family":""}},"vehicle":{"35":[{"year_hidden":false,"brand_info":"1690 куб. см.","sum_rent_comment":"","year":"2007","brand_info_hidden":false,"brand_info_unclear":false,"sum_rent":"","sum":"","brand":"ВАЗ Шевроле-Нива","sum_comment":"","brand_unclear":false,"brand_hidden":false}]},"id":"vulyk_93_138","declaration":{"additional_info_text":"","notfull_lostpages":"","date":"2015-03-30T00:00:00","notfull":"","additional_info":"","url":"http://static.declarations.com.ua/declarations/chosen_ones/judges_batch/3584_savenko_valerii_hryhorovych.pdf"},"liabilities":{"54":{"sum_foreign_comment":"","sum":"","sum_hidden":false,"sum_comment":"","sum_foreign":""},"55":{"sum_foreign_comment":"","sum":"","sum_comment":"","sum_foreign":""},"56":{"sum_foreign_comment":"","sum":"","sum_comment":"","sum_foreign":""},"57":{"sum_foreign_comment":"","sum":"","sum_comment":"","sum_hidden":false,"sum_comment_hidden":false,"sum_unclear":false,"sum_foreign":""},"58":{"sum_foreign_comment":"","sum":"","sum_comment":"","sum_comment_unclear":false,"sum_hidden":false,"sum_unclear":false,"sum_foreign":""},"59":{"sum_foreign_comment":"","sum":"","sum_comment":"","sum_foreign":""},"60":{"sum_foreign_comment":"","sum":"","sum_hidden":false,"sum_comment":"","sum_foreign":""},"61":{"sum_foreign_comment":"","sum":"","sum_comment":"","sum_foreign":""},"62":{"sum_foreign_comment":"","sum":"","sum_comment":"","sum_foreign":""},"63":{"sum_foreign_comment":"","sum":"","sum_comment":"","sum_foreign":""},"64":{"sum_foreign_comment":"","sum":"","sum_comment":"","sum_foreign":""}},"ft_src":"Савенко Валерій Григорович\nсуддя золотоніського міськрайонного суду черкаської області\nЧеркаська область\nЗагальний місцевий суд\nВалерій\nСавенко Г. Л., 1971 р. н\nПодружжя\nСавенко Валерій Григорович\nВалерій Григорович Савенко\nВалерій Савенко\nСавенко Валерій Григорович\nСавенко\nГригорович\n1690 куб. см.\nВАЗ Шевроле-Нива\n2007\n623\n27.6\n111.1\n2014\n15698.39\n228135.32\n12180\n15698.39\n240315.32\n1690 куб. см.\nВАЗ Шевроле-Нива\n2007\n623\n27.6\n111.1\nСавенко\nПодружжя\nСавенко Г. Л., 1971 р. н\nСавенко Валерій Григорович\nВалерій Григорович Савенко\nВалерій Савенко\nСавенко Валерій Григорович\nСавенко Валерій Григорович\nВалерій\nГригорович\nЧеркаська область\nЗагальний місцевий суд\nсуддя золотоніського міськрайонного суду черкаської області\n15698.39\n228135.32\n240315.32\n15698.39\n12180\n2014\nПодружжя\nСавенко Г. Л., 1971 р. н\nСавенко\nГригорович\nЧеркаська область\nЗагальний місцевий суд\nсуддя золотоніського міськрайонного суду черкаської області\nСавенко Валерій Григорович\nСавенко Валерій Григорович\nВалерій Григорович Савенко\nВалерій Савенко\nСавенко Валерій Григорович\nВалерій\nВАЗ Шевроле-Нива\n1690 куб. см.\n2007\n12180\n240315.32\n15698.39\n228135.32\n15698.39\n623\n111.1\n27.6\n2014","general":{"inn":"","inn_hidden":true,"last_name":"Савенко","post":{"post_unclear":false,"region_unclear":false,"region":"Черкаська область","candidate":"","post":"суддя золотоніського міськрайонного суду черкаської області","office":"Загальний місцевий суд","office_unclear":false},"name":"Валерій","full_name":"Савенко Валерій Григорович","family_raw":"","addresses":[{"place_district":"","place_city_hidden":true,"place_city":"","place_city_type_hidden":true,"place_district_hidden":true,"place_city_type":"","place_address_hidden":true,"place_address":"","place_hidden":true,"place":""}],"family":[{"inn":"","relations":"Подружжя","relations_hidden":false,"inn_hidden":false,"relations_other":"","name_hidden":false,"family_name":"Савенко Г. Л., 1971 р. н","name_unclear":false}],"full_name_suggest":{"output":"Савенко Валерій Григорович","input":["Савенко Валерій Григорович","Валерій Григорович Савенко","Валерій Савенко"]},"patronymic":"Григорович"},"source":"VULYK","estate":{"23":[{"space_unclear":false,"costs":"","costs_comment":"","address_hidden":false,"region_hidden":true,"space_comment":"","space":"623","address":"","region":"","costs_rent_comment":"","space_comment_unclear":false,"space_units":"м²","costs_rent":""}],"24":[{"space_unclear":false,"costs":"","costs_comment":"","address_hidden":false,"region_hidden":true,"space_comment":"","space":"111.1","address":"","region":"","costs_rent_comment":"","space_comment_unclear":false,"space_units":"м²","costs_rent":""}],"27":[{"costs_rent":"","region":"","costs":"","costs_rent_comment":"","costs_comment":"","address_hidden":false,"region_hidden":true,"space_comment":"","space_units":"м²","space":"27.6","address":""}]},"intro":{"declaration_year":"2014","isnotdeclaration":""}}