{"income":{"5":{"family_comment":"","value":"229769","value_unclear":false,"family":"163868","comment":""},"6":{"value":"229769","value_unclear":false,"family_hidden":false,"family_comment":"","family":"163868","comment":""},"7":{"source_name_unclear":false,"value":"","family_comment":"","source_name":"","family":"","comment":""},"8":{"family_comment":"","value":"","family":"","comment":""},"9":{"family_comment":"","value":"","family":"","comment":""},"10":{"family_comment":"","value":"","family":"","comment":""},"11":{"family_comment":"","value":"","comment_unclear":false,"family":"","comment":""},"12":{"family_comment":"","value":"","family":"","comment":""},"13":{"family_comment":"","value":"","family":"","comment":""},"14":{"family_comment":"","value":"","family":"","comment":""},"15":{"family_comment":"","value":"","family":"","comment":""},"16":{"family_comment":"","value":"","family":"","comment":""},"17":{"family_comment":"","value":"","family":"","comment":""},"18":{"family_comment":"","value":"","family":"","comment":""},"19":{"family_comment":"","value":"","family":"","comment":""},"20":{"value":"","family_comment":"","value_unclear":false,"family_unclear":false,"comment_unclear":false,"comment":"","family":""}},"vehicle":{"40":[{"brand_info":"об'єм двигуна 1968 , довжина 4255 мм, потужність двигуна 150 к.с.","sum_rent_comment":"","brand":"Volkswagen Golf","sum_comment":"","year":"2014","brand_hidden":false,"brand_info_hidden":false,"brand_info_unclear":true,"sum":"","sum_rent":""}]},"id":"vulyk_101_177","declaration":{"additional_info_text":"","notfull_lostpages":"","date":"2016-03-31T00:00:00","notfull":"","additional_info":"","url":"http://static.declarations.com.ua/declarations/chosen_ones/judges_batch/892_moiseienko_tetiana_volodymyrivna_2015.pdf"},"liabilities":{"54":{"sum_foreign_comment":"","sum":"","sum_comment":"","sum_comment_unclear":false,"sum_hidden":false,"sum_comment_hidden":false,"sum_unclear":false,"sum_foreign":""},"55":{"sum_foreign_comment":"","sum":"","sum_comment":"","sum_foreign":""},"56":{"sum_foreign_comment":"","sum":"","sum_comment":"","sum_comment_hidden":false,"sum_unclear":false,"sum_foreign":""},"57":{"sum_foreign_comment":"","sum":"","sum_comment":"","sum_hidden":false,"sum_comment_hidden":false,"sum_unclear":false,"sum_foreign":""},"58":{"sum_foreign_comment":"","sum":"","sum_comment":"","sum_comment_unclear":false,"sum_hidden":false,"sum_comment_hidden":false,"sum_unclear":false,"sum_foreign":""},"59":{"sum_foreign_comment":"","sum":"","sum_comment":"","sum_foreign":""},"60":{"sum_foreign_comment":"","sum":"23600","sum_comment":"","sum_hidden":true,"sum_comment_hidden":true,"sum_unclear":false,"sum_foreign":""},"61":{"sum_foreign_comment":"","sum":"","sum_comment":"","sum_foreign":""},"62":{"sum_foreign_comment":"","sum":"","sum_comment":"","sum_comment_unclear":false,"sum_foreign":""},"63":{"sum_foreign_comment":"","sum_comment_hidden":false,"sum":"","sum_comment":"","sum_foreign":""},"64":{"sum_foreign_comment":"","sum_comment_hidden":false,"sum":"","sum_comment":"","sum_foreign":""}},"ft_src":"23600\nсуддя господарського суду запорізької області\nЗапорізька область\nГосподарський місцевий суд\nТетяна\nМойсеєнко В. В\nПодружжя\nМойсеєнко Г. В\nДитина\nВолодимирівна\nМойсеєнко Тетяна Володимирівна\nМойсеєнко\nМойсеєнко Тетяна Володимирівна\nТетяна Володимирівна Мойсеєнко\nТетяна Мойсеєнко\nМойсеєнко Тетяна Володимирівна\nоб'єм двигуна 1968 , довжина 4255 мм, потужність двигуна 150 к.с.\nVolkswagen Golf\n2014\n45.6\n79.45\n22.8\n79.45\n2015\n163868\n229769\n163868\n229769\nоб'єм двигуна 1968 , довжина 4255 мм, потужність двигуна 150 к.с.\n2014\nVolkswagen Golf\n45.6\n79.45\n22.8\n79.45\nМойсеєнко Тетяна Володимирівна\nТетяна Володимирівна Мойсеєнко\nТетяна Мойсеєнко\nМойсеєнко Тетяна Володимирівна\nТетяна\nМойсеєнко Тетяна Володимирівна\nВолодимирівна\nсуддя господарського суду запорізької області\nЗапорізька область\nГосподарський місцевий суд\nМойсеєнко\nПодружжя\nМойсеєнко В. В\nДитина\nМойсеєнко Г. В\n23600\n229769\n163868\n229769\n163868\n2015\n23600\nМойсеєнко В. В\nПодружжя\nМойсеєнко Г. В\nДитина\nТетяна\nВолодимирівна\nМойсеєнко\nМойсеєнко Тетяна Володимирівна\nТетяна Володимирівна Мойсеєнко\nТетяна Мойсеєнко\nМойсеєнко Тетяна Володимирівна\nсуддя господарського суду запорізької області\nЗапорізька область\nГосподарський місцевий суд\nМойсеєнко Тетяна Володимирівна\nVolkswagen Golf\nоб'єм двигуна 1968 , довжина 4255 мм, потужність двигуна 150 к.с.\n2014\n163868\n229769\n229769\n163868\n45.6\n79.45\n22.8\n79.45\n2015","general":{"inn":"","name":"Тетяна","inn_unclear":false,"family":[{"inn":"","relations":"Подружжя","relations_other":"","inn_hidden":true,"family_name":"Мойсеєнко В. В","name_hidden":true,"name_unclear":false},{"inn":"","relations":"Дитина","relations_unclear":false,"family_name":"Мойсеєнко Г. В","inn_hidden":false,"relations_other":"","name_hidden":false,"name_unclear":false}],"inn_hidden":true,"family_raw":"","last_name":"Мойсеєнко","post":{"region":"Запорізька область","region_unclear":false,"post":"суддя господарського суду запорізької області","office_unclear":false,"office":"Господарський місцевий суд"},"full_name":"Мойсеєнко Тетяна Володимирівна","addresses":[{"place_district":"","place_address_hidden":true,"place_city":"","place_city_type_hidden":false,"place_district_hidden":false,"place_city_type":"","place_city_hidden":true,"place_address":"","place_hidden":true,"place":""}],"patronymic":"Володимирівна","patronymic_hidden":false,"full_name_suggest":{"output":"Мойсеєнко Тетяна Володимирівна","input":["Мойсеєнко Тетяна Володимирівна","Тетяна Володимирівна Мойсеєнко","Тетяна Мойсеєнко"]}},"source":"VULYK","estate":{"25":[{"space_unclear":false,"costs":"","costs_comment":"","address_hidden":false,"region_hidden":true,"space_comment":"","space_hidden":false,"space":"22.8","address":"","region":"","costs_rent_comment":"","space_comment_unclear":false,"space_units":"м²","costs_rent":""},{"space_unclear":false,"costs":"","costs_comment":"","space_comment":"","space_hidden":false,"space":"79.45","address":"","region":"","costs_rent_comment":"","space_comment_unclear":false,"space_units":"м²","costs_rent":""}],"31":[{"space_unclear":false,"address_hidden":false,"region_hidden":true,"space_comment":"","space_hidden":false,"space":"45.6","address":"","costs_rent_comment_unclear":false,"region":"","costs_property":"","costs_rent_comment":"","space_units":"м²","costs_property_comment":"","costs_rent":""},{"costs_rent":"","region":"","costs_property":"","costs_rent_comment":"","space_comment":"","costs_property_comment":"","space_units":"м²","space":"79.45","address":""}]},"intro":{"declaration_year":"2015"}}