{"income":{"5":{"value":"15464","family_comment":"","value_unclear":false,"comment_hidden":false,"family_hidden":false,"value_hidden":false,"family_unclear":false,"family":"1449028","comment":""},"6":{"value":"","family_comment":"","value_unclear":false,"family_hidden":false,"family_unclear":false,"comment_unclear":false,"comment":"","family":""},"7":{"source_name_unclear":false,"value":"","value_hidden":false,"family_comment":"","source_name":"","family":"","comment":"","source_name_hidden":false},"8":{"value":"","family_hidden":false,"value_hidden":false,"family_comment":"","family":"","comment":""},"9":{"value":"","family_comment":"","value_unclear":false,"family_hidden":false,"value_hidden":false,"family_unclear":false,"family":"69356","comment":""},"10":{"family_comment":"","value":"","family":"","comment":""},"11":{"family_comment":"","value":"","family":"530704","comment":""},"12":{"family_comment":"","value":"","family":"","comment":""},"13":{"family_comment":"","value":"","family":"","comment":""},"14":{"family_comment":"","value":"","family":"","comment":""},"15":{"family_comment":"","value":"","family":"","comment":""},"16":{"value":"","family_comment":"","value_unclear":false,"family_unclear":false,"family":"","comment":""},"17":{"family_comment":"","value":"","family":"822580","comment":""},"18":{"family_comment":"","value":"","family":"","comment":""},"19":{"family_comment":"","value":"","comment_unclear":false,"family":"15000","comment":""},"20":{"value":"15464","family_comment":"","value_unclear":false,"comment_hidden":false,"family_hidden":false,"family":"11388","value_hidden":false,"family_unclear":false,"comment_unclear":false,"comment":"","family_comment_unclear":false}},"vehicle":{"40":[{"brand_info":"2300 куб.см..175 л. с","sum_rent_comment":"","brand":"Mercedes CLK-230","sum_comment":"","brand_unclear":false,"year":"2000","brand_info_unclear":false,"year_unclear":false,"sum":"","sum_rent":""}]},"id":"vulyk_63_134","banks":{"51":[{"sum_foreign_comment":"","sum_units":"UAH","sum_comment":"","sum_foreign_unclear":false,"sum_foreign_units":"UAH","sum_foreign_hidden":false,"sum_hidden":false,"sum_comment_hidden":false,"sum_unclear":false,"sum":"2520","sum_foreign":""}]},"declaration":{"additional_info_text":"","notfull_lostpages":"","date":"2015-03-31T00:00:00","notfull":"","additional_info":"","url":"http://static.declarations.com.ua/declarations/chosen_ones/mega_batch/horiainova_kateryna_anatoliivna.pdf"},"liabilities":{"54":{"sum_foreign_comment":"","sum":"","sum_comment":"","sum_unclear":false,"sum_foreign":""},"55":{"sum_foreign_comment":"","sum":"","sum_comment":"","sum_foreign":""},"56":{"sum_foreign_comment":"","sum":"","sum_comment":"","sum_unclear":false,"sum_foreign":""},"57":{"sum_foreign_comment":"","sum":"","sum_comment":"","sum_comment_hidden":false,"sum_unclear":false,"sum_foreign":""},"58":{"sum_foreign_comment":"","sum_comment_hidden":false,"sum":"","sum_comment":"","sum_foreign":""},"59":{"sum_foreign_comment":"","sum":"","sum_comment":"","sum_foreign":""},"60":{"sum_foreign_comment":"","sum":"14282","sum_comment":"","sum_comment_unclear":false,"sum_foreign":""},"61":{"sum_foreign_comment":"","sum":"","sum_comment":"","sum_unclear":false,"sum_foreign":""},"62":{"sum_foreign_comment":"","sum":"","sum_comment":"","sum_unclear":false,"sum_foreign":""},"63":{"sum_foreign_comment":"","sum":"64658","sum_comment":"","sum_hidden":false,"sum_comment_hidden":false,"sum_unclear":false,"sum_foreign":""},"64":{"sum_foreign_comment":"","sum_comment_hidden":false,"sum":"17648","sum_comment":"","sum_foreign":""}},"ft_src":"17648\n64658\n14282\nОдеса\n65049\nОдеська область\nсуддя южного міського суду одеської області\nОдеська область\nЗагальний місцевий суд\nКатерина\nБатьки\nДитина\nДитина\nАнатоліївна\nГоряінова\nГоряінова Катерина Анатоліївна\nГоряінова Катерина Анатоліївна\nКатерина Анатоліївна Горяінова\nКатерина Горяінова\nГоряінова Катерина Анатоліївна\n2300 куб.см..175 л. с\nMercedes CLK-230\n2000\n2520\n2014\n2300 куб.см..175 л. с\n2000\nMercedes CLK-230\n2520\n1502.5\nОдеська область\nКомінтернівський р-н., с. Широке\n456\nОвідіопольський р-н, с. Грибівка\nОдеська область\n193\nОвідіопольський р-н, с. Грибівка\nОдеська область\n580\nм. Одеса\nОдеська область\n421.7\nм. Одеса\nОдеська область\n136.1\nОдеська область\nм. Одеса\n111\nм. Одеса\nОдеська область\n76\nм. Одеса\nОдеська область\n313.3\nм. Одеса\nОдеська область\n40.8\nОдеська область\nм. Одеса\n18.2\nм. Одеса\nОдеська область\n499.2\nОвідіопольський р-н, с. Грибівка\nОдеська область\n129.25\nОвідіопольський р-н, с. Грибівка\nОдеська область\nАнатоліївна\nГоряінова Катерина Анатоліївна\nКатерина Анатоліївна Горяінова\nКатерина Горяінова\nГоряінова Катерина Анатоліївна\nКатерина\nБатьки\nДитина\nДитина\nГоряінова Катерина Анатоліївна\nЗагальний місцевий суд\nОдеська область\nсуддя южного міського суду одеської області\nГоряінова\nОдеса\n65049\nОдеська область\n64658\n17648\n14282\n822580\n15464\n11388\n15464\n1449028\n530704\n69356\n15000\n2014\n17648\n14282\n64658\nОдеська область\nОвідіопольський р-н, с. Грибівка\n456\nОдеська область\nОвідіопольський р-н, с. Грибівка\n193\nОдеська область\nм. Одеса\n580\nКомінтернівський р-н., с. Широке\n1502.5\nОдеська область\nм. Одеса\nОдеська область\n421.7\nм. Одеса\nОдеська область\n313.3\nОдеська область\nм. Одеса\n40.8\nОдеська область\nм. Одеса\n18.2\nОдеська область\nОвідіопольський р-н, с. Грибівка\n499.2\nОдеська область\nОвідіопольський р-н, с. Грибівка\n129.25\nм. Одеса\nОдеська область\n136.1\nм. Одеса\nОдеська область\n111\nОдеська область\nм. Одеса\n76\nБатьки\nДитина\nДитина\nАнатоліївна\nГоряінова\nГоряінова Катерина Анатоліївна\nКатерина Анатоліївна Горяінова\nКатерина Горяінова\nГоряінова Катерина Анатоліївна\nКатерина\nОдеська область\nОдеса\n65049\nОдеська область\nсуддя южного міського суду одеської області\nЗагальний місцевий суд\nГоряінова Катерина Анатоліївна\n530704\n1449028\n15464\n822580\n15000\n69356\n11388\n15464\n2000\n2300 куб.см..175 л. с\nMercedes CLK-230\n530704\n15000\n15464\n11388\n15464\n1449028\n822580\n69356\nм. Одеса\nОдеська область\n136.1\nм. Одеса\nОдеська область\n111\nм. Одеса\nОдеська область\n76\nм. Одеса\nОдеська область\n421.7\nОвідіопольський р-н, с. Грибівка\nОдеська область\n456\nОвідіопольський р-н, с. Грибівка\nОдеська область\n193\nм. Одеса\nОдеська область\n580\nм. Одеса\nОдеська область\n313.3\nм. Одеса\nОдеська область\n40.8\nм. Одеса\nОдеська область\n18.2\nОвідіопольський р-н, с. Грибівка\nОдеська область\n499.2\nОвідіопольський р-н, с. Грибівка\nОдеська область\n129.25\nОдеська область\nКомінтернівський р-н., с. Широке\n1502.5\n2520\n2014","general":{"name_hidden":false,"name":"Катерина","patronymic_unclear":false,"last_name_hidden":false,"inn":"","family":[{"inn":"","inn_hidden":false,"relations_unclear":false,"relations_hidden":false,"relations_other":"","relations":"Батьки","name_hidden":true,"inn_unclear":false,"family_name":"","name_unclear":false},{"inn":"","relations":"Дитина","relations_unclear":false,"family_name":"","inn_hidden":false,"relations_other":"","name_hidden":false,"inn_unclear":false,"name_unclear":false},{"inn":"","relations":"Дитина","inn_unclear":false,"family_name":"","inn_hidden":false,"relations_other":"","name_hidden":false,"name_unclear":false}],"patronymic":"Анатоліївна","inn_hidden":false,"family_raw":"","inn_unclear":false,"post":{"post_unclear":false,"region_unclear":false,"region":"Одеська область","office_hidden":false,"region_hidden":false,"post":"суддя южного міського суду одеської області","office_unclear":false,"office":"Загальний місцевий суд"},"last_name_unclear":false,"full_name":"Горяінова Катерина Анатоліївна","addresses":[{"place_city_type_unclear":false,"place_address":"65049","place_district_hidden":false,"place_city_type":"Місто","place_address_hidden":true,"place_address_unclear":false,"place_city_type_hidden":false,"place":"Одеська область","place_district":"","place_unclear":false,"place_city":"Одеса","place_city_unclear":false,"place_hidden":false,"place_city_hidden":false,"place_district_unclear":false}],"last_name":"Горяінова","full_name_suggest":{"output":"Горяінова Катерина Анатоліївна","input":["Горяінова Катерина Анатоліївна","Катерина Анатоліївна Горяінова","Катерина Горяінова"]},"name_unclear":false},"source":"VULYK","estate":{"23":[{"space_unclear":false,"costs":"","costs_comment":"","costs_hidden":false,"address_hidden":false,"region_hidden":false,"space_comment":"","space_hidden":false,"space":"1502.5","address":"Комінтернівський р-н., с. Широке","region":"Одеська область","space_units_unclear":false,"costs_rent_hidden":false,"space_units":"м²","space_units_hidden":false,"costs_rent":"","costs_rent_comment":""}],"29":[{"space_hidden":false,"costs_property_comment":"","address_hidden":false,"region_hidden":false,"space_comment":"","space_unclear":false,"space":"456","address":"Овідіопольський р-н, с. Грибівка","region":"Одеська область","costs_property":"","costs_rent_comment":"","address_unclear":false,"space_units":"м²","space_units_unclear":false,"costs_rent":""},{"costs_rent":"","region":"Одеська область","costs_property":"","costs_rent_comment":"","region_hidden":false,"space_comment":"","costs_property_comment":"","space_units":"м²","space":"193","address":"Овідіопольський р-н, с. Грибівка"},{"costs_rent":"","region":"Одеська область","costs_property":"","costs_rent_comment":"","space_comment":"","costs_property_comment":"","space_units":"м²","space":"580","address":"м. Одеса"}],"30":[{"space_unclear":false,"address_hidden":false,"region_hidden":false,"space_comment":"","space_hidden":false,"space":"421.7","address":"м. Одеса","region":"Одеська область","costs_property":"","costs_rent_comment":"","space_units":"м²","costs_property_comment":"","costs_rent":""}],"31":[{"space_unclear":false,"costs_property_hidden":false,"address_hidden":false,"region_hidden":false,"space_comment":"","space_hidden":false,"space":"136.1","address":"м. Одеса","costs_property_comment_hidden":false,"region":"Одеська область","costs_property":"","space_units_unclear":false,"costs_rent_hidden":false,"space_comment_unclear":false,"costs_rent_comment_hidden":false,"space_units":"м²","costs_property_comment":"","costs_rent":"","costs_rent_comment":""},{"address_hidden":false,"region_hidden":false,"space_comment":"","space":"111","address":"м. Одеса","region":"Одеська область","costs_property":"","costs_rent_comment":"","space_comment_unclear":false,"space_units":"м²","costs_property_comment":"","costs_rent":""},{"costs_rent":"","region":"Одеська область","costs_property":"","costs_rent_comment":"","region_hidden":false,"space_comment":"","costs_property_comment":"","space_units":"м²","space":"76","address":"м. Одеса"}],"34":[{"region_unclear":false,"space_hidden":false,"costs_property_hidden":false,"costs_property":"","address_hidden":false,"region_hidden":false,"space_comment":"","space_unclear":false,"space":"313.3","address":"м. Одеса","costs_property_comment_hidden":false,"region":"Одеська область","address_unclear":false,"costs_rent_comment":"","costs_rent_hidden":false,"costs_rent_comment_hidden":false,"space_units":"м²","costs_property_comment":"","costs_rent":""},{"costs_rent":"","space_unclear":false,"region":"Одеська область","costs_property":"","costs_rent_comment":"","space_comment":"","costs_property_comment":"","space_units":"","space":"40.8","address":"м. Одеса"},{"costs_rent":"","region":"Одеська область","costs_property":"","costs_rent_comment":"","space_comment":"","costs_property_comment":"","space_units":"","space":"18.2","address":"м. Одеса"},{"costs_rent":"","region":"Одеська область","costs_property":"","costs_rent_comment":"","space_comment":"","costs_property_comment":"","space_units":"","space":"499.2","address":"Овідіопольський р-н, с. Грибівка"},{"costs_rent":"","region":"Одеська область","costs_property":"","costs_rent_comment":"","space_comment":"","costs_property_comment":"","space_units":"","space":"129.25","address":"Овідіопольський р-н, с. Грибівка"}]},"intro":{"declaration_year":"2014","isnotdeclaration":"","declaration_year_unclear":false}}