{"income":{"5":{"value":"254562","family_comment":"","comment_unclear":false,"family_unclear":false,"family":"","comment":""},"6":{"family_comment":"","value":"245274","family":"","comment":""},"7":{"source_name_unclear":false,"value":"","comment_unclear":false,"family_comment":"","source_name":"","family":"","comment":""},"8":{"family_comment":"","value":"","family":"","comment":""},"9":{"family_comment":"","value":"9285","family":"","comment":""},"10":{"family_comment":"","value":"","family":"","comment":""},"11":{"family_comment":"","value":"","family":"","comment":""},"12":{"family_comment":"","value":"","family":"","comment":""},"13":{"family_comment":"","value":"","family":"","comment":""},"14":{"family_comment":"","value":"","family":"","comment":""},"15":{"family_comment":"","value":"","family":"","comment":""},"16":{"family_comment":"","family_unclear":false,"value":"","family":"","comment":""},"17":{"family_comment":"","value":"","family":"","comment":""},"18":{"family_comment":"","value":"","family":"","comment":""},"19":{"family_comment":"","value":"","family":"","comment":""},"20":{"value":"3","family_comment":"","comment_unclear":false,"family_unclear":false,"family":"","comment":"","family_comment_unclear":false}},"id":"vulyk_107_85","banks":{"45":[{"sum_foreign_comment":"","sum_units":"UAH","sum_comment":"","sum_comment_unclear":false,"sum_foreign_units":"UAH","sum_comment_hidden":false,"sum_unclear":false,"sum":"71600","sum_foreign":""}],"47":[{"sum_foreign_comment":"","sum_units":"UAH","sum_comment":"","sum_foreign_units":"UAH","sum_comment_hidden":false,"sum":"1056.8","sum_foreign":""}]},"declaration":{"additional_info_text":"","notfull_lostpages":"","date":"2016-03-28T00:00:00","notfull":"","additional_info":"","url":"http://static.declarations.com.ua/declarations/chosen_ones/judges_batch/2064_luzan_larysa_viktorivna.pdf"},"liabilities":{"54":{"sum_foreign_comment":"","sum":"","sum_comment":"","sum_comment_unclear":false,"sum_comment_hidden":false,"sum_foreign":""},"55":{"sum_foreign_comment":"","sum":"","sum_comment":"","sum_foreign":""},"56":{"sum_foreign_comment":"","sum":"","sum_comment":"","sum_unclear":false,"sum_foreign":""},"57":{"sum_foreign_comment":"","sum":"","sum_comment":"","sum_comment_unclear":false,"sum_foreign":""},"58":{"sum_foreign_comment":"","sum":"","sum_comment":"","sum_comment_unclear":false,"sum_unclear":false,"sum_foreign":""},"59":{"sum_foreign_comment":"","sum":"","sum_comment":"","sum_unclear":false,"sum_foreign":""},"60":{"sum_foreign_comment":"","sum":"","sum_comment":"","sum_comment_unclear":false,"sum_comment_hidden":false,"sum_foreign":""},"61":{"sum_foreign_comment":"","sum":"","sum_comment":"","sum_foreign":""},"62":{"sum_foreign_comment":"","sum":"","sum_comment":"","sum_foreign":""},"63":{"sum_foreign_comment":"","sum":"","sum_comment":"","sum_foreign":""},"64":{"sum_foreign_comment":"","sum":"","sum_comment":"","sum_foreign":""}},"ft_src":"Лузан Лариса Вікторівна\nсуддя апеляційного суду сумської області\nСумська область\nЗагальний апеляційний суд\nЛариса\nЛузан Лариса Вікторівна\nЛариса Вікторівна Лузан\nЛариса Лузан\nЛузан Лариса Вікторівна\nЛузан\nВікторівна\n9285\n3\n254562\n245274\n1056.8\n71600\n22\n18\n35.2\n2015\n245274\n9285\n254562\n3\n71600\n1056.8\n2015\nЛузан\nЛузан Лариса Вікторівна\nЛариса Вікторівна Лузан\nЛариса Лузан\nЛузан Лариса Вікторівна\nЛариса\nВікторівна\nЛузан Лариса Вікторівна\nЗагальний апеляційний суд\nсуддя апеляційного суду сумської області\nСумська область\n245274\n3\n254562\n9285\n22\n18\n35.2\nЛузан\nВікторівна\nсуддя апеляційного суду сумської області\nСумська область\nЗагальний апеляційний суд\nЛузан Лариса Вікторівна\nЛузан Лариса Вікторівна\nЛариса Вікторівна Лузан\nЛариса Лузан\nЛузан Лариса Вікторівна\nЛариса\n35.2\n22\n18\n1056.8\n71600\n2015","general":{"inn":"","inn_hidden":true,"last_name":"Лузан","post":{"post_unclear":false,"office":"Загальний апеляційний суд","post":"суддя апеляційного суду сумської області","region":"Сумська область"},"name":"Лариса","full_name":"Лузан Лариса Вікторівна","family_raw":"","addresses":[{"place_district":"","place_city_hidden":true,"place_city":"","place_city_type_hidden":true,"place_district_hidden":true,"place_city_type":"","place_address_hidden":true,"place_address":"","place_hidden":true,"place":""}],"full_name_suggest":{"output":"Лузан Лариса Вікторівна","input":["Лузан Лариса Вікторівна","Лариса Вікторівна Лузан","Лариса Лузан"]},"patronymic":"Вікторівна"},"source":"VULYK","estate":{"23":[{"costs":"","costs_comment":"","address_hidden":true,"region_hidden":true,"space_comment":"","space":"22","address":"","region":"","costs_rent_comment":"","space_comment_unclear":false,"space_comment_hidden":false,"space_units":"м²","costs_rent":""}],"25":[{"space_hidden":false,"costs":"","costs_comment":"","address_hidden":true,"region_hidden":true,"space_comment":"","space_unclear":false,"space":"35.2","address":"","region":"","costs_rent_comment":"","space_units":"м²","costs_rent":""}],"27":[{"space_hidden":false,"costs":"","costs_comment":"","address_hidden":true,"region_hidden":true,"space_comment":"","space":"18","address":"","region":"","costs_rent_comment":"","space_units":"м²","costs_rent":""}]},"intro":{"declaration_year":"2015","isnotdeclaration":""}}