{"income":{"5":{"family_comment":"","value":"255196","family":"14731","comment":""},"6":{"family_comment":"","value":"253106","family":"","comment":""},"7":{"value":"","comment_hidden":false,"value_hidden":false,"family_comment":"","source_name":"","family":"","comment":"","source_name_hidden":false},"8":{"family_comment":"","value":"","family":"","comment":""},"9":{"value":"","comment_hidden":false,"family_comment":"","family":"","comment":"","family_comment_unclear":false},"10":{"family_comment":"","value":"","family":"","comment":""},"11":{"family_comment":"","value":"","comment_hidden":false,"family":"","comment":""},"12":{"family_comment":"","value":"","family":"","comment":""},"13":{"family_comment":"","value":"","family":"","comment":""},"14":{"family_comment":"","value":"2090","family":"","comment":"1 черга, кошти (рухоме майно), нерухоме майно"},"15":{"family_comment":"","value":"","family":"","comment":""},"16":{"family_comment":"","value":"","family":"","comment":""},"17":{"family_comment":"","value":"","family":"","comment":""},"18":{"family_comment":"","value":"","family":"","comment":""},"19":{"family_comment":"","value":"","family":"","comment":""},"20":{"family_comment":"пенсія за віком","value":"","comment_hidden":false,"family":"14731","comment":""}},"id":"vulyk_102_121","banks":{"45":[{"sum_foreign_comment":"","sum_units":"UAH","sum_comment":"залишок на зарплатній картці","sum_comment_unclear":false,"sum_hidden":false,"sum_foreign_units":"UAH","sum_comment_hidden":false,"sum_unclear":false,"sum":"2189","sum_foreign":""}],"51":[{"sum_foreign_comment":"","sum_units":"UAH","sum_comment":"залишок на пенсійній карті","sum_comment_unclear":true,"sum_foreign_comment_hidden":false,"sum_hidden":false,"sum_foreign_units":"UAH","sum_comment_hidden":false,"sum_unclear":false,"sum":"7230","sum_foreign":""}],"52":[{"sum_foreign_comment":"","sum_units":"UAH","sum_comment":"","sum_comment_unclear":true,"sum_hidden":false,"sum_foreign_units":"UAH","sum_comment_hidden":false,"sum":"680","sum_foreign":""}]},"declaration":{"date":"2016-03-28T00:00:00","additional_info_text":"","additional_info":"","url":"http://static.declarations.com.ua/declarations/chosen_ones/judges_batch/1195_frolova_hanna_mykolaivna.pdf"},"liabilities":{"54":{"sum_foreign_comment":"","sum":"","sum_comment":"","sum_hidden":false,"sum_comment_hidden":false,"sum_foreign":""},"55":{"sum_foreign_comment":"","sum":"","sum_comment":"","sum_foreign":""},"56":{"sum_foreign_comment":"","sum":"","sum_comment":"","sum_foreign":""},"57":{"sum_foreign_comment":"","sum_comment":"","sum":"","sum_comment_hidden":false,"sum_foreign":""},"58":{"sum_foreign_comment":"","sum_comment":"","sum":"","sum_comment_hidden":false,"sum_foreign":""},"59":{"sum_foreign_comment":"","sum_comment":"","sum":"","sum_comment_hidden":false,"sum_foreign":""},"60":{"sum_foreign_comment":"","sum":"","sum_comment":"","sum_hidden":false,"sum_comment_hidden":false,"sum_foreign":""},"61":{"sum_foreign_comment":"","sum":"","sum_comment":"","sum_foreign":""},"62":{"sum_foreign_comment":"","sum":"","sum_comment":"","sum_unclear":false,"sum_foreign":""},"63":{"sum_foreign_comment":"","sum":"","sum_comment":"","sum_hidden":false,"sum_comment_hidden":false,"sum_foreign":""},"64":{"sum_foreign_comment":"","sum_comment":"","sum":"","sum_comment_hidden":false,"sum_foreign":""}},"ft_src":"5/7\n128.6\n333\n641\n54.2\n2/7, 1/7 спадщина 1 черга\n128.6\nспадщина 1 черга\n70.7\n680\nзалишок на пенсійній карті\n7230\nзалишок на зарплатній картці\n2189\n2015\n2015\nФролова Ганна Миколаївна\nГанна Миколаївна Фролова\nГанна Фролова\nФролова Ганна Миколаївна\nФролова Ганна Миколаївна\nГанна\nМиколаївна\nсуддя вищого господарського суду україни\nЗагальнодержавний регіон\nВищий господарський суд\nФролова\nДитина\nМейтус Є. В\nДитина\nМейтус А. В\nБатьки\nФролова Г. В\n253106\n14731\nпенсія за віком\n1 черга, кошти (рухоме майно), нерухоме майно\n2090\n255196\n14731\n333\n641\n128.6\n5/7\n128.6\n2/7, 1/7 спадщина 1 черга\n70.7\nспадщина 1 черга\n54.2\n2189\nзалишок на зарплатній картці\nзалишок на пенсійній карті\n7230\n680\n253106\n1 черга, кошти (рухоме майно), нерухоме майно\n2090\n14731\n255196\n14731\nпенсія за віком\nМейтус Є. В\nДитина\nДитина\nМейтус А. В\nБатьки\nФролова Г. В\nГанна\nМиколаївна\nФролова\nФролова Ганна Миколаївна\nГанна Миколаївна Фролова\nГанна Фролова\nФролова Ганна Миколаївна\nсуддя вищого господарського суду україни\nЗагальнодержавний регіон\nВищий господарський суд\nФролова Ганна Миколаївна","general":{"inn":"","name":"Ганна","family":[{"inn":"","relations":"Дитина","name_hidden":true,"inn_hidden":true,"family_name":"Мейтус Є. В","name_unclear":false},{"inn":"","relations":"Дитина","relations_other":"","inn_hidden":true,"family_name":"Мейтус А. В","name_hidden":false,"name_unclear":false},{"inn":"","relations":"Батьки","relations_other":"","inn_hidden":false,"family_name":"Фролова Г. В","name_hidden":false,"name_unclear":false}],"patronymic":"Миколаївна","inn_hidden":true,"family_raw":"","last_name":"Фролова","post":{"region":"Загальнодержавний регіон","region_unclear":false,"post":"суддя вищого господарського суду україни","office_unclear":false,"office":"Вищий господарський суд"},"full_name":"Фролова Ганна Миколаївна","addresses":[{"place_district":"","place_address_hidden":true,"place_city":"","place_address":"","place_district_hidden":true,"place_city_type":"","place_city_hidden":true,"place_city_type_hidden":true,"place_hidden":true,"place":""}],"patronymic_hidden":false,"full_name_suggest":{"output":"Фролова Ганна Миколаївна","input":["Фролова Ганна Миколаївна","Ганна Миколаївна Фролова","Ганна Фролова"]}},"source":"VULYK","estate":{"25":[{"costs":"","costs_comment":"","address_hidden":true,"region_hidden":true,"space_comment":"2/7, 1/7 спадщина 1 черга","space":"128.6","address":"","region":"","address_unclear":false,"costs_rent_comment":"","space_units":"м²","costs_rent":""},{"costs_rent":"","region":"","costs":"","costs_rent_comment":"","costs_comment":"","region_hidden":false,"space_comment":"спадщина 1 черга","space_units":"м²","space":"70.7","address":""}],"29":[{"address_hidden":true,"region_hidden":true,"space_comment":"","space":"333","address":"","region":"","costs_property":"","costs_rent_comment":"","space_comment_hidden":false,"space_units":"м²","costs_property_comment":"","costs_rent":""},{"costs_rent":"","region":"","costs_property":"","costs_rent_comment":"","address_hidden":false,"region_hidden":false,"space_comment":"","costs_property_comment":"","space_units":"м²","space":"641","address":""}],"31":[{"costs_rent":"","region":"","costs_property":"","costs_rent_comment":"","address_hidden":true,"region_hidden":true,"space_comment":"5/7","costs_property_comment":"","space_units":"м²","space":"128.6","address":""}],"32":[{"costs_rent":"","region":"","costs_property":"","costs_rent_comment":"","address_hidden":true,"region_hidden":true,"space_comment":"","costs_property_comment":"","space_units":"м²","space":"54.2","address":""}]},"intro":{"declaration_year":"2015"}}