{"id":"vulyk_101_104","ft_src":"Suzuki Grand Vitara\n2400 куб. см.\n2008\n1500 куб. см.\n2004\nВАЗ 2107\n41.4\n1/3 частина\n64.4\n2015\n122453\n247262\nЛьвівське регіональне відділення Національної школі суддів України\n1659\n122453\n261452\nпенсія\n12531\nSuzuki Grand Vitara\n2400 куб. см.\n2008\n1500 куб. см.\n2004\nВАЗ 2107\n2015\nПодружжя\nСтельмах К. В\nДитина\nСтельмах Т. І\nСтельмах Ігор Орестович\nІгор Орестович Стельмах\nІгор Стельмах\nСтельмах Ігор Орестович\nІгор\nСтельмах Ігор Орестович\nОрестович\nЗагальний апеляційний суд\nсуддя апеляційного суду львівської області\nЛьвівська область\nСтельмах\n1659\nЛьвівське регіональне відділення Національної школі суддів України\n247262\n122453\nпенсія\n12531\n261452\n122453\n41.4\n64.4\n1/3 частина\nСтельмах К. В\nПодружжя\nСтельмах Т. І\nДитина\nІгор\nОрестович\nСтельмах\nСтельмах Ігор Орестович\nІгор Орестович Стельмах\nІгор Стельмах\nСтельмах Ігор Орестович\nсуддя апеляційного суду львівської області\nЗагальний апеляційний суд\nЛьвівська область\nСтельмах Ігор Орестович","estate":{"25":[{"address":"","space_units":"м²","space_hidden":false,"space_unclear":false,"region_hidden":true,"costs_comment":"","space_comment":"1/3 частина","address_hidden":false,"space":"64.4","space_comment_unclear":false,"costs_rent_comment":"","costs":"","region":"","costs_rent":""}],"31":[{"costs_property_comment":"","address":"","space_units":"м²","space_hidden":false,"space_unclear":false,"region_hidden":true,"costs_property":"","space_comment":"","address_hidden":false,"costs_rent_comment_unclear":false,"costs_rent_comment":"","space":"41.4","region":"","costs_rent":""}]},"vehicle":{"35":[{"sum_comment":"","brand_info_hidden":false,"sum_rent":"","sum":"","brand_unclear":false,"year":"2008","brand":"Suzuki Grand Vitara","brand_info":"2400 куб. см.","sum_rent_comment":"","brand_info_unclear":false,"sum_rent_unclear":false},{"sum_comment":"","brand_info":"1500 куб. см.","sum":"","sum_rent_comment":"","year":"2004","brand":"ВАЗ 2107","sum_rent":"","brand_info_unclear":false}]},"source":"VULYK","income":{"5":{"family_comment":"","value":"261452","family":"122453","comment":"","value_unclear":false},"6":{"family_comment":"","family":"122453","comment":"","value_unclear":false,"family_hidden":false,"value":"247262"},"7":{"family_comment":"","comment":"","family":"","source_name_unclear":false,"value":"1659","source_name":"Львівське регіональне відділення Національної школі суддів України"},"8":{"family_comment":"","value":"","family":"","comment":""},"9":{"family_comment":"","value":"","family":"","comment":""},"10":{"family_comment":"","value":"","family":"","comment":""},"11":{"family_comment":"","comment_unclear":false,"value":"","family":"","comment":""},"12":{"family_comment":"","value":"","family":"","comment":""},"13":{"family_comment":"","value":"","family":"","comment":""},"14":{"family_comment":"","value":"","family":"","comment":""},"15":{"family_comment":"","value":"","family":"","comment":""},"16":{"family_comment":"","value":"","family":"","comment":""},"17":{"family_comment":"","value":"","family":"","comment":""},"18":{"family_comment":"","value":"","family":"","comment":""},"19":{"family_comment":"","value":"","family":"","comment":""},"20":{"family_comment":"","family":"","comment":"пенсія","value_unclear":false,"family_unclear":false,"comment_unclear":false,"value":"12531"}},"general":{"family":[{"inn":"","family_name":"Стельмах К. В","relations_other":"","name_unclear":false,"inn_hidden":true,"name_hidden":true,"relations":"Подружжя"},{"inn":"","family_name":"Стельмах Т. І","relations_other":"","relations_unclear":false,"name_unclear":false,"inn_hidden":false,"name_hidden":false,"relations":"Дитина"}],"family_raw":"","name":"Ігор","full_name_suggest":{"input":["Стельмах Ігор Орестович","Ігор Орестович Стельмах","Ігор Стельмах"],"output":"Стельмах Ігор Орестович"},"patronymic":"Орестович","inn_hidden":true,"addresses":[{"place_city_type_hidden":false,"place_city_type":"","place_city_hidden":true,"place_hidden":true,"place_district":"","place_district_hidden":false,"place":"","place_address":"","place_address_hidden":true,"place_city":""}],"patronymic_hidden":false,"inn":"","inn_unclear":false,"last_name":"Стельмах","full_name":"Стельмах Ігор Орестович","post":{"office":"Загальний апеляційний суд","region_unclear":false,"post":"суддя апеляційного суду львівської області","region":"Львівська область","office_unclear":false}},"liabilities":{"54":{"sum_comment_unclear":false,"sum_comment":"","sum_hidden":false,"sum":"","sum_foreign_comment":"","sum_foreign":"","sum_unclear":false,"sum_comment_hidden":false},"55":{"sum_comment":"","sum_foreign_comment":"","sum_foreign":"","sum":""},"56":{"sum_comment":"","sum":"","sum_foreign_comment":"","sum_foreign":"","sum_unclear":false,"sum_comment_hidden":false},"57":{"sum_comment":"","sum_hidden":false,"sum":"","sum_foreign_comment":"","sum_foreign":"","sum_unclear":false,"sum_comment_hidden":false},"58":{"sum_comment_unclear":false,"sum_comment":"","sum_hidden":false,"sum":"","sum_foreign_comment":"","sum_foreign":"","sum_unclear":false,"sum_comment_hidden":false},"59":{"sum_comment":"","sum_foreign_comment":"","sum_foreign":"","sum":""},"60":{"sum_comment":"","sum_hidden":false,"sum":"","sum_foreign_comment":"","sum_foreign":"","sum_unclear":false,"sum_comment_hidden":false},"61":{"sum_comment":"","sum_foreign_comment":"","sum_foreign":"","sum":""},"62":{"sum_comment":"","sum_comment_unclear":false,"sum_foreign_comment":"","sum":"","sum_foreign":""},"63":{"sum_comment":"","sum_foreign_comment":"","sum_foreign":"","sum":"","sum_comment_hidden":false},"64":{"sum_comment":"","sum_foreign_comment":"","sum_foreign":"","sum":"","sum_comment_hidden":false}},"declaration":{"notfull_lostpages":"","additional_info_text":"","additional_info":"","date":"2016-03-15T00:00:00","notfull":"","url":"http://static.declarations.com.ua/declarations/chosen_ones/judges_batch/776_stelmakh_ihor_orestovych_2015.pdf"},"intro":{"declaration_year":"2015"}}