{"id":"vulyk_109_57","ft_src":"2012\n2003\n2011\n2145 куб. см., 150 кВт\n2012\nMercedes-Benz ML-Class\n20000\n2212\n20000\n125\nТОВ ЮФ 'Легіс'\n16500\nТОВ 'Метаксія 2011'\n650\nПП 'Тер-Буд'\n25\nПП 'Сігель'\n1000\n2015\n2012\n2003\n2011\n2145 куб. см., 150 кВт\n2012\nMercedes-Benz ML-Class\n2015\nНіколенко Михайло Олександрович\nМихайло Олександрович Ніколенко\nМихайло Ніколенко\nНіколенко Михайло Олександрович\nМихайло\nПодружжя\nНіколенко Тетяна Сергіївна\nДитина\nНіколенко Анастасія Михайлівна\nДитина\nНіколенко Олександр Михайлович\nНіколенко Михайло Олександрович\nОлександрович\nГосподарський місцевий суд\nДніпропетровська область\nсуддя господарського суду дніпропетровської області\nНіколенко\n185004\n18000\n386150\n650\n94642\n3469\n283115\n404800\n20000\n2212\n20000\n125\n16500\nТОВ ЮФ 'Легіс'\nТОВ 'Метаксія 2011'\n650\n25\nПП 'Тер-Буд'\n1000\nПП 'Сігель'\n18000\n185004\n3469\n650\n404800\n283115\n386150\n94642\nПодружжя\nНіколенко Тетяна Сергіївна\nДитина\nНіколенко Анастасія Михайлівна\nДитина\nНіколенко Олександр Михайлович\nОлександрович\nНіколенко\nМихайло\nНіколенко Михайло Олександрович\nМихайло Олександрович Ніколенко\nМихайло Ніколенко\nНіколенко Михайло Олександрович\nДніпропетровська область\nГосподарський місцевий суд\nсуддя господарського суду дніпропетровської області\nНіколенко Михайло Олександрович","estate":{"23":[{"address":"","space_units":"м²","costs_rent_unclear":false,"costs_comment":"","space_unclear":false,"region_hidden":true,"space_comment":"","address_hidden":true,"costs":"","costs_rent_comment":"","space":"20000","region":"","costs_rent":""}],"25":[{"address":"","space_units":"м²","space_hidden":false,"space_unclear":false,"region_hidden":false,"costs_comment":"","space_comment":"","address_hidden":true,"space":"125","costs_rent_comment":"","costs":"","region":"","space_units_hidden":false,"costs_rent":""}],"29":[{"costs_property_comment":"","address":"","space_units":"м²","space_unclear":false,"region_hidden":true,"costs_property":"","space_comment":"","address_hidden":true,"costs_rent_comment":"","space":"2212","region":"","costs_rent":""},{"costs_property_comment":"","address":"","space_units":"м²","costs_rent_comment":"","space":"20000","costs_property":"","space_comment":"","costs_rent":""}]},"vehicle":{"35":[{"sum_comment_unclear":false,"brand_info":"","sum_rent_comment":"","brand_unclear":false,"brand_hidden":true,"year":"2012","sum_comment":"","brand_info_hidden":true,"sum_rent":"","brand":"","year_unclear":false,"brand_info_unclear":false,"sum":""},{"sum_comment":"","brand_info":"","sum":"","sum_rent_comment":"","year":"2003","brand":"","sum_rent":""},{"sum_comment":"","brand_info":"","sum":"","sum_rent_comment":"","year":"2011","brand":"","sum_rent":""}],"40":[{"sum_comment":"","brand_info":"2145 куб. см., 150 кВт","sum":"","sum_rent_comment":"","year":"2012","brand":"Mercedes-Benz ML-Class","sum_rent":"","brand_info_unclear":false}]},"source":"VULYK","income":{"5":{"family_comment":"","value":"283115","family":"404800","comment":""},"6":{"family_comment":"","value":"185004","family":"18000","comment":""},"7":{"source_name_hidden":false,"family_comment":"","comment":"","family":"","comment_hidden":false,"value":"","source_name":""},"8":{"family_comment":"","family_hidden":false,"value":"","family":"","comment":""},"9":{"family_comment":"","family":"","comment":"","value_unclear":false,"family_unclear":false,"value":""},"10":{"family_comment":"","value":"","family":"","comment":""},"11":{"family_comment":"","value":"","family":"","comment":""},"12":{"family_comment":"","value":"","family":"","comment":""},"13":{"family_comment":"","value":"","family":"","comment":""},"14":{"family_comment":"","value":"","family":"","comment":""},"15":{"family_comment":"","value":"3469","family":"","comment":""},"16":{"family_comment":"","value":"","family":"","comment":""},"17":{"family_comment":"","value":"","family":"386150","comment":""},"18":{"family_comment":"","value":"","family":"650","comment":""},"19":{"family_comment":"","value":"","family":"","comment":""},"20":{"family_comment":"","family":"","comment":"","value_unclear":false,"family_hidden":false,"value":"94642"}},"banks":{"53":[{"sum_comment_unclear":true,"sum_units":"UAH","sum_foreign_units_hidden":false,"sum_foreign_units":"UAH","sum":"16500","sum_foreign_comment":"","sum_comment":"ТОВ ЮФ 'Легіс'","sum_foreign":"","sum_comment_hidden":false,"sum_foreign_hidden":false},{"sum_comment":"ТОВ 'Метаксія 2011'","sum_units":"UAH","sum_foreign":"","sum":"650","sum_foreign_comment":""},{"sum_comment_unclear":true,"sum_comment":"ПП 'Тер-Буд'","sum":"25","sum_foreign_comment":"","sum_foreign":"","sum_units":"UAH"},{"sum_comment_unclear":true,"sum_comment":"ПП 'Сігель'","sum":"1000","sum_foreign_comment":"","sum_foreign":"","sum_units":"UAH"}]},"declaration":{"notfull_lostpages":"","additional_info_text":"","additional_info":"","date":"2016-03-31T00:00:00","notfull":"","url":"http://static.declarations.com.ua/declarations/chosen_ones/judges_batch/2514_nikolenko_mykhailo_oleksandrovych_2015.pdf"},"general":{"family_raw":"","name":"Михайло","full_name_suggest":{"input":["Ніколенко Михайло Олександрович","Михайло Олександрович Ніколенко","Михайло Ніколенко"],"output":"Ніколенко Михайло Олександрович"},"patronymic":"Олександрович","inn_hidden":true,"addresses":[{"place_city_type_hidden":true,"place_city_type":"","place_city_hidden":true,"place_hidden":true,"place_district":"","place_district_hidden":true,"place":"","place_address":"","place_address_hidden":true,"place_city":""}],"inn":"","inn_unclear":false,"last_name":"Ніколенко","full_name":"Ніколенко Михайло Олександрович","family":[{"inn":"","family_name":"Ніколенко Тетяна Сергіївна","relations_hidden":false,"name_unclear":false,"relations":"Подружжя","inn_hidden":true,"name_hidden":true,"relations_other":""},{"inn":"","family_name":"Ніколенко Анастасія Михайлівна","relations_other":"","name_unclear":false,"inn_hidden":false,"name_hidden":false,"relations":"Дитина"},{"inn":"","family_name":"Ніколенко Олександр Михайлович","relations_other":"","name_unclear":false,"inn_hidden":true,"name_hidden":false,"relations":"Дитина"}],"post":{"office":"Господарський місцевий суд","post":"суддя господарського суду дніпропетровської області","office_unclear":false,"region_hidden":false,"region":"Дніпропетровська область","office_hidden":false,"region_unclear":false},"name_hidden":false},"liabilities":{"54":{"sum_comment":"","sum_hidden":false,"sum":"","sum_foreign_comment":"","sum_foreign":"","sum_unclear":false,"sum_comment_hidden":false},"55":{"sum_comment":"","sum_comment_unclear":false,"sum_foreign_comment":"","sum":"","sum_foreign":""},"56":{"sum_comment":"","sum_foreign_comment":"","sum_foreign":"","sum":""},"57":{"sum_comment":"","sum_foreign_comment":"","sum_foreign":"","sum":"","sum_comment_hidden":false},"58":{"sum_comment":"","sum_foreign_comment":"","sum_foreign":"","sum":"","sum_comment_hidden":false},"59":{"sum_comment":"","sum_foreign_comment":"","sum_foreign":"","sum":""},"60":{"sum_comment":"","sum_foreign_comment":"","sum_foreign":"","sum":""},"61":{"sum_comment":"","sum_foreign_comment":"","sum_foreign":"","sum":""},"62":{"sum_comment":"","sum_foreign_comment":"","sum_foreign":"","sum":""},"63":{"sum_comment":"","sum_foreign_comment":"","sum_foreign":"","sum":""},"64":{"sum_comment":"","sum_foreign_comment":"","sum_foreign":"","sum":""}},"intro":{"isnotdeclaration":"","declaration_year":"2015"}}