{"income":{"5":{"value":"217598","family_comment":"","value_unclear":false,"family_hidden":false,"value_hidden":false,"family_unclear":false,"family":"288340","comment":""},"6":{"family_comment":"","value":"217598","family":"","comment":"","value_hidden":false},"7":{"value":"","family_comment":"","source_name":"","family":"","comment":"","source_name_hidden":false},"8":{"value":"","family_hidden":false,"value_hidden":false,"family_comment":"","family":"","comment":""},"9":{"family_comment":"","value":"","value_unclear":false,"family":"","comment":""},"10":{"family_comment":"","value":"","family":"","comment":"","value_hidden":false},"11":{"family_comment":"","value":"","family":"","comment":""},"12":{"family_comment":"","value":"","family":"","comment":""},"13":{"family_comment":"","value":"","family":"","comment":""},"14":{"family_comment":"","value":"","family":"","comment":""},"15":{"family_comment":"","value":"","family":"","comment":""},"16":{"value":"","value_unclear":false,"family_hidden":false,"family_comment":"","family":"","comment":""},"17":{"value":"","family_hidden":false,"value_hidden":false,"family_comment":"","family":"269780","comment":""},"18":{"value":"","family_hidden":false,"value_hidden":false,"family_comment":"","family":"","comment":""},"19":{"family_comment":"","value":"","family":"18560","comment":""},"20":{"value":"","value_unclear":false,"comment_hidden":false,"value_hidden":false,"family_comment":"","comment_unclear":false,"comment":"","family":""}},"vehicle":{"35":[{"brand_info":"1995 куб. см., спільна сумісна власність подружжя","sum_rent_comment":"","sum_rent_hidden":false,"year":"2008","brand_info_hidden":false,"brand_info_unclear":false,"sum_rent":"","sum":"","brand":"Suzuki Grand Vitara","sum_comment":"","brand_unclear":false,"brand_hidden":false}],"41":[{"brand_info":"2799 куб. см. спільна сумісна власність подружжя","sum_rent_comment":"","brand":"Renault Master","sum_comment":"","brand_unclear":false,"year":"2000","brand_hidden":false,"brand_info_unclear":false,"sum":"","sum_rent":""}]},"id":"vulyk_30_152","banks":{"45":[{"sum_foreign_comment":"","sum":"","sum_comment":"","sum_comment_unclear":false,"sum_hidden":false,"sum_foreign_units":"UAH","sum_foreign_hidden":false,"sum_units":"UAH","sum_comment_hidden":false,"sum_unclear":false,"sum_foreign":""},{"sum_foreign_comment":"","sum_units":"","sum_comment":"","sum_foreign_units":"","sum":"","sum_foreign":""},{"sum_foreign_comment":"","sum_units":"","sum_comment":"","sum_foreign_units":"","sum":"","sum_foreign":""}],"46":[{"sum_foreign_comment":"","sum_units":"UAH","sum_comment":"","sum_hidden":false,"sum_foreign_units":"UAH","sum_foreign_hidden":false,"sum_comment_hidden":false,"sum_unclear":false,"sum":"","sum_foreign":""},{"sum_foreign_comment":"","sum_units":"","sum_comment":"","sum_foreign_units":"","sum":"","sum_foreign":""}],"47":[{"sum_foreign_comment":"","sum_units":"UAH","sum_comment":"","sum_hidden":false,"sum_foreign_units":"UAH","sum":"","sum_foreign_hidden":false,"sum_foreign":""}],"48":[{"sum_foreign_comment":"","sum_units":"UAH","sum_comment":"","sum_hidden":false,"sum_foreign_units":"UAH","sum":"","sum_foreign_hidden":false,"sum_foreign":""}],"49":[{"sum_foreign_comment":"","sum_units":"UAH","sum_comment":"","sum_hidden":false,"sum_foreign_units":"UAH","sum":"","sum_foreign_hidden":false,"sum_foreign":""}],"50":[{"sum_foreign_comment":"","sum_units":"UAH","sum_comment":"","sum_hidden":false,"sum_foreign_units":"UAH","sum":"","sum_foreign_hidden":false,"sum_foreign":""}],"51":[{"sum_foreign_comment":"","sum_units":"UAH","sum_comment":"","sum_hidden":false,"sum_foreign_units":"UAH","sum_comment_hidden":false,"sum_unclear":false,"sum":"","sum_foreign":""},{"sum_foreign_comment":"","sum_units":"","sum_comment":"","sum_foreign_units":"","sum":"","sum_foreign":""}],"52":[{"sum_foreign_comment":"","sum_units":"UAH","sum_comment":"","sum_hidden":false,"sum_foreign_units":"UAH","sum":"","sum_foreign":""}],"53":[{"sum_foreign_comment":"","sum_units":"UAH","sum_comment":"","sum_foreign_units":"UAH","sum":"","sum_foreign":""}]},"declaration":{"additional_info_text":"","notfull_lostpages":"","date":"2015-03-30T00:00:00","notfull":"","additional_info":"","url":"http://static.declarations.com.ua/declarations/chosen_ones/mega_batch/tsvyntarna_tetiana_mykolaivna.pdf"},"liabilities":{"54":{"sum_foreign_comment":"","sum":"","sum_comment":"","sum_comment_unclear":false,"sum_comment_hidden":false,"sum_unclear":false,"sum_foreign":""},"55":{"sum_foreign_comment":"","sum_comment_hidden":false,"sum":"","sum_comment":"","sum_foreign":""},"56":{"sum_foreign_comment":"","sum":"","sum_comment":"","sum_comment_unclear":false,"sum_unclear":false,"sum_foreign":""},"57":{"sum_foreign_comment":"","sum_foreign_hidden":false,"sum_comment":"","sum_comment_unclear":false,"sum_hidden":false,"sum_comment_hidden":false,"sum_unclear":false,"sum":"11244.91","sum_foreign":""},"58":{"sum_foreign_comment":"","sum_foreign_hidden":false,"sum_comment":"","sum_comment_unclear":false,"sum_hidden":false,"sum_comment_hidden":false,"sum_unclear":false,"sum":"17017.71","sum_foreign":""},"59":{"sum_foreign_comment":"","sum_foreign_hidden":false,"sum_comment":"","sum_hidden":false,"sum":"","sum_foreign":""},"60":{"sum_foreign_comment":"","sum":"","sum_comment":"","sum_comment_hidden":false,"sum_unclear":false,"sum_foreign":""},"61":{"sum_foreign_comment":"","sum_comment_hidden":false,"sum":"","sum_comment":"","sum_foreign":""},"62":{"sum_foreign_comment":"","sum":"11072","sum_comment":"","sum_foreign":""},"63":{"sum_foreign_comment":"","sum_comment_hidden":false,"sum":"32643","sum_comment":"","sum_foreign":""},"64":{"sum_foreign_comment":"","sum_foreign_hidden":false,"sum_comment":"","sum_hidden":false,"sum":"11963","sum_foreign":""}},"ft_src":"11244.91\n11072\n11963\n17017.71\n32643\nсуддя гусятинського районного суду тернопільської області\nТернопільська область\nЗагальний місцевий суд\nТетяна\nЦвинтарний Віктор Васильович\nПодружжя\nЦвинтарна Людмила Вікторівна\nДитина\nЦвинтарна Олександра Вікторівна\nДитина\nМиколаївна\nЦвинтарна Тетяна Миколаївна\nТетяна Миколаївна Цвинтарна\nТетяна Цвинтарна\nЦвинтарна Тетяна Миколаївна\nЦвинтарна Тетяна Миколаївна\nЦвинтарна\nRenault Master\n2799 куб. см. спільна сумісна власність подружжя\n2000\n1995 куб. см., спільна сумісна власність подружжя\nSuzuki Grand Vitara\n2008\n2014\n1995 куб. см., спільна сумісна власність подружжя\nSuzuki Grand Vitara\n2008\n2799 куб. см. спільна сумісна власність подружжя\n2000\nRenault Master\n1500\n68.2\n308.05\nПодружжя\nЦвинтарний Віктор Васильович\nДитина\nЦвинтарна Людмила Вікторівна\nДитина\nЦвинтарна Олександра Вікторівна\nЦвинтарна Тетяна Миколаївна\nТетяна Миколаївна Цвинтарна\nТетяна Цвинтарна\nЦвинтарна Тетяна Миколаївна\nЦвинтарна Тетяна Миколаївна\nТетяна\nМиколаївна\nЗагальний місцевий суд\nсуддя гусятинського районного суду тернопільської області\nТернопільська область\nЦвинтарна\n32643\n11963\n11244.91\n11072\n17017.71\n217598\n269780\n217598\n288340\n18560\n2014\n17017.71\n11244.91\n11963\n11072\n32643\n1500\n308.05\n68.2\nЦвинтарний Віктор Васильович\nПодружжя\nЦвинтарна Людмила Вікторівна\nДитина\nЦвинтарна Олександра Вікторівна\nДитина\nМиколаївна\nЦвинтарна\nТетяна\nЦвинтарна Тетяна Миколаївна\nТетяна Миколаївна Цвинтарна\nТетяна Цвинтарна\nЦвинтарна Тетяна Миколаївна\nТернопільська область\nЗагальний місцевий суд\nсуддя гусятинського районного суду тернопільської області\nЦвинтарна Тетяна Миколаївна\n217598\n288340\n217598\n269780\n18560\n2000\n2799 куб. см. спільна сумісна власність подружжя\nRenault Master\nSuzuki Grand Vitara\n1995 куб. см., спільна сумісна власність подружжя\n2008\n18560\n217598\n288340\n269780\n217598\n68.2\n308.05\n1500\n2014","general":{"inn":"","name":"Тетяна","patronymic_unclear":false,"family":[{"inn":"","inn_hidden":true,"relations_hidden":false,"family_name":"Цвинтарний Віктор Васильович","relations_other":"","relations":"Подружжя","name_hidden":false,"name_unclear":false},{"inn":"","relations":"Дитина","relations_unclear":false,"family_name":"Цвинтарна Людмила Вікторівна","inn_hidden":false,"relations_other":"","name_hidden":false,"name_unclear":false},{"inn":"","relations":"Дитина","relations_other":"","inn_hidden":false,"family_name":"Цвинтарна Олександра Вікторівна","name_hidden":false,"name_unclear":false}],"patronymic":"Миколаївна","inn_hidden":true,"family_raw":"","inn_unclear":false,"post":{"post_unclear":false,"post":"суддя гусятинського районного суду тернопільської області","candidate":"","office_hidden":false,"region":"Тернопільська область","post_hidden":false,"office":"Загальний місцевий суд","office_unclear":false},"full_name_suggest":{"output":"Цвинтарна Тетяна Миколаївна","input":["Цвинтарна Тетяна Миколаївна","Тетяна Миколаївна Цвинтарна","Тетяна Цвинтарна"]},"full_name":"Цвинтарна Тетяна Миколаївна","addresses":[{"place_district":"","place_city_hidden":true,"place_city":"","place_city_unclear":false,"place_district_hidden":true,"place_city_type":"","place_address_hidden":true,"place_city_type_hidden":true,"place_address":"","place_hidden":true,"place":""}],"last_name":"Цвинтарна","last_name_unclear":false,"name_unclear":false},"source":"VULYK","estate":{"23":[{"space_unclear":false,"costs":"","costs_comment":"","address_hidden":false,"region_hidden":false,"space_comment":"","space_hidden":false,"space":"","address":"","region":"","space_units_unclear":false,"space_units":"м²","costs_rent":"","costs_rent_comment":""},{"space_unclear":false,"costs":"","costs_comment":"","address_hidden":false,"region_hidden":false,"space_comment":"","space":"","address":"","costs_comment_unclear":false,"region":"","space_units_unclear":false,"space_units":"","costs_rent":"","costs_rent_comment":""},{"costs_rent":"","region":"","costs":"","costs_rent_comment":"","costs_comment":"","region_hidden":false,"space_comment":"","space_units":"","space":"","address":""},{"costs_rent":"","region":"","costs":"","costs_rent_comment":"","costs_comment":"","region_hidden":false,"space_comment":"","space_units":"","space":"","address":""},{"costs_rent":"","region":"","costs":"","costs_rent_comment":"","costs_comment":"","region_hidden":false,"space_comment":"","space_units":"","space":"","address":""},{"costs_rent":"","region":"","costs":"","costs_rent_comment":"","costs_comment":"","region_hidden":false,"space_comment":"","space_units":"","space":"","address":""},{"costs_rent":"","costs":"","costs_rent_comment":"","costs_comment":"","region_hidden":false,"space_comment":"","space_units":"","space":"","address":""}],"29":[{"space_units_unclear":false,"address_hidden":true,"region_hidden":true,"space_comment":"","space":"1500","address":"","region":"","costs_property":"","costs_rent_comment":"","space_units":"м²","costs_property_comment":"","costs_rent":""}],"31":[{"space_unclear":false,"address_hidden":true,"region_hidden":true,"space_comment":"","space_hidden":false,"space":"68.2","address":"","region":"","costs_property":"","costs_rent_comment":"","space_comment_unclear":false,"space_comment_hidden":false,"space_units":"м²","costs_property_comment":"","costs_rent":""}],"34":[{"costs_rent":"","region":"","costs_property":"","costs_rent_comment":"","address_hidden":true,"region_hidden":true,"space_comment":"","costs_property_comment":"","space_units":"м²","space":"308.05","address":""}]},"intro":{"declaration_year":"2014","declaration_year_unclear":false,"declaration_year_hidden":false}}