{"income":{"5":{"value":"352829.26","family_comment":"","value_unclear":false,"family_hidden":false,"value_hidden":false,"family_unclear":false,"comment_unclear":false,"comment":"","family":"27133.71"},"6":{"value":"255736.66","family_comment":"","value_unclear":false,"family_hidden":false,"value_hidden":false,"family_unclear":false,"comment_unclear":false,"comment":"","family":""},"7":{"source_name_unclear":false,"value":"","family_comment":"","source_name":"","family":"","comment":""},"8":{"family_comment":"","value":"","family":"","comment":""},"9":{"value":"","value_unclear":false,"comment_hidden":false,"family_comment":"","comment_unclear":false,"comment":"","family":""},"10":{"value":"12180","comment_unclear":false,"value_hidden":false,"family_comment":"","family":"","comment":""},"11":{"family_comment":"","value":"","family":"","comment":""},"12":{"family_comment":"","value":"","family":"","comment":""},"13":{"family_comment":"","value":"","family":"","comment":""},"14":{"family_comment":"","value":"","family":"","comment":""},"15":{"family_comment":"","value":"","family":"","comment":""},"16":{"family_comment":"","value":"","family":"","comment":""},"17":{"family_comment":"","value":"","family":"","comment":""},"18":{"value":"","family_hidden":false,"value_hidden":false,"family_comment":"","family":"","comment":""},"19":{"family_comment":"","value":"","family":"","comment":""},"20":{"value":"84912.6","family_comment":"пенсія","value_unclear":false,"family_hidden":false,"value_hidden":false,"family_unclear":false,"family":"27133.71","comment":"пенсія"}},"vehicle":{"40":[{"brand_info":"1800","sum_rent_comment":"","brand":"Toyota Corolla","sum_comment":"","brand_unclear":false,"year":"2005","brand_info_unclear":false,"year_unclear":false,"sum":"","sum_rent":""}]},"id":"vulyk_66_22","banks":{"45":[{"sum_foreign_comment":"","sum_units":"UAH","sum_units_hidden":false,"sum_comment":"","sum_comment_unclear":false,"sum_hidden":false,"sum_foreign_units":"UAH","sum_comment_hidden":false,"sum_unclear":false,"sum":"30","sum_foreign":""}]},"declaration":{"additional_info_text":"","notfull_lostpages":"","date":"2015-03-25T00:00:00","notfull":"","additional_info":"","url":"http://static.declarations.com.ua/declarations/chosen_ones/mega_batch/kondrachuk_anatolii_petrovych.pdf"},"liabilities":{"54":{"sum_foreign_comment":"","sum":"","sum_comment":"","sum_comment_unclear":false,"sum_comment_hidden":false,"sum_unclear":false,"sum_foreign":""},"55":{"sum_foreign_comment":"","sum":"","sum_comment":"","sum_foreign":""},"56":{"sum_foreign_comment":"","sum_foreign_hidden":false,"sum_comment":"","sum_hidden":false,"sum_comment_hidden":false,"sum":"","sum_foreign":""},"57":{"sum_foreign_comment":"","sum":"","sum_comment":"","sum_comment_unclear":false,"sum_hidden":false,"sum_comment_hidden":false,"sum_unclear":false,"sum_foreign":""},"58":{"sum_foreign_comment":"","sum":"","sum_comment":"","sum_comment_unclear":false,"sum_unclear":false,"sum_foreign":""},"59":{"sum_foreign_comment":"","sum_foreign_hidden":false,"sum_comment":"","sum_comment_unclear":false,"sum_hidden":false,"sum":"","sum_foreign":""},"60":{"sum_foreign_comment":"","sum":"","sum_comment":"","sum_comment_unclear":false,"sum_foreign":""},"61":{"sum_foreign_comment":"","sum":"","sum_comment":"","sum_foreign":""},"62":{"sum_foreign_comment":"","sum_foreign_hidden":false,"sum_comment":"","sum_hidden":false,"sum":"","sum_unclear":false,"sum_foreign":""},"63":{"sum_foreign_comment":"","sum":"","sum_comment":"","sum_comment_unclear":false,"sum_comment_hidden":false,"sum_unclear":false,"sum_foreign":""},"64":{"sum_foreign_comment":"","sum":"","sum_comment":"","sum_comment_unclear":false,"sum_foreign":""}},"ft_src":"Криве Озеро\n55104\nКривоозерський\nМиколаївська область\nСМТ\nголова районного суду\nМиколаївська область\nЗагальний місцевий суд\nАнатолій\nКондрачук Л. А\nПодружжя\nПетрович\nКондрачук Анатолій Петрович\nАнатолій Петрович Кондрачук\nАнатолій Кондрачук\nКондрачук Анатолій Петрович\nКондрачук Анатолій Петрович\nКондрачук\n1800\nToyota Corolla\n2005\n30\n2014\n255736.66\n12180\n27133.71\n352829.26\nпенсія\n27133.71\nпенсія\n84912.6\n1800\n2005\nToyota Corolla\n30\n2014\nЗагальний місцевий суд\nголова районного суду\nМиколаївська область\nПодружжя\nКондрачук Л. А\nКондрачук Анатолій Петрович\nАнатолій Петрович Кондрачук\nАнатолій Кондрачук\nКондрачук Анатолій Петрович\nКондрачук Анатолій Петрович\nАнатолій\nКондрачук\nПетрович\nСМТ\nКриве Озеро\n55104\nМиколаївська область\nКривоозерський\n255736.66\n84912.6\nпенсія\nпенсія\n27133.71\n352829.26\n27133.71\n12180\nКондрачук Л. А\nПодружжя\nПетрович\nКондрачук\nАнатолій\nКондрачук Анатолій Петрович\nАнатолій Петрович Кондрачук\nАнатолій Кондрачук\nКондрачук Анатолій Петрович\nМиколаївська область\nКриве Озеро\nКривоозерський\nСМТ\n55104\nМиколаївська область\nголова районного суду\nЗагальний місцевий суд\nКондрачук Анатолій Петрович\n2005\n1800\nToyota Corolla\n12180\nпенсія\n84912.6\nпенсія\n27133.71\n352829.26\n27133.71\n255736.66\n30\n2014","general":{"inn":"","name":"Анатолій","last_name_hidden":false,"family":[{"inn":"","inn_hidden":true,"relations_hidden":false,"family_name":"Кондрачук Л. А","relations_other":"","relations":"Подружжя","name_hidden":false,"name_unclear":false}],"patronymic":"Петрович","inn_hidden":true,"family_raw":"","inn_unclear":false,"post":{"post_unclear":false,"post":"голова районного суду","candidate":"","office_hidden":false,"region":"Миколаївська область","office":"Загальний місцевий суд","office_unclear":false},"full_name_suggest":{"output":"Кондрачук Анатолій Петрович","input":["Кондрачук Анатолій Петрович","Анатолій Петрович Кондрачук","Анатолій Кондрачук"]},"full_name":"Кондрачук Анатолій Петрович","addresses":[{"place_city_type_unclear":false,"place_address":"55104","place_district_hidden":false,"place_city_type":"СМТ","place_address_hidden":true,"place_address_unclear":false,"place_city_type_hidden":false,"place":"Миколаївська область","place_district":"Кривоозерський","place_unclear":false,"place_city":"Криве Озеро","place_city_unclear":false,"place_hidden":false,"place_city_hidden":false,"place_district_unclear":false}],"last_name":"Кондрачук","last_name_unclear":false},"source":"VULYK","intro":{"declaration_year":"2014","isnotdeclaration":"","declaration_year_unclear":false}}