{"income":{"5":{"value":"352437","value_unclear":false,"family_hidden":false,"family_comment":"","family":"20657","comment":""},"6":{"family_comment":"","value":"339534","family":"","comment":""},"7":{"family_comment":"","value":"","source_name":"","family":"","comment":""},"8":{"family_comment":"","value":"","family":"","comment":""},"9":{"family_comment":"","value":"","family":"466","comment":""},"10":{"family_comment":"","value":"","family":"","comment":""},"11":{"family_comment":"","value":"","family_hidden":false,"comment":"","family":""},"12":{"family_comment":"","value":"","family":"","comment":""},"13":{"family_comment":"","value":"","family":"","comment":""},"14":{"family_comment":"","value":"","family":"","comment":""},"15":{"family_comment":"","value":"","family":"","comment":""},"16":{"family_comment":"","value":"","family":"","comment":""},"17":{"family_comment":"","value":"","family":"","comment":"","family_comment_unclear":false},"18":{"family_comment":"","value":"","family":"","comment":""},"19":{"family_comment":"","value":"","family":"","comment":""},"20":{"value":"12903","family_unclear":false,"family_hidden":false,"family_comment":"пенсія","family":"20191","comment":"пенсія"}},"vehicle":{"35":[{"brand_info":"1900 куб. см.","sum":"","brand":"Skoda Superb","sum_comment":"","brand_unclear":false,"year":"2002","brand_hidden":false,"brand_info_hidden":false,"brand_info_unclear":false,"sum_rent_comment":"","sum_rent":""},{"brand_info":"2378 куб. см.","sum_rent_comment":"","brand":"Mitsubishi Galant","sum_comment":"","year":"2008","sum":"","sum_rent":""}],"37":[{"brand_info":"Човен гумовий надувний, 25 к. с., довжина 4.2 м","sum_rent_comment":"","brand":"","sum_comment":"","year":"","brand_hidden":true,"brand_info_unclear":false,"sum":"","sum_rent":""}]},"id":"vulyk_103_75","declaration":{"date":"2016-03-23T00:00:00","additional_info_text":"","additional_info":"","url":"http://static.declarations.com.ua/declarations/chosen_ones/judges_batch/1299_kryzhanovskyi_valentyn_iakovych.pdf"},"liabilities":{"54":{"sum_foreign_comment":"","sum_foreign_hidden":false,"sum_comment":"","sum_foreign_comment_hidden":false,"sum_hidden":false,"sum_foreign_comment_unclear":false,"sum_comment_hidden":false,"sum_unclear":false,"sum":"","sum_foreign":""},"55":{"sum_foreign_comment":"","sum":"","sum_comment":"","sum_foreign":""},"56":{"sum_foreign_comment":"","sum":"","sum_comment":"","sum_foreign":""},"57":{"sum_foreign_comment":"","sum_foreign_hidden":false,"sum_comment":"","sum_foreign_comment_hidden":false,"sum_hidden":false,"sum_comment_hidden":false,"sum":"","sum_foreign":""},"58":{"sum_foreign_comment":"","sum_foreign_hidden":false,"sum_comment":"","sum_foreign_comment_hidden":false,"sum_hidden":false,"sum_comment_hidden":false,"sum":"","sum_foreign":""},"59":{"sum_foreign_comment":"","sum_foreign_hidden":false,"sum_comment":"","sum_foreign_comment_hidden":false,"sum_hidden":false,"sum_comment_hidden":false,"sum":"","sum_foreign":""},"60":{"sum_foreign_comment":"","sum":"","sum_comment":"","sum_hidden":false,"sum_comment_hidden":false,"sum_foreign":""},"61":{"sum_foreign_comment":"","sum":"","sum_comment":"","sum_foreign":""},"62":{"sum_foreign_comment":"","sum_comment_hidden":false,"sum":"","sum_comment":"","sum_foreign":""},"63":{"sum_foreign_comment":"","sum":"","sum_comment":"","sum_foreign":""},"64":{"sum_foreign_comment":"","sum":"","sum_comment":"","sum_foreign":""}},"ft_src":"Крижановський Валентин Якович\nсуддя вищого спецiалiзованого суду україни з розгляду цивiльних і кримiнальних справ\nЗагальнодержавний регіон\nВищий спеціалізований суд з розгляду цивільних і кримінальних справ\nВалентин\nКрижановська Т. Н\nПодружжя\nКрижановський Валентин Якович\nВалентин Якович Крижановський\nВалентин Крижановський\nКрижановський Валентин Якович\nКрижановський\nЯкович\nSkoda Superb\n1900 куб. см.\n2002\n2378 куб. см.\n2008\nMitsubishi Galant\nЧовен гумовий надувний, 25 к. с., довжина 4.2 м\n45\nнезавершене будівництво\n84\nпаркінг\n13.7\n1500\n137.8\n12.21\n62.35\n24.42\nслужбова, не придатна для проживання\n129.79\n2015\n339534\n466\n20657\n352437\nпенсія\n20191\nпенсія\n12903\nЧовен гумовий надувний, 25 к. с., довжина 4.2 м\n1900 куб. см.\n2002\nSkoda Superb\n2378 куб. см.\n2008\nMitsubishi Galant\n137.8\n13.7\nпаркінг\n62.35\n24.42\n129.79\nслужбова, не придатна для проживання\n1500\n45\n84\nнезавершене будівництво\n12.21\nКрижановський\nКрижановський Валентин Якович\nВалентин Якович Крижановський\nВалентин Крижановський\nКрижановський Валентин Якович\nКрижановський Валентин Якович\nЯкович\nПодружжя\nКрижановська Т. Н\nВалентин\nВищий спеціалізований суд з розгляду цивільних і кримінальних справ\nсуддя вищого спецiалiзованого суду україни з розгляду цивiльних і кримiнальних справ\nЗагальнодержавний регіон\n339534\nпенсія\nпенсія\n12903\n20191\n352437\n20657\n466\n2015\nПодружжя\nКрижановська Т. Н\nКрижановський\nЯкович\nсуддя вищого спецiалiзованого суду україни з розгляду цивiльних і кримiнальних справ\nВищий спеціалізований суд з розгляду цивільних і кримінальних справ\nЗагальнодержавний регіон\nКрижановський Валентин Якович\nКрижановський Валентин Якович\nВалентин Якович Крижановський\nВалентин Крижановський\nКрижановський Валентин Якович\nВалентин\nSkoda Superb\n1900 куб. см.\n2002\nMitsubishi Galant\n2378 куб. см.\n2008\nЧовен гумовий надувний, 25 к. с., довжина 4.2 м\n466\nпенсія\n12903\n20191\nпенсія\n352437\n20657\n339534\n12.21\n1500\nнезавершене будівництво\n84\nпаркінг\n13.7\n137.8\n45\n62.35\n24.42\nслужбова, не придатна для проживання\n129.79\n2015","general":{"inn":"","inn_hidden":true,"last_name":"Крижановський","post":{"region":"Загальнодержавний регіон","region_unclear":false,"post":"суддя вищого спецiалiзованого суду україни з розгляду цивiльних і кримiнальних справ","office_unclear":false,"office":"Вищий спеціалізований суд з розгляду цивільних і кримінальних справ"},"name":"Валентин","full_name":"Крижановський Валентин Якович","family_raw":"","addresses":[{"place_district":"","place_city_hidden":true,"place_city":"","place_city_type_hidden":false,"place_district_hidden":false,"place_city_type":"","place_address_hidden":true,"place_address":"","place_hidden":true,"place":""}],"family":[{"inn":"","relations":"Подружжя","relations_hidden":false,"inn_hidden":true,"relations_other":"","name_hidden":true,"family_name":"Крижановська Т. Н","name_unclear":false}],"full_name_suggest":{"output":"Крижановський Валентин Якович","input":["Крижановський Валентин Якович","Валентин Якович Крижановський","Валентин Крижановський"]},"patronymic":"Якович"},"source":"VULYK","estate":{"23":[{"costs_rent":"","region":"","costs":"","costs_rent_comment":"","costs_comment":"","address_hidden":false,"region_hidden":true,"space_comment":"","space_units":"м²","space":"1500","address":""}],"24":[{"space_hidden":false,"costs":"","costs_comment":"","address_hidden":false,"region_hidden":true,"space_comment":"незавершене будівництво","space_unclear":false,"space":"84","address":"","region":"","costs_rent_comment":"","space_units":"м²","costs_rent":""}],"25":[{"costs":"","costs_comment":"","address_hidden":false,"region_hidden":true,"space_comment":"","space":"62.35","address":"","region":"","costs_rent_comment":"","space_comment_unclear":false,"space_comment_hidden":false,"space_units":"м²","costs_rent":""},{"costs_rent":"","region":"","costs":"","costs_rent_comment":"","costs_comment":"","region_hidden":false,"space_comment":"","space_units":"м²","space":"24.42","address":""},{"costs_rent":"","region":"","costs":"","costs_rent_comment":"","costs_comment":"","space_comment":"службова, не придатна для проживання","space_units":"м²","space":"129.79","address":""}],"28":[{"space_hidden":false,"costs":"","costs_comment":"","address_hidden":false,"region_hidden":true,"space_comment":"паркінг","space_unclear":false,"space":"13.7","address":"","region":"","costs_rent_comment":"","space_units":"м²","costs_rent":""}],"30":[{"space_unclear":false,"address_hidden":false,"region_hidden":true,"space_comment":"","space_hidden":false,"space":"137.8","address":"","costs_property":"","costs_rent_comment":"","space_units":"м²","costs_property_comment":"","costs_rent":""}],"31":[{"space_hidden":false,"address_hidden":false,"region_hidden":true,"space_comment":"","space":"12.21","address":"","costs_property":"","costs_rent_comment":"","address_unclear":false,"space_units":"м²","costs_property_comment":"","costs_rent":""}],"33":[{"costs_rent":"","space_hidden":false,"costs_property":"","costs_rent_comment":"","region_hidden":true,"space_comment":"","costs_property_comment":"","space_units":"м²","space":"45","address":""}]},"intro":{"declaration_year":"2015"}}