{"income":{"5":{"family_comment":"","family_unclear":false,"value":"282040","family":"83100","comment":""},"6":{"family_comment":"","value":"195759.5","value_unclear":false,"family":"9000","comment":""},"7":{"family_comment":"","value":"","source_name":"","family":"","comment":""},"8":{"family_comment":"","value":"","family":"","comment":""},"9":{"value":"","value_unclear":false,"family_hidden":false,"family_comment":"","comment_unclear":false,"comment":"","family":""},"10":{"family_comment":"","value":"12180","family":"","comment":""},"11":{"family_comment":"","value":"","family":"","comment":""},"12":{"family_comment":"","value":"","family":"","comment":""},"13":{"family_comment":"","value":"","family":"","comment":""},"14":{"family_comment":"","value":"","family":"","comment":""},"15":{"family_comment":"","value":"","family":"","comment":""},"16":{"family_comment":"","value":"74100","family":"74100","comment":""},"17":{"family_comment":"","value":"","family":"","comment":""},"18":{"family_comment":"","value":"","family":"","comment":""},"19":{"family_comment":"","value":"","family":"","comment":""},"20":{"value":"","value_unclear":false,"comment_hidden":false,"family_comment":"","family":"","comment":""}},"id":"vulyk_40_38","banks":{"45":[{"sum_foreign_comment":"","sum_units":"UAH","sum_comment":"","sum_hidden":false,"sum_foreign_units":"UAH","sum":"","sum_foreign":""},{"sum_foreign_comment":"","sum_units":"","sum_comment":"","sum_foreign_units":"","sum":"","sum_foreign":""},{"sum_foreign_comment":"","sum_units":"","sum_comment":"","sum_foreign_units":"","sum":"","sum_foreign":""}],"46":[{"sum_foreign_comment":"","sum_units":"UAH","sum_comment":"","sum_foreign_units":"UAH","sum":"","sum_unclear":false,"sum_foreign":""}],"47":[{"sum_foreign_comment":"","sum_units":"UAH","sum_comment":"","sum_foreign_units":"UAH","sum":"","sum_foreign":""}],"48":[{"sum_foreign_comment":"","sum_units":"UAH","sum_comment":"","sum_foreign_units":"UAH","sum":"","sum_foreign":""}],"49":[{"sum_foreign_comment":"","sum_units":"UAH","sum_comment":"","sum_foreign_units":"UAH","sum":"","sum_foreign":""}],"50":[{"sum_foreign_comment":"","sum_units":"UAH","sum_comment":"","sum_foreign_units":"UAH","sum":"","sum_foreign":""}],"51":[{"sum_foreign_comment":"","sum_units":"UAH","sum_comment":"","sum_foreign_units":"UAH","sum":"","sum_foreign":""}],"52":[{"sum_foreign_comment":"","sum_units":"UAH","sum_comment":"","sum_foreign_units":"UAH","sum":"","sum_foreign":""}],"53":[{"sum_foreign_comment":"","sum_units":"UAH","sum_comment":"","sum_foreign_units":"UAH","sum":"","sum_foreign":""}]},"declaration":{"date":"2015-03-30T00:00:00","notfull":"","url":"http://static.declarations.com.ua/declarations/chosen_ones/mega_batch/semenova_oksana_serhiivna.pdf","notfull_lostpages":""},"liabilities":{"54":{"sum_foreign_comment":"","sum":"","sum_comment":"","sum_foreign":""},"55":{"sum_foreign_comment":"","sum":"","sum_comment":"","sum_foreign":""},"56":{"sum_foreign_comment":"","sum":"","sum_comment":"","sum_foreign":""},"57":{"sum_foreign_comment":"","sum":"114427","sum_comment":"","sum_hidden":false,"sum_comment_hidden":false,"sum_foreign":""},"58":{"sum_foreign_comment":"","sum":"10073","sum_comment":"","sum_hidden":false,"sum_comment_hidden":false,"sum_foreign":""},"59":{"sum_foreign_comment":"","sum":"","sum_comment":"","sum_foreign":""},"60":{"sum_foreign_comment":"","sum":"","sum_comment":"","sum_foreign":""},"61":{"sum_foreign_comment":"","sum":"","sum_comment":"","sum_foreign":""},"62":{"sum_foreign_comment":"","sum":"","sum_comment":"","sum_foreign":""},"63":{"sum_foreign_comment":"","sum":"","sum_comment":"","sum_foreign":""},"64":{"sum_foreign_comment":"","sum":"","sum_comment":"","sum_foreign":""}},"ft_src":"114427\n10073\nСеменова Оксана Сергіївна\nсуддя великописарівського районного суду сумської області\nСумська область\nЗагальний місцевий суд\nОксана\nСеменова Є. А., 19. 11. 1990\nДитина\nСеменова Оксана Сергіївна\nОксана Сергіївна Семенова\nОксана Семенова\nСеменова Оксана Сергіївна\nСеменова\nСергіївна\n12180\n83100\n282040\n74100\n74100\n9000\n195759.5\n324000\n49.4\n2014\n9000\n195759.5\n12180\n83100\n282040\n74100\n74100\n2014\nСеменова\nСеменова Оксана Сергіївна\nОксана Сергіївна Семенова\nОксана Семенова\nСеменова Оксана Сергіївна\nОксана\nСергіївна\nСеменова Оксана Сергіївна\nЗагальний місцевий суд\nсуддя великописарівського районного суду сумської області\nСумська область\nДитина\nСеменова Є. А., 19. 11. 1990\n114427\n10073\n195759.5\n9000\n282040\n83100\n74100\n74100\n12180\n324000\n49.4\n10073\n114427\nСеменова Є. А., 19. 11. 1990\nДитина\nСергіївна\nСеменова\nсуддя великописарівського районного суду сумської області\nСумська область\nЗагальний місцевий суд\nСеменова Оксана Сергіївна\nСеменова Оксана Сергіївна\nОксана Сергіївна Семенова\nОксана Семенова\nСеменова Оксана Сергіївна\nОксана\n324000\n49.4\n2014","general":{"inn":"","inn_hidden":true,"last_name":"Семенова","post":{"office":"Загальний місцевий суд","region":"Сумська область","post":"суддя великописарівського районного суду сумської області"},"name":"Оксана","full_name":"Семенова Оксана Сергіївна","family_raw":"","addresses":[{"place_district":"","place_city_hidden":false,"place_city":"","place_city_type_hidden":false,"place_district_hidden":false,"place_city_type":"","place_address_hidden":false,"place_address":"","place_hidden":true,"place":""}],"family":[{"inn":"","relations":"Дитина","relations_other":"","inn_hidden":false,"family_name":"Семенова Є. А., 19. 11. 1990","name_hidden":false}],"full_name_suggest":{"output":"Семенова Оксана Сергіївна","input":["Семенова Оксана Сергіївна","Оксана Сергіївна Семенова","Оксана Семенова"]},"patronymic":"Сергіївна"},"source":"VULYK","estate":{"23":[{"costs_rent":"","region":"","costs":"","costs_rent_comment":"","costs_comment":"","address_hidden":false,"region_hidden":false,"space_comment":"","space_units":"м²","space":"","address":""},{"costs_rent":"","region":"","costs":"","costs_rent_comment":"","costs_comment":"","space_comment":"","space_units":"","space":"","address":""},{"costs_rent":"","region":"","costs":"","costs_rent_comment":"","costs_comment":"","space_comment":"","space_units":"","space":"","address":""},{"costs_rent":"","costs":"","costs_rent_comment":"","costs_comment":"","space_comment":"","space_units":"","space":"","address":""}],"25":[{"costs_rent":"","region":"","costs":"324000","costs_rent_comment":"","costs_comment":"","address_hidden":false,"region_hidden":true,"space_comment":"","space_units":"м²","space":"49.4","address":""}]},"intro":{"declaration_year":"2014"}}