{"income":{"5":{"family_comment":"","value":"508541","family":"","comment":""},"6":{"family_comment":"","value":"197023","family_hidden":false,"comment":"","family":""},"7":{"family_comment":"","value":"","source_name":"","family":"","comment":""},"8":{"family_comment":"","value":"","family":"","comment":""},"9":{"value":"","value_unclear":false,"family_hidden":false,"family_comment":"","family":"","comment":""},"10":{"value":"11470","family_comment":"","family_hidden":false,"value_hidden":false,"family_unclear":false,"family":"","comment":""},"11":{"family_comment":"","value":"48","family":"","comment":""},"12":{"family_comment":"","value":"","family":"","comment":""},"13":{"family_comment":"","value":"","family":"","comment":""},"14":{"family_comment":"","value":"","family":"","comment":""},"15":{"family_comment":"","value":"","family":"","comment":""},"16":{"family_comment":"","value":"300000","family":"","comment":""},"17":{"family_comment":"","value":"","family":"","comment":""},"18":{"family_comment":"","value":"","family":"","comment":""},"19":{"family_comment":"","value":"","family":"","comment":""},"20":{"value":"","comment_unclear":false,"family_comment":"","family":"","comment":"","family_comment_unclear":false}},"id":"vulyk_75_140","declaration":{"additional_info_text":"","notfull_lostpages":"","date":"2014-03-17T00:00:00","notfull":"","additional_info":"","url":"http://static.declarations.com.ua/declarations/chosen_ones/judges_batch/1795_miezientsev_ievhen_ihorovych.pdf"},"liabilities":{"54":{"sum_foreign_comment":"","sum":"11448","sum_comment":"","sum_foreign":""},"55":{"sum_foreign_comment":"","sum":"","sum_comment":"","sum_foreign":""},"56":{"sum_foreign_comment":"","sum":"10542","sum_comment":"","sum_foreign":""},"57":{"sum_foreign_comment":"","sum":"","sum_comment":"","sum_foreign":""},"58":{"sum_foreign_comment":"","sum":"","sum_comment":"","sum_foreign":""},"59":{"sum_foreign_comment":"","sum":"","sum_comment":"","sum_comment_unclear":false,"sum_unclear":false,"sum_foreign":""},"60":{"sum_foreign_comment":"","sum":"","sum_comment":"","sum_foreign":""},"61":{"sum_foreign_comment":"","sum":"","sum_comment":"","sum_foreign":""},"62":{"sum_foreign_comment":"","sum":"","sum_comment":"","sum_unclear":false,"sum_foreign":""},"63":{"sum_foreign_comment":"","sum":"","sum_comment":"","sum_foreign":""},"64":{"sum_foreign_comment":"","sum":"","sum_comment":"","sum_foreign":""}},"ft_src":"11448\n10542\nМєзєнцев Євген Ігорович\nголова київського апеляційного адміністративного суду\nм. Київ\nАпеляційний адміністративний суд\nЄвген\nМєзєнцева О. В\nПодружжя\nМєзєнцев П. Є\nДитина\nМєзєнцева М. Є\nДитина\nМєзєнцев Євген Ігорович\nЄвген Ігорович Мєзєнцев\nЄвген Мєзєнцев\nМєзєнцев Євген Ігорович\nМєзєнцев\nІгорович\n48\n11470\n508541\n300000\n197023\nВласність\n637\nВласність\n180.5\nоренда\n53952.75\n183.9\n2013\n197023\n48\n11470\n508541\n300000\n2013\nМєзєнцев\nІгорович\nПодружжя\nМєзєнцева О. В\nДитина\nМєзєнцев П. Є\nДитина\nМєзєнцева М. Є\nМєзєнцев Євген Ігорович\nЄвген Ігорович Мєзєнцев\nЄвген Мєзєнцев\nМєзєнцев Євген Ігорович\nЄвген\nМєзєнцев Євген Ігорович\nАпеляційний адміністративний суд\nголова київського апеляційного адміністративного суду\nм. Київ\n11448\n10542\n197023\n508541\n300000\n11470\n48\n637\nВласність\n180.5\nВласність\n183.9\nоренда\n53952.75\n10542\n11448\nМєзєнцева О. В\nПодружжя\nМєзєнцев П. Є\nДитина\nМєзєнцева М. Є\nДитина\nМєзєнцев\nІгорович\nголова київського апеляційного адміністративного суду\nм. Київ\nАпеляційний адміністративний суд\nМєзєнцев Євген Ігорович\nМєзєнцев Євген Ігорович\nЄвген Ігорович Мєзєнцев\nЄвген Мєзєнцев\nМєзєнцев Євген Ігорович\nЄвген\n53952.75\nоренда\n183.9\nВласність\n637\nВласність\n180.5\n2013","general":{"inn":"","inn_hidden":true,"last_name":"Мєзєнцев","post":{"office":"Апеляційний адміністративний суд","region":"м. Київ","post":"голова київського апеляційного адміністративного суду"},"name":"Євген","full_name":"Мєзєнцев Євген Ігорович","family_raw":"","addresses":[{"place_district":"","place_address_hidden":false,"place_city":"","place_city_type_hidden":false,"place_district_hidden":false,"place_city_type":"","place_city_hidden":false,"place_address":"","place_hidden":true,"place":""}],"family":[{"inn":"","inn_hidden":false,"relations_hidden":false,"family_name":"Мєзєнцева О. В","relations_other":"","relations":"Подружжя","name_hidden":false,"name_unclear":false},{"inn":"","relations":"Дитина","relations_other":"","inn_hidden":false,"family_name":"Мєзєнцев П. Є","name_hidden":false,"name_unclear":false},{"inn":"","relations":"Дитина","relations_other":"","inn_hidden":false,"family_name":"Мєзєнцева М. Є","name_hidden":false,"name_unclear":false}],"full_name_suggest":{"output":"Мєзєнцев Євген Ігорович","input":["Мєзєнцев Євген Ігорович","Євген Ігорович Мєзєнцев","Євген Мєзєнцев"]},"patronymic":"Ігорович"},"source":"VULYK","estate":{"23":[{"costs":"","costs_comment":"","address_hidden":false,"region_hidden":true,"space_comment":"Власність","space":"637","address":"","region":"","costs_rent_comment":"","space_units":"м²","space_units_hidden":false,"costs_rent":""}],"24":[{"costs_rent":"","region":"","costs":"","costs_rent_comment":"","costs_comment":"","region_hidden":true,"space_comment":"Власність","space_units":"м²","space":"180.5","address":""}],"25":[{"space_hidden":false,"costs":"","costs_comment":"","address_hidden":false,"region_hidden":true,"space_comment":"оренда","space_unclear":false,"space":"183.9","address":"","region":"","costs_rent_comment":"","space_units":"м²","costs_rent":"53952.75"}]},"intro":{"declaration_year":"2013","isnotdeclaration":""}}