{"id":"vulyk_103_87","ft_src":"Mercedes-Benz GL 450\nу користуванні\n4663 куб. см.\n2006\n1998 куб. см.\nMazda CX-5\n2012\n52300\n75.6\n87.8\n51.2\n412800\n924400\n2015\n4663 куб. см.\nу користуванні\n2006\nMercedes-Benz GL 450\n1998 куб. см.\n2012\nMazda CX-5\n52300\n75.6\n87.8\n51.2\nПузиревський\nПузиревський Євген Борисович\nЄвген Борисович Пузиревський\nЄвген Пузиревський\nПузиревський Євген Борисович\nПузиревський Євген Борисович\nБорисович\nПодружжя\nПузиревська Тетяна Валентинівна\nЄвген\nВищий спеціалізований суд з розгляду цивільних і кримінальних справ\nсуддя вищого спецiалiзованого суду україни з розгляду цивiльних і кримiнальних справ\nЗагальнодержавний регіон\n280129\n39127\nзі слів\n418545\n29933\n94270\n29933\n5019\n924400\n412800\n2015\n280129\n29933\n94270\nзі слів\n29933\n418545\n5019\n39127\nПодружжя\nПузиревська Тетяна Валентинівна\nПузиревський\nБорисович\nсуддя вищого спецiалiзованого суду україни з розгляду цивiльних і кримiнальних справ\nВищий спеціалізований суд з розгляду цивільних і кримінальних справ\nЗагальнодержавний регіон\nПузиревський Євген Борисович\nПузиревський Євген Борисович\nЄвген Борисович Пузиревський\nЄвген Пузиревський\nПузиревський Євген Борисович\nЄвген","estate":{"23":[{"costs":"","address":"","space_units":"м²","costs_rent_comment":"","space":"52300","space_comment":"","region_hidden":true,"costs_comment":"","region":"","address_hidden":false,"costs_rent":""}],"25":[{"address":"","space_units":"м²","costs_comment":"","region_hidden":true,"space_comment":"","address_hidden":false,"space_comment_hidden":true,"space":"87.8","space_comment_unclear":false,"costs_rent_comment":"","costs":"","region":"","costs_rent":""},{"costs":"","address":"","space_units":"м²","costs_rent_comment":"","space":"51.2","space_comment":"","region_hidden":false,"costs_comment":"","region":"","costs_rent":""}],"31":[{"costs_property_comment":"","address":"","space_units":"м²","space_hidden":false,"region_hidden":true,"costs_property":"","space_comment":"","address_hidden":true,"address_unclear":false,"costs_rent_comment":"","space":"75.6","costs_rent":""}]},"vehicle":{"35":[{"sum_comment":"","brand_info_hidden":false,"brand_info":"4663 куб. см.","sum":"","brand_unclear":false,"brand_hidden":false,"brand":"Mercedes-Benz GL 450","sum_rent":"","brand_info_unclear":false,"sum_rent_comment":"у користуванні","year":"2006"}],"40":[{"year_hidden":false,"brand_info":"1998 куб. см.","sum":"","sum_rent_comment":"","brand_hidden":false,"brand":"Mazda CX-5","sum_rent":"","sum_comment":"","year":"2012","brand_info_unclear":false}]},"source":"VULYK","income":{"5":{"family_comment":"зі слів","family":"29933","comment":"","value_unclear":false,"family_hidden":false,"value":"418545"},"6":{"family_comment":"","value":"280129","family":"","comment":""},"7":{"family":"","family_comment":"","value":"","comment":"","source_name":""},"8":{"family_comment":"","value":"","family":"","comment":""},"9":{"family_comment":"","value":"94270","family":"29933","comment":""},"10":{"family_comment":"","value":"","family":"","comment":""},"11":{"family_comment":"","family_hidden":false,"value":"","family":"","comment":""},"12":{"family_comment":"","value":"","family":"","comment":""},"13":{"family_comment":"","value":"","family":"","comment":""},"14":{"family_comment":"","value":"","family":"","comment":""},"15":{"family_comment":"","value":"","family":"","comment":""},"16":{"family_comment":"","value":"","family":"","comment":""},"17":{"family_comment":"","value":"","family":"","comment":"","family_comment_unclear":false},"18":{"family_comment":"","value":"","family":"","comment":""},"19":{"family_comment":"","value":"5019","family":"","comment":""},"20":{"family_comment":"","family":"","comment":"","family_unclear":false,"family_hidden":false,"value":"39127"}},"banks":{"45":[{"sum_units":"UAH","sum_comment":"","sum_foreign_units":"UAH","sum_hidden":false,"sum":"924400","sum_foreign_comment":"","sum_foreign":"","sum_unclear":false,"sum_comment_hidden":true}],"51":[{"sum_units":"UAH","sum_comment":"","sum_foreign_units":"UAH","sum_hidden":false,"sum":"412800","sum_foreign_comment_hidden":false,"sum_foreign_comment":"","sum_foreign":"","sum_foreign_hidden":false,"sum_comment_hidden":true}]},"declaration":{"additional_info_text":"","additional_info":"","date":"2016-03-16T00:00:00","url":"http://static.declarations.com.ua/declarations/chosen_ones/judges_batch/1311_puzyrevskyi_ievhen_borysovych.pdf"},"general":{"inn":"","addresses":[{"place_city_type_hidden":false,"place_city_type":"","place_city_hidden":true,"place_hidden":true,"place_district":"","place_district_hidden":false,"place":"","place_city":"","place_address_hidden":true,"place_address":""}],"last_name":"Пузиревський","full_name":"Пузиревський Євген Борисович","family":[{"inn":"","family_name":"Пузиревська Тетяна Валентинівна","relations_hidden":false,"name_unclear":false,"relations":"Подружжя","inn_hidden":true,"name_hidden":true,"relations_other":""}],"patronymic":"Борисович","inn_hidden":true,"name":"Євген","post":{"office":"Вищий спеціалізований суд з розгляду цивільних і кримінальних справ","region_unclear":false,"post":"суддя вищого спецiалiзованого суду україни з розгляду цивiльних і кримiнальних справ","region":"Загальнодержавний регіон","office_unclear":false},"family_raw":"","full_name_suggest":{"input":["Пузиревський Євген Борисович","Євген Борисович Пузиревський","Євген Пузиревський"],"output":"Пузиревський Євген Борисович"}},"liabilities":{"54":{"sum_foreign_comment_hidden":false,"sum_foreign_comment_unclear":false,"sum_hidden":false,"sum":"","sum_foreign_comment":"","sum_comment":"","sum_unclear":false,"sum_foreign":"","sum_comment_hidden":false,"sum_foreign_hidden":false},"55":{"sum_comment":"","sum_foreign_comment":"","sum_foreign":"","sum":""},"56":{"sum_comment":"","sum_foreign_comment":"","sum_foreign":"","sum":""},"57":{"sum_comment":"","sum_hidden":false,"sum":"","sum_foreign_comment":"","sum_foreign":"","sum_comment_hidden":false,"sum_foreign_hidden":false,"sum_foreign_comment_hidden":false},"58":{"sum_comment":"","sum_hidden":false,"sum":"","sum_foreign_comment":"","sum_foreign":"","sum_comment_hidden":false,"sum_foreign_hidden":false,"sum_foreign_comment_hidden":false},"59":{"sum_comment":"","sum_hidden":false,"sum":"","sum_foreign_comment":"","sum_foreign":"","sum_comment_hidden":false,"sum_foreign_hidden":false,"sum_foreign_comment_hidden":false},"60":{"sum_comment":"","sum_hidden":false,"sum":"","sum_foreign_comment":"","sum_foreign":"","sum_comment_hidden":false},"61":{"sum_comment":"","sum_foreign_comment":"","sum_foreign":"","sum":""},"62":{"sum_comment":"","sum_foreign_comment":"","sum_foreign":"","sum":"","sum_comment_hidden":false},"63":{"sum_comment":"","sum_foreign_comment":"","sum_foreign":"","sum":""},"64":{"sum_comment":"","sum_foreign_comment":"","sum_foreign":"","sum":""}},"intro":{"declaration_year":"2015"}}