{"income":{"5":{"value":"209712","family_comment":"","value_unclear":false,"family_hidden":false,"value_hidden":false,"family_unclear":false,"comment_unclear":false,"comment":"","family":""},"6":{"value":"209712","family_unclear":false,"family_hidden":false,"family_comment":"","family":"","comment":""},"7":{"value":"","family_hidden":false,"value_hidden":false,"family_comment":"","source_name":"","family":"","comment":""},"8":{"family_comment":"","value":"","family":"","comment":""},"9":{"family_comment":"","value":"","value_unclear":false,"family":"","comment":""},"10":{"family_comment":"","family_unclear":false,"value":"","family":"","comment":""},"11":{"family_comment":"","value":"","family":"","comment":""},"12":{"family_comment":"","value":"","family":"","comment":""},"13":{"family_comment":"","value":"","family":"","comment":""},"14":{"family_comment":"","value":"","family":"","comment":""},"15":{"family_comment":"","value":"","family":"","comment":""},"16":{"family_comment":"","value":"","family":"","comment":""},"17":{"family_comment":"","value":"","family":"","comment":""},"18":{"family_comment":"","value":"","family":"","comment":""},"19":{"family_comment":"","value":"","family":"","comment":""},"20":{"value":"","value_unclear":false,"family_comment":"","comment_unclear":false,"comment":"","family":""}},"id":"vulyk_71_174","declaration":{"additional_info_text":"","notfull_lostpages":"","date":"2014-12-18T00:00:00","notfull":"","additional_info":"","url":"http://static.declarations.com.ua/declarations/chosen_ones/judges_batch/428_kutsenko_tetiana_rudolfivna.pdf"},"liabilities":{"54":{"sum_foreign_comment":"","sum":"","sum_comment":"","sum_comment_unclear":false,"sum_comment_hidden":false,"sum_unclear":false,"sum_foreign":""},"55":{"sum_foreign_comment":"","sum":"","sum_comment":"","sum_foreign":""},"56":{"sum_foreign_comment":"","sum":"","sum_comment":"","sum_comment_unclear":false,"sum_unclear":false,"sum_foreign":""},"57":{"sum_foreign_comment":"","sum":"","sum_comment":"","sum_comment_hidden":false,"sum_unclear":false,"sum_foreign":""},"58":{"sum_foreign_comment":"","sum":"","sum_comment":"","sum_comment_hidden":false,"sum_unclear":false,"sum_foreign":""},"59":{"sum_foreign_comment":"","sum_comment_hidden":false,"sum":"","sum_comment":"","sum_foreign":""},"60":{"sum_foreign_comment":"","sum_comment_hidden":false,"sum":"","sum_comment":"","sum_foreign":""},"61":{"sum_foreign_comment":"","sum":"","sum_comment":"","sum_foreign":""},"62":{"sum_foreign_comment":"","sum":"","sum_comment":"","sum_foreign":""},"63":{"sum_foreign_comment":"","sum":"","sum_comment":"","sum_unclear":false,"sum_foreign":""},"64":{"sum_foreign_comment":"","sum":"","sum_comment":"","sum_unclear":false,"sum_foreign":""}},"ft_src":"суддя апеляційного суду дніпропетровської області\nДніпропетровська область\nЗагальний апеляційний суд\nТетяна\nРудольфівна\nКуценко\nКуценко Тетяна Рудольфівна\nКуценко Тетяна Рудольфівна\nТетяна Рудольфівна Куценко\nТетяна Куценко\nКуценко Тетяна Рудольфівна\n209712\n209712\n25.2\n2013\n209712\n209712\n209712\n209712\nКуценко Тетяна Рудольфівна\nТетяна Рудольфівна Куценко\nТетяна Куценко\nКуценко Тетяна Рудольфівна\nТетяна\nКуценко Тетяна Рудольфівна\nКуценко\nЗагальний апеляційний суд\nДніпропетровська область\nсуддя апеляційного суду дніпропетровської області\nРудольфівна\n25.2\n2013\nТетяна\nРудольфівна\nКуценко\nКуценко Тетяна Рудольфівна\nТетяна Рудольфівна Куценко\nТетяна Куценко\nКуценко Тетяна Рудольфівна\nДніпропетровська область\nЗагальний апеляційний суд\nсуддя апеляційного суду дніпропетровської області\nКуценко Тетяна Рудольфівна\n25.2\n2013","general":{"inn":"","name":"Тетяна","inn_unclear":false,"patronymic":"Рудольфівна","inn_hidden":true,"family_raw":"","last_name":"Куценко","post":{"post_unclear":false,"region_unclear":false,"post":"суддя апеляційного суду дніпропетровської області","office":"Загальний апеляційний суд","region":"Дніпропетровська область","post_hidden":false,"office_unclear":false},"last_name_unclear":false,"full_name":"Куценко Тетяна Рудольфівна","addresses":[{"place_district":"","place_unclear":false,"place_city":"","place_city_type_hidden":false,"place_district_hidden":false,"place_city_type":"","place_city_hidden":true,"place_address_hidden":true,"place_address":"","place_hidden":true,"place":""}],"patronymic_hidden":true,"full_name_suggest":{"output":"Куценко Тетяна Рудольфівна","input":["Куценко Тетяна Рудольфівна","Тетяна Рудольфівна Куценко","Тетяна Куценко"]},"name_unclear":false},"source":"VULYK","estate":{"25":[{"region_unclear":false,"space_unclear":false,"costs":"","costs_rent_unclear":false,"costs_comment":"","costs_hidden":false,"address_hidden":true,"region_hidden":true,"space_comment":"","space_hidden":false,"space":"25.2","address":"","costs_unclear":false,"region":"","address_unclear":false,"costs_rent_comment":"","costs_rent_hidden":false,"space_comment_unclear":false,"space_units":"м²","costs_rent":""}]},"intro":{"declaration_year":"2013","isnotdeclaration":""}}