{"income":{"5":{"family_comment":"","value":"312685","family":"","comment":""},"6":{"value":"250585","family_comment":"","value_unclear":false,"comment_hidden":true,"family_unclear":false,"family":"","comment":""},"7":{"family_comment":"","value":"","source_name":"","family":"","comment":""},"8":{"family_comment":"","value":"","family":"","comment":""},"9":{"family_comment":"","family_unclear":false,"value":"","family":"","comment":""},"10":{"family_comment":"","value":"","value_unclear":false,"family":"","comment":""},"11":{"family_comment":"","value":"","family":"","comment":""},"12":{"family_comment":"","value":"","family":"","comment":""},"13":{"family_comment":"","value":"","family":"","comment":""},"14":{"family_comment":"","value":"","family":"","comment":""},"15":{"family_comment":"","value":"","family":"","comment":""},"16":{"family_comment":"","value":"","family":"","comment":""},"17":{"family_comment":"","value":"","family":"","comment":""},"18":{"family_comment":"","value":"","family":"","comment":""},"19":{"family_comment":"","value":"1900","family":"","comment":""},"20":{"value":"60200","family":"","value_unclear":false,"family_hidden":false,"family_comment":"","comment_unclear":false,"comment":"","family_comment_unclear":false}},"vehicle":{"35":[{"year_hidden":false,"brand_info":"","sum_rent_comment":"","year":"1998","brand_info_hidden":false,"brand_info_unclear":false,"sum_rent":"","sum":"","brand":"ВАЗ 2106","sum_comment":"2002","brand_unclear":false,"brand_hidden":false}]},"id":"vulyk_97_114","declaration":{"additional_info_text":"","notfull_lostpages":"","date":"2015-03-27T00:00:00","notfull":"","additional_info":"","url":"http://static.declarations.com.ua/declarations/chosen_ones/judges_batch/4015_kucheriavets_oleksandr_mykolaiovych.pdf"},"liabilities":{"54":{"sum_foreign_comment":"","sum":"","sum_comment":"","sum_comment_unclear":false,"sum_hidden":false,"sum_comment_hidden":false,"sum_unclear":false,"sum_foreign":""},"55":{"sum_foreign_comment":"","sum":"","sum_comment":"","sum_foreign":""},"56":{"sum_foreign_comment":"","sum":"","sum_comment":"","sum_foreign":""},"57":{"sum_foreign_comment":"","sum":"","sum_comment":"","sum_comment_unclear":false,"sum_hidden":false,"sum_comment_hidden":false,"sum_unclear":false,"sum_foreign":""},"58":{"sum_foreign_comment":"","sum":"","sum_comment":"","sum_comment_unclear":false,"sum_hidden":false,"sum_comment_hidden":false,"sum_unclear":false,"sum_foreign":""},"59":{"sum_foreign_comment":"","sum":"","sum_comment":"","sum_foreign":""},"60":{"sum_foreign_comment":"","sum":"","sum_comment":"","sum_comment_unclear":false,"sum_hidden":false,"sum_comment_hidden":false,"sum_foreign":""},"61":{"sum_foreign_comment":"","sum":"","sum_comment":"","sum_foreign":""},"62":{"sum_foreign_comment":"","sum":"","sum_comment":"","sum_unclear":false,"sum_foreign":""},"63":{"sum_foreign_comment":"","sum":"","sum_hidden":false,"sum_comment":"","sum_foreign":""},"64":{"sum_foreign_comment":"","sum":"","sum_comment":"","sum_foreign":""}},"ft_src":"суддя носівського районного суду\nЧернігівська область\nЗагальний місцевий суд\nОлександр\nМиколайович\nКучерявець Олександр Миколайович\nОлександр Миколайович Кучерявець\nОлександр Кучерявець\nКучерявець Олександр Миколайович\nКучерявець Олександр Миколайович\nКучерявець\n2002\nВАЗ 2106\n1998\nприватизація\n2000\n2014\n250585\n312685\n1900\n60200\nВАЗ 2106\n2002\n1998\n2014\nЗагальний місцевий суд\nЧернігівська область\nсуддя носівського районного суду\nКучерявець Олександр Миколайович\nОлександр Миколайович Кучерявець\nОлександр Кучерявець\nКучерявець Олександр Миколайович\nКучерявець Олександр Миколайович\nОлександр\nКучерявець\nМиколайович\n250585\n60200\n312685\n1900\n2000\nприватизація\nМиколайович\nКучерявець\nОлександр\nКучерявець Олександр Миколайович\nОлександр Миколайович Кучерявець\nОлександр Кучерявець\nКучерявець Олександр Миколайович\nЧернігівська область\nЗагальний місцевий суд\nсуддя носівського районного суду\nКучерявець Олександр Миколайович\n1998\nВАЗ 2106\n2002\n1900\n60200\n312685\n250585\nприватизація\n2000\n2014","general":{"name_hidden":false,"name":"Олександр","last_name_hidden":false,"inn":"","last_name":"Кучерявець","patronymic":"Миколайович","inn_hidden":true,"family_raw":"","inn_unclear":false,"post":{"region_unclear":false,"region":"Чернігівська область","post":"суддя носівського районного суду","office":"Загальний місцевий суд","office_unclear":false,"post_hidden":false},"full_name":"Кучерявець Олександр Миколайович","addresses":[{"place_district":"","place_city_hidden":true,"place_city":"","place_city_unclear":false,"place_district_hidden":false,"place_city_type":"","place_address_hidden":true,"place_city_type_hidden":false,"place_address":"","place_hidden":true,"place":""}],"patronymic_hidden":false,"full_name_suggest":{"output":"Кучерявець Олександр Миколайович","input":["Кучерявець Олександр Миколайович","Олександр Миколайович Кучерявець","Олександр Кучерявець"]}},"source":"VULYK","estate":{"23":[{"region_unclear":false,"space_unclear":false,"costs":"","costs_rent_unclear":false,"costs_comment":"","address_hidden":false,"region_hidden":true,"space_comment":"приватизація","space":"2000","address":"","region":"","address_unclear":false,"costs_rent_comment":"","space_units":"м²","costs_rent":""}]},"intro":{"declaration_year":"2014","isnotdeclaration":""}}