{"income":{"5":{"value":"486357.93","family_comment":"","family_hidden":false,"value_hidden":false,"family_unclear":false,"family":"211528.78","comment":""},"6":{"value":"275624.85","comment_unclear":false,"family_comment":"","family":"211528.78","comment":"","family_comment_unclear":false},"7":{"family_comment":"","value":"","source_name":"","family":"","comment":""},"8":{"family_comment":"","value":"","family":"","comment":""},"9":{"family_comment":"","value":"","family":"","comment":""},"10":{"family_comment":"","value":"","family":"","comment":""},"11":{"family_comment":"","value":"","family":"","comment":"","family_comment_unclear":false},"12":{"family_comment":"","value":"","family":"","comment":""},"13":{"family_comment":"","value":"","family":"","comment":""},"14":{"family_comment":"","value":"","family":"","comment":""},"15":{"family_comment":"","value":"210733.08","family":"","comment":""},"16":{"family_comment":"","value":"","family":"","comment":""},"17":{"family_comment":"","value":"","family":"","comment":""},"18":{"family_comment":"","value":"","family":"","comment":""},"19":{"family_comment":"","value":"","family":"","comment":"","value_hidden":false},"20":{"family_comment":"","value":"","comment_unclear":false,"family":"","comment":""}},"vehicle":{"35":[{"brand_info":"5.7 куб. дм, 317 к.с., 227 кВт , 585,5 см","sum_rent_comment":"сплачено кредит у 2014р","brand":"Nissan Armada","sum_comment":"","sum_rent_hidden":false,"year":"2007","sum_hidden":false,"brand_info_hidden":false,"brand_info_unclear":false,"sum":"","sum_rent":""},{"brand_info":"3.2 куб. дм, 170 к. с., 511,3 см","sum_rent_comment":"","brand":"Mercedes-Benz S320","sum_comment":"","year":"1998","sum":"","sum_rent":""}],"39":[{"brand_info":"мотоцикл","sum":"","brand":"MB 650","sum_comment":"","brand_unclear":false,"year":"1982","brand_hidden":false,"sum_rent_comment":"","sum_rent":""}]},"id":"vulyk_51_80","banks":{"45":[{"sum_foreign_comment":"","sum_units":"UAH","sum_comment":"","sum_comment_unclear":false,"sum_hidden":false,"sum_foreign_units":"UAH","sum_comment_hidden":false,"sum":"","sum_foreign":""},{"sum_foreign_comment":"","sum_units":"","sum_comment":"","sum_foreign_units":"","sum":"","sum_foreign":""},{"sum_foreign_comment":"","sum_units":"","sum_comment":"","sum_foreign_units":"","sum":"","sum_foreign":""},{"sum_foreign_comment":"","sum_units":"","sum_comment":"","sum_foreign_units":"","sum":"","sum_foreign":""},{"sum_foreign_comment":"","sum_units":"","sum_comment":"","sum_foreign_units":"","sum":"","sum_unclear":false,"sum_foreign":""}],"46":[{"sum_foreign_comment":"","sum_units":"UAH","sum_comment":"","sum_foreign_units":"UAH","sum":"","sum_foreign":""}],"47":[{"sum_foreign_comment":"","sum_units":"UAH","sum_comment":"","sum_foreign_units":"UAH","sum":"","sum_foreign":""}],"48":[{"sum_foreign_comment":"","sum_units":"UAH","sum_comment":"","sum_foreign_units":"UAH","sum":"","sum_foreign":""}],"49":[{"sum_foreign_comment":"","sum_units":"UAH","sum_comment":"","sum_foreign_units":"UAH","sum":"","sum_foreign":""}],"50":[{"sum_foreign_comment":"","sum_units":"UAH","sum_comment":"","sum_foreign_units":"UAH","sum":"","sum_foreign":""}],"51":[{"sum_foreign_comment":"","sum_units":"UAH","sum_comment":"","sum_foreign_units":"UAH","sum_comment_hidden":false,"sum":"","sum_foreign":""},{"sum_foreign_comment":"","sum_units":"","sum_comment":"","sum_foreign_units":"","sum":"","sum_foreign":""},{"sum_foreign_comment":"","sum_units":"","sum_comment":"","sum_foreign_units":"","sum":"","sum_foreign":""}],"52":[{"sum_foreign_comment":"","sum_units":"UAH","sum_comment":"","sum_foreign_units":"UAH","sum_comment_hidden":false,"sum":"","sum_foreign":""}],"53":[{"sum_foreign_comment":"","sum_units":"UAH","sum_comment":"","sum_foreign_units":"UAH","sum":"","sum_foreign":""}]},"declaration":{"additional_info_text":"","notfull_lostpages":"","date":"2015-03-31T00:00:00","notfull":"","additional_info":"","url":"http://static.declarations.com.ua/declarations/chosen_ones/mega_batch/prysiazhniuk_oleh_bohdanovych.pdf"},"liabilities":{"54":{"sum_foreign_comment":"","sum_comment_hidden":false,"sum":"","sum_comment":"","sum_foreign":""},"55":{"sum_foreign_comment":"","sum":"","sum_comment":"","sum_foreign":""},"56":{"sum_foreign_comment":"","sum":"","sum_comment":"","sum_foreign":""},"57":{"sum_foreign_comment":"","sum":"84000","sum_comment":"","sum_hidden":false,"sum_comment_hidden":false,"sum_foreign":""},"58":{"sum_foreign_comment":"","sum_comment_hidden":false,"sum":"","sum_comment":"","sum_foreign":""},"59":{"sum_foreign_comment":"","sum":"","sum_comment":"","sum_foreign":""},"60":{"sum_foreign_comment":"","sum":"","sum_comment":"","sum_foreign":""},"61":{"sum_foreign_comment":"","sum":"","sum_comment":"","sum_foreign":""},"62":{"sum_foreign_comment":"","sum":"","sum_comment":"","sum_foreign":""},"63":{"sum_foreign_comment":"","sum_comment_hidden":false,"sum":"","sum_comment":"","sum_foreign":""},"64":{"sum_foreign_comment":"","sum":"","sum_comment":"","sum_foreign":""}},"ft_src":"84000\nПрисяжнюк Олег Богданович\nсуддя апеляційного суду міста києва\nм. Київ\nЗагальний апеляційний суд\nОлег\nПрисяжнюк Світлана Борисівна\nПодружжя\nПрисяжнюк Ірина Олегівна\nДитина\nПрисяжнюк Олег Богданович\nОлег Богданович Присяжнюк\nОлег Присяжнюк\nПрисяжнюк Олег Богданович\nПрисяжнюк\nБогданович\nMB 650\nмотоцикл\n1982\nNissan Armada\nсплачено кредит у 2014р\n5.7 куб. дм, 317 к.с., 227 кВт , 585,5 см\n2007\n3.2 куб. дм, 170 к. с., 511,3 см\n1998\nMercedes-Benz S320\n2014\n5.7 куб. дм, 317 к.с., 227 кВт , 585,5 см\nсплачено кредит у 2014р\n2007\nNissan Armada\n3.2 куб. дм, 170 к. с., 511,3 см\nMercedes-Benz S320\n1998\nмотоцикл\n1982\nMB 650\n70\n20% готовності, недобудова\n110\n1/2 будинку\n68\n1/3, придбання у власність у 1995р\n84\n/1/2\n2070\nпридбання у власність 2004р\n1200\nпридбання  у власність у 2013р\n3930\nпридбання у власність у 2008р\n1000\n450\n90% готовності недобудова\n150\nнедобудова\n40\nПрисяжнюк\nПрисяжнюк Олег Богданович\nОлег Богданович Присяжнюк\nОлег Присяжнюк\nПрисяжнюк Олег Богданович\nОлег\nБогданович\nПрисяжнюк Олег Богданович\nЗагальний апеляційний суд\nсуддя апеляційного суду міста києва\nм. Київ\nПодружжя\nПрисяжнюк Світлана Борисівна\nДитина\nПрисяжнюк Ірина Олегівна\n84000\n275624.85\n211528.78\n210733.08\n211528.78\n486357.93\n2014\n84000\n20% готовності, недобудова\n70\n1000\n90% готовності недобудова\n450\nнедобудова\n150\nпридбання у власність 2004р\n2070\nпридбання  у власність у 2013р\n1200\nпридбання у власність у 2008р\n3930\n1/2 будинку\n110\n40\n1/3, придбання у власність у 1995р\n68\n/1/2\n84\nПрисяжнюк Світлана Борисівна\nПодружжя\nПрисяжнюк Ірина Олегівна\nДитина\nБогданович\nПрисяжнюк\nм. Київ\nЗагальний апеляційний суд\nсуддя апеляційного суду міста києва\nПрисяжнюк Олег Богданович\nПрисяжнюк Олег Богданович\nОлег Богданович Присяжнюк\nОлег Присяжнюк\nПрисяжнюк Олег Богданович\nОлег\n211528.78\n275624.85\n210733.08\n211528.78\n486357.93\nMB 650\nмотоцикл\n1982\nсплачено кредит у 2014р\n2007\nNissan Armada\n5.7 куб. дм, 317 к.с., 227 кВт , 585,5 см\nMercedes-Benz S320\n3.2 куб. дм, 170 к. с., 511,3 см\n1998\n210733.08\n486357.93\n211528.78\n275624.85\n211528.78\n40\nпридбання у власність 2004р\n2070\nпридбання  у власність у 2013р\n1200\nпридбання у власність у 2008р\n3930\n90% готовності недобудова\n450\nнедобудова\n150\n20% готовності, недобудова\n70\n1/2 будинку\n110\n1/3, придбання у власність у 1995р\n68\n/1/2\n84\n1000\n2014","general":{"inn":"","inn_hidden":true,"last_name":"Присяжнюк","post":{"post":"суддя апеляційного суду міста києва","region":"м. Київ","office_hidden":false,"office":"Загальний апеляційний суд","office_unclear":false,"region_hidden":false},"name":"Олег","full_name":"Присяжнюк Олег Богданович","family_raw":"","addresses":[{"place_district":"","place_city_hidden":false,"place_city":"","place_city_type_hidden":false,"place_district_hidden":false,"place_city_type":"","place_address_hidden":false,"place_address":"","place_hidden":true,"place":""}],"family":[{"inn":"","relations":"Подружжя","relations_other":"","inn_hidden":false,"family_name":"Присяжнюк Світлана Борисівна","name_hidden":false,"name_unclear":false},{"inn":"","inn_hidden":false,"relations_hidden":false,"family_name":"Присяжнюк Ірина Олегівна","relations_other":"","relations":"Дитина","name_hidden":false,"name_unclear":false}],"full_name_suggest":{"output":"Присяжнюк Олег Богданович","input":["Присяжнюк Олег Богданович","Олег Богданович Присяжнюк","Олег Присяжнюк"]},"patronymic":"Богданович"},"source":"VULYK","estate":{"23":[{"costs":"","costs_comment":"","costs_hidden":false,"address_hidden":false,"region_hidden":true,"space_comment":"придбання у власність 2004р","space":"2070","address":"","region":"","address_unclear":false,"costs_rent_comment":"","costs_rent_hidden":false,"space_units":"м²","costs_rent":""},{"costs":"","costs_comment":"","costs_hidden":false,"region_hidden":false,"space_comment":"придбання  у власність у 2013р","space":"1200","address":"","region":"","costs_rent_comment":"","costs_rent_hidden":false,"space_units":"м²","costs_rent":""},{"space":"3930","region":"","costs":"","costs_rent_comment":"","costs_comment":"","address_unclear":false,"space_comment":"придбання у власність у 2008р","space_units":"м²","costs_rent":"","address":""},{"costs_rent":"","region":"","costs":"","costs_rent_comment":"","costs_comment":"","space_comment":"","space_units":"","space":"","address":""}],"24":[{"costs_rent":"","region":"","costs":"","costs_rent_comment":"","costs_comment":"","address_hidden":false,"region_hidden":true,"space_comment":"90% готовності недобудова","space_units":"м²","space":"450","address":""},{"costs_rent":"","costs":"","costs_rent_comment":"","costs_comment":"","space_comment":"недобудова","space_units":"м²","space":"150","address":""}],"25":[{"space_unclear":false,"costs":"","costs_comment":"","costs_hidden":false,"address_hidden":false,"region_hidden":true,"space_comment":"1/3, придбання у власність у 1995р","space_hidden":false,"space":"68","address":"","region":"","address_unclear":false,"costs_rent_comment":"","space_units":"м²","costs_rent":""},{"space_hidden":false,"costs":"","costs_comment":"","costs_hidden":false,"address_hidden":false,"region_hidden":false,"space_comment":"/1/2","space":"84","address":"","region":"","address_unclear":false,"costs_rent_comment":"","costs_rent_hidden":false,"space_units":"м²","costs_rent":""}],"27":[{"costs_rent":"","region":"","costs":"","costs_rent_comment":"","costs_comment":"","address_hidden":false,"region_hidden":true,"space_comment":"20% готовності, недобудова","space_units":"м²","space":"70","address":""}],"29":[{"address_hidden":false,"region_hidden":true,"space_comment":"","space":"1000","address":"","region":"","costs_property":"","costs_rent_comment":"","address_unclear":false,"space_units":"м²","costs_property_comment":"","costs_rent":""}],"30":[{"address_hidden":false,"region_hidden":true,"space_comment":"1/2 будинку","space":"110","address":"","region":"","costs_property":"","costs_rent_comment":"","space_comment_unclear":false,"space_units":"м²","costs_property_comment":"","costs_rent":""}],"31":[{"space_hidden":false,"costs_property_hidden":false,"address_hidden":false,"region_hidden":true,"space_comment":"","space_unclear":false,"space":"40","address":"","region":"","address_unclear":false,"costs_rent_comment":"","costs_rent_hidden":false,"costs_property":"","space_units":"м²","costs_property_comment":"","costs_rent":""}]},"intro":{"declaration_year":"2014","isnotdeclaration":""}}