{"income":{"5":{"family_comment":"","value":"211923","family":"","comment":""},"6":{"family_comment":"","value":"198525","value_unclear":false,"family":"","comment":""},"7":{"value":"","family_comment":"","source_name":"","family":"","comment":"","source_name_hidden":false},"8":{"family_comment":"","value":"","family":"","comment":""},"9":{"family_comment":"","value":"","family":"","comment":""},"10":{"family_comment":"","value":"13398","family":"","comment":""},"11":{"family_comment":"","value":"","comment_hidden":false,"family":"","comment":""},"12":{"family_comment":"","value":"","family":"","comment":""},"13":{"family_comment":"","value":"","family":"","comment":""},"14":{"family_comment":"","value":"","family":"","comment":""},"15":{"value":"","family_comment":"","value_unclear":false,"family_unclear":false,"family":"","comment":""},"16":{"family_comment":"","value":"","family":"","comment":""},"17":{"family_comment":"","value":"","family":"","comment":""},"18":{"family_comment":"","value":"","family":"","comment":""},"19":{"family_comment":"","value":"","family":"","comment":""},"20":{"family_comment":"","value":"","comment_unclear":false,"family":"","comment":""}},"vehicle":{"35":[{"brand_info":"1997 , власність","sum_rent_comment":"","brand":"Honda Accord","sum_comment":"","year":"2012","brand_hidden":false,"brand_info_unclear":false,"sum":"","sum_rent":""}]},"id":"vulyk_104_34","declaration":{"date":"2016-03-16T00:00:00","additional_info_text":"","additional_info":"","url":"http://static.declarations.com.ua/declarations/chosen_ones/judges_batch/1832_baranets_oleksandr_mykolaiovych_2015.pdf"},"liabilities":{"54":{"sum_foreign_comment":"","sum_foreign_hidden":false,"sum_comment":"","sum_hidden":false,"sum_comment_hidden":false,"sum_unclear":false,"sum":"","sum_foreign":""},"55":{"sum_foreign_comment":"","sum":"","sum_comment":"","sum_foreign":""},"56":{"sum_foreign_comment":"","sum":"","sum_comment":"","sum_unclear":false,"sum_foreign":""},"57":{"sum_foreign_comment":"","sum_foreign_hidden":false,"sum_comment":"","sum_comment_unclear":false,"sum_comment_hidden":false,"sum":"","sum_foreign":""},"58":{"sum_foreign_comment":"","sum":"","sum_comment":"","sum_unclear":false,"sum_foreign":""},"59":{"sum_foreign_comment":"","sum":"","sum_comment":"","sum_foreign":""},"60":{"sum_foreign_comment":"","sum_foreign_hidden":false,"sum_comment":"","sum_comment_hidden":false,"sum":"","sum_foreign":""},"61":{"sum_foreign_comment":"","sum":"","sum_comment":"","sum_foreign":""},"62":{"sum_foreign_comment":"","sum":"","sum_comment":"","sum_foreign":""},"63":{"sum_foreign_comment":"","sum":"","sum_comment":"","sum_foreign":""},"64":{"sum_foreign_comment":"","sum":"","sum_comment":"","sum_foreign":""}},"ft_src":"Баранець Олександр Миколайович\nсуддя\nм. Київ\nАпеляційний господарський суд\nОлександр\nБаранець В. І\nПодружжя\nБаранець В. О\nДитина\nБаранець Олександр Миколайович\nОлександр Миколайович Баранець\nОлександр Баранець\nБаранець Олександр Миколайович\nБаранець\nМиколайович\n2012\nHonda Accord\n1997 , власність\n1200\n25\n1200\n65.9\n54.6\n2015\n198525\n13398\n211923\n1997 , власність\nHonda Accord\n2012\n2015\nПодружжя\nБаранець В. І\nДитина\nБаранець В. О\nБаранець\nБаранець Олександр Миколайович\nОлександр Миколайович Баранець\nОлександр Баранець\nБаранець Олександр Миколайович\nБаранець Олександр Миколайович\nОлександр\nМиколайович\nАпеляційний господарський суд\nсуддя\nм. Київ\n198525\n211923\n13398\n1200\n1200\n25\n65.9\n54.6\nПодружжя\nБаранець В. І\nДитина\nБаранець В. О\nМиколайович\nБаранець\nсуддя\nАпеляційний господарський суд\nм. Київ\nБаранець Олександр Миколайович\nБаранець Олександр Миколайович\nОлександр Миколайович Баранець\nОлександр Баранець\nБаранець Олександр Миколайович\nОлександр\n2012\n1997 , власність\nHonda Accord\n13398\n211923\n198525\n65.9\n1200\n25\n54.6\n1200\n2015","general":{"inn":"","inn_hidden":true,"last_name":"Баранець","post":{"region":"м. Київ","region_unclear":false,"post":"суддя","office_unclear":false,"office":"Апеляційний господарський суд"},"name":"Олександр","full_name":"Баранець Олександр Миколайович","family_raw":"","addresses":[{"place_district":"","place_city_hidden":true,"place_city":"","place_city_type_hidden":false,"place_district_hidden":false,"place_city_type":"","place_address_hidden":true,"place_address":"","place_hidden":true,"place":""}],"family":[{"inn":"","relations":"Подружжя","relations_other":"","inn_hidden":true,"family_name":"Баранець В. І","name_hidden":true,"name_unclear":false},{"inn":"","relations":"Дитина","relations_other":"","inn_hidden":true,"family_name":"Баранець В. О","name_hidden":false,"name_unclear":false}],"full_name_suggest":{"output":"Баранець Олександр Миколайович","input":["Баранець Олександр Миколайович","Олександр Миколайович Баранець","Олександр Баранець"]},"patronymic":"Миколайович"},"source":"VULYK","estate":{"23":[{"space_hidden":false,"costs":"","costs_comment":"","address_hidden":false,"region_hidden":true,"space_comment":"","space":"1200","address":"","region":"","costs_rent_comment":"","space_comment_unclear":false,"space_units":"м²","costs_rent":""}],"25":[{"costs":"","costs_comment":"","address_hidden":false,"region_hidden":true,"space_comment":"","space":"54.6","address":"","costs_unclear":false,"region":"","costs_rent_comment":"","space_comment_unclear":false,"space_units":"м²","costs_rent":""}],"27":[{"costs":"","costs_comment":"","address_hidden":false,"region_hidden":true,"space_comment":"","space":"25","address":"","region":"","costs_rent_comment":"","space_comment_unclear":false,"space_units":"м²","costs_rent":""}],"29":[{"space_unclear":false,"address_hidden":false,"region_hidden":true,"space_comment":"","space":"1200","address":"","region":"","costs_property":"","costs_rent_comment":"","space_units":"м²","costs_property_comment":"","costs_rent":""}],"31":[{"space_unclear":false,"address_hidden":false,"region_hidden":true,"space_comment":"","space_hidden":false,"space":"65.9","address":"","region":"","costs_property":"","costs_rent_comment":"","space_units":"м²","costs_property_comment":"","costs_rent":""}]},"intro":{"declaration_year":"2015","isnotdeclaration":""}}