{"id":"vulyk_99_77","declaration":{"notfull_lostpages":"","date":"2016-03-29T00:00:00","notfull":"","url":"http://static.declarations.com.ua/declarations/chosen_ones/judges_batch/626_krapivnytska_natalia_leonidivna_2015.pdf"},"estate":{"25":[{"address":"","space_units":"м²","space_hidden":false,"space_unclear":false,"region_hidden":true,"costs_comment":"","space_comment":"1/2 частина","address_hidden":false,"space":"34.5","costs_rent_comment":"","costs":"","region":"","costs_rent":""}],"29":[{"costs_property_comment":"","address":"","space_units":"м²","costs_rent_comment":"","space":"800","region":"","region_hidden":true,"costs_property":"","space_comment":"","address_hidden":true,"costs_rent":""}],"31":[{"costs_property_comment":"","address":"","space_units":"м²","costs_rent_comment":"","space":"34.5","region":"","region_hidden":true,"costs_property":"","space_comment":"1/2 частина","address_hidden":true,"costs_rent":""},{"costs_property_comment":"","address":"","space_units":"м²","costs_rent_comment":"","space":"44.5","region":"","costs_property":"","space_comment":"б.192/кв.29","costs_rent":""},{"costs_property_comment":"","address":"","space_units":"м²","costs_rent_comment":"","space":"73.4","costs_property":"","space_comment":"б.20/кв.98","costs_rent":""}]},"vehicle":{"40":[{"sum_comment":"","brand_info_hidden":false,"sum_rent":"","sum":"","brand_unclear":true,"year":"2008","brand":"Hyundai Accent","brand_info":"1399 куб. см.","sum_rent_comment":"","brand_info_unclear":false}]},"source":"VULYK","income":{"5":{"family_comment":"","family":"537699","comment":"","value_unclear":false,"family_unclear":false,"value":"203045"},"6":{"family_comment":"","family":"124238","comment":"","value_unclear":false,"family_unclear":false,"value":"203045"},"7":{"family":"","family_comment":"","value":"","comment":"","source_name":""},"8":{"family_comment":"","value":"","family":"","comment":""},"9":{"family_comment":"","value":"","family":"730","comment":""},"10":{"family_comment":"","value":"","family":"","comment":""},"11":{"family_comment":"","value":"","family":"","comment":""},"12":{"family_comment":"","value":"","family":"8084","comment":""},"13":{"family_comment":"","value":"","family":"","comment":""},"14":{"family_comment":"","value":"","family":"335491","comment":""},"15":{"family_comment":"","value":"","family":"","comment":"","value_unclear":false},"16":{"family_comment":"","value":"","family":"","comment":""},"17":{"family_comment":"","value":"","family":"","comment":""},"18":{"family_comment":"","value":"","family":"","comment":""},"19":{"family_comment":"","value":"","family":"","comment":""},"20":{"family_comment":"","family":"69156","comment":"","value_unclear":false,"family_unclear":false,"value":"","family_comment_unclear":false}},"banks":{"51":[{"sum_comment_unclear":false,"sum_units":"UAH","sum_foreign_units":"UAH","sum":"706","sum_foreign_comment":"","sum_comment":"","sum_foreign":"","sum_comment_hidden":true}]},"ft_src":"1399 куб. см.\nHyundai Accent\n2008\n706\n2015\n1399 куб. см.\n2008\nHyundai Accent\n706\n800\n34.5\n1/2 частина\n44.5\nб.192/кв.29\n73.4\nб.20/кв.98\n34.5\n1/2 частина\nКрапівницька\nКрапівницька Наталя Леонідівна\nНаталя Леонідівна Крапівницька\nНаталя Крапівницька\nКрапівницька Наталя Леонідівна\nНаталя\nЛеонідівна\nКрапівницька Наталя Леонідівна\nАдміністративний місцевий суд\nсуддя вінницького окружного адміністративного суду\nВінницька область\nПодружжя\nГорбатюк В. В\nДитина\nФіліппов Ю. Ю\nДитина\nГорбатюк А. В\nОщадбанк України\n251925\nОщадбанк України\n24803\n203045\n124238\n8084\n69156\n335491\n203045\n537699\n730\n2015\nОщадбанк України\n251925\nОщадбанк України\n24803\n1/2 частина\n34.5\nб.192/кв.29\n44.5\nб.20/кв.98\n73.4\n800\n1/2 частина\n34.5\nГорбатюк В. В\nПодружжя\nФіліппов Ю. Ю\nДитина\nГорбатюк А. В\nДитина\nЛеонідівна\nКрапівницька\nсуддя вінницького окружного адміністративного суду\nВінницька область\nАдміністративний місцевий суд\nКрапівницька Наталя Леонідівна\nКрапівницька Наталя Леонідівна\nНаталя Леонідівна Крапівницька\nНаталя Крапівницька\nКрапівницька Наталя Леонідівна\nНаталя\n124238\n203045\n335491\n730\n537699\n203045\n69156\n8084","general":{"inn":"","addresses":[{"place_city_type_hidden":false,"place_city_type":"","place_city_hidden":true,"place_hidden":true,"place_district":"","place_district_hidden":false,"place":"","place_address":"","place_address_hidden":true,"place_city":""}],"last_name":"Крапівницька","full_name":"Крапівницька Наталя Леонідівна","family":[{"inn":"","family_name":"Горбатюк В. В","name_unclear":false,"inn_hidden":true,"name_hidden":true,"relations":"Подружжя"},{"inn":"","family_name":"Філіппов Ю. Ю","relations_other":"","name_unclear":false,"inn_hidden":false,"relations":"Дитина"},{"inn":"","family_name":"Горбатюк А. В","relations_other":"","name_unclear":false,"inn_hidden":true,"name_hidden":false,"relations":"Дитина"}],"patronymic":"Леонідівна","inn_hidden":true,"name":"Наталя","post":{"office":"Адміністративний місцевий суд","region":"Вінницька область","post_unclear":false,"post":"суддя вінницького окружного адміністративного суду"},"family_raw":"","full_name_suggest":{"input":["Крапівницька Наталя Леонідівна","Наталя Леонідівна Крапівницька","Наталя Крапівницька"],"output":"Крапівницька Наталя Леонідівна"}},"liabilities":{"54":{"sum_comment_unclear":false,"sum_comment":"","sum":"","sum_foreign_comment":"","sum_foreign":"","sum_comment_hidden":false},"55":{"sum_comment":"","sum_foreign_comment":"","sum_foreign":"","sum":""},"56":{"sum_comment":"","sum_foreign_comment":"","sum_foreign":"","sum":""},"57":{"sum_comment":"","sum_foreign_comment":"","sum_foreign":"","sum":"","sum_comment_hidden":false},"58":{"sum_comment":"","sum_foreign_comment":"","sum_foreign":"","sum":"","sum_comment_hidden":false},"59":{"sum_comment":"","sum":"","sum_foreign_comment":"","sum_foreign":"","sum_unclear":false,"sum_comment_hidden":false},"60":{"sum_comment":"","sum_foreign_comment":"","sum_foreign":"","sum":"","sum_comment_hidden":false},"61":{"sum_comment":"","sum_foreign_comment":"","sum_foreign":"","sum":""},"62":{"sum_comment":"","sum_foreign_comment":"","sum_foreign":"","sum":""},"63":{"sum_comment":"Ощадбанк України","sum_foreign_comment":"","sum_foreign":"","sum":"251925","sum_comment_hidden":false},"64":{"sum_comment":"Ощадбанк України","sum_foreign_comment":"","sum_foreign":"","sum":"24803","sum_comment_hidden":false}},"intro":{"declaration_year":"2015"}}