{"income":{"5":{"value":"306746","family_comment":"","value_unclear":false,"family_hidden":false,"family_unclear":false,"family":"","comment":""},"6":{"value":"277707","value_unclear":true,"family_hidden":false,"family_comment":"","family":"","comment":""},"7":{"source_name_unclear":false,"value":"","family_hidden":false,"family_comment":"","source_name":"","family":"","comment":"","source_name_hidden":false},"8":{"family_comment":"","value":"","family":"","comment":""},"9":{"family_comment":"","family_unclear":false,"value":"","family":"","comment":""},"10":{"family_comment":"","value":"","family":"","comment":""},"11":{"family_comment":"","value":"","comment_unclear":false,"family":"","comment":""},"12":{"family_comment":"","value":"","family":"","comment":""},"13":{"family_comment":"","value":"","family":"","comment":""},"14":{"family_comment":"","value":"","family":"","comment":""},"15":{"family_comment":"","value":"","family":"","comment":""},"16":{"family_comment":"","value":"","family":"","comment":""},"17":{"family_comment":"","value":"","family":"","comment":"","family_comment_unclear":false},"18":{"family_comment":"","value":"","family":"","comment":""},"19":{"family_comment":"","value":"","comment_unclear":false,"family":"","comment":""},"20":{"value":"29039","family_comment":"","comment_unclear":false,"comment_hidden":false,"family_unclear":false,"family":"","comment":"пенсія по інвалідності"}},"vehicle":{"35":[{"brand_info":"2.0 л у користуванні","sum_rent_comment":"","year":"2012","brand_info_hidden":false,"year_unclear":false,"sum_rent":"","sum":"","brand":"Volkswagen Tiguan","sum_comment":"","sum_comment_unclear":false,"sum_unclear":false,"brand_unclear":false}]},"id":"vulyk_8_150","banks":{"45":[{"sum_foreign_comment":"","sum_units":"UAH","sum_comment":"","sum_foreign_unclear":false,"sum_foreign_units":"UAH","sum_hidden":false,"sum_comment_hidden":false,"sum_unclear":false,"sum":"","sum_foreign":""},{"sum_foreign_comment":"","sum_units":"","sum_comment":"","sum_hidden":false,"sum_foreign_units":"","sum":"","sum_unclear":false,"sum_foreign":""},{"sum_foreign_comment":"","sum_units":"","sum_comment":"","sum_foreign_units":"","sum":"","sum_unclear":false,"sum_foreign":""},{"sum_foreign_comment":"","sum_units":"","sum_comment":"","sum_foreign_units":"","sum":"","sum_foreign":""}],"46":[{"sum_foreign_comment":"","sum_units":"UAH","sum_comment":"","sum_foreign_comment_hidden":false,"sum_hidden":false,"sum_foreign_units":"UAH","sum_foreign_hidden":false,"sum_comment_hidden":false,"sum_unclear":false,"sum":"","sum_foreign":""}],"47":[{"sum_foreign_comment":"","sum_units":"UAH","sum_comment":"","sum_foreign_units":"UAH","sum_comment_hidden":false,"sum":"","sum_foreign":""}],"48":[{"sum_foreign_comment":"","sum_units":"UAH","sum_comment":"","sum_foreign_units":"UAH","sum":"","sum_foreign":""}],"49":[{"sum_foreign_comment":"","sum_units":"UAH","sum_comment":"","sum_foreign_units":"UAH","sum":"","sum_foreign":""}],"50":[{"sum_foreign_comment":"","sum_units":"UAH","sum_comment":"","sum_foreign_units":"UAH","sum":"","sum_foreign":""}],"51":[{"sum_foreign_comment":"","sum_units":"UAH","sum_comment":"","sum_comment_unclear":false,"sum_hidden":false,"sum_foreign_units":"UAH","sum_comment_hidden":false,"sum_unclear":false,"sum":"","sum_foreign":""},{"sum_foreign_comment":"","sum_units":"","sum_comment":"","sum_hidden":false,"sum_foreign_units":"","sum":"","sum_foreign":""}],"52":[{"sum_foreign_comment":"","sum_units":"UAH","sum_comment":"","sum_comment_unclear":false,"sum_hidden":false,"sum_foreign_units":"UAH","sum_comment_hidden":false,"sum_unclear":false,"sum":"","sum_foreign":""}],"53":[{"sum_foreign_comment":"","sum_units":"UAH","sum_comment":"","sum_foreign_units":"UAH","sum_comment_hidden":false,"sum":"","sum_foreign":""}]},"declaration":{"additional_info_text":"","notfull_lostpages":"","date":"2015-03-25T00:00:00","notfull":"","additional_info":"","url":"http://static.declarations.com.ua/declarations/chosen_ones/batch_16/ostapchuk_dmytro_oleksiiovych.pdf"},"liabilities":{"54":{"sum_foreign_comment":"","sum_foreign_hidden":false,"sum_comment":"","sum_hidden":false,"sum_comment_hidden":false,"sum":"","sum_foreign":""},"55":{"sum_foreign_comment":"","sum":"","sum_comment":"","sum_foreign":""},"56":{"sum_foreign_comment":"","sum":"","sum_comment":"","sum_unclear":false,"sum_foreign":""},"57":{"sum_foreign_comment":"","sum_comment_hidden":false,"sum":"","sum_comment":"","sum_foreign":""},"58":{"sum_foreign_comment":"","sum":"","sum_comment":"","sum_foreign":""},"59":{"sum_foreign_comment":"","sum":"","sum_comment":"","sum_comment_unclear":false,"sum_foreign":""},"60":{"sum_foreign_comment":"","sum_foreign_hidden":false,"sum_comment":"","sum_hidden":false,"sum_comment_hidden":false,"sum":"","sum_foreign":""},"61":{"sum_foreign_comment":"","sum":"","sum_comment":"","sum_foreign":""},"62":{"sum_foreign_comment":"","sum":"","sum_comment":"","sum_foreign":""},"63":{"sum_foreign_comment":"","sum":"","sum_comment":"","sum_foreign":""},"64":{"sum_foreign_comment":"","sum":"","sum_comment":"","sum_foreign":""}},"ft_src":"суддя вищого спеціалізованого суду україни з розгляду цивільних і кримінальних справ\nЗагальнодержавний регіон\nВищий спецiалiзований суд України з розгляду цивiльних i кримiнальних справ\nДмитро\nОлексійович\nОстапчук Дмитро Олексійович\nДмитро Олексійович Остапчук\nДмитро Остапчук\nОстапчук Дмитро Олексійович\nОстапчук Дмитро Олексійович\nОстапчук\n2.0 л у користуванні\nVolkswagen Tiguan\n2012\n2014\n2.0 л у користуванні\nVolkswagen Tiguan\n2012\n1500\n1200\nотримано безоплатно\n57.7\nу користуванні\nОстапчук Дмитро Олексійович\nДмитро Олексійович Остапчук\nДмитро Остапчук\nОстапчук Дмитро Олексійович\nДмитро\nОстапчук Дмитро Олексійович\nОстапчук\nВищий спецiалiзований суд України з розгляду цивiльних i кримiнальних справ\nсуддя вищого спеціалізованого суду україни з розгляду цивільних і кримінальних справ\nЗагальнодержавний регіон\nОлексійович\n277707\nпенсія по інвалідності\n29039\n306746\n2014\n1500\nотримано безоплатно\n1200\nу користуванні\n57.7\nОстапчук Дмитро Олексійович\nДмитро Олексійович Остапчук\nДмитро Остапчук\nОстапчук Дмитро Олексійович\nОлексійович\nОстапчук\nДмитро\nЗагальнодержавний регіон\nсуддя вищого спеціалізованого суду україни з розгляду цивільних і кримінальних справ\nВищий спецiалiзований суд України з розгляду цивiльних i кримiнальних справ\nОстапчук Дмитро Олексійович\n277707\n306746\nпенсія по інвалідності\n29039\n2012\nVolkswagen Tiguan\n2.0 л у користуванні\nпенсія по інвалідності\n29039\n306746\n277707\nу користуванні\n57.7\n1500\nотримано безоплатно\n1200\n2014","general":{"inn":"","name":"Дмитро","patronymic_unclear":false,"last_name_hidden":false,"last_name":"Остапчук","patronymic":"Олексійович","inn_hidden":true,"family_raw":"","inn_unclear":false,"post":{"post_unclear":false,"post":"суддя вищого спеціалізованого суду україни з розгляду цивільних і кримінальних справ","post_hidden":false,"region":"Загальнодержавний регіон","region_hidden":false,"office":"Вищий спецiалiзований суд України з розгляду цивiльних i кримiнальних справ","office_hidden":false,"office_unclear":false},"full_name":"Остапчук Дмитро Олексійович","addresses":[{"place_district":"","place_city_hidden":true,"place_city":"","place_city_type_hidden":true,"place_district_hidden":true,"place_city_type":"","place_address_hidden":true,"place_address":"","place_hidden":true,"place":""}],"full_name_suggest":{"output":"Остапчук Дмитро Олексійович","input":["Остапчук Дмитро Олексійович","Дмитро Олексійович Остапчук","Дмитро Остапчук"]}},"source":"VULYK","estate":{"23":[{"space_unclear":false,"costs":"","costs_comment":"","address_hidden":true,"region_hidden":true,"space_comment":"","space":"1500","address":"","costs_comment_unclear":false,"region":"","address_unclear":false,"costs_rent_comment":"","space_comment_unclear":true,"space_comment_hidden":false,"space_units":"м²","space_units_hidden":false,"costs_rent":""},{"space_unclear":false,"costs":"","costs_comment":"","address_hidden":true,"region_hidden":false,"space_comment":"отримано безоплатно","space":"1200","address":"","region":"","costs_rent_comment":"","space_comment_unclear":false,"space_units":"м²","costs_rent":""},{"space":"","region":"","costs":"","costs_rent_comment":"","costs_comment":"","space_comment":"","space_units_unclear":false,"space_units":"","costs_rent":"","address":""},{"costs_rent":"","region":"","costs":"","costs_rent_comment":"","costs_comment":"","address_hidden":false,"space_comment":"","space_units":"","space":"","address":""}],"25":[{"region_unclear":false,"space_unclear":false,"costs":"","costs_comment":"","address_hidden":false,"region_hidden":true,"space_comment":"у користуванні","space":"57.7","address":"","costs_comment_unclear":false,"region":"","costs_rent_comment":"","space_comment_unclear":false,"space_units":"м²","costs_rent":""}]},"intro":{"declaration_year":"2014","isnotdeclaration":""}}