{"income":{"5":{"family_comment":"","value":"210309","family":"8280","comment":""},"6":{"value":"210309","family_comment":"","value_unclear":false,"comment_hidden":false,"family_unclear":false,"family":"8280","comment":""},"7":{"family_comment":"","value":"","source_name":"","family":"","comment":""},"8":{"family_comment":"","value":"","family":"","comment":""},"9":{"family_comment":"","family_unclear":false,"value":"","family":"","comment":""},"10":{"family_comment":"","value":"","value_unclear":false,"family":"","comment":""},"11":{"family_comment":"","value":"","family":"","comment":""},"12":{"family_comment":"","value":"","family":"","comment":""},"13":{"family_comment":"","value":"","family":"","comment":""},"14":{"family_comment":"","value":"","family":"","comment":""},"15":{"family_comment":"","value":"","family":"","comment":""},"16":{"family_comment":"","value":"","family":"","comment":""},"17":{"family_comment":"","value":"","family":"","comment":""},"18":{"family_comment":"","value":"","family":"","comment":""},"19":{"family_comment":"","value":"","family":"","comment":""},"20":{"value":"","comment_unclear":false,"family_hidden":false,"family_comment":"","value_unclear":false,"family":"","comment":"","family_comment_unclear":false}},"vehicle":{"40":[{"brand_info":"V 5461","sum_rent_comment":"","brand":"Mercedes-Benz GL 500","sum_comment":"","brand_unclear":false,"year":"2008","brand_info_unclear":false,"year_unclear":false,"sum":"","sum_rent":""},{"brand_info":"V 3498","sum":"","brand":"Mercedes-Benz E 300","sum_comment":"","year":"2008","sum_rent_comment":"","sum_rent":""}]},"id":"vulyk_97_77","declaration":{"additional_info_text":"","notfull_lostpages":"","date":"2015-03-31T00:00:00","notfull":"","additional_info":"","url":"http://static.declarations.com.ua/declarations/chosen_ones/judges_batch/3978_arkhipova_svitlana_viktorivna.pdf"},"liabilities":{"54":{"sum_foreign_comment":"","sum":"","sum_comment":"","sum_comment_unclear":false,"sum_hidden":false,"sum_comment_hidden":false,"sum_unclear":false,"sum_foreign":""},"55":{"sum_foreign_comment":"","sum":"","sum_comment":"","sum_foreign":""},"56":{"sum_foreign_comment":"","sum":"","sum_comment":"","sum_foreign":""},"57":{"sum_foreign_comment":"","sum":"116","sum_comment":"","sum_comment_unclear":false,"sum_hidden":false,"sum_comment_hidden":false,"sum_unclear":false,"sum_foreign":""},"58":{"sum_foreign_comment":"","sum":"34","sum_comment":"","sum_comment_unclear":false,"sum_hidden":false,"sum_comment_hidden":false,"sum_unclear":false,"sum_foreign":""},"59":{"sum_foreign_comment":"","sum":"","sum_comment":"","sum_foreign":""},"60":{"sum_foreign_comment":"","sum":"","sum_comment":"","sum_comment_unclear":false,"sum_hidden":false,"sum_comment_hidden":false,"sum_foreign":""},"61":{"sum_foreign_comment":"","sum":"","sum_comment":"","sum_foreign":""},"62":{"sum_foreign_comment":"","sum":"40303","sum_comment":"","sum_unclear":true,"sum_foreign":""},"63":{"sum_foreign_comment":"","sum":"","sum_foreign":"","sum_comment":"","sum_hidden":false},"64":{"sum_foreign_comment":"","sum":"","sum_comment":"","sum_foreign":""}},"ft_src":"Mercedes-Benz GL 500\nV 5461\n2008\nV 3498\n2008\nMercedes-Benz E 300\n188.6\nХарківська область\nм. Харків\n2014\n8280\n210309\n8280\n210309\nV 5461\nMercedes-Benz GL 500\n2008\nV 3498\n2008\nMercedes-Benz E 300\n2014\nАрхіпова Світлана Вікторівна\nСвітлана Вікторівна Архіпова\nСвітлана Архіпова\nАрхіпова Світлана Вікторівна\nСвітлана\nПодружжя\nГаєвий Г. І\nДитина\nГаєва О. Г\nАрхіпова Світлана Вікторівна\nАрхіпова\nАдміністративний місцевий суд\nХарківська область\nсуддя харківського окружного адміністративного суду\nВікторівна\nХарківська область\n61166\nХарків\n34\n116\n40303\n210309\n8280\n210309\n8280\n188.6\nХарківська область\nм. Харків\n34\n116\n40303\nПодружжя\nГаєвий Г. І\nГаєва О. Г\nДитина\nВікторівна\nАрхіпова\nСвітлана\nАрхіпова Світлана Вікторівна\nСвітлана Вікторівна Архіпова\nСвітлана Архіпова\nАрхіпова Світлана Вікторівна\n61166\nХарків\nХарківська область\nХарківська область\nАдміністративний місцевий суд\nсуддя харківського окружного адміністративного суду\nАрхіпова Світлана Вікторівна","general":{"name_hidden":false,"name":"Світлана","last_name_hidden":false,"inn":"","last_name":"Архіпова","family":[{"inn":"","relations":"Подружжя","relations_other":"","inn_hidden":true,"family_name":"Гаєвий Г. І","name_hidden":false,"name_unclear":false},{"inn":"","relations":"Дитина","name_hidden":false,"inn_hidden":false,"family_name":"Гаєва О. Г","name_unclear":false}],"inn_hidden":true,"family_raw":"","inn_unclear":false,"post":{"region_unclear":false,"post":"суддя харківського окружного адміністративного суду","post_hidden":false,"region":"Харківська область","office":"Адміністративний місцевий суд","office_unclear":false},"full_name":"Архіпова Світлана Вікторівна","addresses":[{"place_district":"","place_address_hidden":true,"place_city":"Харків","place_city_unclear":false,"place_district_hidden":false,"place_city_type":"Місто","place_city_hidden":false,"place_city_type_hidden":false,"place_address":"61166","place_hidden":false,"place":"Харківська область"}],"patronymic":"Вікторівна","patronymic_hidden":false,"full_name_suggest":{"output":"Архіпова Світлана Вікторівна","input":["Архіпова Світлана Вікторівна","Світлана Вікторівна Архіпова","Світлана Архіпова"]}},"source":"VULYK","estate":{"31":[{"space_unclear":false,"address_hidden":true,"region_hidden":false,"space_comment":"","space_hidden":false,"space":"188.6","address":"м. Харків","region":"Харківська область","costs_property":"","costs_rent_comment":"","space_comment_hidden":false,"space_units":"м²","costs_property_comment":"","costs_rent":""}]},"intro":{"declaration_year":"2014","isnotdeclaration":""}}