{"id":"vulyk_109_98","ft_src":"2014\nGeon Dakar\nмотоцикл, 249 куб. см., 28 кВт\n1500 куб. см., 75.8 кВт\n2008\nMazda 2\n2261 куб. см., 182 кВт\nMazda CX-7\n2008\n1998 куб. см., 96.4 кВт\n2005\nChevrolet Evanda\nмотоцикл, 1304 куб. см., 73.5 кВт\n2008\nYamaha XVS\n2/3 квартири\n61.98\n61.9\n229.6\n345\n26\n1/3 квартири\n61.98\n1\nПримітка: відомості про отримані доходи дружини відсутні, оскільки вона проживає окремо в м. Одесі та відмовилась їх надати\n2015\nне відомо\n254700.64\nХерсонський Державний університет\n1262.56\nне відомо\n255963.2\n2261 куб. см., 182 кВт\nMazda CX-7\n2008\n1998 куб. см., 96.4 кВт\nChevrolet Evanda\n2005\n1500 куб. см., 75.8 кВт\n2008\nMazda 2\nмотоцикл, 249 куб. см., 28 кВт\n2014\nGeon Dakar\nмотоцикл, 1304 куб. см., 73.5 кВт\n2008\nYamaha XVS\nПримітка: відомості про отримані доходи дружини відсутні, оскільки вона проживає окремо в м. Одесі та відмовилась їх надати\n1\n2015\nПодружжя\nЗакуріна О. Ю. 06. 09. 1973\nДитина\nЗакуріна А. М. 22. 03. 1995\nДитина\nЗакуріна К. М. 12. 06. 1999\nЗакурін Микола Костянтинович\nМикола Костянтинович Закурін\nМикола Закурін\nЗакурін Микола Костянтинович\nМикола\nЗакурін Микола Костянтинович\nЗакурін\nГосподарський місцевий суд\nХерсонська область\nголова господарського суду херсонської області\nКостянтинович\n1262.56\nХерсонський Державний університет\n254700.64\nне відомо\n255963.2\nне відомо\n345\n229.6\n2/3 квартири\n61.98\n61.9\n61.98\n1/3 квартири\n26\nПодружжя\nЗакуріна О. Ю. 06. 09. 1973\nДитина\nЗакуріна А. М. 22. 03. 1995\nДитина\nЗакуріна К. М. 12. 06. 1999\nМикола\nКостянтинович\nЗакурін\nЗакурін Микола Костянтинович\nМикола Костянтинович Закурін\nМикола Закурін\nЗакурін Микола Костянтинович\nХерсонська область\nГосподарський місцевий суд\nголова господарського суду херсонської області\nЗакурін Микола Костянтинович","estate":{"25":[{"address":"","space_units":"м²","space_hidden":false,"space_unclear":false,"region_hidden":false,"costs_comment":"","space_comment":"1/3 квартири","address_hidden":false,"space":"61.98","costs_rent_comment":"","costs":"","region":"","space_units_hidden":false,"costs_rent":""}],"29":[{"costs_property_comment":"","address":"","space_units":"м²","space_unclear":false,"region_hidden":false,"costs_property":"","space_comment":"","address_hidden":true,"costs_rent_comment":"","space":"345","region":"","costs_rent":""}],"30":[{"costs_property_comment":"","address":"","space_units":"м²","costs_rent_comment":"","space_hidden":false,"region_hidden":false,"costs_property":"","space_comment":"","space":"229.6","address_hidden":false,"costs_rent":""}],"31":[{"costs_property_comment":"","address":"","space_units":"м²","space_hidden":false,"space_comment":"2/3 квартири","region_hidden":false,"costs_property":"","region":"","address_hidden":true,"costs_rent_comment":"","space":"61.98","space_units_hidden":false,"costs_rent":""},{"costs_property_comment":"","address":"","space_units":"м²","costs_rent_comment":"","space":"61.9","region":"","costs_property":"","space_comment":"","costs_rent":""}],"32":[{"costs_property_comment":"","address":"","space_units":"м²","costs_rent_comment":"","space":"26","region":"","region_hidden":false,"costs_property":"","space_comment":"","address_hidden":true,"costs_rent":""}]},"vehicle":{"35":[{"sum_comment_unclear":false,"brand_info":"2261 куб. см., 182 кВт","sum_rent_comment":"","brand_unclear":false,"brand_hidden":false,"year":"2008","sum_comment":"","brand_info_hidden":false,"sum_rent":"","brand":"Mazda CX-7","year_unclear":false,"brand_info_unclear":false,"sum":""},{"sum_comment":"","brand_info":"1998 куб. см., 96.4 кВт","sum":"","sum_rent_comment":"","year":"2005","brand":"Chevrolet Evanda","sum_rent":""}],"39":[{"sum_comment":"","brand_info_hidden":false,"brand_info":"мотоцикл, 249 куб. см., 28 кВт","sum":"","sum_rent_comment":"","brand_hidden":false,"brand":"Geon Dakar","sum_rent":"","year":"2014"}],"40":[{"sum_comment":"","brand_info":"1500 куб. см., 75.8 кВт","sum":"","sum_rent_comment":"","year":"2008","brand":"Mazda 2","sum_rent":"","brand_info_unclear":false}],"44":[{"sum_comment":"","brand_info":"мотоцикл, 1304 куб. см., 73.5 кВт","sum":"","sum_rent_comment":"","year":"2008","brand":"Yamaha XVS","sum_rent":""}]},"source":"VULYK","income":{"5":{"family_comment":"не відомо","value":"255963.2","family":"","comment":""},"6":{"family_comment":"не відомо","value":"254700.64","family":"","comment":""},"7":{"source_name_hidden":false,"family_comment":"","comment":"","family":"","comment_hidden":false,"value":"1262.56","source_name":"Херсонський Державний університет"},"8":{"family_comment":"","family_hidden":false,"value":"","family":"","comment":""},"9":{"family_comment":"","family":"","comment":"","value_unclear":false,"family_unclear":false,"value":""},"10":{"family_comment":"","value":"","family":"","comment":""},"11":{"family_comment":"","value":"","family":"","comment":""},"12":{"family_comment":"","value":"","family":"","comment":""},"13":{"family_comment":"","value":"","family":"","comment":""},"14":{"family_comment":"","value":"","family":"","comment":""},"15":{"family_comment":"","value":"","family":"","comment":""},"16":{"family_comment":"","value":"","family":"","comment":""},"17":{"family_comment":"","value":"","family":"","comment":""},"18":{"family_comment":"","value":"","family":"","comment":""},"19":{"family_comment":"","value":"","family":"","comment":""},"20":{"family_comment":"","family":"","comment":"","value_unclear":false,"family_hidden":false,"value":""}},"general":{"family_raw":"","name":"Микола","full_name_suggest":{"input":["Закурін Микола Костянтинович","Микола Костянтинович Закурін","Микола Закурін"],"output":"Закурін Микола Костянтинович"},"patronymic":"Костянтинович","inn_hidden":true,"inn":"","inn_unclear":false,"last_name":"Закурін","full_name":"Закурін Микола Костянтинович","family":[{"inn":"","family_name":"Закуріна О. Ю. 06. 09. 1973","relations_hidden":false,"name_unclear":false,"relations":"Подружжя","inn_hidden":true,"name_hidden":false,"relations_other":""},{"inn":"","family_name":"Закуріна А. М. 22. 03. 1995","relations_other":"","name_unclear":false,"inn_hidden":false,"name_hidden":false,"relations":"Дитина"},{"inn":"","family_name":"Закуріна К. М. 12. 06. 1999","relations_other":"","name_unclear":false,"inn_hidden":false,"name_hidden":false,"relations":"Дитина"}],"post":{"office":"Господарський місцевий суд","post":"голова господарського суду херсонської області","office_unclear":false,"region_hidden":false,"region":"Херсонська область","office_hidden":false,"region_unclear":false},"name_hidden":false},"liabilities":{"54":{"sum_comment":"","sum_hidden":false,"sum":"","sum_foreign_comment":"","sum_foreign":"","sum_unclear":false,"sum_comment_hidden":false},"55":{"sum_comment":"","sum_comment_unclear":false,"sum_foreign_comment":"","sum":"","sum_foreign":""},"56":{"sum_comment":"","sum_foreign_comment":"","sum_foreign":"","sum":""},"57":{"sum_comment":"","sum_foreign_comment":"","sum_foreign":"","sum":"","sum_comment_hidden":false},"58":{"sum_comment":"","sum_foreign_comment":"","sum_foreign":"","sum":"","sum_comment_hidden":false},"59":{"sum_comment":"","sum_foreign_comment":"","sum_foreign":"","sum":""},"60":{"sum_comment":"","sum_foreign_comment":"","sum_foreign":"","sum":""},"61":{"sum_comment":"","sum_foreign_comment":"","sum_foreign":"","sum":""},"62":{"sum_comment":"","sum_foreign_comment":"","sum_foreign":"","sum":""},"63":{"sum_comment":"","sum_foreign_comment":"","sum_foreign":"","sum":""},"64":{"sum_comment":"","sum_foreign_comment":"","sum_foreign":"","sum":""}},"declaration":{"notfull_lostpages":"","additional_info_text":"Примітка: відомості про отримані доходи дружини відсутні, оскільки вона проживає окремо в м. Одесі та відмовилась їх надати","additional_info":"1","date":"2016-03-29T00:00:00","notfull":"","url":"http://static.declarations.com.ua/declarations/chosen_ones/judges_batch/2555_zakurin_mykola_kostiantynovych_2015.pdf"},"intro":{"isnotdeclaration":"","declaration_year":"2015"}}