{"income":{"5":{"value":"262499","family_comment":"","value_unclear":false,"family_hidden":false,"value_hidden":false,"family_unclear":false,"family":"233641","comment":""},"6":{"value":"228353","family_comment":"","value_unclear":false,"family_hidden":false,"value_hidden":false,"family_unclear":false,"family":"18959","comment":""},"7":{"source_name_unclear":false,"value":"8836","comment_hidden":false,"family_hidden":false,"value_hidden":false,"family_comment":"","source_name":"Чернівецький національний університет імені Юрія Федьковича","family":"","comment":"","source_name_hidden":false},"8":{"value":"","family_hidden":false,"value_hidden":false,"family_comment":"","family":"","comment":""},"9":{"value":"310","family_hidden":false,"value_hidden":false,"family_comment":"","family":"14682","comment":""},"10":{"family_comment":"","value":"","family_hidden":false,"comment":"","family":""},"11":{"value":"","comment_hidden":false,"family_hidden":false,"family_comment":"","family":"","comment":""},"12":{"value":"","family_hidden":false,"value_hidden":false,"family_comment":"","family":"","comment":""},"13":{"value":"","family_hidden":false,"value_hidden":false,"family_comment":"","family":"","comment":""},"14":{"value":"","family_hidden":false,"value_hidden":false,"family_comment":"","family":"","comment":""},"15":{"family_comment":"","value":"","family_hidden":false,"comment":"","family":""},"16":{"value":"","family_hidden":false,"value_hidden":false,"family_comment":"","family":"","comment":""},"17":{"family_comment":"","value":"","family":"","comment":"","value_hidden":false},"18":{"value":"","family_hidden":false,"value_hidden":false,"family_comment":"","family":"","comment":""},"19":{"value":"","family_hidden":false,"value_hidden":false,"family_comment":"","family":"","comment":""},"20":{"value":"25000","comment_unclear":false,"family_hidden":false,"value_hidden":false,"family_comment":"кредитна карта, знятий депозит ПАТ КБ 'Приватбанк', ПАТ КБ 'Хрещатик'","family":"200000","comment":"кредитна картка Приватбанка","family_comment_unclear":true}},"vehicle":{"35":[{"year_hidden":true,"brand_info":"JTNBE40 K103049012. 2362 куб. см. об'єм двигуна","sum_rent_comment":"","sum_rent_hidden":true,"year":"","sum_hidden":true,"brand_info_hidden":true,"brand_info_unclear":false,"year_unclear":false,"sum_rent":"","sum_rent_unclear":true,"sum":"","brand":"Toyota Camry","sum_comment":"","brand_unclear":false,"brand_hidden":false,"sum_unclear":true}],"40":[{"year_hidden":false,"brand_info":"1997 куб. см.","sum_rent_comment":"","sum_rent_hidden":false,"year":"","sum_hidden":false,"brand_info_hidden":false,"brand_info_unclear":false,"year_unclear":false,"sum_rent":"","sum":"","brand":"Honda CR-V","sum_comment":"","brand_unclear":false,"brand_hidden":false}]},"id":"vulyk_34_10","banks":{"45":[{"sum_foreign_comment":"","sum_units":"UAH","sum_comment":"","sum_foreign_units":"UAH","sum_comment_hidden":false,"sum_unclear":false,"sum":"","sum_foreign":""},{"sum_foreign_comment":"","sum_units":"","sum_comment":"","sum_foreign_units":"","sum_comment_hidden":false,"sum":"","sum_foreign":""}],"46":[{"sum_foreign_comment":"","sum_units":"UAH","sum_comment":"","sum_foreign_units":"UAH","sum_comment_hidden":false,"sum_unclear":false,"sum":"","sum_foreign":""},{"sum_foreign_comment":"","sum_units":"","sum_comment":"","sum_foreign_units":"","sum_comment_hidden":false,"sum":"","sum_foreign":""}],"47":[{"sum_foreign_comment":"","sum_units":"UAH","sum_comment":"","sum_foreign_units":"UAH","sum":"","sum_foreign":""}],"48":[{"sum_foreign_comment":"","sum_units":"UAH","sum_comment":"","sum_foreign_units":"UAH","sum":"","sum_foreign":""}],"49":[{"sum_foreign_comment":"","sum_units":"UAH","sum_comment":"","sum_hidden":false,"sum_foreign_units":"UAH","sum":"","sum_foreign":""}],"50":[{"sum_foreign_comment":"","sum_units":"UAH","sum_comment":"","sum_hidden":false,"sum_foreign_units":"UAH","sum":"","sum_foreign":""}],"51":[{"sum_foreign_comment":"","sum_units":"UAH","sum_comment":"","sum_hidden":false,"sum_foreign_units":"UAH","sum_comment_hidden":false,"sum_unclear":false,"sum":"53988","sum_foreign":""},{"sum_foreign_comment":"","sum_units":"","sum_comment":"","sum_foreign_units":"","sum_comment_hidden":false,"sum":"","sum_foreign":""}],"52":[{"sum_foreign_comment":"","sum_units":"UAH","sum_comment":"","sum_foreign_units":"UAH","sum":"","sum_foreign":""}],"53":[{"sum_foreign_comment":"","sum_units":"UAH","sum_comment":"","sum_foreign_units":"UAH","sum":"","sum_foreign":""}]},"declaration":{"additional_info_text":"","notfull_lostpages":"","date":"2015-03-27T00:00:00","notfull":"","additional_info":"","url":"http://static.declarations.com.ua/declarations/chosen_ones/mega_batch/skuliak_ihor_anatoliiovych.pdf"},"liabilities":{"54":{"sum_foreign_comment":"","sum_foreign_hidden":false,"sum_comment":"","sum_hidden":false,"sum_comment_hidden":false,"sum":"","sum_foreign":""},"55":{"sum_foreign_comment":"","sum_foreign_hidden":false,"sum_comment":"","sum_hidden":false,"sum":"","sum_foreign":""},"56":{"sum_foreign_comment":"","sum_foreign_hidden":false,"sum_comment":"","sum":"","sum_unclear":false,"sum_foreign":""},"57":{"sum_foreign_comment":"","sum_foreign_hidden":false,"sum_comment":"","sum_hidden":false,"sum_comment_hidden":false,"sum_unclear":false,"sum":"30339","sum_foreign":""},"58":{"sum_foreign_comment":"","sum_foreign_hidden":false,"sum_comment":"","sum_hidden":false,"sum_comment_hidden":false,"sum_unclear":false,"sum":"","sum_foreign":""},"59":{"sum_foreign_comment":"","sum_foreign_hidden":false,"sum_comment":"","sum_hidden":false,"sum":"","sum_foreign":""},"60":{"sum_foreign_comment":"","sum_foreign_hidden":false,"sum_comment":"","sum_hidden":false,"sum":"","sum_foreign":""},"61":{"sum_foreign_comment":"","sum_foreign_hidden":false,"sum_comment":"","sum_hidden":false,"sum":"","sum_foreign":""},"62":{"sum_foreign_comment":"","sum_foreign_hidden":false,"sum_comment":"","sum":"377","sum_unclear":false,"sum_foreign":""},"63":{"sum_foreign_comment":"","sum_foreign_hidden":false,"sum_comment":"","sum_hidden":false,"sum":"","sum_unclear":false,"sum_foreign":""},"64":{"sum_foreign_comment":"","sum_foreign_hidden":false,"sum_comment":"","sum_comment_unclear":false,"sum_hidden":false,"sum_comment_hidden":false,"sum_unclear":false,"sum":"","sum_foreign":""}},"ft_src":"30339\n377\nЧернівці\nЧернівецька область\nзаступник голови першотравневого районного суду м. чернівців, суддя\nЧернівецька область\nЗагальний місцевий суд\nІгор\nСкуляк В. М., 22. 07. 1987\nПодружжя\nСкуляк В. І., 22. 09. 2007\nДитина\nАнатолійович\nСкуляк\nСкуляк Ігор Анатолійович\nСкуляк Ігор Анатолійович\nІгор Анатолійович Скуляк\nІгор Скуляк\nСкуляк Ігор Анатолійович\nJTNBE40 K103049012. 2362 куб. см. об'єм двигуна\nToyota Camry\n1997 куб. см.\nHonda CR-V\n53988\n2014\nJTNBE40 K103049012. 2362 куб. см. об'єм двигуна\nToyota Camry\n1997 куб. см.\nHonda CR-V\n53988\n.1\nЧернівецька область\nм. Чернівці\nЧернівецька область\n78.1\nм. Чернівці\nкористування\n103.5\nЧернівецька область\nм. Чернівці\nПодружжя\nСкуляк В. М., 22. 07. 1987\nДитина\nСкуляк В. І., 22. 09. 2007\nСкуляк Ігор Анатолійович\nІгор Анатолійович Скуляк\nІгор Скуляк\nСкуляк Ігор Анатолійович\nІгор\nСкуляк Ігор Анатолійович\nСкуляк\nЗагальний місцевий суд\nЧернівецька область\nзаступник голови першотравневого районного суду м. чернівців, суддя\nАнатолійович\nЧернівецька область\nЧернівці\n30339\n377\n8836\nЧернівецький національний університет імені Юрія Федьковича\n228353\n18959\nкредитна картка Приватбанка\nкредитна карта, знятий депозит ПАТ КБ 'Приватбанк', ПАТ КБ 'Хрещатик'\n25000\n200000\n233641\n262499\n310\n14682\n2014\n30339\n377\nм. Чернівці\n.1\nЧернівецька область\nЧернівецька область\nм. Чернівці\n78.1\nкористування\n103.5\nм. Чернівці\nЧернівецька область\nСкуляк В. М., 22. 07. 1987\nПодружжя\nСкуляк В. І., 22. 09. 2007\nДитина\nАнатолійович\nСкуляк\nСкуляк Ігор Анатолійович\nІгор Анатолійович Скуляк\nІгор Скуляк\nСкуляк Ігор Анатолійович\nЧернівці\nЧернівецька область\nЧернівецька область\nЗагальний місцевий суд\nзаступник голови першотравневого районного суду м. чернівців, суддя\nСкуляк Ігор Анатолійович\nІгор\n18959\n228353\nЧернівецький національний університет імені Юрія Федьковича\n8836\n233641\n262499\n14682\n310\nкредитна карта, знятий депозит ПАТ КБ 'Приватбанк', ПАТ КБ 'Хрещатик'\nкредитна картка Приватбанка\n200000\n25000\nToyota Camry\nJTNBE40 K103049012. 2362 куб. см. об'єм двигуна\nHonda CR-V\n1997 куб. см.\nкредитна карта, знятий депозит ПАТ КБ 'Приватбанк', ПАТ КБ 'Хрещатик'\n25000\n200000\nкредитна картка Приватбанка\n262499\n233641\nЧернівецький національний університет імені Юрія Федьковича\n8836\n310\n14682\n228353\n18959\nЧернівецька область\nм. Чернівці\n78.1\nЧернівецька область\nм. Чернівці\n.1\nкористування\nм. Чернівці\nЧернівецька область\n103.5\n53988\n2014","general":{"inn":"","name":"Ігор","patronymic_unclear":false,"family":[{"inn":"","inn_hidden":true,"relations_unclear":false,"relations_hidden":false,"relations_other":"","relations":"Подружжя","name_hidden":false,"family_name":"Скуляк В. М., 22. 07. 1987","name_unclear":false},{"inn":"","inn_hidden":false,"relations_hidden":false,"family_name":"Скуляк В. І., 22. 09. 2007","relations_other":"","relations":"Дитина","name_hidden":false,"name_unclear":false}],"patronymic":"Анатолійович","inn_hidden":true,"family_raw":"","inn_unclear":false,"post":{"post_unclear":false,"region_unclear":false,"post":"заступник голови першотравневого районного суду м. чернівців, суддя","office":"Загальний місцевий суд","region":"Чернівецька область","post_hidden":false,"office_hidden":false,"office_unclear":false,"region_hidden":false},"last_name_unclear":false,"full_name":"Скуляк Ігор Анатолійович","addresses":[{"place_district":"","place_address_hidden":true,"place_city":"Чернівці","place_city_type_hidden":false,"place_district_hidden":false,"place_city_type":"Місто","place_city_hidden":false,"place_address_unclear":false,"place_address":"","place_hidden":false,"place":"Чернівецька область"}],"last_name":"Скуляк","patronymic_hidden":false,"full_name_suggest":{"output":"Скуляк Ігор Анатолійович","input":["Скуляк Ігор Анатолійович","Ігор Анатолійович Скуляк","Ігор Скуляк"]},"name_unclear":false},"source":"VULYK","estate":{"23":[{"space_unclear":false,"costs":"","costs_comment":"","costs_hidden":false,"address_hidden":true,"region_hidden":false,"space_comment":"","space_hidden":false,"space":".1","address":"м. Чернівці","region":"Чернівецька область","address_unclear":false,"space_units_unclear":false,"costs_rent_hidden":false,"costs_unclear":false,"space_units":"га","costs_rent":"","costs_rent_comment":""},{"costs_rent":"","region":"","costs":"","costs_rent_comment":"","costs_comment":"","address_hidden":false,"region_hidden":false,"space_comment":"","space_units":"","space":"","address":""},{"costs_rent":"","region":"","costs":"","costs_rent_comment":"","costs_comment":"","space_comment":"","space_units":"","space":"","address":""},{"costs_rent":"","region":"","costs":"","costs_rent_comment":"","costs_comment":"","space_comment":"","space_units":"","space":"","address":""}],"25":[{"region_unclear":false,"space_unclear":false,"costs":"","costs_comment":"","costs_hidden":false,"address_hidden":true,"region_hidden":false,"space_comment":"користування","space_hidden":false,"space":"103.5","address":"м. Чернівці","costs_rent_comment_unclear":false,"region":"Чернівецька область","address_unclear":false,"costs_rent_comment":"","costs_rent_hidden":false,"space_comment_unclear":false,"space_units":"м²","costs_rent":""}],"31":[{"region_unclear":false,"space_hidden":false,"costs_property_hidden":false,"address_hidden":true,"region_hidden":false,"space_comment":"","space_unclear":false,"space":"78.1","address":"м. Чернівці","region":"Чернівецька область","costs_property":"","costs_rent_comment":"","costs_rent_hidden":false,"space_comment_unclear":false,"space_units":"м²","costs_property_comment":"","costs_rent":""}]},"intro":{"declaration_year":"2014","isnotdeclaration":"","declaration_year_unclear":false}}