{"id":"vulyk_103_61","ft_src":"Audi Q5\n435800\n1984 куб. см.\n2010\n1200\n127.8\n2015\n262083.46\n33627.28\nНаціональна школа суддів України, Національна асоціація адвокатів України, ТОВ Науково-експертний інститут нотаріальної палати України, ДП Інформаційно-видавничий центр українського нотаріату\n540829.64\n244718\n400.9\n1984 куб. см.\n2010\n435800\nAudi Q5\n1200\n127.8\nЮровська Галина Валентинівна\nГалина Валентинівна Юровська\nГалина Юровська\nЮровська Галина Валентинівна\nЮровська Галина Валентинівна\nВалентинівна\nГалина\nЮровська\nВищий спеціалізований суд з розгляду цивільних і кримінальних справ\nсуддя вссу\nЗагальнодержавний регіон\nНаціональна школа суддів України, Національна асоціація адвокатів України, ТОВ Науково-експертний інститут нотаріальної палати України, ДП Інформаційно-видавничий центр українського нотаріату\n33627.28\n262083.46\n400.9\n540829.64\n244718\n2015\nЮровська\nВалентинівна\nсуддя вссу\nВищий спеціалізований суд з розгляду цивільних і кримінальних справ\nЗагальнодержавний регіон\nЮровська Галина Валентинівна\nЮровська Галина Валентинівна\nГалина Валентинівна Юровська\nГалина Юровська\nЮровська Галина Валентинівна\nГалина","estate":{"23":[{"costs":"","address":"","space_units":"м²","costs_rent_comment":"","space":"1200","space_comment":"","region_hidden":true,"costs_comment":"","region":"","address_hidden":false,"costs_rent":""}],"25":[{"address":"","space_units":"м²","costs_comment":"","region_hidden":true,"space_comment":"","address_hidden":false,"space_comment_hidden":false,"space":"127.8","space_comment_unclear":false,"costs_rent_comment":"","costs":"","region":"","costs_rent":""}]},"vehicle":{"35":[{"sum_comment":"","brand_info_hidden":false,"brand_info":"1984 куб. см.","sum":"435800","brand_unclear":false,"brand_hidden":false,"brand":"Audi Q5","sum_rent":"","brand_info_unclear":false,"sum_rent_comment":"","year":"2010"}]},"source":"VULYK","income":{"5":{"family_comment":"","family":"","comment":"","value_unclear":false,"family_hidden":false,"value":"540829.64"},"6":{"family_comment":"","value":"262083.46","family":"","comment":""},"7":{"family":"","family_comment":"","value":"33627.28","comment":"","source_name":"Національна школа суддів України, Національна асоціація адвокатів України, ТОВ Науково-експертний інститут нотаріальної палати України, ДП Інформаційно-видавничий центр українського нотаріату"},"8":{"family_comment":"","value":"","family":"","comment":""},"9":{"family_comment":"","value":"","family":"","comment":""},"10":{"family_comment":"","value":"","family":"","comment":""},"11":{"family_comment":"","family_hidden":false,"value":"","family":"","comment":""},"12":{"family_comment":"","value":"","family":"","comment":""},"13":{"family_comment":"","value":"","family":"","comment":""},"14":{"family_comment":"","value":"","family":"","comment":""},"15":{"family_comment":"","value":"","family":"","comment":""},"16":{"family_comment":"","value":"244718","family":"","comment":""},"17":{"family_comment":"","value":"","family":"","comment":"","family_comment_unclear":false},"18":{"family_comment":"","value":"","family":"","comment":""},"19":{"family_comment":"","value":"","family":"","comment":""},"20":{"family_comment":"","family":"","comment":"","family_unclear":false,"family_hidden":false,"value":"400.9"}},"general":{"inn":"","addresses":[{"place_city_type_hidden":false,"place_city_type":"","place_city_hidden":true,"place_hidden":true,"place_district":"","place_district_hidden":false,"place":"","place_city":"","place_address_hidden":true,"place_address":""}],"last_name":"Юровська","full_name_suggest":{"input":["Юровська Галина Валентинівна","Галина Валентинівна Юровська","Галина Юровська"],"output":"Юровська Галина Валентинівна"},"full_name":"Юровська Галина Валентинівна","patronymic":"Валентинівна","inn_hidden":true,"name":"Галина","post":{"office":"Вищий спеціалізований суд з розгляду цивільних і кримінальних справ","region_unclear":false,"post":"суддя вссу","region":"Загальнодержавний регіон","office_unclear":false},"family_raw":""},"liabilities":{"54":{"sum_foreign_comment_hidden":false,"sum_foreign_comment_unclear":false,"sum_hidden":false,"sum":"","sum_foreign_comment":"","sum_comment":"","sum_unclear":false,"sum_foreign":"","sum_comment_hidden":false,"sum_foreign_hidden":false},"55":{"sum_comment":"","sum_foreign_comment":"","sum_foreign":"","sum":""},"56":{"sum_comment":"","sum_foreign_comment":"","sum_foreign":"","sum":""},"57":{"sum_comment":"","sum_hidden":false,"sum":"","sum_foreign_comment":"","sum_foreign":"","sum_comment_hidden":false,"sum_foreign_hidden":false,"sum_foreign_comment_hidden":false},"58":{"sum_comment":"","sum_hidden":false,"sum":"","sum_foreign_comment":"","sum_foreign":"","sum_comment_hidden":false,"sum_foreign_hidden":false,"sum_foreign_comment_hidden":false},"59":{"sum_comment":"","sum_hidden":false,"sum":"","sum_foreign_comment":"","sum_foreign":"","sum_comment_hidden":false,"sum_foreign_hidden":false,"sum_foreign_comment_hidden":false},"60":{"sum_comment":"","sum_hidden":false,"sum":"","sum_foreign_comment":"","sum_foreign":"","sum_comment_hidden":false},"61":{"sum_comment":"","sum_foreign_comment":"","sum_foreign":"","sum":""},"62":{"sum_comment":"","sum_foreign_comment":"","sum_foreign":"","sum":"","sum_comment_hidden":false},"63":{"sum_comment":"","sum_foreign_comment":"","sum_foreign":"","sum":""},"64":{"sum_comment":"","sum_foreign_comment":"","sum_foreign":"","sum":""}},"declaration":{"additional_info_text":"","additional_info":"","date":"2016-03-25T00:00:00","url":"http://static.declarations.com.ua/declarations/chosen_ones/judges_batch/1285_iurovska_halyna_valentynivna.pdf"},"intro":{"declaration_year":"2015"}}