{"income":{"5":{"value":"290094","value_unclear":false,"family_hidden":false,"family_comment":"","family":"77761","comment":""},"6":{"family_comment":"","value":"290094","family":"77761","comment":""},"7":{"family_comment":"","value":"","source_name":"","family":"","comment":""},"8":{"family_comment":"","value":"","family":"","comment":""},"9":{"family_comment":"","value":"","family":"","comment":""},"10":{"family_comment":"","value":"","family":"","comment":""},"11":{"family_comment":"","value":"","family_hidden":false,"comment":"","family":""},"12":{"family_comment":"","value":"","family":"","comment":""},"13":{"family_comment":"","value":"","family":"","comment":""},"14":{"family_comment":"","value":"","family":"","comment":""},"15":{"family_comment":"","value":"","family":"","comment":""},"16":{"family_comment":"","value":"","family":"","comment":""},"17":{"family_comment":"","value":"","family":"","comment":"","family_comment_unclear":false},"18":{"family_comment":"","value":"","family":"","comment":""},"19":{"family_comment":"","value":"","family":"","comment":""},"20":{"value":"","family_unclear":false,"family_hidden":false,"family_comment":"","family":"","comment":""}},"vehicle":{"35":[{"brand_info":"4608","sum":"","brand":"Toyota Land Cruiser","sum_comment":"","brand_unclear":false,"year":"2013","brand_hidden":false,"brand_info_hidden":false,"brand_info_unclear":false,"sum_rent_comment":"","sum_rent":""}]},"id":"vulyk_103_58","declaration":{"date":"2016-03-30T00:00:00","additional_info_text":"","additional_info":"","url":"http://static.declarations.com.ua/declarations/chosen_ones/judges_batch/1282_khopta_serhii_fedorovych.pdf"},"liabilities":{"54":{"sum_foreign_comment":"","sum_foreign_hidden":false,"sum_comment":"","sum_foreign_comment_hidden":false,"sum_hidden":false,"sum_foreign_comment_unclear":false,"sum_comment_hidden":false,"sum_unclear":false,"sum":"","sum_foreign":""},"55":{"sum_foreign_comment":"","sum":"","sum_comment":"","sum_foreign":""},"56":{"sum_foreign_comment":"","sum":"","sum_comment":"","sum_foreign":""},"57":{"sum_foreign_comment":"","sum_foreign_hidden":false,"sum_comment":"","sum_foreign_comment_hidden":false,"sum_hidden":false,"sum_comment_hidden":false,"sum":"","sum_foreign":""},"58":{"sum_foreign_comment":"","sum_foreign_hidden":false,"sum_comment":"","sum_foreign_comment_hidden":false,"sum_hidden":false,"sum_comment_hidden":false,"sum":"","sum_foreign":""},"59":{"sum_foreign_comment":"","sum_foreign_hidden":false,"sum_comment":"","sum_foreign_comment_hidden":false,"sum_hidden":false,"sum_comment_hidden":false,"sum":"","sum_foreign":""},"60":{"sum_foreign_comment":"","sum":"","sum_comment":"","sum_hidden":false,"sum_comment_hidden":false,"sum_foreign":""},"61":{"sum_foreign_comment":"","sum":"","sum_comment":"","sum_foreign":""},"62":{"sum_foreign_comment":"","sum_comment_hidden":false,"sum":"","sum_comment":"","sum_foreign":""},"63":{"sum_foreign_comment":"","sum":"","sum_comment":"","sum_foreign":""},"64":{"sum_foreign_comment":"","sum":"","sum_comment":"","sum_foreign":""}},"ft_src":"Хопта Сергій Федорович\nсуддя\nЗагальнодержавний регіон\nВищий спеціалізований суд з розгляду цивільних і кримінальних справ\nСергій\nХопта Л. Г\nПодружжя\nХопта Сергій Федорович\nСергій Федорович Хопта\nСергій Хопта\nХопта Сергій Федорович\nХопта\nФедорович\nToyota Land Cruiser\n4608\n2013\n40.9\n36.1\nпаркомісце\n17.79\n3179.73\n178.9\n141.8\n2015\n77761\n290094\n77761\n290094\n4608\n2013\nToyota Land Cruiser\n40.9\n17.79\nпаркомісце\n141.8\n3179.73\n36.1\n178.9\nХопта\nХопта Сергій Федорович\nСергій Федорович Хопта\nСергій Хопта\nХопта Сергій Федорович\nХопта Сергій Федорович\nФедорович\nПодружжя\nХопта Л. Г\nСергій\nВищий спеціалізований суд з розгляду цивільних і кримінальних справ\nсуддя\nЗагальнодержавний регіон\n290094\n77761\n290094\n77761\n2015\nПодружжя\nХопта Л. Г\nХопта\nФедорович\nсуддя\nВищий спеціалізований суд з розгляду цивільних і кримінальних справ\nЗагальнодержавний регіон\nХопта Сергій Федорович\nХопта Сергій Федорович\nСергій Федорович Хопта\nСергій Хопта\nХопта Сергій Федорович\nСергій\nToyota Land Cruiser\n4608\n2013\n290094\n77761\n77761\n290094\n178.9\n3179.73\n36.1\n40.9\nпаркомісце\n17.79\n141.8\n2015","general":{"inn":"","inn_hidden":true,"last_name":"Хопта","post":{"region":"Загальнодержавний регіон","region_unclear":false,"post":"суддя","office_unclear":false,"office":"Вищий спеціалізований суд з розгляду цивільних і кримінальних справ"},"name":"Сергій","full_name":"Хопта Сергій Федорович","family_raw":"","addresses":[{"place_district":"","place_city_hidden":true,"place_city":"","place_city_type_hidden":true,"place_district_hidden":true,"place_city_type":"","place_address_hidden":true,"place_address":"","place_hidden":true,"place":""}],"family":[{"inn":"","relations":"Подружжя","relations_hidden":true,"inn_hidden":true,"relations_other":"","name_hidden":true,"family_name":"Хопта Л. Г","name_unclear":false}],"full_name_suggest":{"output":"Хопта Сергій Федорович","input":["Хопта Сергій Федорович","Сергій Федорович Хопта","Сергій Хопта"]},"patronymic":"Федорович"},"source":"VULYK","estate":{"23":[{"costs_rent":"","region":"","costs":"","costs_rent_comment":"","costs_comment":"","address_hidden":false,"region_hidden":true,"space_comment":"","space_units":"м²","space":"3179.73","address":""}],"24":[{"space_hidden":false,"costs":"","costs_comment":"","address_hidden":false,"region_hidden":true,"space_comment":"","space_unclear":false,"space":"36.1","address":"","region":"","costs_rent_comment":"","space_units":"м²","costs_rent":""}],"25":[{"costs":"","costs_comment":"","address_hidden":false,"region_hidden":true,"space_comment":"","space":"141.8","address":"","region":"","costs_rent_comment":"","space_comment_unclear":false,"space_comment_hidden":false,"space_units":"м²","costs_rent":""}],"27":[{"costs_rent":"","region":"","costs":"","costs_rent_comment":"","costs_comment":"","address_hidden":false,"region_hidden":true,"space_comment":"","space_units":"м²","space":"40.9","address":""}],"28":[{"space_hidden":false,"costs":"","costs_comment":"","address_hidden":false,"region_hidden":true,"space_comment":"паркомісце","space_unclear":false,"space":"17.79","address":"","region":"","costs_rent_comment":"","space_units":"м²","costs_rent":""}],"31":[{"space_hidden":false,"address_hidden":false,"region_hidden":true,"space_comment":"","space":"178.9","address":"","costs_property":"","costs_rent_comment":"","address_unclear":false,"space_units":"м²","costs_property_comment":"","costs_rent":""}]},"intro":{"declaration_year":"2015"}}