{"id":"vulyk_95_29","ft_src":"Volkswagen Passat\n1800 куб. см. (на праві користування\n2012\nVolkswagen Passat\n1800 куб. см.\n2012\nХарківська область\nна праві користування\nХарків\n53.5\nХарківська область\nХарків\n1000\nХарківська область\nЗміївський р-н\n2013\nХарківська область\nЗміївській р-н, с. Миргороди\n1617\nХарківська область\nна праві користування\nХарків\n370\nХарківська область\nм. Харків\n53.5\nна праві користування\nХарків\n1000\nХарківська область\nХарківська область\nм. Харків\n370\n2015\n225679\n213023\n240079\n468692\n208333\n14400\n47336\nVolkswagen Passat\n1800 куб. см. (на праві користування\n2012\nVolkswagen Passat\n1800 куб. см.\n2012\n53.5\nна праві користування\nХарків\nХарківська область\nм. Харків\nХарківська область\n370\n53.5\nХарківська область\nм. Харків\n1000\nна праві користування\nХарків\nХарківська область\nХарків\nХарківська область\n1000\nЗміївський р-н\nХарківська область\n2013\n1617\nХарківська область\nЗміївській р-н, с. Миргороди\n370\nна праві користування\nХарків\nХарківська область\nМихайлівна\nПодружжя\nШабельніков С. К\nДитина\nШабельнікова Є. С\nІнше\nмати чоловіка\nШабельнікова Н. П\nМар'єнко Лариса Михайлівна\nЛариса Михайлівна Мар'єнко\nЛариса Мар'єнко\nМар'єнко Лариса Михайлівна\nЛариса\nХарків\n63000\nХарківська область\nМар'єнко Лариса Михайлівна\nМар'єнко\nАдміністративний місцевий суд\nсуддя харківського окружного адміністративного суду\nХарківська область\n47336\n213023\n225679\n47336\n14400\n468692\n240079\n208333\n2015\n47336\nШабельніков С. К\nПодружжя\nШабельнікова Є. С\nДитина\nмати чоловіка\nШабельнікова Н. П\nІнше\nХарківська область\nХарків\n63000\nМихайлівна\nМар'єнко\nХарківська область\nАдміністративний місцевий суд\nсуддя харківського окружного адміністративного суду\nМар'єнко Лариса Михайлівна\nМар'єнко Лариса Михайлівна\nЛариса Михайлівна Мар'єнко\nЛариса Мар'єнко\nМар'єнко Лариса Михайлівна\nЛариса","estate":{"23":[{"address":"Харків","space_units":"м²","costs_comment":"","space_unclear":false,"costs_comment_hidden":false,"region":"Харківська область","address_hidden":true,"space":"1000","address_unclear":false,"space_comment":"на праві користування","costs_rent_comment":"","costs":"","region_unclear":false,"region_hidden":false,"costs_rent":""}],"24":[{"address":"Харків","space_units":"м²","costs_comment":"","space_comment":"на праві користування","region_hidden":false,"region":"Харківська область","address_hidden":true,"space":"370","address_unclear":false,"costs_rent_comment":"","costs":"","costs_rent":""}],"27":[{"address":"Харків","space_units":"м²","costs_comment":"","space_comment":"на праві користування","region_hidden":false,"region":"Харківська область","address_hidden":true,"space":"53.5","address_unclear":false,"costs_rent_comment":"","costs":"","costs_rent":""}],"29":[{"costs_property_comment":"","address":"Харків","space_units":"м²","space_unclear":false,"region_hidden":false,"costs_property":"","space_comment":"","address_hidden":true,"address_unclear":false,"costs_rent_comment":"","space":"1000","region_unclear":false,"region":"Харківська область","costs_rent":""},{"costs_property_comment":"","address":"Зміївський р-н","space_units":"м²","space_comment":"","region_hidden":false,"costs_property":"","region":"Харківська область","address_hidden":true,"address_unclear":true,"costs_rent_comment":"","space":"2013","costs_rent":""},{"costs_property_comment":"","address":"Зміївській р-н, с. Миргороди","space_units":"м²","costs_rent_comment":"","space":"1617","region":"Харківська область","region_hidden":false,"costs_property":"","space_comment":"","costs_rent":""}],"30":[{"costs_property_comment":"","address":"м. Харків","space_units":"м²","space_unclear":false,"region_hidden":false,"costs_property":"","space_comment":"","address_hidden":true,"address_unclear":false,"costs_rent_comment":"","space":"370","region":"Харківська область","costs_rent":""}],"33":[{"costs_property_comment":"","address":"м. Харків","space_units":"м²","costs_rent_comment":"","space":"53.5","region":"Харківська область","region_hidden":false,"costs_property":"","space_comment":"","address_hidden":true,"costs_rent":""}]},"vehicle":{"35":[{"sum_comment":"","brand_info_hidden":false,"brand_info":"1800 куб. см. (на праві користування","sum":"","brand_unclear":false,"brand_hidden":false,"brand":"Volkswagen Passat","sum_rent":"","sum_rent_comment":"","year":"2012","brand_info_unclear":false}],"40":[{"sum_comment":"","brand_info_hidden":false,"brand_info":"1800 куб. см.","sum":"","brand_unclear":false,"brand_hidden":false,"brand":"Volkswagen Passat","sum_rent":"","sum_rent_comment":"","year":"2012","brand_info_unclear":false}]},"source":"VULYK","income":{"5":{"family_comment":"","value":"468692","family_unclear":false,"family":"240079","comment":""},"6":{"family_comment":"","family":"225679","comment":"","value_unclear":false,"family_unclear":false,"value":"213023"},"7":{"source_name_hidden":false,"family_comment":"","comment":"","family":"","source_name_unclear":false,"value":"","source_name":""},"8":{"family_comment":"","value":"","family":"","comment":""},"9":{"family_comment":"","value":"","family_unclear":false,"family":"","comment":""},"10":{"family_comment":"","value":"","family":"","comment":""},"11":{"family_comment":"","value":"","family":"","comment":""},"12":{"family_comment":"","value":"","family":"","comment":""},"13":{"family_comment":"","value":"","family":"","comment":""},"14":{"family_comment":"","value":"","family":"","comment":""},"15":{"family_comment":"","value":"","family":"","comment":""},"16":{"family_comment":"","value":"208333","family_unclear":false,"family":"","comment":""},"17":{"family_comment":"","value":"","family_unclear":false,"family":"","comment":""},"18":{"family_comment":"","value":"","family":"","comment":""},"19":{"family_comment":"","value":"","family":"","comment":""},"20":{"family_comment":"","comment_unclear":false,"value":"47336","family":"14400","comment":""}},"general":{"inn":"","addresses":[{"place_city_type_hidden":false,"place_district_hidden":false,"place_address_unclear":false,"place":"Харківська область","place_city":"Харків","place_city_type":"Місто","place_city_hidden":false,"place_district":"","place_city_unclear":false,"place_address":"63000","place_address_hidden":true,"place_hidden":false}],"last_name":"Мар'єнко","full_name":"Мар'єнко Лариса Михайлівна","family":[{"inn":"","inn_unclear":false,"family_name":"Шабельніков С. К","relations_other":"","relations_hidden":false,"name_unclear":false,"inn_hidden":true,"name_hidden":true,"relations":"Подружжя"},{"inn":"","inn_unclear":false,"family_name":"Шабельнікова Є. С","relations_other":"","relations_hidden":false,"name_unclear":false,"inn_hidden":false,"name_hidden":true,"relations":"Дитина"},{"inn":"","inn_unclear":false,"family_name":"Шабельнікова Н. П","relations_other":"мати чоловіка","relations_hidden":false,"name_unclear":false,"inn_hidden":true,"name_hidden":false,"relations":"Інше"}],"patronymic":"Михайлівна","inn_hidden":true,"name":"Лариса","post":{"office":"Адміністративний місцевий суд","post":"суддя харківського окружного адміністративного суду","candidate":"","office_unclear":false,"region":"Харківська область","office_hidden":false},"family_raw":"","full_name_suggest":{"input":["Мар'єнко Лариса Михайлівна","Лариса Михайлівна Мар'єнко","Лариса Мар'єнко"],"output":"Мар'єнко Лариса Михайлівна"}},"liabilities":{"54":{"sum_comment":"","sum_hidden":false,"sum":"","sum_foreign_comment":"","sum_foreign":"","sum_unclear":false,"sum_comment_hidden":false},"55":{"sum_comment":"","sum_foreign_comment":"","sum_foreign":"","sum":""},"56":{"sum_comment":"","sum_foreign_comment":"","sum_foreign":"","sum":""},"57":{"sum_comment":"","sum_hidden":false,"sum":"47336","sum_foreign_comment":"","sum_foreign":"","sum_unclear":false,"sum_comment_hidden":false},"58":{"sum_comment":"","sum_hidden":false,"sum":"","sum_foreign_comment":"","sum_foreign":"","sum_unclear":false,"sum_comment_hidden":false},"59":{"sum_comment":"","sum_foreign_comment":"","sum_foreign":"","sum":""},"60":{"sum_comment":"","sum_hidden":false,"sum":"","sum_foreign_comment":"","sum_foreign":"","sum_comment_hidden":false},"61":{"sum_comment":"","sum_foreign_comment":"","sum_foreign":"","sum":""},"62":{"sum_comment":"","sum_foreign_comment":"","sum_foreign":"","sum_unclear":false,"sum":""},"63":{"sum_comment":"","sum_foreign_comment":"","sum_foreign":"","sum_unclear":false,"sum":""},"64":{"sum_comment":"","sum_foreign_comment":"","sum_foreign":"","sum":""}},"declaration":{"notfull_lostpages":"","additional_info_text":"","additional_info":"","date":"2016-03-15T00:00:00","notfull":"","url":"http://static.declarations.com.ua/declarations/chosen_ones/judges_batch/30_mar’yenko_larysa_mykhailivna.pdf"},"intro":{"isnotdeclaration":"","declaration_year":"2015"}}