{"income":{"5":{"value":"181160","family_comment":"","value_unclear":false,"family_unclear":false,"family":"39117","comment":""},"6":{"family_comment":"","value":"181160","value_unclear":false,"family":"39117","comment":""},"7":{"value":"","value_unclear":false,"family_comment":"","source_name":"","family":"","comment":""},"8":{"family_comment":"","value":"","family":"","comment":""},"9":{"value":"","family_comment":"","value_unclear":false,"family_unclear":false,"family":"","comment":""},"10":{"family_comment":"","value":"","comment_unclear":false,"family":"","comment":""},"11":{"family_comment":"","value":"","family":"","comment":""},"12":{"family_comment":"","value":"","family":"","comment":""},"13":{"family_comment":"","value":"","value_unclear":false,"family":"","comment":""},"14":{"family_comment":"","value":"","family":"","comment":""},"15":{"family_comment":"","value":"","family":"","comment":""},"16":{"family_comment":"","family_unclear":false,"value":"","family":"","comment":""},"17":{"family_comment":"","family_unclear":false,"value":"","family":"","comment":""},"18":{"family_comment":"","value":"","family":"","comment":""},"19":{"family_comment":"","value":"","family":"","comment":""},"20":{"value":"","family_comment":"","value_unclear":false,"family_hidden":false,"value_hidden":false,"family_unclear":false,"comment_unclear":false,"comment":"","family":""}},"id":"vulyk_100_172","declaration":{"additional_info_text":"","notfull_lostpages":"","date":"2015-03-27T00:00:00","notfull":"","additional_info":"","url":"http://static.declarations.com.ua/declarations/chosen_ones/judges_batch/4442_kuzniak-hodlevska_eleonora_vitaliivna.pdf"},"liabilities":{"54":{"sum_foreign_comment":"","sum":"","sum_comment":"","sum_comment_hidden":false,"sum_unclear":false,"sum_foreign":""},"55":{"sum_foreign_comment":"","sum":"","sum_comment":"","sum_foreign":""},"56":{"sum_foreign_comment":"","sum":"","sum_comment":"","sum_unclear":false,"sum_foreign":""},"57":{"sum_foreign_comment":"","sum":"","sum_comment":"","sum_comment_unclear":false,"sum_comment_hidden":false,"sum_unclear":false,"sum_foreign":""},"58":{"sum_foreign_comment":"","sum":"","sum_comment":"","sum_comment_hidden":false,"sum_unclear":false,"sum_foreign":""},"59":{"sum_foreign_comment":"","sum":"","sum_comment":"","sum_foreign":""},"60":{"sum_foreign_comment":"","sum_comment_hidden":false,"sum":"191","sum_comment":"ПрАТ АСК Інго Україна","sum_foreign":""},"61":{"sum_foreign_comment":"","sum":"","sum_comment":"","sum_foreign":""},"62":{"sum_foreign_comment":"","sum":"","sum_comment":"","sum_unclear":false,"sum_foreign":""},"63":{"sum_foreign_comment":"","sum_comment_hidden":false,"sum":"","sum_comment":"","sum_foreign":""},"64":{"sum_foreign_comment":"","sum_comment_hidden":false,"sum":"","sum_comment":"","sum_foreign":""}},"ft_src":"ПрАТ АСК Інго Україна\n191\nКузняк-Годлевська Елеонора Віталіївна\nсуддя кам'янець-подільського міськрайонного суду хмельницької області\nХмельницька область\nЗагальний місцевий суд\nЕлеонора\nГодлевський Е. М\nПодружжя\nКузняк-Годлевська Елеонора Віталіївна\nЕлеонора Віталіївна Кузняк-Годлевська\nЕлеонора Кузняк-Годлевська\nКузняк-Годлевська Елеонора Віталіївна\nКузняк-Годлевська\nВіталіївна\n181160\n39117\n39117\n181160\n41\n41\n2014\n39117\n181160\n39117\n181160\n181160\n39117\n181160\n39117\nПодружжя\nГодлевський Е. М\nВіталіївна\nКузняк-Годлевська\nКузняк-Годлевська Елеонора Віталіївна\nЕлеонора Віталіївна Кузняк-Годлевська\nЕлеонора Кузняк-Годлевська\nКузняк-Годлевська Елеонора Віталіївна\nКузняк-Годлевська Елеонора Віталіївна\nЕлеонора\nЗагальний місцевий суд\nХмельницька область\nсуддя кам'янець-подільського міськрайонного суду хмельницької області\n191\nПрАТ АСК Інго Україна\n41\n41\n2014\nПрАТ АСК Інго Україна\n191\nГодлевський Е. М\nПодружжя\nВіталіївна\nКузняк-Годлевська\nХмельницька область\nЗагальний місцевий суд\nсуддя кам'янець-подільського міськрайонного суду хмельницької області\nКузняк-Годлевська Елеонора Віталіївна\nКузняк-Годлевська Елеонора Віталіївна\nЕлеонора Віталіївна Кузняк-Годлевська\nЕлеонора Кузняк-Годлевська\nКузняк-Годлевська Елеонора Віталіївна\nЕлеонора\n41\n41\n2014","general":{"inn":"","inn_hidden":true,"last_name":"Кузняк-Годлевська","post":{"post_unclear":false,"region_unclear":false,"post":"суддя кам'янець-подільського міськрайонного суду хмельницької області","office":"Загальний місцевий суд","region":"Хмельницька область","post_hidden":false,"office_unclear":false},"name":"Елеонора","full_name":"Кузняк-Годлевська Елеонора Віталіївна","family_raw":"","addresses":[{"place_district":"","place_city_hidden":true,"place_city":"","place_city_unclear":false,"place_district_hidden":false,"place_city_type":"","place_address_hidden":true,"place_city_type_hidden":false,"place_address":"","place_hidden":true,"place":""}],"family":[{"inn_hidden":true,"inn":"","name_hidden":true,"family_name":"Годлевський Е. М","relations":"Подружжя","name_unclear":false}],"full_name_suggest":{"output":"Кузняк-Годлевська Елеонора Віталіївна","input":["Кузняк-Годлевська Елеонора Віталіївна","Елеонора Віталіївна Кузняк-Годлевська","Елеонора Кузняк-Годлевська"]},"patronymic":"Віталіївна"},"source":"VULYK","estate":{"25":[{"space_unclear":false,"costs":"","costs_comment":"","address_hidden":false,"region_hidden":true,"space_comment":"","space":"41","address":"","costs_comment_unclear":false,"region":"","address_unclear":false,"costs_rent_comment":"","space_comment_unclear":false,"space_units":"м²","costs_rent":""}],"31":[{"region_unclear":false,"space_unclear":false,"costs_property_comment_unclear":false,"address_hidden":false,"region_hidden":true,"space_comment":"","space":"41","address":"","region":"","costs_property":"","costs_rent_comment":"","space_comment_unclear":false,"address_unclear":false,"space_units":"м²","costs_property_comment":"","costs_rent":""}]},"intro":{"declaration_year":"2014"}}