{"id":"vulyk_86_74","ft_src":"м. Красноармійськ\n29.8\nДонецька область\n2014\n170205\n12180\n182385\n170205\n182385\n12180\nВеличко Олена Володимирівна\nОлена Володимирівна Величко\nОлена Величко\nВеличко Олена Володимирівна\nВеличко Олена Володимирівна\nОлена\nВеличко\nЗагальний місцевий суд\nДонецька область\nсуддя красноармійського міськрайонного суду донецької області\nВолодимирівна\nДонецька область\nКрасноармійськ\n29.8\nм. Красноармійськ\nДонецька область\n2014\nВеличко Олена Володимирівна\nОлена Володимирівна Величко\nОлена Величко\nВеличко Олена Володимирівна\nВолодимирівна\nВеличко\nОлена\nКрасноармійськ\nДонецька область\nДонецька область\nЗагальний місцевий суд\nсуддя красноармійського міськрайонного суду донецької області\nВеличко Олена Володимирівна","estate":{"25":[{"address":"м. Красноармійськ","space_units":"м²","space_hidden":false,"space_unclear":false,"region_hidden":false,"costs_comment":"","space_comment":"","address_hidden":true,"costs":"","address_unclear":true,"costs_rent_comment":"","space":"29.8","region":"Донецька область","costs_rent":""}]},"source":"VULYK","income":{"5":{"family_comment":"","value":"182385","family":"","comment":""},"6":{"family_comment":"","value":"170205","family":"","comment":"","family_comment_unclear":false},"7":{"source_name_hidden":false,"family_comment":"","comment":"","family":"","comment_hidden":false,"value":"","source_name":""},"8":{"family_comment":"","value":"","family":"","comment":""},"9":{"family_comment":"","value":"","family":"","comment":""},"10":{"family":"","family_comment":"","comment":"","value_hidden":false,"value_unclear":false,"value":"12180"},"11":{"family_comment":"","value":"","family":"","comment":""},"12":{"family_comment":"","value":"","family":"","comment":""},"13":{"family_comment":"","value":"","family":"","comment":""},"14":{"family_comment":"","value":"","family":"","comment":""},"15":{"family_comment":"","value":"","family":"","comment":""},"16":{"family_comment":"","value":"","family":"","comment":""},"17":{"family_comment":"","value":"","family":"","comment":""},"18":{"family_comment":"","value":"","family":"","comment":""},"19":{"family_comment":"","value":"","family":"","comment":""},"20":{"family_comment":"","comment_unclear":false,"value":"","family":"","comment":""}},"general":{"family_raw":"","name":"Олена","full_name_suggest":{"input":["Величко Олена Володимирівна","Олена Володимирівна Величко","Олена Величко"],"output":"Величко Олена Володимирівна"},"patronymic":"Володимирівна","inn_hidden":true,"patronymic_unclear":false,"inn":"","inn_unclear":false,"last_name":"Величко","full_name":"Величко Олена Володимирівна","post":{"office":"Загальний місцевий суд","post":"суддя красноармійського міськрайонного суду донецької області","candidate":"","region_hidden":false,"region":"Донецька область","office_hidden":false,"post_unclear":false,"office_unclear":false},"addresses":[{"place_city_type":"Місто","place_city_type_hidden":false,"place_district_hidden":false,"place_city_hidden":false,"place_district":"","place_hidden":false,"place_address":"","place":"Донецька область","place_city":"Красноармійськ","place_address_hidden":true,"place_unclear":false}]},"liabilities":{"54":{"sum_comment":"","sum_foreign_comment":"","sum_foreign":"","sum_unclear":false,"sum":""},"55":{"sum_comment":"","sum_foreign_comment":"","sum_foreign":"","sum":""},"56":{"sum_comment":"","sum_foreign_comment":"","sum_foreign":"","sum_hidden":false,"sum":""},"57":{"sum_comment":"","sum_foreign_comment":"","sum_foreign":"","sum_unclear":false,"sum":""},"58":{"sum_comment":"","sum_foreign_comment":"","sum_foreign":"","sum_unclear":false,"sum":""},"59":{"sum_comment":"","sum_foreign_comment":"","sum_foreign":"","sum":""},"60":{"sum_comment":"","sum_foreign_comment":"","sum_foreign":"","sum":"","sum_comment_hidden":false},"61":{"sum_comment":"","sum_foreign_comment":"","sum_foreign":"","sum":""},"62":{"sum_comment":"","sum_foreign_comment":"","sum_foreign":"","sum":""},"63":{"sum_comment":"","sum_foreign_comment":"","sum_foreign":"","sum":""},"64":{"sum_comment":"","sum_foreign_comment":"","sum_foreign":"","sum":""}},"declaration":{"notfull_lostpages":"","additional_info_text":"","additional_info":"","date":"2015-04-30T00:00:00","notfull":"","url":"http://static.declarations.com.ua/declarations/chosen_ones/judges_batch/2777_velychko_olena_volodymyrivna.pdf"},"intro":{"declaration_year_unclear":false,"declaration_year":"2014"}}