{"income":{"5":{"value":"244602.39","family_comment":"","value_unclear":false,"family_unclear":false,"comment_unclear":false,"comment":"","family":""},"6":{"family_comment":"","value":"220242.39","comment_unclear":false,"family":"","comment":""},"7":{"family_comment":"","value":"","source_name":"","family":"","comment":""},"8":{"family_comment":"","value":"","family":"","comment":""},"9":{"family_comment":"","value":"","value_unclear":false,"family":"","comment":""},"10":{"family_comment":"","value":"24360","value_unclear":false,"family":"","comment":""},"11":{"family_comment":"","value":"","family":"","comment":""},"12":{"family_comment":"","value":"","family":"","comment":""},"13":{"family_comment":"","value":"","family":"","comment":""},"14":{"family_comment":"","value":"","family":"","comment":""},"15":{"family_comment":"","value":"","family":"","comment":""},"16":{"family_comment":"","value":"","family":"","comment":""},"17":{"family_comment":"","value":"","value_unclear":false,"family":"","comment":""},"18":{"family_comment":"","value":"","value_unclear":false,"family":"","comment":""},"19":{"family_comment":"","value":"","family":"","comment":""},"20":{"value":"","family_comment":"","value_unclear":false,"family_unclear":false,"comment_unclear":false,"comment":"","family":""}},"id":"vulyk_84_178","declaration":{"additional_info_text":"","notfull_lostpages":"","date":"2015-03-28T00:00:00","notfull":"","additional_info":"","url":"http://static.declarations.com.ua/declarations/chosen_ones/judges_batch/2592_sukharevych_zinaida_mykolaivna.pdf"},"liabilities":{"54":{"sum_foreign_comment":"","sum_comment_hidden":false,"sum":"","sum_comment":"","sum_foreign":""},"55":{"sum_foreign_comment":"","sum":"","sum_comment":"","sum_foreign":""},"56":{"sum_foreign_comment":"","sum":"","sum_comment":"","sum_foreign":""},"57":{"sum_foreign_comment":"","sum_comment_hidden":false,"sum":"","sum_comment":"","sum_foreign":""},"58":{"sum_foreign_comment":"","sum_comment_hidden":false,"sum":"","sum_comment":"","sum_foreign":""},"59":{"sum_foreign_comment":"","sum":"","sum_comment":"","sum_foreign":""},"60":{"sum_foreign_comment":"","sum":"","sum_comment":"","sum_foreign":""},"61":{"sum_foreign_comment":"","sum":"","sum_comment":"","sum_foreign":""},"62":{"sum_foreign_comment":"","sum":"","sum_comment":"","sum_foreign":""},"63":{"sum_foreign_comment":"","sum_comment_hidden":false,"sum":"","sum_comment":"","sum_foreign":""},"64":{"sum_foreign_comment":"","sum_comment_hidden":false,"sum":"","sum_comment":"","sum_foreign":""}},"ft_src":"суддя заводського районного суду м. миколаєва\nМиколаївська область\nЗагальний місцевий суд\nЗінаїда\nСухаревич А. Д\nДитина\nМиколаївна\nСухаревич Зінаїда Миколаївна\nЗінаїда Миколаївна Сухаревич\nЗінаїда Сухаревич\nСухаревич Зінаїда Миколаївна\nСухаревич Зінаїда Миколаївна\nСухаревич\n24360\n244602.39\n220242.39\n2014\n220242.39\n24360\n244602.39\n220242.39\n244602.39\n24360\nСухаревич Зінаїда Миколаївна\nЗінаїда Миколаївна Сухаревич\nЗінаїда Сухаревич\nСухаревич Зінаїда Миколаївна\nЗінаїда\nДитина\nСухаревич А. Д\nСухаревич Зінаїда Миколаївна\nМиколаївна\nсуддя заводського районного суду м. миколаєва\nЗагальний місцевий суд\nМиколаївська область\nСухаревич\n2014\nСухаревич А. Д\nДитина\nМиколаївна\nСухаревич\nЗінаїда\nСухаревич Зінаїда Миколаївна\nЗінаїда Миколаївна Сухаревич\nЗінаїда Сухаревич\nСухаревич Зінаїда Миколаївна\nМиколаївська область\nсуддя заводського районного суду м. миколаєва\nЗагальний місцевий суд\nСухаревич Зінаїда Миколаївна\n2014","general":{"inn":"","name":"Зінаїда","inn_unclear":false,"family":[{"inn":"","inn_hidden":false,"inn_unclear":false,"relations_hidden":false,"relations_other":"","relations":"Дитина","name_hidden":false,"family_name":"Сухаревич А. Д","name_unclear":false}],"inn_hidden":true,"family_raw":"","last_name":"Сухаревич","post":{"post_unclear":false,"region_unclear":false,"post":"суддя заводського районного суду м. миколаєва","candidate":"","office_hidden":false,"region":"Миколаївська область","post_hidden":false,"office":"Загальний місцевий суд","office_unclear":false,"region_hidden":false},"full_name":"Сухаревич Зінаїда Миколаївна","addresses":[{"place_city_type_unclear":false,"place_address":"","place_district_hidden":true,"place_city_type":"","place_address_hidden":true,"place_address_unclear":false,"place_city_type_hidden":true,"place":"","place_district":"","place_unclear":false,"place_city":"","place_city_unclear":false,"place_hidden":true,"place_city_hidden":true,"place_district_unclear":false}],"patronymic":"Миколаївна","full_name_suggest":{"output":"Сухаревич Зінаїда Миколаївна","input":["Сухаревич Зінаїда Миколаївна","Зінаїда Миколаївна Сухаревич","Зінаїда Сухаревич"]}},"source":"VULYK","intro":{"declaration_year":"2014","isnotdeclaration":"","declaration_year_unclear":false}}