{"income":{"5":{"value":"202927","family_comment":"","value_unclear":false,"family_hidden":false,"family_unclear":false,"family":"37781","comment":""},"6":{"value":"185060","value_unclear":false,"comment_hidden":false,"family_hidden":false,"value_hidden":false,"family_comment":"","family":"37781","comment":""},"7":{"value":"","family_comment":"","source_name":"","family":"","comment":"","source_name_hidden":false},"8":{"family_comment":"","value":"","family":"","comment":""},"9":{"family_comment":"","value":"","family":"","comment":"","value_hidden":false},"10":{"value":"12180","value_unclear":false,"family_hidden":false,"value_hidden":false,"family_comment":"","family":"","comment":""},"11":{"family_comment":"","value":"","family":"","comment":""},"12":{"family_comment":"","value":"","family":"","comment":""},"13":{"family_comment":"","value":"","comment_hidden":false,"family":"","comment":""},"14":{"value":"","comment_hidden":false,"value_hidden":false,"family_comment":"","family":"","comment":""},"15":{"family_comment":"","value":"","family":"","comment":""},"16":{"family_comment":"","value":"","family":"","comment":"","value_hidden":false},"17":{"family_comment":"","value":"","family":"","comment":""},"18":{"family_comment":"","value":"","family":"","comment":""},"19":{"family_comment":"","value":"","family":"","comment":"","value_hidden":false},"20":{"value":"5687","family_comment":"","comment_unclear":false,"family_unclear":false,"family":"","comment":""}},"vehicle":{"40":[{"year_hidden":false,"brand_info":"1390 куб. см., 103 кВт , 440 см","sum_rent_comment":"","year":"2010","brand_info_hidden":false,"brand_info_unclear":false,"sum_rent":"","sum":"","brand":"Volkswagen Touran","sum_comment":"","brand_unclear":false,"brand_hidden":false}]},"id":"vulyk_12_57","banks":{"45":[{"sum_foreign_comment":"","sum":"","sum_comment":"","sum_hidden":false,"sum_foreign_units":"UAH","sum_foreign_hidden":false,"sum_units":"UAH","sum_comment_hidden":false,"sum_unclear":false,"sum_foreign":"","sum_units_hidden":false},{"sum_foreign_comment":"","sum_units":"","sum_comment":"","sum_foreign_units":"","sum":"","sum_foreign":""}],"46":[{"sum_foreign_comment":"","sum_units":"UAH","sum_comment":"","sum_hidden":false,"sum_foreign_units":"UAH","sum":"","sum_foreign_hidden":false,"sum_foreign":""}],"47":[{"sum_foreign_comment":"","sum_units":"UAH","sum_comment":"","sum_comment_unclear":false,"sum_foreign_units":"UAH","sum":"","sum_foreign":""},{"sum_foreign_comment":"","sum_units":"","sum_comment":"","sum_foreign_units":"","sum":"","sum_foreign":""}],"48":[{"sum_foreign_comment":"","sum_units":"UAH","sum_comment":"","sum_foreign_units":"UAH","sum":"","sum_foreign":""}],"49":[{"sum_foreign_comment":"","sum_units":"UAH","sum_comment":"","sum_foreign_units":"UAH","sum":"","sum_foreign":""}],"50":[{"sum_foreign_comment":"","sum_units":"UAH","sum_comment":"","sum_foreign_units":"UAH","sum":"","sum_foreign":""}],"51":[{"sum_foreign_comment":"","sum_units":"UAH","sum_comment":"","sum_hidden":false,"sum_foreign_units":"UAH","sum_comment_hidden":false,"sum_units_hidden":false,"sum":"","sum_foreign":""}],"52":[{"sum_foreign_comment":"","sum_units":"UAH","sum_comment":"","sum_comment_unclear":false,"sum_foreign_units":"UAH","sum":"","sum_foreign":""},{"sum_foreign_comment":"","sum_units":"","sum_comment":"","sum_foreign_units":"","sum":"","sum_foreign":""},{"sum_foreign_comment":"","sum_units":"","sum_comment":"","sum_foreign_units":"","sum":"","sum_foreign":""},{"sum_foreign_comment":"","sum_units":"","sum_comment":"","sum_foreign_units":"","sum":"","sum_foreign":""}],"53":[{"sum_foreign_comment":"","sum_units":"UAH","sum_comment":"","sum_foreign_units":"UAH","sum":"","sum_foreign":""}]},"declaration":{"additional_info_text":"","notfull_lostpages":"","date":"2015-03-27T00:00:00","notfull":"","additional_info":"","url":"http://static.declarations.com.ua/declarations/chosen_ones/mega_batch/yurchenko_inna_mykolaivna.pdf"},"liabilities":{"54":{"sum_foreign_comment":"","sum":"","sum_comment":"","sum_hidden":false,"sum_comment_hidden":false,"sum_foreign":""},"55":{"sum_foreign_comment":"","sum":"","sum_comment":"","sum_foreign":""},"56":{"sum_foreign_comment":"","sum":"","sum_comment":"","sum_foreign":""},"57":{"sum_foreign_comment":"","sum":"","sum_comment":"","sum_comment_unclear":false,"sum_hidden":false,"sum_comment_hidden":false,"sum_unclear":false,"sum_foreign":""},"58":{"sum_foreign_comment":"","sum":"","sum_comment":"","sum_comment_unclear":false,"sum_hidden":false,"sum_foreign":""},"59":{"sum_foreign_comment":"","sum":"","sum_hidden":false,"sum_comment":"","sum_foreign":""},"60":{"sum_foreign_comment":"","sum":"","sum_comment":"","sum_hidden":false,"sum_comment_hidden":false,"sum_foreign":""},"61":{"sum_foreign_comment":"","sum":"","sum_comment":"","sum_foreign":""},"62":{"sum_foreign_comment":"","sum":"","sum_comment":"","sum_comment_unclear":false,"sum_unclear":false,"sum_foreign":""},"63":{"sum_foreign_comment":"","sum":"","sum_comment":"","sum_comment_unclear":false,"sum_foreign":""},"64":{"sum_foreign_comment":"","sum":"","sum_comment":"","sum_comment_unclear":false,"sum_foreign":""}},"ft_src":"Стаханов\n94013\nЛуганська область\n61093\nХарків\nХарківська область\nсуддя стахановського міського суду луганської області\nЛуганська область\nЗагальний місцевий суд\nІнна\nЮрченко Д. О., 09. 05. 1973\nПодружжя\nЮрченко А. Д., 07. 12. 1998\nДитина\nМиколаївна\nЮрченко\nЮрченко Інна Миколаївна\nЮрченко Інна Миколаївна\nІнна Миколаївна Юрченко\nІнна Юрченко\nЮрченко Інна Миколаївна\n1390 куб. см., 103 кВт , 440 см\nVolkswagen Touran\n2010\n2014\n1390 куб. см., 103 кВт , 440 см\nVolkswagen Touran\n2010\n62\n1/4 частина квартири\nЛуганська область\nм. Стаханов\n51.3\nЛуганська область\nм. Стаханов\nЗагальний місцевий суд\nсуддя стахановського міського суду луганської області\nЛуганська область\nПодружжя\nЮрченко Д. О., 09. 05. 1973\nДитина\nЮрченко А. Д., 07. 12. 1998\nЮрченко Інна Миколаївна\nІнна Миколаївна Юрченко\nІнна Юрченко\nЮрченко Інна Миколаївна\nІнна\nЮрченко Інна Миколаївна\nЮрченко\nМиколаївна\n94013\nЛуганська область\nСтаханов\n61093\nХарківська область\nХарків\n185060\n37781\n5687\n37781\n202927\n12180\n2014\nЛуганська область\n1/4 частина квартири\nм. Стаханов\n62\nм. Стаханов\n51.3\nЛуганська область\nПодружжя\nЮрченко Д. О., 09. 05. 1973\nЮрченко А. Д., 07. 12. 1998\nДитина\nМиколаївна\nЮрченко\nІнна\nЮрченко Інна Миколаївна\nІнна Миколаївна Юрченко\nІнна Юрченко\nЮрченко Інна Миколаївна\nЛуганська область\nСтаханов\n94013\n61093\nХарківська область\nХарків\nЛуганська область\nЗагальний місцевий суд\nсуддя стахановського міського суду луганської області\nЮрченко Інна Миколаївна\n37781\n185060\n12180\n37781\n202927\n5687\n2010\nVolkswagen Touran\n1390 куб. см., 103 кВт , 440 см\n12180\n5687\n202927\n37781\n185060\n37781\nм. Стаханов\nЛуганська область\n51.3\n1/4 частина квартири\nм. Стаханов\nЛуганська область\n62\n2014","general":{"inn":"","name":"Інна","patronymic_unclear":false,"last_name_hidden":false,"family":[{"inn":"","inn_hidden":true,"relations_unclear":false,"relations_hidden":false,"relations_other":"","relations":"Подружжя","name_hidden":false,"inn_unclear":false,"family_name":"Юрченко Д. О., 09. 05. 1973","name_unclear":false},{"inn":"","relations":"Дитина","inn_unclear":false,"family_name":"Юрченко А. Д., 07. 12. 1998","inn_hidden":true,"relations_other":"","name_hidden":false,"name_unclear":false}],"patronymic":"Миколаївна","inn_hidden":false,"family_raw":"","inn_unclear":false,"post":{"post_unclear":false,"post":"суддя стахановського міського суду луганської області","candidate":"","office_hidden":false,"region":"Луганська область","post_hidden":false,"office":"Загальний місцевий суд","office_unclear":false},"last_name_unclear":false,"full_name":"Юрченко Інна Миколаївна","addresses":[{"place_district":"","place_city_hidden":false,"place_city":"Стаханов","place_city_type_hidden":false,"place_district_hidden":false,"place_city_type":"Місто","place_address_hidden":true,"place_address":"94013","place_hidden":false,"place":"Луганська область"},{"place_district":"","place_city":"Харків","place_address":"61093","place":"Харківська область","place_city_type":"Місто"}],"last_name":"Юрченко","patronymic_hidden":false,"full_name_suggest":{"output":"Юрченко Інна Миколаївна","input":["Юрченко Інна Миколаївна","Інна Миколаївна Юрченко","Інна Юрченко"]}},"source":"VULYK","estate":{"23":[{"space_unclear":false,"costs":"","costs_comment":"","address_hidden":false,"region_hidden":false,"space_comment":"","space_hidden":false,"space":"","address":"","costs_comment_unclear":false,"region":"","address_unclear":false,"costs_rent_comment":"","space_units":"м²","costs_rent":""},{"space_unclear":false,"costs":"","costs_comment":"","address_hidden":false,"region_hidden":false,"space_comment":"","space":"","address":"","region":"","costs_rent_comment":"","space_units":"","costs_rent":""},{"space_hidden":false,"costs":"","costs_comment":"","address_hidden":false,"region_hidden":false,"space_comment":"","space":"","address":"","region":"","costs_rent_comment":"","space_units":"","costs_rent":""},{"costs_rent":"","region":"","costs":"","costs_rent_comment":"","costs_comment":"","space_comment":"","space_units":"","space":"","address":""}],"25":[{"region_unclear":false,"space_hidden":false,"costs":"","costs_comment":"","costs_hidden":false,"address_hidden":false,"region_hidden":false,"space_comment":"","space_unclear":false,"space":"51.3","address":"м. Стаханов","region":"Луганська область","address_unclear":false,"costs_rent_comment":"","costs_rent_hidden":false,"space_comment_unclear":false,"space_units":"м²","costs_rent":""}],"28":[{"costs":"","costs_comment":"","address_hidden":false,"region_hidden":false,"space_comment":"1/4 частина квартири","space":"62","address":"м. Стаханов","region":"Луганська область","address_unclear":false,"costs_rent_comment":"","space_units":"м²","costs_rent":""}]},"intro":{"declaration_year":"2014","isnotdeclaration":""}}