{"income":{"5":{"family_comment":"","value":"235920","value_unclear":false,"family":"29820","comment":""},"6":{"value":"235920","value_unclear":false,"family_hidden":false,"family_comment":"","family":"","comment":""},"7":{"source_name_unclear":false,"value":"","family_comment":"","source_name":"","family":"","comment":""},"8":{"family_comment":"","value":"","family":"","comment":""},"9":{"family_comment":"","value":"","family":"","comment":""},"10":{"family_comment":"","value":"","family":"","comment":""},"11":{"family_comment":"","value":"","comment_unclear":false,"family":"","comment":""},"12":{"family_comment":"","value":"","family":"","comment":""},"13":{"family_comment":"","value":"","family":"","comment":""},"14":{"family_comment":"","value":"","family":"","comment":""},"15":{"family_comment":"","value":"","family":"6860","comment":""},"16":{"family_comment":"","value":"","family":"","comment":""},"17":{"family_comment":"","value":"","family":"","comment":""},"18":{"family_comment":"","value":"","family":"","comment":""},"19":{"family_comment":"","value":"","family":"","comment":""},"20":{"value":"","family_comment":"","value_unclear":false,"family_unclear":false,"comment_unclear":false,"comment":"","family":"22960"}},"vehicle":{"35":[{"brand_info":"1600 куб. см.","sum_rent_comment":"","brand":"ВАЗ 2110","sum_comment":"","brand_unclear":false,"year":"2004","sum_rent_unclear":false,"brand_info_hidden":false,"brand_info_unclear":false,"sum":"","sum_rent":""}],"40":[{"brand_info":"1997 куб. см., 114 кВт","sum_rent_comment":"","brand":"Honda Accord","sum_comment":"","year":"2008","brand_hidden":false,"brand_info_hidden":false,"brand_info_unclear":false,"sum":"","sum_rent":""}]},"id":"vulyk_101_41","declaration":{"additional_info_text":"","notfull_lostpages":"","date":"2016-03-25T00:00:00","notfull":"","additional_info":"","url":"http://static.declarations.com.ua/declarations/chosen_ones/judges_batch/705_varykasha_oleksandr_dmytrovych_2015.pdf"},"liabilities":{"54":{"sum_foreign_comment":"","sum":"","sum_comment":"","sum_comment_unclear":false,"sum_hidden":false,"sum_comment_hidden":false,"sum_unclear":false,"sum_foreign":""},"55":{"sum_foreign_comment":"","sum":"","sum_comment":"","sum_foreign":""},"56":{"sum_foreign_comment":"","sum":"","sum_comment":"","sum_comment_hidden":false,"sum_unclear":false,"sum_foreign":""},"57":{"sum_foreign_comment":"","sum":"","sum_comment":"","sum_hidden":false,"sum_comment_hidden":false,"sum_unclear":false,"sum_foreign":""},"58":{"sum_foreign_comment":"","sum":"","sum_comment":"","sum_comment_unclear":false,"sum_hidden":false,"sum_comment_hidden":false,"sum_unclear":false,"sum_foreign":""},"59":{"sum_foreign_comment":"","sum":"","sum_comment":"","sum_foreign":""},"60":{"sum_foreign_comment":"","sum":"","sum_comment":"","sum_hidden":false,"sum_comment_hidden":false,"sum_unclear":false,"sum_foreign":""},"61":{"sum_foreign_comment":"","sum":"","sum_comment":"","sum_foreign":""},"62":{"sum_foreign_comment":"","sum":"","sum_comment":"","sum_comment_unclear":false,"sum_foreign":""},"63":{"sum_foreign_comment":"","sum_comment_hidden":false,"sum":"","sum_comment":"","sum_foreign":""},"64":{"sum_foreign_comment":"","sum_comment_hidden":false,"sum":"","sum_comment":"","sum_foreign":""}},"ft_src":"суддя апеляційного суду одеської області\nОдеська область\nЗагальний апеляційний суд\nОлександр\nВарикаша О. М\nПодружжя\nВарикаша І. О\nДитина\nВарикаша М. О\nДитина\nДмитрович\nВарикаша Олександр Дмитрович\nВарикаша\nВарикаша Олександр Дмитрович\nОлександр Дмитрович Варикаша\nОлександр Варикаша\nВарикаша Олександр Дмитрович\nВАЗ 2110\n1600 куб. см.\n2004\n1997 куб. см., 114 кВт\nHonda Accord\n2008\n2/3 64.133\n96.2\n2/3\n64.133\n1/3 32.066\n96.2\n1/3\n32.066\n2015\n235920\n6860\n29820\n235920\n22960\n1600 куб. см.\n2004\nВАЗ 2110\n1997 куб. см., 114 кВт\n2008\nHonda Accord\n2/3 64.133\n96.2\n64.133\n2/3\n96.2\n1/3 32.066\n32.066\n1/3\nВарикаша Олександр Дмитрович\nОлександр Дмитрович Варикаша\nОлександр Варикаша\nВарикаша Олександр Дмитрович\nОлександр\nВарикаша Олександр Дмитрович\nДмитрович\nсуддя апеляційного суду одеської області\nОдеська область\nЗагальний апеляційний суд\nВарикаша\nПодружжя\nВарикаша О. М\nДитина\nВарикаша І. О\nДитина\nВарикаша М. О\n235920\n22960\n6860\n235920\n29820\n2015\nВарикаша О. М\nПодружжя\nВарикаша І. О\nДитина\nВарикаша М. О\nДитина\nОлександр\nДмитрович\nВарикаша\nВарикаша Олександр Дмитрович\nОлександр Дмитрович Варикаша\nОлександр Варикаша\nВарикаша Олександр Дмитрович\nсуддя апеляційного суду одеської області\nОдеська область\nЗагальний апеляційний суд\nВарикаша Олександр Дмитрович\n2004\nВАЗ 2110\n1600 куб. см.\nHonda Accord\n1997 куб. см., 114 кВт\n2008\n6860\n22960\n29820\n235920\n235920\n2/3 64.133\n96.2\n2/3\n64.133\n1/3 32.066\n96.2\n1/3\n32.066\n2015","general":{"inn":"","name":"Олександр","inn_unclear":false,"family":[{"inn":"","relations":"Подружжя","relations_other":"","inn_hidden":true,"family_name":"Варикаша О. М","name_hidden":true,"name_unclear":false},{"inn":"","relations":"Дитина","relations_unclear":false,"family_name":"Варикаша І. О","inn_hidden":true,"relations_other":"","name_hidden":false,"name_unclear":false},{"inn":"","relations":"Дитина","relations_other":"","inn_hidden":true,"family_name":"Варикаша М. О","name_hidden":false,"name_unclear":false}],"inn_hidden":true,"family_raw":"","last_name":"Варикаша","post":{"region":"Одеська область","region_unclear":false,"post":"суддя апеляційного суду одеської області","office_unclear":false,"office":"Загальний апеляційний суд"},"full_name":"Варикаша Олександр Дмитрович","addresses":[{"place_district":"","place_address_hidden":true,"place_city":"","place_city_type_hidden":true,"place_district_hidden":true,"place_city_type":"","place_city_hidden":true,"place_address":"","place_hidden":true,"place":""}],"patronymic":"Дмитрович","patronymic_hidden":false,"full_name_suggest":{"output":"Варикаша Олександр Дмитрович","input":["Варикаша Олександр Дмитрович","Олександр Дмитрович Варикаша","Олександр Варикаша"]}},"source":"VULYK","estate":{"25":[{"space_unclear":false,"costs":"","costs_comment":"","address_hidden":true,"region_hidden":true,"space_comment":"1/3 32.066","space_hidden":false,"space":"96.2","address":"","region":"","costs_rent_comment":"","space_comment_unclear":false,"space_units":"м²","costs_rent":""},{"space_unclear":false,"costs":"","costs_comment":"","space_comment":"1/3","space_hidden":false,"space":"32.066","address":"","region":"","costs_rent_comment":"","space_comment_unclear":false,"space_units":"м²","costs_rent":""}],"31":[{"space_unclear":false,"address_hidden":true,"region_hidden":true,"space_comment":"2/3 64.133","space_hidden":false,"space":"96.2","address":"","costs_rent_comment_unclear":false,"region":"","costs_property":"","costs_rent_comment":"","space_units":"м²","costs_property_comment":"","costs_rent":""},{"costs_rent":"","region":"","costs_property":"","costs_rent_comment":"","space_comment":"2/3","costs_property_comment":"","space_units":"м²","space":"64.133","address":""}]},"intro":{"declaration_year":"2015"}}