{"id":"vulyk_98_23","ft_src":"2012\nHyundai Accent\n1591 куб. см.\n5999 куб. см.\n2002\nMercedes-Benz\n3456 куб. см.\n2014\nToyota Highlander\n24.9\n11500\n356499\n370614\n2014\n1591 куб. см.\n2012\nHyundai Accent\n5999 куб. см.\n2002\nMercedes-Benz\n3456 куб. см.\n2014\nToyota Highlander\n2014\nАдміністративний місцевий суд\nсуддя вінницького окружного адміністративного суду\nВінницька область\nШаповалова Тетяна Михайлівна\nТетяна Михайлівна Шаповалова\nТетяна Шаповалова\nШаповалова Тетяна Михайлівна\nШаповалова Тетяна Михайлівна\nПодружжя\nШаповалов А. С\nДитина\nШаповалова Є. А\nТетяна\nШаповалова\nМихайлівна\n92572\n189804\n10000\n18060\n210933\n122214\n11582\n11129\n24.9\n370614\n11500\n356499\n189804\n92572\n11129\n11582\n10000\n210933\n122214\n18060\nПодружжя\nШаповалов А. С\nДитина\nШаповалова Є. А\nМихайлівна\nШаповалова\nТетяна\nШаповалова Тетяна Михайлівна\nТетяна Михайлівна Шаповалова\nТетяна Шаповалова\nШаповалова Тетяна Михайлівна\nсуддя вінницького окружного адміністративного суду\nВінницька область\nАдміністративний місцевий суд\nШаповалова Тетяна Михайлівна","estate":{"31":[{"costs_property_comment":"","address":"","space_units":"м²","space_comment":"","region_hidden":true,"costs_property":"","region":"","address_hidden":true,"costs_rent_comment":"","space":"24.9","region_unclear":false,"costs_rent":""}]},"vehicle":{"35":[{"sum_comment":"","brand_info":"1591 куб. см.","brand_unclear":false,"sum_rent_comment":"","year":"2012","brand":"Hyundai Accent","sum_rent":"","brand_info_unclear":false,"sum":""}],"40":[{"sum_comment":"","brand_info":"5999 куб. см.","sum":"","sum_rent_comment":"","year":"2002","brand":"Mercedes-Benz","sum_rent":""},{"sum_comment":"","brand_info":"3456 куб. см.","sum":"","sum_rent_comment":"","year":"2014","brand":"Toyota Highlander","sum_rent":"","brand_info_unclear":false}]},"source":"VULYK","income":{"5":{"family_comment":"","family":"210933","comment":"","value_unclear":false,"family_unclear":false,"value":"122214"},"6":{"family_comment":"","value":"92572","family":"189804","comment":"","value_unclear":false},"7":{"family":"","family_comment":"","value":"","comment":"","source_name":""},"8":{"family_comment":"","value":"","family":"","comment":""},"9":{"family_comment":"","value":"11582","family":"11129","comment":"","value_unclear":false},"10":{"family_comment":"","value":"","family":"","comment":""},"11":{"family_comment":"","value":"","family":"","comment":""},"12":{"family_comment":"","value":"","family":"","comment":""},"13":{"family_comment":"","value":"","family":"","comment":""},"14":{"family_comment":"","value":"","family":"","comment":""},"15":{"family_comment":"","value":"","family":"","comment":""},"16":{"family_comment":"","value":"","family":"","comment":""},"17":{"family_comment":"","value":"","family":"","comment":""},"18":{"family_comment":"","value":"","family":"10000","comment":""},"19":{"family_comment":"","value":"","family":"","comment":""},"20":{"family_comment":"","value":"18060","family":"","comment":"","value_unclear":false}},"banks":{"45":[{"sum_units":"UAH","sum_comment":"","sum_foreign_units":"UAH","sum_hidden":false,"sum":"370614","sum_foreign_comment":"","sum_foreign":"","sum_unclear":false,"sum_comment_hidden":true}],"51":[{"sum_units":"UAH","sum_comment":"","sum_foreign_units":"UAH","sum_hidden":false,"sum":"356499","sum_foreign_comment":"","sum_foreign":"","sum_unclear":false,"sum_comment_hidden":true}],"53":[{"sum_units":"UAH","sum_comment":"","sum_foreign_units":"UAH","sum":"11500","sum_foreign_comment":"","sum_foreign":"","sum_unclear":false,"sum_comment_hidden":true}]},"declaration":{"date":"2015-03-30T00:00:00","url":"http://static.declarations.com.ua/declarations/chosen_ones/judges_batch/4494_shapovalova_tetiana_mykhailivna.pdf"},"general":{"family":[{"inn":"","family_name":"Шаповалов А. С","relations_other":"","name_unclear":false,"inn_hidden":true,"name_hidden":true,"relations":"Подружжя"},{"inn":"","family_name":"Шаповалова Є. А","relations_other":"","name_unclear":false,"inn_hidden":false,"name_hidden":false,"relations":"Дитина"}],"family_raw":"","name":"Тетяна","full_name_suggest":{"input":["Шаповалова Тетяна Михайлівна","Тетяна Михайлівна Шаповалова","Тетяна Шаповалова"],"output":"Шаповалова Тетяна Михайлівна"},"patronymic":"Михайлівна","inn_hidden":true,"addresses":[{"place_city_type_hidden":true,"place_city_type":"","place_city_hidden":true,"place_hidden":true,"place_district":"","place_district_hidden":true,"place":"","place_address":"","place_address_hidden":true,"place_city":""}],"last_name_hidden":false,"patronymic_hidden":false,"inn":"","inn_unclear":false,"last_name":"Шаповалова","full_name":"Шаповалова Тетяна Михайлівна","post":{"office":"Адміністративний місцевий суд","region":"Вінницька область","post_unclear":false,"post":"суддя вінницького окружного адміністративного суду"},"last_name_unclear":false},"liabilities":{"54":{"sum_comment_unclear":false,"sum_comment":"","sum_hidden":false,"sum":"","sum_foreign_comment":"","sum_foreign":"","sum_unclear":false,"sum_comment_hidden":false},"55":{"sum_comment":"","sum_foreign_comment":"","sum_foreign":"","sum":""},"56":{"sum_comment":"","sum_foreign_comment":"","sum_foreign":"","sum_unclear":false,"sum":""},"57":{"sum_comment_unclear":false,"sum_comment":"","sum_hidden":false,"sum":"","sum_foreign_comment":"","sum_foreign":"","sum_unclear":false,"sum_comment_hidden":false},"58":{"sum_comment":"","sum_hidden":false,"sum":"","sum_foreign_comment":"","sum_foreign":"","sum_unclear":false,"sum_comment_hidden":false},"59":{"sum_comment":"","sum_comment_unclear":false,"sum_foreign_comment":"","sum":"","sum_foreign":""},"60":{"sum_comment":"","sum_hidden":false,"sum":"","sum_foreign_comment":"","sum_foreign":"","sum_comment_hidden":false},"61":{"sum_comment":"","sum_foreign_comment":"","sum_foreign":"","sum":""},"62":{"sum_comment":"","sum":"","sum_foreign_comment":"","sum_foreign":"","sum_unclear":false,"sum_comment_hidden":false},"63":{"sum_comment_unclear":false,"sum_comment":"","sum":"","sum_foreign_comment":"","sum_foreign":"","sum_comment_hidden":false},"64":{"sum_comment":"","sum_foreign_comment":"","sum_foreign":"","sum":"","sum_comment_hidden":false}},"intro":{"declaration_year":"2014"}}