{"income":{"5":{"value":"292015","value_unclear":false,"family_hidden":false,"family_comment":"","family":"61167","comment":""},"6":{"family_comment":"","value":"277399","value_unclear":false,"family":"61109","comment":""},"7":{"source_name_unclear":false,"value":"","family_comment":"","source_name":"","family":"","comment":"","source_name_hidden":false},"8":{"family_comment":"","value":"","family":"","comment":""},"9":{"family_comment":"","value":"","comment_unclear":false,"family":"","comment":""},"10":{"family_comment":"","value":"14616","family":"","comment":""},"11":{"family_comment":"","family_unclear":false,"value":"","family":"58","comment":""},"12":{"family_comment":"","value":"","family":"","comment":""},"13":{"family_comment":"","value":"","family":"","comment":""},"14":{"family_comment":"","value":"","family":"","comment":""},"15":{"family_comment":"","value":"","family":"","comment":""},"16":{"family_comment":"","value":"","family":"","comment":""},"17":{"family_comment":"","value":"","family":"","comment":""},"18":{"family_comment":"","value":"","family":"","comment":""},"19":{"family_comment":"","value":"","family":"","comment":""},"20":{"value":"","value_unclear":false,"family_comment":"","comment_unclear":false,"comment":"","family":""}},"id":"vulyk_94_40","declaration":{"additional_info_text":"","notfull_lostpages":"","date":"2015-03-25T00:00:00","notfull":"","additional_info":"","url":"http://static.declarations.com.ua/declarations/chosen_ones/judges_batch/3686_oleksiienko_mykola_mykolaiovych.pdf"},"liabilities":{"54":{"sum_foreign_comment":"","sum":"","sum_comment":"","sum_comment_unclear":false,"sum_comment_hidden":false,"sum_unclear":false,"sum_foreign":""},"55":{"sum_foreign_comment":"","sum":"","sum_comment":"","sum_foreign":""},"56":{"sum_foreign_comment":"","sum":"7509","sum_comment":"","sum_unclear":false,"sum_foreign":""},"57":{"sum_foreign_comment":"","sum":"5757","sum_comment":"","sum_hidden":false,"sum_unclear":false,"sum_foreign":""},"58":{"sum_foreign_comment":"","sum":"1817","sum_comment":"","sum_hidden":false,"sum_unclear":true,"sum_foreign":""},"59":{"sum_foreign_comment":"","sum":"19400","sum_comment":"юридична академія","sum_foreign":""},"60":{"sum_foreign_comment":"","sum_comment_hidden":false,"sum":"","sum_comment":"","sum_foreign":""},"61":{"sum_foreign_comment":"","sum":"","sum_comment":"","sum_foreign":""},"62":{"sum_foreign_comment":"","sum":"5945","sum_hidden":false,"sum_comment":"","sum_foreign":""},"63":{"sum_foreign_comment":"","sum_comment_hidden":false,"sum":"9105","sum_comment":"","sum_foreign":""},"64":{"sum_foreign_comment":"","sum":"2391","sum_comment":"","sum_unclear":false,"sum_foreign":""}},"ft_src":"юридична академія\n19400\n5757\n5945\n1817\n9105\n7509\n2391\nсуддя вищого адміністративного суду україни\nЗагальнодержавний регіон\nВищий адміністративний суд України\nМикола\nПодружжя\nДитина\nДитина\nМиколайович\nОлексієнко Микола Миколайович\nМикола Миколайович Олексієнко\nМикола Олексієнко\nОлексієнко Микола Миколайович\nОлексієнко Микола Миколайович\nОлексієнко\n58\n14616\n292015\n61167\n61109\n277399\n189.3\nоренда\n98.4\n2014\n61109\n277399\n58\n14616\n61167\n292015\n189.3\n98.4\nоренда\nПодружжя\nДитина\nДитина\nОлексієнко Микола Миколайович\nМикола Миколайович Олексієнко\nМикола Олексієнко\nОлексієнко Микола Миколайович\nОлексієнко Микола Миколайович\nМикола\nМиколайович\nВищий адміністративний суд України\nЗагальнодержавний регіон\nсуддя вищого адміністративного суду україни\nОлексієнко\nюридична академія\n19400\n1817\n5757\n7509\n5945\n9105\n2391\n277399\n61109\n292015\n61167\n58\n14616\n2014\n1817\n5757\n7509\n5945\nюридична академія\n19400\n9105\n2391\nПодружжя\nДитина\nДитина\nМиколайович\nОлексієнко\nМикола\nОлексієнко Микола Миколайович\nМикола Миколайович Олексієнко\nМикола Олексієнко\nОлексієнко Микола Миколайович\nЗагальнодержавний регіон\nВищий адміністративний суд України\nсуддя вищого адміністративного суду україни\nОлексієнко Микола Миколайович\n189.3\nоренда\n98.4\n2014","general":{"inn":"","name":"Микола","last_name":"Олексієнко","family":[{"inn":"","relations":"Подружжя","relations_hidden":false,"inn_hidden":true,"family_name":"","name_hidden":true,"name_unclear":false},{"inn":"","relations":"Дитина","relations_unclear":false,"family_name":"","inn_hidden":false,"relations_other":"","name_hidden":false,"name_unclear":false},{"inn":"","relations":"Дитина","relations_unclear":false,"family_name":"","inn_hidden":false,"relations_other":"","name_hidden":false,"name_unclear":false}],"inn_hidden":true,"family_raw":"","inn_unclear":false,"post":{"post_unclear":false,"region_unclear":false,"post":"суддя вищого адміністративного суду україни","candidate":"","post_hidden":false,"region":"Загальнодержавний регіон","office":"Вищий адміністративний суд України","office_unclear":false},"full_name":"Олексієнко Микола Миколайович","addresses":[{"place_district":"","place_address_hidden":true,"place_city":"","place_city_type_hidden":true,"place_district_hidden":true,"place_city_type":"","place_city_hidden":true,"place_address":"","place_hidden":true,"place":""}],"patronymic":"Миколайович","patronymic_hidden":false,"full_name_suggest":{"output":"Олексієнко Микола Миколайович","input":["Олексієнко Микола Миколайович","Микола Миколайович Олексієнко","Микола Олексієнко"]}},"source":"VULYK","estate":{"25":[{"region_unclear":false,"space_unclear":false,"costs":"","costs_comment":"","address_hidden":true,"region_hidden":true,"space_comment":"оренда","space_hidden":false,"space":"98.4","address":"","region":"","address_unclear":false,"costs_rent_comment":"","costs_rent_hidden":false,"space_comment_unclear":false,"costs_rent_comment_hidden":false,"space_units":"м²","costs_rent":""}],"30":[{"space_hidden":false,"address_hidden":true,"region_hidden":true,"space_comment":"","space":"189.3","address":"","region":"","costs_property":"","costs_rent_comment":"","space_units":"м²","costs_property_comment":"","costs_rent":""}]},"intro":{"declaration_year":"2014","isnotdeclaration":""}}