{"id":"vulyk_89_5","ft_src":"1596.59.5 , 404\n2008\nВАЗ 1117\n28\n49.6\n2014\n27794\n240823\n735\nНаціональна школа суддів України\n27794\n241558\n1596.59.5 , 404\nВАЗ 1117\n2008\n2014\nВолодимирович\nГайдар О. А\nПодружжя\nДитина\nГайдар М. А\nГайдар Андрій Володимирович\nАндрій Володимирович Гайдар\nАндрій Гайдар\nГайдар Андрій Володимирович\nГайдар Андрій Володимирович\nАндрій\nГайдар\nДонецька область\nсуддя донецького апеляційного адміністративного суду\nАпеляційний адміністративний суд\n735\nНаціональна школа суддів України\n240823\n27794\n241558\n27794\n28\n49.6\nГайдар О. А\nПодружжя\nГайдар М. А\nДитина\nВолодимирович\nГайдар\nсуддя донецького апеляційного адміністративного суду\nДонецька область\nАпеляційний адміністративний суд\nГайдар Андрій Володимирович\nГайдар Андрій Володимирович\nАндрій Володимирович Гайдар\nАндрій Гайдар\nГайдар Андрій Володимирович\nАндрій","estate":{"25":[{"address":"","space_units":"м²","costs_comment":"","region_hidden":true,"space_comment":"","address_hidden":true,"costs":"","space_comment_unclear":false,"costs_rent_comment":"","space":"49.6","region":"","costs_rent":""}],"27":[{"costs":"","address":"","space_units":"м²","costs_rent_comment":"","space":"28","space_comment":"","region_hidden":true,"costs_comment":"","region":"","address_hidden":true,"costs_rent":""}]},"vehicle":{"35":[{"sum_comment":"","brand_info":"1596.59.5 , 404","sum":"","sum_rent_comment":"","year":"2008","brand":"ВАЗ 1117","sum_rent":""}]},"source":"VULYK","income":{"5":{"family":"27794","family_comment":"","comment":"","value_hidden":false,"family_hidden":false,"value":"241558"},"6":{"family_comment":"","value":"240823","family":"27794","comment":""},"7":{"family":"","family_comment":"","value":"735","comment":"","source_name":"Національна школа суддів України"},"8":{"family_comment":"","value":"","family":"","comment":""},"9":{"family_comment":"","value":"","family":"","comment":""},"10":{"family_comment":"","value":"","family":"","comment":""},"11":{"family_comment":"","value":"","family":"","comment":""},"12":{"family_comment":"","value":"","family":"","comment":""},"13":{"family_comment":"","value":"","family":"","comment":""},"14":{"family_comment":"","value":"","family":"","comment":""},"15":{"family_comment":"","value":"","family":"","comment":""},"16":{"family_comment":"","value":"","family":"","comment":""},"17":{"family_comment":"","value":"","family":"","comment":""},"18":{"family_comment":"","value":"","family":"","comment":""},"19":{"family_comment":"","value":"","family":"","comment":""},"20":{"family_comment":"","value":"","family":"","comment":""}},"general":{"inn":"","addresses":[{"place_city_type_hidden":true,"place_city_type":"","place_city_hidden":true,"place_hidden":true,"place_district":"","place_district_hidden":true,"place":"","place_address":"","place_address_hidden":true,"place_city":""}],"last_name":"Гайдар","full_name":"Гайдар Андрій Володимирович","family":[{"inn":"","name_hidden":true,"family_name":"Гайдар О. А","inn_hidden":true,"relations":"Подружжя"},{"inn":"","family_name":"Гайдар М. А","relations_other":"","name_unclear":false,"inn_hidden":true,"name_hidden":true,"relations":"Дитина"}],"patronymic":"Володимирович","inn_hidden":true,"name":"Андрій","post":{"office":"Апеляційний адміністративний суд","region":"Донецька область","post":"суддя донецького апеляційного адміністративного суду"},"family_raw":"","full_name_suggest":{"input":["Гайдар Андрій Володимирович","Андрій Володимирович Гайдар","Андрій Гайдар"],"output":"Гайдар Андрій Володимирович"}},"liabilities":{"54":{"sum_comment":"","sum_foreign_comment":"","sum_foreign":"","sum":""},"55":{"sum_comment":"","sum_foreign_comment":"","sum_foreign":"","sum":""},"56":{"sum_comment":"","sum_foreign_comment":"","sum_foreign":"","sum_unclear":false,"sum":""},"57":{"sum_comment":"","sum_foreign_comment":"","sum_foreign":"","sum":""},"58":{"sum_comment":"","sum_foreign_comment":"","sum_foreign":"","sum":""},"59":{"sum_comment":"","sum_foreign_comment":"","sum_foreign":"","sum":""},"60":{"sum_comment":"","sum_foreign_comment":"","sum_foreign":"","sum":""},"61":{"sum_comment":"","sum_foreign_comment":"","sum_foreign":"","sum":""},"62":{"sum_comment":"","sum_foreign_comment":"","sum_foreign":"","sum_unclear":false,"sum":""},"63":{"sum_comment":"","sum_foreign_comment":"","sum_foreign":"","sum":""},"64":{"sum_comment":"","sum_foreign_comment":"","sum_foreign":"","sum":""}},"declaration":{"notfull_lostpages":"","date":"2015-03-25T00:00:00","notfull":"","url":"http://static.declarations.com.ua/declarations/chosen_ones/judges_batch/3008_haidar_andrii_volodymyrovych.pdf"},"intro":{"declaration_year":"2014"}}