{"income":{"5":{"value":"355130","family_comment":"","value_unclear":false,"family_hidden":false,"value_hidden":false,"family_unclear":false,"family":"52295","comment":""},"6":{"value":"232515","family_comment":"","value_unclear":false,"family_hidden":false,"value_hidden":false,"family_unclear":false,"family":"47426","comment":""},"7":{"source_name_unclear":false,"value":"","comment_hidden":false,"family_hidden":false,"value_hidden":false,"family_comment":"","source_name":"","family":"","comment":"","source_name_hidden":false},"8":{"value":"","family_hidden":false,"value_hidden":false,"family_comment":"","family":"","comment":""},"9":{"value":"3000","family_hidden":false,"value_hidden":false,"family_comment":"","family":"","comment":""},"10":{"family_comment":"","value":"12180","family_hidden":false,"comment":"","family":"4869"},"11":{"value":"","comment_hidden":false,"family_hidden":false,"family_comment":"","family":"","comment":""},"12":{"value":"","family_hidden":false,"value_hidden":false,"family_comment":"","family":"","comment":""},"13":{"value":"","family_hidden":false,"value_hidden":false,"family_comment":"","family":"","comment":""},"14":{"value":"","family_hidden":false,"value_hidden":false,"family_comment":"","family":"","comment":""},"15":{"family_comment":"","value":"","family_hidden":false,"comment":"","family":""},"16":{"value":"","family_hidden":false,"value_hidden":false,"family_comment":"","family":"","comment":""},"17":{"family_comment":"","value":"","family":"","comment":"","value_hidden":false},"18":{"value":"","family_hidden":false,"value_hidden":false,"family_comment":"","family":"","comment":""},"19":{"value":"","family_hidden":false,"value_hidden":false,"family_comment":"","family":"","comment":""},"20":{"value":"119615","comment_unclear":false,"family_hidden":false,"value_hidden":false,"family_comment":"","family":"","comment":"повернення вкладу з банківської установи","family_comment_unclear":false}},"vehicle":{"35":[{"year_hidden":true,"brand_info":"2400 куб. см.","sum_rent_comment":"","sum_rent_hidden":false,"year":"","sum_hidden":false,"brand_info_hidden":false,"brand_info_unclear":false,"year_unclear":false,"sum_rent":"","sum_rent_unclear":false,"sum":"","brand":"Chevrolet Captiva","sum_comment":"","brand_unclear":false,"brand_hidden":false,"sum_unclear":false}]},"id":"vulyk_34_15","banks":{"45":[{"sum_foreign_comment":"","sum_units":"UAH","sum_comment":"","sum_foreign_units":"UAH","sum_comment_hidden":false,"sum_unclear":false,"sum":"","sum_foreign":""},{"sum_foreign_comment":"","sum_units":"","sum_comment":"","sum_foreign_units":"","sum_comment_hidden":false,"sum":"","sum_foreign":""}],"46":[{"sum_foreign_comment":"","sum_units":"UAH","sum_comment":"","sum_foreign_units":"UAH","sum_comment_hidden":false,"sum_unclear":false,"sum":"","sum_foreign":""},{"sum_foreign_comment":"","sum_units":"","sum_comment":"","sum_foreign_units":"","sum_comment_hidden":false,"sum":"","sum_foreign":""}],"47":[{"sum_foreign_comment":"","sum_units":"UAH","sum_comment":"","sum_foreign_units":"UAH","sum":"","sum_foreign":""}],"48":[{"sum_foreign_comment":"","sum_units":"UAH","sum_comment":"","sum_foreign_units":"UAH","sum":"","sum_foreign":""}],"49":[{"sum_foreign_comment":"","sum_units":"UAH","sum_comment":"","sum_hidden":false,"sum_foreign_units":"UAH","sum":"","sum_foreign":""}],"50":[{"sum_foreign_comment":"","sum_units":"UAH","sum_comment":"","sum_hidden":false,"sum_foreign_units":"UAH","sum":"","sum_foreign":""}],"51":[{"sum_foreign_comment":"","sum_units":"UAH","sum_comment":"","sum_hidden":false,"sum_foreign_units":"UAH","sum_comment_hidden":false,"sum_unclear":false,"sum":"","sum_foreign":""},{"sum_foreign_comment":"","sum_units":"","sum_comment":"","sum_foreign_units":"","sum_comment_hidden":false,"sum":"","sum_foreign":""}],"52":[{"sum_foreign_comment":"","sum_units":"UAH","sum_comment":"","sum_foreign_units":"UAH","sum":"","sum_foreign":""}],"53":[{"sum_foreign_comment":"","sum_units":"UAH","sum_comment":"","sum_foreign_units":"UAH","sum":"","sum_foreign":""}]},"declaration":{"additional_info_text":"","notfull_lostpages":"","date":"2015-03-26T00:00:00","notfull":"","additional_info":"","url":"http://static.declarations.com.ua/declarations/chosen_ones/mega_batch/halychanskyi_oleh_ivanovych.pdf"},"liabilities":{"54":{"sum_foreign_comment":"","sum_foreign_hidden":false,"sum_comment":"","sum_hidden":false,"sum_comment_hidden":false,"sum":"400","sum_foreign":""},"55":{"sum_foreign_comment":"","sum_foreign_hidden":false,"sum_comment":"","sum_hidden":false,"sum":"","sum_foreign":""},"56":{"sum_foreign_comment":"","sum_foreign_hidden":false,"sum_comment":"","sum":"20000","sum_unclear":false,"sum_foreign":""},"57":{"sum_foreign_comment":"","sum_foreign_hidden":false,"sum_comment":"","sum_hidden":false,"sum_comment_hidden":false,"sum_unclear":false,"sum":"1700","sum_foreign":""},"58":{"sum_foreign_comment":"","sum_foreign_hidden":false,"sum_comment":"","sum_hidden":false,"sum_comment_hidden":false,"sum_unclear":false,"sum":"","sum_foreign":""},"59":{"sum_foreign_comment":"","sum_foreign_hidden":false,"sum_comment":"","sum_hidden":false,"sum":"","sum_foreign":""},"60":{"sum_foreign_comment":"","sum_foreign_hidden":false,"sum_comment":"","sum_hidden":false,"sum":"","sum_foreign":""},"61":{"sum_foreign_comment":"","sum_foreign_hidden":false,"sum_comment":"","sum_hidden":false,"sum":"","sum_foreign":""},"62":{"sum_foreign_comment":"","sum_foreign_hidden":false,"sum_comment":"","sum":"","sum_unclear":false,"sum_foreign":""},"63":{"sum_foreign_comment":"","sum_foreign_hidden":false,"sum_comment":"","sum_hidden":false,"sum":"","sum_unclear":false,"sum_foreign":""},"64":{"sum_foreign_comment":"","sum_foreign_hidden":false,"sum_comment":"","sum_comment_unclear":false,"sum_hidden":false,"sum_comment_hidden":false,"sum_unclear":false,"sum":"","sum_foreign":""}},"ft_src":"1700\n400\n20000\nЧернівці\nЧернівецька область\nсуддя першотравневого районного суду м. чернівці\nЧернівецька область\nЗагальний місцевий суд\nОлег\nМрачковська К. І\nПодружжя\nГаличанський Н. О., 17. 02. 1999р. н\nДитина\nГаличанська О. О., 02. 08. 01\nДитина\nІванович\nГаличанський\nГаличанський Олег Іванович\nГаличанський Олег Іванович\nОлег Іванович Галичанський\nОлег Галичанський\nГаличанський Олег Іванович\n2400 куб. см.\nChevrolet Captiva\n2014\n2400 куб. см.\nChevrolet Captiva\n.08\nЧернівецька область\n1/4 від 72,5 кв. м\nЧернівецька область\n18.13\nм. Чернівці\nспадок\n42.8\nЧернівецька область\nм. Чернівці,\n72.5\nспадок\nм. Чернівці,\nЧернівецька область\nПодружжя\nМрачковська К. І\nДитина\nГаличанський Н. О., 17. 02. 1999р. н\nДитина\nГаличанська О. О., 02. 08. 01\nГаличанський Олег Іванович\nОлег Іванович Галичанський\nОлег Галичанський\nГаличанський Олег Іванович\nОлег\nГаличанський Олег Іванович\nГаличанський\nЗагальний місцевий суд\nЧернівецька область\nсуддя першотравневого районного суду м. чернівці\nІванович\nЧернівецька область\nЧернівці\n1700\n20000\n400\n232515\n47426\nповернення вкладу з банківської установи\n119615\n52295\n355130\n12180\n4869\n3000\n2014\n1700\n20000\n400\n.08\nЧернівецька область\n1/4 від 72,5 кв. м\nЧернівецька область\nм. Чернівці\n18.13\nспадок\n42.8\nм. Чернівці,\nЧернівецька область\nспадок\nм. Чернівці,\n72.5\nЧернівецька область\nМрачковська К. І\nПодружжя\nГаличанський Н. О., 17. 02. 1999р. н\nДитина\nГаличанська О. О., 02. 08. 01\nДитина\nІванович\nГаличанський\nГаличанський Олег Іванович\nОлег Іванович Галичанський\nОлег Галичанський\nГаличанський Олег Іванович\nЧернівці\nЧернівецька область\nЧернівецька область\nЗагальний місцевий суд\nсуддя першотравневого районного суду м. чернівці\nГаличанський Олег Іванович\nОлег\n47426\n232515\n4869\n12180\n52295\n355130\n3000\nповернення вкладу з банківської установи\n119615\nChevrolet Captiva\n2400 куб. см.\n4869\n12180\n119615\nповернення вкладу з банківської установи\n355130\n52295\n3000\n232515\n47426\nЧернівецька область\n1/4 від 72,5 кв. м\nм. Чернівці\n18.13\nЧернівецька область\n.08\nспадок\nм. Чернівці,\nЧернівецька область\n42.8\nспадок\nЧернівецька область\nм. Чернівці,\n72.5\n2014","general":{"inn":"","name":"Олег","patronymic_unclear":false,"family":[{"inn":"","inn_hidden":true,"relations_unclear":false,"relations_hidden":false,"relations_other":"","relations":"Подружжя","name_hidden":false,"family_name":"Мрачковська К. І","name_unclear":false},{"inn":"","inn_hidden":true,"relations_hidden":false,"family_name":"Галичанський Н. О., 17. 02. 1999р. н","relations_other":"","relations":"Дитина","name_hidden":false,"name_unclear":false},{"inn":"","relations":"Дитина","relations_other":"","inn_hidden":true,"family_name":"Галичанська О. О., 02. 08. 01","name_hidden":false,"name_unclear":false}],"patronymic":"Іванович","inn_hidden":true,"family_raw":"","inn_unclear":false,"post":{"post_unclear":false,"region_unclear":false,"post":"суддя першотравневого районного суду м. чернівці","office":"Загальний місцевий суд","region":"Чернівецька область","post_hidden":false,"office_hidden":false,"office_unclear":false,"region_hidden":false},"last_name_unclear":false,"full_name":"Галичанський Олег Іванович","addresses":[{"place_district":"","place_address_hidden":true,"place_city":"Чернівці","place_city_type_hidden":false,"place_district_hidden":false,"place_city_type":"Місто","place_city_hidden":false,"place_address_unclear":false,"place_address":"","place_hidden":false,"place":"Чернівецька область"}],"last_name":"Галичанський","patronymic_hidden":false,"full_name_suggest":{"output":"Галичанський Олег Іванович","input":["Галичанський Олег Іванович","Олег Іванович Галичанський","Олег Галичанський"]},"name_unclear":false},"source":"VULYK","estate":{"23":[{"space_unclear":false,"costs":"","costs_comment":"","costs_hidden":false,"address_hidden":true,"region_hidden":false,"space_comment":"","space_hidden":false,"space":".08","address":"","region":"Чернівецька область","address_unclear":false,"space_units_unclear":false,"costs_rent_hidden":false,"costs_unclear":false,"space_units":"га","costs_rent":"","costs_rent_comment":""},{"costs_rent":"","region":"","costs":"","costs_rent_comment":"","costs_comment":"","address_hidden":false,"region_hidden":false,"space_comment":"","space_units":"","space":"","address":""},{"costs_rent":"","region":"","costs":"","costs_rent_comment":"","costs_comment":"","space_comment":"","space_units":"","space":"","address":""},{"costs_rent":"","region":"","costs":"","costs_rent_comment":"","costs_comment":"","space_comment":"","space_units":"","space":"","address":""}],"25":[{"region_unclear":false,"space_unclear":false,"costs":"","costs_comment":"","costs_hidden":false,"address_hidden":true,"region_hidden":false,"space_comment":"спадок","space_hidden":false,"space":"42.8","address":"м. Чернівці,","costs_rent_comment_unclear":false,"region":"Чернівецька область","address_unclear":false,"costs_rent_comment":"","costs_rent_hidden":false,"space_comment_unclear":false,"space_units":"м²","costs_rent":""},{"costs_rent":"","region":"Чернівецька область","costs":"","costs_rent_comment":"","costs_comment":"","address_hidden":false,"region_hidden":false,"space_comment":"спадок","space_units":"м²","space":"72.5","address":"м. Чернівці,"}],"31":[{"region_unclear":false,"space_hidden":false,"costs_property_hidden":false,"address_hidden":true,"region_hidden":false,"space_comment":"1/4 від 72,5 кв. м","space_unclear":false,"space":"18.13","address":"м. Чернівці","region":"Чернівецька область","costs_property":"","costs_rent_comment":"","costs_rent_hidden":false,"space_comment_unclear":false,"space_units":"м²","costs_property_comment":"","costs_rent":""}]},"intro":{"declaration_year":"2014","isnotdeclaration":"","declaration_year_unclear":false}}