{"income":{"5":{"value":"181736.04","value_unclear":false,"family_hidden":false,"family_comment":"","family":"","comment":""},"6":{"family_comment":"","value":"181736.04","value_unclear":false,"family":"","comment":""},"7":{"source_name_unclear":false,"value":"","family_comment":"","source_name":"","family":"","comment":"","source_name_hidden":false},"8":{"family_comment":"","value":"","family":"","comment":""},"9":{"family_comment":"","value":"","comment_unclear":false,"family":"","comment":""},"10":{"family_comment":"","value":"","family":"","comment":""},"11":{"family_comment":"","family_unclear":false,"value":"","family":"","comment":""},"12":{"family_comment":"","value":"","family":"","comment":""},"13":{"family_comment":"","value":"","family":"","comment":""},"14":{"family_comment":"","value":"","family":"","comment":""},"15":{"family_comment":"","value":"","family":"","comment":""},"16":{"family_comment":"","value":"","family":"","comment":""},"17":{"family_comment":"","value":"","family":"","comment":""},"18":{"family_comment":"","value":"","family":"","comment":""},"19":{"family_comment":"","value":"","family":"","comment":""},"20":{"value":"","value_unclear":false,"family_comment":"","comment_unclear":false,"comment":"","family":""}},"vehicle":{"35":[{"year_hidden":false,"brand_info":"1591 куб. см.","sum_rent_comment":"","year":"2012","brand_info_hidden":false,"brand_info_unclear":false,"year_unclear":false,"sum_rent":"","sum":"","brand":"Hyundai i30","sum_comment":"у власності","brand_unclear":false,"brand_hidden":false}]},"id":"vulyk_94_79","declaration":{"additional_info_text":"","notfull_lostpages":"","date":"2015-03-31T00:00:00","notfull":"","additional_info":"","url":"http://static.declarations.com.ua/declarations/chosen_ones/judges_batch/3725_shchyhelska_olena_ihorivna.pdf"},"liabilities":{"54":{"sum_foreign_comment":"","sum":"9688.58","sum_comment":"","sum_comment_unclear":false,"sum_comment_hidden":false,"sum_unclear":false,"sum_foreign":""},"55":{"sum_foreign_comment":"","sum":"","sum_comment":"","sum_foreign":""},"56":{"sum_foreign_comment":"","sum":"","sum_comment":"","sum_unclear":false,"sum_foreign":""},"57":{"sum_foreign_comment":"","sum":"46201.76","sum_comment":"","sum_hidden":false,"sum_unclear":false,"sum_foreign":""},"58":{"sum_foreign_comment":"","sum":"4323.6","sum_comment":"","sum_hidden":false,"sum_unclear":false,"sum_foreign":""},"59":{"sum_foreign_comment":"","sum":"","sum_comment":"","sum_foreign":""},"60":{"sum_foreign_comment":"","sum_comment_hidden":false,"sum":"","sum_comment":"","sum_foreign":""},"61":{"sum_foreign_comment":"","sum":"","sum_comment":"","sum_foreign":""},"62":{"sum_foreign_comment":"","sum":"","sum_hidden":false,"sum_comment":"","sum_foreign":""},"63":{"sum_foreign_comment":"","sum_comment_hidden":false,"sum":"","sum_comment":"","sum_foreign":""},"64":{"sum_foreign_comment":"","sum":"","sum_comment":"","sum_unclear":false,"sum_foreign":""}},"ft_src":"46201.76\n9688.58\n4323.6\nсуддя господарського суду львівської області\nЛьвівська область\nГосподарський місцевий суд\nОлена\nІгорівна\nЩигельська Олена Ігорівна\nЩигельська\nЩигельська Олена Ігорівна\nОлена Ігорівна Щигельська\nОлена Щигельська\nЩигельська Олена Ігорівна\nу власності\n1591 куб. см.\nHyundai i30\n2012\n1/2 частина від 69,8 кв. м\n69.8\nкористування\n69.4\n2014\n181736.04\n181736.04\n1591 куб. см.\nHyundai i30\nу власності\n2012\n2014\nЩигельська Олена Ігорівна\nОлена Ігорівна Щигельська\nОлена Щигельська\nЩигельська Олена Ігорівна\nЩигельська Олена Ігорівна\nОлена\nІгорівна\nГосподарський місцевий суд\nЛьвівська область\nсуддя господарського суду львівської області\nЩигельська\n4323.6\n46201.76\n9688.58\n181736.04\n181736.04\n69.8\n1/2 частина від 69,8 кв. м\n69.4\nкористування\n4323.6\n46201.76\n9688.58\nІгорівна\nЩигельська\nОлена\nЩигельська Олена Ігорівна\nОлена Ігорівна Щигельська\nОлена Щигельська\nЩигельська Олена Ігорівна\nЛьвівська область\nГосподарський місцевий суд\nсуддя господарського суду львівської області\nЩигельська Олена Ігорівна\nHyundai i30\nу власності\n1591 куб. см.\n2012\n181736.04\n181736.04\n1/2 частина від 69,8 кв. м\n69.8\nкористування\n69.4\n2014","general":{"inn":"","name":"Олена","inn_unclear":false,"patronymic":"Ігорівна","inn_hidden":true,"family_raw":"","last_name":"Щигельська","post":{"post_unclear":false,"region_unclear":false,"post":"суддя господарського суду львівської області","candidate":"","post_hidden":false,"region":"Львівська область","office":"Господарський місцевий суд","office_unclear":false},"full_name":"Щигельська Олена Ігорівна","addresses":[{"place_district":"","place_address_hidden":false,"place_city":"","place_city_type_hidden":false,"place_district_hidden":false,"place_city_type":"","place_city_hidden":false,"place_address":"","place_hidden":true,"place":""}],"patronymic_hidden":false,"full_name_suggest":{"output":"Щигельська Олена Ігорівна","input":["Щигельська Олена Ігорівна","Олена Ігорівна Щигельська","Олена Щигельська"]}},"source":"VULYK","estate":{"25":[{"region_unclear":false,"space_unclear":false,"costs":"","costs_comment":"","address_hidden":false,"region_hidden":true,"space_comment":"1/2 частина від 69,8 кв. м","space_hidden":false,"space":"69.8","address":"","region":"","address_unclear":false,"costs_rent_comment":"","costs_rent_hidden":false,"space_comment_unclear":false,"costs_rent_comment_hidden":false,"space_units":"м²","costs_rent":""},{"costs_rent":"","region":"","costs":"","costs_rent_comment":"","costs_comment":"","region_hidden":false,"space_comment":"користування","space_units":"м²","space":"69.4","address":""}]},"intro":{"declaration_year":"2014","isnotdeclaration":""}}