{"income":{"5":{"value":"240748.66","family_comment":"","value_unclear":false,"family_hidden":false,"value_hidden":false,"family_unclear":false,"comment_unclear":false,"comment":"","family":"1440"},"6":{"value":"228568.66","family_comment":"","value_unclear":false,"family_hidden":false,"value_hidden":false,"family_unclear":false,"comment_unclear":false,"comment":"","family":"1440"},"7":{"source_name_unclear":false,"value":"","family_comment":"","source_name":"","family":"","comment":""},"8":{"family_comment":"","value":"","family":"","comment":""},"9":{"value":"","value_unclear":false,"comment_hidden":false,"family_comment":"","comment_unclear":false,"comment":"","family":""},"10":{"value":"12180","comment_unclear":false,"value_hidden":false,"family_comment":"","family":"","comment":""},"11":{"family_comment":"","value":"","family":"","comment":""},"12":{"family_comment":"","value":"","family":"","comment":""},"13":{"family_comment":"","value":"","family":"","comment":""},"14":{"family_comment":"","value":"","family":"","comment":""},"15":{"family_comment":"","value":"","family":"","comment":""},"16":{"family_comment":"","value":"","family":"","comment":""},"17":{"family_comment":"","value":"","family":"","comment":""},"18":{"value":"","family_hidden":false,"value_hidden":false,"family_comment":"","family":"","comment":""},"19":{"family_comment":"","value":"1882.78","family":"","comment":"зем. ділянка 2 га"},"20":{"value":"","family_comment":"","value_unclear":false,"family_hidden":false,"value_hidden":false,"family_unclear":false,"family":"","comment":""}},"id":"vulyk_66_13","declaration":{"additional_info_text":"","notfull_lostpages":"","date":"2015-03-31T00:00:00","notfull":"","additional_info":"","url":"http://static.declarations.com.ua/declarations/chosen_ones/mega_batch/tykhonenko_mykhailo_ivanovych.pdf"},"liabilities":{"54":{"sum_foreign_comment":"","sum":"","sum_comment":"","sum_comment_unclear":false,"sum_comment_hidden":false,"sum_unclear":false,"sum_foreign":""},"55":{"sum_foreign_comment":"","sum":"","sum_comment":"","sum_foreign":""},"56":{"sum_foreign_comment":"","sum_foreign_hidden":false,"sum_comment":"","sum_hidden":false,"sum_comment_hidden":false,"sum":"","sum_foreign":""},"57":{"sum_foreign_comment":"","sum":"","sum_comment":"","sum_comment_unclear":false,"sum_hidden":false,"sum_comment_hidden":false,"sum_unclear":false,"sum_foreign":""},"58":{"sum_foreign_comment":"","sum":"","sum_comment":"","sum_comment_unclear":false,"sum_unclear":false,"sum_foreign":""},"59":{"sum_foreign_comment":"","sum_foreign_hidden":false,"sum_comment":"","sum_comment_unclear":false,"sum_hidden":false,"sum":"","sum_foreign":""},"60":{"sum_foreign_comment":"","sum":"","sum_comment":"","sum_comment_unclear":false,"sum_foreign":""},"61":{"sum_foreign_comment":"","sum":"","sum_comment":"","sum_foreign":""},"62":{"sum_foreign_comment":"","sum_foreign_hidden":false,"sum_comment":"","sum_hidden":false,"sum":"","sum_unclear":false,"sum_foreign":""},"63":{"sum_foreign_comment":"","sum":"","sum_comment":"","sum_comment_unclear":false,"sum_comment_hidden":false,"sum_unclear":false,"sum_foreign":""},"64":{"sum_foreign_comment":"","sum":"","sum_comment":"","sum_comment_unclear":false,"sum_foreign":""}},"ft_src":"суддя врадіївського районного суду миколаївської області\nМиколаївська область\nЗагальний місцевий суд\nМихайло\nПодружжя\nІванович\nТихоненко Михайло Іванович\nМихайло Іванович Тихоненко\nМихайло Тихоненко\nТихоненко Михайло Іванович\nТихоненко Михайло Іванович\nТихоненко\nзем. ділянка 2 га\n1882.78\n12180\n240748.66\n1440\n228568.66\n1440\n2014\n1440\n228568.66\n12180\n1440\n240748.66\nзем. ділянка 2 га\n1882.78\nЗагальний місцевий суд\nсуддя врадіївського районного суду миколаївської області\nМиколаївська область\nПодружжя\nТихоненко Михайло Іванович\nМихайло Іванович Тихоненко\nМихайло Тихоненко\nТихоненко Михайло Іванович\nТихоненко Михайло Іванович\nМихайло\nТихоненко\nІванович\n228568.66\n1440\n240748.66\n1440\n12180\n1882.78\nзем. ділянка 2 га\n2014\nПодружжя\nІванович\nТихоненко\nМихайло\nТихоненко Михайло Іванович\nМихайло Іванович Тихоненко\nМихайло Тихоненко\nТихоненко Михайло Іванович\nМиколаївська область\nсуддя врадіївського районного суду миколаївської області\nЗагальний місцевий суд\nТихоненко Михайло Іванович\n2014","general":{"inn":"","name":"Михайло","last_name_hidden":false,"family":[{"inn":"","inn_hidden":true,"relations_hidden":false,"family_name":"","relations_other":"","relations":"Подружжя","name_hidden":true,"name_unclear":false}],"patronymic":"Іванович","inn_hidden":false,"family_raw":"","inn_unclear":false,"post":{"post_unclear":false,"post":"суддя врадіївського районного суду миколаївської області","candidate":"","office_hidden":false,"region":"Миколаївська область","office":"Загальний місцевий суд","office_unclear":false},"full_name_suggest":{"output":"Тихоненко Михайло Іванович","input":["Тихоненко Михайло Іванович","Михайло Іванович Тихоненко","Михайло Тихоненко"]},"full_name":"Тихоненко Михайло Іванович","addresses":[{"place_city_type_unclear":false,"place_address":"","place_district_hidden":true,"place_city_type":"","place_address_hidden":true,"place_address_unclear":false,"place_city_type_hidden":true,"place":"","place_district":"","place_unclear":false,"place_city":"","place_city_unclear":false,"place_hidden":true,"place_city_hidden":true,"place_district_unclear":false}],"last_name":"Тихоненко","last_name_unclear":false},"source":"VULYK","estate":{"23":[{"space_unclear":false,"costs":"","costs_comment":"","costs_hidden":false,"address_hidden":false,"region_hidden":true,"space_comment":"","space_hidden":true,"space":"","space_units_hidden":false,"region":"","address_unclear":false,"space_units_unclear":false,"space_units":"м²","address":"","costs_rent":"","costs_rent_comment":""}],"25":[{"region_unclear":false,"space_hidden":true,"costs":"","costs_comment":"","costs_hidden":false,"address_hidden":false,"region_hidden":true,"space_comment":"","space_unclear":false,"space":"","space_units_hidden":false,"region":"","address_unclear":false,"costs_rent_comment":"","space_comment_unclear":false,"space_units":"м²","address":"","costs_rent":""}]},"intro":{"declaration_year":"2014","isnotdeclaration":"","declaration_year_unclear":true}}