{"income":{"5":{"family_comment":"","value":"253915","family":"185845","comment":""},"6":{"family_comment":"","value":"240331","value_unclear":false,"family":"143862","comment":""},"7":{"value":"","family_comment":"","source_name":"","family":"","comment":"","source_name_hidden":false},"8":{"family_comment":"","value":"","family":"","comment":""},"9":{"family_comment":"","value":"","family":"","comment":""},"10":{"family_comment":"","value":"13398","family":"","comment":""},"11":{"family_comment":"","value":"","comment_hidden":false,"family":"","comment":""},"12":{"family_comment":"","value":"","family":"","comment":""},"13":{"family_comment":"","value":"","family":"","comment":""},"14":{"family_comment":"","value":"","family":"","comment":""},"15":{"value":"","family_comment":"","value_unclear":false,"family_unclear":false,"family":"","comment":""},"16":{"family_comment":"","value":"","family":"","comment":""},"17":{"family_comment":"","value":"","family":"","comment":""},"18":{"family_comment":"","value":"","family":"","comment":""},"19":{"family_comment":"","value":"","family":"13513","comment":""},"20":{"family_comment":"","value":"222","comment_unclear":false,"family":"28470","comment":""}},"id":"vulyk_104_177","declaration":{"date":"2016-03-28T00:00:00","additional_info_text":"","additional_info":"","url":"http://static.declarations.com.ua/declarations/chosen_ones/judges_batch/1975_chornobryvets_olena_saveliivna_2015.pdf"},"liabilities":{"54":{"sum_foreign_comment":"","sum_foreign_hidden":false,"sum_comment":"","sum_hidden":false,"sum_comment_hidden":false,"sum_unclear":false,"sum":"","sum_foreign":""},"55":{"sum_foreign_comment":"","sum":"","sum_comment":"","sum_foreign":""},"56":{"sum_foreign_comment":"","sum":"","sum_comment":"","sum_unclear":false,"sum_foreign":""},"57":{"sum_foreign_comment":"","sum_foreign_hidden":false,"sum_comment":"відділення №1 ПУМБ м. Кіровоград","sum_comment_unclear":false,"sum_comment_hidden":false,"sum":"5532","sum_foreign":""},"58":{"sum_foreign_comment":"","sum":"5932","sum_comment":"відділення №1 ПУМБ м. Кіровоград","sum_unclear":false,"sum_foreign":""},"59":{"sum_foreign_comment":"","sum":"","sum_comment":"","sum_foreign":""},"60":{"sum_foreign_comment":"","sum_foreign_hidden":false,"sum_comment":"","sum_comment_hidden":false,"sum":"","sum_foreign":""},"61":{"sum_foreign_comment":"","sum":"","sum_comment":"","sum_foreign":""},"62":{"sum_foreign_comment":"","sum":"","sum_comment":"","sum_foreign":""},"63":{"sum_foreign_comment":"","sum":"5532","sum_comment":"відділення №1 ПУМБ м. Кіровоград","sum_foreign":""},"64":{"sum_foreign_comment":"","sum":"5941","sum_comment":"відділення №1 ПУМБ м. Кіровоград","sum_foreign":""}},"ft_src":"відділення №1 ПУМБ м. Кіровоград\n5532\nвідділення №1 ПУМБ м. Кіровоград\n5932\nвідділення №1 ПУМБ м. Кіровоград\n5532\nвідділення №1 ПУМБ м. Кіровоград\n5941\nЧорнобривець Олена Савеліївна\nсуддя апеляційного суду кіровоградської області\nКіровоградська область\nЗагальний апеляційний суд\nОлена\nЧорнобривець В. П. 03. 11. 1957\nПодружжя\nЧорнобривець Олена Савеліївна\nОлена Савеліївна Чорнобривець\nОлена Чорнобривець\nЧорнобривець Олена Савеліївна\nЧорнобривець\nСавеліївна\n13513\n13398\n28470\n222\n185845\n253915\n143862\n240331\n29\n28\n247.3\n101\n28\n56\n1000\n1/2 частина\n101\n2015\n143862\n240331\n13398\n185845\n253915\n13513\n28470\n222\n240331\n143862\n222\n28470\n253915\n185845\n13398\n13513\nПодружжя\nЧорнобривець В. П. 03. 11. 1957\nЧорнобривець\nЧорнобривець Олена Савеліївна\nОлена Савеліївна Чорнобривець\nОлена Чорнобривець\nЧорнобривець Олена Савеліївна\nЧорнобривець Олена Савеліївна\nОлена\nСавеліївна\nЗагальний апеляційний суд\nсуддя апеляційного суду кіровоградської області\nКіровоградська область\nвідділення №1 ПУМБ м. Кіровоград\n5932\nвідділення №1 ПУМБ м. Кіровоград\n5532\n5532\nвідділення №1 ПУМБ м. Кіровоград\nвідділення №1 ПУМБ м. Кіровоград\n5941\n28\n56\n101\n1/2 частина\n1000\n28\n247.3\n101\n29\n2015\nвідділення №1 ПУМБ м. Кіровоград\n5932\nвідділення №1 ПУМБ м. Кіровоград\n5532\nвідділення №1 ПУМБ м. Кіровоград\n5532\nвідділення №1 ПУМБ м. Кіровоград\n5941\nПодружжя\nЧорнобривець В. П. 03. 11. 1957\nСавеліївна\nЧорнобривець\nсуддя апеляційного суду кіровоградської області\nЗагальний апеляційний суд\nКіровоградська область\nЧорнобривець Олена Савеліївна\nЧорнобривець Олена Савеліївна\nОлена Савеліївна Чорнобривець\nОлена Чорнобривець\nЧорнобривець Олена Савеліївна\nОлена\n101\n1000\n247.3\n29\n28\n56\n1/2 частина\n101\n28\n2015","general":{"inn":"","inn_hidden":true,"last_name":"Чорнобривець","post":{"region":"Кіровоградська область","region_unclear":false,"post":"суддя апеляційного суду кіровоградської області","office_unclear":false,"office":"Загальний апеляційний суд"},"name":"Олена","full_name":"Чорнобривець Олена Савеліївна","family_raw":"","addresses":[{"place_district":"","place_city_hidden":true,"place_city":"","place_city_type_hidden":false,"place_district_hidden":false,"place_city_type":"","place_address_hidden":true,"place_address":"","place_hidden":true,"place":""}],"family":[{"inn":"","relations":"Подружжя","relations_other":"","inn_hidden":true,"family_name":"Чорнобривець В. П. 03. 11. 1957","name_hidden":false,"name_unclear":false}],"full_name_suggest":{"output":"Чорнобривець Олена Савеліївна","input":["Чорнобривець Олена Савеліївна","Олена Савеліївна Чорнобривець","Олена Чорнобривець"]},"patronymic":"Савеліївна"},"source":"VULYK","estate":{"23":[{"space_hidden":false,"costs":"","costs_comment":"","address_hidden":false,"region_hidden":true,"space_comment":"","space":"1000","address":"","region":"","costs_rent_comment":"","space_comment_unclear":false,"space_units":"м²","costs_rent":""}],"24":[{"space_hidden":false,"costs":"","costs_comment":"","address_hidden":false,"region_hidden":true,"space_comment":"","space":"247.3","address":"","region":"","costs_rent_comment":"","space_comment_unclear":false,"space_units":"м²","costs_rent":""}],"25":[{"costs":"","costs_comment":"","address_hidden":false,"region_hidden":true,"space_comment":"1/2 частина","space":"101","address":"","costs_unclear":false,"region":"","costs_rent_comment":"","space_comment_unclear":false,"space_units":"м²","costs_rent":""}],"26":[{"costs_rent":"","region":"","costs":"","costs_rent_comment":"","costs_comment":"","address_hidden":false,"region_hidden":true,"space_comment":"","space_units":"м²","space":"29","address":""}],"29":[{"space_unclear":false,"address_hidden":false,"region_hidden":true,"space_comment":"","space":"28","address":"","region":"","costs_property":"","costs_rent_comment":"","space_units":"м²","costs_property_comment":"","costs_rent":""}],"30":[{"space_hidden":false,"address_hidden":false,"region_hidden":true,"space_comment":"","space":"28","address":"","region":"","costs_property":"","costs_rent_comment":"","space_comment_unclear":false,"space_units":"м²","costs_property_comment":"","costs_rent":""},{"costs_rent":"","region":"","costs_property":"","costs_rent_comment":"","space_comment":"","costs_property_comment":"","space_units":"м²","space":"56","address":""}],"31":[{"space_unclear":false,"address_hidden":false,"region_hidden":true,"space_comment":"","space_hidden":false,"space":"101","address":"","region":"","costs_property":"","costs_rent_comment":"","space_units":"м²","costs_property_comment":"","costs_rent":""}]},"intro":{"declaration_year":"2015","isnotdeclaration":""}}