{"income":{"5":{"family_comment":"","value":"179457","family":"455556","comment":""},"6":{"value":"167022","family_comment":"","value_unclear":false,"comment_hidden":false,"family_unclear":false,"family":"","comment":""},"7":{"family_comment":"","value":"","source_name":"","family":"","comment":""},"8":{"family_comment":"","value":"","family":"","comment":""},"9":{"family_comment":"","family_unclear":false,"value":"255","family":"325","comment":""},"10":{"family_comment":"","value":"12180","value_unclear":false,"family":"","comment":""},"11":{"family_comment":"","value":"","family":"","comment":""},"12":{"family_comment":"","value":"","family":"","comment":""},"13":{"family_comment":"","value":"","family":"","comment":""},"14":{"family_comment":"","value":"","family":"","comment":""},"15":{"family_comment":"","value":"","family":"","comment":""},"16":{"family_comment":"","value":"","family":"259259","comment":""},"17":{"family_comment":"","value":"","family":"","comment":""},"18":{"family_comment":"","value":"","family":"","comment":""},"19":{"family_comment":"","value":"","family":"","comment":""},"20":{"value":"","family":"195972","value_unclear":false,"family_hidden":false,"family_comment":"","comment_unclear":false,"comment":"","family_comment_unclear":false}},"vehicle":{"35":[{"year_hidden":false,"brand_info":"1558 куб. см.","sum_rent_comment":"","year":"2012","brand_info_hidden":false,"brand_info_unclear":true,"sum_rent":"","sum":"","brand":"Peugeot 308 CC","sum_comment":"","brand_unclear":true,"brand_hidden":false}],"40":[{"brand_info":"2.5 куб. дм","sum_rent_comment":"","brand":"Toyota Hilux","sum_comment":"","brand_unclear":false,"year":"2014","brand_info_unclear":false,"year_unclear":false,"sum":"","sum_rent":""}]},"id":"vulyk_97_84","banks":{"46":[{"sum_foreign_comment":"","sum_units":"UAH","sum_comment":"","sum_foreign_units":"UAH","sum_comment_hidden":true,"sum":"4730","sum_foreign":""}],"51":[{"sum_foreign_comment":"","sum_units":"UAH","sum_comment":"","sum_comment_unclear":false,"sum_hidden":false,"sum_foreign_units":"UAH","sum_comment_hidden":true,"sum_unclear":false,"sum":"47885","sum_foreign":""}]},"declaration":{"additional_info_text":"","notfull_lostpages":"","date":"2015-03-30T00:00:00","notfull":"","additional_info":"","url":"http://static.declarations.com.ua/declarations/chosen_ones/judges_batch/3985_luk’yanenko_maryna_oleksiivna.pdf"},"liabilities":{"54":{"sum_foreign_comment":"","sum":"","sum_comment":"","sum_comment_unclear":false,"sum_hidden":false,"sum_comment_hidden":false,"sum_unclear":false,"sum_foreign":""},"55":{"sum_foreign_comment":"","sum":"","sum_comment":"","sum_foreign":""},"56":{"sum_foreign_comment":"","sum":"","sum_comment":"","sum_foreign":""},"57":{"sum_foreign_comment":"","sum":"105444","sum_comment":"","sum_comment_unclear":false,"sum_hidden":true,"sum_comment_hidden":true,"sum_unclear":false,"sum_foreign":""},"58":{"sum_foreign_comment":"","sum":"3154","sum_comment":"","sum_comment_unclear":false,"sum_hidden":true,"sum_comment_hidden":true,"sum_unclear":false,"sum_foreign":""},"59":{"sum_foreign_comment":"","sum":"","sum_comment":"","sum_foreign":""},"60":{"sum_foreign_comment":"","sum":"10000","sum_comment":"","sum_comment_unclear":false,"sum_hidden":true,"sum_comment_hidden":true,"sum_foreign":""},"61":{"sum_foreign_comment":"","sum":"","sum_comment":"","sum_foreign":""},"62":{"sum_foreign_comment":"","sum":"","sum_comment":"","sum_unclear":false,"sum_foreign":""},"63":{"sum_foreign_comment":"","sum":"","sum_hidden":false,"sum_comment":"","sum_foreign":""},"64":{"sum_foreign_comment":"","sum":"","sum_comment":"","sum_foreign":""}},"ft_src":"105444\n3154\n10000\nБабаї\n62403\nХарківський\nХарківська область\nСело\nсуддя харківського окружного адміністративного суду\nХарківська область\nАдміністративний місцевий суд\nМарина\nДідовець В. А\nПодружжя\nОлексіївна\nЛук'яненко Марина Олексіївна\nМарина Олексіївна Лук'яненко\nМарина Лук'яненко\nЛук'яненко Марина Олексіївна\nЛук'яненко Марина Олексіївна\nЛук'яненко\n1558 куб. см.\nPeugeot 308 CC\n2012\nToyota Hilux\n2.5 куб. дм\n2014\n32\nХарківська область\nм. Харків\nХарківський р-н\nХарківська область\n289.8\nХарківський р-н, с. Бабаї\nХарківська область\n1200\nм. Бердянськ\nЗапорізька область\n600\n30.1\nм. Харків\nХарківська область\n4730\n47885\n2014\n1558 куб. см.\nPeugeot 308 CC\n2012\n2.5 куб. дм\nToyota Hilux\n2014\n2014\nЛук'яненко Марина Олексіївна\nМарина Олексіївна Лук'яненко\nМарина Лук'яненко\nЛук'яненко Марина Олексіївна\nМарина\nПодружжя\nДідовець В. А\nЛук'яненко Марина Олексіївна\nЛук'яненко\nАдміністративний місцевий суд\nХарківська область\nсуддя харківського окружного адміністративного суду\nОлексіївна\nХарківська область\n62403\nСело\nБабаї\nХарківський\n3154\n105444\n10000\n167022\n195972\n179457\n455556\n259259\n255\n325\n12180\n1200\nХарківська область\nХарківський р-н, с. Бабаї\n600\nЗапорізька область\nм. Бердянськ\n289.8\nХарківська область\nХарківський р-н\n32\nХарківська область\nм. Харків\n30.1\nм. Харків\nХарківська область\n47885\n4730\n3154\n105444\n10000\n167022\n325\n255\n12180\n455556\n179457\n259259\n195972\nПодружжя\nДідовець В. А\nОлексіївна\nЛук'яненко\nМарина\nЛук'яненко Марина Олексіївна\nМарина Олексіївна Лук'яненко\nМарина Лук'яненко\nЛук'яненко Марина Олексіївна\nСело\n62403\nБабаї\nХарківська область\nХарківський\nХарківська область\nАдміністративний місцевий суд\nсуддя харківського окружного адміністративного суду\nЛук'яненко Марина Олексіївна\n2012\nPeugeot 308 CC\n1558 куб. см.\n2014\n2.5 куб. дм\nToyota Hilux\n325\n255\n12180\n195972\n455556\n179457\n259259\n167022\nм. Харків\nХарківська область\n32\nХарківський р-н\nХарківська область\n289.8\nм. Харків\nХарківська область\n30.1\nХарківський р-н, с. Бабаї\nХарківська область\n1200\nм. Бердянськ\nЗапорізька область\n600\n47885\n4730\n2014","general":{"name_hidden":false,"name":"Марина","last_name_hidden":false,"inn":"","family":[{"inn":"","relations":"Подружжя","relations_other":"","inn_hidden":true,"family_name":"Дідовець В. А","name_hidden":true,"name_unclear":false}],"patronymic":"Олексіївна","inn_hidden":true,"family_raw":"","inn_unclear":false,"post":{"region_unclear":false,"region":"Харківська область","post":"суддя харківського окружного адміністративного суду","office":"Адміністративний місцевий суд","office_unclear":false,"post_hidden":false},"full_name":"Лук'яненко Марина Олексіївна","addresses":[{"place_district":"Харківський","place_city_hidden":false,"place_city":"Бабаї","place_city_unclear":false,"place_district_hidden":false,"place_city_type":"Село","place_address_hidden":true,"place_city_type_hidden":false,"place_address":"62403","place_hidden":false,"place":"Харківська область"}],"last_name":"Лук'яненко","patronymic_hidden":false,"full_name_suggest":{"output":"Лук'яненко Марина Олексіївна","input":["Лук'яненко Марина Олексіївна","Марина Олексіївна Лук'яненко","Марина Лук'яненко"]}},"source":"VULYK","estate":{"25":[{"region_unclear":false,"space_unclear":false,"costs":"","costs_comment":"","address_hidden":true,"region_hidden":false,"space_comment":"","space_hidden":false,"space":"30.1","address":"м. Харків","region":"Харківська область","costs_rent_comment":"","space_comment_unclear":false,"space_comment_hidden":false,"space_units":"м²","costs_rent":""}],"29":[{"region_unclear":false,"space_unclear":false,"address_hidden":true,"region_hidden":false,"space_comment":"","space":"1200","address":"Харківський р-н, с. Бабаї","region":"Харківська область","costs_property":"","costs_rent_comment":"","space_comment_unclear":false,"address_unclear":false,"space_units":"м²","costs_property_comment":"","costs_rent":""},{"address_hidden":false,"region_hidden":false,"space_comment":"","space":"600","address":"м. Бердянськ","region":"Запорізька область","costs_property":"","costs_rent_comment":"","address_unclear":false,"space_units":"м²","costs_property_comment":"","costs_rent":""}],"30":[{"address_hidden":true,"region_hidden":false,"space_comment":"","space":"289.8","address":"Харківський р-н","region":"Харківська область","costs_property":"","costs_rent_comment":"","address_unclear":false,"space_units":"м²","costs_property_comment":"","costs_rent":""}],"31":[{"space_unclear":false,"address_hidden":true,"region_hidden":false,"space_comment":"","space_hidden":false,"space":"32","address":"м. Харків","region":"Харківська область","costs_property":"","costs_rent_comment":"","space_comment_hidden":false,"space_units":"м²","costs_property_comment":"","costs_rent":""}]},"intro":{"declaration_year":"2014","isnotdeclaration":""}}