{"income":{"5":{"family_comment":"","value":"305830","family":"","comment":""},"6":{"family_comment":"","value":"269445","family":"","comment":""},"7":{"family_comment":"","value":"","source_name":"","family":"","comment":""},"8":{"family_comment":"","value":"","family":"","comment":""},"9":{"value":"36385","comment_unclear":false,"family_comment":"","family":"","comment":"","family_comment_unclear":false},"10":{"family_comment":"","value":"","family":"","comment":""},"11":{"family_comment":"","value":"","family":"","comment":""},"12":{"family_comment":"","value":"","family":"","comment":""},"13":{"family_comment":"","value":"","family":"","comment":""},"14":{"family_comment":"","value":"","family":"","comment":""},"15":{"family_comment":"","value":"","family":"","comment":""},"16":{"family_comment":"","value":"","family":"","comment":""},"17":{"family_comment":"","value":"","family":"","comment":""},"18":{"family_comment":"","value":"","family":"","comment":""},"19":{"value":"","family_comment":"","value_unclear":false,"family_unclear":false,"family":"","comment":""},"20":{"value":"","family_comment":"","value_unclear":false,"comment_hidden":false,"family_comment_hidden":false,"family_unclear":false,"family_comment_unclear":false,"comment_unclear":false,"comment":"","family":""}},"vehicle":{"35":[{"brand_info":"2399 куб. см.","sum_rent_comment":"","brand":"Audi A6","sum_comment":"","year":"2005","sum_hidden":false,"brand_info_hidden":false,"brand_info_unclear":false,"year_unclear":false,"sum":"","sum_rent":""}]},"id":"vulyk_106_18","banks":{"45":[{"sum_foreign_comment":"","sum_units":"UAH","sum_comment":"","sum_foreign_comment_hidden":false,"sum_hidden":false,"sum_foreign_units":"UAH","sum_comment_hidden":false,"sum":"320435","sum_foreign":""},{"sum_foreign_comment":"","sum_units":"","sum_comment":"","sum_foreign_comment_hidden":false,"sum_foreign_units":"","sum_comment_hidden":false,"sum":"184000","sum_foreign":""}]},"declaration":{"additional_info_text":"","notfull_lostpages":"","date":"2016-03-31T00:00:00","notfull":"","additional_info":"","url":"http://static.declarations.com.ua/declarations/chosen_ones/judges_batch/2157_ievstyhneiev_oleksandr_serhiiovych.pdf"},"liabilities":{"54":{"sum_foreign_comment":"","sum":"","sum_comment":"","sum_comment_unclear":false,"sum_hidden":false,"sum_comment_hidden":false,"sum_foreign":""},"55":{"sum_foreign_comment":"","sum":"","sum_hidden":false,"sum_comment":"","sum_foreign":""},"56":{"sum_foreign_comment":"","sum":"","sum_comment":"","sum_hidden":false,"sum_comment_hidden":false,"sum_unclear":false,"sum_foreign":""},"57":{"sum_foreign_comment":"","sum":"","sum_comment":"","sum_hidden":false,"sum_comment_hidden":false,"sum_foreign":""},"58":{"sum_foreign_comment":"","sum":"","sum_comment":"","sum_hidden":false,"sum_comment_hidden":false,"sum_foreign":""},"59":{"sum_foreign_comment":"","sum":"","sum_comment":"","sum_foreign":""},"60":{"sum_foreign_comment":"","sum":"","sum_comment":"","sum_hidden":false,"sum_comment_hidden":false,"sum_foreign":""},"61":{"sum_foreign_comment":"","sum":"","sum_comment":"","sum_foreign":""},"62":{"sum_foreign_comment":"","sum":"","sum_comment":"","sum_comment_hidden":false,"sum_unclear":false,"sum_foreign":""},"63":{"sum_foreign_comment":"","sum":"","sum_comment":"","sum_foreign":""},"64":{"sum_foreign_comment":"","sum":"","sum_comment":"","sum_foreign":""}},"ft_src":"голова дніпропетровського апеляційного господарського суду\nДніпропетровська область\nАпеляційний господарський суд\nОлександр\nСергійович\nЄвстигнеєв Олександр Сергійович\nЄвстигнеєв\nЄвстигнеєв Олександр Сергійович\nОлександр Сергійович Євстигнеєв\nОлександр Євстигнеєв\nЄвстигнеєв Олександр Сергійович\nAudi A6\n2399 куб. см.\n2005\n320435\n184000\n2015\n2399 куб. см.\n2005\nAudi A6\n320435\n184000\n595\nЄвстигнеєв Олександр Сергійович\nОлександр Сергійович Євстигнеєв\nОлександр Євстигнеєв\nЄвстигнеєв Олександр Сергійович\nЄвстигнеєв Олександр Сергійович\nОлександр\nЄвстигнеєв\nДніпропетровська область\nАпеляційний господарський суд\nголова дніпропетровського апеляційного господарського суду\nСергійович\n269445\n305830\n36385\n2015\n595\nСергійович\nЄвстигнеєв\nОлександр\nЄвстигнеєв Олександр Сергійович\nОлександр Сергійович Євстигнеєв\nОлександр Євстигнеєв\nЄвстигнеєв Олександр Сергійович\nДніпропетровська область\nАпеляційний господарський суд\nголова дніпропетровського апеляційного господарського суду\nЄвстигнеєв Олександр Сергійович\n269445\n36385\n305830\n2005\nAudi A6\n2399 куб. см.\n36385\n305830\n269445\n595\n320435\n184000\n2015","general":{"inn":"","name":"Олександр","inn_unclear":false,"patronymic":"Сергійович","inn_hidden":true,"family_raw":"","last_name":"Євстигнеєв","post":{"region_unclear":false,"region":"Дніпропетровська область","post":"голова дніпропетровського апеляційного господарського суду","office":"Апеляційний господарський суд","office_unclear":false,"post_hidden":false},"full_name":"Євстигнеєв Олександр Сергійович","addresses":[{"place_district":"","place_city_hidden":false,"place_city":"","place_city_type_hidden":false,"place_district_hidden":true,"place_city_type":"","place_address_hidden":false,"place_address":"","place_hidden":true,"place":""}],"full_name_suggest":{"output":"Євстигнеєв Олександр Сергійович","input":["Євстигнеєв Олександр Сергійович","Олександр Сергійович Євстигнеєв","Олександр Євстигнеєв"]},"name_unclear":false},"source":"VULYK","estate":{"23":[{"region_unclear":false,"space_hidden":false,"costs":"","costs_comment":"","address_hidden":true,"region_hidden":true,"space_comment":"","space_unclear":false,"space":"595","address":"","costs_comment_unclear":false,"costs_rent_comment_unclear":false,"region":"","address_unclear":false,"costs_rent_comment":"","space_comment_unclear":false,"space_comment_hidden":false,"space_units":"м²","costs_rent":""}]},"intro":{"declaration_year":"2015","isnotdeclaration":""}}