{"income":{"5":{"value":"183039.23","family_comment":"","value_unclear":false,"family_hidden":false,"value_hidden":false,"family_unclear":false,"family":"11709.94","comment":"","family_comment_unclear":false},"6":{"value":"183039.23","family_comment":"","value_unclear":false,"comment_hidden":false,"family_hidden":false,"value_hidden":false,"family_unclear":false,"family":"10387.44","comment":""},"7":{"value":"","value_hidden":false,"family_comment":"","source_name":"","family":"","comment":"","source_name_hidden":false},"8":{"family_comment":"","value":"","family":"","comment":""},"9":{"value":"","comment_hidden":false,"value_hidden":false,"family_comment":"","family":"","comment":""},"10":{"value":"","value_unclear":false,"value_hidden":false,"family_comment":"","family":"","comment":""},"11":{"family_comment":"","value":"","family":"","comment":""},"12":{"family_comment":"","value":"","family":"","comment":""},"13":{"family_comment":"","value":"","family_hidden":false,"comment":"","family":""},"14":{"family_comment":"","value":"","family":"","comment":""},"15":{"family_comment":"","family_unclear":false,"value":"","family":"","comment":""},"16":{"family_comment":"","value":"","value_unclear":false,"family":"","comment":""},"17":{"family_comment":"","value":"","family":"","comment":""},"18":{"family_comment":"","value":"","family":"","comment":""},"19":{"family_comment":"","value":"","comment_unclear":false,"family":"","comment":""},"20":{"value":"","comment_unclear":false,"family_hidden":false,"value_hidden":false,"family_comment":"","family":"1322.5","comment":""}},"vehicle":{"35":[{"year_hidden":false,"brand_info":"NA19 B, 1796 куб. см.","sum_rent_comment":"","brand_info_unclear":true,"sum_rent_hidden":false,"year":"2008","sum_hidden":false,"brand_info_hidden":false,"sum_rent_comment_unclear":false,"year_unclear":false,"sum_rent":"","sum":"","brand":"Chevrolet Lacetti","sum_comment":"","sum_comment_unclear":false,"brand_hidden":false,"sum_unclear":false,"brand_unclear":false}],"40":[{"year_hidden":false,"brand_info":"NA19 B, 1796 куб. см.","sum_rent_comment":"","year":"2008","brand_info_hidden":false,"brand_info_unclear":false,"sum_rent":"","sum":"","brand":"Chevrolet Lacetti","sum_comment":"","brand_unclear":false,"brand_hidden":false}]},"id":"vulyk_64_29","banks":{"51":[{"sum_foreign_comment":"","sum_units":"UAH","sum_comment":"","sum_comment_unclear":false,"sum_foreign_units":"UAH","sum_comment_hidden":false,"sum_unclear":false,"sum":"1756.93","sum_foreign":""}]},"declaration":{"additional_info_text":"","notfull_lostpages":"","date":"2015-03-20T00:00:00","notfull":"","additional_info":"","url":"http://static.declarations.com.ua/declarations/chosen_ones/mega_batch/kratko_dmytro_mykhailovych.pdf"},"liabilities":{"54":{"sum_foreign_comment":"","sum":"280","sum_comment":"","sum_foreign_comment_hidden":false,"sum_hidden":false,"sum_comment_hidden":false,"sum_unclear":false,"sum_foreign":""},"55":{"sum_foreign_comment":"","sum":"","sum_comment":"","sum_comment_unclear":false,"sum_foreign":""},"56":{"sum_foreign_comment":"","sum":"","sum_comment":"","sum_unclear":false,"sum_foreign":""},"57":{"sum_foreign_comment":"","sum":"","sum_comment":"","sum_hidden":false,"sum_unclear":false,"sum_foreign":""},"58":{"sum_foreign_comment":"","sum":"","sum_comment":"","sum_unclear":false,"sum_foreign":""},"59":{"sum_foreign_comment":"","sum":"","sum_comment":"","sum_comment_unclear":false,"sum_comment_hidden":false,"sum_unclear":false,"sum_foreign":""},"60":{"sum_foreign_comment":"","sum":"","sum_comment":"","sum_foreign":""},"61":{"sum_foreign_comment":"","sum":"","sum_comment":"","sum_foreign":""},"62":{"sum_foreign_comment":"","sum":"","sum_comment":"","sum_unclear":false,"sum_foreign":""},"63":{"sum_foreign_comment":"","sum":"","sum_comment":"","sum_unclear":false,"sum_foreign":""},"64":{"sum_foreign_comment":"","sum":"","sum_comment":"","sum_comment_unclear":false,"sum_unclear":false,"sum_foreign":""}},"ft_src":"280\nсуддя маловисківського районного суду кіровоградської області\nКіровоградська область\nЗагальний місцевий суд\nДмитро\nКратко Наталія Анатоліївна 11. 08. 1985 р. н\nПодружжя\nМихайлович\nКратко Дмитро Михайлович\nКратко\nКратко Дмитро Михайлович\nДмитро Михайлович Кратко\nДмитро Кратко\nКратко Дмитро Михайлович\nNA19 B, 1796 куб. см.\nChevrolet Lacetti\n2008\nNA19 B, 1796 куб. см.\nChevrolet Lacetti\n2008\n1756.93\n2014\nNA19 B, 1796 куб. см.\nChevrolet Lacetti\n2008\nNA19 B, 1796 куб. см.\nChevrolet Lacetti\n2008\n1756.93\n155.6\nоб'єкт незавершенного будівництва - житловий будинок\n94.5\nна праві користування\n33\nна підставі договору найму\n1000\n1000\n94.5\nна праві користування\n33\nна підставі договору найму\n155.6\nоб'єкт незавершенного будівництва - житловий будинок\nЗагальний місцевий суд\nКіровоградська область\nсуддя маловисківського районного суду кіровоградської області\nПодружжя\nКратко Наталія Анатоліївна 11. 08. 1985 р. н\nКратко Дмитро Михайлович\nДмитро Михайлович Кратко\nДмитро Кратко\nКратко Дмитро Михайлович\nКратко Дмитро Михайлович\nДмитро\nКратко\nМихайлович\n280\n10387.44\n183039.23\n1322.5\n183039.23\n11709.94\n2014\n280\n1000\nоб'єкт незавершенного будівництва - житловий будинок\n155.6\n1000\nоб'єкт незавершенного будівництва - житловий будинок\n155.6\nна праві користування\n94.5\nна підставі договору найму\n33\nна праві користування\n94.5\nна підставі договору найму\n33\nПодружжя\nКратко Наталія Анатоліївна 11. 08. 1985 р. н\nМихайлович\nКратко\nДмитро\nКратко Дмитро Михайлович\nДмитро Михайлович Кратко\nДмитро Кратко\nКратко Дмитро Михайлович\nКіровоградська область\nЗагальний місцевий суд\nсуддя маловисківського районного суду кіровоградської області\nКратко Дмитро Михайлович\n10387.44\n183039.23\n11709.94\n183039.23\n1322.5\nChevrolet Lacetti\nNA19 B, 1796 куб. см.\n2008\n2008\nChevrolet Lacetti\nNA19 B, 1796 куб. см.\n1322.5\n183039.23\n11709.94\n183039.23\n10387.44\nна праві користування\n94.5\nна підставі договору найму\n33\n1000\nоб'єкт незавершенного будівництва - житловий будинок\n155.6\nоб'єкт незавершенного будівництва - житловий будинок\n155.6\n94.5\nна праві користування\nна підставі договору найму\n33\n1000\n1756.93\n2014","general":{"inn":"","name":"Дмитро","last_name_hidden":false,"family":[{"inn":"","inn_hidden":true,"relations_unclear":false,"relations_hidden":false,"relations_other":"","relations":"Подружжя","name_hidden":false,"inn_unclear":false,"family_name":"Кратко Наталія Анатоліївна 11. 08. 1985 р. н","name_unclear":false}],"patronymic":"Михайлович","inn_hidden":true,"family_raw":"","inn_unclear":false,"post":{"post_unclear":false,"post":"суддя маловисківського районного суду кіровоградської області","candidate":"","office_hidden":false,"region":"Кіровоградська область","post_hidden":false,"office":"Загальний місцевий суд","office_unclear":false,"region_hidden":false},"last_name_unclear":false,"full_name":"Кратко Дмитро Михайлович","addresses":[{"place_city_type_unclear":false,"place_address":"","place_district_hidden":true,"place_city_type":"","place_city_hidden":true,"place_city_type_hidden":true,"place":"","place_district":"","place_unclear":false,"place_city":"","place_city_unclear":false,"place_hidden":true,"place_address_hidden":false}],"last_name":"Кратко","patronymic_hidden":false,"full_name_suggest":{"output":"Кратко Дмитро Михайлович","input":["Кратко Дмитро Михайлович","Дмитро Михайлович Кратко","Дмитро Кратко"]},"name_unclear":false},"source":"VULYK","estate":{"23":[{"space_unclear":false,"costs":"","costs_rent_unclear":false,"costs_comment":"","costs_hidden":false,"space_hidden":false,"space_units_unclear":false,"space_units_hidden":false,"costs_unclear":false,"region":"","space_comment_unclear":false,"space_comment_hidden":false,"costs_rent":"","region_unclear":false,"costs_rent_comment_unclear":false,"address_hidden":true,"region_hidden":true,"space_comment":"","space":"1000","address":"","address_unclear":false,"costs_rent_comment":"","costs_rent_hidden":false,"space_units":"м²"}],"25":[{"region_unclear":false,"space_unclear":false,"costs":"","costs_rent_unclear":false,"costs_comment":"","costs_hidden":false,"address_hidden":true,"region_hidden":true,"space_comment":"на праві користування","space_hidden":false,"space":"94.5","space_units_hidden":false,"costs_rent_comment_unclear":false,"region":"","costs_rent_comment":"","costs_rent_hidden":false,"space_comment_unclear":false,"space_units":"м²","address":"","costs_rent":"","costs_unclear":false},{"region_unclear":false,"space_unclear":false,"costs":"","costs_comment":"","address_hidden":false,"region_hidden":false,"space_comment":"на підставі договору найму","space":"33","address":"","space_comment_unclear":false,"region":"","costs_rent_comment":"","costs_unclear":false,"space_units":"м²","costs_rent":""}],"28":[{"space_unclear":true,"costs":"","costs_comment":"","costs_hidden":false,"address_hidden":true,"region_hidden":true,"space_comment":"об'єкт незавершенного будівництва - житловий будинок","space_hidden":false,"space":"155.6","address":"","region":"","costs_rent_comment":"","costs_rent_hidden":false,"space_units":"м²","costs_rent":""}],"29":[{"region_unclear":false,"space_unclear":false,"costs_rent_unclear":false,"costs_property_hidden":false,"address_hidden":true,"region_hidden":true,"space_comment":"","space_hidden":false,"space":"1000","address":"","region":"","costs_property":"","costs_rent_comment":"","costs_rent_hidden":false,"address_unclear":false,"space_units":"м²","costs_property_comment":"","costs_rent":""}],"31":[{"region_unclear":false,"address_hidden":true,"region_hidden":true,"space_comment":"на праві користування","space":"94.5","address":"","region":"","costs_property":"","costs_rent_comment":"","space_comment_hidden":false,"space_units":"м²","costs_property_comment":"","costs_rent":""},{"region_unclear":false,"space_unclear":false,"address_hidden":false,"region_hidden":false,"space_comment":"на підставі договору найму","space":"33","address":"","region":"","costs_property":"","costs_rent_comment":"","address_unclear":false,"space_units":"м²","costs_property_comment":"","costs_rent":""}],"32":[{"space_hidden":false,"costs_property_hidden":false,"address_hidden":false,"region_hidden":true,"space_comment":"","space":"","address":"","costs_property":"","costs_rent_comment":"","space_units":"м²","costs_property_comment":"","costs_rent":""}],"34":[{"space_hidden":false,"costs_property_hidden":false,"address_hidden":true,"region_hidden":true,"space_comment":"об'єкт незавершенного будівництва - житловий будинок","space":"155.6","address":"","region":"","costs_property":"","costs_rent_comment":"","space_units":"м²","costs_property_comment":"","costs_rent":""}]},"intro":{"declaration_year":"2014","isnotdeclaration":"","declaration_year_unclear":false,"declaration_year_hidden":false}}