{"income":{"5":{"value":"180983","family_unclear":false,"family_hidden":false,"family_comment":"","family":"11388","comment":""},"6":{"family_comment":"","value":"180983","family_hidden":false,"comment":"","family":""},"7":{"family_comment":"","value":"","source_name":"","family":"","comment":""},"8":{"family_comment":"","value":"","family":"","comment":""},"9":{"value":"","comment_unclear":false,"family_hidden":false,"family_comment":"","family":"","comment":""},"10":{"family_comment":"","value":"","family":"","comment":""},"11":{"family_comment":"","value":"","family":"","comment":""},"12":{"family_comment":"","value":"","family":"","comment":""},"13":{"family_comment":"","value":"","family":"","comment":""},"14":{"family_comment":"","value":"","family":"","comment":""},"15":{"family_comment":"","value":"","value_unclear":false,"family":"","comment":""},"16":{"family_comment":"","value":"","family":"","comment":""},"17":{"family_comment":"","value":"","family":"","comment":""},"18":{"family_comment":"","value":"","family":"","comment":""},"19":{"family_comment":"","value":"","family":"","comment":""},"20":{"value":"","comment_unclear":false,"comment_hidden":false,"family_hidden":false,"value_hidden":false,"family_comment":"","value_unclear":false,"family":"11388","comment":"","family_comment_hidden":false}},"vehicle":{"35":[{"brand_info":"1599 куб. см.","sum_rent_comment":"","brand":"Hyundai Accent","sum_comment":"","year":"2008","brand_info_hidden":false,"sum":"","sum_rent":""}]},"id":"vulyk_41_66","banks":{"45":[{"sum_foreign_comment":"","sum_units":"UAH","sum_comment":"","sum_foreign_unclear":false,"sum_foreign_units":"UAH","sum_hidden":false,"sum_comment_hidden":false,"sum":"599","sum_foreign":""},{"sum_foreign_comment":"","sum_units":"","sum_comment":"","sum_foreign_unclear":false,"sum_foreign_units":"","sum":"","sum_foreign":""}],"46":[{"sum_foreign_comment":"","sum_units":"UAH","sum_comment":"","sum_foreign_units":"UAH","sum_comment_hidden":false,"sum_unclear":false,"sum":"","sum_foreign":""},{"sum_foreign_comment":"","sum_units":"","sum_comment":"","sum_foreign_units":"","sum":"","sum_unclear":false,"sum_foreign":""}],"47":[{"sum_foreign_comment":"","sum_units":"UAH","sum_comment":"","sum_foreign_units":"UAH","sum":"","sum_foreign":""},{"sum_foreign_comment":"","sum_units":"","sum_comment":"","sum_foreign_units":"","sum":"","sum_foreign":""}],"48":[{"sum_foreign_comment":"","sum_units":"UAH","sum_comment":"","sum_foreign_units":"UAH","sum":"","sum_foreign":""}],"49":[{"sum_foreign_comment":"","sum_units":"UAH","sum_comment":"","sum_foreign_units":"UAH","sum":"","sum_foreign":""}],"50":[{"sum_foreign_comment":"","sum_units":"UAH","sum_comment":"","sum_foreign_units":"UAH","sum":"","sum_foreign":""}],"51":[{"sum_foreign_comment":"","sum_units":"UAH","sum_comment":"","sum_hidden":false,"sum_foreign_units":"UAH","sum_comment_hidden":false,"sum_unclear":false,"sum":"","sum_foreign":""},{"sum_foreign_comment":"","sum_units":"","sum_comment":"","sum_foreign_units":"","sum":"","sum_foreign":""}],"52":[{"sum_foreign_comment":"","sum_units":"UAH","sum_comment":"","sum_foreign_units":"UAH","sum_comment_hidden":false,"sum_unclear":false,"sum":"","sum_foreign":""}],"53":[{"sum_foreign_comment":"","sum_units":"UAH","sum_comment":"","sum_foreign_units":"UAH","sum_comment_hidden":false,"sum":"","sum_foreign":""},{"sum_foreign_comment":"","sum_units":"","sum_comment":"","sum_foreign_units":"","sum":"","sum_foreign":""},{"sum_foreign_comment":"","sum_units":"","sum_comment":"","sum_foreign_units":"","sum":"","sum_foreign":""}]},"declaration":{"date":"2014-02-12T00:00:00","additional_info_text":"","additional_info":"","url":"http://static.declarations.com.ua/declarations/chosen_ones/mega_batch/konieva_svitlana_oleksandrivna.pdf"},"liabilities":{"54":{"sum_foreign_comment":"","sum_comment_hidden":false,"sum":"559","sum_comment":"","sum_foreign":""},"55":{"sum_foreign_comment":"","sum":"","sum_comment":"","sum_foreign":""},"56":{"sum_foreign_comment":"","sum":"","sum_hidden":false,"sum_comment":"","sum_foreign":""},"57":{"sum_foreign_comment":"","sum":"","sum_comment":"","sum_comment_hidden":false,"sum_unclear":false,"sum_foreign":""},"58":{"sum_foreign_comment":"","sum_comment_hidden":false,"sum":"","sum_comment":"","sum_foreign":""},"59":{"sum_foreign_comment":"","sum":"","sum_comment":"","sum_foreign":""},"60":{"sum_foreign_comment":"","sum_comment_hidden":false,"sum":"","sum_comment":"","sum_foreign":""},"61":{"sum_foreign_comment":"","sum":"","sum_comment":"","sum_foreign":""},"62":{"sum_foreign_comment":"","sum":"","sum_comment":"","sum_foreign":""},"63":{"sum_foreign_comment":"","sum":"","sum_comment":"","sum_comment_hidden":false,"sum_unclear":false,"sum_foreign":""},"64":{"sum_foreign_comment":"","sum_comment_hidden":false,"sum":"","sum_comment":"","sum_foreign":""}},"ft_src":"559\nсуддя дніпропетровського окружного адміністративного суду\nДніпропетровська область\nАдміністративний місцевий суд\nСвітлана\nКонєв Є. А\nПодружжя\nКонєв І. Є\nДитина\nОлександрівна\nКонєва Світлана Олександрівна\nСвітлана Олександрівна Конєва\nСвітлана Конєва\nКонєва Світлана Олександрівна\nКонєва\nКонєва Світлана Олександрівна\nДніпропетровськ\nДніпропетровська область\n1599 куб. см.\n2008\nHyundai Accent\n599\n2014\nHyundai Accent\n1599 куб. см.\n2008\n599\n38.4\nДніпропетровськ\nДніпропетровська область\n19.2\nДніпропетровськ\nДніпропетровська область\nПодружжя\nКонєв Є. А\nДитина\nКонєв І. Є\nКонєва Світлана Олександрівна\nСвітлана Олександрівна Конєва\nСвітлана Конєва\nКонєва Світлана Олександрівна\nКонєва Світлана Олександрівна\nСвітлана\nОлександрівна\nАдміністративний місцевий суд\nсуддя дніпропетровського окружного адміністративного суду\nДніпропетровська область\nКонєва\nДніпропетровська область\nДніпропетровськ\n559\n180983\n11388\n180983\n11388\n2014\n559\nДніпропетровськ\nДніпропетровська область\n38.4\nДніпропетровськ\n19.2\nДніпропетровська область\nКонєв Є. А\nПодружжя\nКонєв І. Є\nДитина\nОлександрівна\nКонєва\nСвітлана\nКонєва Світлана Олександрівна\nСвітлана Олександрівна Конєва\nСвітлана Конєва\nКонєва Світлана Олександрівна\nДніпропетровська область\nДніпропетровськ\nДніпропетровська область\nсуддя дніпропетровського окружного адміністративного суду\nАдміністративний місцевий суд\nКонєва Світлана Олександрівна\n180983\n11388\n180983\n11388\nHyundai Accent\n1599 куб. см.\n2008\n11388\n180983\n11388\n180983\nДніпропетровськ\nДніпропетровська область\n38.4\nДніпропетровськ\nДніпропетровська область\n19.2\n599\n2014","general":{"inn":"","name":"Світлана","family":[{"inn":"","relations":"Подружжя","relations_hidden":false,"inn_hidden":false,"family_name":"Конєв Є. А","name_hidden":false,"name_unclear":false},{"inn":"","relations":"Дитина","relations_other":"","inn_hidden":false,"family_name":"Конєв І. Є","name_hidden":false,"name_unclear":false}],"patronymic":"Олександрівна","inn_hidden":true,"family_raw":"","last_name":"Конєва","post":{"post_unclear":false,"post":"суддя дніпропетровського окружного адміністративного суду","post_hidden":false,"region":"Дніпропетровська область","region_hidden":false,"office":"Адміністративний місцевий суд","office_hidden":false},"last_name_unclear":false,"full_name":"Конєва Світлана Олександрівна","addresses":[{"place_district":"","place_city_hidden":false,"place_city":"Дніпропетровськ","place_city_type_hidden":false,"place_district_hidden":false,"place_city_type":"Місто","place_address_hidden":false,"place_address":"","place_hidden":true,"place":"Дніпропетровська область"}],"patronymic_hidden":false,"full_name_suggest":{"output":"Конєва Світлана Олександрівна","input":["Конєва Світлана Олександрівна","Світлана Олександрівна Конєва","Світлана Конєва"]},"name_unclear":false},"source":"VULYK","estate":{"23":[{"region_unclear":false,"space_unclear":false,"costs":"","costs_comment":"","address_hidden":false,"region_hidden":false,"space_comment":"","space":"","address":"","costs_comment_unclear":false,"region":"","space_units_unclear":false,"space_comment_hidden":false,"space_units":"м²","costs_rent":"","costs_rent_comment":""},{"costs_rent":"","space_unclear":false,"region":"","costs":"","costs_rent_comment":"","costs_comment":"","space_comment":"","space_units":"","space":"","address":""},{"costs_rent":"","region":"","costs":"","costs_rent_comment":"","costs_comment":"","space_comment":"","space_units":"","space":"","address":""}],"25":[{"region_unclear":false,"space_hidden":false,"costs":"","costs_comment":"","address_hidden":false,"region_hidden":false,"space_comment":"","space_unclear":false,"space":"19.2","address":"Дніпропетровськ","costs_comment_unclear":false,"region":"Дніпропетровська область","costs_rent_comment":"","costs_unclear":false,"space_units":"м²","costs_rent":""}],"31":[{"space_hidden":false,"address_hidden":false,"region_hidden":false,"space_comment":"","space":"38.4","address":"Дніпропетровськ","region":"Дніпропетровська область","costs_property":"","costs_rent_comment":"","space_comment_unclear":false,"space_units":"м²","costs_property_comment":"","costs_rent":""}]},"intro":{"declaration_year":"2014"}}