{"id":"vulyk_89_1","ft_src":"82.28\n2014\n251544.26\n252140.53\n596.27\n82.28\nАндрійович\nБлохіна Т. С\nПодружжя\nДитина\nБлохін К. А\nБлохін М. А\nДитина\nБлохін Анатолій Андрійович\nАнатолій Андрійович Блохін\nАнатолій Блохін\nБлохін Анатолій Андрійович\nБлохін Анатолій Андрійович\nАнатолій\nБлохін\nДонецька область\nсуддя донецького апеляційного адміністративного суду\nАпеляційний адміністративний суд\n251544.26\n596.27\n252140.53\n2014\nБлохіна Т. С\nПодружжя\nБлохін К. А\nДитина\nДитина\nБлохін М. А\nАндрійович\nБлохін\nсуддя донецького апеляційного адміністративного суду\nДонецька область\nАпеляційний адміністративний суд\nБлохін Анатолій Андрійович\nБлохін Анатолій Андрійович\nАнатолій Андрійович Блохін\nАнатолій Блохін\nБлохін Анатолій Андрійович\nАнатолій","estate":{"30":[{"costs_property_comment":"","address":"","space_units":"м²","costs_rent_comment":"","space":"82.28","region":"","region_hidden":true,"costs_property":"","space_comment":"","address_hidden":false,"costs_rent":""}]},"source":"VULYK","income":{"5":{"family":"","family_comment":"","comment":"","value_hidden":false,"family_hidden":false,"value":"252140.53"},"6":{"family_comment":"","value":"251544.26","family":"","comment":""},"7":{"family":"","family_comment":"","value":"","comment":"","source_name":""},"8":{"family_comment":"","value":"","family":"","comment":""},"9":{"family_comment":"","value":"","family":"","comment":""},"10":{"family_comment":"","value":"","family":"","comment":""},"11":{"family_comment":"","value":"","family":"","comment":""},"12":{"family_comment":"","value":"","family":"","comment":""},"13":{"family_comment":"","value":"","family":"","comment":""},"14":{"family_comment":"","value":"","family":"","comment":""},"15":{"family_comment":"","value":"","family":"","comment":""},"16":{"family_comment":"","value":"","family":"","comment":""},"17":{"family_comment":"","value":"","family":"","comment":""},"18":{"family_comment":"","value":"","family":"","comment":""},"19":{"family_comment":"","value":"","family":"","comment":""},"20":{"family_comment":"","value":"596.27","family":"","comment":""}},"general":{"inn":"","addresses":[{"place_city_type_hidden":false,"place_city_type":"","place_city_hidden":true,"place_hidden":true,"place_district":"","place_district_hidden":false,"place":"","place_address":"","place_address_hidden":false,"place_city":""}],"last_name":"Блохін","full_name":"Блохін Анатолій Андрійович","family":[{"inn":"","name_hidden":true,"family_name":"Блохіна Т. С","inn_hidden":true,"relations":"Подружжя"},{"inn":"","family_name":"Блохін К. А","relations_other":"","name_unclear":false,"inn_hidden":false,"name_hidden":false,"relations":"Дитина"},{"inn":"","name_unclear":false,"family_name":"Блохін М. А","inn_hidden":false,"relations":"Дитина"}],"patronymic":"Андрійович","inn_hidden":true,"name":"Анатолій","post":{"office":"Апеляційний адміністративний суд","region":"Донецька область","post":"суддя донецького апеляційного адміністративного суду"},"family_raw":"","full_name_suggest":{"input":["Блохін Анатолій Андрійович","Анатолій Андрійович Блохін","Анатолій Блохін"],"output":"Блохін Анатолій Андрійович"}},"liabilities":{"54":{"sum_comment":"","sum_foreign_comment":"","sum_foreign":"","sum":""},"55":{"sum_comment":"","sum_foreign_comment":"","sum_foreign":"","sum":""},"56":{"sum_comment":"","sum_foreign_comment":"","sum_foreign":"","sum_unclear":false,"sum":""},"57":{"sum_comment":"","sum_foreign_comment":"","sum_foreign":"","sum":""},"58":{"sum_comment":"","sum_foreign_comment":"","sum_foreign":"","sum":""},"59":{"sum_comment":"","sum_foreign_comment":"","sum_foreign":"","sum":""},"60":{"sum_comment":"","sum_foreign_comment":"","sum_foreign":"","sum":""},"61":{"sum_comment":"","sum_foreign_comment":"","sum_foreign":"","sum":""},"62":{"sum_comment":"","sum_foreign_comment":"","sum_foreign":"","sum_unclear":false,"sum":""},"63":{"sum_comment":"","sum_foreign_comment":"","sum_foreign":"","sum":""},"64":{"sum_comment":"","sum_foreign_comment":"","sum_foreign":"","sum":""}},"declaration":{"notfull_lostpages":"","date":"2015-03-26T00:00:00","notfull":"","url":"http://static.declarations.com.ua/declarations/chosen_ones/judges_batch/3004_blokhin_anatolii_andriiovych.pdf"},"intro":{"declaration_year":"2014"}}