{"income":{"5":{"family_comment":"","family_unclear":false,"value":"242328","family":"69202","comment":""},"6":{"value":"242328","family_comment":"","comment_unclear":false,"family_unclear":false,"family":"69202","comment":""},"7":{"source_name_unclear":false,"value":"","family_comment":"","source_name":"","family":"","comment":"","source_name_hidden":false},"8":{"family_comment":"","value":"","family":"","comment":""},"9":{"family_comment":"","value":"","family":"","comment":""},"10":{"family_comment":"","value":"","comment_unclear":false,"family":"","comment":""},"11":{"family_comment":"","value":"","family":"","comment":""},"12":{"family_comment":"","value":"","family":"","comment":""},"13":{"family_comment":"","value":"","family":"","comment":""},"14":{"family_comment":"","value":"","family":"","comment":""},"15":{"family_comment":"","value":"","family":"","comment":""},"16":{"value":"","comment_hidden":false,"value_hidden":false,"family_comment":"","family":"","comment":"","family_comment_unclear":false},"17":{"family_comment":"","value":"","family":"","comment":""},"18":{"family_comment":"","value":"","family":"","comment":""},"19":{"family_comment":"","value":"","family":"","comment":""},"20":{"value":"","family_comment":"","value_unclear":false,"family":"","family_unclear":false,"comment_unclear":false,"comment":"","family_comment_unclear":false}},"vehicle":{"35":[{"brand_info":"","sum_rent_comment":"","year":"2007","sum_rent_unclear":false,"brand_info_hidden":false,"brand_info_unclear":false,"sum_rent":"","sum":"","brand":"Lexus GS 350","sum_comment":"","sum_comment_unclear":false,"brand_hidden":false,"sum_unclear":false,"brand_unclear":false}]},"id":"vulyk_58_116","banks":{"45":[{"sum_foreign_comment":"","sum_units":"UAH","sum_comment":"","sum_comment_unclear":false,"sum_hidden":false,"sum_foreign_units":"UAH","sum_comment_hidden":false,"sum_units_hidden":false,"sum":"","sum_foreign":""},{"sum_foreign_comment":"","sum_units":"","sum_comment":"","sum_foreign_units":"","sum":"","sum_foreign":""}],"46":[{"sum_foreign_comment":"","sum_units":"UAH","sum_comment":"","sum_foreign_units":"UAH","sum_comment_hidden":false,"sum":"","sum_foreign":""}],"47":[{"sum_foreign_comment":"","sum_units":"UAH","sum_comment":"","sum_foreign_units":"UAH","sum_comment_hidden":false,"sum":"","sum_foreign":""}],"48":[{"sum_foreign_comment":"","sum_units":"UAH","sum_comment":"","sum_foreign_units":"UAH","sum":"","sum_foreign":""}],"49":[{"sum_foreign_comment":"","sum_units":"UAH","sum_comment":"","sum_foreign_units":"UAH","sum":"","sum_foreign":""}],"50":[{"sum_foreign_comment":"","sum_units":"UAH","sum_comment":"","sum_foreign_units":"UAH","sum":"","sum_foreign":""}],"51":[{"sum_foreign_comment":"","sum_units":"UAH","sum_comment":"","sum_foreign_units":"UAH","sum_comment_hidden":false,"sum":"","sum_foreign":""},{"sum_foreign_comment":"","sum_units":"","sum_comment":"","sum_comment_hidden":false,"sum":"","sum_foreign":""}],"52":[{"sum_foreign_comment":"","sum_units":"UAH","sum_comment":"","sum_foreign_units":"UAH","sum":"","sum_foreign":""}],"53":[{"sum_foreign_comment":"","sum_units":"UAH","sum_comment":"","sum_foreign_units":"UAH","sum":"","sum_foreign":""}]},"declaration":{"additional_info_text":"","notfull_lostpages":"","date":"2015-03-24T00:00:00","notfull":"","additional_info":"","url":"http://static.declarations.com.ua/declarations/chosen_ones/mega_batch/storchak_volodymyr_iuriiovych.pdf"},"liabilities":{"54":{"sum_foreign_comment":"","sum":"","sum_hidden":false,"sum_comment":"","sum_foreign":""},"55":{"sum_foreign_comment":"","sum":"","sum_hidden":false,"sum_comment":"","sum_foreign":""},"56":{"sum_foreign_comment":"","sum":"","sum_comment":"","sum_unclear":false,"sum_foreign":""},"57":{"sum_foreign_comment":"","sum":"","sum_comment":"","sum_comment_unclear":false,"sum_comment_hidden":false,"sum_unclear":false,"sum_foreign":""},"58":{"sum_foreign_comment":"","sum":"","sum_comment":"","sum_comment_unclear":false,"sum_comment_hidden":false,"sum_unclear":false,"sum_foreign":""},"59":{"sum_foreign_comment":"","sum":"","sum_comment":"","sum_foreign":""},"60":{"sum_foreign_comment":"","sum":"","sum_comment":"","sum_comment_unclear":false,"sum_unclear":false,"sum_foreign":""},"61":{"sum_foreign_comment":"","sum":"","sum_comment":"","sum_foreign":""},"62":{"sum_foreign_comment":"","sum":"","sum_comment":"","sum_foreign":""},"63":{"sum_foreign_comment":"","sum":"","sum_comment":"","sum_comment_unclear":false,"sum_comment_hidden":false,"sum_unclear":false,"sum_foreign":""},"64":{"sum_foreign_comment":"","sum":"","sum_comment":"","sum_comment_unclear":false,"sum_comment_hidden":false,"sum_unclear":false,"sum_foreign":""}},"ft_src":"суддя вінницького апеляційного адміністративного суду\nВінницька область\nАпеляційний адміністративний суд\nВолодимир\nСторчак Л. В\nПодружжя\nСторчак М. В\nДитина\nСторчак Ю. В\nДитина\nЮрійович\nСторчак Володимир Юрійович\nВолодимир Юрійович Сторчак\nВолодимир Сторчак\nСторчак Володимир Юрійович\nСторчак Володимир Юрійович\nСторчак\nLexus GS 350\n2007\n2014\nLexus GS 350\n2007\n1200\nВінницька область\nВінницький р-н\n776\nВінницька область\nВінницький р-н\n75.9\nВінницька область\nВінницький р-н\nВінниця\nВінницька область\n64.6\nПодружжя\nСторчак Л. В\nДитина\nСторчак М. В\nДитина\nСторчак Ю. В\nСторчак Володимир Юрійович\nВолодимир Юрійович Сторчак\nВолодимир Сторчак\nСторчак Володимир Юрійович\nСторчак Володимир Юрійович\nВолодимир\nЮрійович\nАпеляційний адміністративний суд\nсуддя вінницького апеляційного адміністративного суду\nВінницька область\nСторчак\n242328\n69202\n242328\n69202\n2014\nВінницький р-н\n1200\nВінницька область\nВінницька область\nВінницький р-н\n776\nВінниця\nВінницька область\n64.6\nВінницький р-н\n75.9\nВінницька область\nСторчак Л. В\nПодружжя\nСторчак М. В\nДитина\nСторчак Ю. В\nДитина\nЮрійович\nСторчак\nВолодимир\nСторчак Володимир Юрійович\nВолодимир Юрійович Сторчак\nВолодимир Сторчак\nСторчак Володимир Юрійович\nВінницька область\nсуддя вінницького апеляційного адміністративного суду\nАпеляційний адміністративний суд\nСторчак Володимир Юрійович\n69202\n242328\n69202\n242328\n2007\nLexus GS 350\n69202\n242328\n242328\n69202\nВінницька область\nВінниця\n64.6\nВінницький р-н\nВінницька область\n1200\nВінницький р-н\nВінницька область\n776\nВінницький р-н\nВінницька область\n75.9\n2014","general":{"inn":"","name":"Володимир","inn_unclear":false,"family":[{"inn":"","inn_hidden":true,"relations_hidden":false,"family_name":"Сторчак Л. В","relations_other":"","relations":"Подружжя","name_hidden":true,"name_unclear":false},{"inn":"","inn_hidden":false,"relations_hidden":false,"family_name":"Сторчак М. В","relations_other":"","relations":"Дитина","name_hidden":false,"name_unclear":false},{"inn":"","relations":"Дитина","inn_unclear":false,"family_name":"Сторчак Ю. В","inn_hidden":true,"relations_other":"","name_hidden":false,"name_unclear":false}],"inn_hidden":true,"family_raw":"","last_name":"Сторчак","post":{"post_unclear":false,"post":"суддя вінницького апеляційного адміністративного суду","post_hidden":false,"region":"Вінницька область","region_hidden":false,"office":"Апеляційний адміністративний суд","office_hidden":false,"office_unclear":false},"full_name_suggest":{"output":"Сторчак Володимир Юрійович","input":["Сторчак Володимир Юрійович","Володимир Юрійович Сторчак","Володимир Сторчак"]},"full_name":"Сторчак Володимир Юрійович","addresses":[{"place_city_type_hidden":true,"place_district_hidden":true,"place_city_type":"","place_city_hidden":true,"place_address_unclear":false,"place_address":"","place_hidden":true,"place":"","place_district":"","place_unclear":false,"place_city":"","place_address_hidden":true,"place_district_unclear":false}],"patronymic":"Юрійович","last_name_unclear":false},"source":"VULYK","estate":{"23":[{"space_unclear":false,"costs":"","costs_comment":"","address_hidden":true,"region_hidden":false,"space_comment":"","space_hidden":false,"space":"1200","address":"Вінницький р-н","costs_comment_unclear":false,"costs_rent_comment_unclear":false,"region":"Вінницька область","address_unclear":false,"costs_rent_comment":"","costs_unclear":false,"space_units":"м²","costs_rent":""},{"costs":"","costs_comment":"","address_hidden":false,"region_hidden":false,"space_comment":"","space":"776","address":"Вінницький р-н","region":"Вінницька область","address_unclear":false,"costs_rent_comment":"","space_units":"м²","costs_rent":""},{"costs":"","costs_comment":"","address_hidden":false,"region_hidden":false,"space_comment":"","space":"","address":"","region":"","address_unclear":false,"costs_rent_comment":"","space_units":"","costs_rent":""},{"costs_rent":"","region":"","costs":"","costs_rent_comment":"","costs_comment":"","space_comment":"","space_units":"","space":"","address":""},{"costs_rent":"","costs":"","costs_rent_comment":"","costs_comment":"","space_comment":"","space_units":"","space":"","address":""}],"24":[{"space_unclear":false,"costs":"","costs_comment":"","address_hidden":true,"region_hidden":false,"space_comment":"","space_hidden":false,"space":"75.9","address":"Вінницький р-н","costs_comment_unclear":false,"costs_unclear":false,"region":"Вінницька область","address_unclear":false,"costs_rent_comment":"","space_comment_unclear":false,"space_units":"м²","costs_rent":""}],"31":[{"space_unclear":false,"costs_property_hidden":false,"address_hidden":true,"region_hidden":false,"space_comment":"","space_hidden":false,"space":"64.6","address":"Вінниця","region":"Вінницька область","costs_property":"","costs_rent_comment":"","costs_rent_hidden":false,"space_comment_unclear":false,"space_units":"м²","costs_property_comment":"","costs_rent":""}]},"intro":{"declaration_year":"2014","isnotdeclaration":"","declaration_year_hidden":false}}