{"income":{"5":{"value":"215358","family_comment":"","value_unclear":false,"family":"","family_unclear":false,"comment_unclear":false,"comment":"","family_comment_unclear":false},"6":{"value":"215358","family_comment":"","value_unclear":false,"family_unclear":false,"family":"","comment":""},"7":{"source_name_unclear":false,"value":"","value_unclear":false,"family_comment":"","source_name":"","family":"","comment":"","source_name_hidden":false},"8":{"family_comment":"","value":"","family":"","comment":""},"9":{"family_comment":"","value":"","family":"","comment":""},"10":{"family_comment":"","value":"","value_unclear":false,"family":"","comment":""},"11":{"value":"","value_unclear":false,"value_hidden":false,"family_comment":"","family":"","comment":""},"12":{"family_comment":"","value":"","family":"","comment":"","value_hidden":false},"13":{"family_comment":"","value":"","family":"","comment":""},"14":{"family_comment":"","value":"","family":"","comment":""},"15":{"family_comment":"","value":"","family":"","comment":""},"16":{"family_comment":"","value":"","family":"","comment":""},"17":{"family_comment":"","value":"","family":"","comment":""},"18":{"family_comment":"","value":"","family":"","comment":""},"19":{"family_comment":"","family_unclear":false,"value":"","family":"","comment":""},"20":{"family_comment":"","family_unclear":false,"value":"","family":"","comment":""}},"id":"vulyk_61_51","declaration":{"additional_info_text":"","notfull_lostpages":"","date":"2015-03-13T00:00:00","notfull":"","additional_info":"","url":"http://static.declarations.com.ua/declarations/chosen_ones/mega_batch/korotkyi_ihor_petrovych.pdf"},"liabilities":{"54":{"sum_foreign_comment":"","sum":"","sum_comment":"","sum_comment_unclear":false,"sum_unclear":false,"sum_foreign":""},"55":{"sum_foreign_comment":"","sum":"","sum_comment":"","sum_foreign":""},"56":{"sum_foreign_comment":"","sum":"","sum_comment":"","sum_unclear":false,"sum_foreign":""},"57":{"sum_foreign_comment":"","sum":"","sum_comment":"","sum_comment_hidden":false,"sum_unclear":false,"sum_foreign":""},"58":{"sum_foreign_comment":"","sum":"","sum_comment":"","sum_unclear":false,"sum_foreign":""},"59":{"sum_foreign_comment":"","sum":"","sum_comment":"","sum_foreign":""},"60":{"sum_foreign_comment":"","sum_foreign_hidden":false,"sum_comment":"","sum_hidden":false,"sum":"","sum_foreign":""},"61":{"sum_foreign_comment":"","sum":"","sum_comment":"","sum_foreign":""},"62":{"sum_foreign_comment":"","sum":"","sum_comment":"","sum_unclear":false,"sum_foreign":""},"63":{"sum_foreign_comment":"","sum":"","sum_comment":"","sum_hidden":false,"sum_unclear":false,"sum_foreign":""},"64":{"sum_foreign_comment":"","sum":"","sum_hidden":false,"sum_comment":"","sum_foreign":""}},"ft_src":"суддя московського районного суду м. харкова\nХарківська область\nЗагальний місцевий суд\n2747513079\nІгор\nПетрович\nКороткий Ігор Петрович\nІгор Петрович Короткий\nІгор Короткий\nКороткий Ігор Петрович\nКороткий Ігор Петрович\nКороткий\n215358\n215358\n2014\n215358\n215358\n215358\n215358\nКороткий Ігор Петрович\nІгор Петрович Короткий\nІгор Короткий\nКороткий Ігор Петрович\nКороткий Ігор Петрович\n2747513079\nІгор\nПетрович\nХарківська область\nЗагальний місцевий суд\nсуддя московського районного суду м. харкова\nКороткий\n2014\n2747513079\nПетрович\nКороткий\nІгор\nКороткий Ігор Петрович\nІгор Петрович Короткий\nІгор Короткий\nКороткий Ігор Петрович\nХарківська область\nсуддя московського районного суду м. харкова\nЗагальний місцевий суд\nКороткий Ігор Петрович\n2014","general":{"inn":"2747513079","name":"Ігор","patronymic_unclear":false,"inn_unclear":false,"patronymic":"Петрович","inn_hidden":false,"family_raw":"","last_name":"Короткий","post":{"post_unclear":false,"region_unclear":false,"post":"суддя московського районного суду м. харкова","office":"Загальний місцевий суд","region":"Харківська область","post_hidden":false,"office_hidden":false,"region_hidden":false},"full_name_suggest":{"output":"Короткий Ігор Петрович","input":["Короткий Ігор Петрович","Ігор Петрович Короткий","Ігор Короткий"]},"full_name":"Короткий Ігор Петрович","addresses":[{"place_address":"","place_district_hidden":true,"place_city_type":"","place_city_hidden":true,"place_address_unclear":false,"place_city_type_hidden":false,"place_hidden":true,"place":"","place_district":"","place_address_hidden":true,"place_city":"","place_district_unclear":false}],"patronymic_hidden":false,"last_name_unclear":false,"name_unclear":false},"source":"VULYK","intro":{"declaration_year":"2014","isnotdeclaration":"","declaration_year_hidden":false}}