{"income":{"5":{"value":"180979.37","value_unclear":false,"value_hidden":false,"family_comment":"","family":"","comment":""},"6":{"value":"168799.37","family_comment":"","value_unclear":false,"family_unclear":false,"family":"","comment":""},"7":{"source_name_unclear":false,"value":"","family_hidden":false,"family_comment":"","source_name":"","family":"","comment":""},"8":{"family_comment":"","value":"","family":"","comment":""},"9":{"family_comment":"","value":"","family":"","comment":""},"10":{"family_comment":"","value":"12180","family":"","comment":""},"11":{"family_comment":"","value":"","family":"","comment":""},"12":{"family_comment":"","value":"","family":"","comment":""},"13":{"family_comment":"","value":"","family":"","comment":""},"14":{"family_comment":"","value":"","family":"","comment":""},"15":{"family_comment":"","value":"","family":"","comment":""},"16":{"family_comment":"","value":"","comment_unclear":false,"family":"","comment":""},"17":{"family_comment":"","family_unclear":false,"value":"","family":"","comment":""},"18":{"family_comment":"","value":"","family":"","comment":""},"19":{"value":"","family_hidden":false,"value_hidden":false,"family_comment":"","family":"","comment":""},"20":{"family_comment":"","value":"","comment_unclear":false,"family":"","comment":""}},"vehicle":{"35":[{"brand_info":"1.4 л","sum_rent_comment":"","year":"2008","sum_rent_unclear":false,"brand_info_hidden":false,"brand_info_unclear":false,"year_unclear":false,"sum_rent":"","sum":"","brand":"ВАЗ 2107 0020","sum_comment":"","sum_comment_unclear":false,"brand_hidden":false,"sum_unclear":false,"brand_unclear":false},{"brand_info":"1450 куб.см.","sum_rent_comment":"","brand":"ВАЗ 2106","sum_comment":"","sum_comment_unclear":false,"year":"2000","brand_info_unclear":false,"sum":"","sum_rent":""}]},"id":"vulyk_67_149","declaration":{"additional_info_text":"","notfull_lostpages":"","date":"2015-04-07T00:00:00","notfull":"","additional_info":"","url":"http://static.declarations.com.ua/declarations/chosen_ones/mega_batch/vasylchenko_nataliia_oleksandrivna.pdf"},"liabilities":{"54":{"sum_foreign_comment":"","sum_foreign_hidden":false,"sum_comment":"","sum_comment_unclear":false,"sum_hidden":false,"sum":"500","sum_unclear":false,"sum_foreign":""},"55":{"sum_foreign_comment":"","sum":"","sum_comment":"","sum_foreign":""},"56":{"sum_foreign_comment":"","sum_foreign_hidden":false,"sum_comment":"","sum_hidden":false,"sum":"40000","sum_unclear":false,"sum_foreign":""},"57":{"sum_foreign_comment":"","sum_foreign_hidden":false,"sum_comment":"","sum_comment_unclear":false,"sum_hidden":false,"sum_comment_hidden":false,"sum_unclear":false,"sum":"","sum_foreign":""},"58":{"sum_foreign_comment":"","sum_foreign_hidden":false,"sum_comment":"","sum_comment_unclear":false,"sum_hidden":false,"sum_comment_hidden":false,"sum_unclear":false,"sum":"","sum_foreign":""},"59":{"sum_foreign_comment":"","sum":"","sum_hidden":false,"sum_comment":"","sum_foreign":""},"60":{"sum_foreign_comment":"","sum":"","sum_comment":"","sum_foreign":""},"61":{"sum_foreign_comment":"","sum_foreign_hidden":false,"sum_comment":"","sum_hidden":false,"sum":"","sum_foreign":""},"62":{"sum_foreign_comment":"","sum":"","sum_hidden":false,"sum_comment":"","sum_foreign":""},"63":{"sum_foreign_comment":"","sum":"","sum_comment":"","sum_comment_unclear":false,"sum_hidden":false,"sum_unclear":false,"sum_foreign":""},"64":{"sum_foreign_comment":"","sum":"","sum_comment":"","sum_hidden":false,"sum_unclear":false,"sum_foreign":""}},"ft_src":"500\n40000\nСуддя Новобузького районного суду Миколаївської області\nМиколаївська область\nЗагальний місцевий суд\nНаталя\nОлександрівна\nВасильченко\nВасильченко Наталя Олександрівна\nВасильченко Наталя Олександрівна\nНаталя Олександрівна Васильченко\nНаталя Васильченко\nВасильченко Наталя Олександрівна\n1.4 л\nВАЗ 2107 0020\n2008\n2000\nВАЗ 2106\n1450 куб.см.\n.1068\n.1\n.00768\n2014\n168799.37\n12180\n180979.37\n1.4 л\nВАЗ 2107 0020\n2008\nВАЗ 2106\n1450 куб.см.\n2000\n.1068\n.1\n.00768\nЗагальний місцевий суд\nСуддя Новобузького районного суду Миколаївської області\nМиколаївська область\nВасильченко Наталя Олександрівна\nНаталя Олександрівна Васильченко\nНаталя Васильченко\nВасильченко Наталя Олександрівна\nНаталя\nВасильченко Наталя Олександрівна\nВасильченко\nОлександрівна\n40000\n500\n168799.37\n180979.37\n12180\n2014\n40000\n500\nВасильченко Наталя Олександрівна\nНаталя Олександрівна Васильченко\nНаталя Васильченко\nВасильченко Наталя Олександрівна\nОлександрівна\nВасильченко\nМиколаївська область\nСуддя Новобузького районного суду Миколаївської області\nЗагальний місцевий суд\nВасильченко Наталя Олександрівна\nНаталя\n2008\nВАЗ 2107 0020\n1.4 л\n2000\n1450 куб.см.\nВАЗ 2106\n12180\n180979.37\n168799.37\n.1068\n.1\n.00768\n2014","general":{"inn":"","name":"Наталя","patronymic_unclear":false,"last_name_hidden":false,"inn_unclear":false,"patronymic":"Олександрівна","inn_hidden":true,"family_raw":"","last_name":"Васильченко","post":{"post_unclear":false,"post":"Суддя Новобузького районного суду Миколаївської області","post_hidden":false,"region":"Миколаївська область","region_hidden":false,"office":"Загальний місцевий суд","office_hidden":false,"office_unclear":false},"last_name_unclear":false,"full_name":"Васильченко Наталя Олександрівна","addresses":[{"place_city_type_hidden":false,"place_district_hidden":false,"place_city_type":"","place_city_hidden":true,"place_address_unclear":false,"place_address":"","place":"","place_district":"","place_unclear":false,"place_city":"","place_city_unclear":false,"place_hidden":false,"place_address_hidden":true,"place_district_unclear":false}],"full_name_suggest":{"output":"Васильченко Наталя Олександрівна","input":["Васильченко Наталя Олександрівна","Наталя Олександрівна Васильченко","Наталя Васильченко"]},"name_unclear":false},"source":"VULYK","estate":{"23":[{"space_hidden":false,"costs":"","costs_comment":"","costs_hidden":false,"address_hidden":false,"region_hidden":true,"space_comment":"","space_unclear":false,"space":".1068","address":"","region":"","address_unclear":false,"space_units_unclear":true,"costs_rent_hidden":false,"space_comment_unclear":false,"space_units":"га","costs_rent":"","costs_rent_comment":""},{"space_unclear":false,"costs":"","costs_comment":"","address_hidden":false,"region_hidden":false,"space_comment":"","space":".1","address":"","region":"","costs_rent_comment":"","space_comment_unclear":false,"space_units":"га","space_units_unclear":true,"costs_rent":""},{"space_unclear":false,"costs":"","costs_comment":"","address_hidden":false,"region_hidden":false,"space_comment":"","space":".00768","address":"","region":"","costs_rent_comment":"","space_units":"га","space_units_unclear":true,"costs_rent":""}]},"intro":{"declaration_year":"2014","isnotdeclaration":"","declaration_year_hidden":false}}