{"id":"vulyk_102_54","ft_src":"1992\n1091 куб. см.\nЗАЗ 1102 Таврия\n1997 куб. см.\n2008\nHonda CR-V\n44\n1/3\n66.3\n140000\nЗалишок на картковому рахунку з/п\n137347\nЗалишок на картковому рахунку, дивіденди\n70158\n2015\n1091 куб. см.\nЗАЗ 1102 Таврия\n1992\n1997 куб. см.\n2008\nHonda CR-V\n2015\nАмєлін Сергій Єгорович\nСергій Єгорович Амєлін\nСергій Амєлін\nАмєлін Сергій Єгорович\nСергій\nЄгорович\nАмєлін Сергій Єгорович\nАмєлін\nсуддя вищого адміністративного суду україни\nЗагальнодержавний регіон\nВищий адміністративний суд\n279117\n23970\n328936\n25849\n44\n66.3\n1/3\n140000\nЗалишок на картковому рахунку з/п\n137347\n70158\nЗалишок на картковому рахунку, дивіденди\n279117\n328936\n25849\n23970\nЄгорович\nАмєлін\nсуддя вищого адміністративного суду україни\nЗагальнодержавний регіон\nВищий адміністративний суд\nАмєлін Сергій Єгорович\nАмєлін Сергій Єгорович\nСергій Єгорович Амєлін\nСергій Амєлін\nАмєлін Сергій Єгорович\nСергій","estate":{"25":[{"address":"","space_units":"м²","costs_comment":"","space_comment":"1/3","region_hidden":true,"region":"","address_hidden":false,"space":"66.3","address_unclear":false,"costs_rent_comment":"","costs":"","costs_rent":""}],"27":[{"costs":"","address":"","space_units":"м²","costs_rent_comment":"","space":"44","space_comment":"","region_hidden":true,"costs_comment":"","region":"","address_hidden":false,"costs_rent":""}]},"vehicle":{"35":[{"sum_comment":"","brand_info":"1091 куб. см.","sum":"","sum_rent_comment":"","year":"1992","brand":"ЗАЗ 1102 Таврия","sum_rent":"","brand_info_unclear":false,"year_unclear":false},{"sum_comment":"","brand_info":"1997 куб. см.","sum":"","sum_rent_comment":"","year":"2008","brand":"Honda CR-V","sum_rent":"","brand_info_unclear":false}]},"source":"VULYK","income":{"5":{"family_comment":"","value":"328936","family":"","comment":""},"6":{"family_comment":"","value":"279117","family":"","comment":""},"7":{"source_name_hidden":false,"family_comment":"","family":"","value_hidden":false,"comment":"","comment_hidden":false,"value":"","source_name":""},"8":{"family_comment":"","value":"","family":"","comment":""},"9":{"family_comment":"","family":"","comment":"","comment_hidden":false,"value":"25849","family_comment_unclear":false},"10":{"family_comment":"","value":"","family":"","comment":""},"11":{"family_comment":"","value":"","family":"","comment":"","comment_hidden":false},"12":{"family_comment":"","value":"","family":"","comment":""},"13":{"family_comment":"","value":"","family":"","comment":""},"14":{"family_comment":"","value":"","family":"","comment":""},"15":{"family_comment":"","value":"","family":"","comment":""},"16":{"family_comment":"","value":"","family":"","comment":""},"17":{"family_comment":"","value":"","family":"","comment":""},"18":{"family_comment":"","value":"","family":"","comment":""},"19":{"family_comment":"","value":"","family":"","comment":""},"20":{"family_comment":"","value":"23970","family":"","comment":"","comment_hidden":false}},"banks":{"45":[{"sum_comment_unclear":false,"sum_units":"UAH","sum_foreign_units":"UAH","sum_hidden":false,"sum":"140000","sum_foreign_comment":"","sum_comment":"","sum_unclear":false,"sum_foreign":"","sum_comment_hidden":true},{"sum_comment_unclear":true,"sum_units":"UAH","sum_hidden":false,"sum":"137347","sum_foreign_comment":"","sum_comment":"Залишок на картковому рахунку з/п","sum_unclear":false,"sum_foreign":"","sum_comment_hidden":true},{"sum_comment_unclear":true,"sum_comment":"Залишок на картковому рахунку, дивіденди","sum_hidden":false,"sum":"70158","sum_foreign_comment":"","sum_foreign":"","sum_units":"UAH"}]},"declaration":{"additional_info_text":"","additional_info":"","date":"2016-03-28T00:00:00","url":"http://static.declarations.com.ua/declarations/chosen_ones/judges_batch/1128_amielin_serhii_iehorovych.pdf"},"general":{"patronymic_hidden":false,"inn":"","addresses":[{"place_city_type_hidden":false,"place_city_type":"","place_city_hidden":true,"place_hidden":true,"place_district":"","place_district_hidden":false,"place":"","place_address":"","place_address_hidden":true,"place_city":""}],"last_name":"Амєлін","full_name_suggest":{"input":["Амєлін Сергій Єгорович","Сергій Єгорович Амєлін","Сергій Амєлін"],"output":"Амєлін Сергій Єгорович"},"full_name":"Амєлін Сергій Єгорович","patronymic":"Єгорович","inn_hidden":true,"name":"Сергій","post":{"office_unclear":false,"region_unclear":false,"post":"суддя вищого адміністративного суду україни","region":"Загальнодержавний регіон","office":"Вищий адміністративний суд"},"family_raw":""},"liabilities":{"54":{"sum_comment":"","sum_hidden":false,"sum":"","sum_foreign_comment":"","sum_foreign":"","sum_comment_hidden":false},"55":{"sum_comment":"","sum_foreign_comment":"","sum_foreign":"","sum":""},"56":{"sum_comment":"","sum_foreign_comment":"","sum_foreign":"","sum":""},"57":{"sum_comment":"","sum_foreign_comment":"","sum_foreign":"","sum":"","sum_comment_hidden":false},"58":{"sum_comment":"","sum_foreign_comment":"","sum_foreign":"","sum":"","sum_comment_hidden":false},"59":{"sum_comment":"","sum_foreign_comment":"","sum_foreign":"","sum":"","sum_comment_hidden":false},"60":{"sum_comment":"","sum_hidden":false,"sum":"","sum_foreign_comment":"","sum_foreign":"","sum_comment_hidden":false},"61":{"sum_comment":"","sum_foreign_comment":"","sum_foreign":"","sum":""},"62":{"sum_comment":"","sum_foreign_comment":"","sum_foreign":"","sum_unclear":false,"sum":""},"63":{"sum_comment":"","sum_hidden":false,"sum":"","sum_foreign_comment":"","sum_foreign":"","sum_comment_hidden":false},"64":{"sum_comment":"","sum_foreign_comment":"","sum_foreign":"","sum":"","sum_comment_hidden":false}},"intro":{"declaration_year":"2015"}}