{"income":{"5":{"value":"221293","family_comment":"","comment_unclear":false,"family_unclear":false,"family":"47847","comment":""},"6":{"family_comment":"","value":"218043","family":"47847","comment":""},"7":{"source_name_unclear":false,"value":"","comment_unclear":false,"family_comment":"","source_name":"","family":"","comment":""},"8":{"family_comment":"","value":"","family":"","comment":""},"9":{"family_comment":"","value":"","family":"","comment":""},"10":{"family_comment":"","value":"1700","family":"","comment":""},"11":{"family_comment":"","value":"","family":"","comment":""},"12":{"family_comment":"","value":"","family":"","comment":""},"13":{"family_comment":"","value":"","family":"","comment":""},"14":{"family_comment":"","value":"","family":"","comment":""},"15":{"family_comment":"","value":"","family":"","comment":""},"16":{"family_comment":"","family_unclear":false,"value":"","family":"","comment":""},"17":{"family_comment":"","value":"","family":"","comment":""},"18":{"family_comment":"","value":"","family":"","comment":""},"19":{"family_comment":"","value":"","family":"","comment":""},"20":{"value":"1550","family_comment":"","comment_unclear":false,"family_unclear":false,"family":"","comment":"","family_comment_unclear":false}},"vehicle":{"35":[{"brand_info":"1598 куб. см.","sum_rent_comment":"","brand":"Chevrolet Lacetti","sum_comment":"","brand_unclear":false,"year":"2007","brand_info_unclear":false,"sum":"","sum_rent":""}]},"id":"vulyk_107_156","declaration":{"additional_info_text":"","notfull_lostpages":"","date":"2016-03-31T00:00:00","notfull":"","additional_info":"","url":"http://static.declarations.com.ua/declarations/chosen_ones/judges_batch/2135_hrynchuk_ruslan_stepanovych.pdf"},"liabilities":{"54":{"sum_foreign_comment":"","sum":"","sum_comment":"","sum_comment_unclear":false,"sum_comment_hidden":false,"sum_foreign":""},"55":{"sum_foreign_comment":"","sum":"","sum_comment":"","sum_foreign":""},"56":{"sum_foreign_comment":"","sum":"","sum_comment":"","sum_unclear":false,"sum_foreign":""},"57":{"sum_foreign_comment":"","sum":"","sum_comment":"","sum_comment_unclear":false,"sum_foreign":""},"58":{"sum_foreign_comment":"","sum":"","sum_comment":"","sum_comment_unclear":false,"sum_unclear":false,"sum_foreign":""},"59":{"sum_foreign_comment":"","sum":"","sum_comment":"","sum_unclear":false,"sum_foreign":""},"60":{"sum_foreign_comment":"","sum":"","sum_comment":"","sum_comment_unclear":false,"sum_comment_hidden":false,"sum_foreign":""},"61":{"sum_foreign_comment":"","sum":"","sum_comment":"","sum_foreign":""},"62":{"sum_foreign_comment":"","sum":"","sum_comment":"","sum_foreign":""},"63":{"sum_foreign_comment":"","sum":"","sum_comment":"","sum_foreign":""},"64":{"sum_foreign_comment":"","sum":"","sum_comment":"","sum_foreign":""}},"ft_src":"Гринчук Руслан Степанович\nсуддя апеляційного суду хмельницької області\nХмельницька область\nЗагальний апеляційний суд\nРуслан\nГринчук М. М\nПодружжя\nГринчук Д. Р\nДитина\nГринчук Руслан Степанович\nРуслан Степанович Гринчук\nРуслан Гринчук\nГринчук Руслан Степанович\nГринчук\nСтепанович\n2007\nChevrolet Lacetti\n1598 куб. см.\n47.9\n2015\n47847\n218043\n1700\n47847\n221293\n1550\n1598 куб. см.\n2007\nChevrolet Lacetti\n2015\nГринчук\nПодружжя\nГринчук М. М\nДитина\nГринчук Д. Р\nГринчук Руслан Степанович\nРуслан Степанович Гринчук\nРуслан Гринчук\nГринчук Руслан Степанович\nРуслан\nСтепанович\nГринчук Руслан Степанович\nЗагальний апеляційний суд\nсуддя апеляційного суду хмельницької області\nХмельницька область\n218043\n47847\n1550\n221293\n47847\n1700\n47.9\nГринчук М. М\nПодружжя\nГринчук Д. Р\nДитина\nГринчук\nСтепанович\nсуддя апеляційного суду хмельницької області\nХмельницька область\nЗагальний апеляційний суд\nГринчук Руслан Степанович\nГринчук Руслан Степанович\nРуслан Степанович Гринчук\nРуслан Гринчук\nГринчук Руслан Степанович\nРуслан\n2007\n1598 куб. см.\nChevrolet Lacetti\n1700\n1550\n221293\n47847\n47847\n218043\n47.9\n2015","general":{"inn":"","inn_hidden":true,"last_name":"Гринчук","post":{"post_unclear":false,"office":"Загальний апеляційний суд","post":"суддя апеляційного суду хмельницької області","region":"Хмельницька область"},"name":"Руслан","full_name":"Гринчук Руслан Степанович","family_raw":"","addresses":[{"place_district":"","place_city_hidden":false,"place_city":"","place_city_type_hidden":false,"place_district_hidden":false,"place_city_type":"","place_address_hidden":true,"place_address":"","place_hidden":true,"place":""}],"family":[{"inn":"","relations":"Подружжя","relations_other":"","inn_hidden":true,"family_name":"Гринчук М. М","name_hidden":true,"name_unclear":false},{"inn":"","relations":"Дитина","relations_other":"","inn_hidden":false,"family_name":"Гринчук Д. Р","name_hidden":false,"name_unclear":false}],"full_name_suggest":{"output":"Гринчук Руслан Степанович","input":["Гринчук Руслан Степанович","Руслан Степанович Гринчук","Руслан Гринчук"]},"patronymic":"Степанович"},"source":"VULYK","estate":{"25":[{"space_hidden":false,"costs":"","costs_comment":"","address_hidden":false,"region_hidden":true,"space_comment":"","space_unclear":false,"space":"47.9","address":"","region":"","costs_rent_comment":"","space_units":"м²","costs_rent":""}]},"intro":{"declaration_year":"2015","isnotdeclaration":""}}