{"income":{"5":{"value":"208406","family_unclear":false,"family_hidden":false,"family_comment":"","family":"44057","comment":""},"6":{"family_comment":"","value":"208406","family_hidden":false,"comment":"","family":"44057"},"7":{"family_comment":"","value":"","source_name":"","family":"","comment":""},"8":{"family_comment":"","value":"","family":"","comment":""},"9":{"value":"","comment_unclear":false,"family_hidden":false,"family_comment":"","family":"","comment":""},"10":{"family_comment":"","value":"","family":"","comment":""},"11":{"family_comment":"","value":"","family":"","comment":""},"12":{"family_comment":"","value":"","family":"","comment":""},"13":{"family_comment":"","value":"","family":"","comment":""},"14":{"family_comment":"","value":"","family":"","comment":""},"15":{"family_comment":"","value":"","value_unclear":false,"family":"","comment":""},"16":{"family_comment":"","value":"","family":"","comment":""},"17":{"family_comment":"","value":"","family":"","comment":""},"18":{"family_comment":"","value":"","family":"","comment":""},"19":{"family_comment":"","value":"","family":"","comment":""},"20":{"value":"","comment_unclear":false,"comment_hidden":false,"family_hidden":false,"value_hidden":false,"family_comment":"","value_unclear":false,"family":"","comment":"","family_comment_hidden":false}},"vehicle":{"40":[{"brand_info":"1569 куб. см.","sum_rent_comment":"","brand":"Kia Cerato","sum_comment":"","year":"2008","brand_info_hidden":false,"sum":"","sum_rent":""}]},"id":"vulyk_41_62","banks":{"45":[{"sum_foreign_comment":"","sum_units":"UAH","sum_comment":"","sum_foreign_unclear":false,"sum_foreign_units":"UAH","sum_hidden":false,"sum_comment_hidden":false,"sum":"","sum_foreign":""},{"sum_foreign_comment":"","sum_units":"","sum_comment":"","sum_foreign_unclear":false,"sum_foreign_units":"","sum":"","sum_foreign":""}],"46":[{"sum_foreign_comment":"","sum_units":"UAH","sum_comment":"","sum_foreign_units":"UAH","sum_comment_hidden":false,"sum_unclear":false,"sum":"","sum_foreign":""},{"sum_foreign_comment":"","sum_units":"","sum_comment":"","sum_foreign_units":"","sum":"","sum_unclear":false,"sum_foreign":""}],"47":[{"sum_foreign_comment":"","sum_units":"UAH","sum_comment":"","sum_foreign_units":"UAH","sum":"","sum_foreign":""},{"sum_foreign_comment":"","sum_units":"","sum_comment":"","sum_foreign_units":"","sum":"","sum_foreign":""}],"48":[{"sum_foreign_comment":"","sum_units":"UAH","sum_comment":"","sum_foreign_units":"UAH","sum":"","sum_foreign":""}],"49":[{"sum_foreign_comment":"","sum_units":"UAH","sum_comment":"","sum_foreign_units":"UAH","sum":"","sum_foreign":""}],"50":[{"sum_foreign_comment":"","sum_units":"UAH","sum_comment":"","sum_foreign_units":"UAH","sum":"","sum_foreign":""}],"51":[{"sum_foreign_comment":"","sum_units":"UAH","sum_comment":"","sum_hidden":false,"sum_foreign_units":"UAH","sum_comment_hidden":false,"sum_unclear":false,"sum":"","sum_foreign":""},{"sum_foreign_comment":"","sum_units":"","sum_comment":"","sum_foreign_units":"","sum":"","sum_foreign":""}],"52":[{"sum_foreign_comment":"","sum_units":"UAH","sum_comment":"","sum_foreign_units":"UAH","sum_comment_hidden":false,"sum_unclear":false,"sum":"","sum_foreign":""}],"53":[{"sum_foreign_comment":"","sum_units":"UAH","sum_comment":"","sum_foreign_units":"UAH","sum_comment_hidden":false,"sum":"","sum_foreign":""},{"sum_foreign_comment":"","sum_units":"","sum_comment":"","sum_foreign_units":"","sum":"","sum_foreign":""},{"sum_foreign_comment":"","sum_units":"","sum_comment":"","sum_foreign_units":"","sum":"","sum_foreign":""}]},"declaration":{"date":"2015-03-15T00:00:00","additional_info_text":"","additional_info":"","url":"http://static.declarations.com.ua/declarations/chosen_ones/mega_batch/zakharchuk-borysenko_nataliia_vitaliivna.pdf"},"liabilities":{"54":{"sum_foreign_comment":"","sum_comment_hidden":false,"sum":"","sum_comment":"","sum_foreign":""},"55":{"sum_foreign_comment":"","sum":"","sum_comment":"","sum_foreign":""},"56":{"sum_foreign_comment":"","sum":"","sum_hidden":false,"sum_comment":"","sum_foreign":""},"57":{"sum_foreign_comment":"","sum":"343359","sum_comment":"","sum_comment_hidden":false,"sum_unclear":true,"sum_foreign":""},"58":{"sum_foreign_comment":"","sum_comment_hidden":false,"sum":"10359","sum_comment":"","sum_foreign":""},"59":{"sum_foreign_comment":"","sum":"","sum_comment":"","sum_foreign":""},"60":{"sum_foreign_comment":"","sum_comment_hidden":false,"sum":"","sum_comment":"","sum_foreign":""},"61":{"sum_foreign_comment":"","sum":"","sum_comment":"","sum_foreign":""},"62":{"sum_foreign_comment":"","sum":"","sum_comment":"","sum_foreign":""},"63":{"sum_foreign_comment":"","sum":"","sum_comment":"","sum_comment_hidden":false,"sum_unclear":false,"sum_foreign":""},"64":{"sum_foreign_comment":"","sum_comment_hidden":false,"sum":"","sum_comment":"","sum_foreign":""}},"ft_src":"343359\n10359\nсуддя дніпропетровського окружного адміністративного суду\nДніпропетровська область\nАдміністративний місцевий суд\nНаталія\nБорисенко Андрій Васильович\nПодружжя\nГунько Іван\nДитина\nВіталіївна\nЗахарчук-Борисенко Наталія Віталіївна\nНаталія Віталіївна Захарчук-Борисенко\nНаталія Захарчук-Борисенко\nЗахарчук-Борисенко Наталія Віталіївна\nЗахарчук-Борисенко\nЗахарчук-Борисенко Наталія Віталіївна\n1569 куб. см.\n2008\nKia Cerato\n2014\nKia Cerato\n1569 куб. см.\n2008\n37\n1/4 частина житлового будинку\nм. Дніпропетровськ\nДніпропетровська область\nПодружжя\nБорисенко Андрій Васильович\nДитина\nГунько Іван\nЗахарчук-Борисенко Наталія Віталіївна\nНаталія Віталіївна Захарчук-Борисенко\nНаталія Захарчук-Борисенко\nЗахарчук-Борисенко Наталія Віталіївна\nЗахарчук-Борисенко Наталія Віталіївна\nНаталія\nВіталіївна\nАдміністративний місцевий суд\nсуддя дніпропетровського окружного адміністративного суду\nДніпропетровська область\nЗахарчук-Борисенко\n343359\n10359\n208406\n44057\n208406\n44057\n2014\n10359\n343359\nДніпропетровська область\n1/4 частина житлового будинку\nм. Дніпропетровськ\n37\nБорисенко Андрій Васильович\nПодружжя\nГунько Іван\nДитина\nВіталіївна\nЗахарчук-Борисенко\nНаталія\nЗахарчук-Борисенко Наталія Віталіївна\nНаталія Віталіївна Захарчук-Борисенко\nНаталія Захарчук-Борисенко\nЗахарчук-Борисенко Наталія Віталіївна\nДніпропетровська область\nсуддя дніпропетровського окружного адміністративного суду\nАдміністративний місцевий суд\nЗахарчук-Борисенко Наталія Віталіївна\n44057\n208406\n44057\n208406\nKia Cerato\n1569 куб. см.\n2008\n208406\n44057\n44057\n208406\n1/4 частина житлового будинку\nм. Дніпропетровськ\nДніпропетровська область\n37\n2014","general":{"inn":"","name":"Наталія","family":[{"inn":"","relations":"Подружжя","relations_hidden":false,"inn_hidden":true,"family_name":"Борисенко Андрій Васильович","name_hidden":true,"name_unclear":false},{"inn":"","relations":"Дитина","relations_other":"","inn_hidden":false,"family_name":"Гунько Іван","name_hidden":false,"name_unclear":false}],"patronymic":"Віталіївна","inn_hidden":true,"family_raw":"","last_name":"Захарчук-Борисенко","post":{"post_unclear":false,"post":"суддя дніпропетровського окружного адміністративного суду","post_hidden":false,"region":"Дніпропетровська область","region_hidden":false,"office":"Адміністративний місцевий суд","office_hidden":false},"last_name_unclear":false,"full_name":"Захарчук-Борисенко Наталія Віталіївна","addresses":[{"place_district":"","place_city_hidden":true,"place_city":"","place_city_type_hidden":true,"place_district_hidden":true,"place_city_type":"","place_address_hidden":true,"place_address":"","place_hidden":true,"place":""}],"patronymic_hidden":false,"full_name_suggest":{"output":"Захарчук-Борисенко Наталія Віталіївна","input":["Захарчук-Борисенко Наталія Віталіївна","Наталія Віталіївна Захарчук-Борисенко","Наталія Захарчук-Борисенко"]},"name_unclear":false},"source":"VULYK","estate":{"23":[{"region_unclear":false,"space_unclear":false,"costs":"","costs_comment":"","address_hidden":false,"region_hidden":false,"space_comment":"","space":"","address":"","costs_comment_unclear":false,"region":"","space_units_unclear":false,"space_comment_hidden":false,"space_units":"м²","costs_rent":"","costs_rent_comment":""},{"costs_rent":"","space_unclear":false,"region":"","costs":"","costs_rent_comment":"","costs_comment":"","space_comment":"","space_units":"","space":"","address":""},{"costs_rent":"","region":"","costs":"","costs_rent_comment":"","costs_comment":"","space_comment":"","space_units":"","space":"","address":""}],"30":[{"costs_rent":"","region":"Дніпропетровська область","costs_property":"","costs_rent_comment":"","address_hidden":true,"region_hidden":false,"space_comment":"1/4 частина житлового будинку","costs_property_comment":"","space_units":"м²","space":"37","address":"м. Дніпропетровськ"}]},"intro":{"declaration_year":"2014"}}