{"income":{"5":{"family_comment":"","value":"236322","family":"661068","comment":""},"6":{"family_comment":"","value":"236322","family":"","comment":""},"7":{"value":"","comment_hidden":false,"family_comment":"","source_name":"","family":"","comment":"","source_name_hidden":false},"8":{"family_comment":"","value":"","family_hidden":false,"comment":"","family":""},"9":{"value":"","family_comment":"","value_unclear":false,"family_unclear":false,"family":"","comment":""},"10":{"family_comment":"","value":"","family":"","comment":""},"11":{"family_comment":"","value":"","family":"","comment":""},"12":{"family_comment":"","value":"","family":"","comment":""},"13":{"family_comment":"","value":"","family":"","comment":""},"14":{"family_comment":"","value":"","family":"","comment":""},"15":{"family_comment":"","value":"","family":"","comment":""},"16":{"family_comment":"","value":"","family":"","comment":""},"17":{"family_comment":"","value":"","family":"661068","comment":""},"18":{"family_comment":"","value":"","family":"","comment":""},"19":{"family_comment":"","value":"","family":"","comment":""},"20":{"value":"","value_unclear":false,"family_hidden":false,"family_comment":"","family":"","comment":""}},"vehicle":{"35":[{"brand_info":"1596 куб. см., 160 к. с","sum_rent_comment":"","year":"2011","brand_info_hidden":false,"brand_info_unclear":false,"year_unclear":false,"sum_rent":"","sum":"","brand":"Ford Mondeo","sum_comment":"","sum_comment_unclear":false,"brand_hidden":false,"brand_unclear":false}]},"id":"vulyk_109_123","banks":{"51":[{"sum_foreign_comment":"","sum_unclear":false,"sum_units":"UAH","sum_comment":"","sum_foreign_units":"UAH","sum_comment_hidden":false,"sum_units_hidden":false,"sum":"5","sum_foreign":""},{"sum_foreign_comment":"","sum_units":"OTHER","sum_comment":"крб. СРСР","sum":"12163","sum_unclear":false,"sum_foreign":""}]},"declaration":{"additional_info_text":"","notfull_lostpages":"","date":"2016-03-30T00:00:00","notfull":"","additional_info":"","url":"http://static.declarations.com.ua/declarations/chosen_ones/judges_batch/2580_radchenia_dmytro_ivanovych_2015.pdf"},"liabilities":{"54":{"sum_foreign_comment":"","sum":"","sum_comment":"","sum_hidden":false,"sum_comment_hidden":false,"sum_unclear":false,"sum_foreign":""},"55":{"sum_foreign_comment":"","sum":"","sum_comment":"","sum_comment_unclear":false,"sum_foreign":""},"56":{"sum_foreign_comment":"","sum":"","sum_comment":"","sum_foreign":""},"57":{"sum_foreign_comment":"","sum_comment_hidden":false,"sum":"","sum_comment":"","sum_foreign":""},"58":{"sum_foreign_comment":"","sum_comment_hidden":false,"sum":"","sum_comment":"","sum_foreign":""},"59":{"sum_foreign_comment":"","sum":"","sum_comment":"","sum_foreign":""},"60":{"sum_foreign_comment":"","sum":"","sum_comment":"","sum_foreign":""},"61":{"sum_foreign_comment":"","sum":"","sum_comment":"","sum_foreign":""},"62":{"sum_foreign_comment":"","sum":"","sum_comment":"","sum_foreign":""},"63":{"sum_foreign_comment":"","sum":"","sum_comment":"","sum_foreign":""},"64":{"sum_foreign_comment":"","sum":"","sum_comment":"","sum_foreign":""}},"ft_src":"суддя господарського суду хмельницької області\nХмельницька область\nГосподарський місцевий суд\nДмитро\nРадченя О. М\nПодружжя\nРадченя В. Д\nДитина\nІванович\nРадченя Дмитро Іванович\nРадченя\nРадченя Дмитро Іванович\nДмитро Іванович Радченя\nДмитро Радченя\nРадченя Дмитро Іванович\n1596 куб. см., 160 к. с\nFord Mondeo\n2011\n.1\n.0021\n42.3\n112\n5\nкрб. СРСР\n12163\nOTHER\n2015\n1596 куб. см., 160 к. с\nFord Mondeo\n2011\n2015\nПодружжя\nРадченя О. М\nДитина\nРадченя В. Д\nРадченя Дмитро Іванович\nДмитро Іванович Радченя\nДмитро Радченя\nРадченя Дмитро Іванович\nДмитро\nРадченя Дмитро Іванович\nРадченя\nГосподарський місцевий суд\nХмельницька область\nсуддя господарського суду хмельницької області\nІванович\n236322\n661068\n236322\n661068\n.1\n.0021\n42.3\n112\n5\nкрб. СРСР\nOTHER\n12163\n236322\n661068\n236322\n661068\nПодружжя\nРадченя О. М\nДитина\nРадченя В. Д\nДмитро\nІванович\nРадченя\nРадченя Дмитро Іванович\nДмитро Іванович Радченя\nДмитро Радченя\nРадченя Дмитро Іванович\nХмельницька область\nГосподарський місцевий суд\nсуддя господарського суду хмельницької області\nРадченя Дмитро Іванович\n2011\nFord Mondeo\n1596 куб. см., 160 к. с\n661068\n236322\n661068\n236322\n42.3\n.1\n.0021\n112\n5\nкрб. СРСР\nOTHER\n12163\n2015","general":{"name_hidden":false,"name":"Дмитро","inn":"","inn_unclear":false,"family":[{"inn":"","relations":"Подружжя","relations_hidden":false,"inn_hidden":true,"relations_other":"","name_hidden":false,"family_name":"Радченя О. М","name_unclear":false},{"inn":"","relations":"Дитина","relations_other":"","inn_hidden":false,"family_name":"Радченя В. Д","name_hidden":false,"name_unclear":false}],"inn_hidden":true,"family_raw":"","last_name":"Радченя","post":{"region_unclear":false,"region":"Хмельницька область","post":"суддя господарського суду хмельницької області","region_hidden":false,"office":"Господарський місцевий суд","office_hidden":false,"office_unclear":false},"full_name":"Радченя Дмитро Іванович","patronymic":"Іванович","full_name_suggest":{"output":"Радченя Дмитро Іванович","input":["Радченя Дмитро Іванович","Дмитро Іванович Радченя","Дмитро Радченя"]}},"source":"VULYK","estate":{"23":[{"space_unclear":false,"costs":"","costs_rent_unclear":false,"costs_comment":"","address_hidden":false,"region_hidden":false,"space_comment":"","space":".1","address":"","region":"","costs_rent_comment":"","space_units":"га","costs_rent":""},{"space_hidden":false,"costs":"","costs_rent_unclear":false,"costs_comment":"","address_hidden":false,"region_hidden":false,"space_comment":"","space":".0021","address":"","region":"","costs_rent_comment":"","space_units":"га","costs_rent":""}],"25":[{"space_unclear":false,"costs":"","costs_comment":"","address_hidden":false,"region_hidden":false,"space_comment":"","space_hidden":false,"space":"112","address":"","region":"","costs_rent_comment":"","space_units":"м²","space_units_hidden":false,"costs_rent":""}],"31":[{"space_hidden":false,"costs_property_comment":"","address_hidden":true,"region_hidden":false,"space_comment":"","space":"42.3","address":"","region":"","costs_property":"","costs_rent_comment":"","space_units":"м²","space_units_hidden":false,"costs_rent":""}]},"intro":{"declaration_year":"2015","isnotdeclaration":""}}