{"income":{"5":{"value":"285225.24","value_unclear":false,"family_hidden":false,"family_comment":"","family":"10417","comment":""},"6":{"family_comment":"","value":"264650.65","family":"","comment":""},"7":{"family_comment":"","value":"","source_name":"","family":"","comment":""},"8":{"family_comment":"","value":"","family":"","comment":""},"9":{"family_comment":"","value":"20574.59","family":"","comment":""},"10":{"family_comment":"","value":"","family":"","comment":""},"11":{"family_comment":"","value":"","family_hidden":false,"comment":"","family":""},"12":{"family_comment":"","value":"","family":"","comment":""},"13":{"family_comment":"","value":"","family":"","comment":""},"14":{"family_comment":"","value":"","family":"","comment":""},"15":{"family_comment":"","value":"","family":"","comment":""},"16":{"family_comment":"","value":"","family":"","comment":""},"17":{"family_comment":"","value":"","family":"","comment":"","family_comment_unclear":false},"18":{"family_comment":"","value":"","family":"","comment":""},"19":{"family_comment":"","value":"","family":"","comment":""},"20":{"value":"","family_unclear":false,"family_hidden":false,"family_comment":"","family":"10417","comment":""}},"vehicle":{"35":[{"brand_info":"2000, 77 кВт , 110 к. с","sum":"","brand":"Volkswagen","sum_comment":"","brand_unclear":false,"year":"2012","brand_hidden":false,"brand_info_hidden":false,"brand_info_unclear":false,"sum_rent_comment":"","sum_rent":""}]},"id":"vulyk_103_96","declaration":{"date":"2016-03-24T00:00:00","additional_info_text":"","additional_info":"","url":"http://static.declarations.com.ua/declarations/chosen_ones/judges_batch/1320_chuiko_olena_heorhiivna.pdf"},"liabilities":{"54":{"sum_foreign_comment":"","sum_foreign_hidden":false,"sum_comment":"","sum_foreign_comment_hidden":false,"sum_hidden":false,"sum_foreign_comment_unclear":false,"sum_comment_hidden":false,"sum_unclear":false,"sum":"","sum_foreign":""},"55":{"sum_foreign_comment":"","sum":"","sum_comment":"","sum_foreign":""},"56":{"sum_foreign_comment":"","sum":"","sum_comment":"","sum_foreign":""},"57":{"sum_foreign_comment":"","sum_foreign_hidden":false,"sum_comment":"","sum_foreign_comment_hidden":false,"sum_hidden":false,"sum_comment_hidden":false,"sum":"","sum_foreign":""},"58":{"sum_foreign_comment":"","sum_foreign_hidden":false,"sum_comment":"","sum_foreign_comment_hidden":false,"sum_hidden":false,"sum_comment_hidden":false,"sum":"","sum_foreign":""},"59":{"sum_foreign_comment":"","sum_foreign_hidden":false,"sum_comment":"","sum_foreign_comment_hidden":false,"sum_hidden":false,"sum_comment_hidden":false,"sum":"","sum_foreign":""},"60":{"sum_foreign_comment":"","sum":"","sum_comment":"","sum_hidden":false,"sum_comment_hidden":false,"sum_foreign":""},"61":{"sum_foreign_comment":"","sum":"","sum_comment":"","sum_foreign":""},"62":{"sum_foreign_comment":"","sum_comment_hidden":false,"sum":"","sum_comment":"","sum_foreign":""},"63":{"sum_foreign_comment":"","sum":"","sum_comment":"","sum_foreign":""},"64":{"sum_foreign_comment":"","sum":"","sum_comment":"","sum_foreign":""}},"ft_src":"Чуйко Олена Георгіївна\nсуддя вищого спецiалiзованого суду україни з розгляду цивiльних і кримiнальних справ\nЗагальнодержавний регіон\nВищий спеціалізований суд з розгляду цивільних і кримінальних справ\nОлена\nХабанець В. П\nПодружжя\nЧуйко А. В\nДитина\nЧуйко Олена Георгіївна\nОлена Георгіївна Чуйко\nОлена Чуйко\nЧуйко Олена Георгіївна\nЧуйко\nГеоргіївна\nVolkswagen\n2000, 77 кВт , 110 к. с\n2012\n6300\n34.7\n7.1\n85\n2015\n264650.65\n20574.59\n10417\n285225.24\n10417\n2000, 77 кВт , 110 к. с\n2012\nVolkswagen\n6300\n7.1\n34.7\n85\nЧуйко\nЧуйко Олена Георгіївна\nОлена Георгіївна Чуйко\nОлена Чуйко\nЧуйко Олена Георгіївна\nЧуйко Олена Георгіївна\nГеоргіївна\nПодружжя\nХабанець В. П\nЧуйко А. В\nДитина\nОлена\nВищий спеціалізований суд з розгляду цивільних і кримінальних справ\nсуддя вищого спецiалiзованого суду україни з розгляду цивiльних і кримiнальних справ\nЗагальнодержавний регіон\n264650.65\n10417\n285225.24\n10417\n20574.59\n2015\nПодружжя\nХабанець В. П\nДитина\nЧуйко А. В\nЧуйко\nГеоргіївна\nсуддя вищого спецiалiзованого суду україни з розгляду цивiльних і кримiнальних справ\nВищий спеціалізований суд з розгляду цивільних і кримінальних справ\nЗагальнодержавний регіон\nЧуйко Олена Георгіївна\nЧуйко Олена Георгіївна\nОлена Георгіївна Чуйко\nОлена Чуйко\nЧуйко Олена Георгіївна\nОлена\nVolkswagen\n2000, 77 кВт , 110 к. с\n2012\n20574.59\n10417\n285225.24\n10417\n264650.65\n34.7\n6300\n7.1\n85\n2015","general":{"inn":"","inn_hidden":true,"last_name":"Чуйко","post":{"region":"Загальнодержавний регіон","region_unclear":false,"post":"суддя вищого спецiалiзованого суду україни з розгляду цивiльних і кримiнальних справ","office_unclear":false,"office":"Вищий спеціалізований суд з розгляду цивільних і кримінальних справ"},"name":"Олена","full_name":"Чуйко Олена Георгіївна","family_raw":"","addresses":[{"place_district":"","place_city_hidden":true,"place_city":"","place_city_type_hidden":false,"place_district_hidden":false,"place_city_type":"","place_address_hidden":true,"place_address":"","place_hidden":true,"place":""}],"family":[{"inn":"","relations":"Подружжя","relations_hidden":false,"inn_hidden":true,"relations_other":"","name_hidden":true,"family_name":"Хабанець В. П","name_unclear":false},{"inn":"","family_name":"Чуйко А. В","relations":"Дитина","inn_hidden":false,"relations_other":""}],"full_name_suggest":{"output":"Чуйко Олена Георгіївна","input":["Чуйко Олена Георгіївна","Олена Георгіївна Чуйко","Олена Чуйко"]},"patronymic":"Георгіївна"},"source":"VULYK","estate":{"23":[{"costs_rent":"","region":"","costs":"","costs_rent_comment":"","costs_comment":"","address_hidden":false,"region_hidden":true,"space_comment":"","space_units":"м²","space":"6300","address":""}],"25":[{"costs":"","costs_comment":"","address_hidden":false,"region_hidden":true,"space_comment":"","space":"85","address":"","region":"","costs_rent_comment":"","space_comment_unclear":false,"space_comment_hidden":false,"space_units":"м²","costs_rent":""}],"26":[{"costs_rent":"","region":"","costs":"","costs_rent_comment":"","costs_comment":"","address_hidden":false,"region_hidden":true,"space_comment":"","space_units":"м²","space":"7.1","address":""}],"31":[{"space_hidden":false,"address_hidden":true,"region_hidden":true,"space_comment":"","space":"34.7","address":"","costs_property":"","costs_rent_comment":"","address_unclear":false,"space_units":"м²","costs_property_comment":"","costs_rent":""}]},"intro":{"declaration_year":"2015"}}