{"income":{"5":{"family_comment":"","family_unclear":false,"value":"181577","family":"25537","comment":""},"6":{"value":"181577","family_comment":"","value_unclear":false,"family_unclear":false,"family":"25537","comment":""},"7":{"source_name_unclear":false,"value":"","family_comment":"","source_name":"","family":"","comment":"","source_name_hidden":false},"8":{"family_comment":"","value":"","family":"","comment":""},"9":{"family_comment":"","family_unclear":false,"value":"","family":"","comment":""},"10":{"family_comment":"","value":"","family":"","comment":""},"11":{"family_comment":"","value":"","family":"","comment":""},"12":{"family_comment":"","value":"","family":"","comment":""},"13":{"family_comment":"","value":"","family":"","comment":""},"14":{"family_comment":"","value":"","family":"","comment":""},"15":{"family_comment":"","value":"","family":"","comment":""},"16":{"family_comment":"","family_unclear":false,"value":"","family":"","comment":""},"17":{"family_comment":"","family_unclear":false,"value":"","family":"","comment":""},"18":{"family_comment":"","value":"","family":"","comment":""},"19":{"family_comment":"","value":"","family":"","comment":""},"20":{"family_comment":"","value":"","comment_unclear":false,"family":"","comment":""}},"vehicle":{"35":[{"brand_info":"1600","sum":"","brand":"Daewoo Lanos","sum_comment":"","brand_unclear":false,"year":"2009","brand_hidden":false,"brand_info_hidden":false,"brand_info_unclear":false,"sum_rent_comment":"","sum_rent":""}],"40":[{"brand_info":"1600","sum":"","brand":"Daewoo Lanos","sum_comment":"","brand_unclear":false,"year":"2009","brand_hidden":false,"brand_info_hidden":false,"brand_info_unclear":false,"sum_rent_comment":"","sum_rent":""}]},"id":"vulyk_95_41","declaration":{"additional_info_text":"","notfull_lostpages":"","date":"2016-03-30T00:00:00","notfull":"","additional_info":"","url":"http://static.declarations.com.ua/declarations/chosen_ones/judges_batch/42_baranov_oleh_ivanovych_2015.pdf"},"liabilities":{"54":{"sum_foreign_comment":"","sum":"","sum_comment":"","sum_hidden":false,"sum_comment_hidden":false,"sum_unclear":false,"sum_foreign":""},"55":{"sum_foreign_comment":"","sum":"","sum_comment":"","sum_foreign":""},"56":{"sum_foreign_comment":"","sum":"","sum_comment":"","sum_foreign":""},"57":{"sum_foreign_comment":"","sum":"","sum_comment":"","sum_hidden":false,"sum_comment_hidden":false,"sum_unclear":false,"sum_foreign":""},"58":{"sum_foreign_comment":"","sum":"","sum_comment":"","sum_hidden":false,"sum_comment_hidden":false,"sum_unclear":false,"sum_foreign":""},"59":{"sum_foreign_comment":"","sum":"","sum_comment":"","sum_foreign":""},"60":{"sum_foreign_comment":"","sum":"","sum_comment":"","sum_hidden":false,"sum_comment_hidden":false,"sum_foreign":""},"61":{"sum_foreign_comment":"","sum":"","sum_comment":"","sum_foreign":""},"62":{"sum_foreign_comment":"","sum":"","sum_comment":"","sum_unclear":false,"sum_foreign":""},"63":{"sum_foreign_comment":"","sum":"","sum_comment":"","sum_unclear":false,"sum_foreign":""},"64":{"sum_foreign_comment":"","sum":"","sum_comment":"","sum_foreign":""}},"ft_src":"суддя катеринопільського районного суду черкаської області\nЧеркаська область\nЗагальний місцевий суд\nБаранов Олег Іванович\nБаранов\nОлег\nПодружжя\nДитина\nБаранов Олег Іванович\nОлег Іванович Баранов\nОлег Баранов\nБаранов Олег Іванович\nІванович\nDaewoo Lanos\n1600\n2009\nDaewoo Lanos\n1600\n2009\n55.9\n55.9\n2015\n25537\n181577\n25537\n181577\nDaewoo Lanos\n1600\n2009\nDaewoo Lanos\n1600\n2009\n55.9\n55.9\nІванович\nПодружжя\nДитина\nБаранов\nБаранов Олег Іванович\nОлег Іванович Баранов\nОлег Баранов\nБаранов Олег Іванович\nОлег\nБаранов Олег Іванович\nЗагальний місцевий суд\nсуддя катеринопільського районного суду черкаської області\nЧеркаська область\n181577\n25537\n181577\n25537\n2015\nПодружжя\nДитина\nІванович\nБаранов\nЧеркаська область\nЗагальний місцевий суд\nсуддя катеринопільського районного суду черкаської області\nБаранов Олег Іванович\nБаранов Олег Іванович\nОлег Іванович Баранов\nОлег Баранов\nБаранов Олег Іванович\nОлег\nDaewoo Lanos\n1600\n2009\nDaewoo Lanos\n1600\n2009\n25537\n181577\n181577\n25537\n55.9\n55.9\n2015","general":{"inn":"","family_raw":"","last_name":"Баранов","post":{"post":"суддя катеринопільського районного суду черкаської області","region":"Черкаська область","candidate":"","office_hidden":false,"office":"Загальний місцевий суд","office_unclear":false},"name":"Олег","full_name":"Баранов Олег Іванович","inn_hidden":true,"family":[{"inn":"","inn_hidden":true,"inn_unclear":false,"relations_hidden":false,"relations_other":"","relations":"Подружжя","name_hidden":true,"family_name":"","name_unclear":false},{"inn":"","inn_hidden":false,"inn_unclear":false,"relations_hidden":false,"relations_other":"","relations":"Дитина","name_hidden":true,"family_name":"","name_unclear":false}],"full_name_suggest":{"output":"Баранов Олег Іванович","input":["Баранов Олег Іванович","Олег Іванович Баранов","Олег Баранов"]},"patronymic":"Іванович"},"source":"VULYK","estate":{"25":[{"space_unclear":false,"costs":"","costs_comment":"","address_hidden":false,"region_hidden":false,"space_comment":"","space_hidden":false,"space":"55.9","address":"","region":"","address_unclear":false,"costs_rent_comment":"","space_comment_unclear":false,"space_units":"м²","costs_rent":""}],"31":[{"space_unclear":false,"address_hidden":false,"region_hidden":false,"space_comment":"","space":"55.9","address":"","region":"","costs_property":"","costs_rent_comment":"","space_comment_unclear":false,"space_units":"м²","costs_property_comment":"","costs_rent":""}]},"intro":{"declaration_year":"2015","isnotdeclaration":""}}