{"income":{"5":{"value":"200031","value_unclear":false,"comment_hidden":false,"family_comment":"","family":"51491","comment":""},"6":{"family_comment":"","value":"200031","family":"51491","comment":"","value_hidden":false},"7":{"family_comment":"","value":"","source_name":"","family":"","comment":""},"8":{"family_comment":"","value":"","family":"","comment":""},"9":{"family_comment":"","value":"","comment_hidden":false,"family":"","comment":""},"10":{"family_comment":"","value":"","family":"","comment":""},"11":{"family_comment":"","value":"","family":"","comment":""},"12":{"family_comment":"","value":"","family":"","comment":""},"13":{"family_comment":"","value":"","family":"","comment":""},"14":{"family_comment":"","value":"","family":"","comment":""},"15":{"family_comment":"","value":"","family":"","comment":"","family_comment_hidden":false},"16":{"family_comment":"","value":"","family":"","comment":""},"17":{"family_comment":"","value":"","family":"","comment":""},"18":{"family_comment":"","value":"","family":"","comment":"","value_hidden":false},"19":{"family_comment":"","value":"","family":"","comment":""},"20":{"family_comment":"","value":"","family":"","comment":"","family_comment_unclear":false}},"id":"vulyk_78_4","declaration":{"additional_info_text":"","notfull_lostpages":"","date":"2015-03-27T00:00:00","notfull":"","additional_info":"","url":"http://static.declarations.com.ua/declarations/chosen_ones/judges_batch/2071_savytskyi_serhii_anatoliiovych.pdf"},"liabilities":{"54":{"sum_foreign_comment":"","sum_foreign_hidden":false,"sum_comment":"","sum_comment_unclear":false,"sum_hidden":false,"sum_comment_hidden":false,"sum":"","sum_foreign":""},"55":{"sum_foreign_comment":"","sum":"","sum_comment":"","sum_foreign":""},"56":{"sum_foreign_comment":"","sum":"","sum_comment":"","sum_foreign":""},"57":{"sum_foreign_comment":"","sum":"","sum_comment":"","sum_foreign":""},"58":{"sum_foreign_comment":"","sum":"","sum_comment":"","sum_unclear":false,"sum_foreign":""},"59":{"sum_foreign_comment":"","sum":"","sum_comment":"","sum_foreign":""},"60":{"sum_foreign_comment":"","sum":"","sum_comment":"","sum_comment_unclear":false,"sum_comment_hidden":false,"sum_foreign":""},"61":{"sum_foreign_comment":"","sum":"","sum_comment":"","sum_foreign":""},"62":{"sum_foreign_comment":"","sum":"","sum_hidden":false,"sum_comment":"","sum_foreign":""},"63":{"sum_foreign_comment":"","sum_foreign_hidden":false,"sum_comment":"","sum":"","sum_unclear":false,"sum_foreign":""},"64":{"sum_foreign_comment":"","sum_foreign_hidden":false,"sum_comment":"","sum_hidden":false,"sum":"","sum_foreign":""}},"ft_src":"суддя хустського районного суду закарпатської області\nЗакарпатська область\nЗагальний місцевий суд\n2778219410\nСергій\n2916200727\nСавицька О. В\nПодружжя\nСавицький А. С\nДитина\nАнатолійович\nСавицький Сергій Анатолійович\nСергій Анатолійович Савицький\nСергій Савицький\nСавицький Сергій Анатолійович\nСавицький\nСавицький Сергій Анатолійович\nХуст\nвул. Борканюка. 8-а\nЗакарпатська область\n200031\n51491\n51491\n200031\n2014\n51491\n200031\n51491\n200031\n200031\n51491\n200031\n51491\nПодружжя\nСавицька О. В\n2916200727\nДитина\nСавицький А. С\nСавицький Сергій Анатолійович\nСергій Анатолійович Савицький\nСергій Савицький\nСавицький Сергій Анатолійович\nСавицький Сергій Анатолійович\n2778219410\nСергій\nАнатолійович\nЗагальний місцевий суд\nсуддя хустського районного суду закарпатської області\nЗакарпатська область\nСавицький\nвул. Борканюка. 8-а\nЗакарпатська область\nХуст\n2014\n2916200727\nПодружжя\nСавицька О. В\nДитина\nСавицький А. С\n2778219410\nАнатолійович\nСавицький\nСергій\nСавицький Сергій Анатолійович\nСергій Анатолійович Савицький\nСергій Савицький\nСавицький Сергій Анатолійович\nЗакарпатська область\nХуст\nвул. Борканюка. 8-а\nЗакарпатська область\nсуддя хустського районного суду закарпатської області\nЗагальний місцевий суд\nСавицький Сергій Анатолійович\n2014","general":{"inn":"2778219410","name":"Сергій","family":[{"inn":"2916200727","relations":"Подружжя","relations_other":"","inn_hidden":false,"family_name":"Савицька О. В","name_hidden":false,"name_unclear":false},{"inn":"","relations":"Дитина","relations_other":"","inn_hidden":false,"family_name":"Савицький А. С","name_hidden":false,"name_unclear":false}],"patronymic":"Анатолійович","inn_hidden":false,"family_raw":"","last_name":"Савицький","post":{"post_unclear":false,"post":"суддя хустського районного суду закарпатської області","post_hidden":false,"region":"Закарпатська область","region_hidden":false,"office":"Загальний місцевий суд","office_hidden":false},"last_name_unclear":false,"full_name":"Савицький Сергій Анатолійович","addresses":[{"place_district":"","place_city_hidden":false,"place_city":"Хуст","place_city_type_hidden":false,"place_district_hidden":false,"place_city_type":"Місто","place_address_hidden":false,"place_address":"вул. Борканюка. 8-а","place_hidden":false,"place":"Закарпатська область"}],"full_name_suggest":{"output":"Савицький Сергій Анатолійович","input":["Савицький Сергій Анатолійович","Сергій Анатолійович Савицький","Сергій Савицький"]},"name_unclear":false},"source":"VULYK","estate":{"30":[{"space_hidden":true,"address_hidden":false,"region_hidden":true,"space_comment":"","space":"","address":"","region":"","costs_property":"","costs_rent_comment":"","space_units":"м²","costs_property_comment":"","costs_rent":""}]},"intro":{"declaration_year":"2014"}}