{"income":{"5":{"family_comment":"","value":"413929","family":"36340","comment":""},"6":{"family_comment":"","value":"225821","family":"36340","comment":""},"7":{"value":"","comment_hidden":false,"family_comment":"","source_name":"","family":"","comment":"","source_name_hidden":false},"8":{"family_comment":"","value":"","family":"","comment":"","family_hidden":false},"9":{"value":"","family_comment":"","value_unclear":false,"family_unclear":false,"family":"","comment":""},"10":{"family_comment":"","value":"","family":"","comment":""},"11":{"family_comment":"","value":"","family":"","comment":""},"12":{"family_comment":"","value":"","family":"","comment":""},"13":{"family_comment":"","value":"","family":"","comment":""},"14":{"family_comment":"","value":"","family":"","comment":""},"15":{"family_comment":"","value":"7163","family":"","comment":""},"16":{"family_comment":"","value":"","family":"","comment":""},"17":{"family_comment":"","value":"","family":"","comment":""},"18":{"family_comment":"","value":"","family":"","comment":""},"19":{"family_comment":"","value":"","family":"","comment":""},"20":{"value":"180945","value_unclear":false,"family_hidden":false,"family_comment":"","family":"","comment":""}},"vehicle":{"35":[{"brand_info":"C346 MCA Comfort, об'єм 998 , потужність 74 кВт","sum_rent_comment":"","year":"2015","brand_info_hidden":false,"brand_info_unclear":false,"year_unclear":false,"sum_rent":"","sum":"361945","brand":"Ford Focus","sum_comment":"","brand_unclear":false,"brand_hidden":false,"sum_comment_unclear":false}]},"id":"vulyk_109_113","declaration":{"additional_info_text":"","notfull_lostpages":"","date":"2016-03-29T00:00:00","notfull":"","additional_info":"","url":"http://static.declarations.com.ua/declarations/chosen_ones/judges_batch/2570_vynohradova_valentyna_volodymyrivna_2015.pdf"},"liabilities":{"54":{"sum_foreign_comment":"","sum":"19002","sum_comment":"","sum_hidden":false,"sum_comment_hidden":false,"sum_unclear":false,"sum_foreign":""},"55":{"sum_foreign_comment":"","sum":"","sum_comment":"","sum_comment_unclear":false,"sum_foreign":""},"56":{"sum_foreign_comment":"","sum":"","sum_comment":"","sum_foreign":""},"57":{"sum_foreign_comment":"","sum_comment":"Центральне відділення ПАТ Креді Агріколь Банк в м. Хмельницький","sum":"20760","sum_comment_hidden":false,"sum_foreign":""},"58":{"sum_foreign_comment":"","sum_comment":"Центральне відділення ПАТ Креді Агріколь Банк в м. Хмельницький","sum":"14240","sum_comment_hidden":false,"sum_foreign":""},"59":{"sum_foreign_comment":"","sum":"","sum_comment":"","sum_foreign":""},"60":{"sum_foreign_comment":"","sum":"","sum_comment":"","sum_foreign":""},"61":{"sum_foreign_comment":"","sum":"","sum_comment":"","sum_foreign":""},"62":{"sum_foreign_comment":"","sum":"","sum_comment":"","sum_foreign":""},"63":{"sum_foreign_comment":"","sum":"","sum_comment":"","sum_foreign":""},"64":{"sum_foreign_comment":"","sum":"","sum_comment":"","sum_foreign":""}},"ft_src":"C346 MCA Comfort, об'єм 998 , потужність 74 кВт\nFord Focus\n2015\n361945\n11249\n8100\n14684\n8091\n21.9\n75.5\n68.8\n46.6\n2015\n36340\n225821\n7163\n36340\n413929\n180945\nC346 MCA Comfort, об'єм 998 , потужність 74 кВт\nFord Focus\n2015\n361945\n2015\nДитина\nВиноградов Б. С\nВиноградова Валентина Володимирівна\nВалентина Володимирівна Виноградова\nВалентина Виноградова\nВиноградова Валентина Володимирівна\nВалентина\nВиноградова Валентина Володимирівна\nВиноградова\nГосподарський місцевий суд\nХмельницька область\nсуддя господарського суду хмельницької області\nВолодимирівна\nЦентральне відділення ПАТ Креді Агріколь Банк в м. Хмельницький\n14240\nЦентральне відділення ПАТ Креді Агріколь Банк в м. Хмельницький\n20760\n19002\n225821\n36340\n180945\n7163\n413929\n36340\n11249\n8100\n14684\n8091\n68.8\n21.9\n75.5\n46.6\nЦентральне відділення ПАТ Креді Агріколь Банк в м. Хмельницький\n14240\nЦентральне відділення ПАТ Креді Агріколь Банк в м. Хмельницький\n20760\n19002\nДитина\nВиноградов Б. С\nВалентина\nВолодимирівна\nВиноградова\nВиноградова Валентина Володимирівна\nВалентина Володимирівна Виноградова\nВалентина Виноградова\nВиноградова Валентина Володимирівна\nХмельницька область\nГосподарський місцевий суд\nсуддя господарського суду хмельницької області\nВиноградова Валентина Володимирівна","general":{"name_hidden":false,"name":"Валентина","inn":"","last_name":"Виноградова","family":[{"inn":"","relations":"Дитина","relations_hidden":false,"inn_hidden":true,"family_name":"Виноградов Б. С","relations_other":"","name_hidden":false,"name_unclear":false}],"inn_hidden":true,"family_raw":"","inn_unclear":false,"post":{"region_unclear":false,"region":"Хмельницька область","post":"суддя господарського суду хмельницької області","region_hidden":false,"office":"Господарський місцевий суд","office_hidden":false,"office_unclear":false},"full_name":"Виноградова Валентина Володимирівна","patronymic":"Володимирівна","full_name_suggest":{"output":"Виноградова Валентина Володимирівна","input":["Виноградова Валентина Володимирівна","Валентина Володимирівна Виноградова","Валентина Виноградова"]}},"source":"VULYK","estate":{"23":[{"space_unclear":false,"costs":"","costs_rent_unclear":false,"costs_comment":"","address_hidden":false,"region_hidden":false,"space_comment":"","space":"11249","address":"","region":"","costs_rent_comment":"","space_units":"м²","costs_rent":""},{"space_hidden":false,"costs":"","costs_rent_unclear":false,"costs_comment":"","address_hidden":false,"region_hidden":false,"space_comment":"","space":"8100","address":"","region":"","costs_rent_comment":"","space_units":"м²","costs_rent":""},{"costs_rent":"","region":"","costs":"","costs_rent_comment":"","costs_comment":"","region_hidden":false,"space_comment":"","space_units":"м²","space":"14684","address":""},{"costs_rent":"","region":"","costs":"","costs_rent_comment":"","costs_comment":"","space_comment":"","space_units":"м²","space":"8091","address":""}],"24":[{"costs_rent":"","region":"","costs":"","costs_rent_comment":"","costs_comment":"","address_hidden":false,"region_hidden":false,"space_comment":"","space_units":"м²","space":"68.8","address":""}],"25":[{"space_unclear":false,"costs":"","costs_comment":"","address_hidden":false,"region_hidden":false,"space_comment":"","space_hidden":false,"space":"75.5","space_units_hidden":false,"region":"","costs_rent_comment":"","space_units":"м²","address":"","costs_rent":""}],"27":[{"space_unclear":false,"costs":"","costs_rent_unclear":false,"costs_comment":"","address_hidden":false,"region_hidden":false,"space_comment":"","space":"21.9","address":"","region":"","costs_rent_comment":"","space_units":"м²","costs_rent":""}],"28":[{"costs_rent":"","region":"","costs":"","costs_rent_comment":"","costs_comment":"","address_hidden":false,"region_hidden":false,"space_comment":"","space_units":"м²","space":"46.6","address":""}]},"intro":{"declaration_year":"2015","isnotdeclaration":""}}