{"income":{"5":{"value":"180718.92","family_comment":"","value_unclear":false,"family_hidden":false,"value_hidden":false,"family_unclear":false,"family":"","comment":""},"6":{"value":"180718.92","value_unclear":false,"family_hidden":false,"value_hidden":false,"family_comment":"","comment_unclear":false,"comment":"","family":""},"7":{"value":"","value_hidden":false,"family_comment":"","source_name":"","family":"","comment":"","source_name_hidden":false},"8":{"family_comment":"","value":"","family":"","comment":""},"9":{"family_comment":"","value":"","comment_unclear":false,"family":"","comment":""},"10":{"family_comment":"","value":"","value_unclear":false,"family":"","comment":""},"11":{"family_comment":"","value":"","family":"","comment":""},"12":{"family_comment":"","value":"","family":"","comment":""},"13":{"family_comment":"","value":"","family":"","comment":""},"14":{"family_comment":"","value":"","family":"","comment":""},"15":{"family_comment":"","value":"","family":"","comment":""},"16":{"family_comment":"","value":"","family":"","comment":""},"17":{"family_comment":"","value":"","family":"","comment":""},"18":{"family_comment":"","value":"","family":"","comment":""},"19":{"value":"","value_unclear":false,"comment_hidden":false,"family_hidden":false,"value_hidden":false,"family_comment":"","family_comment_hidden":false,"comment":"","family":""},"20":{"value":"","family_comment":"","value_unclear":false,"family_hidden":false,"value_hidden":false,"family_unclear":false,"comment_unclear":false,"comment":"","family":""}},"vehicle":{"35":[{"brand_info":"2400 куб. см.","sum_rent_comment":"","year":"2008","brand_info_hidden":false,"brand_info_unclear":false,"year_unclear":false,"sum_rent":"","sum":"","brand":"Toyota Camry","sum_comment":"","brand_unclear":false,"brand_hidden":false}]},"id":"vulyk_65_32","declaration":{"additional_info_text":"","notfull_lostpages":"","date":"2015-03-02T00:00:00","notfull":"","additional_info":"","url":"http://static.declarations.com.ua/declarations/chosen_ones/mega_batch/marych_ievhen_vasylovych.pdf"},"liabilities":{"54":{"sum_foreign_comment":"","sum":"","sum_comment":"","sum_comment_unclear":false,"sum_hidden":false,"sum_comment_hidden":false,"sum_foreign":""},"55":{"sum_foreign_comment":"","sum":"","sum_comment":"","sum_foreign":""},"56":{"sum_foreign_comment":"","sum":"40000","sum_comment":"","sum_unclear":true,"sum_foreign":""},"57":{"sum_foreign_comment":"","sum":"","sum_comment":"","sum_comment_unclear":false,"sum_unclear":false,"sum_foreign":""},"58":{"sum_foreign_comment":"","sum":"","sum_comment":"","sum_comment_unclear":false,"sum_unclear":false,"sum_foreign":""},"59":{"sum_foreign_comment":"","sum":"","sum_comment":"","sum_foreign":""},"60":{"sum_foreign_comment":"","sum":"","sum_comment":"","sum_comment_unclear":false,"sum_foreign":""},"61":{"sum_foreign_comment":"","sum":"","sum_comment":"","sum_foreign":""},"62":{"sum_foreign_comment":"","sum":"","sum_comment":"","sum_foreign":""},"63":{"sum_foreign_comment":"","sum":"","sum_comment":"","sum_foreign":""},"64":{"sum_foreign_comment":"","sum":"","sum_comment":"","sum_unclear":false,"sum_foreign":""}},"ft_src":"40000\nсуддя миколаївського окружного адміністративного суду\nМиколаївська область\nАдміністративний місцевий суд\nЄвген\nВасильович\nМарич\nМарич Євген Васильович\nМарич Євген Васильович\nЄвген Васильович Марич\nЄвген Марич\nМарич Євген Васильович\n2400 куб. см.\nToyota Camry\n2008\n2300\n2014\n180718.92\n180718.92\n2400 куб. см.\nToyota Camry\n2008\n2300\nМарич Євген Васильович\nЄвген Васильович Марич\nЄвген Марич\nМарич Євген Васильович\nМарич Євген Васильович\nЄвген\nМарич\nАдміністративний місцевий суд\nМиколаївська область\nсуддя миколаївського окружного адміністративного суду\nВасильович\n40000\n180718.92\n180718.92\n2014\n40000\nВасильович\nМарич\nЄвген\nМарич Євген Васильович\nЄвген Васильович Марич\nЄвген Марич\nМарич Євген Васильович\nМиколаївська область\nАдміністративний місцевий суд\nсуддя миколаївського окружного адміністративного суду\nМарич Євген Васильович\n2008\nToyota Camry\n2400 куб. см.\n180718.92\n180718.92\n2300\n2014","general":{"name_hidden":false,"name":"Євген","last_name_hidden":false,"inn":"","inn_unclear":false,"patronymic":"Васильович","inn_hidden":false,"family_raw":"","last_name":"Марич","post":{"post_unclear":false,"region_unclear":false,"post":"суддя миколаївського окружного адміністративного суду","office":"Адміністративний місцевий суд","region":"Миколаївська область","post_hidden":false,"office_hidden":false,"office_unclear":false,"region_hidden":false},"last_name_unclear":false,"full_name":"Марич Євген Васильович","patronymic_hidden":false,"full_name_suggest":{"output":"Марич Євген Васильович","input":["Марич Євген Васильович","Євген Васильович Марич","Євген Марич"]},"name_unclear":false},"source":"VULYK","estate":{"23":[{"space_unclear":false,"costs":"","costs_comment":"","address_hidden":false,"region_hidden":false,"space_comment":"","space_hidden":false,"space":"2300","address":"","region":"","address_unclear":false,"costs_rent_comment":"","space_units":"м²","costs_rent":""}]},"intro":{"declaration_year":"2014","isnotdeclaration":"","declaration_year_hidden":false}}