{"income":{"5":{"family_comment":"","family_unclear":false,"value":"215852.76","family":"41940","comment":""},"6":{"value":"202344.18","family_comment":"","value_unclear":false,"family_unclear":false,"family":"","comment":""},"7":{"value":"1328.58","family_comment":"","value_unclear":false,"family_unclear":false,"source_name":"","family":"","comment":"","source_name_hidden":false},"8":{"family_comment":"","value":"","family":"","comment":""},"9":{"family_comment":"","value":"","family":"","comment":""},"10":{"family_comment":"","value":"12180","value_unclear":false,"family":"","comment":""},"11":{"family_comment":"","value":"","family":"","comment":""},"12":{"family_comment":"","value":"","family":"","comment":""},"13":{"family_comment":"","value":"","family":"","comment":""},"14":{"family_comment":"","value":"","family":"","comment":""},"15":{"family_comment":"","value":"","family":"","comment":""},"16":{"family_comment":"","value":"","family":"","comment":""},"17":{"family_comment":"","value":"","family":"","comment":""},"18":{"family_comment":"","value":"","family":"","comment":""},"19":{"family_comment":"","value":"","family":"","comment":""},"20":{"value":"","value_unclear":false,"comment_hidden":false,"family_comment":"","comment_unclear":false,"comment":"","family":""}},"vehicle":{"40":[{"brand_info":"об'єм двигуна 1596 , пот. 107 к. с., дов. 4510 мм","sum":"","brand":"Nissan Almera","sum_comment":"","year":"2008","brand_info_hidden":false,"year_unclear":false,"sum_rent_comment":"","sum_rent":""}]},"id":"vulyk_96_87","declaration":{"additional_info_text":"","notfull_lostpages":"","date":"2016-03-30T00:00:00","notfull":"","additional_info":"","url":"http://static.declarations.com.ua/declarations/chosen_ones/judges_batch/301_lohinova_svitlana_mykolaivna_2015.pdf"},"liabilities":{"54":{"sum_foreign_comment":"","sum":"","sum_comment":"","sum_hidden":false,"sum_comment_hidden":false,"sum_foreign":""},"55":{"sum_foreign_comment":"","sum":"","sum_comment":"","sum_foreign":""},"56":{"sum_foreign_comment":"","sum":"","sum_comment":"","sum_unclear":false,"sum_foreign":""},"57":{"sum_foreign_comment":"","sum_comment":"","sum":"21500","sum_comment_hidden":false,"sum_foreign":""},"58":{"sum_foreign_comment":"","sum":"","sum_comment":"","sum_comment_hidden":false,"sum_unclear":false,"sum_foreign":""},"59":{"sum_foreign_comment":"","sum":"","sum_comment":"","sum_foreign":""},"60":{"sum_foreign_comment":"","sum_comment":"","sum":"","sum_comment_hidden":false,"sum_foreign":""},"61":{"sum_foreign_comment":"","sum":"","sum_comment":"","sum_foreign":""},"62":{"sum_foreign_comment":"","sum":"","sum_comment":"","sum_foreign":""},"63":{"sum_foreign_comment":"","sum_comment":"","sum":"","sum_comment_hidden":false,"sum_foreign":""},"64":{"sum_foreign_comment":"","sum_comment":"","sum":"","sum_comment_hidden":false,"sum_foreign":""}},"ft_src":"2008\nоб'єм двигуна 1596 , пот. 107 к. с., дов. 4510 мм\nNissan Almera\nбезопл\nдля ведення садівництва\n.12\nдля ведення садівництва\n.12\n137\nприватизована\n40.3\n2015\n202344.18\n12180\n1328.58\n41940\n215852.76\nNissan Almera\nоб'єм двигуна 1596 , пот. 107 к. с., дов. 4510 мм\n2008\n2015\nЛогінова Світлана Миколаївна\nСвітлана Миколаївна Логінова\nСвітлана Логінова\nЛогінова Світлана Миколаївна\nЛогінова Світлана Миколаївна\nСвітлана\nЛогінова\nХмельницька область\nсуддя хмельницького міськрайонного суду хмельницької області\nЗагальний місцевий суд\nМиколаївна\nПодружжя\nБевз Микола Васильович\n21500\n1328.58\n202344.18\n215852.76\n41940\n12180\n.12\nдля ведення садівництва\nбезопл\nдля ведення садівництва\n.12\n137\n40.3\nприватизована\n21500\nБевз Микола Васильович\nПодружжя\nСвітлана\nМиколаївна\nЛогінова\nЛогінова Світлана Миколаївна\nСвітлана Миколаївна Логінова\nСвітлана Логінова\nЛогінова Світлана Миколаївна\nсуддя хмельницького міськрайонного суду хмельницької області\nХмельницька область\nЗагальний місцевий суд\nЛогінова Світлана Миколаївна","general":{"inn":"","name":"Світлана","family":[{"inn":"","inn_hidden":true,"inn_unclear":false,"relations_hidden":false,"relations_other":"","relations":"Подружжя","name_hidden":true,"family_name":"Бевз Микола Васильович","name_unclear":false}],"patronymic":"Миколаївна","inn_hidden":true,"family_raw":"","last_name":"Логінова","post":{"office":"Загальний місцевий суд","region":"Хмельницька область","office_unclear":false,"post":"суддя хмельницького міськрайонного суду хмельницької області"},"full_name":"Логінова Світлана Миколаївна","addresses":[{"place_district":"","place_address_hidden":true,"place_city":"","place_address":"","place_district_hidden":false,"place_city_type":"","place_city_hidden":true,"place_city_type_hidden":false,"place_hidden":true,"place":""}],"patronymic_hidden":false,"full_name_suggest":{"output":"Логінова Світлана Миколаївна","input":["Логінова Світлана Миколаївна","Світлана Миколаївна Логінова","Світлана Логінова"]}},"source":"VULYK","estate":{"23":[{"region_unclear":false,"space_unclear":false,"costs":"","costs_rent_unclear":false,"costs_comment":"безопл","address_hidden":false,"region_hidden":true,"space_comment":"для ведення садівництва","space_hidden":false,"space":".12","address":"","region":"","address_unclear":false,"space_units_unclear":false,"space_comment_unclear":false,"space_units":"га","costs_rent":"","costs_rent_comment":""}],"25":[{"space_comment_unclear":false,"space_unclear":false,"costs":"","costs_comment":"","address_hidden":false,"region_hidden":true,"space_comment":"","space_hidden":false,"space":"137","address":"","costs_rent_comment_unclear":false,"region":"","address_unclear":false,"costs_rent_comment":"","costs_unclear":false,"space_comment_hidden":false,"space_units":"м²","costs_rent":""},{"space_hidden":false,"costs":"","costs_comment":"","address_hidden":false,"region_hidden":false,"space_comment":"приватизована","space":"40.3","address":"","region":"","address_unclear":false,"costs_rent_comment":"","space_comment_unclear":true,"space_units":"м²","costs_rent":""}],"29":[{"region_unclear":false,"space_unclear":false,"address_hidden":false,"region_hidden":true,"space_comment":"для ведення садівництва","space":".12","address":"","region":"","costs_property":"","costs_rent_comment":"","address_unclear":false,"space_units":"га","costs_property_comment":"","costs_rent":""}]},"intro":{"declaration_year":"2015","isnotdeclaration":""}}