{"income":{"5":{"value":"185588","family_comment":"","value_unclear":false,"comment_hidden":false,"family_hidden":false,"value_hidden":false,"family_unclear":false,"family_comment_hidden":false,"comment":"","family":"12930"},"6":{"value":"185588","family_comment":"","value_unclear":true,"family_hidden":false,"family_unclear":false,"family":"","comment":""},"7":{"source_name_unclear":false,"value":"","family_hidden":false,"family_comment":"","source_name":"","family":"","comment":"","source_name_hidden":false},"8":{"family_comment":"","value":"","family":"","comment":""},"9":{"value":"","value_unclear":false,"family_hidden":false,"family_comment":"","family":"","comment":""},"10":{"value":"","value_unclear":false,"family_hidden":false,"value_hidden":false,"family_comment":"","comment_unclear":false,"comment":"","family":""},"11":{"family_comment":"","value":"","family":"","comment":""},"12":{"family_comment":"","value":"","family":"","comment":""},"13":{"family_comment":"","value":"","family":"","comment":""},"14":{"family_comment":"","value":"","family":"","comment":""},"15":{"family_comment":"","value":"","family_hidden":false,"comment":"","family":""},"16":{"value":"","value_unclear":false,"family_hidden":false,"family_comment":"","family":"","comment":""},"17":{"family_comment":"","value":"","family_hidden":false,"comment":"","family":""},"18":{"family_comment":"","value":"","value_unclear":false,"family":"","comment":""},"19":{"family_comment":"","value":"","family":"","comment":""},"20":{"value":"","family_comment":"","value_unclear":false,"family_hidden":false,"family_unclear":false,"comment_unclear":false,"comment":"","family":"12930"}},"vehicle":{"35":[{"brand_info":"2497 куб. см., 125.04 кВт","sum_rent_comment":"","brand_info_unclear":false,"year":"2008","sum_rent_unclear":false,"brand_info_hidden":false,"sum_rent_comment_unclear":false,"sum_hidden":false,"sum_rent":"","sum":"","brand":"Kia Sorento","sum_comment":"","brand_unclear":false,"brand_hidden":false}]},"id":"vulyk_72_97","declaration":{"additional_info_text":"","notfull_lostpages":"","date":"2015-03-18T00:00:00","notfull":"","additional_info":"","url":"http://static.declarations.com.ua/declarations/chosen_ones/epic_batch/stelmakh_andrii_petrovych.pdf"},"liabilities":{"54":{"sum_foreign_comment":"","sum":"","sum_comment":"","sum_comment_hidden":false,"sum_unclear":false,"sum_foreign":""},"55":{"sum_foreign_comment":"","sum":"","sum_comment":"","sum_foreign":""},"56":{"sum_foreign_comment":"","sum":"","sum_hidden":false,"sum_comment":"","sum_foreign":""},"57":{"sum_foreign_comment":"","sum":"","sum_comment":"","sum_comment_unclear":false,"sum_hidden":false,"sum_comment_hidden":false,"sum_unclear":false,"sum_foreign":""},"58":{"sum_foreign_comment":"","sum":"","sum_comment":"","sum_comment_unclear":false,"sum_hidden":false,"sum_comment_hidden":false,"sum_unclear":false,"sum_foreign":""},"59":{"sum_foreign_comment":"","sum_foreign_hidden":false,"sum_comment":"","sum_foreign_unclear":false,"sum_comment_hidden":false,"sum":"","sum_foreign":""},"60":{"sum_foreign_comment":"","sum_foreign_hidden":false,"sum_comment":"","sum_hidden":false,"sum":"","sum_foreign":""},"61":{"sum_foreign_comment":"","sum_foreign_hidden":false,"sum_comment":"","sum_hidden":false,"sum":"","sum_foreign":""},"62":{"sum_foreign_comment":"","sum_foreign_hidden":false,"sum_comment":"","sum_hidden":false,"sum":"","sum_foreign":""},"63":{"sum_foreign_comment":"","sum_foreign_hidden":false,"sum_comment":"","sum_comment_unclear":false,"sum_hidden":false,"sum_comment_hidden":false,"sum_unclear":false,"sum":"","sum_foreign":""},"64":{"sum_foreign_comment":"","sum_foreign_hidden":false,"sum_comment":"","sum_hidden":false,"sum":"","sum_foreign":""}},"ft_src":"суддя сосницького районного суду чернігівської області\nЧернігівська область\nЗагальний місцевий суд\nАндрій\nСтельмах О. С., 11. 01. 1981\nПодружжя\nСтельмах Д. А., 18. 12. 2005\nДитина\nСтельмах М. А., 15. 04. 2013\nДитина\nПетрович\nСтельмах\nСтельмах Андрій Петрович\nСтельмах Андрій Петрович\nАндрій Петрович Стельмах\nАндрій Стельмах\nСтельмах Андрій Петрович\n2497 куб. см., 125.04 кВт\nKia Sorento\n2008\n59.9\n2014\n185588\n12930\n185588\n12930\n2497 куб. см., 125.04 кВт\nKia Sorento\n2008\n59.9\nПодружжя\nСтельмах О. С., 11. 01. 1981\nДитина\nСтельмах Д. А., 18. 12. 2005\nДитина\nСтельмах М. А., 15. 04. 2013\nСтельмах Андрій Петрович\nАндрій Петрович Стельмах\nАндрій Стельмах\nСтельмах Андрій Петрович\nАндрій\nСтельмах Андрій Петрович\nСтельмах\nЧернігівська область\nЗагальний місцевий суд\nсуддя сосницького районного суду чернігівської області\nПетрович\n185588\n12930\n185588\n12930\n2014\nСтельмах О. С., 11. 01. 1981\nПодружжя\nСтельмах Д. А., 18. 12. 2005\nДитина\nСтельмах М. А., 15. 04. 2013\nДитина\nПетрович\nСтельмах\nСтельмах Андрій Петрович\nАндрій Петрович Стельмах\nАндрій Стельмах\nСтельмах Андрій Петрович\nЧернігівська область\nЗагальний місцевий суд\nсуддя сосницького районного суду чернігівської області\nСтельмах Андрій Петрович\nАндрій\n2008\nKia Sorento\n2497 куб. см., 125.04 кВт\n12930\n185588\n12930\n185588\n59.9\n2014","general":{"inn":"","name":"Андрій","patronymic_unclear":false,"family":[{"inn":"","inn_hidden":true,"relations_unclear":false,"relations_hidden":false,"relations_other":"","relations":"Подружжя","name_hidden":false,"inn_unclear":false,"family_name":"Стельмах О. С., 11. 01. 1981","name_unclear":false},{"inn":"","inn_hidden":false,"relations_hidden":false,"family_name":"Стельмах Д. А., 18. 12. 2005","relations_other":"","relations":"Дитина","name_hidden":false,"name_unclear":false},{"inn":"","inn_hidden":false,"relations_hidden":false,"family_name":"Стельмах М. А., 15. 04. 2013","relations_other":"","relations":"Дитина","name_hidden":false,"name_unclear":false}],"patronymic":"Петрович","inn_hidden":true,"family_raw":"","inn_unclear":false,"post":{"post_unclear":false,"region_unclear":false,"post":"суддя сосницького районного суду чернігівської області","candidate":"","office_hidden":false,"region":"Чернігівська область","post_hidden":false,"office":"Загальний місцевий суд","office_unclear":false,"region_hidden":false},"last_name_unclear":false,"full_name":"Стельмах Андрій Петрович","addresses":[{"place_city_type_hidden":false,"place_district_hidden":true,"place_city_type":"","place_city_hidden":true,"place_address_unclear":false,"place_address":"","place":"","place_district":"","place_unclear":false,"place_city":"","place_city_unclear":false,"place_hidden":true,"place_address_hidden":true,"place_district_unclear":false}],"last_name":"Стельмах","patronymic_hidden":false,"full_name_suggest":{"output":"Стельмах Андрій Петрович","input":["Стельмах Андрій Петрович","Андрій Петрович Стельмах","Андрій Стельмах"]},"name_unclear":false},"source":"VULYK","estate":{"25":[{"space_unclear":false,"costs":"","costs_rent_unclear":false,"costs_comment":"","costs_hidden":false,"space_hidden":false,"costs_comment_unclear":false,"costs_rent_comment_unclear":false,"region":"","space_comment_hidden":false,"space_comment_unclear":false,"costs_rent_comment_hidden":false,"costs_rent":"","costs_comment_hidden":false,"address_hidden":false,"region_hidden":true,"space_comment":"","space":"59.9","address":"","address_unclear":false,"costs_rent_comment":"","costs_rent_hidden":false,"space_units":"м²"}]},"intro":{"declaration_year":"2014","isnotdeclaration":"","declaration_year_unclear":false}}