{"id":"vulyk_107_150","ft_src":"68922\n110000\n72000\nдо 1991 р.\n5500\nприватизовано\n1000\n60.4\nзбудований\n181.1\n2015\n261121\n15500\n261121\n15500\n72000\nдо 1991 р.\n5500\n110000\n68922\n2015\nКурдзіль\nПодружжя\nКурдзіль М. Ф. 14. 12. 1957\nДитина\nКурдзіль А. В. 11. 10. 1993\nКурдзіль Віталій Йосипович\nВіталій Йосипович Курдзіль\nВіталій Курдзіль\nКурдзіль Віталій Йосипович\nВіталій\nЙосипович\nКурдзіль Віталій Йосипович\nЗагальний апеляційний суд\nсуддя апеляційного суду хмельницької області\nХмельницька область\n108000\n2000\nзгідно договорів\nзгідно договору\n261121\n15500\n261121\n15500\n1000\nприватизовано\n181.1\nзбудований\n60.4\nзгідно договорів\n108000\n2000\nзгідно договору\nКурдзіль М. Ф. 14. 12. 1957\nПодружжя\nКурдзіль А. В. 11. 10. 1993\nДитина\nКурдзіль\nЙосипович\nсуддя апеляційного суду хмельницької області\nХмельницька область\nЗагальний апеляційний суд\nКурдзіль Віталій Йосипович\nКурдзіль Віталій Йосипович\nВіталій Йосипович Курдзіль\nВіталій Курдзіль\nКурдзіль Віталій Йосипович\nВіталій","estate":{"23":[{"address":"","space_units":"м²","costs_comment":"","region_hidden":true,"space_comment":"приватизовано","address_hidden":true,"space_comment_hidden":false,"space":"1000","space_comment_unclear":false,"costs_rent_comment":"","costs":"","region":"","costs_rent":""}],"24":[{"address":"","space_units":"м²","space_hidden":false,"space_comment":"збудований","region_hidden":true,"costs_comment":"","address_hidden":true,"space":"181.1","costs_rent_comment":"","costs":"","region":"","costs_rent":""}],"31":[{"costs_property_comment":"","address":"","space_units":"м²","space_hidden":false,"space_unclear":false,"region_hidden":true,"costs_property":"","space_comment":"","address_hidden":true,"space_comment_unclear":false,"costs_rent_comment":"","space":"60.4","region":"","costs_rent":""}]},"source":"VULYK","income":{"5":{"family_comment":"","comment":"","family":"15500","family_unclear":false,"comment_unclear":false,"value":"261121"},"6":{"family_comment":"","value":"261121","family":"","comment":""},"7":{"family_comment":"","comment":"","family":"","comment_unclear":false,"value":"","source_name_unclear":false,"source_name":""},"8":{"family_comment":"","value":"","family":"","comment":""},"9":{"family_comment":"","value":"","family":"","comment":""},"10":{"family_comment":"","value":"","family":"","comment":""},"11":{"family_comment":"","value":"","family":"","comment":""},"12":{"family_comment":"","value":"","family":"","comment":""},"13":{"family_comment":"","value":"","family":"","comment":""},"14":{"family_comment":"","value":"","family":"","comment":""},"15":{"family_comment":"","value":"","family":"","comment":""},"16":{"family_comment":"","value":"","family_unclear":false,"family":"","comment":""},"17":{"family_comment":"","value":"","family":"","comment":""},"18":{"family_comment":"","value":"","family":"","comment":""},"19":{"family_comment":"","value":"","family":"","comment":""},"20":{"family_comment":"","family":"15500","comment":"","family_unclear":false,"comment_unclear":false,"value":"","family_comment_unclear":false}},"banks":{"45":[{"sum_comment_unclear":false,"sum_units":"UAH","sum_foreign_units":"UAH","sum":"72000","sum_foreign_comment":"","sum_comment":"","sum_unclear":false,"sum_foreign":"","sum_comment_hidden":false},{"sum_comment_unclear":false,"sum_comment":"до 1991 р.","sum":"5500","sum_foreign_comment":"","sum_foreign":"","sum_unclear":false,"sum_units":"UAH"}],"46":[{"sum_units":"UAH","sum_comment":"","sum_foreign_units":"UAH","sum":"68922","sum_foreign_comment":"","sum_foreign":""}],"51":[{"sum_comment_unclear":false,"sum_comment":"","sum_foreign_units":"UAH","sum":"110000","sum_foreign_comment":"","sum_foreign":"","sum_unclear":false,"sum_units":"UAH"}]},"declaration":{"notfull_lostpages":"","additional_info_text":"","additional_info":"","date":"2016-03-16T00:00:00","notfull":"","url":"http://static.declarations.com.ua/declarations/chosen_ones/judges_batch/2129_kurdzil_vitalii_iosypovych.pdf"},"general":{"inn":"","addresses":[{"place_city_type_hidden":true,"place_city_type":"","place_city_hidden":true,"place_hidden":true,"place_district":"","place_district_hidden":true,"place":"","place_city":"","place_address_hidden":true,"place_address":""}],"last_name":"Курдзіль","full_name":"Курдзіль Віталій Йосипович","family":[{"inn":"","family_name":"Курдзіль М. Ф. 14. 12. 1957","relations_other":"","name_unclear":false,"inn_hidden":true,"name_hidden":false,"relations":"Подружжя"},{"inn":"","family_name":"Курдзіль А. В. 11. 10. 1993","relations_other":"","name_unclear":false,"inn_hidden":false,"name_hidden":false,"relations":"Дитина"}],"patronymic":"Йосипович","inn_hidden":true,"name":"Віталій","post":{"office":"Загальний апеляційний суд","region":"Хмельницька область","post_unclear":false,"post":"суддя апеляційного суду хмельницької області"},"family_raw":"","full_name_suggest":{"input":["Курдзіль Віталій Йосипович","Віталій Йосипович Курдзіль","Віталій Курдзіль"],"output":"Курдзіль Віталій Йосипович"}},"liabilities":{"54":{"sum_comment_unclear":false,"sum_comment":"","sum":"","sum_foreign_comment":"","sum_foreign":"","sum_comment_hidden":false},"55":{"sum_comment":"","sum_foreign_comment":"","sum_foreign":"","sum":""},"56":{"sum_comment":"","sum_foreign_comment":"","sum_foreign":"","sum_unclear":false,"sum":""},"57":{"sum_comment":"","sum_comment_unclear":false,"sum_foreign_comment":"","sum":"108000","sum_foreign":""},"58":{"sum_comment_unclear":false,"sum_comment":"згідно договорів","sum":"","sum_foreign_comment":"","sum_foreign":"","sum_unclear":false},"59":{"sum_comment":"","sum_foreign_comment":"","sum_foreign":"","sum_unclear":false,"sum":""},"60":{"sum_comment_unclear":false,"sum_comment":"","sum":"","sum_foreign_comment":"","sum_foreign":"","sum_comment_hidden":false},"61":{"sum_comment":"","sum_foreign_comment":"","sum_foreign":"","sum":""},"62":{"sum_comment":"","sum_foreign_comment":"","sum_foreign":"","sum":""},"63":{"sum_comment":"","sum_foreign_comment":"","sum_foreign":"","sum":"2000"},"64":{"sum_comment":"згідно договору","sum_foreign_comment":"","sum_foreign":"","sum":""}},"intro":{"isnotdeclaration":"","declaration_year":"2015"}}