{"id":"vulyk_109_64","ft_src":"4500 куб. см., 335 к.с., 640 кВт , 490.0 см, маю право користування\nInfiniti M45\n2007\n4500 куб. см., 238 к.с., 480 кВт , 489.0, маю право користування\n2005\nLexus GX 460\n4500 куб. см., 333 к.с., 610 кВт , 482.0, маю право користування\n2004\nBMW 645\n50.9\n45.1\n2015\n226937\n226943\n6\n4500 куб. см., 335 к.с., 640 кВт , 490.0 см, маю право користування\nInfiniti M45\n2007\n4500 куб. см., 238 к.с., 480 кВт , 489.0, маю право користування\nLexus GX 460\n2005\n4500 куб. см., 333 к.с., 610 кВт , 482.0, маю право користування\n2004\nBMW 645\n2015\nПолєв Дмитро Миколайович\nДмитро Миколайович Полєв\nДмитро Полєв\nПолєв Дмитро Миколайович\nПолєв Дмитро Миколайович\nДмитро\nПолєв\nГосподарський місцевий суд\nДніпропетровська область\nсуддя господарського суду дніпропетровської області\nМиколайович\n226937\n226943\n6\n50.9\n45.1\nМиколайович\nПолєв\nДмитро\nПолєв Дмитро Миколайович\nДмитро Миколайович Полєв\nДмитро Полєв\nПолєв Дмитро Миколайович\nДніпропетровська область\nГосподарський місцевий суд\nсуддя господарського суду дніпропетровської області\nПолєв Дмитро Миколайович","estate":{"25":[{"address":"","space_units":"м²","space_hidden":false,"space_unclear":false,"region_hidden":true,"costs_comment":"","space_comment":"","address_hidden":false,"space":"50.9","costs_rent_comment":"","costs":"","region":"","space_units_hidden":false,"costs_rent":""},{"costs":"","address":"","space_units":"м²","costs_rent_comment":"","space":"45.1","space_comment":"","region_hidden":false,"costs_comment":"","region":"","address_hidden":false,"costs_rent":""}]},"vehicle":{"35":[{"sum_comment_unclear":false,"brand_info":"4500 куб. см., 335 к.с., 640 кВт , 490.0 см, маю право користування","sum_rent_comment":"","brand_unclear":false,"brand_hidden":false,"year":"2007","sum_comment":"","brand_info_hidden":false,"sum_rent":"","brand":"Infiniti M45","year_unclear":false,"brand_info_unclear":false,"sum":""},{"sum_comment":"","brand_info":"4500 куб. см., 238 к.с., 480 кВт , 489.0, маю право користування","sum":"","sum_rent_comment":"","year":"2005","brand":"Lexus GX 460","sum_rent":""},{"sum_comment":"","brand_info":"4500 куб. см., 333 к.с., 610 кВт , 482.0, маю право користування","sum":"","sum_rent_comment":"","year":"2004","brand":"BMW 645","sum_rent":""}]},"source":"VULYK","income":{"5":{"family_comment":"","value":"226943","family":"","comment":""},"6":{"family_comment":"","value":"226937","family":"","comment":""},"7":{"source_name_hidden":false,"family_comment":"","comment":"","family":"","comment_hidden":false,"value":"","source_name":""},"8":{"family_comment":"","family_hidden":false,"value":"","family":"","comment":""},"9":{"family_comment":"","family":"","comment":"","value_unclear":false,"family_unclear":false,"value":"6"},"10":{"family_comment":"","value":"","family":"","comment":""},"11":{"family_comment":"","value":"","family":"","comment":""},"12":{"family_comment":"","value":"","family":"","comment":""},"13":{"family_comment":"","value":"","family":"","comment":""},"14":{"family_comment":"","value":"","family":"","comment":""},"15":{"family_comment":"","value":"","family":"","comment":""},"16":{"family_comment":"","value":"","family":"","comment":""},"17":{"family_comment":"","value":"","family":"","comment":""},"18":{"family_comment":"","value":"","family":"","comment":""},"19":{"family_comment":"","value":"","family":"","comment":""},"20":{"family_comment":"","family":"","comment":"","value_unclear":false,"family_hidden":false,"value":""}},"general":{"family_raw":"","name":"Дмитро","full_name_suggest":{"input":["Полєв Дмитро Миколайович","Дмитро Миколайович Полєв","Дмитро Полєв"],"output":"Полєв Дмитро Миколайович"},"patronymic":"Миколайович","inn_hidden":true,"addresses":[{"place_city_type_hidden":true,"place_city_type":"","place_city_hidden":true,"place_hidden":true,"place_district":"","place_district_hidden":true,"place":"","place_address":"","place_address_hidden":true,"place_city":""}],"inn":"","inn_unclear":false,"last_name":"Полєв","full_name":"Полєв Дмитро Миколайович","post":{"office":"Господарський місцевий суд","post":"суддя господарського суду дніпропетровської області","office_unclear":false,"region_hidden":false,"region":"Дніпропетровська область","office_hidden":false,"region_unclear":false},"name_hidden":false},"liabilities":{"54":{"sum_comment":"","sum_hidden":false,"sum":"","sum_foreign_comment":"","sum_foreign":"","sum_unclear":false,"sum_comment_hidden":false},"55":{"sum_comment":"","sum_comment_unclear":false,"sum_foreign_comment":"","sum":"","sum_foreign":""},"56":{"sum_comment":"","sum_foreign_comment":"","sum_foreign":"","sum":""},"57":{"sum_comment":"","sum_foreign_comment":"","sum_foreign":"","sum":"","sum_comment_hidden":false},"58":{"sum_comment":"","sum_foreign_comment":"","sum_foreign":"","sum":"","sum_comment_hidden":false},"59":{"sum_comment":"","sum_foreign_comment":"","sum_foreign":"","sum":""},"60":{"sum_comment":"","sum_foreign_comment":"","sum_foreign":"","sum":""},"61":{"sum_comment":"","sum_foreign_comment":"","sum_foreign":"","sum":""},"62":{"sum_comment":"","sum_foreign_comment":"","sum_foreign":"","sum":""},"63":{"sum_comment":"","sum_foreign_comment":"","sum_foreign":"","sum":""},"64":{"sum_comment":"","sum_foreign_comment":"","sum_foreign":"","sum":""}},"declaration":{"notfull_lostpages":"","additional_info_text":"","additional_info":"","date":"2016-03-31T00:00:00","notfull":"","url":"http://static.declarations.com.ua/declarations/chosen_ones/judges_batch/2521_poliev_dmytro_mykolaiovych_2015.pdf"},"intro":{"isnotdeclaration":"","declaration_year":"2015"}}