{"income":{"5":{"value":"217671.33","family_comment":"","value_unclear":false,"comment_hidden":false,"family_hidden":false,"value_hidden":false,"family_unclear":false,"family":"11407.19","comment":""},"6":{"value":"205590.53","family_comment":"","value_unclear":false,"family_hidden":false,"family_unclear":false,"comment_unclear":false,"comment":"","family":"11407.19"},"7":{"source_name_unclear":false,"value":"12080.8","value_hidden":false,"family_comment":"","source_name":"1. Національний університет 'Одеська юридична академія' 2. Національна школа суддів України","family":"","comment":"","source_name_hidden":false},"8":{"value":"","family_hidden":false,"value_hidden":false,"family_comment":"","family":"","comment":""},"9":{"value":"","family_comment":"","value_unclear":false,"family_hidden":false,"value_hidden":false,"family_unclear":false,"family":"","comment":""},"10":{"family_comment":"","value":"","family":"","comment":""},"11":{"family_comment":"","value":"","family":"","comment":""},"12":{"family_comment":"","value":"","family":"","comment":""},"13":{"family_comment":"","value":"","family":"","comment":""},"14":{"family_comment":"","value":"","family":"","comment":""},"15":{"family_comment":"","value":"","family":"","comment":""},"16":{"value":"","family_comment":"","value_unclear":false,"family_unclear":false,"family":"","comment":""},"17":{"family_comment":"","value":"","family":"","comment":""},"18":{"family_comment":"","value":"","family":"","comment":""},"19":{"family_comment":"","value":"","comment_unclear":false,"family":"","comment":""},"20":{"value":"","family_comment":"","value_unclear":false,"comment_hidden":false,"family_hidden":false,"family":"","value_hidden":false,"family_unclear":false,"comment_unclear":false,"comment":"","family_comment_unclear":false}},"vehicle":{"35":[{"brand_info":"2362.0","sum_rent_comment":"","brand":"Toyota Camry","sum_comment":"","brand_unclear":false,"year":"2007","brand_info_unclear":false,"sum":"","sum_rent":""}]},"id":"vulyk_63_181","declaration":{"additional_info_text":"","notfull_lostpages":"","date":"2015-03-27T00:00:00","notfull":"","additional_info":"","url":"http://static.declarations.com.ua/declarations/chosen_ones/mega_batch/hurevskyi_volodymyr_klymentiiovych.pdf"},"liabilities":{"54":{"sum_foreign_comment":"","sum":"","sum_comment":"","sum_unclear":false,"sum_foreign":""},"55":{"sum_foreign_comment":"","sum":"","sum_comment":"","sum_foreign":""},"56":{"sum_foreign_comment":"","sum":"","sum_comment":"","sum_unclear":false,"sum_foreign":""},"57":{"sum_foreign_comment":"","sum":"","sum_comment":"","sum_comment_hidden":false,"sum_unclear":false,"sum_foreign":""},"58":{"sum_foreign_comment":"","sum_comment_hidden":false,"sum":"","sum_comment":"","sum_foreign":""},"59":{"sum_foreign_comment":"","sum":"","sum_comment":"","sum_foreign":""},"60":{"sum_foreign_comment":"","sum":"","sum_comment":"","sum_comment_unclear":false,"sum_foreign":""},"61":{"sum_foreign_comment":"","sum":"","sum_comment":"","sum_unclear":false,"sum_foreign":""},"62":{"sum_foreign_comment":"","sum":"","sum_comment":"","sum_unclear":false,"sum_foreign":""},"63":{"sum_foreign_comment":"","sum":"","sum_comment":"","sum_hidden":false,"sum_comment_hidden":false,"sum_unclear":false,"sum_foreign":""},"64":{"sum_foreign_comment":"","sum_comment_hidden":false,"sum":"","sum_comment":"","sum_foreign":""}},"ft_src":"суддя малиновського районного суду м. одеси\nОдеська область\nЗагальний місцевий суд\nВолодимир\nГуревська В. В\nДитина\nКлиментійович\nГуревський\nГуревський Володимир Климентійович\nГуревський Володимир Климентійович\nВолодимир Климентійович Гуревський\nВолодимир Гуревський\nГуревський Володимир Климентійович\n2007\nToyota Camry\n2362.0\n520\n171.6\n2014\n11407.19\n205590.53\n1. Національний університет 'Одеська юридична академія' 2. Національна школа суддів України\n12080.8\n11407.19\n217671.33\n2362.0\n2007\nToyota Camry\n520\n171.6\nКлиментійович\nГуревський Володимир Климентійович\nВолодимир Климентійович Гуревський\nВолодимир Гуревський\nГуревський Володимир Климентійович\nВолодимир\nДитина\nГуревська В. В\nГуревський Володимир Климентійович\nЗагальний місцевий суд\nОдеська область\nсуддя малиновського районного суду м. одеси\nГуревський\n12080.8\n1. Національний університет 'Одеська юридична академія' 2. Національна школа суддів України\n205590.53\n11407.19\n217671.33\n11407.19\n2014\nДитина\nГуревська В. В\nКлиментійович\nГуревський\nГуревський Володимир Климентійович\nВолодимир Климентійович Гуревський\nВолодимир Гуревський\nГуревський Володимир Климентійович\nВолодимир\nОдеська область\nсуддя малиновського районного суду м. одеси\nЗагальний місцевий суд\nГуревський Володимир Климентійович\n2007\n2362.0\nToyota Camry\n217671.33\n11407.19\n12080.8\n1. Національний університет 'Одеська юридична академія' 2. Національна школа суддів України\n205590.53\n11407.19\n520\n171.6\n2014","general":{"name_hidden":false,"name":"Володимир","patronymic_unclear":false,"last_name_hidden":false,"inn":"","family":[{"inn":"","inn_hidden":true,"relations_unclear":false,"relations_hidden":false,"relations_other":"","relations":"Дитина","name_hidden":true,"inn_unclear":false,"family_name":"Гуревська В. В","name_unclear":false}],"patronymic":"Климентійович","inn_hidden":true,"family_raw":"","inn_unclear":false,"post":{"post_unclear":false,"region_unclear":false,"region":"Одеська область","office_hidden":false,"region_hidden":false,"post":"суддя малиновського районного суду м. одеси","office_unclear":false,"office":"Загальний місцевий суд"},"last_name_unclear":false,"full_name":"Гуревський Володимир Климентійович","addresses":[{"place_city_type_unclear":false,"place_address":"","place_district_hidden":true,"place_city_type":"","place_address_hidden":true,"place_address_unclear":false,"place_city_type_hidden":true,"place":"","place_district":"","place_unclear":false,"place_city":"","place_city_unclear":false,"place_hidden":true,"place_city_hidden":true,"place_district_unclear":false}],"last_name":"Гуревський","full_name_suggest":{"output":"Гуревський Володимир Климентійович","input":["Гуревський Володимир Климентійович","Володимир Климентійович Гуревський","Володимир Гуревський"]},"name_unclear":false},"source":"VULYK","estate":{"23":[{"space_unclear":false,"costs":"","costs_comment":"","costs_hidden":false,"address_hidden":false,"region_hidden":true,"space_comment":"","space_hidden":false,"space":"520","address":"","region":"","space_units_unclear":false,"costs_rent_hidden":false,"space_units":"м²","space_units_hidden":false,"costs_rent":"","costs_rent_comment":""}],"26":[{"costs":"","costs_comment":"","costs_hidden":false,"address_hidden":false,"region_hidden":true,"space_comment":"","space":"171.6","address":"","region":"","costs_rent_comment":"","costs_rent_hidden":false,"costs_rent_comment_hidden":false,"space_units":"м²","costs_comment_hidden":false,"costs_rent":""}]},"intro":{"declaration_year":"2014","isnotdeclaration":"","declaration_year_unclear":false}}