{"income":{"5":{"value":"83502.89","family_comment":"","family_hidden":false,"value_hidden":false,"family_unclear":true,"family":"12167","comment":""},"6":{"value":"","value_unclear":false,"comment_hidden":false,"family_hidden":false,"value_hidden":true,"family_comment":"","family":"","comment":"","family_comment_hidden":false},"7":{"source_name_unclear":false,"value":"","family_comment":"","source_name":"","family":"","comment":"","source_name_hidden":false},"8":{"family_comment":"","value":"","comment_hidden":false,"family":"","comment":""},"9":{"value":"","family_hidden":false,"value_hidden":false,"family_comment":"","family":"","comment":""},"10":{"value":"","comment_hidden":false,"family_hidden":false,"value_hidden":false,"family_comment":"","family":"","comment":"","family_comment_hidden":false},"11":{"family_comment":"","value":"","family":"","comment":"","family_hidden":false},"12":{"family_comment":"","value":"","family":"","comment":"","family_hidden":false},"13":{"family_comment":"","value":"","family":"","comment":""},"14":{"family_comment":"","value":"","family":"","comment":""},"15":{"value":"2400","comment_hidden":false,"family_comment":"","family":"","comment":"","family_comment_hidden":false},"16":{"family_comment":"","family_unclear":false,"value":"","family":"","comment":""},"17":{"family_comment":"","value":"","family":"","comment":""},"18":{"family_comment":"","value":"","family":"","comment":""},"19":{"family_comment":"","value":"","family":"","comment":""},"20":{"value":"","family_comment":"","comment_unclear":false,"family_hidden":false,"family_unclear":false,"family":"","comment":""}},"vehicle":{"35":[{"brand_info":"1596 куб. см.","sum_rent_comment":"","year":"2011","brand_info_hidden":false,"brand_info_unclear":false,"year_unclear":false,"sum_rent":"","sum":"","brand":"ВАЗ 211540","sum_comment":"","brand_unclear":false,"brand_hidden":false}]},"id":"vulyk_77_24","declaration":{"additional_info_text":"","notfull_lostpages":"","date":"2015-02-19T00:00:00","notfull":"","additional_info":"","url":"http://static.declarations.com.ua/declarations/chosen_ones/judges_batch/1955_havrylenko_oleksandr_mykolaiovych.pdf"},"liabilities":{"54":{"sum_foreign_comment":"","sum":"221.13","sum_comment":"","sum_comment_unclear":false,"sum_foreign":""},"55":{"sum_foreign_comment":"","sum":"","sum_comment":"","sum_foreign":""},"56":{"sum_foreign_comment":"","sum":"20800","sum_comment":"","sum_unclear":false,"sum_foreign":""},"57":{"sum_foreign_comment":"","sum":"","sum_comment":"","sum_foreign":""},"58":{"sum_foreign_comment":"","sum":"","sum_comment":"","sum_foreign":""},"59":{"sum_foreign_comment":"","sum":"","sum_comment":"","sum_foreign":""},"60":{"sum_foreign_comment":"","sum":"","sum_comment":"","sum_foreign":""},"61":{"sum_foreign_comment":"","sum":"","sum_comment":"","sum_foreign":""},"62":{"sum_foreign_comment":"","sum":"","sum_foreign":"","sum_comment":"","sum_hidden":false},"63":{"sum_foreign_comment":"","sum":"","sum_comment":"","sum_foreign":""},"64":{"sum_foreign_comment":"","sum":"","sum_comment":"","sum_foreign":""}},"ft_src":"1596 куб. см.\nВАЗ 211540\n2011\nм. Полтава, вул. Леніна, 96, кв. 64\n10800\n29.9\nПолтавська область\n2014\n2400\n12167\n83502.89\n1596 куб. см.\nВАЗ 211540\n2011\n2014\nГавриленко Олександр Миколайович\nОлександр Миколайович Гавриленко\nОлександр Гавриленко\nГавриленко Олександр Миколайович\nОлександр\nГавриленко Олександр Миколайович\nГавриленко\nМіністерство внутрішніх справ\nперший заступник начальника полтавського му умвс україни в полтавській області – начальник слідчого відділення\nПолтавська область\nМиколайович\n221.13\n20800\n2400\n83502.89\n12167\n29.9\nм. Полтава, вул. Леніна, 96, кв. 64\n10800\nПолтавська область\n20800\n221.13\nМиколайович\nГавриленко\nОлександр\nГавриленко Олександр Миколайович\nОлександр Миколайович Гавриленко\nОлександр Гавриленко\nГавриленко Олександр Миколайович\nперший заступник начальника полтавського му умвс україни в полтавській області – начальник слідчого відділення\nПолтавська область\nМіністерство внутрішніх справ\nГавриленко Олександр Миколайович","general":{"inn":"","name":"Олександр","last_name":"Гавриленко","family":[{"inn":"","relations":"","inn_unclear":false,"relations_hidden":true,"inn_hidden":true,"family_name":"","relations_other":"","name_hidden":true,"name_unclear":false}],"inn_hidden":true,"family_raw":"","inn_unclear":false,"post":{"office":"Міністерство внутрішніх справ","region":"Полтавська область","post":"перший заступник начальника полтавського му умвс україни в полтавській області – начальник слідчого відділення"},"full_name_suggest":{"output":"Гавриленко Олександр Миколайович","input":["Гавриленко Олександр Миколайович","Олександр Миколайович Гавриленко","Олександр Гавриленко"]},"full_name":"Гавриленко Олександр Миколайович","addresses":[{"place_city_type_hidden":false,"place_district_hidden":false,"place_city_type":"","place_address_hidden":false,"place_address_unclear":false,"place_address":"","place":"","place_district":"","place_unclear":false,"place_hidden":true,"place_city_unclear":false,"place_city_hidden":false,"place_city":"","place_district_unclear":false}],"patronymic":"Миколайович","last_name_unclear":false},"source":"VULYK","estate":{"25":[{"space_unclear":false,"costs":"","costs_comment":"","costs_hidden":false,"address_hidden":false,"region_hidden":false,"space_comment":"","space_hidden":false,"space":"29.9","address":"м. Полтава, вул. Леніна, 96, кв. 64","region":"Полтавська область","address_unclear":false,"costs_rent_comment":"","costs_rent_hidden":false,"space_units":"м²","costs_rent":"10800"}]},"intro":{"declaration_year":"2014","isnotdeclaration":"","declaration_year_unclear":true}}