{"income":{"5":{"value":"252662","family_unclear":false,"family_hidden":false,"family_comment":"","family":"59350","comment":""},"6":{"family_comment":"","value":"213902","family_hidden":false,"comment":"","family":"40491"},"7":{"family_comment":"","value":"","source_name":"","family":"","comment":""},"8":{"family_comment":"","value":"","family":"","comment":""},"9":{"value":"139","comment_unclear":false,"family_hidden":false,"family_comment":"","family":"26","comment":""},"10":{"family_comment":"","value":"12180","family":"3233","comment":""},"11":{"family_comment":"","value":"","family":"","comment":""},"12":{"family_comment":"","value":"","family":"","comment":""},"13":{"family_comment":"","value":"","family":"","comment":""},"14":{"family_comment":"","value":"","family":"","comment":""},"15":{"family_comment":"","value":"","value_unclear":false,"family":"","comment":""},"16":{"family_comment":"","value":"37970","family":"","comment":""},"17":{"family_comment":"","value":"","family":"","comment":""},"18":{"family_comment":"","value":"","family":"","comment":""},"19":{"family_comment":"","value":"","family":"","comment":""},"20":{"value":"651","comment_unclear":false,"comment_hidden":false,"family_hidden":false,"value_hidden":false,"family_comment":"","value_unclear":false,"family":"15600","comment":"","family_comment_hidden":false}},"vehicle":{"35":[{"brand_info":"1598 куб. см., 75 кВт","sum_rent_comment":"","brand":"Volkswagen Golf Plus","sum_comment":"","year":"2007","brand_info_hidden":false,"sum":"","sum_rent":""},{"brand_info":"1499 куб. см., 68 кВт","sum_rent_comment":"","brand":"Daewoo Lanos","sum_comment":"","year":"2005","sum":"","sum_rent":""}]},"id":"vulyk_41_51","banks":{"45":[{"sum_foreign_comment":"","sum_units":"UAH","sum_comment":"","sum_foreign_unclear":false,"sum_foreign_units":"UAH","sum_hidden":false,"sum_comment_hidden":false,"sum":"","sum_foreign":""},{"sum_foreign_comment":"","sum_units":"","sum_comment":"","sum_foreign_unclear":false,"sum_foreign_units":"","sum":"","sum_foreign":""}],"46":[{"sum_foreign_comment":"","sum_units":"UAH","sum_comment":"","sum_foreign_units":"UAH","sum_comment_hidden":false,"sum_unclear":false,"sum":"","sum_foreign":""},{"sum_foreign_comment":"","sum_units":"","sum_comment":"","sum_foreign_units":"","sum":"","sum_unclear":false,"sum_foreign":""}],"47":[{"sum_foreign_comment":"","sum_units":"UAH","sum_comment":"","sum_foreign_units":"UAH","sum":"","sum_foreign":""},{"sum_foreign_comment":"","sum_units":"","sum_comment":"","sum_foreign_units":"","sum":"","sum_foreign":""}],"48":[{"sum_foreign_comment":"","sum_units":"UAH","sum_comment":"","sum_foreign_units":"UAH","sum":"","sum_foreign":""}],"49":[{"sum_foreign_comment":"","sum_units":"UAH","sum_comment":"","sum_foreign_units":"UAH","sum":"","sum_foreign":""}],"50":[{"sum_foreign_comment":"","sum_units":"UAH","sum_comment":"","sum_foreign_units":"UAH","sum":"","sum_foreign":""}],"51":[{"sum_foreign_comment":"","sum_units":"UAH","sum_comment":"","sum_hidden":false,"sum_foreign_units":"UAH","sum_comment_hidden":false,"sum_unclear":false,"sum":"","sum_foreign":""},{"sum_foreign_comment":"","sum_units":"","sum_comment":"","sum_foreign_units":"","sum":"","sum_foreign":""}],"52":[{"sum_foreign_comment":"","sum_units":"UAH","sum_comment":"","sum_foreign_units":"UAH","sum_comment_hidden":false,"sum_unclear":false,"sum":"","sum_foreign":""}],"53":[{"sum_foreign_comment":"","sum_units":"UAH","sum_comment":"","sum_foreign_units":"UAH","sum_comment_hidden":false,"sum":"","sum_foreign":""},{"sum_foreign_comment":"","sum_units":"","sum_comment":"","sum_foreign_units":"","sum":"","sum_foreign":""},{"sum_foreign_comment":"","sum_units":"","sum_comment":"","sum_foreign_units":"","sum":"","sum_foreign":""}]},"declaration":{"date":"2015-03-31T00:00:00","additional_info_text":"","additional_info":"","url":"http://static.declarations.com.ua/declarations/chosen_ones/mega_batch/baklanov_roman_volodymyrovych.pdf"},"liabilities":{"54":{"sum_foreign_comment":"","sum_comment_hidden":false,"sum":"","sum_comment":"","sum_foreign":""},"55":{"sum_foreign_comment":"","sum":"","sum_comment":"","sum_foreign":""},"56":{"sum_foreign_comment":"","sum":"","sum_hidden":false,"sum_comment":"","sum_foreign":""},"57":{"sum_foreign_comment":"","sum":"","sum_comment":"","sum_comment_hidden":false,"sum_unclear":false,"sum_foreign":""},"58":{"sum_foreign_comment":"","sum_comment_hidden":false,"sum":"","sum_comment":"","sum_foreign":""},"59":{"sum_foreign_comment":"","sum":"","sum_comment":"","sum_foreign":""},"60":{"sum_foreign_comment":"","sum_comment_hidden":false,"sum":"","sum_comment":"","sum_foreign":""},"61":{"sum_foreign_comment":"","sum":"","sum_comment":"","sum_foreign":""},"62":{"sum_foreign_comment":"","sum":"","sum_comment":"","sum_foreign":""},"63":{"sum_foreign_comment":"","sum":"","sum_comment":"","sum_comment_hidden":false,"sum_unclear":false,"sum_foreign":""},"64":{"sum_foreign_comment":"","sum_comment_hidden":false,"sum":"","sum_comment":"","sum_foreign":""}},"ft_src":"суддя лебединського районного суду сумської області\nСумська область\nЗагальний місцевий суд\nРоман\nБакланова Л. А. 07. 09. 1979\nПодружжя\nБакланов М. Р. 19. 09. 2005\nДитина\nБакланова С. Ф. 01. 01. 1941\nБатьки\nВолодимирович\nБакланов Роман Володимирович\nРоман Володимирович Бакланов\nРоман Бакланов\nБакланов Роман Володимирович\nБакланов\nБакланов Роман Володимирович\n1598 куб. см., 75 кВт\n2007\nVolkswagen Golf Plus\n1499 куб. см., 68 кВт\n2005\nDaewoo Lanos\n2014\nVolkswagen Golf Plus\n1598 куб. см., 75 кВт\n2007\n1499 куб. см., 68 кВт\nDaewoo Lanos\n2005\n50\nПодружжя\nБакланова Л. А. 07. 09. 1979\nДитина\nБакланов М. Р. 19. 09. 2005\nБатьки\nБакланова С. Ф. 01. 01. 1941\nБакланов Роман Володимирович\nРоман Володимирович Бакланов\nРоман Бакланов\nБакланов Роман Володимирович\nБакланов Роман Володимирович\nРоман\nВолодимирович\nЗагальний місцевий суд\nсуддя лебединського районного суду сумської області\nСумська область\nБакланов\n213902\n40491\n651\n15600\n252662\n59350\n37970\n12180\n3233\n139\n26\n2014\n50\nБакланова Л. А. 07. 09. 1979\nПодружжя\nБакланов М. Р. 19. 09. 2005\nДитина\nБакланова С. Ф. 01. 01. 1941\nБатьки\nВолодимирович\nБакланов\nРоман\nБакланов Роман Володимирович\nРоман Володимирович Бакланов\nРоман Бакланов\nБакланов Роман Володимирович\nСумська область\nсуддя лебединського районного суду сумської області\nЗагальний місцевий суд\nБакланов Роман Володимирович\n40491\n213902\n3233\n12180\n59350\n252662\n37970\n26\n139\n15600\n651\nVolkswagen Golf Plus\n1598 куб. см., 75 кВт\n2007\nDaewoo Lanos\n1499 куб. см., 68 кВт\n2005\n3233\n12180\n651\n15600\n252662\n59350\n37970\n139\n26\n40491\n213902\n50\n2014","general":{"inn":"","name":"Роман","family":[{"inn":"","relations":"Подружжя","relations_hidden":false,"inn_hidden":false,"family_name":"Бакланова Л. А. 07. 09. 1979","name_hidden":false,"name_unclear":false},{"inn":"","relations":"Дитина","relations_other":"","inn_hidden":false,"family_name":"Бакланов М. Р. 19. 09. 2005","name_hidden":false,"name_unclear":false},{"inn":"","relations":"Батьки","relations_other":"","inn_hidden":false,"family_name":"Бакланова С. Ф. 01. 01. 1941","name_hidden":false,"name_unclear":false}],"patronymic":"Володимирович","inn_hidden":true,"family_raw":"","last_name":"Бакланов","post":{"post_unclear":false,"post":"суддя лебединського районного суду сумської області","post_hidden":false,"region":"Сумська область","region_hidden":false,"office":"Загальний місцевий суд","office_hidden":false},"last_name_unclear":false,"full_name":"Бакланов Роман Володимирович","addresses":[{"place_district":"","place_city_hidden":true,"place_city":"","place_city_type_hidden":false,"place_district_hidden":true,"place_city_type":"","place_address_hidden":false,"place_address":"","place_hidden":true,"place":""}],"patronymic_hidden":false,"full_name_suggest":{"output":"Бакланов Роман Володимирович","input":["Бакланов Роман Володимирович","Роман Володимирович Бакланов","Роман Бакланов"]},"name_unclear":false},"source":"VULYK","estate":{"23":[{"region_unclear":false,"space_unclear":false,"costs":"","costs_comment":"","address_hidden":false,"region_hidden":false,"space_comment":"","space":"","address":"","costs_comment_unclear":false,"region":"","space_units_unclear":false,"space_comment_hidden":false,"space_units":"м²","costs_rent":"","costs_rent_comment":""},{"costs_rent":"","space_unclear":false,"region":"","costs":"","costs_rent_comment":"","costs_comment":"","space_comment":"","space_units":"","space":"","address":""},{"costs_rent":"","region":"","costs":"","costs_rent_comment":"","costs_comment":"","space_comment":"","space_units":"","space":"","address":""}],"31":[{"space_hidden":false,"address_hidden":true,"region_hidden":true,"space_comment":"","space":"50","address":"","region":"","costs_property":"","costs_rent_comment":"","space_comment_unclear":false,"space_units":"м²","costs_property_comment":"","costs_rent":""}]},"intro":{"declaration_year":"2014"}}