{"income":{"5":{"value":"250570.52","family_comment":"","value_unclear":false,"family_hidden":true,"value_hidden":false,"family_unclear":false,"family":"","comment":""},"6":{"value":"250570.52","value_unclear":false,"family_hidden":true,"value_hidden":false,"family_comment":"","comment_unclear":false,"comment":"","family":""},"7":{"value":"","value_hidden":false,"family_comment":"","source_name":"","family":"","comment":"","source_name_hidden":false},"8":{"family_comment":"","value":"","family":"","comment":""},"9":{"family_comment":"","value":"","comment_unclear":false,"family":"","comment":""},"10":{"family_comment":"","value":"","value_unclear":false,"family":"","comment":""},"11":{"family_comment":"","value":"","family":"","comment":""},"12":{"family_comment":"","value":"","family":"","comment":""},"13":{"family_comment":"","value":"","family":"","comment":""},"14":{"family_comment":"","value":"","family":"","comment":""},"15":{"family_comment":"","value":"","family":"","comment":""},"16":{"family_comment":"","value":"","family":"","comment":""},"17":{"family_comment":"","value":"","family":"","comment":""},"18":{"family_comment":"","value":"","family":"","comment":""},"19":{"value":"","value_unclear":false,"comment_hidden":false,"family_hidden":false,"value_hidden":false,"family_comment":"","family_comment_hidden":false,"comment":"","family":""},"20":{"value":"","family_comment":"","value_unclear":false,"family_hidden":true,"value_hidden":true,"family_unclear":false,"comment_unclear":false,"comment":"","family":""}},"vehicle":{"35":[{"brand_info":"5663 куб. см.","sum_rent_comment":"","year":"2010","brand_info_hidden":false,"brand_info_unclear":false,"year_unclear":true,"sum_rent":"","sum":"","brand":"Lexus LX-570","sum_comment":"","brand_unclear":true,"brand_hidden":false}]},"id":"vulyk_65_87","declaration":{"additional_info_text":"","notfull_lostpages":"","date":"2015-03-31T00:00:00","notfull":"","additional_info":"","url":"http://static.declarations.com.ua/declarations/chosen_ones/mega_batch/sereda_oleksandr_fedorovych.pdf"},"liabilities":{"54":{"sum_foreign_comment":"","sum":"","sum_comment":"","sum_comment_unclear":false,"sum_hidden":false,"sum_comment_hidden":false,"sum_foreign":""},"55":{"sum_foreign_comment":"","sum":"","sum_comment":"","sum_foreign":""},"56":{"sum_foreign_comment":"","sum":"","sum_comment":"","sum_unclear":false,"sum_foreign":""},"57":{"sum_foreign_comment":"","sum":"","sum_comment":"","sum_comment_unclear":false,"sum_unclear":false,"sum_foreign":""},"58":{"sum_foreign_comment":"","sum":"","sum_comment":"","sum_comment_unclear":false,"sum_unclear":false,"sum_foreign":""},"59":{"sum_foreign_comment":"","sum":"","sum_comment":"","sum_foreign":""},"60":{"sum_foreign_comment":"","sum":"","sum_comment":"","sum_comment_unclear":false,"sum_foreign":""},"61":{"sum_foreign_comment":"","sum":"","sum_comment":"","sum_foreign":""},"62":{"sum_foreign_comment":"","sum":"","sum_comment":"","sum_foreign":""},"63":{"sum_foreign_comment":"","sum":"","sum_comment":"","sum_foreign":""},"64":{"sum_foreign_comment":"","sum":"","sum_comment":"","sum_unclear":false,"sum_foreign":""}},"ft_src":"голова миколаївського окружного адміністративного суду\nМиколаївська область\nАдміністративний місцевий суд\nОлександр\nПодружжя\nФедорович\nСереда\nСереда Олександр Федорович\nСереда Олександр Федорович\nОлександр Федорович Середа\nОлександр Середа\nСереда Олександр Федорович\n5663 куб. см.\nLexus LX-570\n2010\n29.6\n51.3\n2014\n250570.52\n250570.52\n5663 куб. см.\nLexus LX-570\n2010\n29.6\n51.3\nАдміністративний місцевий суд\nМиколаївська область\nголова миколаївського окружного адміністративного суду\nСереда Олександр Федорович\nОлександр Федорович Середа\nОлександр Середа\nСереда Олександр Федорович\nОлександр\nПодружжя\nСереда Олександр Федорович\nСереда\nФедорович\n250570.52\n250570.52\n2014\nПодружжя\nФедорович\nСереда\nОлександр\nСереда Олександр Федорович\nОлександр Федорович Середа\nОлександр Середа\nСереда Олександр Федорович\nМиколаївська область\nАдміністративний місцевий суд\nголова миколаївського окружного адміністративного суду\nСереда Олександр Федорович\n2010\nLexus LX-570\n5663 куб. см.\n250570.52\n250570.52\n29.6\n51.3\n2014","general":{"name_hidden":false,"name":"Олександр","last_name_hidden":false,"inn":"","family":[{"inn":"","inn_hidden":true,"inn_unclear":false,"relations_hidden":false,"relations_other":"","relations":"Подружжя","name_hidden":true,"family_name":"","name_unclear":false}],"patronymic":"Федорович","inn_hidden":true,"family_raw":"","inn_unclear":false,"post":{"post_unclear":false,"region_unclear":false,"post":"голова миколаївського окружного адміністративного суду","office":"Адміністративний місцевий суд","region":"Миколаївська область","post_hidden":false,"office_hidden":false,"office_unclear":false,"region_hidden":false},"last_name_unclear":false,"full_name":"Середа Олександр Федорович","addresses":[{"place_district":"","place_address_hidden":true,"place_city":"","place_city_type_hidden":true,"place_district_hidden":true,"place_city_type":"","place_city_hidden":true,"place_address_unclear":false,"place_address":"","place_hidden":true,"place":""}],"last_name":"Середа","patronymic_hidden":false,"full_name_suggest":{"output":"Середа Олександр Федорович","input":["Середа Олександр Федорович","Олександр Федорович Середа","Олександр Середа"]},"name_unclear":false},"source":"VULYK","estate":{"25":[{"space_unclear":false,"costs":"","costs_comment":"","address_hidden":false,"region_hidden":true,"space_comment":"","space_hidden":false,"space":"51.3","address":"","costs_rent_comment_unclear":false,"region":"","address_unclear":false,"costs_rent_comment":"","space_comment_unclear":false,"space_units":"м²","space_units_hidden":false,"costs_rent":""}],"31":[{"space_unclear":false,"address_hidden":false,"region_hidden":true,"space_comment":"","space":"29.6","address":"","region":"","costs_property":"","costs_rent_comment":"","space_comment_unclear":false,"space_units":"м²","costs_property_comment":"","costs_rent":""}]},"intro":{"declaration_year":"2014","isnotdeclaration":"","declaration_year_hidden":false}}