{"income":{"5":{"family_comment":"","family_unclear":false,"value":"372493","family":"71352","comment":""},"6":{"family_comment":"","value":"190928","value_unclear":false,"family":"67855","comment":""},"7":{"family_comment":"","value":"","source_name":"","family":"","comment":""},"8":{"family_comment":"","value":"","family":"","comment":""},"9":{"value":"","value_unclear":false,"family_hidden":false,"family_comment":"","comment_unclear":false,"comment":"","family":""},"10":{"family_comment":"","value":"12180","family":"3497","comment":""},"11":{"family_comment":"","value":"","family":"","comment":""},"12":{"family_comment":"","value":"","family":"","comment":""},"13":{"family_comment":"","value":"","family":"","comment":""},"14":{"family_comment":"","value":"165716","family":"","comment":""},"15":{"family_comment":"","value":"","family":"","comment":""},"16":{"family_comment":"","value":"","family":"","comment":""},"17":{"family_comment":"","value":"","family":"","comment":""},"18":{"family_comment":"","value":"","family":"","comment":""},"19":{"family_comment":"","value":"3669","family":"","comment":""},"20":{"value":"","value_unclear":false,"comment_hidden":false,"family_comment":"","family":"","comment":""}},"vehicle":{"40":[{"brand_info":"1798 куб. см.","sum_rent_comment":"","brand":"Volkswagen Passat","sum_comment":"","year":"2012","brand_info_unclear":false,"sum":"","sum_rent":""}]},"id":"vulyk_40_30","banks":{"45":[{"sum_foreign_comment":"","sum_units":"UAH","sum_comment":"","sum_hidden":false,"sum_foreign_units":"UAH","sum":"","sum_foreign":""},{"sum_foreign_comment":"","sum_units":"","sum_comment":"","sum_foreign_units":"","sum":"","sum_foreign":""},{"sum_foreign_comment":"","sum_units":"","sum_comment":"","sum_foreign_units":"","sum":"","sum_foreign":""}],"46":[{"sum_foreign_comment":"","sum_units":"UAH","sum_comment":"","sum_foreign_units":"UAH","sum":"","sum_unclear":false,"sum_foreign":""}],"47":[{"sum_foreign_comment":"","sum_units":"UAH","sum_comment":"","sum_foreign_units":"UAH","sum":"","sum_foreign":""}],"48":[{"sum_foreign_comment":"","sum_units":"UAH","sum_comment":"","sum_foreign_units":"UAH","sum":"","sum_foreign":""}],"49":[{"sum_foreign_comment":"","sum_units":"UAH","sum_comment":"","sum_foreign_units":"UAH","sum":"","sum_foreign":""}],"50":[{"sum_foreign_comment":"","sum_units":"UAH","sum_comment":"","sum_foreign_units":"UAH","sum":"","sum_foreign":""}],"51":[{"sum_foreign_comment":"","sum_units":"UAH","sum_comment":"","sum_foreign_units":"UAH","sum":"","sum_foreign":""}],"52":[{"sum_foreign_comment":"","sum_units":"UAH","sum_comment":"","sum_foreign_units":"UAH","sum":"","sum_foreign":""}],"53":[{"sum_foreign_comment":"","sum_units":"UAH","sum_comment":"","sum_foreign_units":"UAH","sum":"","sum_foreign":""}]},"declaration":{"date":"2015-03-27T00:00:00","notfull":"","url":"http://static.declarations.com.ua/declarations/chosen_ones/mega_batch/ilchenko_valentyna_mykolaivna.pdf","notfull_lostpages":""},"liabilities":{"54":{"sum_foreign_comment":"","sum":"","sum_comment":"","sum_foreign":""},"55":{"sum_foreign_comment":"","sum":"","sum_comment":"","sum_foreign":""},"56":{"sum_foreign_comment":"","sum":"","sum_comment":"","sum_foreign":""},"57":{"sum_foreign_comment":"","sum":"","sum_comment":"","sum_hidden":false,"sum_comment_hidden":false,"sum_foreign":""},"58":{"sum_foreign_comment":"","sum":"","sum_comment":"","sum_hidden":false,"sum_comment_hidden":false,"sum_foreign":""},"59":{"sum_foreign_comment":"","sum":"","sum_comment":"","sum_foreign":""},"60":{"sum_foreign_comment":"","sum":"","sum_comment":"","sum_foreign":""},"61":{"sum_foreign_comment":"","sum":"","sum_comment":"","sum_foreign":""},"62":{"sum_foreign_comment":"","sum":"","sum_comment":"","sum_foreign":""},"63":{"sum_foreign_comment":"","sum":"","sum_comment":"","sum_foreign":""},"64":{"sum_foreign_comment":"","sum":"","sum_comment":"","sum_foreign":""}},"ft_src":"Ільченко Валентина Миколаївна\nсуддя охтирського міськрайонного суду сумської області\nСумська область\nЗагальний місцевий суд\nВалентина\nІльченко В. В\nПодружжя\nІльченко В. В\nДитина\nІльченко А. В\nДитина\nІльченко Валентина Миколаївна\nВалентина Миколаївна Ільченко\nВалентина Ільченко\nІльченко Валентина Миколаївна\nІльченко\nМиколаївна\n1798 куб. см.\n2012\nVolkswagen Passat\n2014\n1798 куб. см.\nVolkswagen Passat\n2012\n44000\n3100\n62.55\n20.85\n53.2\nІльченко\nІльченко Валентина Миколаївна\nВалентина Миколаївна Ільченко\nВалентина Ільченко\nІльченко Валентина Миколаївна\nВалентина\nМиколаївна\nІльченко Валентина Миколаївна\nЗагальний місцевий суд\nсуддя охтирського міськрайонного суду сумської області\nСумська область\nПодружжя\nІльченко В. В\nДитина\nІльченко В. В\nІльченко А. В\nДитина\n190928\n67855\n165716\n372493\n71352\n12180\n3497\n3669\n2014\n44000\n3100\n62.55\n20.85\n53.2\nІльченко В. В\nПодружжя\nІльченко В. В\nДитина\nІльченко А. В\nДитина\nМиколаївна\nІльченко\nсуддя охтирського міськрайонного суду сумської області\nСумська область\nЗагальний місцевий суд\nІльченко Валентина Миколаївна\nІльченко Валентина Миколаївна\nВалентина Миколаївна Ільченко\nВалентина Ільченко\nІльченко Валентина Миколаївна\nВалентина\n67855\n190928\n165716\n3497\n12180\n71352\n372493\n3669\n2012\n1798 куб. см.\nVolkswagen Passat\n3669\n165716\n3497\n12180\n71352\n372493\n67855\n190928\n62.55\n44000\n20.85\n53.2\n3100\n2014","general":{"inn":"","inn_hidden":true,"last_name":"Ільченко","post":{"office":"Загальний місцевий суд","region":"Сумська область","post":"суддя охтирського міськрайонного суду сумської області"},"name":"Валентина","full_name":"Ільченко Валентина Миколаївна","family_raw":"","addresses":[{"place_district":"","place_city_hidden":false,"place_city":"","place_city_type_hidden":false,"place_district_hidden":false,"place_city_type":"","place_address_hidden":false,"place_address":"","place_hidden":true,"place":""}],"family":[{"inn":"","relations":"Подружжя","relations_other":"","inn_hidden":false,"family_name":"Ільченко В. В","name_hidden":false},{"inn":"","relations":"Дитина","relations_other":"","inn_hidden":false,"family_name":"Ільченко В. В","name_unclear":false},{"inn":"","family_name":"Ільченко А. В","relations":"Дитина","inn_hidden":false}],"full_name_suggest":{"output":"Ільченко Валентина Миколаївна","input":["Ільченко Валентина Миколаївна","Валентина Миколаївна Ільченко","Валентина Ільченко"]},"patronymic":"Миколаївна"},"source":"VULYK","estate":{"23":[{"costs_rent":"","region":"","costs":"","costs_rent_comment":"","costs_comment":"","address_hidden":false,"region_hidden":true,"space_comment":"","space_units":"м²","space":"44000","address":""},{"costs_rent":"","region":"","costs":"","costs_rent_comment":"","costs_comment":"","space_comment":"","space_units":"","space":"","address":""},{"costs_rent":"","region":"","costs":"","costs_rent_comment":"","costs_comment":"","space_comment":"","space_units":"","space":"","address":""},{"costs_rent":"","costs":"","costs_rent_comment":"","costs_comment":"","space_comment":"","space_units":"","space":"","address":""}],"25":[{"costs_rent":"","region":"","costs":"","costs_rent_comment":"","costs_comment":"","address_hidden":false,"region_hidden":true,"space_comment":"","space_units":"м²","space":"20.85","address":""},{"costs_rent":"","costs":"","costs_rent_comment":"","costs_comment":"","region_hidden":false,"space_comment":"","space_units":"м²","space":"53.2","address":""}],"29":[{"costs_rent":"","region":"","costs_property":"","costs_rent_comment":"","address_hidden":false,"region_hidden":true,"space_comment":"","costs_property_comment":"","space_units":"м²","space":"3100","address":""}],"31":[{"space_hidden":false,"address_hidden":false,"region_hidden":true,"space_comment":"","space":"62.55","address":"","region":"","costs_property":"","costs_rent_comment":"","space_units":"м²","costs_property_comment":"","costs_rent":""}]},"intro":{"declaration_year":"2014"}}