{"income":{"5":{"value":"274954","family_comment":"","comment_unclear":false,"family_unclear":false,"family":"","comment":""},"6":{"family_comment":"","value":"264671","family":"","comment":""},"7":{"source_name_unclear":false,"value":"","comment_unclear":false,"family_comment":"","source_name":"","family":"","comment":""},"8":{"family_comment":"","value":"","family":"","comment":""},"9":{"family_comment":"","value":"","family":"","comment":""},"10":{"family_comment":"","value":"","family":"","comment":""},"11":{"family_comment":"","value":"","family":"","comment":""},"12":{"family_comment":"","value":"","family":"","comment":""},"13":{"family_comment":"","value":"","family":"","comment":""},"14":{"family_comment":"","value":"","family":"","comment":""},"15":{"family_comment":"","value":"","family":"","comment":""},"16":{"family_comment":"","family_unclear":false,"value":"","family":"","comment":""},"17":{"family_comment":"","value":"","family":"","comment":""},"18":{"family_comment":"","value":"","family":"","comment":""},"19":{"family_comment":"","value":"2400","family":"","comment":""},"20":{"value":"7883","family_comment":"","comment_unclear":false,"family_unclear":false,"family":"","comment":"","family_comment_unclear":false}},"id":"vulyk_107_59","banks":{"45":[{"sum_foreign_comment":"","sum_units":"UAH","sum_comment":"","sum_comment_unclear":false,"sum_foreign_units":"UAH","sum_comment_hidden":false,"sum_unclear":false,"sum":"83","sum_foreign":""}],"46":[{"sum_foreign_comment":"","sum_units":"UAH","sum_comment":"","sum_foreign_units":"UAH","sum":"83","sum_foreign":""}]},"declaration":{"additional_info_text":"","notfull_lostpages":"","date":"2016-03-30T00:00:00","notfull":"","additional_info":"","url":"http://static.declarations.com.ua/declarations/chosen_ones/judges_batch/2038_mishchenko_olha_andronykivna.pdf"},"liabilities":{"54":{"sum_foreign_comment":"","sum":"","sum_comment":"","sum_comment_unclear":false,"sum_comment_hidden":false,"sum_foreign":""},"55":{"sum_foreign_comment":"","sum":"","sum_comment":"","sum_foreign":""},"56":{"sum_foreign_comment":"","sum":"","sum_comment":"","sum_unclear":false,"sum_foreign":""},"57":{"sum_foreign_comment":"","sum":"15003","sum_comment":"","sum_comment_unclear":false,"sum_foreign":""},"58":{"sum_foreign_comment":"","sum":"8579","sum_comment":"","sum_comment_unclear":false,"sum_unclear":false,"sum_foreign":""},"59":{"sum_foreign_comment":"","sum":"","sum_comment":"","sum_unclear":false,"sum_foreign":""},"60":{"sum_foreign_comment":"","sum":"","sum_comment":"","sum_comment_unclear":false,"sum_comment_hidden":false,"sum_foreign":""},"61":{"sum_foreign_comment":"","sum":"","sum_comment":"","sum_foreign":""},"62":{"sum_foreign_comment":"","sum":"","sum_comment":"","sum_foreign":""},"63":{"sum_foreign_comment":"","sum":"","sum_comment":"","sum_foreign":""},"64":{"sum_foreign_comment":"","sum":"","sum_comment":"","sum_foreign":""}},"ft_src":"15003\n8579\nМіщенко Ольга Андрониківна\nсуддя апеляційного суду рівненської області\nРівненська область\nЗагальний апеляційний суд\nОльга\nМіщенко Ольга Андрониківна\nОльга Андрониківна Міщенко\nОльга Міщенко\nМіщенко Ольга Андрониківна\nМіщенко\nАндрониківна\n2400\n7883\n274954\n264671\n83\n83\nспадщина\n19007\nспадщина\n20204\n3/4 ч.\n62.4\n1/2 ч.\n68.8\n1/2, спадщина\n68.8\n2015\n264671\n274954\n2400\n7883\n83\n83\n2015\nМіщенко\nМіщенко Ольга Андрониківна\nОльга Андрониківна Міщенко\nОльга Міщенко\nМіщенко Ольга Андрониківна\nОльга\nАндрониківна\nМіщенко Ольга Андрониківна\nЗагальний апеляційний суд\nсуддя апеляційного суду рівненської області\nРівненська область\n15003\n8579\n264671\n7883\n274954\n2400\n19007\nспадщина\n20204\nспадщина\n62.4\n3/4 ч.\n68.8\n1/2 ч.\n68.8\n1/2, спадщина\n8579\n15003\nМіщенко\nАндрониківна\nсуддя апеляційного суду рівненської області\nРівненська область\nЗагальний апеляційний суд\nМіщенко Ольга Андрониківна\nМіщенко Ольга Андрониківна\nОльга Андрониківна Міщенко\nОльга Міщенко\nМіщенко Ольга Андрониківна\nОльга\n3/4 ч.\n62.4\n1/2 ч.\n68.8\n1/2, спадщина\n68.8\nспадщина\n19007\nспадщина\n20204\n83\n83\n2015","general":{"inn":"","inn_hidden":true,"last_name":"Міщенко","post":{"post_unclear":false,"office":"Загальний апеляційний суд","post":"суддя апеляційного суду рівненської області","region":"Рівненська область"},"name":"Ольга","full_name":"Міщенко Ольга Андрониківна","family_raw":"","addresses":[{"place_district":"","place_city_hidden":true,"place_city":"","place_city_type_hidden":false,"place_district_hidden":true,"place_city_type":"","place_address_hidden":true,"place_address":"","place_hidden":true,"place":""}],"full_name_suggest":{"output":"Міщенко Ольга Андрониківна","input":["Міщенко Ольга Андрониківна","Ольга Андрониківна Міщенко","Ольга Міщенко"]},"patronymic":"Андрониківна"},"source":"VULYK","estate":{"23":[{"costs":"","costs_comment":"","address_hidden":true,"region_hidden":true,"space_comment":"спадщина","space":"19007","address":"","region":"","costs_rent_comment":"","space_comment_unclear":false,"space_comment_hidden":false,"space_units":"м²","costs_rent":""},{"costs_rent":"","region":"","costs":"","costs_rent_comment":"","costs_comment":"","address_hidden":false,"region_hidden":false,"space_comment":"спадщина","space_units":"м²","space":"20204","address":""}],"25":[{"space_hidden":false,"costs":"","costs_comment":"","address_hidden":true,"region_hidden":true,"space_comment":"3/4 ч.","space_unclear":false,"space":"62.4","address":"","region":"","costs_rent_comment":"","space_units":"м²","costs_rent":""},{"costs_rent":"","region":"","costs":"","costs_rent_comment":"","costs_comment":"","space_comment":"1/2 ч.","space_units":"м²","space":"68.8","address":""},{"costs_rent":"","region":"","costs":"","costs_rent_comment":"","costs_comment":"","space_comment":"1/2, спадщина","space_units":"м²","space":"68.8","address":""}]},"intro":{"declaration_year":"2015","isnotdeclaration":""}}