{"income":{"5":{"value":"185526","family_comment":"","value_unclear":false,"family_unclear":false,"family":"75795","comment":""},"6":{"family_comment":"","value":"185526","value_unclear":false,"family":"31461","comment":""},"7":{"family_comment":"","value":"","source_name":"","family":"","comment":""},"8":{"family_comment":"","value":"","family":"","comment":""},"9":{"family_comment":"","value":"","value_unclear":false,"family":"","comment":""},"10":{"family_comment":"","value":"","family":"","comment":""},"11":{"family_comment":"","value":"","family":"","comment":""},"12":{"family_comment":"","value":"","family":"","comment":""},"13":{"family_comment":"","value":"","family":"","comment":""},"14":{"family_comment":"","value":"","family":"","comment":""},"15":{"family_comment":"","value":"","family":"","comment":""},"16":{"family_comment":"","value":"","family":"","comment":""},"17":{"family_comment":"","value":"","family":"","comment":""},"18":{"family_comment":"","value":"","family":"","comment":""},"19":{"family_comment":"","value":"","family":"","comment":""},"20":{"family_comment":"","value":"","value_unclear":false,"family":"44334","comment":""}},"vehicle":{"35":[{"brand_info":"1598 куб. см.","sum_rent_comment":"","brand":"Toyota Corolla","sum_comment":"","brand_unclear":false,"year":"2008","brand_info_unclear":false,"sum":"","sum_rent":""},{"brand_info":"2698 куб. см.","sum_rent_comment":"","brand":"Toyota Prado","sum_comment":"","brand_unclear":false,"year":"2006","sum":"","sum_rent":""}],"40":[{"brand_info":"1598 куб. см.","sum_rent_comment":"","brand":"Toyota Corolla","sum_comment":"","year":"2008","sum":"","sum_rent":""}]},"id":"vulyk_98_36","banks":{"53":[{"sum_foreign_comment":"","sum_units":"UAH","sum_comment":"Товариство з обмеженної відповідальністю Агрофірма Ватра","sum_foreign_units":"UAH","sum_comment_hidden":false,"sum_unclear":true,"sum":"23316","sum_foreign":""}]},"declaration":{"date":"2015-03-25T00:00:00","url":"http://static.declarations.com.ua/declarations/chosen_ones/judges_batch/4533_kotormus_taras_ihorovych.pdf"},"liabilities":{"54":{"sum_foreign_comment":"","sum":"","sum_comment":"","sum_comment_unclear":false,"sum_hidden":false,"sum_comment_hidden":false,"sum_unclear":false,"sum_foreign":""},"55":{"sum_foreign_comment":"","sum":"","sum_comment":"","sum_foreign":""},"56":{"sum_foreign_comment":"","sum":"","sum_comment":"","sum_unclear":false,"sum_foreign":""},"57":{"sum_foreign_comment":"","sum":"","sum_comment":"","sum_comment_unclear":false,"sum_hidden":false,"sum_comment_hidden":false,"sum_unclear":false,"sum_foreign":""},"58":{"sum_foreign_comment":"","sum":"","sum_comment":"","sum_hidden":false,"sum_comment_hidden":false,"sum_unclear":false,"sum_foreign":""},"59":{"sum_foreign_comment":"","sum":"","sum_comment":"","sum_comment_unclear":false,"sum_foreign":""},"60":{"sum_foreign_comment":"","sum":"","sum_comment":"","sum_hidden":false,"sum_comment_hidden":false,"sum_foreign":""},"61":{"sum_foreign_comment":"","sum":"","sum_comment":"","sum_foreign":""},"62":{"sum_foreign_comment":"","sum":"","sum_comment":"","sum_comment_hidden":false,"sum_unclear":false,"sum_foreign":""},"63":{"sum_foreign_comment":"","sum":"46737","sum_comment":"Публічне акціонерне товариство Укрсоцбанк","sum_comment_unclear":false,"sum_comment_hidden":false,"sum_foreign":""},"64":{"sum_foreign_comment":"","sum_comment_hidden":false,"sum":"3040","sum_comment":"Публічне акціонерне товариство Укрсоцбанк","sum_foreign":""}},"ft_src":"Публічне акціонерне товариство Укрсоцбанк\n3040\nПублічне акціонерне товариство Укрсоцбанк\n46737\nсуддя костянтинівського міськрайонного суду донецької області\nДонецька область\nЗагальний місцевий суд\nТарас\nЛевицька Г. С\nПодружжя\nКотормус Ф. Т\nДитина\nКотормус А. Т\nДитина\nКотормус І. М\nБатьки\nКотормус С. М\nБатьки\nЛевицька Л. Л\nТеща\nІнше\nІгорович\nКотормус Тарас Ігорович\nТарас Ігорович Котормус\nТарас Котормус\nКотормус Тарас Ігорович\nКотормус Тарас Ігорович\nКотормус\n2008\nToyota Corolla\n1598 куб. см.\n2006\n2698 куб. см.\nToyota Prado\n1598 куб. см.\n2008\nToyota Corolla\nЛьвівська область\nс. Доброгостів Дрогобицького району\n.3\nЛьвівська область\nс. Доброгостів Дрогобицького району\n.0155\nЛьвівська область\nм. Львів\n70.6\nЛьвівська область\nм. Львів\n40.2\nЛьвівська область\nс. Доброгостів Дрогобицького району\n196.2\nНежитлове приміщення\nЛьвівська область\nм. Львів\n22.8\nТовариство з обмеженної відповідальністю Агрофірма Ватра\n23316\n2014\n1598 куб. см.\n2008\nToyota Corolla\n2698 куб. см.\nToyota Prado\n2006\n1598 куб. см.\n2008\nToyota Corolla\n2014\nЗагальний місцевий суд\nсуддя костянтинівського міськрайонного суду донецької області\nДонецька область\nКотормус Тарас Ігорович\nТарас Ігорович Котормус\nТарас Котормус\nКотормус Тарас Ігорович\nКотормус Тарас Ігорович\nПодружжя\nЛевицька Г. С\nДитина\nКотормус Ф. Т\nДитина\nКотормус А. Т\nКотормус І. М\nБатьки\nКотормус С. М\nБатьки\nЛевицька Л. Л\nІнше\nТеща\nТарас\nКотормус\nІгорович\nПублічне акціонерне товариство Укрсоцбанк\n3040\nПублічне акціонерне товариство Укрсоцбанк\n46737\n185526\n31461\n44334\n75795\n185526\n.3\nс. Доброгостів Дрогобицького району\nЛьвівська область\n.0155\nЛьвівська область\nс. Доброгостів Дрогобицького району\nЛьвівська область\nс. Доброгостів Дрогобицького району\n196.2\nм. Львів\n70.6\nЛьвівська область\n40.2\nм. Львів\nЛьвівська область\nНежитлове приміщення\nЛьвівська область\nм. Львів\n22.8\n23316\nТовариство з обмеженної відповідальністю Агрофірма Ватра\nПублічне акціонерне товариство Укрсоцбанк\n3040\nПублічне акціонерне товариство Укрсоцбанк\n46737\n31461\n185526\n75795\n185526\n44334\nПодружжя\nЛевицька Г. С\nДитина\nКотормус Ф. Т\nКотормус А. Т\nДитина\nКотормус І. М\nБатьки\nКотормус С. М\nБатьки\nІнше\nТеща\nЛевицька Л. Л\nІгорович\nКотормус\nТарас\nКотормус Тарас Ігорович\nТарас Ігорович Котормус\nТарас Котормус\nКотормус Тарас Ігорович\nсуддя костянтинівського міськрайонного суду донецької області\nДонецька область\nЗагальний місцевий суд\nКотормус Тарас Ігорович\n2008\n1598 куб. см.\nToyota Corolla\n2006\n2698 куб. см.\nToyota Prado\nToyota Corolla\n1598 куб. см.\n2008\n44334\n185526\n75795\n31461\n185526\nм. Львів\nЛьвівська область\n70.6\nм. Львів\nЛьвівська область\n40.2\nс. Доброгостів Дрогобицького району\nЛьвівська область\n196.2\nНежитлове приміщення\nм. Львів\nЛьвівська область\n22.8\nс. Доброгостів Дрогобицького району\nЛьвівська область\n.3\nс. Доброгостів Дрогобицького району\nЛьвівська область\n.0155\nТовариство з обмеженної відповідальністю Агрофірма Ватра\n23316\n2014","general":{"inn":"","name":"Тарас","last_name_hidden":false,"family":[{"inn":"","relations":"Подружжя","relations_other":"","inn_hidden":true,"family_name":"Левицька Г. С","name_hidden":true,"name_unclear":false},{"inn":"","relations":"Дитина","relations_other":"","inn_hidden":true,"family_name":"Котормус Ф. Т","name_hidden":false,"name_unclear":false},{"inn_hidden":true,"inn":"","name_hidden":false,"family_name":"Котормус А. Т","relations":"Дитина","name_unclear":false},{"inn":"","family_name":"Котормус І. М","relations":"Батьки","inn_hidden":true,"name_hidden":false},{"inn":"","family_name":"Котормус С. М","relations":"Батьки","inn_hidden":true},{"inn":"","family_name":"Левицька Л. Л","relations":"Інше","inn_hidden":true,"relations_other":"Теща"}],"patronymic":"Ігорович","inn_hidden":true,"family_raw":"","inn_unclear":false,"post":{"post_unclear":false,"office":"Загальний місцевий суд","post":"суддя костянтинівського міськрайонного суду донецької області","region":"Донецька область"},"full_name_suggest":{"output":"Котормус Тарас Ігорович","input":["Котормус Тарас Ігорович","Тарас Ігорович Котормус","Тарас Котормус"]},"full_name":"Котормус Тарас Ігорович","addresses":[{"place_district":"","place_city_hidden":true,"place_city":"","place_city_type_hidden":false,"place_district_hidden":false,"place_city_type":"","place_address_hidden":true,"place_address":"","place_hidden":true,"place":""}],"last_name":"Котормус","patronymic_hidden":false,"last_name_unclear":false},"source":"VULYK","estate":{"29":[{"costs_rent":"","region":"Львівська область","costs_property":"","costs_rent_comment":"","address_hidden":true,"region_hidden":false,"space_comment":"","costs_property_comment":"","space_units":"га","space":".3","address":"с. Доброгостів Дрогобицького району"},{"costs_rent":"","region":"Львівська область","costs_property":"","costs_rent_comment":"","space_comment":"","costs_property_comment":"","space_units":"га","space":".0155","address":"с. Доброгостів Дрогобицького району"}],"30":[{"space_unclear":false,"address_hidden":true,"region_hidden":false,"space_comment":"","space":"196.2","address":"с. Доброгостів Дрогобицького району","region":"Львівська область","costs_property":"","costs_rent_comment":"","space_units":"м²","costs_property_comment":"","costs_rent":""}],"31":[{"region_unclear":false,"address_hidden":true,"region_hidden":false,"space_comment":"","space":"70.6","address":"м. Львів","region":"Львівська область","costs_property":"","costs_rent_comment":"","space_units":"м²","costs_property_comment":"","costs_rent":""},{"costs_rent":"","region":"Львівська область","costs_property":"","costs_rent_comment":"","space_comment":"","costs_property_comment":"","space_units":"м²","space":"40.2","address":"м. Львів"}],"34":[{"space_unclear":false,"address_hidden":true,"region_hidden":false,"space_comment":"Нежитлове приміщення","space":"22.8","address":"м. Львів","region":"Львівська область","costs_property":"","costs_rent_comment":"","address_unclear":false,"space_units":"м²","costs_property_comment":"","costs_rent":""}]},"intro":{"declaration_year":"2014"}}