{"income":{"5":{"family_comment":"","value":"555846","value_unclear":false,"family":"61849","comment":""},"6":{"family_comment":"","value":"400735","value_unclear":false,"family":"","comment":""},"7":{"source_name_unclear":false,"value":"12520","family_hidden":false,"value_hidden":false,"family_comment":"","source_name":"Верховний Суд України, Національний університет біоресурсів та природокористування","family":"61849","comment":"","source_name_hidden":false},"8":{"value":"","family_hidden":false,"value_hidden":false,"family_comment":"","family":"","comment":""},"9":{"value":"127680","value_unclear":true,"value_hidden":false,"family_comment":"","comment_unclear":true,"comment":"банк 'Даніель'","family":""},"10":{"value":"14911","family_hidden":false,"value_hidden":false,"family_comment":"","family":"","comment":""},"11":{"value":"","family_hidden":false,"value_hidden":false,"family_comment":"","family":"","comment":""},"12":{"value":"","family_hidden":false,"value_hidden":false,"family_comment":"","family":"","comment":""},"13":{"value":"","family_hidden":false,"value_hidden":false,"family_comment":"","family":"","comment":""},"14":{"value":"","family_hidden":false,"value_hidden":false,"family_comment":"","family":"","comment":""},"15":{"value":"","family_hidden":false,"value_hidden":false,"family_comment":"","family":"","comment":""},"16":{"value":"","family_hidden":false,"value_hidden":false,"family_comment":"","family":"","comment":""},"17":{"value":"","family_hidden":false,"value_hidden":false,"family_comment":"","family":"","comment":""},"18":{"value":"","comment_unclear":false,"family_hidden":false,"value_hidden":false,"family_comment":"","family":"","comment":""},"19":{"value":"","family_hidden":false,"value_hidden":false,"family_comment":"","family":"","comment":""},"20":{"value":"","value_unclear":false,"family_hidden":false,"value_hidden":false,"family_comment":"","comment_unclear":false,"comment":"","family":""}},"vehicle":{"35":[{"brand_info":"2.0 л, 150 к. с","sum_rent_comment":"","sum_rent_hidden":false,"year":"2007","sum_hidden":false,"brand_info_unclear":false,"sum_rent":"","sum":"","brand":"Honda CR-V","sum_comment":"","brand_unclear":false,"sum_rent_comment_hidden":false,"sum_comment_hidden":false,"sum_unclear":false}]},"id":"vulyk_70_24","banks":{"51":[{"sum_units":"UAH","sum_hidden":false,"sum":"82425","sum_units_hidden":false,"sum_foreign_comment":"","sum_foreign_hidden":false,"sum_comment":"","sum_comment_unclear":false,"sum_foreign_units":"UAH","sum_foreign":"","sum_comment_hidden":false,"sum_unclear":false}]},"declaration":{"additional_info_text":"","notfull_lostpages":"","date":"2014-03-25T00:00:00","notfull":"","additional_info":"","url":"http://static.declarations.com.ua/declarations/chosen_ones/judges_batch/24_pantaliienko_petro_vasylovych.pdf"},"liabilities":{"54":{"sum_foreign_comment":"","sum_foreign_hidden":false,"sum_comment":"","sum_hidden":false,"sum_foreign_comment_unclear":false,"sum_comment_hidden":false,"sum":"","sum_foreign":""},"55":{"sum_foreign_comment":"","sum":"","sum_hidden":false,"sum_comment":"","sum_foreign":""},"56":{"sum_foreign_comment":"","sum":"","sum_comment":"","sum_foreign":""},"57":{"sum_foreign_comment":"","sum_foreign_hidden":false,"sum_comment":"","sum_hidden":false,"sum_comment_hidden":false,"sum":"","sum_foreign":""},"58":{"sum_foreign_comment":"","sum":"","sum_comment":"","sum_hidden":false,"sum_comment_hidden":false,"sum_foreign":""},"59":{"sum_foreign_comment":"","sum_foreign_hidden":false,"sum_comment":"","sum_hidden":false,"sum":"","sum_foreign":""},"60":{"sum_foreign_comment":"","sum":"","sum_comment":"","sum_comment_unclear":false,"sum_hidden":false,"sum_comment_hidden":false,"sum_foreign":""},"61":{"sum_foreign_comment":"","sum":"","sum_hidden":false,"sum_comment":"","sum_foreign":""},"62":{"sum_foreign_comment":"","sum_foreign_hidden":false,"sum_comment":"","sum_comment_hidden":false,"sum_unclear":false,"sum":"","sum_foreign":""},"63":{"sum_foreign_comment":"","sum_foreign_hidden":false,"sum_comment":"","sum_hidden":false,"sum_comment_hidden":false,"sum":"","sum_foreign":""},"64":{"sum_foreign_comment":"","sum":"","sum_comment":"","sum_hidden":false,"sum_comment_hidden":false,"sum_foreign":""}},"ft_src":"суддя верховного суду україни\nЗагальнодержавний регіон\nВерховний суд\nПетро\nПанталієнко В. В\nПодружжя\nВасильович\nПанталієнко\nПанталієнко Петро Васильович\nПанталієнко Петро Васильович\nПетро Васильович Панталієнко\nПетро Панталієнко\nПанталієнко Петро Васильович\nHonda CR-V\n2.0 л, 150 к. с\n2007\n20\n19.8\n.15\n.09\n.15\n54\n20\n78\n125\n1/3 від 120\n40\nприватизована на 3-х членів сім'і\n120\n1/4 спадщина 3/4 дарунок матері\n51\n82425\n2013\n2.0 л, 150 к. с\nHonda CR-V\n2007\n2013\nПодружжя\nПанталієнко В. В\nПанталієнко Петро Васильович\nПетро Васильович Панталієнко\nПетро Панталієнко\nПанталієнко Петро Васильович\nПетро\nПанталієнко Петро Васильович\nВасильович\nсуддя верховного суду україни\nВерховний суд\nЗагальнодержавний регіон\nПанталієнко\n12520\nВерховний Суд України, Національний університет біоресурсів та природокористування\n61849\n400735\n555846\n61849\n127680\nбанк 'Даніель'\n14911\n20\n19.8\n20\n120\nприватизована на 3-х членів сім'і\n51\n1/4 спадщина 3/4 дарунок матері\n.15\n.09\n.15\n78\n125\n40\n1/3 від 120\n54\n82425\n400735\nбанк 'Даніель'\n127680\n14911\nВерховний Суд України, Національний університет біоресурсів та природокористування\n61849\n12520\n61849\n555846\nПодружжя\nПанталієнко В. В\nПетро\nВасильович\nПанталієнко\nПанталієнко Петро Васильович\nПетро Васильович Панталієнко\nПетро Панталієнко\nПанталієнко Петро Васильович\nЗагальнодержавний регіон\nВерховний суд\nсуддя верховного суду україни\nПанталієнко Петро Васильович\n2007\nHonda CR-V\n2.0 л, 150 к. с\n127680\nбанк 'Даніель'\n14911\n61849\n555846\n12520\n61849\nВерховний Суд України, Національний університет біоресурсів та природокористування\n400735\n78\n125\n1/3 від 120\n40\nприватизована на 3-х членів сім'і\n120\n1/4 спадщина 3/4 дарунок матері\n51\n20\n19.8\n20\n54\n.15\n.09\n.15\n82425\n2013","general":{"inn":"","name":"Петро","inn_unclear":false,"family":[{"inn":"","relations":"Подружжя","inn_unclear":false,"relations_hidden":false,"inn_hidden":true,"relations_other":"","name_hidden":true,"family_name":"Панталієнко В. В","name_unclear":false}],"inn_hidden":true,"family_raw":"","last_name":"Панталієнко","post":{"post":"суддя верховного суду україни","region":"Загальнодержавний регіон","candidate":"","office_hidden":false,"post_hidden":false,"office":"Верховний суд","region_hidden":false},"last_name_unclear":false,"full_name":"Панталієнко Петро Васильович","addresses":[{"place_city_type_unclear":false,"place_address":"","place_district_hidden":true,"place_city_type":"","place_address_hidden":true,"place_address_unclear":false,"place_city_type_hidden":true,"place":"","place_district":"","place_unclear":false,"place_city":"","place_city_unclear":false,"place_hidden":true,"place_city_hidden":true,"place_district_unclear":false}],"patronymic":"Васильович","full_name_suggest":{"output":"Панталієнко Петро Васильович","input":["Панталієнко Петро Васильович","Петро Васильович Панталієнко","Петро Панталієнко"]},"name_unclear":false},"source":"VULYK","estate":{"25":[{"region_unclear":false,"space_unclear":false,"costs":"","costs_comment":"приватизована на 3-х членів сім'і","costs_hidden":false,"address_hidden":false,"region_hidden":true,"space_comment":"","space":"120","address":"","costs_rent_comment_unclear":false,"region":"","costs_rent_comment":"","costs_rent_hidden":false,"space_comment_unclear":false,"costs_rent_comment_hidden":false,"space_units":"м²","costs_comment_hidden":false,"costs_rent":"","costs_unclear":false},{"space_unclear":false,"costs":"","costs_comment":"","address_hidden":false,"region_hidden":false,"space_comment":"1/4 спадщина 3/4 дарунок матері","space":"51","address":"","region":"","address_unclear":false,"costs_rent_comment":"","space_comment_unclear":false,"space_comment_hidden":false,"space_units":"м²","costs_rent":""}],"27":[{"space_hidden":false,"costs":"","costs_comment":"","costs_hidden":false,"address_hidden":false,"region_hidden":true,"space_comment":"","space_unclear":false,"space":"20","address":"","region":"","costs_rent_comment":"","costs_rent_hidden":false,"costs_rent_comment_hidden":false,"space_units":"м²","costs_comment_hidden":false,"costs_rent":""},{"costs_rent":"","region":"","costs":"","costs_rent_comment":"","costs_comment":"","region_hidden":false,"space_comment":"","space_units":"м²","space":"19.8","address":""}],"28":[{"space_hidden":false,"costs":"","costs_comment":"","costs_hidden":false,"address_hidden":false,"region_hidden":true,"space_comment":"","space":"20","address":"","region":"","address_unclear":false,"costs_rent_comment":"","costs_rent_hidden":false,"space_comment_hidden":false,"space_comment_unclear":false,"costs_rent_comment_hidden":false,"space_units":"м²","costs_comment_hidden":false,"costs_rent":""}],"29":[{"space_unclear":false,"costs_property_hidden":false,"address_hidden":false,"region_hidden":true,"space_comment":"","space_hidden":false,"space":".15","address":"","region":"","costs_property":"","costs_rent_comment":"","costs_rent_hidden":false,"space_comment_hidden":false,"space_units":"га","costs_property_comment":"","costs_rent":""},{"space_unclear":false,"region_hidden":false,"space_comment":"","space":".09","address":"","region":"","costs_property":"","costs_rent_comment":"","space_comment_unclear":false,"space_units":"га","costs_property_comment":"","costs_rent":""},{"space_unclear":false,"region_hidden":false,"space_comment":"","space":".15","address":"","region":"","costs_property":"","costs_rent_comment":"","space_comment_unclear":true,"space_units":"га","costs_property_comment":"","costs_rent":""}],"31":[{"region_unclear":false,"space_unclear":false,"costs_property_hidden":false,"address_hidden":false,"region_hidden":true,"space_comment":"","space_units_hidden":false,"space_hidden":false,"space":"78","address":"","region":"","costs_property":"","costs_rent_comment":"","space_comment_unclear":false,"space_units":"м²","costs_property_comment":"","costs_rent":""},{"space_unclear":true,"address_hidden":false,"region_hidden":false,"space_comment":"","space":"125","address":"","region":"","costs_property":"","costs_rent_comment":"","space_comment_unclear":false,"space_units":"м²","costs_property_comment":"","costs_rent":""},{"costs_rent":"","space_unclear":false,"region":"","costs_property":"","costs_rent_comment":"","region_hidden":false,"space_comment":"1/3 від 120","costs_property_comment":"","space_units":"м²","space":"40","address":""}],"32":[{"space_hidden":false,"costs_property_hidden":false,"address_hidden":false,"region_hidden":true,"space_comment":"","space_units_hidden":false,"space":"54","address":"","region":"","costs_property":"","costs_rent_comment":"","costs_rent_hidden":false,"space_units":"м²","costs_property_comment":"","costs_rent":""}]},"intro":{"declaration_year":"2013","isnotdeclaration":"","declaration_year_unclear":false,"declaration_year_hidden":false}}