{"income":{"5":{"family_comment":"","value":"239946","value_unclear":false,"family":"231549","comment":""},"6":{"value":"239442","value_unclear":false,"family_hidden":false,"family_comment":"","family":"231037","comment":""},"7":{"source_name_unclear":false,"value":"","family_comment":"","source_name":"","family":"","comment":""},"8":{"family_comment":"","value":"","family":"","comment":""},"9":{"family_comment":"","value":"504","family":"512","comment":""},"10":{"family_comment":"","value":"","family":"","comment":""},"11":{"family_comment":"","value":"","comment_unclear":false,"family":"","comment":""},"12":{"family_comment":"","value":"","family":"","comment":""},"13":{"family_comment":"","value":"","family":"","comment":""},"14":{"family_comment":"","value":"","family":"","comment":""},"15":{"family_comment":"","value":"","family":"","comment":""},"16":{"family_comment":"","value":"","family":"","comment":""},"17":{"family_comment":"","value":"","family":"","comment":""},"18":{"family_comment":"","value":"","family":"","comment":""},"19":{"family_comment":"","value":"","family":"","comment":""},"20":{"value":"","family_comment":"","comment_unclear":false,"family_unclear":false,"value_unclear":false,"comment":"","family":""}},"vehicle":{"35":[{"brand_info":"1999","sum":"","brand":"Mazda 6","sum_comment":"","brand_unclear":false,"year":"2008","sum_rent_unclear":false,"brand_info_hidden":false,"brand_info_unclear":false,"sum_rent_comment":"","sum_rent":""},{"brand_info":"2696","sum_rent_comment":"","brand":"SsangYong Rexton RX 270","sum_comment":"","year":"2011","brand_info_unclear":false,"sum":"","sum_rent":""}],"40":[{"brand_info":"2696","sum":"","brand":"SsangYong Rexton RX 270","sum_comment":"","year":"2011","brand_hidden":false,"brand_info_hidden":false,"brand_info_unclear":false,"sum_rent_comment":"","sum_rent":""}]},"id":"vulyk_101_67","banks":{"45":[{"sum_foreign_comment":"","sum_units":"UAH","sum_comment":"Укрсиббанк","sum_comment_unclear":false,"sum_hidden":false,"sum_foreign_units":"UAH","sum_comment_hidden":false,"sum_unclear":false,"sum":"64102","sum_foreign":""}],"51":[{"sum_foreign_comment":"","sum_units":"UAH","sum_comment":"Укрсиббанк","sum_hidden":false,"sum_foreign_units":"UAH","sum_comment_hidden":false,"sum_unclear":false,"sum":"64989","sum_foreign":""}]},"declaration":{"additional_info_text":"","notfull_lostpages":"","date":"2016-03-29T00:00:00","notfull":"","additional_info":"","url":"http://static.declarations.com.ua/declarations/chosen_ones/judges_batch/732_stupakov_oleksandr_anatoliiovych_2015.pdf"},"liabilities":{"54":{"sum_foreign_comment":"","sum":"","sum_comment":"","sum_comment_unclear":false,"sum_hidden":false,"sum_comment_hidden":false,"sum_unclear":false,"sum_foreign":""},"55":{"sum_foreign_comment":"","sum":"","sum_comment":"","sum_foreign":""},"56":{"sum_foreign_comment":"","sum":"","sum_comment":"","sum_comment_hidden":false,"sum_unclear":false,"sum_foreign":""},"57":{"sum_foreign_comment":"","sum":"","sum_comment":"","sum_hidden":false,"sum_comment_hidden":false,"sum_unclear":false,"sum_foreign":""},"58":{"sum_foreign_comment":"","sum":"","sum_comment":"","sum_comment_unclear":false,"sum_hidden":false,"sum_comment_hidden":false,"sum_unclear":false,"sum_foreign":""},"59":{"sum_foreign_comment":"","sum":"","sum_comment":"","sum_foreign":""},"60":{"sum_foreign_comment":"","sum":"","sum_comment":"","sum_hidden":false,"sum_comment_hidden":false,"sum_unclear":false,"sum_foreign":""},"61":{"sum_foreign_comment":"","sum":"","sum_comment":"","sum_foreign":""},"62":{"sum_foreign_comment":"","sum":"","sum_comment":"","sum_comment_unclear":false,"sum_foreign":""},"63":{"sum_foreign_comment":"","sum_comment":"","sum":"","sum_comment_hidden":false,"sum_foreign":""},"64":{"sum_foreign_comment":"","sum_comment":"","sum":"","sum_comment_hidden":false,"sum_foreign":""}},"ft_src":"Mazda 6\n1999\n2008\n2696\n2011\nSsangYong Rexton RX 270\n2696\nSsangYong Rexton RX 270\n2011\nУкрсиббанк\n64989\nУкрсиббанк\n64102\n2015\nMazda 6\n1999\n2008\n2696\n2011\nSsangYong Rexton RX 270\n2696\n2011\nSsangYong Rexton RX 270\n64102\nУкрсиббанк\n64989\nУкрсиббанк\n2015\nПодружжя\nСтупакова Інна Гаврилівна\nДитина\nСтупаков Андрій Олександрович\nСтупаков Олександр Анатолійович\nОлександр Анатолійович Ступаков\nОлександр Ступаков\nСтупаков Олександр Анатолійович\nОлександр\nСтупаков Олександр Анатолійович\nАнатолійович\nЗагальний апеляційний суд\nсуддя апеляційного суду одеської області\nОдеська область\nСтупаков\n239442\n231037\n239946\n231549\n504\n512\n57.88\n28.94\n57.88\n28.94\nСтупакова Інна Гаврилівна\nПодружжя\nСтупаков Андрій Олександрович\nДитина\nОлександр\nАнатолійович\nСтупаков\nСтупаков Олександр Анатолійович\nОлександр Анатолійович Ступаков\nОлександр Ступаков\nСтупаков Олександр Анатолійович\nсуддя апеляційного суду одеської області\nЗагальний апеляційний суд\nОдеська область\nСтупаков Олександр Анатолійович\n231037\n239442\n512\n504\n231549\n239946","general":{"inn":"","name":"Олександр","last_name":"Ступаков","family":[{"inn":"","inn_hidden":true,"family_name":"Ступакова Інна Гаврилівна","relations_other":"","relations":"Подружжя","name_hidden":true,"name_unclear":false},{"inn":"","inn_hidden":true,"relations_unclear":false,"family_name":"Ступаков Андрій Олександрович","relations_other":"","relations":"Дитина","name_hidden":false,"name_unclear":false}],"inn_hidden":true,"family_raw":"","inn_unclear":false,"post":{"region":"Одеська область","office":"Загальний апеляційний суд","post":"суддя апеляційного суду одеської області","office_unclear":false,"region_unclear":false},"full_name":"Ступаков Олександр Анатолійович","addresses":[{"place_district":"","place_address_hidden":true,"place_city":"","place_address":"","place_district_hidden":false,"place_city_type":"","place_city_hidden":true,"place_city_type_hidden":false,"place_hidden":true,"place":""}],"patronymic":"Анатолійович","patronymic_hidden":false,"full_name_suggest":{"output":"Ступаков Олександр Анатолійович","input":["Ступаков Олександр Анатолійович","Олександр Анатолійович Ступаков","Олександр Ступаков"]}},"source":"VULYK","estate":{"25":[{"space_unclear":false,"costs":"","costs_comment":"","address_hidden":false,"region_hidden":true,"space_comment":"","space_hidden":false,"space":"28.94","address":"","region":"","costs_rent_comment":"","space_comment_unclear":false,"space_units":"м²","costs_rent":""}],"31":[{"space_unclear":false,"address_hidden":true,"region_hidden":true,"space_comment":"","space_hidden":false,"space":"57.88","address":"","costs_rent_comment_unclear":false,"region":"","costs_property":"","costs_rent_comment":"","space_units":"м²","costs_property_comment":"","costs_rent":""}]},"intro":{"declaration_year":"2015"}}