{"income":{"5":{"value":"191974","family_comment":"","value_unclear":false,"family_unclear":false,"family":"","comment":""},"6":{"value":"191974","family_comment":"","value_unclear":false,"family_unclear":false,"family":"","comment":""},"7":{"family_comment":"","value":"","source_name":"","family":"","comment":""},"8":{"family_comment":"","value":"","family":"","comment":""},"9":{"family_comment":"","value":"","family":"","comment":""},"10":{"family_comment":"","value":"","family":"","comment":""},"11":{"family_comment":"","value":"","family":"","comment":""},"12":{"family_comment":"","value":"","family":"","comment":""},"13":{"family_comment":"","value":"","family":"","comment":""},"14":{"family_comment":"","value":"","family":"","comment":""},"15":{"family_comment":"","value":"","value_unclear":false,"family":"","comment":""},"16":{"family_comment":"","value":"","family":"","comment":""},"17":{"family_comment":"","value":"","family":"","comment":""},"18":{"family_comment":"","value":"","family":"","comment":""},"19":{"family_comment":"","value":"","family":"","comment":""},"20":{"value":"","family_comment":"","value_unclear":false,"family_unclear":false,"family":"","comment":"","family_comment_unclear":false}},"id":"vulyk_99_98","declaration":{"date":"2016-03-23T00:00:00","notfull":"","url":"http://static.declarations.com.ua/declarations/chosen_ones/judges_batch/647_litvinov_serhii_volodymyyrovych_2015.pdf","notfull_lostpages":""},"liabilities":{"54":{"sum_foreign_comment":"","sum":"","sum_comment":"","sum_comment_unclear":false,"sum_comment_hidden":false,"sum_foreign":""},"55":{"sum_foreign_comment":"","sum":"","sum_comment":"","sum_foreign":""},"56":{"sum_foreign_comment":"","sum":"","sum_comment":"","sum_foreign":""},"57":{"sum_foreign_comment":"","sum_comment_hidden":false,"sum":"","sum_comment":"","sum_foreign":""},"58":{"sum_foreign_comment":"","sum_comment_hidden":false,"sum":"","sum_comment":"","sum_foreign":""},"59":{"sum_foreign_comment":"","sum":"","sum_comment":"","sum_comment_hidden":false,"sum_unclear":false,"sum_foreign":""},"60":{"sum_foreign_comment":"","sum_comment_hidden":false,"sum":"","sum_comment":"","sum_foreign":""},"61":{"sum_foreign_comment":"","sum":"","sum_comment":"","sum_foreign":""},"62":{"sum_foreign_comment":"","sum":"","sum_comment":"","sum_foreign":""},"63":{"sum_foreign_comment":"","sum_comment_hidden":false,"sum":"","sum_comment":"","sum_foreign":""},"64":{"sum_foreign_comment":"","sum_comment_hidden":false,"sum":"","sum_comment":"","sum_foreign":""}},"ft_src":"Літвінов Сергій Володимирович\nсуддя господарського суду одеської області\nОдеська область\nГосподарський місцевий суд\nСергій\nЛітвінов В. С\nДитина\nЛітвінов І. С\nДитина\nЛітвінов Сергій Володимирович\nСергій Володимирович Літвінов\nСергій Літвінов\nЛітвінов Сергій Володимирович\nЛітвінов\nВолодимирович\n191974\n191974\n2015\n191974\n191974\n191974\n191974\nЛітвінов\nЛітвінов Сергій Володимирович\nСергій Володимирович Літвінов\nСергій Літвінов\nЛітвінов Сергій Володимирович\nСергій\nВолодимирович\nЛітвінов Сергій Володимирович\nГосподарський місцевий суд\nсуддя господарського суду одеської області\nОдеська область\nДитина\nЛітвінов В. С\nДитина\nЛітвінов І. С\n2015\nЛітвінов В. С\nДитина\nЛітвінов І. С\nДитина\nВолодимирович\nЛітвінов\nсуддя господарського суду одеської області\nОдеська область\nГосподарський місцевий суд\nЛітвінов Сергій Володимирович\nЛітвінов Сергій Володимирович\nСергій Володимирович Літвінов\nСергій Літвінов\nЛітвінов Сергій Володимирович\nСергій\n2015","general":{"inn":"","inn_hidden":true,"last_name":"Літвінов","post":{"post_unclear":false,"office":"Господарський місцевий суд","post":"суддя господарського суду одеської області","region":"Одеська область"},"name":"Сергій","full_name":"Літвінов Сергій Володимирович","family_raw":"","addresses":[{"place_district":"","place_city_hidden":true,"place_city":"","place_city_type_hidden":false,"place_district_hidden":false,"place_city_type":"","place_address_hidden":true,"place_address":"","place_hidden":true,"place":""}],"family":[{"inn_hidden":true,"inn":"","name_hidden":true,"family_name":"Літвінов В. С","relations":"Дитина","name_unclear":false},{"inn":"","relations":"Дитина","relations_other":"","inn_hidden":false,"family_name":"Літвінов І. С","name_unclear":false}],"full_name_suggest":{"output":"Літвінов Сергій Володимирович","input":["Літвінов Сергій Володимирович","Сергій Володимирович Літвінов","Сергій Літвінов"]},"patronymic":"Володимирович"},"source":"VULYK","intro":{"declaration_year":"2015"}}