{"income":{"5":{"value":"63327","value_unclear":false,"comment_hidden":false,"family_comment":"","family":"165648","comment":""},"6":{"family_comment":"","value":"62632","family":"165648","comment":"","value_hidden":false},"7":{"family_comment":"","value":"","source_name":"","family":"","comment":""},"8":{"family_comment":"","value":"","family":"","comment":""},"9":{"family_comment":"","value":"695","comment_hidden":false,"family":"","comment":""},"10":{"family_comment":"","value":"","family":"","comment":""},"11":{"family_comment":"","value":"","family":"","comment":""},"12":{"family_comment":"","value":"","family":"","comment":""},"13":{"family_comment":"","value":"","family":"","comment":""},"14":{"family_comment":"","value":"","family":"","comment":""},"15":{"family_comment":"","value":"","family":"","comment":"","family_comment_hidden":false},"16":{"family_comment":"","value":"","family":"","comment":""},"17":{"family_comment":"","value":"","family":"","comment":""},"18":{"family_comment":"","value":"","family":"","comment":"","value_hidden":false},"19":{"family_comment":"","value":"","family":"","comment":""},"20":{"family_comment":"","value":"","family":"","comment":"","family_comment_unclear":false}},"vehicle":{"35":[{"brand_info":"1598 куб. см.","sum_rent_comment":"","brand":"Mazda 3","sum_comment":"","year":"2008","sum":"","sum_rent":""}],"40":[{"brand_info":"1685 куб. см.","sum_rent_comment":"","brand":"Kia Sportage","sum_comment":"","year":"2011","brand_info_hidden":false,"sum":"","sum_rent":""},{"brand_info":"1490 куб. см.","sum_rent_comment":"","brand":"Daewoo Lanos","sum_comment":"","year":"2008","sum":"","sum_rent":""}]},"id":"vulyk_78_43","banks":{"45":[{"sum_foreign_comment":"","sum_units":"UAH","sum_comment":"","sum_hidden":false,"sum_foreign_units":"UAH","sum":"4232","sum_foreign":""}],"46":[{"sum_foreign_comment":"","sum_units":"UAH","sum_comment":"","sum_foreign_units":"UAH","sum_comment_hidden":false,"sum":"4232","sum_foreign":""}]},"declaration":{"additional_info_text":"","notfull_lostpages":"","date":"2015-03-31T00:00:00","notfull":"","additional_info":"","url":"http://static.declarations.com.ua/declarations/chosen_ones/judges_batch/2110_hladun_khrystyna_anatoliivna.pdf"},"liabilities":{"54":{"sum_foreign_comment":"","sum_foreign_hidden":false,"sum_comment":"","sum_comment_unclear":false,"sum_hidden":false,"sum_comment_hidden":false,"sum":"","sum_foreign":""},"55":{"sum_foreign_comment":"","sum":"","sum_comment":"","sum_foreign":""},"56":{"sum_foreign_comment":"","sum":"","sum_comment":"","sum_foreign":""},"57":{"sum_foreign_comment":"","sum":"","sum_comment":"","sum_foreign":""},"58":{"sum_foreign_comment":"","sum":"","sum_comment":"","sum_unclear":false,"sum_foreign":""},"59":{"sum_foreign_comment":"","sum":"","sum_comment":"","sum_foreign":""},"60":{"sum_foreign_comment":"","sum":"","sum_comment":"","sum_comment_unclear":false,"sum_comment_hidden":false,"sum_foreign":""},"61":{"sum_foreign_comment":"","sum":"","sum_comment":"","sum_foreign":""},"62":{"sum_foreign_comment":"","sum":"","sum_hidden":false,"sum_comment":"","sum_foreign":""},"63":{"sum_foreign_comment":"","sum_foreign_hidden":false,"sum_comment":"","sum":"","sum_unclear":false,"sum_foreign":""},"64":{"sum_foreign_comment":"","sum_foreign_hidden":false,"sum_comment":"","sum_hidden":false,"sum":"","sum_foreign":""}},"ft_src":"суддя печерського районного суду міста києва\nм. Київ\nЗагальний місцевий суд\nХристина\nВолошин В. Ю\nПодружжя\nВолошина В. В\nДитина\nАнатоліївна\nГладун Христина Анатоліївна\nХристина Анатоліївна Гладун\nХристина Гладун\nГладун Христина Анатоліївна\nГладун\nГладун Христина Анатоліївна\nКиєв\nм. Київ\n1598 куб. см.\n2008\nMazda 3\n1685 куб. см.\n2011\nKia Sportage\n1490 куб. см.\n2008\nDaewoo Lanos\n46.3\n17.25\n72.9\n4232\n4232\n2014\n1598 куб. см.\n2008\nMazda 3\n1685 куб. см.\n2011\nKia Sportage\n1490 куб. см.\n2008\nDaewoo Lanos\n2014\nПодружжя\nВолошин В. Ю\nДитина\nВолошина В. В\nГладун Христина Анатоліївна\nХристина Анатоліївна Гладун\nХристина Гладун\nГладун Христина Анатоліївна\nГладун Христина Анатоліївна\nХристина\nАнатоліївна\nЗагальний місцевий суд\nсуддя печерського районного суду міста києва\nм. Київ\nГладун\nм. Київ\nКиєв\n62632\n165648\n63327\n165648\n695\n46.3\n17.25\n72.9\n4232\n4232\n165648\n62632\n695\n165648\n63327\nПодружжя\nВолошин В. Ю\nДитина\nВолошина В. В\nАнатоліївна\nГладун\nХристина\nГладун Христина Анатоліївна\nХристина Анатоліївна Гладун\nХристина Гладун\nГладун Христина Анатоліївна\nм. Київ\nКиєв\nм. Київ\nсуддя печерського районного суду міста києва\nЗагальний місцевий суд\nГладун Христина Анатоліївна\nMazda 3\n1598 куб. см.\n2008\nKia Sportage\n1685 куб. см.\n2011\nDaewoo Lanos\n1490 куб. см.\n2008\n695\n63327\n165648\n165648\n62632\n46.3\n17.25\n72.9\n4232\n4232\n2014","general":{"inn":"","name":"Христина","family":[{"inn":"","relations":"Подружжя","relations_other":"","inn_hidden":true,"family_name":"Волошин В. Ю","name_hidden":false,"name_unclear":false},{"inn":"","relations":"Дитина","relations_other":"","inn_hidden":true,"family_name":"Волошина В. В","name_hidden":true,"name_unclear":false}],"patronymic":"Анатоліївна","inn_hidden":true,"family_raw":"","last_name":"Гладун","post":{"post_unclear":false,"post":"суддя печерського районного суду міста києва","post_hidden":false,"region":"м. Київ","region_hidden":false,"office":"Загальний місцевий суд","office_hidden":false},"last_name_unclear":false,"full_name":"Гладун Христина Анатоліївна","addresses":[{"place_district":"","place_city_hidden":false,"place_city":"Києв","place_city_type_hidden":false,"place_district_hidden":false,"place_city_type":"Місто","place_address_hidden":true,"place_address":"","place_hidden":false,"place":"м. Київ"}],"full_name_suggest":{"output":"Гладун Христина Анатоліївна","input":["Гладун Христина Анатоліївна","Христина Анатоліївна Гладун","Христина Гладун"]},"name_unclear":false},"source":"VULYK","estate":{"25":[{"space_hidden":false,"costs":"","costs_comment":"","address_hidden":false,"region_hidden":true,"space_comment":"","space":"72.9","address":"","region":"","address_unclear":false,"costs_rent_comment":"","space_units":"м²","costs_rent":""}],"31":[{"address_hidden":false,"region_hidden":true,"space_comment":"","space":"46.3","address":"","region":"","costs_property":"","costs_rent_comment":"","address_unclear":false,"space_units":"м²","costs_property_comment":"","costs_rent":""},{"costs_rent":"","region":"","costs_property":"","costs_rent_comment":"","space_comment":"","costs_property_comment":"","space_units":"м²","space":"17.25","address":""}]},"intro":{"declaration_year":"2014"}}