{"income":{"5":{"value":"233016","family_comment":"","value_unclear":false,"comment_hidden":false,"family_hidden":false,"value_hidden":false,"family_unclear":false,"family":"41048","comment":""},"6":{"value":"233016","family_comment":"","value_unclear":false,"family_hidden":false,"family_unclear":false,"comment_unclear":false,"comment":"","family":"41048"},"7":{"source_name_unclear":false,"value":"","value_hidden":false,"family_comment":"","source_name":"","family":"","comment":"","source_name_hidden":false},"8":{"value":"","family_hidden":false,"value_hidden":false,"family_comment":"","family":"","comment":""},"9":{"value":"","family_comment":"","value_unclear":false,"family_hidden":false,"value_hidden":false,"family_unclear":false,"family":"","comment":""},"10":{"family_comment":"","value":"","family":"","comment":""},"11":{"family_comment":"","value":"","family":"","comment":""},"12":{"family_comment":"","value":"","family":"","comment":""},"13":{"family_comment":"","value":"","family":"","comment":""},"14":{"family_comment":"","value":"","family":"","comment":""},"15":{"family_comment":"","value":"","family":"","comment":""},"16":{"value":"","family_comment":"","value_unclear":false,"family_unclear":false,"family":"","comment":""},"17":{"family_comment":"","value":"","family":"","comment":""},"18":{"family_comment":"","value":"","family":"","comment":""},"19":{"family_comment":"","value":"","comment_unclear":false,"family":"","comment":""},"20":{"value":"","family_comment":"","value_unclear":false,"comment_hidden":false,"family_hidden":false,"family":"","value_hidden":false,"family_unclear":false,"comment_unclear":false,"comment":"","family_comment_unclear":false}},"vehicle":{"40":[{"brand_info":"1300 куб. см.","sum_rent_comment":"","brand":"Toyota Yaris","sum_comment":"","brand_unclear":false,"year":"2006","brand_info_unclear":false,"year_unclear":false,"sum":"","sum_rent":""}]},"id":"vulyk_63_38","declaration":{"additional_info_text":"","notfull_lostpages":"","date":"2015-03-24T00:00:00","notfull":"","additional_info":"","url":"http://static.declarations.com.ua/declarations/chosen_ones/mega_batch/perederko_dmytro_petrovych.pdf"},"liabilities":{"54":{"sum_foreign_comment":"","sum":"","sum_comment":"","sum_unclear":false,"sum_foreign":""},"55":{"sum_foreign_comment":"","sum":"","sum_comment":"","sum_foreign":""},"56":{"sum_foreign_comment":"","sum":"","sum_comment":"","sum_unclear":false,"sum_foreign":""},"57":{"sum_foreign_comment":"","sum":"","sum_comment":"","sum_comment_hidden":false,"sum_unclear":false,"sum_foreign":""},"58":{"sum_foreign_comment":"","sum_comment_hidden":false,"sum":"","sum_comment":"","sum_foreign":""},"59":{"sum_foreign_comment":"","sum":"","sum_comment":"","sum_foreign":""},"60":{"sum_foreign_comment":"","sum":"","sum_comment":"","sum_comment_unclear":false,"sum_foreign":""},"61":{"sum_foreign_comment":"","sum":"","sum_comment":"","sum_unclear":false,"sum_foreign":""},"62":{"sum_foreign_comment":"","sum":"","sum_comment":"","sum_unclear":false,"sum_foreign":""},"63":{"sum_foreign_comment":"","sum":"","sum_comment":"","sum_hidden":false,"sum_comment_hidden":false,"sum_unclear":false,"sum_foreign":""},"64":{"sum_foreign_comment":"","sum_comment_hidden":false,"sum":"","sum_comment":"","sum_foreign":""}},"ft_src":"суддя малиновського районного суду міста одеси\nОдеська область\nЗагальний місцевий суд\nДмитро\nКоваль Т. М\nПодружжя\nПередерко І. Д\nДитина\nПетрович\nПередерко\nПередерко Дмитро Петрович\nПередерко Дмитро Петрович\nДмитро Петрович Передерко\nДмитро Передерко\nПередерко Дмитро Петрович\n233016\n41048\n233016\n41048\n2006\n1300 куб. см.\nToyota Yaris\n1300 куб. см.\nToyota Yaris\n2006\n2014\n41048\n233016\n41048\n233016\n1300 куб. см.\n2006\nToyota Yaris\n233016\n41048\n233016\n41048\nПетрович\nПередерко Дмитро Петрович\nДмитро Петрович Передерко\nДмитро Передерко\nПередерко Дмитро Петрович\nДмитро\nПодружжя\nКоваль Т. М\nДитина\nПередерко І. Д\nПередерко Дмитро Петрович\nЗагальний місцевий суд\nОдеська область\nсуддя малиновського районного суду міста одеси\nПередерко\n2014\nПодружжя\nКоваль Т. М\nДитина\nПередерко І. Д\nПетрович\nПередерко\nПередерко Дмитро Петрович\nДмитро Петрович Передерко\nДмитро Передерко\nПередерко Дмитро Петрович\nДмитро\nОдеська область\nсуддя малиновського районного суду міста одеси\nЗагальний місцевий суд\nПередерко Дмитро Петрович\n2014","general":{"name_hidden":false,"name":"Дмитро","patronymic_unclear":false,"last_name_hidden":false,"inn":"","family":[{"inn":"","inn_hidden":true,"relations_unclear":false,"relations_hidden":false,"relations_other":"","relations":"Подружжя","name_hidden":false,"inn_unclear":false,"family_name":"Коваль Т. М","name_unclear":false},{"inn":"","relations":"Дитина","relations_unclear":false,"family_name":"Передерко І. Д","inn_hidden":false,"relations_other":"","name_hidden":false,"inn_unclear":false,"name_unclear":false}],"patronymic":"Петрович","inn_hidden":true,"family_raw":"","inn_unclear":false,"post":{"post_unclear":false,"region_unclear":false,"region":"Одеська область","office_hidden":false,"region_hidden":false,"post":"суддя малиновського районного суду міста одеси","office_unclear":false,"office":"Загальний місцевий суд"},"last_name_unclear":false,"full_name":"Передерко Дмитро Петрович","addresses":[{"place_city_type_unclear":false,"place_address":"","place_district_hidden":true,"place_city_type":"","place_address_hidden":true,"place_address_unclear":false,"place_city_type_hidden":true,"place":"","place_district":"","place_unclear":false,"place_city":"","place_city_unclear":false,"place_hidden":true,"place_city_hidden":true,"place_district_unclear":false}],"last_name":"Передерко","full_name_suggest":{"output":"Передерко Дмитро Петрович","input":["Передерко Дмитро Петрович","Дмитро Петрович Передерко","Дмитро Передерко"]},"name_unclear":false},"source":"VULYK","intro":{"declaration_year":"2014","isnotdeclaration":"","declaration_year_unclear":false}}