{"income":{"5":{"value":"333756","family_comment":"","value_unclear":false,"family_hidden":false,"value_hidden":false,"family_unclear":false,"family":"57560","comment":""},"6":{"value":"276456","family_comment":"","value_unclear":false,"family_hidden":false,"value_hidden":false,"family_unclear":false,"family":"33800","comment":""},"7":{"value":"","family_hidden":false,"value_hidden":false,"family_comment":"","source_name":"","family":"","comment":"","source_name_hidden":false},"8":{"value":"","family_hidden":false,"value_hidden":false,"family_comment":"","family":"","comment":""},"9":{"value":"3840","value_unclear":false,"family_hidden":false,"family_comment":"","family":"","comment":""},"10":{"family_comment":"","value":"12617","value_unclear":false,"family":"1150","comment":""},"11":{"family_comment":"","value":"","family":"","comment":""},"12":{"family_comment":"","value":"","family":"","comment":""},"13":{"family_comment":"","value":"","family":"","comment":""},"14":{"family_comment":"","value":"","family":"","comment":""},"15":{"family_comment":"","value":"","family":"","comment":""},"16":{"family_comment":"","value":"","family":"","comment":""},"17":{"family_comment":"","value":"","family":"","comment":""},"18":{"family_comment":"","value":"","family":"","comment":""},"19":{"family_comment":"","value":"","value_unclear":false,"family":"","comment":""},"20":{"value":"53460","value_unclear":false,"family_comment":"","family_comment_unclear":false,"comment_unclear":false,"comment":"","family":"23760"}},"vehicle":{"40":[{"brand_info":"1.6 л","sum_rent_comment":"","brand":"Volkswagen","sum_comment":"","brand_unclear":false,"year":"1986","brand_info_unclear":false,"sum":"","sum_rent":""}]},"id":"vulyk_49_180","banks":{"45":[{"sum_foreign_comment":"","sum_units":"USD","sum_units_hidden":false,"sum_comment":"","sum_comment_unclear":false,"sum_hidden":false,"sum_foreign_units":"UAH","sum_comment_hidden":true,"sum_unclear":false,"sum":"10587","sum_foreign":""},{"sum_foreign_comment":"","sum_units":"","sum_comment":"","sum_foreign_units":"","sum_comment_hidden":false,"sum_unclear":false,"sum":"","sum_foreign":""},{"sum_foreign_comment":"","sum_units":"","sum_comment":"","sum_foreign_units":"","sum":"","sum_unclear":false,"sum_foreign":""}],"46":[{"sum_foreign_comment":"","sum_units":"UAH","sum_comment":"","sum_hidden":false,"sum_foreign_units":"UAH","sum_comment_hidden":false,"sum_unclear":false,"sum":"","sum_foreign":""}],"47":[{"sum_foreign_comment":"","sum_units":"UAH","sum_comment":"","sum_foreign_units":"UAH","sum_comment_hidden":false,"sum":"","sum_foreign":""}],"48":[{"sum_foreign_comment":"","sum_foreign_hidden":false,"sum_comment":"","sum_foreign_units":"UAH","sum_units":"UAH","sum":"","sum_foreign":""}],"49":[{"sum_foreign_comment":"","sum_units":"UAH","sum_comment":"","sum_foreign_units":"UAH","sum":"","sum_foreign":""}],"50":[{"sum_foreign_comment":"","sum_units":"UAH","sum_comment":"","sum_foreign_units":"UAH","sum":"","sum_foreign":""}],"51":[{"sum_foreign_comment":"","sum_units":"UAH","sum_comment":"","sum_hidden":false,"sum_foreign_units":"UAH","sum_comment_hidden":true,"sum_unclear":false,"sum":"60056","sum_foreign":""},{"sum_foreign_comment":"","sum_units":"","sum_comment":"","sum_foreign_units":"","sum_foreign_units_unclear":false,"sum":"","sum_foreign":""},{"sum_foreign_comment":"","sum_units":"","sum_comment":"","sum_foreign_units":"","sum":"","sum_foreign":""}],"52":[{"sum_foreign_comment":"","sum_units":"UAH","sum_comment":"","sum_foreign_units":"UAH","sum_comment_hidden":false,"sum":"","sum_foreign":""}],"53":[{"sum_foreign_comment":"","sum_units":"UAH","sum_comment":"","sum_hidden":false,"sum_foreign_units":"UAH","sum_comment_hidden":false,"sum":"","sum_foreign":""}]},"declaration":{"additional_info_text":"","notfull_lostpages":"","date":"2014-03-27T00:00:00","notfull":"","additional_info":"","url":"http://static.declarations.com.ua/declarations/sudy/apeliatsiini_sudy_oblastei__m.kyieva/zhytomyrska/troyanovska_g_s_.pdf"},"liabilities":{"54":{"sum_foreign_comment":"","sum_foreign_hidden":false,"sum_comment":"","sum_hidden":false,"sum_comment_hidden":false,"sum_unclear":false,"sum":"","sum_foreign":""},"55":{"sum_foreign_comment":"","sum":"","sum_comment":"","sum_foreign":""},"56":{"sum_foreign_comment":"","sum":"","sum_comment":"","sum_unclear":false,"sum_foreign":""},"57":{"sum_foreign_comment":"","sum":"","sum_comment":"","sum_comment_unclear":false,"sum_hidden":false,"sum_comment_hidden":false,"sum_unclear":false,"sum_foreign":""},"58":{"sum_foreign_comment":"","sum":"","sum_comment":"","sum_hidden":false,"sum_comment_hidden":false,"sum_unclear":false,"sum_foreign":""},"59":{"sum_foreign_comment":"","sum":"","sum_comment":"","sum_foreign":""},"60":{"sum_foreign_comment":"","sum":"","sum_comment":"","sum_hidden":false,"sum_comment_hidden":false,"sum_unclear":false,"sum_foreign":""},"61":{"sum_foreign_comment":"","sum":"","sum_comment":"","sum_foreign":""},"62":{"sum_foreign_comment":"","sum":"3480","sum_comment":"","sum_foreign":""},"63":{"sum_foreign_comment":"","sum_comment_hidden":false,"sum":"","sum_comment":"","sum_foreign":""},"64":{"sum_foreign_comment":"","sum":"","sum_comment":"","sum_comment_hidden":false,"sum_unclear":false,"sum_foreign":""}},"ft_src":"3480\nсуддя апеляційного суду житомирської області\nЖитомирська область\nЗагальний апеляційний суд\nГалина\nТрояновський В. І\nПодружжя\nСергіївна\nТрояновська\nТрояновська Галина Сергіївна\nТрояновська Галина Сергіївна\nГалина Сергіївна Трояновська\nГалина Трояновська\nТрояновська Галина Сергіївна\n1986\nVolkswagen\n1.6 л\n60056\n10587\n2013\n1.6 л\n1986\nVolkswagen\n10587\n60056\n.25\nЖитомирська обл., Любарський р-н,Ст. Любар\nЖитомирська область\n.45\nЖитомирська область\nЖитомирська обл., Любарський р-н,Ст. Любор\n100\nЖитомирська область\n2025\nЖитомирська область\nм. Житомир\n20\nЖитомирська обл., Любарський р-н,Ст. Любар\nЖитомирська область\nТрояновська\nТрояновська Галина Сергіївна\nГалина Сергіївна Трояновська\nГалина Трояновська\nТрояновська Галина Сергіївна\nГалина\nПодружжя\nТрояновський В. І\nТрояновська Галина Сергіївна\nЗагальний апеляційний суд\nЖитомирська область\nсуддя апеляційного суду житомирської області\nСергіївна\n3480\n33800\n276456\n53460\n23760\n57560\n333756\n12617\n1150\n3840\n2013\n3480\n20\nЖитомирська область\nЖитомирська обл., Любарський р-н,Ст. Любар\nЖитомирська область\nЖитомирська обл., Любарський р-н,Ст. Любар\n.25\n100\nЖитомирська область\n.45\nЖитомирська область\nЖитомирська обл., Любарський р-н,Ст. Любор\nм. Житомир\n2025\nЖитомирська область\nТрояновський В. І\nПодружжя\nСергіївна\nТрояновська\nТрояновська Галина Сергіївна\nГалина Сергіївна Трояновська\nГалина Трояновська\nТрояновська Галина Сергіївна\nГалина\nЖитомирська область\nЗагальний апеляційний суд\nсуддя апеляційного суду житомирської області\nТрояновська Галина Сергіївна\n33800\n276456\n1150\n12617\n57560\n333756\n3840\n23760\n53460\n1986\n1.6 л\nVolkswagen\n1150\n12617\n53460\n23760\n333756\n57560\n3840\n276456\n33800\nЖитомирська область\n100\nЖитомирська область\nЖитомирська обл., Любарський р-н,Ст. Любар\n.25\nЖитомирська обл., Любарський р-н,Ст. Любар\nЖитомирська область\n20\n2025\nм. Житомир\nЖитомирська область\nЖитомирська обл., Любарський р-н,Ст. Любор\nЖитомирська область\n.45\n10587\n60056\n2013","general":{"name_hidden":false,"name":"Галина","patronymic_unclear":false,"last_name_hidden":false,"inn":"","family":[{"inn":"","inn_hidden":false,"relations_hidden":false,"family_name":"Трояновський В. І","relations_other":"","relations":"Подружжя","name_hidden":false,"name_unclear":false}],"patronymic":"Сергіївна","inn_hidden":false,"family_raw":"","inn_unclear":false,"post":{"post_unclear":false,"region_unclear":false,"post":"суддя апеляційного суду житомирської області","candidate":"","office_hidden":false,"region":"Житомирська область","post_hidden":false,"office":"Загальний апеляційний суд","office_unclear":false,"region_hidden":false},"last_name_unclear":false,"full_name":"Трояновська Галина Сергіївна","last_name":"Трояновська","patronymic_hidden":false,"full_name_suggest":{"output":"Трояновська Галина Сергіївна","input":["Трояновська Галина Сергіївна","Галина Сергіївна Трояновська","Галина Трояновська"]},"name_unclear":false},"source":"VULYK","estate":{"23":[{"space_unclear":false,"costs":"","costs_comment":"","costs_hidden":false,"address_hidden":true,"region_hidden":false,"space_comment":"","space":".25","address":"Житомирська обл., Любарський р-н,Ст. Любар","region":"Житомирська область","address_unclear":false,"space_units_unclear":false,"costs_rent_hidden":false,"space_comment_hidden":false,"space_units":"га","space_units_hidden":false,"costs_rent":"","costs_rent_comment":""},{"space_unclear":false,"costs":"","costs_comment":"","address_hidden":false,"region_hidden":false,"space_comment":"","space":"","address":"","region":"","address_unclear":false,"costs_rent_comment":"","space_comment_hidden":false,"costs_rent_comment_hidden":false,"space_units":"","costs_comment_hidden":false,"costs_rent":""},{"costs_rent":"","region":"","costs":"","costs_rent_comment":"","costs_comment":"","region_hidden":false,"space_comment":"","space_units":"","space":"","address":""},{"costs_rent":"","region":"","costs":"","costs_rent_comment":"","costs_comment":"","region_hidden":false,"space_comment":"","space_units":"","space":"","address":""},{"costs_rent":"","costs":"","costs_rent_comment":"","costs_comment":"","space_comment":"","space_units":"","space":"","address":""}],"25":[{"region_unclear":false,"space_unclear":false,"costs":"","costs_comment":"","costs_hidden":false,"address_hidden":false,"region_hidden":false,"space_comment":"","space_hidden":false,"space":"","address":"м. Житомир","region":"Житомирська область","address_unclear":false,"costs_rent_comment":"","costs_rent_hidden":false,"space_comment_unclear":false,"space_comment_hidden":false,"space_units":"м²","costs_rent":"2025"}],"29":[{"region_unclear":false,"space_unclear":false,"costs_property_comment":"","address_hidden":true,"region_hidden":false,"space_comment":"","space":".45","address":"Житомирська обл., Любарський р-н,Ст. Любор","region":"Житомирська область","costs_property":"","costs_rent_comment":"","space_comment_unclear":false,"space_comment_hidden":false,"space_units":"га","space_units_unclear":false,"costs_rent":""}],"30":[{"region_unclear":false,"costs_property_comment":"","costs_property_hidden":false,"address_hidden":true,"region_hidden":false,"space_comment":"","space":"100","address":"","region":"Житомирська область","costs_property":"","costs_rent_comment":"","costs_rent_hidden":false,"space_comment_hidden":false,"space_units":"м²","space_units_unclear":false,"costs_rent":""}],"33":[{"space_unclear":false,"address_hidden":true,"region_hidden":false,"space_comment":"","space":"20","address":"Житомирська обл., Любарський р-н,Ст. Любар","region":"Житомирська область","costs_property":"","costs_rent_comment":"","space_comment_hidden":false,"space_units":"м²","costs_property_comment":"","costs_rent":""}]},"intro":{"declaration_year":"2013","isnotdeclaration":""}}