{"income":{"5":{"value":"194295.85","family_comment":"","value_unclear":false,"family_hidden":false,"value_hidden":false,"family_unclear":false,"comment_unclear":false,"comment":"","family":""},"6":{"value":"181678.85","family_unclear":false,"family_hidden":false,"family_comment":"","family":"","comment":""},"7":{"value":"","family_hidden":false,"value_hidden":false,"family_comment":"","source_name":"","family":"","comment":""},"8":{"family_comment":"","value":"","family":"","comment":""},"9":{"family_comment":"","value":"","value_unclear":false,"family":"","comment":""},"10":{"family_comment":"","family_unclear":false,"value":"12617","family":"","comment":""},"11":{"family_comment":"","value":"","family":"","comment":""},"12":{"family_comment":"","value":"","family":"","comment":""},"13":{"family_comment":"","value":"","family":"","comment":""},"14":{"family_comment":"","value":"","family":"","comment":""},"15":{"family_comment":"","value":"","family":"","comment":""},"16":{"family_comment":"","value":"","family":"","comment":""},"17":{"family_comment":"","value":"","family":"","comment":""},"18":{"family_comment":"","value":"","family":"","comment":""},"19":{"family_comment":"","value":"","family":"","comment":""},"20":{"value":"","value_unclear":false,"family_comment":"","comment_unclear":false,"comment":"","family":""}},"vehicle":{"40":[{"brand_info":"2500 куб. см.","sum":"","brand":"Ford Kuga","sum_comment":"","brand_unclear":false,"year":"2011","brand_info_hidden":false,"brand_info_unclear":false,"sum_rent_comment":"","sum_rent":""}]},"id":"vulyk_71_77","declaration":{"additional_info_text":"","notfull_lostpages":"","date":"2014-03-21T00:00:00","notfull":"","additional_info":"","url":"http://static.declarations.com.ua/declarations/chosen_ones/judges_batch/558_topchii_tetiana_v’yacheslavivna.pdf"},"liabilities":{"54":{"sum_foreign_comment":"","sum":"","sum_comment":"","sum_comment_unclear":false,"sum_comment_hidden":false,"sum_unclear":false,"sum_foreign":""},"55":{"sum_foreign_comment":"","sum":"","sum_comment":"","sum_foreign":""},"56":{"sum_foreign_comment":"","sum":"2484","sum_comment":"","sum_comment_unclear":false,"sum_unclear":false,"sum_foreign":""},"57":{"sum_foreign_comment":"","sum":"","sum_comment":"","sum_comment_hidden":false,"sum_unclear":false,"sum_foreign":""},"58":{"sum_foreign_comment":"","sum":"","sum_comment":"","sum_comment_hidden":false,"sum_unclear":false,"sum_foreign":""},"59":{"sum_foreign_comment":"","sum_comment_hidden":false,"sum":"","sum_comment":"","sum_foreign":""},"60":{"sum_foreign_comment":"","sum_comment_hidden":false,"sum":"","sum_comment":"","sum_foreign":""},"61":{"sum_foreign_comment":"","sum":"","sum_comment":"","sum_foreign":""},"62":{"sum_foreign_comment":"","sum":"2105","sum_comment":"","sum_foreign":""},"63":{"sum_foreign_comment":"","sum":"","sum_comment":"","sum_unclear":false,"sum_foreign":""},"64":{"sum_foreign_comment":"","sum":"","sum_comment":"","sum_unclear":false,"sum_foreign":""}},"ft_src":"2105\n2484\nсуддя апеляційного суду донецької області\nДонецька область\nЗагальний апеляційний суд\nТетяна\nТопчій О. О\nПодружжя\nТопчій А. О\nДитина\nВ'ячеславівна\nТопчій Тетяна В'ячеславівна\nТетяна В'ячеславівна Топчій\nТетяна Топчій\nТопчій Тетяна В'ячеславівна\nТопчій Тетяна В'ячеславівна\nТопчій\n2500 куб. см.\nFord Kuga\n2011\n44.2\n16\n70\n2013\n181678.85\n12617\n194295.85\n2500 куб. см.\n2011\nFord Kuga\n16\n44.2\n70\nПодружжя\nТопчій О. О\nДитина\nТопчій А. О\nТопчій Тетяна В'ячеславівна\nТетяна В'ячеславівна Топчій\nТетяна Топчій\nТопчій Тетяна В'ячеславівна\nТопчій Тетяна В'ячеславівна\nТетяна\nВ'ячеславівна\nЗагальний апеляційний суд\nДонецька область\nсуддя апеляційного суду донецької області\nТопчій\n2484\n2105\n181678.85\n194295.85\n12617\n2013\n2484\n2105\nТопчій О. О\nПодружжя\nТопчій А. О\nДитина\nВ'ячеславівна\nТопчій\nТетяна\nТопчій Тетяна В'ячеславівна\nТетяна В'ячеславівна Топчій\nТетяна Топчій\nТопчій Тетяна В'ячеславівна\nДонецька область\nЗагальний апеляційний суд\nсуддя апеляційного суду донецької області\nТопчій Тетяна В'ячеславівна\nFord Kuga\n2500 куб. см.\n2011\n12617\n194295.85\n181678.85\n44.2\n70\n16\n2013","general":{"inn":"","name":"Тетяна","family":[{"inn":"","inn_hidden":true,"relations_hidden":false,"family_name":"Топчій О. О","relations_other":"","relations":"Подружжя","name_hidden":true,"name_unclear":false},{"inn":"","inn_hidden":false,"relations_hidden":false,"family_name":"Топчій А. О","relations_other":"","relations":"Дитина","name_hidden":false,"name_unclear":false}],"patronymic":"В'ячеславівна","inn_hidden":true,"family_raw":"","inn_unclear":false,"post":{"post_unclear":false,"region_unclear":false,"post":"суддя апеляційного суду донецької області","office":"Загальний апеляційний суд","region":"Донецька область","post_hidden":false,"office_unclear":false},"full_name_suggest":{"output":"Топчій Тетяна В'ячеславівна","input":["Топчій Тетяна В'ячеславівна","Тетяна В'ячеславівна Топчій","Тетяна Топчій"]},"full_name":"Топчій Тетяна В'ячеславівна","addresses":[{"place_district":"","place_unclear":false,"place_city":"","place_city_type_hidden":false,"place_district_hidden":false,"place_city_type":"","place_city_hidden":true,"place_address_hidden":true,"place_address":"","place_hidden":true,"place":""}],"last_name":"Топчій","patronymic_hidden":false,"last_name_unclear":false,"name_unclear":false},"source":"VULYK","estate":{"25":[{"region_unclear":false,"space_unclear":false,"costs":"","costs_rent_unclear":false,"costs_comment":"","costs_hidden":false,"address_hidden":true,"region_hidden":true,"space_comment":"","space_hidden":false,"space":"70","address":"","costs_unclear":false,"region":"","address_unclear":false,"costs_rent_comment":"","costs_rent_hidden":false,"space_comment_unclear":false,"space_units":"м²","costs_rent":""}],"27":[{"space_unclear":false,"costs":"","costs_comment":"","costs_hidden":false,"address_hidden":true,"region_hidden":true,"space_comment":"","space":"16","address":"","region":"","costs_rent_comment":"","costs_comment_hidden":false,"space_units":"м²","costs_rent":""}],"31":[{"space_hidden":false,"costs_property_comment":"","address_hidden":true,"region_hidden":true,"space_comment":"","space":"44.2","address":"","region":"","costs_property":"","costs_rent_comment":"","space_comment_unclear":false,"space_units":"м²","space_units_hidden":false,"costs_rent":""}]},"intro":{"declaration_year":"2013","isnotdeclaration":""}}