{"income":{"5":{"value":"243907","family_comment":"","value_unclear":false,"family_hidden":false,"value_hidden":false,"family_unclear":false,"family":"76940","comment":""},"6":{"value":"228446","value_unclear":false,"value_hidden":false,"family_comment":"","family":"75648","comment":""},"7":{"family_comment":"","value":"","source_name":"","family":"","comment":""},"8":{"family_comment":"","value":"","family":"","comment":""},"9":{"family_comment":"","value":"","family":"1298","comment":""},"10":{"value":"13398","family_comment":"","value_unclear":false,"family_unclear":false,"family":"","comment":""},"11":{"family_comment":"","value":"","family":"","comment":""},"12":{"family_comment":"","value":"","family":"","comment":""},"13":{"family_comment":"","value":"","family":"","comment":""},"14":{"family_comment":"","value":"","value_unclear":false,"family":"","comment":""},"15":{"family_comment":"","value":"","family":"","comment":""},"16":{"family_comment":"","value":"","family":"","comment":""},"17":{"family_comment":"","value":"","family":"","comment":""},"18":{"family_comment":"","value":"","family":"","comment":""},"19":{"family_comment":"","value":"2063","family":"","comment":"","family_comment_unclear":false},"20":{"value":"","value_unclear":false,"family_comment":"","comment_unclear":false,"comment":"","family":""}},"vehicle":{"35":[{"year_hidden":false,"brand_info":"2148 куб. см., 170 к. с., 125 кВт","sum_rent_comment":"право користування","brand_info_unclear":false,"year":"2007","brand_info_hidden":false,"sum_rent_comment_unclear":false,"sum_rent":"","sum":"","brand":"Mercedes-Benz E220","sum_comment":"","sum_comment_unclear":false,"brand_hidden":false,"sum_rent_comment_hidden":false,"sum_comment_hidden":false,"sum_unclear":false}]},"id":"vulyk_60_141","banks":{"45":[{"sum_foreign_comment":"","sum_units":"UAH","sum_comment":"","sum_comment_unclear":false,"sum_foreign_units":"UAH","sum":"","sum_unclear":false,"sum_foreign":""}],"46":[{"sum_foreign_comment":"","sum_units":"UAH","sum_comment":"","sum_foreign_units":"UAH","sum":"","sum_foreign":""}],"47":[{"sum_foreign_comment":"","sum_units":"UAH","sum_comment":"","sum_foreign_units":"UAH","sum":"","sum_foreign":""}],"48":[{"sum_foreign_comment":"","sum_units":"UAH","sum_comment":"","sum_foreign_units":"UAH","sum":"","sum_foreign":""}],"49":[{"sum_foreign_comment":"","sum_units":"UAH","sum_comment":"","sum_foreign_units":"UAH","sum":"","sum_foreign":""}],"50":[{"sum_foreign_comment":"","sum_units":"UAH","sum_comment":"","sum_foreign_units":"UAH","sum":"","sum_foreign":""}],"51":[{"sum_foreign_comment":"","sum_units":"UAH","sum_comment":"","sum_foreign_units":"UAH","sum":"114415","sum_unclear":false,"sum_foreign":""}],"52":[{"sum_foreign_comment":"","sum_units":"UAH","sum_comment":"","sum_foreign_units":"UAH","sum":"","sum_foreign":""}],"53":[{"sum_foreign_comment":"","sum_units":"UAH","sum_comment":"","sum_foreign_units":"UAH","sum":"","sum_foreign":""}]},"declaration":{"additional_info_text":"","notfull_lostpages":"","date":"2015-03-30T00:00:00","notfull":"","additional_info":"","url":"http://static.declarations.com.ua/declarations/chosen_ones/mega_batch/zav_iazun_serhii_mykhailovych.pdf"},"liabilities":{"54":{"sum_foreign_comment":"","sum":"","sum_comment":"","sum_foreign":""},"55":{"sum_foreign_comment":"","sum":"","sum_comment":"","sum_foreign":""},"56":{"sum_foreign_comment":"","sum":"","sum_comment":"","sum_foreign":""},"57":{"sum_foreign_comment":"","sum":"","sum_comment":"","sum_unclear":false,"sum_foreign":""},"58":{"sum_foreign_comment":"","sum":"","sum_comment":"","sum_foreign":""},"59":{"sum_foreign_comment":"","sum":"","sum_comment":"","sum_foreign":""},"60":{"sum_foreign_comment":"","sum":"","sum_comment":"","sum_foreign":""},"61":{"sum_foreign_comment":"","sum":"","sum_comment":"","sum_foreign":""},"62":{"sum_foreign_comment":"","sum":"","sum_comment":"","sum_comment_unclear":false,"sum_unclear":false,"sum_foreign":""},"63":{"sum_foreign_comment":"","sum":"","sum_comment":"","sum_foreign":""},"64":{"sum_foreign_comment":"","sum":"","sum_comment":"","sum_foreign":""}},"ft_src":"суддя апеляційного суду житомирської області\nЖитомирська область\nЗагальний апеляційний суд\nСергій\nПодружжя\nДитина\nМихайлович\nЗав'язун\nЗав'язун Сергій Михайлович\nЗав'язун Сергій Михайлович\nСергій Михайлович Зав'язун\nСергій Зав'язун\nЗав'язун Сергій Михайлович\n2148 куб. см., 170 к. с., 125 кВт\nправо користування\n2007\nMercedes-Benz E220\n114415\n2014\n2148 куб. см., 170 к. с., 125 кВт\nправо користування\nMercedes-Benz E220\n2007\n114415\n2.69\nземельний пай, отриманий у спадщину, але остаточно не оформлений\nРадомишльський р-н, с. Кочерів\nЖитомирська область\nЖитомирська область\nКоростишівський р-н, с. Колодязьки\n.2281\n27.32\nЖитомирська область\nм. Коростишів\n15.96\nм. Коростишів\nЖитомирська область\n13.7\nм. Коростишів\nЖитомирська область\nЗав'язун Сергій Михайлович\nСергій Михайлович Зав'язун\nСергій Зав'язун\nЗав'язун Сергій Михайлович\nЗав'язун Сергій Михайлович\nПодружжя\nДитина\nСергій\nМихайлович\nсуддя апеляційного суду житомирської області\nЖитомирська область\nЗагальний апеляційний суд\nЗав'язун\n228446\n75648\n76940\n243907\n13398\n1298\n2063\n2014\nземельний пай, отриманий у спадщину, але остаточно не оформлений\nРадомишльський р-н, с. Кочерів\n2.69\nЖитомирська область\nЖитомирська область\nКоростишівський р-н, с. Колодязьки\n.2281\nм. Коростишів\nЖитомирська область\n27.32\nЖитомирська область\nм. Коростишів\n15.96\nм. Коростишів\nЖитомирська область\n13.7\nПодружжя\nДитина\nСергій\nМихайлович\nЗав'язун\nЗав'язун Сергій Михайлович\nСергій Михайлович Зав'язун\nСергій Зав'язун\nЗав'язун Сергій Михайлович\nсуддя апеляційного суду житомирської області\nЖитомирська область\nЗагальний апеляційний суд\nЗав'язун Сергій Михайлович\n75648\n228446\n13398\n76940\n243907\n2063\n1298\nправо користування\nMercedes-Benz E220\n2148 куб. см., 170 к. с., 125 кВт\n2007\n2063\n13398\n243907\n76940\n1298\n228446\n75648\nм. Коростишів\nЖитомирська область\n27.32\nм. Коростишів\nЖитомирська область\n15.96\nземельний пай, отриманий у спадщину, але остаточно не оформлений\nРадомишльський р-н, с. Кочерів\nЖитомирська область\n2.69\nм. Коростишів\nЖитомирська область\n13.7\nЖитомирська область\nКоростишівський р-н, с. Колодязьки\n.2281\n114415\n2014","general":{"inn":"","name":"Сергій","family":[{"inn":"","inn_hidden":true,"relations_hidden":false,"family_name":"","relations_other":"","relations":"Подружжя","name_hidden":true,"name_unclear":false},{"inn":"","relations":"Дитина","relations_other":"","inn_hidden":true,"family_name":"","name_hidden":true,"name_unclear":false}],"patronymic":"Михайлович","inn_hidden":true,"family_raw":"","last_name":"Зав'язун","post":{"post_unclear":false,"post_hidden":false,"post":"суддя апеляційного суду житомирської області","region":"Житомирська область","office":"Загальний апеляційний суд"},"last_name_unclear":false,"full_name":"Зав'язун Сергій Михайлович","addresses":[{"place_district":"","place_city_hidden":true,"place_city":"","place_city_type_hidden":false,"place_district_hidden":false,"place_city_type":"","place_address_hidden":true,"place_address":"","place_hidden":true,"place":""}],"full_name_suggest":{"output":"Зав'язун Сергій Михайлович","input":["Зав'язун Сергій Михайлович","Сергій Михайлович Зав'язун","Сергій Зав'язун"]}},"source":"VULYK","estate":{"23":[{"space_unclear":false,"costs":"","costs_comment":"","address_hidden":false,"region_hidden":false,"space_comment":"земельний пай, отриманий у спадщину, але остаточно не оформлений","space_hidden":false,"space":"2.69","address":"Радомишльський р-н, с. Кочерів","region":"Житомирська область","address_unclear":false,"costs_rent_comment":"","space_units":"га","costs_rent":""},{"space_unclear":false,"costs":"","costs_comment":"","address_hidden":false,"space_comment":"","space":"","address":"","region":"","address_unclear":false,"costs_rent_comment":"","space_units":"","costs_rent":""},{"costs_rent":"","space_unclear":false,"region":"","costs":"","costs_rent_comment":"","costs_comment":"","space_comment":"","space_units":"","space":"","address":""},{"costs_rent":"","region":"","costs":"","costs_rent_comment":"","costs_comment":"","space_comment":"","space_units":"","space":"","address":""}],"25":[{"space_unclear":false,"costs":"","costs_comment":"","address_hidden":false,"region_hidden":false,"space_comment":"","space_hidden":false,"space":"13.7","address":"м. Коростишів","region":"Житомирська область","costs_rent_comment":"","space_comment_unclear":false,"space_units":"м²","costs_rent":""}],"29":[{"space_unclear":false,"address_hidden":false,"region_hidden":false,"space_comment":"","space_units_hidden":false,"space_hidden":false,"space":".2281","address":"Коростишівський р-н, с. Колодязьки","region":"Житомирська область","address_unclear":false,"space_units_unclear":false,"space_comment_unclear":false,"costs_property":"","space_units":"га","costs_property_comment":"","costs_rent":"","costs_rent_comment":""}],"31":[{"space_unclear":false,"address_hidden":true,"region_hidden":false,"space_comment":"","space_hidden":false,"space":"27.32","address":"м. Коростишів","region":"Житомирська область","costs_property":"","costs_rent_comment":"","address_unclear":false,"space_units":"м²","costs_property_comment":"","costs_rent":""},{"costs_rent":"","region":"Житомирська область","costs_property":"","costs_rent_comment":"","space_comment":"","costs_property_comment":"","space_units":"м²","space":"15.96","address":"м. Коростишів"}]},"intro":{"declaration_year":"2014","isnotdeclaration":"","declaration_year_unclear":false}}