{"income":{"5":{"family_comment":"","value":"256530","family":"14380","comment":""},"6":{"family_comment":"","value":"243132","family":"","comment":""},"7":{"family_comment":"","value":"","source_name":"","family":"","comment":""},"8":{"family_comment":"","value":"","family":"","comment":""},"9":{"value":"","comment_unclear":false,"family_comment":"","family":"","comment":"","family_comment_unclear":false},"10":{"family_comment":"","value":"13398","family":"","comment":""},"11":{"family_comment":"","value":"","family":"","comment":""},"12":{"family_comment":"","value":"","family":"","comment":""},"13":{"family_comment":"","value":"","family":"","comment":""},"14":{"family_comment":"","value":"","family":"","comment":""},"15":{"family_comment":"","value":"","family":"","comment":""},"16":{"family_comment":"","value":"","family":"","comment":""},"17":{"family_comment":"","value":"","family":"","comment":""},"18":{"family_comment":"","value":"","family":"","comment":""},"19":{"value":"","family_comment":"","value_unclear":false,"family_unclear":false,"family":"","comment":""},"20":{"value":"","family_comment":"","value_unclear":false,"comment_hidden":false,"family_comment_hidden":false,"family_unclear":false,"family_comment_unclear":false,"comment_unclear":false,"comment":"","family":"14380"}},"vehicle":{"35":[{"brand_info":"1395 куб. см., 90 кВт","sum_rent_comment":"","brand":"Volkswagen Golf","sum_comment":"","year":"2013","sum_hidden":false,"brand_info_hidden":false,"brand_info_unclear":false,"year_unclear":false,"sum":"","sum_rent":""}]},"id":"vulyk_106_137","declaration":{"additional_info_text":"","notfull_lostpages":"","date":"2016-03-29T00:00:00","notfull":"","additional_info":"","url":"http://static.declarations.com.ua/declarations/chosen_ones/judges_batch/2276_iasenova_tetiana_ivanivna.pdf"},"liabilities":{"54":{"sum_foreign_comment":"","sum":"","sum_comment":"","sum_comment_unclear":false,"sum_hidden":false,"sum_comment_hidden":false,"sum_foreign":""},"55":{"sum_foreign_comment":"","sum":"","sum_hidden":false,"sum_comment":"","sum_foreign":""},"56":{"sum_foreign_comment":"","sum":"","sum_comment":"","sum_hidden":false,"sum_comment_hidden":false,"sum_unclear":false,"sum_foreign":""},"57":{"sum_foreign_comment":"","sum":"","sum_comment":"","sum_hidden":false,"sum_comment_hidden":false,"sum_foreign":""},"58":{"sum_foreign_comment":"","sum":"","sum_comment":"","sum_hidden":false,"sum_comment_hidden":false,"sum_foreign":""},"59":{"sum_foreign_comment":"","sum":"","sum_comment":"","sum_foreign":""},"60":{"sum_foreign_comment":"","sum":"","sum_comment":"","sum_hidden":false,"sum_comment_hidden":false,"sum_foreign":""},"61":{"sum_foreign_comment":"","sum":"","sum_comment":"","sum_foreign":""},"62":{"sum_foreign_comment":"","sum":"","sum_comment":"","sum_comment_hidden":false,"sum_unclear":false,"sum_foreign":""},"63":{"sum_foreign_comment":"","sum":"","sum_comment":"","sum_foreign":""},"64":{"sum_foreign_comment":"","sum":"","sum_comment":"","sum_foreign":""}},"ft_src":"суддя дніпропетровського апеляційного адміністративного суду\nДніпропетровська область\nАпеляційний адміністративний суд\nТетяна\nЯсенова Л. І\nБатьки\nІванівна\nЯсенова Тетяна Іванівна\nТетяна Іванівна Ясенова\nТетяна Ясенова\nЯсенова Тетяна Іванівна\nЯсенова Тетяна Іванівна\nЯсенова\nVolkswagen Golf\n1395 куб. см., 90 кВт\n2013\n60.2\n62.9\n2015\n243132\n13398\n14380\n256530\n14380\n1395 куб. см., 90 кВт\n2013\nVolkswagen Golf\n60.2\n62.9\nЯсенова Тетяна Іванівна\nТетяна Іванівна Ясенова\nТетяна Ясенова\nЯсенова Тетяна Іванівна\nЯсенова Тетяна Іванівна\nБатьки\nЯсенова Л. І\nТетяна\nЯсенова\nДніпропетровська область\nАпеляційний адміністративний суд\nсуддя дніпропетровського апеляційного адміністративного суду\nІванівна\n243132\n14380\n256530\n14380\n13398\n2015\nЯсенова Л. І\nБатьки\nІванівна\nЯсенова\nТетяна\nЯсенова Тетяна Іванівна\nТетяна Іванівна Ясенова\nТетяна Ясенова\nЯсенова Тетяна Іванівна\nДніпропетровська область\nАпеляційний адміністративний суд\nсуддя дніпропетровського апеляційного адміністративного суду\nЯсенова Тетяна Іванівна\n2013\nVolkswagen Golf\n1395 куб. см., 90 кВт\n13398\n14380\n14380\n256530\n243132\n60.2\n62.9\n2015","general":{"inn":"","name":"Тетяна","inn_unclear":false,"family":[{"inn":"","inn_hidden":true,"relations_unclear":false,"relations_hidden":false,"relations_other":"","relations":"Батьки","name_hidden":true,"family_name":"Ясенова Л. І","name_unclear":false}],"inn_hidden":true,"family_raw":"","last_name":"Ясенова","post":{"region_unclear":false,"region":"Дніпропетровська область","post":"суддя дніпропетровського апеляційного адміністративного суду","office":"Апеляційний адміністративний суд","office_unclear":false,"post_hidden":false},"full_name":"Ясенова Тетяна Іванівна","addresses":[{"place_district":"","place_city_hidden":true,"place_city":"","place_city_type_hidden":true,"place_district_hidden":true,"place_city_type":"","place_address_hidden":true,"place_address":"","place_hidden":true,"place":""}],"patronymic":"Іванівна","full_name_suggest":{"output":"Ясенова Тетяна Іванівна","input":["Ясенова Тетяна Іванівна","Тетяна Іванівна Ясенова","Тетяна Ясенова"]},"name_unclear":false},"source":"VULYK","estate":{"25":[{"costs":"","costs_comment":"","address_hidden":true,"region_hidden":true,"space_comment":"","space":"62.9","address":"","region":"","costs_rent_comment":"","space_comment_unclear":false,"space_units":"м²","costs_rent":""}],"31":[{"space_unclear":false,"address_hidden":true,"region_hidden":true,"space_comment":"","space_hidden":false,"space":"60.2","address":"","region":"","costs_property":"","costs_rent_comment":"","space_comment_unclear":false,"space_units":"м²","costs_property_comment":"","costs_rent":""}]},"intro":{"declaration_year":"2015","isnotdeclaration":""}}