{"income":{"5":{"value":"180937","family_comment":"","value_unclear":false,"family_hidden":false,"value_hidden":false,"family_unclear":false,"family":"","comment":""},"6":{"value":"168757","value_unclear":false,"family_hidden":false,"value_hidden":false,"family_comment":"","comment_unclear":false,"comment":"","family":""},"7":{"value":"","value_hidden":false,"family_comment":"","source_name":"","family":"","comment":"","source_name_hidden":false},"8":{"family_comment":"","value":"","family":"","comment":""},"9":{"family_comment":"","value":"","comment_unclear":false,"family":"","comment":""},"10":{"family_comment":"","value":"12180","value_unclear":false,"family":"","comment":""},"11":{"family_comment":"","value":"","family":"","comment":""},"12":{"family_comment":"","value":"","family":"","comment":""},"13":{"family_comment":"","value":"","family":"","comment":""},"14":{"family_comment":"","value":"","family":"","comment":""},"15":{"family_comment":"","value":"","family":"","comment":""},"16":{"family_comment":"","value":"","family":"","comment":""},"17":{"family_comment":"","value":"","family":"","comment":""},"18":{"family_comment":"","value":"","family":"","comment":""},"19":{"value":"","value_unclear":false,"comment_hidden":false,"family_hidden":false,"value_hidden":false,"family_comment":"","family_comment_hidden":false,"comment":"","family":""},"20":{"value":"","family_comment":"","value_unclear":false,"family_hidden":false,"value_hidden":false,"family_unclear":false,"comment_unclear":false,"comment":"","family":""}},"vehicle":{"35":[{"brand_info":"1198 куб. см.","sum_rent_comment":"","year":"1977","brand_info_hidden":false,"brand_info_unclear":false,"year_unclear":false,"sum_rent":"","sum":"","brand":"","sum_comment":"","brand_unclear":false,"brand_hidden":true}]},"id":"vulyk_65_2","declaration":{"additional_info_text":"","notfull_lostpages":"","date":"2015-03-16T00:00:00","notfull":"","additional_info":"","url":"http://static.declarations.com.ua/declarations/chosen_ones/mega_batch/khemych_oksana_bohdanivna.pdf"},"liabilities":{"54":{"sum_foreign_comment":"","sum":"","sum_comment":"","sum_comment_unclear":false,"sum_hidden":false,"sum_comment_hidden":false,"sum_foreign":""},"55":{"sum_foreign_comment":"","sum":"","sum_comment":"","sum_foreign":""},"56":{"sum_foreign_comment":"","sum":"","sum_comment":"","sum_unclear":false,"sum_foreign":""},"57":{"sum_foreign_comment":"","sum":"","sum_comment":"","sum_comment_unclear":false,"sum_unclear":false,"sum_foreign":""},"58":{"sum_foreign_comment":"","sum":"","sum_comment":"","sum_comment_unclear":false,"sum_unclear":false,"sum_foreign":""},"59":{"sum_foreign_comment":"","sum":"","sum_comment":"","sum_foreign":""},"60":{"sum_foreign_comment":"","sum":"","sum_comment":"","sum_comment_unclear":false,"sum_foreign":""},"61":{"sum_foreign_comment":"","sum":"","sum_comment":"","sum_foreign":""},"62":{"sum_foreign_comment":"","sum":"","sum_comment":"","sum_foreign":""},"63":{"sum_foreign_comment":"","sum":"","sum_comment":"","sum_foreign":""},"64":{"sum_foreign_comment":"","sum":"","sum_comment":"","sum_unclear":false,"sum_foreign":""}},"ft_src":"суддя первомайського міськрайонного суду миколаївської області\nМиколаївська область\nЗагальний місцевий суд\nОксана\nБогданівна\nХемич\nХемич Оксана Богданівна\nХемич Оксана Богданівна\nОксана Богданівна Хемич\nОксана Хемич\nХемич Оксана Богданівна\nПервомайськ\n55200, вул. Дзержинського\nМиколаївська область\n1198 куб. см.\n1977\nДрогобицький р-н, с. Новий Кропивник, вул. О. Довбуша\n2474\nЛьвівська область\nМиколаївська область\nм. Первомайськ, вул. Дзержинського\n36.6\n2014\n168757\n12180\n180937\n1198 куб. см.\n1977\n2474\nЛьвівська область\nДрогобицький р-н, с. Новий Кропивник, вул. О. Довбуша\n36.6\nМиколаївська область\nм. Первомайськ, вул. Дзержинського\n55200, вул. Дзержинського\nМиколаївська область\nПервомайськ\nХемич Оксана Богданівна\nОксана Богданівна Хемич\nОксана Хемич\nХемич Оксана Богданівна\nХемич Оксана Богданівна\nОксана\nХемич\nЗагальний місцевий суд\nМиколаївська область\nсуддя первомайського міськрайонного суду миколаївської області\nБогданівна\n168757\n180937\n12180\n2014\nБогданівна\nХемич\nОксана\nХемич Оксана Богданівна\nОксана Богданівна Хемич\nОксана Хемич\nХемич Оксана Богданівна\n55200, вул. Дзержинського\nПервомайськ\nМиколаївська область\nМиколаївська область\nЗагальний місцевий суд\nсуддя первомайського міськрайонного суду миколаївської області\nХемич Оксана Богданівна\n1977\n1198 куб. см.\n12180\n180937\n168757\n36.6\nМиколаївська область\nм. Первомайськ, вул. Дзержинського\nДрогобицький р-н, с. Новий Кропивник, вул. О. Довбуша\nЛьвівська область\n2474\n2014","general":{"name_hidden":false,"name":"Оксана","last_name_hidden":false,"inn":"","inn_unclear":false,"patronymic":"Богданівна","inn_hidden":true,"family_raw":"","last_name":"Хемич","post":{"post_unclear":false,"region_unclear":false,"post":"суддя первомайського міськрайонного суду миколаївської області","office":"Загальний місцевий суд","region":"Миколаївська область","post_hidden":false,"office_hidden":false,"office_unclear":false,"region_hidden":false},"last_name_unclear":false,"full_name":"Хемич Оксана Богданівна","addresses":[{"place_district":"","place_address_hidden":true,"place_city":"Первомайськ","place_city_type_hidden":false,"place_district_hidden":false,"place_city_type":"Місто","place_city_hidden":false,"place_address_unclear":false,"place_address":"55200, вул. Дзержинського","place_hidden":false,"place":"Миколаївська область"},{"place_district":"","place_address_hidden":true,"place_city":"","place_city_type":"","place_address":"","place":""}],"patronymic_hidden":false,"full_name_suggest":{"output":"Хемич Оксана Богданівна","input":["Хемич Оксана Богданівна","Оксана Богданівна Хемич","Оксана Хемич"]},"name_unclear":false},"source":"VULYK","estate":{"23":[{"space_unclear":false,"costs":"","costs_comment":"","address_hidden":true,"region_hidden":false,"space_comment":"","space_hidden":false,"space":"2474","address":"Дрогобицький р-н, с. Новий Кропивник, вул. О. Довбуша","region":"Львівська область","address_unclear":true,"costs_rent_comment":"","space_units":"м²","costs_rent":""}],"25":[{"space_unclear":false,"costs":"","costs_comment":"","address_hidden":true,"region_hidden":false,"space_comment":"","space_hidden":false,"space":"36.6","address":"м. Первомайськ, вул. Дзержинського","costs_rent_comment_unclear":false,"region":"Миколаївська область","address_unclear":false,"costs_rent_comment":"","space_comment_unclear":false,"space_units":"м²","space_units_hidden":false,"costs_rent":""}]},"intro":{"declaration_year":"2014","isnotdeclaration":"","declaration_year_hidden":false}}