{"income":{"5":{"value":"260263","family_comment":"","value_unclear":false,"family_hidden":false,"value_hidden":false,"family_unclear":false,"family":"22605","comment":"","family_comment_unclear":false},"6":{"family_comment":"","family_unclear":false,"value":"260263","family":"","comment":""},"7":{"source_name_unclear":false,"value":"","family_comment":"","source_name":"","family":"","comment":"","source_name_hidden":false},"8":{"family_comment":"","value":"","family":"","comment":""},"9":{"family_comment":"","family_unclear":false,"value":"","family":"","comment":""},"10":{"family_comment":"","value":"","family":"","comment":""},"11":{"family_comment":"","value":"","family":"","comment":""},"12":{"family_comment":"","value":"","family":"","comment":""},"13":{"family_comment":"","value":"","family":"","comment":""},"14":{"family_comment":"","value":"","family":"","comment":""},"15":{"family_comment":"","value":"","family":"","comment":""},"16":{"value":"","value_unclear":false,"value_hidden":false,"family_comment":"","family":"","comment":""},"17":{"family_comment":"","value":"","family":"","comment":""},"18":{"family_comment":"","value":"","family":"","comment":""},"19":{"family_comment":"","value":"","family":"","comment":""},"20":{"value":"","family_comment":"","value_unclear":false,"comment_hidden":false,"family_hidden":false,"family":"22605","value_hidden":false,"family_unclear":false,"comment_unclear":false,"comment":"","family_comment_unclear":false}},"id":"vulyk_62_157","declaration":{"additional_info_text":"","notfull_lostpages":"","date":"2015-03-27T00:00:00","notfull":"","additional_info":"","url":"http://static.declarations.com.ua/declarations/chosen_ones/mega_batch/mykoliuk_oleksandr_volodymyrovych.pdf"},"liabilities":{"54":{"sum_foreign_comment":"","sum":"","sum_comment":"","sum_hidden":false,"sum_comment_hidden":false,"sum_foreign":""},"55":{"sum_foreign_comment":"","sum":"","sum_comment":"","sum_hidden":false,"sum_comment_hidden":false,"sum_unclear":false,"sum_foreign":""},"56":{"sum_foreign_comment":"","sum":"","sum_comment":"","sum_hidden":false,"sum_unclear":false,"sum_foreign":""},"57":{"sum_foreign_comment":"","sum":"","sum_comment":"","sum_hidden":false,"sum_comment_hidden":false,"sum_unclear":false,"sum_foreign":""},"58":{"sum_foreign_comment":"","sum_foreign_hidden":false,"sum_comment":"","sum_hidden":false,"sum_comment_hidden":false,"sum_unclear":false,"sum":"","sum_foreign":""},"59":{"sum_foreign_comment":"","sum":"","sum_comment":"","sum_foreign":""},"60":{"sum_foreign_comment":"","sum_foreign_hidden":false,"sum_comment":"","sum_hidden":false,"sum_comment_hidden":false,"sum_unclear":false,"sum":"","sum_foreign":""},"61":{"sum_foreign_comment":"","sum_foreign_hidden":false,"sum_comment":"","sum_hidden":false,"sum":"","sum_foreign":""},"62":{"sum_foreign_comment":"","sum":"","sum_comment":"","sum_unclear":false,"sum_foreign":""},"63":{"sum_foreign_comment":"","sum":"","sum_comment":"","sum_hidden":false,"sum_comment_hidden":false,"sum_unclear":false,"sum_foreign":""},"64":{"sum_foreign_comment":"","sum":"","sum_comment":"","sum_comment_unclear":false,"sum_hidden":false,"sum_comment_hidden":false,"sum_foreign":""}},"ft_src":"суддя апеляційного суду київської області\nКиївська область\nЗагальний апеляційний суд\nОлександр\nМиколюк В. А\nПодружжя\nМиколюк Д. О\nДитина\nВолодимирович\nМиколюк Олександр Володимирович\nОлександр Володимирович Миколюк\nОлександр Миколюк\nМиколюк Олександр Володимирович\nМиколюк Олександр Володимирович\nМиколюк\n22605\n260263\n22605\n260263\n1200\n1540\n48.3\n138.5\n2014\n260263\n22605\n260263\n22605\n1200\n1540\n48.3\n138.5\nМиколюк Олександр Володимирович\nОлександр Володимирович Миколюк\nОлександр Миколюк\nМиколюк Олександр Володимирович\nМиколюк Олександр Володимирович\nПодружжя\nМиколюк В. А\nДитина\nМиколюк Д. О\nОлександр\nВолодимирович\nЗагальний апеляційний суд\nсуддя апеляційного суду київської області\nКиївська область\nМиколюк\n260263\n22605\n260263\n22605\n2014\nПодружжя\nМиколюк В. А\nМиколюк Д. О\nДитина\nВолодимирович\nМиколюк\nОлександр\nМиколюк Олександр Володимирович\nОлександр Володимирович Миколюк\nОлександр Миколюк\nМиколюк Олександр Володимирович\nКиївська область\nсуддя апеляційного суду київської області\nЗагальний апеляційний суд\nМиколюк Олександр Володимирович\n48.3\n1200\n138.5\n1540\n2014","general":{"inn":"","name":"Олександр","inn_unclear":false,"family":[{"inn":"","inn_hidden":true,"relations_unclear":false,"relations_hidden":false,"relations_other":"","relations":"Подружжя","name_hidden":false,"inn_unclear":false,"family_name":"Миколюк В. А","name_unclear":false},{"inn":"","inn_hidden":false,"relations_hidden":false,"family_name":"Миколюк Д. О","relations_other":"","relations":"Дитина","name_hidden":false,"name_unclear":false}],"inn_hidden":true,"family_raw":"","last_name":"Миколюк","post":{"post_unclear":false,"post":"суддя апеляційного суду київської області","post_hidden":false,"region":"Київська область","region_hidden":false,"office":"Загальний апеляційний суд","office_hidden":false,"office_unclear":false},"full_name_suggest":{"output":"Миколюк Олександр Володимирович","input":["Миколюк Олександр Володимирович","Олександр Володимирович Миколюк","Олександр Миколюк"]},"full_name":"Миколюк Олександр Володимирович","patronymic":"Володимирович","last_name_unclear":false,"name_unclear":false},"source":"VULYK","estate":{"23":[{"region_unclear":false,"space_unclear":false,"costs":"","costs_comment":"","costs_hidden":false,"address_hidden":false,"region_hidden":false,"space_comment":"","space":"1200","address":"","region":"","address_unclear":false,"space_units_unclear":false,"space_comment_unclear":false,"space_units":"м²","space_units_hidden":false,"costs_rent":"","costs_rent_comment":""}],"25":[{"region_unclear":false,"space_hidden":false,"costs":"","costs_comment":"","costs_hidden":false,"address_hidden":false,"region_hidden":false,"space_comment":"","space_unclear":false,"space":"138.5","address":"","region":"","costs_rent_comment":"","space_units":"м²","costs_rent":""}],"29":[{"region_unclear":false,"space_hidden":false,"address_hidden":false,"region_hidden":false,"space_comment":"","space_unclear":false,"space":"1540","address":"","region":"","costs_property":"","costs_rent_comment":"","address_unclear":false,"space_units":"м²","costs_property_comment":"","costs_rent":""}],"31":[{"region_unclear":false,"space_hidden":false,"address_hidden":false,"region_hidden":false,"space_comment":"","space_unclear":false,"space":"48.3","costs_property_unclear":false,"region":"","costs_property":"","costs_rent_comment":"","space_comment_unclear":false,"address_unclear":false,"space_units":"м²","costs_property_comment":"","costs_rent":"","address":""}]},"intro":{"declaration_year":"2014","isnotdeclaration":"","declaration_year_unclear":false,"declaration_year_hidden":false}}