{"income":{"5":{"value":"270939","family_comment":"","value_unclear":false,"family_hidden":false,"value_hidden":false,"family_unclear":false,"comment_unclear":false,"comment":"","family":"2949"},"6":{"value":"266309","family_comment":"","value_unclear":false,"family_hidden":false,"value_hidden":false,"family_unclear":false,"comment_unclear":false,"comment":"","family":""},"7":{"source_name_unclear":false,"value":"","family_comment":"","source_name":"","family":"","comment":""},"8":{"family_comment":"","value":"","family":"","comment":""},"9":{"value":"","value_unclear":false,"comment_hidden":false,"family_comment":"","comment_unclear":false,"comment":"","family":""},"10":{"value":"","comment_unclear":false,"value_hidden":false,"family_comment":"","family":"","comment":""},"11":{"family_comment":"","value":"","family":"","comment":""},"12":{"family_comment":"","value":"","family":"","comment":""},"13":{"family_comment":"","value":"","family":"","comment":""},"14":{"family_comment":"","value":"","family":"","comment":""},"15":{"family_comment":"","value":"","family":"","comment":""},"16":{"family_comment":"","value":"","family":"","comment":""},"17":{"family_comment":"","value":"","family":"","comment":""},"18":{"value":"","family_hidden":false,"value_hidden":false,"family_comment":"","family":"","comment":""},"19":{"family_comment":"","value":"","family":"","comment":""},"20":{"value":"4630","family_comment":"стипендія","value_unclear":false,"family_hidden":false,"value_hidden":false,"family_unclear":false,"family":"2949","comment":"допомога на дитину"}},"id":"vulyk_66_35","declaration":{"additional_info_text":"","notfull_lostpages":"","date":"2015-03-24T00:00:00","notfull":"","additional_info":"","url":"http://static.declarations.com.ua/declarations/chosen_ones/mega_batch/vynohradnyk_olha_mykhailivna.pdf"},"liabilities":{"54":{"sum_foreign_comment":"","sum":"","sum_comment":"","sum_comment_unclear":false,"sum_comment_hidden":false,"sum_unclear":false,"sum_foreign":""},"55":{"sum_foreign_comment":"","sum":"","sum_comment":"","sum_foreign":""},"56":{"sum_foreign_comment":"","sum_foreign_hidden":false,"sum_comment":"","sum_hidden":false,"sum_comment_hidden":false,"sum":"5157","sum_foreign":""},"57":{"sum_foreign_comment":"","sum":"","sum_comment":"","sum_comment_unclear":false,"sum_hidden":false,"sum_comment_hidden":false,"sum_unclear":false,"sum_foreign":""},"58":{"sum_foreign_comment":"","sum":"","sum_comment":"","sum_comment_unclear":false,"sum_unclear":false,"sum_foreign":""},"59":{"sum_foreign_comment":"","sum_foreign_hidden":false,"sum_comment":"","sum_comment_unclear":false,"sum_hidden":false,"sum":"","sum_foreign":""},"60":{"sum_foreign_comment":"","sum":"","sum_comment":"","sum_comment_unclear":false,"sum_foreign":""},"61":{"sum_foreign_comment":"","sum":"","sum_comment":"","sum_foreign":""},"62":{"sum_foreign_comment":"","sum_foreign_hidden":false,"sum_comment":"","sum_hidden":false,"sum":"","sum_unclear":false,"sum_foreign":""},"63":{"sum_foreign_comment":"","sum":"","sum_comment":"","sum_comment_unclear":false,"sum_comment_hidden":false,"sum_unclear":false,"sum_foreign":""},"64":{"sum_foreign_comment":"","sum":"","sum_comment":"","sum_comment_unclear":false,"sum_foreign":""}},"ft_src":"5157\nсуддя дніпропетровського апеляційного господарського суду\nДніпропетровська область\nАпеляційний господарський суд\nОльга\nВиноградник Еліна Сергіївна\nДитина\nМихайлівна\nВиноградник Ольга Михайлівна\nОльга Михайлівна Виноградник\nОльга Виноградник\nВиноградник Ольга Михайлівна\nВиноградник Ольга Михайлівна\nВиноградник\nстипендія\n4630\nдопомога на дитину\n2949\n270939\n2949\n266309\n50.1\n2014\n266309\n2949\n270939\nстипендія\n2949\nдопомога на дитину\n4630\n50.1\nАпеляційний господарський суд\nсуддя дніпропетровського апеляційного господарського суду\nДніпропетровська область\nДитина\nВиноградник Еліна Сергіївна\nВиноградник Ольга Михайлівна\nОльга Михайлівна Виноградник\nОльга Виноградник\nВиноградник Ольга Михайлівна\nВиноградник Ольга Михайлівна\nОльга\nВиноградник\nМихайлівна\n5157\n266309\n4630\nстипендія\nдопомога на дитину\n2949\n270939\n2949\n2014\n5157\nВиноградник Еліна Сергіївна\nДитина\nМихайлівна\nВиноградник\nОльга\nВиноградник Ольга Михайлівна\nОльга Михайлівна Виноградник\nОльга Виноградник\nВиноградник Ольга Михайлівна\nДніпропетровська область\nсуддя дніпропетровського апеляційного господарського суду\nАпеляційний господарський суд\nВиноградник Ольга Михайлівна\n50.1\n2014","general":{"inn":"","name":"Ольга","last_name_hidden":false,"family":[{"inn":"","inn_hidden":true,"relations_hidden":false,"family_name":"Виноградник Еліна Сергіївна","relations_other":"","relations":"Дитина","name_hidden":false,"name_unclear":false}],"patronymic":"Михайлівна","inn_hidden":true,"family_raw":"","inn_unclear":false,"post":{"post_unclear":false,"post":"суддя дніпропетровського апеляційного господарського суду","candidate":"","office_hidden":false,"region":"Дніпропетровська область","office":"Апеляційний господарський суд","office_unclear":false},"full_name_suggest":{"output":"Виноградник Ольга Михайлівна","input":["Виноградник Ольга Михайлівна","Ольга Михайлівна Виноградник","Ольга Виноградник"]},"full_name":"Виноградник Ольга Михайлівна","addresses":[{"place_city_type_unclear":false,"place_address":"","place_district_hidden":false,"place_city_type":"","place_address_hidden":true,"place_address_unclear":false,"place_city_type_hidden":false,"place":"","place_district":"","place_unclear":false,"place_city":"","place_city_unclear":false,"place_hidden":false,"place_city_hidden":false,"place_district_unclear":false}],"last_name":"Виноградник","last_name_unclear":false},"source":"VULYK","estate":{"25":[{"region_unclear":false,"space_hidden":false,"costs":"","costs_comment":"","costs_hidden":false,"address_hidden":false,"region_hidden":true,"space_comment":"","space_unclear":false,"space":"50.1","space_units_hidden":false,"region":"","address_unclear":false,"costs_rent_comment":"","space_comment_unclear":false,"space_units":"м²","address":"","costs_rent":""}]},"intro":{"declaration_year":"2014","isnotdeclaration":"","declaration_year_unclear":false}}