{"income":{"5":{"family_comment":"","family_unclear":false,"value":"191846","family":"27376","comment":""},"6":{"value":"191811","family_comment":"","value_unclear":false,"family_unclear":false,"family":"27326","comment":""},"7":{"value":"","family_comment":"","value_unclear":false,"family_unclear":false,"source_name":"","family":"","comment":"","source_name_hidden":false},"8":{"family_comment":"","value":"","family":"","comment":""},"9":{"family_comment":"","value":"","family":"","comment":""},"10":{"family_comment":"","value":"","value_unclear":false,"family":"","comment":""},"11":{"family_comment":"","value":"","family":"","comment":""},"12":{"family_comment":"","value":"","family":"","comment":""},"13":{"family_comment":"","value":"","family":"","comment":""},"14":{"family_comment":"","value":"","family":"","comment":""},"15":{"family_comment":"","value":"","family":"","comment":""},"16":{"family_comment":"","value":"","family":"","comment":""},"17":{"family_comment":"","value":"","family":"50","comment":""},"18":{"family_comment":"","value":"","family":"","comment":""},"19":{"family_comment":"","value":"","family":"","comment":""},"20":{"value":"35","value_unclear":false,"comment_hidden":false,"family_comment":"","comment_unclear":false,"comment":"","family":""}},"id":"vulyk_96_49","declaration":{"additional_info_text":"","notfull_lostpages":"","date":"2016-03-28T00:00:00","notfull":"","additional_info":"","url":"http://static.declarations.com.ua/declarations/chosen_ones/judges_batch/263_sivchuk_andrii_ievhenovych_2015.pdf"},"liabilities":{"54":{"sum_foreign_comment":"","sum":"","sum_comment":"","sum_hidden":false,"sum_comment_hidden":false,"sum_foreign":""},"55":{"sum_foreign_comment":"","sum":"","sum_comment":"","sum_foreign":""},"56":{"sum_foreign_comment":"","sum":"","sum_comment":"","sum_unclear":false,"sum_foreign":""},"57":{"sum_foreign_comment":"","sum_comment_hidden":false,"sum":"","sum_comment":"","sum_foreign":""},"58":{"sum_foreign_comment":"","sum":"","sum_comment":"","sum_comment_hidden":false,"sum_unclear":false,"sum_foreign":""},"59":{"sum_foreign_comment":"","sum":"","sum_comment":"","sum_foreign":""},"60":{"sum_foreign_comment":"","sum_comment_hidden":false,"sum":"","sum_comment":"","sum_foreign":""},"61":{"sum_foreign_comment":"","sum":"","sum_comment":"","sum_foreign":""},"62":{"sum_foreign_comment":"","sum":"","sum_comment":"","sum_foreign":""},"63":{"sum_foreign_comment":"","sum_comment_hidden":false,"sum":"","sum_comment":"","sum_foreign":""},"64":{"sum_foreign_comment":"","sum_comment_hidden":false,"sum":"","sum_comment":"","sum_foreign":""}},"ft_src":"суддя луцького міськрайонного суду волинської області\nВолинська область\nЗагальний місцевий суд\nАндрій\nСівчук І. М\nПодружжя\nСівчук А. А\nДитина\nЄвгенович\nСівчук Андрій Євгенович\nСівчук\nСівчук Андрій Євгенович\nАндрій Євгенович Сівчук\nАндрій Сівчук\nСівчук Андрій Євгенович\n35\n27376\n191846\n50\n191811\n27326\n62.2\n2015\n27326\n191811\n27376\n191846\n50\n35\n27326\n191811\n50\n35\n191846\n27376\nСівчук Андрій Євгенович\nАндрій Євгенович Сівчук\nАндрій Сівчук\nСівчук Андрій Євгенович\nСівчук Андрій Євгенович\nАндрій\nСівчук\nВолинська область\nсуддя луцького міськрайонного суду волинської області\nЗагальний місцевий суд\nЄвгенович\nПодружжя\nСівчук І. М\nДитина\nСівчук А. А\n62.2\n2015\nСівчук І. М\nПодружжя\nДитина\nСівчук А. А\nАндрій\nЄвгенович\nСівчук\nСівчук Андрій Євгенович\nАндрій Євгенович Сівчук\nАндрій Сівчук\nСівчук Андрій Євгенович\nсуддя луцького міськрайонного суду волинської області\nВолинська область\nЗагальний місцевий суд\nСівчук Андрій Євгенович\n62.2\n2015","general":{"inn":"","name":"Андрій","family":[{"inn":"","inn_hidden":true,"inn_unclear":false,"relations_hidden":false,"relations_other":"","relations":"Подружжя","name_hidden":true,"family_name":"Сівчук І. М","name_unclear":false},{"inn":"","relations":"Дитина","relations_other":"","inn_hidden":true,"family_name":"Сівчук А. А","name_hidden":false,"name_unclear":false}],"patronymic":"Євгенович","inn_hidden":true,"family_raw":"","last_name":"Сівчук","post":{"office":"Загальний місцевий суд","region":"Волинська область","office_unclear":false,"post":"суддя луцького міськрайонного суду волинської області"},"full_name":"Сівчук Андрій Євгенович","addresses":[{"place_district":"","place_city_hidden":true,"place_city":"","place_city_type_hidden":false,"place_district_hidden":false,"place_city_type":"","place_address_hidden":true,"place_address":"","place_hidden":true,"place":""}],"patronymic_hidden":false,"full_name_suggest":{"output":"Сівчук Андрій Євгенович","input":["Сівчук Андрій Євгенович","Андрій Євгенович Сівчук","Андрій Сівчук"]}},"source":"VULYK","estate":{"25":[{"space_comment_unclear":false,"space_unclear":false,"costs":"","costs_comment":"","address_hidden":false,"region_hidden":true,"space_comment":"","space_hidden":false,"space":"62.2","address":"","costs_rent_comment_unclear":false,"region":"","address_unclear":false,"costs_rent_comment":"","costs_unclear":false,"space_comment_hidden":false,"space_units":"м²","costs_rent":""}]},"intro":{"declaration_year":"2015","isnotdeclaration":""}}