{"id":"vulyk_98_31","ft_src":"2005\nOpel Vectra\n1600 куб. см., 77 кВт\n2008\n1600 куб. см., на праві користування\nHyundai\n60.2\n1160\n1160\n2014\n1600 куб. см., 77 кВт\n2005\nOpel Vectra\n1600 куб. см., на праві користування\nHyundai\n2008\n2014\nЗагальний місцевий суд\nзаступник голови кам'янець-подільського міськрайонного суду хмельницької області\nХмельницька область\nШевцова Людмила Михайлівна\nЛюдмила Михайлівна Шевцова\nЛюдмила Шевцова\nШевцова Людмила Михайлівна\nШевцова Людмила Михайлівна\nЛюдмила\nШевцова\nМихайлівна\n499\nУкраїнський страховий дім, Страхове товариство 'Гарантія', ПАТ КБ 'Приватбанк'\n13661\n4556\n212359\n247472\n35000\n113\n60.2\n1160\n1160\n4556\n13661\nУкраїнський страховий дім, Страхове товариство 'Гарантія', ПАТ КБ 'Приватбанк'\n499\n212359\n113\n247472\n35000\nМихайлівна\nШевцова\nЛюдмила\nШевцова Людмила Михайлівна\nЛюдмила Михайлівна Шевцова\nЛюдмила Шевцова\nШевцова Людмила Михайлівна\nзаступник голови кам'янець-подільського міськрайонного суду хмельницької області\nХмельницька область\nЗагальний місцевий суд\nШевцова Людмила Михайлівна","estate":{"25":[{"address":"","space_units":"м²","costs_comment":"","space_unclear":false,"region_hidden":true,"space_comment":"","address_hidden":true,"costs":"","address_unclear":false,"costs_rent_comment":"","space":"60.2","region":"","costs_rent":""}]},"vehicle":{"35":[{"sum_comment":"","brand_info":"1600 куб. см., 77 кВт","brand_unclear":false,"sum_rent_comment":"","year":"2005","brand":"Opel Vectra","sum_rent":"","brand_info_unclear":false,"sum":""},{"sum_comment":"","brand_info":"1600 куб. см., на праві користування","sum":"","brand_unclear":true,"year":"2008","brand":"Hyundai","sum_rent":"","sum_rent_comment":""}]},"source":"VULYK","income":{"5":{"family_comment":"","family":"","comment":"","value_unclear":false,"family_unclear":false,"value":"247472"},"6":{"family_comment":"","value":"212359","family":"","comment":"","value_unclear":false},"7":{"family":"","family_comment":"","value":"","comment":"","source_name":""},"8":{"family_comment":"","value":"","family":"","comment":""},"9":{"family_comment":"","value":"113","family":"","comment":"","value_unclear":false},"10":{"family_comment":"","value":"","family":"","comment":""},"11":{"family_comment":"","value":"","family":"","comment":""},"12":{"family_comment":"","value":"","family":"","comment":""},"13":{"family_comment":"","value":"","family":"","comment":""},"14":{"family_comment":"","value":"","family":"","comment":""},"15":{"family_comment":"","value":"","family":"","comment":""},"16":{"family_comment":"","value":"35000","family":"","comment":""},"17":{"family_comment":"","value":"","family":"","comment":""},"18":{"family_comment":"","value":"","family":"","comment":""},"19":{"family_comment":"","value":"","family":"","comment":""},"20":{"family_comment":"","value":"","family":"","comment":"","value_unclear":false}},"banks":{"45":[{"sum_units":"UAH","sum_comment":"","sum_foreign_units":"UAH","sum_hidden":false,"sum":"1160","sum_foreign_comment":"","sum_foreign":"","sum_unclear":false,"sum_comment_hidden":false}],"46":[{"sum_units":"UAH","sum_comment":"","sum_foreign_units":"UAH","sum_hidden":false,"sum":"1160","sum_foreign_comment":"","sum_foreign":"","sum_unclear":false,"sum_comment_hidden":false}]},"declaration":{"date":"2015-03-27T00:00:00","url":"http://static.declarations.com.ua/declarations/chosen_ones/judges_batch/4505_shevtsova_liudmyla_mykhailivna.pdf"},"general":{"family_raw":"","name":"Людмила","full_name_suggest":{"input":["Шевцова Людмила Михайлівна","Людмила Михайлівна Шевцова","Людмила Шевцова"],"output":"Шевцова Людмила Михайлівна"},"patronymic":"Михайлівна","inn_hidden":true,"addresses":[{"place_city_type_hidden":true,"place_city_type":"","place_city_hidden":true,"place_hidden":true,"place_district":"","place_district_hidden":true,"place":"","place_address":"","place_address_hidden":true,"place_city":""}],"last_name_hidden":false,"patronymic_hidden":false,"inn":"","inn_unclear":false,"last_name":"Шевцова","full_name":"Шевцова Людмила Михайлівна","post":{"office":"Загальний місцевий суд","region":"Хмельницька область","post_unclear":false,"post":"заступник голови кам'янець-подільського міськрайонного суду хмельницької області"},"last_name_unclear":false},"liabilities":{"54":{"sum_comment_unclear":true,"sum_comment":"Український страховий дім, Страхове товариство 'Гарантія', ПАТ КБ 'Приватбанк'","sum_hidden":false,"sum":"499","sum_foreign_comment":"","sum_foreign":"","sum_unclear":true,"sum_comment_hidden":false},"55":{"sum_comment":"","sum_foreign_comment":"","sum_foreign":"","sum":""},"56":{"sum_comment":"","sum_foreign_comment":"","sum_foreign":"","sum_unclear":false,"sum":""},"57":{"sum_comment_unclear":false,"sum_comment":"","sum_hidden":false,"sum":"13661","sum_foreign_comment":"","sum_foreign":"","sum_unclear":false,"sum_comment_hidden":false},"58":{"sum_comment":"","sum_hidden":false,"sum":"4556","sum_foreign_comment":"","sum_foreign":"","sum_unclear":false,"sum_comment_hidden":false},"59":{"sum_comment":"","sum_comment_unclear":false,"sum_foreign_comment":"","sum":"","sum_foreign":""},"60":{"sum_comment":"","sum_hidden":false,"sum":"","sum_foreign_comment":"","sum_foreign":"","sum_comment_hidden":false},"61":{"sum_comment":"","sum_foreign_comment":"","sum_foreign":"","sum":""},"62":{"sum_comment":"","sum":"","sum_foreign_comment":"","sum_foreign":"","sum_unclear":false,"sum_comment_hidden":false},"63":{"sum_comment_unclear":false,"sum_comment":"","sum":"","sum_foreign_comment":"","sum_foreign":"","sum_comment_hidden":false},"64":{"sum_comment":"","sum_foreign_comment":"","sum_foreign":"","sum":"","sum_comment_hidden":false}},"intro":{"declaration_year":"2014"}}