{"income":{"5":{"family_comment":"","value":"184350","value_unclear":false,"family":"184498","comment":""},"6":{"value":"184350","value_unclear":false,"family_hidden":false,"family_comment":"","family":"184495","comment":""},"7":{"source_name_unclear":false,"value":"","family_comment":"","source_name":"","family":"","comment":""},"8":{"family_comment":"","value":"","family":"","comment":""},"9":{"family_comment":"","value":"","family":"3","comment":""},"10":{"family_comment":"","value":"","family":"","comment":""},"11":{"family_comment":"","value":"","comment_unclear":false,"family":"","comment":""},"12":{"family_comment":"","value":"","family":"","comment":""},"13":{"family_comment":"","value":"","family":"","comment":""},"14":{"family_comment":"","value":"","family":"","comment":""},"15":{"family_comment":"","value":"","family":"","comment":""},"16":{"family_comment":"","value":"","family":"","comment":""},"17":{"family_comment":"","value":"","family":"","comment":""},"18":{"family_comment":"","value":"","family":"","comment":""},"19":{"family_comment":"","value":"","family":"","comment":""},"20":{"value":"","family_comment":"","value_unclear":false,"family_unclear":false,"comment_unclear":false,"comment":"","family":""}},"id":"vulyk_101_7","banks":{"51":[{"sum_foreign_comment":"","sum_units":"UAH","sum_comment":"","sum_hidden":false,"sum_foreign_units":"UAH","sum_comment_hidden":true,"sum_unclear":false,"sum":"116","sum_foreign":""}]},"declaration":{"additional_info_text":"","notfull_lostpages":"","date":"2016-03-23T00:00:00","notfull":"","additional_info":"","url":"http://static.declarations.com.ua/declarations/chosen_ones/judges_batch/666_bezdolia_iuliia_serhiivna_2015.pdf"},"liabilities":{"54":{"sum_foreign_comment":"","sum":"","sum_comment":"","sum_comment_unclear":false,"sum_hidden":false,"sum_comment_hidden":false,"sum_unclear":false,"sum_foreign":""},"55":{"sum_foreign_comment":"","sum":"","sum_comment":"","sum_foreign":""},"56":{"sum_foreign_comment":"","sum":"","sum_comment":"","sum_comment_hidden":false,"sum_unclear":false,"sum_foreign":""},"57":{"sum_foreign_comment":"","sum":"","sum_comment":"","sum_hidden":false,"sum_comment_hidden":false,"sum_unclear":false,"sum_foreign":""},"58":{"sum_foreign_comment":"","sum":"","sum_comment":"","sum_comment_unclear":false,"sum_hidden":false,"sum_comment_hidden":false,"sum_unclear":false,"sum_foreign":""},"59":{"sum_foreign_comment":"","sum":"","sum_comment":"","sum_foreign":""},"60":{"sum_foreign_comment":"","sum":"","sum_comment":"","sum_hidden":false,"sum_comment_hidden":false,"sum_unclear":false,"sum_foreign":""},"61":{"sum_foreign_comment":"","sum":"","sum_comment":"","sum_foreign":""},"62":{"sum_foreign_comment":"","sum":"","sum_comment":"","sum_comment_unclear":false,"sum_foreign":""},"63":{"sum_foreign_comment":"","sum_comment_hidden":false,"sum":"","sum_comment":"","sum_foreign":""},"64":{"sum_foreign_comment":"","sum_comment_hidden":false,"sum":"","sum_comment":"","sum_foreign":""}},"ft_src":"суддя господарського суду одеської області\nОдеська область\nГосподарський місцевий суд\nЮлія\nБездоля Д. О\nПодружжя\nБритавська А. В\nДитина\nСергіївна\nБездоля Юлія Сергіївна\nБездоля\nБездоля Юлія Сергіївна\nЮлія Сергіївна Бездоля\nЮлія Бездоля\nБездоля Юлія Сергіївна\nм. Одеса\nОдеська область\n103.9\n1/2\nм. Одеса\n67.8\nОдеська область\n116\n2015\n2015\nПодружжя\nБездоля Д. О\nДитина\nБритавська А. В\nБездоля Юлія Сергіївна\nЮлія Сергіївна Бездоля\nЮлія Бездоля\nБездоля Юлія Сергіївна\nЮлія\nБездоля Юлія Сергіївна\nСергіївна\nГосподарський місцевий суд\nсуддя господарського суду одеської області\nОдеська область\nБездоля\n184350\n184495\n184350\n184498\n3\n103.9\nм. Одеса\nОдеська область\n67.8\n1/2\nОдеська область\nм. Одеса\n116\n184495\n184350\n3\n184498\n184350\nБездоля Д. О\nПодружжя\nБритавська А. В\nДитина\nЮлія\nСергіївна\nБездоля\nБездоля Юлія Сергіївна\nЮлія Сергіївна Бездоля\nЮлія Бездоля\nБездоля Юлія Сергіївна\nсуддя господарського суду одеської області\nГосподарський місцевий суд\nОдеська область\nБездоля Юлія Сергіївна\n3\n184498\n184350\n184350\n184495\nм. Одеса\nОдеська область\n103.9\n1/2\nм. Одеса\nОдеська область\n67.8\n116\n2015","general":{"inn":"","name":"Юлія","inn_unclear":false,"family":[{"inn":"","relations":"Подружжя","relations_other":"","inn_hidden":true,"family_name":"Бездоля Д. О","name_hidden":true,"name_unclear":false},{"inn":"","relations":"Дитина","relations_unclear":false,"family_name":"Бритавська А. В","inn_hidden":true,"relations_other":"","name_hidden":false,"name_unclear":false}],"inn_hidden":true,"family_raw":"","last_name":"Бездоля","post":{"region":"Одеська область","region_unclear":false,"post":"суддя господарського суду одеської області","office_unclear":false,"office":"Господарський місцевий суд"},"full_name":"Бездоля Юлія Сергіївна","addresses":[{"place_district":"","place_city_hidden":true,"place_city":"","place_city_type_hidden":false,"place_district_hidden":false,"place_city_type":"","place_address_hidden":true,"place_address":"","place_hidden":true,"place":""}],"patronymic":"Сергіївна","patronymic_hidden":false,"full_name_suggest":{"output":"Бездоля Юлія Сергіївна","input":["Бездоля Юлія Сергіївна","Юлія Сергіївна Бездоля","Юлія Бездоля"]}},"source":"VULYK","estate":{"25":[{"space_unclear":false,"costs":"","costs_comment":"","address_hidden":true,"region_hidden":false,"space_comment":"","space_hidden":false,"space":"103.9","address":"м. Одеса","region":"Одеська область","costs_rent_comment":"","space_comment_unclear":false,"space_units":"м²","costs_rent":""},{"space_unclear":false,"costs":"","costs_comment":"","space_comment":"1/2","space_hidden":false,"space":"67.8","address":"м. Одеса","region":"Одеська область","costs_rent_comment":"","space_comment_unclear":false,"space_units":"м²","costs_rent":""}]},"intro":{"declaration_year":"2015"}}