{"income":{"5":{"family_comment":"","family_unclear":false,"value":"187298","family":"58614","comment":""},"6":{"family_comment":"","family_unclear":false,"value":"187298","family":"58489","comment":""},"7":{"value":"","comment_hidden":false,"family_comment":"","source_name":"","family":"","comment":""},"8":{"family_comment":"","value":"","family":"","comment":""},"9":{"family_comment":"","value":"","family":"","comment":""},"10":{"family_comment":"","value":"","family":"","comment":""},"11":{"family_comment":"","value":"","value_unclear":false,"family":"","comment":""},"12":{"family_comment":"","value":"","family":"","comment":""},"13":{"family_comment":"","value":"","family":"","comment":""},"14":{"family_comment":"","value":"","family":"","comment":""},"15":{"family_comment":"","value":"","value_unclear":false,"family":"","comment":""},"16":{"family_comment":"","family_unclear":false,"value":"","family":"","comment":""},"17":{"family_comment":"","value":"","family":"","comment":""},"18":{"family_comment":"","value":"","family_hidden":false,"comment":"","family":""},"19":{"family_comment":"","value":"","family":"","comment":""},"20":{"value":"","comment_unclear":false,"comment_hidden":false,"family_comment":"","family":"125","comment":"","family_comment_hidden":false}},"id":"vulyk_68_167","declaration":{"additional_info_text":"","notfull_lostpages":"","date":"2015-03-30T00:00:00","notfull":"","additional_info":"","url":"http://static.declarations.com.ua/declarations/chosen_ones/mega_batch/polovyi_oleksandr_leonidovych.pdf"},"liabilities":{"54":{"sum_foreign_comment":"","sum":"120","sum_comment":"","sum_comment_unclear":false,"sum_hidden":false,"sum_comment_hidden":false,"sum_unclear":false,"sum_foreign":""},"55":{"sum_foreign_comment":"","sum":"","sum_hidden":false,"sum_comment":"","sum_foreign":""},"56":{"sum_foreign_comment":"","sum_foreign_hidden":false,"sum_comment":"","sum":"4165","sum_unclear":false,"sum_foreign":""},"57":{"sum_foreign_comment":"","sum":"","sum_comment":"","sum_comment_unclear":false,"sum_hidden":false,"sum_comment_hidden":false,"sum_unclear":false,"sum_foreign":""},"58":{"sum_foreign_comment":"","sum":"","sum_comment":"","sum_hidden":false,"sum_comment_hidden":false,"sum_unclear":false,"sum_foreign":""},"59":{"sum_foreign_comment":"","sum":"","sum_comment":"","sum_foreign":""},"60":{"sum_foreign_comment":"","sum":"120","sum_comment":"","sum_comment_unclear":false,"sum_hidden":false,"sum_comment_hidden":false,"sum_unclear":false,"sum_foreign":""},"61":{"sum_foreign_comment":"","sum":"","sum_hidden":false,"sum_comment":"","sum_foreign":""},"62":{"sum_foreign_comment":"","sum":"","sum_comment":"","sum_unclear":false,"sum_foreign":""},"63":{"sum_foreign_comment":"","sum":"","sum_comment":"","sum_hidden":false,"sum_comment_hidden":false,"sum_unclear":false,"sum_foreign":""},"64":{"sum_foreign_comment":"","sum":"","sum_comment":"","sum_hidden":false,"sum_comment_hidden":false,"sum_foreign":""}},"ft_src":"120\n4165\n120\nсуддя хмельницького окружного адміністративного суду\nХмельницька область\nАдміністративний місцевий суд\nОлександр\nПольова В. Є\nПодружжя\nПольовий Т. О\nДитина\nЛеонідович\nПольовий Олександр Леонідович\nОлександр Леонідович Польовий\nОлександр Польовий\nПольовий Олександр Леонідович\nПольовий Олександр Леонідович\nПольовий\n125\n58614\n187298\n58489\n187298\nУкраїна\n35.1\n2014\n58489\n187298\n58614\n187298\n125\n35.1\nУкраїна\nПодружжя\nПольова В. Є\nДитина\nПольовий Т. О\nПольовий Олександр Леонідович\nОлександр Леонідович Польовий\nОлександр Польовий\nПольовий Олександр Леонідович\nПольовий Олександр Леонідович\nОлександр\nЛеонідович\nАдміністративний місцевий суд\nХмельницька область\nсуддя хмельницького окружного адміністративного суду\nПольовий\n120\n4165\n120\n187298\n58489\n125\n187298\n58614\n2014\n4165\n120\n120\nПодружжя\nПольова В. Є\nПольовий Т. О\nДитина\nЛеонідович\nПольовий\nОлександр\nПольовий Олександр Леонідович\nОлександр Леонідович Польовий\nОлександр Польовий\nПольовий Олександр Леонідович\nХмельницька область\nАдміністративний місцевий суд\nсуддя хмельницького окружного адміністративного суду\nПольовий Олександр Леонідович\n35.1\nУкраїна\n2014","general":{"inn":"","name":"Олександр","inn_unclear":false,"family":[{"inn":"","inn_hidden":true,"relations_unclear":false,"relations_hidden":false,"relations_other":"","relations":"Подружжя","name_hidden":false,"inn_unclear":false,"family_name":"Польова В. Є","name_unclear":false},{"inn":"","inn_hidden":false,"inn_unclear":false,"relations_hidden":false,"relations_other":"","relations":"Дитина","name_hidden":false,"family_name":"Польовий Т. О","name_unclear":false}],"inn_hidden":true,"family_raw":"","last_name":"Польовий","post":{"post_unclear":false,"region_unclear":false,"post":"суддя хмельницького окружного адміністративного суду","office":"Адміністративний місцевий суд","region":"Хмельницька область","post_hidden":false,"office_hidden":false,"office_unclear":false,"region_hidden":false},"full_name_suggest":{"output":"Польовий Олександр Леонідович","input":["Польовий Олександр Леонідович","Олександр Леонідович Польовий","Олександр Польовий"]},"full_name":"Польовий Олександр Леонідович","addresses":[{"place_city_type_hidden":true,"place_district_hidden":true,"place_city_type":"","place_city_hidden":true,"place_address_unclear":false,"place_address":"","place_hidden":true,"place":"","place_district":"","place_unclear":false,"place_city":"","place_address_hidden":true}],"patronymic":"Леонідович","last_name_unclear":false,"name_unclear":false},"source":"VULYK","estate":{"25":[{"space_unclear":false,"costs":"","costs_comment":"","address_hidden":true,"region_hidden":true,"space_comment":"","space_hidden":false,"space":"35.1","address":"Україна","space_comment_unclear":false,"region":"","address_unclear":false,"costs_rent_comment":"","costs_unclear":false,"space_units":"м²","space_units_hidden":false,"costs_rent":""}]},"intro":{"declaration_year":"2014","isnotdeclaration":""}}