{"income":{"5":{"value":"53923","family_comment":"","value_unclear":false,"family_hidden":false,"value_hidden":false,"family_unclear":false,"family":"205399","comment":"","family_comment_unclear":false},"6":{"value":"32220","family_comment":"","value_unclear":false,"comment_hidden":false,"family_hidden":false,"value_hidden":false,"family_unclear":false,"family":"204604","comment":""},"7":{"value":"","value_hidden":false,"family_comment":"","source_name":"Кіровоградський окружний адміністративний суд","family":"","comment":"","source_name_hidden":false},"8":{"family_comment":"","value":"","family":"","comment":""},"9":{"value":"","comment_hidden":false,"value_hidden":false,"family_comment":"","family":"","comment":""},"10":{"value":"","value_unclear":false,"value_hidden":false,"family_comment":"","family":"","comment":""},"11":{"family_comment":"","value":"","family":"","comment":""},"12":{"family_comment":"","value":"","family":"","comment":""},"13":{"family_comment":"","value":"8911","family_hidden":false,"comment":"","family":""},"14":{"family_comment":"","value":"","family":"","comment":""},"15":{"family_comment":"","family_unclear":false,"value":"","family":"","comment":""},"16":{"family_comment":"","value":"","value_unclear":false,"family":"","comment":""},"17":{"family_comment":"","value":"","family":"","comment":""},"18":{"family_comment":"","value":"","family":"","comment":""},"19":{"family_comment":"","value":"","comment_unclear":false,"family":"","comment":""},"20":{"value":"12792","comment_unclear":false,"family_hidden":false,"value_hidden":false,"family_comment":"","family":"795","comment":""}},"id":"vulyk_64_103","declaration":{"additional_info_text":"","notfull_lostpages":"","date":"2015-03-26T00:00:00","notfull":"","additional_info":"","url":"http://static.declarations.com.ua/declarations/chosen_ones/mega_batch/petrenko_olena_serhiivna.pdf"},"liabilities":{"54":{"sum_foreign_comment":"","sum":"","sum_comment":"","sum_foreign_comment_hidden":false,"sum_hidden":false,"sum_comment_hidden":false,"sum_unclear":false,"sum_foreign":""},"55":{"sum_foreign_comment":"","sum":"","sum_comment":"","sum_comment_unclear":false,"sum_foreign":""},"56":{"sum_foreign_comment":"","sum":"","sum_comment":"","sum_unclear":false,"sum_foreign":""},"57":{"sum_foreign_comment":"","sum":"","sum_comment":"","sum_hidden":false,"sum_unclear":false,"sum_foreign":""},"58":{"sum_foreign_comment":"","sum":"","sum_comment":"","sum_unclear":false,"sum_foreign":""},"59":{"sum_foreign_comment":"","sum":"","sum_comment":"","sum_comment_unclear":false,"sum_comment_hidden":false,"sum_unclear":false,"sum_foreign":""},"60":{"sum_foreign_comment":"","sum":"","sum_comment":"","sum_foreign":""},"61":{"sum_foreign_comment":"","sum":"","sum_comment":"","sum_foreign":""},"62":{"sum_foreign_comment":"","sum":"3441","sum_comment":"","sum_unclear":false,"sum_foreign":""},"63":{"sum_foreign_comment":"","sum":"","sum_comment":"","sum_unclear":false,"sum_foreign":""},"64":{"sum_foreign_comment":"","sum":"","sum_comment":"","sum_comment_unclear":false,"sum_unclear":false,"sum_foreign":""}},"ft_src":"3441\nсуддя кіровоградського окружного адміністративного суду\nКіровоградська область\nАдміністративний місцевий суд\nОлена\nФлоренко О. Ю\nПодружжя\nКонибок А. С\nДитина\nФлоренко К. О\nДитина\nСергіївна\nПетренко Олена Сергіївна\nПетренко\nПетренко Олена Сергіївна\nОлена Сергіївна Петренко\nОлена Петренко\nПетренко Олена Сергіївна\n12792\n795\n53923\n205399\nКіровоградський окружний адміністративний суд\n32220\n204604\n8911\nвласник 1/4 частини\n30.4\n48.4\n2014\n204604\n32220\n8911\nКіровоградський окружний адміністративний суд\n205399\n53923\n795\n12792\n30.4\nвласник 1/4 частини\n48.4\nАдміністративний місцевий суд\nКіровоградська область\nсуддя кіровоградського окружного адміністративного суду\nПодружжя\nФлоренко О. Ю\nДитина\nКонибок А. С\nДитина\nФлоренко К. О\nПетренко Олена Сергіївна\nОлена Сергіївна Петренко\nОлена Петренко\nПетренко Олена Сергіївна\nПетренко Олена Сергіївна\nОлена\nПетренко\nСергіївна\n3441\nКіровоградський окружний адміністративний суд\n204604\n32220\n8911\n12792\n795\n53923\n205399\n2014\n3441\nПодружжя\nФлоренко О. Ю\nДитина\nКонибок А. С\nФлоренко К. О\nДитина\nСергіївна\nПетренко\nОлена\nПетренко Олена Сергіївна\nОлена Сергіївна Петренко\nОлена Петренко\nПетренко Олена Сергіївна\nКіровоградська область\nАдміністративний місцевий суд\nсуддя кіровоградського окружного адміністративного суду\nПетренко Олена Сергіївна\nвласник 1/4 частини\n30.4\n48.4\n2014","general":{"inn":"","name":"Олена","last_name_hidden":false,"family":[{"inn":"","inn_hidden":true,"relations_unclear":false,"relations_hidden":false,"relations_other":"","relations":"Подружжя","name_hidden":false,"inn_unclear":false,"family_name":"Флоренко О. Ю","name_unclear":false},{"inn":"","inn_hidden":false,"relations_unclear":false,"relations_hidden":false,"relations_other":"","relations":"Дитина","name_hidden":false,"family_name":"Конибок А. С","name_unclear":true},{"inn":"","relations":"Дитина","relations_other":"","inn_hidden":true,"family_name":"Флоренко К. О","name_hidden":false,"name_unclear":true}],"patronymic":"Сергіївна","inn_hidden":true,"family_raw":"","inn_unclear":false,"post":{"post_unclear":false,"post":"суддя кіровоградського окружного адміністративного суду","candidate":"","office_hidden":false,"region":"Кіровоградська область","post_hidden":false,"office":"Адміністративний місцевий суд","office_unclear":false,"region_hidden":false},"last_name_unclear":false,"full_name":"Петренко Олена Сергіївна","addresses":[{"place_city_type_unclear":false,"place_address":"","place_district_hidden":false,"place_city_type":"","place_city_hidden":true,"place_city_type_hidden":true,"place":"","place_district":"","place_unclear":false,"place_city":"","place_city_unclear":false,"place_hidden":true,"place_address_hidden":true}],"last_name":"Петренко","patronymic_hidden":false,"full_name_suggest":{"output":"Петренко Олена Сергіївна","input":["Петренко Олена Сергіївна","Олена Сергіївна Петренко","Олена Петренко"]},"name_unclear":false},"source":"VULYK","estate":{"25":[{"region_unclear":false,"space_unclear":false,"costs":"","costs_rent_unclear":false,"costs_comment":"","costs_hidden":false,"address_hidden":false,"region_hidden":true,"space_comment":"","space_hidden":false,"space":"48.4","space_units_hidden":false,"costs_rent_comment_unclear":false,"region":"","costs_rent_comment":"","costs_rent_hidden":false,"space_comment_unclear":false,"space_units":"м²","address":"","costs_rent":"","costs_unclear":false}],"30":[{"region_unclear":false,"space_unclear":false,"costs_property_hidden":false,"address_hidden":false,"region_hidden":false,"space_comment":"власник 1/4 частини","space_hidden":false,"space":"30.4","address":"","region":"","costs_property":"","costs_rent_comment":"","costs_rent_hidden":false,"space_comment_unclear":false,"address_unclear":false,"space_units":"м²","costs_property_comment":"","costs_rent":""}]},"intro":{"declaration_year":"2014","isnotdeclaration":"","declaration_year_unclear":false,"declaration_year_hidden":false}}