{"income":{"5":{"value":"246155","family_comment":"","value_unclear":false,"family_hidden":false,"value_hidden":false,"family_unclear":false,"family":"","comment":""},"6":{"value":"246155","value_unclear":false,"family_hidden":false,"value_hidden":false,"family_comment":"","comment_unclear":false,"comment":"","family":""},"7":{"value":"","value_hidden":false,"family_comment":"","source_name":"","family":"","comment":"","source_name_hidden":false},"8":{"family_comment":"","value":"","family":"","comment":""},"9":{"family_comment":"","value":"","comment_unclear":false,"family":"","comment":""},"10":{"family_comment":"","value":"","value_unclear":false,"family":"","comment":""},"11":{"family_comment":"","value":"","family":"","comment":""},"12":{"family_comment":"","value":"","family":"","comment":""},"13":{"family_comment":"","value":"","family":"","comment":""},"14":{"family_comment":"","value":"","family":"","comment":""},"15":{"family_comment":"","value":"","family":"","comment":""},"16":{"family_comment":"","value":"","family":"","comment":""},"17":{"family_comment":"","value":"","family":"","comment":""},"18":{"family_comment":"","value":"","family":"","comment":""},"19":{"value":"","value_unclear":false,"comment_hidden":false,"family_hidden":false,"value_hidden":false,"family_comment":"","family_comment_hidden":false,"comment":"","family":""},"20":{"value":"","family_comment":"","value_unclear":false,"family_hidden":false,"value_hidden":false,"family_unclear":false,"comment_unclear":false,"comment":"","family":""}},"vehicle":{"35":[{"brand_info":"1498 куб. см.","sum_rent_comment":"","year":"2007","brand_info_hidden":false,"brand_info_unclear":false,"year_unclear":false,"sum_rent":"","sum":"","brand":"Daewoo Lanos","sum_comment":"","brand_unclear":false,"brand_hidden":false},{"brand_info":"1598 куб. см.","sum_rent_comment":"","brand":"Opel Astra","sum_comment":"","brand_unclear":true,"year":"2007","brand_hidden":false,"brand_info_unclear":false,"sum":"","sum_rent":""}]},"id":"vulyk_65_192","declaration":{"additional_info_text":"","notfull_lostpages":"","date":"2015-03-26T00:00:00","notfull":"","additional_info":"","url":"http://static.declarations.com.ua/declarations/chosen_ones/mega_batch/oleshchuk_tetiana_lvivna.pdf"},"liabilities":{"54":{"sum_foreign_comment":"","sum":"","sum_comment":"","sum_comment_unclear":false,"sum_hidden":false,"sum_comment_hidden":false,"sum_foreign":""},"55":{"sum_foreign_comment":"","sum":"","sum_comment":"","sum_foreign":""},"56":{"sum_foreign_comment":"","sum":"","sum_comment":"","sum_unclear":false,"sum_foreign":""},"57":{"sum_foreign_comment":"","sum":"22833","sum_comment":"","sum_comment_unclear":false,"sum_unclear":false,"sum_foreign":""},"58":{"sum_foreign_comment":"","sum":"2667","sum_comment":"","sum_comment_unclear":false,"sum_unclear":false,"sum_foreign":""},"59":{"sum_foreign_comment":"","sum":"","sum_comment":"","sum_foreign":""},"60":{"sum_foreign_comment":"","sum":"","sum_comment":"","sum_comment_unclear":false,"sum_foreign":""},"61":{"sum_foreign_comment":"","sum":"","sum_comment":"","sum_foreign":""},"62":{"sum_foreign_comment":"","sum":"","sum_comment":"","sum_foreign":""},"63":{"sum_foreign_comment":"","sum":"","sum_comment":"","sum_foreign":""},"64":{"sum_foreign_comment":"","sum":"","sum_comment":"","sum_unclear":false,"sum_foreign":""}},"ft_src":"22833\n2667\nсуддя апеляційного суду миколаївської області\nМиколаївська область\nЗагальний апеляційний суд\nТетяна\nЛьвівна\nОлещук\nОлещук Тетяна Львівна\nОлещук Тетяна Львівна\nТетяна Львівна Олещук\nТетяна Олещук\nОлещук Тетяна Львівна\n1498 куб. см.\nDaewoo Lanos\n2007\nOpel Astra\n1598 куб. см.\n2007\n65.9\n41.2\n2014\n246155\n246155\n1498 куб. см.\nDaewoo Lanos\n2007\n1598 куб. см.\n2007\nOpel Astra\n65.9\n41.2\nОлещук Тетяна Львівна\nТетяна Львівна Олещук\nТетяна Олещук\nОлещук Тетяна Львівна\nОлещук Тетяна Львівна\nТетяна\nОлещук\nЗагальний апеляційний суд\nМиколаївська область\nсуддя апеляційного суду миколаївської області\nЛьвівна\n22833\n2667\n246155\n246155\n2014\n2667\n22833\nЛьвівна\nОлещук\nТетяна\nОлещук Тетяна Львівна\nТетяна Львівна Олещук\nТетяна Олещук\nОлещук Тетяна Львівна\nМиколаївська область\nЗагальний апеляційний суд\nсуддя апеляційного суду миколаївської області\nОлещук Тетяна Львівна\n2007\nDaewoo Lanos\n1498 куб. см.\n2007\n1598 куб. см.\nOpel Astra\n246155\n246155\n65.9\n41.2\n2014","general":{"name_hidden":false,"name":"Тетяна","last_name_hidden":false,"inn":"","inn_unclear":false,"patronymic":"Львівна","inn_hidden":true,"family_raw":"","last_name":"Олещук","post":{"post_unclear":false,"region_unclear":false,"post":"суддя апеляційного суду миколаївської області","office":"Загальний апеляційний суд","region":"Миколаївська область","post_hidden":false,"office_hidden":false,"office_unclear":false,"region_hidden":false},"last_name_unclear":false,"full_name":"Олещук Тетяна Львівна","addresses":[{"place_district":"","place_address_hidden":true,"place_city":"","place_city_type_hidden":true,"place_district_hidden":true,"place_city_type":"","place_city_hidden":true,"place_address_unclear":false,"place_address":"","place_hidden":true,"place":""}],"patronymic_hidden":false,"full_name_suggest":{"output":"Олещук Тетяна Львівна","input":["Олещук Тетяна Львівна","Тетяна Львівна Олещук","Тетяна Олещук"]},"name_unclear":false},"source":"VULYK","estate":{"25":[{"space_unclear":false,"costs":"","costs_comment":"","address_hidden":false,"region_hidden":true,"space_comment":"","space_hidden":false,"space":"65.9","address":"","costs_rent_comment_unclear":false,"region":"","address_unclear":false,"costs_rent_comment":"","space_comment_unclear":false,"space_units":"м²","space_units_hidden":false,"costs_rent":""},{"space_hidden":false,"costs":"","costs_comment":"","address_hidden":false,"region_hidden":false,"space_comment":"","space_unclear":false,"space":"41.2","address":"","region":"","costs_rent_comment":"","space_units":"","costs_rent":""}],"26":[{"costs":"","costs_comment":"","address_hidden":false,"region_hidden":true,"space_comment":"","space":"","address":"","region":"","address_unclear":false,"costs_rent_comment":"","space_units":"м²","space_units_hidden":false,"costs_rent":""}]},"intro":{"declaration_year":"2014","isnotdeclaration":"","declaration_year_hidden":false}}