{"income":{"5":{"value":"244557.49","family_comment":"","value_unclear":false,"comment_hidden":false,"family_hidden":false,"value_hidden":false,"family_unclear":false,"family_comment_hidden":false,"comment":"","family":""},"6":{"value":"218603.49","family_comment":"","value_unclear":false,"family_hidden":false,"family_unclear":false,"family":"","comment":""},"7":{"source_name_unclear":false,"value":"25954","family_hidden":false,"family_comment":"","source_name":"1. Святошинський районний суд міста Києва 2. м. Київ Університет 'Україна'","family":"","comment":"","source_name_hidden":false},"8":{"family_comment":"","value":"","family":"","comment":""},"9":{"value":"","value_unclear":false,"family_hidden":false,"family_comment":"","family":"","comment":""},"10":{"value":"","value_unclear":false,"family_hidden":false,"value_hidden":false,"family_comment":"","comment_unclear":false,"comment":"","family":""},"11":{"family_comment":"","value":"","family":"","comment":""},"12":{"family_comment":"","value":"","family":"","comment":""},"13":{"family_comment":"","value":"","family":"","comment":""},"14":{"family_comment":"","value":"","family":"","comment":""},"15":{"family_comment":"","value":"","family_hidden":false,"comment":"","family":""},"16":{"value":"","value_unclear":false,"family_hidden":false,"family_comment":"","family":"","comment":""},"17":{"family_comment":"","value":"","family_hidden":false,"comment":"","family":""},"18":{"family_comment":"","value":"","value_unclear":false,"family":"","comment":""},"19":{"family_comment":"","value":"","family":"","comment":""},"20":{"value":"","family_comment":"","value_unclear":false,"family_hidden":false,"family_unclear":false,"comment_unclear":false,"comment":"","family":""}},"vehicle":{"35":[{"brand_info":"2100 об'єм двигуна","sum_rent_comment":"","brand_info_unclear":false,"year":"1961","sum_rent_unclear":false,"brand_info_hidden":false,"sum_rent_comment_unclear":false,"sum_hidden":false,"sum_rent":"","sum":"","brand":"ГАЗ 21","sum_comment":"22. 07. 2008","brand_unclear":false,"brand_hidden":false}]},"id":"vulyk_72_185","declaration":{"additional_info_text":"","notfull_lostpages":"","date":"2015-03-27T00:00:00","notfull":"","additional_info":"","url":"http://static.declarations.com.ua/declarations/chosen_ones/epic_batch/ul’yanovska_oksana_vasylivna.pdf"},"liabilities":{"54":{"sum_foreign_comment":"","sum":"","sum_comment":"","sum_comment_hidden":false,"sum_unclear":false,"sum_foreign":""},"55":{"sum_foreign_comment":"","sum":"","sum_comment":"","sum_foreign":""},"56":{"sum_foreign_comment":"","sum":"","sum_hidden":false,"sum_comment":"","sum_foreign":""},"57":{"sum_foreign_comment":"","sum":"","sum_comment":"","sum_comment_unclear":false,"sum_hidden":false,"sum_comment_hidden":false,"sum_unclear":false,"sum_foreign":""},"58":{"sum_foreign_comment":"","sum":"","sum_comment":"","sum_comment_unclear":false,"sum_hidden":false,"sum_comment_hidden":false,"sum_unclear":false,"sum_foreign":""},"59":{"sum_foreign_comment":"","sum_foreign_hidden":false,"sum_comment":"","sum_foreign_unclear":false,"sum_comment_hidden":false,"sum":"","sum_foreign":""},"60":{"sum_foreign_comment":"","sum_foreign_hidden":false,"sum_comment":"","sum_hidden":false,"sum":"","sum_foreign":""},"61":{"sum_foreign_comment":"","sum_foreign_hidden":false,"sum_comment":"","sum_hidden":false,"sum":"","sum_foreign":""},"62":{"sum_foreign_comment":"","sum_foreign_hidden":false,"sum_comment":"","sum_hidden":false,"sum":"","sum_foreign":""},"63":{"sum_foreign_comment":"","sum_foreign_hidden":false,"sum_comment":"","sum_comment_unclear":false,"sum_hidden":false,"sum_comment_hidden":false,"sum_unclear":false,"sum":"","sum_foreign":""},"64":{"sum_foreign_comment":"","sum_foreign_hidden":false,"sum_comment":"","sum_hidden":false,"sum":"","sum_foreign":""}},"ft_src":"суддя святошинського районного суду міста києва\nм. Київ\nЗагальний місцевий суд\nОксана\nЧервінко Софія Костянтинівна\nДитина\nВасилівна\nУл'яновська\nУл'яновська Оксана Василівна\nУл'яновська Оксана Василівна\nОксана Василівна Ул'яновська\nОксана Ул'яновська\nУл'яновська Оксана Василівна\n244557.49\n25954\n1. Святошинський районний суд міста Києва 2. м. Київ Університет 'Україна'\n218603.49\n1961\nГАЗ 21\n22. 07. 2008\n2100 об'єм двигуна\n22. 07. 2008\n2100 об'єм двигуна\nГАЗ 21\n1961\n2014\n218603.49\n1. Святошинський районний суд міста Києва 2. м. Київ Університет 'Україна'\n25954\n244557.49\n2100 об'єм двигуна\nГАЗ 21\n22. 07. 2008\n1961\n25954\n1. Святошинський районний суд міста Києва 2. м. Київ Університет 'Україна'\n218603.49\n244557.49\nДитина\nЧервінко Софія Костянтинівна\nУл'яновська Оксана Василівна\nОксана Василівна Ул'яновська\nОксана Ул'яновська\nУл'яновська Оксана Василівна\nОксана\nУл'яновська Оксана Василівна\nУл'яновська\nм. Київ\nЗагальний місцевий суд\nсуддя святошинського районного суду міста києва\nВасилівна\n2014\nЧервінко Софія Костянтинівна\nДитина\nВасилівна\nУл'яновська\nУл'яновська Оксана Василівна\nОксана Василівна Ул'яновська\nОксана Ул'яновська\nУл'яновська Оксана Василівна\nм. Київ\nЗагальний місцевий суд\nсуддя святошинського районного суду міста києва\nУл'яновська Оксана Василівна\nОксана\n2014","general":{"inn":"","name":"Оксана","patronymic_unclear":false,"family":[{"inn":"","inn_hidden":true,"relations_unclear":false,"relations_hidden":false,"relations_other":"","relations":"Дитина","name_hidden":false,"inn_unclear":false,"family_name":"Червінко Софія Костянтинівна","name_unclear":false}],"patronymic":"Василівна","inn_hidden":true,"family_raw":"","inn_unclear":false,"post":{"post_unclear":false,"region_unclear":false,"post":"суддя святошинського районного суду міста києва","candidate":"","office_hidden":false,"region":"м. Київ","post_hidden":false,"office":"Загальний місцевий суд","office_unclear":false,"region_hidden":false},"last_name_unclear":false,"full_name":"Ул'яновська Оксана Василівна","addresses":[{"place_city_type_hidden":true,"place_district_hidden":true,"place_city_type":"","place_city_hidden":true,"place_address_unclear":false,"place_address":"","place":"","place_district":"","place_unclear":false,"place_city":"","place_city_unclear":false,"place_hidden":true,"place_address_hidden":true,"place_district_unclear":false}],"last_name":"Ул'яновська","patronymic_hidden":true,"full_name_suggest":{"output":"Ул'яновська Оксана Василівна","input":["Ул'яновська Оксана Василівна","Оксана Василівна Ул'яновська","Оксана Ул'яновська"]},"name_unclear":false},"source":"VULYK","intro":{"declaration_year":"2014","isnotdeclaration":"","declaration_year_unclear":false}}