{"id":"vulyk_61_59","ft_src":"смт. Любашівка, вул. Гайдара. 32\n333\nОдеська область\n66\nОдеська область\nсмт. Любашівка, вул. Гайдара, 32\n666\nОдеська область\nсмт. Любашівка, вул. Гайдара, 32\nсмт. Любашівка, вул. Гайдара, 32\n33\nОдеська область\n2014\n232327\n12930\n232327\n12930\n333\nОдеська область\nсмт. Любашівка, вул. Гайдара. 32\nОдеська область\nсмт. Любашівка, вул. Гайдара, 32\n666\n33\nОдеська область\nсмт. Любашівка, вул. Гайдара, 32\n66\nсмт. Любашівка, вул. Гайдара, 32\nОдеська область\nПодружжя\nВужиловська Ірина Петрівна, 12. 09. 1988 р. н\n3130113663\nДитина\nВужиловська Лілія Олегівна, 10. 02. 2005 р. н\nДитина\nВужиловський Єгор Олегович, 09. 01. 2013 р. н\nВужиловський Олег Володимирович\nОлег Володимирович Вужиловський\nОлег Вужиловський\nВужиловський Олег Володимирович\nОлег\n2722205136\nВужиловський Олег Володимирович\nВужиловський\nОдеська область\nЗагальний місцевий суд\nголова суду, суддя любашівського районного суду одеської області\nВолодимирович\nСМТ\nЛюбашівка\nвул. Гайдара, 32\nОдеська область\n232327\n12930\n232327\n12930\n2014\n3130113663\nВужиловська Ірина Петрівна, 12. 09. 1988 р. н\nПодружжя\nВужиловська Лілія Олегівна, 10. 02. 2005 р. н\nДитина\nВужиловський Єгор Олегович, 09. 01. 2013 р. н\nДитина\n2722205136\nВолодимирович\nВужиловський\nВужиловський Олег Володимирович\nОлег Володимирович Вужиловський\nОлег Вужиловський\nВужиловський Олег Володимирович\nОдеська область\nЛюбашівка\nСМТ\nвул. Гайдара, 32\nОдеська область\nголова суду, суддя любашівського районного суду одеської області\nЗагальний місцевий суд\nВужиловський Олег Володимирович\nОлег","estate":{"23":[{"address":"смт. Любашівка, вул. Гайдара. 32","space_units":"м²","costs_comment":"","space_unclear":false,"region_hidden":false,"space_units_unclear":false,"space_comment":"","address_hidden":false,"costs":"","address_unclear":false,"space_comment_unclear":false,"costs_rent_comment":"","space":"333","region_unclear":false,"region":"Одеська область","costs_rent":""}],"24":[{"address":"смт. Любашівка, вул. Гайдара, 32","space_units":"м²","space_hidden":false,"space_unclear":false,"region_hidden":false,"costs_rent_comment":"","space_comment":"","address_hidden":false,"costs":"","address_unclear":false,"space_comment_unclear":false,"costs_comment":"","space":"33","region_unclear":false,"region":"Одеська область","costs_rent":""}],"29":[{"costs_property_comment":"","address":"смт. Любашівка, вул. Гайдара, 32","space_units":"м²","space_hidden":false,"space_unclear":false,"region_hidden":false,"costs_property":"","space_comment":"","address_hidden":false,"space_comment_hidden":false,"space_units_unclear":false,"address_unclear":false,"costs_rent_comment":"","space":"666","region":"Одеська область","space_units_hidden":false,"costs_rent":""}],"30":[{"costs_property_comment":"","address":"смт. Любашівка, вул. Гайдара, 32","space_units":"м²","space_hidden":false,"space_comment":"","region_hidden":false,"costs_property":"","region":"Одеська область","space_comment_unclear":false,"space_comment_hidden":false,"address_unclear":false,"address_hidden":false,"costs_rent_comment":"","space":"66","space_units_hidden":false,"costs_rent":""}]},"source":"VULYK","income":{"5":{"family_comment":"","comment":"","family":"12930","value_unclear":false,"family_unclear":false,"comment_unclear":false,"value":"232327","family_comment_unclear":false},"6":{"family_comment":"","family":"","comment":"","value_unclear":false,"family_unclear":false,"value":"232327"},"7":{"source_name_hidden":false,"family_comment":"","comment":"","family":"","value_unclear":false,"source_name_unclear":false,"value":"","source_name":""},"8":{"family_comment":"","value":"","family":"","comment":""},"9":{"family_comment":"","value":"","family":"","comment":""},"10":{"family_comment":"","value":"","family":"","comment":"","value_unclear":false},"11":{"family":"","family_comment":"","comment":"","value_hidden":false,"value_unclear":false,"value":""},"12":{"family":"","family_comment":"","value":"","comment":"","value_hidden":false},"13":{"family_comment":"","value":"","family":"","comment":""},"14":{"family_comment":"","value":"","family":"","comment":""},"15":{"family_comment":"","value":"","family":"","comment":""},"16":{"family_comment":"","value":"","family":"","comment":""},"17":{"family_comment":"","value":"","family":"","comment":""},"18":{"family_comment":"","value":"","family":"","comment":""},"19":{"family_comment":"","value":"","family_unclear":false,"family":"","comment":""},"20":{"family_comment":"","value":"","family_unclear":false,"family":"12930","comment":""}},"general":{"family":[{"inn":"3130113663","family_name":"Вужиловська Ірина Петрівна, 12. 09. 1988 р. н","relations_other":"","relations_hidden":false,"relations_unclear":false,"name_unclear":true,"inn_hidden":false,"name_hidden":false,"relations":"Подружжя"},{"inn":"","family_name":"Вужиловська Лілія Олегівна, 10. 02. 2005 р. н","relations_other":"","name_unclear":true,"inn_hidden":false,"name_hidden":false,"relations":"Дитина"},{"inn":"","family_name":"Вужиловський Єгор Олегович, 09. 01. 2013 р. н","relations_other":"","name_unclear":true,"inn_hidden":false,"name_hidden":false,"relations":"Дитина"}],"family_raw":"","name":"Олег","full_name_suggest":{"input":["Вужиловський Олег Володимирович","Олег Володимирович Вужиловський","Олег Вужиловський"],"output":"Вужиловський Олег Володимирович"},"name_unclear":false,"patronymic":"Володимирович","inn_hidden":false,"patronymic_unclear":false,"patronymic_hidden":false,"inn":"2722205136","inn_unclear":false,"last_name":"Вужиловський","full_name":"Вужиловський Олег Володимирович","post":{"post_hidden":false,"office":"Загальний місцевий суд","post_unclear":false,"post":"голова суду, суддя любашівського районного суду одеської області","region_hidden":false,"region":"Одеська область","region_unclear":false,"office_hidden":false},"addresses":[{"place_city_type_hidden":false,"place_district_hidden":false,"place_address_unclear":false,"place":"Одеська область","place_city":"Любашівка","place_city_type":"СМТ","place_city_hidden":false,"place_district":"","place_district_unclear":false,"place_address":"вул. Гайдара, 32","place_address_hidden":false,"place_hidden":false}],"last_name_unclear":false},"liabilities":{"54":{"sum_comment_unclear":false,"sum_comment":"","sum":"","sum_foreign_comment":"","sum_foreign":"","sum_unclear":false},"55":{"sum_comment":"","sum_foreign_comment":"","sum_foreign":"","sum":""},"56":{"sum_comment":"","sum_foreign_comment":"","sum_foreign":"","sum_unclear":false,"sum":""},"57":{"sum_comment":"","sum":"","sum_foreign_comment":"","sum_foreign":"","sum_unclear":false,"sum_comment_hidden":false},"58":{"sum_comment":"","sum_foreign_comment":"","sum_foreign":"","sum_unclear":false,"sum":""},"59":{"sum_comment":"","sum_foreign_comment":"","sum_foreign":"","sum":""},"60":{"sum_comment":"","sum_hidden":false,"sum":"","sum_foreign_comment":"","sum_foreign":"","sum_foreign_hidden":false},"61":{"sum_comment":"","sum_foreign_comment":"","sum_foreign":"","sum":""},"62":{"sum_comment":"","sum_foreign_comment":"","sum_foreign":"","sum_unclear":false,"sum":""},"63":{"sum_comment":"","sum_hidden":false,"sum":"","sum_foreign_comment":"","sum_foreign":"","sum_unclear":false},"64":{"sum_comment":"","sum_foreign_comment":"","sum_foreign":"","sum_hidden":false,"sum":""}},"declaration":{"notfull_lostpages":"","additional_info_text":"","additional_info":"","date":"2015-03-13T00:00:00","notfull":"","url":"http://static.declarations.com.ua/declarations/chosen_ones/mega_batch/vuzhylovskyi_oleh_volodymyrovych.pdf"},"intro":{"declaration_year_hidden":false,"isnotdeclaration":"","declaration_year":"2014"}}