{"income":{"5":{"value":"239114","value_unclear":false,"value_hidden":false,"family_comment":"","family":"336777","comment":""},"6":{"value":"239114","family_comment":"","value_unclear":false,"family_unclear":false,"family":"32973","comment":""},"7":{"source_name_unclear":false,"value":"","family_hidden":false,"family_comment":"","source_name":"Доцент кафедре систем захисту інформації Навчально-наукового інституту захистц інформації Державного угіверситету телекомунікацій","family":"65404","comment":""},"8":{"family_comment":"","value":"","family":"","comment":""},"9":{"family_comment":"","value":"","family":"","comment":""},"10":{"family_comment":"","value":"","family":"","comment":""},"11":{"family_comment":"","value":"","family":"","comment":""},"12":{"family_comment":"","value":"","family":"","comment":""},"13":{"family_comment":"","value":"","family":"","comment":""},"14":{"family_comment":"","value":"","family":"","comment":""},"15":{"family_comment":"","value":"","family":"38400","comment":""},"16":{"family_comment":"","value":"","comment_unclear":false,"family":"200000","comment":""},"17":{"family_comment":"","family_unclear":false,"value":"","family":"","comment":""},"18":{"family_comment":"","value":"","family":"","comment":""},"19":{"value":"","family_hidden":false,"value_hidden":false,"family_comment":"","family":"","comment":""},"20":{"family_comment":"","value":"","comment_unclear":false,"family":"","comment":""}},"vehicle":{"40":[{"brand_info":"2494 куб. см.","sum_rent_comment":"","brand":"Toyota Rav 4","sum_comment":"","brand_unclear":false,"year":"2014","brand_info_unclear":false,"year_unclear":false,"sum":"","sum_rent":""}]},"id":"vulyk_67_169","declaration":{"additional_info_text":"","notfull_lostpages":"","date":"2015-03-31T00:00:00","notfull":"","additional_info":"","url":"http://static.declarations.com.ua/declarations/chosen_ones/mega_batch/lazarenko_vladlena_volodymyrivna.pdf"},"liabilities":{"54":{"sum_foreign_comment":"","sum_unclear":false,"sum":"","sum_comment":"","sum_comment_unclear":false,"sum_hidden":false,"sum_foreign_hidden":false,"sum_foreign":""},"55":{"sum_foreign_comment":"","sum":"","sum_comment":"","sum_foreign":""},"56":{"sum_foreign_comment":"","sum_unclear":false,"sum":"","sum_comment":"","sum_hidden":false,"sum_foreign_hidden":false,"sum_foreign":""},"57":{"sum_foreign_comment":"","sum_unclear":false,"sum":"","sum_comment":"","sum_comment_unclear":false,"sum_hidden":false,"sum_comment_hidden":false,"sum_foreign_hidden":false,"sum_foreign":""},"58":{"sum_foreign_comment":"","sum_unclear":false,"sum":"","sum_comment":"","sum_comment_unclear":false,"sum_hidden":false,"sum_comment_hidden":false,"sum_foreign_hidden":false,"sum_foreign":""},"59":{"sum_foreign_comment":"","sum":"","sum_foreign":"","sum_comment":"","sum_hidden":false},"60":{"sum_foreign_comment":"","sum":"","sum_comment":"","sum_foreign":""},"61":{"sum_foreign_comment":"","sum":"","sum_comment":"","sum_hidden":false,"sum_foreign_hidden":false,"sum_foreign":""},"62":{"sum_foreign_comment":"","sum":"","sum_foreign":"","sum_comment":"","sum_hidden":false},"63":{"sum_foreign_comment":"","sum":"57000","sum_comment":"","sum_comment_unclear":false,"sum_hidden":false,"sum_unclear":false,"sum_foreign":""},"64":{"sum_foreign_comment":"","sum":"","sum_comment":"","sum_hidden":false,"sum_unclear":false,"sum_foreign":""}},"ft_src":"2494 куб. см.\nToyota Rav 4\n2014\n43.76\n68.7\n2014\n32973\n239114\n38400\nДоцент кафедре систем захисту інформації Навчально-наукового інституту захистц інформації Державного угіверситету телекомунікацій\n65404\n336777\n239114\n200000\n2494 куб. см.\n2014\nToyota Rav 4\n43.76\n68.7\nЗагальний місцевий суд\nсуддя солом'янського районного суду міста києва\nм. Київ\nПодружжя\nЛазаренко С. В., 28. 06. 1971\nДитина\nЛазаренко А. С., 14. 10. 2005\nЛазаренко Владлена Володимирівна\nВладлена Володимирівна Лазаренко\nВладлена Лазаренко\nЛазаренко Владлена Володимирівна\nЛазаренко Владлена Володимирівна\nВладлена\nЛазаренко\nВолодимирівна\n57000\nДоцент кафедре систем захисту інформації Навчально-наукового інституту захистц інформації Державного угіверситету телекомунікацій\n65404\n32973\n239114\n38400\n239114\n336777\n200000\n2014\n57000\nПодружжя\nЛазаренко С. В., 28. 06. 1971\nДитина\nЛазаренко А. С., 14. 10. 2005\nВолодимирівна\nЛазаренко\nВладлена\nЛазаренко Владлена Володимирівна\nВладлена Володимирівна Лазаренко\nВладлена Лазаренко\nЛазаренко Владлена Володимирівна\nм. Київ\nсуддя солом'янського районного суду міста києва\nЗагальний місцевий суд\nЛазаренко Владлена Володимирівна","general":{"inn":"","name":"Владлена","patronymic_unclear":false,"last_name_hidden":false,"last_name":"Лазаренко","family":[{"inn":"","inn_hidden":true,"relations_unclear":false,"relations_hidden":false,"relations_other":"","relations":"Подружжя","name_hidden":false,"inn_unclear":false,"family_name":"Лазаренко С. В., 28. 06. 1971","name_unclear":false},{"inn":"","inn_hidden":true,"relations_unclear":false,"relations_hidden":false,"relations_other":"","relations":"Дитина","name_hidden":false,"inn_unclear":false,"family_name":"Лазаренко А. С., 14. 10. 2005","name_unclear":false}],"inn_hidden":true,"family_raw":"","inn_unclear":false,"post":{"post_unclear":false,"post":"суддя солом'янського районного суду міста києва","office_hidden":false,"region":"м. Київ","post_hidden":false,"office":"Загальний місцевий суд","office_unclear":false,"region_hidden":false},"full_name_suggest":{"output":"Лазаренко Владлена Володимирівна","input":["Лазаренко Владлена Володимирівна","Владлена Володимирівна Лазаренко","Владлена Лазаренко"]},"full_name":"Лазаренко Владлена Володимирівна","addresses":[{"place_city_type_hidden":true,"place_district_hidden":true,"place_city_type":"","place_address_hidden":true,"place_address_unclear":false,"place_address":"","place":"","place_district":"","place_unclear":false,"place_hidden":true,"place_city_unclear":false,"place_city_hidden":true,"place_city":"","place_district_unclear":false}],"patronymic":"Володимирівна","last_name_unclear":false,"name_unclear":false},"source":"VULYK","estate":{"25":[{"space_unclear":false,"costs":"","costs_comment":"","costs_hidden":false,"address_hidden":true,"region_hidden":true,"space_comment":"","space":"68.7","address":"","region":"","address_unclear":false,"space_units_unclear":false,"space_comment_unclear":false,"space_units":"м²","costs_rent":"","costs_rent_comment":""}],"31":[{"space_unclear":false,"address_hidden":true,"region_hidden":true,"space_comment":"","space_hidden":false,"space":"43.76","address":"","region":"","costs_property":"","costs_rent_comment":"","space_comment_unclear":false,"address_unclear":false,"space_units":"м²","costs_property_comment":"","costs_rent":""}]},"intro":{"declaration_year":"2014","isnotdeclaration":"","declaration_year_hidden":false}}