{"id":"vulyk_109_39","ft_src":"2477 куб. см., 136 к. с., 504.0 см\nMitsubishi L 200\n2008\n2015\n198744.2\n198839.31\n95.11\n2477 куб. см., 136 к. с., 504.0 см\nMitsubishi L 200\n2008\n198744.2\n95.11\n198839.31\nДитина\nВладимиренко Владислав Ігоревич\nВладимиренко Ігор Вячеславович\nІгор Вячеславович Владимиренко\nІгор Владимиренко\nВладимиренко Ігор Вячеславович\nІгор\nВладимиренко Ігор Вячеславович\nВладимиренко\nГосподарський місцевий суд\nДніпропетровська область\nсуддя господарського суду дніпропетровської області\nВячеславович\n2015\nДитина\nВладимиренко Владислав Ігоревич\nІгор\nВячеславович\nВладимиренко\nВладимиренко Ігор Вячеславович\nІгор Вячеславович Владимиренко\nІгор Владимиренко\nВладимиренко Ігор Вячеславович\nДніпропетровська область\nГосподарський місцевий суд\nсуддя господарського суду дніпропетровської області\nВладимиренко Ігор Вячеславович","vehicle":{"35":[{"sum_comment_unclear":false,"brand_info":"2477 куб. см., 136 к. с., 504.0 см","sum_rent_comment":"","brand_unclear":false,"brand_hidden":false,"year":"2008","sum_comment":"","brand_info_hidden":false,"sum_rent":"","brand":"Mitsubishi L 200","year_unclear":false,"brand_info_unclear":false,"sum":""}]},"source":"VULYK","income":{"5":{"family_comment":"","value":"198839.31","family":"","comment":""},"6":{"family_comment":"","value":"198744.2","family":"","comment":""},"7":{"source_name_hidden":false,"family_comment":"","comment":"","family":"","comment_hidden":false,"value":"","source_name":""},"8":{"family_comment":"","family_hidden":false,"value":"","family":"","comment":""},"9":{"family_comment":"","family":"","comment":"","value_unclear":false,"family_unclear":false,"value":""},"10":{"family_comment":"","value":"","family":"","comment":""},"11":{"family_comment":"","value":"","family":"","comment":""},"12":{"family_comment":"","value":"","family":"","comment":""},"13":{"family_comment":"","value":"","family":"","comment":""},"14":{"family_comment":"","value":"","family":"","comment":""},"15":{"family_comment":"","value":"","family":"","comment":""},"16":{"family_comment":"","value":"","family":"","comment":""},"17":{"family_comment":"","value":"","family":"","comment":""},"18":{"family_comment":"","value":"","family":"","comment":""},"19":{"family_comment":"","value":"","family":"","comment":""},"20":{"family_comment":"","family":"","comment":"","value_unclear":false,"family_hidden":false,"value":"95.11"}},"general":{"family_raw":"","name":"Ігор","full_name_suggest":{"input":["Владимиренко Ігор Вячеславович","Ігор Вячеславович Владимиренко","Ігор Владимиренко"],"output":"Владимиренко Ігор Вячеславович"},"patronymic":"Вячеславович","inn_hidden":true,"inn":"","inn_unclear":false,"last_name":"Владимиренко","full_name":"Владимиренко Ігор Вячеславович","family":[{"inn":"","family_name":"Владимиренко Владислав Ігоревич","relations_hidden":false,"name_unclear":false,"relations":"Дитина","inn_hidden":true,"name_hidden":false,"relations_other":""}],"post":{"office":"Господарський місцевий суд","post":"суддя господарського суду дніпропетровської області","office_unclear":false,"region_hidden":false,"region":"Дніпропетровська область","office_hidden":false,"region_unclear":false},"name_hidden":false},"liabilities":{"54":{"sum_comment":"","sum_hidden":false,"sum":"","sum_foreign_comment":"","sum_foreign":"","sum_unclear":false,"sum_comment_hidden":false},"55":{"sum_comment":"","sum_comment_unclear":false,"sum_foreign_comment":"","sum":"","sum_foreign":""},"56":{"sum_comment":"","sum_foreign_comment":"","sum_foreign":"","sum":""},"57":{"sum_comment":"","sum_foreign_comment":"","sum_foreign":"","sum":"","sum_comment_hidden":false},"58":{"sum_comment":"","sum_foreign_comment":"","sum_foreign":"","sum":"","sum_comment_hidden":false},"59":{"sum_comment":"","sum_foreign_comment":"","sum_foreign":"","sum":""},"60":{"sum_comment":"","sum_foreign_comment":"","sum_foreign":"","sum":""},"61":{"sum_comment":"","sum_foreign_comment":"","sum_foreign":"","sum":""},"62":{"sum_comment":"","sum_foreign_comment":"","sum_foreign":"","sum":""},"63":{"sum_comment":"","sum_foreign_comment":"","sum_foreign":"","sum":""},"64":{"sum_comment":"","sum_foreign_comment":"","sum_foreign":"","sum":""}},"declaration":{"notfull_lostpages":"","additional_info_text":"","additional_info":"","date":"2016-03-29T00:00:00","notfull":"","url":"http://static.declarations.com.ua/declarations/chosen_ones/judges_batch/2496_vladymyrenko_ihor_viacheslavovych_2015.pdf"},"intro":{"isnotdeclaration":"","declaration_year":"2015"}}