{"income":{"5":{"value":"221228","family_comment":"","value_unclear":false,"family_hidden":false,"family_unclear":false,"family":"233463","comment":""},"6":{"value":"217695","family_comment":"","value_unclear":false,"family_hidden":false,"family_unclear":false,"family":"216766","comment":""},"7":{"family_comment":"","value":"","source_name":"","family":"","comment":""},"8":{"family_comment":"","value":"","family":"","comment":""},"9":{"family_comment":"","value":"","family":"","comment":""},"10":{"family_comment":"","value":"","value_unclear":false,"family":"","comment":""},"11":{"family_comment":"","value":"","family":"","comment":""},"12":{"family_comment":"","value":"","family":"","comment":""},"13":{"family_comment":"","value":"","family":"","comment":""},"14":{"family_comment":"","value":"","value_unclear":false,"family":"","comment":""},"15":{"family_comment":"","value":"3530","family_hidden":false,"comment":"","family":""},"16":{"family_comment":"","value":"","family":"","comment":"","family_comment_unclear":false},"17":{"family_comment":"","value":"","family_hidden":false,"comment":"","family":""},"18":{"family_comment":"","value":"","family":"","comment":""},"19":{"family_comment":"","value":"","family":"","comment":""},"20":{"value":"","family":"16697","value_unclear":false,"family_hidden":false,"value_hidden":false,"family_comment":"","comment_unclear":false,"comment":"","family_comment_unclear":false}},"vehicle":{"35":[{"year_hidden":false,"brand_info":"1998 м куб","sum_rent_comment":"","year":"2011","brand_info_hidden":false,"brand_info_unclear":false,"year_unclear":false,"sum_rent":"","sum":"","brand":"SsangYong Korando","sum_comment":"","brand_unclear":false,"brand_hidden":false}],"40":[{"year_hidden":false,"brand_info":"1798 куб. см.","sum_rent_comment":"","year":"2005","brand_info_hidden":false,"brand_info_unclear":false,"sum_rent":"","sum":"","brand":"Hyundai Matrix","sum_comment":"","brand_unclear":false,"brand_hidden":false}]},"id":"vulyk_39_136","banks":{"45":[{"sum_foreign_comment":"","sum_units":"UAH","sum_comment":"","sum_comment_unclear":false,"sum_foreign_units":"UAH","sum_comment_hidden":false,"sum_unclear":false,"sum":"","sum_foreign":""},{"sum_foreign_comment":"","sum_units":"","sum_comment":"","sum_foreign_units":"","sum":"","sum_unclear":false,"sum_foreign":""},{"sum_foreign_comment":"","sum_units":"","sum_comment":"","sum_foreign_units":"","sum":"","sum_foreign":""}],"46":[{"sum_foreign_comment":"","sum_units":"UAH","sum_comment":"","sum_foreign_units":"UAH","sum":"","sum_foreign":""}],"47":[{"sum_foreign_comment":"","sum_units":"UAH","sum_comment":"","sum_foreign_units":"UAH","sum_comment_hidden":false,"sum":"","sum_foreign":""}],"48":[{"sum_foreign_comment":"","sum_units":"UAH","sum_comment":"","sum_foreign_units":"UAH","sum":"","sum_foreign":""}],"49":[{"sum_foreign_comment":"","sum_units":"UAH","sum_comment":"","sum_hidden":false,"sum_foreign_units":"UAH","sum_comment_hidden":false,"sum":"","sum_foreign":""},{"sum_foreign_comment":"","sum_units":"","sum_comment":"","sum_foreign_units":"","sum":"","sum_foreign":""}],"50":[{"sum_foreign_comment":"","sum_units":"UAH","sum_comment":"","sum_foreign_units":"UAH","sum":"","sum_foreign":""}],"51":[{"sum_foreign_comment":"","sum_units":"UAH","sum_comment":"","sum_foreign_units":"UAH","sum_comment_hidden":false,"sum":"","sum_foreign":""}],"52":[{"sum_foreign_comment":"","sum_units":"UAH","sum_comment":"","sum_foreign_units":"UAH","sum":"","sum_foreign":""}],"53":[{"sum_foreign_comment":"","sum_units":"UAH","sum_comment":"","sum_comment_unclear":false,"sum_foreign_units":"UAH","sum":"","sum_foreign":""}]},"declaration":{"additional_info_text":"","notfull_lostpages":"","date":"2015-03-30T00:00:00","notfull":"","additional_info":"","url":"http://static.declarations.com.ua/declarations/chosen_ones/mega_batch/sop’yanenko_oleksandr_volodymyrovych.pdf"},"liabilities":{"54":{"sum_foreign_comment":"","sum":"7329","sum_comment":"","sum_comment_unclear":false,"sum_comment_hidden":false,"sum_unclear":false,"sum_foreign":""},"55":{"sum_foreign_comment":"","sum":"","sum_comment":"","sum_unclear":false,"sum_foreign":""},"56":{"sum_foreign_comment":"","sum":"","sum_comment":"","sum_foreign":""},"57":{"sum_foreign_comment":"","sum":"","sum_comment":"","sum_comment_unclear":false,"sum_hidden":false,"sum_comment_hidden":false,"sum_foreign":""},"58":{"sum_foreign_comment":"","sum_foreign_hidden":false,"sum_comment":"","sum_hidden":false,"sum_comment_hidden":false,"sum_unclear":false,"sum":"","sum_foreign":""},"59":{"sum_foreign_comment":"","sum":"","sum_comment":"","sum_foreign":""},"60":{"sum_foreign_comment":"","sum_comment_hidden":false,"sum":"","sum_comment":"","sum_foreign":""},"61":{"sum_foreign_comment":"","sum":"","sum_comment":"","sum_foreign":""},"62":{"sum_foreign_comment":"","sum":"","sum_comment":"","sum_unclear":false,"sum_foreign":""},"63":{"sum_foreign_comment":"","sum":"","sum_comment":"","sum_foreign":""},"64":{"sum_foreign_comment":"","sum":"","sum_comment":"","sum_foreign":""}},"ft_src":"7329\nсуддя сумського окружного адміністративного суду\nСумська область\nАдміністративний місцевий суд\nОлександр\nСоп'яненко О. Ю\nПодружжя\nСоп'яненко Є. О\nДитина\nТернових М. І\nІнше\nтеща\nВолодимирович\nСоп'яненко\nСоп'яненко Олександр Володимирович\nСоп'яненко Олександр Володимирович\nОлександр Володимирович Соп'яненко\nОлександр Соп'яненко\nСоп'яненко Олександр Володимирович\n1998 м куб\nSsangYong Korando\n2011\n1798 куб. см.\nHyundai Matrix\n2005\n2014\n1998 м куб\nSsangYong Korando\n2011\n1798 куб. см.\nHyundai Matrix\n2005\n1205\n50.6\n70.65\n64\n70.65\nСоп'яненко Олександр Володимирович\nОлександр Володимирович Соп'яненко\nОлександр Соп'яненко\nСоп'яненко Олександр Володимирович\nСоп'яненко Олександр Володимирович\nПодружжя\nСоп'яненко О. Ю\nДитина\nСоп'яненко Є. О\nІнше\nтеща\nТернових М. І\nОлександр\nВолодимирович\nАдміністративний місцевий суд\nсуддя сумського окружного адміністративного суду\nСумська область\nСоп'яненко\n7329\n216766\n217695\n16697\n3530\n233463\n221228\n2014\n7329\n1205\n50.6\n70.65\n64\n70.65\nСоп'яненко О. Ю\nПодружжя\nСоп'яненко Є. О\nДитина\nтеща\nТернових М. І\nІнше\nОлександр\nВолодимирович\nСоп'яненко\nСоп'яненко Олександр Володимирович\nОлександр Володимирович Соп'яненко\nОлександр Соп'яненко\nСоп'яненко Олександр Володимирович\nСумська область\nАдміністративний місцевий суд\nсуддя сумського окружного адміністративного суду\nСоп'яненко Олександр Володимирович\n216766\n217695\n3530\n233463\n221228\n16697\nSsangYong Korando\n1998 м куб\n2011\n2005\nHyundai Matrix\n1798 куб. см.\n3530\n16697\n221228\n233463\n217695\n216766\n50.6\n70.65\n1205\n64\n70.65\n2014","general":{"inn":"","name":"Олександр","family":[{"inn":"","relations":"Подружжя","relations_other":"","inn_hidden":false,"family_name":"Соп'яненко О. Ю","name_hidden":false,"name_unclear":false},{"inn":"","relations":"Дитина","relations_other":"","inn_hidden":false,"family_name":"Соп'яненко Є. О","name_hidden":false,"name_unclear":false},{"inn":"","relations":"Інше","relations_other":"теща","inn_hidden":false,"family_name":"Тернових М. І","name_hidden":false,"name_unclear":false}],"patronymic":"Володимирович","inn_hidden":false,"family_raw":"","last_name":"Соп'яненко","post":{"post_unclear":false,"post":"суддя сумського окружного адміністративного суду","candidate":"","post_hidden":false,"region":"Сумська область","office":"Адміністративний місцевий суд"},"full_name_suggest":{"output":"Соп'яненко Олександр Володимирович","input":["Соп'яненко Олександр Володимирович","Олександр Володимирович Соп'яненко","Олександр Соп'яненко"]},"full_name":"Соп'яненко Олександр Володимирович","last_name_unclear":false,"name_unclear":false},"source":"VULYK","estate":{"23":[{"space_unclear":false,"costs":"","costs_comment":"","costs_hidden":false,"address_hidden":false,"region_hidden":true,"space_comment":"","space":"1205","address":"","region":"","space_units_unclear":false,"costs_rent_hidden":false,"space_units":"м²","costs_rent":"","costs_rent_comment":""},{"space":"","region":"","costs":"","costs_rent_comment":"","costs_comment":"","region_hidden":false,"space_comment":"","space_units_unclear":false,"space_units":"","costs_rent":"","address":""},{"space":"","region":"","costs":"","costs_rent_comment":"","costs_comment":"","space_comment":"","space_units_unclear":false,"space_units":"","costs_rent":"","address":""},{"costs_rent":"","costs":"","costs_rent_comment":"","costs_comment":"","space_comment":"","space_units":"","space":"","address":""}],"25":[{"space_hidden":false,"costs":"","costs_comment":"","address_hidden":false,"region_hidden":true,"space_comment":"","space_unclear":false,"space":"64","address":"","region":"","costs_rent_comment":"","space_units":"м²","costs_rent":""},{"costs_rent":"","region":"","costs":"","costs_rent_comment":"","costs_comment":"","region_hidden":false,"space_comment":"","space_units":"м²","space":"70.65","address":""}],"31":[{"space_unclear":false,"address_hidden":false,"region_hidden":true,"space_comment":"","space_hidden":false,"space":"50.6","address":"","region":"","costs_property":"","costs_rent_comment":"","space_units":"м²","costs_property_comment":"","costs_rent":""},{"costs_rent":"","region":"","costs_property":"","costs_rent_comment":"","address_hidden":false,"region_hidden":false,"space_comment":"","costs_property_comment":"","space_units":"м²","space":"70.65","address":""}]},"intro":{"declaration_year":"2014"}}