{"income":{"5":{"family_comment":"","value":"296260","family":"","comment":""},"6":{"family_comment":"","value":"281425","family":"","comment":""},"7":{"family_comment":"","value":"","source_name":"","family":"","comment":""},"8":{"family_comment":"","value":"","family":"","comment":""},"9":{"value":"","comment_unclear":false,"family_comment":"","family":"","comment":"","family_comment_unclear":false},"10":{"family_comment":"","value":"","family":"","comment":""},"11":{"family_comment":"","value":"","family":"","comment":""},"12":{"family_comment":"","value":"","family":"","comment":""},"13":{"family_comment":"","value":"","family":"","comment":""},"14":{"family_comment":"","value":"","family":"","comment":""},"15":{"family_comment":"","value":"","family":"","comment":""},"16":{"family_comment":"","value":"","family":"","comment":""},"17":{"family_comment":"","value":"","family":"","comment":""},"18":{"family_comment":"","value":"","family":"","comment":""},"19":{"value":"","family_comment":"","value_unclear":false,"family_unclear":false,"family":"","comment":""},"20":{"value":"14835","family_comment":"","value_unclear":false,"comment_hidden":false,"family_comment_hidden":false,"family_unclear":false,"family_comment_unclear":false,"comment_unclear":false,"comment":"пенсія","family":""}},"vehicle":{"35":[{"brand_info":"1800 куб. см., 118 кВт","sum_rent_comment":"","brand":"Volkswagen Passat B6","sum_comment":"","year":"2008","sum_hidden":false,"brand_info_hidden":false,"brand_info_unclear":false,"year_unclear":false,"sum":"","sum_rent":""}]},"id":"vulyk_106_97","declaration":{"additional_info_text":"","notfull_lostpages":"","date":"2016-03-28T00:00:00","notfull":"","additional_info":"","url":"http://static.declarations.com.ua/declarations/chosen_ones/judges_batch/2236_sovhyra_dmytro_ivanovych.pdf"},"liabilities":{"54":{"sum_foreign_comment":"","sum":"","sum_comment":"","sum_comment_unclear":false,"sum_hidden":false,"sum_comment_hidden":false,"sum_foreign":""},"55":{"sum_foreign_comment":"","sum":"","sum_hidden":false,"sum_comment":"","sum_foreign":""},"56":{"sum_foreign_comment":"","sum":"","sum_comment":"","sum_hidden":false,"sum_comment_hidden":false,"sum_unclear":false,"sum_foreign":""},"57":{"sum_foreign_comment":"","sum":"","sum_comment":"","sum_hidden":false,"sum_comment_hidden":false,"sum_foreign":""},"58":{"sum_foreign_comment":"","sum":"","sum_comment":"","sum_hidden":false,"sum_comment_hidden":false,"sum_foreign":""},"59":{"sum_foreign_comment":"","sum":"","sum_comment":"","sum_foreign":""},"60":{"sum_foreign_comment":"","sum":"","sum_comment":"","sum_hidden":false,"sum_comment_hidden":false,"sum_foreign":""},"61":{"sum_foreign_comment":"","sum":"","sum_comment":"","sum_foreign":""},"62":{"sum_foreign_comment":"","sum":"","sum_comment":"","sum_comment_hidden":false,"sum_unclear":false,"sum_foreign":""},"63":{"sum_foreign_comment":"","sum":"","sum_comment":"","sum_foreign":""},"64":{"sum_foreign_comment":"","sum":"","sum_comment":"","sum_foreign":""}},"ft_src":"суддя вінницького апеляційного адміністративного суду\nВінницька область\nАпеляційний адміністративний суд\nДмитро\nІванович\nСовгира Дмитро Іванович\nСовгира\nСовгира Дмитро Іванович\nДмитро Іванович Совгира\nДмитро Совгира\nСовгира Дмитро Іванович\nVolkswagen Passat B6\n1800 куб. см., 118 кВт\n2008\n750\n46\n21.6\n10.8\n11.8\n349.4\n143.2\n2015\n281425\n296260\nпенсія\n14835\n1800 куб. см., 118 кВт\n2008\nVolkswagen Passat B6\n750\n46\n349.4\n143.2\n21.6\n10.8\n11.8\nСовгира Дмитро Іванович\nДмитро Іванович Совгира\nДмитро Совгира\nСовгира Дмитро Іванович\nСовгира Дмитро Іванович\nДмитро\nСовгира\nВінницька область\nАпеляційний адміністративний суд\nсуддя вінницького апеляційного адміністративного суду\nІванович\n281425\n14835\nпенсія\n296260\n2015\nІванович\nСовгира\nДмитро\nСовгира Дмитро Іванович\nДмитро Іванович Совгира\nДмитро Совгира\nСовгира Дмитро Іванович\nВінницька область\nАпеляційний адміністративний суд\nсуддя вінницького апеляційного адміністративного суду\nСовгира Дмитро Іванович\n2008\nVolkswagen Passat B6\n1800 куб. см., 118 кВт\n14835\nпенсія\n296260\n281425\n750\n46\n349.4\n143.2\n21.6\n10.8\n11.8\n2015","general":{"inn":"","name":"Дмитро","inn_unclear":false,"patronymic":"Іванович","inn_hidden":true,"family_raw":"","last_name":"Совгира","post":{"region_unclear":false,"region":"Вінницька область","post":"суддя вінницького апеляційного адміністративного суду","office":"Апеляційний адміністративний суд","office_unclear":false,"post_hidden":false},"full_name":"Совгира Дмитро Іванович","addresses":[{"place_district":"","place_city_hidden":true,"place_city":"","place_city_type_hidden":true,"place_district_hidden":true,"place_city_type":"","place_address_hidden":true,"place_address":"","place_hidden":true,"place":""}],"full_name_suggest":{"output":"Совгира Дмитро Іванович","input":["Совгира Дмитро Іванович","Дмитро Іванович Совгира","Дмитро Совгира"]},"name_unclear":false},"source":"VULYK","estate":{"23":[{"region_unclear":false,"space_hidden":false,"costs":"","costs_comment":"","address_hidden":true,"region_hidden":true,"space_comment":"","space_unclear":false,"space":"750","address":"","costs_comment_unclear":false,"costs_rent_comment_unclear":false,"region":"","address_unclear":false,"costs_rent_comment":"","space_comment_unclear":false,"space_comment_hidden":false,"space_units":"м²","costs_rent":""},{"space_unclear":false,"costs":"","costs_comment":"","address_hidden":false,"region_hidden":false,"space_comment":"","space":"46","address":"","costs_comment_unclear":false,"region":"","address_unclear":false,"costs_rent_comment":"","space_units":"м²","costs_rent":""}],"24":[{"space_unclear":false,"costs":"","costs_comment":"","address_hidden":true,"region_hidden":true,"space_comment":"","space_hidden":false,"space":"349.4","address":"","region":"","costs_rent_comment":"","space_comment_unclear":false,"space_comment_hidden":false,"space_units":"м²","costs_rent":""},{"costs_rent":"","space_unclear":false,"region":"","costs":"","costs_rent_comment":"","costs_comment":"","space_comment_unclear":false,"space_comment":"","space_units":"м²","space":"143.2","address":""}],"27":[{"space_hidden":false,"costs":"","costs_comment":"","address_hidden":true,"region_hidden":true,"space_comment":"","space":"21.6","address":"","region":"","costs_rent_comment":"","space_units":"м²","costs_rent":""},{"costs_rent":"","region":"","costs":"","costs_rent_comment":"","costs_comment":"","space_comment":"","space_units":"м²","space":"10.8","address":""},{"costs_rent":"","region":"","costs":"","costs_rent_comment":"","costs_comment":"","space_comment":"","space_units":"м²","space":"11.8","address":""}]},"intro":{"declaration_year":"2015","isnotdeclaration":""}}