{"income":{"5":{"value":"420187","family_comment":"","value_unclear":false,"comment_hidden":false,"family_hidden":false,"value_hidden":false,"family_unclear":false,"family_comment_hidden":false,"comment":"","family":"11442"},"6":{"value":"232173","family_comment":"","value_unclear":false,"family_hidden":false,"family_unclear":false,"family":"","comment":""},"7":{"source_name_unclear":false,"value":"","family_hidden":false,"family_comment":"","source_name":"","family":"","comment":"","source_name_hidden":false},"8":{"family_comment":"","value":"","family":"","comment":""},"9":{"value":"","value_unclear":false,"family_hidden":false,"family_comment":"","family":"","comment":""},"10":{"value":"","value_unclear":false,"family_hidden":false,"value_hidden":false,"family_comment":"","comment_unclear":false,"comment":"","family":""},"11":{"family_comment":"","value":"","family":"","comment":""},"12":{"family_comment":"","value":"","family":"","comment":""},"13":{"family_comment":"","value":"","family":"","comment":""},"14":{"family_comment":"","value":"","family":"","comment":""},"15":{"family_comment":"","value":"","family_hidden":false,"comment":"","family":""},"16":{"value":"188014","value_unclear":false,"family_hidden":false,"family_comment":"","family":"","comment":""},"17":{"family_comment":"","value":"","family_hidden":false,"comment":"","family":""},"18":{"family_comment":"","value":"","value_unclear":false,"family":"","comment":""},"19":{"family_comment":"","value":"","family":"","comment":""},"20":{"value":"","family_comment":"","value_unclear":false,"family_hidden":false,"family_unclear":false,"comment_unclear":false,"comment":"","family":"11442"}},"vehicle":{"35":[{"brand_info":"2378 куб. см.","sum_rent_comment":"","brand_info_unclear":false,"year":"2007","sum_rent_unclear":false,"brand_info_hidden":false,"sum_rent_comment_unclear":false,"sum_hidden":false,"sum_rent":"","sum":"186059","brand":"Mitsubishi Outlander","sum_comment":"","brand_unclear":false,"brand_hidden":false}]},"id":"vulyk_72_119","banks":{"51":[{"sum_foreign_comment":"","sum":"56754","sum_comment":"","sum_comment_unclear":false,"sum_hidden":false,"sum_foreign_units":"UAH","sum_foreign_hidden":false,"sum_units":"UAH","sum_comment_hidden":true,"sum_unclear":false,"sum_foreign":""}]},"declaration":{"additional_info_text":"","notfull_lostpages":"","date":"2015-03-30T00:00:00","notfull":"","additional_info":"","url":"http://static.declarations.com.ua/declarations/chosen_ones/epic_batch/murashko_ihor_anatoliiovych.pdf"},"liabilities":{"54":{"sum_foreign_comment":"","sum":"","sum_comment":"","sum_comment_hidden":false,"sum_unclear":false,"sum_foreign":""},"55":{"sum_foreign_comment":"","sum":"","sum_comment":"","sum_foreign":""},"56":{"sum_foreign_comment":"","sum":"","sum_hidden":false,"sum_comment":"","sum_foreign":""},"57":{"sum_foreign_comment":"","sum":"","sum_comment":"","sum_comment_unclear":false,"sum_hidden":false,"sum_comment_hidden":false,"sum_unclear":false,"sum_foreign":""},"58":{"sum_foreign_comment":"","sum":"","sum_comment":"","sum_comment_unclear":false,"sum_hidden":false,"sum_comment_hidden":false,"sum_unclear":false,"sum_foreign":""},"59":{"sum_foreign_comment":"","sum_foreign_hidden":false,"sum_comment":"","sum_foreign_unclear":false,"sum_comment_hidden":false,"sum":"","sum_foreign":""},"60":{"sum_foreign_comment":"","sum_foreign_hidden":false,"sum_comment":"","sum_hidden":false,"sum":"","sum_foreign":""},"61":{"sum_foreign_comment":"","sum_foreign_hidden":false,"sum_comment":"","sum_hidden":false,"sum":"","sum_foreign":""},"62":{"sum_foreign_comment":"","sum_foreign_hidden":false,"sum_comment":"","sum_hidden":false,"sum":"","sum_foreign":""},"63":{"sum_foreign_comment":"","sum_foreign_hidden":false,"sum_comment":"","sum_comment_unclear":false,"sum_hidden":false,"sum_comment_hidden":false,"sum_unclear":false,"sum":"","sum_foreign":""},"64":{"sum_foreign_comment":"","sum_foreign_hidden":false,"sum_comment":"","sum_hidden":false,"sum":"","sum_foreign":""}},"ft_src":"Чернігів\nЧернігівська область\nсуддя деснянського районного суду м. чернігова\nЧернігівська область\nЗагальний місцевий суд\nІгор\nБондар В. М\nдружина без реєстрації шлюбу\nПодружжя\nМурашко М. І\nДитина\nМурашко Є. І\nДитина\nАнатолійович\nМурашко\nМурашко Ігор Анатолійович\nМурашко Ігор Анатолійович\nІгор Анатолійович Мурашко\nІгор Мурашко\nМурашко Ігор Анатолійович\n2378 куб. см.\nMitsubishi Outlander\n2007\n186059\n500\n54787\n1000\n49.3\n56754\n2014\n2378 куб. см.\nMitsubishi Outlander\n2007\n186059\n500\n54787\n1000\n49.3\nПодружжя\nдружина без реєстрації шлюбу\nБондар В. М\nДитина\nМурашко М. І\nДитина\nМурашко Є. І\nМурашко Ігор Анатолійович\nІгор Анатолійович Мурашко\nІгор Мурашко\nМурашко Ігор Анатолійович\nІгор\nМурашко Ігор Анатолійович\nМурашко\nЧернігівська область\nЗагальний місцевий суд\nсуддя деснянського районного суду м. чернігова\nАнатолійович\nЧернігів\nЧернігівська область\n232173\n11442\n420187\n11442\n188014\n56754\n2014\n232173\n11442\n420187\n188014\n11442\nдружина без реєстрації шлюбу\nБондар В. М\nПодружжя\nМурашко М. І\nДитина\nМурашко Є. І\nДитина\nАнатолійович\nМурашко\nМурашко Ігор Анатолійович\nІгор Анатолійович Мурашко\nІгор Мурашко\nМурашко Ігор Анатолійович\nЧернігівська область\nЧернігів\nЧернігівська область\nЗагальний місцевий суд\nсуддя деснянського районного суду м. чернігова\nМурашко Ігор Анатолійович\nІгор\n2007\nMitsubishi Outlander\n186059\n2378 куб. см.\n11442\n420187\n11442\n188014\n232173\n49.3\n500\n54787\n1000\n56754\n2014","general":{"inn":"","name":"Ігор","patronymic_unclear":false,"family":[{"inn":"","inn_hidden":true,"relations_unclear":false,"relations_hidden":false,"relations_other":"дружина без реєстрації шлюбу","relations":"Подружжя","name_hidden":false,"inn_unclear":false,"family_name":"Бондар В. М","name_unclear":false},{"inn":"","inn_hidden":false,"relations_hidden":false,"family_name":"Мурашко М. І","relations_other":"","relations":"Дитина","name_hidden":false,"name_unclear":false},{"inn":"","inn_hidden":false,"relations_hidden":false,"family_name":"Мурашко Є. І","relations_other":"","relations":"Дитина","name_hidden":false,"name_unclear":false}],"patronymic":"Анатолійович","inn_hidden":false,"family_raw":"","inn_unclear":false,"post":{"post_unclear":false,"region_unclear":false,"post":"суддя деснянського районного суду м. чернігова","candidate":"","office_hidden":false,"region":"Чернігівська область","post_hidden":false,"office":"Загальний місцевий суд","office_unclear":false,"region_hidden":false},"last_name_unclear":false,"full_name":"Мурашко Ігор Анатолійович","addresses":[{"place_city_type_hidden":false,"place_district_hidden":false,"place_city_type":"Місто","place_city_hidden":false,"place_address_unclear":false,"place_address":"","place":"Чернігівська область","place_district":"","place_unclear":false,"place_city":"Чернігів","place_city_unclear":false,"place_hidden":false,"place_address_hidden":true,"place_district_unclear":false}],"last_name":"Мурашко","patronymic_hidden":false,"full_name_suggest":{"output":"Мурашко Ігор Анатолійович","input":["Мурашко Ігор Анатолійович","Ігор Анатолійович Мурашко","Ігор Мурашко"]},"name_unclear":false},"source":"VULYK","estate":{"23":[{"space_hidden":false,"costs":"","costs_rent_unclear":false,"costs_comment":"","costs_hidden":false,"address_hidden":false,"region_hidden":true,"space_comment":"","space_unclear":false,"space":"500","address":"","region":"","address_unclear":false,"costs_rent_comment":"","costs_rent_hidden":false,"space_units":"м²","space_units_hidden":false,"costs_rent":""}],"29":[{"space_hidden":false,"costs_property_comment":"","address_hidden":false,"region_hidden":true,"space_comment":"","space_unclear":false,"space":"54787","address":"","region":"","costs_property":"","costs_rent_comment":"","address_unclear":false,"space_units":"м²","space_units_unclear":false,"costs_rent":""},{"costs_rent":"","region":"","costs_property":"","costs_rent_comment":"","address_hidden":false,"region_hidden":false,"space_comment":"","costs_property_comment":"","space_units":"м²","space":"1000","address":""}],"31":[{"space_unclear":false,"address_hidden":false,"region_hidden":true,"space_comment":"","space_units_hidden":false,"space_hidden":false,"space":"49.3","address":"","region":"","address_unclear":false,"costs_rent_comment":"","costs_property":"","space_units":"м²","costs_property_comment":"","costs_rent":""}]},"intro":{"declaration_year":"2014","isnotdeclaration":"","declaration_year_unclear":false}}