{"income":{"5":{"family_comment":"","value":"226321","value_unclear":false,"family":"16010","comment":""},"6":{"value":"226321","value_unclear":false,"family_hidden":false,"family_comment":"","family":"","comment":""},"7":{"source_name_unclear":false,"value":"","family_comment":"","source_name":"","family":"","comment":""},"8":{"family_comment":"","value":"","family":"","comment":""},"9":{"family_comment":"","value":"","family":"","comment":""},"10":{"family_comment":"","value":"","family":"","comment":""},"11":{"family_comment":"","value":"","comment_unclear":false,"family":"","comment":""},"12":{"family_comment":"","value":"","family":"","comment":""},"13":{"family_comment":"","value":"","family":"","comment":""},"14":{"family_comment":"","value":"","family":"","comment":""},"15":{"family_comment":"","value":"","family":"","comment":""},"16":{"family_comment":"","value":"","family":"","comment":""},"17":{"family_comment":"","value":"","family":"","comment":""},"18":{"family_comment":"","value":"","family":"","comment":""},"19":{"family_comment":"","value":"","family":"","comment":""},"20":{"value":"","family_comment":"","value_unclear":false,"family_unclear":false,"comment_unclear":false,"comment":"","family":"16010"}},"vehicle":{"41":[{"brand_info":"4250 куб. см., 115 к. с., 75 см","sum_rent_comment":"","brand":"ГАЗ 3307","sum_comment":"","year":"2004","brand_info_unclear":true,"sum":"","sum_rent":""}]},"id":"vulyk_101_176","banks":{"51":[{"sum_foreign_comment":"","sum_units":"UAH","sum_comment":"","sum_hidden":false,"sum_foreign_units":"UAH","sum_comment_hidden":true,"sum_unclear":false,"sum":"13346","sum_foreign":""}],"53":[{"sum_foreign_comment":"","sum_units":"UAH","sum_comment":"","sum_foreign_units":"UAH","sum_comment_hidden":true,"sum":"40000","sum_foreign":""}]},"declaration":{"additional_info_text":"","notfull_lostpages":"","date":"2016-03-31T00:00:00","notfull":"","additional_info":"","url":"http://static.declarations.com.ua/declarations/chosen_ones/judges_batch/891_misiura_liudmyla_serhiivna_2015.pdf"},"liabilities":{"54":{"sum_foreign_comment":"","sum":"","sum_comment":"","sum_comment_unclear":false,"sum_hidden":false,"sum_comment_hidden":false,"sum_unclear":false,"sum_foreign":""},"55":{"sum_foreign_comment":"","sum":"","sum_comment":"","sum_foreign":""},"56":{"sum_foreign_comment":"","sum":"","sum_comment":"","sum_comment_hidden":false,"sum_unclear":false,"sum_foreign":""},"57":{"sum_foreign_comment":"","sum":"","sum_comment":"","sum_hidden":false,"sum_comment_hidden":false,"sum_unclear":false,"sum_foreign":""},"58":{"sum_foreign_comment":"","sum":"","sum_comment":"","sum_comment_unclear":false,"sum_hidden":false,"sum_comment_hidden":false,"sum_unclear":false,"sum_foreign":""},"59":{"sum_foreign_comment":"","sum":"","sum_comment":"","sum_foreign":""},"60":{"sum_foreign_comment":"","sum":"","sum_comment":"","sum_hidden":false,"sum_comment_hidden":false,"sum_unclear":false,"sum_foreign":""},"61":{"sum_foreign_comment":"","sum":"","sum_comment":"","sum_foreign":""},"62":{"sum_foreign_comment":"","sum":"","sum_comment":"","sum_comment_unclear":false,"sum_foreign":""},"63":{"sum_foreign_comment":"","sum_comment_hidden":false,"sum":"","sum_comment":"","sum_foreign":""},"64":{"sum_foreign_comment":"","sum_comment_hidden":false,"sum":"","sum_comment":"","sum_foreign":""}},"ft_src":"суддя господарського суду запорізької області\nЗапорізька область\nГосподарський місцевий суд\nЛюдмила\nВагіс В. В\nІнше\nособа, з якою спільно проживаю та пов'язана спільним побутом\nСергіївна\nМісюра Людмила Сергіївна\nМісюра\nМісюра Людмила Сергіївна\nЛюдмила Сергіївна Місюра\nЛюдмила Місюра\nМісюра Людмила Сергіївна\n4250 куб. см., 115 к. с., 75 см\n2004\nГАЗ 3307\n40000\n13346\n2015\n4250 куб. см., 115 к. с., 75 см\nГАЗ 3307\n2004\n40000\n13346\n45.7\n68.36\n21\n504\n1223\n1223\n46.1\nМісюра Людмила Сергіївна\nЛюдмила Сергіївна Місюра\nЛюдмила Місюра\nМісюра Людмила Сергіївна\nЛюдмила\nМісюра Людмила Сергіївна\nСергіївна\nсуддя господарського суду запорізької області\nЗапорізька область\nГосподарський місцевий суд\nМісюра\nІнше\nособа, з якою спільно проживаю та пов'язана спільним побутом\nВагіс В. В\n226321\n16010\n226321\n16010\n2015\n1223\n504\n1223\n21\n46.1\n45.7\n68.36\nособа, з якою спільно проживаю та пов'язана спільним побутом\nВагіс В. В\nІнше\nЛюдмила\nСергіївна\nМісюра\nМісюра Людмила Сергіївна\nЛюдмила Сергіївна Місюра\nЛюдмила Місюра\nМісюра Людмила Сергіївна\nсуддя господарського суду запорізької області\nЗапорізька область\nГосподарський місцевий суд\nМісюра Людмила Сергіївна\n226321\n16010\n226321\n16010\n2004\n4250 куб. см., 115 к. с., 75 см\nГАЗ 3307\n16010\n16010\n226321\n226321\n46.1\n504\n1223\n45.7\n21\n68.36\n1223\n13346\n40000\n2015","general":{"inn":"","name":"Людмила","inn_unclear":false,"family":[{"inn":"","relations":"Інше","relations_other":"особа, з якою спільно проживаю та пов'язана спільним побутом","inn_hidden":true,"family_name":"Вагіс В. В","name_hidden":true,"name_unclear":false}],"inn_hidden":true,"family_raw":"","last_name":"Місюра","post":{"region":"Запорізька область","region_unclear":false,"post":"суддя господарського суду запорізької області","office_unclear":false,"office":"Господарський місцевий суд"},"full_name":"Місюра Людмила Сергіївна","addresses":[{"place_district":"","place_address_hidden":true,"place_city":"","place_city_type_hidden":false,"place_district_hidden":false,"place_city_type":"","place_city_hidden":true,"place_address":"","place_hidden":true,"place":""}],"patronymic":"Сергіївна","patronymic_hidden":false,"full_name_suggest":{"output":"Місюра Людмила Сергіївна","input":["Місюра Людмила Сергіївна","Людмила Сергіївна Місюра","Людмила Місюра"]}},"source":"VULYK","estate":{"23":[{"space_unclear":false,"costs":"","costs_comment":"","address_hidden":false,"region_hidden":true,"space_comment":"","space_hidden":false,"space":"504","address":"","costs_comment_unclear":false,"region":"","space_units_unclear":false,"space_units":"м²","costs_rent":"","costs_rent_comment":""},{"costs_rent":"","space_unclear":false,"region":"","costs":"","costs_rent_comment":"","costs_comment":"","space_comment":"","space_units":"м²","space":"1223","address":""}],"25":[{"space_unclear":false,"costs":"","costs_comment":"","address_hidden":false,"region_hidden":true,"space_comment":"","space_hidden":false,"space":"68.36","address":"","region":"","costs_rent_comment":"","space_comment_unclear":false,"space_units":"м²","costs_rent":""}],"26":[{"costs_rent":"","region":"","costs":"","costs_rent_comment":"","costs_comment":"","address_hidden":false,"region_hidden":true,"space_comment":"","space_units":"м²","space":"45.7","address":""}],"29":[{"costs_rent":"","region":"","costs_property":"","costs_rent_comment":"","address_hidden":false,"region_hidden":true,"space_comment":"","costs_property_comment":"","space_units":"м²","space":"1223","address":""}],"31":[{"space_unclear":false,"address_hidden":false,"region_hidden":true,"space_comment":"","space_hidden":false,"space":"46.1","address":"","costs_rent_comment_unclear":false,"region":"","costs_property":"","costs_rent_comment":"","space_units":"м²","costs_property_comment":"","costs_rent":""}],"33":[{"costs_rent":"","region":"","costs_property":"","costs_rent_comment":"","address_hidden":false,"region_hidden":true,"space_comment":"","costs_property_comment":"","space_units":"м²","space":"21","address":""}]},"intro":{"declaration_year":"2015"}}