{"income":{"5":{"value":"231607","family_comment":"","family_hidden":false,"value_hidden":false,"family_unclear":false,"family":"","comment":""},"6":{"value":"231607","comment_unclear":false,"family_comment":"","family":"","comment":"","family_comment_unclear":false},"7":{"family_comment":"","value":"","source_name":"","family":"","comment":""},"8":{"family_comment":"","value":"","family":"","comment":""},"9":{"family_comment":"","value":"","family":"","comment":""},"10":{"family_comment":"","value":"","family":"","comment":""},"11":{"family_comment":"","value":"","family":"","comment":"","family_comment_unclear":false},"12":{"family_comment":"","value":"","family":"","comment":""},"13":{"family_comment":"","value":"","family":"","comment":""},"14":{"family_comment":"","value":"","family":"","comment":""},"15":{"family_comment":"","value":"","family":"","comment":""},"16":{"family_comment":"","value":"","family":"","comment":""},"17":{"family_comment":"","value":"","family":"","comment":""},"18":{"family_comment":"","value":"","family":"","comment":""},"19":{"family_comment":"","value":"","family":"","comment":"","value_hidden":false},"20":{"family_comment":"","value":"","comment_unclear":false,"family":"","comment":""}},"id":"vulyk_51_139","banks":{"45":[{"sum_foreign_comment":"","sum_units":"UAH","sum_comment":"","sum_comment_unclear":false,"sum_hidden":false,"sum_foreign_units":"UAH","sum_comment_hidden":false,"sum":"","sum_foreign":""},{"sum_foreign_comment":"","sum_units":"","sum_comment":"","sum_foreign_units":"","sum":"","sum_foreign":""},{"sum_foreign_comment":"","sum_units":"","sum_comment":"","sum_foreign_units":"","sum":"","sum_foreign":""},{"sum_foreign_comment":"","sum_units":"","sum_comment":"","sum_foreign_units":"","sum":"","sum_foreign":""},{"sum_foreign_comment":"","sum_units":"","sum_comment":"","sum_foreign_units":"","sum":"","sum_unclear":false,"sum_foreign":""}],"46":[{"sum_foreign_comment":"","sum_units":"UAH","sum_comment":"","sum_foreign_units":"UAH","sum":"","sum_foreign":""}],"47":[{"sum_foreign_comment":"","sum_units":"UAH","sum_comment":"","sum_foreign_units":"UAH","sum":"","sum_foreign":""}],"48":[{"sum_foreign_comment":"","sum_units":"UAH","sum_comment":"","sum_foreign_units":"UAH","sum":"","sum_foreign":""}],"49":[{"sum_foreign_comment":"","sum_units":"UAH","sum_comment":"","sum_foreign_units":"UAH","sum":"","sum_foreign":""}],"50":[{"sum_foreign_comment":"","sum_units":"UAH","sum_comment":"","sum_foreign_units":"UAH","sum":"","sum_foreign":""}],"51":[{"sum_foreign_comment":"","sum_units":"UAH","sum_comment":"","sum_foreign_units":"UAH","sum_comment_hidden":false,"sum":"","sum_foreign":""},{"sum_foreign_comment":"","sum_units":"","sum_comment":"","sum_foreign_units":"","sum":"","sum_foreign":""},{"sum_foreign_comment":"","sum_units":"","sum_comment":"","sum_foreign_units":"","sum":"","sum_foreign":""}],"52":[{"sum_foreign_comment":"","sum_units":"UAH","sum_comment":"","sum_foreign_units":"UAH","sum_comment_hidden":false,"sum":"","sum_foreign":""}],"53":[{"sum_foreign_comment":"","sum_units":"UAH","sum_comment":"","sum_foreign_units":"UAH","sum":"","sum_foreign":""}]},"declaration":{"additional_info_text":"","notfull_lostpages":"","date":"2015-03-27T00:00:00","notfull":"","additional_info":"","url":"http://static.declarations.com.ua/declarations/chosen_ones/mega_batch/koziatnyk_liudmyla_hryhorivna.pdf"},"liabilities":{"54":{"sum_foreign_comment":"","sum_comment_hidden":false,"sum":"","sum_comment":"","sum_foreign":""},"55":{"sum_foreign_comment":"","sum":"","sum_comment":"","sum_foreign":""},"56":{"sum_foreign_comment":"","sum":"","sum_comment":"","sum_foreign":""},"57":{"sum_foreign_comment":"","sum":"13352","sum_comment":"","sum_hidden":false,"sum_comment_hidden":false,"sum_foreign":""},"58":{"sum_foreign_comment":"","sum_comment_hidden":false,"sum":"6503","sum_comment":"","sum_foreign":""},"59":{"sum_foreign_comment":"","sum":"","sum_comment":"","sum_foreign":""},"60":{"sum_foreign_comment":"","sum":"","sum_comment":"","sum_foreign":""},"61":{"sum_foreign_comment":"","sum":"","sum_comment":"","sum_foreign":""},"62":{"sum_foreign_comment":"","sum":"","sum_comment":"","sum_foreign":""},"63":{"sum_foreign_comment":"","sum_comment_hidden":false,"sum":"","sum_comment":"","sum_foreign":""},"64":{"sum_foreign_comment":"","sum":"","sum_comment":"","sum_foreign":""}},"ft_src":"13352\n6503\n08158\nКиївська область\nКозятник Людмила Григорівна\nсуддя шевченківського районного суду міста києва\nм. Київ\nЗагальний місцевий суд\nЛюдмила\nМаніло А. А\nДитина\nКозятник Людмила Григорівна\nЛюдмила Григорівна Козятник\nЛюдмила Козятник\nКозятник Людмила Григорівна\nКозятник\nГригорівна\n231607\n231607\n.12\nКиївська область\n.12\nКиївська область\nу користуванні\n99.5\nКиївська область\n2014\n231607\n231607\n2014\nКозятник\nКозятник Людмила Григорівна\nЛюдмила Григорівна Козятник\nЛюдмила Козятник\nКозятник Людмила Григорівна\nЛюдмила\nГригорівна\n08158\nКиївська область\nКозятник Людмила Григорівна\nЗагальний місцевий суд\nсуддя шевченківського районного суду міста києва\nм. Київ\nДитина\nМаніло А. А\n13352\n6503\n231607\n231607\n.12\nКиївська область\n.12\nКиївська область\n99.5\nу користуванні\nКиївська область\n6503\n13352\nМаніло А. А\nДитина\nГригорівна\nКиївська область\n08158\nКозятник\nм. Київ\nЗагальний місцевий суд\nсуддя шевченківського районного суду міста києва\nКозятник Людмила Григорівна\nКозятник Людмила Григорівна\nЛюдмила Григорівна Козятник\nЛюдмила Козятник\nКозятник Людмила Григорівна\nЛюдмила\nКиївська область\n.12\nКиївська область\n.12\nу користуванні\nКиївська область\n99.5\n2014","general":{"inn":"","inn_hidden":true,"last_name":"Козятник","post":{"post":"суддя шевченківського районного суду міста києва","region":"м. Київ","office_hidden":false,"office":"Загальний місцевий суд","office_unclear":false,"region_hidden":false},"name":"Людмила","full_name":"Козятник Людмила Григорівна","family_raw":"","addresses":[{"place_district":"","place_city_hidden":true,"place_city":"","place_city_type_hidden":false,"place_district_hidden":false,"place_city_type":"","place_address_hidden":true,"place_address":"08158","place_hidden":false,"place":"Київська область"}],"family":[{"inn":"","relations":"Дитина","relations_other":"","inn_hidden":false,"family_name":"Маніло А. А","name_hidden":true,"name_unclear":false}],"full_name_suggest":{"output":"Козятник Людмила Григорівна","input":["Козятник Людмила Григорівна","Людмила Григорівна Козятник","Людмила Козятник"]},"patronymic":"Григорівна"},"source":"VULYK","estate":{"23":[{"costs":"","costs_comment":"","costs_hidden":false,"address_hidden":true,"region_hidden":false,"space_comment":"","space":".12","address":"","region":"Київська область","address_unclear":false,"costs_rent_comment":"","costs_rent_hidden":false,"space_units":"га","costs_rent":""},{"costs":"","costs_comment":"","costs_hidden":false,"region_hidden":false,"space_comment":"","space":".12","address":"","region":"Київська область","costs_rent_comment":"","costs_rent_hidden":false,"space_units":"га","costs_rent":""},{"space":"","region":"","costs":"","costs_rent_comment":"","costs_comment":"","address_unclear":false,"space_comment":"","space_units":"","costs_rent":"","address":""},{"costs_rent":"","region":"","costs":"","costs_rent_comment":"","costs_comment":"","space_comment":"","space_units":"","space":"","address":""}],"24":[{"costs_rent":"","region":"Київська область","costs":"","costs_rent_comment":"","costs_comment":"","address_hidden":false,"region_hidden":true,"space_comment":"у користуванні","space_units":"м²","space":"99.5","address":""}]},"intro":{"declaration_year":"2014","isnotdeclaration":""}}