{"income":{"5":{"value":"229371","family_comment":"","value_unclear":false,"comment_hidden":false,"family_hidden":false,"value_hidden":false,"family_unclear":false,"family_comment_hidden":false,"comment":"","family":"35897"},"6":{"value":"217325","family_comment":"","value_unclear":false,"family_hidden":false,"family_unclear":false,"family":"34330","comment":""},"7":{"source_name_unclear":false,"value":"","family_hidden":false,"family_comment":"","source_name":"","family":"","comment":"","source_name_hidden":false},"8":{"family_comment":"","value":"","family":"","comment":""},"9":{"value":"3495","value_unclear":false,"family_hidden":false,"family_comment":"","family":"","comment":""},"10":{"value":"","value_unclear":false,"family_hidden":false,"value_hidden":false,"family_comment":"","comment_unclear":false,"comment":"","family":""},"11":{"family_comment":"","value":"","family":"","comment":""},"12":{"family_comment":"","value":"","family":"","comment":""},"13":{"family_comment":"","value":"","family":"","comment":""},"14":{"family_comment":"","value":"","family":"","comment":""},"15":{"family_comment":"","value":"8030","family_hidden":false,"comment":"","family":""},"16":{"value":"","value_unclear":false,"family_hidden":false,"family_comment":"","family":"","comment":""},"17":{"family_comment":"","value":"","family_hidden":false,"comment":"","family":""},"18":{"family_comment":"","value":"","value_unclear":false,"family":"","comment":""},"19":{"family_comment":"","value":"","family":"667","comment":""},"20":{"value":"521","family_comment":"","value_unclear":false,"family_hidden":false,"family_unclear":false,"comment_unclear":false,"comment":"","family":"900"}},"vehicle":{"35":[{"brand_info":"1997 куб. см.","sum_rent_comment":"","brand_info_unclear":false,"year":"2007","sum_rent_unclear":false,"brand_info_hidden":false,"sum_rent_comment_unclear":false,"sum_hidden":false,"sum_rent":"","sum":"","brand":"Mitsubishi Outlander","sum_comment":"","brand_unclear":false,"brand_hidden":false}]},"id":"vulyk_72_234","banks":{"45":[{"sum_foreign_comment":"","sum_units":"USD","sum_comment":"","sum_comment_unclear":false,"sum_hidden":false,"sum_foreign_units":"UAH","sum_comment_hidden":false,"sum_unclear":false,"sum":"7830","sum_foreign":""}],"46":[{"sum_foreign_comment":"","sum_units":"USD","sum_comment":"","sum_hidden":false,"sum_foreign_units":"UAH","sum_comment_hidden":false,"sum_unclear":false,"sum":"1830","sum_foreign":""}]},"declaration":{"additional_info_text":"","notfull_lostpages":"","date":"2015-03-20T00:00:00","notfull":"","additional_info":"","url":"http://static.declarations.com.ua/declarations/chosen_ones/epic_batch/derkach_oleksandr_hryhorovych.pdf"},"liabilities":{"54":{"sum_foreign_comment":"","sum":"6429","sum_comment":"","sum_comment_hidden":false,"sum_unclear":false,"sum_foreign":""},"55":{"sum_foreign_comment":"","sum":"","sum_comment":"","sum_foreign":""},"56":{"sum_foreign_comment":"","sum":"","sum_hidden":false,"sum_comment":"","sum_foreign":""},"57":{"sum_foreign_comment":"","sum":"","sum_comment":"","sum_comment_unclear":false,"sum_hidden":false,"sum_comment_hidden":false,"sum_unclear":false,"sum_foreign":""},"58":{"sum_foreign_comment":"","sum":"","sum_comment":"","sum_comment_unclear":false,"sum_hidden":false,"sum_comment_hidden":false,"sum_unclear":false,"sum_foreign":""},"59":{"sum_foreign_comment":"","sum_foreign_hidden":false,"sum_comment":"","sum_foreign_unclear":false,"sum_comment_hidden":false,"sum":"","sum_foreign":""},"60":{"sum_foreign_comment":"","sum_foreign_hidden":false,"sum_comment":"","sum_hidden":false,"sum":"","sum_foreign":""},"61":{"sum_foreign_comment":"","sum_foreign_hidden":false,"sum_comment":"","sum_hidden":false,"sum":"","sum_foreign":""},"62":{"sum_foreign_comment":"","sum_foreign_hidden":false,"sum_comment":"","sum_hidden":false,"sum":"","sum_foreign":""},"63":{"sum_foreign_comment":"","sum_foreign_hidden":false,"sum_comment":"","sum_comment_unclear":false,"sum_hidden":false,"sum_comment_hidden":false,"sum_unclear":false,"sum":"","sum_foreign":""},"64":{"sum_foreign_comment":"","sum_foreign_hidden":false,"sum_comment":"","sum_hidden":false,"sum":"","sum_foreign":""}},"ft_src":"6429\nЧернігів\nсуддя новозаводського районного суду м. чернігова\nЧернігівська область\nЗагальний місцевий суд\nОлександр\nПодружжя\nДитина\nДитина\nГригорович\nДеркач\nДеркач Олександр Григорович\nДеркач Олександр Григорович\nОлександр Григорович Деркач\nОлександр Деркач\nДеркач Олександр Григорович\n1997 куб. см.\nMitsubishi Outlander\n2007\nЧернігівська область\nм. Чернігів\n66\nЧернігівська область\nСосницький район\n20000\nЧернігівська область\n2016/01/02\nм. Чернігів\n54\n54\nм. Чернігів\nЧернігівська область\n1830\n7830\n2014\n1997 куб. см.\nMitsubishi Outlander\n2007\nСосницький район\nЧернігівська область\n20000\n54\n2016/01/02\nЧернігівська область\nм. Чернігів\nЧернігівська область\nм. Чернігів\n66\nм. Чернігів\n54\nЧернігівська область\nПодружжя\nДитина\nДитина\nДеркач Олександр Григорович\nОлександр Григорович Деркач\nОлександр Деркач\nДеркач Олександр Григорович\nОлександр\nДеркач Олександр Григорович\nДеркач\nЧернігівська область\nЗагальний місцевий суд\nсуддя новозаводського районного суду м. чернігова\nГригорович\nЧернігів\n6429\n217325\n34330\n521\n900\n8030\n229371\n35897\n3495\n667\n7830\n1830\n2014\n6429\n34330\n217325\n8030\n3495\n35897\n229371\n667\n900\n521\nПодружжя\nДитина\nДитина\nГригорович\nДеркач\nДеркач Олександр Григорович\nОлександр Григорович Деркач\nОлександр Деркач\nДеркач Олександр Григорович\nЧернігів\nЧернігівська область\nЗагальний місцевий суд\nсуддя новозаводського районного суду м. чернігова\nДеркач Олександр Григорович\nОлександр\n2007\nMitsubishi Outlander\n1997 куб. см.\n667\n8030\n3495\n521\n900\n229371\n35897\n217325\n34330\nЧернігівська область\nм. Чернігів\n66\n54\nм. Чернігів\nЧернігівська область\n2016/01/02\nм. Чернігів\nЧернігівська область\n54\nСосницький район\nЧернігівська область\n20000\n7830\n1830\n2014","general":{"inn":"","name":"Олександр","patronymic_unclear":false,"family":[{"inn":"","inn_hidden":false,"relations_unclear":false,"relations_hidden":false,"relations_other":"","relations":"Подружжя","name_hidden":true,"inn_unclear":false,"family_name":"","name_unclear":false},{"inn":"","inn_hidden":false,"relations_hidden":false,"family_name":"","relations_other":"","relations":"Дитина","name_hidden":false,"name_unclear":false},{"inn":"","inn_hidden":false,"relations_hidden":false,"family_name":"","relations_other":"","relations":"Дитина","name_hidden":false,"name_unclear":false}],"patronymic":"Григорович","inn_hidden":true,"family_raw":"","inn_unclear":false,"post":{"post_unclear":false,"region_unclear":false,"post":"суддя новозаводського районного суду м. чернігова","candidate":"","office_hidden":false,"region":"Чернігівська область","post_hidden":false,"office":"Загальний місцевий суд","office_unclear":false,"region_hidden":false},"last_name_unclear":false,"full_name":"Деркач Олександр Григорович","addresses":[{"place_city_type_hidden":false,"place_district_hidden":false,"place_city_type":"Місто","place_city_hidden":false,"place_address_unclear":false,"place_address":"","place":"","place_district":"","place_unclear":false,"place_city":"Чернігів","place_city_unclear":false,"place_hidden":true,"place_address_hidden":false,"place_district_unclear":false}],"last_name":"Деркач","patronymic_hidden":false,"full_name_suggest":{"output":"Деркач Олександр Григорович","input":["Деркач Олександр Григорович","Олександр Григорович Деркач","Олександр Деркач"]},"name_unclear":false},"source":"VULYK","estate":{"24":[{"space_hidden":false,"costs":"","costs_comment":"","address_hidden":false,"region_hidden":false,"space_comment":"2016/01/02","space":"54","address":"м. Чернігів","region":"Чернігівська область","address_unclear":false,"costs_rent_comment":"","space_units":"м²","costs_rent":""}],"25":[{"space_unclear":false,"costs":"","costs_rent_unclear":false,"costs_comment":"","costs_hidden":false,"space_hidden":false,"costs_comment_unclear":false,"costs_rent_comment_unclear":false,"region":"Чернігівська область","space_comment_hidden":false,"space_comment_unclear":false,"costs_rent_comment_hidden":false,"costs_rent":"","costs_comment_hidden":false,"address_hidden":false,"region_hidden":false,"space_comment":"","space":"54","address":"м. Чернігів","address_unclear":false,"costs_rent_comment":"","costs_rent_hidden":false,"space_units":"м²"}],"29":[{"space_hidden":false,"costs_property_comment":"","address_hidden":false,"region_hidden":false,"space_comment":"","space_unclear":false,"space":"20000","address":"Сосницький район","region":"Чернігівська область","costs_property":"","costs_rent_comment":"","address_unclear":false,"space_units":"м²","space_units_unclear":false,"costs_rent":""}],"31":[{"space_unclear":false,"address_hidden":false,"region_hidden":false,"space_comment":"","space_units_hidden":false,"space_hidden":false,"space":"66","address":"м. Чернігів","region":"Чернігівська область","address_unclear":false,"costs_rent_comment":"","costs_property":"","space_units":"м²","costs_property_comment":"","costs_rent":""}]},"intro":{"declaration_year":"2014","isnotdeclaration":"","declaration_year_unclear":false}}