{"income":{"5":{"value":"296710","family_comment":"","value_unclear":false,"family_unclear":false,"family":"","comment":""},"6":{"family_comment":"","value":"251270","value_unclear":false,"family":"","comment":""},"7":{"value":"","value_unclear":false,"family_comment":"","source_name":"","family":"","comment":""},"8":{"family_comment":"","value":"","family":"","comment":""},"9":{"value":"","family_comment":"","value_unclear":false,"family_unclear":false,"family":"","comment":""},"10":{"family_comment":"","value":"12180","comment_unclear":false,"family":"","comment":""},"11":{"family_comment":"","value":"","family":"","comment":""},"12":{"family_comment":"","value":"","family":"","comment":""},"13":{"family_comment":"","value":"","value_unclear":false,"family":"","comment":""},"14":{"family_comment":"","value":"","family":"","comment":""},"15":{"family_comment":"","value":"","family":"","comment":""},"16":{"family_comment":"","family_unclear":false,"value":"","family":"","comment":""},"17":{"family_comment":"","family_unclear":false,"value":"","family":"","comment":""},"18":{"family_comment":"","value":"","family":"","comment":""},"19":{"family_comment":"","value":"","family":"","comment":""},"20":{"value":"44160","family_comment":"","value_unclear":false,"family_hidden":false,"value_hidden":false,"family_unclear":false,"comment_unclear":false,"comment":"","family":""}},"vehicle":{"40":[{"brand_info":"2285, 95.7 , 492.1","sum_rent_comment":"","brand":"ГАЗ 31105","sum_comment":"","year":"2007","brand_info_hidden":false,"brand_info_unclear":false,"sum":"","sum_rent":""}]},"id":"vulyk_100_168","declaration":{"additional_info_text":"","notfull_lostpages":"","date":"2015-05-12T00:00:00","notfull":"","additional_info":"","url":"http://static.declarations.com.ua/declarations/chosen_ones/judges_batch/4438_kovalchuk_vasyl_oleksandrovych.pdf"},"liabilities":{"54":{"sum_foreign_comment":"","sum":"","sum_comment":"","sum_comment_hidden":false,"sum_unclear":false,"sum_foreign":""},"55":{"sum_foreign_comment":"","sum":"","sum_comment":"","sum_foreign":""},"56":{"sum_foreign_comment":"","sum":"","sum_comment":"","sum_unclear":false,"sum_foreign":""},"57":{"sum_foreign_comment":"","sum":"45000","sum_comment":"","sum_comment_unclear":false,"sum_comment_hidden":false,"sum_unclear":false,"sum_foreign":""},"58":{"sum_foreign_comment":"","sum":"105000","sum_comment":"","sum_comment_hidden":false,"sum_unclear":false,"sum_foreign":""},"59":{"sum_foreign_comment":"","sum":"","sum_comment":"","sum_foreign":""},"60":{"sum_foreign_comment":"","sum_comment_hidden":false,"sum":"","sum_comment":"","sum_foreign":""},"61":{"sum_foreign_comment":"","sum":"","sum_comment":"","sum_foreign":""},"62":{"sum_foreign_comment":"","sum":"","sum_comment":"","sum_unclear":false,"sum_foreign":""},"63":{"sum_foreign_comment":"","sum_comment_hidden":false,"sum":"6000","sum_comment":"","sum_foreign":""},"64":{"sum_foreign_comment":"","sum_comment_hidden":false,"sum":"8000","sum_comment":"","sum_foreign":""}},"ft_src":"45000\n105000\n6000\n8000\nКовальчук Василь Олександрович\nсуддя луцького міськрайонного суду волинської області\nВолинська область\nЗагальний місцевий суд\nВасиль\nКовальчук І. М\nПодружжя\nКовальчук Василь Олександрович\nВасиль Олександрович Ковальчук\nВасиль Ковальчук\nКовальчук Василь Олександрович\nКовальчук\nОлександрович\n2007\n2285, 95.7 , 492.1\nГАЗ 31105\n55\n63\n55\n66\n2014\n251270\n12180\n296710\n44160\nГАЗ 31105\n2285, 95.7 , 492.1\n2007\n55\n55\n63\n66\nПодружжя\nКовальчук І. М\nОлександрович\nКовальчук\nКовальчук Василь Олександрович\nВасиль Олександрович Ковальчук\nВасиль Ковальчук\nКовальчук Василь Олександрович\nКовальчук Василь Олександрович\nВасиль\nЗагальний місцевий суд\nВолинська область\nсуддя луцького міськрайонного суду волинської області\n6000\n45000\n105000\n8000\n251270\n44160\n296710\n12180\n2014\n105000\n45000\n6000\n8000\nКовальчук І. М\nПодружжя\nОлександрович\nКовальчук\nВолинська область\nЗагальний місцевий суд\nсуддя луцького міськрайонного суду волинської області\nКовальчук Василь Олександрович\nКовальчук Василь Олександрович\nВасиль Олександрович Ковальчук\nВасиль Ковальчук\nКовальчук Василь Олександрович\nВасиль\n2007\n2285, 95.7 , 492.1\nГАЗ 31105\n12180\n44160\n296710\n251270\n55\n63\n66\n55\n2014","general":{"inn":"","inn_hidden":true,"last_name":"Ковальчук","post":{"post_unclear":false,"region_unclear":false,"post":"суддя луцького міськрайонного суду волинської області","office":"Загальний місцевий суд","region":"Волинська область","post_hidden":false,"office_unclear":false},"name":"Василь","full_name":"Ковальчук Василь Олександрович","family_raw":"","addresses":[{"place_district":"","place_city_hidden":false,"place_city":"","place_city_unclear":false,"place_district_hidden":false,"place_city_type":"","place_address_hidden":true,"place_city_type_hidden":false,"place_address":"","place_hidden":true,"place":""}],"family":[{"inn_hidden":true,"inn":"","name_hidden":true,"family_name":"Ковальчук І. М","relations":"Подружжя","name_unclear":false}],"full_name_suggest":{"output":"Ковальчук Василь Олександрович","input":["Ковальчук Василь Олександрович","Василь Олександрович Ковальчук","Василь Ковальчук"]},"patronymic":"Олександрович"},"source":"VULYK","estate":{"24":[{"space_unclear":false,"costs":"","costs_comment":"","address_hidden":false,"region_hidden":true,"space_comment":"","space":"55","address":"","region":"","costs_rent_comment":"","space_comment_unclear":false,"space_units":"м²","costs_rent":""}],"25":[{"space_unclear":false,"costs":"","costs_comment":"","address_hidden":false,"region_hidden":true,"space_comment":"","space":"66","address":"","costs_comment_unclear":false,"region":"","address_unclear":false,"costs_rent_comment":"","space_comment_unclear":false,"space_units":"м²","costs_rent":""}],"30":[{"costs_rent":"","region":"","costs_property":"","costs_rent_comment":"","address_hidden":false,"region_hidden":true,"space_comment":"","costs_property_comment":"","space_units":"м²","space":"55","address":""},{"costs_rent":"","space_unclear":false,"costs_property":"","costs_rent_comment":"","space_comment":"","costs_property_comment":"","space_units":"м²","space":"63","address":""}]},"intro":{"declaration_year":"2014"}}