{"income":{"5":{"value":"251661","family_comment":"","value_unclear":false,"family":"","family_unclear":false,"comment_unclear":false,"comment":"","family_comment_unclear":false},"6":{"value":"238389","family_comment":"","value_unclear":false,"family_unclear":false,"family":"","comment":""},"7":{"source_name_unclear":false,"value":"","value_unclear":false,"family_comment":"","source_name":"","family":"","comment":"","source_name_hidden":false},"8":{"family_comment":"","value":"","family":"","comment":""},"9":{"family_comment":"","value":"","family":"","comment":""},"10":{"family_comment":"","value":"12180","value_unclear":false,"family":"","comment":""},"11":{"value":"","value_unclear":false,"value_hidden":false,"family_comment":"","family":"","comment":""},"12":{"family_comment":"","value":"","family":"","comment":"","value_hidden":false},"13":{"family_comment":"","value":"","family":"","comment":""},"14":{"family_comment":"","value":"","family":"","comment":""},"15":{"family_comment":"","value":"","family":"","comment":""},"16":{"family_comment":"","value":"","family":"","comment":""},"17":{"family_comment":"","value":"","family":"","comment":""},"18":{"family_comment":"","value":"","family":"","comment":""},"19":{"family_comment":"","family_unclear":false,"value":"882","family":"","comment":""},"20":{"family_comment":"","family_unclear":false,"value":"210","family":"","comment":""}},"vehicle":{"40":[{"brand_info":"2300 куб. см.","sum":"","brand":"Mazda CX-7","sum_comment":"","brand_unclear":false,"year":"2006","brand_hidden":false,"brand_info_hidden":false,"brand_info_unclear":false,"sum_rent_comment":"","sum_rent":""},{"brand_info":"1600 куб. см.","sum_rent_comment":"","brand":"Volkswagen Polo","sum_comment":"","brand_unclear":false,"year":"1998","brand_info_unclear":false,"sum":"","sum_rent":""}]},"id":"vulyk_61_175","declaration":{"additional_info_text":"","notfull_lostpages":"","date":"2015-03-31T00:00:00","notfull":"","additional_info":"","url":"http://static.declarations.com.ua/declarations/chosen_ones/mega_batch/sokolovska_tetiana_oleksiivna.pdf"},"liabilities":{"54":{"sum_foreign_comment":"","sum":"10000","sum_comment":"","sum_comment_unclear":false,"sum_unclear":false,"sum_foreign":""},"55":{"sum_foreign_comment":"","sum":"","sum_comment":"","sum_foreign":""},"56":{"sum_foreign_comment":"","sum":"18000","sum_comment":"","sum_unclear":false,"sum_foreign":""},"57":{"sum_foreign_comment":"","sum":"5235","sum_comment":"","sum_comment_hidden":false,"sum_unclear":false,"sum_foreign":""},"58":{"sum_foreign_comment":"","sum":"","sum_comment":"","sum_unclear":false,"sum_foreign":""},"59":{"sum_foreign_comment":"","sum":"","sum_comment":"","sum_foreign":""},"60":{"sum_foreign_comment":"","sum_foreign_hidden":false,"sum_comment":"","sum_hidden":false,"sum":"5000","sum_foreign":""},"61":{"sum_foreign_comment":"","sum":"","sum_comment":"","sum_foreign":""},"62":{"sum_foreign_comment":"","sum":"","sum_comment":"","sum_unclear":false,"sum_foreign":""},"63":{"sum_foreign_comment":"","sum":"","sum_comment":"","sum_hidden":false,"sum_unclear":false,"sum_foreign":""},"64":{"sum_foreign_comment":"","sum":"","sum_hidden":false,"sum_comment":"","sum_foreign":""}},"ft_src":"5235\n10000\n18000\n5000\nголова шаргородського районного суду вінницької області\nВінницька область\nЗагальний місцевий суд\nТетяна\nСоколовський Сергій Віталійович\nДитина\nОлексіївна\nСоколовська\nСоколовська Тетяна Олексіївна\nСоколовська Тетяна Олексіївна\nТетяна Олексіївна Соколовська\nТетяна Соколовська\nСоколовська Тетяна Олексіївна\nMazda CX-7\n2300 куб. см.\n2006\n1998\nVolkswagen Polo\n1600 куб. см.\n8529\n2832\n1500\n30\n32\n14287\n168.74\n164.7\n2014\n238389\n12180\n251661\n882\n210\n2300 куб. см.\n2006\nMazda CX-7\n1600 куб. см.\n1998\nVolkswagen Polo\n8529\n2832\n1500\n14287\n168.74\n164.7\n30\n32\nДитина\nСоколовський Сергій Віталійович\nСоколовська Тетяна Олексіївна\nТетяна Олексіївна Соколовська\nТетяна Соколовська\nСоколовська Тетяна Олексіївна\nТетяна\nСоколовська Тетяна Олексіївна\nСоколовська\nВінницька область\nЗагальний місцевий суд\nголова шаргородського районного суду вінницької області\nОлексіївна\n5235\n5000\n18000\n10000\n238389\n210\n251661\n12180\n882\n2014\n5235\n18000\n10000\n5000\nСоколовський Сергій Віталійович\nДитина\nОлексіївна\nСоколовська\nСоколовська Тетяна Олексіївна\nТетяна Олексіївна Соколовська\nТетяна Соколовська\nСоколовська Тетяна Олексіївна\nВінницька область\nголова шаргородського районного суду вінницької області\nЗагальний місцевий суд\nСоколовська Тетяна Олексіївна\nТетяна\nMazda CX-7\n2300 куб. см.\n2006\n1998\n1600 куб. см.\nVolkswagen Polo\n882\n12180\n210\n251661\n238389\n8529\n2832\n1500\n168.74\n164.7\n30\n32\n14287\n2014","general":{"inn":"","name":"Тетяна","patronymic_unclear":false,"family":[{"inn":"","inn_hidden":true,"relations_unclear":false,"relations_hidden":false,"relations_other":"","relations":"Дитина","name_hidden":false,"family_name":"Соколовський Сергій Віталійович","name_unclear":false}],"patronymic":"Олексіївна","inn_hidden":true,"family_raw":"","inn_unclear":false,"post":{"post_unclear":false,"region_unclear":false,"post":"голова шаргородського районного суду вінницької області","office":"Загальний місцевий суд","region":"Вінницька область","post_hidden":false,"office_hidden":false,"region_hidden":false},"last_name_unclear":false,"full_name":"Соколовська Тетяна Олексіївна","addresses":[{"place_address":"","place_district_hidden":false,"place_city_type":"","place_city_hidden":true,"place_address_unclear":false,"place_city_type_hidden":false,"place_hidden":true,"place":"","place_district":"","place_address_hidden":true,"place_city":"","place_district_unclear":false}],"last_name":"Соколовська","patronymic_hidden":false,"full_name_suggest":{"output":"Соколовська Тетяна Олексіївна","input":["Соколовська Тетяна Олексіївна","Тетяна Олексіївна Соколовська","Тетяна Соколовська"]},"name_unclear":false},"source":"VULYK","estate":{"23":[{"region_unclear":false,"space_unclear":false,"costs":"","costs_comment":"","address_hidden":false,"region_hidden":true,"space_comment":"","space":"8529","address":"","region":"","address_unclear":false,"costs_rent_comment":"","space_comment_unclear":false,"space_units":"м²","space_units_unclear":false,"costs_rent":""},{"costs_rent":"","region":"","costs":"","costs_rent_comment":"","costs_comment":"","address_hidden":false,"region_hidden":false,"space_comment":"","space_units":"м²","space":"2832","address":""},{"costs_rent":"","space_unclear":false,"region":"","costs":"","costs_rent_comment":"","costs_comment":"","space_comment":"","space_units":"м²","space":"1500","address":""}],"24":[{"region_unclear":false,"space_unclear":false,"costs":"","costs_comment":"","address_hidden":false,"region_hidden":true,"space_comment":"","space_hidden":false,"space":"168.74","address":"","region":"","address_unclear":false,"costs_rent_comment":"","space_comment_unclear":false,"space_units":"м²","costs_rent":""},{"costs_rent":"","region":"","costs":"","costs_rent_comment":"","costs_comment":"","address_hidden":false,"region_hidden":false,"space_comment":"","space_units":"м²","space":"164.7","address":""}],"27":[{"costs":"","costs_rent_unclear":false,"costs_comment":"","address_hidden":false,"region_hidden":true,"space_comment":"","space":"30","address":"","region":"","address_unclear":false,"costs_rent_comment":"","space_units":"м²","costs_rent":""},{"costs_rent":"","region":"","costs":"","costs_rent_comment":"","costs_comment":"","space_comment":"","space_units":"м²","space":"32","address":""}],"29":[{"space_hidden":false,"costs_property":"","address_hidden":true,"region_hidden":true,"space_comment":"","space_units_hidden":false,"space_unclear":false,"space_units_unclear":false,"address":"","region":"","address_unclear":false,"space":"14287","space_comment_hidden":false,"space_units":"м²","costs_property_comment":"","costs_rent":"","costs_rent_comment":""}]},"intro":{"declaration_year":"2014","isnotdeclaration":"","declaration_year_hidden":false}}