{"income":{"5":{"value":"254605","family_comment":"","value_unclear":false,"family_hidden":false,"value_hidden":false,"family_unclear":false,"comment_unclear":false,"comment":"","family":"163881"},"6":{"value":"192925","family_comment":"","value_unclear":false,"family_hidden":false,"value_hidden":false,"family_unclear":false,"comment_unclear":false,"comment":"","family":"163881"},"7":{"source_name_unclear":false,"value":"","family_comment":"","source_name":"","family":"","comment":""},"8":{"family_comment":"","value":"","family":"","comment":""},"9":{"value":"271","value_unclear":false,"comment_hidden":false,"family_comment":"","comment_unclear":false,"comment":"","family":""},"10":{"value":"","comment_unclear":false,"value_hidden":false,"family_comment":"","family":"","comment":""},"11":{"family_comment":"","value":"","family":"","comment":""},"12":{"family_comment":"","value":"","family":"","comment":""},"13":{"family_comment":"","value":"","family":"","comment":""},"14":{"family_comment":"","value":"","family":"","comment":""},"15":{"family_comment":"","value":"","family":"","comment":""},"16":{"family_comment":"","value":"","family":"","comment":""},"17":{"family_comment":"","value":"","family":"","comment":""},"18":{"value":"","family_hidden":false,"value_hidden":false,"family_comment":"","family":"","comment":""},"19":{"family_comment":"","value":"49200","family":"","comment":""},"20":{"value":"12209","family_comment":"","value_unclear":false,"family_hidden":false,"value_hidden":false,"family_unclear":false,"family":"","comment":""}},"vehicle":{"35":[{"year_hidden":false,"brand_info":"1968 (користування","sum_rent_comment":"","year":"2013","brand_info_unclear":false,"year_unclear":false,"sum_rent":"","sum":"","brand":"Audi Q5","sum_comment":"","brand_unclear":false,"brand_hidden":false}],"40":[{"brand_info":"3471 (користування","sum_rent_comment":"","brand":"Honda Pilot","sum_comment":"","brand_unclear":false,"year":"2008","brand_info_unclear":false,"year_unclear":false,"sum":"","sum_rent":""}]},"id":"vulyk_66_9","banks":{"45":[{"sum_foreign_comment":"","sum_units":"UAH","sum_units_hidden":false,"sum_comment":"","sum_comment_unclear":false,"sum_hidden":false,"sum_foreign_units":"UAH","sum_comment_hidden":false,"sum_unclear":false,"sum":"2266","sum_foreign":""}],"46":[{"sum_foreign_comment":"","sum_units":"UAH","sum_comment":"","sum_foreign_units":"UAH","sum":"2266","sum_foreign":""}]},"declaration":{"additional_info_text":"","notfull_lostpages":"","date":"2015-03-31T00:00:00","notfull":"","additional_info":"","url":"http://static.declarations.com.ua/declarations/chosen_ones/mega_batch/smyrnova_iuliia_mykolaivna.pdf"},"liabilities":{"54":{"sum_foreign_comment":"","sum":"","sum_comment":"","sum_comment_unclear":false,"sum_comment_hidden":false,"sum_unclear":false,"sum_foreign":""},"55":{"sum_foreign_comment":"","sum":"","sum_comment":"","sum_foreign":""},"56":{"sum_foreign_comment":"","sum_foreign_hidden":false,"sum_comment":"","sum_hidden":false,"sum_comment_hidden":false,"sum":"","sum_foreign":""},"57":{"sum_foreign_comment":"","sum":"","sum_comment":"","sum_comment_unclear":false,"sum_hidden":false,"sum_comment_hidden":false,"sum_unclear":false,"sum_foreign":""},"58":{"sum_foreign_comment":"","sum":"","sum_comment":"","sum_comment_unclear":false,"sum_unclear":false,"sum_foreign":""},"59":{"sum_foreign_comment":"","sum_foreign_hidden":false,"sum_comment":"","sum_comment_unclear":false,"sum_hidden":false,"sum":"","sum_foreign":""},"60":{"sum_foreign_comment":"","sum":"","sum_comment":"","sum_comment_unclear":false,"sum_foreign":""},"61":{"sum_foreign_comment":"","sum":"","sum_comment":"","sum_foreign":""},"62":{"sum_foreign_comment":"","sum_foreign_hidden":false,"sum_comment":"","sum_hidden":false,"sum":"","sum_unclear":false,"sum_foreign":""},"63":{"sum_foreign_comment":"","sum":"","sum_comment":"","sum_comment_unclear":false,"sum_comment_hidden":false,"sum_unclear":false,"sum_foreign":""},"64":{"sum_foreign_comment":"","sum":"","sum_comment":"","sum_comment_unclear":false,"sum_foreign":""}},"ft_src":"Київ\nм. Київ\nсуддя господарського суду міста києва\nм. Київ\nГосподарський місцевий суд\nЮлія\nМора О. М\nПодружжя\nМора М. О\nДитина\nМора В. О\nДитина\nМиколаївна\nСмирнова Юлія Миколаївна\nЮлія Миколаївна Смирнова\nЮлія Смирнова\nСмирнова Юлія Миколаївна\nСмирнова Юлія Миколаївна\nСмирнова\n1968 (користування\nAudi Q5\n2013\n3471 (користування\nHonda Pilot\n2008\n2266\n2266\n2014\n1968 (користування\nAudi Q5\n2013\n3471 (користування\n2008\nHonda Pilot\n2266\n2266\n143.1\nвласність\nКиївська область\n73.3\n140.3\nкористування\nм. Київ\nм. Київ\n1180\nвласність\nКиївська область\nвласність\n1034\nКиївська область\nвласність\n1200\nКиївська область\nвласність\n968\nКиївська область\nвласність\n1180\nвласність\nКиївська область\nвласність\n1200\nКиївська область\nвласність\n968\nКиївська область\nвласність\n1800\nКиївська область\n73.3\nвласність\nм. Київ\n55.92\nвласність\nм. Київ\n140.3\nкористування\nм. Київ\n49.85\nвласність\nКиївська область\n143.1\nвласність\nКиївська область\nГосподарський місцевий суд\nсуддя господарського суду міста києва\nм. Київ\nПодружжя\nМора О. М\nДитина\nМора М. О\nДитина\nМора В. О\nСмирнова Юлія Миколаївна\nЮлія Миколаївна Смирнова\nЮлія Смирнова\nСмирнова Юлія Миколаївна\nСмирнова Юлія Миколаївна\nЮлія\nСмирнова\nМиколаївна\nКиїв\nм. Київ\n192925\n163881\n12209\n254605\n163881\n271\n49200\n2014\nвласність\n143.1\nКиївська область\nвласність\nвласність\nКиївська область\n1180\nвласність\nКиївська область\n1200\nвласність\nКиївська область\n968\nвласність\nКиївська область\n1800\nКиївська область\nвласність\n143.1\nвласність\n73.3\nм. Київ\nм. Київ\nвласність\n55.92\nм. Київ\nкористування\n140.3\nвласність\nКиївська область\n49.85\nвласність\n1180\nКиївська область\nвласність\n1034\nКиївська область\nвласність\n1200\nКиївська область\nвласність\n968\nКиївська область\n73.3\nкористування\nм. Київ\n140.3\nм. Київ\nМора О. М\nПодружжя\nМора М. О\nДитина\nМора В. О\nДитина\nМиколаївна\nСмирнова\nЮлія\nСмирнова Юлія Миколаївна\nЮлія Миколаївна Смирнова\nЮлія Смирнова\nСмирнова Юлія Миколаївна\nм. Київ\nКиїв\nм. Київ\nсуддя господарського суду міста києва\nГосподарський місцевий суд\nСмирнова Юлія Миколаївна\n163881\n192925\n163881\n254605\n49200\n271\n12209\nAudi Q5\n1968 (користування\n2013\n2008\n3471 (користування\nHonda Pilot\n49200\n12209\n254605\n163881\n271\n192925\n163881\nвласність\nм. Київ\n73.3\nвласність\nм. Київ\n55.92\nкористування\nм. Київ\n140.3\nвласність\nКиївська область\n1180\nКиївська область\n1034\nвласність\nКиївська область\n1200\nвласність\nКиївська область\n968\nвласність\nвласність\nКиївська область\n143.1\nвласність\nКиївська область\n143.1\nвласність\nКиївська область\n49.85\n73.3\nкористування\nм. Київ\nм. Київ\n140.3\nвласність\nКиївська область\nвласність\n1180\nКиївська область\nвласність\n1200\nКиївська область\nвласність\n968\nКиївська область\nвласність\n1800\n2266\n2266\n2014","general":{"inn":"","name":"Юлія","last_name_hidden":false,"family":[{"inn":"","inn_hidden":true,"relations_hidden":false,"family_name":"Мора О. М","relations_other":"","relations":"Подружжя","name_hidden":false,"name_unclear":false},{"inn":"","inn_hidden":true,"relations_unclear":false,"relations_hidden":false,"relations_other":"","relations":"Дитина","name_hidden":false,"family_name":"Мора М. О","name_unclear":false},{"inn":"","inn_hidden":false,"relations_hidden":false,"family_name":"Мора В. О","relations_other":"","relations":"Дитина","name_hidden":false,"name_unclear":false}],"patronymic":"Миколаївна","inn_hidden":false,"family_raw":"","inn_unclear":false,"post":{"post_unclear":false,"post":"суддя господарського суду міста києва","candidate":"","office_hidden":false,"region":"м. Київ","office":"Господарський місцевий суд","office_unclear":false},"full_name_suggest":{"output":"Смирнова Юлія Миколаївна","input":["Смирнова Юлія Миколаївна","Юлія Миколаївна Смирнова","Юлія Смирнова"]},"full_name":"Смирнова Юлія Миколаївна","addresses":[{"place_city_type_unclear":false,"place_address":"","place_district_hidden":true,"place_city_type":"Місто","place_address_hidden":true,"place_address_unclear":false,"place_city_type_hidden":true,"place":"м. Київ","place_district":"","place_unclear":false,"place_city":"Київ","place_city_unclear":false,"place_hidden":false,"place_city_hidden":true,"place_district_unclear":false}],"last_name":"Смирнова","last_name_unclear":false},"source":"VULYK","estate":{"23":[{"space_unclear":false,"costs":"","costs_comment":"","costs_hidden":false,"address_hidden":true,"region_hidden":false,"space_comment":"власність","space_hidden":false,"space":"1180","space_units_hidden":false,"region":"Київська область","address_unclear":false,"space_units_unclear":false,"space_units":"м²","address":"","costs_rent":"","costs_rent_comment":""},{"costs_rent":"","region":"Київська область","costs":"","costs_rent_comment":"","costs_comment":"власність","address_hidden":true,"space_comment":"","space_units":"м²","space":"1034","address":""},{"costs_rent":"","region":"Київська область","costs":"","costs_rent_comment":"","costs_comment":"власність","address_hidden":true,"space_comment":"","space_units":"м²","space":"1200","address":""},{"costs_rent":"","region":"Київська область","costs":"","costs_rent_comment":"","costs_comment":"власність","space_comment":"","space_units":"м²","space":"968","address":""}],"25":[{"region_unclear":false,"space_hidden":false,"costs":"","costs_comment":"","costs_hidden":false,"address_hidden":true,"region_hidden":true,"space_comment":"","space_unclear":false,"space":"73.3","space_units_hidden":false,"region":"","address_unclear":false,"costs_rent_comment":"","space_comment_unclear":false,"space_units":"м²","address":"","costs_rent":""},{"space_hidden":false,"costs":"","costs_comment":"","costs_hidden":false,"address_hidden":true,"region_hidden":true,"space_comment":"користування","space_unclear":false,"space":"140.3","address":"м. Київ","costs_comment_unclear":false,"region":"м. Київ","costs_rent_comment":"","space_units":"м²","costs_rent":""}],"26":[{"space_unclear":false,"costs":"","costs_comment":"","address_hidden":false,"region_hidden":false,"space_comment":"власність","space":"143.1","space_units_hidden":false,"costs_comment_unclear":false,"region":"Київська область","address_unclear":false,"costs_rent_comment":"","space_units":"м²","address":"","costs_rent":""}],"29":[{"space_unclear":false,"address_hidden":true,"region_hidden":false,"space_comment":"власність","space_hidden":false,"space":"1180","address":"","region":"Київська область","costs_property":"","costs_rent_comment":"","space_units":"м²","costs_property_comment":"власність","costs_rent":""},{"costs_rent":"","region":"Київська область","costs_property":"","costs_rent_comment":"","address_hidden":true,"region_hidden":false,"space_comment":"","costs_property_comment":"власність","space_units":"м²","space":"1200","address":""},{"costs_rent":"","region":"Київська область","costs_property":"","costs_rent_comment":"","address_hidden":true,"space_comment":"","costs_property_comment":"власність","space_units":"м²","space":"968","address":""},{"costs_rent":"","space_unclear":false,"region":"Київська область","costs_property":"","costs_rent_comment":"","address_hidden":true,"space_comment":"","costs_property_comment":"власність","space_units":"м²","space":"1800","address":""}],"30":[{"space_unclear":false,"address_hidden":true,"region_hidden":false,"space_comment":"власність","space_hidden":false,"space":"49.85","address":"","region":"Київська область","costs_property":"","costs_rent_comment":"","address_unclear":false,"space_units":"м²","costs_property_comment":"","costs_rent":""}],"31":[{"space_unclear":false,"address_hidden":true,"region_hidden":false,"space_comment":"власність","space_hidden":false,"space":"73.3","address":"","region":"м. Київ","costs_property":"","costs_rent_comment":"","space_comment_unclear":false,"space_comment_hidden":false,"space_units":"м²","costs_property_comment":"","costs_rent":""},{"costs_rent":"","region":"м. Київ","costs_property":"","costs_rent_comment":"","address_hidden":true,"region_hidden":false,"space_comment":"власність","costs_property_comment":"","space_units":"м²","space":"55.92","address":""},{"costs_rent":"","region":"м. Київ","costs_property":"","costs_rent_comment":"","address_hidden":true,"space_comment":"користування","costs_property_comment":"","space_units":"м²","space":"140.3","address":""}],"32":[{"costs_rent":"","region":"Київська область","costs_property":"","costs_rent_comment":"","address_hidden":true,"region_hidden":false,"space_comment":"власність","costs_property_comment":"","space_units":"м²","space":"143.1","address":""}]},"intro":{"declaration_year":"2014","isnotdeclaration":"","declaration_year_unclear":false}}