{"income":{"5":{"value":"180044","family_comment":"","value_unclear":false,"family_unclear":false,"family":"7812","comment":""},"6":{"value":"179878","family_comment":"","value_unclear":false,"family_unclear":false,"family":"","comment":""},"7":{"family_comment":"","value":"","source_name":"","family":"","comment":""},"8":{"family_comment":"","value":"","family":"","comment":""},"9":{"family_comment":"","value":"","family":"","comment":""},"10":{"family_comment":"","value":"","family":"","comment":""},"11":{"family_comment":"","value":"","family":"","comment":""},"12":{"family_comment":"","value":"","family":"","comment":""},"13":{"family_comment":"","value":"","family":"","comment":""},"14":{"family_comment":"","value":"","family":"","comment":""},"15":{"family_comment":"","value":"","value_unclear":false,"family":"","comment":""},"16":{"family_comment":"","value":"","family":"","comment":""},"17":{"family_comment":"","value":"","family":"","comment":""},"18":{"family_comment":"","value":"","family":"","comment":""},"19":{"family_comment":"","value":"","family":"","comment":""},"20":{"value":"166","family_comment":"","value_unclear":false,"family_unclear":false,"family":"7812","comment":"","family_comment_unclear":false}},"vehicle":{"35":[{"brand_info":"1598 куб. см., 75 кВт","sum_rent_comment":"","brand":"Skoda Octavia","sum_comment":"власність","brand_unclear":false,"year":"2005","brand_info_unclear":false,"sum":"","sum_rent":""}]},"id":"vulyk_99_70","declaration":{"date":"2016-03-24T00:00:00","notfull":"","notfull_lostpages":"","url":"http://static.declarations.com.ua/declarations/chosen_ones/judges_batch/619_bohonis_mykhailo_bohdanovych_2015.pdf"},"liabilities":{"54":{"sum_foreign_comment":"","sum":"2278","sum_comment":"ПАТ СК 'УСГ'","sum_comment_unclear":true,"sum_comment_hidden":false,"sum_foreign":""},"55":{"sum_foreign_comment":"","sum":"","sum_comment":"","sum_foreign":""},"56":{"sum_foreign_comment":"","sum":"","sum_comment":"","sum_foreign":""},"57":{"sum_foreign_comment":"","sum_comment":"Приватбанк, Укргазбанк","sum":"60527","sum_comment_hidden":false,"sum_foreign":""},"58":{"sum_foreign_comment":"","sum_comment":"Укргазбанк","sum":"5669","sum_comment_hidden":false,"sum_foreign":""},"59":{"sum_foreign_comment":"","sum":"","sum_comment":"","sum_comment_hidden":false,"sum_unclear":false,"sum_foreign":""},"60":{"sum_foreign_comment":"","sum_comment":"","sum":"","sum_comment_hidden":false,"sum_foreign":""},"61":{"sum_foreign_comment":"","sum":"","sum_comment":"","sum_foreign":""},"62":{"sum_foreign_comment":"","sum":"","sum_comment":"","sum_foreign":""},"63":{"sum_foreign_comment":"","sum_comment":"Приватбанк","sum":"3550","sum_comment_hidden":false,"sum_foreign":""},"64":{"sum_foreign_comment":"","sum_comment":"Приватбанк","sum":"7","sum_comment_hidden":false,"sum_foreign":""}},"ft_src":"власність\n2005\nSkoda Octavia\n1598 куб. см., 75 кВт\n69\n1/4\n49\n66.5\n60.2\n2015\n179878\n7812\n180044\n7812\n166\n1598 куб. см., 75 кВт\nSkoda Octavia\n2005\nвласність\n2015\nБогоніс\nБогоніс Михайло Богданович\nМихайло Богданович Богоніс\nМихайло Богоніс\nБогоніс Михайло Богданович\nМихайло\nБогданович\nБогоніс Михайло Богданович\nАдміністративний місцевий суд\nсуддя вінницького окружного адміністративного суду\nВінницька область\nПодружжя\nБогоніс Н. Я\nДитина\nБогоніс Н. М\nДитина\nБогоніс Д. М\nУкргазбанк\n5669\n2278\nПАТ СК 'УСГ'\nПриватбанк\n3550\nПриватбанк, Укргазбанк\n60527\nПриватбанк\n7\n179878\n166\n7812\n180044\n7812\n69\n49\n1/4\n66.5\n60.2\nУкргазбанк\n5669\nПриватбанк, Укргазбанк\n60527\nПАТ СК 'УСГ'\n2278\nПриватбанк\n3550\nПриватбанк\n7\nБогоніс Н. Я\nПодружжя\nБогоніс Н. М\nДитина\nБогоніс Д. М\nДитина\nБогданович\nБогоніс\nсуддя вінницького окружного адміністративного суду\nВінницька область\nАдміністративний місцевий суд\nБогоніс Михайло Богданович\nБогоніс Михайло Богданович\nМихайло Богданович Богоніс\nМихайло Богоніс\nБогоніс Михайло Богданович\nМихайло","general":{"inn":"","inn_hidden":true,"last_name":"Богоніс","post":{"post_unclear":false,"office":"Адміністративний місцевий суд","post":"суддя вінницького окружного адміністративного суду","region":"Вінницька область"},"name":"Михайло","full_name":"Богоніс Михайло Богданович","family_raw":"","addresses":[{"place_district":"","place_address_hidden":true,"place_city":"","place_address":"","place_district_hidden":false,"place_city_type":"","place_city_hidden":true,"place_city_type_hidden":false,"place_hidden":true,"place":""}],"family":[{"inn":"","relations":"Подружжя","name_hidden":true,"inn_hidden":true,"family_name":"Богоніс Н. Я","name_unclear":false},{"inn":"","inn_hidden":true,"family_name":"Богоніс Н. М","relations_other":"","relations":"Дитина","name_unclear":false},{"inn":"","inn_hidden":true,"family_name":"Богоніс Д. М","relations_other":"","relations":"Дитина","name_hidden":false,"name_unclear":false}],"full_name_suggest":{"output":"Богоніс Михайло Богданович","input":["Богоніс Михайло Богданович","Михайло Богданович Богоніс","Михайло Богоніс"]},"patronymic":"Богданович"},"source":"VULYK","estate":{"25":[{"space_unclear":false,"costs":"","costs_comment":"","address_hidden":false,"region_hidden":true,"space_comment":"","space_hidden":false,"space":"66.5","address":"","region":"","costs_rent_comment":"","space_units":"м²","costs_rent":""},{"costs_rent":"","region":"","costs":"","costs_rent_comment":"","costs_comment":"","address_hidden":false,"space_comment":"","space_units":"м²","space":"60.2","address":""}],"31":[{"costs_rent":"","region":"","costs_property":"","costs_rent_comment":"","address_hidden":false,"region_hidden":true,"space_comment":"","costs_property_comment":"","space_units":"м²","space":"69","address":""},{"costs_rent":"","region":"","costs_property":"","costs_rent_comment":"","space_comment":"1/4","costs_property_comment":"","space_units":"м²","space":"49","address":""}]},"intro":{"declaration_year":"2015"}}