{"income":{"5":{"value":"803042.77","family_comment":"","family_hidden":false,"value_hidden":false,"family_unclear":false,"family":"875383.09","comment":""},"6":{"value":"190862.77","family_unclear":false,"family_hidden":false,"family_comment":"","family":"32143.09","comment":""},"7":{"value":"","family_comment":"","source_name":"","family":"","comment":"","source_name_hidden":false},"8":{"family_comment":"","value":"","family":"","comment":""},"9":{"family_comment":"","family_unclear":false,"value":"","family":"","comment":""},"10":{"family_comment":"","value":"12180","family":"","comment":""},"11":{"family_comment":"","value":"600000","family":"","comment":"Дарунок Батьків від продажу квартири"},"12":{"family_comment":"","value":"","family":"","comment":""},"13":{"family_comment":"","value":"","family":"","comment":""},"14":{"family_comment":"","value":"","family":"","comment":""},"15":{"family_comment":"","family_unclear":false,"value":"","family":"","comment":""},"16":{"family_comment":"","family_unclear":false,"value":"","family":"","comment":""},"17":{"family_comment":"","value":"","value_unclear":false,"family":"843240","comment":""},"18":{"family_comment":"","value":"","family":"","comment":""},"19":{"family_comment":"","value":"","family":"","comment":""},"20":{"family_comment":"","value":"","comment_unclear":false,"family":"","comment":""}},"vehicle":{"40":[{"brand_info":"2000 куб. см.","sum":"","brand":"KIA Karena","sum_comment":"","brand_unclear":false,"year":"2008","brand_hidden":false,"brand_info_hidden":false,"brand_info_unclear":false,"sum_rent_comment":"","sum_rent":""}]},"id":"vulyk_18_58","banks":{"45":[{"sum_units":"UAH","sum_hidden":false,"sum_units_hidden":false,"sum_foreign":"","sum_foreign_comment":"","sum":"","sum_comment":"","sum_comment_unclear":false,"sum_foreign_units":"UAH","sum_units_unclear":false,"sum_comment_hidden":false,"sum_unclear":false}],"46":[{"sum_foreign_comment":"","sum_units":"UAH","sum_comment":"","sum_foreign_units":"UAH","sum":"","sum_foreign":""}],"47":[{"sum_foreign_comment":"","sum_units":"UAH","sum_comment":"","sum_foreign_units":"UAH","sum":"","sum_foreign":""}],"48":[{"sum_foreign_comment":"","sum_units":"UAH","sum_comment":"","sum_foreign_units":"UAH","sum":"","sum_foreign":""}],"49":[{"sum_foreign_comment":"","sum_units":"UAH","sum_comment":"","sum_foreign_units":"UAH","sum":"","sum_foreign":""}],"50":[{"sum_foreign_comment":"","sum_units":"UAH","sum_comment":"","sum_foreign_units":"UAH","sum":"","sum_foreign":""}],"51":[{"sum_foreign_comment":"","sum_units":"UAH","sum_comment":"","sum_hidden":false,"sum_foreign_units":"UAH","sum_units_unclear":false,"sum_comment_hidden":false,"sum_units_hidden":false,"sum":"","sum_foreign":""}],"52":[{"sum_foreign_comment":"","sum_units":"UAH","sum_comment":"","sum_foreign_units":"UAH","sum":"","sum_foreign":""}],"53":[{"sum_foreign_comment":"","sum_units":"UAH","sum_comment":"","sum_foreign_unclear":false,"sum_foreign_units":"UAH","sum":"","sum_foreign_hidden":false,"sum_foreign":""}]},"declaration":{"additional_info_text":"","notfull_lostpages":"","date":"2015-03-30T00:00:00","notfull":"","additional_info":"","url":"http://static.declarations.com.ua/declarations/chosen_ones/mega_batch/vanivskyi_iurii_mykhailovych.pdf"},"liabilities":{"54":{"sum_foreign_comment":"","sum":"","sum_comment":"","sum_comment_unclear":false,"sum_hidden":false,"sum_comment_hidden":false,"sum_unclear":false,"sum_foreign":""},"55":{"sum_foreign_comment":"","sum":"","sum_comment":"","sum_comment_unclear":false,"sum_hidden":false,"sum_unclear":false,"sum_foreign":""},"56":{"sum_foreign_comment":"","sum":"10638.1","sum_comment":"","sum_hidden":false,"sum_unclear":false,"sum_foreign":""},"57":{"sum_foreign_comment":"","sum":"","sum_comment":"","sum_unclear":false,"sum_foreign":""},"58":{"sum_foreign_comment":"","sum":"","sum_comment":"","sum_unclear":false,"sum_foreign":""},"59":{"sum_foreign_comment":"","sum":"","sum_comment":"","sum_foreign":""},"60":{"sum_foreign_comment":"","sum":"5577.6","sum_comment":"","sum_hidden":false,"sum_comment_hidden":false,"sum_unclear":false,"sum_foreign":""},"61":{"sum_foreign_comment":"","sum":"","sum_hidden":false,"sum_comment":"","sum_foreign":""},"62":{"sum_foreign_comment":"","sum":"9816.98","sum_hidden":false,"sum_comment":"","sum_foreign":""},"63":{"sum_foreign_comment":"","sum":"","sum_hidden":false,"sum_comment":"","sum_foreign":""},"64":{"sum_foreign_comment":"","sum":"","sum_hidden":false,"sum_comment":"","sum_foreign":""}},"ft_src":"9816.98\n10638.1\n5577.6\nсуддя франківського районного суду м. львова\nЛьвівська область\nЗагальний місцевий суд\nЮрій\nВанівська О. І\nПодружжя\nВанівська А. Ю\nДитина\nВанівський С. Ю\nДитина\nМихайлович\nВанівський\nВанівський Юрій Михайлович\nВанівський Юрій Михайлович\nЮрій Михайлович Ванівський\nЮрій Ванівський\nВанівський Юрій Михайлович\nKIA Karena\n2000 куб. см.\n2008\n2014\n2000 куб. см.\n2008\nKIA Karena\n48.4\n190.8\nВанівський Юрій Михайлович\nЮрій Михайлович Ванівський\nЮрій Ванівський\nВанівський Юрій Михайлович\nВанівський Юрій Михайлович\nПодружжя\nВанівська О. І\nДитина\nВанівська А. Ю\nДитина\nВанівський С. Ю\nЮрій\nВанівський\nЗагальний місцевий суд\nсуддя франківського районного суду м. львова\nЛьвівська область\nМихайлович\n5577.6\n10638.1\n9816.98\n190862.77\n32143.09\n843240\n875383.09\n803042.77\nДарунок Батьків від продажу квартири\n600000\n12180\n2014\n10638.1\n9816.98\n5577.6\n48.4\n190.8\nПодружжя\nВанівська О. І\nВанівська А. Ю\nДитина\nВанівський С. Ю\nДитина\nМихайлович\nВанівський\nЮрій\nВанівський Юрій Михайлович\nЮрій Михайлович Ванівський\nЮрій Ванівський\nВанівський Юрій Михайлович\nЛьвівська область\nЗагальний місцевий суд\nсуддя франківського районного суду м. львова\nВанівський Юрій Михайлович\n32143.09\n190862.77\nДарунок Батьків від продажу квартири\n600000\n12180\n875383.09\n803042.77\n843240\nKIA Karena\n2000 куб. см.\n2008\nДарунок Батьків від продажу квартири\n600000\n12180\n803042.77\n875383.09\n843240\n190862.77\n32143.09\n190.8\n48.4\n2014","general":{"inn":"","name":"Юрій","last_name_hidden":false,"family":[{"inn":"","inn_hidden":true,"relations_unclear":false,"relations_hidden":false,"relations_other":"","relations":"Подружжя","name_hidden":false,"inn_unclear":false,"family_name":"Ванівська О. І","name_unclear":false},{"inn":"","inn_hidden":true,"relations_hidden":false,"family_name":"Ванівська А. Ю","relations_other":"","relations":"Дитина","name_hidden":false,"name_unclear":false},{"inn":"","relations":"Дитина","relations_other":"","inn_hidden":false,"family_name":"Ванівський С. Ю","name_hidden":false,"name_unclear":false}],"patronymic":"Михайлович","inn_hidden":false,"family_raw":"","inn_unclear":false,"post":{"post_unclear":false,"post":"суддя франківського районного суду м. львова","candidate":"","office_hidden":false,"region":"Львівська область","post_hidden":false,"office":"Загальний місцевий суд","office_unclear":false,"region_hidden":false},"last_name_unclear":false,"full_name":"Ванівський Юрій Михайлович","last_name":"Ванівський","full_name_suggest":{"output":"Ванівський Юрій Михайлович","input":["Ванівський Юрій Михайлович","Юрій Михайлович Ванівський","Юрій Ванівський"]}},"source":"VULYK","estate":{"23":[{"space_hidden":false,"costs":"","costs_comment":"","costs_hidden":false,"space_unclear":false,"space_units_unclear":false,"space_units_hidden":false,"costs_comment_unclear":false,"region":"","space_comment_unclear":false,"space_comment_hidden":false,"costs_rent":"","region_unclear":false,"address_hidden":false,"region_hidden":false,"space_comment":"","space":"","address":"","address_unclear":false,"costs_rent_comment":"","costs_rent_hidden":false,"space_units":"м²"},{"costs_rent":"","region":"","costs":"","costs_rent_comment":"","costs_comment":"","region_hidden":false,"space_comment":"","space_units":"","space":"","address":""},{"costs_rent":"","region":"","costs":"","costs_rent_comment":"","costs_comment":"","region_hidden":false,"space_comment":"","space_units":"","space":"","address":""},{"costs_rent":"","costs":"","costs_rent_comment":"","costs_comment":"","region_hidden":false,"space_comment":"","space_units":"","space":"","address":""}],"31":[{"space_unclear":false,"address_hidden":false,"region_hidden":false,"space_comment":"","space_hidden":false,"space":"190.8","address":"","region":"","costs_property":"","costs_rent_comment":"","space_comment_unclear":false,"space_comment_hidden":false,"space_units":"м²","costs_property_comment":"","costs_rent":""}],"33":[{"space_hidden":false,"address_hidden":false,"region_hidden":false,"space_comment":"","space":"48.4","address":"","region":"","costs_property":"","costs_rent_comment":"","space_units":"м²","costs_property_comment":"","costs_rent":""}]},"intro":{"declaration_year":"2014","isnotdeclaration":"","declaration_year_unclear":false,"declaration_year_hidden":false}}