{"income":{"5":{"family_comment":"","value":"229039","family":"104254","comment":"","family_hidden":false},"6":{"value":"216859","value_unclear":false,"family_hidden":false,"family_comment":"","family":"104254","comment":""},"7":{"value":"","value_unclear":false,"family_comment":"","source_name":"","family":"","comment":""},"8":{"family_comment":"","value":"","family":"","comment":""},"9":{"family_comment":"","value":"","family":"","comment":""},"10":{"value":"12180","family_comment":"","comment_unclear":false,"family_unclear":false,"family":"","comment":"","family_comment_unclear":false},"11":{"family_comment":"","value":"","value_unclear":false,"family":"","comment":""},"12":{"family_comment":"","value":"","family":"","comment":""},"13":{"family_comment":"","value":"","family":"","comment":""},"14":{"family_comment":"","value":"","family":"","comment":""},"15":{"value":"","family_comment":"","comment_unclear":false,"family_unclear":false,"family":"","comment":""},"16":{"family_comment":"","value":"","family":"","comment":""},"17":{"family_comment":"","value":"","family":"","comment":""},"18":{"family_comment":"","family_unclear":false,"value":"","family":"","comment":""},"19":{"family_comment":"","value":"","family":"","comment":""},"20":{"family_comment":"","family_unclear":false,"value":"","family":"","comment":""}},"vehicle":{"40":[{"year_hidden":false,"brand_info":"2000 куб. см.","sum_rent_comment":"","year":"1996","brand_info_hidden":false,"year_unclear":false,"sum_rent":"","sum":"","brand":"Mercedes-Benz","sum_comment":"","sum_comment_unclear":false,"brand_hidden":false}]},"id":"vulyk_92_146","declaration":{"additional_info_text":"","notfull_lostpages":"","date":"2015-03-24T00:00:00","notfull":"","additional_info":"","url":"http://static.declarations.com.ua/declarations/chosen_ones/judges_batch/3394_bonetskyi_liubomyr_iosyfovych.pdf"},"liabilities":{"54":{"sum_foreign_comment":"","sum":"","sum_comment":"","sum_hidden":false,"sum_unclear":false,"sum_foreign":""},"55":{"sum_foreign_comment":"","sum":"","sum_comment":"","sum_unclear":false,"sum_foreign":""},"56":{"sum_foreign_comment":"","sum":"","sum_comment":"","sum_comment_unclear":false,"sum_hidden":false,"sum_unclear":false,"sum_foreign":""},"57":{"sum_foreign_comment":"","sum":"","sum_comment":"","sum_hidden":false,"sum_comment_hidden":false,"sum_foreign":""},"58":{"sum_foreign_comment":"","sum":"","sum_comment":"","sum_foreign":""},"59":{"sum_foreign_comment":"","sum":"","sum_comment":"","sum_comment_unclear":false,"sum_foreign":""},"60":{"sum_foreign_comment":"","sum":"","sum_comment":"","sum_foreign":""},"61":{"sum_foreign_comment":"","sum":"","sum_comment":"","sum_foreign":""},"62":{"sum_foreign_comment":"","sum":"","sum_comment":"","sum_comment_unclear":false,"sum_hidden":false,"sum_unclear":false,"sum_foreign":""},"63":{"sum_foreign_comment":"","sum":"","sum_comment":"","sum_foreign":""},"64":{"sum_foreign_comment":"","sum":"","sum_comment":"","sum_foreign":""}},"ft_src":"2000 куб. см.\nMercedes-Benz\n1996\nм. Старий Самбір\n1000\nЛьвівська область\nЛьвівська область\nм. Старий Самбір\n18\nЛьвівська область\nм. Старий Самбір\n64.5\n2014\n104254\n216859\n12180\n104254\n229039\n2000 куб. см.\nMercedes-Benz\n1996\n1000\nЛьвівська область\nм. Старий Самбір\n18\nм. Старий Самбір\nЛьвівська область\nЛьвівська область\nм. Старий Самбір\n64.5\nПодружжя\nБонецька О. М. 21. 08. 1966\nДитина\nБонецька С. Л. 02. 06. 1992\nДитина\nБонецький М. Л. 04. 10. 1999\nБонецький Любомир Йосифович\nЛюбомир Йосифович Бонецький\nЛюбомир Бонецький\nБонецький Любомир Йосифович\nБонецький Любомир Йосифович\nЛюбомир\nБонецький\nЗагальний місцевий суд\nсуддя старосамбірського районного суду львівської області\nЛьвівська область\nЙосифович\n216859\n104254\n229039\n104254\n12180\n2014\nПодружжя\nБонецька О. М. 21. 08. 1966\nДитина\nБонецька С. Л. 02. 06. 1992\nДитина\nБонецький М. Л. 04. 10. 1999\nЙосифович\nБонецький\nЛюбомир\nБонецький Любомир Йосифович\nЛюбомир Йосифович Бонецький\nЛюбомир Бонецький\nБонецький Любомир Йосифович\nЛьвівська область\nЗагальний місцевий суд\nсуддя старосамбірського районного суду львівської області\nБонецький Любомир Йосифович","general":{"inn":"","name":"Любомир","patronymic_unclear":false,"last_name":"Бонецький","family":[{"inn":"","relations":"Подружжя","inn_unclear":false,"relations_hidden":false,"inn_hidden":true,"family_name":"Бонецька О. М. 21. 08. 1966","relations_other":"","name_hidden":false,"name_unclear":false},{"inn":"","relations":"Дитина","inn_unclear":false,"relations_hidden":false,"inn_hidden":true,"family_name":"Бонецька С. Л. 02. 06. 1992","relations_other":"","name_hidden":false,"name_unclear":false},{"inn":"","relations":"Дитина","relations_other":"","inn_hidden":true,"family_name":"Бонецький М. Л. 04. 10. 1999","name_unclear":false}],"inn_hidden":true,"family_raw":"","inn_unclear":false,"post":{"post_unclear":false,"post":"суддя старосамбірського районного суду львівської області","office_hidden":false,"region":"Львівська область","region_hidden":false,"office":"Загальний місцевий суд","office_unclear":false},"full_name":"Бонецький Любомир Йосифович","addresses":[{"place_district":"","place_address_hidden":true,"place_city":"","place_address":"","place_district_hidden":true,"place_city_type":"","place_city_hidden":true,"place_address_unclear":false,"place_city_type_hidden":true,"place_hidden":true,"place":""}],"patronymic":"Йосифович","full_name_suggest":{"output":"Бонецький Любомир Йосифович","input":["Бонецький Любомир Йосифович","Любомир Йосифович Бонецький","Любомир Бонецький"]}},"source":"VULYK","estate":{"23":[{"region_unclear":false,"space_unclear":false,"costs":"","costs_comment":"","address_hidden":true,"region_hidden":false,"space_comment":"","space":"1000","address":"м. Старий Самбір","region":"Львівська область","costs_rent_comment":"","space_units":"м²","costs_rent":""}],"31":[{"space_unclear":false,"address_hidden":true,"region_hidden":false,"space_comment":"","space_hidden":false,"space":"64.5","address":"м. Старий Самбір","region":"Львівська область","costs_property":"","costs_rent_comment":"","address_unclear":false,"space_units":"м²","costs_property_comment":"","costs_rent":""}],"33":[{"costs_rent":"","region":"Львівська область","costs_property":"","costs_rent_comment":"","address_hidden":true,"region_hidden":false,"space_comment":"","costs_property_comment":"","space_units":"м²","space":"18","address":"м. Старий Самбір"}]},"intro":{"declaration_year":"2014","isnotdeclaration":""}}