{"income":{"5":{"family_comment":"","value":"196520","value_unclear":false,"family":"","comment":""},"6":{"value":"196520","value_unclear":false,"family_hidden":false,"family_comment":"","family":"","comment":""},"7":{"source_name_unclear":false,"value":"","family_comment":"","source_name":"","family":"","comment":""},"8":{"family_comment":"","value":"","family":"","comment":""},"9":{"family_comment":"","value":"","family":"","comment":""},"10":{"family_comment":"","value":"","family":"","comment":""},"11":{"family_comment":"","value":"","comment_unclear":false,"family":"","comment":""},"12":{"family_comment":"","value":"","family":"","comment":""},"13":{"family_comment":"","value":"","family":"","comment":""},"14":{"family_comment":"","value":"","family":"","comment":""},"15":{"family_comment":"","value":"","family":"","comment":""},"16":{"family_comment":"","value":"","family":"","comment":""},"17":{"family_comment":"","value":"","family":"","comment":""},"18":{"family_comment":"","value":"","family":"","comment":""},"19":{"family_comment":"","value":"","family":"","comment":""},"20":{"value":"","family_comment":"","value_unclear":false,"family_unclear":false,"comment_unclear":false,"comment":"","family":""}},"id":"vulyk_101_142","declaration":{"additional_info_text":"","notfull_lostpages":"","date":"2016-03-21T00:00:00","notfull":"","additional_info":"","url":"http://static.declarations.com.ua/declarations/chosen_ones/judges_batch/857_mirosiedi_andrii_illich_2015.pdf"},"liabilities":{"54":{"sum_foreign_comment":"","sum":"","sum_comment":"","sum_comment_unclear":false,"sum_hidden":false,"sum_comment_hidden":false,"sum_unclear":false,"sum_foreign":""},"55":{"sum_foreign_comment":"","sum":"","sum_comment":"","sum_foreign":""},"56":{"sum_foreign_comment":"","sum":"","sum_comment":"","sum_comment_hidden":false,"sum_unclear":false,"sum_foreign":""},"57":{"sum_foreign_comment":"","sum":"","sum_comment":"","sum_hidden":false,"sum_comment_hidden":false,"sum_unclear":false,"sum_foreign":""},"58":{"sum_foreign_comment":"","sum":"","sum_comment":"","sum_comment_unclear":false,"sum_hidden":false,"sum_comment_hidden":false,"sum_unclear":false,"sum_foreign":""},"59":{"sum_foreign_comment":"","sum":"","sum_comment":"","sum_foreign":""},"60":{"sum_foreign_comment":"","sum":"","sum_comment":"","sum_hidden":false,"sum_comment_hidden":false,"sum_unclear":false,"sum_foreign":""},"61":{"sum_foreign_comment":"","sum":"","sum_comment":"","sum_foreign":""},"62":{"sum_foreign_comment":"","sum":"","sum_comment":"","sum_comment_unclear":false,"sum_foreign":""},"63":{"sum_foreign_comment":"","sum_comment_hidden":false,"sum":"","sum_comment":"","sum_foreign":""},"64":{"sum_foreign_comment":"","sum_comment_hidden":false,"sum":"","sum_comment":"","sum_foreign":""}},"ft_src":"суддя костянтинівського міськрайонного суду донецької області\nДонецька область\nЗагальний місцевий суд\nАндрій\nІлліч\nМіросєді Андрій Ілліч\nМіросєді\nМіросєді Андрій Ілліч\nАндрій Ілліч Міросєді\nАндрій Міросєді\nМіросєді Андрій Ілліч\n196520\n196520\n2015\n196520\n196520\n196520\n196520\nМіросєді Андрій Ілліч\nАндрій Ілліч Міросєді\nАндрій Міросєді\nМіросєді Андрій Ілліч\nАндрій\nМіросєді Андрій Ілліч\nМіросєді\nЗагальний місцевий суд\nсуддя костянтинівського міськрайонного суду донецької області\nДонецька область\nІлліч\n2015\nІлліч\nМіросєді\nАндрій\nМіросєді Андрій Ілліч\nАндрій Ілліч Міросєді\nАндрій Міросєді\nМіросєді Андрій Ілліч\nсуддя костянтинівського міськрайонного суду донецької області\nЗагальний місцевий суд\nДонецька область\nМіросєді Андрій Ілліч\n2015","general":{"inn":"","name":"Андрій","inn_unclear":false,"patronymic":"Ілліч","inn_hidden":true,"family_raw":"","last_name":"Міросєді","post":{"region":"Донецька область","region_unclear":false,"post":"суддя костянтинівського міськрайонного суду донецької області","office_unclear":false,"office":"Загальний місцевий суд"},"full_name":"Міросєді Андрій Ілліч","addresses":[{"place_district":"","place_city_hidden":true,"place_city":"","place_city_type_hidden":false,"place_district_hidden":false,"place_city_type":"","place_address_hidden":true,"place_address":"","place_hidden":true,"place":""}],"patronymic_hidden":false,"full_name_suggest":{"output":"Міросєді Андрій Ілліч","input":["Міросєді Андрій Ілліч","Андрій Ілліч Міросєді","Андрій Міросєді"]}},"source":"VULYK","intro":{"declaration_year":"2015"}}