{"income":{"5":{"family_comment":"","value":"288309","family":"","comment":""},"6":{"family_comment":"","value":"286764","family_hidden":false,"comment":"","family":""},"7":{"family_comment":"","value":"","source_name":"","family":"","comment":""},"8":{"family_comment":"","value":"","family":"","comment":""},"9":{"value":"1545","value_unclear":false,"family_hidden":false,"family_comment":"","family":"","comment":""},"10":{"value":"","family_comment":"","family_hidden":false,"value_hidden":false,"family_unclear":false,"family":"","comment":""},"11":{"family_comment":"","value":"","family":"","comment":""},"12":{"family_comment":"","value":"","family":"","comment":""},"13":{"family_comment":"","value":"","family":"","comment":""},"14":{"family_comment":"","value":"","family":"","comment":""},"15":{"family_comment":"","value":"","family":"","comment":""},"16":{"family_comment":"","value":"","family":"","comment":""},"17":{"family_comment":"","value":"","family":"","comment":""},"18":{"family_comment":"","value":"","family":"","comment":""},"19":{"family_comment":"","value":"","family":"","comment":""},"20":{"value":"","comment_unclear":false,"family_comment":"","family":"","comment":"","family_comment_unclear":false}},"vehicle":{"35":[{"brand_info":"4608 куб. см.","sum_rent_comment":"","brand":"Lexus LS 460","sum_comment":"","brand_unclear":false,"year":"2007","brand_hidden":false,"brand_info_unclear":false,"sum":"","sum_rent":"","sum_unclear":false}]},"id":"vulyk_75_66","banks":{"45":[{"sum_foreign_comment":"","sum_units":"UAH","sum_comment":"","sum_comment_unclear":false,"sum_foreign_units":"UAH","sum":"34045","sum_unclear":false,"sum_foreign":""}],"46":[{"sum_foreign_comment":"","sum_units":"UAH","sum_comment":"","sum_foreign_units":"UAH","sum":"26554","sum_foreign":""}]},"declaration":{"additional_info_text":"","notfull_lostpages":"","date":"2015-03-24T00:00:00","notfull":"","additional_info":"","url":"http://static.declarations.com.ua/declarations/chosen_ones/judges_batch/1869_bocharnykov_serhii_olehovych.pdf"},"liabilities":{"54":{"sum_foreign_comment":"","sum":"","sum_comment":"","sum_foreign":""},"55":{"sum_foreign_comment":"","sum":"","sum_comment":"","sum_foreign":""},"56":{"sum_foreign_comment":"","sum":"","sum_comment":"","sum_foreign":""},"57":{"sum_foreign_comment":"","sum":"","sum_comment":"","sum_foreign":""},"58":{"sum_foreign_comment":"","sum":"","sum_comment":"","sum_foreign":""},"59":{"sum_foreign_comment":"","sum":"","sum_comment":"","sum_comment_unclear":false,"sum_unclear":false,"sum_foreign":""},"60":{"sum_foreign_comment":"","sum":"","sum_comment":"","sum_foreign":""},"61":{"sum_foreign_comment":"","sum":"","sum_comment":"","sum_foreign":""},"62":{"sum_foreign_comment":"","sum":"","sum_comment":"","sum_unclear":false,"sum_foreign":""},"63":{"sum_foreign_comment":"","sum":"","sum_comment":"","sum_foreign":""},"64":{"sum_foreign_comment":"","sum":"","sum_comment":"","sum_foreign":""}},"ft_src":"Бочарников Сергій Олегович\nсуддя апеляційного суду запорізької області\nЗапорізька область\nЗагальний апеляційний суд\nСергій\nБочарников Сергій Олегович\nСергій Олегович Бочарников\nСергій Бочарников\nБочарников Сергій Олегович\nБочарников\nОлегович\nLexus LS 460\n4608 куб. см.\n2007\n26554\n34045\n2014\n4608 куб. см.\n2007\nLexus LS 460\n34045\n26554\n2014\nБочарников\nОлегович\nБочарников Сергій Олегович\nСергій Олегович Бочарников\nСергій Бочарников\nБочарников Сергій Олегович\nСергій\nБочарников Сергій Олегович\nЗагальний апеляційний суд\nсуддя апеляційного суду запорізької області\nЗапорізька область\n286764\n288309\n1545\n648\n212\n648\n212\nБочарников\nОлегович\nсуддя апеляційного суду запорізької області\nЗапорізька область\nЗагальний апеляційний суд\nБочарников Сергій Олегович\nБочарников Сергій Олегович\nСергій Олегович Бочарников\nСергій Бочарников\nБочарников Сергій Олегович\nСергій\n286764\n1545\n288309\n2007\nLexus LS 460\n4608 куб. см.\n1545\n288309\n286764\n648\n212\n34045\n26554\n2014","general":{"inn":"","inn_hidden":true,"last_name":"Бочарников","post":{"office":"Загальний апеляційний суд","region":"Запорізька область","post":"суддя апеляційного суду запорізької області"},"name":"Сергій","full_name":"Бочарников Сергій Олегович","family_raw":"","addresses":[{"place_district":"","place_address_hidden":true,"place_city":"","place_city_type_hidden":true,"place_district_hidden":false,"place_city_type":"","place_city_hidden":true,"place_address":"","place_hidden":true,"place":""}],"family":[{"inn":"","inn_hidden":false,"relations_hidden":true,"family_name":"","relations_other":"","relations":"","name_hidden":false,"name_unclear":false}],"full_name_suggest":{"output":"Бочарников Сергій Олегович","input":["Бочарников Сергій Олегович","Сергій Олегович Бочарников","Сергій Бочарников"]},"patronymic":"Олегович"},"source":"VULYK","estate":{"23":[{"costs":"","costs_comment":"","address_hidden":false,"region_hidden":true,"space_comment":"","space":"648","address":"","region":"","costs_rent_comment":"","space_units":"м²","space_units_hidden":false,"costs_rent":""}],"24":[{"costs_rent":"","region":"","costs":"","costs_rent_comment":"","costs_comment":"","region_hidden":true,"space_comment":"","space_units":"м²","space":"212","address":""}]},"intro":{"declaration_year":"2014","isnotdeclaration":""}}