{"income":{"5":{"family_comment":"","value":"1345145","family":"271536","comment":""},"6":{"family_comment":"","value":"217769","family":"255107","comment":""},"7":{"family_comment":"","value":"","source_name":"","family":"","comment":""},"8":{"family_comment":"","value":"","family":"","comment":""},"9":{"value":"","comment_unclear":false,"family_comment":"","family":"","comment":"","family_comment_unclear":false},"10":{"family_comment":"","value":"13398","family":"16429","comment":""},"11":{"family_comment":"","value":"","family":"","comment":""},"12":{"family_comment":"","value":"","family":"","comment":""},"13":{"family_comment":"","value":"","family":"","comment":""},"14":{"family_comment":"","value":"","family":"","comment":""},"15":{"family_comment":"","value":"","family":"","comment":""},"16":{"family_comment":"","value":"1113978","family":"","comment":""},"17":{"family_comment":"","value":"","family":"","comment":""},"18":{"family_comment":"","value":"","family":"","comment":""},"19":{"value":"","family_comment":"","value_unclear":false,"family_unclear":false,"family":"","comment":""},"20":{"value":"","family_comment":"","value_unclear":false,"comment_hidden":false,"family_comment_hidden":false,"family_unclear":false,"family_comment_unclear":false,"comment_unclear":false,"comment":"","family":""}},"vehicle":{"35":[{"brand_info":"2000 куб. см., 110 кВт (1 /2 частка)","sum_rent_comment":"","brand":"Mitsubishi Lancer","sum_comment":"","year":"2007","sum_hidden":false,"brand_info_hidden":false,"brand_info_unclear":false,"year_unclear":false,"sum":"","sum_rent":""},{"brand_info":"1600 куб. см. (1 /2 частка","sum_rent_comment":"","brand":"Suzuki SX4 new","sum_comment":"","year":"2013","sum":"","sum_rent":""}],"40":[{"year_hidden":false,"brand_info":"2000 куб. см., 110 кВт (1 /2 частка)","sum_rent_comment":"","brand":"Mitsubishi Lancer","sum_comment":"","year":"2007","brand_hidden":false,"brand_info_hidden":false,"brand_info_unclear":false,"sum":"","sum_rent":""},{"brand_info":"1600 куб. см. (1 /2 частина","sum_rent_comment":"","brand":"Suzuki SX4 new","sum_comment":"","year":"2013","brand_info_hidden":false,"sum":"","sum_rent":""}]},"id":"vulyk_106_120","declaration":{"additional_info_text":"","notfull_lostpages":"","date":"2016-03-30T00:00:00","notfull":"","additional_info":"","url":"http://static.declarations.com.ua/declarations/chosen_ones/judges_batch/2259_panchenko_olha_mykhailivna.pdf"},"liabilities":{"54":{"sum_foreign_comment":"","sum":"","sum_comment":"","sum_comment_unclear":false,"sum_hidden":false,"sum_comment_hidden":false,"sum_foreign":""},"55":{"sum_foreign_comment":"","sum":"","sum_hidden":false,"sum_comment":"","sum_foreign":""},"56":{"sum_foreign_comment":"","sum":"","sum_comment":"","sum_hidden":false,"sum_comment_hidden":false,"sum_unclear":false,"sum_foreign":""},"57":{"sum_foreign_comment":"","sum":"","sum_comment":"","sum_hidden":false,"sum_comment_hidden":false,"sum_foreign":""},"58":{"sum_foreign_comment":"","sum":"","sum_comment":"","sum_hidden":false,"sum_comment_hidden":false,"sum_foreign":""},"59":{"sum_foreign_comment":"","sum":"","sum_comment":"","sum_foreign":""},"60":{"sum_foreign_comment":"","sum":"","sum_comment":"","sum_hidden":false,"sum_comment_hidden":false,"sum_foreign":""},"61":{"sum_foreign_comment":"","sum":"","sum_comment":"","sum_foreign":""},"62":{"sum_foreign_comment":"","sum":"","sum_comment":"","sum_comment_hidden":false,"sum_unclear":false,"sum_foreign":""},"63":{"sum_foreign_comment":"","sum":"","sum_comment":"","sum_foreign":""},"64":{"sum_foreign_comment":"","sum":"","sum_comment":"","sum_foreign":""}},"ft_src":"суддя дніпропетровського апеляційного адміністративного суду\nДніпропетровська область\nАпеляційний адміністративний суд\nОльга\nМельник В. В\nПодружжя\nМихайлівна\nПанченко Ольга Михайлівна\nОльга Михайлівна Панченко\nОльга Панченко\nПанченко Ольга Михайлівна\nПанченко Ольга Михайлівна\nПанченко\nMitsubishi Lancer\n2000 куб. см., 110 кВт (1 /2 частка)\n2007\n1600 куб. см. (1 /2 частка\n2013\nSuzuki SX4 new\n2000 куб. см., 110 кВт (1 /2 частка)\nMitsubishi Lancer\n2007\n1600 куб. см. (1 /2 частина\n2013\nSuzuki SX4 new\n600\n30.5\n400500\n72.8\n2015\n255107\n217769\n16429\n13398\n271536\n1345145\n1113978\n2000 куб. см., 110 кВт (1 /2 частка)\n2007\nMitsubishi Lancer\n1600 куб. см. (1 /2 частка\nSuzuki SX4 new\n2013\n2000 куб. см., 110 кВт (1 /2 частка)\n2007\nMitsubishi Lancer\nSuzuki SX4 new\n1600 куб. см. (1 /2 частина\n2013\n600\n30.5\n400500\n72.8\nПанченко Ольга Михайлівна\nОльга Михайлівна Панченко\nОльга Панченко\nПанченко Ольга Михайлівна\nПанченко Ольга Михайлівна\nПодружжя\nМельник В. В\nОльга\nПанченко\nДніпропетровська область\nАпеляційний адміністративний суд\nсуддя дніпропетровського апеляційного адміністративного суду\nМихайлівна\n217769\n255107\n1345145\n271536\n1113978\n13398\n16429\n2015\nМельник В. В\nПодружжя\nМихайлівна\nПанченко\nОльга\nПанченко Ольга Михайлівна\nОльга Михайлівна Панченко\nОльга Панченко\nПанченко Ольга Михайлівна\nДніпропетровська область\nАпеляційний адміністративний суд\nсуддя дніпропетровського апеляційного адміністративного суду\nПанченко Ольга Михайлівна\n2007\nMitsubishi Lancer\n2000 куб. см., 110 кВт (1 /2 частка)\nSuzuki SX4 new\n1600 куб. см. (1 /2 частка\n2013\nMitsubishi Lancer\n2000 куб. см., 110 кВт (1 /2 частка)\n2007\nSuzuki SX4 new\n1600 куб. см. (1 /2 частина\n2013\n16429\n13398\n271536\n1345145\n1113978\n255107\n217769\n30.5\n400500\n72.8\n600\n2015","general":{"inn":"","name":"Ольга","inn_unclear":false,"family":[{"inn":"","inn_hidden":true,"relations_unclear":false,"relations_hidden":false,"relations_other":"","relations":"Подружжя","name_hidden":true,"family_name":"Мельник В. В","name_unclear":false}],"inn_hidden":true,"family_raw":"","last_name":"Панченко","post":{"region_unclear":false,"region":"Дніпропетровська область","post":"суддя дніпропетровського апеляційного адміністративного суду","office":"Апеляційний адміністративний суд","office_unclear":false,"post_hidden":false},"full_name":"Панченко Ольга Михайлівна","addresses":[{"place_district":"","place_city_hidden":true,"place_city":"","place_city_type_hidden":true,"place_district_hidden":true,"place_city_type":"","place_address_hidden":true,"place_address":"","place_hidden":true,"place":""}],"patronymic":"Михайлівна","full_name_suggest":{"output":"Панченко Ольга Михайлівна","input":["Панченко Ольга Михайлівна","Ольга Михайлівна Панченко","Ольга Панченко"]},"name_unclear":false},"source":"VULYK","estate":{"23":[{"region_unclear":false,"space_hidden":false,"costs":"","costs_comment":"","address_hidden":true,"region_hidden":true,"space_comment":"","space_unclear":false,"space":"600","address":"","costs_comment_unclear":false,"costs_rent_comment_unclear":false,"region":"","address_unclear":false,"costs_rent_comment":"","space_comment_unclear":false,"space_comment_hidden":false,"space_units":"м²","costs_rent":""}],"25":[{"costs":"","costs_comment":"","address_hidden":true,"region_hidden":true,"space_comment":"","space":"30.5","address":"","region":"","costs_rent_comment":"","space_comment_unclear":false,"space_units":"м²","costs_rent":""},{"space_unclear":false,"costs":"400500","costs_comment":"","address_hidden":false,"region_hidden":false,"space_comment":"","space":"72.8","address":"","region":"","costs_rent_comment":"","space_comment_unclear":false,"space_units":"м²","costs_rent":""}]},"intro":{"declaration_year":"2015","isnotdeclaration":""}}