{"income":{"5":{"value":"2530384.69","value_unclear":false,"family_hidden":false,"family_comment":"","family":"","comment":""},"6":{"family_comment":"","value":"261884.69","family":"","comment":""},"7":{"family_comment":"","value":"","source_name":"","family":"","comment":""},"8":{"family_comment":"","value":"","family":"","comment":""},"9":{"family_comment":"","value":"","family":"","comment":""},"10":{"family_comment":"","value":"","family":"","comment":""},"11":{"family_comment":"","value":"","family":"","comment":"","family_hidden":false},"12":{"family_comment":"","value":"","family":"","comment":""},"13":{"family_comment":"","value":"","family":"","comment":""},"14":{"family_comment":"","value":"","family":"","comment":""},"15":{"family_comment":"","value":"","family":"","comment":""},"16":{"family_comment":"","value":"1146000","family":"","comment":""},"17":{"family_comment":"","value":"","family":"","comment":"","family_comment_unclear":false},"18":{"family_comment":"","value":"","family":"","comment":""},"19":{"family_comment":"","value":"","family":"","comment":""},"20":{"value":"1122500","family_comment":"","family_hidden":false,"family_unclear":false,"family":"","comment":"позика"}},"vehicle":{"35":[{"brand_info":"","sum":"1738074.14","brand":"BMW X5","sum_comment":"","brand_unclear":false,"year":"2015","brand_hidden":false,"brand_info_hidden":false,"brand_info_unclear":false,"sum_rent_comment":"","sum_rent":""}]},"id":"vulyk_103_30","declaration":{"date":"2016-03-16T00:00:00","additional_info_text":"","additional_info":"","url":"http://static.declarations.com.ua/declarations/chosen_ones/judges_batch/1254_ivanenko_iuliia_hennadiivna.pdf"},"liabilities":{"54":{"sum_foreign_comment":"","sum_unclear":false,"sum":"86103","sum_comment":"","sum_foreign_comment_hidden":false,"sum_hidden":false,"sum_foreign_comment_unclear":false,"sum_comment_hidden":true,"sum_foreign_hidden":false,"sum_foreign":""},"55":{"sum_foreign_comment":"","sum":"","sum_comment":"","sum_foreign":""},"56":{"sum_foreign_comment":"","sum":"","sum_comment":"","sum_foreign":""},"57":{"sum_foreign_comment":"","sum":"","sum_comment":"","sum_foreign_comment_hidden":false,"sum_hidden":false,"sum_comment_hidden":false,"sum_foreign_hidden":false,"sum_foreign":""},"58":{"sum_foreign_comment":"","sum":"","sum_comment":"","sum_foreign_comment_hidden":false,"sum_hidden":false,"sum_comment_hidden":false,"sum_foreign_hidden":false,"sum_foreign":""},"59":{"sum_foreign_comment":"","sum":"","sum_comment":"","sum_foreign_comment_hidden":false,"sum_hidden":false,"sum_comment_hidden":false,"sum_foreign_hidden":false,"sum_foreign":""},"60":{"sum_foreign_comment":"","sum":"","sum_comment":"","sum_hidden":false,"sum_comment_hidden":false,"sum_foreign":""},"61":{"sum_foreign_comment":"","sum":"","sum_comment":"","sum_foreign":""},"62":{"sum_foreign_comment":"","sum_comment":"","sum":"","sum_comment_hidden":false,"sum_foreign":""},"63":{"sum_foreign_comment":"","sum":"","sum_comment":"","sum_foreign":""},"64":{"sum_foreign_comment":"","sum":"","sum_comment":"","sum_foreign":""}},"ft_src":"BMW X5\n1738074.14\n2015\n.1\n69\n240\n2015\n261884.69\n2530384.69\n1146000\nпозика\n1122500\n2015\n1738074.14\nBMW X5\n.1\n240\n69\nІваненко\nІваненко Юлія Геннадіївна\nЮлія Геннадіївна Іваненко\nЮлія Іваненко\nІваненко Юлія Геннадіївна\nІваненко Юлія Геннадіївна\nГеннадіївна\nДитина\nФролькіс Н. С\nЮлія\nВищий спеціалізований суд з розгляду цивільних і кримінальних справ\nсуддя вищого спецiалiзованого суду україни з розгляду цивiльних і кримiнальних справ\nЗагальнодержавний регіон\n86103\n261884.69\nпозика\n1122500\n2530384.69\n1146000\n2015\n86103\nДитина\nФролькіс Н. С\nІваненко\nГеннадіївна\nсуддя вищого спецiалiзованого суду україни з розгляду цивiльних і кримiнальних справ\nВищий спеціалізований суд з розгляду цивільних і кримінальних справ\nЗагальнодержавний регіон\nІваненко Юлія Геннадіївна\nІваненко Юлія Геннадіївна\nЮлія Геннадіївна Іваненко\nЮлія Іваненко\nІваненко Юлія Геннадіївна\nЮлія","general":{"inn_hidden":true,"inn":"","last_name":"Іваненко","post":{"region":"Загальнодержавний регіон","office":"Вищий спеціалізований суд з розгляду цивільних і кримінальних справ","post":"суддя вищого спецiалiзованого суду україни з розгляду цивiльних і кримiнальних справ","office_unclear":false,"region_unclear":false},"name":"Юлія","full_name":"Іваненко Юлія Геннадіївна","family_raw":"","addresses":[{"place_district":"","place_address_hidden":true,"place_city":"","place_address":"","place_district_hidden":true,"place_city_type":"","place_city_hidden":true,"place_city_type_hidden":true,"place_hidden":true,"place":""}],"family":[{"inn":"","relations":"Дитина","relations_hidden":false,"inn_hidden":true,"family_name":"Фролькіс Н. С","relations_other":"","name_hidden":true,"name_unclear":true}],"full_name_suggest":{"output":"Іваненко Юлія Геннадіївна","input":["Іваненко Юлія Геннадіївна","Юлія Геннадіївна Іваненко","Юлія Іваненко"]},"patronymic":"Геннадіївна"},"source":"VULYK","estate":{"23":[{"costs_rent":"","region":"","costs":"","costs_rent_comment":"","costs_comment":"","address_hidden":true,"region_hidden":true,"space_comment":"","space_units":"га","space":".1","address":""}],"26":[{"costs_rent":"","region":"","costs":"","costs_rent_comment":"","costs_comment":"","address_hidden":true,"region_hidden":true,"space_comment":"","space_units":"м²","space":"240","address":""}],"31":[{"space_hidden":false,"address_hidden":true,"region_hidden":true,"space_comment":"","space":"69","address":"","costs_property":"","costs_rent_comment":"","address_unclear":false,"space_units":"м²","costs_property_comment":"","costs_rent":""}]},"intro":{"declaration_year":"2015"}}