{"id":"vulyk_105_65","ft_src":"1490 куб. см., 1.5 кВт\nВАЗ 21103\n2004\n2400 куб. см., 112 кВт\n2004\nToyota Camry\n4.4\n2014\n223350\n7466\n13398\n7466\n236748\n1490 куб. см., 1.5 кВт\n2004\nВАЗ 21103\nToyota Camry\n2400 куб. см., 112 кВт\n2004\n2014\nсуддя київського апеляційного господарського суду\nАпеляційний господарський суд\nм. Київ\nДоманська\nДоманська Марина Леонідівна\nМарина Леонідівна Доманська\nМарина Доманська\nДоманська Марина Леонідівна\nДоманська Марина Леонідівна\nМарина\nЛеонідівна\nПодружжя\nДоманський О. В\nІнше\nсин чоловіка\nДоманський А. О\nДитина\nДоманська М. О\nДоманська А. О\nДитина\n223350\n7466\n236748\n7466\n13398\n4.4\nДоманський О. В\nПодружжя\nсин чоловіка\nДоманський А. О\nІнше\nДоманська М. О\nДитина\nДоманська А. О\nДитина\nЛеонідівна\nДоманська\nм. Київ\nсуддя київського апеляційного господарського суду\nАпеляційний господарський суд\nДоманська Марина Леонідівна\nДоманська Марина Леонідівна\nМарина Леонідівна Доманська\nМарина Доманська\nДоманська Марина Леонідівна\nМарина","estate":{"31":[{"costs_property_comment":"","address":"","space_units":"м²","space_hidden":false,"space_comment":"","region_hidden":true,"costs_property":"","region":"","address_hidden":false,"costs_rent_comment":"","space":"4.4","costs_rent":""}]},"vehicle":{"40":[{"sum_comment":"","brand_info_hidden":false,"sum_rent":"","sum":"","sum_rent_comment":"","brand_hidden":false,"brand":"ВАЗ 21103","brand_info":"1490 куб. см., 1.5 кВт","year_hidden":false,"year":"2004"},{"sum_comment":"","brand_info_hidden":false,"brand_info":"2400 куб. см., 112 кВт","sum":"","sum_rent_comment":"","year":"2004","brand":"Toyota Camry","sum_rent":""}]},"source":"VULYK","income":{"5":{"family_comment":"","family_hidden":false,"value":"236748","family":"7466","comment":""},"6":{"family_comment":"","family_hidden":false,"value":"223350","family":"","comment":""},"7":{"family":"","family_comment":"","value":"","comment":"","source_name":""},"8":{"family_comment":"","value":"","family":"","comment":""},"9":{"family_comment":"","value":"","family":"","comment":""},"10":{"family_comment":"","value":"13398","family":"","comment":""},"11":{"family_comment":"","value":"","family":"","comment":""},"12":{"family_comment":"","value":"","family":"","comment":""},"13":{"family_comment":"","value":"","family":"","comment":""},"14":{"family_comment":"","value":"","family":"","comment":""},"15":{"family_comment":"","value":"","family":"7466","comment":""},"16":{"family_comment":"","value":"","family":"","comment":""},"17":{"family_comment":"","value":"","family":"","comment":""},"18":{"family_comment":"","value":"","family":"","comment":""},"19":{"family_comment":"","value":"","family":"","comment":""},"20":{"family_comment":"","value":"","family":"","comment":""}},"general":{"inn":"","addresses":[{"place_city_type_hidden":false,"place_city_type":"","place_city_hidden":true,"place_hidden":true,"place_district":"","place_district_hidden":false,"place":"","place_address":"","place_address_hidden":true,"place_city":""}],"last_name":"Доманська","full_name":"Доманська Марина Леонідівна","family":[{"inn":"","family_name":"Доманський О. В","relations_other":"","relations_hidden":false,"name_unclear":false,"inn_hidden":true,"name_hidden":true,"relations":"Подружжя"},{"inn":"","family_name":"Доманський А. О","relations_other":"син чоловіка","name_unclear":false,"inn_hidden":true,"name_hidden":true,"relations":"Інше"},{"inn":"","family_name":"Доманська М. О","relations_other":"","name_unclear":false,"inn_hidden":false,"name_hidden":true,"relations":"Дитина"},{"inn":"","name_hidden":true,"family_name":"Доманська А. О","relations":"Дитина"}],"patronymic":"Леонідівна","inn_hidden":true,"name":"Марина","post":{"office":"Апеляційний господарський суд","post":"суддя київського апеляційного господарського суду","office_unclear":false,"office_hidden":false,"region":"м. Київ","region_unclear":false,"post_unclear":false},"family_raw":"","full_name_suggest":{"input":["Доманська Марина Леонідівна","Марина Леонідівна Доманська","Марина Доманська"],"output":"Доманська Марина Леонідівна"}},"liabilities":{"54":{"sum_comment":"","sum_foreign_comment":"","sum_foreign":"","sum":"","sum_comment_hidden":false},"55":{"sum_comment":"","sum_foreign_comment":"","sum_foreign":"","sum":""},"56":{"sum_comment":"","sum_foreign_comment":"","sum_foreign":"","sum":""},"57":{"sum_comment_unclear":false,"sum_comment":"","sum":"","sum_foreign_comment":"","sum_foreign":"","sum_comment_hidden":false},"58":{"sum_comment":"","sum_foreign_comment":"","sum_foreign":"","sum":""},"59":{"sum_comment":"","sum_foreign_comment":"","sum_foreign":"","sum":""},"60":{"sum_comment":"","sum_foreign_comment":"","sum_foreign":"","sum":""},"61":{"sum_comment":"","sum_foreign_comment":"","sum_foreign":"","sum":""},"62":{"sum_comment":"","sum_foreign_comment":"","sum_foreign":"","sum_hidden":false,"sum":""},"63":{"sum_comment":"","sum_foreign_comment":"","sum_foreign":"","sum":""},"64":{"sum_comment":"","sum_foreign_comment":"","sum_foreign":"","sum":""}},"declaration":{"additional_info_text":"","additional_info":"","date":"2015-03-30T00:00:00","url":"http://static.declarations.com.ua/declarations/chosen_ones/judges_batch/4640_domanska_maryna_leonidivna.pdf"},"intro":{"declaration_year":"2014"}}