{"income":{"5":{"family_comment":"","value":"216283","family":"","comment":""},"6":{"value":"216283","family_comment":"","value_unclear":false,"comment_hidden":false,"family_unclear":false,"family":"","comment":""},"7":{"family_comment":"","value":"","source_name":"","family":"","comment":""},"8":{"family_comment":"","value":"","family":"","comment":""},"9":{"family_comment":"","family_unclear":false,"value":"","family":"","comment":""},"10":{"family_comment":"","value":"","value_unclear":false,"family":"","comment":""},"11":{"family_comment":"","value":"","family":"","comment":""},"12":{"family_comment":"","value":"","family":"","comment":""},"13":{"family_comment":"","value":"","family":"","comment":""},"14":{"family_comment":"","value":"","family":"","comment":""},"15":{"family_comment":"","value":"","family":"","comment":""},"16":{"family_comment":"","value":"","family":"","comment":""},"17":{"family_comment":"","value":"","family":"","comment":""},"18":{"family_comment":"","value":"","family":"","comment":""},"19":{"family_comment":"","value":"","family":"","comment":""},"20":{"value":"","family":"","value_unclear":false,"family_hidden":false,"family_comment":"","comment_unclear":false,"comment":"","family_comment_unclear":false}},"id":"vulyk_97_139","banks":{"45":[{"sum_foreign_comment":"","sum_units":"UAH","sum_comment":"","sum_comment_unclear":false,"sum_hidden":false,"sum_foreign_units":"UAH","sum_comment_hidden":false,"sum_unclear":false,"sum":"700","sum_foreign":""}],"46":[{"sum_foreign_comment":"","sum_units":"UAH","sum_comment":"","sum_foreign_units":"UAH","sum_comment_hidden":false,"sum":"700","sum_foreign":""}]},"declaration":{"additional_info_text":"","notfull_lostpages":"","date":"2015-03-23T00:00:00","notfull":"","additional_info":"","url":"http://static.declarations.com.ua/declarations/chosen_ones/judges_batch/4041_dehtiarchuk_maryna_oleksandrivna.pdf"},"liabilities":{"54":{"sum_foreign_comment":"","sum":"","sum_comment":"","sum_comment_unclear":false,"sum_hidden":false,"sum_comment_hidden":false,"sum_unclear":false,"sum_foreign":""},"55":{"sum_foreign_comment":"","sum":"","sum_comment":"","sum_foreign":""},"56":{"sum_foreign_comment":"","sum":"","sum_comment":"","sum_foreign":""},"57":{"sum_foreign_comment":"","sum":"","sum_comment":"","sum_comment_unclear":false,"sum_hidden":false,"sum_comment_hidden":false,"sum_unclear":false,"sum_foreign":""},"58":{"sum_foreign_comment":"","sum":"","sum_comment":"","sum_comment_unclear":false,"sum_hidden":false,"sum_comment_hidden":false,"sum_unclear":false,"sum_foreign":""},"59":{"sum_foreign_comment":"","sum":"","sum_comment":"","sum_foreign":""},"60":{"sum_foreign_comment":"","sum":"","sum_comment":"","sum_comment_unclear":false,"sum_hidden":false,"sum_comment_hidden":false,"sum_foreign":""},"61":{"sum_foreign_comment":"","sum":"","sum_comment":"","sum_foreign":""},"62":{"sum_foreign_comment":"","sum":"","sum_comment":"","sum_unclear":false,"sum_foreign":""},"63":{"sum_foreign_comment":"","sum":"","sum_hidden":false,"sum_comment":"","sum_foreign":""},"64":{"sum_foreign_comment":"","sum":"","sum_comment":"","sum_foreign":""}},"ft_src":"Лозова\n64600\nХарківська область\nсуддя лозівського міськрайонного суду харківської області\nХарківська область\nЗагальний місцевий суд\nМарина\nОлександрівна\nДегтярчук Марина Олександрівна\nМарина Олександрівна Дегтярчук\nМарина Дегтярчук\nДегтярчук Марина Олександрівна\nДегтярчук Марина Олександрівна\nДегтярчук\n55\nм. Лозова\nХарківська область\n700\n700\n2014\n2014\nЗагальний місцевий суд\nХарківська область\nсуддя лозівського міськрайонного суду харківської області\nДегтярчук Марина Олександрівна\nМарина Олександрівна Дегтярчук\nМарина Дегтярчук\nДегтярчук Марина Олександрівна\nДегтярчук Марина Олександрівна\nМарина\nДегтярчук\nОлександрівна\nХарківська область\n64600\nЛозова\n216283\n216283\n55\nм. Лозова\nХарківська область\n700\n700\n216283\n216283\nОлександрівна\nДегтярчук\nМарина\nДегтярчук Марина Олександрівна\nМарина Олександрівна Дегтярчук\nМарина Дегтярчук\nДегтярчук Марина Олександрівна\n64600\nЛозова\nХарківська область\nХарківська область\nЗагальний місцевий суд\nсуддя лозівського міськрайонного суду харківської області\nДегтярчук Марина Олександрівна\n216283\n216283\nм. Лозова\nХарківська область\n55\n700\n700\n2014","general":{"name_hidden":false,"name":"Марина","last_name_hidden":false,"inn":"","last_name":"Дегтярчук","patronymic":"Олександрівна","inn_hidden":true,"family_raw":"","inn_unclear":false,"post":{"region_unclear":false,"region":"Харківська область","post":"суддя лозівського міськрайонного суду харківської області","office":"Загальний місцевий суд","office_unclear":false,"post_hidden":false},"full_name":"Дегтярчук Марина Олександрівна","addresses":[{"place_district":"","place_city_hidden":false,"place_city":"Лозова","place_city_unclear":false,"place_district_hidden":false,"place_city_type":"Місто","place_address_hidden":true,"place_city_type_hidden":false,"place_address":"64600","place_hidden":false,"place":"Харківська область"}],"patronymic_hidden":false,"full_name_suggest":{"output":"Дегтярчук Марина Олександрівна","input":["Дегтярчук Марина Олександрівна","Марина Олександрівна Дегтярчук","Марина Дегтярчук"]}},"source":"VULYK","estate":{"25":[{"region_unclear":false,"space_unclear":false,"costs":"","costs_comment":"","address_hidden":true,"region_hidden":false,"space_comment":"","space_hidden":false,"space":"55","address":"м. Лозова","region":"Харківська область","costs_rent_comment":"","space_comment_unclear":false,"space_comment_hidden":false,"space_units":"м²","costs_rent":""}]},"intro":{"declaration_year":"2014","isnotdeclaration":""}}