{"income":{"5":{"value":"33650","value_unclear":false,"comment_hidden":true,"family_comment":"","family":"100450","comment":""},"6":{"family_comment":"","value":"","family":"93450","comment":"","value_hidden":false},"7":{"family_comment":"","value":"","source_name":"","family":"","comment":""},"8":{"family_comment":"","value":"","family":"","comment":""},"9":{"family_comment":"","value":"","comment_hidden":false,"family":"","comment":""},"10":{"family_comment":"","value":"","family":"","comment":""},"11":{"family_comment":"","value":"","family":"","comment":""},"12":{"family_comment":"","value":"","family":"","comment":""},"13":{"family_comment":"","value":"","family":"","comment":""},"14":{"family_comment":"","value":"","family":"","comment":""},"15":{"family_comment":"","value":"","family":"","comment":"","family_comment_hidden":false},"16":{"family_comment":"","value":"","family":"","comment":""},"17":{"family_comment":"","value":"","family":"","comment":""},"18":{"family_comment":"","value":"","family":"","comment":"","value_hidden":false},"19":{"family_comment":"","value":"","family":"","comment":""},"20":{"family_comment":"","value":"33650","family":"7000","comment":"","family_comment_unclear":false}},"vehicle":{"35":[{"brand_info":"1799 куб. см.","sum_rent_comment":"","brand":"Honda Civic","sum_comment":"","year":"2008","sum":"","sum_rent":"5700"}]},"id":"vulyk_78_30","declaration":{"additional_info_text":"","notfull_lostpages":"","date":"2015-03-23T00:00:00","notfull":"","additional_info":"","url":"http://static.declarations.com.ua/declarations/chosen_ones/judges_batch/2097_busyk_olena_leonidivna.pdf"},"liabilities":{"54":{"sum_foreign_comment":"","sum_foreign_hidden":false,"sum_comment":"","sum_comment_unclear":false,"sum_hidden":false,"sum_comment_hidden":true,"sum":"870","sum_foreign":""},"55":{"sum_foreign_comment":"","sum":"","sum_comment":"","sum_foreign":""},"56":{"sum_foreign_comment":"","sum":"5700","sum_comment":"","sum_foreign":""},"57":{"sum_foreign_comment":"","sum":"","sum_comment":"","sum_foreign":""},"58":{"sum_foreign_comment":"","sum":"","sum_comment":"","sum_unclear":false,"sum_foreign":""},"59":{"sum_foreign_comment":"","sum":"","sum_comment":"","sum_foreign":""},"60":{"sum_foreign_comment":"","sum":"","sum_comment":"","sum_comment_unclear":false,"sum_comment_hidden":false,"sum_foreign":""},"61":{"sum_foreign_comment":"","sum":"","sum_comment":"","sum_foreign":""},"62":{"sum_foreign_comment":"","sum":"5200","sum_hidden":false,"sum_comment":"","sum_foreign":""},"63":{"sum_foreign_comment":"","sum_foreign_hidden":false,"sum_comment":"","sum":"","sum_unclear":false,"sum_foreign":""},"64":{"sum_foreign_comment":"","sum_foreign_hidden":false,"sum_comment":"","sum_hidden":false,"sum":"","sum_foreign":""}},"ft_src":"5200\n870\n5700\nсуддя печерського районного суду міста києва\nм. Київ\nЗагальний місцевий суд\nОлена\nЯхно О. А\nПодружжя\nЯхно С. О\nДитина\nЯхно Д. О\nДитина\nЯхно О. О\nДитина\nБусик О. О\nДитина\nЛеонідівна\nБусик Олена Леонідівна\nОлена Леонідівна Бусик\nОлена Бусик\nБусик Олена Леонідівна\nБусик\nБусик Олена Леонідівна\n1799 куб. см.\n2008\nHonda Civic\n5700\nслужбова\n97.8\n45.1\n2500\nм. Київ\n1/2 частина\n20.5\n2014\n93450\n100450\n33650\n7000\n33650\n1799 куб. см.\n2008\n5700\nHonda Civic\n2014\nПодружжя\nЯхно О. А\nДитина\nЯхно С. О\nДитина\nЯхно Д. О\nЯхно О. О\nДитина\nБусик О. О\nДитина\nБусик Олена Леонідівна\nОлена Леонідівна Бусик\nОлена Бусик\nБусик Олена Леонідівна\nБусик Олена Леонідівна\nОлена\nЛеонідівна\nЗагальний місцевий суд\nсуддя печерського районного суду міста києва\nм. Київ\nБусик\n870\n5700\n5200\n93450\n33650\n7000\n33650\n100450\n2500\n45.1\nслужбова\n97.8\n20.5\n1/2 частина\nм. Київ\n5700\n5200\n870\nПодружжя\nЯхно О. А\nДитина\nЯхно С. О\nДитина\nЯхно Д. О\nДитина\nЯхно О. О\nБусик О. О\nДитина\nЛеонідівна\nБусик\nОлена\nБусик Олена Леонідівна\nОлена Леонідівна Бусик\nОлена Бусик\nБусик Олена Леонідівна\nм. Київ\nсуддя печерського районного суду міста києва\nЗагальний місцевий суд\nБусик Олена Леонідівна\n5700\nHonda Civic\n1799 куб. см.\n2008\n7000\n33650\n33650\n100450\n93450\nслужбова\n97.8\n45.1\n1/2 частина\nм. Київ\n20.5\n2500\n2014","general":{"inn":"","name":"Олена","family":[{"inn":"","relations":"Подружжя","relations_other":"","inn_hidden":true,"family_name":"Яхно О. А","name_hidden":true,"name_unclear":false},{"inn":"","relations":"Дитина","relations_other":"","inn_hidden":false,"family_name":"Яхно С. О","name_hidden":false,"name_unclear":false},{"inn":"","relations":"Дитина","relations_other":"","inn_hidden":false,"family_name":"Яхно Д. О","name_unclear":false},{"inn":"","family_name":"Яхно О. О","relations":"Дитина","relations_other":""},{"inn":"","family_name":"Бусик О. О","relations":"Дитина","inn_hidden":true}],"patronymic":"Леонідівна","inn_hidden":true,"family_raw":"","last_name":"Бусик","post":{"post_unclear":false,"post":"суддя печерського районного суду міста києва","post_hidden":false,"region":"м. Київ","region_hidden":false,"office":"Загальний місцевий суд","office_hidden":false},"last_name_unclear":false,"full_name":"Бусик Олена Леонідівна","addresses":[{"place_district":"","place_city_hidden":true,"place_city":"","place_city_type_hidden":true,"place_district_hidden":true,"place_city_type":"","place_address_hidden":true,"place_address":"","place_hidden":true,"place":""}],"full_name_suggest":{"output":"Бусик Олена Леонідівна","input":["Бусик Олена Леонідівна","Олена Леонідівна Бусик","Олена Бусик"]},"name_unclear":false},"source":"VULYK","estate":{"25":[{"space_hidden":false,"costs":"","costs_comment":"","address_hidden":false,"region_hidden":true,"space_comment":"1/2 частина","space":"20.5","address":"","region":"м. Київ","address_unclear":false,"costs_rent_comment":"","space_units":"м²","costs_rent":""}],"29":[{"space_unclear":false,"address_hidden":true,"region_hidden":false,"space_comment":"","space":"2500","address":"","region":"","costs_property":"","costs_rent_comment":"","space_units":"м²","costs_property_comment":"","costs_rent":""}],"30":[{"space_hidden":false,"address_hidden":true,"region_hidden":false,"space_comment":"","space":"45.1","address":"","region":"","costs_property":"","costs_rent_comment":"","space_units":"м²","costs_property_comment":"","costs_rent":""}],"31":[{"address_hidden":true,"region_hidden":false,"space_comment":"службова","space":"97.8","address":"","region":"","costs_property":"","costs_rent_comment":"","address_unclear":false,"space_units":"м²","costs_property_comment":"","costs_rent":""}]},"intro":{"declaration_year":"2014"}}