{"id":"vulyk_92_63","ft_src":"1.6 л 110 кВт\nPeugeot 3008\n2011\nХарківська область\nм. Харків\n80.3\nм. Харків\n21.8\nХарківська область\nсоток\nХарківська область\nм. Харків\n10\nХарківська область\nДергачівський р-н\n87.3\nм. Харків\n80.3\nХарківська область\nДельта Банк\n3603\nАТ Дельта Банк\n105053\n2014\n1.6 л 110 кВт\nPeugeot 3008\n2011\n10\nм. Харків\nХарківська область\nсоток\n21.8\nХарківська область\nм. Харків\nХарківська область\nДергачівський р-н\n87.3\nХарківська область\nм. Харків\n80.3\n80.3\nХарківська область\nм. Харків\nПодружжя\nОчеретна Л. М\nОчеретний Сергій Степанович\nСергій Степанович Очеретний\nСергій Очеретний\nОчеретний Сергій Степанович\nОчеретний Сергій Степанович\nСергій\nОчеретний\nЗагальний апеляційний суд\nсуддя апеляційного суду харківської області\nХарківська область\nСтепанович\n269447\n81173\n5479\n691413\n6552\n335000\nспадщина\n5792\n1073\nАТ Дельта Банк\n105053\n3603\nДельта Банк\n2014\n269447\n1073\n5792\n6552\n691413\nспадщина\n335000\n5479\n81173\nПодружжя\nОчеретна Л. М\nСтепанович\nОчеретний\nСергій\nОчеретний Сергій Степанович\nСергій Степанович Очеретний\nСергій Очеретний\nОчеретний Сергій Степанович\nХарківська область\nЗагальний апеляційний суд\nсуддя апеляційного суду харківської області\nОчеретний Сергій Степанович","estate":{"25":[{"address":"м. Харків","space_units":"м²","space_hidden":false,"space_comment":"","region_hidden":false,"costs_comment":"","address_hidden":false,"costs":"","address_unclear":false,"space_comment_unclear":false,"costs_rent_comment":"","space":"80.3","region":"Харківська область","costs_rent":""}],"27":[{"address":"м. Харків","space_units":"м²","space_hidden":false,"space_unclear":true,"region_hidden":false,"costs_comment":"","space_comment":"","address_hidden":false,"costs":"","address_unclear":false,"costs_rent_comment":"","space":"21.8","region":"Харківська область","costs_rent":""}],"29":[{"costs_property_comment":"","costs_property":"","address":"м. Харків","space_units":"соток","space_unclear":false,"region_hidden":false,"space_units_unclear":false,"space_comment":"","address_hidden":false,"costs_rent_comment":"","space":"10","region":"Харківська область","space_units_hidden":false,"costs_rent":""}],"30":[{"costs_property_comment":"","address":"Дергачівський р-н","space_units":"м²","space_hidden":false,"space_unclear":false,"region_hidden":false,"costs_property":"","space_comment":"","address_hidden":false,"address_unclear":false,"costs_rent_comment":"","space":"87.3","region":"Харківська область","costs_rent":""}],"31":[{"costs_property_comment":"","address":"м. Харків","space_units":"м²","space_hidden":false,"space_unclear":false,"region_hidden":false,"costs_property":"","space_comment":"","address_hidden":false,"address_unclear":false,"costs_rent_comment":"","space":"80.3","region":"Харківська область","costs_rent":""}]},"vehicle":{"35":[{"sum_comment_unclear":false,"brand_info":"1.6 л 110 кВт","sum_rent_comment":"","brand_unclear":false,"brand_hidden":false,"year":"2011","sum_comment":"","brand_info_hidden":false,"sum_rent":"","brand":"Peugeot 3008","year_unclear":false,"brand_info_unclear":false,"sum":""}]},"source":"VULYK","income":{"5":{"family_comment":"","family_hidden":false,"value":"691413","family":"6552","comment":""},"6":{"family_comment":"","family":"","comment":"","value_unclear":false,"family_hidden":false,"value":"269447"},"7":{"family_comment":"","comment":"","family":"","value_unclear":false,"value":"","source_name":""},"8":{"family_comment":"","value":"","family":"","comment":""},"9":{"family_comment":"","value":"5792","family":"1073","comment":""},"10":{"family_comment":"","comment":"","family":"","family_unclear":false,"comment_unclear":false,"value":"","family_comment_unclear":false},"11":{"family_comment":"","value":"","family":"","comment":"","value_unclear":false},"12":{"family_comment":"","value":"","family":"","comment":""},"13":{"family_comment":"","value":"","family":"","comment":""},"14":{"family_comment":"","value":"","family":"","comment":""},"15":{"family_comment":"","comment":"","family":"","family_unclear":false,"comment_unclear":false,"value":""},"16":{"family_comment":"","value":"335000","family":"","comment":"спадщина"},"17":{"family_comment":"","value":"","family":"","comment":""},"18":{"family_comment":"","value":"","family_unclear":false,"family":"","comment":""},"19":{"family_comment":"","value":"","family":"","comment":""},"20":{"family_comment":"","value":"81173","family_unclear":false,"family":"5479","comment":""}},"banks":{"45":[{"sum_units":"UAH","sum_comment":"АТ Дельта Банк","sum_foreign_units_hidden":false,"sum_foreign_units":"UAH","sum_hidden":false,"sum":"105053","sum_foreign_comment":"","sum_foreign":"","sum_comment_hidden":false,"sum_foreign_hidden":false,"sum_comment_unclear":false}],"51":[{"sum_units":"UAH","sum_comment":"Дельта Банк","sum_foreign_units_hidden":false,"sum_foreign_units":"UAH","sum_hidden":false,"sum":"3603","sum_foreign_comment":"","sum_foreign_units_unclear":false,"sum_foreign":"","sum_unclear":false,"sum_foreign_hidden":false}]},"declaration":{"notfull_lostpages":"","additional_info_text":"","additional_info":"","date":"2015-03-30T00:00:00","notfull":"","url":"http://static.declarations.com.ua/declarations/chosen_ones/judges_batch/3311_ocheretnyi_serhii_stepanovych.pdf"},"general":{"family_raw":"","name":"Сергій","full_name_suggest":{"input":["Очеретний Сергій Степанович","Сергій Степанович Очеретний","Сергій Очеретний"],"output":"Очеретний Сергій Степанович"},"patronymic":"Степанович","inn_hidden":true,"patronymic_unclear":false,"inn":"","inn_unclear":true,"last_name":"Очеретний","full_name":"Очеретний Сергій Степанович","family":[{"inn":"","inn_unclear":false,"family_name":"Очеретна Л. М","relations_hidden":false,"name_unclear":false,"relations":"Подружжя","inn_hidden":false,"name_hidden":false,"relations_other":""}],"post":{"office":"Загальний апеляційний суд","post":"суддя апеляційного суду харківської області","office_unclear":false,"region_hidden":false,"region":"Харківська область","office_hidden":false,"post_unclear":false},"addresses":[{"place_city_type":"","place_address_unclear":false,"place_city_type_hidden":false,"place_hidden":true,"place_city_hidden":false,"place_district":"","place_district_hidden":false,"place":"","place_city":"","place_address_hidden":false,"place_address":""}]},"liabilities":{"54":{"sum_comment":"","sum_hidden":false,"sum":"","sum_foreign_comment":"","sum_foreign":"","sum_unclear":false},"55":{"sum_comment":"","sum_foreign_comment":"","sum_foreign":"","sum_unclear":false,"sum":""},"56":{"sum_comment_unclear":false,"sum_comment":"","sum_hidden":false,"sum":"","sum_foreign_comment":"","sum_foreign":"","sum_unclear":false},"57":{"sum_comment":"","sum_hidden":false,"sum":"","sum_foreign_comment":"","sum_foreign":"","sum_comment_hidden":false},"58":{"sum_comment":"","sum_foreign_comment":"","sum_foreign":"","sum":""},"59":{"sum_comment":"","sum_comment_unclear":false,"sum_foreign_comment":"","sum":"","sum_foreign":""},"60":{"sum_comment":"","sum_foreign_comment":"","sum_foreign":"","sum":""},"61":{"sum_comment":"","sum_foreign_comment":"","sum_foreign":"","sum":""},"62":{"sum_comment_unclear":false,"sum_comment":"","sum_hidden":false,"sum":"","sum_foreign_comment":"","sum_foreign":"","sum_unclear":false},"63":{"sum_comment":"","sum_foreign_comment":"","sum_foreign":"","sum":""},"64":{"sum_comment":"","sum_foreign_comment":"","sum_foreign":"","sum":""}},"intro":{"isnotdeclaration":"","declaration_year":"2014"}}