{"income":{"5":{"family_comment":"","value":"294088","value_unclear":false,"family":"64355","comment":""},"6":{"family_comment":"","value":"240323","value_unclear":false,"family":"17848","comment":""},"7":{"source_name_unclear":false,"value":"","family_hidden":false,"value_hidden":false,"family_comment":"","source_name":"","family":"","comment":"","source_name_hidden":false},"8":{"value":"","family_hidden":false,"value_hidden":false,"family_comment":"","family":"","comment":""},"9":{"value":"1","value_unclear":false,"value_hidden":false,"family_comment":"","comment_unclear":false,"comment":"","family":"46507"},"10":{"value":"13764","family_hidden":false,"value_hidden":false,"family_comment":"","family":"","comment":""},"11":{"value":"","family_hidden":false,"value_hidden":false,"family_comment":"","family":"","comment":""},"12":{"value":"","family_hidden":false,"value_hidden":false,"family_comment":"","family":"","comment":""},"13":{"value":"","family_hidden":false,"value_hidden":false,"family_comment":"","family":"","comment":""},"14":{"value":"","family_hidden":false,"value_hidden":false,"family_comment":"","family":"","comment":""},"15":{"value":"","family_hidden":false,"value_hidden":false,"family_comment":"","family":"","comment":""},"16":{"value":"40000","family_hidden":false,"value_hidden":false,"family_comment":"","family":"","comment":""},"17":{"value":"","family_hidden":false,"value_hidden":false,"family_comment":"","family":"","comment":""},"18":{"value":"","comment_unclear":false,"family_hidden":false,"value_hidden":false,"family_comment":"","family":"","comment":""},"19":{"value":"","family_hidden":false,"value_hidden":false,"family_comment":"","family":"","comment":""},"20":{"value":"","value_unclear":false,"family_hidden":false,"value_hidden":false,"family_comment":"","comment_unclear":false,"comment":"","family":""}},"vehicle":{"35":[{"brand_info":"2398 куб. см.,176 к.с.","sum_rent_comment":"","sum_rent_hidden":false,"year":"2010","sum_hidden":false,"brand_info_unclear":false,"sum_rent":"","sum":"","brand":"Hyundai Sonata","sum_comment":"","brand_unclear":false,"sum_rent_comment_hidden":false,"sum_comment_hidden":false,"sum_unclear":false}],"39":[{"brand_info":"мотоцикл, 400 куб.см., 32 к.с.","sum_rent_comment":"","brand":"Suzuki Intruder","sum_comment":"","year":"1994","brand_hidden":false,"sum":"","sum_rent":""}]},"id":"vulyk_1_383","banks":{"45":[{"sum_units":"UAH","sum_foreign":"","sum_hidden":false,"sum":"42","sum_units_hidden":false,"sum_foreign_comment":"","sum_foreign_hidden":false,"sum_comment":"","sum_foreign_units":"UAH","sum_units_unclear":false,"sum_comment_hidden":true,"sum_unclear":false}],"51":[{"sum_units":"UAH","sum_hidden":false,"sum":"428000","sum_units_hidden":false,"sum_foreign_comment":"","sum_foreign_hidden":false,"sum_comment":"","sum_comment_unclear":false,"sum_foreign_units":"UAH","sum_foreign":"","sum_comment_hidden":false,"sum_unclear":false}]},"declaration":{"additional_info_text":"","notfull_lostpages":"","date":"2014-03-17T00:00:00","notfull":"","additional_info":"","url":"http://static.declarations.com.ua/declarations/chosen_ones/judges_batch/59_kravtsov_oleh_viktorovych.pdf"},"liabilities":{"54":{"sum_foreign_comment":"","sum_foreign_hidden":false,"sum_comment":"","sum_hidden":false,"sum_foreign_comment_unclear":false,"sum_comment_hidden":false,"sum":"","sum_foreign":""},"55":{"sum_foreign_comment":"","sum":"","sum_hidden":false,"sum_comment":"","sum_foreign":""},"56":{"sum_foreign_comment":"","sum":"","sum_comment":"","sum_foreign":""},"57":{"sum_foreign_comment":"","sum_foreign_hidden":false,"sum_comment":"","sum_hidden":false,"sum_comment_hidden":false,"sum":"","sum_foreign":""},"58":{"sum_foreign_comment":"","sum":"","sum_comment":"","sum_hidden":false,"sum_comment_hidden":false,"sum_foreign":""},"59":{"sum_foreign_comment":"","sum_foreign_hidden":false,"sum_comment":"","sum_hidden":false,"sum":"","sum_foreign":""},"60":{"sum_foreign_comment":"","sum":"","sum_comment":"","sum_comment_unclear":false,"sum_hidden":false,"sum_comment_hidden":false,"sum_foreign":""},"61":{"sum_foreign_comment":"","sum":"","sum_hidden":false,"sum_comment":"","sum_foreign":""},"62":{"sum_foreign_comment":"","sum_foreign_hidden":false,"sum_comment":"","sum_comment_hidden":false,"sum_unclear":false,"sum":"","sum_foreign":""},"63":{"sum_foreign_comment":"","sum_foreign_hidden":false,"sum_comment":"","sum_hidden":false,"sum_comment_hidden":false,"sum":"","sum_foreign":""},"64":{"sum_foreign_comment":"","sum":"","sum_comment":"","sum_hidden":false,"sum_comment_hidden":false,"sum_foreign":""}},"ft_src":"суддя вищого адміністративного суду україни\nЗагальнодержавний регіон\nВищий адміністративний суд\nОлег\nДружина\nПодружжя\nСин\nДитина\nВікторович\nКравцов\nКравцов Олег Вікторович\nКравцов Олег Вікторович\nОлег Вікторович Кравцов\nОлег Кравцов\nКравцов Олег Вікторович\n1994\nмотоцикл, 400 куб.см., 32 к.с.\nSuzuki Intruder\nHyundai Sonata\n2398 куб. см.,176 к.с.\n2010\n12000\n63\n123\nслужбова\n428000\n42\n2013\n2398 куб. см.,176 к.с.\nHyundai Sonata\n2010\nмотоцикл, 400 куб.см., 32 к.с.\nSuzuki Intruder\n1994\n2013\nПодружжя\nДружина\nДитина\nСин\nКравцов Олег Вікторович\nОлег Вікторович Кравцов\nОлег Кравцов\nКравцов Олег Вікторович\nОлег\nКравцов Олег Вікторович\nВікторович\nсуддя вищого адміністративного суду україни\nВищий адміністративний суд\nЗагальнодержавний регіон\nКравцов\n240323\n17848\n294088\n64355\n40000\n1\n46507\n13764\n12000\n63\n123\nслужбова\n42\n428000\n17848\n240323\n46507\n1\n13764\n64355\n294088\n40000\nПодружжя\nДружина\nДитина\nСин\nОлег\nВікторович\nКравцов\nКравцов Олег Вікторович\nОлег Вікторович Кравцов\nОлег Кравцов\nКравцов Олег Вікторович\nЗагальнодержавний регіон\nВищий адміністративний суд\nсуддя вищого адміністративного суду україни\nКравцов Олег Вікторович\n1994\nмотоцикл, 400 куб.см., 32 к.с.\nSuzuki Intruder\n2010\nHyundai Sonata\n2398 куб. см.,176 к.с.\n1\n46507\n13764\n64355\n294088\n40000\n17848\n240323\n63\nслужбова\n123\n12000\n42\n428000\n2013","general":{"inn":"","name":"Олег","inn_unclear":false,"family":[{"inn":"","relations":"Подружжя","inn_unclear":false,"relations_hidden":false,"inn_hidden":true,"relations_other":"","name_hidden":true,"family_name":"Дружина","name_unclear":false},{"inn":"","relations":"Дитина","relations_hidden":false,"inn_hidden":false,"relations_other":"","name_hidden":false,"family_name":"Син","name_unclear":false}],"inn_hidden":true,"family_raw":"","last_name":"Кравцов","post":{"post":"суддя вищого адміністративного суду україни","region":"Загальнодержавний регіон","candidate":"","office_hidden":false,"post_hidden":false,"office":"Вищий адміністративний суд","region_hidden":false},"last_name_unclear":false,"full_name":"Кравцов Олег Вікторович","addresses":[{"place_city_type_unclear":false,"place_address":"","place_district_hidden":true,"place_city_type":"","place_address_hidden":true,"place_address_unclear":false,"place_city_type_hidden":false,"place":"","place_district":"","place_unclear":false,"place_city":"","place_city_unclear":false,"place_hidden":true,"place_city_hidden":true,"place_district_unclear":false}],"patronymic":"Вікторович","full_name_suggest":{"output":"Кравцов Олег Вікторович","input":["Кравцов Олег Вікторович","Олег Вікторович Кравцов","Олег Кравцов"]},"name_unclear":false},"source":"VULYK","estate":{"25":[{"region_unclear":false,"space_unclear":false,"costs":"","costs_comment":"","costs_hidden":false,"address_hidden":false,"region_hidden":true,"space_comment":"","space":"63","address":"","costs_rent_comment_unclear":false,"region":"","costs_rent_comment":"","costs_rent_hidden":false,"space_comment_unclear":false,"costs_rent_comment_hidden":false,"space_units":"м²","costs_comment_hidden":false,"costs_rent":"","costs_unclear":false},{"space_unclear":false,"costs":"","costs_comment":"","address_hidden":false,"region_hidden":false,"space_comment":"","space":"123","address":"","region":"","address_unclear":false,"costs_rent_comment":"службова","space_comment_unclear":false,"space_comment_hidden":false,"space_units":"м²","costs_rent":""}],"29":[{"space_unclear":false,"costs_property_hidden":false,"address_hidden":false,"region_hidden":true,"space_comment":"","space_hidden":false,"space":"12000","address":"","region":"","costs_property":"","costs_rent_comment":"","costs_rent_hidden":false,"space_comment_hidden":false,"space_units":"м²","costs_property_comment":"","costs_rent":""}]},"intro":{"declaration_year":"2013","isnotdeclaration":"","declaration_year_unclear":false,"declaration_year_hidden":false}}