{"income":{"5":{"family_comment":"","value":"213300","family":"134925","comment":""},"6":{"family_comment":"","value":"213300","value_unclear":false,"family":"120921","comment":""},"7":{"value":"","family_comment":"","source_name":"","family":"","comment":"","source_name_hidden":false},"8":{"family_comment":"","value":"","family":"","comment":""},"9":{"family_comment":"","value":"","family":"","comment":""},"10":{"family_comment":"","value":"","family":"","comment":""},"11":{"family_comment":"","value":"","comment_hidden":false,"family":"","comment":""},"12":{"family_comment":"","value":"","family":"","comment":""},"13":{"family_comment":"","value":"","family":"","comment":""},"14":{"family_comment":"","value":"","family":"","comment":""},"15":{"value":"","family_comment":"","value_unclear":false,"family_unclear":false,"family":"","comment":""},"16":{"family_comment":"","value":"","family":"","comment":""},"17":{"family_comment":"","value":"","family":"","comment":""},"18":{"family_comment":"","value":"","family":"","comment":""},"19":{"family_comment":"","value":"","family":"","comment":""},"20":{"family_comment":"пенсія","value":"","comment_unclear":false,"family":"14004","comment":""}},"id":"vulyk_104_14","declaration":{"date":"2016-03-29T00:00:00","additional_info_text":"","additional_info":"","url":"http://static.declarations.com.ua/declarations/chosen_ones/judges_batch/1812_korsakova_hanna_valeriivna_2015.pdf"},"liabilities":{"54":{"sum_foreign_comment":"","sum_foreign_hidden":false,"sum_comment":"","sum_hidden":false,"sum_comment_hidden":false,"sum_unclear":false,"sum":"","sum_foreign":""},"55":{"sum_foreign_comment":"","sum":"","sum_comment":"","sum_foreign":""},"56":{"sum_foreign_comment":"","sum":"","sum_comment":"","sum_unclear":false,"sum_foreign":""},"57":{"sum_foreign_comment":"","sum_foreign_hidden":false,"sum_comment":"","sum_comment_unclear":false,"sum_comment_hidden":false,"sum":"","sum_foreign":""},"58":{"sum_foreign_comment":"","sum":"","sum_comment":"","sum_unclear":false,"sum_foreign":""},"59":{"sum_foreign_comment":"","sum":"","sum_comment":"","sum_foreign":""},"60":{"sum_foreign_comment":"","sum_foreign_hidden":false,"sum_comment":"","sum_comment_hidden":false,"sum":"","sum_foreign":""},"61":{"sum_foreign_comment":"","sum":"","sum_comment":"","sum_foreign":""},"62":{"sum_foreign_comment":"","sum":"","sum_comment":"","sum_foreign":""},"63":{"sum_foreign_comment":"","sum":"","sum_comment":"","sum_foreign":""},"64":{"sum_foreign_comment":"","sum":"","sum_comment":"","sum_foreign":""}},"ft_src":"Корсакова Ганна Валеріївна\nсуддя київського апеляційного господарського суду\nм. Київ\nАпеляційний господарський суд\nГанна\nКорсаков К. В\nПодружжя\nКорсаков В. К\nДитина\nМала О. І\nБатьки\nКорсакова Ганна Валеріївна\nГанна Валеріївна Корсакова\nГанна Корсакова\nКорсакова Ганна Валеріївна\nКорсакова\nВалеріївна\n14004\nпенсія\n134925\n213300\n120921\n213300\n3/4 від 56,8\n56.8\n1/4 від 56,8\n56.8\n2015\n120921\n213300\n134925\n213300\n14004\nпенсія\n213300\n120921\n14004\nпенсія\n213300\n134925\nПодружжя\nКорсаков К. В\nДитина\nКорсаков В. К\nБатьки\nМала О. І\nКорсакова\nКорсакова Ганна Валеріївна\nГанна Валеріївна Корсакова\nГанна Корсакова\nКорсакова Ганна Валеріївна\nКорсакова Ганна Валеріївна\nГанна\nВалеріївна\nАпеляційний господарський суд\nсуддя київського апеляційного господарського суду\nм. Київ\n56.8\n3/4 від 56,8\n56.8\n1/4 від 56,8\n2015\nПодружжя\nКорсаков К. В\nДитина\nКорсаков В. К\nМала О. І\nБатьки\nВалеріївна\nКорсакова\nсуддя київського апеляційного господарського суду\nАпеляційний господарський суд\nм. Київ\nКорсакова Ганна Валеріївна\nКорсакова Ганна Валеріївна\nГанна Валеріївна Корсакова\nГанна Корсакова\nКорсакова Ганна Валеріївна\nГанна\n3/4 від 56,8\n56.8\n1/4 від 56,8\n56.8\n2015","general":{"inn":"","inn_hidden":true,"last_name":"Корсакова","post":{"region":"м. Київ","region_unclear":false,"post":"суддя київського апеляційного господарського суду","office_unclear":false,"office":"Апеляційний господарський суд"},"name":"Ганна","full_name":"Корсакова Ганна Валеріївна","family_raw":"","addresses":[{"place_district":"","place_city_hidden":true,"place_city":"","place_city_type_hidden":false,"place_district_hidden":false,"place_city_type":"","place_address_hidden":true,"place_address":"","place_hidden":true,"place":""}],"family":[{"inn":"","relations":"Подружжя","relations_other":"","inn_hidden":true,"family_name":"Корсаков К. В","name_hidden":false,"name_unclear":false},{"inn":"","relations":"Дитина","relations_other":"","inn_hidden":false,"family_name":"Корсаков В. К","name_hidden":false,"name_unclear":false},{"inn":"","relations":"Батьки","relations_other":"","inn_hidden":true,"family_name":"Мала О. І","name_unclear":false}],"full_name_suggest":{"output":"Корсакова Ганна Валеріївна","input":["Корсакова Ганна Валеріївна","Ганна Валеріївна Корсакова","Ганна Корсакова"]},"patronymic":"Валеріївна"},"source":"VULYK","estate":{"25":[{"costs":"","costs_comment":"","address_hidden":false,"region_hidden":true,"space_comment":"1/4 від 56,8","space":"56.8","address":"","costs_unclear":false,"region":"","costs_rent_comment":"","space_comment_unclear":false,"space_units":"м²","costs_rent":""}],"31":[{"space_unclear":false,"address_hidden":false,"region_hidden":true,"space_comment":"3/4 від 56,8","space_hidden":false,"space":"56.8","address":"","region":"","costs_property":"","costs_rent_comment":"","space_units":"м²","costs_property_comment":"","costs_rent":""}]},"intro":{"declaration_year":"2015","isnotdeclaration":""}}