{"id":"vulyk_74_179","ft_src":"1.6 л\nВАЗ 21124\n2007\nХарківська область\nм. Харків\n58.1\nм. Харків\nХарківська область\n32.4\n2013\n45047.67\n254562.44\n57047.67\n295362.44\n12000\n40800\n1.6 л\nВАЗ 21124\n2007\n2013\nЗагальний апеляційний суд\nХарківська область\nсуддя апеляційного суду харківської області\nВікторівна\nКарімова Лариса Вікторівна\nЛариса Вікторівна Карімова\nЛариса Карімова\nКарімова Лариса Вікторівна\nЛариса\nКарімова Лариса Вікторівна\nКарімова\nПодружжя\nКарімов В. Б., 15. 07. 1955 р. н\n45047.67\n254562.44\n40800\n12000\n295362.44\n57047.67\nХарківська область\nм. Харків\n58.1\n32.4\nм. Харків\nХарківська область\nПодружжя\nКарімов В. Б., 15. 07. 1955 р. н\nВікторівна\nКарімова\nХарківська область\nЗагальний апеляційний суд\nсуддя апеляційного суду харківської області\nКарімова Лариса Вікторівна\nКарімова Лариса Вікторівна\nЛариса Вікторівна Карімова\nЛариса Карімова\nКарімова Лариса Вікторівна\nЛариса","estate":{"25":[{"address":"м. Харків","space_units":"м²","space_hidden":false,"space_unclear":false,"region_hidden":false,"costs_comment":"","space_comment":"","address_hidden":false,"space":"32.4","costs_rent_comment":"","costs":"","region":"Харківська область","costs_rent":""}],"31":[{"costs_property_comment":"","address":"м. Харків","space_units":"м²","space_unclear":false,"region_hidden":false,"costs_property":"","space_comment":"","address_hidden":false,"address_unclear":false,"costs_rent_comment":"","space":"58.1","region":"Харківська область","costs_rent":""}]},"vehicle":{"35":[{"brand_info":"1.6 л","sum_rent_comment":"","brand_unclear":false,"year":"2007","brand_hidden":false,"sum_comment":"","brand_info_hidden":false,"sum_rent":"","brand":"ВАЗ 21124","year_unclear":false,"brand_info_unclear":false,"sum":""}]},"source":"VULYK","income":{"5":{"family_comment":"","family":"57047.67","comment":"","family_unclear":false,"family_hidden":false,"value":"295362.44"},"6":{"family_comment":"","family":"45047.67","comment":"","value_unclear":false,"family_unclear":false,"family_hidden":false,"value":"254562.44"},"7":{"source_name_hidden":false,"family_comment":"","family":"","value_hidden":false,"comment":"","family_hidden":false,"value":"","source_name":""},"8":{"family_comment":"","value":"","family":"","comment":""},"9":{"family_comment":"","value":"","family":"","comment":""},"10":{"family_comment":"","value":"","family":"","comment":"","value_unclear":false},"11":{"family_comment":"","value":"","family":"","comment":""},"12":{"family_comment":"","value":"","family":"","comment":""},"13":{"family_comment":"","value":"","family":"","comment":""},"14":{"family_comment":"","value":"","family":"","comment":""},"15":{"family_comment":"","value":"","family":"","comment":""},"16":{"family_comment":"","value":"","family":"","comment":""},"17":{"family_comment":"","value":"","family":"","comment":""},"18":{"family_comment":"","value":"","family":"","comment":""},"19":{"family_comment":"","value":"","family":"","comment":""},"20":{"family_comment":"","comment":"","family":"12000","value_unclear":false,"family_unclear":false,"comment_unclear":false,"value":"40800"}},"general":{"inn":"","addresses":[{"place_city_type_hidden":false,"place_city_type":"","place_city_hidden":false,"place_hidden":true,"place_district":"","place_district_hidden":false,"place":"","place_address":"","place_address_hidden":false,"place_city":""}],"last_name":"Карімова","full_name":"Карімова Лариса Вікторівна","family":[{"inn":"","family_name":"Карімов В. Б., 15. 07. 1955 р. н","relations_other":"","name_unclear":false,"inn_hidden":false,"name_hidden":false,"relations":"Подружжя"}],"patronymic":"Вікторівна","inn_hidden":true,"name":"Лариса","post":{"post_hidden":false,"office":"Загальний апеляційний суд","post":"суддя апеляційного суду харківської області","office_unclear":false,"region_unclear":false,"region":"Харківська область"},"family_raw":"","full_name_suggest":{"input":["Карімова Лариса Вікторівна","Лариса Вікторівна Карімова","Лариса Карімова"],"output":"Карімова Лариса Вікторівна"}},"liabilities":{"54":{"sum_comment_unclear":false,"sum_comment":"","sum":"","sum_foreign_comment":"","sum_foreign":"","sum_comment_hidden":false},"55":{"sum_comment":"","sum_hidden":false,"sum":"","sum_foreign_comment":"","sum_foreign":"","sum_unclear":false},"56":{"sum_comment":"","sum_hidden":false,"sum":"","sum_foreign_comment":"","sum_foreign":"","sum_unclear":false},"57":{"sum_comment_unclear":false,"sum_comment":"","sum":"","sum_foreign_comment":"","sum_foreign":"","sum_comment_hidden":false},"58":{"sum_comment":"","sum_foreign_comment":"","sum_foreign":"","sum":"","sum_comment_hidden":false},"59":{"sum_comment":"","sum_foreign_comment":"","sum_foreign":"","sum":""},"60":{"sum_comment":"","sum_foreign_comment":"","sum_foreign":"","sum_hidden":false,"sum":""},"61":{"sum_comment":"","sum_foreign_comment":"","sum_foreign":"","sum":""},"62":{"sum_comment":"","sum_foreign_comment":"","sum_foreign":"","sum":""},"63":{"sum_comment_unclear":false,"sum_comment":"","sum":"","sum_foreign_comment":"","sum_foreign":"","sum_unclear":false},"64":{"sum_comment_unclear":false,"sum_comment":"","sum":"","sum_foreign_comment":"","sum_foreign":"","sum_unclear":false}},"declaration":{"notfull_lostpages":"","additional_info_text":"","additional_info":"","date":"2014-03-25T00:00:00","notfull":"","url":"http://static.declarations.com.ua/declarations/chosen_ones/judges_batch/1514_karimova_larysa_viktorivna.pdf"},"intro":{"isnotdeclaration":"","declaration_year_unclear":false,"declaration_year":"2013"}}