{"income":{"5":{"family_comment":"","value":"265111.01","family":"11388","comment":""},"6":{"value":"251713.01","comment_hidden":false,"family_comment":"","family":"","comment":"","family_comment_hidden":false},"7":{"value":"","comment_unclear":false,"family_comment":"","source_name":"","family":"","comment":""},"8":{"family_comment":"","value":"","family":"","comment":""},"9":{"family_comment":"","value":"","family":"","comment":""},"10":{"family_comment":"","value":"13398","family_hidden":false,"comment":"","family":""},"11":{"family_comment":"","value":"","family":"","comment":""},"12":{"family_comment":"","value":"","family":"","comment":""},"13":{"family_comment":"","value":"","family":"","comment":""},"14":{"family_comment":"","value":"","family":"","comment":""},"15":{"family_comment":"","value":"","family":"","comment":""},"16":{"family_comment":"","value":"","family":"","comment":""},"17":{"family_comment":"","value":"","family":"","comment":""},"18":{"family_comment":"","value":"","family":"","comment":""},"19":{"family_comment":"","value":"","family":"","comment":""},"20":{"value":"","value_unclear":false,"family_hidden":false,"family_comment":"","family":"","comment":""}},"vehicle":{"35":[{"brand_info":"1598 куб. см. 77 кВт","sum_rent_comment":"","brand":"Skoda Octavia","sum_comment":"","year":"2008","brand_info_unclear":false,"sum":"","sum_rent":""}],"36":[{"brand_info":"2148 куб. см. 95 кВт","sum_rent_comment":"","brand":"Mercedes-Benz Sprinter 313","sum_comment":"","year":"2003","sum":"","sum_rent":""}]},"id":"vulyk_83_39","banks":{"53":[{"sum_foreign_comment":"","sum_units":"UAH","sum_comment":"","sum_comment_unclear":false,"sum_foreign_unclear":false,"sum_foreign_units":"UAH","sum_foreign_comment_unclear":false,"sum":"50000","sum_foreign":""}]},"declaration":{"additional_info_text":"","notfull_lostpages":"","date":"2015-03-23T00:00:00","notfull":"","additional_info":"","url":"http://static.declarations.com.ua/declarations/chosen_ones/judges_batch/2309_remez_petro_mykolaiovych.pdf"},"liabilities":{"54":{"sum_foreign_comment":"","sum":"","sum_comment":"","sum_foreign":""},"55":{"sum_foreign_comment":"","sum":"","sum_comment":"","sum_foreign":""},"56":{"sum_foreign_comment":"","sum":"17800","sum_comment":"","sum_foreign":""},"57":{"sum_foreign_comment":"","sum":"","sum_comment":"","sum_foreign":""},"58":{"sum_foreign_comment":"","sum":"","sum_comment":"","sum_foreign":""},"59":{"sum_foreign_comment":"","sum":"","sum_comment":"","sum_foreign":""},"60":{"sum_foreign_comment":"","sum":"","sum_comment":"","sum_foreign":""},"61":{"sum_foreign_comment":"","sum":"","sum_comment":"","sum_foreign":""},"62":{"sum_foreign_comment":"","sum":"15700","sum_comment":"","sum_foreign":""},"63":{"sum_foreign_comment":"","sum":"","sum_comment":"","sum_foreign":""},"64":{"sum_foreign_comment":"","sum":"","sum_comment":"","sum_foreign":""}},"ft_src":"15700\n17800\nсуддя апеляційного суду кіровоградської області\nКіровоградська область\nЗагальний апеляційний суд\nПетро\nРемез Л. В\nПодружжя\nМиколайович\nРемез Петро Миколайович\nПетро Миколайович Ремез\nПетро Ремез\nРемез Петро Миколайович\nРемез Петро Миколайович\nРемез\n1598 куб. см. 77 кВт\n2008\nSkoda Octavia\n2148 куб. см. 95 кВт\n2003\nMercedes-Benz Sprinter 313\n50000\n2014\n1598 куб. см. 77 кВт\nSkoda Octavia\n2008\n2148 куб. см. 95 кВт\n2003\nMercedes-Benz Sprinter 313\n50000\n2889\n403.3\n64.36\nПодружжя\nРемез Л. В\nРемез Петро Миколайович\nПетро Миколайович Ремез\nПетро Ремез\nРемез Петро Миколайович\nРемез Петро Миколайович\nПетро\nМиколайович\nЗагальний апеляційний суд\nКіровоградська область\nсуддя апеляційного суду кіровоградської області\nРемез\n17800\n15700\n251713.01\n265111.01\n11388\n13398\n2014\n17800\n15700\n403.3\n2889\n64.36\nРемез Л. В\nПодружжя\nМиколайович\nРемез\nПетро\nРемез Петро Миколайович\nПетро Миколайович Ремез\nПетро Ремез\nРемез Петро Миколайович\nКіровоградська область\nЗагальний апеляційний суд\nсуддя апеляційного суду кіровоградської області\nРемез Петро Миколайович\n251713.01\n13398\n11388\n265111.01\n2008\n1598 куб. см. 77 кВт\nSkoda Octavia\nMercedes-Benz Sprinter 313\n2148 куб. см. 95 кВт\n2003\n13398\n11388\n265111.01\n251713.01\n403.3\n64.36\n2889\n50000\n2014","general":{"inn":"","name":"Петро","inn_unclear":false,"family":[{"inn":"","inn_hidden":true,"relations_hidden":false,"family_name":"Ремез Л. В","relations_other":"","relations":"Подружжя","name_hidden":false,"name_unclear":false}],"inn_hidden":true,"family_raw":"","last_name":"Ремез","post":{"post_unclear":false,"post":"суддя апеляційного суду кіровоградської області","candidate":"","region":"Кіровоградська область","office":"Загальний апеляційний суд","office_unclear":false},"full_name_suggest":{"output":"Ремез Петро Миколайович","input":["Ремез Петро Миколайович","Петро Миколайович Ремез","Петро Ремез"]},"full_name":"Ремез Петро Миколайович","addresses":[{"place_city_type_unclear":false,"place_address":"","place_district_hidden":true,"place_city_type":"","place_address_hidden":true,"place_address_unclear":false,"place_city_type_hidden":true,"place":"","place_district":"","place_city_hidden":true,"place_city":"","place_city_unclear":false,"place_hidden":true}],"patronymic":"Миколайович","last_name_unclear":false},"source":"VULYK","estate":{"25":[{"region_unclear":false,"space_hidden":false,"costs":"","costs_comment":"","address_hidden":false,"region_hidden":true,"space_comment":"","space_unclear":false,"space":"64.36","address":"","region":"","costs_rent_comment":"","space_comment_unclear":false,"space_units":"м²","costs_rent":""}],"29":[{"address_hidden":false,"region_hidden":true,"space_comment":"","space":"2889","address":"","region":"","costs_property":"","costs_rent_comment":"","space_comment_unclear":false,"space_units":"м²","costs_property_comment":"","costs_rent":""}],"30":[{"address_hidden":false,"region_hidden":true,"space_comment":"","space":"403.3","address":"","region":"","costs_property":"","costs_rent_comment":"","space_comment_unclear":false,"space_units":"м²","costs_property_comment":"","costs_rent":""}]},"intro":{"declaration_year":"2014"}}