{"income":{"5":{"family_comment":"","value":"411124","family":"278462","comment":""},"6":{"family_comment":"","value":"200255","value_unclear":false,"family":"","comment":""},"7":{"value":"","family_comment":"","source_name":"","family":"","comment":"","source_name_hidden":false},"8":{"family_comment":"","value":"","family":"","comment":""},"9":{"family_comment":"","value":"197471","family":"263062","comment":""},"10":{"family_comment":"","value":"13398","family":"15400","comment":""},"11":{"family_comment":"","value":"","comment_hidden":false,"family":"","comment":""},"12":{"family_comment":"","value":"","family":"","comment":""},"13":{"family_comment":"","value":"","family":"","comment":""},"14":{"family_comment":"","value":"","family":"","comment":""},"15":{"value":"","family_comment":"","value_unclear":false,"family_unclear":false,"family":"","comment":""},"16":{"family_comment":"","value":"","family":"","comment":""},"17":{"family_comment":"","value":"","family":"","comment":""},"18":{"family_comment":"","value":"","family":"","comment":""},"19":{"family_comment":"","value":"","family":"","comment":""},"20":{"family_comment":"","value":"","comment_unclear":false,"family":"","comment":""}},"vehicle":{"40":[{"brand_info":"3.6","sum_rent_comment":"","brand":"Jeep Grand Cherokee","sum_comment":"","year":"2011","brand_hidden":false,"brand_info_hidden":false,"brand_info_unclear":false,"sum":"","sum_rent":""}]},"id":"vulyk_104_154","banks":{"45":[{"sum_foreign_comment":"","sum_units":"UAH","sum_comment":"","sum_hidden":false,"sum_foreign_units":"UAH","sum_foreign_hidden":false,"sum_comment_hidden":false,"sum_unclear":false,"sum":"1350000","sum_foreign":""}],"46":[{"sum_foreign_comment":"","sum_units":"UAH","sum_comment":"","sum_hidden":false,"sum_foreign_units":"UAH","sum_comment_hidden":false,"sum":"873000","sum_foreign":""}],"51":[{"sum_foreign_comment":"","sum_foreign_hidden":false,"sum_comment":"","sum_comment_unclear":false,"sum_hidden":false,"sum_foreign_units":"UAH","sum_foreign_comment_unclear":false,"sum_comment_hidden":false,"sum_units":"UAH","sum":"1330000","sum_foreign":""}]},"declaration":{"date":"2016-03-31T00:00:00","additional_info_text":"","additional_info":"","url":"http://static.declarations.com.ua/declarations/chosen_ones/judges_batch/1952_ivanov_dem_ian_leonidovych_2015.pdf"},"liabilities":{"54":{"sum_foreign_comment":"","sum_foreign_hidden":false,"sum_comment":"","sum_hidden":false,"sum_comment_hidden":false,"sum_unclear":false,"sum":"","sum_foreign":""},"55":{"sum_foreign_comment":"","sum":"","sum_comment":"","sum_foreign":""},"56":{"sum_foreign_comment":"","sum":"","sum_comment":"","sum_unclear":false,"sum_foreign":""},"57":{"sum_foreign_comment":"","sum_foreign_hidden":false,"sum_comment":"","sum_comment_unclear":false,"sum_comment_hidden":false,"sum":"","sum_foreign":""},"58":{"sum_foreign_comment":"","sum":"","sum_comment":"","sum_unclear":false,"sum_foreign":""},"59":{"sum_foreign_comment":"","sum":"","sum_comment":"","sum_foreign":""},"60":{"sum_foreign_comment":"","sum_foreign_hidden":false,"sum_comment":"","sum_comment_hidden":false,"sum":"","sum_foreign":""},"61":{"sum_foreign_comment":"","sum":"","sum_comment":"","sum_foreign":""},"62":{"sum_foreign_comment":"","sum":"","sum_comment":"","sum_foreign":""},"63":{"sum_foreign_comment":"","sum":"","sum_comment":"","sum_foreign":""},"64":{"sum_foreign_comment":"","sum":"","sum_comment":"","sum_foreign":""}},"ft_src":"Іванов Дем'ян Леонідович\nсуддя апеляційного суду кіровоградської області\nКіровоградська область\nЗагальний апеляційний суд\nДем'ян\nКорольова О. В\nПодружжя\nІванова Є. Д\nДитина\nІванова З. Д\nДитина\nІванов Дем'ян Леонідович\nДем'ян Леонідович Іванов\nДем'ян Іванов\nІванов Дем'ян Леонідович\nІванов\nЛеонідович\nJeep Grand Cherokee\n3.6\n2011\n873000\n1330000\n1350000\n2015\nJeep Grand Cherokee\n3.6\n2011\n1350000\n1330000\n873000\n2015\nПодружжя\nКорольова О. В\nДитина\nІванова Є. Д\nДитина\nІванова З. Д\nІванов\nІванов Дем'ян Леонідович\nДем'ян Леонідович Іванов\nДем'ян Іванов\nІванов Дем'ян Леонідович\nІванов Дем'ян Леонідович\nДем'ян\nЛеонідович\nЗагальний апеляційний суд\nсуддя апеляційного суду кіровоградської області\nКіровоградська область\n200255\n411124\n278462\n197471\n263062\n13398\n15400\n1199.5\n111\n86\n1199.5\n86\n111\nПодружжя\nКорольова О. В\nДитина\nІванова Є. Д\nІванова З. Д\nДитина\nЛеонідович\nІванов\nсуддя апеляційного суду кіровоградської області\nЗагальний апеляційний суд\nКіровоградська область\nІванов Дем'ян Леонідович\nІванов Дем'ян Леонідович\nДем'ян Леонідович Іванов\nДем'ян Іванов\nІванов Дем'ян Леонідович\nДем'ян\n200255\n263062\n197471\n15400\n13398\n278462\n411124\nJeep Grand Cherokee\n3.6\n2011\n263062\n197471\n15400\n13398\n278462\n411124\n200255\n86\n1199.5\n111\n1350000\n1330000\n873000\n2015","general":{"inn":"","inn_hidden":true,"last_name":"Іванов","post":{"region":"Кіровоградська область","region_unclear":false,"post":"суддя апеляційного суду кіровоградської області","office_unclear":false,"office":"Загальний апеляційний суд"},"name":"Дем'ян","full_name":"Іванов Дем'ян Леонідович","family_raw":"","addresses":[{"place_district":"","place_city_hidden":true,"place_city":"","place_city_type_hidden":false,"place_district_hidden":false,"place_city_type":"","place_address_hidden":true,"place_address":"","place_hidden":true,"place":""}],"family":[{"inn":"","relations":"Подружжя","relations_other":"","inn_hidden":true,"family_name":"Корольова О. В","name_hidden":true,"name_unclear":false},{"inn":"","relations":"Дитина","relations_other":"","inn_hidden":false,"family_name":"Іванова Є. Д","name_hidden":false,"name_unclear":false},{"inn":"","relations":"Дитина","relations_other":"","inn_hidden":false,"family_name":"Іванова З. Д","name_unclear":false}],"full_name_suggest":{"output":"Іванов Дем'ян Леонідович","input":["Іванов Дем'ян Леонідович","Дем'ян Леонідович Іванов","Дем'ян Іванов"]},"patronymic":"Леонідович"},"source":"VULYK","estate":{"23":[{"space_hidden":false,"costs":"","costs_comment":"","address_hidden":false,"region_hidden":true,"space_comment":"","space":"1199.5","address":"","region":"","costs_rent_comment":"","space_comment_unclear":false,"space_units":"м²","costs_rent":""}],"26":[{"costs_rent":"","region":"","costs":"","costs_rent_comment":"","costs_comment":"","address_hidden":false,"region_hidden":true,"space_comment":"","space_units":"м²","space":"111","address":""}],"31":[{"space_unclear":false,"address_hidden":true,"region_hidden":true,"space_comment":"","space_hidden":false,"space":"86","address":"","region":"","costs_property":"","costs_rent_comment":"","space_units":"м²","costs_property_comment":"","costs_rent":""}]},"intro":{"declaration_year":"2015","isnotdeclaration":""}}