{"income":{"5":{"value":"227884","family_comment":"","value_unclear":false,"family_hidden":false,"family_unclear":false,"family_comment_unclear":false,"family_comment_hidden":false,"comment":"","family":"62277"},"6":{"value":"227884","family_comment":"","value_unclear":false,"family_hidden":false,"family_unclear":false,"family":"49367","comment":""},"7":{"value":"","comment_unclear":false,"family_comment":"","source_name":"","family_comment_unclear":false,"family":"","comment":"","source_name_hidden":false},"8":{"value":"","comment_unclear":false,"family_comment":"","family":"","comment":"","family_comment_unclear":false},"9":{"family_comment":"","value":"","family":"","comment":""},"10":{"value":"","family_comment":"","value_unclear":false,"family_hidden":false,"family_unclear":false,"family":"","comment":""},"11":{"value":"","family_unclear":false,"family_hidden":false,"family_comment":"","family":"85","comment":""},"12":{"value":"","family_unclear":false,"family_hidden":false,"family_comment":"","family":"","comment":""},"13":{"family_comment":"","value":"","family_hidden":false,"comment":"","family":""},"14":{"family_comment":"","value":"","family_hidden":false,"comment":"","family":""},"15":{"family_comment":"","value":"","family_hidden":false,"comment":"","family":""},"16":{"value":"","family_hidden":false,"value_hidden":false,"family_comment":"","family":"","comment":""},"17":{"family_comment":"","value":"","family":"","comment":""},"18":{"value":"","family_comment":"","value_unclear":false,"family_unclear":false,"family":"","comment":""},"19":{"value":"","family_comment":"","value_unclear":false,"family_unclear":false,"comment_unclear":false,"comment":"","family":""},"20":{"value":"","family_comment":"","value_unclear":false,"family_unclear":false,"comment_unclear":false,"comment":"","family":"12825"}},"vehicle":{"35":[{"brand_info":"1595 куб. см.","sum_rent_comment":"","year":"2012","sum_rent_unclear":false,"brand_info_hidden":false,"brand_info_unclear":false,"year_unclear":false,"sum_rent":"","sum":"","brand":"Skoda Octavia A5","sum_comment":"","brand_unclear":false,"brand_hidden":false,"sum_unclear":false}]},"id":"vulyk_21_194","banks":{"45":[{"sum_units":"UAH","sum_hidden":false,"sum_foreign":"","sum_foreign_comment":"","sum":"","sum_comment":"","sum_comment_unclear":false,"sum_foreign_units":"UAH","sum_foreign_comment_unclear":false,"sum_units_unclear":false,"sum_comment_hidden":false,"sum_unclear":false},{"sum_foreign_comment":"","sum_units":"","sum_comment":"","sum_foreign_comment_hidden":false,"sum_foreign_unclear":false,"sum_foreign_units":"","sum":"","sum_foreign":""},{"sum_foreign_comment":"","sum_units":"","sum_comment":"","sum_hidden":false,"sum_foreign_units":"","sum_comment_hidden":false,"sum_unclear":false,"sum":"","sum_foreign":""}],"46":[{"sum_foreign_comment":"","sum_units":"UAH","sum_comment":"","sum_comment_unclear":false,"sum_hidden":false,"sum_foreign_units":"UAH","sum":"","sum_unclear":false,"sum_foreign":""}],"47":[{"sum_foreign_comment":"","sum_units":"UAH","sum_comment":"","sum_comment_unclear":false,"sum_foreign_units":"UAH","sum":"","sum_unclear":false,"sum_foreign":""}],"48":[{"sum_foreign_comment":"","sum_units":"UAH","sum_comment":"","sum_foreign_units":"UAH","sum":"","sum_foreign":""}],"49":[{"sum_foreign_comment":"","sum_units":"UAH","sum_comment":"","sum_foreign_units":"UAH","sum":"","sum_foreign":""}],"50":[{"sum_foreign_comment":"","sum_units":"UAH","sum_comment":"","sum_hidden":false,"sum_foreign_units":"UAH","sum":"","sum_foreign":""}],"51":[{"sum_foreign_comment":"","sum_units":"UAH","sum_comment":"","sum_comment_unclear":false,"sum_hidden":false,"sum_foreign_units":"UAH","sum_foreign_comment_unclear":false,"sum_comment_hidden":false,"sum_unclear":false,"sum":"9424","sum_foreign":""},{"sum_foreign_comment":"","sum_units":"","sum_comment":"","sum_foreign_unclear":false,"sum_foreign_units":"","sum_hidden":false,"sum_comment_hidden":false,"sum_unclear":false,"sum":"","sum_foreign":""},{"sum_foreign_comment":"","sum_units":"","sum_comment":"","sum_foreign_units":"","sum":"","sum_foreign":""}],"52":[{"sum_foreign_comment":"","sum_units":"UAH","sum_comment":"","sum_comment_unclear":false,"sum_hidden":false,"sum_foreign_units":"UAH","sum":"","sum_unclear":false,"sum_foreign":""}],"53":[{"sum_foreign_comment":"","sum_units":"UAH","sum_comment":"","sum_foreign_units":"UAH","sum":"","sum_foreign":""},{"sum_foreign_comment":"","sum_units":"","sum_comment":"","sum_foreign_units":"","sum":"","sum_foreign":""}]},"declaration":{"additional_info_text":"","notfull_lostpages":"","date":"2015-03-23T00:00:00","notfull":"","additional_info":"","url":"http://static.declarations.com.ua/declarations/chosen_ones/mega_batch/volodko_ihor_stepanovych.pdf"},"liabilities":{"54":{"sum_foreign_comment":"","sum":"","sum_comment":"","sum_comment_unclear":false,"sum_hidden":false,"sum_foreign":""},"55":{"sum_foreign_comment":"","sum":"","sum_comment":"","sum_foreign":""},"56":{"sum_foreign_comment":"","sum":"","sum_comment":"","sum_unclear":false,"sum_foreign":""},"57":{"sum_foreign_comment":"","sum":"5262","sum_comment":"","sum_comment_unclear":false,"sum_hidden":false,"sum_comment_hidden":false,"sum_unclear":false,"sum_foreign":""},"58":{"sum_foreign_comment":"","sum":"","sum_comment":"","sum_comment_unclear":false,"sum_hidden":false,"sum_comment_hidden":false,"sum_unclear":false,"sum_foreign":""},"59":{"sum_foreign_comment":"","sum":"","sum_comment":"","sum_foreign":""},"60":{"sum_foreign_comment":"","sum":"","sum_comment":"","sum_hidden":false,"sum_comment_hidden":false,"sum_foreign":""},"61":{"sum_foreign_comment":"","sum":"","sum_hidden":false,"sum_comment":"","sum_foreign":""},"62":{"sum_foreign_comment":"","sum":"","sum_comment":"","sum_comment_unclear":false,"sum_foreign":""},"63":{"sum_foreign_comment":"","sum":"","sum_comment":"","sum_hidden":false,"sum_unclear":false,"sum_foreign":""},"64":{"sum_foreign_comment":"","sum":"","sum_comment":"","sum_unclear":false,"sum_foreign":""}},"ft_src":"5262\nБіла Церква\n9107\nКиївська область\nсуддя білоцерківського міськрайонного суду київської області\nКиївська область\nЗагальний місцевий суд\nІгор\nВолодько В. О\nПодружжя\nВолодько Р. І\nДитина\nВолодько Б. І\nДитина\nСтепанович\nВолодько Ігор Степанович\nВолодько\nВолодько Ігор Степанович\nІгор Степанович Володько\nІгор Володько\nВолодько Ігор Степанович\n1595 куб. см.\nSkoda Octavia A5\n2012\n9424\n2014\n1595 куб. см.\nSkoda Octavia A5\n2012\n9424\n1220\nБілоцерківський район, с. Шкарівка,\nКиївська область\n70.5\nКиївська область\nм. Біла Церква, вул. Павліченко, б. 22, кв. 95\n106.1\nКиївська область\nБілоцерківський район, с. Шкарівка,\nВолодько Ігор Степанович\nІгор Степанович Володько\nІгор Володько\nВолодько Ігор Степанович\nІгор\nПодружжя\nВолодько В. О\nДитина\nВолодько Р. І\nДитина\nВолодько Б. І\nВолодько Ігор Степанович\nВолодько\nЗагальний місцевий суд\nсуддя білоцерківського міськрайонного суду київської області\nКиївська область\nСтепанович\nБіла Церква\n9107\nКиївська область\n5262\n49367\n227884\n12825\n227884\n62277\n85\n2014\n5262\nБілоцерківський район, с. Шкарівка,\n1220\nКиївська область\nБілоцерківський район, с. Шкарівка,\nКиївська область\n106.1\nм. Біла Церква, вул. Павліченко, б. 22, кв. 95\n70.5\nКиївська область\nПодружжя\nВолодько В. О\nДитина\nВолодько Р. І\nДитина\nВолодько Б. І\nСтепанович\nВолодько\nІгор\nВолодько Ігор Степанович\nІгор Степанович Володько\nІгор Володько\nВолодько Ігор Степанович\nКиївська область\nБіла Церква\n9107\nКиївська область\nсуддя білоцерківського міськрайонного суду київської області\nЗагальний місцевий суд\nВолодько Ігор Степанович\n49367\n227884\n85\n62277\n227884\n12825\n2012\nSkoda Octavia A5\n1595 куб. см.\n85\n12825\n227884\n62277\n227884\n49367\nм. Біла Церква, вул. Павліченко, б. 22, кв. 95\nКиївська область\n70.5\nБілоцерківський район, с. Шкарівка,\nКиївська область\n1220\nБілоцерківський район, с. Шкарівка,\nКиївська область\n106.1\n9424\n2014","general":{"name_hidden":false,"name":"Ігор","last_name_hidden":false,"inn":"","family":[{"inn":"","relations":"Подружжя","relations_unclear":false,"family_name":"Володько В. О","inn_hidden":true,"relations_other":"","name_hidden":true,"inn_unclear":false,"name_unclear":false},{"inn":"","relations":"Дитина","relations_unclear":false,"family_name":"Володько Р. І","inn_hidden":false,"relations_other":"","name_hidden":false,"inn_unclear":false,"name_unclear":false},{"inn":"","relations":"Дитина","relations_unclear":false,"family_name":"Володько Б. І","inn_hidden":false,"relations_other":"","name_hidden":false,"inn_unclear":false,"name_unclear":false}],"patronymic":"Степанович","inn_hidden":true,"family_raw":"","inn_unclear":false,"post":{"post_unclear":false,"post":"суддя білоцерківського міськрайонного суду київської області","post_hidden":false,"region":"Київська область","region_hidden":false,"office":"Загальний місцевий суд","office_hidden":false,"office_unclear":false},"full_name":"Володько Ігор Степанович","addresses":[{"place_city_type_unclear":false,"place_address":"9107","place_district_hidden":false,"place_city_type":"Місто","place_address_hidden":true,"place_address_unclear":false,"place_city_type_hidden":false,"place":"Київська область","place_district":"","place_unclear":false,"place_city":"Біла Церква","place_city_unclear":false,"place_hidden":false,"place_city_hidden":false,"place_district_unclear":false}],"last_name":"Володько","patronymic_hidden":false,"full_name_suggest":{"output":"Володько Ігор Степанович","input":["Володько Ігор Степанович","Ігор Степанович Володько","Ігор Володько"]},"name_unclear":false},"source":"VULYK","estate":{"23":[{"region_unclear":false,"space_hidden":false,"costs":"","costs_comment":"","costs_hidden":false,"address_hidden":false,"region_hidden":false,"space_comment":"","space_unclear":false,"space_units_unclear":false,"address":"","region":"","address_unclear":false,"space":"","costs_rent_hidden":false,"space_units":"м²","costs_rent":"","costs_rent_comment":""},{"costs":"","costs_comment":"","address_hidden":false,"region_hidden":false,"space_comment":"","space":"","address":"","region":"","costs_rent_comment":"","space_comment_unclear":false,"space_comment_hidden":false,"space_units":"","costs_rent":""},{"costs_rent":"","region":"","costs":"","costs_rent_comment":"","costs_comment":"","address_hidden":false,"space_comment":"","space_units":"","space":"","address":""},{"costs_rent":"","region":"","costs":"","costs_rent_comment":"","costs_comment":"","address_hidden":false,"space_comment":"","space_units":"","space":"","address":""},{"costs_rent":"","region":"","costs":"","costs_rent_comment":"","costs_comment":"","space_comment":"","space_units":"","space":"","address":""},{"costs_rent":"","costs":"","costs_rent_comment":"","costs_comment":"","space_comment":"","space_units":"","space":"","address":""}],"25":[{"space_unclear":false,"costs":"","costs_rent_unclear":false,"costs_comment":"","address_hidden":false,"region_hidden":false,"space_comment":"","space_hidden":false,"space":"70.5","address":"м. Біла Церква, вул. Павліченко, б. 22, кв. 95","region":"Київська область","address_unclear":false,"costs_rent_comment":"","costs_unclear":false,"space_units":"м²","costs_rent":""}],"29":[{"space_hidden":false,"costs_property_hidden":false,"address_hidden":true,"region_hidden":false,"space_comment":"","space_unclear":false,"space":"1220","address":"Білоцерківський район, с. Шкарівка,","region":"Київська область","costs_property":"","space_units_unclear":false,"costs_rent_hidden":false,"space_comment_unclear":false,"space_comment_hidden":false,"space_units":"м²","costs_property_comment":"","costs_rent":"","costs_rent_comment":""}],"32":[{"space_hidden":false,"costs_property_hidden":false,"address_hidden":true,"region_hidden":false,"space_comment":"","space_units_hidden":false,"space":"106.1","address":"Білоцерківський район, с. Шкарівка,","region":"Київська область","costs_property":"","costs_rent_comment":"","space_units":"м²","costs_property_comment":"","costs_rent":""}]},"intro":{"declaration_year":"2014","isnotdeclaration":"","declaration_year_unclear":false,"declaration_year_hidden":false}}