{"income":{"5":{"family_comment":"","value":"225957","family":"","comment":""},"6":{"family_comment":"","value":"225592","family":"","comment":""},"7":{"family_comment":"","value":"","source_name":"","family":"","comment":""},"8":{"family_comment":"","value":"","family":"","comment":""},"9":{"value":"365","comment_unclear":false,"family_comment":"","family":"","comment":"","family_comment_unclear":false},"10":{"family_comment":"","value":"","family":"","comment":""},"11":{"family_comment":"","value":"","family":"","comment":""},"12":{"family_comment":"","value":"","family":"","comment":""},"13":{"family_comment":"","value":"","family":"","comment":""},"14":{"family_comment":"","value":"","family":"","comment":""},"15":{"family_comment":"","value":"","family":"","comment":""},"16":{"family_comment":"","value":"","family":"","comment":""},"17":{"family_comment":"","value":"","family":"","comment":""},"18":{"family_comment":"","value":"","family":"","comment":""},"19":{"value":"","family_comment":"","value_unclear":false,"family_unclear":false,"family":"","comment":""},"20":{"value":"","family_comment":"","value_unclear":false,"comment_hidden":false,"family_comment_hidden":false,"family_unclear":false,"family_comment_unclear":false,"comment_unclear":false,"comment":"","family":""}},"id":"vulyk_106_29","declaration":{"additional_info_text":"","notfull_lostpages":"","date":"2016-03-25T00:00:00","notfull":"","additional_info":"","url":"http://static.declarations.com.ua/declarations/chosen_ones/judges_batch/2168_herasymenko_iryna_mykolaivna.pdf"},"liabilities":{"54":{"sum_foreign_comment":"","sum":"","sum_comment":"","sum_comment_unclear":false,"sum_hidden":false,"sum_comment_hidden":false,"sum_foreign":""},"55":{"sum_foreign_comment":"","sum":"","sum_hidden":false,"sum_comment":"","sum_foreign":""},"56":{"sum_foreign_comment":"","sum":"","sum_comment":"","sum_hidden":false,"sum_comment_hidden":false,"sum_unclear":false,"sum_foreign":""},"57":{"sum_foreign_comment":"","sum":"","sum_comment":"","sum_hidden":false,"sum_comment_hidden":false,"sum_foreign":""},"58":{"sum_foreign_comment":"","sum":"","sum_comment":"","sum_hidden":false,"sum_comment_hidden":false,"sum_foreign":""},"59":{"sum_foreign_comment":"","sum":"","sum_comment":"","sum_foreign":""},"60":{"sum_foreign_comment":"","sum":"","sum_comment":"","sum_hidden":false,"sum_comment_hidden":false,"sum_foreign":""},"61":{"sum_foreign_comment":"","sum":"","sum_comment":"","sum_foreign":""},"62":{"sum_foreign_comment":"","sum":"","sum_comment":"","sum_comment_hidden":false,"sum_unclear":false,"sum_foreign":""},"63":{"sum_foreign_comment":"","sum":"","sum_comment":"","sum_foreign":""},"64":{"sum_foreign_comment":"","sum":"","sum_comment":"","sum_foreign":""}},"ft_src":"суддя 2 кваліфакаційного класу дніпропетровського апеляційного господарського суду\nДніпропетровська область\nАпеляційний господарський суд\nІрина\nГерасименко Лев Леонідович\nДитина\nМиколаївна\nГерасименко Ірина Миколаївна\nІрина Миколаївна Герасименко\nІрина Герасименко\nГерасименко Ірина Миколаївна\nГерасименко Ірина Миколаївна\nГерасименко\n365\n225957\n225592\n650\n207\n54\n2015\n225592\n365\n225957\n650\n207\n54\nГерасименко Ірина Миколаївна\nІрина Миколаївна Герасименко\nІрина Герасименко\nГерасименко Ірина Миколаївна\nГерасименко Ірина Миколаївна\nДитина\nГерасименко Лев Леонідович\nІрина\nГерасименко\nДніпропетровська область\nАпеляційний господарський суд\nсуддя 2 кваліфакаційного класу дніпропетровського апеляційного господарського суду\nМиколаївна\n225592\n225957\n365\n2015\nГерасименко Лев Леонідович\nДитина\nМиколаївна\nГерасименко\nІрина\nГерасименко Ірина Миколаївна\nІрина Миколаївна Герасименко\nІрина Герасименко\nГерасименко Ірина Миколаївна\nДніпропетровська область\nАпеляційний господарський суд\nсуддя 2 кваліфакаційного класу дніпропетровського апеляційного господарського суду\nГерасименко Ірина Миколаївна\n54\n650\n207\n2015","general":{"inn":"","name":"Ірина","inn_unclear":false,"family":[{"inn":"","inn_hidden":true,"relations_unclear":false,"relations_hidden":false,"relations_other":"","relations":"Дитина","name_hidden":true,"family_name":"Герасименко Лев Леонідович","name_unclear":false}],"inn_hidden":true,"family_raw":"","last_name":"Герасименко","post":{"region_unclear":false,"region":"Дніпропетровська область","post":"суддя 2 кваліфакаційного класу дніпропетровського апеляційного господарського суду","office":"Апеляційний господарський суд","office_unclear":false,"post_hidden":false},"full_name":"Герасименко Ірина Миколаївна","addresses":[{"place_district":"","place_city_hidden":true,"place_city":"","place_city_type_hidden":true,"place_district_hidden":true,"place_city_type":"","place_address_hidden":true,"place_address":"","place_hidden":true,"place":""}],"patronymic":"Миколаївна","full_name_suggest":{"output":"Герасименко Ірина Миколаївна","input":["Герасименко Ірина Миколаївна","Ірина Миколаївна Герасименко","Ірина Герасименко"]},"name_unclear":false},"source":"VULYK","estate":{"23":[{"region_unclear":false,"space_hidden":false,"costs":"","costs_comment":"","address_hidden":true,"region_hidden":true,"space_comment":"","space_unclear":false,"space":"650","address":"","costs_comment_unclear":false,"costs_rent_comment_unclear":false,"region":"","address_unclear":false,"costs_rent_comment":"","space_comment_unclear":false,"space_comment_hidden":false,"space_units":"м²","costs_rent":""}],"24":[{"space_unclear":false,"costs":"","costs_comment":"","address_hidden":true,"region_hidden":true,"space_comment":"","space_hidden":false,"space":"207","address":"","region":"","costs_rent_comment":"","space_comment_unclear":false,"space_comment_hidden":false,"space_units":"м²","costs_rent":""}],"25":[{"costs":"","costs_comment":"","address_hidden":true,"region_hidden":true,"space_comment":"","space":"54","address":"","region":"","costs_rent_comment":"","space_comment_unclear":false,"space_units":"м²","costs_rent":""}]},"intro":{"declaration_year":"2015","isnotdeclaration":""}}