{"income":{"5":{"value":"391216.44","family_comment":"","value_unclear":false,"family_hidden":false,"family_unclear":false,"family":"13832","comment":""},"6":{"value":"341216.44","value_unclear":false,"family_hidden":false,"family_comment":"","family":"13832","comment":""},"7":{"source_name_unclear":false,"value":"","family_hidden":false,"family_comment":"","source_name":"","family":"","comment":"","source_name_hidden":false},"8":{"family_comment":"","value":"","family":"","comment":""},"9":{"family_comment":"","family_unclear":false,"value":"","family":"","comment":""},"10":{"family_comment":"","value":"","family":"","comment":""},"11":{"family_comment":"","value":"","comment_unclear":false,"family":"","comment":""},"12":{"family_comment":"","value":"","family":"","comment":""},"13":{"family_comment":"","value":"","family":"","comment":""},"14":{"family_comment":"","value":"","family":"","comment":""},"15":{"family_comment":"","value":"","family":"","comment":""},"16":{"family_comment":"","value":"50000","family":"","comment":""},"17":{"family_comment":"","value":"","family":"","comment":"","family_comment_unclear":false},"18":{"family_comment":"","value":"","family":"","comment":""},"19":{"family_comment":"","value":"","comment_unclear":false,"family":"","comment":""},"20":{"value":"","family_comment":"","comment_unclear":false,"comment_hidden":false,"family_unclear":false,"family":"","comment":""}},"vehicle":{"35":[{"brand_info":"1798 куб. см.","sum_rent_comment":"","year":"2011","brand_info_hidden":false,"year_unclear":false,"sum_rent":"","sum":"","brand":"Mazda 6","sum_comment":"","sum_comment_unclear":false,"sum_unclear":false,"brand_unclear":false}]},"id":"vulyk_8_139","banks":{"45":[{"sum_foreign_comment":"","sum_units":"UAH","sum_comment":"","sum_foreign_unclear":false,"sum_foreign_units":"UAH","sum_hidden":false,"sum_comment_hidden":false,"sum_unclear":false,"sum":"","sum_foreign":""},{"sum_foreign_comment":"","sum_units":"","sum_comment":"","sum_hidden":false,"sum_foreign_units":"","sum":"","sum_unclear":false,"sum_foreign":""},{"sum_foreign_comment":"","sum_units":"","sum_comment":"","sum_foreign_units":"","sum":"","sum_unclear":false,"sum_foreign":""},{"sum_foreign_comment":"","sum_units":"","sum_comment":"","sum_foreign_units":"","sum":"","sum_foreign":""}],"46":[{"sum_foreign_comment":"","sum_units":"UAH","sum_comment":"","sum_foreign_comment_hidden":false,"sum_hidden":false,"sum_foreign_units":"UAH","sum_foreign_hidden":false,"sum_comment_hidden":false,"sum_unclear":false,"sum":"","sum_foreign":""}],"47":[{"sum_foreign_comment":"","sum_units":"UAH","sum_comment":"","sum_foreign_units":"UAH","sum_comment_hidden":false,"sum":"","sum_foreign":""}],"48":[{"sum_foreign_comment":"","sum_units":"UAH","sum_comment":"","sum_foreign_units":"UAH","sum":"","sum_foreign":""}],"49":[{"sum_foreign_comment":"","sum_units":"UAH","sum_comment":"","sum_foreign_units":"UAH","sum":"","sum_foreign":""}],"50":[{"sum_foreign_comment":"","sum_units":"UAH","sum_comment":"","sum_foreign_units":"UAH","sum":"","sum_foreign":""}],"51":[{"sum_foreign_comment":"","sum_units":"UAH","sum_comment":"","sum_comment_unclear":false,"sum_hidden":false,"sum_foreign_units":"UAH","sum_comment_hidden":false,"sum_unclear":false,"sum":"","sum_foreign":""},{"sum_foreign_comment":"","sum_units":"","sum_comment":"","sum_hidden":false,"sum_foreign_units":"","sum":"","sum_foreign":""}],"52":[{"sum_foreign_comment":"","sum_units":"UAH","sum_comment":"","sum_comment_unclear":false,"sum_hidden":false,"sum_foreign_units":"UAH","sum_comment_hidden":false,"sum_unclear":false,"sum":"","sum_foreign":""}],"53":[{"sum_foreign_comment":"","sum_units":"UAH","sum_comment":"","sum_foreign_units":"UAH","sum_comment_hidden":false,"sum":"","sum_foreign":""}]},"declaration":{"additional_info_text":"","notfull_lostpages":"","date":"2015-03-31T00:00:00","notfull":"","additional_info":"","url":"http://static.declarations.com.ua/declarations/chosen_ones/batch_16/kolodiichuk_viktor_mykolaiovych.pdf"},"liabilities":{"54":{"sum_foreign_comment":"","sum_foreign_hidden":false,"sum_comment":"","sum_hidden":false,"sum_comment_hidden":false,"sum":"","sum_foreign":""},"55":{"sum_foreign_comment":"","sum":"","sum_comment":"","sum_foreign":""},"56":{"sum_foreign_comment":"","sum":"13789.05","sum_comment":"","sum_unclear":false,"sum_foreign":""},"57":{"sum_foreign_comment":"","sum_comment_hidden":false,"sum":"","sum_comment":"","sum_foreign":""},"58":{"sum_foreign_comment":"","sum":"","sum_comment":"","sum_foreign":""},"59":{"sum_foreign_comment":"","sum":"","sum_comment":"","sum_comment_unclear":false,"sum_foreign":""},"60":{"sum_foreign_comment":"","sum_foreign_hidden":false,"sum_comment":"","sum_hidden":false,"sum_comment_hidden":false,"sum":"","sum_foreign":""},"61":{"sum_foreign_comment":"","sum":"","sum_comment":"","sum_foreign":""},"62":{"sum_foreign_comment":"","sum":"","sum_comment":"","sum_foreign":""},"63":{"sum_foreign_comment":"","sum":"","sum_comment":"","sum_foreign":""},"64":{"sum_foreign_comment":"","sum":"","sum_comment":"","sum_foreign":""}},"ft_src":"13789.05\nсуддя вищого спеціалізованого суду україни з розгляду цивільних і кримінальних справ\nЗагальнодержавний регіон\nВищий спецiалiзований суд України з розгляду цивiльних i кримiнальних справ\nВіктор\nКолодійчук Тетяна Володимирівна\nПодружжя\nМиколайович\nКолодійчук Віктор Миколайович\nВіктор Миколайович Колодійчук\nВіктор Колодійчук\nКолодійчук Віктор Миколайович\nКолодійчук Віктор Миколайович\nКолодійчук\n1798 куб. см.\nMazda 6\n2011\n2014\n1798 куб. см.\nMazda 6\n2011\n18\n63.6\n87.5\n63.6\nприватизована\nПодружжя\nКолодійчук Тетяна Володимирівна\nКолодійчук Віктор Миколайович\nВіктор Миколайович Колодійчук\nВіктор Колодійчук\nКолодійчук Віктор Миколайович\nКолодійчук Віктор Миколайович\nВіктор\nКолодійчук\nВищий спецiалiзований суд України з розгляду цивiльних i кримiнальних справ\nсуддя вищого спеціалізованого суду україни з розгляду цивільних і кримінальних справ\nЗагальнодержавний регіон\nМиколайович\n13789.05\n341216.44\n13832\n13832\n391216.44\n50000\n2014\n13789.05\n18\n63.6\n87.5\nприватизована\n63.6\nКолодійчук Тетяна Володимирівна\nПодружжя\nМиколайович\nКолодійчук\nВіктор\nКолодійчук Віктор Миколайович\nВіктор Миколайович Колодійчук\nВіктор Колодійчук\nКолодійчук Віктор Миколайович\nЗагальнодержавний регіон\nсуддя вищого спеціалізованого суду україни з розгляду цивільних і кримінальних справ\nВищий спецiалiзований суд України з розгляду цивiльних i кримiнальних справ\nКолодійчук Віктор Миколайович\n13832\n341216.44\n13832\n391216.44\n50000\n2011\nMazda 6\n1798 куб. см.\n391216.44\n13832\n50000\n341216.44\n13832\n63.6\n87.5\nприватизована\n63.6\n18\n2014","general":{"inn":"","name":"Віктор","patronymic_unclear":false,"last_name_hidden":false,"family":[{"inn":"","inn_hidden":true,"relations_hidden":false,"family_name":"Колодійчук Тетяна Володимирівна","relations_other":"","relations":"Подружжя","name_hidden":false,"name_unclear":false}],"patronymic":"Миколайович","inn_hidden":true,"family_raw":"","inn_unclear":false,"post":{"post_unclear":false,"post":"суддя вищого спеціалізованого суду україни з розгляду цивільних і кримінальних справ","post_hidden":false,"region":"Загальнодержавний регіон","region_hidden":false,"office":"Вищий спецiалiзований суд України з розгляду цивiльних i кримiнальних справ","office_hidden":false,"office_unclear":false},"full_name":"Колодійчук Віктор Миколайович","addresses":[{"place_district":"","place_city_hidden":true,"place_city":"","place_city_type_hidden":false,"place_district_hidden":true,"place_city_type":"","place_address_hidden":false,"place_address":"","place_hidden":true,"place":""}],"last_name":"Колодійчук","full_name_suggest":{"output":"Колодійчук Віктор Миколайович","input":["Колодійчук Віктор Миколайович","Віктор Миколайович Колодійчук","Віктор Колодійчук"]}},"source":"VULYK","estate":{"23":[{"space_unclear":false,"costs":"","costs_comment":"","address_hidden":false,"region_hidden":false,"space_comment":"","space":"","address":"","costs_comment_unclear":false,"region":"","address_unclear":false,"costs_rent_comment":"","space_comment_unclear":false,"space_comment_hidden":false,"space_units":"м²","space_units_hidden":false,"costs_rent":""},{"space_unclear":false,"costs":"","costs_comment":"","address_hidden":false,"region_hidden":false,"space_comment":"","space":"","address":"","region":"","costs_rent_comment":"","space_comment_unclear":false,"space_units":"","costs_rent":""},{"space":"","region":"","costs":"","costs_rent_comment":"","costs_comment":"","space_comment":"","space_units_unclear":false,"space_units":"","costs_rent":"","address":""},{"costs_rent":"","region":"","costs":"","costs_rent_comment":"","costs_comment":"","address_hidden":false,"space_comment":"","space_units":"","space":"","address":""}],"25":[{"region_unclear":false,"space_unclear":true,"costs":"","costs_comment":"","address_hidden":false,"region_hidden":true,"space_comment":"приватизована","space":"63.6","address":"","costs_comment_unclear":true,"region":"","costs_rent_comment":"","space_comment_unclear":false,"space_units":"м²","costs_rent":""}],"27":[{"costs_rent":"","region":"","costs":"","costs_rent_comment":"","costs_comment":"","address_hidden":false,"region_hidden":true,"space_comment":"","space_units":"м²","space":"18","address":""}],"31":[{"space_unclear":false,"address_hidden":false,"region_hidden":true,"space_comment":"","space_hidden":false,"space":"63.6","address":"","region":"","costs_property":"","costs_rent_comment":"","address_unclear":false,"space_units":"м²","costs_property_comment":"","costs_rent":""},{"space_unclear":false,"address_hidden":false,"region_hidden":false,"space_comment":"","space":"87.5","address":"","region":"","costs_property":"","costs_rent_comment":"","space_units":"м²","costs_property_comment":"","costs_rent":""}]},"intro":{"declaration_year":"2014","isnotdeclaration":""}}