{"income":{"5":{"value":"186952","family_comment":"","value_unclear":false,"family_unclear":false,"family":"12896","comment":""},"6":{"value":"185489","family_comment":"","value_unclear":false,"family_unclear":false,"family":"","comment":""},"7":{"family_comment":"","value":"1360","source_name":"Національний університет державної податкової служби України","family":"","comment":""},"8":{"family_comment":"","value":"","family":"","comment":""},"9":{"family_comment":"","value":"","family":"","comment":""},"10":{"family_comment":"","value":"","family":"","comment":""},"11":{"family_comment":"","value":"75","family":"115","comment":""},"12":{"family_comment":"","value":"","family":"1156","comment":""},"13":{"family_comment":"","value":"","family":"","comment":""},"14":{"family_comment":"","value":"","family":"","comment":""},"15":{"family_comment":"","value":"","value_unclear":false,"family":"","comment":""},"16":{"family_comment":"","value":"","family":"","comment":""},"17":{"family_comment":"","value":"","family":"","comment":""},"18":{"family_comment":"","value":"","family":"","comment":""},"19":{"family_comment":"","value":"","family":"","comment":""},"20":{"value":"28","family_comment":"","value_unclear":true,"family_unclear":true,"family":"11625","comment":"","family_comment_unclear":false}},"vehicle":{"35":[{"brand_info":"1596 куб. см., 63 кВт","sum_rent_comment":"","brand":"Ford Focus","sum_comment":"","brand_unclear":false,"year":"2012","brand_info_unclear":false,"sum":"","sum_rent":""}]},"id":"vulyk_99_30","declaration":{"date":"2016-03-29T00:00:00","notfull":"","notfull_lostpages":"","url":"http://static.declarations.com.ua/declarations/chosen_ones/judges_batch/579_mantuliak_iurii_viktorovych_2015.pdf"},"liabilities":{"54":{"sum_foreign_comment":"","sum":"120","sum_comment":"ПАТ СК 'Інгострах'","sum_comment_unclear":false,"sum_comment_hidden":false,"sum_foreign":""},"55":{"sum_foreign_comment":"","sum":"","sum_comment":"","sum_foreign":""},"56":{"sum_foreign_comment":"","sum":"","sum_comment":"","sum_foreign":""},"57":{"sum_foreign_comment":"","sum_comment":"Приватбанк, Ощадбанк","sum":"156042","sum_comment_hidden":false,"sum_foreign":""},"58":{"sum_foreign_comment":"","sum_comment":"Приватбанк, Ощадбанк","sum":"7389","sum_comment_hidden":false,"sum_foreign":""},"59":{"sum_foreign_comment":"","sum":"","sum_comment":"","sum_comment_hidden":false,"sum_unclear":false,"sum_foreign":""},"60":{"sum_foreign_comment":"","sum_comment":"","sum":"","sum_comment_hidden":false,"sum_foreign":""},"61":{"sum_foreign_comment":"","sum":"","sum_comment":"","sum_foreign":""},"62":{"sum_foreign_comment":"","sum":"","sum_comment":"","sum_foreign":""},"63":{"sum_foreign_comment":"","sum_comment":"","sum":"","sum_comment_hidden":false,"sum_foreign":""},"64":{"sum_foreign_comment":"","sum_comment":"","sum":"","sum_comment_hidden":false,"sum_foreign":""}},"ft_src":"2012\nFord Focus\n1596 куб. см., 63 кВт\n1000\n85\n2015\n185489\n115\n75\n1360\nНаціональний університет державної податкової служби України\n12896\n186952\n11625\n28\n1156\n1596 куб. см., 63 кВт\nFord Focus\n2012\n2015\nМантуляк\nМантуляк Юрій Вікторович\nЮрій Вікторович Мантуляк\nЮрій Мантуляк\nМантуляк Юрій Вікторович\nЮрій\nВікторович\nМантуляк Юрій Вікторович\nЗагальний місцевий суд\nсуддя кам'янець-подільського міськрайонного суду хмельницької області\nХмельницька область\nПодружжя\nМантуляк Т. І\nДитина\nМантуляк Т. Ю\nДитина\nМантуляк М. Ю\nПриватбанк, Ощадбанк\n7389\n120\nПАТ СК 'Інгострах'\nПриватбанк, Ощадбанк\n156042\nНаціональний університет державної податкової служби України\n1360\n185489\n1156\n28\n11625\n186952\n12896\n75\n115\n1000\n85\nПриватбанк, Ощадбанк\n7389\nПриватбанк, Ощадбанк\n156042\nПАТ СК 'Інгострах'\n120\nМантуляк Т. І\nПодружжя\nМантуляк Т. Ю\nДитина\nМантуляк М. Ю\nДитина\nВікторович\nМантуляк\nсуддя кам'янець-подільського міськрайонного суду хмельницької області\nХмельницька область\nЗагальний місцевий суд\nМантуляк Юрій Вікторович\nМантуляк Юрій Вікторович\nЮрій Вікторович Мантуляк\nЮрій Мантуляк\nМантуляк Юрій Вікторович\nЮрій","general":{"inn":"","inn_hidden":true,"last_name":"Мантуляк","post":{"post_unclear":false,"office":"Загальний місцевий суд","post":"суддя кам'янець-подільського міськрайонного суду хмельницької області","region":"Хмельницька область"},"name":"Юрій","full_name":"Мантуляк Юрій Вікторович","family_raw":"","addresses":[{"place_district":"","place_address_hidden":true,"place_city":"","place_address":"","place_district_hidden":true,"place_city_type":"","place_city_hidden":true,"place_city_type_hidden":true,"place_hidden":true,"place":""}],"family":[{"inn":"","relations":"Подружжя","name_hidden":true,"inn_hidden":true,"family_name":"Мантуляк Т. І","name_unclear":false},{"inn":"","inn_hidden":true,"family_name":"Мантуляк Т. Ю","relations_other":"","relations":"Дитина","name_unclear":false},{"inn":"","inn_hidden":true,"family_name":"Мантуляк М. Ю","relations_other":"","relations":"Дитина","name_hidden":false,"name_unclear":false}],"full_name_suggest":{"output":"Мантуляк Юрій Вікторович","input":["Мантуляк Юрій Вікторович","Юрій Вікторович Мантуляк","Юрій Мантуляк"]},"patronymic":"Вікторович"},"source":"VULYK","estate":{"23":[{"space_unclear":false,"costs":"","costs_comment":"","address_hidden":true,"region_hidden":true,"space_comment":"","space":"1000","address":"","region":"","costs_rent_comment":"","space_units":"м²","costs_rent":""}],"25":[{"space_unclear":false,"costs":"","costs_comment":"","address_hidden":true,"region_hidden":true,"space_comment":"","space_hidden":false,"space":"85","address":"","region":"","costs_rent_comment":"","space_units":"м²","costs_rent":""}]},"intro":{"declaration_year":"2015"}}