{"income":{"5":{"value":"234278","value_unclear":false,"value_hidden":false,"family_comment":"","family":"93649","comment":""},"6":{"value":"225419","family_comment":"","value_unclear":false,"family_unclear":false,"family":"85054","comment":""},"7":{"source_name_unclear":false,"value":"8859","family_hidden":false,"family_comment":"","source_name":"Ужгородський національний університет","family":"","comment":""},"8":{"family_comment":"","value":"","family":"","comment":""},"9":{"family_comment":"","value":"","family":"","comment":""},"10":{"family_comment":"","value":"","family":"8595","comment":""},"11":{"family_comment":"","value":"","family":"","comment":""},"12":{"family_comment":"","value":"","family":"","comment":""},"13":{"family_comment":"","value":"","family":"","comment":""},"14":{"family_comment":"","value":"","family":"","comment":""},"15":{"family_comment":"","value":"","family":"","comment":""},"16":{"family_comment":"","value":"","comment_unclear":false,"family":"","comment":""},"17":{"family_comment":"","family_unclear":false,"value":"","family":"","comment":""},"18":{"family_comment":"","value":"","family":"","comment":""},"19":{"value":"","family_hidden":false,"value_hidden":false,"family_comment":"","family":"","comment":""},"20":{"family_comment":"","value":"","comment_unclear":false,"family":"","comment":""}},"id":"vulyk_67_177","declaration":{"additional_info_text":"","notfull_lostpages":"","date":"2015-03-30T00:00:00","notfull":"","additional_info":"","url":"http://static.declarations.com.ua/declarations/chosen_ones/mega_batch/pryhara_lesia_ivanivna.pdf"},"liabilities":{"54":{"sum_foreign_comment":"","sum_foreign_hidden":false,"sum_comment":"","sum_comment_unclear":false,"sum_hidden":false,"sum":"","sum_unclear":false,"sum_foreign":""},"55":{"sum_foreign_comment":"","sum":"","sum_comment":"","sum_foreign":""},"56":{"sum_foreign_comment":"","sum_foreign_hidden":false,"sum_comment":"","sum_hidden":false,"sum":"9962","sum_unclear":false,"sum_foreign":""},"57":{"sum_foreign_comment":"","sum_foreign_hidden":false,"sum_comment":"","sum_comment_unclear":false,"sum_hidden":false,"sum_comment_hidden":false,"sum_unclear":false,"sum":"","sum_foreign":""},"58":{"sum_foreign_comment":"","sum_foreign_hidden":false,"sum_comment":"","sum_comment_unclear":false,"sum_hidden":false,"sum_comment_hidden":false,"sum_unclear":false,"sum":"","sum_foreign":""},"59":{"sum_foreign_comment":"","sum":"","sum_hidden":false,"sum_comment":"","sum_foreign":""},"60":{"sum_foreign_comment":"","sum":"","sum_comment":"","sum_foreign":""},"61":{"sum_foreign_comment":"","sum_foreign_hidden":false,"sum_comment":"","sum_hidden":false,"sum":"","sum_foreign":""},"62":{"sum_foreign_comment":"","sum":"","sum_hidden":false,"sum_comment":"","sum_foreign":""},"63":{"sum_foreign_comment":"","sum":"","sum_comment":"","sum_comment_unclear":false,"sum_hidden":false,"sum_unclear":false,"sum_foreign":""},"64":{"sum_foreign_comment":"","sum":"","sum_comment":"","sum_hidden":false,"sum_unclear":false,"sum_foreign":""}},"ft_src":"9962\nУжгород\nЗакарпатська область\nсуддя господарського суду закарпатської області\nЗакарпатська область\nГосподарський місцевий суд\nЛеся\nПригара В. М\nПодружжя\nПригара І. В\nДитина\nПригара В. В\nДитина\nІванівна\nПригара Леся Іванівна\nПригара\nПригара Леся Іванівна\nЛеся Іванівна Пригара\nЛеся Пригара\nПригара Леся Іванівна\n8595\n234278\n93649\n8859\nУжгородський національний університет\n225419\n85054\nУжгород\n9962\nоренда\n84.6\nЗакарпатська область\n2014\n85054\n225419\n8595\nУжгородський національний університет\n8859\n93649\n234278\n84.6\nЗакарпатська область\n9962\nоренда\nУжгород\nГосподарський місцевий суд\nсуддя господарського суду закарпатської області\nЗакарпатська область\nПодружжя\nПригара В. М\nДитина\nПригара І. В\nДитина\nПригара В. В\nПригара Леся Іванівна\nЛеся Іванівна Пригара\nЛеся Пригара\nПригара Леся Іванівна\nПригара Леся Іванівна\nЛеся\nПригара\nІванівна\nУжгород\nЗакарпатська область\n9962\n8859\nУжгородський національний університет\n85054\n225419\n234278\n93649\n8595\n2014\n9962\nПодружжя\nПригара В. М\nДитина\nПригара І. В\nПригара В. В\nДитина\nІванівна\nПригара\nЛеся\nПригара Леся Іванівна\nЛеся Іванівна Пригара\nЛеся Пригара\nПригара Леся Іванівна\nЗакарпатська область\nУжгород\nЗакарпатська область\nсуддя господарського суду закарпатської області\nГосподарський місцевий суд\nПригара Леся Іванівна\n9962\nоренда\nУжгород\nЗакарпатська область\n84.6\n2014","general":{"inn":"","name":"Леся","patronymic_unclear":false,"last_name_hidden":false,"family":[{"inn":"","inn_hidden":false,"relations_unclear":false,"relations_hidden":false,"relations_other":"","relations":"Подружжя","name_hidden":false,"inn_unclear":false,"family_name":"Пригара В. М","name_unclear":false},{"inn":"","inn_hidden":false,"relations_unclear":false,"relations_hidden":false,"relations_other":"","relations":"Дитина","name_hidden":false,"inn_unclear":false,"family_name":"Пригара І. В","name_unclear":false},{"inn":"","relations":"Дитина","relations_unclear":false,"family_name":"Пригара В. В","inn_hidden":false,"relations_other":"","name_hidden":false,"name_unclear":false}],"patronymic":"Іванівна","inn_hidden":false,"family_raw":"","inn_unclear":false,"post":{"post_unclear":false,"post":"суддя господарського суду закарпатської області","post_hidden":false,"region":"Закарпатська область","region_hidden":false,"office":"Господарський місцевий суд","office_hidden":false,"office_unclear":false},"last_name_unclear":false,"full_name":"Пригара Леся Іванівна","addresses":[{"place_city_type_hidden":false,"place_district_hidden":false,"place_city_type":"Місто","place_city_hidden":false,"place_address_unclear":false,"place_address":"","place":"Закарпатська область","place_district":"","place_unclear":false,"place_city":"Ужгород","place_city_unclear":false,"place_hidden":false,"place_address_hidden":false,"place_district_unclear":false}],"last_name":"Пригара","full_name_suggest":{"output":"Пригара Леся Іванівна","input":["Пригара Леся Іванівна","Леся Іванівна Пригара","Леся Пригара"]},"name_unclear":false},"source":"VULYK","estate":{"25":[{"space_unclear":false,"costs":"","costs_comment":"","costs_hidden":false,"address_hidden":false,"region_hidden":false,"space_comment":"","space":"84.6","address":"Ужгород","region":"Закарпатська область","address_unclear":false,"space_units_unclear":false,"space_comment_unclear":false,"space_units":"м²","costs_rent":"9962","costs_rent_comment":"оренда"}]},"intro":{"declaration_year":"2014","isnotdeclaration":"","declaration_year_hidden":false}}