{"income":{"5":{"family_comment":"","value":"202894.33","family":"","comment":""},"6":{"family_comment":"","value":"202894.33","family":"","comment":""},"7":{"value":"","comment_hidden":false,"family_comment":"","source_name":"","family":"","comment":"","source_name_hidden":false},"8":{"family_comment":"","value":"","family_hidden":false,"comment":"","family":""},"9":{"value":"","family_comment":"","value_unclear":false,"family_unclear":false,"family":"","comment":""},"10":{"family_comment":"","value":"","family":"","comment":""},"11":{"family_comment":"","value":"","family":"","comment":""},"12":{"family_comment":"","value":"","family":"","comment":""},"13":{"family_comment":"","value":"","family":"","comment":""},"14":{"family_comment":"","value":"","family":"","comment":""},"15":{"family_comment":"","value":"","family":"","comment":""},"16":{"family_comment":"","value":"","family":"","comment":""},"17":{"family_comment":"","value":"","family":"","comment":""},"18":{"family_comment":"","value":"","family":"","comment":""},"19":{"family_comment":"","value":"","family":"","comment":""},"20":{"value":"","value_unclear":false,"family_hidden":false,"family_comment":"","family":"","comment":""}},"id":"vulyk_109_19","declaration":{"additional_info_text":"","notfull_lostpages":"","date":"2016-01-22T00:00:00","notfull":"","additional_info":"","url":"http://static.declarations.com.ua/declarations/chosen_ones/judges_batch/2476_stefaniv_tetiana_vasylivna_2015.pdf"},"liabilities":{"54":{"sum_foreign_comment":"","sum":"","sum_comment":"","sum_hidden":false,"sum_comment_hidden":false,"sum_unclear":false,"sum_foreign":""},"55":{"sum_foreign_comment":"","sum":"","sum_comment":"","sum_comment_unclear":false,"sum_foreign":""},"56":{"sum_foreign_comment":"","sum":"","sum_comment":"","sum_foreign":""},"57":{"sum_foreign_comment":"","sum_comment_hidden":false,"sum":"","sum_comment":"","sum_foreign":""},"58":{"sum_foreign_comment":"","sum_comment_hidden":false,"sum":"","sum_comment":"","sum_foreign":""},"59":{"sum_foreign_comment":"","sum":"","sum_comment":"","sum_foreign":""},"60":{"sum_foreign_comment":"","sum":"","sum_comment":"","sum_foreign":""},"61":{"sum_foreign_comment":"","sum":"","sum_comment":"","sum_foreign":""},"62":{"sum_foreign_comment":"","sum":"","sum_comment":"","sum_foreign":""},"63":{"sum_foreign_comment":"","sum":"","sum_comment":"","sum_foreign":""},"64":{"sum_foreign_comment":"","sum":"","sum_comment":"","sum_foreign":""}},"ft_src":"суддя господарського суду вінницької області\nВінницька область\nГосподарський місцевий суд\nТетяна\nСтефанів Ю. А\nДитина\nВасилівна\nСтефанів Тетяна Василівна\nТетяна Василівна Стефанів\nТетяна Стефанів\nСтефанів Тетяна Василівна\nСтефанів Тетяна Василівна\nСтефанів\n202894.33\n202894.33\n2015\n202894.33\n202894.33\n202894.33\n202894.33\nСтефанів Тетяна Василівна\nТетяна Василівна Стефанів\nТетяна Стефанів\nСтефанів Тетяна Василівна\nТетяна\nДитина\nСтефанів Ю. А\nСтефанів Тетяна Василівна\nВасилівна\nГосподарський місцевий суд\nВінницька область\nсуддя господарського суду вінницької області\nСтефанів\n2015\nДитина\nСтефанів Ю. А\nВасилівна\nСтефанів\nТетяна\nСтефанів Тетяна Василівна\nТетяна Василівна Стефанів\nТетяна Стефанів\nСтефанів Тетяна Василівна\nВінницька область\nГосподарський місцевий суд\nсуддя господарського суду вінницької області\nСтефанів Тетяна Василівна\n2015","general":{"name_hidden":false,"name":"Тетяна","inn":"","family":[{"inn":"","relations":"Дитина","relations_hidden":false,"inn_hidden":true,"relations_other":"","name_hidden":false,"family_name":"Стефанів Ю. А","name_unclear":false}],"patronymic":"Василівна","inn_hidden":true,"family_raw":"","inn_unclear":false,"post":{"region_unclear":false,"region":"Вінницька область","post":"суддя господарського суду вінницької області","region_hidden":false,"office":"Господарський місцевий суд","office_hidden":false,"office_unclear":false},"full_name":"Стефанів Тетяна Василівна","addresses":[{"place_district":"","place_city_hidden":true,"place_city":"","place_city_type_hidden":true,"place_district_hidden":true,"place_city_type":"","place_address_hidden":true,"place_address":"","place_hidden":true,"place":""}],"last_name":"Стефанів","full_name_suggest":{"output":"Стефанів Тетяна Василівна","input":["Стефанів Тетяна Василівна","Тетяна Василівна Стефанів","Тетяна Стефанів"]}},"source":"VULYK","intro":{"declaration_year":"2015","isnotdeclaration":""}}