{"income":{"5":{"family_comment":"","value":"331177","family":"","comment":""},"6":{"family_comment":"","value":"271758","family_hidden":false,"comment":"","family":""},"7":{"family_comment":"","value":"","source_name":"","family":"","comment":""},"8":{"family_comment":"","value":"","family":"","comment":""},"9":{"value":"2316","value_unclear":false,"family_hidden":false,"family_comment":"","family":"","comment":""},"10":{"value":"","family_comment":"","family_hidden":false,"value_hidden":false,"family_unclear":false,"family":"","comment":""},"11":{"family_comment":"","value":"","family":"","comment":""},"12":{"family_comment":"","value":"","family":"","comment":""},"13":{"family_comment":"","value":"","family":"","comment":""},"14":{"family_comment":"","value":"","family":"","comment":""},"15":{"family_comment":"","value":"","family":"","comment":""},"16":{"family_comment":"","value":"","family":"","comment":""},"17":{"family_comment":"","value":"","family":"","comment":""},"18":{"family_comment":"","value":"","family":"","comment":""},"19":{"family_comment":"","value":"","family":"","comment":""},"20":{"value":"57103","comment_unclear":false,"family_comment":"","family":"","comment":"пенсія","family_comment_unclear":false}},"vehicle":{"35":[{"brand_info":"1332 куб. см.","sum_rent_comment":"","brand":"Mitsubishi Colt","sum_comment":"","brand_unclear":false,"year":"2009","brand_hidden":false,"brand_info_unclear":false,"sum":"","sum_rent":"","sum_unclear":false}]},"id":"vulyk_75_54","banks":{"45":[{"sum_foreign_comment":"","sum_units":"UAH","sum_comment":"","sum_comment_unclear":false,"sum_foreign_units":"UAH","sum":"27377","sum_unclear":false,"sum_foreign":""}],"46":[{"sum_foreign_comment":"","sum_units":"UAH","sum_comment":"","sum_foreign_units":"UAH","sum":"25000","sum_foreign":""}]},"declaration":{"additional_info_text":"","notfull_lostpages":"","date":"2015-03-24T00:00:00","notfull":"","additional_info":"","url":"http://static.declarations.com.ua/declarations/chosen_ones/judges_batch/1881_starovoit_iryna_pylypivna.pdf"},"liabilities":{"54":{"sum_foreign_comment":"","sum":"","sum_comment":"","sum_foreign":""},"55":{"sum_foreign_comment":"","sum":"","sum_comment":"","sum_foreign":""},"56":{"sum_foreign_comment":"","sum":"","sum_comment":"","sum_foreign":""},"57":{"sum_foreign_comment":"","sum":"","sum_comment":"","sum_foreign":""},"58":{"sum_foreign_comment":"","sum":"","sum_comment":"","sum_foreign":""},"59":{"sum_foreign_comment":"","sum":"","sum_comment":"","sum_comment_unclear":false,"sum_unclear":false,"sum_foreign":""},"60":{"sum_foreign_comment":"","sum":"","sum_comment":"","sum_foreign":""},"61":{"sum_foreign_comment":"","sum":"","sum_comment":"","sum_foreign":""},"62":{"sum_foreign_comment":"","sum":"","sum_comment":"","sum_unclear":false,"sum_foreign":""},"63":{"sum_foreign_comment":"","sum":"","sum_comment":"","sum_foreign":""},"64":{"sum_foreign_comment":"","sum":"","sum_comment":"","sum_foreign":""}},"ft_src":"Старовойт Ірина Пилипівна\nсуддя апеляційного суду запорізької області\nЗапорізька область\nЗагальний апеляційний суд\nІрина\nСтаровойт Ірина Пилипівна\nІрина Пилипівна Старовойт\nІрина Старовойт\nСтаровойт Ірина Пилипівна\nСтаровойт\nПилипівна\nMitsubishi Colt\n1332 куб. см.\n2009\n25000\n27377\n2014\n1332 куб. см.\n2009\nMitsubishi Colt\n27377\n25000\n2014\nЗагальний апеляційний суд\nсуддя апеляційного суду запорізької області\nЗапорізька область\nСтаровойт\nСтаровойт Ірина Пилипівна\nІрина Пилипівна Старовойт\nІрина Старовойт\nСтаровойт Ірина Пилипівна\nІрина\nСтаровойт Ірина Пилипівна\nПилипівна\n271758\n57103\nпенсія\n331177\n2316\n69.93\n69.93\nСтаровойт\nПилипівна\nсуддя апеляційного суду запорізької області\nЗапорізька область\nЗагальний апеляційний суд\nСтаровойт Ірина Пилипівна\nСтаровойт Ірина Пилипівна\nІрина Пилипівна Старовойт\nІрина Старовойт\nСтаровойт Ірина Пилипівна\nІрина\n271758\n2316\n331177\nпенсія\n57103\n2009\nMitsubishi Colt\n1332 куб. см.\n2316\n57103\nпенсія\n331177\n271758\n69.93\n27377\n25000\n2014","general":{"inn":"","inn_hidden":true,"last_name":"Старовойт","post":{"office":"Загальний апеляційний суд","region":"Запорізька область","post":"суддя апеляційного суду запорізької області"},"name":"Ірина","full_name":"Старовойт Ірина Пилипівна","family_raw":"","addresses":[{"place_district":"","place_address_hidden":false,"place_city":"","place_city_type_hidden":false,"place_district_hidden":false,"place_city_type":"","place_city_hidden":false,"place_address":"","place_hidden":true,"place":""}],"full_name_suggest":{"output":"Старовойт Ірина Пилипівна","input":["Старовойт Ірина Пилипівна","Ірина Пилипівна Старовойт","Ірина Старовойт"]},"patronymic":"Пилипівна"},"source":"VULYK","estate":{"25":[{"space_hidden":false,"costs":"","costs_comment":"","address_hidden":false,"region_hidden":true,"space_comment":"","space_unclear":false,"space":"69.93","address":"","region":"","costs_rent_comment":"","space_units":"м²","costs_rent":""}]},"intro":{"declaration_year":"2014","isnotdeclaration":""}}