{"income":{"5":{"family_comment":"","family_unclear":false,"value":"252242","family":"91589","comment":""},"6":{"value":"239050","family_comment":"","comment_unclear":false,"family_unclear":false,"family":"42043","comment":""},"7":{"source_name_unclear":false,"value":"","family_comment":"","source_name":"","family":"","comment":"","source_name_hidden":false},"8":{"family_comment":"","value":"","family":"","comment":""},"9":{"family_comment":"","value":"13192","family":"2545","comment":""},"10":{"family_comment":"","value":"","comment_unclear":false,"family":"","comment":""},"11":{"family_comment":"","value":"","family":"","comment":""},"12":{"family_comment":"","value":"","family":"","comment":""},"13":{"family_comment":"","value":"","family":"","comment":""},"14":{"family_comment":"","value":"","family":"","comment":""},"15":{"family_comment":"","value":"","family":"","comment":""},"16":{"value":"","comment_hidden":false,"value_hidden":false,"family_comment":"","family":"","comment":"","family_comment_unclear":false},"17":{"family_comment":"","value":"","family":"","comment":""},"18":{"family_comment":"","value":"","family":"","comment":""},"19":{"family_comment":"","value":"","family":"","comment":""},"20":{"value":"","family_comment":"","value_unclear":false,"family":"49546","family_unclear":false,"comment_unclear":false,"comment":"","family_comment_unclear":false}},"vehicle":{"35":[{"brand_info":"легковий універсал, 2.0 л , Д 5 м","sum_rent_comment":"","year":"2008","sum_rent_unclear":false,"brand_info_hidden":false,"brand_info_unclear":false,"sum_rent":"","sum":"","brand":"Hyundai Tucson","sum_comment":"","sum_comment_unclear":false,"brand_hidden":false,"sum_unclear":false,"brand_unclear":false}],"44":[{"brand_info":"Причіп легковий","sum_rent_comment":"","brand":"Фермер","sum_comment":"","year":"2007","brand_hidden":true,"sum":"","sum_rent":""}]},"id":"vulyk_58_92","banks":{"45":[{"sum_foreign_comment":"","sum_units":"UAH","sum_comment":"","sum_comment_unclear":true,"sum_hidden":false,"sum_foreign_units":"UAH","sum_comment_hidden":false,"sum_units_hidden":false,"sum":"84503","sum_foreign":""},{"sum_foreign_comment":"","sum_units":"UAH","sum_comment":"","sum_foreign_units":"UAH","sum":"1095","sum_foreign":""}],"46":[{"sum_foreign_comment":"","sum_units":"UAH","sum_comment":"","sum_foreign_units":"UAH","sum_comment_hidden":false,"sum":"","sum_foreign":""}],"47":[{"sum_foreign_comment":"","sum_units":"UAH","sum_comment":"","sum_foreign_units":"UAH","sum_comment_hidden":false,"sum":"","sum_foreign":""}],"48":[{"sum_foreign_comment":"","sum_units":"UAH","sum_comment":"","sum_foreign_units":"UAH","sum":"","sum_foreign":""}],"49":[{"sum_foreign_comment":"","sum_units":"UAH","sum_comment":"","sum_foreign_units":"UAH","sum":"","sum_foreign":""}],"50":[{"sum_foreign_comment":"","sum_units":"UAH","sum_comment":"","sum_foreign_units":"UAH","sum":"","sum_foreign":""}],"51":[{"sum_foreign_comment":"","sum_units":"UAH","sum_comment":"","sum_foreign_units":"UAH","sum_comment_hidden":false,"sum":"","sum_foreign":""},{"sum_foreign_comment":"","sum_units":"","sum_comment":"","sum_comment_hidden":false,"sum":"","sum_foreign":""}],"52":[{"sum_foreign_comment":"","sum_units":"UAH","sum_comment":"","sum_foreign_units":"UAH","sum":"","sum_foreign":""}],"53":[{"sum_foreign_comment":"","sum_units":"UAH","sum_comment":"","sum_foreign_units":"UAH","sum":"","sum_foreign":""}]},"declaration":{"additional_info_text":"","notfull_lostpages":"","date":"2015-03-27T00:00:00","notfull":"","additional_info":"","url":"http://static.declarations.com.ua/declarations/chosen_ones/mega_batch/zadorozhna_larysa_ivanivna.pdf"},"liabilities":{"54":{"sum_foreign_comment":"","sum":"","sum_hidden":false,"sum_comment":"","sum_foreign":""},"55":{"sum_foreign_comment":"","sum":"","sum_hidden":false,"sum_comment":"","sum_foreign":""},"56":{"sum_foreign_comment":"","sum":"","sum_comment":"","sum_unclear":false,"sum_foreign":""},"57":{"sum_foreign_comment":"","sum":"","sum_comment":"","sum_comment_unclear":false,"sum_comment_hidden":false,"sum_unclear":false,"sum_foreign":""},"58":{"sum_foreign_comment":"","sum":"","sum_comment":"","sum_comment_unclear":false,"sum_comment_hidden":false,"sum_unclear":false,"sum_foreign":""},"59":{"sum_foreign_comment":"","sum":"","sum_comment":"","sum_foreign":""},"60":{"sum_foreign_comment":"","sum":"","sum_comment":"","sum_comment_unclear":false,"sum_unclear":false,"sum_foreign":""},"61":{"sum_foreign_comment":"","sum":"","sum_comment":"","sum_foreign":""},"62":{"sum_foreign_comment":"","sum":"","sum_comment":"","sum_foreign":""},"63":{"sum_foreign_comment":"","sum":"32670","sum_comment":"","sum_comment_unclear":false,"sum_comment_hidden":false,"sum_unclear":false,"sum_foreign":""},"64":{"sum_foreign_comment":"","sum":"497","sum_comment":"","sum_comment_unclear":false,"sum_comment_hidden":false,"sum_unclear":false,"sum_foreign":""}},"ft_src":"497\n32670\nсуддя теплицького районного суду вінницької області, голова суду\nВінницька область\nЗагальний місцевий суд\nЛариса\nЗадорожний Є. П\nПодружжя\nЗадорожна Є. Є\nДитина\nЗадорожна П. Є\nДитина\nІванівна\nЗадорожна\nЗадорожна Лариса Іванівна\nЗадорожна Лариса Іванівна\nЛариса Іванівна Задорожна\nЛариса Задорожна\nЗадорожна Лариса Іванівна\nлегковий універсал, 2.0 л , Д 5 м\nHyundai Tucson\n2008\nФермер\n2007\nПричіп легковий\n84503\n1095\n2014\nлегковий універсал, 2.0 л , Д 5 м\nHyundai Tucson\n2008\nПричіп легковий\nФермер\n2007\n84503\n1095\n1000\n1000\n1/3\n43.66\n43.66\n1/3\n43.66\n1/3\nЗадорожна Лариса Іванівна\nЛариса Іванівна Задорожна\nЛариса Задорожна\nЗадорожна Лариса Іванівна\nЗадорожна Лариса Іванівна\nПодружжя\nЗадорожний Є. П\nДитина\nЗадорожна Є. Є\nДитина\nЗадорожна П. Є\nЛариса\nІванівна\nЗагальний місцевий суд\nсуддя теплицького районного суду вінницької області, голова суду\nВінницька область\nЗадорожна\n32670\n497\n239050\n42043\n49546\n252242\n91589\n13192\n2545\n2014\n497\n32670\n1000\n1000\n1/3\n43.66\n1/3\n43.66\n1/3\n43.66\nЗадорожний Є. П\nПодружжя\nЗадорожна Є. Є\nДитина\nЗадорожна П. Є\nДитина\nІванівна\nЗадорожна\nЛариса\nЗадорожна Лариса Іванівна\nЛариса Іванівна Задорожна\nЛариса Задорожна\nЗадорожна Лариса Іванівна\nВінницька область\nсуддя теплицького районного суду вінницької області, голова суду\nЗагальний місцевий суд\nЗадорожна Лариса Іванівна\n42043\n239050\n91589\n252242\n2545\n13192\n49546\nПричіп легковий\nФермер\n2007\n2008\nHyundai Tucson\nлегковий універсал, 2.0 л , Д 5 м\n49546\n91589\n252242\n2545\n13192\n239050\n42043\n1/3\n43.66\n1/3\n43.66\n1000\n1/3\n43.66\n1000\n84503\n1095\n2014","general":{"inn":"","name":"Лариса","inn_unclear":false,"family":[{"inn":"","inn_hidden":true,"relations_hidden":false,"family_name":"Задорожний Є. П","relations_other":"","relations":"Подружжя","name_hidden":false,"name_unclear":false},{"inn":"","inn_hidden":false,"relations_hidden":false,"family_name":"Задорожна Є. Є","relations_other":"","relations":"Дитина","name_hidden":false,"name_unclear":false},{"inn":"","relations":"Дитина","inn_unclear":false,"family_name":"Задорожна П. Є","inn_hidden":false,"relations_other":"","name_hidden":false,"name_unclear":false}],"inn_hidden":true,"family_raw":"","last_name":"Задорожна","post":{"post_unclear":false,"post":"суддя теплицького районного суду вінницької області, голова суду","post_hidden":false,"region":"Вінницька область","region_hidden":false,"office":"Загальний місцевий суд","office_hidden":false,"office_unclear":false},"last_name_unclear":false,"full_name":"Задорожна Лариса Іванівна","patronymic":"Іванівна","full_name_suggest":{"output":"Задорожна Лариса Іванівна","input":["Задорожна Лариса Іванівна","Лариса Іванівна Задорожна","Лариса Задорожна"]}},"source":"VULYK","estate":{"23":[{"space_unclear":false,"costs":"","costs_comment":"","address_hidden":false,"region_hidden":true,"space_comment":"","space_hidden":false,"space":"1000","address":"","costs_comment_unclear":false,"costs_rent_comment_unclear":false,"region":"","address_unclear":false,"costs_rent_comment":"","costs_unclear":false,"space_units":"м²","costs_rent":""},{"costs":"","costs_comment":"","address_hidden":false,"region_hidden":false,"space_comment":"","space":"","address":"","region":"","address_unclear":false,"costs_rent_comment":"","space_units":"","costs_rent":""},{"costs":"","costs_comment":"","address_hidden":false,"region_hidden":false,"space_comment":"","space":"","address":"","region":"","address_unclear":false,"costs_rent_comment":"","space_units":"","costs_rent":""},{"costs_rent":"","region":"","costs":"","costs_rent_comment":"","costs_comment":"","space_comment":"","space_units":"","space":"","address":""},{"costs_rent":"","costs":"","costs_rent_comment":"","costs_comment":"","space_comment":"","space_units":"","space":"","address":""}],"25":[{"region_unclear":false,"space_hidden":false,"costs":"","costs_comment":"","address_hidden":false,"region_hidden":true,"space_comment":"1/3","space":"43.66","address":"","region":"","costs_rent_comment":"","space_comment_unclear":false,"space_units":"м²","costs_rent":""}],"29":[{"space_unclear":false,"address_hidden":false,"region_hidden":true,"space_comment":"","space_hidden":false,"space":"1000","address":"","region":"","costs_property":"","costs_rent_comment":"","address_unclear":false,"space_units":"м²","costs_property_comment":"","costs_rent":""}],"31":[{"space_unclear":false,"costs_property_hidden":false,"address_hidden":false,"region_hidden":true,"space_comment":"1/3","space_hidden":false,"space":"43.66","address":"","region":"","costs_property":"","costs_rent_comment":"","costs_rent_hidden":false,"space_comment_unclear":false,"space_units":"м²","costs_property_comment":"","costs_rent":""},{"space_unclear":false,"address_hidden":false,"region_hidden":false,"space_comment":"1/3","space":"43.66","address":"","region":"","costs_property":"","costs_rent_comment":"","space_comment_unclear":true,"space_units":"м²","costs_property_comment":"","costs_rent":""}]},"intro":{"declaration_year":"2014","isnotdeclaration":"","declaration_year_hidden":false}}