{"id":"vulyk_89_12","ft_src":"1.2 л\n1973\nВАЗ 21013\n.1072\n14.2\n66.8\n14.2\n2014\n278874.18\n12734.51\n278874.18\n12734.51\n1.2 л\nВАЗ 21013\n1973\n2014\nГаврилович\nЕлфімова Л. Б\nПодружжя\nСухарьок Михайло Гаврилович\nМихайло Гаврилович Сухарьок\nМихайло Сухарьок\nСухарьок Михайло Гаврилович\nСухарьок Михайло Гаврилович\nМихайло\nСухарьок\nДонецька область\nсуддя донецького апеляційного адміністративного суду\nАпеляційний адміністративний суд\n12375\n278874.18\n12734.51\n278874.18\n12734.51\n.1072\n14.2\n66.8\n14.2\n12375\nЕлфімова Л. Б\nПодружжя\nГаврилович\nСухарьок\nсуддя донецького апеляційного адміністративного суду\nДонецька область\nАпеляційний адміністративний суд\nСухарьок Михайло Гаврилович\nСухарьок Михайло Гаврилович\nМихайло Гаврилович Сухарьок\nМихайло Сухарьок\nСухарьок Михайло Гаврилович\nМихайло","estate":{"23":[{"address":"","space_units":"га","costs_comment":"","space_comment":"","region_hidden":true,"region":"","address_hidden":false,"space":".1072","address_unclear":false,"costs_rent_comment":"","costs":"","costs_rent":""}],"25":[{"address":"","space_units":"м²","costs_comment":"","region_hidden":true,"space_comment":"","address_hidden":false,"costs":"","space_comment_unclear":false,"costs_rent_comment":"","space":"66.8","region":"","costs_rent":""},{"space":"14.2","address":"","space_units":"м²","costs_rent_comment":"","costs":"","costs_comment":"","space_comment":"","region":"","costs_rent":""}],"31":[{"costs_property_comment":"","address":"","space_units":"м²","space_hidden":false,"space_comment":"","region_hidden":true,"costs_property":"","region":"","address_hidden":false,"costs_rent_comment":"","space":"14.2","costs_rent":""}]},"vehicle":{"35":[{"sum_comment":"","brand_info":"1.2 л","sum":"","sum_rent_comment":"","year":"1973","brand":"ВАЗ 21013","sum_rent":""}]},"source":"VULYK","income":{"5":{"family":"12734.51","family_comment":"","comment":"","value_hidden":false,"family_hidden":false,"value":"278874.18"},"6":{"family_comment":"","value":"278874.18","family":"","comment":""},"7":{"family":"","family_comment":"","value":"","comment":"","source_name":""},"8":{"family_comment":"","value":"","family":"","comment":""},"9":{"family_comment":"","value":"","family":"","comment":""},"10":{"family_comment":"","value":"","family":"","comment":""},"11":{"family_comment":"","value":"","family":"","comment":""},"12":{"family_comment":"","value":"","family":"","comment":""},"13":{"family_comment":"","value":"","family":"","comment":""},"14":{"family_comment":"","value":"","family":"","comment":""},"15":{"family_comment":"","value":"","family":"","comment":""},"16":{"family_comment":"","value":"","family":"","comment":""},"17":{"family_comment":"","value":"","family":"","comment":""},"18":{"family_comment":"","value":"","family":"","comment":""},"19":{"family_comment":"","value":"","family":"","comment":""},"20":{"family_comment":"","value":"","family":"12734.51","comment":""}},"general":{"inn":"","addresses":[{"place_city_type_hidden":true,"place_city_type":"","place_city_hidden":true,"place_hidden":true,"place_district":"","place_district_hidden":true,"place":"","place_address":"","place_address_hidden":false,"place_city":""}],"last_name":"Сухарьок","full_name":"Сухарьок Михайло Гаврилович","family":[{"inn":"","name_hidden":false,"family_name":"Елфімова Л. Б","inn_hidden":true,"relations":"Подружжя"}],"patronymic":"Гаврилович","inn_hidden":true,"name":"Михайло","post":{"office":"Апеляційний адміністративний суд","region":"Донецька область","post":"суддя донецького апеляційного адміністративного суду"},"family_raw":"","full_name_suggest":{"input":["Сухарьок Михайло Гаврилович","Михайло Гаврилович Сухарьок","Михайло Сухарьок"],"output":"Сухарьок Михайло Гаврилович"}},"liabilities":{"54":{"sum_comment":"","sum_foreign_comment":"","sum_foreign":"","sum":""},"55":{"sum_comment":"","sum_foreign_comment":"","sum_foreign":"","sum":""},"56":{"sum_comment":"","sum_foreign_comment":"","sum_foreign":"","sum_unclear":false,"sum":"12375"},"57":{"sum_comment":"","sum_foreign_comment":"","sum_foreign":"","sum":""},"58":{"sum_comment":"","sum_foreign_comment":"","sum_foreign":"","sum":""},"59":{"sum_comment":"","sum_foreign_comment":"","sum_foreign":"","sum":""},"60":{"sum_comment":"","sum_foreign_comment":"","sum_foreign":"","sum":""},"61":{"sum_comment":"","sum_foreign_comment":"","sum_foreign":"","sum":""},"62":{"sum_comment":"","sum_foreign_comment":"","sum_foreign":"","sum_unclear":false,"sum":""},"63":{"sum_comment":"","sum_foreign_comment":"","sum_foreign":"","sum":""},"64":{"sum_comment":"","sum_foreign_comment":"","sum_foreign":"","sum":""}},"declaration":{"notfull_lostpages":"","date":"2015-03-27T00:00:00","notfull":"","url":"http://static.declarations.com.ua/declarations/chosen_ones/judges_batch/3015_sukharok_mykhailo_havrylovych.pdf"},"intro":{"declaration_year":"2014"}}