{"income":{"5":{"value":"173768","family_comment":"","value_unclear":false,"comment_hidden":false,"family_hidden":false,"value_hidden":false,"family_unclear":false,"family":"7000","comment":""},"6":{"value":"173768","family_comment":"","value_unclear":false,"family_hidden":false,"family_unclear":false,"comment_unclear":false,"comment":"","family":""},"7":{"source_name_unclear":false,"value":"","value_hidden":false,"family_comment":"","source_name":"","family":"","comment":"","source_name_hidden":false},"8":{"value":"","family_hidden":false,"value_hidden":false,"family_comment":"","family":"","comment":""},"9":{"value":"","family_comment":"","value_unclear":false,"family_hidden":false,"value_hidden":false,"family_unclear":false,"family":"","comment":""},"10":{"family_comment":"","value":"","family":"","comment":""},"11":{"family_comment":"","value":"","family":"","comment":""},"12":{"family_comment":"","value":"","family":"","comment":""},"13":{"family_comment":"","value":"","family":"","comment":""},"14":{"family_comment":"","value":"","family":"","comment":""},"15":{"family_comment":"","value":"","family":"","comment":""},"16":{"value":"","family_comment":"","value_unclear":false,"family_unclear":false,"family":"","comment":""},"17":{"family_comment":"","value":"","family":"","comment":""},"18":{"family_comment":"","value":"","family":"","comment":""},"19":{"family_comment":"","value":"","comment_unclear":false,"family":"","comment":""},"20":{"value":"","family_comment":"","value_unclear":false,"comment_hidden":false,"family_hidden":false,"family":"7000","value_hidden":false,"family_unclear":false,"comment_unclear":false,"comment":"","family_comment_unclear":false}},"vehicle":{"35":[{"brand_info":"1991 куб. см., довжина - 478","sum_rent_comment":"","brand":"BMW 520i","sum_comment":"","brand_unclear":false,"year":"1998","brand_info_unclear":false,"sum":"","sum_rent":""}]},"id":"vulyk_63_5","declaration":{"additional_info_text":"","notfull_lostpages":"","date":"2015-03-27T00:00:00","notfull":"","additional_info":"","url":"http://static.declarations.com.ua/declarations/chosen_ones/mega_batch/vasylieva_olena_oleksandrivna.pdf"},"liabilities":{"54":{"sum_foreign_comment":"","sum":"1761","sum_comment":"","sum_unclear":true,"sum_foreign":""},"55":{"sum_foreign_comment":"","sum":"","sum_comment":"","sum_foreign":""},"56":{"sum_foreign_comment":"","sum":"36260","sum_comment":"","sum_unclear":false,"sum_foreign":""},"57":{"sum_foreign_comment":"","sum":"15212","sum_comment":"","sum_comment_hidden":false,"sum_unclear":false,"sum_foreign":""},"58":{"sum_foreign_comment":"","sum_comment_hidden":false,"sum":"59236","sum_comment":"","sum_foreign":""},"59":{"sum_foreign_comment":"","sum":"","sum_comment":"","sum_foreign":""},"60":{"sum_foreign_comment":"","sum":"","sum_comment":"","sum_comment_unclear":false,"sum_foreign":""},"61":{"sum_foreign_comment":"","sum":"","sum_comment":"","sum_unclear":false,"sum_foreign":""},"62":{"sum_foreign_comment":"","sum":"","sum_comment":"","sum_unclear":false,"sum_foreign":""},"63":{"sum_foreign_comment":"","sum":"","sum_comment":"","sum_hidden":false,"sum_comment_hidden":false,"sum_unclear":false,"sum_foreign":""},"64":{"sum_foreign_comment":"","sum_comment_hidden":false,"sum":"","sum_comment":"","sum_foreign":""}},"ft_src":"15212\n1761\n59236\n36260\nсуддя червонозаводського районного суду м. харкова\nХарківська область\nЗагальний місцевий суд\nОлена\nВасильєв В. А\nПодружжя\nОлександрівна\nВасильєва\nВасильєва Олена Олександрівна\nВасильєва Олена Олександрівна\nОлена Олександрівна Васильєва\nОлена Васильєва\nВасильєва Олена Олександрівна\n1998\nBMW 520i\n1991 куб. см., довжина - 478\n55\n2014\n173768\n7000\n173768\n7000\n1991 куб. см., довжина - 478\n1998\nBMW 520i\n55\nОлександрівна\nВасильєва Олена Олександрівна\nОлена Олександрівна Васильєва\nОлена Васильєва\nВасильєва Олена Олександрівна\nОлена\nПодружжя\nВасильєв В. А\nВасильєва Олена Олександрівна\nЗагальний місцевий суд\nХарківська область\nсуддя червонозаводського районного суду м. харкова\nВасильєва\n15212\n36260\n59236\n1761\n173768\n7000\n173768\n7000\n2014\n59236\n15212\n36260\n1761\nПодружжя\nВасильєв В. А\nОлександрівна\nВасильєва\nВасильєва Олена Олександрівна\nОлена Олександрівна Васильєва\nОлена Васильєва\nВасильєва Олена Олександрівна\nОлена\nХарківська область\nсуддя червонозаводського районного суду м. харкова\nЗагальний місцевий суд\nВасильєва Олена Олександрівна\n1998\n1991 куб. см., довжина - 478\nBMW 520i\n7000\n173768\n7000\n173768\n55\n2014","general":{"name_hidden":false,"name":"Олена","patronymic_unclear":false,"last_name_hidden":false,"inn":"","family":[{"inn":"","inn_hidden":true,"relations_unclear":false,"relations_hidden":false,"relations_other":"","relations":"Подружжя","name_hidden":false,"inn_unclear":false,"family_name":"Васильєв В. А","name_unclear":false}],"patronymic":"Олександрівна","inn_hidden":true,"family_raw":"","inn_unclear":false,"post":{"post_unclear":false,"region_unclear":false,"region":"Харківська область","office_hidden":false,"region_hidden":false,"post":"суддя червонозаводського районного суду м. харкова","office_unclear":false,"office":"Загальний місцевий суд"},"last_name_unclear":false,"full_name":"Васильєва Олена Олександрівна","addresses":[{"place_city_type_unclear":false,"place_address":"","place_district_hidden":true,"place_city_type":"","place_address_hidden":true,"place_address_unclear":false,"place_city_type_hidden":false,"place":"","place_district":"","place_unclear":false,"place_city":"","place_city_unclear":false,"place_hidden":false,"place_city_hidden":true,"place_district_unclear":false}],"last_name":"Васильєва","full_name_suggest":{"output":"Васильєва Олена Олександрівна","input":["Васильєва Олена Олександрівна","Олена Олександрівна Васильєва","Олена Васильєва"]},"name_unclear":false},"source":"VULYK","estate":{"31":[{"space_unclear":false,"costs_property_hidden":false,"address_hidden":false,"region_hidden":true,"space_comment":"","space_hidden":false,"space":"55","address":"","costs_property_comment_hidden":false,"region":"","costs_property":"","space_units_unclear":false,"costs_rent_hidden":false,"space_comment_unclear":false,"costs_rent_comment_hidden":false,"space_units":"м²","costs_property_comment":"","costs_rent":"","costs_rent_comment":""}]},"intro":{"declaration_year":"2014","isnotdeclaration":"","declaration_year_unclear":false}}