{"income":{"5":{"family_comment":"","family_unclear":false,"value":"181076.63","family":"31841.63","comment":""},"6":{"family_comment":"","value":"168869.22","value_unclear":false,"family":"31841.63","comment":""},"7":{"family_comment":"","value":"","source_name":"","family":"","comment":""},"8":{"family_comment":"","value":"","family":"","comment":""},"9":{"value":"27.41","value_unclear":false,"family_hidden":false,"family_comment":"","comment_unclear":false,"comment":"","family":""},"10":{"family_comment":"","value":"12180","family":"","comment":""},"11":{"family_comment":"","value":"","family":"","comment":""},"12":{"family_comment":"","value":"","family":"","comment":""},"13":{"family_comment":"","value":"","family":"","comment":""},"14":{"family_comment":"","value":"","family":"","comment":""},"15":{"family_comment":"","value":"","family":"","comment":""},"16":{"family_comment":"","value":"","family":"","comment":""},"17":{"family_comment":"","value":"","family":"","comment":""},"18":{"family_comment":"","value":"","family":"","comment":""},"19":{"family_comment":"","value":"","family":"","comment":""},"20":{"value":"","value_unclear":false,"comment_hidden":false,"family_comment":"","family":"","comment":""}},"vehicle":{"35":[{"brand_info":"1.4 л","sum_rent_comment":"","brand":"ВАЗ 2108","sum_comment":"","year":"1986","brand_info_hidden":false,"brand_info_unclear":false,"sum":"","sum_rent":""},{"brand_info":"1.6 л","sum_rent_comment":"","brand":"Nissan Qashqai","sum_comment":"","year":"2007","sum":"","sum_rent":""}]},"id":"vulyk_40_36","banks":{"45":[{"sum_foreign_comment":"","sum_units":"UAH","sum_comment":"","sum_hidden":false,"sum_foreign_units":"UAH","sum":"","sum_foreign":""},{"sum_foreign_comment":"","sum_units":"","sum_comment":"","sum_foreign_units":"","sum":"","sum_foreign":""},{"sum_foreign_comment":"","sum_units":"","sum_comment":"","sum_foreign_units":"","sum":"","sum_foreign":""}],"46":[{"sum_foreign_comment":"","sum_units":"UAH","sum_comment":"","sum_foreign_units":"UAH","sum":"","sum_unclear":false,"sum_foreign":""}],"47":[{"sum_foreign_comment":"","sum_units":"UAH","sum_comment":"","sum_foreign_units":"UAH","sum":"","sum_foreign":""}],"48":[{"sum_foreign_comment":"","sum_units":"UAH","sum_comment":"","sum_foreign_units":"UAH","sum":"","sum_foreign":""}],"49":[{"sum_foreign_comment":"","sum_units":"UAH","sum_comment":"","sum_foreign_units":"UAH","sum":"","sum_foreign":""}],"50":[{"sum_foreign_comment":"","sum_units":"UAH","sum_comment":"","sum_foreign_units":"UAH","sum":"","sum_foreign":""}],"51":[{"sum_foreign_comment":"","sum_units":"UAH","sum_comment":"","sum_foreign_units":"UAH","sum":"","sum_foreign":""}],"52":[{"sum_foreign_comment":"","sum_units":"UAH","sum_comment":"","sum_foreign_units":"UAH","sum":"","sum_foreign":""}],"53":[{"sum_foreign_comment":"","sum_units":"UAH","sum_comment":"","sum_foreign_units":"UAH","sum":"","sum_foreign":""}]},"declaration":{"date":"2015-03-27T00:00:00","notfull":"","url":"http://static.declarations.com.ua/declarations/chosen_ones/mega_batch/sokolova_nataliia_oleksandrivna.pdf","notfull_lostpages":""},"liabilities":{"54":{"sum_foreign_comment":"","sum":"60.5","sum_comment":"","sum_foreign":""},"55":{"sum_foreign_comment":"","sum":"","sum_comment":"","sum_foreign":""},"56":{"sum_foreign_comment":"","sum":"","sum_comment":"","sum_foreign":""},"57":{"sum_foreign_comment":"","sum":"","sum_comment":"","sum_hidden":false,"sum_comment_hidden":false,"sum_foreign":""},"58":{"sum_foreign_comment":"","sum":"","sum_comment":"","sum_hidden":false,"sum_comment_hidden":false,"sum_foreign":""},"59":{"sum_foreign_comment":"","sum":"","sum_comment":"","sum_foreign":""},"60":{"sum_foreign_comment":"","sum":"","sum_comment":"","sum_foreign":""},"61":{"sum_foreign_comment":"","sum":"","sum_comment":"","sum_foreign":""},"62":{"sum_foreign_comment":"","sum":"","sum_comment":"","sum_foreign":""},"63":{"sum_foreign_comment":"","sum":"","sum_comment":"","sum_foreign":""},"64":{"sum_foreign_comment":"","sum":"","sum_comment":"","sum_foreign":""}},"ft_src":"60.5\nСоколова Наталія Олександрівна\nсуддя охтирського міськрайонного суду сумської області\nСумська область\nЗагальний місцевий суд\nНаталія\nСоколов Є. О\nПодружжя\nСоколов В. Є\nДитина\nСоколова Наталія Олександрівна\nНаталія Олександрівна Соколова\nНаталія Соколова\nСоколова Наталія Олександрівна\nСоколова\nОлександрівна\n1986\n1.4 л\nВАЗ 2108\n1.6 л\n2007\nNissan Qashqai\n2014\n1.4 л\n1986\nВАЗ 2108\n1.6 л\nNissan Qashqai\n2007\n32.3\nУкраїна\nСоколова\nСоколова Наталія Олександрівна\nНаталія Олександрівна Соколова\nНаталія Соколова\nСоколова Наталія Олександрівна\nНаталія\nОлександрівна\nСоколова Наталія Олександрівна\nЗагальний місцевий суд\nсуддя охтирського міськрайонного суду сумської області\nСумська область\nПодружжя\nСоколов Є. О\nДитина\nСоколов В. Є\n60.5\n168869.22\n31841.63\n181076.63\n31841.63\n12180\n27.41\n2014\n60.5\nУкраїна\n32.3\nСоколов Є. О\nПодружжя\nСоколов В. Є\nДитина\nОлександрівна\nСоколова\nсуддя охтирського міськрайонного суду сумської області\nСумська область\nЗагальний місцевий суд\nСоколова Наталія Олександрівна\nСоколова Наталія Олександрівна\nНаталія Олександрівна Соколова\nНаталія Соколова\nСоколова Наталія Олександрівна\nНаталія\n31841.63\n168869.22\n12180\n31841.63\n181076.63\n27.41\n1986\n1.4 л\nВАЗ 2108\nNissan Qashqai\n1.6 л\n2007\n12180\n31841.63\n181076.63\n27.41\n31841.63\n168869.22\nУкраїна\n32.3\n2014","general":{"inn":"","inn_hidden":true,"last_name":"Соколова","post":{"office":"Загальний місцевий суд","region":"Сумська область","post":"суддя охтирського міськрайонного суду сумської області"},"name":"Наталія","full_name":"Соколова Наталія Олександрівна","family_raw":"","addresses":[{"place_district":"","place_city_hidden":false,"place_city":"","place_city_type_hidden":false,"place_district_hidden":false,"place_city_type":"","place_address_hidden":false,"place_address":"","place_hidden":true,"place":""}],"family":[{"inn":"","relations":"Подружжя","relations_other":"","inn_hidden":false,"family_name":"Соколов Є. О","name_hidden":false},{"inn":"","relations":"Дитина","relations_other":"","inn_hidden":false,"family_name":"Соколов В. Є","name_unclear":false}],"full_name_suggest":{"output":"Соколова Наталія Олександрівна","input":["Соколова Наталія Олександрівна","Наталія Олександрівна Соколова","Наталія Соколова"]},"patronymic":"Олександрівна"},"source":"VULYK","estate":{"23":[{"costs_rent":"","region":"","costs":"","costs_rent_comment":"","costs_comment":"","address_hidden":false,"region_hidden":false,"space_comment":"","space_units":"м²","space":"","address":""},{"costs_rent":"","region":"","costs":"","costs_rent_comment":"","costs_comment":"","space_comment":"","space_units":"","space":"","address":""},{"costs_rent":"","region":"","costs":"","costs_rent_comment":"","costs_comment":"","space_comment":"","space_units":"","space":"","address":""},{"costs_rent":"","costs":"","costs_rent_comment":"","costs_comment":"","space_comment":"","space_units":"","space":"","address":""}],"31":[{"space_hidden":false,"address_hidden":false,"region_hidden":true,"space_comment":"","space":"32.3","address":"Україна","region":"","costs_property":"","costs_rent_comment":"","space_units":"м²","costs_property_comment":"","costs_rent":""}]},"intro":{"declaration_year":"2014"}}