{"income":{"5":{"family_comment":"","value":"192123","value_unclear":false,"family":"23503","comment":""},"6":{"value":"188592","value_unclear":false,"family_hidden":false,"family_comment":"","family":"23503","comment":""},"7":{"source_name_unclear":false,"value":"","family_comment":"","source_name":"","family":"","comment":""},"8":{"family_comment":"","value":"","family":"","comment":""},"9":{"family_comment":"","value":"","family":"","comment":""},"10":{"family_comment":"","value":"","family":"","comment":""},"11":{"family_comment":"","value":"","comment_unclear":false,"family":"","comment":""},"12":{"family_comment":"","value":"","family":"","comment":""},"13":{"family_comment":"","value":"","family":"","comment":""},"14":{"family_comment":"","value":"","family":"","comment":""},"15":{"family_comment":"","value":"","family":"","comment":""},"16":{"family_comment":"","value":"","family":"","comment":""},"17":{"family_comment":"","value":"","family":"","comment":""},"18":{"family_comment":"","value":"","family":"","comment":""},"19":{"family_comment":"","value":"","family":"","comment":""},"20":{"value":"3531","family_comment":"","comment_unclear":false,"family_unclear":false,"value_unclear":false,"comment":"пенсія інв. дит. 3 гр","family":""}},"id":"vulyk_101_139","declaration":{"additional_info_text":"","notfull_lostpages":"","date":"2016-03-21T00:00:00","notfull":"","additional_info":"","url":"http://static.declarations.com.ua/declarations/chosen_ones/judges_batch/854_malinov_oleksandr_serhiiovych_2015.pdf"},"liabilities":{"54":{"sum_foreign_comment":"","sum":"","sum_comment":"","sum_comment_unclear":false,"sum_hidden":false,"sum_comment_hidden":false,"sum_unclear":false,"sum_foreign":""},"55":{"sum_foreign_comment":"","sum":"","sum_comment":"","sum_foreign":""},"56":{"sum_foreign_comment":"","sum":"","sum_comment":"","sum_comment_hidden":false,"sum_unclear":false,"sum_foreign":""},"57":{"sum_foreign_comment":"","sum":"","sum_comment":"","sum_hidden":false,"sum_comment_hidden":false,"sum_unclear":false,"sum_foreign":""},"58":{"sum_foreign_comment":"","sum":"","sum_comment":"","sum_comment_unclear":false,"sum_hidden":false,"sum_comment_hidden":false,"sum_unclear":false,"sum_foreign":""},"59":{"sum_foreign_comment":"","sum":"","sum_comment":"","sum_foreign":""},"60":{"sum_foreign_comment":"","sum":"","sum_comment":"","sum_hidden":false,"sum_comment_hidden":false,"sum_unclear":false,"sum_foreign":""},"61":{"sum_foreign_comment":"","sum":"","sum_comment":"","sum_foreign":""},"62":{"sum_foreign_comment":"","sum":"","sum_comment":"","sum_comment_unclear":false,"sum_foreign":""},"63":{"sum_foreign_comment":"","sum_comment":"","sum":"","sum_comment_hidden":false,"sum_foreign":""},"64":{"sum_foreign_comment":"","sum_comment":"","sum":"","sum_comment_hidden":false,"sum_foreign":""}},"ft_src":"Донецька область\nм. Костянтинівка\n76.5\nДонецька область\nм. Костянтинівка\n851\n2015\n23503\n188592\n23503\n192123\nпенсія інв. дит. 3 гр\n3531\n851\nДонецька область\nм. Костянтинівка\n76.5\nм. Костянтинівка\nДонецька область\nПодружжя\nМалінова А. В\nДитина\nМалінов С. О\nМалінов Олександр Сергійович\nОлександр Сергійович Малінов\nОлександр Малінов\nМалінов Олександр Сергійович\nОлександр\nМалінов Олександр Сергійович\nСергійович\nЗагальний місцевий суд\nсуддя костянтинівського міськрайонного суду донецької області\nДонецька область\nМалінов\n188592\n23503\nпенсія інв. дит. 3 гр\n3531\n192123\n23503\n2015\nМалінова А. В\nПодружжя\nМалінов С. О\nДитина\nОлександр\nСергійович\nМалінов\nМалінов Олександр Сергійович\nОлександр Сергійович Малінов\nОлександр Малінов\nМалінов Олександр Сергійович\nсуддя костянтинівського міськрайонного суду донецької області\nЗагальний місцевий суд\nДонецька область\nМалінов Олександр Сергійович","general":{"inn":"","name":"Олександр","last_name":"Малінов","family":[{"inn":"","inn_hidden":true,"family_name":"Малінова А. В","relations_other":"","relations":"Подружжя","name_hidden":true,"name_unclear":false},{"inn":"","inn_hidden":true,"relations_unclear":false,"family_name":"Малінов С. О","relations_other":"","relations":"Дитина","name_hidden":false,"name_unclear":false}],"inn_hidden":true,"family_raw":"","inn_unclear":false,"post":{"region":"Донецька область","office":"Загальний місцевий суд","post":"суддя костянтинівського міськрайонного суду донецької області","office_unclear":false,"region_unclear":false},"full_name":"Малінов Олександр Сергійович","addresses":[{"place_district":"","place_address_hidden":true,"place_city":"","place_address":"","place_district_hidden":false,"place_city_type":"","place_city_hidden":true,"place_city_type_hidden":false,"place_hidden":true,"place":""}],"patronymic":"Сергійович","patronymic_hidden":false,"full_name_suggest":{"output":"Малінов Олександр Сергійович","input":["Малінов Олександр Сергійович","Олександр Сергійович Малінов","Олександр Малінов"]}},"source":"VULYK","estate":{"29":[{"costs_rent":"","region":"Донецька область","costs_property":"","costs_rent_comment":"","address_hidden":true,"region_hidden":false,"space_comment":"","costs_property_comment":"","space_units":"м²","space":"851","address":"м. Костянтинівка"}],"30":[{"costs_rent":"","region":"Донецька область","costs_property":"","costs_rent_comment":"","address_hidden":true,"region_hidden":false,"space_comment":"","costs_property_comment":"","space_units":"м²","space":"76.5","address":"м. Костянтинівка"}]},"intro":{"declaration_year":"2015"}}