{"income":{"5":{"family_comment":"","value":"291393","family":"","comment":""},"6":{"family_comment":"","value":"195860","family_hidden":false,"comment":"","family":""},"7":{"family_comment":"","value":"","source_name":"","family":"","comment":""},"8":{"family_comment":"","value":"","family":"","comment":""},"9":{"value":"52453","value_unclear":false,"family_hidden":false,"family_comment":"","family":"","comment":""},"10":{"value":"","family_comment":"","family_hidden":false,"value_hidden":false,"family_unclear":false,"family":"","comment":""},"11":{"family_comment":"","value":"","family":"","comment":""},"12":{"family_comment":"","value":"","family":"","comment":""},"13":{"family_comment":"","value":"","family":"","comment":""},"14":{"family_comment":"","value":"","family":"","comment":""},"15":{"family_comment":"","value":"","family":"","comment":""},"16":{"family_comment":"","value":"","family":"","comment":""},"17":{"family_comment":"","value":"","family":"","comment":""},"18":{"family_comment":"","value":"","family":"","comment":""},"19":{"family_comment":"","value":"","family":"","comment":""},"20":{"value":"43080","comment_unclear":false,"family_comment":"","family":"","comment":"","family_comment_unclear":false}},"vehicle":{"35":[{"brand_info":"2450 куб. см.","sum_rent_comment":"","brand":"ГАЗ 21","sum_comment":"","brand_unclear":false,"year":"1968","brand_hidden":false,"brand_info_unclear":false,"sum":"","sum_rent":"","sum_unclear":false},{"brand_info":"1600 куб. см.","sum_rent_comment":"","brand":"Daewoo Lanos","sum_comment":"","sum_comment_unclear":false,"year":"2005","sum":"","sum_rent":""}]},"id":"vulyk_75_114","banks":{"45":[{"sum_foreign_comment":"","sum_units":"UAH","sum_comment":"","sum_comment_unclear":false,"sum_foreign_units":"UAH","sum":"975897","sum_unclear":false,"sum_foreign":""}],"46":[{"sum_foreign_comment":"","sum_units":"UAH","sum_comment":"","sum_foreign_units":"UAH","sum":"95533","sum_foreign":""}]},"declaration":{"additional_info_text":"","notfull_lostpages":"","date":"2015-03-26T00:00:00","notfull":"","additional_info":"","url":"http://static.declarations.com.ua/declarations/chosen_ones/judges_batch/1821_boiarskyi_oleksandr_oleksandrovych.pdf"},"liabilities":{"54":{"sum_foreign_comment":"","sum":"","sum_comment":"","sum_foreign":""},"55":{"sum_foreign_comment":"","sum":"","sum_comment":"","sum_foreign":""},"56":{"sum_foreign_comment":"","sum":"","sum_comment":"","sum_foreign":""},"57":{"sum_foreign_comment":"","sum":"","sum_comment":"","sum_foreign":""},"58":{"sum_foreign_comment":"","sum":"","sum_comment":"","sum_foreign":""},"59":{"sum_foreign_comment":"","sum":"","sum_comment":"","sum_comment_unclear":false,"sum_unclear":false,"sum_foreign":""},"60":{"sum_foreign_comment":"","sum":"","sum_comment":"","sum_foreign":""},"61":{"sum_foreign_comment":"","sum":"","sum_comment":"","sum_foreign":""},"62":{"sum_foreign_comment":"","sum":"","sum_comment":"","sum_unclear":false,"sum_foreign":""},"63":{"sum_foreign_comment":"","sum":"","sum_comment":"","sum_foreign":""},"64":{"sum_foreign_comment":"","sum":"","sum_comment":"","sum_foreign":""}},"ft_src":"Боярський Олександр Олександрович\nсуддя білгород-дністровського міськрайонного суду одеської області\nОдеська область\nЗагальний місцевий суд\nОлександр\nБоярський Олександр Олександрович\nОлександр Олександрович Боярський\nОлександр Боярський\nБоярський Олександр Олександрович\nБоярський\nОлександрович\nГАЗ 21\n2450 куб. см.\n1968\n1600 куб. см.\nDaewoo Lanos\n2005\n95533\n975897\n2014\n2450 куб. см.\n1968\nГАЗ 21\n1600 куб. см.\nDaewoo Lanos\n2005\n975897\n95533\n2014\nЗагальний місцевий суд\nсуддя білгород-дністровського міськрайонного суду одеської області\nОдеська область\nБоярський\nБоярський Олександр Олександрович\nОлександр Олександрович Боярський\nОлександр Боярський\nБоярський Олександр Олександрович\nОлександр\nБоярський Олександр Олександрович\nОлександрович\n195860\n43080\n291393\n52453\n56\n64.7\n47\n43\n63\n47.1\n59.2\n71.6\n56\n64.7\n47\n43\n63\n47.1\n59.2\n71.6\nБоярський\nОлександрович\nсуддя білгород-дністровського міськрайонного суду одеської області\nОдеська область\nЗагальний місцевий суд\nБоярський Олександр Олександрович\nБоярський Олександр Олександрович\nОлександр Олександрович Боярський\nОлександр Боярський\nБоярський Олександр Олександрович\nОлександр\n195860\n52453\n291393\n43080\n1968\nГАЗ 21\n2450 куб. см.\nDaewoo Lanos\n1600 куб. см.\n2005\n52453\n43080\n291393\n195860\n64.7\n47\n43\n63\n47.1\n59.2\n71.6\n56\n975897\n95533\n2014","general":{"inn":"","inn_hidden":true,"last_name":"Боярський","post":{"office":"Загальний місцевий суд","region":"Одеська область","post":"суддя білгород-дністровського міськрайонного суду одеської області"},"name":"Олександр","full_name":"Боярський Олександр Олександрович","family_raw":"","addresses":[{"place_district":"","place_address_hidden":true,"place_city":"","place_city_type_hidden":false,"place_district_hidden":false,"place_city_type":"","place_city_hidden":false,"place_address":"","place_hidden":true,"place":""}],"full_name_suggest":{"output":"Боярський Олександр Олександрович","input":["Боярський Олександр Олександрович","Олександр Олександрович Боярський","Олександр Боярський"]},"patronymic":"Олександрович"},"source":"VULYK","estate":{"25":[{"space_hidden":false,"costs":"","costs_comment":"","address_hidden":false,"region_hidden":true,"space_comment":"","space_unclear":false,"space":"64.7","address":"","region":"","costs_rent_comment":"","space_units":"м²","costs_rent":""},{"costs_rent":"","space_unclear":false,"region":"","costs":"","costs_rent_comment":"","costs_comment":"","region_hidden":true,"space_comment":"","space_units":"м²","space":"47","address":""},{"costs_rent":"","region":"","costs":"","costs_rent_comment":"","costs_comment":"","region_hidden":true,"space_comment":"","space_units":"м²","space":"43","address":""},{"costs_rent":"","region":"","costs":"","costs_rent_comment":"","costs_comment":"","space_comment":"","space_units":"м²","space":"63","address":""},{"costs_rent":"","region":"","costs":"","costs_rent_comment":"","costs_comment":"","space_comment":"","space_units":"м²","space":"47.1","address":""},{"costs_rent":"","region":"","costs":"","costs_rent_comment":"","costs_comment":"","space_comment":"","space_units":"м²","space":"59.2","address":""},{"costs_rent":"","costs":"","costs_rent_comment":"","costs_comment":"","space_comment":"","space_units":"м²","space":"71.6","address":""}],"28":[{"costs_rent":"","region":"","costs":"","costs_rent_comment":"","costs_comment":"","region_hidden":true,"space_comment":"","space_units":"м²","space":"56","address":""}]},"intro":{"declaration_year":"2014","isnotdeclaration":""}}