{"income":{"5":{"family_comment":"","family_unclear":false,"value":"308685","family":"60005","comment":""},"6":{"value":"294099","family_comment":"","value_unclear":false,"family_unclear":false,"family":"","comment":""},"7":{"value":"","family_comment":"","value_unclear":false,"family_unclear":false,"source_name":"","family":"","comment":"","source_name_hidden":false},"8":{"family_comment":"","value":"","family":"","comment":""},"9":{"family_comment":"","value":"","family":"","comment":""},"10":{"family_comment":"","value":"","value_unclear":false,"family":"22000","comment":""},"11":{"family_comment":"","value":"","family":"","comment":""},"12":{"family_comment":"","value":"","family":"","comment":""},"13":{"family_comment":"","value":"","family":"","comment":""},"14":{"family_comment":"","value":"","family":"","comment":""},"15":{"family_comment":"","value":"14586","family":"","comment":""},"16":{"family_comment":"","value":"","family":"","comment":""},"17":{"family_comment":"","value":"","family":"","comment":""},"18":{"family_comment":"","value":"","family":"","comment":""},"19":{"family_comment":"","value":"","family":"","comment":""},"20":{"value":"","value_unclear":false,"comment_hidden":false,"family_comment":"","comment_unclear":false,"comment":"","family":"38005"}},"vehicle":{"35":[{"year_hidden":false,"brand_info":"об'єм циліндра 2498 , потужність 126 кВт","sum_rent_comment":"","year":"2011","brand_info_hidden":false,"year_unclear":false,"sum_rent":"","sum":"","brand":"Subaru Forester","sum_comment":"кредит","brand_unclear":false,"brand_hidden":false,"sum_unclear":false}]},"id":"vulyk_96_28","declaration":{"additional_info_text":"","notfull_lostpages":"","date":"2015-03-30T00:00:00","notfull":"","additional_info":"","url":"http://static.declarations.com.ua/declarations/chosen_ones/judges_batch/242_holik_ninel_olehivna_2015.pdf"},"liabilities":{"54":{"sum_foreign_comment":"","sum":"15398","sum_comment":"ПрАТ СК Арсенал Страхування","sum_hidden":false,"sum_comment_hidden":false,"sum_foreign":""},"55":{"sum_foreign_comment":"","sum":"","sum_comment":"","sum_foreign":""},"56":{"sum_foreign_comment":"","sum":"","sum_comment":"","sum_unclear":false,"sum_foreign":""},"57":{"sum_foreign_comment":"","sum_comment":"ПАТ УкрСиббанк, АТ Банк Ренесанс Капітал, UniCreditBank","sum":"44842","sum_comment_hidden":false,"sum_foreign":""},"58":{"sum_foreign_comment":"","sum":"24235","sum_comment":"UniCreditBank","sum_comment_hidden":false,"sum_unclear":false,"sum_foreign":""},"59":{"sum_foreign_comment":"","sum":"","sum_comment":"","sum_foreign":""},"60":{"sum_foreign_comment":"","sum_comment":"","sum":"","sum_comment_hidden":false,"sum_foreign":""},"61":{"sum_foreign_comment":"","sum":"","sum_comment":"","sum_foreign":""},"62":{"sum_foreign_comment":"","sum":"","sum_comment":"","sum_foreign":""},"63":{"sum_foreign_comment":"","sum_comment":"","sum":"","sum_comment_hidden":false,"sum_foreign":""},"64":{"sum_foreign_comment":"","sum_comment":"","sum":"","sum_comment_hidden":false,"sum_foreign":""}},"ft_src":"кредит\nоб'єм циліндра 2498 , потужність 126 кВт\nSubaru Forester\n2011\n2/3 частки-приватизація\nм. Київ\nвул. Ю. Коцюбинського, буд. 12, кв. 9\n58.6\nКиївська область\nм. Ржищів, вул. Щорса, 54\n102.2\nспадщина\nКиївська область\nм. Ржищів, вул. Щорса, 54\n880\n1/3 частки приватизація\nвул. Ю. Коцюбинського,12 кв9\n58.6\nм. Київ\n2014\n294099\n14586\n22000\n60005\n308685\n38005\nоб'єм циліндра 2498 , потужність 126 кВт\nSubaru Forester\nкредит\n2011\n2014\nГолік Нінель Олегівна\nНінель Олегівна Голік\nНінель Голік\nГолік Нінель Олегівна\nГолік Нінель Олегівна\n2524113388\nНінель\nГолік\nКиївська область\nсуддя рокитнянського районного суду київської області\nЗагальний місцевий суд\nОлегівна\nвул. Юрія Коцюбинського, буд. 12, кв. 9, 04053\nм. Київ\nКиїв\nДитина\nШвець Тарас Вікторович 25. 10. 1992\n3390113396\nБатьки\nГолік Ольга Федорівна 19. 02. 1937\n1356402744\nБатьки\nГолік Олег Олексійович 24,11,1937\n1384200997\nUniCreditBank\n24235\n15398\nПрАТ СК Арсенал Страхування\nПАТ УкрСиббанк, АТ Банк Ренесанс Капітал, UniCreditBank\n44842\n294099\n38005\n14586\n308685\n60005\n22000\nспадщина\nм. Ржищів, вул. Щорса, 54\n880\nКиївська область\n102.2\nм. Ржищів, вул. Щорса, 54\nКиївська область\n2/3 частки-приватизація\nвул. Ю. Коцюбинського, буд. 12, кв. 9\nм. Київ\n58.6\n1/3 частки приватизація\n58.6\nвул. Ю. Коцюбинського,12 кв9\nм. Київ\nUniCreditBank\n24235\nПАТ УкрСиббанк, АТ Банк Ренесанс Капітал, UniCreditBank\n44842\nПрАТ СК Арсенал Страхування\n15398\n3390113396\nШвець Тарас Вікторович 25. 10. 1992\nДитина\n1356402744\nБатьки\nГолік Ольга Федорівна 19. 02. 1937\n1384200997\nБатьки\nГолік Олег Олексійович 24,11,1937\n2524113388\nНінель\nОлегівна\nГолік\nГолік Нінель Олегівна\nНінель Олегівна Голік\nНінель Голік\nГолік Нінель Олегівна\nм. Київ\nКиїв\nвул. Юрія Коцюбинського, буд. 12, кв. 9, 04053\nсуддя рокитнянського районного суду київської області\nКиївська область\nЗагальний місцевий суд\nГолік Нінель Олегівна","general":{"inn":"2524113388","name":"Нінель","family":[{"inn":"3390113396","inn_hidden":false,"inn_unclear":false,"relations_hidden":false,"relations_other":"","relations":"Дитина","name_hidden":false,"family_name":"Швець Тарас Вікторович 25. 10. 1992","name_unclear":false},{"inn":"1356402744","relations":"Батьки","relations_other":"","inn_hidden":false,"family_name":"Голік Ольга Федорівна 19. 02. 1937","name_hidden":false,"name_unclear":false},{"inn":"1384200997","relations":"Батьки","relations_other":"","inn_hidden":false,"family_name":"Голік Олег Олексійович 24,11,1937","name_unclear":false}],"patronymic":"Олегівна","inn_hidden":false,"family_raw":"","last_name":"Голік","post":{"office":"Загальний місцевий суд","region":"Київська область","office_unclear":false,"post":"суддя рокитнянського районного суду київської області"},"full_name":"Голік Нінель Олегівна","addresses":[{"place_district":"","place_address_hidden":false,"place_city":"Київ","place_address":"вул. Юрія Коцюбинського, буд. 12, кв. 9, 04053","place_district_hidden":false,"place_city_type":"Місто","place_city_hidden":false,"place_city_type_hidden":false,"place_hidden":false,"place":"м. Київ"}],"patronymic_hidden":false,"full_name_suggest":{"output":"Голік Нінель Олегівна","input":["Голік Нінель Олегівна","Нінель Олегівна Голік","Нінель Голік"]}},"source":"VULYK","estate":{"25":[{"space_comment_unclear":false,"space_unclear":false,"costs":"","costs_comment":"","address_hidden":false,"region_hidden":false,"space_comment":"1/3 частки приватизація","space_hidden":false,"space":"58.6","address":"вул. Ю. Коцюбинського,12 кв9","costs_rent_comment_unclear":false,"region":"м. Київ","address_unclear":false,"costs_rent_comment":"","costs_unclear":false,"space_comment_hidden":false,"space_units":"м²","costs_rent":""}],"29":[{"region_unclear":false,"space_unclear":false,"address_hidden":false,"region_hidden":false,"space_comment":"спадщина","space":"880","address":"м. Ржищів, вул. Щорса, 54","region":"Київська область","costs_property":"","costs_rent_comment":"","address_unclear":false,"space_units":"м²","costs_property_comment":"","costs_rent":""}],"30":[{"costs_rent":"","region":"Київська область","costs_property":"","costs_rent_comment":"","address_hidden":false,"region_hidden":false,"space_comment":"","costs_property_comment":"","space_units":"м²","space":"102.2","address":"м. Ржищів, вул. Щорса, 54"}],"31":[{"space_unclear":false,"address_hidden":false,"region_hidden":false,"space_comment":"2/3 частки-приватизація","space_hidden":false,"space":"58.6","address":"вул. Ю. Коцюбинського, буд. 12, кв. 9","region":"м. Київ","costs_property":"","costs_rent_comment":"","address_unclear":false,"space_units":"м²","costs_property_comment":"","costs_rent":""}]},"intro":{"declaration_year":"2014","isnotdeclaration":""}}