{"id":"vulyk_103_50","ft_src":"Honda CR-V\n2354\n2008\n600\n10\n1\nВідомості про членів сім'ї не зазначено, оскільки вони не надали згоди на їх внесення до цієї декларації\n2015\n242712.45\n242712.45\n2354\n2008\nHonda CR-V\n1\nВідомості про членів сім'ї не зазначено, оскільки вони не надали згоди на їх внесення до цієї декларації\n600\n10\nПисана\nПисана Таміла Олександрівна\nТаміла Олександрівна Писана\nТаміла Писана\nПисана Таміла Олександрівна\nПисана Таміла Олександрівна\nОлександрівна\nПодружжя\nПисаний Віктор Григорович\nПисаний Роман Вікторович\nДитина\nДитина\nПисаний Максим Вікторович\nТаміла\nВищий спеціалізований суд з розгляду цивільних і кримінальних справ\nсуддя вищого спецiалiзованого суду україни з розгляду цивiльних і кримiнальних справ\nЗагальнодержавний регіон\n242712.45\n242712.45\n2015\nПодружжя\nПисаний Віктор Григорович\nДитина\nПисаний Роман Вікторович\nДитина\nПисаний Максим Вікторович\nПисана\nОлександрівна\nсуддя вищого спецiалiзованого суду україни з розгляду цивiльних і кримiнальних справ\nВищий спеціалізований суд з розгляду цивільних і кримінальних справ\nЗагальнодержавний регіон\nПисана Таміла Олександрівна\nПисана Таміла Олександрівна\nТаміла Олександрівна Писана\nТаміла Писана\nПисана Таміла Олександрівна\nТаміла","estate":{"23":[{"costs":"","address":"","space_units":"м²","costs_rent_comment":"","space":"600","space_comment":"","region_hidden":true,"costs_comment":"","region":"","address_hidden":false,"costs_rent":""}],"27":[{"costs":"","address":"","space_units":"м²","costs_rent_comment":"","space":"10","space_comment":"","region_hidden":true,"costs_comment":"","region":"","address_hidden":false,"costs_rent":""}]},"vehicle":{"35":[{"sum_comment":"","brand_info_hidden":false,"brand_info":"2354","sum":"","brand_unclear":false,"brand_hidden":false,"brand":"Honda CR-V","sum_rent":"","brand_info_unclear":false,"sum_rent_comment":"","year":"2008"}]},"source":"VULYK","income":{"5":{"family_comment":"","family":"","comment":"","value_unclear":false,"family_hidden":false,"value":"242712.45"},"6":{"family_comment":"","value":"242712.45","family":"","comment":""},"7":{"family":"","family_comment":"","value":"","comment":"","source_name":""},"8":{"family_comment":"","value":"","family":"","comment":""},"9":{"family_comment":"","value":"","family":"","comment":""},"10":{"family_comment":"","value":"","family":"","comment":""},"11":{"family_comment":"","family_hidden":false,"value":"","family":"","comment":""},"12":{"family_comment":"","value":"","family":"","comment":""},"13":{"family_comment":"","value":"","family":"","comment":""},"14":{"family_comment":"","value":"","family":"","comment":""},"15":{"family_comment":"","value":"","family":"","comment":""},"16":{"family_comment":"","value":"","family":"","comment":""},"17":{"family_comment":"","value":"","family":"","comment":"","family_comment_unclear":false},"18":{"family_comment":"","value":"","family":"","comment":""},"19":{"family_comment":"","value":"","family":"","comment":""},"20":{"family_comment":"","family":"","comment":"","family_unclear":false,"family_hidden":false,"value":""}},"general":{"inn":"","addresses":[{"place_city_type_hidden":false,"place_city_type":"","place_city_hidden":true,"place_hidden":true,"place_district":"","place_district_hidden":false,"place":"","place_city":"","place_address_hidden":true,"place_address":""}],"last_name":"Писана","full_name":"Писана Таміла Олександрівна","family":[{"inn":"","family_name":"Писаний Віктор Григорович","relations_hidden":false,"name_unclear":false,"relations":"Подружжя","inn_hidden":true,"name_hidden":true,"relations_other":""},{"inn":"","family_name":"Писаний Роман Вікторович","inn_hidden":true,"relations_other":"","relations":"Дитина"},{"inn":"","family_name":"Писаний Максим Вікторович","relations_other":"","name_unclear":false,"inn_hidden":false,"relations":"Дитина"}],"patronymic":"Олександрівна","inn_hidden":true,"name":"Таміла","post":{"office":"Вищий спеціалізований суд з розгляду цивільних і кримінальних справ","region_unclear":false,"post":"суддя вищого спецiалiзованого суду україни з розгляду цивiльних і кримiнальних справ","region":"Загальнодержавний регіон","office_unclear":false},"family_raw":"","full_name_suggest":{"input":["Писана Таміла Олександрівна","Таміла Олександрівна Писана","Таміла Писана"],"output":"Писана Таміла Олександрівна"}},"liabilities":{"54":{"sum_foreign_comment_hidden":false,"sum_foreign_comment_unclear":false,"sum_hidden":false,"sum":"","sum_foreign_comment":"","sum_comment":"","sum_unclear":false,"sum_foreign":"","sum_comment_hidden":false,"sum_foreign_hidden":false},"55":{"sum_comment":"","sum_foreign_comment":"","sum_foreign":"","sum":""},"56":{"sum_comment":"","sum_foreign_comment":"","sum_foreign":"","sum":""},"57":{"sum_comment":"","sum_hidden":false,"sum":"","sum_foreign_comment":"","sum_foreign":"","sum_comment_hidden":false,"sum_foreign_hidden":false,"sum_foreign_comment_hidden":false},"58":{"sum_comment":"","sum_hidden":false,"sum":"","sum_foreign_comment":"","sum_foreign":"","sum_comment_hidden":false,"sum_foreign_hidden":false,"sum_foreign_comment_hidden":false},"59":{"sum_comment":"","sum_hidden":false,"sum":"","sum_foreign_comment":"","sum_foreign":"","sum_comment_hidden":false,"sum_foreign_hidden":false,"sum_foreign_comment_hidden":false},"60":{"sum_comment":"","sum_hidden":false,"sum":"","sum_foreign_comment":"","sum_foreign":"","sum_comment_hidden":false},"61":{"sum_comment":"","sum_foreign_comment":"","sum_foreign":"","sum":""},"62":{"sum_comment":"","sum_foreign_comment":"","sum_foreign":"","sum":"","sum_comment_hidden":false},"63":{"sum_comment":"","sum_foreign_comment":"","sum_foreign":"","sum":""},"64":{"sum_comment":"","sum_foreign_comment":"","sum_foreign":"","sum":""}},"declaration":{"additional_info_text":"Відомості про членів сім'ї не зазначено, оскільки вони не надали згоди на їх внесення до цієї декларації","additional_info":"1","date":"2016-03-30T00:00:00","url":"http://static.declarations.com.ua/declarations/chosen_ones/judges_batch/1274_pysana_tamila_oleksandrivna.pdf"},"intro":{"declaration_year":"2015"}}