{"income":{"5":{"value":"182531","value_unclear":false,"value_hidden":false,"family_comment":"","family":"38534","comment":""},"6":{"value":"182531","family_comment":"","value_unclear":false,"family_unclear":false,"family":"38534","comment":""},"7":{"source_name_unclear":false,"value":"","family_hidden":false,"family_comment":"","source_name":"","family":"","comment":""},"8":{"family_comment":"","value":"","family":"","comment":""},"9":{"family_comment":"","value":"","family":"","comment":""},"10":{"family_comment":"","value":"","family":"","comment":""},"11":{"family_comment":"","value":"","family":"","comment":""},"12":{"family_comment":"","value":"","family":"","comment":""},"13":{"family_comment":"","value":"","family":"","comment":""},"14":{"family_comment":"","value":"","family":"","comment":""},"15":{"family_comment":"","value":"","family":"","comment":""},"16":{"family_comment":"","value":"","comment_unclear":false,"family":"","comment":""},"17":{"family_comment":"","family_unclear":false,"value":"","family":"","comment":""},"18":{"family_comment":"","value":"","family":"","comment":""},"19":{"value":"","family_hidden":false,"value_hidden":false,"family_comment":"","family":"","comment":""},"20":{"family_comment":"","value":"","comment_unclear":false,"family":"","comment":""}},"vehicle":{"35":[{"brand_info":"1781 куб. см., 66.2 кВт , власність","sum_rent_comment":"","year":"1989","sum_rent_unclear":false,"brand_info_hidden":false,"brand_info_unclear":true,"year_unclear":false,"sum_rent":"","sum":"","brand":"Volkswagen Passat","sum_comment":"","brand_unclear":false,"brand_hidden":false,"sum_unclear":false,"sum_comment_unclear":false},{"brand_info":"1997 куб. см., 105.18 кВт , користування","sum_rent_comment":"","brand":"Peugeot 407","sum_comment":"","sum_comment_unclear":false,"year":"2006","brand_info_unclear":true,"sum":"","sum_rent":""},{"brand_info":"2477 куб. см., 103 кВт , користування","sum_rent_comment":"","brand":"Mitsubishi Pajero","sum_comment":"","sum_comment_unclear":false,"year":"2007","brand_info_unclear":true,"sum":"","sum_rent":""}]},"id":"vulyk_67_113","declaration":{"additional_info_text":"","notfull_lostpages":"","date":"2015-03-25T00:00:00","notfull":"","additional_info":"","url":"http://static.declarations.com.ua/declarations/chosen_ones/mega_batch/kost_vitalii_volodymyrovych.pdf"},"liabilities":{"54":{"sum_foreign_comment":"","sum_unclear":false,"sum":"","sum_comment":"","sum_comment_unclear":false,"sum_hidden":false,"sum_foreign_hidden":false,"sum_foreign":""},"55":{"sum_foreign_comment":"","sum":"","sum_comment":"","sum_foreign":""},"56":{"sum_foreign_comment":"","sum_unclear":false,"sum":"","sum_comment":"","sum_hidden":false,"sum_foreign_hidden":false,"sum_foreign":""},"57":{"sum_foreign_comment":"","sum_unclear":false,"sum":"","sum_comment":"","sum_comment_unclear":false,"sum_hidden":false,"sum_comment_hidden":false,"sum_foreign_hidden":false,"sum_foreign":""},"58":{"sum_foreign_comment":"","sum_unclear":false,"sum":"","sum_comment":"","sum_comment_unclear":false,"sum_hidden":false,"sum_comment_hidden":false,"sum_foreign_hidden":false,"sum_foreign":""},"59":{"sum_foreign_comment":"","sum":"","sum_foreign":"","sum_comment":"","sum_hidden":false},"60":{"sum_foreign_comment":"","sum":"","sum_comment":"","sum_foreign":""},"61":{"sum_foreign_comment":"","sum":"","sum_comment":"","sum_hidden":false,"sum_foreign_hidden":false,"sum_foreign":""},"62":{"sum_foreign_comment":"","sum":"","sum_foreign":"","sum_comment":"","sum_hidden":false},"63":{"sum_foreign_comment":"","sum":"","sum_comment":"","sum_comment_unclear":false,"sum_hidden":false,"sum_unclear":false,"sum_foreign":""},"64":{"sum_foreign_comment":"","sum":"","sum_comment":"","sum_hidden":false,"sum_unclear":false,"sum_foreign":""}},"ft_src":"1781 куб. см., 66.2 кВт , власність\nVolkswagen Passat\n1989\n2006\nPeugeot 407\n1997 куб. см., 105.18 кВт , користування\n2007\nMitsubishi Pajero\n2477 куб. см., 103 кВт , користування\n.0874\n2014\n38534\n182531\n38534\n182531\n1781 куб. см., 66.2 кВт , власність\nVolkswagen Passat\n1989\nPeugeot 407\n1997 куб. см., 105.18 кВт , користування\n2006\nMitsubishi Pajero\n2477 куб. см., 103 кВт , користування\n2007\n.0874\nЗагальний місцевий суд\nсуддя мукачівського міськрайонного суду закарпатської області\nЗакарпатська область\nПодружжя\nКость О. В\nКость Віталій Володимирович\nВіталій Володимирович Кость\nВіталій Кость\nКость Віталій Володимирович\nКость Віталій Володимирович\nВіталій\nКость\nВолодимирович\n38534\n182531\n182531\n38534\n2014\nПодружжя\nКость О. В\nВолодимирович\nКость\nВіталій\nКость Віталій Володимирович\nВіталій Володимирович Кость\nВіталій Кость\nКость Віталій Володимирович\nЗакарпатська область\nсуддя мукачівського міськрайонного суду закарпатської області\nЗагальний місцевий суд\nКость Віталій Володимирович","general":{"inn":"","name":"Віталій","patronymic_unclear":false,"last_name_hidden":false,"last_name":"Кость","family":[{"inn":"","inn_hidden":true,"relations_unclear":false,"relations_hidden":false,"relations_other":"","relations":"Подружжя","name_hidden":true,"inn_unclear":false,"family_name":"Кость О. В","name_unclear":false}],"inn_hidden":true,"family_raw":"","inn_unclear":false,"post":{"post_unclear":false,"post":"суддя мукачівського міськрайонного суду закарпатської області","office_hidden":false,"region":"Закарпатська область","post_hidden":false,"office":"Загальний місцевий суд","office_unclear":false,"region_hidden":false},"full_name_suggest":{"output":"Кость Віталій Володимирович","input":["Кость Віталій Володимирович","Віталій Володимирович Кость","Віталій Кость"]},"full_name":"Кость Віталій Володимирович","addresses":[{"place_city_type_hidden":true,"place_district_hidden":true,"place_city_type":"","place_address_hidden":true,"place_address_unclear":false,"place_address":"","place":"","place_district":"","place_unclear":false,"place_hidden":true,"place_city_unclear":false,"place_city_hidden":true,"place_city":"","place_district_unclear":false}],"patronymic":"Володимирович","last_name_unclear":false,"name_unclear":false},"source":"VULYK","estate":{"23":[{"space_hidden":true,"costs":"","costs_comment":"","costs_hidden":false,"address_hidden":true,"region_hidden":true,"space_comment":"","space_unclear":false,"space":".0874","address":"","region":"","address_unclear":false,"space_units_unclear":false,"costs_rent_hidden":false,"space_comment_unclear":false,"space_units":"га","costs_rent":"","costs_rent_comment":""}]},"intro":{"declaration_year":"2014","isnotdeclaration":"","declaration_year_hidden":false}}