{"income":{"5":{"family_comment":"","value":"265380","family":"","comment":""},"6":{"value":"252979","family_comment":"","value_unclear":false,"comment_hidden":false,"family_unclear":false,"family":"","comment":""},"7":{"family_comment":"","value":"","source_name":"","family":"","comment":""},"8":{"family_comment":"","value":"","family":"","comment":""},"9":{"family_comment":"","family_unclear":false,"value":"","family":"","comment":""},"10":{"family_comment":"","value":"12180","value_unclear":false,"family":"","comment":""},"11":{"family_comment":"","value":"","family":"","comment":""},"12":{"family_comment":"","value":"","family":"","comment":""},"13":{"family_comment":"","value":"","family":"","comment":""},"14":{"family_comment":"","value":"","family":"","comment":""},"15":{"family_comment":"","value":"","family":"","comment":""},"16":{"family_comment":"","value":"","family":"","comment":""},"17":{"family_comment":"","value":"","family":"","comment":""},"18":{"family_comment":"","value":"","family":"","comment":""},"19":{"family_comment":"","value":"","family":"","comment":""},"20":{"value":"221","family":"","value_unclear":false,"family_hidden":false,"family_comment":"","comment_unclear":false,"comment":"відсотки по банківських рахунках","family_comment_unclear":false}},"id":"vulyk_97_149","banks":{"45":[{"sum_foreign_comment":"","sum_units":"UAH","sum_comment":"","sum_comment_unclear":false,"sum_hidden":false,"sum_foreign_units":"UAH","sum_comment_hidden":false,"sum_unclear":false,"sum":"32491","sum_foreign":""}]},"declaration":{"additional_info_text":"","notfull_lostpages":"","date":"2015-03-25T00:00:00","notfull":"","additional_info":"","url":"http://static.declarations.com.ua/declarations/chosen_ones/judges_batch/4051_vynohradova_oksana_ivanivna.pdf"},"liabilities":{"54":{"sum_foreign_comment":"","sum":"","sum_comment":"","sum_comment_unclear":false,"sum_hidden":false,"sum_comment_hidden":false,"sum_unclear":false,"sum_foreign":""},"55":{"sum_foreign_comment":"","sum":"","sum_comment":"","sum_foreign":""},"56":{"sum_foreign_comment":"","sum":"","sum_comment":"","sum_foreign":""},"57":{"sum_foreign_comment":"","sum":"","sum_comment":"","sum_comment_unclear":false,"sum_hidden":false,"sum_comment_hidden":false,"sum_unclear":false,"sum_foreign":""},"58":{"sum_foreign_comment":"","sum":"","sum_comment":"","sum_comment_unclear":false,"sum_hidden":false,"sum_comment_hidden":false,"sum_unclear":false,"sum_foreign":""},"59":{"sum_foreign_comment":"","sum":"","sum_comment":"","sum_foreign":""},"60":{"sum_foreign_comment":"","sum":"","sum_comment":"","sum_comment_unclear":false,"sum_hidden":false,"sum_comment_hidden":false,"sum_foreign":""},"61":{"sum_foreign_comment":"","sum":"","sum_comment":"","sum_foreign":""},"62":{"sum_foreign_comment":"","sum":"","sum_comment":"","sum_unclear":false,"sum_foreign":""},"63":{"sum_foreign_comment":"","sum":"","sum_hidden":false,"sum_comment":"","sum_foreign":""},"64":{"sum_foreign_comment":"","sum":"","sum_comment":"","sum_foreign":""}},"ft_src":"заступник голови київського окружного адміністративного суду\nКиївська область\nАдміністративний місцевий суд\nОксана\nІванівна\nВиноградова Оксана Іванівна\nОксана Іванівна Виноградова\nОксана Виноградова\nВиноградова Оксана Іванівна\nВиноградова Оксана Іванівна\nВиноградова\n117\n32491\n2014\n2014\nАдміністративний місцевий суд\nКиївська область\nзаступник голови київського окружного адміністративного суду\nВиноградова Оксана Іванівна\nОксана Іванівна Виноградова\nОксана Виноградова\nВиноградова Оксана Іванівна\nВиноградова Оксана Іванівна\nОксана\nВиноградова\nІванівна\n252979\nвідсотки по банківських рахунках\n221\n265380\n12180\n117\n32491\n252979\n12180\n265380\nвідсотки по банківських рахунках\n221\nІванівна\nВиноградова\nОксана\nВиноградова Оксана Іванівна\nОксана Іванівна Виноградова\nОксана Виноградова\nВиноградова Оксана Іванівна\nКиївська область\nАдміністративний місцевий суд\nзаступник голови київського окружного адміністративного суду\nВиноградова Оксана Іванівна\n12180\n221\nвідсотки по банківських рахунках\n265380\n252979\n117\n32491\n2014","general":{"name_hidden":false,"name":"Оксана","last_name_hidden":false,"inn":"","last_name":"Виноградова","patronymic":"Іванівна","inn_hidden":true,"family_raw":"","inn_unclear":false,"post":{"region_unclear":false,"region":"Київська область","post":"заступник голови київського окружного адміністративного суду","office":"Адміністративний місцевий суд","office_unclear":false,"post_hidden":false},"full_name":"Виноградова Оксана Іванівна","addresses":[{"place_district":"","place_city_hidden":true,"place_city":"","place_city_unclear":false,"place_district_hidden":false,"place_city_type":"","place_address_hidden":true,"place_city_type_hidden":false,"place_address":"","place_hidden":true,"place":""}],"patronymic_hidden":false,"full_name_suggest":{"output":"Виноградова Оксана Іванівна","input":["Виноградова Оксана Іванівна","Оксана Іванівна Виноградова","Оксана Виноградова"]}},"source":"VULYK","estate":{"25":[{"region_unclear":false,"space_unclear":false,"costs":"","costs_comment":"","address_hidden":false,"region_hidden":true,"space_comment":"","space_hidden":false,"space":"117","address":"","region":"","costs_rent_comment":"","space_comment_unclear":false,"space_comment_hidden":false,"space_units":"м²","costs_rent":""}]},"intro":{"declaration_year":"2014","isnotdeclaration":""}}