{"income":{"5":{"value":"268179","family_comment":"","value_unclear":false,"family_unclear":false,"family":"6215","comment":""},"6":{"value":"258090","family_comment":"","value_unclear":false,"family_unclear":false,"family":"5246","comment":""},"7":{"source_name_unclear":false,"value":"10089","family_comment":"","source_name":"","family":"","comment":""},"8":{"family_comment":"","value":"","family":"","comment":""},"9":{"family_comment":"","value":"","comment_unclear":false,"family":"","comment":""},"10":{"family_comment":"","value":"","family":"","comment":""},"11":{"family_comment":"","value":"","family":"","comment":""},"12":{"family_comment":"","value":"","family":"","comment":""},"13":{"family_comment":"","value":"","family":"","comment":""},"14":{"family_comment":"","value":"","family":"","comment":""},"15":{"family_comment":"","value":"","family":"","comment":""},"16":{"family_comment":"","value":"","family":"","comment":""},"17":{"family_comment":"","value":"","family":"","comment":""},"18":{"family_comment":"","value":"","family":"","comment":""},"19":{"family_comment":"","value":"","family":"","comment":""},"20":{"family_comment":"","value":"","comment_unclear":false,"family":"969","comment":""}},"vehicle":{"35":[{"year_hidden":false,"brand_info":"3956 куб. см.","sum_rent_comment":"","year":"2008","brand_info_unclear":false,"year_unclear":false,"sum_rent":"","sum":"","brand":"Toyota Land Cruiser Prado","sum_comment":"придбана у 2008 році","brand_unclear":false,"brand_hidden":false}],"40":[{"brand_info":"2354 куб. см.","sum_rent_comment":"","year":"2008","sum_hidden":false,"brand_info_unclear":false,"year_unclear":false,"sum_rent":"","sum":"","brand":"Honda CR-V","sum_comment":"придбано у 2013 році","brand_unclear":false,"brand_hidden":false}]},"id":"vulyk_17_187","banks":{"45":[{"sum_foreign_comment":"","sum_units":"UAH","sum_comment":"","sum_comment_unclear":false,"sum_hidden":false,"sum_foreign_units":"UAH","sum_units_unclear":false,"sum_comment_hidden":false,"sum_unclear":false,"sum":"","sum_foreign":""},{"sum_foreign_comment":"","sum_units":"","sum_comment":"","sum_foreign_units":"","sum_comment_hidden":false,"sum":"","sum_foreign":""},{"sum_foreign_comment":"","sum_units":"","sum_comment":"","sum_foreign_units":"","sum":"","sum_foreign":""},{"sum_foreign_comment":"","sum_units":"","sum_comment":"","sum_foreign_units":"","sum":"","sum_foreign":""}],"46":[{"sum_foreign_comment":"","sum_units":"UAH","sum_comment":"","sum_comment_unclear":false,"sum_hidden":false,"sum_foreign_units":"UAH","sum_comment_hidden":false,"sum":"","sum_foreign":""},{"sum_foreign_comment":"","sum_units":"","sum_comment":"","sum_foreign_units":"","sum":"","sum_foreign":""},{"sum_foreign_comment":"","sum_units":"","sum_comment":"","sum_foreign_units":"","sum":"","sum_foreign":""}],"47":[{"sum_foreign_comment":"","sum_units":"UAH","sum_comment":"","sum_comment_unclear":false,"sum_foreign_units":"UAH","sum":"","sum_foreign":""}],"48":[{"sum_foreign_comment":"","sum_units":"UAH","sum_comment":"","sum_foreign_units":"UAH","sum":"","sum_foreign":""}],"49":[{"sum_foreign_comment":"","sum_units":"UAH","sum_comment":"","sum_foreign_units":"UAH","sum":"","sum_foreign":""}],"50":[{"sum_foreign_comment":"","sum_units":"UAH","sum_comment":"","sum_foreign_units":"UAH","sum":"","sum_foreign":""}],"51":[{"sum_foreign_comment":"","sum_units":"UAH","sum_comment":"","sum_hidden":false,"sum_foreign_units":"UAH","sum_units_unclear":false,"sum_comment_hidden":false,"sum_unclear":false,"sum":"","sum_foreign":""},{"sum_foreign_comment":"","sum_units":"","sum_comment":"","sum_comment_unclear":false,"sum_foreign_units":"","sum":"","sum_unclear":false,"sum_foreign":""},{"sum_foreign_comment":"","sum_units":"","sum_comment":"","sum_foreign_units":"","sum":"","sum_foreign":""},{"sum_foreign_comment":"","sum_units":"","sum_comment":"","sum_foreign_units":"","sum":"","sum_foreign":""}],"52":[{"sum_foreign_comment":"","sum_units":"UAH","sum_comment":"","sum_comment_unclear":false,"sum_foreign_units":"UAH","sum":"","sum_foreign":""}],"53":[{"sum_foreign_comment":"","sum_units":"UAH","sum_comment":"","sum_foreign_units":"UAH","sum_comment_hidden":false,"sum":"","sum_foreign":""}]},"declaration":{"additional_info_text":"","notfull_lostpages":"","date":"2015-03-27T00:00:00","notfull":"","additional_info":"","url":"http://static.declarations.com.ua/declarations/chosen_ones/mega_batch/yurkevych_mykhailo_vasylovych.pdf"},"liabilities":{"54":{"sum_foreign_comment":"","sum":"12673","sum_comment":"","sum_comment_unclear":false,"sum_comment_hidden":false,"sum_unclear":false,"sum_foreign":""},"55":{"sum_foreign_comment":"","sum":"","sum_comment":"","sum_foreign":""},"56":{"sum_foreign_comment":"","sum":"16130","sum_comment":"","sum_unclear":false,"sum_foreign":""},"57":{"sum_foreign_comment":"","sum":"","sum_comment":"","sum_comment_unclear":false,"sum_hidden":false,"sum_comment_hidden":false,"sum_unclear":false,"sum_foreign":""},"58":{"sum_foreign_comment":"","sum":"","sum_comment":"","sum_comment_unclear":false,"sum_hidden":false,"sum_comment_hidden":false,"sum_unclear":false,"sum_foreign":""},"59":{"sum_foreign_comment":"","sum":"","sum_comment":"","sum_comment_unclear":false,"sum_foreign":""},"60":{"sum_foreign_comment":"","sum":"9012","sum_comment":"","sum_comment_unclear":false,"sum_hidden":false,"sum_comment_hidden":false,"sum_foreign":""},"61":{"sum_foreign_comment":"","sum":"","sum_comment":"","sum_foreign":""},"62":{"sum_foreign_comment":"","sum":"7620","sum_comment":"","sum_foreign":""},"63":{"sum_foreign_comment":"","sum":"","sum_comment":"","sum_comment_unclear":false,"sum_hidden":false,"sum_comment_hidden":false,"sum_unclear":false,"sum_foreign":""},"64":{"sum_foreign_comment":"","sum":"","sum_comment":"","sum_comment_unclear":false,"sum_hidden":false,"sum_comment_hidden":false,"sum_foreign":""}},"ft_src":"7620\n12673\n16130\n9012\nголова господарського суду львівської області\nЛьвівська область\nГосподарський місцевий суд\nМихайло\nЮркевич О. Я\nПодружжя\nЮркевич О. М\nДитина\nВасильович\nЮркевич\nЮркевич Михайло Васильович\nЮркевич Михайло Васильович\nМихайло Васильович Юркевич\nМихайло Юркевич\nЮркевич Михайло Васильович\nпридбана у 2008 році\n3956 куб. см.\nToyota Land Cruiser Prado\n2008\nпридбано у 2013 році\nHonda CR-V\n2354 куб. см.\n2008\n2014\n3956 куб. см.\nпридбана у 2008 році\nToyota Land Cruiser Prado\n2008\n2354 куб. см.\nHonda CR-V\nпридбано у 2013 році\n2008\n5.6\n1/5 квартири від пл. 28 кв м\n70.2\nпридбана у 2000р\nЮркевич Михайло Васильович\nМихайло Васильович Юркевич\nМихайло Юркевич\nЮркевич Михайло Васильович\nМихайло\nПодружжя\nЮркевич О. Я\nДитина\nЮркевич О. М\nЮркевич Михайло Васильович\nЮркевич\nГосподарський місцевий суд\nЛьвівська область\nголова господарського суду львівської області\nВасильович\n9012\n16130\n7620\n12673\n10089\n258090\n5246\n969\n268179\n6215\n2014\n16130\n7620\n12673\n9012\n1/5 квартири від пл. 28 кв м\n5.6\nпридбана у 2000р\n70.2\nПодружжя\nЮркевич О. Я\nЮркевич О. М\nДитина\nВасильович\nЮркевич\nМихайло\nЮркевич Михайло Васильович\nМихайло Васильович Юркевич\nМихайло Юркевич\nЮркевич Михайло Васильович\nЛьвівська область\nГосподарський місцевий суд\nголова господарського суду львівської області\nЮркевич Михайло Васильович\n5246\n258090\n10089\n6215\n268179\n969\nToyota Land Cruiser Prado\nпридбана у 2008 році\n3956 куб. см.\n2008\n2008\nHonda CR-V\nпридбано у 2013 році\n2354 куб. см.\n969\n268179\n6215\n10089\n258090\n5246\n1/5 квартири від пл. 28 кв м\n5.6\n70.2\nпридбана у 2000р\n2014","general":{"name_hidden":false,"name":"Михайло","patronymic_unclear":false,"inn":"","family":[{"inn":"","inn_hidden":true,"relations_unclear":false,"relations_hidden":false,"relations_other":"","relations":"Подружжя","name_hidden":false,"inn_unclear":false,"family_name":"Юркевич О. Я","name_unclear":false},{"inn":"","relations":"Дитина","inn_unclear":false,"family_name":"Юркевич О. М","inn_hidden":false,"relations_other":"","name_hidden":false,"name_unclear":false}],"patronymic":"Васильович","inn_hidden":true,"family_raw":"","inn_unclear":false,"post":{"post_unclear":false,"region_unclear":false,"post":"голова господарського суду львівської області","candidate":"","office_hidden":false,"region":"Львівська область","post_hidden":false,"office":"Господарський місцевий суд","office_unclear":false,"region_hidden":false},"last_name_unclear":false,"full_name":"Юркевич Михайло Васильович","addresses":[{"place_address":"","place_district_hidden":true,"place_city_type":"","place_city_hidden":true,"place_city_type_hidden":true,"place":"","place_district":"","place_unclear":false,"place_city":"","place_city_unclear":false,"place_hidden":true,"place_address_hidden":true,"place_district_unclear":false}],"last_name":"Юркевич","patronymic_hidden":false,"full_name_suggest":{"output":"Юркевич Михайло Васильович","input":["Юркевич Михайло Васильович","Михайло Васильович Юркевич","Михайло Юркевич"]},"name_unclear":false},"source":"VULYK","estate":{"23":[{"space_hidden":false,"costs":"","costs_comment":"","address_hidden":false,"region_hidden":false,"space_comment":"","space":"","address":"","region":"","costs_rent_comment":"","space_units":"м²","costs_rent":""},{"costs_rent":"","region":"","costs":"","costs_rent_comment":"","costs_comment":"","region_hidden":false,"space_comment":"","space_units":"","space":"","address":""},{"costs_rent":"","costs":"","costs_rent_comment":"","costs_comment":"","space_comment":"","space_units":"","space":"","address":""}],"25":[{"space_unclear":false,"costs":"","costs_comment":"придбана у 2000р","address_hidden":true,"region_hidden":false,"space_comment":"","space_hidden":false,"space":"70.2","address":"","region":"","costs_rent_comment":"","space_comment_unclear":false,"space_units":"м²","space_units_hidden":false,"costs_rent":""}],"31":[{"region_unclear":false,"space_unclear":false,"address_hidden":true,"region_hidden":false,"space_comment":"1/5 квартири від пл. 28 кв м","space_hidden":false,"space":"5.6","address":"","region":"","costs_property":"","costs_rent_comment":"","space_comment_unclear":false,"space_comment_hidden":false,"space_units":"м²","costs_property_comment":"","costs_rent":""}]},"intro":{"declaration_year":"2014","isnotdeclaration":"","declaration_year_hidden":false}}