{"income":{"5":{"value":"304436","value_unclear":false,"family_hidden":false,"family_comment":"","family":"100260","comment":""},"6":{"family_comment":"","value":"247362","value_unclear":false,"family":"83291","comment":""},"7":{"source_name_unclear":false,"value":"","family_comment":"","source_name":"","family":"","comment":"","source_name_hidden":false},"8":{"family_comment":"","value":"","family":"","comment":""},"9":{"family_comment":"","value":"","comment_unclear":false,"family":"","comment":""},"10":{"family_comment":"","value":"","family":"","comment":""},"11":{"family_comment":"","family_unclear":false,"value":"","family":"","comment":""},"12":{"family_comment":"","value":"","family":"","comment":""},"13":{"family_comment":"","value":"","family":"","comment":""},"14":{"family_comment":"","value":"","family":"","comment":""},"15":{"family_comment":"","value":"","family":"","comment":""},"16":{"family_comment":"","value":"","family":"","comment":""},"17":{"family_comment":"","value":"","family":"","comment":""},"18":{"family_comment":"","value":"","family":"","comment":""},"19":{"family_comment":"","value":"","family":"","comment":""},"20":{"value":"57074","value_unclear":false,"family_comment":"","comment_unclear":false,"comment":"","family":"16969"}},"vehicle":{"40":[{"brand_info":"1497 куб. см.","sum":"","brand":"ЗАЗ Vida","sum_comment":"","brand_unclear":false,"year":"2013","brand_hidden":false,"brand_info_hidden":false,"brand_info_unclear":false,"sum_rent_comment":"","sum_rent":""}]},"id":"vulyk_94_155","declaration":{"additional_info_text":"","notfull_lostpages":"","date":"2015-03-25T00:00:00","notfull":"","additional_info":"","url":"http://static.declarations.com.ua/declarations/chosen_ones/judges_batch/3801_makarenko_ihor_volodymyrovych.pdf"},"liabilities":{"54":{"sum_foreign_comment":"","sum":"","sum_comment":"","sum_comment_unclear":false,"sum_comment_hidden":false,"sum_unclear":false,"sum_foreign":""},"55":{"sum_foreign_comment":"","sum":"","sum_comment":"","sum_foreign":""},"56":{"sum_foreign_comment":"","sum":"","sum_comment":"","sum_unclear":false,"sum_foreign":""},"57":{"sum_foreign_comment":"","sum":"","sum_comment":"","sum_hidden":false,"sum_unclear":false,"sum_foreign":""},"58":{"sum_foreign_comment":"","sum":"","sum_comment":"","sum_hidden":false,"sum_unclear":false,"sum_foreign":""},"59":{"sum_foreign_comment":"","sum":"","sum_comment":"","sum_foreign":""},"60":{"sum_foreign_comment":"","sum_comment":"","sum":"","sum_comment_hidden":false,"sum_foreign":""},"61":{"sum_foreign_comment":"","sum":"","sum_comment":"","sum_foreign":""},"62":{"sum_foreign_comment":"","sum":"","sum_foreign":"","sum_comment":"","sum_hidden":false},"63":{"sum_foreign_comment":"","sum_comment":"","sum":"","sum_comment_hidden":false,"sum_foreign":""},"64":{"sum_foreign_comment":"","sum":"","sum_comment":"","sum_unclear":false,"sum_foreign":""}},"ft_src":"ЗАЗ Vida\n1497 куб. см.\n2013\n1/2 частина\nм. Черкаси\nЧеркаська область\n94.5\nЧеркаська область\nм. Черкаси\n42.8\n2014\n83291\n247362\n100260\n304436\n16969\n57074\n1497 куб. см.\n2013\nЗАЗ Vida\n2014\nПодружжя\nМакаренко О. В\nДитина\nМакаренко А. І\nІнше\nзять\nМакаренко С. Ю\nМакаренко Ігор Володимирович\nІгор Володимирович Макаренко\nІгор Макаренко\nМакаренко Ігор Володимирович\nМакаренко Ігор Володимирович\nІгор\nВолодимирович\nЗагальний місцевий суд\nЧеркаська область\nзаступник голови придніпровського районного суду м. черкаси\nМакаренко\n18023\nЧеркаська область\nЧеркаси\n247362\n83291\n57074\n16969\n304436\n100260\n94.5\n1/2 частина\nм. Черкаси\nЧеркаська область\n42.8\nм. Черкаси\nЧеркаська область\nМакаренко О. В\nПодружжя\nМакаренко А. І\nДитина\nзять\nМакаренко С. Ю\nІнше\nВолодимирович\nМакаренко\nІгор\nМакаренко Ігор Володимирович\nІгор Володимирович Макаренко\nІгор Макаренко\nМакаренко Ігор Володимирович\nЧеркаська область\nЧеркаси\n18023\nЧеркаська область\nЗагальний місцевий суд\nзаступник голови придніпровського районного суду м. черкаси\nМакаренко Ігор Володимирович","general":{"inn":"","name":"Ігор","last_name":"Макаренко","family":[{"inn":"","inn_hidden":true,"relations_hidden":false,"family_name":"Макаренко О. В","relations":"Подружжя","name_hidden":true,"name_unclear":false},{"inn":"","inn_hidden":false,"relations_unclear":false,"family_name":"Макаренко А. І","relations_other":"","relations":"Дитина","name_hidden":true,"name_unclear":false},{"inn":"","inn_hidden":false,"relations_unclear":false,"family_name":"Макаренко С. Ю","relations_other":"зять","relations":"Інше","name_hidden":true,"name_unclear":false}],"inn_hidden":true,"family_raw":"","inn_unclear":false,"post":{"post_unclear":false,"region_unclear":false,"post":"заступник голови придніпровського районного суду м. черкаси","candidate":"","post_hidden":false,"region":"Черкаська область","office":"Загальний місцевий суд","office_unclear":false},"full_name":"Макаренко Ігор Володимирович","addresses":[{"place_district":"","place_address_hidden":true,"place_city":"Черкаси","place_address":"18023","place_district_hidden":false,"place_city_type":"Місто","place_city_hidden":false,"place_city_type_hidden":false,"place_hidden":false,"place":"Черкаська область"}],"patronymic":"Володимирович","patronymic_hidden":false,"full_name_suggest":{"output":"Макаренко Ігор Володимирович","input":["Макаренко Ігор Володимирович","Ігор Володимирович Макаренко","Ігор Макаренко"]}},"source":"VULYK","estate":{"31":[{"space_hidden":false,"costs_property_hidden":false,"address_hidden":false,"region_hidden":false,"space_comment":"1/2 частина","space_unclear":false,"space":"94.5","address":"м. Черкаси","costs_property_comment_hidden":false,"region":"Черкаська область","costs_property":"","costs_rent_comment":"","costs_rent_hidden":false,"space_comment_unclear":false,"costs_rent_comment_hidden":false,"space_units":"м²","costs_property_comment":"","costs_rent":""},{"costs_rent":"","region":"Черкаська область","costs_property":"","costs_rent_comment":"","address_hidden":false,"region_hidden":false,"space_comment":"","costs_property_comment":"","space_units":"м²","space":"42.8","address":"м. Черкаси"}]},"intro":{"declaration_year":"2014","isnotdeclaration":""}}