{"income":{"5":{"family_comment":"","value":"320497","family_hidden":false,"comment":"","family":"15419"},"6":{"value":"320497","value_unclear":false,"family_hidden":false,"family_comment":"","family":"","comment":""},"7":{"family_comment":"","value":"","source_name":"","family":"","comment":""},"8":{"family_comment":"","value":"","family":"","comment":""},"9":{"family_comment":"","value":"","value_unclear":false,"family":"","comment":""},"10":{"family_comment":"","value":"","value_unclear":false,"family":"","comment":""},"11":{"family_comment":"","value":"","family":"","comment":""},"12":{"family_comment":"","value":"","family":"","comment":""},"13":{"family_comment":"","value":"","family":"","comment":""},"14":{"family_comment":"","value":"","family":"","comment":""},"15":{"family_comment":"","value":"","family":"","comment":""},"16":{"family_comment":"","value":"","family":"","comment":"","family_comment_hidden":false},"17":{"family_comment":"","value":"","family_hidden":false,"comment":"","family":""},"18":{"family_comment":"","value":"","family":"","comment":""},"19":{"family_comment":"","value":"","family":"","comment":""},"20":{"value":"","value_unclear":false,"family_comment_hidden":false,"family_comment":"","comment_unclear":false,"comment":"","family":"15419"}},"vehicle":{"35":[{"year_hidden":false,"brand_info":"2.0 л","sum_rent_comment":"","year":"1990","brand_info_hidden":false,"brand_info_unclear":false,"year_unclear":false,"sum_rent":"","sum":"","brand":"Audi 100","sum_comment":"","brand_unclear":false,"brand_hidden":false,"sum_unclear":false}]},"id":"vulyk_42_125","banks":{"45":[{"sum_foreign_comment":"","sum_units":"UAH","sum_comment":"","sum_foreign_comment_hidden":false,"sum_hidden":false,"sum_foreign_units":"UAH","sum_foreign_hidden":false,"sum_comment_hidden":false,"sum_unclear":false,"sum":"1198","sum_foreign":""},{"sum_foreign_comment":"","sum_units":"","sum_comment":"","sum_foreign_units":"","sum":"","sum_foreign":""}],"46":[{"sum_foreign_comment":"","sum_units":"UAH","sum_comment":"","sum_hidden":false,"sum_foreign_units":"UAH","sum_comment_hidden":false,"sum_unclear":false,"sum":"","sum_foreign":""}],"47":[{"sum_foreign_comment":"","sum_units":"UAH","sum_comment":"","sum_comment_unclear":false,"sum_hidden":false,"sum_foreign_units":"UAH","sum":"","sum_foreign":""},{"sum_foreign_comment":"","sum":"","sum_comment":"","sum_foreign":""}],"48":[{"sum_foreign_comment":"","sum_units":"UAH","sum_comment":"","sum_foreign_units":"UAH","sum":"","sum_foreign":""}],"49":[{"sum_foreign_comment":"","sum_units":"UAH","sum_comment":"","sum_foreign_units":"UAH","sum":"","sum_foreign":""}],"50":[{"sum_foreign_comment":"","sum_units":"UAH","sum_comment":"","sum_foreign_units":"UAH","sum":"","sum_foreign":""}],"51":[{"sum_foreign_comment":"","sum_units":"UAH","sum_comment":"","sum_comment_unclear":false,"sum_hidden":false,"sum_foreign_units":"UAH","sum_comment_hidden":false,"sum":"","sum_foreign":""},{"sum_foreign_comment":"","sum_units":"","sum_comment":"","sum_hidden":false,"sum_foreign_units":"","sum":"","sum_units_hidden":false,"sum_foreign":""}],"52":[{"sum_foreign_comment":"","sum_units":"UAH","sum_comment":"","sum_comment_unclear":false,"sum_hidden":false,"sum_foreign_units":"UAH","sum":"","sum_units_hidden":false,"sum_foreign":""}],"53":[{"sum_foreign_comment":"","sum_units":"UAH","sum_comment":"","sum_foreign_units":"UAH","sum":"59791","sum_foreign":""}]},"declaration":{"additional_info_text":"","notfull_lostpages":"","date":"2015-03-27T00:00:00","notfull":"","additional_info":"","url":"http://static.declarations.com.ua/declarations/chosen_ones/mega_batch/martsynkevych_anatolii_mykolaiovych.pdf"},"liabilities":{"54":{"sum_foreign_comment":"","sum":"","sum_comment":"","sum_foreign_comment_hidden":false,"sum_comment_hidden":false,"sum_foreign":""},"55":{"sum_foreign_comment":"","sum":"","sum_comment":"","sum_foreign":""},"56":{"sum_foreign_comment":"","sum":"","sum_comment":"","sum_foreign":""},"57":{"sum_foreign_comment":"","sum":"86851","sum_comment":"","sum_comment_unclear":false,"sum_comment_hidden":false,"sum_unclear":false,"sum_foreign":""},"58":{"sum_foreign_comment":"","sum":"29800","sum_comment":"","sum_foreign_unclear":false,"sum_comment_hidden":false,"sum_unclear":false,"sum_foreign":""},"59":{"sum_foreign_comment":"","sum":"","sum_comment":"","sum_foreign":""},"60":{"sum_foreign_comment":"","sum":"","sum_comment":"","sum_comment_unclear":false,"sum_hidden":false,"sum_comment_hidden":false,"sum_foreign":""},"61":{"sum_foreign_comment":"","sum":"","sum_comment":"","sum_foreign":""},"62":{"sum_foreign_comment":"","sum":"","sum_comment":"","sum_hidden":false,"sum_comment_hidden":false,"sum_foreign":""},"63":{"sum_foreign_comment":"","sum":"","sum_comment":"","sum_comment_hidden":false,"sum_unclear":false,"sum_foreign":""},"64":{"sum_foreign_comment":"","sum":"","sum_comment":"","sum_hidden":false,"sum_comment_hidden":false,"sum_foreign":""}},"ft_src":"86851\n29800\nКиїв\nм. Київ\nсуддя апеляційного суду хмельницької області\nХмельницька область\nЗагальний апеляційний суд\nАнатолій\nМарцинкевич Г. П.\nПодружжя\nМиколайович\nМарцинкевич Анатолій Миколайович\nАнатолій Миколайович Марцинкевич\nАнатолій Марцинкевич\nМарцинкевич Анатолій Миколайович\nМарцинкевич\nМарцинкевич Анатолій Миколайович\n2.0 л\nAudi 100\n1990\n1198\n59791\n2014\n2.0 л\nAudi 100\n1990\n1198\n59791\n1000\nХмельницька область\nм. Хмельницький\n1800\nХмельницька область\nм. Хмельницький\nм. Хмельницький\nХмельницька область\n81\nХмельницька область\nм. Хмельницький\nПодружжя\nМарцинкевич Г. П.\nМарцинкевич Анатолій Миколайович\nАнатолій Миколайович Марцинкевич\nАнатолій Марцинкевич\nМарцинкевич Анатолій Миколайович\nМарцинкевич Анатолій Миколайович\nАнатолій\nМарцинкевич\nсуддя апеляційного суду хмельницької області\nЗагальний апеляційний суд\nХмельницька область\nМиколайович\nм. Київ\nКиїв\n86851\n29800\n320497\n15419\n320497\n15419\n2014\n29800\n86851\nм. Хмельницький\n1000\nХмельницька область\nм. Хмельницький\nХмельницька область\n81\nм. Хмельницький\nХмельницька область\n1800\nм. Хмельницький\nХмельницька область\nМарцинкевич Г. П.\nПодружжя\nМиколайович\nМарцинкевич\nАнатолій\nМарцинкевич Анатолій Миколайович\nАнатолій Миколайович Марцинкевич\nАнатолій Марцинкевич\nМарцинкевич Анатолій Миколайович\nм. Київ\nКиїв\nХмельницька область\nсуддя апеляційного суду хмельницької області\nЗагальний апеляційний суд\nМарцинкевич Анатолій Миколайович\n320497\n15419\n320497\n15419\nAudi 100\n2.0 л\n1990\n15419\n15419\n320497\n320497\nм. Хмельницький\nХмельницька область\n81\nм. Хмельницький\nХмельницька область\n1000\nм. Хмельницький\nХмельницька область\nм. Хмельницький\nХмельницька область\n1800\n1198\n59791\n2014","general":{"inn":"","name":"Анатолій","patronymic_unclear":false,"last_name_hidden":false,"family":[{"inn":"","inn_hidden":true,"relations_hidden":false,"family_name":"Марцинкевич Г. П.","relations_other":"","relations":"Подружжя","name_hidden":false,"name_unclear":false}],"patronymic":"Миколайович","inn_hidden":true,"family_raw":"","last_name":"Марцинкевич","post":{"region_unclear":false,"region":"Хмельницька область","post":"суддя апеляційного суду хмельницької області","office":"Загальний апеляційний суд","office_hidden":false,"region_hidden":false},"last_name_unclear":false,"full_name":"Марцинкевич Анатолій Миколайович","addresses":[{"place_district":"","place_city_hidden":false,"place_city":"Київ","place_city_type_hidden":false,"place_district_hidden":false,"place_city_type":"Місто","place_address_hidden":true,"place_address":"","place_hidden":false,"place":"м. Київ"}],"full_name_suggest":{"output":"Марцинкевич Анатолій Миколайович","input":["Марцинкевич Анатолій Миколайович","Анатолій Миколайович Марцинкевич","Анатолій Марцинкевич"]}},"source":"VULYK","estate":{"23":[{"space_unclear":false,"costs":"","costs_comment":"","address_hidden":true,"region_hidden":false,"space_comment":"","space_hidden":false,"space":"1000","address":"м. Хмельницький","region":"Хмельницька область","address_unclear":false,"space_units_unclear":false,"space_comment_unclear":false,"space_units":"м²","costs_rent":"","costs_rent_comment":""},{"costs":"","costs_comment":"","address_hidden":false,"region_hidden":false,"space_comment":"","space_units_unclear":false,"address":"","space":"","region":"","costs_rent_comment":"","space_units":"","costs_rent":""},{"costs_rent":"","region":"","costs":"","costs_rent_comment":"","costs_comment":"","space_comment":"","space_units":"","space":"","address":""},{"costs_rent":"","region":"","costs":"","costs_rent_comment":"","costs_comment":"","space_comment":"","space_units":"","space":"","address":""},{"costs_rent":"","region":"","costs":"","costs_rent_comment":"","costs_comment":"","space_comment":"","space_units":"","space":"","address":""},{"costs_rent":"","costs":"","costs_rent_comment":"","costs_comment":"","space_comment":"","space_units":"","space":"","address":""}],"24":[{"space_hidden":true,"costs":"","costs_comment":"","address_hidden":true,"region_hidden":false,"space_comment":"","space_unclear":false,"space":"","address":"м. Хмельницький","region":"Хмельницька область","costs_rent_comment":"","space_units":"м²","costs_rent":""}],"29":[{"space_hidden":false,"address_hidden":false,"region_hidden":false,"space_comment":"","space":"1800","address":"м. Хмельницький","region":"Хмельницька область","costs_property":"","costs_rent_comment":"","space_units":"м²","costs_property_comment":"","costs_rent":""}],"30":[{"space_hidden":false,"address_hidden":true,"region_hidden":true,"space_comment":"","space":"81","address":"м. Хмельницький","region":"Хмельницька область","costs_property":"","costs_rent_comment":"","space_units":"м²","costs_property_comment":"","costs_rent":""}]},"intro":{"declaration_year":"2014","isnotdeclaration":""}}