{"income":{"5":{"value":"234875","family_comment":"","value_unclear":false,"family_hidden":false,"value_hidden":false,"family_unclear":false,"family":"88463","comment":""},"6":{"value":"234875","family_comment":"","value_unclear":false,"family_unclear":false,"family":"24865","comment":""},"7":{"source_name_unclear":false,"value":"","comment_hidden":false,"family_comment":"","source_name":"","family":"","comment":"","source_name_hidden":false},"8":{"family_comment":"","value":"","family":"","comment":""},"9":{"value":"","family_comment":"","value_unclear":false,"family_hidden":false,"family_unclear":false,"family":"","comment":"","family_comment_unclear":false},"10":{"family_comment":"","value":"","family":"","comment":""},"11":{"family_comment":"","value":"","family":"","comment":""},"12":{"family_comment":"","value":"","family":"","comment":""},"13":{"family_comment":"","value":"","family":"","comment":""},"14":{"family_comment":"","value":"","family":"","comment":""},"15":{"family_comment":"","value":"","family":"","comment":""},"16":{"family_comment":"","value":"","family":"","comment":""},"17":{"family_comment":"","value":"","family":"","comment":""},"18":{"family_comment":"","value":"","family":"","comment":""},"19":{"family_comment":"","value":"","family":"","comment":""},"20":{"value":"","family_comment":"пенсія, стипендія, виплати по народженню дитини","value_unclear":false,"family_comment_hidden":false,"family_unclear":false,"family_comment_unclear":false,"comment_unclear":false,"comment":"","family":"63598"}},"vehicle":{"39":[{"brand_info":"автопричіп","sum_rent_comment":"","brand":"ПФ-1 фермер","sum_comment":"","brand_unclear":false,"year":"2006","sum":"","sum_rent":""}],"40":[{"brand_info":"1500 куб. см., 81 кВт","sum_rent_comment":"","brand":"Renault Megane","sum_comment":"","year":"2010","brand_info_unclear":false,"sum":"","sum_rent":""}]},"id":"vulyk_93_137","declaration":{"additional_info_text":"","notfull_lostpages":"","date":"2015-03-30T00:00:00","notfull":"","additional_info":"","url":"http://static.declarations.com.ua/declarations/chosen_ones/judges_batch/3583_taratin_valentyn_oleksandrovych.pdf"},"liabilities":{"54":{"sum_foreign_comment":"","sum":"","sum_hidden":false,"sum_comment":"","sum_foreign":""},"55":{"sum_foreign_comment":"","sum":"","sum_comment":"","sum_foreign":""},"56":{"sum_foreign_comment":"","sum":"","sum_comment":"","sum_foreign":""},"57":{"sum_foreign_comment":"","sum":"","sum_comment":"","sum_hidden":false,"sum_comment_hidden":false,"sum_unclear":false,"sum_foreign":""},"58":{"sum_foreign_comment":"","sum":"","sum_comment":"","sum_comment_unclear":false,"sum_hidden":false,"sum_unclear":false,"sum_foreign":""},"59":{"sum_foreign_comment":"","sum":"","sum_comment":"","sum_foreign":""},"60":{"sum_foreign_comment":"","sum":"","sum_hidden":false,"sum_comment":"","sum_foreign":""},"61":{"sum_foreign_comment":"","sum":"","sum_comment":"","sum_foreign":""},"62":{"sum_foreign_comment":"","sum":"","sum_comment":"","sum_foreign":""},"63":{"sum_foreign_comment":"","sum":"","sum_comment":"","sum_foreign":""},"64":{"sum_foreign_comment":"","sum":"","sum_comment":"","sum_foreign":""}},"ft_src":"Таратін Валентин Олександрович\nсуддя золотоніського міськрайонного суду черкаської області\nЧеркаська область\nЗагальний місцевий суд\nВалентин\nТаратіна А. В. 23. 11. 1978\nПодружжя\nТаратіна А. В. 16. 08. 1995\nДитина\nТаратіна В. В. 25. 09. 2000\nДитина\nТаратін Г. В. 23. 10. 2013\nДитина\nТаратін Валентин Олександрович\nВалентин Олександрович Таратін\nВалентин Таратін\nТаратін Валентин Олександрович\nТаратін\nОлександрович\n2006\nавтопричіп\nПФ-1 фермер\n1500 куб. см., 81 кВт\n2010\nRenault Megane\n6.93\n6.93\n27.3\n180\n180\n27.3\n25.5\n2014\n24865\n234875\n88463\n234875\n63598\nпенсія, стипендія, виплати по народженню дитини\n1500 куб. см., 81 кВт\nRenault Megane\n2010\nавтопричіп\nПФ-1 фермер\n2006\n6.93\n27.3\n25.5\n180\n180\n6.93\n27.3\nТаратін\nПодружжя\nТаратіна А. В. 23. 11. 1978\nДитина\nТаратіна А. В. 16. 08. 1995\nДитина\nТаратіна В. В. 25. 09. 2000\nДитина\nТаратін Г. В. 23. 10. 2013\nТаратін Валентин Олександрович\nВалентин Олександрович Таратін\nВалентин Таратін\nТаратін Валентин Олександрович\nТаратін Валентин Олександрович\nВалентин\nОлександрович\nЧеркаська область\nЗагальний місцевий суд\nсуддя золотоніського міськрайонного суду черкаської області\n24865\n234875\n63598\nпенсія, стипендія, виплати по народженню дитини\n234875\n88463\n2014\nПодружжя\nТаратіна А. В. 23. 11. 1978\nДитина\nТаратіна А. В. 16. 08. 1995\nДитина\nТаратіна В. В. 25. 09. 2000\nТаратін Г. В. 23. 10. 2013\nДитина\nТаратін\nОлександрович\nЧеркаська область\nЗагальний місцевий суд\nсуддя золотоніського міськрайонного суду черкаської області\nТаратін Валентин Олександрович\nТаратін Валентин Олександрович\nВалентин Олександрович Таратін\nВалентин Таратін\nТаратін Валентин Олександрович\nВалентин\n2006\nавтопричіп\nПФ-1 фермер\n2010\n1500 куб. см., 81 кВт\nRenault Megane\nпенсія, стипендія, виплати по народженню дитини\n63598\n234875\n88463\n234875\n24865\n25.5\n180\n27.3\n6.93\n27.3\n6.93\n180\n2014","general":{"inn":"","inn_hidden":true,"last_name":"Таратін","post":{"post_unclear":false,"region_unclear":false,"region":"Черкаська область","candidate":"","post":"суддя золотоніського міськрайонного суду черкаської області","office":"Загальний місцевий суд","office_unclear":false},"name":"Валентин","full_name":"Таратін Валентин Олександрович","family_raw":"","addresses":[{"place_district":"","place_city_hidden":false,"place_city":"","place_city_type_hidden":false,"place_district_hidden":false,"place_city_type":"","place_address_hidden":false,"place_address":"","place_hidden":true,"place":""}],"family":[{"inn":"","relations":"Подружжя","relations_hidden":false,"inn_hidden":false,"relations_other":"","name_hidden":false,"family_name":"Таратіна А. В. 23. 11. 1978","name_unclear":false},{"inn":"","relations":"Дитина","relations_other":"","inn_hidden":false,"family_name":"Таратіна А. В. 16. 08. 1995","name_hidden":false,"name_unclear":false},{"inn":"","relations":"Дитина","relations_other":"","inn_hidden":false,"family_name":"Таратіна В. В. 25. 09. 2000","name_hidden":false,"name_unclear":false},{"inn":"","relations":"Дитина","relations_other":"","inn_hidden":false,"family_name":"Таратін Г. В. 23. 10. 2013","name_hidden":false}],"full_name_suggest":{"output":"Таратін Валентин Олександрович","input":["Таратін Валентин Олександрович","Валентин Олександрович Таратін","Валентин Таратін"]},"patronymic":"Олександрович"},"source":"VULYK","estate":{"23":[{"space_unclear":false,"costs":"","costs_comment":"","address_hidden":false,"region_hidden":true,"space_comment":"","space":"180","address":"","region":"","costs_rent_comment":"","space_comment_unclear":false,"space_units":"м²","costs_rent":""}],"24":[{"space_unclear":false,"costs":"","costs_comment":"","address_hidden":false,"region_hidden":true,"space_comment":"","space":"27.3","address":"","region":"","costs_rent_comment":"","space_comment_unclear":false,"space_units":"м²","costs_rent":""}],"25":[{"space_hidden":false,"costs":"","costs_comment":"","address_hidden":false,"region_hidden":true,"space_comment":"","space_unclear":false,"space":"25.5","address":"","costs_rent_comment_unclear":false,"region":"","costs_rent_comment":"","space_units":"м²","costs_rent":""}],"27":[{"costs_rent":"","region":"","costs":"","costs_rent_comment":"","costs_comment":"","address_hidden":false,"region_hidden":true,"space_comment":"","space_units":"м²","space":"6.93","address":""}],"29":[{"space_unclear":false,"address_hidden":true,"region_hidden":true,"space_comment":"","space":"180","address":"","region":"","costs_property":"","costs_rent_comment":"","space_comment_unclear":false,"space_units":"м²","costs_property_comment":"","costs_rent":""}],"30":[{"space_unclear":false,"address_hidden":true,"region_hidden":true,"space_comment":"","space":"27.3","address":"","region":"","costs_property":"","costs_rent_comment":"","space_units":"м²","costs_property_comment":"","costs_rent":""}],"33":[{"space_hidden":false,"address_hidden":true,"region_hidden":true,"space_comment":"","space":"6.93","address":"","region":"","costs_property":"","costs_rent_comment":"","space_units":"м²","costs_property_comment":"","costs_rent":""}]},"intro":{"declaration_year":"2014","isnotdeclaration":""}}