{"income":{"5":{"value":"178556","family_comment":"","value_unclear":false,"family_hidden":false,"family_unclear":false,"family":"133258","comment":""},"6":{"value":"165673","value_unclear":false,"comment_hidden":false,"family_hidden":false,"value_hidden":false,"family_comment":"","family":"133258","comment":""},"7":{"value":"","family_comment":"","source_name":"","family":"","comment":"","source_name_hidden":false},"8":{"family_comment":"","value":"","family":"","comment":""},"9":{"family_comment":"","value":"","family":"","comment":"","value_hidden":false},"10":{"value":"12180","value_unclear":false,"family_hidden":false,"value_hidden":false,"family_comment":"","family":"","comment":""},"11":{"family_comment":"","value":"","family":"","comment":""},"12":{"family_comment":"","value":"","family":"","comment":""},"13":{"family_comment":"","value":"","comment_hidden":false,"family":"","comment":""},"14":{"value":"","comment_hidden":false,"value_hidden":false,"family_comment":"","family":"","comment":""},"15":{"family_comment":"","value":"","family":"","comment":""},"16":{"family_comment":"","value":"","family":"","comment":"","value_hidden":false},"17":{"family_comment":"","value":"","family":"","comment":""},"18":{"family_comment":"","value":"","family":"","comment":""},"19":{"family_comment":"","value":"","family":"","comment":"","value_hidden":false},"20":{"value":"702","family_comment":"","comment_unclear":false,"family_unclear":false,"family":"","comment":""}},"vehicle":{"40":[{"year_hidden":false,"brand_info":"2362 куб. см., 123 кВт , 480.5 см","sum_rent_comment":"","year":"2008","brand_info_hidden":false,"brand_info_unclear":false,"sum_rent":"","sum":"","brand":"Toyota Camry","sum_comment":"","brand_unclear":false,"brand_hidden":false}]},"id":"vulyk_12_71","banks":{"45":[{"sum_foreign_comment":"","sum":"","sum_comment":"","sum_hidden":false,"sum_foreign_units":"UAH","sum_foreign_hidden":false,"sum_units":"UAH","sum_comment_hidden":false,"sum_unclear":false,"sum_foreign":"","sum_units_hidden":false},{"sum_foreign_comment":"","sum_units":"","sum_comment":"","sum_foreign_units":"","sum":"","sum_foreign":""}],"46":[{"sum_foreign_comment":"","sum_units":"UAH","sum_comment":"","sum_hidden":false,"sum_foreign_units":"UAH","sum":"","sum_foreign_hidden":false,"sum_foreign":""}],"47":[{"sum_foreign_comment":"","sum_units":"UAH","sum_comment":"","sum_comment_unclear":false,"sum_foreign_units":"UAH","sum":"","sum_foreign":""},{"sum_foreign_comment":"","sum_units":"","sum_comment":"","sum_foreign_units":"","sum":"","sum_foreign":""}],"48":[{"sum_foreign_comment":"","sum_units":"UAH","sum_comment":"","sum_foreign_units":"UAH","sum":"","sum_foreign":""}],"49":[{"sum_foreign_comment":"","sum_units":"UAH","sum_comment":"","sum_foreign_units":"UAH","sum":"","sum_foreign":""}],"50":[{"sum_foreign_comment":"","sum_units":"UAH","sum_comment":"","sum_foreign_units":"UAH","sum":"","sum_foreign":""}],"51":[{"sum_foreign_comment":"","sum_units":"UAH","sum_comment":"","sum_hidden":false,"sum_foreign_units":"UAH","sum_comment_hidden":false,"sum_units_hidden":false,"sum":"","sum_foreign":""}],"52":[{"sum_foreign_comment":"","sum_units":"UAH","sum_comment":"","sum_comment_unclear":false,"sum_foreign_units":"UAH","sum":"","sum_foreign":""},{"sum_foreign_comment":"","sum_units":"","sum_comment":"","sum_foreign_units":"","sum":"","sum_foreign":""},{"sum_foreign_comment":"","sum_units":"","sum_comment":"","sum_foreign_units":"","sum":"","sum_foreign":""},{"sum_foreign_comment":"","sum_units":"","sum_comment":"","sum_foreign_units":"","sum":"","sum_foreign":""}],"53":[{"sum_foreign_comment":"","sum_units":"UAH","sum_comment":"","sum_foreign_units":"UAH","sum":"","sum_foreign":""}]},"declaration":{"additional_info_text":"","notfull_lostpages":"","date":"2015-03-30T00:00:00","notfull":"","additional_info":"","url":"http://static.declarations.com.ua/declarations/chosen_ones/mega_batch/khodakivskyi_maksym_petrovych.pdf"},"liabilities":{"54":{"sum_foreign_comment":"","sum":"","sum_comment":"","sum_hidden":false,"sum_comment_hidden":false,"sum_foreign":""},"55":{"sum_foreign_comment":"","sum":"","sum_comment":"","sum_foreign":""},"56":{"sum_foreign_comment":"","sum":"","sum_comment":"","sum_foreign":""},"57":{"sum_foreign_comment":"","sum":"","sum_comment":"","sum_comment_unclear":false,"sum_hidden":false,"sum_comment_hidden":false,"sum_unclear":false,"sum_foreign":""},"58":{"sum_foreign_comment":"","sum":"","sum_comment":"","sum_comment_unclear":false,"sum_hidden":false,"sum_foreign":""},"59":{"sum_foreign_comment":"","sum":"","sum_hidden":false,"sum_comment":"","sum_foreign":""},"60":{"sum_foreign_comment":"","sum":"","sum_comment":"","sum_hidden":false,"sum_comment_hidden":false,"sum_foreign":""},"61":{"sum_foreign_comment":"","sum":"","sum_comment":"","sum_foreign":""},"62":{"sum_foreign_comment":"","sum":"","sum_comment":"","sum_comment_unclear":false,"sum_unclear":false,"sum_foreign":""},"63":{"sum_foreign_comment":"","sum":"","sum_comment":"","sum_comment_unclear":false,"sum_foreign":""},"64":{"sum_foreign_comment":"","sum":"","sum_comment":"","sum_comment_unclear":false,"sum_foreign":""}},"ft_src":"суддя жовтневого районного суду м. дніпропетровська\nДніпропетровська область\nЗагальний місцевий суд\nМаксим\nФрантовська Юлія Олександрівна\nПодружжя\nХодаківський Микола Максимович\nДитина\nПетрович\nХодаківський\nХодаківський Максим Петрович\nХодаківський Максим Петрович\nМаксим Петрович Ходаківський\nМаксим Ходаківський\nХодаківський Максим Петрович\n2362 куб. см., 123 кВт , 480.5 см\nToyota Camry\n2008\n2014\n2362 куб. см., 123 кВт , 480.5 см\nToyota Camry\n2008\n.0779\nКиївська область\n10.25\n1/4 вд 41м2\nЖитомирська область\nм. Новгород-Волинський\n249.2\nКиївська область\nЗагальний місцевий суд\nсуддя жовтневого районного суду м. дніпропетровська\nДніпропетровська область\nПодружжя\nФрантовська Юлія Олександрівна\nДитина\nХодаківський Микола Максимович\nХодаківський Максим Петрович\nМаксим Петрович Ходаківський\nМаксим Ходаківський\nХодаківський Максим Петрович\nМаксим\nХодаківський Максим Петрович\nХодаківський\nПетрович\n165673\n133258\n702\n133258\n178556\n12180\n2014\nКиївська область\n.0779\nКиївська область\n249.2\n1/4 вд 41м2\nм. Новгород-Волинський\n10.25\nЖитомирська область\nПодружжя\nФрантовська Юлія Олександрівна\nХодаківський Микола Максимович\nДитина\nПетрович\nХодаківський\nМаксим\nХодаківський Максим Петрович\nМаксим Петрович Ходаківський\nМаксим Ходаківський\nХодаківський Максим Петрович\nДніпропетровська область\nЗагальний місцевий суд\nсуддя жовтневого районного суду м. дніпропетровська\nХодаківський Максим Петрович\n133258\n165673\n12180\n133258\n178556\n702\n2008\nToyota Camry\n2362 куб. см., 123 кВт , 480.5 см\n12180\n702\n178556\n133258\n165673\n133258\n1/4 вд 41м2\nм. Новгород-Волинський\nЖитомирська область\n10.25\nКиївська область\n.0779\nКиївська область\n249.2\n2014","general":{"inn":"","name":"Максим","patronymic_unclear":false,"last_name_hidden":false,"family":[{"inn":"","inn_hidden":true,"relations_unclear":false,"relations_hidden":false,"relations_other":"","relations":"Подружжя","name_hidden":false,"inn_unclear":false,"family_name":"Франтовська Юлія Олександрівна","name_unclear":false},{"inn":"","relations":"Дитина","inn_unclear":false,"family_name":"Ходаківський Микола Максимович","inn_hidden":true,"relations_other":"","name_hidden":false,"name_unclear":false}],"patronymic":"Петрович","inn_hidden":true,"family_raw":"","inn_unclear":false,"post":{"post_unclear":false,"post":"суддя жовтневого районного суду м. дніпропетровська","candidate":"","office_hidden":false,"region":"Дніпропетровська область","post_hidden":false,"office":"Загальний місцевий суд","office_unclear":false},"last_name_unclear":false,"full_name":"Ходаківський Максим Петрович","addresses":[{"place_district":"","place_city_hidden":true,"place_city":"","place_city_type_hidden":true,"place_district_hidden":true,"place_city_type":"","place_address_hidden":true,"place_address":"","place_hidden":true,"place":""}],"last_name":"Ходаківський","patronymic_hidden":false,"full_name_suggest":{"output":"Ходаківський Максим Петрович","input":["Ходаківський Максим Петрович","Максим Петрович Ходаківський","Максим Ходаківський"]}},"source":"VULYK","estate":{"23":[{"space_unclear":false,"costs":"","costs_comment":"","address_hidden":false,"region_hidden":false,"space_comment":"","space_hidden":false,"space":"","address":"","costs_comment_unclear":false,"region":"","address_unclear":false,"costs_rent_comment":"","space_units":"м²","costs_rent":""},{"space_unclear":false,"costs":"","costs_comment":"","address_hidden":false,"region_hidden":false,"space_comment":"","space":"","address":"","region":"","costs_rent_comment":"","space_units":"","costs_rent":""},{"space_hidden":false,"costs":"","costs_comment":"","address_hidden":false,"region_hidden":false,"space_comment":"","space":"","address":"","region":"","costs_rent_comment":"","space_units":"","costs_rent":""},{"costs_rent":"","region":"","costs":"","costs_rent_comment":"","costs_comment":"","space_comment":"","space_units":"","space":"","address":""}],"25":[{"region_unclear":false,"space_hidden":false,"costs":"","costs_comment":"","costs_hidden":false,"address_hidden":false,"region_hidden":false,"space_comment":"1/4 вд 41м2","space_unclear":false,"space":"10.25","address":"м. Новгород-Волинський","region":"Житомирська область","address_unclear":false,"costs_rent_comment":"","costs_rent_hidden":false,"space_comment_unclear":false,"space_units":"м²","costs_rent":""}],"29":[{"region_unclear":false,"space_unclear":false,"address_hidden":true,"region_hidden":false,"space_comment":"","space":".0779","address":"","region":"Київська область","costs_property":"","costs_rent_comment":"","space_comment_unclear":false,"address_unclear":false,"space_units":"га","costs_property_comment":"","costs_rent":""}],"32":[{"space_unclear":false,"address_hidden":true,"region_hidden":false,"space_comment":"","space":"249.2","address":"","region":"Київська область","costs_property":"","costs_rent_comment":"","space_units":"м²","costs_property_comment":"","costs_rent":""}]},"intro":{"declaration_year":"2014","isnotdeclaration":""}}