{"id":"vulyk_101_141","ft_src":"Ford Kuga\n1997 куб. см.\n2012\nм. Костянтинівка\nДонецька область\n1136\nДонецька область\nЛиманський р-н, с. Рубці\n42.05\nм. Костянтинівка\n160.9\nДонецька область\nДонецька область\nЛиманський р-н, с. Рубці\n30\n2015\n110985\n216433\n117395\n216433\n6410\n1997 куб. см.\n2012\nFord Kuga\n1136\nДонецька область\nм. Костянтинівка\n42.05\nДонецька область\nЛиманський р-н, с. Рубці\n160.9\nДонецька область\nм. Костянтинівка\n30\nДонецька область\nЛиманський р-н, с. Рубці\nЯнюк Юрій Броніславович\nЮрій Броніславович Янюк\nЮрій Янюк\nЯнюк Юрій Броніславович\nЮрій\nЯнюк Юрій Броніславович\nБроніславович\nсуддя костянтинівського міськрайонного суду донецької області\nДонецька область\nЗагальний місцевий суд\nЯнюк\nПодружжя\nЯнюк С. В\nДитина\nЯнюк Я. Ю\n318\n216433\n110985\n6410\n216433\n117395\n2015\n318\nЯнюк С. В\nПодружжя\nЯнюк Я. Ю\nДитина\nЮрій\nБроніславович\nЯнюк\nЯнюк Юрій Броніславович\nЮрій Броніславович Янюк\nЮрій Янюк\nЯнюк Юрій Броніславович\nсуддя костянтинівського міськрайонного суду донецької області\nДонецька область\nЗагальний місцевий суд\nЯнюк Юрій Броніславович","estate":{"23":[{"address":"м. Костянтинівка","space_units":"м²","space_hidden":false,"space_unclear":false,"region_hidden":false,"costs_comment":"","space_comment":"","address_hidden":true,"space_units_unclear":false,"space":"1136","costs_comment_unclear":false,"costs_rent_comment":"","costs":"","region":"Донецька область","costs_rent":""}],"24":[{"address":"м. Костянтинівка","space_units":"м²","costs_comment":"","space_unclear":false,"region_hidden":false,"space_comment":"","address_hidden":true,"costs":"","costs_rent_comment":"","space":"160.9","region":"Донецька область","costs_rent":""}],"29":[{"costs_property_comment":"","address":"Лиманський р-н, с. Рубці","space_units":"м²","costs_rent_comment":"","space":"42.05","region":"Донецька область","region_hidden":false,"costs_property":"","space_comment":"","address_hidden":true,"costs_rent":""}],"32":[{"costs_property_comment":"","address":"Лиманський р-н, с. Рубці","space_units":"м²","costs_rent_comment":"","space":"30","region":"Донецька область","region_hidden":false,"costs_property":"","space_comment":"","address_hidden":true,"costs_rent":""}]},"vehicle":{"35":[{"sum_comment":"","brand_info_hidden":false,"sum_rent":"","sum":"","brand_unclear":false,"year":"2012","brand":"Ford Kuga","brand_info":"1997 куб. см.","sum_rent_comment":"","brand_info_unclear":false,"sum_rent_unclear":false}]},"source":"VULYK","income":{"5":{"family_comment":"","value":"216433","family":"117395","comment":"","value_unclear":false},"6":{"family_comment":"","family":"110985","comment":"","value_unclear":false,"family_hidden":false,"value":"216433"},"7":{"family_comment":"","comment":"","family":"","source_name_unclear":false,"value":"","source_name":""},"8":{"family_comment":"","value":"","family":"","comment":""},"9":{"family_comment":"","value":"","family":"","comment":""},"10":{"family_comment":"","value":"","family":"","comment":""},"11":{"family_comment":"","comment_unclear":false,"value":"","family":"","comment":""},"12":{"family_comment":"","value":"","family":"","comment":""},"13":{"family_comment":"","value":"","family":"","comment":""},"14":{"family_comment":"","value":"","family":"","comment":""},"15":{"family_comment":"","value":"","family":"","comment":""},"16":{"family_comment":"","value":"","family":"","comment":""},"17":{"family_comment":"","value":"","family":"","comment":""},"18":{"family_comment":"","value":"","family":"","comment":""},"19":{"family_comment":"","value":"","family":"","comment":""},"20":{"family_comment":"","comment":"","family":"6410","value_unclear":false,"family_unclear":false,"comment_unclear":false,"value":""}},"general":{"family":[{"inn":"","family_name":"Янюк С. В","relations_other":"","name_unclear":false,"inn_hidden":true,"name_hidden":true,"relations":"Подружжя"},{"inn":"","family_name":"Янюк Я. Ю","relations_other":"","relations_unclear":false,"name_unclear":false,"inn_hidden":true,"name_hidden":false,"relations":"Дитина"}],"family_raw":"","name":"Юрій","full_name_suggest":{"input":["Янюк Юрій Броніславович","Юрій Броніславович Янюк","Юрій Янюк"],"output":"Янюк Юрій Броніславович"},"patronymic":"Броніславович","inn_hidden":true,"addresses":[{"place_city_type_hidden":false,"place_city_type":"","place_city_hidden":true,"place_hidden":true,"place_district":"","place_district_hidden":false,"place":"","place_city":"","place_address_hidden":true,"place_address":""}],"patronymic_hidden":false,"inn":"","inn_unclear":false,"last_name":"Янюк","full_name":"Янюк Юрій Броніславович","post":{"office_unclear":false,"region_unclear":false,"post":"суддя костянтинівського міськрайонного суду донецької області","region":"Донецька область","office":"Загальний місцевий суд"}},"liabilities":{"54":{"sum_comment_unclear":false,"sum_comment":"","sum_hidden":false,"sum":"318","sum_foreign_comment":"","sum_foreign":"","sum_unclear":false,"sum_comment_hidden":false},"55":{"sum_comment":"","sum_foreign_comment":"","sum_foreign":"","sum":""},"56":{"sum_comment":"","sum":"","sum_foreign_comment":"","sum_foreign":"","sum_unclear":false,"sum_comment_hidden":false},"57":{"sum_comment":"","sum_hidden":false,"sum":"","sum_foreign_comment":"","sum_foreign":"","sum_unclear":false,"sum_comment_hidden":false},"58":{"sum_comment_unclear":false,"sum_comment":"","sum_hidden":false,"sum":"","sum_foreign_comment":"","sum_foreign":"","sum_unclear":false,"sum_comment_hidden":false},"59":{"sum_comment":"","sum_foreign_comment":"","sum_foreign":"","sum":""},"60":{"sum_comment":"","sum_hidden":false,"sum":"","sum_foreign_comment":"","sum_foreign":"","sum_unclear":false,"sum_comment_hidden":false},"61":{"sum_comment":"","sum_foreign_comment":"","sum_foreign":"","sum":""},"62":{"sum_comment":"","sum_comment_unclear":false,"sum_foreign_comment":"","sum":"","sum_foreign":""},"63":{"sum_comment":"","sum_foreign_comment":"","sum_foreign":"","sum":"","sum_comment_hidden":false},"64":{"sum_comment":"","sum_foreign_comment":"","sum_foreign":"","sum":"","sum_comment_hidden":false}},"declaration":{"notfull_lostpages":"","additional_info_text":"","additional_info":"","date":"2016-03-15T00:00:00","notfull":"","url":"http://static.declarations.com.ua/declarations/chosen_ones/judges_batch/856_ianiuk_iurii_bronislavovych_2015.pdf"},"intro":{"declaration_year":"2015"}}