{"income":{"5":{"value":"329405","family_comment":"","family_hidden":false,"family_unclear":false,"family":"28694","comment":""},"6":{"value":"263222","family_comment":"","value_unclear":false,"family_hidden":false,"family_unclear":false,"family":"","comment":""},"7":{"value":"","family_hidden":false,"value_hidden":false,"family_comment":"","source_name":"","family":"","comment":"","source_name_hidden":false},"8":{"family_comment":"","value":"","family":"","comment":""},"9":{"family_comment":"","value":"","family":"15702","comment":""},"10":{"family_comment":"","value":"","value_unclear":false,"family":"","comment":""},"11":{"family_comment":"","value":"","family":"","comment":""},"12":{"family_comment":"","value":"","family":"","comment":""},"13":{"family_comment":"","value":"","family":"","comment":""},"14":{"family_comment":"","value":"","family":"","comment":""},"15":{"family_comment":"","value":"","family":"","comment":""},"16":{"family_comment":"","value":"","family":"","comment":""},"17":{"family_comment":"","value":"","family":"","comment":""},"18":{"family_comment":"","value":"","family":"","comment":""},"19":{"family_comment":"","value":"","family":"","comment":""},"20":{"value":"66183","family_comment":"","value_unclear":false,"family_unclear":false,"comment_unclear":false,"comment":"","family":"12992"}},"vehicle":{"35":[{"brand_info":"1600 куб. см.","sum_rent_comment":"","year":"2007","brand_info_hidden":false,"brand_info_unclear":false,"year_unclear":false,"sum_rent":"","sum":"","brand":"Volkswagen Jetta","sum_comment":"","brand_unclear":false,"brand_hidden":false}],"40":[{"brand_info":"1100 куб. см.","sum_rent_comment":"","brand":"ВАЗ 21011","sum_comment":"","brand_unclear":false,"year":"1997","brand_info_unclear":false,"year_unclear":false,"sum":"","sum_rent":""}]},"id":"vulyk_74_196","banks":{"51":[{"sum_foreign_comment":"","sum_unclear":false,"sum_units":"UAH","sum_comment":"","sum_comment_unclear":false,"sum_hidden":false,"sum_foreign_units":"UAH","sum_comment_hidden":false,"sum_foreign_hidden":false,"sum":"97391","sum_foreign":""}]},"declaration":{"additional_info_text":"","notfull_lostpages":"","date":"2014-03-28T00:00:00","notfull":"","additional_info":"","url":"http://static.declarations.com.ua/declarations/chosen_ones/judges_batch/1497_zubkov_leonid_iakovych.pdf"},"liabilities":{"54":{"sum_foreign_comment":"","sum":"","sum_comment":"","sum_comment_unclear":false,"sum_comment_hidden":false,"sum_foreign":""},"55":{"sum_foreign_comment":"","sum":"","sum_comment":"","sum_hidden":false,"sum_unclear":false,"sum_foreign":""},"56":{"sum_foreign_comment":"","sum":"","sum_comment":"","sum_hidden":false,"sum_unclear":false,"sum_foreign":""},"57":{"sum_foreign_comment":"","sum":"","sum_comment":"","sum_comment_unclear":false,"sum_comment_hidden":false,"sum_foreign":""},"58":{"sum_foreign_comment":"","sum_comment":"","sum":"","sum_comment_hidden":false,"sum_foreign":""},"59":{"sum_foreign_comment":"","sum":"","sum_comment":"","sum_foreign":""},"60":{"sum_foreign_comment":"","sum":"","sum_foreign":"","sum_comment":"","sum_hidden":false},"61":{"sum_foreign_comment":"","sum":"","sum_comment":"","sum_foreign":""},"62":{"sum_foreign_comment":"","sum":"","sum_comment":"","sum_foreign":""},"63":{"sum_foreign_comment":"","sum":"","sum_comment":"","sum_comment_unclear":false,"sum_unclear":false,"sum_foreign":""},"64":{"sum_foreign_comment":"","sum":"","sum_comment":"","sum_comment_unclear":false,"sum_unclear":false,"sum_foreign":""}},"ft_src":"1600 куб. см.\nVolkswagen Jetta\n2007\nВАЗ 21011\n1100 куб. см.\n1997\nм. Харків\n24.8\nХарківська область\nХарківська область\nм. Харків\n28.3\nХарківська область\nм. Харків\n924\nХарківська область\nм. Харків\n97.5\nХарківська область\nм. Харків\n30.9\nм. Харків\nХарківська область\n62.9\n97391\n2013\n1600 куб. см.\nVolkswagen Jetta\n2007\n1100 куб. см.\nВАЗ 21011\n1997\n2013\nЗагальний апеляційний суд\nХарківська область\nсуддя апеляційного суду харківської області\nЯкович\nЗубков Леонід Якович\nЛеонід Якович Зубков\nЛеонід Зубков\nЗубков Леонід Якович\nЛеонід\nЗубков Леонід Якович\nЗубков\nПодружжя\nЗубкова С. О., 23. 02. 1953\n263222\n66183\n12992\n329405\n28694\n15702\n24.8\nХарківська область\nм. Харків\nХарківська область\nм. Харків\n97.5\n62.9\nм. Харків\nХарківська область\n924\nм. Харків\nХарківська область\n28.3\nХарківська область\nм. Харків\n30.9\nм. Харків\nХарківська область\n97391\n263222\n15702\n28694\n329405\n12992\n66183\nПодружжя\nЗубкова С. О., 23. 02. 1953\nЯкович\nЗубков\nХарківська область\nЗагальний апеляційний суд\nсуддя апеляційного суду харківської області\nЗубков Леонід Якович\nЗубков Леонід Якович\nЛеонід Якович Зубков\nЛеонід Зубков\nЗубков Леонід Якович\nЛеонід","general":{"inn":"","inn_hidden":true,"last_name":"Зубков","post":{"region_unclear":false,"post":"суддя апеляційного суду харківської області","post_hidden":false,"region":"Харківська область","office":"Загальний апеляційний суд","office_unclear":false},"name":"Леонід","full_name":"Зубков Леонід Якович","family_raw":"","addresses":[{"place_district":"","place_address_hidden":true,"place_city":"","place_address":"","place_district_hidden":true,"place_city_type":"","place_city_hidden":true,"place_city_type_hidden":true,"place_hidden":true,"place":""}],"family":[{"inn":"","relations":"Подружжя","relations_other":"","inn_hidden":true,"family_name":"Зубкова С. О., 23. 02. 1953","name_hidden":false,"name_unclear":false}],"full_name_suggest":{"output":"Зубков Леонід Якович","input":["Зубков Леонід Якович","Леонід Якович Зубков","Леонід Зубков"]},"patronymic":"Якович"},"source":"VULYK","estate":{"25":[{"space_unclear":false,"costs":"","costs_comment":"","address_hidden":true,"region_hidden":false,"space_comment":"","space_hidden":false,"space":"62.9","address":"м. Харків","region":"Харківська область","costs_rent_comment":"","space_units":"м²","costs_rent":""}],"27":[{"costs":"","costs_comment":"","address_hidden":true,"region_hidden":false,"space_comment":"","space":"24.8","address":"м. Харків","region":"Харківська область","address_unclear":false,"costs_rent_comment":"","space_units":"м²","costs_rent":""}],"29":[{"costs_rent":"","region":"Харківська область","costs_property":"","costs_rent_comment":"","address_hidden":true,"region_hidden":false,"space_comment":"","costs_property_comment":"","space_units":"м²","space":"924","address":"м. Харків"}],"30":[{"space_unclear":false,"address_hidden":true,"region_hidden":false,"space_comment":"","space":"97.5","address":"м. Харків","region":"Харківська область","costs_property":"","costs_rent_comment":"","space_comment_unclear":false,"address_unclear":false,"space_units":"м²","costs_property_comment":"","costs_rent":""}],"33":[{"costs_rent":"","region":"Харківська область","costs_property":"","costs_rent_comment":"","address_hidden":true,"region_hidden":false,"space_comment":"","costs_property_comment":"","space_units":"м²","space":"28.3","address":"м. Харків"}],"34":[{"costs_rent":"","region":"Харківська область","costs_property":"","costs_rent_comment":"","address_hidden":true,"region_hidden":false,"space_comment":"","costs_property_comment":"","space_units":"м²","space":"30.9","address":"м. Харків"}]},"intro":{"declaration_year":"2013","isnotdeclaration":"","declaration_year_unclear":false}}