{"income":{"5":{"value":"198876","family_comment":"","value_unclear":false,"family_unclear":false,"family":"51794","comment":""},"6":{"family_comment":"","value":"186696","value_unclear":false,"family":"51794","comment":""},"7":{"value":"","value_unclear":false,"family_comment":"","source_name":"","family":"","comment":""},"8":{"family_comment":"","value":"","family":"","comment":""},"9":{"value":"","family_comment":"","value_unclear":false,"family_unclear":false,"family":"","comment":""},"10":{"family_comment":"","value":"12180","comment_unclear":false,"family":"","comment":""},"11":{"family_comment":"","value":"","family":"","comment":""},"12":{"family_comment":"","value":"","family":"","comment":""},"13":{"family_comment":"","value":"","value_unclear":false,"family":"","comment":""},"14":{"family_comment":"","value":"","family":"","comment":""},"15":{"family_comment":"","value":"","family":"","comment":""},"16":{"family_comment":"","family_unclear":false,"value":"","family":"","comment":""},"17":{"family_comment":"","family_unclear":false,"value":"","family":"","comment":""},"18":{"family_comment":"","value":"","family":"","comment":""},"19":{"family_comment":"","value":"","family":"","comment":""},"20":{"value":"","family_comment":"","value_unclear":false,"family_hidden":false,"value_hidden":false,"family_unclear":false,"comment_unclear":false,"comment":"","family":""}},"vehicle":{"35":[{"brand_info":"об'єм двиг. 1.6","sum_rent_comment":"","brand_info_unclear":false,"year":"2006","brand_info_hidden":false,"sum_rent_comment_unclear":false,"sum_rent":"","sum":"","brand":"ВАЗ 21124","sum_comment":"","brand_unclear":false,"brand_hidden":false}],"39":[{"brand_info":"причіп до легкового автомобіля","sum":"","brand":"","sum_comment":"","brand_unclear":false,"year":"1998","brand_hidden":true,"sum_rent_comment":"","sum_rent":""}],"44":[{"brand_info":"мопед, 49 м. к","sum_rent_comment":"","brand":"Viper","sum_comment":"","year":"","brand_info_unclear":true,"sum":"","sum_rent":""}]},"id":"vulyk_100_72","declaration":{"additional_info_text":"","notfull_lostpages":"","date":"2015-02-23T00:00:00","notfull":"","additional_info":"","url":"http://static.declarations.com.ua/declarations/chosen_ones/judges_batch/4271_ieremenko_volodymyr_maksymovych.pdf"},"liabilities":{"54":{"sum_foreign_comment":"","sum":"","sum_comment":"","sum_comment_hidden":false,"sum_unclear":false,"sum_foreign":""},"55":{"sum_foreign_comment":"","sum":"","sum_comment":"","sum_foreign":""},"56":{"sum_foreign_comment":"","sum":"","sum_comment":"","sum_unclear":false,"sum_foreign":""},"57":{"sum_foreign_comment":"","sum":"","sum_comment":"","sum_comment_unclear":false,"sum_comment_hidden":false,"sum_unclear":false,"sum_foreign":""},"58":{"sum_foreign_comment":"","sum":"","sum_comment":"","sum_comment_hidden":false,"sum_unclear":false,"sum_foreign":""},"59":{"sum_foreign_comment":"","sum":"","sum_comment":"","sum_foreign":""},"60":{"sum_foreign_comment":"","sum_comment_hidden":false,"sum":"","sum_comment":"","sum_foreign":""},"61":{"sum_foreign_comment":"","sum":"","sum_comment":"","sum_foreign":""},"62":{"sum_foreign_comment":"","sum":"","sum_comment":"","sum_unclear":false,"sum_foreign":""},"63":{"sum_foreign_comment":"","sum_comment_hidden":false,"sum":"","sum_comment":"","sum_foreign":""},"64":{"sum_foreign_comment":"","sum_comment_hidden":false,"sum":"","sum_comment":"","sum_foreign":""}},"ft_src":"Єременко Володимир Максимович\nсуддя баришівського районного суду київської області\nКиївська область\nЗагальний місцевий суд\nВолодимир\nЄременко С. А. 11. 01. 1964\nПодружжя\nЄременко Володимир Максимович\nВолодимир Максимович Єременко\nВолодимир Єременко\nЄременко Володимир Максимович\nЄременко\nМаксимович\nпричіп до легкового автомобіля\n1998\nоб'єм двиг. 1.6\nВАЗ 21124\n2006\nмопед, 49 м. к\nViper\nспадщина\nспадщина\n.15\nпередано у власність безкоштовно\n.1613\nгараж металевий, спадщина\n24\nпо договору купівлі-продажу від 07. 11. 2001\n1/2 частина однокімнатної квартири\n28.9\nспадщина\nспадщина\n89.1\n2014\n51794\n186696\n12180\n51794\n198876\nоб'єм двиг. 1.6\nВАЗ 21124\n2006\nпричіп до легкового автомобіля\n1998\nмопед, 49 м. к\nViper\n.15\nспадщина\nспадщина\n.1613\nпередано у власність безкоштовно\n89.1\nспадщина\nспадщина\n24\nгараж металевий, спадщина\n28.9\n1/2 частина однокімнатної квартири\nпо договору купівлі-продажу від 07. 11. 2001\nПодружжя\nЄременко С. А. 11. 01. 1964\nМаксимович\nЄременко\nЄременко Володимир Максимович\nВолодимир Максимович Єременко\nВолодимир Єременко\nЄременко Володимир Максимович\nЄременко Володимир Максимович\nВолодимир\nЗагальний місцевий суд\nКиївська область\nсуддя баришівського районного суду київської області\n186696\n51794\n198876\n51794\n12180\n2014\nЄременко С. А. 11. 01. 1964\nПодружжя\nМаксимович\nЄременко\nКиївська область\nЗагальний місцевий суд\nсуддя баришівського районного суду київської області\nЄременко Володимир Максимович\nЄременко Володимир Максимович\nВолодимир Максимович Єременко\nВолодимир Єременко\nЄременко Володимир Максимович\nВолодимир\nпричіп до легкового автомобіля\n1998\nмопед, 49 м. к\nViper\n2006\nВАЗ 21124\nоб'єм двиг. 1.6\n12180\n198876\n51794\n51794\n186696\n1/2 частина однокімнатної квартири\n28.9\nпо договору купівлі-продажу від 07. 11. 2001\nспадщина\n.15\nспадщина\nпередано у власність безкоштовно\n.1613\nспадщина\n89.1\nспадщина\nгараж металевий, спадщина\n24\n2014","general":{"inn":"","inn_hidden":true,"last_name":"Єременко","post":{"post_unclear":false,"region_unclear":false,"post":"суддя баришівського районного суду київської області","office":"Загальний місцевий суд","region":"Київська область","post_hidden":false,"office_unclear":false},"name":"Володимир","full_name":"Єременко Володимир Максимович","family_raw":"","addresses":[{"place_district":"","place_city_hidden":true,"place_city":"","place_city_unclear":false,"place_district_hidden":false,"place_city_type":"","place_address_hidden":true,"place_city_type_hidden":false,"place_address":"","place_hidden":true,"place":""}],"family":[{"inn_hidden":true,"inn":"","name_hidden":false,"family_name":"Єременко С. А. 11. 01. 1964","relations":"Подружжя","name_unclear":false}],"full_name_suggest":{"output":"Єременко Володимир Максимович","input":["Єременко Володимир Максимович","Володимир Максимович Єременко","Володимир Єременко"]},"patronymic":"Максимович"},"source":"VULYK","estate":{"23":[{"space_unclear":false,"costs":"","costs_comment":"спадщина","address_hidden":false,"region_hidden":true,"space_comment":"спадщина","space":".15","address":"","costs_comment_unclear":false,"region":"","address_unclear":false,"costs_rent_comment":"","space_comment_unclear":false,"space_units":"га","costs_rent":""},{"costs_rent":"","space_unclear":false,"region":"","costs":"","costs_rent_comment":"","costs_comment":"","space_comment":"передано у власність безкоштовно","space_units":"га","space":".1613","address":""}],"24":[{"space_unclear":false,"costs":"","costs_comment":"спадщина","address_hidden":false,"region_hidden":true,"space_comment":"спадщина","space":"89.1","address":"","region":"","costs_rent_comment":"","space_comment_unclear":false,"space_units":"м²","costs_rent":""}],"25":[{"space_unclear":false,"costs":"","costs_comment":"по договору купівлі-продажу від 07. 11. 2001","address_hidden":false,"region_hidden":true,"space_comment":"1/2 частина однокімнатної квартири","space":"28.9","address":"","costs_comment_unclear":false,"region":"","address_unclear":false,"costs_rent_comment":"","space_comment_unclear":false,"space_units":"м²","costs_rent":""}],"27":[{"space_unclear":false,"costs":"","costs_comment":"","address_hidden":false,"region_hidden":true,"space_comment":"гараж металевий, спадщина","space":"24","address":"","region":"","address_unclear":false,"costs_rent_comment":"","space_units":"м²","costs_rent":""}],"28":[{"costs_rent":"","region":"","costs":"","costs_rent_comment":"","costs_comment":"","address_hidden":false,"region_hidden":true,"space_comment":"","space_units":"м²","space":"","address":""}]},"intro":{"declaration_year":"2014"}}