{"income":{"5":{"value":"267481.25","comment_hidden":false,"family_comment":"","family":"","comment":"","family_comment_hidden":false},"6":{"value":"239775.25","family_comment":"","comment_hidden":false,"family_hidden":false,"family_unclear":false,"family_comment_hidden":false,"comment":"","family":""},"7":{"value":"","comment_hidden":false,"family_comment_hidden":false,"family_comment":"","source_name":"","family":"","comment":"","source_name_hidden":false},"8":{"family_comment":"","value":"","family":"","comment":""},"9":{"value":"27706","family_comment":"","value_unclear":false,"family_unclear":false,"comment_unclear":false,"comment":"","family":""},"10":{"family_comment":"","family_unclear":false,"value":"","family":"","comment":""},"11":{"family_comment":"","value":"","family":"","comment":""},"12":{"family_comment":"","value":"","family":"","comment":""},"13":{"family_comment":"","value":"","family":"","comment":""},"14":{"family_comment":"","value":"","family":"","comment":""},"15":{"family_comment":"","value":"","comment_unclear":false,"family":"","comment":""},"16":{"family_comment":"","value":"","comment_unclear":false,"family":"","comment":""},"17":{"family_comment":"","value":"","family":"","comment":""},"18":{"family_comment":"","value":"","family":"","comment":""},"19":{"family_comment":"","value":"","family":"","comment":""},"20":{"value":"","family_comment":"","value_unclear":false,"family_unclear":false,"family_comment_unclear":false,"family_comment_hidden":false,"comment":"","family":""}},"id":"vulyk_73_169","banks":{"45":[{"sum_foreign_comment":"","sum_units":"UAH","sum_comment":"","sum_comment_unclear":false,"sum_hidden":false,"sum_foreign_units":"UAH","sum_comment_hidden":false,"sum_unclear":false,"sum":"279682","sum_foreign":""}],"46":[{"sum_foreign_comment":"","sum_units":"UAH","sum_comment":"","sum_foreign_units":"UAH","sum":"278164","sum_foreign":""}],"47":[{"sum_foreign_comment":"","sum_units":"UAH","sum_comment":"","sum_foreign_units":"UAH","sum":"402","sum_foreign":""}]},"declaration":{"additional_info_text":"","notfull_lostpages":"","date":"2014-03-28T00:00:00","notfull":"","additional_info":"","url":"http://static.declarations.com.ua/declarations/chosen_ones/judges_batch/859_melinyshyn_halyna_petrivna.pdf"},"liabilities":{"54":{"sum_foreign_comment":"","sum_foreign_hidden":false,"sum_comment":"","sum_comment_unclear":false,"sum_hidden":false,"sum_comment_hidden":false,"sum_unclear":false,"sum":"180","sum_foreign":""},"55":{"sum_foreign_comment":"","sum_comment_hidden":false,"sum":"","sum_comment":"","sum_foreign":""},"56":{"sum_foreign_comment":"","sum":"","sum_comment":"","sum_comment_unclear":false,"sum_foreign":""},"57":{"sum_foreign_comment":"","sum":"5768","sum_comment":"","sum_hidden":false,"sum_comment_hidden":false,"sum_unclear":false,"sum_foreign":""},"58":{"sum_foreign_comment":"","sum":"3231","sum_comment":"","sum_hidden":false,"sum_comment_hidden":false,"sum_foreign":""},"59":{"sum_foreign_comment":"","sum":"","sum_comment":"","sum_comment_unclear":false,"sum_unclear":false,"sum_foreign":""},"60":{"sum_foreign_comment":"","sum":"","sum_comment":"","sum_hidden":false,"sum_comment_hidden":false,"sum_unclear":false,"sum_foreign":""},"61":{"sum_foreign_comment":"","sum":"","sum_comment":"","sum_foreign":""},"62":{"sum_foreign_comment":"","sum":"","sum_comment":"","sum_foreign":""},"63":{"sum_foreign_comment":"","sum":"","sum_comment":"","sum_hidden":false,"sum_comment_hidden":false,"sum_foreign":""},"64":{"sum_foreign_comment":"","sum":"","sum_comment":"","sum_foreign":""}},"ft_src":"5768\n180\n3231\nсуддя апеляційного суду івано-франківської області\nІвано-Франківська область\nЗагальний апеляційний суд\nМелінишин Галина Петрівна\nГалина\nМелінишин Галина Петрівна\nГалина Петрівна Мелінишин\nГалина Мелінишин\nМелінишин Галина Петрівна\nМелінишин\nПетрівна\nспадщина\n1900\n68.8\n278164\n402\n279682\n2013\n2013\nЗагальний апеляційний суд\nІвано-Франківська область\nсуддя апеляційного суду івано-франківської області\nПетрівна\nМелінишин Галина Петрівна\nГалина Петрівна Мелінишин\nГалина Мелінишин\nМелінишин Галина Петрівна\nМелінишин Галина Петрівна\nГалина\nМелінишин\n3231\n180\n5768\n239775.25\n267481.25\n27706\n1900\nспадщина\n68.8\n279682\n278164\n402\n3231\n5768\n180\n239775.25\n27706\n267481.25\nМелінишин\nПетрівна\nІвано-Франківська область\nЗагальний апеляційний суд\nсуддя апеляційного суду івано-франківської області\nМелінишин Галина Петрівна\nМелінишин Галина Петрівна\nГалина Петрівна Мелінишин\nГалина Мелінишин\nМелінишин Галина Петрівна\nГалина\n27706\n267481.25\n239775.25\n68.8\nспадщина\n1900\n402\n279682\n278164\n2013","general":{"inn":"","family_raw":"","last_name":"Мелінишин","post":{"post_unclear":false,"region_unclear":false,"post":"суддя апеляційного суду івано-франківської області","office":"Загальний апеляційний суд","region":"Івано-Франківська область","post_hidden":false,"office_hidden":false,"office_unclear":false,"region_hidden":false},"name":"Галина","full_name":"Мелінишин Галина Петрівна","inn_hidden":false,"name_unclear":false,"last_name_unclear":false,"full_name_suggest":{"output":"Мелінишин Галина Петрівна","input":["Мелінишин Галина Петрівна","Галина Петрівна Мелінишин","Галина Мелінишин"]},"patronymic":"Петрівна"},"source":"VULYK","estate":{"23":[{"space_hidden":false,"costs":"","costs_comment":"","costs_hidden":false,"address_hidden":false,"region_hidden":false,"space_comment":"спадщина","space_unclear":false,"space":"1900","address":"","region":"","space_units_unclear":false,"costs_unclear":false,"space_units":"м²","costs_rent":"","costs_rent_comment":""}],"25":[{"space_unclear":false,"costs":"","costs_comment":"","costs_hidden":false,"address_hidden":false,"region_hidden":false,"space_comment":"","space_hidden":false,"space":"68.8","address":"","region":"","costs_rent_comment":"","space_comment_hidden":false,"space_units":"м²","costs_rent":""}]},"intro":{"declaration_year":"2013"}}