{"id":"vulyk_75_116","ft_src":"1995 куб. см.\n2006\nSuzuki Grand Vitara\n1992\n1480 куб. см.\nИЖ 27186\n.0577\n137\n59\n2014\n209687\n13237\n241324\n13237\n31637\n1995 куб. см.\n2006\nSuzuki Grand Vitara\n1480 куб. см.\nИЖ 27186\n1992\n2014\nОстра\nСтепанівна\nПодружжя\nОстрий Степан Васильович\nОстра Наталія Степанівна\nНаталія Степанівна Остра\nНаталія Остра\nОстра Наталія Степанівна\nНаталія\nОстра Наталія Степанівна\nЗагальний місцевий суд\nсуддя білгород-дністровського міськрайонного суду одеської області\nОдеська область\n209687\n31637\n13237\n241324\n13237\n.0577\n59\n137\nОстрий Степан Васильович\nПодружжя\nОстра\nСтепанівна\nсуддя білгород-дністровського міськрайонного суду одеської області\nОдеська область\nЗагальний місцевий суд\nОстра Наталія Степанівна\nОстра Наталія Степанівна\nНаталія Степанівна Остра\nНаталія Остра\nОстра Наталія Степанівна\nНаталія","estate":{"23":[{"address":"","space_units":"га","costs_comment":"","region_hidden":true,"space_comment":"","address_hidden":false,"costs":"","costs_rent_comment":"","space":".0577","region":"","space_units_hidden":true,"costs_rent":""}],"27":[{"address":"","space_units":"м²","space_hidden":false,"space_unclear":false,"region_hidden":true,"costs_comment":"","space_comment":"","space":"137","costs_rent_comment":"","costs":"","region":"","costs_rent":""}],"33":[{"costs_property_comment":"","address":"","space_units":"м²","costs_rent_comment":"","space":"59","region":"","region_hidden":true,"costs_property":"","space_comment":"","costs_rent":""}]},"vehicle":{"40":[{"sum_comment":"","brand_info":"1995 куб. см.","sum":"","sum_rent_comment":"","year":"2006","brand":"Suzuki Grand Vitara","sum_rent":"","brand_info_unclear":false},{"sum_comment":"","brand_info":"1480 куб. см.","sum":"","brand_unclear":true,"year":"1992","brand":"ИЖ 27186","sum_rent":"","sum_rent_comment":""}]},"source":"VULYK","income":{"5":{"family_comment":"","value":"241324","family":"13237","comment":""},"6":{"family_comment":"","family_hidden":false,"value":"209687","family":"","comment":""},"7":{"family":"","family_comment":"","value":"","comment":"","source_name":""},"8":{"family_comment":"","value":"","family":"","comment":""},"9":{"family_comment":"","family":"","comment":"","value_unclear":false,"family_hidden":false,"value":""},"10":{"family":"","family_comment":"","comment":"","value_hidden":false,"value":"","family_hidden":false,"family_unclear":false},"11":{"family_comment":"","value":"","family":"","comment":""},"12":{"family_comment":"","value":"","family":"","comment":""},"13":{"family_comment":"","value":"","family":"","comment":""},"14":{"family_comment":"","value":"","family":"","comment":""},"15":{"family_comment":"","value":"","family":"","comment":""},"16":{"family_comment":"","value":"","family":"","comment":""},"17":{"family_comment":"","value":"","family":"","comment":""},"18":{"family_comment":"","value":"","family":"","comment":""},"19":{"family_comment":"","value":"","family":"","comment":""},"20":{"family_comment":"","comment":"","family":"13237","comment_unclear":false,"value":"31637","family_comment_unclear":false}},"general":{"inn":"","addresses":[{"place_city_type_hidden":true,"place_city_type":"","place_city_hidden":true,"place_hidden":true,"place_district":"","place_district_hidden":true,"place":"","place_city":"","place_address_hidden":true,"place_address":""}],"last_name":"Остра","full_name":"Остра Наталія Степанівна","family":[{"inn":"","family_name":"Острий Степан Васильович","relations_other":"","relations_hidden":false,"name_unclear":false,"inn_hidden":true,"name_hidden":true,"relations":"Подружжя"}],"patronymic":"Степанівна","inn_hidden":true,"name":"Наталія","post":{"office":"Загальний місцевий суд","region":"Одеська область","post":"суддя білгород-дністровського міськрайонного суду одеської області"},"family_raw":"","full_name_suggest":{"input":["Остра Наталія Степанівна","Наталія Степанівна Остра","Наталія Остра"],"output":"Остра Наталія Степанівна"}},"liabilities":{"54":{"sum_comment":"","sum_foreign_comment":"","sum_foreign":"","sum":""},"55":{"sum_comment":"","sum_foreign_comment":"","sum_foreign":"","sum":""},"56":{"sum_comment":"","sum_foreign_comment":"","sum_foreign":"","sum":""},"57":{"sum_comment":"","sum_foreign_comment":"","sum_foreign":"","sum":""},"58":{"sum_comment":"","sum_foreign_comment":"","sum_foreign":"","sum":""},"59":{"sum_comment_unclear":false,"sum_comment":"","sum":"","sum_foreign_comment":"","sum_foreign":"","sum_unclear":false},"60":{"sum_comment":"","sum_foreign_comment":"","sum_foreign":"","sum":""},"61":{"sum_comment":"","sum_foreign_comment":"","sum_foreign":"","sum":""},"62":{"sum_comment":"","sum_foreign_comment":"","sum_foreign":"","sum_unclear":false,"sum":""},"63":{"sum_comment":"","sum_foreign_comment":"","sum_foreign":"","sum":""},"64":{"sum_comment":"","sum_foreign_comment":"","sum_foreign":"","sum":""}},"declaration":{"notfull_lostpages":"","additional_info_text":"","additional_info":"","date":"2015-03-25T00:00:00","notfull":"","url":"http://static.declarations.com.ua/declarations/chosen_ones/judges_batch/1819_ostra_nataliia_stepanivna.pdf"},"intro":{"isnotdeclaration":"","declaration_year":"2014"}}