{"income":{"5":{"family_comment":"","family_unclear":false,"value":"210328","family":"134682","comment":""},"6":{"family_comment":"","family_unclear":false,"value":"207715","family":"120767","comment":""},"7":{"value":"","comment_hidden":false,"family_comment":"","source_name":"","family":"","comment":""},"8":{"family_comment":"","value":"","family":"","comment":""},"9":{"family_comment":"","value":"1000","family":"","comment":""},"10":{"family_comment":"","value":"","family":"13915","comment":""},"11":{"family_comment":"","value":"","value_unclear":false,"family":"","comment":""},"12":{"family_comment":"","value":"","family":"","comment":""},"13":{"family_comment":"","value":"","family":"","comment":""},"14":{"family_comment":"","value":"","family":"","comment":""},"15":{"family_comment":"","value":"","value_unclear":false,"family":"","comment":""},"16":{"family_comment":"","family_unclear":false,"value":"","family":"","comment":""},"17":{"family_comment":"","value":"","family":"","comment":""},"18":{"family_comment":"","value":"","family_hidden":false,"comment":"","family":""},"19":{"family_comment":"","value":"1613","family":"","comment":"пай"},"20":{"value":"","comment_unclear":false,"comment_hidden":false,"family_comment":"","family":"","comment":"","family_comment_hidden":false}},"vehicle":{"35":[{"brand_info":"1968 куб.см, 2.0 TDI, у користуванні","sum_rent_comment":"","year":"2013","brand_info_hidden":false,"brand_info_unclear":false,"year_unclear":false,"sum_rent":"","sum":"","brand":"Volkswagen Tiguan","sum_comment":"","brand_unclear":false,"brand_hidden":false}],"40":[{"brand_info":"3311 куб. см. у користуванні","sum_rent_comment":"","brand":"Lexus RX 400 H","sum_comment":"","year":"2008","brand_hidden":false,"brand_info_hidden":false,"brand_info_unclear":false,"year_unclear":false,"sum":"","sum_rent":""}]},"id":"vulyk_68_134","banks":{"45":[{"sum_foreign_comment":"","sum_units":"UAH","sum_units_hidden":false,"sum_comment":"","sum_comment_unclear":false,"sum_hidden":false,"sum_foreign_units":"UAH","sum_comment_hidden":false,"sum_unclear":false,"sum":"9605","sum_foreign":""}],"46":[{"sum_foreign_comment":"","sum_units":"UAH","sum_comment":"","sum_foreign_units":"UAH","sum":"8605","sum_foreign":""}]},"declaration":{"additional_info_text":"","notfull_lostpages":"","date":"2015-03-30T00:00:00","notfull":"","additional_info":"","url":"http://static.declarations.com.ua/declarations/chosen_ones/mega_batch/feloniuk_diana_leonidivna.pdf"},"liabilities":{"54":{"sum_foreign_comment":"","sum":"","sum_comment":"","sum_comment_unclear":false,"sum_hidden":false,"sum_comment_hidden":false,"sum_unclear":false,"sum_foreign":""},"55":{"sum_foreign_comment":"","sum":"","sum_hidden":false,"sum_comment":"","sum_foreign":""},"56":{"sum_foreign_comment":"","sum_foreign_hidden":false,"sum_comment":"","sum":"","sum_unclear":false,"sum_foreign":""},"57":{"sum_foreign_comment":"","sum":"","sum_comment":"","sum_comment_unclear":false,"sum_hidden":false,"sum_comment_hidden":false,"sum_unclear":false,"sum_foreign":""},"58":{"sum_foreign_comment":"","sum":"","sum_comment":"","sum_hidden":false,"sum_comment_hidden":false,"sum_unclear":false,"sum_foreign":""},"59":{"sum_foreign_comment":"","sum":"","sum_comment":"","sum_foreign":""},"60":{"sum_foreign_comment":"","sum":"","sum_comment":"","sum_comment_unclear":false,"sum_hidden":false,"sum_comment_hidden":false,"sum_unclear":false,"sum_foreign":""},"61":{"sum_foreign_comment":"","sum":"","sum_hidden":false,"sum_comment":"","sum_foreign":""},"62":{"sum_foreign_comment":"","sum":"","sum_comment":"","sum_unclear":false,"sum_foreign":""},"63":{"sum_foreign_comment":"","sum":"","sum_comment":"","sum_hidden":false,"sum_comment_hidden":false,"sum_unclear":false,"sum_foreign":""},"64":{"sum_foreign_comment":"","sum":"","sum_comment":"","sum_hidden":false,"sum_comment_hidden":false,"sum_foreign":""}},"ft_src":"суддя хмельницького окружного адміністративного суду\nХмельницька область\nАдміністративний місцевий суд\nДіана\nФелонюк Ю. В\nПодружжя\nФелонюк А. Ю\nДитина\nЛеонідівна\nФелонюк Діана Леонідівна\nДіана Леонідівна Фелонюк\nДіана Фелонюк\nФелонюк Діана Леонідівна\nФелонюк Діана Леонідівна\nФелонюк\n1968 куб.см, 2.0 TDI, у користуванні\nVolkswagen Tiguan\n2013\n3311 куб. см. у користуванні\nLexus RX 400 H\n2008\n8605\n9605\n2014\n1968 куб.см, 2.0 TDI, у користуванні\nVolkswagen Tiguan\n2013\n3311 куб. см. у користуванні\n2008\nLexus RX 400 H\n9605\n8605\n21890\nпай землі\n1500\n62\n1/2 будинку\n14\n1/5 квартири\n54.3\n58/100 квартири\n71.1\nквартира у користуванні\n39.3\n42/100 квартири\n71.1\nкористування\nПодружжя\nФелонюк Ю. В\nДитина\nФелонюк А. Ю\nФелонюк Діана Леонідівна\nДіана Леонідівна Фелонюк\nДіана Фелонюк\nФелонюк Діана Леонідівна\nФелонюк Діана Леонідівна\nДіана\nЛеонідівна\nАдміністративний місцевий суд\nХмельницька область\nсуддя хмельницького окружного адміністративного суду\nФелонюк\n207715\n120767\n210328\n134682\n13915\n1000\nпай\n1613\n2014\nпай землі\n21890\n1500\n1/5 квартири\n14\n58/100 квартири\n54.3\nквартира у користуванні\n71.1\n1/2 будинку\n62\n42/100 квартири\n39.3\nкористування\n71.1\nПодружжя\nФелонюк Ю. В\nФелонюк А. Ю\nДитина\nЛеонідівна\nФелонюк\nДіана\nФелонюк Діана Леонідівна\nДіана Леонідівна Фелонюк\nДіана Фелонюк\nФелонюк Діана Леонідівна\nХмельницька область\nАдміністративний місцевий суд\nсуддя хмельницького окружного адміністративного суду\nФелонюк Діана Леонідівна\n120767\n207715\n13915\n134682\n210328\nпай\n1613\n1000\n2013\nVolkswagen Tiguan\n1968 куб.см, 2.0 TDI, у користуванні\nLexus RX 400 H\n3311 куб. см. у користуванні\n2008\nпай\n1613\n13915\n134682\n210328\n1000\n120767\n207715\n1/5 квартири\n14\n58/100 квартири\n54.3\nквартира у користуванні\n71.1\nпай землі\n21890\n1500\n1/2 будинку\n62\n39.3\n42/100 квартири\nкористування\n71.1\n9605\n8605\n2014","general":{"inn":"","name":"Діана","inn_unclear":false,"family":[{"inn":"","inn_hidden":false,"relations_unclear":false,"relations_hidden":false,"relations_other":"","relations":"Подружжя","name_hidden":false,"inn_unclear":false,"family_name":"Фелонюк Ю. В","name_unclear":false},{"inn":"","inn_hidden":false,"inn_unclear":false,"relations_hidden":false,"relations_other":"","relations":"Дитина","name_hidden":false,"family_name":"Фелонюк А. Ю","name_unclear":false}],"inn_hidden":true,"family_raw":"","last_name":"Фелонюк","post":{"post_unclear":false,"region_unclear":false,"post":"суддя хмельницького окружного адміністративного суду","office":"Адміністративний місцевий суд","region":"Хмельницька область","post_hidden":false,"office_hidden":false,"office_unclear":false,"region_hidden":false},"full_name_suggest":{"output":"Фелонюк Діана Леонідівна","input":["Фелонюк Діана Леонідівна","Діана Леонідівна Фелонюк","Діана Фелонюк"]},"full_name":"Фелонюк Діана Леонідівна","addresses":[{"place_city_type_hidden":false,"place_district_hidden":false,"place_city_type":"","place_city_hidden":false,"place_address_unclear":false,"place_address":"","place_hidden":true,"place":"","place_district":"","place_unclear":false,"place_city":"","place_address_hidden":false}],"patronymic":"Леонідівна","last_name_unclear":false,"name_unclear":false},"source":"VULYK","estate":{"23":[{"costs":"","costs_comment":"","address_hidden":false,"region_hidden":true,"space_comment":"пай землі","space":"21890","address":"","region":"","costs_rent_comment":"","space_comment_hidden":false,"space_units":"м²","costs_rent":""},{"costs_rent":"","region":"","costs":"","costs_rent_comment":"","costs_comment":"","address_hidden":false,"region_hidden":false,"space_comment":"","space_units":"м²","space":"1500","address":""}],"24":[{"region_unclear":false,"space_unclear":false,"costs":"","costs_comment":"","address_hidden":false,"region_hidden":true,"space_comment":"1/2 будинку","space":"62","address":"","region":"","costs_rent_comment":"","space_units":"м²","costs_rent":""}],"25":[{"space_unclear":false,"costs":"","costs_comment":"","address_hidden":false,"region_hidden":true,"space_comment":"42/100 квартири","space_hidden":false,"space":"39.3","address":"","space_comment_unclear":false,"region":"","address_unclear":false,"costs_rent_comment":"","costs_unclear":false,"space_units":"м²","space_units_hidden":false,"costs_rent":""},{"costs":"","costs_comment":"","address_hidden":false,"region_hidden":true,"space_comment":"користування","space":"71.1","address":"","costs_rent_comment_unclear":false,"region":"","costs_rent_comment":"","space_comment_unclear":false,"space_units":"м²","costs_rent":""}],"31":[{"space_unclear":false,"address_hidden":false,"region_hidden":true,"space_comment":"1/5 квартири","space_hidden":false,"space":"14","address":"","region":"","costs_property":"","costs_rent_comment":"","space_units":"м²","costs_property_comment":"","costs_rent":""},{"costs_rent":"","region":"","costs_property":"","costs_rent_comment":"","address_hidden":false,"region_hidden":false,"space_comment":"58/100 квартири","costs_property_comment":"","space_units":"м²","space":"54.3","address":""},{"costs_rent":"","costs_property":"","costs_rent_comment":"","space_comment":"квартира у користуванні","costs_property_comment":"","space_units":"м²","space":"71.1","address":""}]},"intro":{"declaration_year":"2014","isnotdeclaration":""}}