{"id":"vulyk_104_106","declaration":{"additional_info_text":"","additional_info":"","date":"2016-03-30T00:00:00","url":"http://static.declarations.com.ua/declarations/chosen_ones/judges_batch/1904_dryha_andrii_mykolaiovych_2015.pdf"},"estate":{"31":[{"costs_property_comment":"","address":"","space_units":"м²","space_hidden":false,"space_unclear":false,"region_hidden":true,"costs_property":"","space_comment":"","address_hidden":false,"costs_rent_comment":"","space":"90.8","region":"","costs_rent":""}]},"vehicle":{"35":[{"sum_comment":"","brand_info":"2360 куб. см.","sum":"177260","sum_rent_comment":"","year":"2008","brand":"Mitsubishi Outlander XL","sum_rent":"","brand_info_unclear":false,"brand_hidden":false}]},"source":"VULYK","income":{"5":{"family_comment":"","value":"248057","family":"108340","comment":""},"6":{"family_comment":"","value":"248057","family":"57427","comment":"","value_unclear":false},"7":{"source_name_hidden":false,"family_comment":"","comment":"","family":"","value":"","source_name":"Кредитна спілка 'Суперкредит' Приватбанк"},"8":{"family_comment":"","value":"","family":"","comment":""},"9":{"family_comment":"","value":"","family":"41769","comment":""},"10":{"family_comment":"","value":"","family":"","comment":""},"11":{"family_comment":"","value":"","family":"","comment":"","comment_hidden":false},"12":{"family_comment":"","value":"","family":"9144","comment":""},"13":{"family_comment":"","value":"","family":"","comment":""},"14":{"family_comment":"","value":"","family":"","comment":""},"15":{"family_comment":"","family":"","comment":"","value_unclear":false,"family_unclear":false,"value":""},"16":{"family_comment":"","value":"","family":"","comment":""},"17":{"family_comment":"","value":"","family":"","comment":""},"18":{"family_comment":"","value":"","family":"","comment":""},"19":{"family_comment":"","value":"","family":"","comment":""},"20":{"family_comment":"","comment_unclear":false,"value":"","family":"","comment":""}},"banks":{"51":[{"sum_comment_unclear":false,"sum_units":"UAH","sum_foreign_units":"UAH","sum_hidden":false,"sum":"290261","sum_foreign_comment_unclear":false,"sum_foreign_comment":"","sum_comment":"","sum_foreign":"","sum_comment_hidden":false,"sum_foreign_hidden":false}]},"ft_src":"2008\nMitsubishi Outlander XL\n2360 куб. см.\n177260\n290261\n2015\n2360 куб. см.\n177260\nMitsubishi Outlander XL\n2008\n290261\n2015\nПодружжя\nДрига І. Л. 08. 08. 1976\nДитина\nДрига Д. А. 10. 02. 1996\nДитина\nДрига К. А. 24. 03. 2009\nДрига\nДрига Андрій Миколайович\nАндрій Миколайович Дрига\nАндрій Дрига\nДрига Андрій Миколайович\nДрига Андрій Миколайович\nАндрій\nМиколайович\nЗагальний апеляційний суд\nсуддя апеляційного суду київської області\nКиївська область\nКредитна спілка 'Суперкредит' Приватбанк\n248057\n57427\n9144\n248057\n108340\n41769\n90.8\n90.8\nПодружжя\nДрига І. Л. 08. 08. 1976\nДитина\nДрига Д. А. 10. 02. 1996\nДрига К. А. 24. 03. 2009\nДитина\nМиколайович\nДрига\nсуддя апеляційного суду київської області\nЗагальний апеляційний суд\nКиївська область\nДрига Андрій Миколайович\nДрига Андрій Миколайович\nАндрій Миколайович Дрига\nАндрій Дрига\nДрига Андрій Миколайович\nАндрій\n57427\n248057\n41769\nКредитна спілка 'Суперкредит' Приватбанк\n108340\n248057\n9144","general":{"inn":"","addresses":[{"place_city_type_hidden":false,"place_city_type":"","place_city_hidden":true,"place_hidden":true,"place_district":"","place_district_hidden":false,"place":"","place_address":"","place_address_hidden":true,"place_city":""}],"last_name":"Дрига","full_name":"Дрига Андрій Миколайович","family":[{"inn":"","family_name":"Дрига І. Л. 08. 08. 1976","relations_other":"","name_unclear":false,"inn_hidden":true,"name_hidden":false,"relations":"Подружжя"},{"inn":"","family_name":"Дрига Д. А. 10. 02. 1996","relations_other":"","name_unclear":false,"inn_hidden":false,"name_hidden":false,"relations":"Дитина"},{"inn":"","family_name":"Дрига К. А. 24. 03. 2009","relations_other":"","name_unclear":false,"inn_hidden":true,"relations":"Дитина"}],"patronymic":"Миколайович","inn_hidden":true,"name":"Андрій","post":{"office":"Загальний апеляційний суд","region_unclear":false,"post":"суддя апеляційного суду київської області","region":"Київська область","office_unclear":false},"family_raw":"","full_name_suggest":{"input":["Дрига Андрій Миколайович","Андрій Миколайович Дрига","Андрій Дрига"],"output":"Дрига Андрій Миколайович"}},"liabilities":{"54":{"sum_comment":"","sum_hidden":false,"sum":"","sum_foreign_comment":"","sum_foreign":"","sum_unclear":false,"sum_foreign_hidden":false,"sum_comment_hidden":false},"55":{"sum_comment":"","sum_foreign_comment":"","sum_foreign":"","sum":""},"56":{"sum_comment":"","sum_foreign_comment":"","sum_foreign":"","sum_unclear":false,"sum":""},"57":{"sum_comment_unclear":false,"sum_comment":"","sum":"","sum_foreign_comment":"","sum_foreign":"","sum_foreign_hidden":false,"sum_comment_hidden":false},"58":{"sum_comment":"","sum_foreign_comment":"","sum_foreign":"","sum_unclear":false,"sum":""},"59":{"sum_comment":"","sum_foreign_comment":"","sum_foreign":"","sum":""},"60":{"sum_comment":"","sum":"","sum_foreign_comment":"","sum_foreign":"","sum_foreign_hidden":false,"sum_comment_hidden":false},"61":{"sum_comment":"","sum_foreign_comment":"","sum_foreign":"","sum":""},"62":{"sum_comment":"","sum_foreign_comment":"","sum_foreign":"","sum":""},"63":{"sum_comment":"","sum_foreign_comment":"","sum_foreign":"","sum":""},"64":{"sum_comment":"","sum_foreign_comment":"","sum_foreign":"","sum":""}},"intro":{"isnotdeclaration":"","declaration_year":"2015"}}