{"income":{"5":{"value":"180481.08","family_comment":"","value_unclear":false,"family_unclear":false,"family":"","comment":""},"6":{"value":"180481.08","family_comment":"","value_unclear":false,"family_unclear":false,"family":"","comment":""},"7":{"family_comment":"","value":"","source_name":"","family":"","comment":""},"8":{"family_comment":"","value":"","family":"","comment":""},"9":{"family_comment":"","value":"","family":"","comment":"","family_comment_unclear":false},"10":{"family_comment":"","value":"","family":"","comment":""},"11":{"family_comment":"","value":"","family":"","comment":""},"12":{"family_comment":"","value":"","family":"","comment":""},"13":{"family_comment":"","value":"","family":"","comment":""},"14":{"family_comment":"","value":"","family":"","comment":""},"15":{"family_comment":"","value":"","family":"","comment":""},"16":{"family_comment":"","family_unclear":false,"value":"","family":"","comment":""},"17":{"family_comment":"","family_unclear":false,"value":"","family":"","comment":""},"18":{"family_comment":"","value":"","family":"","comment":""},"19":{"family_comment":"","value":"","family":"","comment":""},"20":{"family_comment":"","value":"","family":"","comment":""}},"id":"vulyk_88_47","declaration":{"additional_info_text":"","notfull_lostpages":"","date":"2015-03-27T00:00:00","notfull":"","additional_info":"","url":"http://static.declarations.com.ua/declarations/chosen_ones/judges_batch/2950_ikorska_ielizaveta_serhiivna.pdf"},"liabilities":{"54":{"sum_foreign_comment":"","sum":"","sum_comment":"","sum_comment_unclear":false,"sum_foreign":""},"55":{"sum_foreign_comment":"","sum":"","sum_comment":"","sum_foreign":""},"56":{"sum_foreign_comment":"","sum":"6000","sum_comment":"","sum_foreign":""},"57":{"sum_foreign_comment":"","sum":"","sum_comment":"","sum_hidden":false,"sum_comment_hidden":false,"sum_unclear":false,"sum_foreign":""},"58":{"sum_foreign_comment":"","sum":"","sum_comment":"","sum_hidden":false,"sum_comment_hidden":false,"sum_foreign":""},"59":{"sum_foreign_comment":"","sum":"","sum_comment":"","sum_foreign":""},"60":{"sum_foreign_comment":"","sum":"","sum_comment":"","sum_comment_unclear":false,"sum_hidden":false,"sum_comment_hidden":false,"sum_foreign":""},"61":{"sum_foreign_comment":"","sum":"","sum_comment":"","sum_foreign":""},"62":{"sum_foreign_comment":"","sum":"","sum_comment":"","sum_foreign":""},"63":{"sum_foreign_comment":"","sum":"","sum_comment":"","sum_foreign":""},"64":{"sum_foreign_comment":"","sum":"","sum_comment":"","sum_foreign":""}},"ft_src":"6000\nсуддя жовтневого районного суду м. маріуполя донецької області\nДонецька область\nЗагальний місцевий суд\nЄлізавета\nСергіївна\nІкорська Єлізавета Сергіївна\nЄлізавета Сергіївна Ікорська\nЄлізавета Ікорська\nІкорська Єлізавета Сергіївна\nІкорська\nІкорська Єлізавета Сергіївна\n180481.08\n180481.08\n537\n71\n2014\n180481.08\n180481.08\n537\n71\nІкорська Єлізавета Сергіївна\nЄлізавета Сергіївна Ікорська\nЄлізавета Ікорська\nІкорська Єлізавета Сергіївна\nІкорська Єлізавета Сергіївна\nЄлізавета\nІкорська\nЗагальний місцевий суд\nсуддя жовтневого районного суду м. маріуполя донецької області\nДонецька область\nСергіївна\n6000\n180481.08\n180481.08\n2014\n6000\nСергіївна\nІкорська\nЄлізавета\nІкорська Єлізавета Сергіївна\nЄлізавета Сергіївна Ікорська\nЄлізавета Ікорська\nІкорська Єлізавета Сергіївна\nДонецька область\nЗагальний місцевий суд\nсуддя жовтневого районного суду м. маріуполя донецької області\nІкорська Єлізавета Сергіївна\n71\n537\n2014","general":{"inn":"","name":"Єлізавета","patronymic_unclear":false,"patronymic":"Сергіївна","inn_hidden":true,"family_raw":"","last_name":"Ікорська","post":{"post":"суддя жовтневого районного суду м. маріуполя донецької області","region":"Донецька область","candidate":"","office_hidden":false,"region_hidden":false,"office":"Загальний місцевий суд"},"last_name_unclear":false,"full_name":"Ікорська Єлізавета Сергіївна","addresses":[{"place_district":"","place_city_hidden":false,"place_city":"","place_city_type_hidden":false,"place_district_hidden":false,"place_city_type":"","place_address_hidden":false,"place_address":"","place_hidden":true,"place":""}],"patronymic_hidden":false,"full_name_suggest":{"output":"Ікорська Єлізавета Сергіївна","input":["Ікорська Єлізавета Сергіївна","Єлізавета Сергіївна Ікорська","Єлізавета Ікорська"]}},"source":"VULYK","estate":{"23":[{"space_unclear":false,"costs":"","costs_rent_unclear":false,"costs_comment":"","address_hidden":false,"region_hidden":true,"space_comment":"","space":"537","address":"","region":"","address_unclear":false,"costs_rent_comment":"","space_comment_unclear":false,"space_units":"м²","costs_rent":""}],"25":[{"space_unclear":false,"costs":"","costs_comment":"","address_hidden":false,"region_hidden":true,"space_comment":"","space_hidden":false,"space":"71","address":"","region":"","address_unclear":false,"costs_rent_comment":"","space_comment_unclear":false,"space_units":"м²","costs_rent":""}]},"intro":{"declaration_year":"2014","isnotdeclaration":""}}