{"income":{"5":{"value":"201538","family_comment":"","value_unclear":false,"family_unclear":false,"family":"49247","comment":""},"6":{"value":"126713","family_comment":"","value_unclear":false,"family_unclear":false,"family":"49247","comment":""},"7":{"family_comment":"","value":"","source_name":"","family":"","comment":""},"8":{"family_comment":"","value":"","family":"","comment":""},"9":{"family_comment":"","value":"","family":"","comment":""},"10":{"family_comment":"","value":"","family":"","comment":""},"11":{"family_comment":"","value":"","family":"","comment":""},"12":{"family_comment":"","value":"","family":"","comment":""},"13":{"family_comment":"","value":"","family":"","comment":""},"14":{"family_comment":"","value":"","family":"","comment":""},"15":{"family_comment":"","value":"","value_unclear":false,"family":"","comment":""},"16":{"family_comment":"","value":"","family":"","comment":""},"17":{"family_comment":"","value":"","family":"","comment":""},"18":{"family_comment":"","value":"","family":"","comment":""},"19":{"family_comment":"","value":"","family":"","comment":""},"20":{"value":"74825","family_comment":"","value_unclear":false,"family_unclear":false,"family":"","comment":"","family_comment_unclear":false}},"id":"vulyk_99_17","banks":{"45":[{"sum_foreign_comment":"","sum":"1000","sum_comment":"Ощадбанк України","sum_foreign_units":"UAH","sum_comment_hidden":false,"sum_units":"UAH","sum_foreign":""}],"51":[{"sum_foreign_comment":"","sum":"10189","sum_comment":"Ощадбанк України","sum_comment_unclear":false,"sum_foreign_units":"UAH","sum_comment_hidden":false,"sum_units":"UAH","sum_foreign":""}]},"declaration":{"date":"2016-01-25T00:00:00","notfull":"1","notfull_lostpages":"7","url":"http://static.declarations.com.ua/declarations/chosen_ones/judges_batch/566_kysil_olesia_anatoliivna_2015.pdf"},"liabilities":{"54":{"sum_foreign_comment":"","sum":"","sum_comment":"","sum_comment_unclear":false,"sum_comment_hidden":false,"sum_foreign":""},"55":{"sum_foreign_comment":"","sum":"","sum_comment":"","sum_foreign":""},"56":{"sum_foreign_comment":"","sum":"","sum_comment":"","sum_foreign":""},"57":{"sum_foreign_comment":"","sum_comment":"","sum":"","sum_comment_hidden":false,"sum_foreign":""},"58":{"sum_foreign_comment":"","sum_comment":"","sum":"","sum_comment_hidden":false,"sum_foreign":""},"59":{"sum_foreign_comment":"","sum":"","sum_comment":"","sum_comment_hidden":false,"sum_unclear":false,"sum_foreign":""},"60":{"sum_foreign_comment":"","sum_comment":"","sum":"","sum_comment_hidden":false,"sum_foreign":""},"61":{"sum_foreign_comment":"","sum":"","sum_comment":"","sum_foreign":""},"62":{"sum_foreign_comment":"","sum":"","sum_comment":"","sum_foreign":""},"63":{"sum_foreign_comment":"","sum_comment":"","sum":"","sum_comment_hidden":false,"sum_foreign":""},"64":{"sum_foreign_comment":"","sum_comment":"","sum":"","sum_comment_hidden":false,"sum_foreign":""}},"ft_src":"Ощадбанк України\n10189\nОщадбанк України\n1000\nм. Яготин\n.0999\nКиївська область\nКиївська область\nм. Яготин\n.1117\nм. Яготин\n.1\nКиївська область\nКиївська область\nм. Яготин\n130.5\nм. Яготин\n90.7\nКиївська область\n7\n1\n2015\n49247\n126713\n49247\n201538\n74825\n7\n1\nОщадбанк України\n1000\n10189\nОщадбанк України\n2015\nКисіль\nКисіль Олеся Анатоліївна\nОлеся Анатоліївна Кисіль\nОлеся Кисіль\nКисіль Олеся Анатоліївна\nОлеся\nАнатоліївна\n07700\nКиївська область\nЯготин\nКисіль Олеся Анатоліївна\nЗагальний місцевий суд\nсуддя яготинського районного суду київської області\nКиївська область\nПодружжя\nКисіль Євгеній Олександрович\nДитина\nКисіль Владислав Євгенійович\nДитина\nКисіль Назарій Євгенійович\n126713\n49247\n74825\n201538\n49247\n.0999\nм. Яготин\nКиївська область\n.1117\nКиївська область\nм. Яготин\n.1\nКиївська область\nм. Яготин\nКиївська область\n90.7\nм. Яготин\n130.5\nКиївська область\nм. Яготин\nКисіль Євгеній Олександрович\nПодружжя\nКисіль Владислав Євгенійович\nДитина\nКисіль Назарій Євгенійович\nДитина\nАнатоліївна\nКиївська область\nЯготин\n07700\nКисіль\nсуддя яготинського районного суду київської області\nКиївська область\nЗагальний місцевий суд\nКисіль Олеся Анатоліївна\nКисіль Олеся Анатоліївна\nОлеся Анатоліївна Кисіль\nОлеся Кисіль\nКисіль Олеся Анатоліївна\nОлеся","general":{"inn":"","inn_hidden":true,"last_name":"Кисіль","post":{"post_unclear":false,"office":"Загальний місцевий суд","post":"суддя яготинського районного суду київської області","region":"Київська область"},"name":"Олеся","full_name":"Кисіль Олеся Анатоліївна","family_raw":"","addresses":[{"place_district":"","place_address_hidden":true,"place_city":"Яготин","place_address":"07700","place_district_hidden":false,"place_city_type":"Місто","place_city_hidden":false,"place_city_type_hidden":false,"place_hidden":true,"place":"Київська область"}],"family":[{"inn":"","relations":"Подружжя","name_hidden":true,"inn_hidden":true,"family_name":"Кисіль Євгеній Олександрович","name_unclear":false},{"inn":"","inn_hidden":true,"family_name":"Кисіль Владислав Євгенійович","relations_other":"","relations":"Дитина","name_unclear":false},{"inn":"","inn_hidden":true,"family_name":"Кисіль Назарій Євгенійович","relations_other":"","relations":"Дитина","name_hidden":false,"name_unclear":false}],"full_name_suggest":{"output":"Кисіль Олеся Анатоліївна","input":["Кисіль Олеся Анатоліївна","Олеся Анатоліївна Кисіль","Олеся Кисіль"]},"patronymic":"Анатоліївна"},"source":"VULYK","estate":{"23":[{"space_unclear":false,"costs":"","costs_comment":"","address_hidden":true,"region_hidden":false,"space_comment":"","space":".0999","address":"м. Яготин","region":"Київська область","costs_rent_comment":"","space_units":"га","costs_rent":""},{"space_unclear":false,"costs":"","costs_comment":"","address_hidden":false,"space_comment":"","space":".1117","address":"м. Яготин","costs_comment_unclear":false,"region":"Київська область","address_unclear":false,"costs_rent_comment":"","space_units":"га","costs_rent":""},{"costs_rent":"","space_unclear":false,"region":"Київська область","costs":"","costs_rent_comment":"","costs_comment":"","space_comment":"","space_units":"га","space":".1","address":"м. Яготин"}],"24":[{"costs_rent":"","region":"Київська область","costs":"","costs_rent_comment":"","costs_comment":"","address_hidden":true,"region_hidden":false,"space_comment":"","space_units":"м²","space":"90.7","address":"м. Яготин"}],"30":[{"costs_rent":"","region":"Київська область","costs_property":"","costs_rent_comment":"","address_hidden":true,"region_hidden":false,"space_comment":"","costs_property_comment":"","space_units":"м²","space":"130.5","address":"м. Яготин"}]},"intro":{"declaration_year":"2015"}}