{"income":{"5":{"value":"226101.69","comment_hidden":false,"family_comment":"","family":"248996.27","comment":"","family_comment_hidden":false},"6":{"value":"213058.99","family_comment":"","comment_hidden":false,"family_hidden":false,"family_unclear":false,"family_comment_hidden":false,"comment":"","family":"237526.27"},"7":{"value":"","comment_hidden":false,"family_comment_hidden":false,"family_comment":"","source_name":"","family":"","comment":"","source_name_hidden":false},"8":{"family_comment":"","value":"","family":"","comment":""},"9":{"value":"401.73","family_comment":"","value_unclear":false,"family_unclear":false,"comment_unclear":false,"comment":"","family":""},"10":{"family_comment":"","family_unclear":false,"value":"12617","family":"11470","comment":""},"11":{"family_comment":"","value":"","family":"","comment":""},"12":{"family_comment":"","value":"","family":"","comment":""},"13":{"family_comment":"","value":"","family":"","comment":""},"14":{"family_comment":"","value":"","family":"","comment":""},"15":{"family_comment":"","value":"","comment_unclear":false,"family":"","comment":""},"16":{"family_comment":"","value":"","comment_unclear":false,"family":"","comment":""},"17":{"family_comment":"","value":"","family":"","comment":""},"18":{"family_comment":"","value":"","family":"","comment":""},"19":{"family_comment":"","value":"","family":"","comment":""},"20":{"value":"23.97","family_comment":"","value_unclear":false,"family_unclear":false,"family_comment_unclear":false,"family_comment_hidden":false,"comment":"соціальні виплати","family":""}},"id":"vulyk_73_155","banks":{"45":[{"sum_foreign_comment":"","sum_units":"UAH","sum_comment":"","sum_comment_unclear":false,"sum_hidden":false,"sum_foreign_units":"UAH","sum_comment_hidden":false,"sum_unclear":false,"sum":"27459.15","sum_foreign":""}]},"declaration":{"additional_info_text":"","notfull_lostpages":"","date":"2014-03-20T00:00:00","notfull":"","additional_info":"","url":"http://static.declarations.com.ua/declarations/chosen_ones/judges_batch/1122_bonk_tetiana_bohdanivna.pdf"},"liabilities":{"54":{"sum_foreign_comment":"","sum_foreign_hidden":false,"sum_comment":"","sum_comment_unclear":false,"sum_hidden":false,"sum_comment_hidden":false,"sum_unclear":false,"sum":"","sum_foreign":""},"55":{"sum_foreign_comment":"","sum_comment_hidden":false,"sum":"","sum_comment":"","sum_foreign":""},"56":{"sum_foreign_comment":"","sum":"","sum_comment":"","sum_comment_unclear":false,"sum_foreign":""},"57":{"sum_foreign_comment":"","sum":"","sum_comment":"","sum_hidden":false,"sum_comment_hidden":false,"sum_unclear":false,"sum_foreign":""},"58":{"sum_foreign_comment":"","sum":"","sum_comment":"","sum_hidden":false,"sum_comment_hidden":false,"sum_foreign":""},"59":{"sum_foreign_comment":"","sum":"","sum_comment":"","sum_comment_unclear":false,"sum_unclear":false,"sum_foreign":""},"60":{"sum_foreign_comment":"","sum":"","sum_comment":"","sum_hidden":false,"sum_comment_hidden":false,"sum_unclear":false,"sum_foreign":""},"61":{"sum_foreign_comment":"","sum":"","sum_comment":"","sum_foreign":""},"62":{"sum_foreign_comment":"","sum":"11257.35","sum_comment":"","sum_foreign":""},"63":{"sum_foreign_comment":"","sum":"","sum_comment":"","sum_hidden":false,"sum_comment_hidden":false,"sum_foreign":""},"64":{"sum_foreign_comment":"","sum":"","sum_comment":"","sum_foreign":""}},"ft_src":"11257.35\nсуддя львівського апеляційного господарського суду\nЛьвівська область\nАпеляційний господарський суд\nТетяна\nДонченко Ю. В\nПодружжя\nДонченко Н. Ю\nДитина\nБогданівна\nБонк Тетяна Богданівна\nТетяна Богданівна Бонк\nТетяна Бонк\nБонк Тетяна Богданівна\nБонк\nБонк Тетяна Богданівна\n25\n86\n1000\n27459.15\n2013\n2013\nБонк Тетяна Богданівна\nТетяна Богданівна Бонк\nТетяна Бонк\nБонк Тетяна Богданівна\nТетяна\nПодружжя\nДонченко Ю. В\nДитина\nДонченко Н. Ю\nБонк Тетяна Богданівна\nБогданівна\nАпеляційний господарський суд\nЛьвівська область\nсуддя львівського апеляційного господарського суду\nБонк\n11257.35\n237526.27\n213058.99\nсоціальні виплати\n23.97\n226101.69\n248996.27\n401.73\n12617\n11470\n25\n86\n1000\n27459.15\n11257.35\n237526.27\n213058.99\n401.73\n11470\n12617\n248996.27\n226101.69\nсоціальні виплати\n23.97\nПодружжя\nДонченко Ю. В\nДитина\nДонченко Н. Ю\nБогданівна\nБонк\nТетяна\nБонк Тетяна Богданівна\nТетяна Богданівна Бонк\nТетяна Бонк\nБонк Тетяна Богданівна\nЛьвівська область\nАпеляційний господарський суд\nсуддя львівського апеляційного господарського суду\nБонк Тетяна Богданівна\n401.73\n11470\n12617\n23.97\nсоціальні виплати\n226101.69\n248996.27\n213058.99\n237526.27\n86\n25\n1000\n27459.15\n2013","general":{"inn":"","name":"Тетяна","family":[{"inn":"","relations":"Подружжя","inn_unclear":false,"relations_hidden":false,"inn_hidden":true,"relations_other":"","name_hidden":true,"family_name":"Донченко Ю. В","name_unclear":false},{"inn":"","relations":"Дитина","inn_unclear":false,"family_name":"Донченко Н. Ю","inn_hidden":false,"relations_other":"","name_hidden":false,"name_unclear":false}],"patronymic":"Богданівна","inn_hidden":true,"family_raw":"","last_name":"Бонк","post":{"post_unclear":false,"region_unclear":false,"post":"суддя львівського апеляційного господарського суду","office":"Апеляційний господарський суд","region":"Львівська область","post_hidden":false,"office_hidden":false,"office_unclear":false,"region_hidden":false},"last_name_unclear":false,"full_name":"Бонк Тетяна Богданівна","addresses":[{"place_district":"","place_city_hidden":true,"place_city":"","place_city_type_hidden":false,"place_district_hidden":false,"place_city_type":"","place_address_hidden":false,"place_address":"","place_hidden":true,"place":""}],"full_name_suggest":{"output":"Бонк Тетяна Богданівна","input":["Бонк Тетяна Богданівна","Тетяна Богданівна Бонк","Тетяна Бонк"]},"name_unclear":false},"source":"VULYK","estate":{"29":[{"space_unclear":false,"address_hidden":false,"region_hidden":true,"space_comment":"","space":"1000","address":"","region":"","costs_property":"","costs_rent_comment":"","space_units":"м²","costs_property_comment":"","costs_rent":""}],"31":[{"space_unclear":false,"address_hidden":false,"region_hidden":true,"space_comment":"","space":"86","address":"","region":"","costs_property":"","costs_rent_comment":"","space_units":"м²","costs_property_comment":"","costs_rent":""}],"33":[{"space_hidden":false,"address_hidden":false,"region_hidden":true,"space_comment":"","space":"25","address":"","region":"","costs_property":"","costs_rent_comment":"","space_units":"м²","costs_property_comment":"","costs_rent":""}]},"intro":{"declaration_year":"2013"}}