{"income":{"5":{"value":"183340","family_comment":"","value_unclear":false,"family_unclear":false,"family":"","comment":""},"6":{"value":"183340","family_comment":"","value_unclear":false,"family_unclear":false,"family":"","comment":""},"7":{"family_comment":"","value":"","source_name":"","family":"","comment":""},"8":{"family_comment":"","value":"","family":"","comment":""},"9":{"family_comment":"","value":"","value_unclear":false,"family":"","comment":""},"10":{"family_comment":"","value":"","value_unclear":false,"family":"","comment":""},"11":{"family_comment":"","value":"","family":"","comment":""},"12":{"family_comment":"","value":"","family":"","comment":""},"13":{"family_comment":"","value":"","value_unclear":false,"family":"","comment":""},"14":{"family_comment":"","value":"","family":"","comment":""},"15":{"family_comment":"","value":"","family":"","comment":""},"16":{"family_comment":"","value":"","family":"","comment":""},"17":{"family_comment":"","value":"","family":"","comment":""},"18":{"family_comment":"","value":"","family":"","comment":""},"19":{"family_comment":"","value":"","family":"","comment":""},"20":{"family_comment":"","family_unclear":false,"value":"","family":"","comment":""}},"id":"vulyk_85_53","declaration":{"additional_info_text":"","notfull_lostpages":"","date":"2015-03-26T00:00:00","notfull":"","additional_info":"","url":"http://static.declarations.com.ua/declarations/chosen_ones/judges_batch/2656_babich_stanislav_ihorovych.pdf"},"liabilities":{"54":{"sum_foreign_comment":"","sum":"","sum_comment":"","sum_comment_unclear":false,"sum_foreign":""},"55":{"sum_foreign_comment":"","sum":"","sum_comment":"","sum_foreign":""},"56":{"sum_foreign_comment":"","sum":"","sum_comment":"","sum_unclear":false,"sum_foreign":""},"57":{"sum_foreign_comment":"","sum":"","sum_comment":"","sum_foreign":""},"58":{"sum_foreign_comment":"","sum_comment_hidden":false,"sum":"","sum_comment":"","sum_foreign":""},"59":{"sum_foreign_comment":"","sum":"","sum_comment":"","sum_foreign":""},"60":{"sum_foreign_comment":"","sum":"","sum_comment":"","sum_foreign":""},"61":{"sum_foreign_comment":"","sum":"","sum_comment":"","sum_foreign":""},"62":{"sum_foreign_comment":"","sum":"","sum_comment":"","sum_unclear":false,"sum_foreign":""},"63":{"sum_foreign_comment":"","sum":"","sum_comment":"","sum_unclear":false,"sum_foreign":""},"64":{"sum_foreign_comment":"","sum":"","sum_comment":"","sum_foreign":""}},"ft_src":"суддя донецького окружного адміністративного суду\nДонецька область\nАдміністративний місцевий суд\nСтаніслав\nІгорович\nБабіч\nБабіч Станіслав Ігорович\nБабіч Станіслав Ігорович\nСтаніслав Ігорович Бабіч\nСтаніслав Бабіч\nБабіч Станіслав Ігорович\n183340\n183340\n1/2 від 88,4 кв. м\n44.2\n1/2 від 43,6 кв. м\n21.8\n2014\n183340\n183340\n183340\n183340\nАдміністративний місцевий суд\nсуддя донецького окружного адміністративного суду\nДонецька область\nБабіч Станіслав Ігорович\nСтаніслав Ігорович Бабіч\nСтаніслав Бабіч\nБабіч Станіслав Ігорович\nСтаніслав\nБабіч Станіслав Ігорович\nБабіч\nІгорович\n44.2\n1/2 від 88,4 кв. м\n21.8\n1/2 від 43,6 кв. м\n2014\nІгорович\nБабіч\nСтаніслав\nБабіч Станіслав Ігорович\nСтаніслав Ігорович Бабіч\nСтаніслав Бабіч\nБабіч Станіслав Ігорович\nсуддя донецького окружного адміністративного суду\nДонецька область\nАдміністративний місцевий суд\nБабіч Станіслав Ігорович\n1/2 від 88,4 кв. м\n44.2\n1/2 від 43,6 кв. м\n21.8\n2014","general":{"inn":"","name":"Станіслав","last_name_hidden":false,"patronymic":"Ігорович","inn_hidden":true,"family_raw":"","last_name":"Бабіч","post":{"post_unclear":false,"post_hidden":false,"post":"суддя донецького окружного адміністративного суду","region":"Донецька область","office":"Адміністративний місцевий суд"},"full_name_suggest":{"output":"Бабіч Станіслав Ігорович","input":["Бабіч Станіслав Ігорович","Станіслав Ігорович Бабіч","Станіслав Бабіч"]},"full_name":"Бабіч Станіслав Ігорович","addresses":[{"place_district":"","place_city_hidden":true,"place_city":"","place_city_type_hidden":false,"place_district_hidden":false,"place_city_type":"","place_address_hidden":true,"place_address":"","place_hidden":true,"place":""}],"last_name_unclear":false},"source":"VULYK","estate":{"25":[{"space_hidden":false,"costs":"","costs_comment":"","address_hidden":false,"region_hidden":true,"space_comment":"1/2 від 88,4 кв. м","space_unclear":false,"space":"44.2","address":"","costs_comment_unclear":false,"region":"","costs_rent_comment":"","space_comment_unclear":false,"space_units":"м²","costs_rent":""},{"space_hidden":false,"costs":"","costs_comment":"","address_hidden":false,"region_hidden":true,"space_comment":"1/2 від 43,6 кв. м","space":"21.8","address":"","region":"","costs_rent_comment":"","space_units":"м²","costs_rent":""}]},"intro":{"declaration_year":"2014","isnotdeclaration":""}}