{"income":{"5":{"value":"240727","comment_hidden":false,"family_comment":"","family":"24889","comment":"","family_comment_hidden":false},"6":{"value":"228110","family_comment":"","comment_hidden":false,"family_hidden":false,"family_unclear":false,"family_comment_hidden":false,"comment":"","family":"24889"},"7":{"value":"","comment_hidden":false,"family_comment_hidden":false,"family_comment":"","source_name":"","family":"","comment":"","source_name_hidden":false},"8":{"family_comment":"","value":"","family":"","comment":""},"9":{"value":"","family_comment":"","value_unclear":false,"family_unclear":false,"comment_unclear":false,"comment":"","family":""},"10":{"family_comment":"","family_unclear":false,"value":"12617","family":"","comment":""},"11":{"family_comment":"","value":"","family":"","comment":""},"12":{"family_comment":"","value":"","family":"","comment":""},"13":{"family_comment":"","value":"","family":"","comment":""},"14":{"family_comment":"","value":"","family":"","comment":""},"15":{"family_comment":"","value":"","comment_unclear":false,"family":"","comment":""},"16":{"family_comment":"","value":"","comment_unclear":false,"family":"","comment":""},"17":{"family_comment":"","value":"","family":"","comment":""},"18":{"family_comment":"","value":"","family":"","comment":""},"19":{"family_comment":"","value":"","family":"","comment":""},"20":{"value":"","family_comment":"","value_unclear":false,"family_unclear":false,"family_comment_unclear":false,"family_comment_hidden":false,"comment":"","family":""}},"vehicle":{"35":[{"brand_info":"1998 куб. см., 110 кВт","sum_rent_comment":"","brand":"Mazda CX-5","sum_comment":"","brand_unclear":false,"year":"2012","sum_hidden":false,"brand_info_unclear":false,"sum":"","sum_rent":""}],"40":[{"brand_info":"1998 куб. см., 110 кВт","sum_rent_comment":"","brand":"Mazda CX-5","sum_comment":"","brand_unclear":false,"year":"2012","brand_info_unclear":false,"sum":"","sum_rent":""}]},"id":"vulyk_53_56","banks":{"45":[{"sum_foreign_comment":"","sum_units":"UAH","sum_comment":"","sum_comment_unclear":false,"sum_hidden":false,"sum_foreign_units":"UAH","sum_comment_hidden":false,"sum_unclear":false,"sum":"7","sum_foreign":""}],"51":[{"sum_foreign_comment":"","sum_units":"UAH","sum_comment":"","sum_hidden":false,"sum_foreign_units":"UAH","sum_comment_hidden":false,"sum":"14234","sum_foreign":""}]},"declaration":{"additional_info_text":"","notfull_lostpages":"","date":"2014-03-21T00:00:00","notfull":"","additional_info":"","url":"http://static.declarations.com.ua/declarations/chosen_ones/judges_batch/1164_sapiha_vitalii_petrovych.pdf"},"liabilities":{"54":{"sum_foreign_comment":"","sum_foreign_hidden":false,"sum_comment":"","sum_comment_unclear":false,"sum_hidden":false,"sum_comment_hidden":false,"sum_unclear":false,"sum":"","sum_foreign":""},"55":{"sum_foreign_comment":"","sum_comment_hidden":false,"sum":"","sum_comment":"","sum_foreign":""},"56":{"sum_foreign_comment":"","sum":"","sum_comment":"","sum_comment_unclear":false,"sum_foreign":""},"57":{"sum_foreign_comment":"","sum":"","sum_comment":"","sum_hidden":false,"sum_comment_hidden":false,"sum_unclear":false,"sum_foreign":""},"58":{"sum_foreign_comment":"","sum":"","sum_comment":"","sum_hidden":false,"sum_comment_hidden":false,"sum_foreign":""},"59":{"sum_foreign_comment":"","sum":"","sum_comment":"","sum_comment_unclear":false,"sum_unclear":false,"sum_foreign":""},"60":{"sum_foreign_comment":"","sum":"","sum_comment":"","sum_hidden":false,"sum_comment_hidden":false,"sum_unclear":false,"sum_foreign":""},"61":{"sum_foreign_comment":"","sum":"","sum_comment":"","sum_foreign":""},"62":{"sum_foreign_comment":"","sum":"","sum_comment":"","sum_foreign":""},"63":{"sum_foreign_comment":"","sum":"","sum_comment":"","sum_hidden":false,"sum_comment_hidden":false,"sum_foreign":""},"64":{"sum_foreign_comment":"","sum":"","sum_comment":"","sum_foreign":""}},"ft_src":"суддя львівського апеляційного адміністративного суду\nЛьвівська область\nАпеляційний адміністративний суд\nВіталій\nСапіга О. М\nПодружжя\nСапіга А. В\nДитина\nСапіга Д. В\nДитина\nПетрович\nСапіга Віталій Петрович\nВіталій Петрович Сапіга\nВіталій Сапіга\nСапіга Віталій Петрович\nСапіга\nСапіга Віталій Петрович\nMazda CX-5\n1998 куб. см., 110 кВт\n2012\n2012\nMazda CX-5\n1998 куб. см., 110 кВт\n361\n295.9\n361\n295.9\n67.3\n14234\n7\n2013\n1998 куб. см., 110 кВт\nMazda CX-5\n2012\n1998 куб. см., 110 кВт\nMazda CX-5\n2012\n2013\nСапіга Віталій Петрович\nВіталій Петрович Сапіга\nВіталій Сапіга\nСапіга Віталій Петрович\nВіталій\nПодружжя\nСапіга О. М\nДитина\nСапіга А. В\nДитина\nСапіга Д. В\nСапіга Віталій Петрович\nПетрович\nАпеляційний адміністративний суд\nЛьвівська область\nсуддя львівського апеляційного адміністративного суду\nСапіга\n24889\n228110\n240727\n24889\n12617\n361\n361\n295.9\n295.9\n67.3\n7\n14234\n24889\n228110\n12617\n24889\n240727\nПодружжя\nСапіга О. М\nДитина\nСапіга А. В\nДитина\nСапіга Д. В\nПетрович\nСапіга\nВіталій\nСапіга Віталій Петрович\nВіталій Петрович Сапіга\nВіталій Сапіга\nСапіга Віталій Петрович\nЛьвівська область\nАпеляційний адміністративний суд\nсуддя львівського апеляційного адміністративного суду\nСапіга Віталій Петрович\n2012\n1998 куб. см., 110 кВт\nMazda CX-5\n2012\n1998 куб. см., 110 кВт\nMazda CX-5\n12617\n240727\n24889\n228110\n24889\n295.9\n361\n295.9\n67.3\n361\n7\n14234\n2013","general":{"inn":"","name":"Віталій","family":[{"inn":"","relations":"Подружжя","inn_unclear":false,"relations_hidden":false,"inn_hidden":true,"relations_other":"","name_hidden":false,"family_name":"Сапіга О. М","name_unclear":false},{"inn":"","relations":"Дитина","inn_unclear":false,"family_name":"Сапіга А. В","inn_hidden":false,"relations_other":"","name_hidden":false,"name_unclear":false},{"inn":"","relations":"Дитина","relations_other":"","inn_hidden":false,"family_name":"Сапіга Д. В","name_hidden":false,"name_unclear":false}],"patronymic":"Петрович","inn_hidden":true,"family_raw":"","last_name":"Сапіга","post":{"post_unclear":false,"region_unclear":false,"post":"суддя львівського апеляційного адміністративного суду","office":"Апеляційний адміністративний суд","region":"Львівська область","post_hidden":false,"office_hidden":false,"office_unclear":false,"region_hidden":false},"last_name_unclear":false,"full_name":"Сапіга Віталій Петрович","addresses":[{"place_district":"","place_city_hidden":true,"place_city":"","place_city_type_hidden":false,"place_district_hidden":false,"place_city_type":"","place_address_hidden":false,"place_address":"","place_hidden":true,"place":""}],"full_name_suggest":{"output":"Сапіга Віталій Петрович","input":["Сапіга Віталій Петрович","Віталій Петрович Сапіга","Віталій Сапіга"]},"name_unclear":false},"source":"VULYK","estate":{"23":[{"space_hidden":false,"costs":"","costs_comment":"","costs_hidden":false,"address_hidden":true,"region_hidden":true,"space_comment":"","space_unclear":false,"space":"361","address":"","region":"","space_units_unclear":false,"costs_unclear":false,"space_units":"м²","costs_rent":"","costs_rent_comment":""}],"24":[{"space_unclear":false,"costs":"","costs_comment":"","costs_hidden":false,"address_hidden":true,"region_hidden":true,"space_comment":"","space":"295.9","address":"","region":"","space_units_unclear":false,"space_comment_unclear":false,"space_comment_hidden":false,"space_units":"м²","costs_rent":"","costs_rent_comment":""}],"25":[{"space_unclear":false,"costs":"","costs_comment":"","costs_hidden":false,"address_hidden":true,"region_hidden":true,"space_comment":"","space_hidden":false,"space":"67.3","address":"","region":"","costs_rent_comment":"","space_comment_hidden":false,"space_units":"м²","costs_rent":""}],"29":[{"space_unclear":false,"address_hidden":true,"region_hidden":true,"space_comment":"","space":"361","address":"","region":"","costs_property":"","costs_rent_comment":"","space_units":"м²","costs_property_comment":"","costs_rent":""}],"30":[{"space_unclear":false,"address_hidden":false,"region_hidden":true,"space_comment":"","space_hidden":false,"space":"295.9","address":"","region":"","costs_property":"","costs_rent_comment":"","space_comment_unclear":false,"space_units":"м²","costs_property_comment":"","costs_rent":""}]},"intro":{"declaration_year":"2013"}}