{"income":{"5":{"value":"234157.5","family_comment":"","value_unclear":false,"family_unclear":false,"family":"30047.68","comment":""},"6":{"family_comment":"","value":"234157.5","value_unclear":false,"family":"","comment":""},"7":{"value":"","value_unclear":false,"family_comment":"","source_name":"","family":"","comment":""},"8":{"family_comment":"","value":"","family":"","comment":""},"9":{"value":"","family_comment":"","value_unclear":false,"family_unclear":false,"family":"30047.68","comment":""},"10":{"family_comment":"","value":"","comment_unclear":false,"family":"","comment":""},"11":{"family_comment":"","value":"","family":"","comment":""},"12":{"family_comment":"","value":"","family":"","comment":""},"13":{"family_comment":"","value":"","value_unclear":false,"family":"","comment":""},"14":{"family_comment":"","value":"","family":"","comment":""},"15":{"family_comment":"","value":"","family":"","comment":""},"16":{"family_comment":"","family_unclear":false,"value":"","family":"","comment":""},"17":{"family_comment":"","family_unclear":false,"value":"","family":"","comment":""},"18":{"family_comment":"","value":"","family":"","comment":""},"19":{"family_comment":"","value":"","family":"","comment":""},"20":{"value":"","family_comment":"","value_unclear":false,"family_hidden":false,"value_hidden":false,"family_unclear":false,"comment_unclear":false,"comment":"","family":""}},"vehicle":{"40":[{"brand_info":"3956 куб. см., 249 к. с., 4715 мм","sum_rent_comment":"","brand":"Toyota Land Cruiser Prado","sum_comment":"особиста приватна власність","year":"2008","brand_info_hidden":false,"brand_info_unclear":false,"sum":"","sum_rent":""},{"brand_info":"4461 куб. см., 235 к. с., 4990 мм","sum_rent_comment":"","brand":"Toyota Land Cruiser","sum_comment":"особиста приватна власність","year":"2009","brand_info_hidden":false,"sum":"","sum_rent":""}]},"id":"vulyk_100_6","banks":{"51":[{"sum_foreign_comment":"","sum_units":"UAH","sum_comment":"","sum_comment_unclear":false,"sum_foreign_units":"UAH","sum_units_unclear":false,"sum_comment_hidden":false,"sum_unclear":false,"sum":"172759.55","sum_foreign":""}]},"declaration":{"additional_info_text":"","notfull_lostpages":"","date":"2015-03-26T00:00:00","notfull":"","additional_info":"","url":"http://static.declarations.com.ua/declarations/chosen_ones/judges_batch/4124_vasylyshyn_valerii_oleksandrovych.pdf"},"liabilities":{"54":{"sum_foreign_comment":"","sum":"","sum_comment":"","sum_comment_hidden":false,"sum_unclear":false,"sum_foreign":""},"55":{"sum_foreign_comment":"","sum":"","sum_comment":"","sum_foreign":""},"56":{"sum_foreign_comment":"","sum":"","sum_comment":"","sum_unclear":false,"sum_foreign":""},"57":{"sum_foreign_comment":"","sum":"","sum_comment":"","sum_comment_unclear":false,"sum_comment_hidden":false,"sum_unclear":false,"sum_foreign":""},"58":{"sum_foreign_comment":"","sum":"","sum_comment":"","sum_comment_hidden":false,"sum_unclear":false,"sum_foreign":""},"59":{"sum_foreign_comment":"","sum":"","sum_comment":"","sum_foreign":""},"60":{"sum_foreign_comment":"","sum_comment_hidden":false,"sum":"","sum_comment":"","sum_foreign":""},"61":{"sum_foreign_comment":"","sum":"","sum_comment":"","sum_foreign":""},"62":{"sum_foreign_comment":"","sum":"","sum_comment":"","sum_unclear":false,"sum_foreign":""},"63":{"sum_foreign_comment":"","sum_comment_hidden":false,"sum":"","sum_comment":"","sum_foreign":""},"64":{"sum_foreign_comment":"","sum_comment_hidden":false,"sum":"","sum_comment":"","sum_foreign":""}},"ft_src":"Василишин Валерій Олександрович\nголова броварського міськрайонного суду київської області\nКиївська область\nЗагальний місцевий суд\nВалерій\nВасилишина Н. Т\nПодружжя\nВасилишин Д. В\nДитина\nВасилишин Валерій Олександрович\nВалерій Олександрович Василишин\nВалерій Василишин\nВасилишин Валерій Олександрович\nВасилишин\nОлександрович\nособиста приватна власність\n2008\n3956 куб. см., 249 к. с., 4715 мм\nToyota Land Cruiser Prado\nособиста приватна власність\n4461 куб. см., 235 к. с., 4990 мм\n2009\nToyota Land Cruiser\n172759.55\n2014\nToyota Land Cruiser Prado\n3956 куб. см., 249 к. с., 4715 мм\n2008\nособиста приватна власність\nToyota Land Cruiser\n4461 куб. см., 235 к. с., 4990 мм\n2009\nособиста приватна власність\n172759.55\n2264\n1200\n1200\n17\n15.5\n65.8\n1/3 частина власність\n65.8\n1/3 частина власність\n85.8\n65.8\n1/3 частина власність\nПодружжя\nВасилишина Н. Т\nДитина\nВасилишин Д. В\nОлександрович\nВасилишин\nВасилишин Валерій Олександрович\nВалерій Олександрович Василишин\nВалерій Василишин\nВасилишин Валерій Олександрович\nВасилишин Валерій Олександрович\nВалерій\nЗагальний місцевий суд\nКиївська область\nголова броварського міськрайонного суду київської області\n234157.5\n234157.5\n30047.68\n30047.68\n2014\n2264\n1200\n17\n15.5\n1200\n1/3 частина власність\n65.8\n1/3 частина власність\n65.8\n85.8\n1/3 частина власність\n65.8\nВасилишина Н. Т\nПодружжя\nДитина\nВасилишин Д. В\nОлександрович\nВасилишин\nКиївська область\nЗагальний місцевий суд\nголова броварського міськрайонного суду київської області\nВасилишин Валерій Олександрович\nВасилишин Валерій Олександрович\nВалерій Олександрович Василишин\nВалерій Василишин\nВасилишин Валерій Олександрович\nВалерій\n234157.5\n30047.68\n234157.5\n30047.68\nособиста приватна власність\n2008\n3956 куб. см., 249 к. с., 4715 мм\nToyota Land Cruiser Prado\nособиста приватна власність\nToyota Land Cruiser\n4461 куб. см., 235 к. с., 4990 мм\n2009\n234157.5\n30047.68\n30047.68\n234157.5\n1/3 частина власність\n65.8\n1/3 частина власність\n65.8\n2264\n1200\n17\n15.5\n85.8\n1/3 частина власність\n65.8\n1200\n172759.55\n2014","general":{"inn":"","inn_hidden":true,"last_name":"Василишин","post":{"post_unclear":false,"region_unclear":false,"post":"голова броварського міськрайонного суду київської області","office":"Загальний місцевий суд","region":"Київська область","post_hidden":false,"office_unclear":false},"name":"Валерій","full_name":"Василишин Валерій Олександрович","family_raw":"","addresses":[{"place_district":"","place_city_hidden":true,"place_city":"","place_city_unclear":false,"place_district_hidden":false,"place_city_type":"","place_address_hidden":true,"place_city_type_hidden":false,"place_address":"","place_hidden":true,"place":""}],"family":[{"inn_hidden":true,"inn":"","name_hidden":true,"family_name":"Василишина Н. Т","relations":"Подружжя","name_unclear":false},{"inn":"","relations":"Дитина","relations_other":"","inn_hidden":false,"family_name":"Василишин Д. В","name_hidden":false,"name_unclear":false}],"full_name_suggest":{"output":"Василишин Валерій Олександрович","input":["Василишин Валерій Олександрович","Валерій Олександрович Василишин","Валерій Василишин"]},"patronymic":"Олександрович"},"source":"VULYK","estate":{"23":[{"space_unclear":false,"costs":"","costs_comment":"","address_hidden":false,"region_hidden":true,"space_comment":"","space":"2264","address":"","costs_comment_unclear":false,"region":"","address_unclear":false,"costs_rent_comment":"","space_comment_unclear":false,"space_units":"м²","costs_rent":""},{"costs_rent":"","space_unclear":false,"region":"","costs":"","costs_rent_comment":"","costs_comment":"","space_comment":"","space_units":"м²","space":"1200","address":""}],"25":[{"space_unclear":false,"costs":"","costs_comment":"","address_hidden":false,"region_hidden":true,"space_comment":"","space":"85.8","address":"","costs_comment_unclear":false,"region":"","address_unclear":false,"costs_rent_comment":"","space_comment_unclear":false,"space_units":"м²","costs_rent":""},{"costs_rent":"","region":"","costs":"","costs_rent_comment":"","costs_comment":"","region_hidden":false,"space_comment":"1/3 частина власність","space_units":"м²","space":"65.8","address":""}],"27":[{"space_unclear":false,"costs":"","costs_comment":"","address_hidden":false,"region_hidden":true,"space_comment":"","space":"17","address":"","region":"","address_unclear":false,"costs_rent_comment":"","space_units":"м²","costs_rent":""},{"costs_rent":"","region":"","costs":"","costs_rent_comment":"","costs_comment":"","space_comment":"","space_units":"м²","space":"15.5","address":""}],"29":[{"region_unclear":false,"space_unclear":false,"address_hidden":false,"region_hidden":true,"space_comment":"","space":"1200","address":"","region":"","costs_property":"","costs_rent_comment":"","address_unclear":false,"space_units":"м²","costs_property_comment":"","costs_rent":""}],"31":[{"region_unclear":false,"space_unclear":false,"costs_property_comment_unclear":false,"address_hidden":false,"region_hidden":true,"space_comment":"1/3 частина власність","space":"65.8","address":"","region":"","costs_property":"","costs_rent_comment":"","space_comment_unclear":false,"address_unclear":false,"space_units":"м²","costs_property_comment":"","costs_rent":""},{"costs_rent":"","region_unclear":false,"region":"","costs_property":"","costs_rent_comment":"","region_hidden":false,"space_comment":"1/3 частина власність","costs_property_comment":"","space_units":"м²","space":"65.8","address":""}]},"intro":{"declaration_year":"2014"}}