{"income":{"5":{"value":"207860","family_comment":"","value_unclear":false,"family_hidden":false,"value_hidden":false,"family_unclear":false,"family":"15600","comment":"","family_comment_unclear":false},"6":{"family_comment":"","family_unclear":false,"value":"207860","family":"15600","comment":""},"7":{"source_name_unclear":false,"value":"","family_comment":"","source_name":"","family":"","comment":"","source_name_hidden":false},"8":{"family_comment":"","value":"","family":"","comment":""},"9":{"family_comment":"","family_unclear":false,"value":"","family":"","comment":""},"10":{"family_comment":"","value":"","family":"","comment":""},"11":{"family_comment":"","value":"","family":"","comment":""},"12":{"family_comment":"","value":"","family":"","comment":""},"13":{"family_comment":"","value":"","family":"","comment":""},"14":{"family_comment":"","value":"","family":"","comment":""},"15":{"family_comment":"","value":"","family":"","comment":""},"16":{"value":"","value_unclear":false,"value_hidden":false,"family_comment":"","family":"","comment":""},"17":{"family_comment":"","value":"","family":"","comment":""},"18":{"family_comment":"","value":"","family":"","comment":""},"19":{"family_comment":"","value":"","family":"","comment":""},"20":{"value":"","family_comment":"","value_unclear":false,"comment_hidden":false,"family_hidden":false,"family":"","value_hidden":false,"family_unclear":false,"comment_unclear":false,"comment":"","family_comment_unclear":false}},"vehicle":{"35":[{"year_hidden":false,"brand_info":"1598 куб. см., 78 кВт , 462 см","sum_rent_comment":"","sum_rent_hidden":false,"year":"2011","sum_hidden":false,"brand_info_hidden":false,"brand_info_unclear":false,"year_unclear":false,"sum_rent":"","sum":"130000","brand":"Renault Fluence","sum_comment":"","brand_unclear":false,"brand_hidden":false}],"40":[{"brand_info":"1798 куб. см., 85 кВт , 449 см","sum":"","brand":"Opel Vectra","sum_comment":"","brand_unclear":false,"year":"2001","brand_hidden":false,"brand_info_hidden":false,"brand_info_unclear":false,"sum_rent_comment":"","sum_rent":""}]},"id":"vulyk_62_147","declaration":{"additional_info_text":"","notfull_lostpages":"","date":"2015-03-31T00:00:00","notfull":"","additional_info":"","url":"http://static.declarations.com.ua/declarations/chosen_ones/mega_batch/zhurba_serhii_oleksandrovych.pdf"},"liabilities":{"54":{"sum_foreign_comment":"","sum":"","sum_comment":"","sum_hidden":false,"sum_comment_hidden":false,"sum_foreign":""},"55":{"sum_foreign_comment":"","sum":"","sum_comment":"","sum_hidden":false,"sum_comment_hidden":false,"sum_unclear":false,"sum_foreign":""},"56":{"sum_foreign_comment":"","sum":"","sum_comment":"","sum_hidden":false,"sum_unclear":false,"sum_foreign":""},"57":{"sum_foreign_comment":"","sum":"","sum_comment":"","sum_hidden":false,"sum_comment_hidden":false,"sum_unclear":false,"sum_foreign":""},"58":{"sum_foreign_comment":"","sum_foreign_hidden":false,"sum_comment":"","sum_hidden":false,"sum_comment_hidden":false,"sum_unclear":false,"sum":"","sum_foreign":""},"59":{"sum_foreign_comment":"","sum":"","sum_comment":"","sum_foreign":""},"60":{"sum_foreign_comment":"","sum_foreign_hidden":false,"sum_comment":"","sum_hidden":false,"sum_comment_hidden":false,"sum_unclear":false,"sum":"","sum_foreign":""},"61":{"sum_foreign_comment":"","sum_foreign_hidden":false,"sum_comment":"","sum_hidden":false,"sum":"","sum_foreign":""},"62":{"sum_foreign_comment":"","sum":"","sum_comment":"","sum_unclear":false,"sum_foreign":""},"63":{"sum_foreign_comment":"","sum":"","sum_comment":"","sum_hidden":false,"sum_comment_hidden":false,"sum_unclear":false,"sum_foreign":""},"64":{"sum_foreign_comment":"","sum":"","sum_comment":"","sum_comment_unclear":false,"sum_hidden":false,"sum_comment_hidden":false,"sum_foreign":""}},"ft_src":"суддя апеляційного суду київської області\nКиївська область\nЗагальний апеляційний суд\nСергій\nЖурба К. В\nПодружжя\nОлександрович\nЖурба Сергій Олександрович\nСергій Олександрович Журба\nСергій Журба\nЖурба Сергій Олександрович\nЖурба Сергій Олександрович\nЖурба\n1598 куб. см., 78 кВт , 462 см\nRenault Fluence\n2011\n130000\nOpel Vectra\n1798 куб. см., 85 кВт , 449 см\n2001\n2400\n190.5\n51.5\n44\n2014\n15600\n207860\n15600\n207860\n1598 куб. см., 78 кВт , 462 см\nRenault Fluence\n2011\n130000\n1798 куб. см., 85 кВт , 449 см\n2001\nOpel Vectra\n2400\n190.5\n51.5\n44\nПодружжя\nЖурба К. В\nЖурба Сергій Олександрович\nСергій Олександрович Журба\nСергій Журба\nЖурба Сергій Олександрович\nЖурба Сергій Олександрович\nСергій\nОлександрович\nЗагальний апеляційний суд\nсуддя апеляційного суду київської області\nКиївська область\nЖурба\n207860\n15600\n207860\n15600\n2014\nПодружжя\nЖурба К. В\nОлександрович\nЖурба\nСергій\nЖурба Сергій Олександрович\nСергій Олександрович Журба\nСергій Журба\nЖурба Сергій Олександрович\nКиївська область\nсуддя апеляційного суду київської області\nЗагальний апеляційний суд\nЖурба Сергій Олександрович\nRenault Fluence\n130000\n1598 куб. см., 78 кВт , 462 см\n2011\nOpel Vectra\n1798 куб. см., 85 кВт , 449 см\n2001\n207860\n15600\n15600\n207860\n51.5\n44\n2400\n190.5\n2014","general":{"inn":"","name":"Сергій","inn_unclear":false,"family":[{"inn":"","inn_hidden":true,"relations_unclear":false,"relations_hidden":false,"relations_other":"","relations":"Подружжя","name_hidden":true,"inn_unclear":false,"family_name":"Журба К. В","name_unclear":false}],"inn_hidden":true,"family_raw":"","last_name":"Журба","post":{"post_unclear":false,"post":"суддя апеляційного суду київської області","post_hidden":false,"region":"Київська область","region_hidden":false,"office":"Загальний апеляційний суд","office_hidden":false,"office_unclear":false},"full_name_suggest":{"output":"Журба Сергій Олександрович","input":["Журба Сергій Олександрович","Сергій Олександрович Журба","Сергій Журба"]},"full_name":"Журба Сергій Олександрович","addresses":[{"place_city_type_unclear":false,"place_address":"","place_district_hidden":true,"place_city_type":"","place_address_hidden":true,"place_address_unclear":false,"place_city_type_hidden":true,"place":"","place_district":"","place_unclear":false,"place_city":"","place_city_unclear":false,"place_hidden":true,"place_city_hidden":true,"place_district_unclear":false}],"patronymic":"Олександрович","last_name_unclear":false,"name_unclear":false},"source":"VULYK","estate":{"23":[{"region_unclear":false,"space_unclear":false,"costs":"","costs_comment":"","costs_hidden":false,"address_hidden":true,"region_hidden":true,"space_comment":"","space":"2400","address":"","region":"","address_unclear":false,"space_units_unclear":false,"space_comment_unclear":false,"space_units":"м²","space_units_hidden":false,"costs_rent":"","costs_rent_comment":""}],"25":[{"region_unclear":false,"space_hidden":false,"costs":"","costs_comment":"","costs_hidden":false,"address_hidden":true,"region_hidden":true,"space_comment":"","space_unclear":false,"space":"51.5","address":"","region":"","costs_rent_comment":"","space_units":"м²","costs_rent":""},{"costs":"","costs_comment":"","costs_hidden":false,"address_hidden":true,"region_hidden":false,"space_comment":"","space":"44","address":"","region":"","costs_rent_comment":"","space_comment_unclear":false,"space_units":"м²","costs_rent":""}],"26":[{"space_hidden":false,"costs":"","costs_comment":"","address_hidden":true,"region_hidden":true,"space_comment":"","space_unclear":false,"space":"190.5","address":"","region":"","costs_rent_comment":"","space_units":"м²","costs_rent":""}]},"intro":{"declaration_year":"2014","isnotdeclaration":"","declaration_year_unclear":false,"declaration_year_hidden":false}}