{"id":"vulyk_98_35","ft_src":"2006\nDaewoo 13110\n1299 куб. см.\nм. Костянтинівка\n24\nДонецька область\nм. Костянтинівка\n24\nДонецька область\nм. Костянтинівка\n68.3\nДонецька область\n2014\n231327\n254943\n23616\n1299 куб. см.\n2006\nDaewoo 13110\n2014\nЗагальний місцевий суд\nсуддя костянтинівського міськрайонного суду донецької області\nДонецька область\nЧернецький Володимир Анатолійович\nВолодимир Анатолійович Чернецький\nВолодимир Чернецький\nЧернецький Володимир Анатолійович\nЧернецький Володимир Анатолійович\nВолодимир\nЧернецький\nАнатолійович\n231327\n23616\n254943\n24\nДонецька область\nм. Костянтинівка\n24\nДонецька область\nм. Костянтинівка\n68.3\nДонецька область\nм. Костянтинівка\nАнатолійович\nЧернецький\nВолодимир\nЧернецький Володимир Анатолійович\nВолодимир Анатолійович Чернецький\nВолодимир Чернецький\nЧернецький Володимир Анатолійович\nсуддя костянтинівського міськрайонного суду донецької області\nДонецька область\nЗагальний місцевий суд\nЧернецький Володимир Анатолійович","estate":{"23":[{"address":"м. Костянтинівка","space_units":"м²","costs_comment":"","space_unclear":false,"region_hidden":false,"space_comment":"","address_hidden":true,"costs":"","costs_rent_comment":"","space":"24","region":"Донецька область","costs_rent":""}],"25":[{"address":"м. Костянтинівка","space_units":"м²","costs_comment":"","space_unclear":false,"region_hidden":false,"space_comment":"","address_hidden":true,"costs":"","address_unclear":false,"costs_rent_comment":"","space":"68.3","region":"Донецька область","costs_rent":""}],"27":[{"address":"м. Костянтинівка","space_units":"м²","costs_comment":"","space_unclear":false,"region_hidden":false,"space_comment":"","address_hidden":true,"costs":"","costs_rent_comment":"","space":"24","region":"Донецька область","costs_rent":""}]},"vehicle":{"35":[{"sum_comment":"","brand_info":"1299 куб. см.","brand_unclear":false,"sum_rent_comment":"","year":"2006","brand":"Daewoo 13110","sum_rent":"","brand_info_unclear":false,"sum":""}]},"source":"VULYK","income":{"5":{"family_comment":"","family":"","comment":"","value_unclear":false,"family_unclear":false,"value":"254943"},"6":{"family_comment":"","value":"231327","family":"","comment":"","value_unclear":false},"7":{"family":"","family_comment":"","value":"","comment":"","source_name":""},"8":{"family_comment":"","value":"","family":"","comment":""},"9":{"family_comment":"","value":"","family":"","comment":"","value_unclear":false},"10":{"family_comment":"","value":"","family":"","comment":""},"11":{"family_comment":"","value":"","family":"","comment":""},"12":{"family_comment":"","value":"","family":"","comment":""},"13":{"family_comment":"","value":"","family":"","comment":""},"14":{"family_comment":"","value":"","family":"","comment":""},"15":{"family_comment":"","value":"","family":"","comment":""},"16":{"family_comment":"","value":"","family":"","comment":""},"17":{"family_comment":"","value":"","family":"","comment":""},"18":{"family_comment":"","value":"","family":"","comment":""},"19":{"family_comment":"","value":"","family":"","comment":""},"20":{"family_comment":"","value":"23616","family":"","comment":"","value_unclear":false}},"general":{"family_raw":"","name":"Володимир","full_name_suggest":{"input":["Чернецький Володимир Анатолійович","Володимир Анатолійович Чернецький","Володимир Чернецький"],"output":"Чернецький Володимир Анатолійович"},"patronymic":"Анатолійович","inn_hidden":true,"addresses":[{"place_city_type_hidden":false,"place_city_type":"","place_city_hidden":true,"place_hidden":true,"place_district":"","place_district_hidden":false,"place":"","place_address":"","place_address_hidden":true,"place_city":""}],"last_name_hidden":false,"patronymic_hidden":false,"inn":"","inn_unclear":false,"last_name":"Чернецький","full_name":"Чернецький Володимир Анатолійович","post":{"office":"Загальний місцевий суд","region":"Донецька область","post_unclear":false,"post":"суддя костянтинівського міськрайонного суду донецької області"},"last_name_unclear":false},"liabilities":{"54":{"sum_comment_unclear":false,"sum_comment":"","sum_hidden":false,"sum":"","sum_foreign_comment":"","sum_foreign":"","sum_unclear":false,"sum_comment_hidden":false},"55":{"sum_comment":"","sum_foreign_comment":"","sum_foreign":"","sum":""},"56":{"sum_comment":"","sum_foreign_comment":"","sum_foreign":"","sum_unclear":false,"sum":""},"57":{"sum_comment_unclear":false,"sum_comment":"","sum_hidden":false,"sum":"","sum_foreign_comment":"","sum_foreign":"","sum_unclear":false,"sum_comment_hidden":false},"58":{"sum_comment":"","sum_hidden":false,"sum":"","sum_foreign_comment":"","sum_foreign":"","sum_unclear":false,"sum_comment_hidden":false},"59":{"sum_comment":"","sum_comment_unclear":false,"sum_foreign_comment":"","sum":"","sum_foreign":""},"60":{"sum_comment":"","sum_hidden":false,"sum":"","sum_foreign_comment":"","sum_foreign":"","sum_comment_hidden":false},"61":{"sum_comment":"","sum_foreign_comment":"","sum_foreign":"","sum":""},"62":{"sum_comment":"","sum":"","sum_foreign_comment":"","sum_foreign":"","sum_unclear":false,"sum_comment_hidden":false},"63":{"sum_comment_unclear":false,"sum_comment":"","sum":"","sum_foreign_comment":"","sum_foreign":"","sum_comment_hidden":false},"64":{"sum_comment":"","sum_foreign_comment":"","sum_foreign":"","sum":"","sum_comment_hidden":false}},"declaration":{"date":"2015-03-26T00:00:00","url":"http://static.declarations.com.ua/declarations/chosen_ones/judges_batch/4532_chernetskyi_volodymyr_anatoliiovych.pdf"},"intro":{"declaration_year":"2014"}}