{"income":{"5":{"value":"252648","value_unclear":false,"comment_hidden":false,"family_comment":"","family":"22800","comment":""},"6":{"family_comment":"","value":"206771","family":"22800","comment":"","value_hidden":false},"7":{"family_comment":"","value":"","source_name":"","family":"","comment":""},"8":{"family_comment":"","value":"","family":"","comment":""},"9":{"family_comment":"","value":"","comment_hidden":false,"family":"","comment":""},"10":{"family_comment":"","value":"","family":"","comment":""},"11":{"family_comment":"","value":"","family":"","comment":""},"12":{"family_comment":"","value":"","family":"","comment":""},"13":{"family_comment":"","value":"","family":"","comment":""},"14":{"family_comment":"","value":"","family":"","comment":""},"15":{"family_comment":"","value":"","family":"","comment":"","family_comment_hidden":false},"16":{"family_comment":"","value":"","family":"","comment":""},"17":{"family_comment":"","value":"","family":"","comment":""},"18":{"family_comment":"","value":"","family":"","comment":"","value_hidden":false},"19":{"family_comment":"","value":"","family":"","comment":""},"20":{"family_comment":"","value":"45877","family":"","comment":"","family_comment_unclear":false}},"vehicle":{"35":[{"brand_info":"3999 куб. см.","sum_rent_comment":"","brand":"BMW 540","sum_comment":"","year":"1999","sum":"","sum_rent":""}],"40":[{"brand_info":"1495 куб. см.","sum_rent_comment":"","brand":"ВАЗ 2106","sum_comment":"","year":"1989","brand_info_hidden":false,"sum":"","sum_rent":""}]},"id":"vulyk_78_18","declaration":{"additional_info_text":"","notfull_lostpages":"","date":"2015-03-30T00:00:00","notfull":"","additional_info":"","url":"http://static.declarations.com.ua/declarations/chosen_ones/judges_batch/2085_smoliar_oleksandr_andriiovych.pdf"},"liabilities":{"54":{"sum_foreign_comment":"","sum_foreign_hidden":false,"sum_comment":"","sum_comment_unclear":false,"sum_hidden":false,"sum_comment_hidden":false,"sum":"","sum_foreign":""},"55":{"sum_foreign_comment":"","sum":"","sum_comment":"","sum_foreign":""},"56":{"sum_foreign_comment":"","sum":"5000","sum_comment":"","sum_foreign":""},"57":{"sum_foreign_comment":"","sum":"","sum_comment":"","sum_foreign":""},"58":{"sum_foreign_comment":"","sum":"","sum_comment":"","sum_unclear":false,"sum_foreign":""},"59":{"sum_foreign_comment":"","sum":"","sum_comment":"","sum_foreign":""},"60":{"sum_foreign_comment":"","sum":"570","sum_comment":"","sum_comment_unclear":false,"sum_comment_hidden":false,"sum_foreign":""},"61":{"sum_foreign_comment":"","sum":"","sum_comment":"","sum_foreign":""},"62":{"sum_foreign_comment":"","sum":"","sum_hidden":false,"sum_comment":"","sum_foreign":""},"63":{"sum_foreign_comment":"","sum_foreign_hidden":false,"sum_comment":"","sum":"","sum_unclear":false,"sum_foreign":""},"64":{"sum_foreign_comment":"","sum_foreign_hidden":false,"sum_comment":"","sum_hidden":false,"sum":"","sum_foreign":""}},"ft_src":"5000\n570\nсуддя черкаського районного суду черкаської області\nЧеркаська область\nЗагальний місцевий суд\nОлександр\nСмоляр С. І\nПодружжя\nСмоляр А. О\nДитина\nСмоляр К. О\nДитина\nАндрійович\nСмоляр Олександр Андрійович\nОлександр Андрійович Смоляр\nОлександр Смоляр\nСмоляр Олександр Андрійович\nСмоляр\nСмоляр Олександр Андрійович\n3999 куб. см.\n1999\nBMW 540\n1495 куб. см.\n1989\nВАЗ 2106\n21\n2014\n22800\n206771\n22800\n252648\n45877\n3999 куб. см.\n1999\nBMW 540\n1495 куб. см.\n1989\nВАЗ 2106\n2014\nПодружжя\nСмоляр С. І\nДитина\nСмоляр А. О\nДитина\nСмоляр К. О\nСмоляр Олександр Андрійович\nОлександр Андрійович Смоляр\nОлександр Смоляр\nСмоляр Олександр Андрійович\nСмоляр Олександр Андрійович\nОлександр\nАндрійович\nЗагальний місцевий суд\nсуддя черкаського районного суду черкаської області\nЧеркаська область\nСмоляр\n570\n5000\n206771\n22800\n45877\n252648\n22800\n21\n5000\n570\nПодружжя\nСмоляр С. І\nДитина\nСмоляр А. О\nДитина\nСмоляр К. О\nАндрійович\nСмоляр\nОлександр\nСмоляр Олександр Андрійович\nОлександр Андрійович Смоляр\nОлександр Смоляр\nСмоляр Олександр Андрійович\nЧеркаська область\nсуддя черкаського районного суду черкаської області\nЗагальний місцевий суд\nСмоляр Олександр Андрійович\nBMW 540\n3999 куб. см.\n1999\nВАЗ 2106\n1495 куб. см.\n1989\n45877\n252648\n22800\n22800\n206771\n21\n2014","general":{"inn":"","name":"Олександр","family":[{"inn":"","relations":"Подружжя","relations_other":"","inn_hidden":true,"family_name":"Смоляр С. І","name_hidden":false,"name_unclear":false},{"inn":"","relations":"Дитина","relations_other":"","inn_hidden":true,"family_name":"Смоляр А. О","name_hidden":false,"name_unclear":false},{"inn":"","relations":"Дитина","relations_other":"","inn_hidden":false,"family_name":"Смоляр К. О","name_unclear":false}],"patronymic":"Андрійович","inn_hidden":true,"family_raw":"","last_name":"Смоляр","post":{"post_unclear":false,"post":"суддя черкаського районного суду черкаської області","post_hidden":false,"region":"Черкаська область","region_hidden":false,"office":"Загальний місцевий суд","office_hidden":false},"last_name_unclear":false,"full_name":"Смоляр Олександр Андрійович","addresses":[{"place_district":"","place_city_hidden":true,"place_city":"","place_city_type_hidden":true,"place_district_hidden":true,"place_city_type":"","place_address_hidden":true,"place_address":"","place_hidden":true,"place":""}],"full_name_suggest":{"output":"Смоляр Олександр Андрійович","input":["Смоляр Олександр Андрійович","Олександр Андрійович Смоляр","Олександр Смоляр"]},"name_unclear":false},"source":"VULYK","estate":{"27":[{"space_hidden":false,"costs":"","costs_comment":"","costs_hidden":false,"address_hidden":true,"region_hidden":true,"space_comment":"","space":"21","address":"","region":"","costs_rent_comment":"","costs_rent_hidden":false,"space_comment_hidden":false,"space_units":"м²","costs_rent":""}]},"intro":{"declaration_year":"2014"}}