{"income":{"5":{"value":"207786.85","family_comment":"","value_unclear":false,"family_unclear":false,"family":"136520","comment":""},"6":{"family_comment":"","value":"207786.85","value_unclear":false,"family":"","comment":""},"7":{"family_comment":"","value":"","source_name":"","family":"","comment":""},"8":{"family_comment":"","value":"","family":"","comment":""},"9":{"family_comment":"","value":"","value_unclear":false,"family":"","comment":""},"10":{"family_comment":"","value":"","family":"","comment":""},"11":{"family_comment":"","value":"","family":"","comment":""},"12":{"family_comment":"","value":"","family":"","comment":""},"13":{"family_comment":"","value":"","family":"","comment":""},"14":{"family_comment":"","value":"","family":"","comment":""},"15":{"family_comment":"","value":"","family":"","comment":""},"16":{"family_comment":"","value":"","family":"","comment":""},"17":{"family_comment":"","value":"","family":"136520","comment":""},"18":{"family_comment":"","value":"","family":"","comment":""},"19":{"family_comment":"","value":"","family":"","comment":""},"20":{"family_comment":"","value":"","value_unclear":false,"family":"","comment":""}},"vehicle":{"40":[{"brand_info":"3.5","sum":"","brand":"Toyota Highlander","sum_comment":"","year":"2014","sum_rent_comment":"","sum_rent":""}]},"id":"vulyk_98_9","declaration":{"date":"2015-03-27T00:00:00","url":"http://static.declarations.com.ua/declarations/chosen_ones/judges_batch/4480_vilchynskyi_oleksandr_vanadiiovych.pdf"},"liabilities":{"54":{"sum_foreign_comment":"","sum":"","sum_comment":"","sum_comment_unclear":false,"sum_hidden":false,"sum_comment_hidden":false,"sum_unclear":false,"sum_foreign":""},"55":{"sum_foreign_comment":"","sum":"","sum_comment":"","sum_foreign":""},"56":{"sum_foreign_comment":"","sum":"","sum_comment":"","sum_unclear":false,"sum_foreign":""},"57":{"sum_foreign_comment":"","sum":"","sum_comment":"","sum_comment_unclear":false,"sum_hidden":false,"sum_comment_hidden":false,"sum_unclear":false,"sum_foreign":""},"58":{"sum_foreign_comment":"","sum":"","sum_comment":"","sum_hidden":false,"sum_comment_hidden":false,"sum_unclear":false,"sum_foreign":""},"59":{"sum_foreign_comment":"","sum":"","sum_comment":"","sum_comment_unclear":false,"sum_foreign":""},"60":{"sum_foreign_comment":"","sum":"","sum_comment":"","sum_hidden":false,"sum_comment_hidden":false,"sum_foreign":""},"61":{"sum_foreign_comment":"","sum":"","sum_comment":"","sum_foreign":""},"62":{"sum_foreign_comment":"","sum":"","sum_comment":"","sum_comment_hidden":false,"sum_unclear":false,"sum_foreign":""},"63":{"sum_foreign_comment":"","sum":"","sum_comment":"","sum_comment_unclear":false,"sum_comment_hidden":false,"sum_foreign":""},"64":{"sum_foreign_comment":"","sum_comment":"","sum":"","sum_comment_hidden":false,"sum_foreign":""}},"ft_src":"3.5\n2014\nToyota Highlander\n.0791\n2014\n207786.85\n136520\n207786.85\n136520\n3.5\n2014\nToyota Highlander\n2014\nАдміністративний місцевий суд\nсуддя вінницького окружного адміністративного суду\nВінницька область\nВільчинський Олександр Ванадійович\nОлександр Ванадійович Вільчинський\nОлександр Вільчинський\nВільчинський Олександр Ванадійович\nВільчинський Олександр Ванадійович\nПодружжя\nВільчинська Н. В\nДитина\nВільчинська Г. О\nДитина\nВільчинський О. О\nОлександр\nВільчинський\nВанадійович\n207786.85\n136520\n136520\n207786.85\n.0791\nПодружжя\nВільчинська Н. В\nДитина\nВільчинська Г. О\nВільчинський О. О\nДитина\nВанадійович\nВільчинський\nОлександр\nВільчинський Олександр Ванадійович\nОлександр Ванадійович Вільчинський\nОлександр Вільчинський\nВільчинський Олександр Ванадійович\nсуддя вінницького окружного адміністративного суду\nВінницька область\nАдміністративний місцевий суд\nВільчинський Олександр Ванадійович","general":{"inn":"","name":"Олександр","last_name_hidden":false,"last_name":"Вільчинський","family":[{"inn":"","relations":"Подружжя","relations_other":"","inn_hidden":true,"family_name":"Вільчинська Н. В","name_hidden":true,"name_unclear":false},{"inn":"","relations":"Дитина","relations_other":"","inn_hidden":true,"family_name":"Вільчинська Г. О","name_hidden":false,"name_unclear":false},{"inn":"","relations":"Дитина","name_hidden":false,"inn_hidden":true,"family_name":"Вільчинський О. О","name_unclear":false}],"inn_hidden":true,"family_raw":"","inn_unclear":false,"post":{"post_unclear":false,"office":"Адміністративний місцевий суд","post":"суддя вінницького окружного адміністративного суду","region":"Вінницька область"},"full_name_suggest":{"output":"Вільчинський Олександр Ванадійович","input":["Вільчинський Олександр Ванадійович","Олександр Ванадійович Вільчинський","Олександр Вільчинський"]},"full_name":"Вільчинський Олександр Ванадійович","addresses":[{"place_district":"","place_address_hidden":true,"place_city":"","place_address":"","place_district_hidden":false,"place_city_type":"","place_city_hidden":true,"place_city_type_hidden":false,"place_hidden":true,"place":""}],"patronymic":"Ванадійович","patronymic_hidden":false,"last_name_unclear":false},"source":"VULYK","estate":{"23":[{"space_unclear":false,"costs":"","costs_comment":"","address_hidden":false,"region_hidden":true,"space_comment":"","space":".0791","address":"","region":"","costs_rent_comment":"","space_units":"га","costs_rent":""}]},"intro":{"declaration_year":"2014"}}