{"income":{"5":{"value":"211781","family_comment":"","comment_unclear":false,"family_unclear":false,"family":"","comment":""},"6":{"family_comment":"","value":"211770","family":"","comment":""},"7":{"source_name_unclear":false,"value":"","comment_unclear":false,"family_comment":"","source_name":"","family":"","comment":""},"8":{"family_comment":"","value":"","family":"","comment":""},"9":{"family_comment":"","value":"","family":"","comment":""},"10":{"family_comment":"","value":"","family":"","comment":""},"11":{"family_comment":"","value":"","family":"","comment":""},"12":{"family_comment":"","value":"","family":"","comment":""},"13":{"family_comment":"","value":"","family":"","comment":""},"14":{"family_comment":"","value":"","family":"","comment":""},"15":{"family_comment":"","value":"","family":"","comment":""},"16":{"family_comment":"","family_unclear":false,"value":"","family":"","comment":""},"17":{"family_comment":"","value":"","family":"","comment":""},"18":{"family_comment":"","value":"","family":"","comment":""},"19":{"family_comment":"","value":"","family":"","comment":""},"20":{"value":"11","family_comment":"","comment_unclear":false,"family_unclear":false,"family":"","comment":"ПриватБанк 'Бонус Плюс'","family_comment_unclear":false}},"vehicle":{"35":[{"brand_info":"1997 куб. см., 140 к.с. , право користування","sum_rent_comment":"","brand":"Ford Kuga","sum_comment":"","brand_unclear":false,"year":"2013","brand_info_unclear":false,"sum":"","sum_rent":""}]},"id":"vulyk_107_70","banks":{"45":[{"sum_foreign_comment":"","sum_units":"UAH","sum_comment":"","sum_comment_unclear":false,"sum_foreign_units":"UAH","sum_comment_hidden":false,"sum_unclear":false,"sum":"253","sum_foreign":""}],"47":[{"sum_foreign_comment":"","sum_units":"UAH","sum_comment":"","sum_foreign_units":"UAH","sum_comment_hidden":false,"sum":"43","sum_foreign":""}]},"declaration":{"additional_info_text":"","notfull_lostpages":"","date":"2016-03-30T00:00:00","notfull":"","additional_info":"","url":"http://static.declarations.com.ua/declarations/chosen_ones/judges_batch/2049_makarovets_alla_mykolaivna.pdf"},"liabilities":{"54":{"sum_foreign_comment":"","sum":"","sum_comment":"","sum_comment_unclear":false,"sum_comment_hidden":false,"sum_foreign":""},"55":{"sum_foreign_comment":"","sum":"","sum_comment":"","sum_foreign":""},"56":{"sum_foreign_comment":"","sum":"","sum_comment":"","sum_unclear":false,"sum_foreign":""},"57":{"sum_foreign_comment":"","sum":"","sum_comment":"","sum_comment_unclear":false,"sum_foreign":""},"58":{"sum_foreign_comment":"","sum":"","sum_comment":"","sum_comment_unclear":false,"sum_unclear":false,"sum_foreign":""},"59":{"sum_foreign_comment":"","sum":"","sum_comment":"","sum_unclear":false,"sum_foreign":""},"60":{"sum_foreign_comment":"","sum":"","sum_comment":"","sum_comment_unclear":false,"sum_comment_hidden":false,"sum_foreign":""},"61":{"sum_foreign_comment":"","sum":"","sum_comment":"","sum_foreign":""},"62":{"sum_foreign_comment":"","sum":"","sum_comment":"","sum_foreign":""},"63":{"sum_foreign_comment":"","sum":"","sum_comment":"","sum_foreign":""},"64":{"sum_foreign_comment":"","sum":"","sum_comment":"","sum_foreign":""}},"ft_src":"Макаровець Алла Миколаївна\nсуддя апеляційного суду сумської області\nСумська область\nЗагальний апеляційний суд\nАлла\nМакаровець Алла Миколаївна\nАлла Миколаївна Макаровець\nАлла Макаровець\nМакаровець Алла Миколаївна\nМакаровець\nМиколаївна\n2013\nFord Kuga\n1997 куб. см., 140 к.с. , право користування\n43\n253\n2015\n1997 куб. см., 140 к.с. , право користування\n2013\nFord Kuga\n253\n43\n2015\nМакаровець\nМакаровець Алла Миколаївна\nАлла Миколаївна Макаровець\nАлла Макаровець\nМакаровець Алла Миколаївна\nАлла\nМиколаївна\nМакаровець Алла Миколаївна\nЗагальний апеляційний суд\nсуддя апеляційного суду сумської області\nСумська область\n211770\n11\nПриватБанк 'Бонус Плюс'\n211781\n907\n1/2, у користуванні\n118.6\n1/2 ч.\n26.8\n1/2 ч.\n20\nу користуванні\n1/2, у користуванні\n907\n1/2 ч.\n26.8\n1/2 ч.\n118.6\nу користуванні\n20\nМакаровець\nМиколаївна\nсуддя апеляційного суду сумської області\nСумська область\nЗагальний апеляційний суд\nМакаровець Алла Миколаївна\nМакаровець Алла Миколаївна\nАлла Миколаївна Макаровець\nАлла Макаровець\nМакаровець Алла Миколаївна\nАлла\n211770\n211781\nПриватБанк 'Бонус Плюс'\n11\n2013\n1997 куб. см., 140 к.с. , право користування\nFord Kuga\nПриватБанк 'Бонус Плюс'\n11\n211781\n211770\n1/2, у користуванні\n907\n1/2 ч.\n118.6\nу користуванні\n20\n1/2 ч.\n26.8\n43\n253\n2015","general":{"inn":"","inn_hidden":true,"last_name":"Макаровець","post":{"post_unclear":false,"office":"Загальний апеляційний суд","post":"суддя апеляційного суду сумської області","region":"Сумська область"},"name":"Алла","full_name":"Макаровець Алла Миколаївна","family_raw":"","addresses":[{"place_district":"","place_city_hidden":true,"place_city":"","place_city_type_hidden":false,"place_district_hidden":false,"place_city_type":"","place_address_hidden":true,"place_address":"","place_hidden":true,"place":""}],"full_name_suggest":{"output":"Макаровець Алла Миколаївна","input":["Макаровець Алла Миколаївна","Алла Миколаївна Макаровець","Алла Макаровець"]},"patronymic":"Миколаївна"},"source":"VULYK","estate":{"23":[{"costs":"","costs_comment":"","address_hidden":false,"region_hidden":true,"space_comment":"1/2, у користуванні","space":"907","address":"","region":"","costs_rent_comment":"","space_comment_unclear":false,"space_comment_hidden":false,"space_units":"м²","costs_rent":""}],"24":[{"space_hidden":false,"costs":"","costs_comment":"","address_hidden":false,"region_hidden":true,"space_comment":"1/2 ч.","space":"118.6","address":"","region":"","costs_rent_comment":"","space_units":"м²","costs_rent":""}],"27":[{"space_hidden":false,"costs":"","costs_comment":"","address_hidden":false,"region_hidden":true,"space_comment":"1/2 ч.","space":"26.8","address":"","region":"","costs_rent_comment":"","space_units":"м²","costs_rent":""}],"28":[{"costs_rent":"","region":"","costs":"","costs_rent_comment":"","costs_comment":"","address_hidden":false,"region_hidden":true,"space_comment":"у користуванні","space_units":"м²","space":"20","address":""}]},"intro":{"declaration_year":"2015","isnotdeclaration":""}}