{"income":{"5":{"value":"240490.96","value_unclear":false,"family_hidden":false,"value_hidden":false,"family_comment":"","family":"9411.16","comment":""},"6":{"value":"238259.22","value_unclear":false,"family_hidden":false,"family_comment":"","family":"","comment":""},"7":{"value":"2231.74","comment_hidden":false,"family_comment":"","source_name":"Господарський суд Тернопільської області, Тернопільський інститут МАУП","family":"","comment":"","source_name_hidden":false},"8":{"family_comment":"","value":"","family":"","comment":""},"9":{"family_comment":"","value":"","family":"","comment":""},"10":{"family_comment":"","family_unclear":false,"value":"","family":"","comment":""},"11":{"family_comment":"","value":"","family":"","comment":""},"12":{"family_comment":"","value":"","family":"","comment":""},"13":{"family_comment":"","value":"","family":"","comment":""},"14":{"family_comment":"","value":"","family":"","comment":""},"15":{"family_comment":"","value":"","family":"","comment":""},"16":{"family_comment":"","value":"","family":"","comment":""},"17":{"family_comment":"","value":"","family":"","comment":""},"18":{"family_comment":"","value":"","family":"","comment":""},"19":{"family_comment":"","value":"","family":"","comment":""},"20":{"value":"","family_comment":"","family_hidden":false,"family_unclear":false,"family":"9411.16","comment":"","family_comment_unclear":false}},"vehicle":{"35":[{"brand_info":"седан-8.1.300 куб. см.","sum_rent_comment":"користування","brand_info_unclear":false,"year":"2007","brand_info_hidden":false,"sum_rent_comment_unclear":false,"sum_rent":"","sum":"","brand":"DAEWOO 13110","sum_comment":"","sum_comment_unclear":false,"brand_hidden":false,"brand_unclear":false}]},"id":"vulyk_45_125","banks":{"45":[{"sum_foreign_comment":"","sum_units":"UAH","sum_comment":"","sum_comment_unclear":false,"sum_foreign_units":"UAH","sum_comment_hidden":false,"sum_unclear":false,"sum":"380","sum_foreign":""},{"sum_foreign_comment":"","sum_units":"","sum_comment":"","sum_foreign_units":"","sum":"","sum_foreign":""}],"46":[{"sum_foreign_comment":"","sum_units":"UAH","sum_comment":"","sum_comment_unclear":false,"sum_foreign_units":"UAH","sum":"","sum_unclear":false,"sum_foreign":""}],"47":[{"sum_foreign_comment":"","sum_units":"UAH","sum_comment":"","sum_foreign_units":"UAH","sum":"40","sum_foreign":""}],"48":[{"sum_foreign_comment":"","sum_units":"UAH","sum_comment":"","sum_foreign_units":"UAH","sum":"","sum_foreign":""}],"49":[{"sum_foreign_comment":"","sum_units":"UAH","sum_comment":"","sum_foreign_units":"UAH","sum":"","sum_foreign":""}],"50":[{"sum_foreign_comment":"","sum_units":"UAH","sum_comment":"","sum_foreign_units":"UAH","sum":"","sum_foreign":""}],"51":[{"sum_foreign_comment":"","sum_units":"UAH","sum_comment":"","sum_foreign_units":"UAH","sum_comment_hidden":false,"sum":"28","sum_foreign":""},{"sum_foreign_comment":"","sum_units":"","sum_comment":"","sum_foreign_units":"","sum":"","sum_foreign":""}],"52":[{"sum_foreign_comment":"","sum_units":"UAH","sum_comment":"","sum_comment_unclear":false,"sum_foreign_units":"UAH","sum":"40","sum_unclear":false,"sum_foreign":""}],"53":[{"sum_foreign_comment":"","sum_units":"UAH","sum_comment":"","sum_foreign_comment_hidden":false,"sum_hidden":false,"sum_foreign_units":"UAH","sum_comment_hidden":false,"sum_foreign_hidden":false,"sum":"","sum_foreign":""}]},"declaration":{"additional_info_text":"","notfull_lostpages":"","date":"2015-03-27T00:00:00","notfull":"","additional_info":"","url":"http://static.declarations.com.ua/declarations/chosen_ones/mega_batch/pivtorak_mykhailo_ievstakhiiovych.pdf"},"liabilities":{"54":{"sum_foreign_comment":"","sum":"330","sum_comment":"","sum_comment_unclear":false,"sum_comment_hidden":false,"sum_unclear":false,"sum_foreign":""},"55":{"sum_foreign_comment":"","sum":"","sum_comment":"","sum_foreign":""},"56":{"sum_foreign_comment":"","sum":"10354","sum_comment":"","sum_comment_unclear":false,"sum_unclear":false,"sum_foreign":""},"57":{"sum_foreign_comment":"","sum":"","sum_comment":"","sum_comment_unclear":false,"sum_hidden":false,"sum_comment_hidden":false,"sum_foreign":""},"58":{"sum_foreign_comment":"","sum":"","sum_comment":"","sum_comment_unclear":false,"sum_hidden":false,"sum_comment_hidden":false,"sum_foreign":""},"59":{"sum_foreign_comment":"","sum":"","sum_comment":"","sum_foreign":""},"60":{"sum_foreign_comment":"","sum":"","sum_comment":"","sum_comment_unclear":false,"sum_comment_hidden":false,"sum_foreign":""},"61":{"sum_foreign_comment":"","sum":"","sum_comment":"","sum_foreign":""},"62":{"sum_foreign_comment":"","sum":"","sum_comment":"","sum_foreign":""},"63":{"sum_foreign_comment":"","sum":"","sum_comment":"","sum_comment_unclear":false,"sum_comment_hidden":false,"sum_unclear":false,"sum_foreign":""},"64":{"sum_foreign_comment":"","sum":"","sum_comment":"","sum_comment_unclear":false,"sum_comment_hidden":false,"sum_unclear":false,"sum_foreign":""}},"ft_src":"330\n10354\nТернопіль\nТернопільська область\nсуддя господарського суду тернопільської області\nТернопільська область\nГосподарський місцевий суд\nМихайло\nПівторак Г. П\nПодружжя\nПівторак М. М\nДитина\nЄвстахійович\nПівторак Михайло Євстахійович\nМихайло Євстахійович Півторак\nМихайло Півторак\nПівторак Михайло Євстахійович\nПівторак Михайло Євстахійович\nПівторак\nседан-8.1.300 куб. см.\nкористування\nDAEWOO 13110\n2007\n40\n28\n380\n40\n2014\nседан-8.1.300 куб. см.\nDAEWOO 13110\nкористування\n2007\n380\n28\n40\n40\n.09\nТернопільська область\n10. 10. 2012р. власність, договір дарування\nТернопільский р-н Ступківська с/р, садове товариство 'Росинка'\n24\nметалевий\nТернопільська область\nм. Тернопіль\n50.7\nвласність\nм. Тернопіль\nТернопільська область\nПодружжя\nПівторак Г. П\nДитина\nПівторак М. М\nПівторак Михайло Євстахійович\nМихайло Євстахійович Півторак\nМихайло Півторак\nПівторак Михайло Євстахійович\nПівторак Михайло Євстахійович\nМихайло\nПівторак\nГосподарський місцевий суд\nсуддя господарського суду тернопільської області\nТернопільська область\nЄвстахійович\nТернопільська область\nТернопіль\n10354\n330\n2231.74\nГосподарський суд Тернопільської області, Тернопільський інститут МАУП\n238259.22\n9411.16\n240490.96\n9411.16\n2014\n10354\n330\n10. 10. 2012р. власність, договір дарування\nТернопільский р-н Ступківська с/р, садове товариство 'Росинка'\n.09\nТернопільська область\nТернопільська область\nметалевий\nм. Тернопіль\n24\nвласність\nм. Тернопіль\n50.7\nТернопільська область\nПівторак Г. П\nПодружжя\nПівторак М. М\nДитина\nЄвстахійович\nПівторак\nМихайло\nПівторак Михайло Євстахійович\nМихайло Євстахійович Півторак\nМихайло Півторак\nПівторак Михайло Євстахійович\nТернопільська область\nТернопіль\nТернопільська область\nсуддя господарського суду тернопільської області\nГосподарський місцевий суд\nПівторак Михайло Євстахійович\n238259.22\nГосподарський суд Тернопільської області, Тернопільський інститут МАУП\n2231.74\n9411.16\n240490.96\n9411.16\n2007\nDAEWOO 13110\nкористування\nседан-8.1.300 куб. см.\n9411.16\n240490.96\n9411.16\n2231.74\nГосподарський суд Тернопільської області, Тернопільський інститут МАУП\n238259.22\nТернопільська область\nвласність\nм. Тернопіль\n50.7\nТернопільский р-н Ступківська с/р, садове товариство 'Росинка'\nТернопільська область\n.09\n10. 10. 2012р. власність, договір дарування\nметалевий\nм. Тернопіль\nТернопільська область\n24\n40\n380\n40\n28\n2014","general":{"inn":"","name":"Михайло","last_name_hidden":false,"family":[{"inn":"","inn_hidden":true,"relations_unclear":false,"relations_hidden":false,"relations_other":"","relations":"Подружжя","name_hidden":true,"family_name":"Півторак Г. П","name_unclear":false},{"inn":"","relations":"Дитина","relations_other":"","inn_hidden":false,"family_name":"Півторак М. М","name_hidden":false,"name_unclear":false}],"patronymic":"Євстахійович","inn_hidden":true,"family_raw":"","inn_unclear":false,"post":{"post_unclear":false,"post":"суддя господарського суду тернопільської області","post_hidden":false,"region":"Тернопільська область","region_hidden":false,"office":"Господарський місцевий суд","office_hidden":false,"office_unclear":false},"full_name":"Півторак Михайло Євстахійович","addresses":[{"place_district":"","place_city_hidden":false,"place_city":"Тернопіль","place_city_type_hidden":false,"place_district_hidden":false,"place_city_type":"Місто","place_address_hidden":true,"place_address":"","place_hidden":false,"place":"Тернопільська область"}],"last_name":"Півторак","full_name_suggest":{"output":"Півторак Михайло Євстахійович","input":["Півторак Михайло Євстахійович","Михайло Євстахійович Півторак","Михайло Півторак"]}},"source":"VULYK","estate":{"23":[{"space_unclear":false,"costs":"","costs_comment":"10. 10. 2012р. власність, договір дарування","costs_hidden":false,"address_hidden":false,"region_hidden":false,"space_comment":"","space":".09","address":"Тернопільский р-н Ступківська с/р, садове товариство 'Росинка'","region":"Тернопільська область","space_units_unclear":false,"space_units":"га","costs_rent":"","costs_rent_comment":""},{"costs":"","costs_comment":"","costs_hidden":false,"address_hidden":false,"region_hidden":false,"space_comment":"","space":"","address":"","region":"","costs_rent_comment":"","space_units":"","costs_rent":""},{"costs_rent":"","space_unclear":false,"region":"","costs":"","costs_rent_comment":"","costs_comment":"","address_hidden":false,"space_comment":"","space_units":"","space":"","address":""},{"costs_rent":"","region":"","costs":"","costs_rent_comment":"","costs_comment":"","space_comment":"","space_units":"","space":"","address":""},{"costs_rent":"","region":"","costs":"","costs_rent_comment":"","costs_comment":"","space_comment":"","space_units":"","space":"","address":""},{"costs_rent":"","region":"","costs":"","costs_rent_comment":"","costs_comment":"","space_comment":"","space_units":"","space":"","address":""}],"25":[{"space_unclear":false,"costs":"","costs_comment":"","address_hidden":true,"region_hidden":false,"space_comment":"власність","space_hidden":false,"space":"50.7","address":"м. Тернопіль","region":"Тернопільська область","address_unclear":false,"costs_rent_comment":"","costs_rent_hidden":false,"space_comment_hidden":false,"space_units":"м²","space_units_hidden":false,"costs_rent":""}],"27":[{"costs":"","costs_comment":"","address_hidden":true,"region_hidden":false,"space_comment":"металевий","space":"24","address":"м. Тернопіль","region":"Тернопільська область","address_unclear":false,"costs_rent_comment":"","space_units":"м²","costs_rent":""}]},"intro":{"declaration_year":"2014","isnotdeclaration":""}}