{"id":"vulyk_106_106","ft_src":"ЗАЗ 1102 Таврия\n1.3 куб. дм, власність\n2005\n2.0 куб.дм, право керувати\n2008\nHyundai Tucson\nвласність\n28\nвласність\n47\nкористування\n70\n2015\n210046\n13398\n263206\nпенсія\n39762\n1.3 куб. дм, власність\n2005\nЗАЗ 1102 Таврия\n2.0 куб.дм, право керувати\nHyundai Tucson\n2008\n28\nвласність\n47\nвласність\n70\nкористування\nБогданенко Ігор Юрійович\nІгор Юрійович Богданенко\nІгор Богданенко\nБогданенко Ігор Юрійович\nБогданенко Ігор Юрійович\nІгор\nБогданенко\nДніпропетровська область\nАпеляційний адміністративний суд\nсуддя дніпропетровського апеляційного адміністративного суду\nЮрійович\n210046\n39762\nпенсія\n263206\n13398\n2015\nЮрійович\nБогданенко\nІгор\nБогданенко Ігор Юрійович\nІгор Юрійович Богданенко\nІгор Богданенко\nБогданенко Ігор Юрійович\nДніпропетровська область\nАпеляційний адміністративний суд\nсуддя дніпропетровського апеляційного адміністративного суду\nБогданенко Ігор Юрійович","estate":{"25":[{"address":"","space_units":"м²","costs_comment":"","region_hidden":true,"space_comment":"власність","address_hidden":false,"costs":"","space_comment_unclear":false,"costs_rent_comment":"","space":"47","region":"","costs_rent":""},{"address":"","space_units":"м²","costs_comment":"","space_unclear":false,"region_hidden":false,"space_comment":"користування","address_hidden":false,"space":"70","space_comment_unclear":false,"costs_rent_comment":"","costs":"","region":"","costs_rent":""}],"27":[{"address":"","space_units":"м²","space_hidden":false,"space_comment":"власність","region_hidden":true,"costs_comment":"","address_hidden":false,"space":"28","costs_rent_comment":"","costs":"","region":"","costs_rent":""}]},"vehicle":{"35":[{"sum_comment":"","brand_info_hidden":false,"sum_rent":"","sum":"","sum_rent_comment":"","year":"2005","brand":"ЗАЗ 1102 Таврия","brand_info":"1.3 куб. дм, власність","brand_info_unclear":false,"year_unclear":false,"sum_hidden":false},{"sum_comment":"","brand_info":"2.0 куб.дм, право керувати","sum":"","sum_rent_comment":"","year":"2008","brand":"Hyundai Tucson","sum_rent":""}]},"source":"VULYK","income":{"5":{"family_comment":"","value":"263206","family":"","comment":""},"6":{"family_comment":"","value":"210046","family":"","comment":""},"7":{"family":"","family_comment":"","value":"","comment":"","source_name":""},"8":{"family_comment":"","value":"","family":"","comment":""},"9":{"family_comment":"","comment":"","family":"","comment_unclear":false,"value":"","family_comment_unclear":false},"10":{"family_comment":"","value":"13398","family":"","comment":""},"11":{"family_comment":"","value":"","family":"","comment":""},"12":{"family_comment":"","value":"","family":"","comment":""},"13":{"family_comment":"","value":"","family":"","comment":""},"14":{"family_comment":"","value":"","family":"","comment":""},"15":{"family_comment":"","value":"","family":"","comment":""},"16":{"family_comment":"","value":"","family":"","comment":""},"17":{"family_comment":"","value":"","family":"","comment":""},"18":{"family_comment":"","value":"","family":"","comment":""},"19":{"family_comment":"","family":"","comment":"","value_unclear":false,"family_unclear":false,"value":""},"20":{"family_comment":"","family":"","comment":"пенсія","value_unclear":false,"value":"39762","comment_hidden":false,"comment_unclear":false,"family_unclear":false,"family_comment_hidden":false,"family_comment_unclear":false}},"general":{"family_raw":"","name":"Ігор","full_name_suggest":{"input":["Богданенко Ігор Юрійович","Ігор Юрійович Богданенко","Ігор Богданенко"],"output":"Богданенко Ігор Юрійович"},"name_unclear":false,"patronymic":"Юрійович","inn_hidden":true,"addresses":[{"place_city_type_hidden":false,"place_city_type":"","place_city_hidden":false,"place_hidden":true,"place_district":"","place_district_hidden":false,"place":"","place_city":"","place_address_hidden":false,"place_address":""}],"inn":"","inn_unclear":false,"last_name":"Богданенко","full_name":"Богданенко Ігор Юрійович","post":{"post_hidden":false,"office":"Апеляційний адміністративний суд","post":"суддя дніпропетровського апеляційного адміністративного суду","office_unclear":false,"region_unclear":false,"region":"Дніпропетровська область"}},"liabilities":{"54":{"sum_comment_unclear":false,"sum_comment":"","sum_hidden":false,"sum":"","sum_foreign_comment":"","sum_foreign":"","sum_comment_hidden":false},"55":{"sum_comment":"","sum_foreign_comment":"","sum_foreign":"","sum_hidden":false,"sum":""},"56":{"sum_comment":"","sum_hidden":false,"sum":"","sum_foreign_comment":"","sum_foreign":"","sum_unclear":false,"sum_comment_hidden":false},"57":{"sum_comment":"","sum_hidden":false,"sum":"","sum_foreign_comment":"","sum_foreign":"","sum_comment_hidden":false},"58":{"sum_comment":"","sum_hidden":false,"sum":"","sum_foreign_comment":"","sum_foreign":"","sum_comment_hidden":false},"59":{"sum_comment":"","sum_foreign_comment":"","sum_foreign":"","sum":""},"60":{"sum_comment":"","sum_hidden":false,"sum":"","sum_foreign_comment":"","sum_foreign":"","sum_comment_hidden":false},"61":{"sum_comment":"","sum_foreign_comment":"","sum_foreign":"","sum":""},"62":{"sum_comment":"","sum":"","sum_foreign_comment":"","sum_foreign":"","sum_unclear":false,"sum_comment_hidden":false},"63":{"sum_comment":"","sum_foreign_comment":"","sum_foreign":"","sum":""},"64":{"sum_comment":"","sum_foreign_comment":"","sum_foreign":"","sum":""}},"declaration":{"notfull_lostpages":"","additional_info_text":"","additional_info":"","date":"2016-03-30T00:00:00","notfull":"","url":"http://static.declarations.com.ua/declarations/chosen_ones/judges_batch/2245_bohdanenko_ihor_iuriiovych.pdf"},"intro":{"isnotdeclaration":"","declaration_year":"2015"}}