{"income":{"5":{"family_comment":"","value":"331090","family_hidden":false,"comment":"","family":""},"6":{"family_comment":"","value":"255522","family_hidden":false,"comment":"","family":""},"7":{"family_comment":"","value":"","source_name":"","family":"","comment":""},"8":{"family_comment":"","value":"","family":"","comment":""},"9":{"family_comment":"","value":"30659","family":"","comment":""},"10":{"family_comment":"","value":"13398","family":"","comment":""},"11":{"family_comment":"","value":"","family":"","comment":""},"12":{"family_comment":"","value":"","family":"","comment":""},"13":{"family_comment":"","value":"","family":"","comment":""},"14":{"family_comment":"","value":"","family":"","comment":""},"15":{"family_comment":"","value":"","family":"","comment":""},"16":{"family_comment":"","value":"","family":"","comment":""},"17":{"family_comment":"","value":"","family":"","comment":""},"18":{"family_comment":"","value":"","family":"","comment":""},"19":{"family_comment":"","value":"","family":"","comment":""},"20":{"family_comment":"","value":"31511","family":"","comment":"пенсія"}},"id":"vulyk_105_51","banks":{"45":[{"sum_foreign_comment":"","sum_units":"UAH","sum_comment":"","sum_foreign_units":"UAH","sum_comment_hidden":false,"sum":"451920","sum_foreign":""}],"46":[{"sum_foreign_comment":"","sum_units":"UAH","sum_comment":"","sum_foreign_units":"UAH","sum":"145344","sum_foreign":""}]},"declaration":{"date":"2015-03-24T00:00:00","additional_info_text":"","additional_info":"","url":"http://static.declarations.com.ua/declarations/chosen_ones/judges_batch/4626_ropii_liudmyla_mykolaivna.pdf"},"liabilities":{"54":{"sum_foreign_comment":"","sum_comment_hidden":false,"sum":"","sum_comment":"","sum_foreign":""},"55":{"sum_foreign_comment":"","sum":"","sum_comment":"","sum_foreign":""},"56":{"sum_foreign_comment":"","sum":"","sum_comment":"","sum_foreign":""},"57":{"sum_foreign_comment":"","sum":"","sum_comment":"","sum_comment_unclear":false,"sum_comment_hidden":false,"sum_foreign":""},"58":{"sum_foreign_comment":"","sum":"","sum_comment":"","sum_foreign":""},"59":{"sum_foreign_comment":"","sum":"","sum_comment":"","sum_foreign":""},"60":{"sum_foreign_comment":"","sum":"","sum_comment":"","sum_foreign":""},"61":{"sum_foreign_comment":"","sum":"","sum_comment":"","sum_foreign":""},"62":{"sum_foreign_comment":"","sum":"","sum_hidden":false,"sum_comment":"","sum_foreign":""},"63":{"sum_foreign_comment":"","sum":"","sum_comment":"","sum_foreign":""},"64":{"sum_foreign_comment":"","sum":"","sum_comment":"","sum_foreign":""}},"ft_src":"Миколаївна\nРопій Людмила Миколаївна\nсуддя\nм. Київ\nАпеляційний господарський суд\nЛюдмила\nРопій Людмила Миколаївна\nЛюдмила Миколаївна Ропій\nЛюдмила Ропій\nРопій Людмила Миколаївна\nРопій\n13398\nпенсія\n31511\n331090\n30659\n255522\n145344\n451920\n65.1\n2014\n255522\n13398\n331090\n30659\nпенсія\n31511\n451920\n145344\n2014\nРопій\nРопій Людмила Миколаївна\nЛюдмила Миколаївна Ропій\nЛюдмила Ропій\nРопій Людмила Миколаївна\nЛюдмила\nРопій Людмила Миколаївна\nМиколаївна\nсуддя\nАпеляційний господарський суд\nм. Київ\n255522\n31511\nпенсія\n331090\n13398\n30659\n65.1\nМиколаївна\nРопій\nм. Київ\nсуддя\nАпеляційний господарський суд\nРопій Людмила Миколаївна\nРопій Людмила Миколаївна\nЛюдмила Миколаївна Ропій\nЛюдмила Ропій\nРопій Людмила Миколаївна\nЛюдмила\n65.1\n451920\n145344\n2014","general":{"inn":"","inn_hidden":true,"last_name":"Ропій","post":{"post_unclear":false,"region_unclear":true,"region":"м. Київ","office_hidden":false,"office":"Апеляційний господарський суд","post":"суддя","office_unclear":true},"name":"Людмила","full_name":"Ропій Людмила Миколаївна","family_raw":"","addresses":[{"place_district":"","place_city_hidden":false,"place_city":"","place_city_type_hidden":false,"place_district_hidden":false,"place_city_type":"","place_address_hidden":false,"place_address":"","place_hidden":true,"place":""}],"full_name_suggest":{"output":"Ропій Людмила Миколаївна","input":["Ропій Людмила Миколаївна","Людмила Миколаївна Ропій","Людмила Ропій"]},"patronymic":"Миколаївна"},"source":"VULYK","estate":{"25":[{"space_hidden":false,"costs":"","costs_comment":"","address_hidden":false,"region_hidden":true,"space_comment":"","space":"65.1","address":"","region":"","costs_rent_comment":"","space_units":"м²","costs_rent":""}]},"intro":{"declaration_year":"2014"}}