{"id":"vulyk_102_57","ft_src":"2005\n2.4 куб. дм.\nHonda Element\n1.1 куб. дм.\n1993\nЗАЗ 1102 Таврия\n2.0\n2008\nHyundai Tucson\n21\n1000\n260\n61\n1000\n110\n156\n27.28\n171000\n449000\n171000\n2015\n2.4 куб. дм.\nHonda Element\n2005\n1.1 куб. дм.\n1993\nЗАЗ 1102 Таврия\n2.0\n2008\nHyundai Tucson\n2015\nВинокуров Костянтин Сергійович\nКостянтин Сергійович Винокуров\nКостянтин Винокуров\nВинокуров Костянтин Сергійович\nВинокуров Костянтин Сергійович\nКостянтин\nСергійович\nсуддя вищого адміністративного суду україни\nЗагальнодержавний регіон\nВищий адміністративний суд\nВинокуров\nПодружжя\nДитина\nДитина\nДитина\nДитина\n147000\n147000\n17000\n34687\n30574\nдопомога при народженні дитини\n26705\n2700\n62856\nстрахове відшкодування за договором страхування здоров'я дитини\n1766571\n1012115\n15868\n56568\nвключаючи податок на доходи та військовий збір\n1689311\n924973\nвключаючи податок на доходи та військовий збір\n21\n260\n61\n156\n27.28\n1000\n1000\n110\n171000\n449000\n171000\n17000\n147000\n147000\n30574\n34687\n62856\n2700\nстрахове відшкодування за договором страхування здоров'я дитини\n1012115\n1766571\n924973\nвключаючи податок на доходи та військовий збір\nвключаючи податок на доходи та військовий збір\n1689311\n56568\n15868\nдопомога при народженні дитини\n26705\nПодружжя\nДитина\nДитина\nДитина\nДитина\nКостянтин\nСергійович\nВинокуров\nВинокуров Костянтин Сергійович\nКостянтин Сергійович Винокуров\nКостянтин Винокуров\nВинокуров Костянтин Сергійович\nсуддя вищого адміністративного суду україни\nЗагальнодержавний регіон\nВищий адміністративний суд\nВинокуров Костянтин Сергійович","estate":{"23":[{"address":"","space_units":"м²","space_comment":"","region_hidden":true,"space_units_unclear":false,"costs_comment":"","address_hidden":false,"space":"1000","space_comment_unclear":false,"costs_rent_comment":"","costs":"","region":"","costs_rent":""}],"25":[{"address":"","space_units":"м²","costs_comment":"","space_comment":"","region_hidden":true,"region":"","address_hidden":false,"space":"156","address_unclear":false,"costs_rent_comment":"","costs":"","costs_rent":""},{"costs":"","address":"","space_units":"м²","costs_rent_comment":"","space":"27.28","space_comment":"","region_hidden":false,"costs_comment":"","region":"","costs_rent":""}],"27":[{"costs":"","address":"","space_units":"м²","costs_rent_comment":"","space":"21","space_comment":"","region_hidden":true,"costs_comment":"","region":"","address_hidden":false,"costs_rent":""}],"28":[{"address":"","space_units":"м²","costs_comment":"","space_unclear":false,"region_hidden":true,"space_comment":"","address_hidden":false,"costs":"","costs_rent_comment":"","space":"260","region":"","costs_rent":""},{"address":"","space_units":"м²","costs_comment":"","space_unclear":false,"region_hidden":false,"space_comment":"","address_hidden":false,"space":"61","space_comment_unclear":false,"costs_rent_comment":"","costs":"","region":"","costs_rent":""}],"29":[{"costs_property_comment":"","address":"","space_units":"м²","space_comment":"","region_hidden":true,"costs_property":"","region":"","address_hidden":false,"space_comment_hidden":false,"costs_rent_comment":"","space":"1000","costs_rent":""}],"31":[{"costs_property_comment":"","address":"","space_units":"м²","costs_rent_comment":"","space":"110","region":"","region_hidden":true,"costs_property":"","space_comment":"","address_hidden":false,"costs_rent":""}]},"vehicle":{"35":[{"sum_comment":"","brand_info":"2.4 куб. дм.","sum":"","sum_rent_comment":"","year":"2005","brand":"Honda Element","sum_rent":"","brand_info_unclear":false,"year_unclear":false},{"sum_comment":"","brand_info":"1.1 куб. дм.","sum":"","sum_rent_comment":"","year":"1993","brand":"ЗАЗ 1102 Таврия","sum_rent":"","brand_info_unclear":true}],"40":[{"sum_comment":"","brand_info":"2.0","sum":"","sum_rent_comment":"","year":"2008","brand":"Hyundai Tucson","sum_rent":"","brand_info_unclear":false}]},"source":"VULYK","income":{"5":{"family_comment":"","value":"1766571","family":"1012115","comment":""},"6":{"family_comment":"","value":"34687","family":"30574","comment":""},"7":{"source_name_hidden":false,"family_comment":"","family":"","value_hidden":false,"comment":"","comment_hidden":false,"value":"","source_name":""},"8":{"family_comment":"","value":"","family":"","comment":""},"9":{"family_comment":"","family":"56568","comment":"","comment_hidden":false,"value":"15868","family_comment_unclear":false},"10":{"family_comment":"","value":"","family":"","comment":""},"11":{"family_comment":"","value":"","family":"","comment":"","comment_hidden":false},"12":{"family_comment":"","value":"","family":"","comment":""},"13":{"family_comment":"","value":"","family":"","comment":""},"14":{"family_comment":"","value":"","family":"","comment":""},"15":{"family_comment":"","value":"","family":"","comment":""},"16":{"family_comment":"","value":"","family":"","comment":""},"17":{"family_comment":"","value":"","family":"","comment":""},"18":{"family_comment":"","value":"","family":"","comment":""},"19":{"family_comment":"включаючи податок на доходи та військовий збір","value":"1689311","family":"924973","comment":"включаючи податок на доходи та військовий збір"},"20":{"family_comment":"","value":"26705","family":"","comment":"допомога при народженні дитини","comment_hidden":false},"21":[{"country_hidden":true,"country_comment":"страхове відшкодування за договором страхування здоров'я дитини","uah_equal":"62856","cur_units":"USD","country":"","cur":"2700"}]},"banks":{"45":[{"sum_comment_unclear":false,"sum_units":"UAH","sum_foreign_units":"UAH","sum_hidden":false,"sum":"171000","sum_foreign_comment":"","sum_comment":"","sum_unclear":false,"sum_foreign":"","sum_comment_hidden":true}],"46":[{"sum_units":"UAH","sum_comment":"","sum_foreign_units":"UAH","sum_hidden":false,"sum":"171000","sum_foreign_comment":"","sum_foreign":"","sum_unclear":false,"sum_comment_hidden":true}],"51":[{"sum_comment_unclear":false,"sum_units":"UAH","sum_foreign_units":"UAH","sum_hidden":false,"sum":"449000","sum_foreign_comment_hidden":false,"sum_foreign_comment":"","sum_comment":"","sum_unclear":false,"sum_foreign":"","sum_comment_hidden":true}]},"declaration":{"additional_info_text":"","additional_info":"","date":"2016-03-31T00:00:00","url":"http://static.declarations.com.ua/declarations/chosen_ones/judges_batch/1131_vynokurov_kostiantyn_serhiiovych.pdf"},"general":{"family":[{"inn":"","family_name":"","name_unclear":false,"inn_hidden":true,"name_hidden":true,"relations":"Подружжя"},{"inn":"","family_name":"","relations_other":"","name_unclear":false,"inn_hidden":true,"name_hidden":false,"relations":"Дитина"},{"inn":"","family_name":"","relations_other":"","name_unclear":false,"inn_hidden":true,"name_hidden":false,"relations":"Дитина"},{"inn":"","family_name":"","relations_other":"","name_unclear":false,"inn_hidden":true,"name_hidden":false,"relations":"Дитина"},{"inn":"","family_name":"","relations_other":"","name_hidden":false,"inn_hidden":true,"relations":"Дитина"}],"family_raw":"","name":"Костянтин","full_name_suggest":{"input":["Винокуров Костянтин Сергійович","Костянтин Сергійович Винокуров","Костянтин Винокуров"],"output":"Винокуров Костянтин Сергійович"},"patronymic":"Сергійович","inn_hidden":true,"patronymic_hidden":false,"inn":"","addresses":[{"place_city_type_hidden":false,"place_city_type":"","place_city_hidden":true,"place_hidden":true,"place_district":"","place_district_hidden":false,"place":"","place_address":"","place_address_hidden":true,"place_city":""}],"last_name":"Винокуров","full_name":"Винокуров Костянтин Сергійович","post":{"office_unclear":false,"region_unclear":false,"post":"суддя вищого адміністративного суду україни","region":"Загальнодержавний регіон","office":"Вищий адміністративний суд"}},"liabilities":{"54":{"sum_comment":"","sum_hidden":false,"sum":"147000","sum_foreign_comment":"","sum_foreign":"147000","sum_comment_hidden":true},"55":{"sum_comment":"","sum_foreign_comment":"","sum_foreign":"","sum":""},"56":{"sum_comment":"","sum_foreign_comment":"","sum_foreign":"","sum":"17000"},"57":{"sum_comment":"","sum_foreign_comment":"","sum_foreign":"","sum":"","sum_comment_hidden":false},"58":{"sum_comment":"","sum_foreign_comment":"","sum_foreign":"","sum":"","sum_comment_hidden":false},"59":{"sum_comment":"","sum_foreign_comment":"","sum_foreign":"","sum":"","sum_comment_hidden":false},"60":{"sum_comment":"","sum_hidden":false,"sum":"","sum_foreign_comment":"","sum_foreign":"","sum_comment_hidden":false},"61":{"sum_comment":"","sum_foreign_comment":"","sum_foreign":"","sum":""},"62":{"sum_comment":"","sum_foreign_comment":"","sum_foreign":"","sum_unclear":false,"sum":""},"63":{"sum_comment":"","sum_hidden":false,"sum":"","sum_foreign_comment":"","sum_foreign":"","sum_comment_hidden":false},"64":{"sum_comment":"","sum_foreign_comment":"","sum_foreign":"","sum":"","sum_comment_hidden":false}},"intro":{"declaration_year":"2015"}}