{"income":{"5":{"value":"218837","family_comment":"","value_unclear":false,"family_unclear":false,"family":"148693","comment":""},"6":{"family_comment":"","value":"218837","value_unclear":false,"family":"92304","comment":""},"7":{"value":"","value_unclear":false,"family_comment":"","source_name":"","family":"5583","comment":""},"8":{"family_comment":"","value":"","family":"","comment":""},"9":{"value":"","family_comment":"","value_unclear":false,"family_unclear":false,"family":"","comment":""},"10":{"family_comment":"","value":"","comment_unclear":false,"family":"","comment":""},"11":{"family_comment":"","value":"","family":"","comment":""},"12":{"family_comment":"","value":"","family":"","comment":""},"13":{"family_comment":"","value":"","value_unclear":false,"family":"","comment":""},"14":{"family_comment":"","value":"","family":"","comment":""},"15":{"family_comment":"","value":"","family":"","comment":""},"16":{"family_comment":"","family_unclear":false,"value":"","family":"","comment":""},"17":{"family_comment":"","family_unclear":false,"value":"","family":"","comment":""},"18":{"family_comment":"","value":"","family":"","comment":""},"19":{"family_comment":"","value":"","family":"","comment":""},"20":{"value":"","family_comment":"","value_unclear":false,"family_hidden":false,"value_hidden":false,"family_unclear":false,"comment_unclear":false,"comment":"","family":"50806"}},"vehicle":{"35":[{"brand_info":"2488 куб. см.","sum_rent_comment":"","brand_info_unclear":false,"year":"2008","brand_info_hidden":false,"sum_rent_comment_unclear":false,"sum_rent":"","sum":"","brand":"Nissan X-Trail","sum_comment":"","brand_unclear":false,"brand_hidden":false}],"40":[{"brand_info":"1390 куб. см.","sum_rent_comment":"","brand":"Volkswagen Golf","sum_comment":"","year":"2011","brand_info_hidden":false,"brand_info_unclear":false,"sum":"","sum_rent":""}]},"id":"vulyk_100_94","declaration":{"additional_info_text":"","notfull_lostpages":"","date":"2015-03-24T00:00:00","notfull":"","additional_info":"","url":"http://static.declarations.com.ua/declarations/chosen_ones/judges_batch/4294_prodan_borys_hryhorovych.pdf"},"liabilities":{"54":{"sum_foreign_comment":"","sum":"","sum_comment":"","sum_comment_hidden":false,"sum_unclear":false,"sum_foreign":""},"55":{"sum_foreign_comment":"","sum":"","sum_comment":"","sum_foreign":""},"56":{"sum_foreign_comment":"","sum":"21000","sum_comment":"","sum_unclear":false,"sum_foreign":""},"57":{"sum_foreign_comment":"","sum":"","sum_comment":"","sum_comment_unclear":false,"sum_comment_hidden":false,"sum_unclear":false,"sum_foreign":""},"58":{"sum_foreign_comment":"","sum":"","sum_comment":"","sum_comment_hidden":false,"sum_unclear":false,"sum_foreign":""},"59":{"sum_foreign_comment":"","sum":"","sum_comment":"","sum_foreign":""},"60":{"sum_foreign_comment":"","sum_comment_hidden":false,"sum":"","sum_comment":"","sum_foreign":""},"61":{"sum_foreign_comment":"","sum":"","sum_comment":"","sum_foreign":""},"62":{"sum_foreign_comment":"","sum":"12000","sum_comment":"","sum_unclear":false,"sum_foreign":""},"63":{"sum_foreign_comment":"","sum_comment_hidden":false,"sum":"","sum_comment":"","sum_foreign":""},"64":{"sum_foreign_comment":"","sum_comment_hidden":false,"sum":"","sum_comment":"","sum_foreign":""}},"ft_src":"12000\n21000\nПродан Борис Григорович\nсуддя хмельницького міськрайонного суду\nХмельницька область\nЗагальний місцевий суд\nБорис\nПродан Н. В\nПодружжя\nПродан Борис Григорович\nБорис Григорович Продан\nБорис Продан\nПродан Борис Григорович\nПродан\nГригорович\n2488 куб. см.\nNissan X-Trail\n2008\n2011\n1390 куб. см.\nVolkswagen Golf\n.15\nмашиномісце\n.04\n206.2\n90.4\n106.2\n2014\n92304\n218837\n5583\n148693\n218837\n50806\n2488 куб. см.\nNissan X-Trail\n2008\nVolkswagen Golf\n1390 куб. см.\n2011\n206.2\nмашиномісце\n106.2\n.04\n.15\n90.4\nПодружжя\nПродан Н. В\nГригорович\nПродан\nПродан Борис Григорович\nБорис Григорович Продан\nБорис Продан\nПродан Борис Григорович\nПродан Борис Григорович\nБорис\nЗагальний місцевий суд\nХмельницька область\nсуддя хмельницького міськрайонного суду\n21000\n12000\n5583\n218837\n92304\n50806\n218837\n148693\n2014\n21000\n12000\nПродан Н. В\nПодружжя\nГригорович\nПродан\nХмельницька область\nЗагальний місцевий суд\nсуддя хмельницького міськрайонного суду\nПродан Борис Григорович\nПродан Борис Григорович\nБорис Григорович Продан\nБорис Продан\nПродан Борис Григорович\nБорис\n2008\nNissan X-Trail\n2488 куб. см.\n2011\n1390 куб. см.\nVolkswagen Golf\n50806\n218837\n148693\n5583\n92304\n218837\n106.2\n.04\n90.4\n206.2\nмашиномісце\n.15\n2014","general":{"inn":"","inn_hidden":true,"last_name":"Продан","post":{"post_unclear":false,"region_unclear":false,"post":"суддя хмельницького міськрайонного суду","office":"Загальний місцевий суд","region":"Хмельницька область","post_hidden":false,"office_unclear":false},"name":"Борис","full_name":"Продан Борис Григорович","family_raw":"","addresses":[{"place_district":"","place_city_hidden":true,"place_city":"","place_city_unclear":false,"place_district_hidden":false,"place_city_type":"","place_address_hidden":true,"place_city_type_hidden":false,"place_address":"","place_hidden":true,"place":""}],"family":[{"inn_hidden":true,"inn":"","name_hidden":true,"family_name":"Продан Н. В","relations":"Подружжя","name_unclear":true}],"full_name_suggest":{"output":"Продан Борис Григорович","input":["Продан Борис Григорович","Борис Григорович Продан","Борис Продан"]},"patronymic":"Григорович"},"source":"VULYK","estate":{"23":[{"space_unclear":false,"costs":"","costs_comment":"","address_hidden":false,"region_hidden":true,"space_comment":"","space":".04","address":"","costs_comment_unclear":false,"region":"","address_unclear":false,"costs_rent_comment":"","space_comment_unclear":false,"space_units":"га","costs_rent":""}],"25":[{"space_unclear":false,"costs":"","costs_comment":"","address_hidden":false,"region_hidden":true,"space_comment":"","space":"106.2","address":"","costs_comment_unclear":false,"region":"","address_unclear":false,"costs_rent_comment":"","space_comment_unclear":false,"space_units":"м²","costs_rent":""}],"26":[{"costs_rent":"","region":"","costs":"","costs_rent_comment":"","costs_comment":"","address_hidden":false,"region_hidden":true,"space_comment":"","space_units":"м²","space":"90.4","address":""}],"28":[{"costs_rent":"","region":"","costs":"","costs_rent_comment":"","costs_comment":"","address_hidden":false,"region_hidden":true,"space_comment":"","space_units":"м²","space":"","address":"машиномісце"}],"29":[{"region_unclear":false,"space_unclear":false,"address_hidden":true,"region_hidden":true,"space_comment":"","space":".15","address":"","region":"","costs_property":"","costs_rent_comment":"","address_unclear":false,"space_units":"га","costs_property_comment":"","costs_rent":""}],"30":[{"costs_rent":"","region":"","costs_property":"","costs_rent_comment":"","address_hidden":true,"region_hidden":true,"space_comment":"","costs_property_comment":"","space_units":"м²","space":"206.2","address":""}]},"intro":{"declaration_year":"2014"}}