{"income":{"5":{"family_comment":"","family_unclear":false,"value":"223289.25","family":"17926.97","comment":""},"6":{"family_comment":"","family_unclear":false,"value":"209891.25","family":"","comment":""},"7":{"value":"","comment_hidden":false,"family_comment":"","source_name":"","family":"","comment":""},"8":{"family_comment":"","value":"","family":"","comment":""},"9":{"family_comment":"","value":"","family":"97.01","comment":""},"10":{"family_comment":"","value":"13398","family":"","comment":""},"11":{"family_comment":"","value":"","value_unclear":false,"family":"","comment":""},"12":{"family_comment":"","value":"","family":"","comment":""},"13":{"family_comment":"","value":"","family":"","comment":""},"14":{"family_comment":"","value":"","family":"","comment":""},"15":{"family_comment":"","value":"","value_unclear":false,"family":"","comment":""},"16":{"family_comment":"","family_unclear":false,"value":"","family":"","comment":""},"17":{"family_comment":"","value":"","family":"","comment":""},"18":{"family_comment":"","value":"","family_hidden":false,"comment":"","family":""},"19":{"family_comment":"","value":"","family":"","comment":""},"20":{"value":"","comment_unclear":false,"comment_hidden":false,"family_comment":"допомога на дитину","family":"17829.96","comment":"","family_comment_hidden":false}},"vehicle":{"35":[{"brand_info":"E280, 3000 куб.см","sum_rent_comment":"","year":"2007","brand_info_hidden":false,"brand_info_unclear":false,"year_unclear":false,"sum_rent":"","sum":"","brand":"Mercedes-Benz E-Class","sum_comment":"","brand_unclear":false,"brand_hidden":false}]},"id":"vulyk_68_142","declaration":{"additional_info_text":"","notfull_lostpages":"","date":"2015-03-30T00:00:00","notfull":"","additional_info":"","url":"http://static.declarations.com.ua/declarations/chosen_ones/mega_batch/zhelik_maksym_borysovych.pdf"},"liabilities":{"54":{"sum_foreign_comment":"","sum":"","sum_comment":"","sum_comment_unclear":false,"sum_hidden":false,"sum_comment_hidden":false,"sum_unclear":false,"sum_foreign":""},"55":{"sum_foreign_comment":"","sum":"","sum_hidden":false,"sum_comment":"","sum_foreign":""},"56":{"sum_foreign_comment":"","sum_foreign_hidden":false,"sum_comment":"","sum":"","sum_unclear":false,"sum_foreign":""},"57":{"sum_foreign_comment":"","sum":"","sum_comment":"","sum_comment_unclear":false,"sum_hidden":false,"sum_comment_hidden":false,"sum_unclear":false,"sum_foreign":""},"58":{"sum_foreign_comment":"","sum":"","sum_comment":"","sum_hidden":false,"sum_comment_hidden":false,"sum_unclear":false,"sum_foreign":""},"59":{"sum_foreign_comment":"","sum":"","sum_comment":"","sum_foreign":""},"60":{"sum_foreign_comment":"","sum":"","sum_comment":"","sum_comment_unclear":false,"sum_hidden":false,"sum_comment_hidden":false,"sum_unclear":false,"sum_foreign":""},"61":{"sum_foreign_comment":"","sum":"","sum_hidden":false,"sum_comment":"","sum_foreign":""},"62":{"sum_foreign_comment":"","sum":"","sum_comment":"","sum_unclear":false,"sum_foreign":""},"63":{"sum_foreign_comment":"","sum":"","sum_comment":"","sum_hidden":false,"sum_comment_hidden":false,"sum_unclear":false,"sum_foreign":""},"64":{"sum_foreign_comment":"","sum":"","sum_comment":"","sum_hidden":false,"sum_comment_hidden":false,"sum_foreign":""}},"ft_src":"суддя львівського апеляційного\nЛьвівська область\nАпеляційний господарський суд\nМаксим\nЖелік Олександра Мирославівна\nПодружжя\nЖелік Борис Максимович\nДитина\nЖелік Роман Максимович\nДитина\nЖелік Юстина Максимівна\nДитина\nБорисович\nЖелік Максим Борисович\nМаксим Борисович Желік\nМаксим Желік\nЖелік Максим Борисович\nЖелік Максим Борисович\nЖелік\nE280, 3000 куб.см\nMercedes-Benz E-Class\n2007\n.0812\n2014\n209891.25\n13398\n17926.97\n223289.25\n97.01\nдопомога на дитину\n17829.96\nE280, 3000 куб.см\nMercedes-Benz E-Class\n2007\n.0812\nПодружжя\nЖелік Олександра Мирославівна\nДитина\nЖелік Борис Максимович\nДитина\nЖелік Роман Максимович\nДитина\nЖелік Юстина Максимівна\nЖелік Максим Борисович\nМаксим Борисович Желік\nМаксим Желік\nЖелік Максим Борисович\nЖелік Максим Борисович\nМаксим\nБорисович\nАпеляційний господарський суд\nЛьвівська область\nсуддя львівського апеляційного\nЖелік\n209891.25\nдопомога на дитину\n17829.96\n223289.25\n17926.97\n13398\n97.01\n2014\nПодружжя\nЖелік Олександра Мирославівна\nЖелік Борис Максимович\nДитина\nЖелік Роман Максимович\nДитина\nЖелік Юстина Максимівна\nДитина\nБорисович\nЖелік\nМаксим\nЖелік Максим Борисович\nМаксим Борисович Желік\nМаксим Желік\nЖелік Максим Борисович\nЛьвівська область\nАпеляційний господарський суд\nсуддя львівського апеляційного\nЖелік Максим Борисович\n2007\nMercedes-Benz E-Class\nE280, 3000 куб.см\n13398\nдопомога на дитину\n17829.96\n17926.97\n223289.25\n97.01\n209891.25\n.0812\n2014","general":{"inn":"","name":"Максим","inn_unclear":false,"family":[{"inn":"","inn_hidden":false,"relations_unclear":false,"relations_hidden":false,"relations_other":"","relations":"Подружжя","name_hidden":false,"inn_unclear":false,"family_name":"Желік Олександра Мирославівна","name_unclear":true},{"inn":"","inn_hidden":false,"inn_unclear":false,"relations_hidden":false,"relations_other":"","relations":"Дитина","name_hidden":false,"family_name":"Желік Борис Максимович","name_unclear":false},{"inn":"","relations":"Дитина","relations_other":"","inn_hidden":false,"family_name":"Желік Роман Максимович","name_hidden":false,"name_unclear":false},{"inn":"","relations":"Дитина","relations_other":"","inn_hidden":false,"family_name":"Желік Юстина Максимівна","name_unclear":true}],"inn_hidden":true,"family_raw":"","last_name":"Желік","post":{"post_unclear":false,"region_unclear":false,"post":"суддя львівського апеляційного","office":"Апеляційний господарський суд","region":"Львівська область","post_hidden":false,"office_hidden":false,"office_unclear":false,"region_hidden":false},"full_name_suggest":{"output":"Желік Максим Борисович","input":["Желік Максим Борисович","Максим Борисович Желік","Максим Желік"]},"full_name":"Желік Максим Борисович","addresses":[{"place_city_type_hidden":false,"place_district_hidden":false,"place_city_type":"","place_city_hidden":false,"place_address_unclear":false,"place_address":"","place_hidden":true,"place":"","place_district":"","place_unclear":false,"place_city":"","place_address_hidden":false}],"patronymic":"Борисович","last_name_unclear":true,"name_unclear":false},"source":"VULYK","estate":{"23":[{"costs":"","costs_comment":"","address_hidden":false,"region_hidden":false,"space_comment":"","space":".0812","address":"","region":"","costs_rent_comment":"","space_comment_hidden":false,"space_units":"га","costs_rent":""}]},"intro":{"declaration_year":"2014","isnotdeclaration":""}}