{"income":{"5":{"value":"283171.32","family_comment":"","value_unclear":false,"family_unclear":false,"family":"","comment":""},"6":{"family_comment":"","value":"278946.22","value_unclear":false,"family":"","comment":""},"7":{"value":"4225.1","value_unclear":false,"family_comment":"","source_name":"Національна школа суддів України","family":"","comment":""},"8":{"family_comment":"","value":"","family":"","comment":""},"9":{"value":"","family_comment":"","value_unclear":false,"family_unclear":false,"family":"","comment":""},"10":{"family_comment":"","value":"","comment_unclear":false,"family":"","comment":""},"11":{"family_comment":"","value":"","family":"","comment":""},"12":{"family_comment":"","value":"","family":"","comment":""},"13":{"family_comment":"","value":"","value_unclear":false,"family":"","comment":""},"14":{"family_comment":"","value":"","family":"","comment":""},"15":{"family_comment":"","value":"","family":"","comment":""},"16":{"family_comment":"","family_unclear":false,"value":"","family":"","comment":""},"17":{"family_comment":"","family_unclear":false,"value":"","family":"","comment":""},"18":{"family_comment":"","value":"","family":"","comment":""},"19":{"family_comment":"","value":"","family":"","comment":""},"20":{"value":"","family_comment":"","value_unclear":false,"family_hidden":false,"value_hidden":false,"family_unclear":false,"comment_unclear":false,"comment":"","family":""}},"vehicle":{"35":[{"brand_info":"2967.240 к. с","sum_rent_comment":"","brand_info_unclear":false,"year":"2012","brand_info_hidden":false,"sum_rent_comment_unclear":false,"sum_rent":"","sum":"","brand":"Volkswagen Touareg","sum_comment":"","brand_unclear":false,"brand_hidden":false}]},"id":"vulyk_100_118","declaration":{"additional_info_text":"","notfull_lostpages":"","date":"2015-03-19T00:00:00","notfull":"","additional_info":"","url":"http://static.declarations.com.ua/declarations/chosen_ones/judges_batch/4322_dzhulai_oleksandr_borysovych.pdf"},"liabilities":{"54":{"sum_foreign_comment":"","sum":"","sum_comment":"","sum_comment_hidden":false,"sum_unclear":false,"sum_foreign":""},"55":{"sum_foreign_comment":"","sum":"","sum_comment":"","sum_foreign":""},"56":{"sum_foreign_comment":"","sum":"","sum_comment":"","sum_unclear":false,"sum_foreign":""},"57":{"sum_foreign_comment":"","sum":"","sum_comment":"","sum_comment_unclear":false,"sum_comment_hidden":false,"sum_unclear":false,"sum_foreign":""},"58":{"sum_foreign_comment":"","sum":"","sum_comment":"","sum_comment_hidden":false,"sum_unclear":false,"sum_foreign":""},"59":{"sum_foreign_comment":"","sum":"","sum_comment":"","sum_foreign":""},"60":{"sum_foreign_comment":"","sum_comment_hidden":false,"sum":"","sum_comment":"","sum_foreign":""},"61":{"sum_foreign_comment":"","sum":"","sum_comment":"","sum_foreign":""},"62":{"sum_foreign_comment":"","sum":"","sum_comment":"","sum_unclear":false,"sum_foreign":""},"63":{"sum_foreign_comment":"","sum_comment_hidden":false,"sum":"","sum_comment":"","sum_foreign":""},"64":{"sum_foreign_comment":"","sum_comment_hidden":false,"sum":"","sum_comment":"","sum_foreign":""}},"ft_src":"Борисович\nДжулай Олександр Борисович\nсуддя апеляційного суду одеської області\nОдеська область\nЗагальний апеляційний суд\nОлександр\nДжулай Олександр Борисович\nОлександр Борисович Джулай\nОлександр Джулай\nДжулай Олександр Борисович\nДжулай\n2967.240 к. с\nVolkswagen Touareg\n2012\n600\n528\n2014\n278946.22\nНаціональна школа суддів України\n4225.1\n283171.32\n2967.240 к. с\nVolkswagen Touareg\n2012\n600\n528\nЗагальний апеляційний суд\nОдеська область\nсуддя апеляційного суду одеської області\nБорисович\nДжулай Олександр Борисович\nОлександр Борисович Джулай\nОлександр Джулай\nДжулай Олександр Борисович\nДжулай Олександр Борисович\nОлександр\nДжулай\n4225.1\nНаціональна школа суддів України\n278946.22\n283171.32\n2014\nБорисович\nДжулай\nОдеська область\nЗагальний апеляційний суд\nсуддя апеляційного суду одеської області\nДжулай Олександр Борисович\nДжулай Олександр Борисович\nОлександр Борисович Джулай\nОлександр Джулай\nДжулай Олександр Борисович\nОлександр\n2012\nVolkswagen Touareg\n2967.240 к. с\n283171.32\n4225.1\nНаціональна школа суддів України\n278946.22\n600\n528\n2014","general":{"inn":"","inn_hidden":true,"last_name":"Джулай","post":{"post_unclear":false,"region_unclear":false,"post":"суддя апеляційного суду одеської області","office":"Загальний апеляційний суд","region":"Одеська область","post_hidden":false,"office_unclear":false},"name":"Олександр","full_name":"Джулай Олександр Борисович","family_raw":"","addresses":[{"place_district":"","place_city_hidden":true,"place_city":"","place_city_unclear":false,"place_district_hidden":false,"place_city_type":"","place_address_hidden":true,"place_city_type_hidden":false,"place_address":"","place_hidden":true,"place":""}],"full_name_suggest":{"output":"Джулай Олександр Борисович","input":["Джулай Олександр Борисович","Олександр Борисович Джулай","Олександр Джулай"]},"patronymic":"Борисович"},"source":"VULYK","estate":{"23":[{"space_unclear":false,"costs":"","costs_comment":"","address_hidden":false,"region_hidden":true,"space_comment":"","space":"600","address":"","costs_comment_unclear":false,"region":"","address_unclear":false,"costs_rent_comment":"","space_comment_unclear":false,"space_units":"м²","costs_rent":""}],"24":[{"space_unclear":false,"costs":"","costs_comment":"","address_hidden":false,"region_hidden":true,"space_comment":"","space":"528","address":"","region":"","costs_rent_comment":"","space_comment_unclear":false,"space_units":"м²","costs_rent":""}]},"intro":{"declaration_year":"2014"}}