{"id":"vulyk_88_99","ft_src":"Nissan Teana\n2008\n2496 куб. см.\n246 куб. см., 11 кВт , 400 см\n2013\nКолібрі КМ 400\n2008\nSkoda Fabia\n1390 куб. см.\n27\n26\n22\n92\n72300\n2014\n2496 куб. см.\nNissan Teana\n2008\n246 куб. см., 11 кВт , 400 см\n2013\nКолібрі КМ 400\n1390 куб. см.\n2008\nSkoda Fabia\n26\n22\n27\n92\nГеращенко Ігор Володимирович\nІгор Володимирович Геращенко\nІгор Геращенко\nГеращенко Ігор Володимирович\nІгор\nПодружжя\nГеращенко І. В\nДитина\nГеращенко Р. І\nГеращенко Ігор Володимирович\nГеращенко\nАпеляційний адміністративний суд\nзаступник голови донецького апеляційного адміністративного суду\nДонецька область\nВолодимирович\n734.8\n248517.16\n500.93\n24433.27\n249962.89\n27733.32\n3300.05\n210\n72300\n2014\n248517.16\n3300.05\n210\n734.8\n27733.32\n249962.89\n500.93\n24433.27\nГеращенко І. В\nПодружжя\nГеращенко Р. І\nДитина\nВолодимирович\nГеращенко\nІгор\nГеращенко Ігор Володимирович\nІгор Володимирович Геращенко\nІгор Геращенко\nГеращенко Ігор Володимирович\nДонецька область\nАпеляційний адміністративний суд\nзаступник голови донецького апеляційного адміністративного суду\nГеращенко Ігор Володимирович","estate":{"25":[{"address":"","space_units":"м²","space_hidden":false,"space_unclear":false,"region_hidden":true,"costs_rent_comment":"","space_comment":"","address_hidden":false,"costs":"","address_unclear":false,"space_comment_unclear":false,"costs_comment":"","space":"92","region":"","costs_rent":""}],"27":[{"address":"","space_units":"м²","space_hidden":false,"space_comment":"","region_hidden":true,"costs_comment":"","address_hidden":false,"space":"26","space_comment_unclear":false,"costs_rent_comment":"","costs":"","region":"","costs_rent":""},{"costs":"","address":"","space_units":"м²","costs_rent_comment":"","space":"22","space_comment":"","costs_comment":"","region":"","costs_rent":""}],"31":[{"costs_property_comment":"","address":"","space_units":"м²","space_unclear":false,"region_hidden":true,"costs_property":"","space_comment":"","address_hidden":true,"costs_rent_comment":"","space":"27","region":"","costs_rent":""}]},"vehicle":{"35":[{"sum_comment_unclear":false,"sum_comment":"","brand_info":"2496 куб. см.","sum":"","brand_unclear":false,"year":"2008","brand":"Nissan Teana","sum_rent":"","sum_rent_comment":"","brand_hidden":false}],"37":[{"sum_comment":"","brand_info":"246 куб. см., 11 кВт , 400 см","sum":"","sum_rent_comment":"","year":"2013","brand":"Колібрі КМ 400","sum_rent":""}],"40":[{"sum_comment":"","brand_info_hidden":false,"brand_info":"1390 куб. см.","sum":"","sum_rent_comment":"","brand_hidden":false,"brand":"Skoda Fabia","sum_rent":"","year":"2008"}]},"source":"VULYK","income":{"5":{"family_comment":"","family":"27733.32","comment":"","value_unclear":false,"family_unclear":false,"value":"249962.89"},"6":{"family_comment":"","family":"","comment":"","value_unclear":false,"family_unclear":false,"value":"248517.16"},"7":{"family":"","family_comment":"","value":"734.8","comment":"","source_name":""},"8":{"family_comment":"","value":"","family":"","comment":""},"9":{"family_comment":"","value":"","family":"3300.05","comment":"","family_comment_unclear":false},"10":{"family_comment":"","value":"","family":"","comment":""},"11":{"family_comment":"","value":"210","family":"","comment":""},"12":{"family_comment":"","value":"","family":"24433.27","comment":""},"13":{"family_comment":"","value":"","family":"","comment":""},"14":{"family_comment":"","value":"","family":"","comment":""},"15":{"family_comment":"","value":"","family":"","comment":""},"16":{"family_comment":"","value":"","family_unclear":false,"family":"","comment":""},"17":{"family_comment":"","value":"","family_unclear":false,"family":"","comment":""},"18":{"family_comment":"","value":"","family":"","comment":""},"19":{"family_comment":"","value":"","family":"","comment":""},"20":{"family_comment":"","value":"500.93","family":"","comment":""}},"banks":{"51":[{"sum_units":"UAH","sum_comment":"","sum_foreign_units":"UAH","sum_hidden":false,"sum":"72300","sum_foreign_comment":"","sum_foreign":"","sum_comment_hidden":false}]},"declaration":{"notfull_lostpages":"","additional_info_text":"","additional_info":"","date":"2015-03-25T00:00:00","notfull":"","url":"http://static.declarations.com.ua/declarations/chosen_ones/judges_batch/3002_herashchenko_ihor_volodymyrovych.pdf"},"general":{"family":[{"inn":"","family_name":"Геращенко І. В","name_unclear":false,"inn_hidden":false,"name_hidden":false,"relations":"Подружжя"},{"inn":"","family_name":"Геращенко Р. І","relations_other":"","name_unclear":false,"inn_hidden":false,"name_hidden":false,"relations":"Дитина"}],"family_raw":"","name":"Ігор","full_name_suggest":{"input":["Геращенко Ігор Володимирович","Ігор Володимирович Геращенко","Ігор Геращенко"],"output":"Геращенко Ігор Володимирович"},"patronymic":"Володимирович","inn_hidden":true,"patronymic_unclear":false,"patronymic_hidden":false,"inn":"","addresses":[{"place_city_type_hidden":false,"place_city_type":"","place_city_hidden":false,"place_hidden":true,"place_district":"","place_district_hidden":false,"place":"","place_address":"","place_address_hidden":false,"place_city":""}],"last_name":"Геращенко","full_name":"Геращенко Ігор Володимирович","post":{"office":"Апеляційний адміністративний суд","post":"заступник голови донецького апеляційного адміністративного суду","candidate":"","region_hidden":false,"region":"Донецька область","office_hidden":false},"last_name_unclear":false},"liabilities":{"54":{"sum_comment":"","sum_comment_unclear":false,"sum_foreign_comment":"","sum":"","sum_foreign":""},"55":{"sum_comment":"","sum_foreign_comment":"","sum_foreign":"","sum":""},"56":{"sum_comment":"","sum_foreign_comment":"","sum_foreign":"","sum":""},"57":{"sum_comment":"","sum_hidden":false,"sum":"","sum_foreign_comment":"","sum_foreign":"","sum_unclear":false,"sum_comment_hidden":false},"58":{"sum_comment":"","sum_hidden":false,"sum":"","sum_foreign_comment":"","sum_foreign":"","sum_comment_hidden":false},"59":{"sum_comment":"","sum_foreign_comment":"","sum_foreign":"","sum":""},"60":{"sum_comment_unclear":false,"sum_comment":"","sum_hidden":false,"sum":"","sum_foreign_comment":"","sum_foreign":"","sum_comment_hidden":false},"61":{"sum_comment":"","sum_foreign_comment":"","sum_foreign":"","sum":""},"62":{"sum_comment":"","sum_foreign_comment":"","sum_foreign":"","sum":""},"63":{"sum_comment":"","sum_foreign_comment":"","sum_foreign":"","sum":""},"64":{"sum_comment":"","sum_foreign_comment":"","sum_foreign":"","sum":""}},"intro":{"isnotdeclaration":"","declaration_year":"2014"}}