{"id":"vulyk_103_89","ft_src":"Mercedes-Benz\nв користуванні\n2987\n2011\nу користуванні\n3499 куб. см.\nMercedes-Benz ML-Class\n2011\n1500\n108\n500000\n96\n1617375\n500000\n2015\n2987\nв користуванні\n2011\nMercedes-Benz\n3499 куб. см.\nу користуванні\n2011\nMercedes-Benz ML-Class\n1500\n108\nСахно\nСахно Роман Іванович\nРоман Іванович Сахно\nРоман Сахно\nСахно Роман Іванович\nСахно Роман Іванович\nІванович\nПодружжя\nСахно Людмила Миколаївна\nРоман\nВищий спеціалізований суд з розгляду цивільних і кримінальних справ\nсуддя вищого спецiалiзованого суду україни з розгляду цивiльних і кримiнальних справ\nЗагальнодержавний регіон\n310245\n121615\n18127\n4\n399514\n121619\n71142\n1617375\n500000\n96\n500000\n2015\n121615\n310245\n71142\n121619\n399514\n4\n18127\nПодружжя\nСахно Людмила Миколаївна\nСахно\nІванович\nсуддя вищого спецiалiзованого суду україни з розгляду цивiльних і кримiнальних справ\nВищий спеціалізований суд з розгляду цивільних і кримінальних справ\nЗагальнодержавний регіон\nСахно Роман Іванович\nСахно Роман Іванович\nРоман Іванович Сахно\nРоман Сахно\nСахно Роман Іванович\nРоман","estate":{"23":[{"costs":"","address":"","space_units":"м²","costs_rent_comment":"","space":"1500","space_comment":"","region_hidden":true,"costs_comment":"","region":"","address_hidden":true,"costs_rent":""}],"25":[{"address":"","space_units":"м²","costs_comment":"","region_hidden":true,"space_comment":"","address_hidden":true,"space_comment_hidden":false,"space":"108","space_comment_unclear":false,"costs_rent_comment":"","costs":"","region":"","costs_rent":""}]},"vehicle":{"35":[{"sum_comment":"","brand_info_hidden":false,"brand_info":"2987","sum":"","brand_unclear":false,"brand_hidden":false,"brand":"Mercedes-Benz","sum_rent":"","brand_info_unclear":false,"sum_rent_comment":"в користуванні","year":"2011"}],"40":[{"year_hidden":false,"brand_info":"3499 куб. см.","sum":"","sum_rent_comment":"у користуванні","brand_hidden":false,"brand":"Mercedes-Benz ML-Class","sum_rent":"","sum_comment":"","year":"2011","brand_info_unclear":false}]},"source":"VULYK","income":{"5":{"family_comment":"","family":"121619","comment":"","value_unclear":false,"family_hidden":false,"value":"399514"},"6":{"family_comment":"","value":"310245","family":"121615","comment":""},"7":{"family":"","family_comment":"","value":"","comment":"","source_name":""},"8":{"family_comment":"","value":"","family":"","comment":""},"9":{"family_comment":"","value":"71142","family":"","comment":""},"10":{"family_comment":"","value":"","family":"","comment":""},"11":{"family_comment":"","family_hidden":false,"value":"","family":"","comment":""},"12":{"family_comment":"","value":"","family":"","comment":""},"13":{"family_comment":"","value":"","family":"","comment":""},"14":{"family_comment":"","value":"","family":"","comment":""},"15":{"family_comment":"","value":"","family":"","comment":""},"16":{"family_comment":"","value":"","family":"","comment":""},"17":{"family_comment":"","value":"","family":"","comment":"","family_comment_unclear":false},"18":{"family_comment":"","value":"","family":"","comment":""},"19":{"family_comment":"","value":"","family":"","comment":""},"20":{"family_comment":"","family":"4","comment":"","family_unclear":false,"family_hidden":false,"value":"18127"}},"banks":{"45":[{"sum_units":"UAH","sum_comment":"","sum_foreign_units":"UAH","sum_hidden":false,"sum":"1617375","sum_foreign_comment":"","sum_foreign":"","sum_unclear":false,"sum_comment_hidden":true},{"sum_units":"UAH","sum_comment":"","sum":"500000","sum_foreign_comment":"","sum_foreign":"","sum_comment_hidden":false}],"46":[{"sum_units":"UAH","sum_comment":"","sum_foreign_units":"UAH","sum_hidden":false,"sum":"500000","sum_foreign_comment":"","sum_foreign":"","sum_comment_hidden":true}],"51":[{"sum_units":"UAH","sum_comment":"","sum_foreign_units":"UAH","sum_hidden":false,"sum":"96","sum_foreign_comment_hidden":false,"sum_foreign_comment":"","sum_foreign":"","sum_foreign_hidden":false,"sum_comment_hidden":true}]},"declaration":{"additional_info_text":"","additional_info":"","date":"2016-03-28T00:00:00","url":"http://static.declarations.com.ua/declarations/chosen_ones/judges_batch/1313_sakhno_roman_ivanovych.pdf"},"general":{"inn":"","addresses":[{"place_city_type_hidden":true,"place_city_type":"","place_city_hidden":true,"place_hidden":true,"place_district":"","place_district_hidden":true,"place":"","place_city":"","place_address_hidden":true,"place_address":""}],"last_name":"Сахно","full_name":"Сахно Роман Іванович","family":[{"inn":"","family_name":"Сахно Людмила Миколаївна","relations_hidden":false,"name_unclear":false,"relations":"Подружжя","inn_hidden":true,"name_hidden":true,"relations_other":""}],"patronymic":"Іванович","inn_hidden":true,"name":"Роман","post":{"office":"Вищий спеціалізований суд з розгляду цивільних і кримінальних справ","region_unclear":false,"post":"суддя вищого спецiалiзованого суду україни з розгляду цивiльних і кримiнальних справ","region":"Загальнодержавний регіон","office_unclear":false},"family_raw":"","full_name_suggest":{"input":["Сахно Роман Іванович","Роман Іванович Сахно","Роман Сахно"],"output":"Сахно Роман Іванович"}},"liabilities":{"54":{"sum_foreign_comment_hidden":false,"sum_foreign_comment_unclear":false,"sum_hidden":false,"sum":"","sum_foreign_comment":"","sum_comment":"","sum_unclear":false,"sum_foreign":"","sum_comment_hidden":false,"sum_foreign_hidden":false},"55":{"sum_comment":"","sum_foreign_comment":"","sum_foreign":"","sum":""},"56":{"sum_comment":"","sum_foreign_comment":"","sum_foreign":"","sum":""},"57":{"sum_comment":"","sum_hidden":false,"sum":"","sum_foreign_comment":"","sum_foreign":"","sum_comment_hidden":false,"sum_foreign_hidden":false,"sum_foreign_comment_hidden":false},"58":{"sum_comment":"","sum_hidden":false,"sum":"","sum_foreign_comment":"","sum_foreign":"","sum_comment_hidden":false,"sum_foreign_hidden":false,"sum_foreign_comment_hidden":false},"59":{"sum_comment":"","sum_hidden":false,"sum":"","sum_foreign_comment":"","sum_foreign":"","sum_comment_hidden":false,"sum_foreign_hidden":false,"sum_foreign_comment_hidden":false},"60":{"sum_comment":"","sum_hidden":false,"sum":"","sum_foreign_comment":"","sum_foreign":"","sum_comment_hidden":false},"61":{"sum_comment":"","sum_foreign_comment":"","sum_foreign":"","sum":""},"62":{"sum_comment":"","sum_foreign_comment":"","sum_foreign":"","sum":"","sum_comment_hidden":false},"63":{"sum_comment":"","sum_foreign_comment":"","sum_foreign":"","sum":""},"64":{"sum_comment":"","sum_foreign_comment":"","sum_foreign":"","sum":""}},"intro":{"declaration_year":"2015"}}