{"income":{"5":{"value":"179860","family_hidden":false,"value_hidden":false,"family_comment":"","family":"29473","comment":""},"6":{"family_comment":"","value":"179860","family":"29473","comment":""},"7":{"family_comment":"","value":"","source_name":"","family":"","comment":""},"8":{"family_comment":"","value":"","family":"","comment":""},"9":{"family_comment":"","value":"","family":"","comment":""},"10":{"family_comment":"","value":"","family":"","comment":""},"11":{"family_comment":"","value":"","family":"","comment":""},"12":{"family_comment":"","value":"","family":"","comment":""},"13":{"family_comment":"","value":"","family":"","comment":""},"14":{"family_comment":"","value":"","family":"","comment":""},"15":{"family_comment":"","value":"","family":"","comment":""},"16":{"family_comment":"","value":"","family":"","comment":""},"17":{"family_comment":"","value":"","family":"","comment":""},"18":{"family_comment":"","value":"","family":"","comment":""},"19":{"family_comment":"","value":"","family":"","comment":""},"20":{"family_comment":"","value":"","family":"","comment":""}},"vehicle":{"35":[{"brand_info":"1787 куб. см.","sum":"","brand":"Volkswagen Golf","sum_comment":"","year":"1996","sum_rent_comment":"","sum_rent":""}]},"id":"vulyk_89_22","declaration":{"date":"2015-03-26T00:00:00","notfull":"","notfull_lostpages":"","url":"http://static.declarations.com.ua/declarations/chosen_ones/judges_batch/3025_kalyniuk_oleksandr_petrovych.pdf"},"liabilities":{"54":{"sum_foreign_comment":"","sum":"","sum_comment":"","sum_foreign":""},"55":{"sum_foreign_comment":"","sum":"","sum_comment":"","sum_foreign":""},"56":{"sum_foreign_comment":"","sum":"","sum_comment":"","sum_unclear":false,"sum_foreign":""},"57":{"sum_foreign_comment":"","sum":"","sum_comment":"","sum_foreign":""},"58":{"sum_foreign_comment":"","sum":"","sum_comment":"","sum_foreign":""},"59":{"sum_foreign_comment":"","sum":"","sum_comment":"","sum_foreign":""},"60":{"sum_foreign_comment":"","sum":"","sum_comment":"","sum_foreign":""},"61":{"sum_foreign_comment":"","sum":"","sum_comment":"","sum_foreign":""},"62":{"sum_foreign_comment":"","sum":"","sum_comment":"","sum_unclear":false,"sum_foreign":""},"63":{"sum_foreign_comment":"","sum":"","sum_comment":"","sum_foreign":""},"64":{"sum_foreign_comment":"","sum":"","sum_comment":"","sum_foreign":""}},"ft_src":"1787 куб. см.\n1996\nVolkswagen Golf\n2014\n29473\n179860\n29473\n179860\n1787 куб. см.\nVolkswagen Golf\n1996\n179860\n29473\n179860\n29473\nПетрович\nКалинюк О. Д., 21. 02. 1986\nПодружжя\nДитина\nКалинюк М. О., 30. 12. 2008\nКалинюк Олександр Петрович\nОлександр Петрович Калинюк\nОлександр Калинюк\nКалинюк Олександр Петрович\nКалинюк Олександр Петрович\n78500,\nІвано-Франківська область\nЯремче\nОлександр\nКалинюк\nІвано-Франківська область\nсуддя коломийського міськрайонного суду івано-франківської області\nЗагальний місцевий суд\n2014\nКалинюк О. Д., 21. 02. 1986\nПодружжя\nКалинюк М. О., 30. 12. 2008\nДитина\nІвано-Франківська область\nЯремче\n78500,\nПетрович\nКалинюк\nсуддя коломийського міськрайонного суду івано-франківської області\nІвано-Франківська область\nЗагальний місцевий суд\nКалинюк Олександр Петрович\nКалинюк Олександр Петрович\nОлександр Петрович Калинюк\nОлександр Калинюк\nКалинюк Олександр Петрович\nОлександр","general":{"inn":"","inn_hidden":true,"last_name":"Калинюк","post":{"office":"Загальний місцевий суд","region":"Івано-Франківська область","post":"суддя коломийського міськрайонного суду івано-франківської області"},"name":"Олександр","full_name":"Калинюк Олександр Петрович","family_raw":"","addresses":[{"place_district":"","place_address_hidden":true,"place_city":"Яремче","place_address":"78500,","place_district_hidden":false,"place_city_type":"Місто","place_city_hidden":false,"place_city_type_hidden":false,"place_hidden":false,"place":"Івано-Франківська область"}],"family":[{"inn":"","inn_hidden":true,"relations":"Подружжя","family_name":"Калинюк О. Д., 21. 02. 1986","name_hidden":false},{"inn":"","inn_hidden":false,"family_name":"Калинюк М. О., 30. 12. 2008","relations_other":"","relations":"Дитина","name_hidden":false,"name_unclear":false}],"full_name_suggest":{"output":"Калинюк Олександр Петрович","input":["Калинюк Олександр Петрович","Олександр Петрович Калинюк","Олександр Калинюк"]},"patronymic":"Петрович"},"source":"VULYK","intro":{"declaration_year":"2014"}}