{"income":{"5":{"family_comment":"","value":"185187","family":"87456","comment":""},"6":{"value":"185006","family_comment":"","value_unclear":false,"comment_hidden":false,"family_unclear":false,"family":"87456","comment":""},"7":{"family_comment":"","value":"","source_name":"","family":"","comment":""},"8":{"family_comment":"","value":"","family":"","comment":""},"9":{"family_comment":"","family_unclear":false,"value":"181","family":"","comment":""},"10":{"family_comment":"","value":"","value_unclear":false,"family":"","comment":""},"11":{"family_comment":"","value":"","family":"","comment":""},"12":{"family_comment":"","value":"","family":"","comment":""},"13":{"family_comment":"","value":"","family":"","comment":""},"14":{"family_comment":"","value":"","family":"","comment":""},"15":{"family_comment":"","value":"","family":"","comment":""},"16":{"family_comment":"","value":"","family":"","comment":""},"17":{"family_comment":"","value":"","family":"","comment":""},"18":{"family_comment":"","value":"","family":"","comment":""},"19":{"family_comment":"","value":"","family":"","comment":""},"20":{"value":"","family":"","value_unclear":false,"family_hidden":false,"family_comment":"","comment_unclear":false,"comment":"","family_comment_unclear":false}},"vehicle":{"35":[{"year_hidden":false,"brand_info":"2498, 178, 459.5","sum_rent_comment":"","year":"2014","brand_info_hidden":false,"brand_info_unclear":false,"sum_rent":"","sum":"301300","brand":"Subaru Forester","sum_comment":"","brand_unclear":false,"brand_hidden":false}]},"id":"vulyk_97_85","banks":{"45":[{"sum_foreign_comment":"","sum_units":"UAH","sum_comment":"","sum_comment_unclear":false,"sum_hidden":false,"sum_foreign_units":"UAH","sum_comment_hidden":false,"sum_unclear":false,"sum":"29501","sum_foreign":""}],"46":[{"sum_foreign_comment":"","sum_units":"UAH","sum_comment":"","sum_foreign_units":"UAH","sum_comment_hidden":false,"sum":"29501","sum_foreign":""}]},"declaration":{"additional_info_text":"","notfull_lostpages":"","date":"2015-03-30T00:00:00","notfull":"","additional_info":"","url":"http://static.declarations.com.ua/declarations/chosen_ones/judges_batch/3986_moroko_anastasiia_serhiivna.pdf"},"liabilities":{"54":{"sum_foreign_comment":"","sum":"","sum_comment":"","sum_comment_unclear":false,"sum_hidden":false,"sum_comment_hidden":false,"sum_unclear":false,"sum_foreign":""},"55":{"sum_foreign_comment":"","sum":"","sum_comment":"","sum_foreign":""},"56":{"sum_foreign_comment":"","sum":"","sum_comment":"","sum_foreign":""},"57":{"sum_foreign_comment":"","sum":"","sum_comment":"","sum_comment_unclear":false,"sum_hidden":false,"sum_comment_hidden":false,"sum_unclear":false,"sum_foreign":""},"58":{"sum_foreign_comment":"","sum":"","sum_comment":"","sum_comment_unclear":false,"sum_hidden":false,"sum_comment_hidden":false,"sum_unclear":false,"sum_foreign":""},"59":{"sum_foreign_comment":"","sum":"","sum_comment":"","sum_foreign":""},"60":{"sum_foreign_comment":"","sum":"","sum_comment":"","sum_comment_unclear":false,"sum_hidden":false,"sum_comment_hidden":false,"sum_foreign":""},"61":{"sum_foreign_comment":"","sum":"","sum_comment":"","sum_foreign":""},"62":{"sum_foreign_comment":"","sum":"","sum_comment":"","sum_unclear":false,"sum_foreign":""},"63":{"sum_foreign_comment":"","sum":"","sum_hidden":false,"sum_comment":"","sum_foreign":""},"64":{"sum_foreign_comment":"","sum":"","sum_comment":"","sum_foreign":""}},"ft_src":"Харків\n61002\nХарківська область\nсуддя харківського окружного адміністративного суду\nХарківська область\nАдміністративний місцевий суд\nАнастасія\nМороко О. О\nПодружжя\nСергіївна\nМороко Анастасія Сергіївна\nАнастасія Сергіївна Мороко\nАнастасія Мороко\nМороко Анастасія Сергіївна\nМороко Анастасія Сергіївна\nМороко\n181\n87456\n185187\n185006\n87456\n2014\nSubaru Forester\n301300\n2498, 178, 459.5\n2498, 178, 459.5\nSubaru Forester\n2014\n301300\n29501\n29501\n2014\n2498, 178, 459.5\nSubaru Forester\n2014\n301300\n2014\nМороко Анастасія Сергіївна\nАнастасія Сергіївна Мороко\nАнастасія Мороко\nМороко Анастасія Сергіївна\nАнастасія\nПодружжя\nМороко О. О\nМороко Анастасія Сергіївна\nМороко\nАдміністративний місцевий суд\nХарківська область\nсуддя харківського окружного адміністративного суду\nСергіївна\nХарківська область\n61002\nХарків\n185006\n87456\n185187\n87456\n181\n29501\n29501\n87456\n185006\n181\n87456\n185187\nПодружжя\nМороко О. О\nСергіївна\nМороко\nАнастасія\nМороко Анастасія Сергіївна\nАнастасія Сергіївна Мороко\nАнастасія Мороко\nМороко Анастасія Сергіївна\n61002\nХарків\nХарківська область\nХарківська область\nАдміністративний місцевий суд\nсуддя харківського окружного адміністративного суду\nМороко Анастасія Сергіївна\n29501\n29501\n2014","general":{"name_hidden":false,"name":"Анастасія","last_name_hidden":false,"inn":"","family":[{"inn":"","relations":"Подружжя","relations_other":"","inn_hidden":true,"family_name":"Мороко О. О","name_hidden":true,"name_unclear":false}],"patronymic":"Сергіївна","inn_hidden":true,"family_raw":"","inn_unclear":false,"post":{"region_unclear":false,"region":"Харківська область","post":"суддя харківського окружного адміністративного суду","office":"Адміністративний місцевий суд","office_unclear":false,"post_hidden":false},"full_name":"Мороко Анастасія Сергіївна","addresses":[{"place_district":"","place_city_hidden":false,"place_city":"Харків","place_city_unclear":false,"place_district_hidden":false,"place_city_type":"Місто","place_address_hidden":true,"place_city_type_hidden":false,"place_address":"61002","place_hidden":false,"place":"Харківська область"}],"last_name":"Мороко","patronymic_hidden":false,"full_name_suggest":{"output":"Мороко Анастасія Сергіївна","input":["Мороко Анастасія Сергіївна","Анастасія Сергіївна Мороко","Анастасія Мороко"]}},"source":"VULYK","intro":{"declaration_year":"2014","isnotdeclaration":""}}