{"income":{"5":{"family_comment":"","value":"256198.93","family_hidden":false,"comment":"","family":"38000"},"6":{"value":"256145.93","value_unclear":false,"family_hidden":false,"family_comment":"","family":"38000","comment":""},"7":{"family_comment":"","value":"","source_name":"","family":"","comment":""},"8":{"family_comment":"","value":"","family":"","comment":""},"9":{"family_comment":"","value":"53","value_unclear":false,"family":"","comment":""},"10":{"family_comment":"","value":"","value_unclear":false,"family":"","comment":""},"11":{"family_comment":"","value":"","family":"","comment":""},"12":{"family_comment":"","value":"","family":"","comment":""},"13":{"family_comment":"","value":"","family":"","comment":""},"14":{"family_comment":"","value":"","family":"","comment":""},"15":{"family_comment":"","value":"","family":"","comment":""},"16":{"family_comment":"","value":"","family":"","comment":"","family_comment_hidden":false},"17":{"family_comment":"","value":"","family_hidden":false,"comment":"","family":""},"18":{"family_comment":"","value":"","family":"","comment":""},"19":{"family_comment":"","value":"","family":"","comment":""},"20":{"value":"","value_unclear":false,"family_comment_hidden":false,"family_comment":"","comment_unclear":false,"comment":"","family":""}},"vehicle":{"35":[{"year_hidden":false,"brand_info":"2378 куб. см.","sum_rent_comment":"","year":"2008","brand_info_hidden":false,"brand_info_unclear":false,"year_unclear":false,"sum_rent":"","sum":"","brand":"Mitsubishi Outlander","sum_comment":"","brand_unclear":false,"brand_hidden":false,"sum_unclear":false}]},"id":"vulyk_42_131","banks":{"45":[{"sum_foreign_comment":"","sum_units":"UAH","sum_comment":"","sum_foreign_comment_hidden":false,"sum_hidden":false,"sum_foreign_units":"UAH","sum_foreign_hidden":false,"sum_comment_hidden":false,"sum_unclear":false,"sum":"","sum_foreign":""},{"sum_foreign_comment":"","sum_units":"","sum_comment":"","sum_foreign_units":"","sum":"","sum_foreign":""}],"46":[{"sum_foreign_comment":"","sum_units":"UAH","sum_comment":"","sum_hidden":false,"sum_foreign_units":"UAH","sum_comment_hidden":false,"sum_unclear":false,"sum":"","sum_foreign":""}],"47":[{"sum_foreign_comment":"","sum_units":"UAH","sum_comment":"","sum_comment_unclear":false,"sum_hidden":false,"sum_foreign_units":"UAH","sum":"","sum_foreign":""},{"sum_foreign_comment":"","sum":"","sum_comment":"","sum_foreign":""}],"48":[{"sum_foreign_comment":"","sum_units":"UAH","sum_comment":"","sum_foreign_units":"UAH","sum":"","sum_foreign":""}],"49":[{"sum_foreign_comment":"","sum_units":"UAH","sum_comment":"","sum_foreign_units":"UAH","sum":"","sum_foreign":""}],"50":[{"sum_foreign_comment":"","sum_units":"UAH","sum_comment":"","sum_foreign_units":"UAH","sum":"","sum_foreign":""}],"51":[{"sum_foreign_comment":"","sum_units":"UAH","sum_comment":"","sum_comment_unclear":false,"sum_hidden":false,"sum_foreign_units":"UAH","sum_comment_hidden":false,"sum":"","sum_foreign":""},{"sum_foreign_comment":"","sum_units":"","sum_comment":"","sum_hidden":false,"sum_foreign_units":"","sum":"","sum_units_hidden":false,"sum_foreign":""}],"52":[{"sum_foreign_comment":"","sum_units":"UAH","sum_comment":"","sum_comment_unclear":false,"sum_hidden":false,"sum_foreign_units":"UAH","sum":"","sum_units_hidden":false,"sum_foreign":""}],"53":[{"sum_foreign_comment":"","sum_units":"UAH","sum_comment":"","sum_foreign_units":"UAH","sum":"","sum_foreign":""}]},"declaration":{"additional_info_text":"","notfull_lostpages":"","date":"2015-03-23T00:00:00","notfull":"","additional_info":"","url":"http://static.declarations.com.ua/declarations/chosen_ones/mega_batch/fanda_volodymyr_petrovych.pdf"},"liabilities":{"54":{"sum_foreign_comment":"","sum":"","sum_comment":"","sum_foreign_comment_hidden":false,"sum_comment_hidden":false,"sum_foreign":""},"55":{"sum_foreign_comment":"","sum":"","sum_comment":"","sum_foreign":""},"56":{"sum_foreign_comment":"","sum":"","sum_comment":"","sum_foreign":""},"57":{"sum_foreign_comment":"","sum":"","sum_comment":"","sum_comment_unclear":false,"sum_comment_hidden":false,"sum_unclear":false,"sum_foreign":""},"58":{"sum_foreign_comment":"","sum":"","sum_comment":"","sum_foreign_unclear":false,"sum_comment_hidden":false,"sum_unclear":false,"sum_foreign":""},"59":{"sum_foreign_comment":"","sum":"","sum_comment":"","sum_foreign":""},"60":{"sum_foreign_comment":"","sum":"","sum_comment":"","sum_comment_unclear":false,"sum_hidden":false,"sum_comment_hidden":false,"sum_foreign":""},"61":{"sum_foreign_comment":"","sum":"","sum_comment":"","sum_foreign":""},"62":{"sum_foreign_comment":"","sum":"","sum_comment":"","sum_hidden":false,"sum_comment_hidden":false,"sum_foreign":""},"63":{"sum_foreign_comment":"","sum":"","sum_comment":"","sum_comment_hidden":false,"sum_unclear":false,"sum_foreign":""},"64":{"sum_foreign_comment":"","sum":"","sum_comment":"","sum_hidden":false,"sum_comment_hidden":false,"sum_foreign":""}},"ft_src":"Хмельницький\nХмельницька область\nсуддя апеляційного суду хмельницької області\nХмельницька область\nЗагальний апеляційний суд\nВолодимир\nПіхурець І. В. 21. 07. 1987\nДитина\nПіхурець А. П. 11. 06. 1986\nІнше\nзять\nПіхурець Т. А. 19. 02. 2014\nПетрович\nФанда Володимир Петрович\nВолодимир Петрович Фанда\nВолодимир Фанда\nФанда Володимир Петрович\nФанда\nФанда Володимир Петрович\n2378 куб. см.\nMitsubishi Outlander\n2008\n2014\n2378 куб. см.\nMitsubishi Outlander\n2008\n69\nХмельницький\nХмельницька область\nДитина\nПіхурець І. В. 21. 07. 1987\nІнше\nзять\nПіхурець А. П. 11. 06. 1986\nПіхурець Т. А. 19. 02. 2014\nФанда Володимир Петрович\nВолодимир Петрович Фанда\nВолодимир Фанда\nФанда Володимир Петрович\nФанда Володимир Петрович\nВолодимир\nФанда\nсуддя апеляційного суду хмельницької області\nЗагальний апеляційний суд\nХмельницька область\nПетрович\nХмельницька область\nХмельницький\n256145.93\n38000\n256198.93\n38000\n53\n2014\nХмельницький\nХмельницька область\n69\nПіхурець І. В. 21. 07. 1987\nДитина\nзять\nПіхурець А. П. 11. 06. 1986\nІнше\nПіхурець Т. А. 19. 02. 2014\nПетрович\nФанда\nВолодимир\nФанда Володимир Петрович\nВолодимир Петрович Фанда\nВолодимир Фанда\nФанда Володимир Петрович\nХмельницька область\nХмельницький\nХмельницька область\nсуддя апеляційного суду хмельницької області\nЗагальний апеляційний суд\nФанда Володимир Петрович\n38000\n256145.93\n38000\n256198.93\n53\nMitsubishi Outlander\n2378 куб. см.\n2008\n38000\n256198.93\n53\n256145.93\n38000\nХмельницький\nХмельницька область\n69\n2014","general":{"inn":"","name":"Володимир","patronymic_unclear":false,"last_name_hidden":false,"family":[{"inn":"","inn_hidden":false,"relations_hidden":false,"family_name":"Піхурець І. В. 21. 07. 1987","relations_other":"","relations":"Дитина","name_hidden":false,"name_unclear":false},{"inn":"","relations":"Інше","relations_other":"зять","inn_hidden":false,"family_name":"Піхурець А. П. 11. 06. 1986","name_hidden":false,"name_unclear":false},{"inn":"","relations":"","relations_other":"","inn_hidden":false,"family_name":"Піхурець Т. А. 19. 02. 2014","name_hidden":false,"name_unclear":false}],"patronymic":"Петрович","inn_hidden":true,"family_raw":"","last_name":"Фанда","post":{"region_unclear":false,"region":"Хмельницька область","post":"суддя апеляційного суду хмельницької області","office":"Загальний апеляційний суд","office_hidden":false,"region_hidden":false},"last_name_unclear":false,"full_name":"Фанда Володимир Петрович","addresses":[{"place_district":"","place_city_hidden":false,"place_city":"Хмельницький","place_city_type_hidden":false,"place_district_hidden":false,"place_city_type":"Місто","place_address_hidden":false,"place_address":"","place_hidden":false,"place":"Хмельницька область"}],"full_name_suggest":{"output":"Фанда Володимир Петрович","input":["Фанда Володимир Петрович","Володимир Петрович Фанда","Володимир Фанда"]}},"source":"VULYK","estate":{"23":[{"space_unclear":false,"costs":"","costs_comment":"","address_hidden":false,"region_hidden":false,"space_comment":"","space_hidden":false,"space":"","address":"","region":"","address_unclear":false,"space_units_unclear":false,"space_comment_unclear":false,"space_units":"м²","costs_rent":"","costs_rent_comment":""},{"costs":"","costs_comment":"","address_hidden":false,"region_hidden":false,"space_comment":"","space_units_unclear":false,"address":"","space":"","region":"","costs_rent_comment":"","space_units":"","costs_rent":""},{"costs_rent":"","region":"","costs":"","costs_rent_comment":"","costs_comment":"","space_comment":"","space_units":"","space":"","address":""},{"costs_rent":"","region":"","costs":"","costs_rent_comment":"","costs_comment":"","space_comment":"","space_units":"","space":"","address":""},{"costs_rent":"","region":"","costs":"","costs_rent_comment":"","costs_comment":"","space_comment":"","space_units":"","space":"","address":""},{"costs_rent":"","costs":"","costs_rent_comment":"","costs_comment":"","space_comment":"","space_units":"","space":"","address":""}],"25":[{"space_unclear":false,"costs":"","costs_comment":"","address_hidden":false,"region_hidden":false,"space_comment":"","space_hidden":false,"space":"69","address":"Хмельницький","region":"Хмельницька область","costs_rent_comment":"","space_comment_unclear":false,"space_units":"м²","costs_rent":""}]},"intro":{"declaration_year":"2014","isnotdeclaration":""}}