{"income":{"5":{"value":"180228","family_comment":"","value_unclear":false,"family_hidden":false,"value_hidden":false,"family_unclear":false,"family":"40110","comment":""},"6":{"value":"168048","family_comment":"","value_unclear":false,"family_hidden":false,"value_hidden":false,"family_unclear":false,"family":"30965","comment":""},"7":{"source_name_unclear":false,"value":"","comment_hidden":false,"family_hidden":false,"value_hidden":false,"family_comment":"","source_name":"","family":"","comment":"","source_name_hidden":false},"8":{"value":"","family_hidden":false,"value_hidden":false,"family_comment":"","family":"","comment":""},"9":{"value":"","family_hidden":false,"value_hidden":false,"family_comment":"","family":"9145","comment":""},"10":{"family_comment":"","value":"12180","family_hidden":false,"comment":"","family":""},"11":{"value":"","comment_hidden":false,"family_hidden":false,"family_comment":"","family":"","comment":""},"12":{"value":"","family_hidden":false,"value_hidden":false,"family_comment":"","family":"","comment":""},"13":{"value":"","family_hidden":false,"value_hidden":false,"family_comment":"","family":"","comment":""},"14":{"value":"","family_hidden":false,"value_hidden":false,"family_comment":"","family":"","comment":""},"15":{"family_comment":"","value":"","family_hidden":false,"comment":"","family":""},"16":{"value":"","family_hidden":false,"value_hidden":false,"family_comment":"","family":"","comment":""},"17":{"family_comment":"","value":"","family":"","comment":"","value_hidden":false},"18":{"value":"","family_hidden":false,"value_hidden":false,"family_comment":"","family":"","comment":""},"19":{"value":"","family_hidden":false,"value_hidden":false,"family_comment":"","family":"","comment":""},"20":{"value":"","comment_unclear":false,"family_hidden":false,"value_hidden":false,"family_comment":"","family":"","comment":"","family_comment_unclear":false}},"vehicle":{"35":[{"year_hidden":false,"brand_info":"1400 куб. см.","sum_rent_comment":"","sum_rent_hidden":false,"year":"2013","sum_hidden":false,"brand_info_hidden":false,"brand_info_unclear":false,"year_unclear":false,"sum_rent":"","sum_rent_unclear":false,"sum":"","brand":"Kia Rio","sum_comment":"","brand_unclear":false,"brand_hidden":false,"sum_unclear":false},{"year_hidden":false,"brand_info":"1600 куб. см.","sum_rent_comment":"","brand":"Kia Ceed","sum_comment":"","year":"2008","brand_hidden":false,"brand_info_hidden":false,"sum_hidden":false,"sum":"","sum_rent":""}],"40":[{"year_hidden":false,"brand_info":"1600 куб. см.","sum_rent_comment":"","sum_rent_hidden":false,"year":"2012","sum_hidden":false,"brand_info_hidden":false,"brand_info_unclear":false,"year_unclear":false,"sum_rent":"","sum":"","brand":"Renault Duster","sum_comment":"","brand_unclear":false,"brand_hidden":false}]},"id":"vulyk_34_6","banks":{"45":[{"sum_foreign_comment":"","sum_units":"UAH","sum_comment":"","sum_foreign_units":"UAH","sum_comment_hidden":false,"sum_unclear":false,"sum":"","sum_foreign":""},{"sum_foreign_comment":"","sum_units":"","sum_comment":"","sum_foreign_units":"","sum_comment_hidden":false,"sum":"","sum_foreign":""}],"46":[{"sum_foreign_comment":"","sum_units":"UAH","sum_comment":"","sum_foreign_units":"UAH","sum_comment_hidden":false,"sum_unclear":false,"sum":"","sum_foreign":""},{"sum_foreign_comment":"","sum_units":"","sum_comment":"","sum_foreign_units":"","sum_comment_hidden":false,"sum":"","sum_foreign":""}],"47":[{"sum_foreign_comment":"","sum_units":"UAH","sum_comment":"","sum_foreign_units":"UAH","sum":"","sum_foreign":""}],"48":[{"sum_foreign_comment":"","sum_units":"UAH","sum_comment":"","sum_foreign_units":"UAH","sum":"","sum_foreign":""}],"49":[{"sum_foreign_comment":"","sum_units":"UAH","sum_comment":"","sum_hidden":false,"sum_foreign_units":"UAH","sum":"","sum_foreign":""}],"50":[{"sum_foreign_comment":"","sum_units":"UAH","sum_comment":"","sum_hidden":false,"sum_foreign_units":"UAH","sum":"","sum_foreign":""}],"51":[{"sum_foreign_comment":"","sum_units":"UAH","sum_comment":"","sum_hidden":false,"sum_foreign_units":"UAH","sum_comment_hidden":false,"sum_unclear":false,"sum":"","sum_foreign":""},{"sum_foreign_comment":"","sum_units":"","sum_comment":"","sum_foreign_units":"","sum_comment_hidden":false,"sum":"","sum_foreign":""}],"52":[{"sum_foreign_comment":"","sum_units":"UAH","sum_comment":"","sum_foreign_units":"UAH","sum":"","sum_foreign":""}],"53":[{"sum_foreign_comment":"","sum_units":"UAH","sum_comment":"","sum_foreign_units":"UAH","sum":"","sum_foreign":""}]},"declaration":{"additional_info_text":"","notfull_lostpages":"","date":"2015-03-18T00:00:00","notfull":"","additional_info":"","url":"http://static.declarations.com.ua/declarations/chosen_ones/mega_batch/lutsiv_oleksandra_volodymyrivna.pdf"},"liabilities":{"54":{"sum_foreign_comment":"","sum_foreign_hidden":false,"sum_comment":"","sum_hidden":false,"sum_comment_hidden":false,"sum":"","sum_foreign":""},"55":{"sum_foreign_comment":"","sum_foreign_hidden":false,"sum_comment":"","sum_hidden":false,"sum":"","sum_foreign":""},"56":{"sum_foreign_comment":"","sum_foreign_hidden":false,"sum_comment":"","sum":"","sum_unclear":false,"sum_foreign":""},"57":{"sum_foreign_comment":"","sum_foreign_hidden":false,"sum_comment":"","sum_hidden":false,"sum_comment_hidden":false,"sum_unclear":false,"sum":"","sum_foreign":""},"58":{"sum_foreign_comment":"","sum_foreign_hidden":false,"sum_comment":"","sum_hidden":false,"sum_comment_hidden":false,"sum_unclear":false,"sum":"","sum_foreign":""},"59":{"sum_foreign_comment":"","sum_foreign_hidden":false,"sum_comment":"","sum_hidden":false,"sum":"","sum_foreign":""},"60":{"sum_foreign_comment":"","sum_foreign_hidden":false,"sum_comment":"","sum_hidden":false,"sum":"","sum_foreign":""},"61":{"sum_foreign_comment":"","sum_foreign_hidden":false,"sum_comment":"","sum_hidden":false,"sum":"","sum_foreign":""},"62":{"sum_foreign_comment":"","sum_foreign_hidden":false,"sum_comment":"","sum":"","sum_unclear":false,"sum_foreign":""},"63":{"sum_foreign_comment":"","sum_foreign_hidden":false,"sum_comment":"","sum_hidden":false,"sum":"","sum_unclear":false,"sum_foreign":""},"64":{"sum_foreign_comment":"","sum_foreign_hidden":false,"sum_comment":"","sum_comment_unclear":false,"sum_hidden":false,"sum_comment_hidden":false,"sum_unclear":false,"sum":"","sum_foreign":""}},"ft_src":"Новодністровськ\n60236\nЧернівецька область\nсуддя\nЧернівецька область\nЗагальний місцевий суд\nОлександра\nЛуців О. Я\nПодружжя\nЛуців В. О\nДитина\nЛуців Я. О\nДитина\nВолодимирівна\nЛуців\nЛуців Олександра Володимирівна\nЛуців Олександра Володимирівна\nОлександра Володимирівна Луців\nОлександра Луців\nЛуців Олександра Володимирівна\n1400 куб. см.\nKia Rio\n2013\n1600 куб. см.\nKia Ceed\n2008\n1600 куб. см.\nRenault Duster\n2012\n2014\n1400 куб. см.\nKia Rio\n2013\n1600 куб. см.\n2008\nKia Ceed\n1600 куб. см.\nRenault Duster\n2012\n.885\nЧернівецька область\nм. Чернівці\n.885\nм. Чернівці\nЧернівецька область\nЧернівецька область\n66.7\nм. Чернівці\n66.7\nЧернівецька область\nм. Чернівці\n64.12\nм. Новодністровськ\nЧернівецька область\nПодружжя\nЛуців О. Я\nДитина\nЛуців В. О\nДитина\nЛуців Я. О\nЛуців Олександра Володимирівна\nОлександра Володимирівна Луців\nОлександра Луців\nЛуців Олександра Володимирівна\nОлександра\nЛуців Олександра Володимирівна\nЛуців\nЗагальний місцевий суд\nЧернівецька область\nсуддя\nВолодимирівна\n60236\nЧернівецька область\nНоводністровськ\n168048\n30965\n40110\n180228\n12180\n9145\n2014\nм. Чернівці\n.885\nЧернівецька область\nм. Чернівці\nЧернівецька область\n.885\nЧернівецька область\nм. Чернівці\n66.7\n66.7\nм. Чернівці\nЧернівецька область\nм. Новодністровськ\n64.12\nЧернівецька область\nЛуців О. Я\nПодружжя\nЛуців В. О\nДитина\nЛуців Я. О\nДитина\nВолодимирівна\nЛуців\nЛуців Олександра Володимирівна\nОлександра Володимирівна Луців\nОлександра Луців\nЛуців Олександра Володимирівна\n60236\nНоводністровськ\nЧернівецька область\nЧернівецька область\nЗагальний місцевий суд\nсуддя\nЛуців Олександра Володимирівна\nОлександра\n30965\n168048\n12180\n40110\n180228\n9145\nKia Rio\n1400 куб. см.\n2013\n2008\nKia Ceed\n1600 куб. см.\nRenault Duster\n1600 куб. см.\n2012\n12180\n180228\n40110\n9145\n168048\n30965\nЧернівецька область\nм. Чернівці\n66.7\nЧернівецька область\nм. Чернівці\n.885\nм. Чернівці\nЧернівецька область\n66.7\nЧернівецька область\nм. Новодністровськ\n64.12\n.885\nм. Чернівці\nЧернівецька область\n2014","general":{"inn":"","name":"Олександра","patronymic_unclear":false,"family":[{"inn":"","inn_hidden":true,"relations_unclear":false,"relations_hidden":false,"relations_other":"","relations":"Подружжя","name_hidden":true,"family_name":"Луців О. Я","name_unclear":false},{"inn":"","inn_hidden":true,"relations_hidden":false,"family_name":"Луців В. О","relations_other":"","relations":"Дитина","name_hidden":false,"name_unclear":false},{"inn":"","relations":"Дитина","relations_other":"","inn_hidden":false,"family_name":"Луців Я. О","name_hidden":false,"name_unclear":false}],"patronymic":"Володимирівна","inn_hidden":true,"family_raw":"","inn_unclear":false,"post":{"post_unclear":false,"region_unclear":false,"post":"суддя","office":"Загальний місцевий суд","region":"Чернівецька область","post_hidden":false,"office_hidden":false,"office_unclear":false,"region_hidden":false},"last_name_unclear":false,"full_name":"Луців Олександра Володимирівна","addresses":[{"place_district":"","place_address_hidden":true,"place_city":"Новодністровськ","place_city_type_hidden":false,"place_district_hidden":false,"place_city_type":"Місто","place_city_hidden":false,"place_address_unclear":false,"place_address":"60236","place_hidden":false,"place":"Чернівецька область"}],"last_name":"Луців","patronymic_hidden":false,"full_name_suggest":{"output":"Луців Олександра Володимирівна","input":["Луців Олександра Володимирівна","Олександра Володимирівна Луців","Олександра Луців"]},"name_unclear":false},"source":"VULYK","estate":{"23":[{"space_unclear":false,"costs":"","costs_comment":"","costs_hidden":false,"address_hidden":true,"region_hidden":false,"space_comment":"","space_hidden":false,"space":".885","address":"м. Чернівці","region":"Чернівецька область","address_unclear":false,"space_units_unclear":false,"costs_rent_hidden":false,"costs_unclear":false,"space_units":"га","costs_rent":"","costs_rent_comment":""},{"costs_rent":"","region":"","costs":"","costs_rent_comment":"","costs_comment":"","address_hidden":false,"region_hidden":false,"space_comment":"","space_units":"","space":"","address":""},{"costs_rent":"","region":"","costs":"","costs_rent_comment":"","costs_comment":"","space_comment":"","space_units":"","space":"","address":""},{"costs_rent":"","region":"","costs":"","costs_rent_comment":"","costs_comment":"","space_comment":"","space_units":"","space":"","address":""}],"25":[{"region_unclear":false,"space_unclear":false,"costs":"","costs_comment":"","costs_hidden":false,"address_hidden":true,"region_hidden":false,"space_comment":"","space_hidden":false,"space":"66.7","address":"м. Чернівці","costs_rent_comment_unclear":false,"region":"Чернівецька область","address_unclear":false,"costs_rent_comment":"","costs_rent_hidden":false,"space_comment_unclear":false,"space_units":"м²","costs_rent":""},{"costs_rent":"","region":"Чернівецька область","costs":"","costs_rent_comment":"","costs_comment":"","address_hidden":true,"region_hidden":false,"space_comment":"","space_units":"м²","space":"64.12","address":"м. Новодністровськ"}],"29":[{"space_unclear":false,"costs_property_hidden":false,"address_hidden":true,"region_hidden":false,"space_comment":"","space_hidden":false,"space":".885","address":"м. Чернівці","region":"Чернівецька область","costs_property":"","space_units_unclear":false,"costs_rent_hidden":false,"address_unclear":false,"space_units":"га","costs_property_comment":"","costs_rent":"","costs_rent_comment":""}],"31":[{"region_unclear":false,"space_hidden":false,"costs_property_hidden":false,"address_hidden":true,"region_hidden":false,"space_comment":"","space_unclear":false,"space":"66.7","address":"м. Чернівці","region":"Чернівецька область","costs_property":"","costs_rent_comment":"","costs_rent_hidden":false,"space_comment_unclear":false,"space_units":"м²","costs_property_comment":"","costs_rent":""}]},"intro":{"declaration_year":"2014","isnotdeclaration":"","declaration_year_unclear":false}}