{"id":"vulyk_99_12","ft_src":"1993\n49\nYamaha Aprio\n2001\nToyota Land Cruiser 100\n4700\n2000\nToyota Rav 4\n2002\n.029\n51\n109\n107\n2015\n50879.83\n204140.4\n7082.94\n12180\n57962.77\n217170.4\n850\n4700\nToyota Land Cruiser 100\n2001\n2000\n2002\nToyota Rav 4\n49\nYamaha Aprio\n1993\n2015\nКоваленко\nКоваленко Костянтин Вікторович\nКостянтин Вікторович Коваленко\nКостянтин Коваленко\nКоваленко Костянтин Вікторович\nКостянтин\nВікторович\nКоваленко Костянтин Вікторович\nЗагальний місцевий суд\nсуддя баришівського районного суду київської області\nКиївська область\nПодружжя\nКоваленко О. В., 27. 04. 1971\n204140.4\n50879.83\n850\n217170.4\n57962.77\n12180\n7082.94\n.029\n109\n51\n107\nКоваленко О. В., 27. 04. 1971\nПодружжя\nВікторович\nКоваленко\nсуддя баришівського районного суду київської області\nКиївська область\nЗагальний місцевий суд\nКоваленко Костянтин Вікторович\nКоваленко Костянтин Вікторович\nКостянтин Вікторович Коваленко\nКостянтин Коваленко\nКоваленко Костянтин Вікторович\nКостянтин","estate":{"23":[{"address":"","space_units":"га","costs_comment":"","space_unclear":false,"region_hidden":true,"space_comment":"","address_hidden":false,"costs":"","costs_rent_comment":"","space":".029","region":"","costs_rent":""}],"24":[{"costs":"","address":"","space_units":"м²","costs_rent_comment":"","space":"109","space_comment":"","region_hidden":true,"costs_comment":"","region":"","address_hidden":false,"costs_rent":""}],"27":[{"costs":"","address":"","space_units":"м²","costs_rent_comment":"","space":"51","space_comment":"","region_hidden":true,"costs_comment":"","region":"","address_hidden":false,"costs_rent":""}],"28":[{"costs":"","address":"","space_units":"м²","costs_rent_comment":"","space":"107","space_comment":"","region_hidden":true,"costs_comment":"","region":"","address_hidden":false,"costs_rent":""}]},"vehicle":{"35":[{"sum_comment":"","brand_info":"4700","brand_unclear":false,"sum_rent_comment":"","year":"2001","brand":"Toyota Land Cruiser 100","sum_rent":"","brand_info_unclear":false,"sum":""}],"39":[{"sum_comment":"","brand_info":"49","sum":"","brand_unclear":false,"year":"1993","brand":"Yamaha Aprio","sum_rent":"","sum_rent_comment":""}],"40":[{"sum_comment":"","brand_info_hidden":false,"sum_rent":"","sum":"","brand_unclear":false,"year":"2002","brand":"Toyota Rav 4","brand_info":"2000","sum_rent_comment":"","brand_info_unclear":false}]},"source":"VULYK","income":{"5":{"family_comment":"","family":"57962.77","comment":"","value_unclear":false,"family_unclear":false,"value":"217170.4"},"6":{"family_comment":"","family":"50879.83","comment":"","value_unclear":false,"family_unclear":false,"value":"204140.4"},"7":{"family":"","family_comment":"","value":"","comment":"","source_name":""},"8":{"family_comment":"","value":"","family":"","comment":""},"9":{"family_comment":"","value":"","family":"","comment":""},"10":{"family_comment":"","value":"12180","family":"7082.94","comment":""},"11":{"family_comment":"","value":"","family":"","comment":""},"12":{"family_comment":"","value":"","family":"","comment":""},"13":{"family_comment":"","value":"","family":"","comment":""},"14":{"family_comment":"","value":"","family":"","comment":""},"15":{"family_comment":"","value":"","family":"","comment":"","value_unclear":false},"16":{"family_comment":"","value":"","family":"","comment":""},"17":{"family_comment":"","value":"","family":"","comment":""},"18":{"family_comment":"","value":"","family":"","comment":""},"19":{"family_comment":"","value":"","family":"","comment":""},"20":{"family_comment":"","family":"","comment":"","value_unclear":false,"family_unclear":false,"value":"850","family_comment_unclear":false}},"general":{"inn":"","addresses":[{"place_city_type_hidden":false,"place_city_type":"","place_city_hidden":true,"place_hidden":true,"place_district":"","place_district_hidden":false,"place":"","place_address":"","place_address_hidden":true,"place_city":""}],"last_name":"Коваленко","full_name":"Коваленко Костянтин Вікторович","family":[{"inn":"","family_name":"Коваленко О. В., 27. 04. 1971","name_unclear":true,"inn_hidden":true,"name_hidden":false,"relations":"Подружжя"}],"patronymic":"Вікторович","inn_hidden":true,"name":"Костянтин","post":{"office":"Загальний місцевий суд","region":"Київська область","post_unclear":false,"post":"суддя баришівського районного суду київської області"},"family_raw":"","full_name_suggest":{"input":["Коваленко Костянтин Вікторович","Костянтин Вікторович Коваленко","Костянтин Коваленко"],"output":"Коваленко Костянтин Вікторович"}},"liabilities":{"54":{"sum_comment_unclear":false,"sum_comment":"","sum":"","sum_foreign_comment":"","sum_foreign":"","sum_comment_hidden":false},"55":{"sum_comment":"","sum_foreign_comment":"","sum_foreign":"","sum":""},"56":{"sum_comment":"","sum_foreign_comment":"","sum_foreign":"","sum":""},"57":{"sum_comment":"","sum_foreign_comment":"","sum_foreign":"","sum":"","sum_comment_hidden":false},"58":{"sum_comment":"","sum_foreign_comment":"","sum_foreign":"","sum":"","sum_comment_hidden":false},"59":{"sum_comment":"","sum":"","sum_foreign_comment":"","sum_foreign":"","sum_unclear":false,"sum_comment_hidden":false},"60":{"sum_comment":"","sum_foreign_comment":"","sum_foreign":"","sum":"","sum_comment_hidden":false},"61":{"sum_comment":"","sum_foreign_comment":"","sum_foreign":"","sum":""},"62":{"sum_comment":"","sum_foreign_comment":"","sum_foreign":"","sum":""},"63":{"sum_comment":"","sum_foreign_comment":"","sum_foreign":"","sum":"","sum_comment_hidden":false},"64":{"sum_comment":"","sum_foreign_comment":"","sum_foreign":"","sum":"","sum_comment_hidden":false}},"declaration":{"notfull_lostpages":"","date":"2016-02-24T00:00:00","notfull":"","url":"http://static.declarations.com.ua/declarations/chosen_ones/judges_batch/561_kovalenko_konstiantyn_viktorovych_2015.pdf"},"intro":{"declaration_year":"2015"}}