{"id":"vulyk_101_175","ft_src":"2199 куб. см.\nHyundai Santa FE\n2013\n2015\n18052\n215481\n19508\n215481\n1456\n2199 куб. см.\n2013\nHyundai Santa FE\n215481\n18052\n1456\n215481\n19508\nПодружжя\nМірошниченко Ю. О\nДитина\nМірошниченко Н. М\nМірошниченко Михайло Володимирович\nМихайло Володимирович Мірошниченко\nМихайло Мірошниченко\nМірошниченко Михайло Володимирович\nМихайло\nМірошниченко Михайло Володимирович\nВолодимирович\nГосподарський місцевий суд\nсуддя господарського суду запорізької області\nЗапорізька область\nМірошниченко\n2015\nМірошниченко Ю. О\nПодружжя\nМірошниченко Н. М\nДитина\nМихайло\nВолодимирович\nМірошниченко\nМірошниченко Михайло Володимирович\nМихайло Володимирович Мірошниченко\nМихайло Мірошниченко\nМірошниченко Михайло Володимирович\nсуддя господарського суду запорізької області\nГосподарський місцевий суд\nЗапорізька область\nМірошниченко Михайло Володимирович","vehicle":{"40":[{"sum_comment":"","brand_info_hidden":false,"brand_info":"2199 куб. см.","sum":"","sum_rent_comment":"","brand_hidden":false,"brand":"Hyundai Santa FE","sum_rent":"","brand_info_unclear":false,"year":"2013"}]},"source":"VULYK","income":{"5":{"family_comment":"","value":"215481","family":"19508","comment":"","value_unclear":false},"6":{"family_comment":"","family":"18052","comment":"","value_unclear":false,"family_hidden":false,"value":"215481"},"7":{"family_comment":"","comment":"","family":"","source_name_unclear":false,"value":"","source_name":""},"8":{"family_comment":"","value":"","family":"","comment":""},"9":{"family_comment":"","value":"","family":"","comment":""},"10":{"family_comment":"","value":"","family":"","comment":""},"11":{"family_comment":"","comment_unclear":false,"value":"","family":"","comment":""},"12":{"family_comment":"","value":"","family":"","comment":""},"13":{"family_comment":"","value":"","family":"","comment":""},"14":{"family_comment":"","value":"","family":"","comment":""},"15":{"family_comment":"","value":"","family":"","comment":""},"16":{"family_comment":"","value":"","family":"","comment":""},"17":{"family_comment":"","value":"","family":"","comment":""},"18":{"family_comment":"","value":"","family":"","comment":""},"19":{"family_comment":"","value":"","family":"","comment":""},"20":{"family_comment":"","family":"1456","comment":"","value_unclear":false,"family_unclear":false,"comment_unclear":false,"value":""}},"general":{"family":[{"inn":"","family_name":"Мірошниченко Ю. О","relations_other":"","name_unclear":false,"inn_hidden":true,"name_hidden":true,"relations":"Подружжя"},{"inn":"","family_name":"Мірошниченко Н. М","relations_other":"","relations_unclear":false,"name_unclear":false,"inn_hidden":false,"name_hidden":false,"relations":"Дитина"}],"family_raw":"","name":"Михайло","full_name_suggest":{"input":["Мірошниченко Михайло Володимирович","Михайло Володимирович Мірошниченко","Михайло Мірошниченко"],"output":"Мірошниченко Михайло Володимирович"},"patronymic":"Володимирович","inn_hidden":true,"addresses":[{"place_city_type_hidden":false,"place_city_type":"","place_city_hidden":true,"place_hidden":true,"place_district":"","place_district_hidden":false,"place":"","place_address":"","place_address_hidden":true,"place_city":""}],"patronymic_hidden":false,"inn":"","inn_unclear":false,"last_name":"Мірошниченко","full_name":"Мірошниченко Михайло Володимирович","post":{"office":"Господарський місцевий суд","region_unclear":false,"post":"суддя господарського суду запорізької області","region":"Запорізька область","office_unclear":false}},"liabilities":{"54":{"sum_comment_unclear":false,"sum_comment":"","sum_hidden":false,"sum":"","sum_foreign_comment":"","sum_foreign":"","sum_unclear":false,"sum_comment_hidden":false},"55":{"sum_comment":"","sum_foreign_comment":"","sum_foreign":"","sum":""},"56":{"sum_comment":"","sum":"","sum_foreign_comment":"","sum_foreign":"","sum_unclear":false,"sum_comment_hidden":false},"57":{"sum_comment":"","sum_hidden":false,"sum":"","sum_foreign_comment":"","sum_foreign":"","sum_unclear":false,"sum_comment_hidden":false},"58":{"sum_comment_unclear":false,"sum_comment":"","sum_hidden":false,"sum":"","sum_foreign_comment":"","sum_foreign":"","sum_unclear":false,"sum_comment_hidden":false},"59":{"sum_comment":"","sum_foreign_comment":"","sum_foreign":"","sum":""},"60":{"sum_comment":"","sum_hidden":false,"sum":"","sum_foreign_comment":"","sum_foreign":"","sum_unclear":false,"sum_comment_hidden":false},"61":{"sum_comment":"","sum_foreign_comment":"","sum_foreign":"","sum":""},"62":{"sum_comment":"","sum_comment_unclear":false,"sum_foreign_comment":"","sum":"","sum_foreign":""},"63":{"sum_comment":"","sum_foreign_comment":"","sum_foreign":"","sum":"","sum_comment_hidden":false},"64":{"sum_comment":"","sum_foreign_comment":"","sum_foreign":"","sum":"","sum_comment_hidden":false}},"declaration":{"notfull_lostpages":"","additional_info_text":"","additional_info":"","date":"2016-03-31T00:00:00","notfull":"","url":"http://static.declarations.com.ua/declarations/chosen_ones/judges_batch/890_miroshnychenko_mykhailo_volodymyrovych_2015.pdf"},"intro":{"declaration_year":"2015"}}