{"income":{"5":{"value":"636829","family_comment":"","value_unclear":false,"value_hidden":false,"family_unclear":false,"family":"","comment":""},"6":{"value":"352829","family_hidden":false,"value_hidden":false,"family_comment":"","family_comment_hidden":false,"comment":"","family":""},"7":{"value":"","value_unclear":false,"family_hidden":false,"value_hidden":false,"family_comment":"","source_name":"","family":"","comment":"","source_name_hidden":false},"8":{"value":"","comment_hidden":false,"family_hidden":false,"value_hidden":false,"family_comment":"","family":"","comment":""},"9":{"value":"4000","family_comment":"","comment_hidden":false,"family_hidden":false,"value_hidden":false,"family_unclear":false,"family":"","comment":"проценти"},"10":{"value":"","comment_hidden":false,"family_hidden":false,"value_hidden":false,"family_comment":"","family":"","comment":""},"11":{"value":"","value_unclear":false,"comment_hidden":false,"family_hidden":false,"value_hidden":false,"family_comment":"","family":"","comment":""},"12":{"value":"","comment_hidden":false,"family_hidden":false,"value_hidden":false,"family_comment":"","family":"","comment":""},"13":{"value":"","comment_hidden":false,"family_hidden":false,"value_hidden":false,"family_comment":"","family":"","comment":""},"14":{"value":"","comment_hidden":false,"family_hidden":false,"value_hidden":false,"family_comment":"","family":"","comment":""},"15":{"value":"","comment_hidden":false,"family_hidden":false,"value_hidden":false,"family_comment":"","family":"","comment":""},"16":{"value":"280000","comment_hidden":false,"family_hidden":false,"value_hidden":false,"family_comment":"","family":"","comment":""},"17":{"value":"","comment_hidden":false,"family_hidden":false,"value_hidden":false,"family_comment":"","family":"","comment":""},"18":{"value":"","value_unclear":false,"comment_hidden":false,"family_hidden":false,"value_hidden":false,"family_comment":"","family":"","comment":""},"19":{"value":"","comment_hidden":false,"family_hidden":false,"value_hidden":false,"family_comment":"","family":"","comment":""},"20":{"value":"","value_unclear":false,"family_comment":"","comment_unclear":false,"comment":"","family":""}},"vehicle":{"40":[{"year_hidden":false,"brand_info":"2000 куб. см.","sum_rent_comment":"","brand":"Nissan","sum_comment":"","brand_unclear":false,"year":"2005","brand_hidden":false,"brand_info_unclear":false,"sum":"","sum_rent":""},{"brand_info":"3456 куб. см.","sum_rent_comment":"","brand":"Lexus RX 350","sum_comment":"","year":"2013","brand_info_unclear":false,"sum":"","sum_rent":""}],"44":[{"brand_info":"0.800 куб. см.","sum_rent_comment":"","brand":"Honda VFR 800","sum_comment":"","year":"2006","brand_hidden":false,"brand_info_hidden":false,"sum":"","sum_rent":""}]},"id":"vulyk_1_755","banks":{"45":[{"sum_units":"UAH","sum_foreign":"","sum_hidden":false,"sum":"73600","sum_units_hidden":false,"sum_foreign_comment":"","sum_foreign_hidden":false,"sum_comment":"","sum_foreign_units":"UAH","sum_units_unclear":false,"sum_comment_hidden":false,"sum_unclear":false}]},"declaration":{"additional_info_text":"","notfull_lostpages":"","date":"2014-03-12T00:00:00","notfull":"","additional_info":"","url":"http://static.declarations.com.ua/declarations/chosen_ones/judges_batch/286_dembovskyi_serhii_heorhiiovych.pdf"},"liabilities":{"54":{"sum_foreign_comment":"","sum_foreign_hidden":false,"sum_comment":"","sum_hidden":false,"sum_comment_hidden":false,"sum":"","sum_foreign":""},"55":{"sum_foreign_comment":"","sum":"","sum_hidden":false,"sum_comment":"","sum_foreign":""},"56":{"sum_foreign_comment":"","sum":"","sum_comment":"","sum_foreign":""},"57":{"sum_foreign_comment":"","sum_foreign_hidden":false,"sum_comment":"","sum_hidden":false,"sum_comment_hidden":false,"sum_unclear":false,"sum":"","sum_foreign":""},"58":{"sum_foreign_comment":"","sum_foreign_hidden":false,"sum_comment":"","sum_hidden":false,"sum_comment_hidden":false,"sum_unclear":false,"sum":"","sum_foreign":""},"59":{"sum_foreign_comment":"","sum":"","sum_hidden":false,"sum_comment":"","sum_foreign":""},"60":{"sum_foreign_comment":"","sum_foreign_hidden":false,"sum_comment":"","sum_hidden":false,"sum_comment_hidden":false,"sum_unclear":false,"sum":"","sum_foreign":""},"61":{"sum_foreign_comment":"","sum":"","sum_hidden":false,"sum_comment":"","sum_foreign":""},"62":{"sum_foreign_comment":"","sum":"","sum_comment":"","sum_hidden":false,"sum_comment_hidden":false,"sum_foreign":""},"63":{"sum_foreign_comment":"","sum":"","sum_hidden":false,"sum_comment":"","sum_foreign":""},"64":{"sum_foreign_comment":"","sum":"","sum_hidden":false,"sum_comment":"","sum_foreign":""}},"ft_src":"суддя вссу\nЗагальнодержавний регіон\nВищий спеціалізований суд з розгляду цивільних і кримінальних справ\nСергій\nДембовська О. В\nПодружжя\nДембовська О. С\nДитина\nГеоргійович\nДембовський Сергій Георгійович\nСергій Георгійович Дембовський\nСергій Дембовський\nДембовський Сергій Георгійович\nДембовський Сергій Георгійович\nДембовський\nNissan\n2000 куб. см.\n2005\n3456 куб. см.\n2013\nLexus RX 350\n0.800 куб. см.\nHonda VFR 800\n2006\n43.6\n68.6\n.446\n84.1\n73600\n2013\n2000 куб. см.\nNissan\n2005\n3456 куб. см.\nLexus RX 350\n2013\nHonda VFR 800\n0.800 куб. см.\n2006\n.446\n68.6\n43.6\n84.1\nПодружжя\nДембовська О. В\nДитина\nДембовська О. С\nДембовський Сергій Георгійович\nСергій Георгійович Дембовський\nСергій Дембовський\nДембовський Сергій Георгійович\nДембовський Сергій Георгійович\nСергій\nГеоргійович\nВищий спеціалізований суд з розгляду цивільних і кримінальних справ\nсуддя вссу\nЗагальнодержавний регіон\nДембовський\n352829\n636829\n280000\nпроценти\n4000\n73600\n2013\n352829\nпроценти\n4000\n636829\n280000\nДембовська О. В\nПодружжя\nДитина\nДембовська О. С\nГеоргійович\nДембовський\nСергій\nДембовський Сергій Георгійович\nСергій Георгійович Дембовський\nСергій Дембовський\nДембовський Сергій Георгійович\nЗагальнодержавний регіон\nсуддя вссу\nВищий спеціалізований суд з розгляду цивільних і кримінальних справ\nДембовський Сергій Георгійович\n0.800 куб. см.\nHonda VFR 800\n2006\n2005\nNissan\n2000 куб. см.\n2013\n3456 куб. см.\nLexus RX 350\n4000\nпроценти\n636829\n280000\n352829\n43.6\n68.6\n84.1\n.446\n73600\n2013","general":{"inn":"","name":"Сергій","inn_unclear":false,"family":[{"inn":"","inn_hidden":false,"relations_unclear":false,"relations_hidden":false,"relations_other":"","relations":"Подружжя","name_hidden":true,"family_name":"Дембовська О. В","name_unclear":false},{"inn":"","inn_hidden":false,"relations_unclear":false,"relations_hidden":false,"relations_other":"","relations":"Дитина","name_hidden":false,"family_name":"Дембовська О. С","name_unclear":false}],"inn_hidden":false,"family_raw":"","last_name":"Дембовський","post":{"post_unclear":false,"post":"суддя вссу","candidate":"","office_hidden":false,"region":"Загальнодержавний регіон","office":"Вищий спеціалізований суд з розгляду цивільних і кримінальних справ","office_unclear":false,"region_hidden":false},"full_name_suggest":{"output":"Дембовський Сергій Георгійович","input":["Дембовський Сергій Георгійович","Сергій Георгійович Дембовський","Сергій Дембовський"]},"full_name":"Дембовський Сергій Георгійович","patronymic":"Георгійович","last_name_unclear":false,"name_unclear":false},"source":"VULYK","estate":{"25":[{"space_unclear":false,"costs":"","costs_comment":"","address_hidden":false,"region_hidden":false,"space_comment":"","space_hidden":false,"space":"84.1","address":"","region":"","costs_rent_comment":"","space_comment_unclear":false,"space_comment_hidden":false,"space_units":"м²","costs_rent":""}],"29":[{"space_unclear":false,"address_hidden":false,"region_hidden":false,"space_comment":"","space_hidden":false,"space":".446","address":"","region":"","costs_property":"","costs_rent_comment":"","space_units":"га","costs_property_comment":"","costs_rent":""}],"30":[{"space_hidden":false,"address_hidden":false,"region_hidden":false,"space_comment":"","space":"68.6","address":"","region":"","costs_property":"","costs_rent_comment":"","space_units":"м²","costs_property_comment":"","costs_rent":""}],"31":[{"space_unclear":false,"address_hidden":false,"region_hidden":false,"space_comment":"","space_hidden":false,"space":"43.6","address":"","region":"","costs_property":"","costs_rent_comment":"","space_comment_unclear":false,"space_units":"м²","costs_property_comment":"","costs_rent":""}]},"intro":{"declaration_year":"2013","isnotdeclaration":"","declaration_year_unclear":false,"declaration_year_hidden":false}}