{"income":{"5":{"value":"209917","family_comment":"","value_unclear":false,"family_unclear":false,"family":"54590","comment":""},"6":{"family_comment":"","value":"209851","value_unclear":false,"family":"22990","comment":""},"7":{"family_comment":"","value":"","source_name":"","family":"","comment":""},"8":{"family_comment":"","value":"","family":"","comment":""},"9":{"family_comment":"","value":"","value_unclear":false,"family":"","comment":""},"10":{"family_comment":"","value":"","family":"","comment":""},"11":{"family_comment":"","value":"","family":"","comment":""},"12":{"family_comment":"","value":"","family":"31600","comment":""},"13":{"family_comment":"","value":"","family":"","comment":""},"14":{"family_comment":"","value":"","family":"","comment":""},"15":{"family_comment":"","value":"","family":"","comment":""},"16":{"family_comment":"","value":"","family":"","comment":""},"17":{"family_comment":"","value":"","family":"","comment":""},"18":{"family_comment":"","value":"","family":"","comment":""},"19":{"family_comment":"","value":"","family":"","comment":""},"20":{"family_comment":"","value":"66","value_unclear":false,"family":"","comment":""}},"vehicle":{"35":[{"brand_info":"1596 куб. см., 78.7 кВт","sum_rent_comment":"","brand":"Nissan Almera Classic","sum_comment":"","brand_unclear":false,"year":"2010","brand_info_unclear":false,"sum":"","sum_rent":""}]},"id":"vulyk_98_14","declaration":{"date":"2015-03-23T00:00:00","url":"http://static.declarations.com.ua/declarations/chosen_ones/judges_batch/4485_vorobiova_inna_anatoliivna.pdf"},"liabilities":{"54":{"sum_foreign_comment":"","sum":"10250","sum_comment":"ПАТ Граве Україна страхування життя, ПАТ Метлайф","sum_comment_unclear":false,"sum_hidden":false,"sum_comment_hidden":false,"sum_unclear":false,"sum_foreign":""},"55":{"sum_foreign_comment":"","sum":"","sum_comment":"","sum_foreign":""},"56":{"sum_foreign_comment":"","sum":"","sum_comment":"","sum_unclear":false,"sum_foreign":""},"57":{"sum_foreign_comment":"","sum":"","sum_comment":"","sum_comment_unclear":false,"sum_hidden":false,"sum_comment_hidden":false,"sum_unclear":false,"sum_foreign":""},"58":{"sum_foreign_comment":"","sum":"","sum_comment":"","sum_hidden":false,"sum_comment_hidden":false,"sum_unclear":false,"sum_foreign":""},"59":{"sum_foreign_comment":"","sum":"","sum_comment":"","sum_comment_unclear":false,"sum_foreign":""},"60":{"sum_foreign_comment":"","sum":"5050","sum_comment":"ПАТ Граве Україна страхування життя","sum_hidden":false,"sum_comment_hidden":false,"sum_foreign":""},"61":{"sum_foreign_comment":"","sum":"","sum_comment":"","sum_foreign":""},"62":{"sum_foreign_comment":"","sum":"","sum_comment":"","sum_comment_hidden":false,"sum_unclear":false,"sum_foreign":""},"63":{"sum_foreign_comment":"","sum":"8665","sum_comment":"ОТР Банк","sum_comment_unclear":false,"sum_comment_hidden":false,"sum_foreign":""},"64":{"sum_foreign_comment":"","sum_comment_hidden":true,"sum":"1379","sum_comment":"","sum_foreign":""}},"ft_src":"ПАТ Граве Україна страхування життя, ПАТ Метлайф\n10250\n1379\nОТР Банк\n8665\nПАТ Граве Україна страхування життя\n5050\nсуддя вінницького окружного адміністративного суду\nВінницька область\nАдміністративний місцевий суд\nІнна\nВоловодівський І. В\nПодружжя\nВоловодівский І. І\nДитина\nАнатоліївна\nВоробйова Інна Анатоліївна\nІнна Анатоліївна Воробйова\nІнна Воробйова\nВоробйова Інна Анатоліївна\nВоробйова Інна Анатоліївна\nВоробйова\n2010\nNissan Almera Classic\n1596 куб. см., 78.7 кВт\n79.3\n100\n120\n2014\n22990\n209851\n54590\n209917\n66\n31600\n1596 куб. см., 78.7 кВт\n2010\nNissan Almera Classic\n2014\nАдміністративний місцевий суд\nсуддя вінницького окружного адміністративного суду\nВінницька область\nВоробйова Інна Анатоліївна\nІнна Анатоліївна Воробйова\nІнна Воробйова\nВоробйова Інна Анатоліївна\nВоробйова Інна Анатоліївна\nПодружжя\nВоловодівський І. В\nДитина\nВоловодівский І. І\nІнна\nВоробйова\nАнатоліївна\n10250\nПАТ Граве Україна страхування життя, ПАТ Метлайф\n1379\nОТР Банк\n8665\n5050\nПАТ Граве Україна страхування життя\n209851\n22990\n31600\n66\n54590\n209917\n79.3\n100\n120\n1379\nПАТ Граве Україна страхування життя, ПАТ Метлайф\n10250\nПАТ Граве Україна страхування життя\n5050\nОТР Банк\n8665\nПодружжя\nВоловодівський І. В\nДитина\nВоловодівский І. І\nАнатоліївна\nВоробйова\nІнна\nВоробйова Інна Анатоліївна\nІнна Анатоліївна Воробйова\nІнна Воробйова\nВоробйова Інна Анатоліївна\nсуддя вінницького окружного адміністративного суду\nВінницька область\nАдміністративний місцевий суд\nВоробйова Інна Анатоліївна\n2010\n1596 куб. см., 78.7 кВт\nNissan Almera Classic\n66\n209917\n54590\n31600\n22990\n209851\n79.3\n100\n120\n2014","general":{"inn":"","name":"Інна","last_name_hidden":false,"family":[{"inn":"","relations":"Подружжя","relations_other":"","inn_hidden":true,"family_name":"Воловодівський І. В","name_hidden":true,"name_unclear":true},{"inn":"","relations":"Дитина","relations_other":"","inn_hidden":true,"family_name":"Воловодівский І. І","name_hidden":false,"name_unclear":false}],"patronymic":"Анатоліївна","inn_hidden":true,"family_raw":"","inn_unclear":false,"post":{"post_unclear":false,"office":"Адміністративний місцевий суд","post":"суддя вінницького окружного адміністративного суду","region":"Вінницька область"},"full_name_suggest":{"output":"Воробйова Інна Анатоліївна","input":["Воробйова Інна Анатоліївна","Інна Анатоліївна Воробйова","Інна Воробйова"]},"full_name":"Воробйова Інна Анатоліївна","addresses":[{"place_district":"","place_city_hidden":true,"place_city":"","place_city_type_hidden":false,"place_district_hidden":false,"place_city_type":"","place_address_hidden":true,"place_address":"","place_hidden":true,"place":""}],"last_name":"Воробйова","patronymic_hidden":false,"last_name_unclear":false},"source":"VULYK","estate":{"23":[{"space_unclear":false,"costs":"","costs_comment":"","address_hidden":false,"region_hidden":true,"space_comment":"","space":"79.3","address":"","region":"","costs_rent_comment":"","space_units":"м²","costs_rent":""}],"29":[{"costs_rent":"","region":"","costs_property":"","costs_rent_comment":"","address_hidden":true,"region_hidden":true,"space_comment":"","costs_property_comment":"","space_units":"м²","space":"100","address":""},{"costs_rent":"","region":"","costs_property":"","costs_rent_comment":"","space_comment":"","costs_property_comment":"","space_units":"м²","space":"120","address":""}]},"intro":{"declaration_year":"2014"}}