{"income":{"5":{"value":"1761207.62","family_comment":"","value_unclear":false,"family_hidden":false,"value_hidden":false,"family_unclear":false,"family":"16800","comment":""},"6":{"value":"262074.62","family_comment":"","value_unclear":false,"family_unclear":false,"family":"","comment":""},"7":{"source_name_unclear":false,"value":"","comment_hidden":false,"family_comment":"","source_name":"","family":"","comment":"","source_name_hidden":false},"8":{"family_comment":"","value":"","family":"","comment":""},"9":{"value":"","family_comment":"","value_unclear":false,"family_hidden":false,"family_unclear":false,"family":"","comment":"","family_comment_unclear":false},"10":{"family_comment":"","value":"","family":"","comment":""},"11":{"family_comment":"","value":"","family":"","comment":""},"12":{"family_comment":"","value":"","family":"","comment":""},"13":{"family_comment":"","value":"","family":"","comment":""},"14":{"family_comment":"","value":"","family":"","comment":""},"15":{"family_comment":"","value":"","family":"16800","comment":""},"16":{"family_comment":"","value":"1499133","family":"","comment":""},"17":{"family_comment":"","value":"","family":"","comment":""},"18":{"family_comment":"","value":"","family":"","comment":""},"19":{"family_comment":"","value":"","family":"","comment":""},"20":{"value":"","family_comment":"","value_unclear":false,"family_comment_hidden":false,"family_unclear":false,"family_comment_unclear":false,"comment_unclear":false,"comment":"","family":""}},"id":"vulyk_93_5","declaration":{"additional_info_text":"","notfull_lostpages":"","date":"2015-03-31T00:00:00","notfull":"","additional_info":"","url":"http://static.declarations.com.ua/declarations/chosen_ones/judges_batch/3451_zheliezna_svitlana_petrivna.pdf"},"liabilities":{"54":{"sum_foreign_comment":"","sum":"","sum_hidden":false,"sum_comment":"","sum_foreign":""},"55":{"sum_foreign_comment":"","sum":"","sum_comment":"","sum_foreign":""},"56":{"sum_foreign_comment":"","sum":"","sum_comment":"","sum_foreign":""},"57":{"sum_foreign_comment":"","sum":"","sum_comment":"","sum_hidden":false,"sum_comment_hidden":false,"sum_unclear":false,"sum_foreign":""},"58":{"sum_foreign_comment":"","sum":"","sum_comment":"","sum_comment_unclear":false,"sum_hidden":false,"sum_unclear":false,"sum_foreign":""},"59":{"sum_foreign_comment":"","sum":"","sum_comment":"","sum_foreign":""},"60":{"sum_foreign_comment":"","sum":"","sum_hidden":false,"sum_comment":"","sum_foreign":""},"61":{"sum_foreign_comment":"","sum":"","sum_comment":"","sum_foreign":""},"62":{"sum_foreign_comment":"","sum":"","sum_comment":"","sum_foreign":""},"63":{"sum_foreign_comment":"","sum":"","sum_comment":"","sum_foreign":""},"64":{"sum_foreign_comment":"","sum":"","sum_comment":"","sum_foreign":""}},"ft_src":"Желєзна Світлана Петрівна\nсуддя господарського суду одеської області\nОдеська область\nГосподарський місцевий суд\nСвітлана\nУварова Г. М\nБатьки\nЖелєзна Світлана Петрівна\nСвітлана Петрівна Желєзна\nСвітлана Желєзна\nЖелєзна Світлана Петрівна\nЖелєзна\nПетрівна\n16800\n1761207.62\n16800\n1499133\n262074.62\n.054\n24\n2014\n262074.62\n16800\n16800\n1761207.62\n1499133\n.054\n24\nЖелєзна\nБатьки\nУварова Г. М\nЖелєзна Світлана Петрівна\nСвітлана Петрівна Желєзна\nСвітлана Желєзна\nЖелєзна Світлана Петрівна\nЖелєзна Світлана Петрівна\nСвітлана\nПетрівна\nОдеська область\nГосподарський місцевий суд\nсуддя господарського суду одеської області\n262074.62\n16800\n1761207.62\n16800\n1499133\n2014\nБатьки\nУварова Г. М\nЖелєзна\nПетрівна\nОдеська область\nГосподарський місцевий суд\nсуддя господарського суду одеської області\nЖелєзна Світлана Петрівна\nЖелєзна Світлана Петрівна\nСвітлана Петрівна Желєзна\nСвітлана Желєзна\nЖелєзна Світлана Петрівна\nСвітлана\n24\n.054\n2014","general":{"inn":"","inn_hidden":true,"last_name":"Желєзна","post":{"post_unclear":false,"region_unclear":false,"region":"Одеська область","candidate":"","post":"суддя господарського суду одеської області","office":"Господарський місцевий суд","office_unclear":false},"name":"Світлана","full_name":"Желєзна Світлана Петрівна","family_raw":"","addresses":[{"place_district":"","place_city_hidden":true,"place_city":"","place_city_type_hidden":true,"place_district_hidden":true,"place_city_type":"","place_address_hidden":true,"place_address":"","place_hidden":true,"place":""}],"family":[{"inn":"","relations":"Батьки","relations_hidden":false,"inn_hidden":false,"relations_other":"","name_hidden":false,"family_name":"Уварова Г. М","name_unclear":false}],"full_name_suggest":{"output":"Желєзна Світлана Петрівна","input":["Желєзна Світлана Петрівна","Світлана Петрівна Желєзна","Світлана Желєзна"]},"patronymic":"Петрівна"},"source":"VULYK","estate":{"25":[{"space_hidden":false,"costs":"","costs_comment":"","address_hidden":false,"region_hidden":true,"space_comment":"","space_unclear":false,"space":"24","address":"","costs_rent_comment_unclear":false,"region":"","costs_rent_comment":"","space_units":"м²","costs_rent":""}],"29":[{"space_unclear":false,"address_hidden":false,"region_hidden":true,"space_comment":"","space":".054","address":"","region":"","costs_property":"","costs_rent_comment":"","space_comment_unclear":false,"space_units":"га","costs_property_comment":"","costs_rent":""}]},"intro":{"declaration_year":"2014","isnotdeclaration":""}}