{"income":{"5":{"family_comment":"","value":"243755","value_unclear":false,"family":"","comment":""},"6":{"value":"243755","value_unclear":false,"family_hidden":false,"family_comment":"","family":"","comment":""},"7":{"source_name_unclear":false,"value":"","family_comment":"","source_name":"","family":"","comment":""},"8":{"family_comment":"","value":"","family":"","comment":""},"9":{"family_comment":"","value":"","family":"","comment":""},"10":{"family_comment":"","value":"","family":"","comment":""},"11":{"family_comment":"","value":"","comment_unclear":false,"family":"","comment":""},"12":{"family_comment":"","value":"","family":"","comment":""},"13":{"family_comment":"","value":"","family":"","comment":""},"14":{"family_comment":"","value":"","family":"","comment":""},"15":{"family_comment":"","value":"","family":"","comment":""},"16":{"family_comment":"","value":"","family":"","comment":""},"17":{"family_comment":"","value":"","family":"","comment":""},"18":{"family_comment":"","value":"","family":"","comment":""},"19":{"family_comment":"","value":"","family":"","comment":""},"20":{"value":"","family_comment":"","value_unclear":false,"family_unclear":false,"comment_unclear":false,"comment":"","family":""}},"vehicle":{"35":[{"brand_info":"1.9","sum_rent_comment":"","brand":"Nissan Qashqai","sum_comment":"","brand_unclear":false,"year":"2008","sum_rent_unclear":false,"brand_info_hidden":false,"brand_info_unclear":false,"sum":"","sum_rent":""}]},"id":"vulyk_101_48","declaration":{"additional_info_text":"","notfull_lostpages":"","date":"2016-03-14T00:00:00","notfull":"","additional_info":"","url":"http://static.declarations.com.ua/declarations/chosen_ones/judges_batch/712_zhuravlov_oleksandr_hennadiiovych_2015.pdf"},"liabilities":{"54":{"sum_foreign_comment":"","sum":"","sum_comment":"","sum_comment_unclear":false,"sum_hidden":false,"sum_comment_hidden":false,"sum_unclear":false,"sum_foreign":""},"55":{"sum_foreign_comment":"","sum":"","sum_comment":"","sum_foreign":""},"56":{"sum_foreign_comment":"","sum":"","sum_comment":"","sum_comment_hidden":false,"sum_unclear":false,"sum_foreign":""},"57":{"sum_foreign_comment":"","sum":"","sum_comment":"","sum_hidden":false,"sum_comment_hidden":false,"sum_unclear":false,"sum_foreign":""},"58":{"sum_foreign_comment":"","sum":"","sum_comment":"","sum_comment_unclear":false,"sum_hidden":false,"sum_comment_hidden":false,"sum_unclear":false,"sum_foreign":""},"59":{"sum_foreign_comment":"","sum":"","sum_comment":"","sum_foreign":""},"60":{"sum_foreign_comment":"","sum":"","sum_comment":"","sum_hidden":false,"sum_comment_hidden":false,"sum_unclear":false,"sum_foreign":""},"61":{"sum_foreign_comment":"","sum":"","sum_comment":"","sum_foreign":""},"62":{"sum_foreign_comment":"","sum":"","sum_comment":"","sum_comment_unclear":false,"sum_foreign":""},"63":{"sum_foreign_comment":"","sum_comment_hidden":false,"sum":"","sum_comment":"","sum_foreign":""},"64":{"sum_foreign_comment":"","sum_comment_hidden":false,"sum":"","sum_comment":"","sum_foreign":""}},"ft_src":"суддя апеляційного суду одеської області\nОдеська область\nЗагальний апеляційний суд\nОлександр\nЖуравльова Д. О\nДитина\nГеннадійович\nЖуравльов Олександр Геннадійович\nЖуравльов\nЖуравльов Олександр Геннадійович\nОлександр Геннадійович Журавльов\nОлександр Журавльов\nЖуравльов Олександр Геннадійович\nNissan Qashqai\n1.9\n2008\n.606\n30.1\n313.6\n2015\n243755\n243755\nNissan Qashqai\n1.9\n2008\n2015\nДитина\nЖуравльова Д. О\nЖуравльов Олександр Геннадійович\nОлександр Геннадійович Журавльов\nОлександр Журавльов\nЖуравльов Олександр Геннадійович\nОлександр\nЖуравльов Олександр Геннадійович\nГеннадійович\nЗагальний апеляційний суд\nсуддя апеляційного суду одеської області\nОдеська область\nЖуравльов\n243755\n243755\n.606\n30.1\n313.6\nЖуравльова Д. О\nДитина\nОлександр\nГеннадійович\nЖуравльов\nЖуравльов Олександр Геннадійович\nОлександр Геннадійович Журавльов\nОлександр Журавльов\nЖуравльов Олександр Геннадійович\nсуддя апеляційного суду одеської області\nЗагальний апеляційний суд\nОдеська область\nЖуравльов Олександр Геннадійович\n2008\nNissan Qashqai\n1.9\n243755\n243755\n.606\n313.6\n30.1\n2015","general":{"inn":"","name":"Олександр","inn_unclear":false,"family":[{"inn":"","relations":"Дитина","relations_other":"","inn_hidden":true,"family_name":"Журавльова Д. О","name_hidden":true,"name_unclear":false}],"inn_hidden":true,"family_raw":"","last_name":"Журавльов","post":{"region":"Одеська область","region_unclear":false,"post":"суддя апеляційного суду одеської області","office_unclear":false,"office":"Загальний апеляційний суд"},"full_name":"Журавльов Олександр Геннадійович","addresses":[{"place_district":"","place_city_hidden":true,"place_city":"","place_city_type_hidden":false,"place_district_hidden":false,"place_city_type":"","place_address_hidden":true,"place_address":"","place_hidden":true,"place":""}],"patronymic":"Геннадійович","patronymic_hidden":false,"full_name_suggest":{"output":"Журавльов Олександр Геннадійович","input":["Журавльов Олександр Геннадійович","Олександр Геннадійович Журавльов","Олександр Журавльов"]}},"source":"VULYK","estate":{"23":[{"space_unclear":false,"costs":"","costs_comment":"","address_hidden":false,"region_hidden":true,"space_comment":"","space_hidden":false,"space":".606","address":"","costs_comment_unclear":false,"region":"","space_units_unclear":false,"space_units":"га","costs_rent":"","costs_rent_comment":""}],"26":[{"costs_rent":"","region":"","costs":"","costs_rent_comment":"","costs_comment":"","address_hidden":false,"region_hidden":true,"space_comment":"","space_units":"м²","space":"313.6","address":""}],"27":[{"space_hidden":false,"costs":"","costs_comment":"","address_hidden":false,"region_hidden":true,"space_comment":"","space":"30.1","address":"","region":"","costs_rent_comment":"","space_units":"м²","costs_rent":""}]},"intro":{"declaration_year":"2015"}}