{"income":{"5":{"family_comment":"","family_unclear":false,"value":"183420","family":"49004","comment":""},"6":{"value":"183420","family_comment":"","value_unclear":false,"family_unclear":false,"family":"","comment":""},"7":{"value":"","family_comment":"","value_unclear":false,"family_unclear":false,"source_name":"","family":"","comment":"","source_name_hidden":false},"8":{"family_comment":"","value":"","family":"","comment":""},"9":{"family_comment":"","value":"","family":"","comment":""},"10":{"family_comment":"","value":"","value_unclear":false,"family":"","comment":""},"11":{"family_comment":"","value":"","family":"16013","comment":""},"12":{"family_comment":"","value":"","family":"","comment":""},"13":{"family_comment":"","value":"","family":"","comment":""},"14":{"family_comment":"","value":"","family":"","comment":""},"15":{"family_comment":"","value":"","family":"","comment":""},"16":{"family_comment":"","value":"","family":"","comment":""},"17":{"family_comment":"","value":"","family":"","comment":""},"18":{"family_comment":"","value":"","family":"","comment":""},"19":{"family_comment":"","value":"","family":"","comment":""},"20":{"value":"","value_unclear":false,"comment_hidden":false,"family_comment":"","comment_unclear":false,"comment":"","family":"32991"}},"vehicle":{"35":[{"year_hidden":false,"brand_info":"1998 куб. см.","sum_rent_comment":"","year":"2004","brand_info_hidden":false,"year_unclear":false,"sum_rent":"","sum":"","brand":"Chevrolet Evanda","sum_comment":"","brand_unclear":false,"brand_hidden":false,"sum_unclear":false}],"36":[{"brand_info":"1998 куб. см.","sum_rent_comment":"","brand":"Ford Transit","sum_comment":"","year":"1998","sum":"","sum_rent":""}]},"id":"vulyk_96_45","declaration":{"additional_info_text":"","notfull_lostpages":"","date":"2016-03-25T00:00:00","notfull":"","additional_info":"","url":"http://static.declarations.com.ua/declarations/chosen_ones/judges_batch/259_podzirov_andrii_olehovych_2015.pdf"},"liabilities":{"54":{"sum_foreign_comment":"","sum":"","sum_comment":"","sum_hidden":false,"sum_comment_hidden":false,"sum_foreign":""},"55":{"sum_foreign_comment":"","sum":"","sum_comment":"","sum_foreign":""},"56":{"sum_foreign_comment":"","sum":"","sum_comment":"","sum_unclear":false,"sum_foreign":""},"57":{"sum_foreign_comment":"","sum_comment_hidden":false,"sum":"","sum_comment":"","sum_foreign":""},"58":{"sum_foreign_comment":"","sum":"","sum_comment":"","sum_comment_hidden":false,"sum_unclear":false,"sum_foreign":""},"59":{"sum_foreign_comment":"","sum":"","sum_comment":"","sum_foreign":""},"60":{"sum_foreign_comment":"","sum_comment_hidden":false,"sum":"","sum_comment":"","sum_foreign":""},"61":{"sum_foreign_comment":"","sum":"","sum_comment":"","sum_foreign":""},"62":{"sum_foreign_comment":"","sum":"","sum_comment":"","sum_foreign":""},"63":{"sum_foreign_comment":"","sum_comment_hidden":false,"sum":"","sum_comment":"","sum_foreign":""},"64":{"sum_foreign_comment":"","sum_comment_hidden":false,"sum":"","sum_comment":"","sum_foreign":""}},"ft_src":"суддя луцького міськрайонного суду волинської області\nВолинська область\nЗагальний місцевий суд\nАндрій\nПодзірова І. В\nПодружжя\nПодзіров Д. А\nДитина\nПодзірова Д. А\nДитина\nОлегович\nПодзіров Андрій Олегович\nПодзіров\nПодзіров Андрій Олегович\nАндрій Олегович Подзіров\nАндрій Подзіров\nПодзіров Андрій Олегович\n1998 куб. см.\nChevrolet Evanda\n2004\n1998 куб. см.\n1998\nFord Transit\n54.8\n34\n64\n2015\n183420\n16013\n49004\n183420\n32991\n1998 куб. см.\nChevrolet Evanda\n2004\n1998 куб. см.\n1998\nFord Transit\n2015\nПодзіров Андрій Олегович\nАндрій Олегович Подзіров\nАндрій Подзіров\nПодзіров Андрій Олегович\nПодзіров Андрій Олегович\nАндрій\nПодзіров\nВолинська область\nсуддя луцького міськрайонного суду волинської області\nЗагальний місцевий суд\nОлегович\nПодружжя\nПодзірова І. В\nДитина\nПодзіров Д. А\nДитина\nПодзірова Д. А\n183420\n32991\n183420\n49004\n16013\n64\n54.8\n34\nПодзірова І. В\nПодружжя\nДитина\nПодзіров Д. А\nДитина\nПодзірова Д. А\nАндрій\nОлегович\nПодзіров\nПодзіров Андрій Олегович\nАндрій Олегович Подзіров\nАндрій Подзіров\nПодзіров Андрій Олегович\nсуддя луцького міськрайонного суду волинської області\nВолинська область\nЗагальний місцевий суд\nПодзіров Андрій Олегович\nChevrolet Evanda\n1998 куб. см.\n2004\nFord Transit\n1998 куб. см.\n1998\n16013\n32991\n49004\n183420\n183420\n54.8\n34\n64\n2015","general":{"inn":"","name":"Андрій","family":[{"inn":"","inn_hidden":true,"inn_unclear":false,"relations_hidden":false,"relations_other":"","relations":"Подружжя","name_hidden":true,"family_name":"Подзірова І. В","name_unclear":false},{"inn":"","relations":"Дитина","relations_other":"","inn_hidden":true,"family_name":"Подзіров Д. А","name_hidden":false,"name_unclear":false},{"inn":"","relations":"Дитина","relations_other":"","inn_hidden":true,"family_name":"Подзірова Д. А","name_unclear":false}],"patronymic":"Олегович","inn_hidden":true,"family_raw":"","last_name":"Подзіров","post":{"office":"Загальний місцевий суд","region":"Волинська область","office_unclear":false,"post":"суддя луцького міськрайонного суду волинської області"},"full_name":"Подзіров Андрій Олегович","addresses":[{"place_district":"","place_city_hidden":true,"place_city":"","place_city_type_hidden":false,"place_district_hidden":false,"place_city_type":"","place_address_hidden":true,"place_address":"","place_hidden":true,"place":""}],"patronymic_hidden":false,"full_name_suggest":{"output":"Подзіров Андрій Олегович","input":["Подзіров Андрій Олегович","Андрій Олегович Подзіров","Андрій Подзіров"]}},"source":"VULYK","estate":{"24":[{"space_unclear":false,"costs":"","costs_comment":"","address_hidden":false,"region_hidden":true,"space_comment":"","space_hidden":false,"space":"64","address":"","region":"","costs_rent_comment":"","space_comment_unclear":false,"space_units":"м²","costs_rent":""}],"31":[{"space_unclear":false,"address_hidden":true,"region_hidden":true,"space_comment":"","space_hidden":false,"space":"54.8","address":"","region":"","costs_property":"","costs_rent_comment":"","address_unclear":false,"space_units":"м²","costs_property_comment":"","costs_rent":""},{"costs_rent":"","region":"","costs_property":"","costs_rent_comment":"","address_unclear":false,"region_hidden":false,"space_comment":"","costs_property_comment":"","space_units":"м²","space":"34","address":""}]},"intro":{"declaration_year":"2015","isnotdeclaration":""}}