{"income":{"5":{"value":"186901.05","family_comment":"","value_unclear":false,"family_unclear":false,"family":"58656.54","comment":""},"6":{"value":"171855.05","family_comment":"","value_unclear":false,"family_unclear":false,"family":"57701.54","comment":""},"7":{"family_comment":"","value":"","source_name":"","family":"","comment":""},"8":{"family_comment":"","value":"","family":"","comment":""},"9":{"family_comment":"","value":"","value_unclear":false,"family":"","comment":""},"10":{"family_comment":"","value":"12180","value_unclear":false,"family":"","comment":""},"11":{"family_comment":"","value":"","family":"","comment":""},"12":{"family_comment":"","value":"","family":"","comment":""},"13":{"family_comment":"","value":"","value_unclear":false,"family":"","comment":""},"14":{"family_comment":"","value":"","family":"","comment":""},"15":{"family_comment":"","value":"","family":"","comment":""},"16":{"family_comment":"","value":"","family":"","comment":""},"17":{"family_comment":"","value":"","family":"","comment":""},"18":{"family_comment":"","value":"","family":"","comment":""},"19":{"family_comment":"","value":"","family":"","comment":""},"20":{"family_comment":"","family_unclear":false,"value":"2866","family":"955","comment":""}},"vehicle":{"40":[{"brand_info":"1.8 л 250 к. с","sum":"","brand":"Skoda Octavia","sum_comment":"","brand_unclear":false,"year":"2007","brand_info_hidden":false,"brand_info_unclear":false,"year_unclear":false,"sum_rent_comment":"","sum_rent":""}]},"id":"vulyk_85_32","declaration":{"additional_info_text":"","notfull_lostpages":"","date":"2015-03-16T00:00:00","notfull":"","additional_info":"","url":"http://static.declarations.com.ua/declarations/chosen_ones/judges_batch/2635_zahatska__tetiana_vasylivna.pdf"},"liabilities":{"54":{"sum_foreign_comment":"","sum":"","sum_comment":"","sum_comment_unclear":false,"sum_foreign":""},"55":{"sum_foreign_comment":"","sum":"","sum_comment":"","sum_foreign":""},"56":{"sum_foreign_comment":"","sum":"","sum_comment":"","sum_unclear":false,"sum_foreign":""},"57":{"sum_foreign_comment":"","sum":"","sum_comment":"","sum_foreign":""},"58":{"sum_foreign_comment":"","sum_comment":"","sum":"","sum_comment_hidden":false,"sum_foreign":""},"59":{"sum_foreign_comment":"","sum":"","sum_comment":"","sum_foreign":""},"60":{"sum_foreign_comment":"","sum":"","sum_comment":"","sum_foreign":""},"61":{"sum_foreign_comment":"","sum":"","sum_comment":"","sum_foreign":""},"62":{"sum_foreign_comment":"","sum":"","sum_comment":"","sum_unclear":false,"sum_foreign":""},"63":{"sum_foreign_comment":"","sum":"","sum_comment":"","sum_unclear":false,"sum_foreign":""},"64":{"sum_foreign_comment":"","sum":"","sum_comment":"","sum_foreign":""}},"ft_src":"Skoda Octavia\n1.8 л 250 к. с\n2007\n2014\n57701.54\n171855.05\n12180\n58656.54\n186901.05\n955\n2866\n1.8 л 250 к. с\n2007\nSkoda Octavia\n2014\nЗагацька Тетяна Василівна\nТетяна Василівна Загацька\nТетяна Загацька\nЗагацька Тетяна Василівна\nТетяна\nПодружжя\nДитина\nЗагацька Тетяна Василівна\nЗагацька\nАдміністративний місцевий суд\nсуддя донецького окружного адміністративного суду\nДонецька область\nВасилівна\n171855.05\n57701.54\n2866\n955\n186901.05\n58656.54\n12180\nПодружжя\nДитина\nВасилівна\nЗагацька\nТетяна\nЗагацька Тетяна Василівна\nТетяна Василівна Загацька\nТетяна Загацька\nЗагацька Тетяна Василівна\nсуддя донецького окружного адміністративного суду\nДонецька область\nАдміністративний місцевий суд\nЗагацька Тетяна Василівна","general":{"inn":"","name":"Тетяна","last_name_hidden":false,"family":[{"inn":"","inn_hidden":false,"relations_unclear":false,"relations_hidden":false,"relations_other":"","relations":"Подружжя","name_hidden":true,"family_name":"","name_unclear":false},{"inn":"","inn_hidden":false,"family_name":"","relations_other":"","relations":"Дитина","name_hidden":false,"name_unclear":false}],"patronymic":"Василівна","inn_hidden":true,"family_raw":"","last_name":"Загацька","post":{"post_unclear":false,"post_hidden":false,"post":"суддя донецького окружного адміністративного суду","region":"Донецька область","office":"Адміністративний місцевий суд"},"full_name_suggest":{"output":"Загацька Тетяна Василівна","input":["Загацька Тетяна Василівна","Тетяна Василівна Загацька","Тетяна Загацька"]},"full_name":"Загацька Тетяна Василівна","addresses":[{"place_district":"","place_address_hidden":true,"place_city":"","place_address":"","place_district_hidden":false,"place_city_type":"","place_city_hidden":true,"place_city_type_hidden":false,"place_hidden":true,"place":""}],"last_name_unclear":false},"source":"VULYK","intro":{"declaration_year":"2014","isnotdeclaration":""}}