{"income":{"5":{"family_comment":"","family_unclear":false,"value":"163710","family":"15560","comment":""},"6":{"value":"163710","family_comment":"","value_unclear":false,"family_unclear":false,"family":"","comment":""},"7":{"value":"","family_comment":"","value_unclear":false,"family_unclear":false,"source_name":"","family":"","comment":"","source_name_hidden":false},"8":{"family_comment":"","value":"","family":"","comment":""},"9":{"family_comment":"","value":"","family":"1495","comment":""},"10":{"family_comment":"","value":"","value_unclear":false,"family":"","comment":""},"11":{"family_comment":"","value":"","family":"","comment":""},"12":{"family_comment":"","value":"","family":"","comment":""},"13":{"family_comment":"","value":"","family":"","comment":""},"14":{"family_comment":"","value":"","family":"","comment":""},"15":{"family_comment":"","value":"","family":"","comment":""},"16":{"family_comment":"","value":"","family":"","comment":""},"17":{"family_comment":"","value":"","family":"","comment":""},"18":{"family_comment":"","value":"","family":"","comment":""},"19":{"family_comment":"","value":"","family":"","comment":""},"20":{"value":"","value_unclear":false,"comment_hidden":false,"family_comment":"","comment_unclear":false,"comment":"","family":"14065"}},"id":"vulyk_96_53","banks":{"51":[{"sum_foreign_comment":"","sum_unclear":false,"sum_units":"UAH","sum_comment":"Промислово-інвестиційний банк України","sum_hidden":false,"sum_foreign_units":"UAH","sum_comment_hidden":false,"sum_foreign_hidden":false,"sum":"77664.83","sum_foreign":""}]},"declaration":{"additional_info_text":"","notfull_lostpages":"","date":"2016-03-01T00:00:00","notfull":"","additional_info":"","url":"http://static.declarations.com.ua/declarations/chosen_ones/judges_batch/267_lipchanskyi_serhii_mykolaiovych_2015.pdf"},"liabilities":{"54":{"sum_foreign_comment":"","sum":"","sum_comment":"","sum_hidden":false,"sum_comment_hidden":false,"sum_foreign":""},"55":{"sum_foreign_comment":"","sum":"","sum_comment":"","sum_foreign":""},"56":{"sum_foreign_comment":"","sum":"","sum_comment":"","sum_unclear":false,"sum_foreign":""},"57":{"sum_foreign_comment":"","sum_comment":"","sum":"","sum_comment_hidden":false,"sum_foreign":""},"58":{"sum_foreign_comment":"","sum":"","sum_comment":"","sum_comment_hidden":false,"sum_unclear":false,"sum_foreign":""},"59":{"sum_foreign_comment":"","sum":"","sum_comment":"","sum_foreign":""},"60":{"sum_foreign_comment":"","sum_comment":"","sum":"","sum_comment_hidden":false,"sum_foreign":""},"61":{"sum_foreign_comment":"","sum":"","sum_comment":"","sum_foreign":""},"62":{"sum_foreign_comment":"","sum":"","sum_comment":"","sum_foreign":""},"63":{"sum_foreign_comment":"","sum_comment":"","sum":"","sum_comment_hidden":false,"sum_foreign":""},"64":{"sum_foreign_comment":"","sum_comment":"","sum":"","sum_comment_hidden":false,"sum_foreign":""}},"ft_src":"Промислово-інвестиційний банк України\n77664.83\nСпільна часткова власність 1/4\nДонецька область\nм. Донецьк, вул. Богдана Хмельницького, 92 кв. 54\n74\nособиста власність\nм. Донецьк, вул. Куйбишева, б. 244 кв. 14\n48\nДонецька область\n2015\n163710\n1495\n15560\n163710\n14065\nПромислово-інвестиційний банк України\n77664.83\n2015\nЛіпчанський Сергій Миколайович\nСергій Миколайович Ліпчанський\nСергій Ліпчанський\nЛіпчанський Сергій Миколайович\nЛіпчанський Сергій Миколайович\n2934707695\nСергій\nЛіпчанський\nДонецька область\nсуддя мар'їнського районного суду донецької області\nЗагальний місцевий суд\nМиколайович\nМісце проживання: 85612, м, Курахове, вул. Лермонтова, б. 1 кв. 1, зареєстрований: м. Донецьк, вул. Куйбишева, б. 244 кв. 14\nДонецька область\nДонецьк\nПодружжя\nЛіпчанська Ю. Я. 26. 10. 1978\n2878800085\nДитина\nЛіпчанська Е. С. 01. 12. 2012\n4124302228\n163710\n14065\n163710\n15560\n1495\nСпільна часткова власність 1/4\nм. Донецьк, вул. Богдана Хмельницького, 92 кв. 54\nДонецька область\n74\nособиста власність\n48\nм. Донецьк, вул. Куйбишева, б. 244 кв. 14\nДонецька область\n2878800085\nЛіпчанська Ю. Я. 26. 10. 1978\nПодружжя\n4124302228\nДитина\nЛіпчанська Е. С. 01. 12. 2012\n2934707695\nСергій\nМиколайович\nЛіпчанський\nЛіпчанський Сергій Миколайович\nСергій Миколайович Ліпчанський\nСергій Ліпчанський\nЛіпчанський Сергій Миколайович\nДонецька область\nДонецьк\nМісце проживання: 85612, м, Курахове, вул. Лермонтова, б. 1 кв. 1, зареєстрований: м. Донецьк, вул. Куйбишева, б. 244 кв. 14\nсуддя мар'їнського районного суду донецької області\nДонецька область\nЗагальний місцевий суд\nЛіпчанський Сергій Миколайович","general":{"inn":"2934707695","name":"Сергій","family":[{"inn":"2878800085","inn_hidden":false,"inn_unclear":false,"relations_hidden":false,"relations_other":"","relations":"Подружжя","name_hidden":false,"family_name":"Ліпчанська Ю. Я. 26. 10. 1978","name_unclear":false},{"inn":"4124302228","relations":"Дитина","relations_other":"","inn_hidden":false,"family_name":"Ліпчанська Е. С. 01. 12. 2012","name_hidden":false,"name_unclear":false}],"patronymic":"Миколайович","inn_hidden":false,"family_raw":"","last_name":"Ліпчанський","post":{"office":"Загальний місцевий суд","region":"Донецька область","office_unclear":false,"post":"суддя мар'їнського районного суду донецької області"},"full_name":"Ліпчанський Сергій Миколайович","addresses":[{"place_district":"","place_address_hidden":false,"place_city":"Донецьк","place_address":"Місце проживання: 85612, м, Курахове, вул. Лермонтова, б. 1 кв. 1, зареєстрований: м. Донецьк, вул. Куйбишева, б. 244 кв. 14","place_district_hidden":false,"place_city_type":"Місто","place_city_hidden":false,"place_city_type_hidden":false,"place_hidden":false,"place":"Донецька область"}],"patronymic_hidden":false,"full_name_suggest":{"output":"Ліпчанський Сергій Миколайович","input":["Ліпчанський Сергій Миколайович","Сергій Миколайович Ліпчанський","Сергій Ліпчанський"]}},"source":"VULYK","estate":{"25":[{"space_comment_unclear":false,"space_unclear":false,"costs":"","costs_comment":"","address_hidden":false,"region_hidden":false,"space_comment":"особиста власність","space_hidden":false,"space":"48","address":"м. Донецьк, вул. Куйбишева, б. 244 кв. 14","costs_rent_comment_unclear":false,"region":"Донецька область","address_unclear":false,"costs_rent_comment":"","costs_unclear":false,"space_comment_hidden":false,"space_units":"м²","costs_rent":""}],"31":[{"space_unclear":false,"address_hidden":false,"region_hidden":false,"space_comment":"Спільна часткова власність 1/4","space_hidden":false,"space":"74","address":"м. Донецьк, вул. Богдана Хмельницького, 92 кв. 54","region":"Донецька область","costs_property":"","costs_rent_comment":"","address_unclear":false,"space_units":"м²","costs_property_comment":"","costs_rent":""}]},"intro":{"declaration_year":"2015","isnotdeclaration":""}}