{"income":{"5":{"value":"169765","family_comment":"","value_unclear":false,"family_unclear":false,"family":"","comment":""},"6":{"value":"169628","family_comment":"","value_unclear":false,"family_unclear":false,"family":"","comment":""},"7":{"family_comment":"","value":"","source_name":"","family":"","comment":""},"8":{"family_comment":"","value":"","family":"","comment":""},"9":{"family_comment":"","value":"137","family":"","comment":""},"10":{"family_comment":"","value":"","family":"","comment":""},"11":{"family_comment":"","value":"","family":"","comment":""},"12":{"family_comment":"","value":"","family":"","comment":""},"13":{"family_comment":"","value":"","family":"","comment":""},"14":{"family_comment":"","value":"","family":"","comment":""},"15":{"family_comment":"","value":"","value_unclear":false,"family":"","comment":""},"16":{"family_comment":"","value":"","family":"","comment":""},"17":{"family_comment":"","value":"","family":"","comment":""},"18":{"family_comment":"","value":"","family":"","comment":""},"19":{"family_comment":"","value":"","family":"","comment":""},"20":{"value":"","family_comment":"","value_unclear":false,"family_unclear":false,"family":"","comment":"","family_comment_unclear":false}},"id":"vulyk_99_101","declaration":{"date":"2016-03-28T00:00:00","notfull":"","url":"http://static.declarations.com.ua/declarations/chosen_ones/judges_batch/650_mostepanenko_iuliia_ivanivna_2015.pdf","notfull_lostpages":""},"liabilities":{"54":{"sum_foreign_comment":"","sum":"","sum_comment":"","sum_comment_unclear":false,"sum_comment_hidden":false,"sum_foreign":""},"55":{"sum_foreign_comment":"","sum":"","sum_comment":"","sum_foreign":""},"56":{"sum_foreign_comment":"","sum":"","sum_comment":"","sum_foreign":""},"57":{"sum_foreign_comment":"","sum_comment_hidden":false,"sum":"","sum_comment":"","sum_foreign":""},"58":{"sum_foreign_comment":"","sum_comment_hidden":false,"sum":"","sum_comment":"","sum_foreign":""},"59":{"sum_foreign_comment":"","sum":"","sum_comment":"","sum_comment_hidden":false,"sum_unclear":false,"sum_foreign":""},"60":{"sum_foreign_comment":"","sum_comment_hidden":false,"sum":"","sum_comment":"","sum_foreign":""},"61":{"sum_foreign_comment":"","sum":"","sum_comment":"","sum_foreign":""},"62":{"sum_foreign_comment":"","sum":"","sum_comment":"","sum_foreign":""},"63":{"sum_foreign_comment":"","sum_comment_hidden":false,"sum":"","sum_comment":"","sum_foreign":""},"64":{"sum_foreign_comment":"","sum_comment_hidden":false,"sum":"","sum_comment":"","sum_foreign":""}},"ft_src":"Мостепаненко Юлія Іванівна\nсуддя господарського суду одеської області\nОдеська область\nГосподарський місцевий суд\nЮлія\nМостепаненко А. С\nПодружжя\nМостепаненко Юлія Іванівна\nЮлія Іванівна Мостепаненко\nЮлія Мостепаненко\nМостепаненко Юлія Іванівна\nМостепаненко\nІванівна\n137\n169765\n169628\nОдеська область\nм. Одеса\n72.8\n2015\n169628\n137\n169765\n169628\n169765\n137\nМостепаненко\nМостепаненко Юлія Іванівна\nЮлія Іванівна Мостепаненко\nЮлія Мостепаненко\nМостепаненко Юлія Іванівна\nЮлія\nІванівна\nМостепаненко Юлія Іванівна\nГосподарський місцевий суд\nсуддя господарського суду одеської області\nОдеська область\nПодружжя\nМостепаненко А. С\n72.8\nОдеська область\nм. Одеса\n2015\nМостепаненко А. С\nПодружжя\nІванівна\nМостепаненко\nсуддя господарського суду одеської області\nОдеська область\nГосподарський місцевий суд\nМостепаненко Юлія Іванівна\nМостепаненко Юлія Іванівна\nЮлія Іванівна Мостепаненко\nЮлія Мостепаненко\nМостепаненко Юлія Іванівна\nЮлія\nм. Одеса\nОдеська область\n72.8\n2015","general":{"inn":"","inn_hidden":true,"last_name":"Мостепаненко","post":{"post_unclear":false,"office":"Господарський місцевий суд","post":"суддя господарського суду одеської області","region":"Одеська область"},"name":"Юлія","full_name":"Мостепаненко Юлія Іванівна","family_raw":"","addresses":[{"place_district":"","place_city_hidden":true,"place_city":"","place_city_type_hidden":false,"place_district_hidden":false,"place_city_type":"","place_address_hidden":true,"place_address":"","place_hidden":true,"place":""}],"family":[{"inn_hidden":true,"inn":"","name_hidden":true,"family_name":"Мостепаненко А. С","relations":"Подружжя","name_unclear":false}],"full_name_suggest":{"output":"Мостепаненко Юлія Іванівна","input":["Мостепаненко Юлія Іванівна","Юлія Іванівна Мостепаненко","Юлія Мостепаненко"]},"patronymic":"Іванівна"},"source":"VULYK","estate":{"31":[{"costs_rent":"","region":"Одеська область","costs_property":"","costs_rent_comment":"","address_hidden":true,"region_hidden":false,"space_comment":"","costs_property_comment":"","space_units":"м²","space":"72.8","address":"м. Одеса"}]},"intro":{"declaration_year":"2015"}}