{"income":{"5":{"value":"249474","family_comment":"","value_unclear":false,"family":"46800","family_unclear":false,"comment_unclear":false,"comment":"","family_comment_unclear":false},"6":{"value":"249474","family_comment":"","value_unclear":false,"family_unclear":false,"family":"46800","comment":""},"7":{"source_name_unclear":false,"value":"","value_unclear":false,"family_comment":"","source_name":"","family":"","comment":"","source_name_hidden":false},"8":{"family_comment":"","value":"","family":"","comment":""},"9":{"family_comment":"","value":"","family":"","comment":""},"10":{"family_comment":"","value":"","value_unclear":false,"family":"","comment":""},"11":{"value":"","value_unclear":false,"value_hidden":false,"family_comment":"","family":"","comment":""},"12":{"family_comment":"","value":"","family":"","comment":"","value_hidden":false},"13":{"family_comment":"","value":"","family":"","comment":""},"14":{"family_comment":"","value":"","family":"","comment":""},"15":{"family_comment":"","value":"","family":"","comment":""},"16":{"family_comment":"","value":"","family":"","comment":""},"17":{"family_comment":"","value":"","family":"","comment":""},"18":{"family_comment":"","value":"","family":"","comment":""},"19":{"family_comment":"","family_unclear":false,"value":"","family":"","comment":""},"20":{"family_comment":"","family_unclear":false,"value":"","family":"","comment":""}},"vehicle":{"35":[{"year_hidden":false,"brand_info":"1968 куб. см.","sum_rent_comment":"","year":"2013","sum_hidden":false,"brand_info_hidden":false,"brand_info_unclear":false,"year_unclear":false,"sum_rent":"","sum":"362986","brand":"Volkswagen Tiguan","sum_comment":"","brand_unclear":false,"brand_hidden":false}],"36":[{"brand_info":"2.0 л","sum_rent_comment":"","brand":"Volkswagen Amarok","sum_comment":"","year":"2011","sum":"151377","sum_rent":""}]},"id":"vulyk_61_122","declaration":{"additional_info_text":"","notfull_lostpages":"","date":"2015-03-30T00:00:00","notfull":"","additional_info":"","url":"http://static.declarations.com.ua/declarations/chosen_ones/mega_batch/vyshar_ihor_iuriiovych.pdf"},"liabilities":{"54":{"sum_foreign_comment":"","sum":"","sum_comment":"","sum_comment_unclear":false,"sum_unclear":false,"sum_foreign":""},"55":{"sum_foreign_comment":"","sum":"","sum_comment":"","sum_foreign":""},"56":{"sum_foreign_comment":"","sum":"","sum_comment":"","sum_unclear":false,"sum_foreign":""},"57":{"sum_foreign_comment":"","sum":"45445","sum_comment":"","sum_comment_hidden":false,"sum_unclear":false,"sum_foreign":""},"58":{"sum_foreign_comment":"","sum":"27010","sum_comment":"","sum_unclear":false,"sum_foreign":""},"59":{"sum_foreign_comment":"","sum":"","sum_comment":"","sum_foreign":""},"60":{"sum_foreign_comment":"","sum_foreign_hidden":false,"sum_comment":"","sum_hidden":false,"sum":"","sum_foreign":""},"61":{"sum_foreign_comment":"","sum":"","sum_comment":"","sum_foreign":""},"62":{"sum_foreign_comment":"","sum":"","sum_comment":"","sum_unclear":false,"sum_foreign":""},"63":{"sum_foreign_comment":"","sum":"","sum_comment":"","sum_hidden":false,"sum_unclear":false,"sum_foreign":""},"64":{"sum_foreign_comment":"","sum":"","sum_hidden":false,"sum_comment":"","sum_foreign":""}},"ft_src":"45445\n27010\nсуддя вінницького міського суду вінницької області\nВінницька область\nЗагальний місцевий суд\nІгор\nВишар С. П\nПодружжя\nЮрійович\nВишар\nВишар Ігор Юрійович\nВишар Ігор Юрійович\nІгор Юрійович Вишар\nІгор Вишар\nВишар Ігор Юрійович\n1968 куб. см.\nVolkswagen Tiguan\n2013\n362986\n2.0 л\n151377\n2011\nVolkswagen Amarok\n2204\n2014\n46800\n249474\n46800\n249474\n1968 куб. см.\nVolkswagen Tiguan\n2013\n362986\n2.0 л\nVolkswagen Amarok\n2011\n151377\n2204\nПодружжя\nВишар С. П\nВишар Ігор Юрійович\nІгор Юрійович Вишар\nІгор Вишар\nВишар Ігор Юрійович\nІгор\nВишар Ігор Юрійович\nВишар\nВінницька область\nЗагальний місцевий суд\nсуддя вінницького міського суду вінницької області\nЮрійович\n45445\n27010\n46800\n249474\n249474\n46800\n2014\n27010\n45445\nВишар С. П\nПодружжя\nЮрійович\nВишар\nВишар Ігор Юрійович\nІгор Юрійович Вишар\nІгор Вишар\nВишар Ігор Юрійович\nВінницька область\nсуддя вінницького міського суду вінницької області\nЗагальний місцевий суд\nВишар Ігор Юрійович\nІгор\nVolkswagen Tiguan\n362986\n1968 куб. см.\n2013\n151377\nVolkswagen Amarok\n2.0 л\n2011\n249474\n46800\n249474\n46800\n2204\n2014","general":{"inn":"","name":"Ігор","patronymic_unclear":false,"family":[{"inn":"","inn_hidden":true,"relations_unclear":false,"relations_hidden":false,"relations_other":"","relations":"Подружжя","name_hidden":true,"family_name":"Вишар С. П","name_unclear":false}],"patronymic":"Юрійович","inn_hidden":true,"family_raw":"","inn_unclear":false,"post":{"post_unclear":false,"region_unclear":false,"post":"суддя вінницького міського суду вінницької області","office":"Загальний місцевий суд","region":"Вінницька область","post_hidden":false,"office_hidden":false,"region_hidden":false},"last_name_unclear":false,"full_name":"Вишар Ігор Юрійович","addresses":[{"place_address":"","place_district_hidden":true,"place_city_type":"","place_city_hidden":true,"place_address_unclear":false,"place_city_type_hidden":false,"place_hidden":true,"place":"","place_district":"","place_address_hidden":true,"place_city":"","place_district_unclear":false}],"last_name":"Вишар","patronymic_hidden":false,"full_name_suggest":{"output":"Вишар Ігор Юрійович","input":["Вишар Ігор Юрійович","Ігор Юрійович Вишар","Ігор Вишар"]},"name_unclear":false},"source":"VULYK","estate":{"23":[{"region_unclear":false,"space_unclear":false,"costs":"","costs_comment":"","address_hidden":true,"region_hidden":true,"space_comment":"","space":"2204","address":"","region":"","address_unclear":false,"costs_rent_comment":"","space_comment_unclear":false,"space_units":"м²","space_units_unclear":false,"costs_rent":""}]},"intro":{"declaration_year":"2014","isnotdeclaration":"","declaration_year_hidden":false}}