{"income":{"5":{"value":"70295","family_comment":"","value_unclear":false,"family_unclear":false,"family":"10320","comment":""},"6":{"value":"70295","family_comment":"","value_unclear":false,"family_unclear":false,"family":"","comment":""},"7":{"family_comment":"","value":"","source_name":"","family":"","comment":""},"8":{"family_comment":"","value":"","family":"","comment":""},"9":{"family_comment":"","value":"","family":"","comment":""},"10":{"family_comment":"","value":"","family":"","comment":""},"11":{"family_comment":"","value":"","family":"","comment":""},"12":{"family_comment":"","value":"","family":"","comment":""},"13":{"family_comment":"","value":"","family":"","comment":""},"14":{"family_comment":"","value":"","family":"","comment":""},"15":{"family_comment":"","value":"","value_unclear":false,"family":"","comment":""},"16":{"family_comment":"","value":"","family":"","comment":""},"17":{"family_comment":"","value":"","family":"","comment":""},"18":{"family_comment":"","value":"","family":"","comment":""},"19":{"family_comment":"","value":"","family":"","comment":""},"20":{"value":"","family_comment":"","value_unclear":false,"family_unclear":false,"family":"10320","comment":"","family_comment_unclear":false}},"vehicle":{"35":[{"brand_info":"3456 куб. см.","sum_rent_comment":"","brand":"Lexus ES 350","sum_comment":"","brand_unclear":false,"year":"2008","brand_info_unclear":false,"sum":"","sum_rent":""}],"40":[{"brand_info":"","sum_rent_comment":"","brand":"Honda Civic","sum_comment":"","brand_unclear":false,"year":"1988","brand_info_hidden":false,"brand_info_unclear":false,"sum":"","sum_rent":""},{"brand_info":"","sum":"","brand":"Ford Festiva","sum_comment":"","year":"1989","sum_rent_comment":"","sum_rent":""},{"brand_info":"","sum":"","brand":"Peugeot 405","sum_comment":"","year":"1991","sum_rent_comment":"","sum_rent":""}]},"id":"vulyk_99_110","declaration":{"date":"2016-04-18T00:00:00","notfull":"","notfull_lostpages":"","url":"http://static.declarations.com.ua/declarations/chosen_ones/judges_batch/659_smelianets_hanna_ievheniivna_2015.pdf"},"liabilities":{"54":{"sum_foreign_comment":"","sum":"","sum_comment":"","sum_comment_unclear":false,"sum_comment_hidden":false,"sum_foreign":""},"55":{"sum_foreign_comment":"","sum":"","sum_comment":"","sum_foreign":""},"56":{"sum_foreign_comment":"","sum":"","sum_comment":"","sum_foreign":""},"57":{"sum_foreign_comment":"","sum_comment":"","sum":"","sum_comment_hidden":false,"sum_foreign":""},"58":{"sum_foreign_comment":"","sum_comment":"","sum":"","sum_comment_hidden":false,"sum_foreign":""},"59":{"sum_foreign_comment":"","sum":"","sum_comment":"","sum_comment_hidden":false,"sum_unclear":false,"sum_foreign":""},"60":{"sum_foreign_comment":"","sum_comment":"","sum":"","sum_comment_hidden":false,"sum_foreign":""},"61":{"sum_foreign_comment":"","sum":"","sum_comment":"","sum_foreign":""},"62":{"sum_foreign_comment":"","sum":"","sum_comment":"","sum_foreign":""},"63":{"sum_foreign_comment":"","sum_comment":"","sum":"","sum_comment_hidden":false,"sum_foreign":""},"64":{"sum_foreign_comment":"","sum_comment":"","sum":"","sum_comment_hidden":false,"sum_foreign":""}},"ft_src":"2008\nLexus ES 350\n3456 куб. см.\nHonda Civic\n1988\n1989\nFord Festiva\n1991\nPeugeot 405\nОдеська область\nм. Одеса\n21\nм. Одеса\nОдеська область\n21\n2015\n70295\n10320\n70295\n10320\n3456 куб. см.\nLexus ES 350\n2008\n1988\nHonda Civic\n1989\nFord Festiva\n1991\nPeugeot 405\n2015\nСмелянець\nСмелянець Ганна Євгеніївна\nГанна Євгеніївна Смелянець\nГанна Смелянець\nСмелянець Ганна Євгеніївна\nГанна\nЄвгеніївна\nСмелянець Ганна Євгеніївна\nГосподарський місцевий суд\nсуддя господарського суду одеської області\nОдеська область\nПодружжя\nСмелянець В. І\nДитина\nСмелянець В. В\n70295\n10320\n70295\n10320\n21\nОдеська область\nм. Одеса\n21\nм. Одеса\nОдеська область\nСмелянець В. І\nПодружжя\nСмелянець В. В\nДитина\nЄвгеніївна\nСмелянець\nсуддя господарського суду одеської області\nОдеська область\nГосподарський місцевий суд\nСмелянець Ганна Євгеніївна\nСмелянець Ганна Євгеніївна\nГанна Євгеніївна Смелянець\nГанна Смелянець\nСмелянець Ганна Євгеніївна\nГанна","general":{"inn":"","inn_hidden":true,"last_name":"Смелянець","post":{"post_unclear":false,"office":"Господарський місцевий суд","post":"суддя господарського суду одеської області","region":"Одеська область"},"name":"Ганна","full_name":"Смелянець Ганна Євгеніївна","family_raw":"","addresses":[{"place_district":"","place_address_hidden":true,"place_city":"","place_address":"","place_district_hidden":false,"place_city_type":"","place_city_hidden":true,"place_city_type_hidden":false,"place_hidden":true,"place":""}],"family":[{"inn":"","relations":"Подружжя","name_hidden":true,"inn_hidden":true,"family_name":"Смелянець В. І","name_unclear":false},{"inn":"","inn_hidden":false,"family_name":"Смелянець В. В","relations_other":"","relations":"Дитина","name_unclear":false}],"full_name_suggest":{"output":"Смелянець Ганна Євгеніївна","input":["Смелянець Ганна Євгеніївна","Ганна Євгеніївна Смелянець","Ганна Смелянець"]},"patronymic":"Євгеніївна"},"source":"VULYK","estate":{"25":[{"space_unclear":false,"costs":"","costs_comment":"","address_hidden":true,"region_hidden":false,"space_comment":"","space_hidden":false,"space":"21","address":"м. Одеса","region":"Одеська область","costs_rent_comment":"","space_units":"м²","costs_rent":""}],"31":[{"costs_rent":"","region":"Одеська область","costs_property":"","costs_rent_comment":"","address_hidden":true,"region_hidden":false,"space_comment":"","costs_property_comment":"","space_units":"м²","space":"21","address":"м. Одеса"}]},"intro":{"declaration_year":"2015"}}