{"id":"vulyk_103_95","ft_src":"мопед, об'єм циліндрів двигуна 48\n2008\nMusstang\nоб'єм циліндрів 2700 куб. см., потужність 136 кВт , викрадено 16.01.2015 р\nToyota Venza\n2013\n2011\nоб'єм циліндрів 1500 куб. см, потужність 77 кВт\nDaihatsu Terios\n108\n86\n80\n108\n2015\n259968.77\n108500\n259968.77\n108500\nоб'єм циліндрів 2700 куб. см., потужність 136 кВт , викрадено 16.01.2015 р\n2013\nToyota Venza\nоб'єм циліндрів 1500 куб. см, потужність 77 кВт\n2011\nDaihatsu Terios\nмопед, об'єм циліндрів двигуна 48\n2008\nMusstang\n108\n86\n80\n108\nФурик\nФурик Юрій Петрович\nЮрій Петрович Фурик\nЮрій Фурик\nФурик Юрій Петрович\nФурик Юрій Петрович\nПетрович\nБатьки\nФурик Марія Петрівна\nФурик Всеволод Юрійович\nДитина\nПодружжя\nФурик Валентина Борисівна\nЮрій\nВищий спеціалізований суд з розгляду цивільних і кримінальних справ\nсуддя вищого спецiалiзованого суду україни з розгляду цивiльних і кримiнальних справ\nЗагальнодержавний регіон\n259968.77\n108500\n259968.77\n108500\n2015\nБатьки\nФурик Марія Петрівна\nДитина\nФурик Всеволод Юрійович\nПодружжя\nФурик Валентина Борисівна\nФурик\nПетрович\nсуддя вищого спецiалiзованого суду україни з розгляду цивiльних і кримiнальних справ\nВищий спеціалізований суд з розгляду цивільних і кримінальних справ\nЗагальнодержавний регіон\nФурик Юрій Петрович\nФурик Юрій Петрович\nЮрій Петрович Фурик\nЮрій Фурик\nФурик Юрій Петрович\nЮрій","estate":{"25":[{"address":"","space_units":"м²","costs_comment":"","region_hidden":true,"space_comment":"","address_hidden":false,"space_comment_hidden":false,"space":"80","space_comment_unclear":false,"costs_rent_comment":"","costs":"","region":"","costs_rent":""},{"costs":"","address":"","space_units":"м²","costs_rent_comment":"","space":"108","space_comment":"","region_hidden":false,"costs_comment":"","region":"","costs_rent":""}],"31":[{"costs_property_comment":"","address":"","space_units":"м²","space_hidden":false,"region_hidden":true,"costs_property":"","space_comment":"","address_hidden":false,"address_unclear":false,"costs_rent_comment":"","space":"108","costs_rent":""},{"address_hidden":false,"costs_property_comment":"","address":"","space_units":"м²","costs_rent_comment":"","space_hidden":false,"costs_property":"","space_comment":"","space":"86","space_comment_unclear":false,"costs_rent":""}]},"vehicle":{"39":[{"sum_comment":"","brand_info_hidden":false,"brand_info":"мопед, об'єм циліндрів двигуна 48","sum":"","sum_rent_comment":"","year":"2008","brand":"Musstang","sum_rent":""}],"40":[{"year_hidden":false,"brand_info":"об'єм циліндрів 2700 куб. см., потужність 136 кВт , викрадено 16.01.2015 р","sum":"","sum_rent_comment":"","brand_hidden":false,"brand":"Toyota Venza","sum_rent":"","sum_comment":"","year":"2013","brand_info_unclear":false},{"sum_comment":"","brand_info_hidden":false,"brand_info":"об'єм циліндрів 1500 куб. см, потужність 77 кВт","sum":"","sum_rent_comment":"","year":"2011","brand":"Daihatsu Terios","sum_rent":"","brand_info_unclear":false}]},"source":"VULYK","income":{"5":{"family_comment":"","family":"108500","comment":"","value_unclear":false,"family_hidden":false,"value":"259968.77"},"6":{"family_comment":"","value":"259968.77","family":"","comment":""},"7":{"family":"","family_comment":"","value":"","comment":"","source_name":""},"8":{"family_comment":"","value":"","family":"","comment":""},"9":{"family_comment":"","value":"","family":"","comment":""},"10":{"family_comment":"","value":"","family":"","comment":""},"11":{"family_comment":"","family_hidden":false,"value":"","family":"","comment":""},"12":{"family_comment":"","value":"","family":"","comment":""},"13":{"family_comment":"","value":"","family":"","comment":""},"14":{"family_comment":"","value":"","family":"","comment":""},"15":{"family_comment":"","value":"","family":"","comment":""},"16":{"family_comment":"","value":"","family":"","comment":""},"17":{"family_comment":"","value":"","family":"","comment":"","family_comment_unclear":false},"18":{"family_comment":"","value":"","family":"","comment":""},"19":{"family_comment":"","value":"","family":"","comment":""},"20":{"family_comment":"","family":"108500","comment":"","family_unclear":false,"family_hidden":false,"value":""}},"general":{"inn":"","addresses":[{"place_city_type_hidden":false,"place_city_type":"","place_city_hidden":true,"place_hidden":true,"place_district":"","place_district_hidden":false,"place":"","place_city":"","place_address_hidden":true,"place_address":""}],"last_name":"Фурик","full_name":"Фурик Юрій Петрович","family":[{"inn":"","family_name":"Фурик Марія Петрівна","relations_hidden":false,"name_unclear":false,"relations":"Батьки","inn_hidden":true,"name_hidden":true,"relations_other":""},{"inn":"","family_name":"Фурик Всеволод Юрійович","inn_hidden":false,"relations_other":"","relations":"Дитина"},{"inn":"","family_name":"Фурик Валентина Борисівна","relations_other":"","name_unclear":false,"inn_hidden":false,"relations":"Подружжя"}],"patronymic":"Петрович","inn_hidden":true,"name":"Юрій","post":{"office":"Вищий спеціалізований суд з розгляду цивільних і кримінальних справ","region_unclear":false,"post":"суддя вищого спецiалiзованого суду україни з розгляду цивiльних і кримiнальних справ","region":"Загальнодержавний регіон","office_unclear":false},"family_raw":"","full_name_suggest":{"input":["Фурик Юрій Петрович","Юрій Петрович Фурик","Юрій Фурик"],"output":"Фурик Юрій Петрович"}},"liabilities":{"54":{"sum_foreign_comment_hidden":false,"sum_foreign_comment_unclear":false,"sum_hidden":false,"sum":"","sum_foreign_comment":"","sum_comment":"","sum_unclear":false,"sum_foreign":"","sum_comment_hidden":false,"sum_foreign_hidden":false},"55":{"sum_comment":"","sum_foreign_comment":"","sum_foreign":"","sum":""},"56":{"sum_comment":"","sum_foreign_comment":"","sum_foreign":"","sum":""},"57":{"sum_comment":"","sum_hidden":false,"sum":"","sum_foreign_comment":"","sum_foreign":"","sum_comment_hidden":false,"sum_foreign_hidden":false,"sum_foreign_comment_hidden":false},"58":{"sum_comment":"","sum_hidden":false,"sum":"","sum_foreign_comment":"","sum_foreign":"","sum_comment_hidden":false,"sum_foreign_hidden":false,"sum_foreign_comment_hidden":false},"59":{"sum_comment":"","sum_hidden":false,"sum":"","sum_foreign_comment":"","sum_foreign":"","sum_comment_hidden":false,"sum_foreign_hidden":false,"sum_foreign_comment_hidden":false},"60":{"sum_comment":"","sum_hidden":false,"sum":"","sum_foreign_comment":"","sum_foreign":"","sum_comment_hidden":false},"61":{"sum_comment":"","sum_foreign_comment":"","sum_foreign":"","sum":""},"62":{"sum_comment":"","sum_foreign_comment":"","sum_foreign":"","sum":"","sum_comment_hidden":false},"63":{"sum_comment":"","sum_foreign_comment":"","sum_foreign":"","sum":""},"64":{"sum_comment":"","sum_foreign_comment":"","sum_foreign":"","sum":""}},"declaration":{"additional_info_text":"","additional_info":"","date":"2016-03-23T00:00:00","url":"http://static.declarations.com.ua/declarations/chosen_ones/judges_batch/1319_furyk_iurii_petrovych.pdf"},"intro":{"declaration_year":"2015"}}