{"income":{"5":{"family_comment":"","family_unclear":false,"value":"248363","family":"69614","comment":""},"6":{"family_comment":"","family_unclear":false,"value":"234092","family":"","comment":""},"7":{"value":"735","comment_hidden":false,"family_comment":"","source_name":"Львівське регіональне відділення Національної школи суддів України","family":"","comment":""},"8":{"family_comment":"","value":"","family":"","comment":""},"9":{"family_comment":"","value":"","family":"","comment":""},"10":{"family_comment":"","value":"13398","family":"","comment":""},"11":{"family_comment":"","value":"138","value_unclear":false,"family":"","comment":""},"12":{"family_comment":"","value":"","family":"","comment":""},"13":{"family_comment":"","value":"","family":"","comment":""},"14":{"family_comment":"","value":"","family":"","comment":""},"15":{"family_comment":"","value":"","value_unclear":false,"family":"","comment":""},"16":{"family_comment":"","family_unclear":false,"value":"","family":"","comment":""},"17":{"family_comment":"","value":"","family":"","comment":""},"18":{"family_comment":"","value":"","family_hidden":false,"comment":"","family":""},"19":{"family_comment":"","value":"","family":"","comment":""},"20":{"value":"","comment_unclear":false,"comment_hidden":false,"family_comment":"","family":"69614","comment":"","family_comment_hidden":false}},"id":"vulyk_68_164","banks":{"45":[{"sum_foreign_comment":"","sum_units":"UAH","sum_units_hidden":true,"sum_comment":"","sum_comment_unclear":false,"sum_hidden":true,"sum_foreign_units":"UAH","sum_comment_hidden":true,"sum_unclear":false,"sum":"7422","sum_foreign":""}]},"declaration":{"additional_info_text":"","notfull_lostpages":"","date":"2014-03-30T00:00:00","notfull":"","additional_info":"","url":"http://static.declarations.com.ua/declarations/chosen_ones/mega_batch/matkovska_zoriana_myroslavivna.pdf"},"liabilities":{"54":{"sum_foreign_comment":"","sum":"","sum_comment":"","sum_comment_unclear":false,"sum_hidden":false,"sum_comment_hidden":false,"sum_unclear":false,"sum_foreign":""},"55":{"sum_foreign_comment":"","sum":"","sum_hidden":false,"sum_comment":"","sum_foreign":""},"56":{"sum_foreign_comment":"","sum_foreign_hidden":false,"sum_comment":"","sum":"","sum_unclear":false,"sum_foreign":""},"57":{"sum_foreign_comment":"","sum":"22904","sum_comment":"","sum_comment_unclear":false,"sum_hidden":false,"sum_comment_hidden":true,"sum_unclear":false,"sum_foreign":""},"58":{"sum_foreign_comment":"","sum":"7096","sum_comment":"","sum_hidden":false,"sum_comment_hidden":true,"sum_unclear":false,"sum_foreign":""},"59":{"sum_foreign_comment":"","sum":"","sum_comment":"","sum_foreign":""},"60":{"sum_foreign_comment":"","sum":"","sum_comment":"","sum_comment_unclear":false,"sum_hidden":false,"sum_comment_hidden":false,"sum_unclear":false,"sum_foreign":""},"61":{"sum_foreign_comment":"","sum":"","sum_hidden":false,"sum_comment":"","sum_foreign":""},"62":{"sum_foreign_comment":"","sum":"","sum_comment":"","sum_unclear":false,"sum_foreign":""},"63":{"sum_foreign_comment":"","sum":"4130","sum_comment":"","sum_hidden":false,"sum_comment_hidden":true,"sum_unclear":false,"sum_foreign":""},"64":{"sum_foreign_comment":"","sum":"","sum_comment":"","sum_hidden":false,"sum_comment_hidden":false,"sum_foreign":""}},"ft_src":"22904\n7096\n4130\nсуддя львівського апеляційного адміністративного суду\nЛьвівська область\nАпеляційний адміністративний суд\nЗоряна\nДовгополов В. М\nПодружжя\nМатковський С. С\nДитина\nДовгополов М. В\nДитина\nМатковська І. Г\nБатьки\nМирославівна\nМатковська Зоряна Мирославівна\nЗоряна Мирославівна Матковська\nЗоряна Матковська\nМатковська Зоряна Мирославівна\nМатковська Зоряна Мирославівна\nМатковська\n138\n13398\n69614\n69614\n248363\n735\nЛьвівське регіональне відділення Національної школи суддів України\n234092\n7422\n45.4\n90\n2014\n234092\n138\n13398\nЛьвівське регіональне відділення Національної школи суддів України\n735\n69614\n248363\n69614\n7422\n2014\nПодружжя\nДовгополов В. М\nДитина\nМатковський С. С\nДитина\nДовгополов М. В\nБатьки\nМатковська І. Г\nМатковська Зоряна Мирославівна\nЗоряна Мирославівна Матковська\nЗоряна Матковська\nМатковська Зоряна Мирославівна\nМатковська Зоряна Мирославівна\nЗоряна\nМирославівна\nАпеляційний адміністративний суд\nЛьвівська область\nсуддя львівського апеляційного адміністративного суду\nМатковська\n4130\n22904\n7096\n735\nЛьвівське регіональне відділення Національної школи суддів України\n234092\n69614\n248363\n69614\n138\n13398\n90\n45.4\n7096\n22904\n4130\nПодружжя\nДовгополов В. М\nМатковський С. С\nДитина\nДовгополов М. В\nДитина\nМатковська І. Г\nБатьки\nМирославівна\nМатковська\nЗоряна\nМатковська Зоряна Мирославівна\nЗоряна Мирославівна Матковська\nЗоряна Матковська\nМатковська Зоряна Мирославівна\nЛьвівська область\nАпеляційний адміністративний суд\nсуддя львівського апеляційного адміністративного суду\nМатковська Зоряна Мирославівна\n45.4\n90\n7422\n2014","general":{"inn":"","name":"Зоряна","inn_unclear":false,"family":[{"inn":"","inn_hidden":true,"relations_unclear":false,"relations_hidden":false,"relations_other":"","relations":"Подружжя","name_hidden":true,"inn_unclear":false,"family_name":"Довгополов В. М","name_unclear":false},{"inn":"","inn_hidden":false,"inn_unclear":false,"relations_hidden":false,"relations_other":"","relations":"Дитина","name_hidden":false,"family_name":"Матковський С. С","name_unclear":false},{"inn":"","relations":"Дитина","relations_other":"","inn_hidden":true,"family_name":"Довгополов М. В","name_hidden":false,"name_unclear":false},{"inn":"","relations":"Батьки","relations_other":"","inn_hidden":false,"family_name":"Матковська І. Г","name_unclear":false}],"inn_hidden":true,"family_raw":"","last_name":"Матковська","post":{"post_unclear":false,"region_unclear":false,"post":"суддя львівського апеляційного адміністративного суду","office":"Апеляційний адміністративний суд","region":"Львівська область","post_hidden":false,"office_hidden":false,"office_unclear":false,"region_hidden":false},"full_name_suggest":{"output":"Матковська Зоряна Мирославівна","input":["Матковська Зоряна Мирославівна","Зоряна Мирославівна Матковська","Зоряна Матковська"]},"full_name":"Матковська Зоряна Мирославівна","addresses":[{"place_city_type_hidden":true,"place_district_hidden":true,"place_city_type":"","place_city_hidden":true,"place_address_unclear":false,"place_address":"","place_hidden":true,"place":"","place_district":"","place_unclear":false,"place_city":"","place_address_hidden":true}],"patronymic":"Мирославівна","last_name_unclear":false,"name_unclear":false},"source":"VULYK","estate":{"24":[{"region_unclear":false,"space_unclear":false,"costs":"","costs_comment":"","address_hidden":true,"region_hidden":true,"space_comment":"","space":"90","address":"","region":"","costs_rent_comment":"","space_units":"м²","costs_rent":""}],"25":[{"space_unclear":false,"costs":"","costs_comment":"","address_hidden":true,"region_hidden":true,"space_comment":"","space_hidden":false,"space":"","address":"","space_comment_unclear":false,"region":"","address_unclear":false,"costs_rent_comment":"","costs_unclear":false,"space_units":"м²","space_units_hidden":false,"costs_rent":""}],"31":[{"space_unclear":false,"address_hidden":true,"region_hidden":true,"space_comment":"","space_hidden":false,"space":"45.4","address":"","region":"","costs_property":"","costs_rent_comment":"","space_units":"м²","costs_property_comment":"","costs_rent":""}]},"intro":{"declaration_year":"2014","isnotdeclaration":""}}