{"income":{"5":{"value":"187888","family_comment":"","value_unclear":false,"family_hidden":false,"value_hidden":false,"family_unclear":false,"family":"","comment":""},"6":{"value":"187888","family_comment":"","value_unclear":false,"family_unclear":false,"family":"","comment":""},"7":{"source_name_unclear":false,"value":"","comment_hidden":false,"family_comment":"","source_name":"","family":"","comment":"","source_name_hidden":false},"8":{"family_comment":"","value":"","family":"","comment":""},"9":{"value":"","family_comment":"","value_unclear":false,"family_hidden":false,"family_unclear":false,"family":"","comment":"","family_comment_unclear":false},"10":{"family_comment":"","value":"","family":"","comment":""},"11":{"family_comment":"","value":"","family":"","comment":""},"12":{"family_comment":"","value":"","family":"","comment":""},"13":{"family_comment":"","value":"","family":"","comment":""},"14":{"family_comment":"","value":"","family":"","comment":""},"15":{"family_comment":"","value":"","family":"","comment":""},"16":{"family_comment":"","value":"","family":"","comment":""},"17":{"family_comment":"","value":"","family":"","comment":""},"18":{"family_comment":"","value":"","family":"","comment":""},"19":{"family_comment":"","value":"","family":"","comment":""},"20":{"value":"","family_comment":"","value_unclear":false,"family_comment_hidden":false,"family_unclear":false,"family_comment_unclear":false,"comment_unclear":false,"comment":"","family":""}},"vehicle":{"35":[{"year_hidden":false,"brand_info":"1.6 л","sum_rent_comment":"","year":"2008","brand_info_hidden":false,"brand_info_unclear":false,"sum_rent":"","sum":"","brand":"Skoda Octavia","sum_comment":"","brand_unclear":false,"brand_hidden":false}]},"id":"vulyk_93_121","declaration":{"additional_info_text":"","notfull_lostpages":"","date":"2015-03-17T00:00:00","notfull":"","additional_info":"","url":"http://static.declarations.com.ua/declarations/chosen_ones/judges_batch/3567_nesteruk_tetiana_mykolaivna.pdf"},"liabilities":{"54":{"sum_foreign_comment":"","sum":"","sum_hidden":false,"sum_comment":"","sum_foreign":""},"55":{"sum_foreign_comment":"","sum":"","sum_comment":"","sum_foreign":""},"56":{"sum_foreign_comment":"","sum":"","sum_comment":"","sum_foreign":""},"57":{"sum_foreign_comment":"","sum":"","sum_comment":"","sum_hidden":false,"sum_comment_hidden":false,"sum_unclear":false,"sum_foreign":""},"58":{"sum_foreign_comment":"","sum":"","sum_comment":"","sum_comment_unclear":false,"sum_hidden":false,"sum_unclear":false,"sum_foreign":""},"59":{"sum_foreign_comment":"","sum":"","sum_comment":"","sum_foreign":""},"60":{"sum_foreign_comment":"","sum":"","sum_hidden":false,"sum_comment":"","sum_foreign":""},"61":{"sum_foreign_comment":"","sum":"","sum_comment":"","sum_foreign":""},"62":{"sum_foreign_comment":"","sum":"","sum_comment":"","sum_foreign":""},"63":{"sum_foreign_comment":"","sum":"","sum_comment":"","sum_foreign":""},"64":{"sum_foreign_comment":"","sum":"","sum_comment":"","sum_foreign":""}},"ft_src":"Нестерук Тетяна Миколаївна\nзаступник голови звенигородського районного суду черкаської області\nЧеркаська область\nЗагальний місцевий суд\nТетяна\nНестерук М. В\nДитина\nНестерук Тетяна Миколаївна\nТетяна Миколаївна Нестерук\nТетяна Нестерук\nНестерук Тетяна Миколаївна\nНестерук\nМиколаївна\n1.6 л\nSkoda Octavia\n2008\n46.2\n46.2\n2014\n187888\n187888\n1.6 л\nSkoda Octavia\n2008\n46.2\n46.2\nНестерук\nДитина\nНестерук М. В\nНестерук Тетяна Миколаївна\nТетяна Миколаївна Нестерук\nТетяна Нестерук\nНестерук Тетяна Миколаївна\nНестерук Тетяна Миколаївна\nТетяна\nМиколаївна\nЧеркаська область\nЗагальний місцевий суд\nзаступник голови звенигородського районного суду черкаської області\n187888\n187888\n2014\nДитина\nНестерук М. В\nНестерук\nМиколаївна\nЧеркаська область\nЗагальний місцевий суд\nзаступник голови звенигородського районного суду черкаської області\nНестерук Тетяна Миколаївна\nНестерук Тетяна Миколаївна\nТетяна Миколаївна Нестерук\nТетяна Нестерук\nНестерук Тетяна Миколаївна\nТетяна\nSkoda Octavia\n1.6 л\n2008\n187888\n187888\n46.2\n46.2\n2014","general":{"inn":"","inn_hidden":true,"last_name":"Нестерук","post":{"post_unclear":false,"region_unclear":false,"region":"Черкаська область","candidate":"","post":"заступник голови звенигородського районного суду черкаської області","office":"Загальний місцевий суд","office_unclear":false},"name":"Тетяна","full_name":"Нестерук Тетяна Миколаївна","family_raw":"","addresses":[{"place_district":"","place_city_hidden":true,"place_city":"","place_city_type_hidden":true,"place_district_hidden":true,"place_city_type":"","place_address_hidden":true,"place_address":"","place_hidden":true,"place":""}],"family":[{"inn":"","relations":"Дитина","relations_hidden":false,"inn_hidden":false,"relations_other":"","name_hidden":false,"family_name":"Нестерук М. В","name_unclear":false}],"full_name_suggest":{"output":"Нестерук Тетяна Миколаївна","input":["Нестерук Тетяна Миколаївна","Тетяна Миколаївна Нестерук","Тетяна Нестерук"]},"patronymic":"Миколаївна"},"source":"VULYK","estate":{"25":[{"space_hidden":false,"costs":"","costs_comment":"","address_hidden":false,"region_hidden":true,"space_comment":"","space_unclear":false,"space":"46.2","address":"","costs_rent_comment_unclear":false,"region":"","costs_rent_comment":"","space_units":"м²","costs_rent":""}],"31":[{"space_hidden":false,"address_hidden":false,"region_hidden":true,"space_comment":"","space":"46.2","address":"","region":"","costs_property":"","costs_rent_comment":"","space_comment_unclear":false,"space_units":"м²","costs_property_comment":"","costs_rent":""}]},"intro":{"declaration_year":"2014","isnotdeclaration":""}}