{"id":"vulyk_102_32","ft_src":"2007\n2.0 i, 1998 куб. см., 110 кВт при 600 об/хв\nMitsubishi Lancer\n1/3\n18\nордер\n83.5\nмашиномісце\n34.7\n1/3\n18\nордер\n83.5\n129599\n2015\n2.0 i, 1998 куб. см., 110 кВт при 600 об/хв\nMitsubishi Lancer\n2007\n2015\nВеденяпін Олександр Андрійович\nОлександр Андрійович Веденяпін\nОлександр Веденяпін\nВеденяпін Олександр Андрійович\nВеденяпін Олександр Андрійович\nОлександр\nАндрійович\nсуддя вищого адміністративного суду україни\nЗагальнодержавний регіон\nВищий адміністративний суд\nВеденяпін\nПодружжя\n260\n263192\nза рішенням суду про стягнення недоотриманої заробітної плати\n89814\n367622\n14616\n18\n1/3\n83.5\nордер\n34.7\nмашиномісце\n18\n1/3\n83.5\nордер\n129599\n260\n263192\n14616\n367622\nза рішенням суду про стягнення недоотриманої заробітної плати\n89814\nПодружжя\nОлександр\nАндрійович\nВеденяпін\nВеденяпін Олександр Андрійович\nОлександр Андрійович Веденяпін\nОлександр Веденяпін\nВеденяпін Олександр Андрійович\nсуддя вищого адміністративного суду україни\nЗагальнодержавний регіон\nВищий адміністративний суд\nВеденяпін Олександр Андрійович","estate":{"25":[{"address":"","space_units":"м²","costs_comment":"","space_comment":"1/3","region_hidden":true,"region":"","address_hidden":false,"space":"18","address_unclear":false,"costs_rent_comment":"","costs":"","costs_rent":""},{"costs":"","address":"","space_units":"м²","costs_rent_comment":"","space":"83.5","space_comment":"ордер","region_hidden":false,"costs_comment":"","region":"","costs_rent":""}],"28":[{"address":"","space_units":"м²","costs_comment":"","space_unclear":false,"region_hidden":true,"space_comment":"машиномісце","address_hidden":false,"costs":"","costs_rent_comment":"","space":"34.7","region":"","costs_rent":""}],"31":[{"costs_property_comment":"","address":"","space_units":"м²","costs_rent_comment":"","space":"18","region":"","region_hidden":true,"costs_property":"","space_comment":"1/3","address_hidden":false,"costs_rent":""},{"costs_property_comment":"","address":"","space_units":"м²","costs_rent_comment":"","space":"83.5","region_hidden":false,"costs_property":"","space_comment":"ордер","costs_rent":""}]},"vehicle":{"35":[{"sum_comment":"","brand_info":"2.0 i, 1998 куб. см., 110 кВт при 600 об/хв","sum":"","sum_rent_comment":"","year":"2007","brand":"Mitsubishi Lancer","sum_rent":"","brand_info_unclear":false,"year_unclear":false}]},"source":"VULYK","income":{"5":{"family_comment":"","value":"367622","family":"","comment":""},"6":{"family_comment":"","value":"263192","family":"","comment":""},"7":{"source_name_hidden":false,"family_comment":"","family":"","value_hidden":false,"comment":"","comment_hidden":false,"value":"","source_name":""},"8":{"family_comment":"","value":"","family":"","comment":""},"9":{"family_comment":"","family":"","comment":"","comment_hidden":false,"value":"","family_comment_unclear":false},"10":{"family_comment":"","value":"14616","family":"","comment":""},"11":{"family_comment":"","value":"","family":"","comment":"","comment_hidden":false},"12":{"family_comment":"","value":"","family":"","comment":""},"13":{"family_comment":"","value":"","family":"","comment":""},"14":{"family_comment":"","value":"","family":"","comment":""},"15":{"family_comment":"","value":"","family":"","comment":""},"16":{"family_comment":"","value":"","family":"","comment":""},"17":{"family_comment":"","value":"","family":"","comment":""},"18":{"family_comment":"","value":"","family":"","comment":""},"19":{"family_comment":"","value":"","family":"","comment":""},"20":{"family_comment":"","value":"89814","family":"","comment":"за рішенням суду про стягнення недоотриманої заробітної плати","comment_hidden":false}},"banks":{"45":[{"sum_comment_unclear":false,"sum_units":"UAH","sum_foreign_units":"UAH","sum_hidden":false,"sum":"129599","sum_foreign_comment":"","sum_comment":"","sum_unclear":false,"sum_foreign":"","sum_comment_hidden":true}]},"declaration":{"additional_info_text":"","additional_info":"","date":"2016-03-28T00:00:00","url":"http://static.declarations.com.ua/declarations/chosen_ones/judges_batch/1106_vedeniapin_oleksandr_andriiovych.pdf"},"general":{"family":[{"inn":"","family_name":"","name_unclear":false,"inn_hidden":true,"name_hidden":true,"relations":"Подружжя"}],"family_raw":"","name":"Олександр","full_name_suggest":{"input":["Веденяпін Олександр Андрійович","Олександр Андрійович Веденяпін","Олександр Веденяпін"],"output":"Веденяпін Олександр Андрійович"},"patronymic":"Андрійович","inn_hidden":true,"patronymic_hidden":false,"inn":"","addresses":[{"place_city_type_hidden":false,"place_city_type":"","place_city_hidden":true,"place_hidden":true,"place_district":"","place_district_hidden":false,"place":"","place_address":"","place_address_hidden":true,"place_city":""}],"last_name":"Веденяпін","full_name":"Веденяпін Олександр Андрійович","post":{"office_unclear":false,"region_unclear":false,"post":"суддя вищого адміністративного суду україни","region":"Загальнодержавний регіон","office":"Вищий адміністративний суд"}},"liabilities":{"54":{"sum_comment":"","sum_hidden":false,"sum":"260","sum_foreign_comment":"","sum_foreign":"","sum_comment_hidden":true},"55":{"sum_comment":"","sum_foreign_comment":"","sum_foreign":"","sum":""},"56":{"sum_comment":"","sum_foreign_comment":"","sum_foreign":"","sum":""},"57":{"sum_comment":"","sum_foreign_comment":"","sum_foreign":"","sum":"","sum_comment_hidden":false},"58":{"sum_comment":"","sum_foreign_comment":"","sum_foreign":"","sum":"","sum_comment_hidden":false},"59":{"sum_comment":"","sum_foreign_comment":"","sum_foreign":"","sum":"","sum_comment_hidden":false},"60":{"sum_comment":"","sum_hidden":false,"sum":"","sum_foreign_comment":"","sum_foreign":"","sum_comment_hidden":false},"61":{"sum_comment":"","sum_foreign_comment":"","sum_foreign":"","sum":""},"62":{"sum_comment":"","sum_foreign_comment":"","sum_foreign":"","sum_unclear":false,"sum":""},"63":{"sum_comment":"","sum_hidden":false,"sum":"","sum_foreign_comment":"","sum_foreign":"","sum_comment_hidden":false},"64":{"sum_comment":"","sum_foreign_comment":"","sum_foreign":"","sum":"","sum_comment_hidden":false}},"intro":{"declaration_year":"2015"}}