{"id":"vulyk_108_149","ft_src":"1968 куб. см., 442.6\n2010\nVolkswagen Tiguan\n190\nДніпропетровська область\nм. Дніпропетровськ\n16\nДніпропетровська область\nДніпропетровська область\nм. Дніпропетровськ\n18.6\nм. Дніпропетровськ\nДніпропетровська область\n58\nм. Дніпропетровськ\n46\nДніпропетровська область\n2015\n36065\n188060\n36065\n188060\n1968 куб. см., 442.6\n2010\nVolkswagen Tiguan\n2015\nДемидова Світлана Олександрівна\nСвітлана Олександрівна Демидова\nСвітлана Демидова\nДемидова Світлана Олександрівна\nСвітлана\nПодружжя\nПогосян А. Г\nДитина\nДемидов К. О\nПогосян Г. А\nДитина\nДемидова Світлана Олександрівна\nОлександрівна\nЗагальний місцевий суд\nДніпропетровська область\nсуддя жовтневого районного суду м. дніпропетровська\nДемидова\nДніпропетровськ\n49000\nДніпропетровська область\n188060\n36065\n188060\n36065\n190\nДніпропетровська область\n18.6\nм. Дніпропетровськ\nДніпропетровська область\n16\nДніпропетровська область\nм. Дніпропетровськ\n58\nДніпропетровська область\nм. Дніпропетровськ\n46\nм. Дніпропетровськ\nДніпропетровська область\nПодружжя\nПогосян А. Г\nДитина\nДемидов К. О\nПогосян Г. А\nДитина\nОлександрівна\nДемидова\nСвітлана\nДемидова Світлана Олександрівна\nСвітлана Олександрівна Демидова\nСвітлана Демидова\nДемидова Світлана Олександрівна\nДніпропетровська область\nДніпропетровськ\n49000\nДніпропетровська область\nсуддя жовтневого районного суду м. дніпропетровська\nЗагальний місцевий суд\nДемидова Світлана Олександрівна","estate":{"23":[{"address":"","space_units":"м²","costs_comment":"","space_unclear":false,"region_hidden":false,"space_units_unclear":false,"space_comment":"","address_hidden":false,"costs":"","address_unclear":false,"costs_rent_comment":"","space":"190","region_unclear":false,"region":"Дніпропетровська область","space_units_hidden":false,"costs_rent":""}],"25":[{"address":"м. Дніпропетровськ","space_units":"м²","costs_comment":"","space_unclear":false,"region_hidden":false,"space_units_unclear":false,"space_comment":"","address_hidden":true,"costs":"","space_comment_unclear":false,"costs_rent_comment":"","space":"46","region":"Дніпропетровська область","costs_rent":""}],"27":[{"address":"м. Дніпропетровськ","space_units":"м²","costs_comment":"","space_unclear":false,"region_hidden":false,"space_comment":"","address_hidden":true,"costs":"","costs_rent_comment":"","space":"16","region":"Дніпропетровська область","costs_rent":""}],"31":[{"costs_property_comment":"","address":"м. Дніпропетровськ","space_units":"м²","space_hidden":false,"space_comment":"","region_hidden":false,"costs_property":"","region":"Дніпропетровська область","address_hidden":true,"address_unclear":false,"space_comment_unclear":false,"costs_rent_comment":"","space":"58","costs_rent":""}],"33":[{"costs_property_comment":"","address":"м. Дніпропетровськ","space_units":"м²","costs_rent_comment":"","space":"18.6","region":"Дніпропетровська область","region_hidden":false,"costs_property":"","space_comment":"","address_hidden":true,"costs_rent":""}]},"vehicle":{"35":[{"sum_comment":"","brand_info":"1968 куб. см., 442.6","sum":"","sum_rent_comment":"","year":"2010","brand":"Volkswagen Tiguan","sum_rent":"","brand_info_unclear":false}]},"source":"VULYK","income":{"5":{"family_comment":"","family":"36065","comment":"","value_unclear":false,"family_unclear":false,"value":"188060"},"6":{"family_comment":"","value":"188060","family_unclear":false,"family":"36065","comment":""},"7":{"family_comment":"","comment":"","family":"","source_name_unclear":false,"value":"","source_name":""},"8":{"family_comment":"","value":"","family":"","comment":""},"9":{"family_comment":"","family":"","comment":"","family_unclear":false,"comment_hidden":false,"value":"","family_comment_hidden":false},"10":{"family_comment":"","value":"","family":"","comment":""},"11":{"family_comment":"","value":"","family":"","comment":""},"12":{"family_comment":"","value":"","family":"","comment":""},"13":{"family_comment":"","value":"","family":"","comment":""},"14":{"family_comment":"","value":"","family":"","comment":""},"15":{"family_comment":"","value":"","family":"","comment":""},"16":{"family_comment":"","value":"","family":"","comment":""},"17":{"family_comment":"","value":"","family":"","comment":""},"18":{"family_comment":"","value":"","family":"","comment":""},"19":{"family_comment":"","value":"","family":"","comment":""},"20":{"family_comment":"","comment":"","family":"","value_unclear":false,"comment_hidden":false,"comment_unclear":false,"value":""}},"general":{"family_raw":"","name":"Світлана","full_name_suggest":{"input":["Демидова Світлана Олександрівна","Світлана Олександрівна Демидова","Світлана Демидова"],"output":"Демидова Світлана Олександрівна"},"patronymic":"Олександрівна","inn_hidden":true,"addresses":[{"place_city_type_hidden":false,"place_hidden":false,"place_address_unclear":false,"place":"Дніпропетровська область","place_city":"Дніпропетровськ","place_unclear":false,"place_city_type":"Місто","place_city_hidden":false,"place_district":"","place_district_hidden":false,"place_address":"49000","place_address_hidden":true}],"inn":"","inn_unclear":false,"last_name":"Демидова","full_name":"Демидова Світлана Олександрівна","family":[{"inn":"","inn_unclear":false,"family_name":"Погосян А. Г","relations_hidden":false,"name_unclear":false,"relations":"Подружжя","inn_hidden":true,"name_hidden":false,"relations_other":""},{"inn":"","family_name":"Демидов К. О","relations_other":"","name_unclear":false,"inn_hidden":false,"name_hidden":false,"relations":"Дитина"},{"inn":"","name_hidden":false,"family_name":"Погосян Г. А","inn_hidden":false,"relations":"Дитина"}],"post":{"office":"Загальний місцевий суд","post":"суддя жовтневого районного суду м. дніпропетровська","office_unclear":false,"office_hidden":false,"region":"Дніпропетровська область","post_unclear":false}},"liabilities":{"54":{"sum_comment":"","sum_foreign_comment":"","sum_foreign":"","sum_hidden":false,"sum":""},"55":{"sum_comment":"","sum_foreign_comment":"","sum_foreign":"","sum":""},"56":{"sum_comment":"","sum_foreign_comment":"","sum_foreign":"","sum_unclear":false,"sum":""},"57":{"sum_comment":"","sum_hidden":false,"sum":"","sum_foreign_comment":"","sum_foreign":"","sum_comment_hidden":false},"58":{"sum_comment":"","sum_foreign_comment":"","sum_foreign":"","sum":"","sum_comment_hidden":false},"59":{"sum_comment":"","sum_foreign_comment":"","sum_foreign":"","sum_unclear":false,"sum":""},"60":{"sum_comment":"","sum_foreign_comment":"","sum_foreign":"","sum":"","sum_comment_hidden":false},"61":{"sum_comment":"","sum_foreign_comment":"","sum_foreign":"","sum":"","sum_comment_hidden":false},"62":{"sum_comment":"","sum_foreign_comment":"","sum_foreign":"","sum":""},"63":{"sum_comment":"","sum_hidden":false,"sum":"","sum_foreign_comment":"","sum_foreign":"","sum_unclear":false,"sum_comment_hidden":false},"64":{"sum_comment":"","sum":"","sum_foreign_comment":"","sum_foreign":"","sum_unclear":false,"sum_comment_hidden":false}},"declaration":{"notfull_lostpages":"","additional_info_text":"","additional_info":"","date":"2016-03-28T00:00:00","notfull":"","url":"http://static.declarations.com.ua/declarations/chosen_ones/judges_batch/2448_demydova_svitlana_oleksandrivna_2015.pdf"},"intro":{"declaration_year_hidden":false,"isnotdeclaration":"","declaration_year":"2015"}}