{"income":{"5":{"value":"231403","family_comment":"","value_unclear":false,"family":"43489","family_unclear":false,"comment_unclear":false,"comment":"","family_comment_unclear":false},"6":{"value":"228313","family_comment":"","value_unclear":false,"family_unclear":false,"family":"43489","comment":""},"7":{"source_name_unclear":false,"value":"1210","value_unclear":false,"family_comment":"","source_name":"Технологічно-промисловий коледж ВНАУ, Київський університет права","family":"","comment":"","source_name_hidden":false},"8":{"family_comment":"","value":"","family":"","comment":""},"9":{"family_comment":"","value":"1880","family":"","comment":""},"10":{"family_comment":"","value":"","value_unclear":false,"family":"","comment":""},"11":{"value":"","value_unclear":false,"value_hidden":false,"family_comment":"","family":"","comment":""},"12":{"family_comment":"","value":"","family":"","comment":"","value_hidden":false},"13":{"family_comment":"","value":"","family":"","comment":""},"14":{"family_comment":"","value":"","family":"","comment":""},"15":{"family_comment":"","value":"","family":"","comment":""},"16":{"family_comment":"","value":"","family":"","comment":""},"17":{"family_comment":"","value":"","family":"","comment":""},"18":{"family_comment":"","value":"","family":"","comment":""},"19":{"family_comment":"","family_unclear":false,"value":"","family":"","comment":""},"20":{"family_comment":"","family_unclear":false,"value":"","family":"","comment":""}},"vehicle":{"40":[{"brand_info":"1600 куб. см.","sum":"","brand":"Opel Vectra","sum_comment":"","brand_unclear":false,"year":"1992","brand_hidden":false,"brand_info_hidden":false,"brand_info_unclear":false,"sum_rent_comment":"","sum_rent":""}]},"id":"vulyk_61_131","banks":{"45":[{"sum_foreign_comment":"","sum_units":"UAH","sum_comment":"","sum_foreign_units":"UAH","sum_comment_hidden":false,"sum_unclear":false,"sum":"1585","sum_foreign":""}]},"declaration":{"additional_info_text":"","notfull_lostpages":"","date":"2015-03-30T00:00:00","notfull":"","additional_info":"","url":"http://static.declarations.com.ua/declarations/chosen_ones/mega_batch/sychuk_mykola_mykolaiovych.pdf"},"liabilities":{"54":{"sum_foreign_comment":"","sum":"","sum_comment":"","sum_comment_unclear":false,"sum_unclear":false,"sum_foreign":""},"55":{"sum_foreign_comment":"","sum":"","sum_comment":"","sum_foreign":""},"56":{"sum_foreign_comment":"","sum":"","sum_comment":"","sum_unclear":false,"sum_foreign":""},"57":{"sum_foreign_comment":"","sum":"","sum_comment":"","sum_comment_hidden":false,"sum_unclear":false,"sum_foreign":""},"58":{"sum_foreign_comment":"","sum":"","sum_comment":"","sum_unclear":false,"sum_foreign":""},"59":{"sum_foreign_comment":"","sum":"","sum_comment":"","sum_foreign":""},"60":{"sum_foreign_comment":"","sum_foreign_hidden":false,"sum_comment":"","sum_hidden":false,"sum":"","sum_foreign":""},"61":{"sum_foreign_comment":"","sum":"","sum_comment":"","sum_foreign":""},"62":{"sum_foreign_comment":"","sum":"","sum_comment":"","sum_unclear":false,"sum_foreign":""},"63":{"sum_foreign_comment":"","sum":"","sum_comment":"","sum_hidden":false,"sum_unclear":false,"sum_foreign":""},"64":{"sum_foreign_comment":"","sum":"","sum_hidden":false,"sum_comment":"","sum_foreign":""}},"ft_src":"суддя вінницького міського суду вінницької області\nВінницька область\nЗагальний місцевий суд\nМикола\nСичук С. М\nПодружжя\nСичук О. М\nДитина\nМиколайович\nСичук\nСичук Микола Миколайович\nСичук Микола Миколайович\nМикола Миколайович Сичук\nМикола Сичук\nСичук Микола Миколайович\nOpel Vectra\n1600 куб. см.\n1992\n1585\n2014\n43489\n228313\nТехнологічно-промисловий коледж ВНАУ, Київський університет права\n1210\n43489\n231403\n1880\n1600 куб. см.\n1992\nOpel Vectra\n1585\n2014\nПодружжя\nСичук С. М\nДитина\nСичук О. М\nСичук Микола Миколайович\nМикола Миколайович Сичук\nМикола Сичук\nСичук Микола Миколайович\nМикола\nСичук Микола Миколайович\nСичук\nВінницька область\nЗагальний місцевий суд\nсуддя вінницького міського суду вінницької області\nМиколайович\n1210\nТехнологічно-промисловий коледж ВНАУ, Київський університет права\n43489\n228313\n231403\n43489\n1880\nСичук С. М\nПодружжя\nСичук О. М\nДитина\nМиколайович\nСичук\nСичук Микола Миколайович\nМикола Миколайович Сичук\nМикола Сичук\nСичук Микола Миколайович\nВінницька область\nсуддя вінницького міського суду вінницької області\nЗагальний місцевий суд\nСичук Микола Миколайович\nМикола\nOpel Vectra\n1600 куб. см.\n1992\n231403\n43489\n1210\nТехнологічно-промисловий коледж ВНАУ, Київський університет права\n1880\n228313\n43489\n1585\n2014","general":{"inn":"","name":"Микола","patronymic_unclear":false,"family":[{"inn":"","inn_hidden":false,"relations_unclear":false,"relations_hidden":false,"relations_other":"","relations":"Подружжя","name_hidden":false,"family_name":"Сичук С. М","name_unclear":false},{"inn":"","relations":"Дитина","relations_other":"","inn_hidden":false,"family_name":"Сичук О. М","name_hidden":false,"name_unclear":false}],"patronymic":"Миколайович","inn_hidden":true,"family_raw":"","inn_unclear":false,"post":{"post_unclear":false,"region_unclear":false,"post":"суддя вінницького міського суду вінницької області","office":"Загальний місцевий суд","region":"Вінницька область","post_hidden":false,"office_hidden":false,"region_hidden":false},"last_name_unclear":false,"full_name":"Сичук Микола Миколайович","addresses":[{"place_address":"","place_district_hidden":false,"place_city_type":"","place_city_hidden":false,"place_address_unclear":false,"place_city_type_hidden":false,"place_hidden":true,"place":"","place_district":"","place_address_hidden":false,"place_city":"","place_district_unclear":false}],"last_name":"Сичук","patronymic_hidden":false,"full_name_suggest":{"output":"Сичук Микола Миколайович","input":["Сичук Микола Миколайович","Микола Миколайович Сичук","Микола Сичук"]},"name_unclear":false},"source":"VULYK","intro":{"declaration_year":"2014","isnotdeclaration":"","declaration_year_hidden":false}}