{"income":{"5":{"value":"182440.32","family_comment":"","value_unclear":false,"family_hidden":false,"value_hidden":false,"family_unclear":true,"comment_unclear":false,"comment":"","family":"16800"},"6":{"value":"180479.74","family_comment":"","value_unclear":false,"family_hidden":false,"value_hidden":false,"family_unclear":true,"comment_unclear":false,"comment":"","family":"16800"},"7":{"source_name_unclear":false,"value":"","family_comment":"","source_name":"","family":"","comment":""},"8":{"family_comment":"","value":"","family":"","comment":""},"9":{"value":"","value_unclear":false,"comment_hidden":false,"family_comment":"","comment_unclear":false,"comment":"","family":""},"10":{"value":"1958.83","comment_unclear":false,"value_hidden":false,"family_comment":"","family":"","comment":""},"11":{"family_comment":"","value":"","family":"","comment":""},"12":{"family_comment":"","value":"","family":"","comment":""},"13":{"family_comment":"","value":"","family":"","comment":""},"14":{"family_comment":"","value":"","family":"","comment":""},"15":{"family_comment":"","value":"","family":"","comment":""},"16":{"family_comment":"","value":"","family":"","comment":""},"17":{"family_comment":"","value":"","family":"","comment":""},"18":{"value":"","family_hidden":false,"value_hidden":false,"family_comment":"","family":"","comment":""},"19":{"family_comment":"","value":"","family":"","comment":""},"20":{"value":"1.75","family_comment":"","value_unclear":false,"family_hidden":false,"value_hidden":false,"family_unclear":false,"family":"","comment":""}},"vehicle":{"40":[{"brand_info":"1.6","sum_rent_comment":"","brand":"ВАЗ 21099","sum_comment":"","brand_unclear":false,"year":"2008","brand_info_unclear":false,"year_unclear":false,"sum":"","sum_rent":""}]},"id":"vulyk_66_28","banks":{"45":[{"sum_foreign_comment":"","sum_units":"UAH","sum_units_hidden":false,"sum_comment":"","sum_comment_unclear":false,"sum_hidden":false,"sum_foreign_units":"UAH","sum_comment_hidden":false,"sum_unclear":false,"sum":"32494","sum_foreign":""}],"46":[{"sum_foreign_comment":"","sum_units":"UAH","sum_comment":"","sum_foreign_units":"UAH","sum":"30000","sum_foreign":""}]},"declaration":{"additional_info_text":"","notfull_lostpages":"","date":"2015-03-26T00:00:00","notfull":"","additional_info":"","url":"http://static.declarations.com.ua/declarations/chosen_ones/mega_batch/skarnytska_inna_borysivna.pdf"},"liabilities":{"54":{"sum_foreign_comment":"","sum":"","sum_comment":"","sum_comment_unclear":false,"sum_comment_hidden":false,"sum_unclear":false,"sum_foreign":""},"55":{"sum_foreign_comment":"","sum":"","sum_comment":"","sum_foreign":""},"56":{"sum_foreign_comment":"","sum_foreign_hidden":false,"sum_comment":"","sum_hidden":false,"sum_comment_hidden":false,"sum":"2000","sum_foreign":""},"57":{"sum_foreign_comment":"","sum":"5361.8","sum_comment":"","sum_comment_unclear":false,"sum_hidden":false,"sum_comment_hidden":false,"sum_unclear":false,"sum_foreign":""},"58":{"sum_foreign_comment":"","sum":"55.48","sum_comment":"","sum_comment_unclear":false,"sum_unclear":false,"sum_foreign":""},"59":{"sum_foreign_comment":"","sum_foreign_hidden":false,"sum_comment":"","sum_comment_unclear":false,"sum_hidden":false,"sum":"","sum_foreign":""},"60":{"sum_foreign_comment":"","sum":"","sum_comment":"","sum_comment_unclear":false,"sum_foreign":""},"61":{"sum_foreign_comment":"","sum":"","sum_comment":"","sum_foreign":""},"62":{"sum_foreign_comment":"","sum_foreign_hidden":false,"sum_comment":"","sum_hidden":false,"sum":"","sum_unclear":false,"sum_foreign":""},"63":{"sum_foreign_comment":"","sum":"","sum_comment":"","sum_comment_unclear":false,"sum_comment_hidden":false,"sum_unclear":false,"sum_foreign":""},"64":{"sum_foreign_comment":"","sum":"","sum_comment":"","sum_comment_unclear":false,"sum_foreign":""}},"ft_src":"5361.8\n55.48\n2000\nМиколаїв\n54039\nМиколаївська область\nсуддя братського районного суду миколаївської області\nМиколаївська область\nЗагальний місцевий суд\nІнна\nСкарницький С. Г\nПодружжя\nСкарницький Н. С\nДитина\nБорисівна\nСкарницька Інна Борисівна\nІнна Борисівна Скарницька\nІнна Скарницька\nСкарницька Інна Борисівна\nСкарницька Інна Борисівна\nСкарницька\n1.6\nВАЗ 21099\n2008\n30000\n32494\n2014\n1.6\n2008\nВАЗ 21099\n32494\n30000\n60.7\nкористування\nм. Миколаїв\nМиколаївська область\n60.7\nМиколаївська область\nм. Миколаїв\nЗагальний місцевий суд\nсуддя братського районного суду миколаївської області\nМиколаївська область\nПодружжя\nСкарницький С. Г\nДитина\nСкарницький Н. С\nСкарницька Інна Борисівна\nІнна Борисівна Скарницька\nІнна Скарницька\nСкарницька Інна Борисівна\nСкарницька Інна Борисівна\nІнна\nСкарницька\nБорисівна\nМиколаїв\n54039\nМиколаївська область\n5361.8\n2000\n55.48\n180479.74\n16800\n1.75\n182440.32\n16800\n1958.83\n2014\n55.48\n5361.8\n2000\nм. Миколаїв\nМиколаївська область\n60.7\nкористування\nм. Миколаїв\n60.7\nМиколаївська область\nСкарницький С. Г\nПодружжя\nСкарницький Н. С\nДитина\nБорисівна\nСкарницька\nІнна\nСкарницька Інна Борисівна\nІнна Борисівна Скарницька\nІнна Скарницька\nСкарницька Інна Борисівна\nМиколаївська область\nМиколаїв\n54039\nМиколаївська область\nсуддя братського районного суду миколаївської області\nЗагальний місцевий суд\nСкарницька Інна Борисівна\n16800\n180479.74\n1958.83\n16800\n182440.32\n1.75\n2008\n1.6\nВАЗ 21099\n1958.83\n1.75\n182440.32\n16800\n180479.74\n16800\nм. Миколаїв\nМиколаївська область\n60.7\nкористування\nм. Миколаїв\nМиколаївська область\n60.7\n32494\n30000\n2014","general":{"inn":"","name":"Інна","last_name_hidden":false,"family":[{"inn":"","inn_hidden":true,"relations_hidden":false,"family_name":"Скарницький С. Г","relations_other":"","relations":"Подружжя","name_hidden":false,"name_unclear":false},{"inn":"","inn_hidden":false,"relations_unclear":false,"relations_hidden":false,"relations_other":"","relations":"Дитина","name_hidden":false,"family_name":"Скарницький Н. С","name_unclear":false}],"patronymic":"Борисівна","inn_hidden":true,"family_raw":"","inn_unclear":false,"post":{"post_unclear":false,"post":"суддя братського районного суду миколаївської області","candidate":"","office_hidden":false,"region":"Миколаївська область","office":"Загальний місцевий суд","office_unclear":false},"full_name_suggest":{"output":"Скарницька Інна Борисівна","input":["Скарницька Інна Борисівна","Інна Борисівна Скарницька","Інна Скарницька"]},"full_name":"Скарницька Інна Борисівна","addresses":[{"place_city_type_unclear":false,"place_address":"54039","place_district_hidden":false,"place_city_type":"Місто","place_address_hidden":true,"place_address_unclear":true,"place_city_type_hidden":false,"place":"Миколаївська область","place_district":"","place_unclear":false,"place_city":"Миколаїв","place_city_unclear":false,"place_hidden":false,"place_city_hidden":false,"place_district_unclear":false}],"last_name":"Скарницька","last_name_unclear":false},"source":"VULYK","estate":{"24":[{"space_unclear":true,"costs":"","costs_comment":"","costs_hidden":false,"address_hidden":true,"region_hidden":false,"space_comment":"користування","space_hidden":false,"space":"60.7","address":"м. Миколаїв","region":"Миколаївська область","address_unclear":false,"costs_rent_comment":"","costs_rent_hidden":false,"space_comment_unclear":false,"space_units":"м²","costs_rent":""}],"30":[{"space_unclear":false,"address_hidden":true,"region_hidden":false,"space_comment":"","space_hidden":false,"space":"60.7","address":"м. Миколаїв","region":"Миколаївська область","costs_property":"","costs_rent_comment":"","address_unclear":false,"space_units":"м²","costs_property_comment":"","costs_rent":""}]},"intro":{"declaration_year":"2014","isnotdeclaration":"","declaration_year_unclear":false}}