{"income":{"5":{"value":"204251","family_comment":"","value_unclear":false,"family_hidden":false,"value_hidden":false,"family_unclear":false,"comment_unclear":false,"comment":"","family":""},"6":{"value":"204251","family_comment":"","value_unclear":false,"family_hidden":false,"value_hidden":false,"family_unclear":false,"comment_unclear":false,"comment":"","family":""},"7":{"source_name_unclear":false,"value":"","family_comment":"","source_name":"","family":"","comment":""},"8":{"family_comment":"","value":"","family":"","comment":""},"9":{"value":"","value_unclear":false,"comment_hidden":false,"family_comment":"","comment_unclear":false,"comment":"","family":""},"10":{"value":"","comment_unclear":false,"value_hidden":false,"family_comment":"","family":"","comment":""},"11":{"family_comment":"","value":"","family":"","comment":""},"12":{"family_comment":"","value":"","family":"","comment":""},"13":{"family_comment":"","value":"","family":"","comment":""},"14":{"family_comment":"","value":"","family":"","comment":""},"15":{"family_comment":"","value":"","family":"","comment":""},"16":{"family_comment":"","value":"","family":"","comment":""},"17":{"family_comment":"","value":"","family":"","comment":""},"18":{"value":"","family_hidden":false,"value_hidden":false,"family_comment":"","family":"","comment":""},"19":{"family_comment":"","value":"","family":"","comment":""},"20":{"value":"","family_comment":"","value_unclear":false,"family_hidden":false,"value_hidden":false,"family_unclear":false,"family":"","comment":""}},"id":"vulyk_66_106","declaration":{"additional_info_text":"","notfull_lostpages":"","date":"2015-03-31T00:00:00","notfull":"","additional_info":"","url":"http://static.declarations.com.ua/declarations/chosen_ones/mega_batch/zakharchuk_svitlana_stepanivna.pdf"},"liabilities":{"54":{"sum_foreign_comment":"","sum":"","sum_comment":"","sum_comment_unclear":false,"sum_comment_hidden":false,"sum_unclear":false,"sum_foreign":""},"55":{"sum_foreign_comment":"","sum":"","sum_comment":"","sum_foreign":""},"56":{"sum_foreign_comment":"","sum_foreign_hidden":false,"sum_comment":"","sum_hidden":false,"sum_comment_hidden":false,"sum":"","sum_foreign":""},"57":{"sum_foreign_comment":"","sum":"","sum_comment":"","sum_comment_unclear":false,"sum_hidden":false,"sum_comment_hidden":false,"sum_unclear":false,"sum_foreign":""},"58":{"sum_foreign_comment":"","sum":"","sum_comment":"","sum_comment_unclear":false,"sum_unclear":false,"sum_foreign":""},"59":{"sum_foreign_comment":"","sum_foreign_hidden":false,"sum_comment":"","sum_comment_unclear":false,"sum_hidden":false,"sum":"","sum_foreign":""},"60":{"sum_foreign_comment":"","sum":"","sum_comment":"","sum_comment_unclear":false,"sum_foreign":""},"61":{"sum_foreign_comment":"","sum":"","sum_comment":"","sum_foreign":""},"62":{"sum_foreign_comment":"","sum_foreign_hidden":false,"sum_comment":"","sum_hidden":false,"sum":"","sum_unclear":false,"sum_foreign":""},"63":{"sum_foreign_comment":"","sum":"","sum_comment":"","sum_comment_unclear":false,"sum_comment_hidden":false,"sum_unclear":false,"sum_foreign":""},"64":{"sum_foreign_comment":"","sum":"","sum_comment":"","sum_comment_unclear":false,"sum_foreign":""}},"ft_src":"суддя подільського районного суду м. києва\nм. Київ\nЗагальний місцевий суд\nСвітлана\nСтепанівна\nЗахарчук Світлана Степанівна\nСвітлана Степанівна Захарчук\nСвітлана Захарчук\nЗахарчук Світлана Степанівна\nЗахарчук Світлана Степанівна\nЗахарчук\n204251\n204251\n1/4 частина квартири\n17.67\n2014\n204251\n204251\n17.67\n1/4 частина квартири\nЗахарчук Світлана Степанівна\nСвітлана Степанівна Захарчук\nСвітлана Захарчук\nЗахарчук Світлана Степанівна\nСвітлана\nЗахарчук Світлана Степанівна\nЗахарчук\nЗагальний місцевий суд\nсуддя подільського районного суду м. києва\nм. Київ\nСтепанівна\n204251\n204251\n2014\nСтепанівна\nЗахарчук\nСвітлана\nЗахарчук Світлана Степанівна\nСвітлана Степанівна Захарчук\nСвітлана Захарчук\nЗахарчук Світлана Степанівна\nм. Київ\nсуддя подільського районного суду м. києва\nЗагальний місцевий суд\nЗахарчук Світлана Степанівна\n17.67\n1/4 частина квартири\n2014","general":{"inn":"","name":"Світлана","last_name_hidden":false,"last_name":"Захарчук","patronymic":"Степанівна","inn_hidden":true,"family_raw":"","inn_unclear":false,"post":{"post_unclear":false,"post":"суддя подільського районного суду м. києва","candidate":"","office_hidden":false,"region":"м. Київ","office":"Загальний місцевий суд","office_unclear":false},"full_name_suggest":{"output":"Захарчук Світлана Степанівна","input":["Захарчук Світлана Степанівна","Світлана Степанівна Захарчук","Світлана Захарчук"]},"full_name":"Захарчук Світлана Степанівна","addresses":[{"place_city_type_unclear":false,"place_address":"","place_district_hidden":true,"place_city_type":"","place_address_hidden":true,"place_address_unclear":false,"place_city_type_hidden":true,"place":"","place_district":"","place_unclear":false,"place_city":"","place_city_unclear":false,"place_hidden":true,"place_city_hidden":true,"place_district_unclear":false}],"last_name_unclear":false},"source":"VULYK","estate":{"25":[{"region_unclear":false,"space_hidden":false,"costs":"","costs_comment":"","costs_hidden":false,"address_hidden":true,"region_hidden":true,"space_comment":"1/4 частина квартири","space_unclear":false,"space":"17.67","space_units_hidden":false,"region":"","address_unclear":false,"costs_rent_comment":"","space_comment_unclear":false,"space_units":"м²","address":"","costs_rent":""}]},"intro":{"declaration_year":"2014","isnotdeclaration":"","declaration_year_unclear":false}}