{"income":{"5":{"family_comment":"відмовилася надавати відомості","value":"304496","family":"","comment":""},"6":{"family_comment":"","value":"245979","family_hidden":false,"comment":"","family":""},"7":{"family_comment":"","value":"","source_name":"","family":"","comment":""},"8":{"family_comment":"","value":"","family":"","comment":""},"9":{"value":"","value_unclear":false,"family_hidden":false,"family_comment":"","family":"","comment":""},"10":{"value":"12617","family_comment":"","family_hidden":false,"value_hidden":false,"family_unclear":false,"family":"","comment":""},"11":{"family_comment":"","value":"","family":"","comment":""},"12":{"family_comment":"","value":"","family":"","comment":""},"13":{"family_comment":"","value":"","family":"","comment":""},"14":{"family_comment":"","value":"","family":"","comment":""},"15":{"family_comment":"","value":"45900","family":"","comment":""},"16":{"family_comment":"","value":"","family":"","comment":""},"17":{"family_comment":"","value":"","family":"","comment":""},"18":{"family_comment":"","value":"","family":"","comment":""},"19":{"family_comment":"","value":"","family":"","comment":""},"20":{"value":"","comment_unclear":false,"family_comment":"","family":"","comment":"","family_comment_unclear":false}},"vehicle":{"35":[{"brand_info":"1690 куб. см.","sum_rent_comment":"","brand":"ВАЗ 21214","sum_comment":"","brand_unclear":false,"year":"2007","brand_hidden":false,"brand_info_unclear":false,"sum":"","sum_rent":"","sum_unclear":false}]},"id":"vulyk_75_122","declaration":{"additional_info_text":"","notfull_lostpages":"","date":"2014-03-28T00:00:00","notfull":"","additional_info":"","url":"http://static.declarations.com.ua/declarations/chosen_ones/judges_batch/1813_shurko_oleh_ivanovych.pdf"},"liabilities":{"54":{"sum_foreign_comment":"","sum":"","sum_comment":"","sum_foreign":""},"55":{"sum_foreign_comment":"","sum":"","sum_comment":"","sum_foreign":""},"56":{"sum_foreign_comment":"","sum":"76000","sum_comment":"","sum_foreign":""},"57":{"sum_foreign_comment":"","sum":"","sum_comment":"","sum_foreign":""},"58":{"sum_foreign_comment":"","sum":"","sum_comment":"","sum_foreign":""},"59":{"sum_foreign_comment":"","sum":"","sum_comment":"","sum_comment_unclear":false,"sum_unclear":false,"sum_foreign":""},"60":{"sum_foreign_comment":"","sum":"","sum_comment":"","sum_foreign":""},"61":{"sum_foreign_comment":"","sum":"","sum_comment":"","sum_foreign":""},"62":{"sum_foreign_comment":"","sum":"","sum_comment":"","sum_unclear":false,"sum_foreign":""},"63":{"sum_foreign_comment":"","sum":"","sum_comment":"","sum_foreign":""},"64":{"sum_foreign_comment":"","sum":"","sum_comment":"","sum_foreign":""}},"ft_src":"76000\nШурко Олег Іванович\nсуддя київського апеляційного адміністративного суду\nм. Київ\nАпеляційний адміністративний суд\nОлег\nЧернишенко О. В\nПодружжя\nШурко О. О\nДитина\nШурко Олег Іванович\nОлег Іванович Шурко\nОлег Шурко\nШурко Олег Іванович\nШурко\nІванович\nВАЗ 21214\n1690 куб. см.\n2007\n2500\n800\n52.9\n70.4\n2013\n245979\n45900\n12617\nвідмовилася надавати відомості\n304496\n1690 куб. см.\n2007\nВАЗ 21214\n2013\nШурко\nІванович\nПодружжя\nЧернишенко О. В\nДитина\nШурко О. О\nШурко Олег Іванович\nОлег Іванович Шурко\nОлег Шурко\nШурко Олег Іванович\nОлег\nШурко Олег Іванович\nАпеляційний адміністративний суд\nсуддя київського апеляційного адміністративного суду\nм. Київ\n76000\n245979\n45900\n304496\nвідмовилася надавати відомості\n12617\n2500\n800\n52.9\n70.4\n76000\nЧернишенко О. В\nПодружжя\nШурко О. О\nДитина\nШурко\nІванович\nсуддя київського апеляційного адміністративного суду\nм. Київ\nАпеляційний адміністративний суд\nШурко Олег Іванович\nШурко Олег Іванович\nОлег Іванович Шурко\nОлег Шурко\nШурко Олег Іванович\nОлег\n2007\nВАЗ 21214\n1690 куб. см.\n45900\n12617\nвідмовилася надавати відомості\n304496\n245979\n70.4\n2500\n800\n52.9\n2013","general":{"inn":"","inn_hidden":true,"last_name":"Шурко","post":{"office":"Апеляційний адміністративний суд","region":"м. Київ","post":"суддя київського апеляційного адміністративного суду"},"name":"Олег","full_name":"Шурко Олег Іванович","family_raw":"","addresses":[{"place_district":"","place_address_hidden":false,"place_city":"","place_city_type_hidden":false,"place_district_hidden":false,"place_city_type":"","place_city_hidden":false,"place_address":"","place_hidden":true,"place":""}],"family":[{"inn":"","inn_hidden":true,"relations_hidden":false,"family_name":"Чернишенко О. В","relations_other":"","relations":"Подружжя","name_hidden":false,"name_unclear":false},{"inn":"","relations":"Дитина","relations_other":"","inn_hidden":false,"family_name":"Шурко О. О","name_hidden":false,"name_unclear":false}],"full_name_suggest":{"output":"Шурко Олег Іванович","input":["Шурко Олег Іванович","Олег Іванович Шурко","Олег Шурко"]},"patronymic":"Іванович"},"source":"VULYK","estate":{"23":[{"costs":"","costs_comment":"","address_hidden":false,"region_hidden":true,"space_comment":"","space":"2500","address":"","region":"","costs_rent_comment":"","space_units":"м²","space_units_hidden":false,"costs_rent":""},{"costs_rent":"","region":"","costs":"","costs_rent_comment":"","costs_comment":"","region_hidden":true,"space_comment":"","space_units":"м²","space":"800","address":""}],"25":[{"space_hidden":false,"costs":"","costs_comment":"","address_hidden":false,"region_hidden":true,"space_comment":"","space_unclear":false,"space":"70.4","address":"","region":"","costs_rent_comment":"","space_units":"м²","costs_rent":""}],"26":[{"costs_rent":"","region":"","costs":"","costs_rent_comment":"","costs_comment":"","address_hidden":false,"region_hidden":true,"space_comment":"","space_units":"м²","space":"52.9","address":""}]},"intro":{"declaration_year":"2013","isnotdeclaration":""}}