{"id":"vulyk_97_113","ft_src":"Lexus GX 470\n4664\n2008\nХарківський р-н, Пісочинська сільрада\n830\nХарківська область\nХарківський р-н, пос. Високий\nХарківська область\n300\nХарківський р-н, пос. Високий\nХарківська область\n1900\n46.5\nХарківська область\nм. Харків\n25.5\nм. Харків\nХарківська область\n2014\n34049\n173637\n34049\n173637\n4664\nLexus GX 470\n2008\n2014\nШляхова Олена Миколаївна\nОлена Миколаївна Шляхова\nОлена Шляхова\nШляхова Олена Миколаївна\nОлена\nПодружжя\nШляхов В. Е\nШляхова Олена Миколаївна\nШляхова\nАдміністративний місцевий суд\nХарківська область\nсуддя\nМиколаївна\nХарківська область\nСМТ\nВисокий\nХарківський\n173637\n34049\n173637\n34049\n830\nХарківський р-н, Пісочинська сільрада\nХарківська область\n1900\nХарківська область\nХарківський р-н, пос. Високий\n300\nХарківська область\nХарківський р-н, пос. Високий\n46.5\nХарківська область\nм. Харків\n25.5\nм. Харків\nХарківська область\nПодружжя\nШляхов В. Е\nМиколаївна\nШляхова\nОлена\nШляхова Олена Миколаївна\nОлена Миколаївна Шляхова\nОлена Шляхова\nШляхова Олена Миколаївна\nСМТ\nВисокий\nХарківська область\nХарківський\nХарківська область\nАдміністративний місцевий суд\nсуддя\nШляхова Олена Миколаївна","estate":{"23":[{"address":"Харківський р-н, Пісочинська сільрада","space_units":"м²","costs_rent_unclear":false,"costs_comment":"","space_unclear":false,"region_hidden":false,"space_comment":"","address_hidden":true,"costs":"","address_unclear":false,"costs_rent_comment":"","space":"830","region_unclear":false,"region":"Харківська область","costs_rent":""}],"25":[{"address":"м. Харків","space_units":"м²","space_hidden":false,"space_unclear":false,"region_hidden":false,"costs_rent_comment":"","space_comment":"","address_hidden":true,"space_comment_hidden":false,"costs":"","space_comment_unclear":false,"costs_comment":"","space":"25.5","region_unclear":false,"region":"Харківська область","costs_rent":""}],"29":[{"costs_property_comment":"","address":"Харківський р-н, пос. Високий","space_units":"м²","space_unclear":false,"region_hidden":false,"costs_property":"","space_comment":"","address_hidden":false,"address_unclear":false,"space_comment_unclear":false,"costs_rent_comment":"","space":"1900","region_unclear":false,"region":"Харківська область","costs_rent":""}],"30":[{"costs_property_comment":"","address":"Харківський р-н, пос. Високий","space_units":"м²","space_comment":"","region_hidden":false,"costs_property":"","region":"Харківська область","address_hidden":true,"address_unclear":false,"costs_rent_comment":"","space":"300","costs_rent":""}],"31":[{"costs_property_comment":"","address":"м. Харків","space_units":"м²","space_hidden":false,"space_unclear":false,"region_hidden":false,"costs_property":"","space_comment":"","address_hidden":false,"space_comment_hidden":false,"costs_rent_comment":"","space":"46.5","region":"Харківська область","costs_rent":""}]},"vehicle":{"40":[{"sum_comment":"","brand_info":"4664","brand_unclear":false,"sum_rent_comment":"","year":"2008","brand":"Lexus GX 470","sum_rent":"","brand_info_unclear":false,"year_unclear":false,"sum":""}]},"source":"VULYK","income":{"5":{"family_comment":"","value":"173637","family":"34049","comment":""},"6":{"family_comment":"","family":"34049","comment":"","value_unclear":false,"family_unclear":false,"comment_hidden":false,"value":"173637"},"7":{"family":"","family_comment":"","value":"","comment":"","source_name":""},"8":{"family_comment":"","value":"","family":"","comment":""},"9":{"family_comment":"","value":"","family_unclear":false,"family":"","comment":""},"10":{"family_comment":"","value":"","family":"","comment":"","value_unclear":false},"11":{"family_comment":"","value":"","family":"","comment":""},"12":{"family_comment":"","value":"","family":"","comment":""},"13":{"family_comment":"","value":"","family":"","comment":""},"14":{"family_comment":"","value":"","family":"","comment":""},"15":{"family_comment":"","value":"","family":"","comment":""},"16":{"family_comment":"","value":"","family":"","comment":""},"17":{"family_comment":"","value":"","family":"","comment":""},"18":{"family_comment":"","value":"","family":"","comment":""},"19":{"family_comment":"","value":"","family":"","comment":""},"20":{"family_comment":"","comment":"","family":"","value_unclear":false,"comment_unclear":false,"value":"","family_hidden":false,"family_comment_unclear":false}},"general":{"family":[{"inn":"","family_name":"Шляхов В. Е","relations_other":"","name_unclear":false,"inn_hidden":true,"name_hidden":true,"relations":"Подружжя"}],"family_raw":"","name":"Олена","full_name_suggest":{"input":["Шляхова Олена Миколаївна","Олена Миколаївна Шляхова","Олена Шляхова"],"output":"Шляхова Олена Миколаївна"},"patronymic":"Миколаївна","inn_hidden":true,"addresses":[{"place_city_type":"СМТ","place_city_type_hidden":false,"place_hidden":false,"place_city_hidden":false,"place_district_hidden":false,"place_district":"Харківський","place_city_unclear":false,"place":"Харківська область","place_city":"Високий","place_address_hidden":true,"place_address":""}],"last_name_hidden":false,"patronymic_hidden":false,"inn":"","inn_unclear":false,"last_name":"Шляхова","full_name":"Шляхова Олена Миколаївна","post":{"post_hidden":false,"office":"Адміністративний місцевий суд","post":"суддя","office_unclear":true,"region_unclear":false,"region":"Харківська область"},"name_hidden":false},"liabilities":{"54":{"sum_comment_unclear":false,"sum_comment":"","sum_hidden":false,"sum":"","sum_foreign_comment":"","sum_foreign":"","sum_unclear":false,"sum_comment_hidden":false},"55":{"sum_comment":"","sum_foreign_comment":"","sum_foreign":"","sum":""},"56":{"sum_comment":"","sum_foreign_comment":"","sum_foreign":"","sum":""},"57":{"sum_comment_unclear":false,"sum_comment":"","sum_hidden":false,"sum":"","sum_foreign_comment":"","sum_foreign":"","sum_unclear":false,"sum_comment_hidden":false},"58":{"sum_comment_unclear":false,"sum_comment":"","sum_hidden":false,"sum":"","sum_foreign_comment":"","sum_foreign":"","sum_unclear":false,"sum_comment_hidden":false},"59":{"sum_comment":"","sum_foreign_comment":"","sum_foreign":"","sum":""},"60":{"sum_comment_unclear":false,"sum_comment":"","sum_hidden":false,"sum":"","sum_foreign_comment":"","sum_foreign":"","sum_comment_hidden":false},"61":{"sum_comment":"","sum_foreign_comment":"","sum_foreign":"","sum":""},"62":{"sum_comment":"","sum_foreign_comment":"","sum_foreign":"","sum_unclear":false,"sum":""},"63":{"sum_comment":"","sum_foreign_comment":"","sum_foreign":"","sum_hidden":false,"sum":""},"64":{"sum_comment":"","sum_foreign_comment":"","sum_foreign":"","sum":""}},"declaration":{"notfull_lostpages":"","additional_info_text":"","additional_info":"","date":"2015-03-26T00:00:00","notfull":"","url":"http://static.declarations.com.ua/declarations/chosen_ones/judges_batch/4014_shliakhova_olena_mykolaivna.pdf"},"intro":{"isnotdeclaration":"","declaration_year":"2014"}}