{"id":"vulyk_92_64","ft_src":"1598 куб. см.\nToyota Corolla\n2008\nм. Харків\n24.6\nХарківська область\nХарківська область\nХарківський р-н\n2125\nХарківська область\nХарківський р-н\n65.9\nм. Харків\n77\nХарківська область\nм. Харків\n37.6\nХарківська область\n2014\n279523\n68\n13150\n393471\n13150\nпенсія\n113880\n1598 куб. см.\nToyota Corolla\n2008\n2125\nХарківський р-н\nХарківська область\n24.6\nХарківська область\nм. Харків\nХарківська область\nХарківський р-н\n65.9\n77\nХарківська область\nм. Харків\nм. Харків\n37.6\nХарківська область\nПодружжя\nПашнєва М. М\nДитина\nПашнєва О. Г\nПашнєв Григорій Григорович\nГригорій Григорович Пашнєв\nГригорій Пашнєв\nПашнєв Григорій Григорович\nПашнєв Григорій Григорович\nГригорій\nПашнєв\nЗагальний апеляційний суд\nсуддя апеляційного суду харківської області\nХарківська область\nГригорович\n279523\n113880\nпенсія\n13150\n393471\n13150\n68\n2014\nПодружжя\nПашнєва М. М\nДитина\nПашнєва О. Г\nГригорович\nПашнєв\nГригорій\nПашнєв Григорій Григорович\nГригорій Григорович Пашнєв\nГригорій Пашнєв\nПашнєв Григорій Григорович\nХарківська область\nЗагальний апеляційний суд\nсуддя апеляційного суду харківської області\nПашнєв Григорій Григорович","estate":{"25":[{"address":"м. Харків","space_units":"м²","space_hidden":false,"space_comment":"","region_hidden":false,"costs_comment":"","address_hidden":false,"costs":"","address_unclear":false,"space_comment_unclear":false,"costs_rent_comment":"","space":"77","region":"Харківська область","costs_rent":""},{"costs":"","address":"м. Харків","space_units":"","costs_rent_comment":"","space":"37.6","space_comment":"","region_hidden":false,"costs_comment":"","region":"Харківська область","address_hidden":false,"costs_rent":""}],"27":[{"address":"м. Харків","space_units":"м²","space_hidden":false,"space_unclear":false,"region_hidden":false,"costs_comment":"","space_comment":"","address_hidden":false,"costs":"","address_unclear":false,"costs_rent_comment":"","space":"24.6","region":"Харківська область","costs_rent":""}],"29":[{"costs_property_comment":"","costs_property":"","address":"Харківський р-н","space_units":"м²","space_unclear":false,"region_hidden":false,"space_units_unclear":false,"space_comment":"","address_hidden":false,"costs_rent_comment":"","space":"2125","region":"Харківська область","space_units_hidden":false,"costs_rent":""}],"30":[{"costs_property_comment":"","address":"Харківський р-н","space_units":"м²","space_hidden":false,"space_unclear":false,"region_hidden":false,"costs_property":"","space_comment":"","address_hidden":false,"address_unclear":false,"costs_rent_comment":"","space":"65.9","region":"Харківська область","costs_rent":""}]},"vehicle":{"35":[{"sum_comment_unclear":false,"brand_info":"1598 куб. см.","sum_rent_comment":"","brand_unclear":false,"brand_hidden":false,"year":"2008","sum_comment":"","brand_info_hidden":false,"sum_rent":"","brand":"Toyota Corolla","year_unclear":false,"brand_info_unclear":false,"sum":""}]},"source":"VULYK","income":{"5":{"family_comment":"","family_hidden":false,"value":"393471","family":"13150","comment":""},"6":{"family_comment":"","family":"","comment":"","value_unclear":false,"family_hidden":false,"value":"279523"},"7":{"family_comment":"","comment":"","family":"","value_unclear":false,"value":"","source_name":""},"8":{"family_comment":"","value":"","family":"","comment":""},"9":{"family_comment":"","value":"68","family":"","comment":""},"10":{"family_comment":"","comment":"","family":"","family_unclear":false,"comment_unclear":false,"value":"","family_comment_unclear":false},"11":{"family_comment":"","value":"","family":"","comment":"","value_unclear":false},"12":{"family_comment":"","value":"","family":"","comment":""},"13":{"family_comment":"","value":"","family":"","comment":""},"14":{"family_comment":"","value":"","family":"","comment":""},"15":{"family_comment":"","comment":"","family":"","family_unclear":false,"comment_unclear":false,"value":""},"16":{"family_comment":"","value":"","family":"","comment":""},"17":{"family_comment":"","value":"","family":"","comment":""},"18":{"family_comment":"","value":"","family_unclear":false,"family":"","comment":""},"19":{"family_comment":"","value":"","family":"","comment":""},"20":{"family_comment":"","value":"113880","family_unclear":false,"family":"13150","comment":"пенсія"}},"general":{"family_raw":"","name":"Григорій","full_name_suggest":{"input":["Пашнєв Григорій Григорович","Григорій Григорович Пашнєв","Григорій Пашнєв"],"output":"Пашнєв Григорій Григорович"},"patronymic":"Григорович","inn_hidden":true,"patronymic_unclear":false,"inn":"","inn_unclear":false,"last_name":"Пашнєв","full_name":"Пашнєв Григорій Григорович","family":[{"inn":"","inn_unclear":false,"family_name":"Пашнєва М. М","relations_hidden":false,"name_unclear":false,"relations":"Подружжя","inn_hidden":false,"name_hidden":false,"relations_other":""},{"inn":"","inn_unclear":false,"family_name":"Пашнєва О. Г","relations_hidden":false,"name_unclear":false,"relations":"Дитина","inn_hidden":false,"name_hidden":false,"relations_other":""}],"post":{"office":"Загальний апеляційний суд","post":"суддя апеляційного суду харківської області","office_unclear":false,"region_hidden":false,"region":"Харківська область","office_hidden":false,"post_unclear":false},"addresses":[{"place_city_type":"","place_address_unclear":false,"place_city_type_hidden":false,"place_hidden":true,"place_city_hidden":false,"place_district":"","place_district_hidden":false,"place":"","place_city":"","place_address_hidden":false,"place_address":""}]},"liabilities":{"54":{"sum_comment":"","sum_hidden":false,"sum":"","sum_foreign_comment":"","sum_foreign":"","sum_unclear":false},"55":{"sum_comment":"","sum_foreign_comment":"","sum_foreign":"","sum_unclear":false,"sum":""},"56":{"sum_comment_unclear":false,"sum_comment":"","sum_hidden":false,"sum":"","sum_foreign_comment":"","sum_foreign":"","sum_unclear":false},"57":{"sum_comment":"","sum_hidden":false,"sum":"","sum_foreign_comment":"","sum_foreign":"","sum_comment_hidden":false},"58":{"sum_comment":"","sum_foreign_comment":"","sum_foreign":"","sum":""},"59":{"sum_comment":"","sum_comment_unclear":false,"sum_foreign_comment":"","sum":"","sum_foreign":""},"60":{"sum_comment":"","sum_foreign_comment":"","sum_foreign":"","sum":""},"61":{"sum_comment":"","sum_foreign_comment":"","sum_foreign":"","sum":""},"62":{"sum_comment_unclear":false,"sum_comment":"","sum_hidden":false,"sum":"","sum_foreign_comment":"","sum_foreign":"","sum_unclear":false},"63":{"sum_comment":"","sum_foreign_comment":"","sum_foreign":"","sum":""},"64":{"sum_comment":"","sum_foreign_comment":"","sum_foreign":"","sum":""}},"declaration":{"notfull_lostpages":"","additional_info_text":"","additional_info":"","date":"2015-03-31T00:00:00","notfull":"","url":"http://static.declarations.com.ua/declarations/chosen_ones/judges_batch/3312_pashniev_hryhorii_hryhorovych.pdf"},"intro":{"isnotdeclaration":"","declaration_year":"2014"}}