{"id":"vulyk_99_64","ft_src":"2010\nNissan Almera Classic\n1596 куб. см., 18.7 кВт\n1248 куб. см., 66 кВт\nFiat Punto\n2009\n79.3\n100\n120\n2015\n6778.95\n184532\n106\n12180\n6778.95\n197065\n247\n1596 куб. см., 18.7 кВт\nNissan Almera Classic\n2010\n1248 куб. см., 66 кВт\n2009\nFiat Punto\n2015\nВоробйова\nВоробйова Інна Анатоліївна\nІнна Анатоліївна Воробйова\nІнна Воробйова\nВоробйова Інна Анатоліївна\nІнна\nАнатоліївна\nВоробйова Інна Анатоліївна\nАдміністративний місцевий суд\nсуддя вінницького окружного адміністративного суду\nВінницька область\nПодружжя\nВоловодівський І. В\nДитина\nВоловодівський І. І\n6406.6\n5150 Граве-Украина, 1256,6 Митлайв\nПАТ Граве Україна страхування життя\n5000\nОТР Банк\n1573.8\n105.93\n184532\n6778.95\n247\n197065\n6778.95\n106\n12180\n79.3\n100\n120\n5150 Граве-Украина, 1256,6 Митлайв\n6406.6\nПАТ Граве Україна страхування життя\n5000\nОТР Банк\n1573.8\n105.93\nВоловодівський І. В\nПодружжя\nВоловодівський І. І\nДитина\nАнатоліївна\nВоробйова\nсуддя вінницького окружного адміністративного суду\nВінницька область\nАдміністративний місцевий суд\nВоробйова Інна Анатоліївна\nВоробйова Інна Анатоліївна\nІнна Анатоліївна Воробйова\nІнна Воробйова\nВоробйова Інна Анатоліївна\nІнна","estate":{"23":[{"address":"","space_units":"м²","costs_comment":"","space_unclear":false,"region_hidden":true,"space_comment":"","address_hidden":false,"costs":"","costs_rent_comment":"","space":"79.3","region":"","costs_rent":""}],"29":[{"costs_property_comment":"","address":"","space_units":"м²","costs_rent_comment":"","space":"100","region":"","region_hidden":true,"costs_property":"","space_comment":"","address_hidden":false,"costs_rent":""},{"costs_property_comment":"","address":"","space_units":"м²","costs_rent_comment":"","space":"120","region":"","costs_property":"","space_comment":"","costs_rent":""}]},"vehicle":{"35":[{"sum_comment":"","brand_info":"1596 куб. см., 18.7 кВт","brand_unclear":false,"sum_rent_comment":"","year":"2010","brand":"Nissan Almera Classic","sum_rent":"","brand_info_unclear":false,"sum":""}],"40":[{"sum_comment":"","brand_info_hidden":false,"sum_rent":"","sum":"","brand_unclear":false,"year":"2009","brand":"Fiat Punto","brand_info":"1248 куб. см., 66 кВт","sum_rent_comment":"","brand_info_unclear":false}]},"source":"VULYK","income":{"5":{"family_comment":"","family":"6778.95","comment":"","value_unclear":false,"family_unclear":false,"value":"197065"},"6":{"family_comment":"","family":"6778.95","comment":"","value_unclear":false,"family_unclear":false,"value":"184532"},"7":{"family":"","family_comment":"","value":"","comment":"","source_name":""},"8":{"family_comment":"","value":"","family":"","comment":""},"9":{"family_comment":"","value":"106","family":"","comment":""},"10":{"family_comment":"","value":"12180","family":"","comment":""},"11":{"family_comment":"","value":"","family":"","comment":""},"12":{"family_comment":"","value":"","family":"","comment":""},"13":{"family_comment":"","value":"","family":"","comment":""},"14":{"family_comment":"","value":"","family":"","comment":""},"15":{"family_comment":"","value":"","family":"","comment":"","value_unclear":false},"16":{"family_comment":"","value":"","family":"","comment":""},"17":{"family_comment":"","value":"","family":"","comment":""},"18":{"family_comment":"","value":"","family":"","comment":""},"19":{"family_comment":"","value":"","family":"","comment":""},"20":{"family_comment":"","family":"","comment":"","value_unclear":false,"family_unclear":false,"value":"247","family_comment_unclear":false}},"general":{"inn":"","addresses":[{"place_city_type_hidden":false,"place_city_type":"","place_city_hidden":true,"place_hidden":true,"place_district":"","place_district_hidden":false,"place":"","place_address":"","place_address_hidden":true,"place_city":""}],"last_name":"Воробйова","full_name":"Воробйова Інна Анатоліївна","family":[{"inn":"","family_name":"Воловодівський І. В","name_unclear":true,"inn_hidden":true,"name_hidden":true,"relations":"Подружжя"},{"inn":"","family_name":"Воловодівський І. І","relations_other":"","name_unclear":false,"inn_hidden":true,"relations":"Дитина"}],"patronymic":"Анатоліївна","inn_hidden":true,"name":"Інна","post":{"office":"Адміністративний місцевий суд","region":"Вінницька область","post_unclear":false,"post":"суддя вінницького окружного адміністративного суду"},"family_raw":"","full_name_suggest":{"input":["Воробйова Інна Анатоліївна","Інна Анатоліївна Воробйова","Інна Воробйова"],"output":"Воробйова Інна Анатоліївна"}},"liabilities":{"54":{"sum_comment_unclear":false,"sum_comment":"5150 Граве-Украина, 1256,6 Митлайв","sum":"6406.6","sum_foreign_comment":"","sum_foreign":"","sum_comment_hidden":false},"55":{"sum_comment":"","sum_foreign_comment":"","sum_foreign":"","sum":""},"56":{"sum_comment":"","sum_foreign_comment":"","sum_foreign":"","sum":""},"57":{"sum_comment":"","sum_foreign_comment":"","sum_foreign":"","sum":"","sum_comment_hidden":false},"58":{"sum_comment":"","sum_foreign_comment":"","sum_foreign":"","sum":"","sum_comment_hidden":false},"59":{"sum_comment":"","sum":"","sum_foreign_comment":"","sum_foreign":"","sum_unclear":false,"sum_comment_hidden":false},"60":{"sum_comment":"ПАТ Граве Україна страхування життя","sum_foreign_comment":"","sum_foreign":"","sum":"5000","sum_comment_hidden":false},"61":{"sum_comment":"","sum_foreign_comment":"","sum_foreign":"","sum":""},"62":{"sum_comment":"","sum_foreign_comment":"","sum_foreign":"","sum":""},"63":{"sum_comment":"ОТР Банк","sum_foreign_comment":"","sum_foreign":"","sum":"1573.8","sum_comment_hidden":false},"64":{"sum_comment":"","sum_foreign_comment":"","sum_foreign":"","sum":"105.93","sum_comment_hidden":false}},"declaration":{"notfull_lostpages":"","date":"2016-03-30T00:00:00","notfull":"","url":"http://static.declarations.com.ua/declarations/chosen_ones/judges_batch/613_vorobiova_inna_anatoliivna_2015.pdf"},"intro":{"declaration_year":"2015"}}