{"income":{"5":{"value":"225816","family_comment":"","value_unclear":true,"family_unclear":false,"family":"","comment":""},"6":{"family_comment":"","family_unclear":false,"value":"225816","family":"","comment":""},"7":{"source_name_unclear":false,"value":"","family_comment":"","source_name":"","family":"","comment":""},"8":{"family_comment":"","value":"","family":"","comment":""},"9":{"value":"","family_comment":"","comment_hidden":false,"family_unclear":false,"family":"","comment":"","family_comment_hidden":false},"10":{"family_comment":"","value":"","family":"","comment":""},"11":{"family_comment":"","value":"","family":"","comment":""},"12":{"family_comment":"","value":"","family":"","comment":""},"13":{"family_comment":"","value":"","family":"","comment":""},"14":{"family_comment":"","value":"","family":"","comment":""},"15":{"family_comment":"","value":"","family":"","comment":""},"16":{"family_comment":"","value":"","family":"","comment":""},"17":{"family_comment":"","value":"","family":"","comment":""},"18":{"family_comment":"","value":"","family":"","comment":""},"19":{"family_comment":"","value":"","family":"","comment":""},"20":{"value":"","value_unclear":false,"comment_hidden":false,"family_comment":"","comment_unclear":false,"comment":"","family":""}},"vehicle":{"35":[{"brand_info":"1498 куб. см.,  464 см","sum_rent_comment":"","brand":"Chevrolet Aveo","sum_comment":"","year":"2007","brand_info_unclear":true,"sum":"","sum_rent":""}]},"id":"vulyk_108_63","declaration":{"additional_info_text":"","notfull_lostpages":"","date":"2016-03-24T00:00:00","notfull":"","additional_info":"","url":"http://static.declarations.com.ua/declarations/chosen_ones/judges_batch/2362_vasetska_viktoriia_vasylivna_2015.pdf"},"liabilities":{"54":{"sum_foreign_comment":"","sum":"","sum_hidden":false,"sum_comment":"","sum_foreign":""},"55":{"sum_foreign_comment":"","sum":"","sum_comment":"","sum_foreign":""},"56":{"sum_foreign_comment":"","sum":"","sum_comment":"","sum_unclear":false,"sum_foreign":""},"57":{"sum_foreign_comment":"","sum":"","sum_comment":"","sum_hidden":false,"sum_comment_hidden":false,"sum_foreign":""},"58":{"sum_foreign_comment":"","sum_comment_hidden":false,"sum":"","sum_comment":"","sum_foreign":""},"59":{"sum_foreign_comment":"","sum":"","sum_comment":"","sum_unclear":false,"sum_foreign":""},"60":{"sum_foreign_comment":"","sum_comment_hidden":false,"sum":"","sum_comment":"","sum_foreign":""},"61":{"sum_foreign_comment":"","sum_comment_hidden":false,"sum":"","sum_comment":"","sum_foreign":""},"62":{"sum_foreign_comment":"","sum":"","sum_comment":"","sum_foreign":""},"63":{"sum_foreign_comment":"","sum":"","sum_comment":"","sum_hidden":false,"sum_comment_hidden":false,"sum_unclear":false,"sum_foreign":""},"64":{"sum_foreign_comment":"","sum":"","sum_comment":"","sum_comment_hidden":false,"sum_unclear":false,"sum_foreign":""}},"ft_src":"суддя апеляційного суду дніпропетровської області\nДніпропетровська область\nЗагальний апеляційний суд\nВікторія\nВасецький Г. Ф\nДитина\nВасецький М. Ф\nДитина\nВасилівна\nВасецька Вікторія Василівна\nВікторія Василівна Васецька\nВікторія Васецька\nВасецька Вікторія Василівна\nВасецька Вікторія Василівна\nВасецька\n225816\n225816\n2007\n1498 куб. см.,  464 см\nChevrolet Aveo\n1498 куб. см.,  464 см\n2007\nChevrolet Aveo\n2015\n225816\n225816\n1498 куб. см.,  464 см\n2007\nChevrolet Aveo\n225816\n225816\nВасецька Вікторія Василівна\nВікторія Василівна Васецька\nВікторія Васецька\nВасецька Вікторія Василівна\nВікторія\nДитина\nВасецький Г. Ф\nДитина\nВасецький М. Ф\nВасецька Вікторія Василівна\nВасилівна\nЗагальний апеляційний суд\nДніпропетровська область\nсуддя апеляційного суду дніпропетровської області\nВасецька\n2015\nДитина\nВасецький Г. Ф\nДитина\nВасецький М. Ф\nВасилівна\nВасецька\nВікторія\nВасецька Вікторія Василівна\nВікторія Василівна Васецька\nВікторія Васецька\nВасецька Вікторія Василівна\nДніпропетровська область\nсуддя апеляційного суду дніпропетровської області\nЗагальний апеляційний суд\nВасецька Вікторія Василівна\n2015","general":{"inn":"","name":"Вікторія","inn_unclear":false,"family":[{"inn":"","relations":"Дитина","inn_unclear":false,"relations_hidden":false,"inn_hidden":true,"relations_other":"","name_hidden":true,"family_name":"Васецький Г. Ф","name_unclear":true},{"inn":"","relations":"Дитина","relations_other":"","inn_hidden":false,"family_name":"Васецький М. Ф","name_hidden":false,"name_unclear":false}],"inn_hidden":true,"family_raw":"","last_name":"Васецька","post":{"post_unclear":false,"post":"суддя апеляційного суду дніпропетровської області","office_hidden":false,"region":"Дніпропетровська область","office":"Загальний апеляційний суд","office_unclear":false},"full_name":"Васецька Вікторія Василівна","addresses":[{"place_city_type_hidden":true,"place_district_hidden":true,"place_city_type":"","place_city_hidden":true,"place_address_unclear":false,"place_address":"","place_hidden":true,"place":"","place_district":"","place_unclear":false,"place_city":"","place_address_hidden":true}],"patronymic":"Василівна","full_name_suggest":{"output":"Васецька Вікторія Василівна","input":["Васецька Вікторія Василівна","Вікторія Василівна Васецька","Вікторія Васецька"]}},"source":"VULYK","intro":{"declaration_year":"2015","isnotdeclaration":"","declaration_year_hidden":false}}