{"income":{"5":{"value":"228370","family_comment":"","value_unclear":false,"family_hidden":false,"family_unclear":false,"family":"","comment":""},"6":{"family_comment":"","value":"227957","family":"","comment":""},"7":{"family_comment":"","value":"","source_name":"","family":"","comment":""},"8":{"family_comment":"","value":"","family":"","comment":""},"9":{"family_comment":"","value":"413","family":"","comment":""},"10":{"family_comment":"","value":"","value_unclear":false,"family":"","comment":""},"11":{"family_comment":"","value":"","family":"","comment":""},"12":{"family_comment":"","value":"","family":"","comment":""},"13":{"family_comment":"","value":"","family":"","comment":""},"14":{"family_comment":"","value":"","family":"","comment":""},"15":{"family_comment":"","value":"","family":"","comment":""},"16":{"family_comment":"","value":"","family":"","comment":""},"17":{"family_comment":"","value":"","family":"","comment":""},"18":{"family_comment":"","value":"","family":"","comment":""},"19":{"family_comment":"","value":"","family":"","comment":""},"20":{"family_comment":"","value":"","family":"","comment":""}},"vehicle":{"35":[{"brand_info":"1.5","sum_rent_comment":"","brand":"Daewoo Lanos","sum_comment":"","brand_unclear":false,"year":"2007","sum":"","sum_rent":""},{"brand_info":"1.6","sum_rent_comment":"","brand":"Nissan Note","sum_comment":"","year":"2008","sum":"","sum_rent":""}]},"id":"vulyk_82_43","declaration":{"date":"2015-03-31T00:00:00","additional_info_text":"","additional_info":"","url":"http://static.declarations.com.ua/declarations/chosen_ones/judges_batch/2238_nabudovych_iryna_oleksandrivna.pdf"},"liabilities":{"54":{"sum_foreign_comment":"","sum_comment_hidden":false,"sum":"","sum_comment":"","sum_foreign":""},"55":{"sum_foreign_comment":"","sum":"","sum_hidden":false,"sum_comment":"","sum_foreign":""},"56":{"sum_foreign_comment":"","sum":"","sum_comment":"","sum_foreign":""},"57":{"sum_foreign_comment":"","sum":"","sum_comment":"","sum_foreign":""},"58":{"sum_foreign_comment":"","sum":"","sum_comment":"","sum_foreign":""},"59":{"sum_foreign_comment":"","sum":"","sum_comment":"","sum_foreign":""},"60":{"sum_foreign_comment":"","sum":"","sum_comment":"","sum_foreign":""},"61":{"sum_foreign_comment":"","sum":"","sum_comment":"","sum_foreign":""},"62":{"sum_foreign_comment":"","sum":"","sum_comment":"","sum_foreign":""},"63":{"sum_foreign_comment":"","sum":"","sum_comment":"","sum_foreign":""},"64":{"sum_foreign_comment":"","sum":"","sum_comment":"","sum_foreign":""}},"ft_src":"заступник голови дарницького районного суду м. києва\nм. Київ\nЗагальний місцевий суд\nІрина\nДитина\nДитина\nОлександрівна\nНабудович Ірина Олександрівна\nІрина Олександрівна Набудович\nІрина Набудович\nНабудович Ірина Олександрівна\nНабудович Ірина Олександрівна\nНабудович\n2007\n1.5\nDaewoo Lanos\n1.6\n2008\nNissan Note\n66.4\n2014\n227957\n413\n228370\n1.5\n2007\nDaewoo Lanos\n1.6\n2008\nNissan Note\n2014\nДитина\nДитина\nНабудович Ірина Олександрівна\nІрина Олександрівна Набудович\nІрина Набудович\nНабудович Ірина Олександрівна\nНабудович Ірина Олександрівна\nІрина\nНабудович\nЗагальний місцевий суд\nм. Київ\nзаступник голови дарницького районного суду м. києва\nОлександрівна\n227957\n228370\n413\n66.4\nДитина\nДитина\nОлександрівна\nНабудович\nІрина\nНабудович Ірина Олександрівна\nІрина Олександрівна Набудович\nІрина Набудович\nНабудович Ірина Олександрівна\nм. Київ\nЗагальний місцевий суд\nзаступник голови дарницького районного суду м. києва\nНабудович Ірина Олександрівна\n2007\n1.5\nDaewoo Lanos\nNissan Note\n1.6\n2008\n413\n228370\n227957\n66.4\n2014","general":{"inn":"","name":"Ірина","inn_unclear":false,"family":[{"inn":"","inn_hidden":true,"relations_hidden":false,"family_name":"","relations_other":"","relations":"Дитина","name_hidden":true,"name_unclear":false},{"inn":"","relations":"Дитина","relations_other":"","inn_hidden":false,"family_name":"","name_hidden":false,"name_unclear":false}],"inn_hidden":true,"family_raw":"","last_name":"Набудович","post":{"post":"заступник голови дарницького районного суду м. києва","region":"м. Київ","office_hidden":false,"office":"Загальний місцевий суд","office_unclear":false,"post_hidden":false,"region_hidden":false},"full_name_suggest":{"output":"Набудович Ірина Олександрівна","input":["Набудович Ірина Олександрівна","Ірина Олександрівна Набудович","Ірина Набудович"]},"full_name":"Набудович Ірина Олександрівна","addresses":[{"place_district":"","place_city_hidden":true,"place_city":"","place_city_type_hidden":false,"place_district_hidden":false,"place_city_type":"","place_address_hidden":false,"place_address":"","place_hidden":true,"place":""}],"patronymic":"Олександрівна","last_name_unclear":false},"source":"VULYK","estate":{"25":[{"space_hidden":false,"costs":"","costs_comment":"","costs_hidden":false,"address_hidden":false,"region_hidden":true,"space_comment":"","space_unclear":false,"space":"66.4","address":"","region":"","costs_rent_comment":"","space_comment_unclear":false,"space_units":"м²","costs_rent":""}]},"intro":{"declaration_year":"2014"}}