{"income":{"5":{"family_comment":"","value":"220400","family_hidden":false,"comment":"","family":"11655"},"6":{"value":"220400","value_unclear":false,"family_hidden":false,"family_comment":"","family":"","comment":""},"7":{"value":"","value_unclear":false,"family_comment":"","source_name":"","family":"","comment":""},"8":{"family_comment":"","value":"","family":"","comment":""},"9":{"family_comment":"","value":"","family":"","comment":""},"10":{"value":"12180","family_comment":"","comment_unclear":false,"family_unclear":false,"family":"","comment":"","family_comment_unclear":false},"11":{"family_comment":"","value":"","value_unclear":false,"family":"","comment":""},"12":{"family_comment":"","value":"","family":"","comment":""},"13":{"family_comment":"","value":"","family":"","comment":""},"14":{"family_comment":"","value":"","family":"","comment":""},"15":{"value":"","family_comment":"","comment_unclear":false,"family_unclear":false,"family":"","comment":""},"16":{"family_comment":"","value":"","family":"","comment":""},"17":{"family_comment":"","value":"","family":"","comment":""},"18":{"family_comment":"","family_unclear":false,"value":"","family":"","comment":""},"19":{"family_comment":"","value":"","family":"","comment":""},"20":{"family_comment":"","family_unclear":false,"value":"","family":"11655","comment":""}},"vehicle":{"35":[{"brand_info":"2500 куб. см., 124 кВт , 463 см","sum_rent_comment":"","year":"2008","brand_info_hidden":false,"brand_info_unclear":false,"year_unclear":false,"sum_rent":"","sum":"","brand":"Nissan X-Trail","sum_comment":"","sum_comment_unclear":false,"brand_hidden":false,"brand_unclear":false}]},"id":"vulyk_92_177","declaration":{"additional_info_text":"","notfull_lostpages":"","date":"2015-03-27T00:00:00","notfull":"","additional_info":"","url":"http://static.declarations.com.ua/declarations/chosen_ones/judges_batch/3423_hulkevych_orest_vasylovych.pdf"},"liabilities":{"54":{"sum_foreign_comment":"","sum":"","sum_comment":"","sum_hidden":false,"sum_unclear":false,"sum_foreign":""},"55":{"sum_foreign_comment":"","sum":"","sum_comment":"","sum_unclear":false,"sum_foreign":""},"56":{"sum_foreign_comment":"","sum":"","sum_comment":"","sum_comment_unclear":false,"sum_hidden":false,"sum_unclear":false,"sum_foreign":""},"57":{"sum_foreign_comment":"","sum":"","sum_comment":"","sum_hidden":false,"sum_comment_hidden":false,"sum_foreign":""},"58":{"sum_foreign_comment":"","sum":"","sum_comment":"","sum_foreign":""},"59":{"sum_foreign_comment":"","sum":"","sum_comment":"","sum_comment_unclear":false,"sum_foreign":""},"60":{"sum_foreign_comment":"","sum":"","sum_comment":"","sum_foreign":""},"61":{"sum_foreign_comment":"","sum":"","sum_comment":"","sum_foreign":""},"62":{"sum_foreign_comment":"","sum":"","sum_comment":"","sum_comment_unclear":false,"sum_hidden":false,"sum_unclear":false,"sum_foreign":""},"63":{"sum_foreign_comment":"","sum":"","sum_comment":"","sum_foreign":""},"64":{"sum_foreign_comment":"","sum":"","sum_comment":"","sum_foreign":""}},"ft_src":"Стрий\nЛьвівська область\nсуддя стрийського міськрайонного суду львівської області\nЛьвівська область\nЗагальний місцевий суд\nОрест\nНебесна Н. В\nПодружжя\nГулкевич О. О\nДитина\nГулкевич А. О\nДитина\nВасильович\nГулкевич Орест Васильович\nОрест Васильович Гулкевич\nОрест Гулкевич\nГулкевич Орест Васильович\nГулкевич Орест Васильович\nГулкевич\n2500 куб. см., 124 кВт , 463 см\nNissan X-Trail\n2008\nЛьвівська область\nм. Стрий\n31.1\n1/4 частина\nм. Ходорів\n52.2\nЛьвівська область\nЛьвівська область\nСтрийський р-н\n100\nЛьвівська область\nСтрийський р-н\n124\nм. Стрий\n226.2\nЛьвівська область\n2014\n220400\n12180\n11655\n220400\n11655\n2500 куб. см., 124 кВт , 463 см\nNissan X-Trail\n2008\n100\nСтрийський р-н\nЛьвівська область\nСтрийський р-н\nЛьвівська область\n124\nЛьвівська область\nм. Стрий\n31.1\nЛьвівська область\n52.2\n1/4 частина\nм. Ходорів\n226.2\nЛьвівська область\nм. Стрий\nПодружжя\nНебесна Н. В\nДитина\nГулкевич О. О\nДитина\nГулкевич А. О\nГулкевич Орест Васильович\nОрест Васильович Гулкевич\nОрест Гулкевич\nГулкевич Орест Васильович\nГулкевич Орест Васильович\nОрест\nГулкевич\nЗагальний місцевий суд\nсуддя стрийського міськрайонного суду львівської області\nЛьвівська область\nВасильович\nЛьвівська область\nСтрий\n220400\n11655\n220400\n11655\n12180\n2014\nПодружжя\nНебесна Н. В\nДитина\nГулкевич О. О\nДитина\nГулкевич А. О\nВасильович\nГулкевич\nОрест\nГулкевич Орест Васильович\nОрест Васильович Гулкевич\nОрест Гулкевич\nГулкевич Орест Васильович\nСтрий\nЛьвівська область\nЛьвівська область\nЗагальний місцевий суд\nсуддя стрийського міськрайонного суду львівської області\nГулкевич Орест Васильович\n2008\nNissan X-Trail\n2500 куб. см., 124 кВт , 463 см\n12180\n11655\n11655\n220400\n220400\nм. Стрий\nЛьвівська область\n31.1\nм. Стрий\nЛьвівська область\n226.2\n1/4 частина\nЛьвівська область\nм. Ходорів\n52.2\nЛьвівська область\nСтрийський р-н\n100\nСтрийський р-н\nЛьвівська область\n124\n2014","general":{"inn":"","name":"Орест","patronymic_unclear":false,"family":[{"inn":"","relations":"Подружжя","inn_unclear":false,"relations_hidden":false,"inn_hidden":true,"relations_other":"","name_hidden":false,"family_name":"Небесна Н. В","name_unclear":false},{"inn":"","relations":"Дитина","inn_unclear":false,"relations_hidden":false,"inn_hidden":false,"relations_other":"","name_hidden":false,"family_name":"Гулкевич О. О","name_unclear":false},{"inn":"","relations":"Дитина","relations_other":"","inn_hidden":false,"family_name":"Гулкевич А. О","name_unclear":false}],"patronymic":"Васильович","inn_hidden":true,"family_raw":"","inn_unclear":false,"post":{"post_unclear":false,"post":"суддя стрийського міськрайонного суду львівської області","office_hidden":false,"region":"Львівська область","office":"Загальний місцевий суд","office_unclear":false,"region_hidden":false},"full_name":"Гулкевич Орест Васильович","addresses":[{"place_district":"","place_address_hidden":true,"place_city":"Стрий","place_city_type_hidden":false,"place_district_hidden":false,"place_city_type":"Місто","place_city_hidden":false,"place_address_unclear":false,"place_address":"","place_hidden":false,"place":"Львівська область"}],"last_name":"Гулкевич","full_name_suggest":{"output":"Гулкевич Орест Васильович","input":["Гулкевич Орест Васильович","Орест Васильович Гулкевич","Орест Гулкевич"]}},"source":"VULYK","estate":{"25":[{"space_hidden":false,"costs":"","costs_comment":"","address_hidden":true,"region_hidden":false,"space_comment":"","space":"226.2","address":"м. Стрий","region":"Львівська область","address_unclear":false,"costs_rent_comment":"","space_comment_unclear":false,"space_units":"м²","costs_rent":""}],"28":[{"costs_rent":"","region":"Львівська область","costs":"","costs_rent_comment":"","costs_comment":"","address_hidden":true,"region_hidden":false,"space_comment":"1/4 частина","space_units":"м²","space":"52.2","address":"м. Ходорів"}],"29":[{"space_unclear":false,"space_units_unclear":false,"address_hidden":true,"region_hidden":false,"space_comment":"","space_units_hidden":false,"space":"100","address":"Стрийський р-н","region":"Львівська область","costs_property":"","costs_rent_comment":"","space_units":"м²","costs_property_comment":"","costs_rent":""},{"address_hidden":false,"region_hidden":false,"space_comment":"","space":"124","address":"Стрийський р-н","region":"Львівська область","costs_property":"","costs_rent_comment":"","address_unclear":false,"space_units":"м²","costs_property_comment":"","costs_rent":""}],"31":[{"space_unclear":false,"address_hidden":false,"region_hidden":false,"space_comment":"","space_hidden":false,"space":"31.1","address":"м. Стрий","region":"Львівська область","costs_property":"","costs_rent_comment":"","address_unclear":false,"space_units":"м²","costs_property_comment":"","costs_rent":""}]},"intro":{"declaration_year":"2014","isnotdeclaration":""}}