{"id":"vulyk_99_104","ft_src":"2013\nToyota Corolla\n1598 куб. см. 124 к. с\n1000\nм. Одеса\nОдеська область\n67.4\n2015\n213004.35\n213004.35\n1598 куб. см. 124 к. с\nToyota Corolla\n2013\n1000\n2015\nНикифорчук\nНикифорчук Микола Іванович\nМикола Іванович Никифорчук\nМикола Никифорчук\nНикифорчук Микола Іванович\nМикола\nІванович\nНикифорчук Микола Іванович\nГосподарський місцевий суд\nсуддя господарського суду одеської області\nОдеська область\n213004.35\n213004.35\n67.4\nм. Одеса\nОдеська область\nНикифорчук\nІванович\nсуддя господарського суду одеської області\nОдеська область\nГосподарський місцевий суд\nНикифорчук Микола Іванович\nНикифорчук Микола Іванович\nМикола Іванович Никифорчук\nМикола Никифорчук\nНикифорчук Микола Іванович\nМикола","estate":{"25":[{"address":"м. Одеса","space_units":"м²","space_hidden":false,"space_unclear":false,"region_hidden":false,"costs_comment":"","space_comment":"","address_hidden":true,"space":"67.4","costs_rent_comment":"","costs":"","region":"Одеська область","costs_rent":""}]},"vehicle":{"35":[{"sum_comment":"","brand_info":"1598 куб. см. 124 к. с","brand_unclear":false,"sum_rent_comment":"","year":"2013","brand":"Toyota Corolla","sum_rent":"1000","brand_info_unclear":false,"sum":""}]},"source":"VULYK","income":{"5":{"family_comment":"","family":"","comment":"","value_unclear":false,"family_unclear":false,"value":"213004.35"},"6":{"family_comment":"","family":"","comment":"","value_unclear":false,"family_unclear":false,"value":"213004.35"},"7":{"family":"","family_comment":"","value":"","comment":"","source_name":""},"8":{"family_comment":"","value":"","family":"","comment":""},"9":{"family_comment":"","value":"","family":"","comment":""},"10":{"family_comment":"","value":"","family":"","comment":""},"11":{"family_comment":"","value":"","family":"","comment":""},"12":{"family_comment":"","value":"","family":"","comment":""},"13":{"family_comment":"","value":"","family":"","comment":""},"14":{"family_comment":"","value":"","family":"","comment":""},"15":{"family_comment":"","value":"","family":"","comment":"","value_unclear":false},"16":{"family_comment":"","value":"","family":"","comment":""},"17":{"family_comment":"","value":"","family":"","comment":""},"18":{"family_comment":"","value":"","family":"","comment":""},"19":{"family_comment":"","value":"","family":"","comment":""},"20":{"family_comment":"","family":"","comment":"","value_unclear":false,"family_unclear":false,"value":"","family_comment_unclear":false}},"general":{"inn":"","addresses":[{"place_city_type_hidden":false,"place_city_type":"","place_city_hidden":true,"place_hidden":true,"place_district":"","place_district_hidden":false,"place":"","place_address":"","place_address_hidden":true,"place_city":""}],"last_name":"Никифорчук","full_name_suggest":{"input":["Никифорчук Микола Іванович","Микола Іванович Никифорчук","Микола Никифорчук"],"output":"Никифорчук Микола Іванович"},"full_name":"Никифорчук Микола Іванович","patronymic":"Іванович","inn_hidden":true,"name":"Микола","post":{"office":"Господарський місцевий суд","region":"Одеська область","post_unclear":false,"post":"суддя господарського суду одеської області"},"family_raw":""},"liabilities":{"54":{"sum_comment_unclear":false,"sum_comment":"","sum":"","sum_foreign_comment":"","sum_foreign":"","sum_comment_hidden":false},"55":{"sum_comment":"","sum_foreign_comment":"","sum_foreign":"","sum":""},"56":{"sum_comment":"","sum_foreign_comment":"","sum_foreign":"","sum":""},"57":{"sum_comment":"","sum_foreign_comment":"","sum_foreign":"","sum":"","sum_comment_hidden":false},"58":{"sum_comment":"","sum_foreign_comment":"","sum_foreign":"","sum":"","sum_comment_hidden":false},"59":{"sum_comment":"","sum":"","sum_foreign_comment":"","sum_foreign":"","sum_unclear":false,"sum_comment_hidden":false},"60":{"sum_comment":"","sum_foreign_comment":"","sum_foreign":"","sum":"","sum_comment_hidden":false},"61":{"sum_comment":"","sum_foreign_comment":"","sum_foreign":"","sum":""},"62":{"sum_comment":"","sum_foreign_comment":"","sum_foreign":"","sum":""},"63":{"sum_comment":"","sum_foreign_comment":"","sum_foreign":"","sum":"","sum_comment_hidden":false},"64":{"sum_comment":"","sum_foreign_comment":"","sum_foreign":"","sum":"","sum_comment_hidden":false}},"declaration":{"notfull_lostpages":"","date":"2016-03-30T00:00:00","notfull":"","url":"http://static.declarations.com.ua/declarations/chosen_ones/judges_batch/653_nykyforchuk_mykola_ivanovych_2015.pdf"},"intro":{"declaration_year":"2015"}}