{"income":{"5":{"value":"238261","family_comment":"","value_unclear":false,"family_unclear":false,"family":"71302","comment":""},"6":{"family_comment":"","family_unclear":false,"value":"237992","family":"","comment":""},"7":{"source_name_unclear":false,"value":"","family_comment":"","source_name":"","family":"","comment":""},"8":{"family_comment":"","value":"","family":"","comment":""},"9":{"value":"269","family_comment":"","comment_hidden":false,"family_unclear":false,"family":"","comment":"","family_comment_hidden":false},"10":{"family_comment":"","value":"","family":"","comment":""},"11":{"family_comment":"","value":"","family":"","comment":""},"12":{"family_comment":"","value":"","family":"","comment":""},"13":{"family_comment":"","value":"","family":"","comment":""},"14":{"family_comment":"","value":"","family":"","comment":""},"15":{"family_comment":"пенсійні виплати","value":"","family":"71302","comment":""},"16":{"family_comment":"","value":"","family":"","comment":""},"17":{"family_comment":"","value":"","family":"","comment":""},"18":{"family_comment":"","value":"","family":"","comment":""},"19":{"family_comment":"","value":"","family":"","comment":""},"20":{"value":"","value_unclear":false,"comment_hidden":false,"family_comment":"","comment_unclear":false,"comment":"","family":""}},"vehicle":{"40":[{"brand_info":"4000 куб. см.","sum_rent_comment":"","brand":"Toyota Prado","sum_comment":"","brand_unclear":false,"year":"2007","brand_info_unclear":false,"year_unclear":false,"sum":"","sum_rent":""}]},"id":"vulyk_108_120","declaration":{"additional_info_text":"","notfull_lostpages":"","date":"2016-03-30T00:00:00","notfull":"","additional_info":"","url":"http://static.declarations.com.ua/declarations/chosen_ones/judges_batch/2419_sviderska_tetiana_anatoliivna_2015.pdf"},"liabilities":{"54":{"sum_foreign_comment":"","sum":"","sum_hidden":false,"sum_comment":"","sum_foreign":""},"55":{"sum_foreign_comment":"","sum":"","sum_comment":"","sum_foreign":""},"56":{"sum_foreign_comment":"","sum":"","sum_comment":"","sum_unclear":false,"sum_foreign":""},"57":{"sum_foreign_comment":"","sum":"","sum_comment":"","sum_hidden":false,"sum_comment_hidden":false,"sum_foreign":""},"58":{"sum_foreign_comment":"","sum_comment_hidden":false,"sum":"","sum_comment":"","sum_foreign":""},"59":{"sum_foreign_comment":"","sum":"","sum_comment":"","sum_unclear":false,"sum_foreign":""},"60":{"sum_foreign_comment":"","sum_comment_hidden":false,"sum":"","sum_comment":"","sum_foreign":""},"61":{"sum_foreign_comment":"","sum_comment_hidden":false,"sum":"","sum_comment":"","sum_foreign":""},"62":{"sum_foreign_comment":"","sum":"","sum_comment":"","sum_foreign":""},"63":{"sum_foreign_comment":"","sum":"8071","sum_comment":"","sum_hidden":false,"sum_comment_hidden":false,"sum_unclear":false,"sum_foreign":""},"64":{"sum_foreign_comment":"","sum":"3149","sum_comment":"","sum_comment_hidden":false,"sum_unclear":false,"sum_foreign":""}},"ft_src":"3149\n8071\nсуддя апеляційного суду дніпропетровської області\nДніпропетровська область\nЗагальний апеляційний суд\nТетяна\nСвідерський Ю. П\nПодружжя\nАнатоліївна\nСвідерська Тетяна Анатоліївна\nТетяна Анатоліївна Свідерська\nТетяна Свідерська\nСвідерська Тетяна Анатоліївна\nСвідерська Тетяна Анатоліївна\nСвідерська\n4000 куб. см.\nToyota Prado\n2007\n30.15\n26.25\n30.15\n2015\n237992\n71302\nпенсійні виплати\n269\n71302\n238261\n4000 куб. см.\n2007\nToyota Prado\n2015\nСвідерська Тетяна Анатоліївна\nТетяна Анатоліївна Свідерська\nТетяна Свідерська\nСвідерська Тетяна Анатоліївна\nТетяна\nПодружжя\nСвідерський Ю. П\nСвідерська Тетяна Анатоліївна\nАнатоліївна\nЗагальний апеляційний суд\nДніпропетровська область\nсуддя апеляційного суду дніпропетровської області\nСвідерська\n3149\n8071\n237992\n71302\nпенсійні виплати\n238261\n71302\n269\n26.25\n30.15\n30.15\n3149\n8071\nПодружжя\nСвідерський Ю. П\nАнатоліївна\nСвідерська\nТетяна\nСвідерська Тетяна Анатоліївна\nТетяна Анатоліївна Свідерська\nТетяна Свідерська\nСвідерська Тетяна Анатоліївна\nДніпропетровська область\nсуддя апеляційного суду дніпропетровської області\nЗагальний апеляційний суд\nСвідерська Тетяна Анатоліївна\n2007\n4000 куб. см.\nToyota Prado\n71302\nпенсійні виплати\n269\n238261\n71302\n237992\n30.15\n30.15\n26.25\n2015","general":{"inn":"","name":"Тетяна","inn_unclear":false,"family":[{"inn":"","relations":"Подружжя","inn_unclear":false,"relations_hidden":false,"inn_hidden":false,"relations_other":"","name_hidden":false,"family_name":"Свідерський Ю. П","name_unclear":false}],"inn_hidden":true,"family_raw":"","last_name":"Свідерська","post":{"post_unclear":false,"post":"суддя апеляційного суду дніпропетровської області","office_hidden":false,"region":"Дніпропетровська область","office":"Загальний апеляційний суд","office_unclear":false},"full_name":"Свідерська Тетяна Анатоліївна","addresses":[{"place_city_type_hidden":false,"place_district_hidden":false,"place_city_type":"","place_city_hidden":false,"place_address_unclear":false,"place_address":"","place_hidden":true,"place":"","place_district":"","place_unclear":false,"place_city":"","place_address_hidden":false}],"patronymic":"Анатоліївна","full_name_suggest":{"output":"Свідерська Тетяна Анатоліївна","input":["Свідерська Тетяна Анатоліївна","Тетяна Анатоліївна Свідерська","Тетяна Свідерська"]}},"source":"VULYK","estate":{"25":[{"space_unclear":false,"costs":"","costs_comment":"","address_hidden":false,"region_hidden":true,"space_comment":"","space":"30.15","address":"","region":"","costs_rent_comment":"","space_comment_unclear":false,"space_units":"м²","space_units_unclear":false,"costs_rent":""}],"27":[{"space_unclear":false,"costs":"","costs_comment":"","address_hidden":false,"region_hidden":true,"space_comment":"","space":"26.25","address":"","region":"","costs_rent_comment":"","space_units":"м²","costs_rent":""}],"31":[{"space_hidden":false,"address_hidden":true,"region_hidden":true,"space_comment":"","space":"30.15","address":"","region":"","costs_property":"","costs_rent_comment":"","space_comment_unclear":false,"address_unclear":false,"space_units":"м²","costs_property_comment":"","costs_rent":""}]},"intro":{"declaration_year":"2015","isnotdeclaration":"","declaration_year_hidden":false}}