{"income":{"5":{"value":"233155","value_unclear":false,"value_hidden":false,"family_comment":"","family":"397043","comment":""},"6":{"value":"232252","family_comment":"","value_unclear":false,"family_unclear":false,"family":"","comment":""},"7":{"source_name_unclear":false,"value":"","family_hidden":false,"family_comment":"","source_name":"","family":"","comment":""},"8":{"family_comment":"","value":"","family":"","comment":""},"9":{"family_comment":"","value":"","family":"","comment":""},"10":{"family_comment":"","value":"","family":"","comment":""},"11":{"family_comment":"","value":"","family":"","comment":""},"12":{"family_comment":"","value":"","family":"","comment":""},"13":{"family_comment":"","value":"","family":"","comment":""},"14":{"family_comment":"","value":"","family":"","comment":""},"15":{"family_comment":"","value":"","family":"","comment":""},"16":{"family_comment":"","value":"","comment_unclear":false,"family":"","comment":""},"17":{"family_comment":"","family_unclear":false,"value":"","family":"397043","comment":""},"18":{"family_comment":"","value":"","family":"","comment":""},"19":{"value":"","family_hidden":false,"value_hidden":false,"family_comment":"","family":"","comment":""},"20":{"family_comment":"","value":"903","comment_unclear":false,"family":"","comment":""}},"vehicle":{"35":[{"brand_info":"1596 куб. см., 160 к. с","sum_rent_comment":"","year":"2011","sum_rent_unclear":false,"brand_info_hidden":false,"brand_info_unclear":false,"year_unclear":false,"sum_rent":"","sum":"","brand":"Ford Mondeo","sum_comment":"","sum_comment_unclear":false,"brand_hidden":false,"sum_unclear":false,"brand_unclear":false}]},"id":"vulyk_67_14","banks":{"51":[{"sum_foreign_comment":"","sum_units":"UAH","sum_comment":"","sum_comment_unclear":false,"sum_hidden":false,"sum_foreign_units":"UAH","sum_comment_hidden":false,"sum_unclear":false,"sum":"5","sum_foreign":""},{"sum_foreign_comment":"","sum_units":"OTHER","sum_comment":"","sum_foreign_units":"UAH","sum":"12163","sum_foreign":""}]},"declaration":{"additional_info_text":"","notfull_lostpages":"","date":"2015-03-24T00:00:00","notfull":"","additional_info":"","url":"http://static.declarations.com.ua/declarations/chosen_ones/mega_batch/radchenia_dmytro_ivanovych.pdf"},"liabilities":{"54":{"sum_foreign_comment":"","sum_foreign_hidden":false,"sum_comment":"","sum_comment_unclear":false,"sum_hidden":false,"sum":"","sum_unclear":false,"sum_foreign":""},"55":{"sum_foreign_comment":"","sum":"","sum_comment":"","sum_foreign":""},"56":{"sum_foreign_comment":"","sum_foreign_hidden":false,"sum_comment":"","sum_hidden":false,"sum":"","sum_unclear":false,"sum_foreign":""},"57":{"sum_foreign_comment":"","sum_foreign_hidden":false,"sum_comment":"","sum_comment_unclear":false,"sum_hidden":false,"sum_comment_hidden":false,"sum_unclear":false,"sum":"","sum_foreign":""},"58":{"sum_foreign_comment":"","sum_foreign_hidden":false,"sum_comment":"","sum_comment_unclear":false,"sum_hidden":false,"sum_comment_hidden":false,"sum_unclear":false,"sum":"","sum_foreign":""},"59":{"sum_foreign_comment":"","sum":"","sum_hidden":false,"sum_comment":"","sum_foreign":""},"60":{"sum_foreign_comment":"","sum":"","sum_comment":"","sum_foreign":""},"61":{"sum_foreign_comment":"","sum_foreign_hidden":false,"sum_comment":"","sum_hidden":false,"sum":"","sum_foreign":""},"62":{"sum_foreign_comment":"","sum":"","sum_hidden":false,"sum_comment":"","sum_foreign":""},"63":{"sum_foreign_comment":"","sum":"","sum_comment":"","sum_comment_unclear":false,"sum_hidden":false,"sum_unclear":false,"sum_foreign":""},"64":{"sum_foreign_comment":"","sum":"","sum_comment":"","sum_hidden":false,"sum_unclear":false,"sum_foreign":""}},"ft_src":"суддя господарського суду хмельницької області\nХмельницька область\nГосподарський місцевий суд\nДмитро\nРадченя О. М\nПодружжя\nРадченя В. Д\nДитина\nІванович\nРадченя Дмитро Іванович\nРадченя\nРадченя Дмитро Іванович\nДмитро Іванович Радченя\nДмитро Радченя\nРадченя Дмитро Іванович\n1596 куб. см., 160 к. с\nFord Mondeo\n2011\n5\n12163\nOTHER\n2014\n1596 куб. см., 160 к. с\nFord Mondeo\n2011\n5\nOTHER\n12163\n.1\n.0021\n112\nГосподарський місцевий суд\nсуддя господарського суду хмельницької області\nХмельницька область\nПодружжя\nРадченя О. М\nДитина\nРадченя В. Д\nРадченя Дмитро Іванович\nДмитро Іванович Радченя\nДмитро Радченя\nРадченя Дмитро Іванович\nРадченя Дмитро Іванович\nДмитро\nРадченя\nІванович\n232252\n397043\n903\n233155\n397043\n2014\n.1\n.0021\n112\nПодружжя\nРадченя О. М\nДитина\nРадченя В. Д\nІванович\nРадченя\nДмитро\nРадченя Дмитро Іванович\nДмитро Іванович Радченя\nДмитро Радченя\nРадченя Дмитро Іванович\nХмельницька область\nсуддя господарського суду хмельницької області\nГосподарський місцевий суд\nРадченя Дмитро Іванович\n232252\n397043\n233155\n397043\n903\n2011\nFord Mondeo\n1596 куб. см., 160 к. с\n903\n233155\n397043\n397043\n232252\n112\n.1\n.0021\n5\nOTHER\n12163\n2014","general":{"inn":"","name":"Дмитро","patronymic_unclear":false,"last_name_hidden":false,"family":[{"inn":"","inn_hidden":true,"relations_unclear":false,"relations_hidden":false,"relations_other":"","relations":"Подружжя","name_hidden":true,"inn_unclear":false,"family_name":"Радченя О. М","name_unclear":false},{"inn":"","inn_hidden":false,"relations_unclear":false,"relations_hidden":false,"relations_other":"","relations":"Дитина","name_hidden":false,"inn_unclear":false,"family_name":"Радченя В. Д","name_unclear":false}],"patronymic":"Іванович","inn_hidden":true,"family_raw":"","inn_unclear":false,"post":{"post_unclear":false,"post":"суддя господарського суду хмельницької області","post_hidden":false,"region":"Хмельницька область","region_hidden":false,"office":"Господарський місцевий суд","office_hidden":false,"office_unclear":false},"last_name_unclear":false,"full_name":"Радченя Дмитро Іванович","addresses":[{"place_city_type_hidden":true,"place_district_hidden":true,"place_city_type":"","place_city_hidden":true,"place_address_unclear":false,"place_address":"","place":"","place_district":"","place_unclear":false,"place_city":"","place_city_unclear":false,"place_hidden":true,"place_address_hidden":true,"place_district_unclear":false}],"last_name":"Радченя","full_name_suggest":{"output":"Радченя Дмитро Іванович","input":["Радченя Дмитро Іванович","Дмитро Іванович Радченя","Дмитро Радченя"]},"name_unclear":false},"source":"VULYK","estate":{"23":[{"space_hidden":false,"costs":"","costs_comment":"","costs_hidden":false,"address_hidden":true,"region_hidden":true,"space_comment":"","space_unclear":false,"space":".1","address":"","region":"","address_unclear":false,"space_units_unclear":false,"costs_rent_hidden":false,"space_comment_unclear":false,"space_units":"га","costs_rent":"","costs_rent_comment":""},{"space_unclear":false,"costs":"","costs_comment":"","address_hidden":false,"region_hidden":false,"space_comment":"","space":".0021","address":"","region":"","costs_rent_comment":"","space_comment_unclear":false,"space_units":"га","space_units_unclear":false,"costs_rent":""}],"25":[{"space_unclear":false,"costs":"","costs_comment":"","costs_hidden":false,"address_hidden":true,"region_hidden":true,"space_comment":"","space":"112","address":"","region":"","address_unclear":false,"space_units_unclear":false,"space_comment_unclear":false,"space_units":"м²","costs_rent":"","costs_rent_comment":""}]},"intro":{"declaration_year":"2014","isnotdeclaration":"","declaration_year_hidden":false}}