{"income":{"5":{"value":"254996","family_unclear":false,"family_hidden":false,"family_comment":"","family":"69816","comment":""},"6":{"value":"254996","family_comment":"","value_unclear":false,"family_hidden":false,"family_unclear":false,"family":"69816","comment":""},"7":{"value":"","family_hidden":false,"value_hidden":false,"family_comment":"","source_name":"","family":"","comment":"","source_name_hidden":false},"8":{"family_comment":"","value":"","family":"","comment":""},"9":{"family_comment":"","value":"","family":"","comment":""},"10":{"family_comment":"","value":"","value_unclear":false,"family":"","comment":""},"11":{"family_comment":"","value":"","family":"","comment":""},"12":{"family_comment":"","value":"","family":"","comment":""},"13":{"family_comment":"","value":"","family":"","comment":""},"14":{"family_comment":"","value":"","family":"","comment":""},"15":{"family_comment":"","value":"","family":"","comment":""},"16":{"family_comment":"","value":"","family":"","comment":""},"17":{"family_comment":"","value":"","family":"","comment":""},"18":{"family_comment":"","value":"","family":"","comment":""},"19":{"family_comment":"","value":"","family":"","comment":""},"20":{"value":"","family_comment":"","value_unclear":false,"family_unclear":false,"comment_unclear":false,"comment":"","family":""}},"vehicle":{"35":[{"brand_info":"1.6 л","sum_rent_comment":"","year":"2006","brand_info_hidden":false,"brand_info_unclear":false,"year_unclear":false,"sum_rent":"","sum":"","brand":"Skoda Octavia A5","sum_comment":"","brand_unclear":false,"brand_hidden":false}],"40":[{"brand_info":"1.6 л","sum_rent_comment":"","brand":"Chevrolet Aveo","sum_comment":"","brand_unclear":false,"year":"2009","brand_info_unclear":false,"year_unclear":false,"sum":"","sum_rent":""}]},"id":"vulyk_74_140","declaration":{"additional_info_text":"","notfull_lostpages":"","date":"2014-03-28T00:00:00","notfull":"","additional_info":"","url":"http://static.declarations.com.ua/declarations/chosen_ones/judges_batch/1553_mikulin_mykola_ivnovych.pdf"},"liabilities":{"54":{"sum_foreign_comment":"","sum":"","sum_comment":"","sum_comment_unclear":false,"sum_comment_hidden":false,"sum_foreign":""},"55":{"sum_foreign_comment":"","sum":"","sum_comment":"","sum_hidden":false,"sum_unclear":false,"sum_foreign":""},"56":{"sum_foreign_comment":"","sum":"","sum_comment":"","sum_hidden":false,"sum_unclear":false,"sum_foreign":""},"57":{"sum_foreign_comment":"","sum":"","sum_comment":"","sum_comment_unclear":false,"sum_comment_hidden":false,"sum_foreign":""},"58":{"sum_foreign_comment":"","sum_comment_hidden":false,"sum":"","sum_comment":"","sum_foreign":""},"59":{"sum_foreign_comment":"","sum":"","sum_comment":"","sum_foreign":""},"60":{"sum_foreign_comment":"","sum":"","sum_hidden":false,"sum_comment":"","sum_foreign":""},"61":{"sum_foreign_comment":"","sum":"","sum_comment":"","sum_foreign":""},"62":{"sum_foreign_comment":"","sum":"","sum_comment":"","sum_foreign":""},"63":{"sum_foreign_comment":"","sum":"","sum_comment":"","sum_comment_unclear":false,"sum_unclear":false,"sum_foreign":""},"64":{"sum_foreign_comment":"","sum":"","sum_comment":"","sum_comment_unclear":false,"sum_unclear":false,"sum_foreign":""}},"ft_src":"Мікулін Микола Іванович\nсуддя апеляційного суду харківської області\nХарківська область\nЗагальний апеляційний суд\nМикола\nМікуліна Н. Г., 1957 р. н\nПодружжя\nМікулін Микола Іванович\nМикола Іванович Мікулін\nМикола Мікулін\nМікулін Микола Іванович\nМікулін\nІванович\n1.6 л\nSkoda Octavia A5\n2006\nChevrolet Aveo\n1.6 л\n2009\n80\n20\n74\n70\n2013\n69816\n254996\n69816\n254996\n1.6 л\nSkoda Octavia A5\n2006\n1.6 л\nChevrolet Aveo\n2009\n2013\nЗагальний апеляційний суд\nХарківська область\nсуддя апеляційного суду харківської області\nІванович\nМікулін Микола Іванович\nМикола Іванович Мікулін\nМикола Мікулін\nМікулін Микола Іванович\nМикола\nМікулін Микола Іванович\nМікулін\nПодружжя\nМікуліна Н. Г., 1957 р. н\n69816\n254996\n254996\n69816\n74\n80\n20\n70\nПодружжя\nМікуліна Н. Г., 1957 р. н\nІванович\nМікулін\nХарківська область\nЗагальний апеляційний суд\nсуддя апеляційного суду харківської області\nМікулін Микола Іванович\nМікулін Микола Іванович\nМикола Іванович Мікулін\nМикола Мікулін\nМікулін Микола Іванович\nМикола\nSkoda Octavia A5\n1.6 л\n2006\n2009\n1.6 л\nChevrolet Aveo\n254996\n69816\n254996\n69816\n80\n70\n74\n20\n2013","general":{"inn":"","inn_hidden":true,"last_name":"Мікулін","post":{"region_unclear":false,"region":"Харківська область","post":"суддя апеляційного суду харківської області","office":"Загальний апеляційний суд","office_unclear":false,"post_hidden":false},"name":"Микола","full_name":"Мікулін Микола Іванович","family_raw":"","addresses":[{"place_district":"","place_city_hidden":true,"place_city":"","place_city_type_hidden":true,"place_district_hidden":true,"place_city_type":"","place_address_hidden":true,"place_address":"","place_hidden":true,"place":""}],"family":[{"inn":"","relations":"Подружжя","relations_other":"","inn_hidden":true,"family_name":"Мікуліна Н. Г., 1957 р. н","name_hidden":false,"name_unclear":false}],"full_name_suggest":{"output":"Мікулін Микола Іванович","input":["Мікулін Микола Іванович","Микола Іванович Мікулін","Микола Мікулін"]},"patronymic":"Іванович"},"source":"VULYK","estate":{"24":[{"region_unclear":false,"space_hidden":false,"costs":"","costs_comment":"","address_hidden":false,"region_hidden":true,"space_comment":"","space":"74","address":"","region":"","space_units_unclear":false,"space_units":"м²","costs_rent":"","costs_rent_comment":""}],"25":[{"space_hidden":false,"costs":"","costs_comment":"","address_hidden":false,"region_hidden":true,"space_comment":"","space_unclear":false,"space":"70","address":"","region":"","costs_rent_comment":"","space_units":"м²","costs_rent":""}],"27":[{"costs":"","costs_comment":"","address_hidden":false,"region_hidden":true,"space_comment":"","space":"20","address":"","region":"","address_unclear":false,"costs_rent_comment":"","space_units":"м²","costs_rent":""}],"31":[{"space_unclear":false,"address_hidden":false,"region_hidden":true,"space_comment":"","space":"80","address":"","region":"","costs_property":"","costs_rent_comment":"","address_unclear":false,"space_units":"м²","costs_property_comment":"","costs_rent":""}]},"intro":{"declaration_year":"2013","isnotdeclaration":"","declaration_year_unclear":false}}