{"income":{"5":{"value":"201032.52","value_unclear":false,"family_hidden":false,"family_comment":"","family":"310.32","comment":""},"6":{"family_comment":"","value":"192090.52","value_unclear":false,"family":"","comment":""},"7":{"source_name_unclear":false,"value":"4592.5","family_comment":"","source_name":"Національна школа суддів України","family":"","comment":"","source_name_hidden":false},"8":{"family_comment":"","value":"","family":"","comment":""},"9":{"family_comment":"","value":"4349.5","comment_unclear":false,"family":"","comment":""},"10":{"family_comment":"","value":"","family":"","comment":""},"11":{"family_comment":"","family_unclear":false,"value":"","family":"","comment":""},"12":{"family_comment":"","value":"","family":"","comment":""},"13":{"family_comment":"","value":"","family":"","comment":""},"14":{"family_comment":"","value":"","family":"","comment":""},"15":{"family_comment":"","value":"","family":"","comment":""},"16":{"family_comment":"","value":"","family":"","comment":""},"17":{"family_comment":"","value":"","family":"","comment":""},"18":{"family_comment":"","value":"","family":"","comment":""},"19":{"family_comment":"","value":"","family":"","comment":""},"20":{"value":"","value_unclear":false,"family_comment":"","comment_unclear":false,"comment":"","family":"310.32"}},"vehicle":{"35":[{"year_hidden":false,"brand_info":"1200 куб. см., 47 кВт , 397 см, користування за довіреністю","sum_rent_comment":"","year":"2004","brand_info_hidden":false,"brand_info_unclear":false,"year_unclear":false,"sum_rent":"","sum":"","brand":"Skoda Fabia","sum_comment":"","brand_unclear":false,"brand_hidden":false}],"40":[{"brand_info":"1200 куб. см., 47 кВт , 397 см, користування за довіреністю","sum":"","brand":"Skoda Fabia","sum_comment":"","brand_unclear":false,"year":"2004","brand_hidden":false,"brand_info_hidden":false,"brand_info_unclear":false,"sum_rent_comment":"","sum_rent":""}]},"id":"vulyk_94_76","banks":{"45":[{"sum_foreign_comment":"","sum_units":"UAH","sum_comment":"","sum_hidden":false,"sum_foreign_units":"UAH","sum_foreign":"","sum_units_unclear":false,"sum_comment_hidden":false,"sum_units_hidden":false,"sum":"48.54","sum_unclear":false}]},"declaration":{"additional_info_text":"","notfull_lostpages":"","date":"2015-03-31T00:00:00","notfull":"","additional_info":"","url":"http://static.declarations.com.ua/declarations/chosen_ones/judges_batch/3722_fartushok_taras_bohdanovych.pdf"},"liabilities":{"54":{"sum_foreign_comment":"","sum":"","sum_comment":"","sum_comment_unclear":false,"sum_comment_hidden":false,"sum_unclear":false,"sum_foreign":""},"55":{"sum_foreign_comment":"","sum":"","sum_comment":"","sum_foreign":""},"56":{"sum_foreign_comment":"","sum":"","sum_comment":"","sum_unclear":false,"sum_foreign":""},"57":{"sum_foreign_comment":"","sum":"","sum_comment":"","sum_hidden":false,"sum_unclear":false,"sum_foreign":""},"58":{"sum_foreign_comment":"","sum":"","sum_comment":"","sum_hidden":false,"sum_unclear":false,"sum_foreign":""},"59":{"sum_foreign_comment":"","sum":"","sum_comment":"","sum_foreign":""},"60":{"sum_foreign_comment":"","sum_comment":"","sum":"","sum_comment_hidden":false,"sum_foreign":""},"61":{"sum_foreign_comment":"","sum":"","sum_comment":"","sum_foreign":""},"62":{"sum_foreign_comment":"","sum":"","sum_foreign":"","sum_comment":"","sum_hidden":false},"63":{"sum_foreign_comment":"","sum_comment":"","sum":"","sum_comment_hidden":false,"sum_foreign":""},"64":{"sum_foreign_comment":"","sum":"","sum_comment":"","sum_unclear":false,"sum_foreign":""}},"ft_src":"1200 куб. см., 47 кВт , 397 см, користування за довіреністю\nSkoda Fabia\n2004\nSkoda Fabia\n1200 куб. см., 47 кВт , 397 см, користування за довіреністю\n2004\n600\n65\n48.54\n2014\n1200 куб. см., 47 кВт , 397 см, користування за довіреністю\nSkoda Fabia\n2004\n1200 куб. см., 47 кВт , 397 см, користування за довіреністю\n2004\nSkoda Fabia\n2014\nПодружжя\nФартушок Я. С\nДитина\nФартушок В. Т\nДитина\nФартушок О. Т\nФартушок Тарас Богданович\nТарас Богданович Фартушок\nТарас Фартушок\nФартушок Тарас Богданович\nФартушок Тарас Богданович\nТарас\nБогданович\nГосподарський місцевий суд\nЛьвівська область\nсуддя господарського суду львівської області\nФартушок\n4592.5\nНаціональна школа суддів України\n192090.52\n310.32\n201032.52\n310.32\n4349.5\n600\n65\n48.54\n192090.52\nНаціональна школа суддів України\n4592.5\n310.32\n201032.52\n4349.5\n310.32\nФартушок Я. С\nПодружжя\nФартушок В. Т\nДитина\nФартушок О. Т\nДитина\nБогданович\nФартушок\nТарас\nФартушок Тарас Богданович\nТарас Богданович Фартушок\nТарас Фартушок\nФартушок Тарас Богданович\nЛьвівська область\nГосподарський місцевий суд\nсуддя господарського суду львівської області\nФартушок Тарас Богданович","general":{"inn":"","name":"Тарас","last_name":"Фартушок","family":[{"inn":"","inn_hidden":true,"relations_hidden":false,"family_name":"Фартушок Я. С","relations":"Подружжя","name_hidden":true,"name_unclear":false},{"inn":"","inn_hidden":true,"relations_unclear":false,"family_name":"Фартушок В. Т","relations_other":"","relations":"Дитина","name_hidden":false,"name_unclear":false},{"inn":"","inn_hidden":false,"relations_unclear":false,"family_name":"Фартушок О. Т","relations_other":"","relations":"Дитина","name_hidden":false,"name_unclear":false}],"inn_hidden":true,"family_raw":"","inn_unclear":false,"post":{"post_unclear":false,"region_unclear":false,"post":"суддя господарського суду львівської області","candidate":"","post_hidden":false,"region":"Львівська область","office":"Господарський місцевий суд","office_unclear":false},"full_name":"Фартушок Тарас Богданович","addresses":[{"place_district":"","place_address_hidden":true,"place_city":"","place_address":"","place_district_hidden":true,"place_city_type":"","place_city_hidden":true,"place_city_type_hidden":true,"place_hidden":true,"place":""}],"patronymic":"Богданович","patronymic_hidden":false,"full_name_suggest":{"output":"Фартушок Тарас Богданович","input":["Фартушок Тарас Богданович","Тарас Богданович Фартушок","Тарас Фартушок"]}},"source":"VULYK","estate":{"23":[{"region_unclear":false,"space_hidden":false,"costs":"","costs_comment":"","address_hidden":true,"region_hidden":true,"space_comment":"","space_unclear":false,"space":"600","address":"","region":"","address_unclear":false,"space_units_unclear":false,"costs_rent_hidden":false,"costs_rent_comment_hidden":false,"space_units":"м²","costs_rent":"","costs_rent_comment":""}],"24":[{"space_unclear":false,"costs":"","costs_comment":"","address_hidden":true,"region_hidden":true,"space_comment":"","space_hidden":false,"space":"65","address":"","region":"","costs_rent_comment":"","costs_rent_hidden":false,"costs_rent_comment_hidden":false,"space_units":"м²","costs_rent":""}]},"intro":{"declaration_year":"2014","isnotdeclaration":""}}