{"income":{"5":{"family_comment":"","value":"281434","family":"29865","comment":""},"6":{"family_comment":"","value":"254726","family":"29865","comment":""},"7":{"value":"367","comment_hidden":false,"family_comment":"","source_name":"Національна школв суддів України, м. Київ, вул. Липська, 16г","family":"","comment":"","source_name_hidden":false},"8":{"family_comment":"","value":"","family_hidden":false,"comment":"","family":""},"9":{"value":"41","family_comment":"","value_unclear":false,"family_unclear":false,"family":"","comment":""},"10":{"family_comment":"","value":"","family":"","comment":""},"11":{"family_comment":"","value":"26300","family":"","comment":""},"12":{"family_comment":"","value":"","family":"","comment":""},"13":{"family_comment":"","value":"","family":"","comment":""},"14":{"family_comment":"","value":"","family":"","comment":""},"15":{"family_comment":"","value":"","family":"","comment":""},"16":{"family_comment":"","value":"","family":"","comment":""},"17":{"family_comment":"","value":"","family":"","comment":""},"18":{"family_comment":"","value":"","family":"","comment":""},"19":{"family_comment":"","value":"","family":"","comment":""},"20":{"value":"","value_unclear":false,"family_hidden":false,"family_comment":"","family":"","comment":""}},"id":"vulyk_109_45","declaration":{"additional_info_text":"","notfull_lostpages":"","date":"2016-03-22T00:00:00","notfull":"","additional_info":"","url":"http://static.declarations.com.ua/declarations/chosen_ones/judges_batch/2502_kamsha_nina_mykolaivna_2015.pdf"},"liabilities":{"54":{"sum_foreign_comment":"","sum":"","sum_comment":"","sum_hidden":false,"sum_comment_hidden":false,"sum_unclear":false,"sum_foreign":""},"55":{"sum_foreign_comment":"","sum":"","sum_comment":"","sum_comment_unclear":false,"sum_foreign":""},"56":{"sum_foreign_comment":"","sum":"","sum_comment":"","sum_foreign":""},"57":{"sum_foreign_comment":"","sum_comment_hidden":false,"sum":"","sum_comment":"","sum_foreign":""},"58":{"sum_foreign_comment":"","sum_comment_hidden":false,"sum":"","sum_comment":"","sum_foreign":""},"59":{"sum_foreign_comment":"","sum":"","sum_comment":"","sum_foreign":""},"60":{"sum_foreign_comment":"","sum":"","sum_comment":"","sum_foreign":""},"61":{"sum_foreign_comment":"","sum":"","sum_comment":"","sum_foreign":""},"62":{"sum_foreign_comment":"","sum":"","sum_comment":"","sum_foreign":""},"63":{"sum_foreign_comment":"","sum":"","sum_comment":"","sum_foreign":""},"64":{"sum_foreign_comment":"","sum":"","sum_comment":"","sum_foreign":""}},"ft_src":"суддя, заступник голови господарського суду дніпропетровської області\nДніпропетровська область\nГосподарський місцевий суд\nНіна\nКамша В. В\nПодружжя\nМиколаївна\nКамша Ніна Миколаївна\nНіна Миколаївна Камша\nНіна Камша\nКамша Ніна Миколаївна\nКамша Ніна Миколаївна\nКамша\n26300\n29865\n281434\n367\nНаціональна школв суддів України, м. Київ, вул. Липська, 16г\n41\n29865\n254726\n2015\n29865\n254726\n26300\nНаціональна школв суддів України, м. Київ, вул. Липська, 16г\n367\n29865\n281434\n41\n367\nНаціональна школв суддів України, м. Київ, вул. Липська, 16г\n254726\n29865\n281434\n29865\n26300\n41\nКамша Ніна Миколаївна\nНіна Миколаївна Камша\nНіна Камша\nКамша Ніна Миколаївна\nНіна\nПодружжя\nКамша В. В\nКамша Ніна Миколаївна\nМиколаївна\nГосподарський місцевий суд\nДніпропетровська область\nсуддя, заступник голови господарського суду дніпропетровської області\nКамша\n2015\nПодружжя\nКамша В. В\nМиколаївна\nКамша\nНіна\nКамша Ніна Миколаївна\nНіна Миколаївна Камша\nНіна Камша\nКамша Ніна Миколаївна\nДніпропетровська область\nГосподарський місцевий суд\nсуддя, заступник голови господарського суду дніпропетровської області\nКамша Ніна Миколаївна\n2015","general":{"name_hidden":false,"name":"Ніна","inn":"","family":[{"inn":"","relations":"Подружжя","relations_hidden":false,"inn_hidden":true,"relations_other":"","name_hidden":true,"family_name":"Камша В. В","name_unclear":false}],"patronymic":"Миколаївна","inn_hidden":true,"family_raw":"","inn_unclear":false,"post":{"region_unclear":false,"region":"Дніпропетровська область","post":"суддя, заступник голови господарського суду дніпропетровської області","region_hidden":false,"office":"Господарський місцевий суд","office_hidden":false,"office_unclear":false},"full_name":"Камша Ніна Миколаївна","addresses":[{"place_district":"","place_city_hidden":true,"place_city":"","place_city_type_hidden":true,"place_district_hidden":true,"place_city_type":"","place_address_hidden":true,"place_address":"","place_hidden":true,"place":""}],"last_name":"Камша","full_name_suggest":{"output":"Камша Ніна Миколаївна","input":["Камша Ніна Миколаївна","Ніна Миколаївна Камша","Ніна Камша"]}},"source":"VULYK","estate":{"25":[{"space_unclear":false,"costs":"","costs_comment":"","address_hidden":true,"region_hidden":true,"space_comment":"","space_hidden":true,"space":"","address":"","region":"","costs_rent_comment":"","space_units":"м²","space_units_hidden":true,"costs_rent":""}],"31":[{"space_hidden":true,"costs_property_comment":"","address_hidden":true,"region_hidden":true,"space_comment":"","space":"","address":"","region":"","costs_property":"","costs_rent_comment":"","space_units":"м²","space_units_hidden":true,"costs_rent":""}]},"intro":{"declaration_year":"2015","isnotdeclaration":""}}