{"income":{"5":{"family_comment":"","family_unclear":false,"value":"228043.48","family":"","comment":""},"6":{"family_comment":"","family_unclear":false,"value":"228043.48","family":"","comment":""},"7":{"value":"","comment_hidden":false,"family_comment":"","source_name":"","family":"","comment":""},"8":{"family_comment":"","value":"","family":"","comment":""},"9":{"family_comment":"","value":"","family":"","comment":""},"10":{"family_comment":"","value":"","family":"","comment":""},"11":{"family_comment":"","value":"","value_unclear":false,"family":"","comment":""},"12":{"family_comment":"","value":"","family":"","comment":""},"13":{"family_comment":"","value":"","family":"","comment":""},"14":{"family_comment":"","value":"20796","family":"","comment":"дол. США"},"15":{"family_comment":"","value":"","value_unclear":false,"family":"","comment":""},"16":{"family_comment":"","family_unclear":false,"value":"","family":"","comment":""},"17":{"family_comment":"","value":"","family":"","comment":""},"18":{"family_comment":"","value":"","family":"","comment":"","family_hidden":false},"19":{"family_comment":"","value":"","family":"","comment":""},"20":{"value":"","comment_unclear":false,"comment_hidden":false,"family_comment":"","family":"","comment":"","family_comment_hidden":false}},"vehicle":{"35":[{"brand_info":"2354","sum_rent_comment":"","year":"2008","brand_info_hidden":false,"brand_info_unclear":true,"year_unclear":false,"sum_rent":"","sum":"","brand":"Honda CR-V","sum_comment":"","brand_unclear":false,"brand_hidden":false}]},"id":"vulyk_68_114","declaration":{"additional_info_text":"Згідно рішення КСУ №2-рп/2012р. від 20. 01. 2012р. члени сім'ї відмовились дати відомості","notfull_lostpages":"","date":"2015-03-27T00:00:00","notfull":"","additional_info":"1","url":"http://static.declarations.com.ua/declarations/chosen_ones/mega_batch/monych_oksana_vasylivna.pdf"},"liabilities":{"54":{"sum_foreign_comment":"","sum":"1000","sum_comment":"","sum_comment_unclear":false,"sum_hidden":false,"sum_comment_hidden":false,"sum_unclear":false,"sum_foreign":""},"55":{"sum_foreign_comment":"","sum":"","sum_foreign":"","sum_comment":"","sum_hidden":false},"56":{"sum_foreign_comment":"","sum":"","sum_comment":"","sum_foreign":"","sum_foreign_hidden":false,"sum_unclear":false},"57":{"sum_foreign_comment":"","sum":"","sum_comment":"","sum_comment_unclear":false,"sum_hidden":false,"sum_comment_hidden":false,"sum_unclear":false,"sum_foreign":""},"58":{"sum_foreign_comment":"","sum":"","sum_comment":"","sum_hidden":false,"sum_comment_hidden":false,"sum_unclear":false,"sum_foreign":""},"59":{"sum_foreign_comment":"","sum":"","sum_comment":"","sum_foreign":""},"60":{"sum_foreign_comment":"","sum":"","sum_comment":"","sum_comment_unclear":false,"sum_hidden":false,"sum_comment_hidden":false,"sum_unclear":false,"sum_foreign":""},"61":{"sum_foreign_comment":"","sum":"","sum_foreign":"","sum_comment":"","sum_hidden":false},"62":{"sum_foreign_comment":"","sum":"","sum_comment":"","sum_unclear":false,"sum_foreign":""},"63":{"sum_foreign_comment":"","sum":"","sum_comment":"","sum_hidden":false,"sum_comment_hidden":false,"sum_unclear":false,"sum_foreign":""},"64":{"sum_foreign_comment":"","sum":"","sum_comment":"","sum_hidden":false,"sum_comment_hidden":false,"sum_foreign":""}},"ft_src":"2354\nHonda CR-V\n2008\n500\n230\n1\nЗгідно рішення КСУ №2-рп/2012р. від 20. 01. 2012р. члени сім'ї відмовились дати відомості\n2014\n228043.48\nдол. США\n20796\n228043.48\n2354\nHonda CR-V\n2008\nЗгідно рішення КСУ №2-рп/2012р. від 20. 01. 2012р. члени сім'ї відмовились дати відомості\n1\n500\n230\nПодружжя\nКузнецов В. В. 20. 09. 197? р\nДитина\nКузнецов М. В. 27. 02. 200? р\nБатьки\nМонич В. М. 11. 12. 1941 р\nМонич Оксана Ласлівна\nОксана Ласлівна Монич\nОксана Монич\nМонич Оксана Ласлівна\nМонич Оксана Ласлівна\nОксана\nЛаслівна\nЗагальний місцевий суд\nЗакарпатська область\nсуддя ужгородського міськрайонного суду\nМонич\n1000\n228043.48\nдол. США\n20796\n228043.48\n2014\n1000\nПодружжя\nКузнецов В. В. 20. 09. 197? р\nКузнецов М. В. 27. 02. 200? р\nДитина\nМонич В. М. 11. 12. 1941 р\nБатьки\nЛаслівна\nМонич\nОксана\nМонич Оксана Ласлівна\nОксана Ласлівна Монич\nОксана Монич\nМонич Оксана Ласлівна\nЗакарпатська область\nЗагальний місцевий суд\nсуддя ужгородського міськрайонного суду\nМонич Оксана Ласлівна","general":{"inn":"","name":"Оксана","last_name":"Монич","family":[{"inn":"","inn_hidden":true,"relations_unclear":false,"relations_hidden":false,"relations_other":"","relations":"Подружжя","name_hidden":false,"inn_unclear":false,"family_name":"Кузнецов В. В. 20. 09. 197? р","name_unclear":false},{"inn":"","inn_hidden":true,"inn_unclear":false,"relations_hidden":false,"relations_other":"","relations":"Дитина","name_hidden":false,"family_name":"Кузнецов М. В. 27. 02. 200? р","name_unclear":false},{"inn":"","inn_hidden":true,"family_name":"Монич В. М. 11. 12. 1941 р","relations_other":"","relations":"Батьки","name_hidden":false,"name_unclear":false}],"inn_hidden":false,"family_raw":"","inn_unclear":false,"post":{"post_unclear":false,"region_unclear":false,"post":"суддя ужгородського міськрайонного суду","post_hidden":false,"region":"Закарпатська область","region_hidden":false,"office":"Загальний місцевий суд","office_hidden":false,"office_unclear":false},"full_name_suggest":{"output":"Монич Оксана Ласлівна","input":["Монич Оксана Ласлівна","Оксана Ласлівна Монич","Оксана Монич"]},"full_name":"Монич Оксана Ласлівна","addresses":[{"place_address":"","place_district_hidden":true,"place_city_type":"","place_city_hidden":true,"place_address_unclear":false,"place_city_type_hidden":true,"place_city":"","place":"","place_district":"","place_unclear":false,"place_hidden":true,"place_address_hidden":true}],"patronymic":"Ласлівна","last_name_unclear":false,"name_unclear":false},"source":"VULYK","estate":{"23":[{"costs":"","costs_comment":"","address_hidden":false,"region_hidden":true,"space_comment":"","space":"500","address":"","region":"","costs_rent_comment":"","space_comment_hidden":false,"space_units":"м²","costs_rent":""}],"30":[{"space_unclear":false,"address_hidden":true,"region_hidden":true,"space_comment":"","space_hidden":false,"space":"230","address":"","region":"","costs_property":"","costs_rent_comment":"","space_units":"м²","costs_property_comment":"","costs_rent":""}]},"intro":{"declaration_year":"2014","isnotdeclaration":""}}