{"income":{"5":{"family_comment":"","value":"289439.58","family":"","comment":""},"6":{"family_comment":"","value":"265229.27","family_hidden":false,"comment":"","family":""},"7":{"family_comment":"","value":"","source_name":"","family":"","comment":""},"8":{"family_comment":"","value":"","family":"","comment":""},"9":{"value":"","value_unclear":false,"family_hidden":false,"family_comment":"","family":"","comment":""},"10":{"value":"","family_comment":"","family_hidden":false,"value_hidden":false,"family_unclear":false,"family":"","comment":""},"11":{"family_comment":"","value":"","family":"","comment":""},"12":{"family_comment":"","value":"","family":"","comment":""},"13":{"family_comment":"","value":"","family":"","comment":""},"14":{"family_comment":"","value":"","family":"","comment":""},"15":{"family_comment":"","value":"","family":"","comment":""},"16":{"family_comment":"","value":"","family":"","comment":""},"17":{"family_comment":"","value":"","family":"","comment":""},"18":{"family_comment":"","value":"","family":"","comment":""},"19":{"family_comment":"","value":"","family":"","comment":""},"20":{"value":"24210.31","comment_unclear":false,"family_comment":"","family":"","comment":"пенсія за віком","family_comment_unclear":false}},"id":"vulyk_75_73","declaration":{"additional_info_text":"","notfull_lostpages":"","date":"2015-03-23T00:00:00","notfull":"","additional_info":"","url":"http://static.declarations.com.ua/declarations/chosen_ones/judges_batch/1862_sapun_olena_anatoliivna.pdf"},"liabilities":{"54":{"sum_foreign_comment":"","sum":"","sum_comment":"","sum_foreign":""},"55":{"sum_foreign_comment":"","sum":"","sum_comment":"","sum_foreign":""},"56":{"sum_foreign_comment":"","sum":"","sum_comment":"","sum_foreign":""},"57":{"sum_foreign_comment":"","sum":"","sum_comment":"","sum_foreign":""},"58":{"sum_foreign_comment":"","sum":"","sum_comment":"","sum_foreign":""},"59":{"sum_foreign_comment":"","sum":"","sum_comment":"","sum_comment_unclear":false,"sum_unclear":false,"sum_foreign":""},"60":{"sum_foreign_comment":"","sum":"","sum_comment":"","sum_foreign":""},"61":{"sum_foreign_comment":"","sum":"","sum_comment":"","sum_foreign":""},"62":{"sum_foreign_comment":"","sum":"","sum_comment":"","sum_unclear":false,"sum_foreign":""},"63":{"sum_foreign_comment":"","sum":"","sum_comment":"","sum_foreign":""},"64":{"sum_foreign_comment":"","sum":"","sum_comment":"","sum_foreign":""}},"ft_src":"Сапун Олена Анатоліївна\nсуддя апеляційного суду запорізької області\nЗапорізька область\nЗагальний апеляційний суд\nОлена\nТучинський С. В\nДитина\nСапун Олена Анатоліївна\nОлена Анатоліївна Сапун\nОлена Сапун\nСапун Олена Анатоліївна\nСапун\nАнатоліївна\n24210.31\nпенсія за віком\n289439.58\n265229.27\n80.19\n40.91\n2014\n265229.27\n289439.58\nпенсія за віком\n24210.31\n2014\nСапун\nАнатоліївна\nДитина\nТучинський С. В\nСапун Олена Анатоліївна\nОлена Анатоліївна Сапун\nОлена Сапун\nСапун Олена Анатоліївна\nОлена\nСапун Олена Анатоліївна\nЗагальний апеляційний суд\nсуддя апеляційного суду запорізької області\nЗапорізька область\n265229.27\n24210.31\nпенсія за віком\n289439.58\n80.19\n40.91\nТучинський С. В\nДитина\nСапун\nАнатоліївна\nсуддя апеляційного суду запорізької області\nЗапорізька область\nЗагальний апеляційний суд\nСапун Олена Анатоліївна\nСапун Олена Анатоліївна\nОлена Анатоліївна Сапун\nОлена Сапун\nСапун Олена Анатоліївна\nОлена\n80.19\n40.91\n2014","general":{"inn":"","inn_hidden":true,"last_name":"Сапун","post":{"office":"Загальний апеляційний суд","region":"Запорізька область","post":"суддя апеляційного суду запорізької області"},"name":"Олена","full_name":"Сапун Олена Анатоліївна","family_raw":"","addresses":[{"place_district":"","place_address_hidden":false,"place_city":"","place_city_type_hidden":false,"place_district_hidden":false,"place_city_type":"","place_city_hidden":true,"place_address":"","place_hidden":true,"place":""}],"family":[{"inn":"","inn_hidden":true,"relations_hidden":false,"family_name":"Тучинський С. В","relations_other":"","relations":"Дитина","name_hidden":false,"name_unclear":false}],"full_name_suggest":{"output":"Сапун Олена Анатоліївна","input":["Сапун Олена Анатоліївна","Олена Анатоліївна Сапун","Олена Сапун"]},"patronymic":"Анатоліївна"},"source":"VULYK","estate":{"25":[{"space_hidden":false,"costs":"","costs_comment":"","address_hidden":false,"region_hidden":true,"space_comment":"","space_unclear":false,"space":"80.19","address":"","region":"","costs_rent_comment":"","space_units":"м²","costs_rent":""},{"costs_rent":"","space_unclear":false,"region":"","costs":"","costs_rent_comment":"","costs_comment":"","region_hidden":false,"space_comment":"","space_units":"м²","space":"40.91","address":""}]},"intro":{"declaration_year":"2014","isnotdeclaration":""}}