{"income":{"5":{"value":"240127","family_comment":"","value_unclear":false,"comment_hidden":false,"family_hidden":false,"value_hidden":false,"family_unclear":false,"family_comment_hidden":false,"comment":"","family":"1540"},"6":{"value":"240127","family_comment":"","value_unclear":false,"family_hidden":false,"family_unclear":false,"family":"1540","comment":""},"7":{"source_name_unclear":false,"value":"","family_hidden":false,"family_comment":"","source_name":"","family":"","comment":"","source_name_hidden":false},"8":{"family_comment":"","value":"","family":"","comment":""},"9":{"value":"","value_unclear":false,"family_hidden":false,"family_comment":"","family":"","comment":""},"10":{"value":"","value_unclear":false,"family_hidden":false,"value_hidden":false,"family_comment":"","comment_unclear":false,"comment":"","family":""},"11":{"family_comment":"","value":"","family":"","comment":""},"12":{"family_comment":"","value":"","family":"","comment":""},"13":{"family_comment":"","value":"","family":"","comment":""},"14":{"family_comment":"","value":"","family":"","comment":""},"15":{"family_comment":"","value":"","family_hidden":false,"comment":"","family":""},"16":{"value":"","value_unclear":false,"family_hidden":false,"family_comment":"","family":"","comment":""},"17":{"family_comment":"","value":"","family_hidden":false,"comment":"","family":""},"18":{"family_comment":"","value":"","value_unclear":false,"family":"","comment":""},"19":{"family_comment":"","value":"","family":"","comment":""},"20":{"value":"","family_comment":"","value_unclear":false,"family_hidden":false,"family_unclear":false,"comment_unclear":false,"comment":"","family":""}},"id":"vulyk_72_125","declaration":{"additional_info_text":"","notfull_lostpages":"","date":"2015-03-25T00:00:00","notfull":"","additional_info":"","url":"http://static.declarations.com.ua/declarations/chosen_ones/epic_batch/steblina_andrii_viktorovych.pdf"},"liabilities":{"54":{"sum_foreign_comment":"","sum":"","sum_comment":"","sum_comment_hidden":false,"sum_unclear":false,"sum_foreign":""},"55":{"sum_foreign_comment":"","sum":"","sum_comment":"","sum_foreign":""},"56":{"sum_foreign_comment":"","sum":"15870","sum_hidden":false,"sum_comment":"","sum_foreign":""},"57":{"sum_foreign_comment":"","sum":"84220","sum_comment":"","sum_comment_unclear":false,"sum_hidden":false,"sum_comment_hidden":false,"sum_unclear":false,"sum_foreign":""},"58":{"sum_foreign_comment":"","sum":"34485","sum_comment":"","sum_comment_unclear":false,"sum_hidden":false,"sum_comment_hidden":false,"sum_unclear":false,"sum_foreign":""},"59":{"sum_foreign_comment":"","sum_foreign_hidden":false,"sum_comment":"","sum_foreign_unclear":false,"sum_comment_hidden":false,"sum":"","sum_foreign":""},"60":{"sum_foreign_comment":"","sum_foreign_hidden":false,"sum_comment":"","sum_hidden":false,"sum":"","sum_foreign":""},"61":{"sum_foreign_comment":"","sum_foreign_hidden":false,"sum_comment":"","sum_hidden":false,"sum":"","sum_foreign":""},"62":{"sum_foreign_comment":"","sum_foreign_hidden":false,"sum_comment":"","sum_hidden":false,"sum":"","sum_foreign":""},"63":{"sum_foreign_comment":"","sum_foreign_hidden":false,"sum_comment":"","sum_comment_unclear":false,"sum_hidden":false,"sum_comment_hidden":false,"sum_unclear":false,"sum":"","sum_foreign":""},"64":{"sum_foreign_comment":"","sum_foreign_hidden":false,"sum_comment":"","sum_hidden":false,"sum":"","sum_foreign":""}},"ft_src":"84220\n34485\n15870\nЧернігів\nЧернігівська область\nсуддя деснянського районного суду м. чернігова\nЧернігівська область\nЗагальний місцевий суд\nАндрій\nСтебліна О. О\nПодружжя\nВікторович\nСтебліна\nСтебліна Андрій Вікторович\nСтебліна Андрій Вікторович\nАндрій Вікторович Стебліна\nАндрій Стебліна\nСтебліна Андрій Вікторович\n240127\n1540\n240127\n1540\nУкраїна\n45.9\nУкраїна\n67.8\nУкраїна\n32.5\nУкраїна\n.1\n45.9\nУкраїна\n2014\n1540\n240127\n1540\n240127\n240127\n1540\n240127\n1540\nПодружжя\nСтебліна О. О\nСтебліна Андрій Вікторович\nАндрій Вікторович Стебліна\nАндрій Стебліна\nСтебліна Андрій Вікторович\nАндрій\nСтебліна Андрій Вікторович\nСтебліна\nЧернігівська область\nЗагальний місцевий суд\nсуддя деснянського районного суду м. чернігова\nВікторович\nЧернігів\nЧернігівська область\n34485\n84220\n15870\nУкраїна\n.1\nУкраїна\n45.9\n67.8\nУкраїна\n32.5\nУкраїна\nУкраїна\n45.9\n2014\n34485\n84220\n15870\nСтебліна О. О\nПодружжя\nВікторович\nСтебліна\nСтебліна Андрій Вікторович\nАндрій Вікторович Стебліна\nАндрій Стебліна\nСтебліна Андрій Вікторович\nЧернігівська область\nЧернігів\nЧернігівська область\nЗагальний місцевий суд\nсуддя деснянського районного суду м. чернігова\nСтебліна Андрій Вікторович\nАндрій\nУкраїна\n45.9\nУкраїна\n67.8\nУкраїна\n32.5\n45.9\nУкраїна\nУкраїна\n.1\n2014","general":{"inn":"","name":"Андрій","patronymic_unclear":false,"family":[{"inn":"","inn_hidden":false,"relations_unclear":false,"relations_hidden":false,"relations_other":"","relations":"Подружжя","name_hidden":false,"inn_unclear":false,"family_name":"Стебліна О. О","name_unclear":false}],"patronymic":"Вікторович","inn_hidden":true,"family_raw":"","inn_unclear":false,"post":{"post_unclear":false,"region_unclear":false,"post":"суддя деснянського районного суду м. чернігова","candidate":"","office_hidden":false,"region":"Чернігівська область","post_hidden":false,"office":"Загальний місцевий суд","office_unclear":false,"region_hidden":false},"last_name_unclear":false,"full_name":"Стебліна Андрій Вікторович","addresses":[{"place_city_type_hidden":false,"place_district_hidden":false,"place_city_type":"Місто","place_city_hidden":false,"place_address_unclear":false,"place_address":"","place":"Чернігівська область","place_district":"","place_unclear":false,"place_city":"Чернігів","place_city_unclear":false,"place_hidden":false,"place_address_hidden":false,"place_district_unclear":false}],"last_name":"Стебліна","patronymic_hidden":false,"full_name_suggest":{"output":"Стебліна Андрій Вікторович","input":["Стебліна Андрій Вікторович","Андрій Вікторович Стебліна","Андрій Стебліна"]},"name_unclear":false},"source":"VULYK","estate":{"25":[{"space_unclear":false,"costs":"","costs_rent_unclear":false,"costs_comment":"","costs_hidden":false,"space_hidden":false,"costs_comment_unclear":false,"costs_rent_comment_unclear":false,"region":"","space_comment_hidden":false,"space_comment_unclear":false,"costs_rent_comment_hidden":false,"costs_rent":"","costs_comment_hidden":false,"address_hidden":false,"region_hidden":true,"space_comment":"","space":"45.9","address":"Україна","address_unclear":false,"costs_rent_comment":"","costs_rent_hidden":false,"space_units":"м²"}],"29":[{"space_hidden":false,"costs_property_comment":"","address_hidden":false,"region_hidden":true,"space_comment":"","space_unclear":false,"space":".1","address":"Україна","region":"","costs_property":"","costs_rent_comment":"","address_unclear":false,"space_units":"га","space_units_unclear":false,"costs_rent":""}],"31":[{"space_unclear":false,"address_hidden":false,"region_hidden":true,"space_comment":"","space_units_hidden":false,"space_hidden":false,"space":"45.9","address":"Україна","region":"","address_unclear":false,"costs_rent_comment":"","costs_property":"","space_units":"м²","costs_property_comment":"","costs_rent":""},{"costs_rent":"","region":"","costs_property":"","costs_rent_comment":"","address_hidden":false,"region_hidden":false,"space_comment":"","costs_property_comment":"","space_units":"м²","space":"67.8","address":"Україна"},{"costs_rent":"","costs_property":"","costs_rent_comment":"","address_hidden":false,"region_hidden":false,"space_comment":"","costs_property_comment":"","space_units":"м²","space":"32.5","address":"Україна"}]},"intro":{"declaration_year":"2014","isnotdeclaration":"","declaration_year_unclear":false}}