{"income":{"5":{"value":"241745","family_comment":"","value_unclear":false,"value_hidden":false,"family_unclear":false,"family":"","comment":""},"6":{"value":"240265","family_hidden":false,"value_hidden":false,"family_comment":"","family_comment_hidden":false,"comment":"","family":""},"7":{"value":"1480","value_unclear":false,"family_hidden":false,"value_hidden":false,"family_comment":"","source_name":"Регіональне відділення Національної школи суддів України","family":"","comment":"","source_name_hidden":false},"8":{"value":"","comment_hidden":false,"family_hidden":false,"value_hidden":false,"family_comment":"","family":"","comment":""},"9":{"value":"","family_comment":"","comment_hidden":false,"family_hidden":false,"value_hidden":false,"family_unclear":false,"family":"","comment":""},"10":{"value":"","comment_hidden":false,"family_hidden":false,"value_hidden":false,"family_comment":"","family":"","comment":""},"11":{"value":"","value_unclear":false,"comment_hidden":false,"family_hidden":false,"value_hidden":false,"family_comment":"","family":"","comment":""},"12":{"value":"","comment_hidden":false,"family_hidden":false,"value_hidden":false,"family_comment":"","family":"","comment":""},"13":{"value":"","comment_hidden":false,"family_hidden":false,"value_hidden":false,"family_comment":"","family":"","comment":""},"14":{"value":"","comment_hidden":false,"family_hidden":false,"value_hidden":false,"family_comment":"","family":"","comment":""},"15":{"value":"","comment_hidden":false,"family_hidden":false,"value_hidden":false,"family_comment":"","family":"","comment":""},"16":{"value":"","comment_hidden":false,"family_hidden":false,"value_hidden":false,"family_comment":"","family":"","comment":""},"17":{"value":"","comment_hidden":false,"family_hidden":false,"value_hidden":false,"family_comment":"","family":"","comment":""},"18":{"value":"","value_unclear":false,"comment_hidden":false,"family_hidden":false,"value_hidden":false,"family_comment":"","family":"","comment":""},"19":{"value":"","comment_hidden":false,"family_hidden":false,"value_hidden":false,"family_comment":"","family":"","comment":""},"20":{"value":"","value_unclear":false,"family_comment":"","comment_unclear":false,"comment":"","family":""}},"id":"vulyk_76_193","declaration":{"additional_info_text":"","notfull_lostpages":"","date":"2014-12-19T00:00:00","notfull":"","additional_info":"","url":"http://static.declarations.com.ua/declarations/chosen_ones/judges_batch/394_kovalenko_nina_vasylivna.pdf"},"liabilities":{"54":{"sum_foreign_comment":"","sum_foreign_hidden":false,"sum_comment":"","sum_hidden":false,"sum_comment_hidden":false,"sum":"","sum_foreign":""},"55":{"sum_foreign_comment":"","sum":"","sum_hidden":false,"sum_comment":"","sum_foreign":""},"56":{"sum_foreign_comment":"","sum":"","sum_comment":"","sum_foreign":""},"57":{"sum_foreign_comment":"","sum_foreign_hidden":true,"sum_comment":"","sum_hidden":false,"sum_comment_hidden":false,"sum_unclear":false,"sum":"62958","sum_foreign":""},"58":{"sum_foreign_comment":"","sum_foreign_hidden":true,"sum_comment":"","sum_hidden":false,"sum_comment_hidden":false,"sum_unclear":false,"sum":"1624","sum_foreign":""},"59":{"sum_foreign_comment":"","sum":"","sum_hidden":false,"sum_comment":"","sum_foreign":""},"60":{"sum_foreign_comment":"","sum_foreign_hidden":false,"sum_comment":"","sum_hidden":false,"sum_comment_hidden":false,"sum_unclear":false,"sum":"","sum_foreign":""},"61":{"sum_foreign_comment":"","sum":"","sum_hidden":false,"sum_comment":"","sum_foreign":""},"62":{"sum_foreign_comment":"","sum":"","sum_comment":"","sum_hidden":false,"sum_comment_hidden":false,"sum_foreign":""},"63":{"sum_foreign_comment":"","sum":"","sum_hidden":false,"sum_comment":"","sum_foreign":""},"64":{"sum_foreign_comment":"","sum":"","sum_hidden":false,"sum_comment":"","sum_foreign":""}},"ft_src":"62958\n1624\nсуддя апеляційного суду дніпропетровськоі області\nДніпропетровська область\nЗагальний апеляційний суд\nНіна\nВасилівна\nКоваленко\nКоваленко Ніна Василівна\nКоваленко Ніна Василівна\nНіна Василівна Коваленко\nНіна Коваленко\nКоваленко Ніна Василівна\n241745\n1480\nРегіональне відділення Національної школи суддів України\n240265\n52.3\n2013\n240265\nРегіональне відділення Національної школи суддів України\n1480\n241745\n1480\nРегіональне відділення Національної школи суддів України\n240265\n241745\nКоваленко Ніна Василівна\nНіна Василівна Коваленко\nНіна Коваленко\nКоваленко Ніна Василівна\nКоваленко Ніна Василівна\nНіна\nВасилівна\nЗагальний апеляційний суд\nсуддя апеляційного суду дніпропетровськоі області\nДніпропетровська область\nКоваленко\n1624\n62958\n52.3\n2013\n1624\n62958\nВасилівна\nКоваленко\nНіна\nКоваленко Ніна Василівна\nНіна Василівна Коваленко\nНіна Коваленко\nКоваленко Ніна Василівна\nДніпропетровська область\nсуддя апеляційного суду дніпропетровськоі області\nЗагальний апеляційний суд\nКоваленко Ніна Василівна\n52.3\n2013","general":{"inn":"","name":"Ніна","inn_unclear":false,"patronymic":"Василівна","inn_hidden":true,"family_raw":"","last_name":"Коваленко","post":{"post_unclear":false,"post":"суддя апеляційного суду дніпропетровськоі області","candidate":"","office_hidden":false,"region":"Дніпропетровська область","office":"Загальний апеляційний суд","office_unclear":false,"region_hidden":false},"last_name_unclear":true,"full_name":"Коваленко Ніна Василівна","addresses":[{"place_city_type_unclear":false,"place_address":"","place_district_hidden":true,"place_city_type":"","place_city_hidden":true,"place_city_type_hidden":true,"place":"","place_district":"","place_unclear":false,"place_city":"","place_city_unclear":false,"place_hidden":true,"place_address_hidden":true}],"full_name_suggest":{"output":"Коваленко Ніна Василівна","input":["Коваленко Ніна Василівна","Ніна Василівна Коваленко","Ніна Коваленко"]},"name_unclear":false},"source":"VULYK","estate":{"25":[{"space_unclear":false,"costs":"","costs_comment":"","address_hidden":true,"region_hidden":true,"space_comment":"","space_hidden":false,"space":"52.3","address":"","region":"","costs_rent_comment":"","space_comment_unclear":false,"space_comment_hidden":false,"space_units":"м²","costs_rent":""}]},"intro":{"declaration_year":"2013","isnotdeclaration":"","declaration_year_unclear":false,"declaration_year_hidden":false}}