{"id":"vulyk_99_10","ft_src":"1/4\n61.5\n2015\n82524\n168971\n101751\n168971\n19227\n168971\n82524\n19227\n168971\n101751\nФорощук\nФорощук Олександр Віталійович\nОлександр Віталійович Форощук\nОлександр Форощук\nФорощук Олександр Віталійович\nОлександр\nВіталійович\nФорощук Олександр Віталійович\nЗагальний місцевий суд\nсуддя старобільського районного суду луганської області\nЛуганська область\nПодружжя\nФорощук С. А\nІнше\nПасинок\nТимохін С. А\n61.5\n1/4\n2015\nФорощук С. А\nПодружжя\nПасинок\nТимохін С. А\nІнше\nВіталійович\nФорощук\nсуддя старобільського районного суду луганської області\nЛуганська область\nЗагальний місцевий суд\nФорощук Олександр Віталійович\nФорощук Олександр Віталійович\nОлександр Віталійович Форощук\nОлександр Форощук\nФорощук Олександр Віталійович\nОлександр","estate":{"31":[{"costs_property_comment":"","address":"","space_units":"м²","costs_rent_comment":"","space":"61.5","region":"","region_hidden":true,"costs_property":"","space_comment":"1/4","address_hidden":false,"costs_rent":""}]},"source":"VULYK","income":{"5":{"family_comment":"","family":"101751","comment":"","value_unclear":false,"family_unclear":true,"value":"168971"},"6":{"family_comment":"","family":"82524","comment":"","value_unclear":false,"family_unclear":true,"value":"168971"},"7":{"family":"","family_comment":"","value":"","comment":"","source_name":""},"8":{"family_comment":"","value":"","family":"","comment":""},"9":{"family_comment":"","value":"","family":"","comment":""},"10":{"family_comment":"","value":"","family":"","comment":""},"11":{"family_comment":"","value":"","family":"","comment":""},"12":{"family_comment":"","value":"","family":"","comment":""},"13":{"family_comment":"","value":"","family":"","comment":""},"14":{"family_comment":"","value":"","family":"","comment":""},"15":{"family_comment":"","value":"","family":"","comment":"","value_unclear":false},"16":{"family_comment":"","value":"","family":"","comment":""},"17":{"family_comment":"","value":"","family":"","comment":""},"18":{"family_comment":"","value":"","family":"","comment":""},"19":{"family_comment":"","value":"","family":"","comment":""},"20":{"family_comment":"","family":"19227","comment":"","value_unclear":false,"family_unclear":false,"value":"","family_comment_unclear":false}},"general":{"inn":"","addresses":[{"place_city_type_hidden":false,"place_city_type":"","place_city_hidden":true,"place_hidden":true,"place_district":"","place_district_hidden":false,"place":"","place_address":"","place_address_hidden":true,"place_city":""}],"last_name":"Форощук","full_name":"Форощук Олександр Віталійович","family":[{"inn":"","family_name":"Форощук С. А","name_unclear":false,"inn_hidden":true,"name_hidden":true,"relations":"Подружжя"},{"inn":"","family_name":"Тимохін С. А","relations_other":"Пасинок","name_unclear":false,"inn_hidden":true,"relations":"Інше"}],"patronymic":"Віталійович","inn_hidden":true,"name":"Олександр","post":{"office":"Загальний місцевий суд","region":"Луганська область","post_unclear":false,"post":"суддя старобільського районного суду луганської області"},"family_raw":"","full_name_suggest":{"input":["Форощук Олександр Віталійович","Олександр Віталійович Форощук","Олександр Форощук"],"output":"Форощук Олександр Віталійович"}},"liabilities":{"54":{"sum_comment_unclear":false,"sum_comment":"","sum":"","sum_foreign_comment":"","sum_foreign":"","sum_comment_hidden":false},"55":{"sum_comment":"","sum_foreign_comment":"","sum_foreign":"","sum":""},"56":{"sum_comment":"","sum_foreign_comment":"","sum_foreign":"","sum":""},"57":{"sum_comment":"","sum_foreign_comment":"","sum_foreign":"","sum":"","sum_comment_hidden":false},"58":{"sum_comment":"","sum_foreign_comment":"","sum_foreign":"","sum":"","sum_comment_hidden":false},"59":{"sum_comment":"","sum":"","sum_foreign_comment":"","sum_foreign":"","sum_unclear":false,"sum_comment_hidden":false},"60":{"sum_comment":"","sum_foreign_comment":"","sum_foreign":"","sum":"","sum_comment_hidden":false},"61":{"sum_comment":"","sum_foreign_comment":"","sum_foreign":"","sum":""},"62":{"sum_comment":"","sum_foreign_comment":"","sum_foreign":"","sum":""},"63":{"sum_comment":"","sum_foreign_comment":"","sum_foreign":"","sum":"","sum_comment_hidden":false},"64":{"sum_comment":"","sum_foreign_comment":"","sum_foreign":"","sum":"","sum_comment_hidden":false}},"declaration":{"notfull_lostpages":"","date":"2016-03-30T00:00:00","notfull":"","url":"http://static.declarations.com.ua/declarations/chosen_ones/judges_batch/559_foroshchuk_oleksandr_vitaliiovych_2015.pdf"},"intro":{"declaration_year":"2015"}}