{"income":{"5":{"value":"234188","family_comment":"","value_unclear":false,"comment_hidden":false,"family_hidden":false,"value_hidden":false,"family_unclear":false,"family_comment_hidden":false,"comment":"","family":""},"6":{"value":"234188","family_comment":"","value_unclear":false,"family_hidden":false,"family_unclear":false,"family":"","comment":""},"7":{"source_name_unclear":false,"value":"","family_hidden":false,"family_comment":"","source_name":"","family":"","comment":"","source_name_hidden":false},"8":{"family_comment":"","value":"","family":"","comment":""},"9":{"value":"","value_unclear":false,"family_hidden":false,"family_comment":"","family":"","comment":""},"10":{"value":"","value_unclear":false,"family_hidden":false,"value_hidden":false,"family_comment":"","comment_unclear":false,"comment":"","family":""},"11":{"family_comment":"","value":"","family":"","comment":""},"12":{"family_comment":"","value":"","family":"","comment":""},"13":{"family_comment":"","value":"","family":"","comment":""},"14":{"family_comment":"","value":"","family":"","comment":""},"15":{"family_comment":"","value":"","family_hidden":false,"comment":"","family":""},"16":{"value":"","value_unclear":false,"family_hidden":false,"family_comment":"","family":"60000","comment":""},"17":{"family_comment":"","value":"","family_hidden":false,"comment":"","family":""},"18":{"family_comment":"","value":"","value_unclear":false,"family":"","comment":""},"19":{"family_comment":"","value":"","family":"","comment":""},"20":{"value":"","family_comment":"","value_unclear":false,"family_hidden":false,"family_unclear":false,"comment_unclear":false,"comment":"","family":""}},"vehicle":{"35":[{"brand_info":"1593 куб. см.","sum_rent_comment":"","brand_info_unclear":false,"year":"2007","sum_rent_unclear":false,"brand_info_hidden":false,"sum_rent_comment_unclear":false,"sum_hidden":false,"sum_rent":"","sum":"","brand":"Mazda 3","sum_comment":"","brand_unclear":false,"brand_hidden":false}]},"id":"vulyk_72_142","declaration":{"additional_info_text":"","notfull_lostpages":"","date":"2015-03-27T00:00:00","notfull":"","additional_info":"","url":"http://static.declarations.com.ua/declarations/chosen_ones/epic_batch/antonova_nataliia_volodymyrivna.pdf"},"liabilities":{"54":{"sum_foreign_comment":"","sum":"","sum_comment":"","sum_comment_hidden":false,"sum_unclear":false,"sum_foreign":""},"55":{"sum_foreign_comment":"","sum":"","sum_comment":"","sum_foreign":""},"56":{"sum_foreign_comment":"","sum":"","sum_hidden":false,"sum_comment":"","sum_foreign":""},"57":{"sum_foreign_comment":"","sum":"","sum_comment":"","sum_comment_unclear":false,"sum_hidden":false,"sum_comment_hidden":false,"sum_unclear":false,"sum_foreign":""},"58":{"sum_foreign_comment":"","sum":"","sum_comment":"","sum_comment_unclear":false,"sum_hidden":false,"sum_comment_hidden":false,"sum_unclear":false,"sum_foreign":""},"59":{"sum_foreign_comment":"","sum_foreign_hidden":false,"sum_comment":"","sum_foreign_unclear":false,"sum_comment_hidden":false,"sum":"","sum_foreign":""},"60":{"sum_foreign_comment":"","sum_foreign_hidden":false,"sum_comment":"","sum_hidden":false,"sum":"780","sum_foreign":""},"61":{"sum_foreign_comment":"","sum_foreign_hidden":false,"sum_comment":"","sum_hidden":false,"sum":"","sum_foreign":""},"62":{"sum_foreign_comment":"","sum_foreign_hidden":false,"sum_comment":"","sum_hidden":false,"sum":"10880","sum_foreign":""},"63":{"sum_foreign_comment":"","sum_foreign_hidden":false,"sum_comment":"","sum_comment_unclear":false,"sum_hidden":false,"sum_comment_hidden":false,"sum_unclear":false,"sum":"1713","sum_foreign":""},"64":{"sum_foreign_comment":"","sum_foreign_hidden":false,"sum_comment":"","sum_hidden":false,"sum":"5942","sum_foreign":""}},"ft_src":"10880\n1713\n780\n5942\nКиїв\n3022\nм. Київ\nсуддя голосіївського районного суду міста києва\nм. Київ\nЗагальний місцевий суд\nНаталія\nАнтонов О. В\nПодружжя\nАнтонов А. О\nДитина\nАнтонова Є. О\nДитина\nВолодимирівна\nАнтонова\nАнтонова Наталія Володимирівна\nАнтонова Наталія Володимирівна\nНаталія Володимирівна Антонова\nНаталія Антонова\nАнтонова Наталія Володимирівна\n1593 куб. см.\nMazda 3\n2007\nм. Київ\nм. Київ, вул. Ломоносова\n93.6\n2014\n234188\n234188\n60000\n1593 куб. см.\nMazda 3\n2007\nм. Київ\nм. Київ, вул. Ломоносова\n93.6\nПодружжя\nАнтонов О. В\nДитина\nАнтонов А. О\nДитина\nАнтонова Є. О\nАнтонова Наталія Володимирівна\nНаталія Володимирівна Антонова\nНаталія Антонова\nАнтонова Наталія Володимирівна\nНаталія\nАнтонова Наталія Володимирівна\nАнтонова\nм. Київ\nЗагальний місцевий суд\nсуддя голосіївського районного суду міста києва\nВолодимирівна\nКиїв\n3022\nм. Київ\n780\n10880\n1713\n5942\n234188\n234188\n60000\n2014\n10880\n780\n1713\n5942\nАнтонов О. В\nПодружжя\nАнтонов А. О\nДитина\nАнтонова Є. О\nДитина\nВолодимирівна\nАнтонова\nАнтонова Наталія Володимирівна\nНаталія Володимирівна Антонова\nНаталія Антонова\nАнтонова Наталія Володимирівна\nм. Київ\nКиїв\n3022\nм. Київ\nЗагальний місцевий суд\nсуддя голосіївського районного суду міста києва\nАнтонова Наталія Володимирівна\nНаталія\n2007\nMazda 3\n1593 куб. см.\n234188\n60000\n234188\nм. Київ\nм. Київ, вул. Ломоносова\n93.6\n2014","general":{"inn":"","name":"Наталія","patronymic_unclear":false,"family":[{"inn":"","inn_hidden":false,"relations_unclear":false,"relations_hidden":false,"relations_other":"","relations":"Подружжя","name_hidden":false,"inn_unclear":false,"family_name":"Антонов О. В","name_unclear":false},{"inn":"","inn_hidden":false,"relations_hidden":false,"family_name":"Антонов А. О","relations_other":"","relations":"Дитина","name_hidden":false,"name_unclear":false},{"inn":"","inn_hidden":false,"relations_hidden":false,"family_name":"Антонова Є. О","relations_other":"","relations":"Дитина","name_hidden":false,"name_unclear":false}],"patronymic":"Володимирівна","inn_hidden":true,"family_raw":"","inn_unclear":false,"post":{"post_unclear":false,"region_unclear":false,"post":"суддя голосіївського районного суду міста києва","candidate":"","office_hidden":false,"region":"м. Київ","post_hidden":false,"office":"Загальний місцевий суд","office_unclear":false,"region_hidden":false},"last_name_unclear":false,"full_name":"Антонова Наталія Володимирівна","addresses":[{"place_city_type_hidden":false,"place_district_hidden":false,"place_city_type":"Місто","place_city_hidden":false,"place_address_unclear":false,"place_address":"3022","place":"м. Київ","place_district":"","place_unclear":false,"place_city":"Київ","place_city_unclear":false,"place_hidden":false,"place_address_hidden":false,"place_district_unclear":false}],"last_name":"Антонова","patronymic_hidden":false,"full_name_suggest":{"output":"Антонова Наталія Володимирівна","input":["Антонова Наталія Володимирівна","Наталія Володимирівна Антонова","Наталія Антонова"]},"name_unclear":false},"source":"VULYK","estate":{"31":[{"space_unclear":false,"address_hidden":false,"region_hidden":false,"space_comment":"","space_units_hidden":false,"space_hidden":false,"space":"93.6","address":"м. Київ, вул. Ломоносова","region":"м. Київ","address_unclear":false,"costs_rent_comment":"","costs_property":"","space_units":"м²","costs_property_comment":"","costs_rent":""}]},"intro":{"declaration_year":"2014","isnotdeclaration":"","declaration_year_unclear":false}}