{"id":"vulyk_97_94","ft_src":"1999 куб. см.\nMazda 6\n2011\nNissan Note\n1386 куб. см.\n2007\nNissan Note\n1386 куб. см.\n2007\n1999 куб. см.\n2011\nMazda 6\nм. Харків\n750\nХарківська область\nм. Харків\n126.55\nХарківська область\n65.2\nм. Харків\nХарківська область\nм. Харків\n16.3\nХарківська область\n131\n4494\n2014\n1999 куб. см.\nMazda 6\n2011\nNissan Note\n1386 куб. см.\n2007\n1386 куб. см.\nNissan Note\n2007\n1999 куб. см.\n2011\nMazda 6\n2014\nЧудних Світлана Олександрівна\nСвітлана Олександрівна Чудних\nСвітлана Чудних\nЧудних Світлана Олександрівна\nСвітлана\nПодружжя\nЧудних Є. А\nЧудних Світлана Олександрівна\nЧудних\nАдміністративний місцевий суд\nХарківська область\nсуддя харківського окружного адміністративного суду\nОлександрівна\nХарківська область\n61107\nХарків\n181421\n53426\n181421\n53426\n750\nм. Харків\nХарківська область\n126.55\nХарківська область\nм. Харків\n65.2\nм. Харків\nХарківська область\n16.3\nХарківська область\nм. Харків\n4494\n131\n53426\n181421\n53426\n181421\nПодружжя\nЧудних Є. А\nОлександрівна\nЧудних\nСвітлана\nЧудних Світлана Олександрівна\nСвітлана Олександрівна Чудних\nСвітлана Чудних\nЧудних Світлана Олександрівна\n61107\nХарків\nХарківська область\nХарківська область\nАдміністративний місцевий суд\nсуддя харківського окружного адміністративного суду\nЧудних Світлана Олександрівна","estate":{"23":[{"address":"м. Харків","space_units":"м²","costs_rent_unclear":false,"costs_comment":"","space_unclear":false,"region_hidden":false,"space_comment":"","address_hidden":true,"costs":"","address_unclear":false,"costs_rent_comment":"","space":"750","region_unclear":false,"region":"Харківська область","costs_rent":""}],"24":[{"address":"м. Харків","space_units":"м²","space_hidden":false,"space_unclear":true,"region_hidden":false,"costs_rent_comment":"","space_comment":"","address_hidden":true,"costs":"","address_unclear":false,"space_comment_unclear":false,"costs_comment":"","space":"126.55","region_unclear":false,"region":"Харківська область","costs_rent":""}],"25":[{"address":"м. Харків","space_units":"м²","space_hidden":false,"space_unclear":false,"region_hidden":false,"costs_rent_comment":"","space_comment":"","address_hidden":true,"space_comment_hidden":false,"costs":"","space_comment_unclear":false,"costs_comment":"","space":"65.2","region_unclear":false,"region":"Харківська область","costs_rent":""},{"address":"м. Харків","space_units":"м²","space_unclear":false,"costs_comment":"","space_comment":"","address_hidden":false,"space":"16.3","space_comment_unclear":false,"costs_rent_comment":"","costs":"","region":"Харківська область","costs_rent":""}]},"vehicle":{"35":[{"year_hidden":false,"brand_info":"1999 куб. см.","brand_unclear":false,"sum_rent_comment":"","brand_hidden":false,"year":"2011","sum_comment":"","brand_info_hidden":false,"sum_rent":"","brand":"Mazda 6","brand_info_unclear":false,"sum":""},{"sum_comment":"","brand_info_hidden":false,"sum_rent":"","sum":"","brand_unclear":false,"year":"2007","brand":"Nissan Note","brand_info":"1386 куб. см.","sum_rent_comment":"","brand_info_unclear":false,"year_unclear":false}],"40":[{"sum_comment":"","brand_info":"1386 куб. см.","brand_unclear":false,"sum_rent_comment":"","year":"2007","brand":"Nissan Note","sum_rent":"","brand_info_unclear":false,"year_unclear":false,"sum":""},{"sum_comment":"","brand_info":"1999 куб. см.","sum":"","sum_rent_comment":"","year":"2011","brand":"Mazda 6","sum_rent":""}]},"source":"VULYK","income":{"5":{"family_comment":"","value":"181421","family":"53426","comment":""},"6":{"family_comment":"","family":"53426","comment":"","value_unclear":false,"family_unclear":false,"comment_hidden":false,"value":"181421"},"7":{"family":"","family_comment":"","value":"","comment":"","source_name":""},"8":{"family_comment":"","value":"","family":"","comment":""},"9":{"family_comment":"","value":"","family_unclear":false,"family":"","comment":""},"10":{"family_comment":"","value":"","family":"","comment":"","value_unclear":false},"11":{"family_comment":"","value":"","family":"","comment":""},"12":{"family_comment":"","value":"","family":"","comment":""},"13":{"family_comment":"","value":"","family":"","comment":""},"14":{"family_comment":"","value":"","family":"","comment":""},"15":{"family_comment":"","value":"","family":"","comment":""},"16":{"family_comment":"","value":"","family":"","comment":""},"17":{"family_comment":"","value":"","family":"","comment":""},"18":{"family_comment":"","value":"","family":"","comment":""},"19":{"family_comment":"","value":"","family":"","comment":""},"20":{"family_comment":"","comment":"","family":"","value_unclear":false,"comment_unclear":false,"value":"","family_hidden":false,"family_comment_unclear":false}},"banks":{"45":[{"sum_comment_unclear":false,"sum_units":"UAH","sum_foreign_units":"UAH","sum_hidden":false,"sum":"4494","sum_foreign_comment":"","sum_comment":"","sum_unclear":false,"sum_foreign":"","sum_comment_hidden":true}],"51":[{"sum_comment_unclear":false,"sum_units":"UAH","sum_foreign_units":"UAH","sum_hidden":false,"sum":"131","sum_foreign_comment":"","sum_comment":"","sum_unclear":false,"sum_foreign":"","sum_comment_hidden":true}]},"declaration":{"notfull_lostpages":"","additional_info_text":"","additional_info":"","date":"2015-03-30T00:00:00","notfull":"","url":"http://static.declarations.com.ua/declarations/chosen_ones/judges_batch/3995_chudnykh_svitlana_oleksandrivna.pdf"},"general":{"family":[{"inn":"","family_name":"Чудних Є. А","relations_other":"","name_unclear":false,"inn_hidden":true,"name_hidden":true,"relations":"Подружжя"}],"family_raw":"","name":"Світлана","full_name_suggest":{"input":["Чудних Світлана Олександрівна","Світлана Олександрівна Чудних","Світлана Чудних"],"output":"Чудних Світлана Олександрівна"},"patronymic":"Олександрівна","inn_hidden":true,"addresses":[{"place_city_type":"Місто","place_city_type_hidden":false,"place_hidden":false,"place_city_hidden":false,"place_district_hidden":false,"place_district":"","place_city_unclear":false,"place":"Харківська область","place_city":"Харків","place_address_hidden":true,"place_address":"61107"}],"last_name_hidden":false,"patronymic_hidden":false,"inn":"","inn_unclear":false,"last_name":"Чудних","full_name":"Чудних Світлана Олександрівна","post":{"post_hidden":false,"office":"Адміністративний місцевий суд","post":"суддя харківського окружного адміністративного суду","office_unclear":false,"region_unclear":false,"region":"Харківська область"},"name_hidden":false},"liabilities":{"54":{"sum_comment_unclear":false,"sum_comment":"","sum_hidden":false,"sum":"","sum_foreign_comment":"","sum_foreign":"","sum_unclear":false,"sum_comment_hidden":false},"55":{"sum_comment":"","sum_foreign_comment":"","sum_foreign":"","sum":""},"56":{"sum_comment":"","sum_foreign_comment":"","sum_foreign":"","sum":""},"57":{"sum_comment_unclear":false,"sum_comment":"","sum_hidden":false,"sum":"","sum_foreign_comment":"","sum_foreign":"","sum_unclear":false,"sum_comment_hidden":false},"58":{"sum_comment_unclear":false,"sum_comment":"","sum_hidden":false,"sum":"","sum_foreign_comment":"","sum_foreign":"","sum_unclear":false,"sum_comment_hidden":false},"59":{"sum_comment":"","sum_foreign_comment":"","sum_foreign":"","sum":""},"60":{"sum_comment_unclear":false,"sum_comment":"","sum_hidden":false,"sum":"","sum_foreign_comment":"","sum_foreign":"","sum_comment_hidden":false},"61":{"sum_comment":"","sum_foreign_comment":"","sum_foreign":"","sum":""},"62":{"sum_comment":"","sum_foreign_comment":"","sum_foreign":"","sum_unclear":false,"sum":""},"63":{"sum_comment":"","sum_foreign_comment":"","sum_foreign":"","sum_hidden":false,"sum":""},"64":{"sum_comment":"","sum_foreign_comment":"","sum_foreign":"","sum":""}},"intro":{"isnotdeclaration":"","declaration_year":"2014"}}