{"id":"vulyk_89_4","ft_src":"1598 куб. см.\n2011\nToyota Auris\nмашиномісце\n15\n81.6\n2014\n228000\n228000\n1598 куб. см.\nToyota Auris\n2011\n2014\nДонецька область\nсуддя донецького апеляційного адміністративного суду\nАпеляційний адміністративний суд\nГригорівна\nГаврищук Тетяна Григорівна\nТетяна Григорівна Гаврищук\nТетяна Гаврищук\nГаврищук Тетяна Григорівна\nГаврищук Тетяна Григорівна\nТетяна\nГаврищук\n228000\n228000\n15\nмашиномісце\n81.6\nГригорівна\nГаврищук\nсуддя донецького апеляційного адміністративного суду\nДонецька область\nАпеляційний адміністративний суд\nГаврищук Тетяна Григорівна\nГаврищук Тетяна Григорівна\nТетяна Григорівна Гаврищук\nТетяна Гаврищук\nГаврищук Тетяна Григорівна\nТетяна","estate":{"25":[{"address":"","space_units":"м²","costs_comment":"","region_hidden":true,"space_comment":"","address_hidden":false,"costs":"","space_comment_unclear":false,"costs_rent_comment":"","space":"81.6","region":"","costs_rent":""}],"28":[{"costs":"","address":"","space_units":"м²","costs_rent_comment":"","space":"15","space_comment":"машиномісце","region_hidden":true,"costs_comment":"","region":"","costs_rent":""}]},"vehicle":{"35":[{"sum_comment":"","brand_info":"1598 куб. см.","sum":"","sum_rent_comment":"","year":"2011","brand":"Toyota Auris","sum_rent":""}]},"source":"VULYK","income":{"5":{"family":"","family_comment":"","comment":"","value_hidden":false,"family_hidden":false,"value":"228000"},"6":{"family_comment":"","value":"228000","family":"","comment":""},"7":{"family":"","family_comment":"","value":"","comment":"","source_name":""},"8":{"family_comment":"","value":"","family":"","comment":""},"9":{"family_comment":"","value":"","family":"","comment":""},"10":{"family_comment":"","value":"","family":"","comment":""},"11":{"family_comment":"","value":"","family":"","comment":""},"12":{"family_comment":"","value":"","family":"","comment":""},"13":{"family_comment":"","value":"","family":"","comment":""},"14":{"family_comment":"","value":"","family":"","comment":""},"15":{"family_comment":"","value":"","family":"","comment":""},"16":{"family_comment":"","value":"","family":"","comment":""},"17":{"family_comment":"","value":"","family":"","comment":""},"18":{"family_comment":"","value":"","family":"","comment":""},"19":{"family_comment":"","value":"","family":"","comment":""},"20":{"family_comment":"","value":"","family":"","comment":""}},"general":{"inn":"","addresses":[{"place_city_type_hidden":false,"place_city_type":"","place_city_hidden":true,"place_hidden":true,"place_district":"","place_district_hidden":false,"place":"","place_address":"","place_address_hidden":false,"place_city":""}],"last_name":"Гаврищук","full_name_suggest":{"input":["Гаврищук Тетяна Григорівна","Тетяна Григорівна Гаврищук","Тетяна Гаврищук"],"output":"Гаврищук Тетяна Григорівна"},"full_name":"Гаврищук Тетяна Григорівна","patronymic":"Григорівна","inn_hidden":true,"name":"Тетяна","post":{"office":"Апеляційний адміністративний суд","region":"Донецька область","post":"суддя донецького апеляційного адміністративного суду"},"family_raw":""},"liabilities":{"54":{"sum_comment":"","sum_foreign_comment":"","sum_foreign":"","sum":""},"55":{"sum_comment":"","sum_foreign_comment":"","sum_foreign":"","sum":""},"56":{"sum_comment":"","sum_foreign_comment":"","sum_foreign":"","sum_unclear":false,"sum":""},"57":{"sum_comment":"","sum_foreign_comment":"","sum_foreign":"","sum":""},"58":{"sum_comment":"","sum_foreign_comment":"","sum_foreign":"","sum":""},"59":{"sum_comment":"","sum_foreign_comment":"","sum_foreign":"","sum":""},"60":{"sum_comment":"","sum_foreign_comment":"","sum_foreign":"","sum":""},"61":{"sum_comment":"","sum_foreign_comment":"","sum_foreign":"","sum":""},"62":{"sum_comment":"","sum_foreign_comment":"","sum_foreign":"","sum_unclear":false,"sum":""},"63":{"sum_comment":"","sum_foreign_comment":"","sum_foreign":"","sum":""},"64":{"sum_comment":"","sum_foreign_comment":"","sum_foreign":"","sum":""}},"declaration":{"notfull_lostpages":"","date":"2015-03-24T00:00:00","notfull":"","url":"http://static.declarations.com.ua/declarations/chosen_ones/judges_batch/3007_havryshchuk_tetiana_hryhorivna.pdf"},"intro":{"declaration_year":"2014"}}