{"income":{"5":{"value":"217890","value_unclear":false,"value_hidden":false,"family_comment":"","family":"29861","comment":""},"6":{"value":"205710","family_comment":"","value_unclear":false,"family_unclear":false,"family":"29861","comment":""},"7":{"source_name_unclear":false,"value":"","family_hidden":false,"family_comment":"","source_name":"","family":"","comment":""},"8":{"family_comment":"","value":"","family":"","comment":""},"9":{"family_comment":"","value":"","family":"","comment":""},"10":{"family_comment":"","value":"12180","family":"","comment":""},"11":{"family_comment":"","value":"","family":"","comment":""},"12":{"family_comment":"","value":"","family":"","comment":""},"13":{"family_comment":"","value":"","family":"","comment":""},"14":{"family_comment":"","value":"","family":"","comment":""},"15":{"family_comment":"","value":"","family":"","comment":""},"16":{"family_comment":"","value":"","comment_unclear":false,"family":"","comment":""},"17":{"family_comment":"","family_unclear":false,"value":"","family":"","comment":""},"18":{"family_comment":"","value":"","family":"","comment":""},"19":{"value":"","family_hidden":false,"value_hidden":false,"family_comment":"","family":"","comment":""},"20":{"family_comment":"","value":"","comment_unclear":false,"family":"","comment":""}},"vehicle":{"39":[{"brand_info":"Мотоцикл, 659 куб. см.","sum_rent_comment":"","brand":"Дніпро МТ 11","sum_comment":"","year":"1992","brand_hidden":false,"sum":"","sum_rent":""}]},"id":"vulyk_67_70","declaration":{"additional_info_text":"","notfull_lostpages":"","date":"2015-03-25T00:00:00","notfull":"","additional_info":"","url":"http://static.declarations.com.ua/declarations/chosen_ones/mega_batch/tretiak_oleksandr_hryhorovych.pdf"},"liabilities":{"54":{"sum_foreign_comment":"","sum_foreign_hidden":false,"sum_comment":"","sum_comment_unclear":false,"sum_hidden":false,"sum":"","sum_unclear":false,"sum_foreign":""},"55":{"sum_foreign_comment":"","sum":"","sum_comment":"","sum_foreign":""},"56":{"sum_foreign_comment":"","sum_foreign_hidden":false,"sum_comment":"","sum_hidden":false,"sum":"15000","sum_unclear":false,"sum_foreign":""},"57":{"sum_foreign_comment":"","sum_foreign_hidden":false,"sum_comment":"","sum_comment_unclear":false,"sum_hidden":false,"sum_comment_hidden":false,"sum_unclear":false,"sum":"","sum_foreign":""},"58":{"sum_foreign_comment":"","sum_foreign_hidden":false,"sum_comment":"","sum_comment_unclear":false,"sum_hidden":false,"sum_comment_hidden":false,"sum_unclear":false,"sum":"","sum_foreign":""},"59":{"sum_foreign_comment":"","sum":"","sum_hidden":false,"sum_comment":"","sum_foreign":""},"60":{"sum_foreign_comment":"","sum":"","sum_comment":"","sum_foreign":""},"61":{"sum_foreign_comment":"","sum_foreign_hidden":false,"sum_comment":"","sum_hidden":false,"sum":"","sum_foreign":""},"62":{"sum_foreign_comment":"","sum":"","sum_hidden":false,"sum_comment":"","sum_foreign":""},"63":{"sum_foreign_comment":"","sum":"","sum_comment":"","sum_comment_unclear":false,"sum_hidden":false,"sum_unclear":false,"sum_foreign":""},"64":{"sum_foreign_comment":"","sum":"","sum_comment":"","sum_hidden":false,"sum_unclear":false,"sum_foreign":""}},"ft_src":"15000\nсуддя білокуракинського районного суду луганської області\nЛуганська область\nЗагальний місцевий суд\nОлександр\nТретяк Т. В\nПодружжя\nТретяк Л. О\nДитина\nТретяк В. О\nДитина\nГригорович\nТретяк Олександр Григорович\nТретяк\nТретяк Олександр Григорович\nОлександр Григорович Третяк\nОлександр Третяк\nТретяк Олександр Григорович\nДніпро МТ 11\n1992\nМотоцикл, 659 куб. см.\nсмт Білокуракине\n10000\nЛуганська область\nсмт Білокуракине\nЛуганська область\n10000\nсмт Білокуракине\n76\nЛуганська область\n2014\n29861\n205710\n12180\n29861\n217890\nМотоцикл, 659 куб. см.\nДніпро МТ 11\n1992\n10000\nЛуганська область\nсмт Білокуракине\n10000\nсмт Білокуракине\nЛуганська область\n76\nЛуганська область\nсмт Білокуракине\nЗагальний місцевий суд\nсуддя білокуракинського районного суду луганської області\nЛуганська область\nПодружжя\nТретяк Т. В\nДитина\nТретяк Л. О\nДитина\nТретяк В. О\nТретяк Олександр Григорович\nОлександр Григорович Третяк\nОлександр Третяк\nТретяк Олександр Григорович\nТретяк Олександр Григорович\nОлександр\nТретяк\nГригорович\n15000\n29861\n205710\n217890\n29861\n12180\n2014\n15000\nПодружжя\nТретяк Т. В\nДитина\nТретяк Л. О\nТретяк В. О\nДитина\nГригорович\nТретяк\nОлександр\nТретяк Олександр Григорович\nОлександр Григорович Третяк\nОлександр Третяк\nТретяк Олександр Григорович\nЛуганська область\nсуддя білокуракинського районного суду луганської області\nЗагальний місцевий суд\nТретяк Олександр Григорович\nМотоцикл, 659 куб. см.\nДніпро МТ 11\n1992\n12180\n217890\n29861\n205710\n29861\nсмт Білокуракине\nЛуганська область\n76\nсмт Білокуракине\nЛуганська область\n10000\nЛуганська область\nсмт Білокуракине\n10000\n2014","general":{"inn":"","name":"Олександр","patronymic_unclear":false,"last_name_hidden":false,"family":[{"inn":"","inn_hidden":true,"relations_unclear":false,"relations_hidden":false,"relations_other":"","relations":"Подружжя","name_hidden":true,"inn_unclear":false,"family_name":"Третяк Т. В","name_unclear":false},{"inn":"","inn_hidden":false,"relations_unclear":false,"relations_hidden":false,"relations_other":"","relations":"Дитина","name_hidden":false,"inn_unclear":false,"family_name":"Третяк Л. О","name_unclear":false},{"inn":"","relations":"Дитина","relations_unclear":false,"family_name":"Третяк В. О","inn_hidden":false,"relations_other":"","name_hidden":false,"name_unclear":false}],"patronymic":"Григорович","inn_hidden":true,"family_raw":"","inn_unclear":false,"post":{"post_unclear":false,"post":"суддя білокуракинського районного суду луганської області","post_hidden":false,"region":"Луганська область","region_hidden":false,"office":"Загальний місцевий суд","office_hidden":false,"office_unclear":false},"last_name_unclear":false,"full_name":"Третяк Олександр Григорович","addresses":[{"place_city_type_hidden":true,"place_district_hidden":true,"place_city_type":"","place_city_hidden":true,"place_address_unclear":false,"place_address":"","place":"","place_district":"","place_unclear":false,"place_city":"","place_city_unclear":false,"place_hidden":true,"place_address_hidden":true,"place_district_unclear":false}],"last_name":"Третяк","full_name_suggest":{"output":"Третяк Олександр Григорович","input":["Третяк Олександр Григорович","Олександр Григорович Третяк","Олександр Третяк"]},"name_unclear":false},"source":"VULYK","estate":{"23":[{"space_hidden":false,"costs":"","costs_comment":"","costs_hidden":false,"address_hidden":true,"region_hidden":true,"space_comment":"","space_unclear":false,"space":"10000","address":"смт Білокуракине","region":"Луганська область","address_unclear":true,"space_units_unclear":false,"costs_rent_hidden":false,"space_comment_unclear":false,"space_units":"м²","costs_rent":"","costs_rent_comment":""}],"25":[{"space_unclear":false,"costs":"","costs_comment":"","costs_hidden":false,"address_hidden":true,"region_hidden":true,"space_comment":"","space":"76","address":"смт Білокуракине","region":"Луганська область","address_unclear":false,"space_units_unclear":false,"space_comment_unclear":false,"space_units":"м²","costs_rent":"","costs_rent_comment":""}],"29":[{"region_unclear":false,"space_unclear":false,"address_hidden":true,"region_hidden":true,"space_comment":"","space_units_hidden":false,"space_hidden":false,"space":"10000","address":"смт Білокуракине","region":"Луганська область","costs_property":"","costs_rent_comment":"","space_units":"м²","costs_property_comment":"","costs_rent":""}]},"intro":{"declaration_year":"2014","isnotdeclaration":"","declaration_year_hidden":false}}