{"income":{"5":{"family_comment":"","value":"257036","value_unclear":false,"family":"","comment":""},"6":{"value":"257036","value_unclear":false,"family_hidden":false,"family_comment":"","family":"","comment":""},"7":{"source_name_unclear":false,"value":"","family_comment":"","source_name":"","family":"","comment":""},"8":{"family_comment":"","value":"","family":"","comment":""},"9":{"family_comment":"","value":"6584","family":"","comment":""},"10":{"family_comment":"","value":"","family":"","comment":""},"11":{"family_comment":"","value":"","comment_unclear":false,"family":"","comment":""},"12":{"family_comment":"","value":"","family":"","comment":""},"13":{"family_comment":"","value":"","family":"","comment":""},"14":{"family_comment":"","value":"","family":"","comment":""},"15":{"family_comment":"","value":"","family":"","comment":""},"16":{"family_comment":"","value":"","family":"","comment":""},"17":{"family_comment":"","value":"","family":"","comment":""},"18":{"family_comment":"","value":"","family":"","comment":""},"19":{"family_comment":"","value":"","family":"","comment":""},"20":{"value":"","family_comment":"","value_unclear":false,"family_unclear":false,"comment_unclear":false,"comment":"","family":""}},"vehicle":{"35":[{"brand_info":"2488","sum_rent_comment":"","brand":"Mazda CX-5","sum_comment":"","brand_unclear":false,"year":"2014","sum_rent_unclear":false,"brand_info_hidden":false,"brand_info_unclear":false,"sum":"","sum_rent":""}]},"id":"vulyk_101_70","banks":{"45":[{"sum_foreign_comment":"","sum_units":"UAH","sum_comment":"Приватбанк","sum_comment_unclear":false,"sum_hidden":false,"sum_foreign_units":"UAH","sum_comment_hidden":false,"sum_unclear":false,"sum":"41924","sum_foreign":""}]},"declaration":{"additional_info_text":"","notfull_lostpages":"","date":"2016-03-30T00:00:00","notfull":"","additional_info":"","url":"http://static.declarations.com.ua/declarations/chosen_ones/judges_batch/735_tsiura_taisiia_vasylivna_2015.pdf"},"liabilities":{"54":{"sum_foreign_comment":"","sum":"18891","sum_comment":"ПАТ Страхове товариство Іллічівське","sum_comment_unclear":false,"sum_hidden":false,"sum_comment_hidden":false,"sum_unclear":false,"sum_foreign":""},"55":{"sum_foreign_comment":"","sum":"","sum_comment":"","sum_foreign":""},"56":{"sum_foreign_comment":"","sum":"","sum_comment":"","sum_comment_hidden":false,"sum_unclear":false,"sum_foreign":""},"57":{"sum_foreign_comment":"","sum":"","sum_comment":"","sum_hidden":false,"sum_comment_hidden":false,"sum_unclear":false,"sum_foreign":""},"58":{"sum_foreign_comment":"","sum":"","sum_comment":"","sum_comment_unclear":false,"sum_hidden":false,"sum_comment_hidden":false,"sum_unclear":false,"sum_foreign":""},"59":{"sum_foreign_comment":"","sum":"","sum_comment":"","sum_foreign":""},"60":{"sum_foreign_comment":"","sum":"","sum_comment":"","sum_hidden":false,"sum_comment_hidden":false,"sum_unclear":false,"sum_foreign":""},"61":{"sum_foreign_comment":"","sum":"","sum_comment":"","sum_foreign":""},"62":{"sum_foreign_comment":"","sum":"","sum_comment":"","sum_comment_unclear":false,"sum_foreign":""},"63":{"sum_foreign_comment":"","sum_comment_hidden":false,"sum":"","sum_comment":"","sum_foreign":""},"64":{"sum_foreign_comment":"","sum_comment_hidden":false,"sum":"","sum_comment":"","sum_foreign":""}},"ft_src":"ПАТ Страхове товариство Іллічівське\n18891\nсуддя апеляційного суду одеської області\nОдеська область\nЗагальний апеляційний суд\nТаїсія\nВасилівна\nЦюра Таїсія Василівна\nЦюра\nЦюра Таїсія Василівна\nТаїсія Василівна Цюра\nТаїсія Цюра\nЦюра Таїсія Василівна\nMazda CX-5\n2488\n2014\nПриватбанк\n41924\n2015\n2488\n2014\nMazda CX-5\nПриватбанк\n41924\n29\nприв.\n80\nдарування\nЦюра Таїсія Василівна\nТаїсія Василівна Цюра\nТаїсія Цюра\nЦюра Таїсія Василівна\nТаїсія\nЦюра Таїсія Василівна\nВасилівна\nсуддя апеляційного суду одеської області\nОдеська область\nЗагальний апеляційний суд\nЦюра\n18891\nПАТ Страхове товариство Іллічівське\n257036\n257036\n6584\n2015\nПАТ Страхове товариство Іллічівське\n18891\n29\nприв.\nдарування\n80\nВасилівна\nЦюра\nТаїсія\nЦюра Таїсія Василівна\nТаїсія Василівна Цюра\nТаїсія Цюра\nЦюра Таїсія Василівна\nсуддя апеляційного суду одеської області\nОдеська область\nЗагальний апеляційний суд\nЦюра Таїсія Василівна\n257036\n6584\n257036\n2014\nMazda CX-5\n2488\n6584\n257036\n257036\nприв.\nдарування\n80\n29\nПриватбанк\n41924\n2015","general":{"inn":"","name":"Таїсія","inn_unclear":false,"patronymic":"Василівна","inn_hidden":true,"family_raw":"","last_name":"Цюра","post":{"region":"Одеська область","region_unclear":false,"post":"суддя апеляційного суду одеської області","office_unclear":false,"office":"Загальний апеляційний суд"},"full_name":"Цюра Таїсія Василівна","addresses":[{"place_district":"","place_address_hidden":true,"place_city":"","place_city_type_hidden":false,"place_district_hidden":false,"place_city_type":"","place_city_hidden":true,"place_address":"","place_hidden":true,"place":""}],"patronymic_hidden":false,"full_name_suggest":{"output":"Цюра Таїсія Василівна","input":["Цюра Таїсія Василівна","Таїсія Василівна Цюра","Таїсія Цюра"]}},"source":"VULYK","estate":{"25":[{"space_unclear":true,"costs":"","costs_comment":"","address_hidden":false,"region_hidden":true,"space_comment":"прив.","space_hidden":true,"space":"","address":"","region":"","costs_rent_comment":"","space_comment_unclear":false,"space_units":"м²","costs_rent":""},{"space_unclear":true,"costs":"","costs_comment":"","space_comment":"дарування","space_hidden":true,"space":"80","address":"","region":"","costs_rent_comment":"","space_comment_unclear":false,"space_units":"м²","costs_rent":""}],"27":[{"space_hidden":false,"costs":"","costs_comment":"","address_hidden":false,"region_hidden":true,"space_comment":"","space":"29","address":"","region":"","costs_rent_comment":"","space_units":"м²","costs_rent":""}]},"intro":{"declaration_year":"2015"}}