{"income":{"5":{"family_comment":"","value":"259886","family":"","comment":"","family_hidden":false},"6":{"family_comment":"","value":"246488","family":"","comment":"","family_hidden":false},"7":{"family_comment":"","value":"","source_name":"","family":"","comment":""},"8":{"family_comment":"","value":"","family":"","comment":""},"9":{"family_comment":"","value":"","family":"","comment":""},"10":{"family_comment":"","value":"13398","family":"","comment":""},"11":{"family_comment":"","value":"","family":"","comment":""},"12":{"family_comment":"","value":"","family":"","comment":""},"13":{"family_comment":"","value":"","family":"","comment":""},"14":{"family_comment":"","value":"","family":"","comment":""},"15":{"family_comment":"","value":"","family":"","comment":""},"16":{"family_comment":"","value":"","family":"","comment":""},"17":{"family_comment":"","value":"","family":"","comment":""},"18":{"family_comment":"","value":"","family":"","comment":""},"19":{"family_comment":"","value":"","family":"","comment":""},"20":{"family_comment":"","value":"","family":"","comment":""}},"id":"vulyk_105_63","declaration":{"date":"2016-02-12T00:00:00","additional_info_text":"Уточнююча декларація","additional_info":"1","url":"http://static.declarations.com.ua/declarations/chosen_ones/judges_batch/4638_shevchenko_eduard_oleksandrovych.pdf"},"liabilities":{"54":{"sum_foreign_comment":"","sum_comment":"","sum":"","sum_comment_hidden":false,"sum_foreign":""},"55":{"sum_foreign_comment":"","sum":"","sum_comment":"","sum_foreign":""},"56":{"sum_foreign_comment":"","sum":"","sum_comment":"","sum_foreign":""},"57":{"sum_foreign_comment":"","sum":"","sum_comment":"","sum_comment_unclear":false,"sum_comment_hidden":false,"sum_foreign":""},"58":{"sum_foreign_comment":"","sum":"","sum_comment":"","sum_foreign":""},"59":{"sum_foreign_comment":"","sum":"75000","sum_comment":"","sum_foreign":""},"60":{"sum_foreign_comment":"","sum":"","sum_comment":"","sum_foreign":""},"61":{"sum_foreign_comment":"","sum":"","sum_comment":"","sum_foreign":""},"62":{"sum_foreign_comment":"","sum":"","sum_foreign":"","sum_comment":"","sum_hidden":false},"63":{"sum_foreign_comment":"","sum":"","sum_comment":"","sum_foreign":""},"64":{"sum_foreign_comment":"","sum":"","sum_comment":"","sum_foreign":""}},"ft_src":"1\nУточнююча декларація\n2014\n246488\n13398\n259886\n1\nУточнююча декларація\n246488\n259886\n13398\nШевченко\nШевченко Едуард Олександрович\nЕдуард Олександрович Шевченко\nЕдуард Шевченко\nШевченко Едуард Олександрович\nЕдуард\nШевченко Едуард Олександрович\nОлександрович\nсуддя київського апеляційного господарського суду\nАпеляційний господарський суд\nм. Київ\n75000\n2014\n75000\nОлександрович\nШевченко\nм. Київ\nсуддя київського апеляційного господарського суду\nАпеляційний господарський суд\nШевченко Едуард Олександрович\nШевченко Едуард Олександрович\nЕдуард Олександрович Шевченко\nЕдуард Шевченко\nШевченко Едуард Олександрович\nЕдуард","general":{"inn":"","inn_hidden":true,"last_name":"Шевченко","post":{"post_unclear":false,"region_unclear":false,"post":"суддя київського апеляційного господарського суду","office_hidden":false,"region":"м. Київ","office":"Апеляційний господарський суд","office_unclear":false},"name":"Едуард","full_name":"Шевченко Едуард Олександрович","family_raw":"","addresses":[{"place_district":"","place_address_hidden":false,"place_city":"","place_address":"","place_district_hidden":false,"place_city_type":"","place_city_hidden":false,"place_city_type_hidden":false,"place_hidden":true,"place":""}],"full_name_suggest":{"output":"Шевченко Едуард Олександрович","input":["Шевченко Едуард Олександрович","Едуард Олександрович Шевченко","Едуард Шевченко"]},"patronymic":"Олександрович"},"source":"VULYK","intro":{"declaration_year":"2014"}}