{"income":{"5":{"family_comment":"","value":"284554","family":"","comment":""},"6":{"family_comment":"","value":"257229","value_unclear":false,"family":"","comment":""},"7":{"value":"","family_comment":"","source_name":"","family":"","comment":"","source_name_hidden":false},"8":{"family_comment":"","value":"","family":"","comment":""},"9":{"family_comment":"","value":"1925","family":"","comment":""},"10":{"family_comment":"","value":"13398","family":"","comment":""},"11":{"family_comment":"","value":"","comment_hidden":false,"family":"","comment":""},"12":{"family_comment":"","value":"","family":"","comment":""},"13":{"family_comment":"","value":"","family":"","comment":""},"14":{"family_comment":"","value":"","family":"","comment":""},"15":{"value":"","family_comment":"","value_unclear":false,"family_unclear":false,"family":"","comment":""},"16":{"family_comment":"","value":"","family":"","comment":""},"17":{"family_comment":"","value":"","family":"","comment":""},"18":{"family_comment":"","value":"","family":"","comment":""},"19":{"family_comment":"","value":"","family":"","comment":""},"20":{"family_comment":"","value":"12002","comment_unclear":false,"family":"","comment":"пенсія"}},"id":"vulyk_104_158","banks":{"45":[{"sum_foreign_comment":"","sum_units":"UAH","sum_comment":"","sum_hidden":false,"sum_foreign_units":"UAH","sum_foreign_hidden":false,"sum_comment_hidden":false,"sum_unclear":false,"sum":"59","sum_foreign":""}]},"declaration":{"date":"2016-03-31T00:00:00","additional_info_text":"","additional_info":"","url":"http://static.declarations.com.ua/declarations/chosen_ones/judges_batch/1956_kryvokhyzha_vira_ivanivna_2015.pdf"},"liabilities":{"54":{"sum_foreign_comment":"","sum_foreign_hidden":false,"sum_comment":"","sum_hidden":false,"sum_comment_hidden":false,"sum_unclear":false,"sum":"1461","sum_foreign":""},"55":{"sum_foreign_comment":"","sum":"","sum_comment":"","sum_foreign":""},"56":{"sum_foreign_comment":"","sum":"5251","sum_comment":"","sum_unclear":false,"sum_foreign":""},"57":{"sum_foreign_comment":"","sum_foreign_hidden":false,"sum_comment":"","sum_comment_unclear":false,"sum_comment_hidden":false,"sum":"31051","sum_foreign":""},"58":{"sum_foreign_comment":"","sum":"42138","sum_comment":"","sum_unclear":false,"sum_foreign":""},"59":{"sum_foreign_comment":"","sum":"","sum_comment":"","sum_foreign":""},"60":{"sum_foreign_comment":"","sum_foreign_hidden":false,"sum_comment":"","sum_comment_hidden":false,"sum":"","sum_foreign":""},"61":{"sum_foreign_comment":"","sum":"","sum_comment":"","sum_foreign":""},"62":{"sum_foreign_comment":"","sum":"","sum_comment":"","sum_foreign":""},"63":{"sum_foreign_comment":"","sum":"","sum_comment":"","sum_foreign":""},"64":{"sum_foreign_comment":"","sum":"","sum_comment":"","sum_foreign":""}},"ft_src":"31051\n1461\n42138\n5251\nКривохижа Віра Іванівна\nсуддя апеляційного суду кіровоградської області\nКіровоградська область\nЗагальний апеляційний суд\nВіра\nКривохижа Віра Іванівна\nВіра Іванівна Кривохижа\nВіра Кривохижа\nКривохижа Віра Іванівна\nКривохижа\nІванівна\n1925\n13398\nпенсія\n12002\n284554\n257229\n59\nіпотека, кредит\n111.8\n2015\n257229\n1925\n13398\n284554\nпенсія\n12002\n59\n2015\nКривохижа Віра Іванівна\nВіра Іванівна Кривохижа\nВіра Кривохижа\nКривохижа Віра Іванівна\nКривохижа Віра Іванівна\nІванівна\nВіра\nКривохижа\nЗагальний апеляційний суд\nсуддя апеляційного суду кіровоградської області\nКіровоградська область\n42138\n1461\n5251\n31051\n257229\nпенсія\n12002\n284554\n1925\n13398\n111.8\nіпотека, кредит\n42138\n5251\n31051\n1461\nКривохижа\nІванівна\nсуддя апеляційного суду кіровоградської області\nЗагальний апеляційний суд\nКіровоградська область\nКривохижа Віра Іванівна\nКривохижа Віра Іванівна\nВіра Іванівна Кривохижа\nВіра Кривохижа\nКривохижа Віра Іванівна\nВіра\nіпотека, кредит\n111.8\n59\n2015","general":{"inn":"","inn_hidden":true,"last_name":"Кривохижа","post":{"region":"Кіровоградська область","region_unclear":false,"post":"суддя апеляційного суду кіровоградської області","office_unclear":false,"office":"Загальний апеляційний суд"},"name":"Віра","full_name":"Кривохижа Віра Іванівна","family_raw":"","addresses":[{"place_district":"","place_city_hidden":true,"place_city":"","place_city_type_hidden":false,"place_district_hidden":false,"place_city_type":"","place_address_hidden":true,"place_address":"","place_hidden":true,"place":""}],"full_name_suggest":{"output":"Кривохижа Віра Іванівна","input":["Кривохижа Віра Іванівна","Віра Іванівна Кривохижа","Віра Кривохижа"]},"patronymic":"Іванівна"},"source":"VULYK","estate":{"24":[{"space_hidden":false,"costs":"","costs_comment":"","address_hidden":false,"region_hidden":true,"space_comment":"іпотека, кредит","space":"111.8","address":"","region":"","costs_rent_comment":"","space_comment_unclear":false,"space_units":"м²","costs_rent":""}]},"intro":{"declaration_year":"2015","isnotdeclaration":""}}