{"income":{"5":{"value":"231420.57","family_comment":"","value_unclear":false,"family_unclear":false,"family":"30684.8","comment":""},"6":{"value":"231420.57","family_comment":"","value_unclear":false,"family_unclear":false,"family":"","comment":""},"7":{"family_comment":"","value":"","source_name":"","family":"","comment":""},"8":{"family_comment":"","value":"","family":"","comment":""},"9":{"family_comment":"","value":"","family":"","comment":""},"10":{"family_comment":"","value":"","family":"","comment":""},"11":{"family_comment":"","value":"","family":"","comment":""},"12":{"family_comment":"","value":"","family":"","comment":""},"13":{"family_comment":"","value":"","family":"","comment":""},"14":{"family_comment":"","value":"","family":"","comment":""},"15":{"family_comment":"","value":"","value_unclear":false,"family":"","comment":""},"16":{"family_comment":"","value":"","family":"","comment":""},"17":{"family_comment":"","value":"","family":"","comment":""},"18":{"family_comment":"","value":"","family":"","comment":""},"19":{"family_comment":"","value":"","family":"","comment":""},"20":{"value":"","family_comment":"пенсія","value_unclear":false,"family_unclear":false,"family":"30684.8","comment":"","family_comment_unclear":false}},"vehicle":{"35":[{"brand_info":"2.2 D","sum_rent_comment":"","brand":"Nissan X-Trail","sum_comment":"","brand_unclear":false,"year":"2007","brand_info_unclear":false,"sum":"","sum_rent":""}]},"id":"vulyk_99_42","declaration":{"date":"2016-03-11T00:00:00","notfull":"","url":"http://static.declarations.com.ua/declarations/chosen_ones/judges_batch/591_krotinov_viktor_oleksandrovych_2015.pdf","notfull_lostpages":""},"liabilities":{"54":{"sum_foreign_comment":"","sum":"","sum_comment":"","sum_comment_unclear":false,"sum_comment_hidden":false,"sum_foreign":""},"55":{"sum_foreign_comment":"","sum":"","sum_comment":"","sum_foreign":""},"56":{"sum_foreign_comment":"","sum":"","sum_comment":"","sum_foreign":""},"57":{"sum_foreign_comment":"","sum_comment_hidden":false,"sum":"","sum_comment":"","sum_foreign":""},"58":{"sum_foreign_comment":"","sum_comment_hidden":false,"sum":"","sum_comment":"","sum_foreign":""},"59":{"sum_foreign_comment":"","sum":"","sum_comment":"","sum_comment_hidden":false,"sum_unclear":false,"sum_foreign":""},"60":{"sum_foreign_comment":"","sum_comment_hidden":false,"sum":"","sum_comment":"","sum_foreign":""},"61":{"sum_foreign_comment":"","sum":"","sum_comment":"","sum_foreign":""},"62":{"sum_foreign_comment":"","sum":"","sum_comment":"","sum_foreign":""},"63":{"sum_foreign_comment":"","sum_comment_hidden":false,"sum":"","sum_comment":"","sum_foreign":""},"64":{"sum_foreign_comment":"","sum_comment_hidden":false,"sum":"","sum_comment":"","sum_foreign":""}},"ft_src":"Кротінов Віктор Олександрович\nсуддя селидівського міського суду донецької області\nДонецька область\nЗагальний місцевий суд\nВіктор\nКротінова І. Е\nПодружжя\nКротінов Віктор Олександрович\nВіктор Олександрович Кротінов\nВіктор Кротінов\nКротінов Віктор Олександрович\nКротінов\nОлександрович\n2007\nNissan X-Trail\n2.2 D\n.0257\n42\n84.3\n2015\n231420.57\n30684.8\n231420.57\nпенсія\n30684.8\n2.2 D\nNissan X-Trail\n2007\n2015\nКротінов\nКротінов Віктор Олександрович\nВіктор Олександрович Кротінов\nВіктор Кротінов\nКротінов Віктор Олександрович\nВіктор\nОлександрович\nКротінов Віктор Олександрович\nЗагальний місцевий суд\nсуддя селидівського міського суду донецької області\nДонецька область\nПодружжя\nКротінова І. Е\n231420.57\nпенсія\n30684.8\n231420.57\n30684.8\n.0257\n42\n84.3\nКротінова І. Е\nПодружжя\nОлександрович\nКротінов\nсуддя селидівського міського суду донецької області\nДонецька область\nЗагальний місцевий суд\nКротінов Віктор Олександрович\nКротінов Віктор Олександрович\nВіктор Олександрович Кротінов\nВіктор Кротінов\nКротінов Віктор Олександрович\nВіктор\n2007\n2.2 D\nNissan X-Trail\nпенсія\n30684.8\n231420.57\n30684.8\n231420.57\n84.3\n.0257\n42\n2015","general":{"inn":"","inn_hidden":true,"last_name":"Кротінов","post":{"post_unclear":false,"office":"Загальний місцевий суд","post":"суддя селидівського міського суду донецької області","region":"Донецька область"},"name":"Віктор","full_name":"Кротінов Віктор Олександрович","family_raw":"","addresses":[{"place_district":"","place_city_hidden":true,"place_city":"","place_city_type_hidden":false,"place_district_hidden":false,"place_city_type":"","place_address_hidden":true,"place_address":"","place_hidden":true,"place":""}],"family":[{"inn_hidden":true,"inn":"","name_hidden":true,"family_name":"Кротінова І. Е","relations":"Подружжя","name_unclear":false}],"full_name_suggest":{"output":"Кротінов Віктор Олександрович","input":["Кротінов Віктор Олександрович","Віктор Олександрович Кротінов","Віктор Кротінов"]},"patronymic":"Олександрович"},"source":"VULYK","estate":{"23":[{"space_unclear":false,"costs":"","costs_comment":"","address_hidden":false,"region_hidden":true,"space_comment":"","space":".0257","address":"","region":"","costs_rent_comment":"","space_units":"га","costs_rent":""}],"25":[{"space_hidden":false,"costs":"","costs_comment":"","address_hidden":false,"region_hidden":true,"space_comment":"","space_unclear":false,"space":"84.3","address":"","region":"","costs_rent_comment":"","space_units":"м²","costs_rent":""}],"27":[{"costs_rent":"","region":"","costs":"","costs_rent_comment":"","costs_comment":"","address_hidden":false,"region_hidden":true,"space_comment":"","space_units":"м²","space":"42","address":""}]},"intro":{"declaration_year":"2015"}}