{"income":{"5":{"family_comment":"","value":"216748","family":"1886788","comment":""},"6":{"family_comment":"","value":"216748","family":"1783726","comment":"","family_hidden":false},"7":{"family_comment":"","value":"","source_name":"","family":"","comment":""},"8":{"family_comment":"","value":"","family":"","comment":""},"9":{"value":"","value_unclear":false,"family_hidden":false,"family_comment":"","family":"","comment":""},"10":{"value":"","family_comment":"","family_hidden":false,"value_hidden":false,"family_unclear":false,"family":"","comment":""},"11":{"family_comment":"","value":"","family":"","comment":""},"12":{"family_comment":"","value":"","family":"","comment":""},"13":{"family_comment":"","value":"","family":"","comment":""},"14":{"family_comment":"","value":"","family":"","comment":""},"15":{"family_comment":"","value":"","family":"","comment":""},"16":{"family_comment":"","value":"","family":"","comment":""},"17":{"family_comment":"","value":"","family":"","comment":""},"18":{"family_comment":"","value":"","family":"","comment":""},"19":{"family_comment":"","value":"","family":"103062","comment":""},"20":{"value":"","comment_unclear":false,"family_comment":"","family":"","comment":"","family_comment_unclear":false}},"vehicle":{"40":[{"brand_info":"4608 куб. см.","sum_rent_comment":"","brand":"Lexus LS 460","sum_comment":"","year":"2007","brand_info_unclear":false,"sum":"","sum_rent":""},{"brand_info":"1598 куб. см.","sum":"","brand":"ЗАЗ Daewoo Lanos","sum_comment":"","brand_unclear":false,"year":"2006","sum_rent_comment":"","sum_rent":""},{"brand_info":"1498 куб. см.","sum":"","brand":"Chevrolet Aveo","sum_comment":"","year":"2006","sum_rent_comment":"","sum_rent":""}]},"id":"vulyk_75_38","banks":{"53":[{"sum_foreign_comment":"","sum":"1215000","sum_comment":"","sum_comment_unclear":false,"sum_foreign_units":"UAH","sum_units":"UAH","sum_foreign":""},{"sum_foreign_comment":"","sum":"863000","sum_comment":"","sum_foreign_units":"UAH","sum_units":"UAH","sum_foreign":""},{"sum_foreign_comment":"","sum":"21000","sum_comment":"","sum_foreign_units":"UAH","sum_units":"UAH","sum_foreign":""},{"sum_foreign_comment":"","sum":"33000","sum_comment":"","sum_foreign_units":"UAH","sum_units":"UAH","sum_foreign":""}]},"declaration":{"additional_info_text":"","notfull_lostpages":"3,4,6","date":"2015-03-31T00:00:00","notfull":"1","additional_info":"","url":"http://static.declarations.com.ua/declarations/chosen_ones/judges_batch/1897_morshchahina_nataliia_stanislavivna.pdf"},"liabilities":{"54":{"sum_foreign_comment":"","sum":"","sum_comment":"","sum_foreign":""},"55":{"sum_foreign_comment":"","sum":"","sum_comment":"","sum_foreign":""},"56":{"sum_foreign_comment":"","sum":"","sum_comment":"","sum_foreign":""},"57":{"sum_foreign_comment":"","sum":"","sum_comment":"","sum_foreign":""},"58":{"sum_foreign_comment":"","sum":"","sum_comment":"","sum_foreign":""},"59":{"sum_foreign_comment":"","sum":"","sum_comment":"","sum_comment_unclear":false,"sum_unclear":false,"sum_foreign":""},"60":{"sum_foreign_comment":"","sum":"","sum_comment":"","sum_foreign":""},"61":{"sum_foreign_comment":"","sum":"","sum_comment":"","sum_foreign":""},"62":{"sum_foreign_comment":"","sum":"","sum_comment":"","sum_unclear":false,"sum_foreign":""},"63":{"sum_foreign_comment":"","sum":"","sum_comment":"","sum_foreign":""},"64":{"sum_foreign_comment":"","sum":"","sum_comment":"","sum_foreign":""}},"ft_src":"4608 куб. см.\n2007\nLexus LS 460\n2006\n1598 куб. см.\nЗАЗ Daewoo Lanos\n1498 куб. см.\n2006\nChevrolet Aveo\n1215000\n863000\n21000\n33000\n3,4,6\n1\n2014\n4608 куб. см.\n2007\nLexus LS 460\n1598 куб. см.\nЗАЗ Daewoo Lanos\n2006\n1498 куб. см.\n2006\nChevrolet Aveo\n3,4,6\n1\n1215000\n863000\n21000\n33000\n2014\nМорщагіна\nСтаніславівна\nПодружжя\nМорщагін О. В\nДитина\nМорщагін Д. О\nМорщагіна Наталія Станіславівна\nНаталія Станіславівна Морщагіна\nНаталія Морщагіна\nМорщагіна Наталія Станіславівна\nНаталія\nМорщагіна Наталія Станіславівна\nАпеляційний господарський суд\nсуддя, голова одеського апеляційного господарського суду\nОдеська область\n216748\n1783726\n216748\n1886788\n103062\n1650\n530\n165\n1650\n530\n165\nМорщагін О. В\nПодружжя\nМорщагін Д. О\nДитина\nМорщагіна\nСтаніславівна\nсуддя, голова одеського апеляційного господарського суду\nОдеська область\nАпеляційний господарський суд\nМорщагіна Наталія Станіславівна\nМорщагіна Наталія Станіславівна\nНаталія Станіславівна Морщагіна\nНаталія Морщагіна\nМорщагіна Наталія Станіславівна\nНаталія\n1783726\n216748\n1886788\n216748\n103062","general":{"inn_hidden":true,"inn":"","last_name":"Морщагіна","post":{"office":"Апеляційний господарський суд","region":"Одеська область","post":"суддя, голова одеського апеляційного господарського суду"},"name":"Наталія","full_name":"Морщагіна Наталія Станіславівна","family_raw":"","addresses":[{"place_district":"","place_address_hidden":true,"place_hidden":true,"place_address":"","place_district_hidden":true,"place_city_type":"","place_city_hidden":true,"place_city_type_hidden":false,"place_city":"","place":""}],"family":[{"inn":"","inn_hidden":false,"relations_hidden":false,"family_name":"Морщагін О. В","relations_other":"","relations":"Подружжя","name_hidden":false,"name_unclear":false},{"inn":"","inn_hidden":false,"family_name":"Морщагін Д. О","relations_other":"","relations":"Дитина","name_hidden":false,"name_unclear":false}],"full_name_suggest":{"output":"Морщагіна Наталія Станіславівна","input":["Морщагіна Наталія Станіславівна","Наталія Станіславівна Морщагіна","Наталія Морщагіна"]},"patronymic":"Станіславівна"},"source":"VULYK","estate":{"29":[{"space_units_unclear":false,"address_hidden":true,"region_hidden":true,"space_comment":"","space":"1650","address":"","region":"","costs_property":"","costs_rent_comment":"","space_units":"м²","costs_property_comment":"","costs_rent":""}],"30":[{"costs_rent":"","region":"","costs_property":"","costs_rent_comment":"","region_hidden":true,"space_comment":"","costs_property_comment":"","space_units":"м²","space":"530","address":""}],"34":[{"costs_rent":"","region":"","costs_property":"","costs_rent_comment":"","address_hidden":true,"region_hidden":true,"space_comment":"","costs_property_comment":"","space_units":"м²","space":"165","address":""}]},"intro":{"declaration_year":"2014","isnotdeclaration":""}}