{"income":{"5":{"value":"276351","family_comment":"","value_unclear":false,"comment_hidden":false,"family_hidden":false,"value_hidden":false,"family_unclear":false,"family_comment_hidden":false,"comment":"","family":"67800.9"},"6":{"value":"238786.8","family_comment":"","value_unclear":false,"family_hidden":false,"family_unclear":false,"family":"67694.9","comment":""},"7":{"source_name_unclear":false,"value":"9503.77","family_hidden":false,"family_comment":"","source_name":"Чернігівський національний технологічний університет","family":"","comment":"","source_name_hidden":false},"8":{"family_comment":"","value":"","family":"","comment":""},"9":{"value":"11688.44","value_unclear":false,"family_hidden":false,"family_comment":"","family":"","comment":""},"10":{"value":"","value_unclear":false,"family_hidden":false,"value_hidden":false,"family_comment":"","comment_unclear":false,"comment":"","family":""},"11":{"family_comment":"","value":"","family":"106","comment":""},"12":{"family_comment":"","value":"","family":"","comment":""},"13":{"family_comment":"","value":"","family":"","comment":""},"14":{"family_comment":"","value":"","family":"","comment":""},"15":{"family_comment":"","value":"","family_hidden":false,"comment":"","family":""},"16":{"value":"","value_unclear":false,"family_hidden":false,"family_comment":"","family":"","comment":""},"17":{"family_comment":"","value":"","family_hidden":false,"comment":"","family":""},"18":{"family_comment":"","value":"","value_unclear":false,"family":"","comment":""},"19":{"family_comment":"","value":"","family":"","comment":""},"20":{"value":"16372","family_comment":"","value_unclear":false,"family_hidden":false,"family_unclear":false,"comment_unclear":false,"comment":"","family":""}},"vehicle":{"35":[{"brand_info":"1195.39 кВт","sum_rent_comment":"","brand_info_unclear":false,"year":"2000","sum_rent_unclear":false,"brand_info_hidden":false,"sum_rent_comment_unclear":false,"sum_hidden":false,"sum_rent":"","sum":"","brand":"ЗАЗ 110216","sum_comment":"","brand_unclear":false,"brand_hidden":false},{"brand_info":"1598.77.28 кВт","sum_rent_comment":"","brand":"Opel Astra","sum_comment":"","year":"2008","brand_info_unclear":false,"year_unclear":false,"sum":"","sum_rent":""}],"39":[{"brand_info":"причіп (саморобний","sum_rent_comment":"","brand":"Одісей-5","sum_comment":"","brand_unclear":false,"year":"2009","brand_info_unclear":false,"sum":"","sum_rent":""}]},"id":"vulyk_72_110","banks":{"45":[{"sum_foreign_comment":"","sum_units":"UAH","sum_comment":"","sum_comment_unclear":false,"sum_hidden":false,"sum_foreign_units":"UAH","sum_comment_hidden":false,"sum_unclear":false,"sum":"112566","sum_foreign":""}],"46":[{"sum_foreign_comment":"","sum_units":"UAH","sum_comment":"","sum_hidden":false,"sum_foreign_units":"UAH","sum_comment_hidden":false,"sum_unclear":false,"sum":"112566","sum_foreign":""}]},"declaration":{"additional_info_text":"","notfull_lostpages":"","date":"2015-03-23T00:00:00","notfull":"","additional_info":"","url":"http://static.declarations.com.ua/declarations/chosen_ones/epic_batch/koverznev_vadym_oleksandrovych.pdf"},"liabilities":{"54":{"sum_foreign_comment":"","sum":"","sum_comment":"","sum_comment_hidden":false,"sum_unclear":false,"sum_foreign":""},"55":{"sum_foreign_comment":"","sum":"","sum_comment":"","sum_foreign":""},"56":{"sum_foreign_comment":"","sum":"","sum_hidden":false,"sum_comment":"","sum_foreign":""},"57":{"sum_foreign_comment":"","sum":"16372","sum_comment":"","sum_comment_unclear":false,"sum_hidden":false,"sum_comment_hidden":false,"sum_unclear":false,"sum_foreign":""},"58":{"sum_foreign_comment":"","sum":"","sum_comment":"","sum_comment_unclear":false,"sum_hidden":false,"sum_comment_hidden":false,"sum_unclear":false,"sum_foreign":""},"59":{"sum_foreign_comment":"","sum_foreign_hidden":false,"sum_comment":"","sum_foreign_unclear":false,"sum_comment_hidden":false,"sum":"","sum_foreign":""},"60":{"sum_foreign_comment":"","sum_foreign_hidden":false,"sum_comment":"","sum_hidden":false,"sum":"","sum_foreign":""},"61":{"sum_foreign_comment":"","sum_foreign_hidden":false,"sum_comment":"","sum_hidden":false,"sum":"","sum_foreign":""},"62":{"sum_foreign_comment":"","sum_foreign_hidden":false,"sum_comment":"","sum_hidden":false,"sum":"","sum_foreign":""},"63":{"sum_foreign_comment":"","sum_foreign_hidden":false,"sum_comment":"","sum_comment_unclear":false,"sum_hidden":false,"sum_comment_hidden":false,"sum_unclear":false,"sum":"","sum_foreign":""},"64":{"sum_foreign_comment":"","sum_foreign_hidden":false,"sum_comment":"","sum_hidden":false,"sum":"","sum_foreign":""}},"ft_src":"16372\nЧернігів\nЧернігівська область\nзаступник голови деснянського районного суду м. чернігова\nЧернігівська область\nЗагальний місцевий суд\nВадим\nКоверзнева І. Л\nПодружжя\nКоверзнева Ю. В\nДитина\nОлександрович\nКоверзнев\nКоверзнев Вадим Олександрович\nКоверзнев Вадим Олександрович\nВадим Олександрович Коверзнев\nВадим Коверзнев\nКоверзнев Вадим Олександрович\n2009\nОдісей-5\nпричіп (саморобний\n1195.39 кВт\nЗАЗ 110216\n2000\n2008\n1598.77.28 кВт\nOpel Astra\n41.7\n3760\n108\nсарай\n41.7\n287\n44.4\n80\n112566\n112566\n2014\n1195.39 кВт\nЗАЗ 110216\n2000\n1598.77.28 кВт\nOpel Astra\n2008\nпричіп (саморобний\nОдісей-5\n2009\n41.7\n44.4\n41.7\nсарай\n287\n3760\n108\n80\nПодружжя\nКоверзнева І. Л\nДитина\nКоверзнева Ю. В\nКоверзнев Вадим Олександрович\nВадим Олександрович Коверзнев\nВадим Коверзнев\nКоверзнев Вадим Олександрович\nВадим\nКоверзнев Вадим Олександрович\nКоверзнев\nЧернігівська область\nЗагальний місцевий суд\nзаступник голови деснянського районного суду м. чернігова\nОлександрович\nЧернігів\nЧернігівська область\n16372\n9503.77\nЧернігівський національний технологічний університет\n238786.8\n67694.9\n16372\n276351\n67800.9\n11688.44\n106\n112566\n112566\n2014\n16372\n67694.9\n238786.8\n11688.44\n106\nЧернігівський національний технологічний університет\n9503.77\n67800.9\n276351\n16372\nКоверзнева І. Л\nПодружжя\nКоверзнева Ю. В\nДитина\nОлександрович\nКоверзнев\nКоверзнев Вадим Олександрович\nВадим Олександрович Коверзнев\nВадим Коверзнев\nКоверзнев Вадим Олександрович\nЧернігівська область\nЧернігів\nЧернігівська область\nЗагальний місцевий суд\nзаступник голови деснянського районного суду м. чернігова\nКоверзнев Вадим Олександрович\nВадим\n2009\nпричіп (саморобний\nОдісей-5\n2000\nЗАЗ 110216\n1195.39 кВт\n2008\n1598.77.28 кВт\nOpel Astra\n106\n11688.44\n16372\n276351\n67800.9\n9503.77\nЧернігівський національний технологічний університет\n238786.8\n67694.9\n80\n287\n108\n41.7\n44.4\nсарай\n41.7\n3760\n112566\n112566\n2014","general":{"inn":"","name":"Вадим","patronymic_unclear":false,"family":[{"inn":"","inn_hidden":true,"relations_unclear":false,"relations_hidden":false,"relations_other":"","relations":"Подружжя","name_hidden":true,"inn_unclear":false,"family_name":"Коверзнева І. Л","name_unclear":false},{"inn":"","inn_hidden":true,"relations_hidden":false,"family_name":"Коверзнева Ю. В","relations_other":"","relations":"Дитина","name_hidden":false,"name_unclear":false}],"patronymic":"Олександрович","inn_hidden":true,"family_raw":"","inn_unclear":false,"post":{"post_unclear":false,"region_unclear":false,"post":"заступник голови деснянського районного суду м. чернігова","candidate":"","office_hidden":false,"region":"Чернігівська область","post_hidden":false,"office":"Загальний місцевий суд","office_unclear":false,"region_hidden":false},"last_name_unclear":false,"full_name":"Коверзнев Вадим Олександрович","addresses":[{"place_city_type_hidden":false,"place_district_hidden":false,"place_city_type":"Місто","place_city_hidden":false,"place_address_unclear":false,"place_address":"","place":"Чернігівська область","place_district":"","place_unclear":false,"place_city":"Чернігів","place_city_unclear":false,"place_hidden":false,"place_address_hidden":true,"place_district_unclear":false}],"last_name":"Коверзнев","patronymic_hidden":false,"full_name_suggest":{"output":"Коверзнев Вадим Олександрович","input":["Коверзнев Вадим Олександрович","Вадим Олександрович Коверзнев","Вадим Коверзнев"]},"name_unclear":false},"source":"VULYK","estate":{"23":[{"space_hidden":false,"costs":"","costs_rent_unclear":false,"costs_comment":"","costs_hidden":false,"address_hidden":false,"region_hidden":true,"space_comment":"","space_unclear":false,"space":"287","address":"","region":"","address_unclear":false,"costs_rent_comment":"","costs_rent_hidden":false,"space_units":"м²","space_units_hidden":false,"costs_rent":""}],"24":[{"space_hidden":false,"costs":"","costs_comment":"","address_hidden":false,"region_hidden":true,"space_comment":"","space":"108","address":"","region":"","address_unclear":false,"costs_rent_comment":"","space_units":"м²","costs_rent":""}],"27":[{"space_unclear":false,"costs":"","costs_comment":"","address_hidden":false,"region_hidden":true,"space_comment":"","space":"41.7","address":"","region":"","address_unclear":false,"costs_rent_comment":"","space_units":"м²","costs_rent":""}],"28":[{"space_hidden":false,"costs":"","costs_comment":"","address_hidden":false,"region_hidden":false,"space_comment":"сарай","space_unclear":false,"space":"41.7","address":"","region":"","costs_rent_comment":"","space_units":"м²","costs_rent":""}],"29":[{"space_hidden":false,"costs_property_comment":"","address_hidden":false,"region_hidden":true,"space_comment":"","space_unclear":false,"space":"3760","address":"","region":"","costs_property":"","costs_rent_comment":"","address_unclear":false,"space_units":"м²","space_units_unclear":false,"costs_rent":""}],"30":[{"region_unclear":false,"space_unclear":false,"address_hidden":false,"region_hidden":true,"space_comment":"","space_hidden":false,"space":"44.4","address":"","region":"","costs_property":"","costs_rent_comment":"","space_units":"м²","costs_property_comment":"","costs_rent":""}],"31":[{"space_unclear":false,"address_hidden":false,"region_hidden":true,"space_comment":"","space_units_hidden":false,"space_hidden":false,"space":"80","address":"","region":"","address_unclear":false,"costs_rent_comment":"","costs_property":"","space_units":"м²","costs_property_comment":"","costs_rent":""}]},"intro":{"declaration_year":"2014","isnotdeclaration":"","declaration_year_unclear":false}}