{"income":{"5":{"value":"204240","family_comment":"","value_unclear":false,"comment_hidden":false,"family_hidden":false,"value_hidden":false,"family_unclear":false,"family":"43056","comment":""},"6":{"value":"189859","family_comment":"","comment_unclear":false,"family_hidden":false,"family_unclear":false,"value_unclear":false,"comment":"","family":"40815"},"7":{"source_name_unclear":false,"value":"","value_hidden":false,"family_comment":"","source_name":"Ленінський районний суд м. Донецьк, ТОВ 'СДС - Донецьк', ТОВ 'БІТА Едвертайзінг'","family":"","comment":"","source_name_hidden":false},"8":{"value":"","family_hidden":false,"value_hidden":false,"family_comment":"","family":"","comment":""},"9":{"value":"","family_comment":"","value_unclear":false,"family_hidden":false,"value_hidden":false,"family_unclear":false,"family":"","comment":""},"10":{"family_comment":"","value":"12180","family":"","comment":""},"11":{"family_comment":"","value":"","family":"","comment":""},"12":{"family_comment":"","value":"","family":"","comment":""},"13":{"family_comment":"","value":"","family":"","comment":""},"14":{"family_comment":"","value":"","family":"","comment":""},"15":{"family_comment":"","value":"1700","family":"","comment":""},"16":{"value":"","family_comment":"","value_unclear":false,"family_unclear":false,"family":"","comment":""},"17":{"family_comment":"","value":"","family":"","comment":""},"18":{"family_comment":"","value":"","family":"","comment":""},"19":{"family_comment":"","value":"","comment_unclear":false,"family":"","comment":""},"20":{"value":"501","family_comment":"","comment_unclear":false,"comment_hidden":false,"family_hidden":false,"value_hidden":false,"family_unclear":false,"value_unclear":false,"family":"2241","comment":"","family_comment_unclear":false}},"vehicle":{"35":[{"brand_info":"1591","sum_rent_comment":"","brand":"Hyundai Elantra","sum_comment":"","brand_unclear":false,"year":"2010","brand_info_unclear":false,"sum":"","sum_rent":""}],"40":[{"brand_info":"1399 куб.см.","sum_rent_comment":"","brand":"Hyundai Accent","sum_comment":"","brand_unclear":false,"year":"2008","brand_info_unclear":false,"year_unclear":false,"sum":"","sum_rent":""}]},"id":"vulyk_63_115","declaration":{"additional_info_text":"","notfull_lostpages":"","date":"2015-03-27T00:00:00","notfull":"","additional_info":"","url":"http://static.declarations.com.ua/declarations/chosen_ones/mega_batch/shestopalova_iana_volodymyrivna.pdf"},"liabilities":{"54":{"sum_foreign_comment":"","sum":"","sum_comment":"","sum_unclear":false,"sum_foreign":""},"55":{"sum_foreign_comment":"","sum":"","sum_comment":"","sum_foreign":""},"56":{"sum_foreign_comment":"","sum":"","sum_comment":"","sum_unclear":false,"sum_foreign":""},"57":{"sum_foreign_comment":"","sum":"7800","sum_comment":"","sum_comment_hidden":false,"sum_unclear":false,"sum_foreign":""},"58":{"sum_foreign_comment":"","sum_comment":"","sum":"","sum_comment_hidden":false,"sum_foreign":""},"59":{"sum_foreign_comment":"","sum":"","sum_comment":"","sum_foreign":""},"60":{"sum_foreign_comment":"","sum":"","sum_comment":"","sum_comment_unclear":false,"sum_foreign":""},"61":{"sum_foreign_comment":"","sum":"","sum_comment":"","sum_unclear":false,"sum_foreign":""},"62":{"sum_foreign_comment":"","sum":"","sum_comment":"","sum_unclear":false,"sum_foreign":""},"63":{"sum_foreign_comment":"","sum":"","sum_comment":"","sum_hidden":false,"sum_comment_hidden":false,"sum_unclear":false,"sum_foreign":""},"64":{"sum_foreign_comment":"","sum_comment":"","sum":"","sum_comment_hidden":false,"sum_foreign":""}},"ft_src":"2010\nHyundai Elantra\n1591\n1399 куб.см.\nHyundai Accent\n2008\nм. Донецьк\nДонецька область\n63\n2014\n40815\n189859\n1700\n12180\nЛенінський районний суд м. Донецьк, ТОВ 'СДС - Донецьк', ТОВ 'БІТА Едвертайзінг'\n43056\n204240\n2241\n501\n1591\n2010\nHyundai Elantra\n1399 куб.см.\n2008\nHyundai Accent\n63\nДонецька область\nм. Донецьк\nВолодимирівна\nШестопалова Яна Володимирівна\nЯна Володимирівна Шестопалова\nЯна Шестопалова\nШестопалова Яна Володимирівна\nЯна\nПодружжя\nШестопалов С. В\nДитина\nШестопалова А. С\nБатьки\nПершакова О. В\nШестопалова Яна Володимирівна\nЗагальний місцевий суд\nДонецька область\nсуддя ленінського районного суду м. донецька\nШестопалова\nЖитомирська область\n7800\nЛенінський районний суд м. Донецьк, ТОВ 'СДС - Донецьк', ТОВ 'БІТА Едвертайзінг'\n189859\n40815\n501\n2241\n1700\n204240\n43056\n12180\n2014\n7800\nПодружжя\nШестопалов С. В\nДитина\nШестопалова А. С\nБатьки\nПершакова О. В\nВолодимирівна\nШестопалова\nШестопалова Яна Володимирівна\nЯна Володимирівна Шестопалова\nЯна Шестопалова\nШестопалова Яна Володимирівна\nЯна\nЖитомирська область\nДонецька область\nсуддя ленінського районного суду м. донецька\nЗагальний місцевий суд\nШестопалова Яна Володимирівна","general":{"name_hidden":false,"name":"Яна","patronymic_unclear":false,"last_name_hidden":false,"inn":"","last_name":"Шестопалова","family":[{"inn":"","inn_hidden":true,"relations_unclear":false,"relations_hidden":false,"relations_other":"","relations":"Подружжя","name_hidden":false,"inn_unclear":false,"family_name":"Шестопалов С. В","name_unclear":false},{"inn":"","relations":"Дитина","relations_unclear":false,"family_name":"Шестопалова А. С","inn_hidden":true,"relations_other":"","name_hidden":false,"inn_unclear":false,"name_unclear":false},{"inn":"","relations":"Батьки","inn_unclear":false,"family_name":"Першакова О. В","inn_hidden":true,"relations_other":"","name_hidden":false,"name_unclear":false}],"inn_hidden":true,"family_raw":"","inn_unclear":false,"post":{"post_unclear":false,"region_unclear":false,"post":"суддя ленінського районного суду м. донецька","office_hidden":false,"region":"Донецька область","region_hidden":false,"office":"Загальний місцевий суд","office_unclear":false},"full_name_suggest":{"output":"Шестопалова Яна Володимирівна","input":["Шестопалова Яна Володимирівна","Яна Володимирівна Шестопалова","Яна Шестопалова"]},"full_name":"Шестопалова Яна Володимирівна","addresses":[{"place_city_type_unclear":false,"place_city_type_hidden":false,"place_district_hidden":true,"place_city_type":"","place_address_hidden":true,"place_address_unclear":false,"place_address":"","place":"Житомирська область","place_district":"","place_unclear":false,"place_hidden":false,"place_city_unclear":false,"place_city_hidden":true,"place_city":"","place_district_unclear":false}],"patronymic":"Володимирівна","last_name_unclear":false,"name_unclear":false},"source":"VULYK","estate":{"31":[{"space_hidden":false,"costs_property_hidden":false,"address_hidden":false,"region_hidden":false,"space_comment":"","space_unclear":false,"space":"63","address":"м. Донецьк","costs_property_comment_hidden":false,"region":"Донецька область","costs_property":"","space_units_unclear":false,"costs_rent_hidden":false,"space_comment_unclear":false,"costs_rent_comment_hidden":false,"space_units":"м²","costs_property_comment":"","costs_rent":"","costs_rent_comment":""}]},"intro":{"declaration_year":"2014","isnotdeclaration":"","declaration_year_unclear":false}}