{"id":"vulyk_100_150","ft_src":"RX 270 X01, 2700\nSsangYong Rexton\n2008\n48.7\n2014\n243083\n13398\nНаціональна школа суддів України, Національний університет 'Одеська юридична академія'\n15647.27\n258730.27\nRX 270 X01, 2700\nSsangYong Rexton\n2008\n48.7\nДитина\nРоманенко С. С\nСтаніславівна\nСєвєрова\nСєвєрова Єлєна Станіславівна\nЄлєна Станіславівна Сєвєрова\nЄлєна Сєвєрова\nСєвєрова Єлєна Станіславівна\nСєвєрова Єлєна Станіславівна\nЄлєна\nЗагальний апеляційний суд\nОдеська область\nсуддя апеляційного суду одеської області\n15647.27\nНаціональна школа суддів України, Національний університет 'Одеська юридична академія'\n243083\n258730.27\n13398\n2014\nРоманенко С. С\nДитина\nСтаніславівна\nСєвєрова\nОдеська область\nЗагальний апеляційний суд\nсуддя апеляційного суду одеської області\nСєвєрова Єлєна Станіславівна\nСєвєрова Єлєна Станіславівна\nЄлєна Станіславівна Сєвєрова\nЄлєна Сєвєрова\nСєвєрова Єлєна Станіславівна\nЄлєна","estate":{"25":[{"address":"","space_units":"м²","costs_comment":"","space_unclear":false,"region_hidden":true,"space_comment":"","address_hidden":false,"costs":"","address_unclear":false,"space_comment_unclear":false,"costs_comment_unclear":false,"costs_rent_comment":"","space":"48.7","region":"","costs_rent":""}]},"vehicle":{"35":[{"brand_info":"RX 270 X01, 2700","sum_rent_comment":"","brand_unclear":false,"sum_rent_comment_unclear":false,"brand_hidden":false,"sum_comment":"","brand_info_hidden":false,"sum_rent":"","brand":"SsangYong Rexton","brand_info_unclear":false,"year":"2008","sum":""}]},"source":"VULYK","income":{"5":{"family_comment":"","family":"","comment":"","value_unclear":false,"family_unclear":false,"value":"258730.27"},"6":{"family_comment":"","value":"243083","family":"","comment":"","value_unclear":false},"7":{"family_comment":"","comment":"","family":"","value_unclear":false,"value":"15647.27","source_name":"Національна школа суддів України, Національний університет 'Одеська юридична академія'"},"8":{"family_comment":"","value":"","family":"","comment":""},"9":{"family_comment":"","family":"","comment":"","value_unclear":false,"family_unclear":false,"value":""},"10":{"family_comment":"","comment_unclear":false,"value":"13398","family":"","comment":""},"11":{"family_comment":"","value":"","family":"","comment":""},"12":{"family_comment":"","value":"","family":"","comment":""},"13":{"family_comment":"","value":"","family":"","comment":"","value_unclear":false},"14":{"family_comment":"","value":"","family":"","comment":""},"15":{"family_comment":"","value":"","family":"","comment":""},"16":{"family_comment":"","value":"","family_unclear":false,"family":"","comment":""},"17":{"family_comment":"","value":"","family_unclear":false,"family":"","comment":""},"18":{"family_comment":"","value":"","family":"","comment":""},"19":{"family_comment":"","value":"","family":"","comment":""},"20":{"family":"","family_comment":"","comment":"","value_hidden":false,"value_unclear":false,"value":"","comment_unclear":false,"family_unclear":false,"family_hidden":false}},"general":{"inn":"","addresses":[{"place_city_type":"","place_city_type_hidden":false,"place_hidden":true,"place_city_hidden":false,"place_district_hidden":false,"place_district":"","place_city_unclear":false,"place":"","place_city":"","place_address_hidden":true,"place_address":""}],"last_name":"Сєвєрова","full_name":"Сєвєрова Єлєна Станіславівна","family":[{"inn":"","family_name":"Романенко С. С","name_unclear":false,"inn_hidden":false,"name_hidden":true,"relations":"Дитина"}],"patronymic":"Станіславівна","inn_hidden":true,"name":"Єлєна","post":{"post_hidden":false,"office":"Загальний апеляційний суд","post":"суддя апеляційного суду одеської області","office_unclear":false,"region_unclear":false,"region":"Одеська область","post_unclear":false},"family_raw":"","full_name_suggest":{"input":["Сєвєрова Єлєна Станіславівна","Єлєна Станіславівна Сєвєрова","Єлєна Сєвєрова"],"output":"Сєвєрова Єлєна Станіславівна"}},"liabilities":{"54":{"sum_comment":"","sum":"","sum_foreign_comment":"","sum_foreign":"","sum_unclear":false,"sum_comment_hidden":false},"55":{"sum_comment":"","sum_foreign_comment":"","sum_foreign":"","sum":""},"56":{"sum_comment":"","sum_foreign_comment":"","sum_foreign":"","sum_unclear":false,"sum":""},"57":{"sum_comment_unclear":false,"sum_comment":"","sum":"","sum_foreign_comment":"","sum_foreign":"","sum_unclear":false,"sum_comment_hidden":false},"58":{"sum_comment":"","sum":"","sum_foreign_comment":"","sum_foreign":"","sum_unclear":false,"sum_comment_hidden":false},"59":{"sum_comment":"","sum_foreign_comment":"","sum_foreign":"","sum":""},"60":{"sum_comment":"","sum_foreign_comment":"","sum_foreign":"","sum":"","sum_comment_hidden":false},"61":{"sum_comment":"","sum_foreign_comment":"","sum_foreign":"","sum":""},"62":{"sum_comment":"","sum_foreign_comment":"","sum_foreign":"","sum_unclear":false,"sum":""},"63":{"sum_comment":"","sum_foreign_comment":"","sum_foreign":"","sum":"","sum_comment_hidden":false},"64":{"sum_comment":"","sum_foreign_comment":"","sum_foreign":"","sum":"","sum_comment_hidden":false}},"declaration":{"notfull_lostpages":"","additional_info_text":"","additional_info":"","date":"2015-03-27T00:00:00","notfull":"","url":"http://static.declarations.com.ua/declarations/chosen_ones/judges_batch/4354_sievierova_ieliena_stanislavivna.pdf"},"intro":{"declaration_year":"2014"}}