{"income":{"5":{"family_comment":"","value":"400982","value_unclear":false,"family":"12000","comment":""},"6":{"family_comment":"","value":"366671","value_unclear":false,"family":"12000","comment":""},"7":{"source_name_unclear":false,"value":"19400","family_hidden":false,"value_hidden":false,"family_comment":"","source_name":"1. Академія Адвокатури України 2. Національна асаціація адвокатів України","family":"","comment":"","source_name_hidden":false},"8":{"value":"","family_hidden":false,"value_hidden":false,"family_comment":"","family":"","comment":""},"9":{"value":"","value_unclear":false,"value_hidden":false,"family_comment":"","comment_unclear":false,"comment":"","family":""},"10":{"value":"14911","family_hidden":false,"value_hidden":false,"family_comment":"","family":"","comment":""},"11":{"value":"","family_hidden":false,"value_hidden":false,"family_comment":"","family":"","comment":""},"12":{"value":"","family_hidden":false,"value_hidden":false,"family_comment":"","family":"","comment":""},"13":{"value":"","family_hidden":false,"value_hidden":false,"family_comment":"","family":"","comment":""},"14":{"value":"","family_hidden":false,"value_hidden":false,"family_comment":"","family":"","comment":""},"15":{"value":"","family_hidden":false,"value_hidden":false,"family_comment":"","family":"","comment":""},"16":{"value":"","family_hidden":false,"value_hidden":false,"family_comment":"","family":"","comment":""},"17":{"value":"","family_hidden":false,"value_hidden":false,"family_comment":"","family":"","comment":""},"18":{"value":"","comment_unclear":false,"family_hidden":false,"value_hidden":false,"family_comment":"","family":"","comment":""},"19":{"value":"","family_hidden":false,"value_hidden":false,"family_comment":"","family":"","comment":""},"20":{"value":"","value_unclear":false,"family_hidden":false,"value_hidden":false,"family_comment":"","comment_unclear":false,"comment":"","family":""}},"vehicle":{"35":[{"brand_info":"2.4 л","sum_rent_comment":"","sum_rent_hidden":false,"year":"2012","sum_hidden":false,"brand_info_unclear":false,"sum_rent":"","sum":"","brand":"Kia Sorento","sum_comment":"","brand_unclear":false,"sum_rent_comment_hidden":false,"sum_comment_hidden":false,"sum_unclear":false}]},"id":"vulyk_70_14","declaration":{"additional_info_text":"","notfull_lostpages":"","date":"2014-03-26T00:00:00","notfull":"","additional_info":"","url":"http://static.declarations.com.ua/declarations/chosen_ones/judges_batch/14_poshva_bohdan_mykolaiovych.pdf"},"liabilities":{"54":{"sum_foreign_comment":"","sum_foreign_hidden":false,"sum_comment":"","sum_hidden":false,"sum_foreign_comment_unclear":true,"sum_comment_hidden":false,"sum":"14500","sum_foreign":""},"55":{"sum_foreign_comment":"","sum":"","sum_hidden":false,"sum_comment":"","sum_foreign":""},"56":{"sum_foreign_comment":"","sum":"","sum_comment":"","sum_foreign":""},"57":{"sum_foreign_comment":"","sum_foreign_hidden":false,"sum_comment":"","sum_hidden":false,"sum_comment_hidden":false,"sum":"","sum_foreign":""},"58":{"sum_foreign_comment":"","sum":"","sum_comment":"","sum_hidden":false,"sum_comment_hidden":false,"sum_foreign":""},"59":{"sum_foreign_comment":"","sum_foreign_hidden":false,"sum_comment":"","sum_hidden":false,"sum":"","sum_foreign":""},"60":{"sum_foreign_comment":"","sum":"","sum_comment":"","sum_comment_unclear":false,"sum_hidden":false,"sum_comment_hidden":false,"sum_foreign":""},"61":{"sum_foreign_comment":"","sum":"","sum_hidden":false,"sum_comment":"","sum_foreign":""},"62":{"sum_foreign_comment":"","sum_foreign_hidden":false,"sum_comment":"","sum_comment_hidden":false,"sum_unclear":false,"sum":"","sum_foreign":""},"63":{"sum_foreign_comment":"","sum_foreign_hidden":false,"sum_comment":"","sum_hidden":false,"sum_comment_hidden":false,"sum":"","sum_foreign":""},"64":{"sum_foreign_comment":"","sum":"","sum_comment":"","sum_hidden":false,"sum_comment_hidden":false,"sum_foreign":""}},"ft_src":"14500\nсуддя верховного суду україни\nЗагальнодержавний регіон\nВерховний суд\nБогдан\nПошва З. О\nПодружжя\nМиколайович\nПошва\nПошва Богдан Миколайович\nПошва Богдан Миколайович\nБогдан Миколайович Пошва\nБогдан Пошва\nПошва Богдан Миколайович\nKia Sorento\n2.4 л\n2012\nприватизація\n1000\n2260\n122.8\n2013\n12000\n366671\n14911\n1. Академія Адвокатури України 2. Національна асаціація адвокатів України\n19400\n12000\n400982\n2.4 л\nKia Sorento\n2012\n2013\nПодружжя\nПошва З. О\nПошва Богдан Миколайович\nБогдан Миколайович Пошва\nБогдан Пошва\nПошва Богдан Миколайович\nБогдан\nПошва Богдан Миколайович\nМиколайович\nсуддя верховного суду україни\nВерховний суд\nЗагальнодержавний регіон\nПошва\n14500\n19400\n1. Академія Адвокатури України 2. Національна асаціація адвокатів України\n366671\n12000\n400982\n12000\n14911\n1000\nприватизація\n2260\n122.8\n14500\nПодружжя\nПошва З. О\nБогдан\nМиколайович\nПошва\nПошва Богдан Миколайович\nБогдан Миколайович Пошва\nБогдан Пошва\nПошва Богдан Миколайович\nЗагальнодержавний регіон\nВерховний суд\nсуддя верховного суду україни\nПошва Богдан Миколайович\n2012\nKia Sorento\n2.4 л\n14911\n12000\n400982\n19400\n1. Академія Адвокатури України 2. Національна асаціація адвокатів України\n12000\n366671\n122.8\nприватизація\n1000\n2260\n2013","general":{"inn":"","name":"Богдан","inn_unclear":false,"family":[{"inn":"","relations":"Подружжя","inn_unclear":false,"relations_hidden":false,"inn_hidden":true,"relations_other":"","name_hidden":false,"family_name":"Пошва З. О","name_unclear":false}],"inn_hidden":true,"family_raw":"","last_name":"Пошва","post":{"post":"суддя верховного суду україни","region":"Загальнодержавний регіон","candidate":"","office_hidden":false,"post_hidden":false,"office":"Верховний суд","region_hidden":false},"last_name_unclear":false,"full_name":"Пошва Богдан Миколайович","addresses":[{"place_city_type_unclear":false,"place_address":"","place_district_hidden":true,"place_city_type":"","place_address_hidden":true,"place_address_unclear":false,"place_city_type_hidden":true,"place":"","place_district":"","place_unclear":false,"place_city":"","place_city_unclear":false,"place_hidden":true,"place_city_hidden":true,"place_district_unclear":false}],"patronymic":"Миколайович","full_name_suggest":{"output":"Пошва Богдан Миколайович","input":["Пошва Богдан Миколайович","Богдан Миколайович Пошва","Богдан Пошва"]},"name_unclear":false},"source":"VULYK","estate":{"23":[{"region_unclear":false,"space_unclear":false,"costs":"","costs_comment":"","costs_hidden":false,"address_hidden":false,"region_hidden":true,"space_comment":"приватизація","space_hidden":false,"space_units_unclear":false,"address":"","costs_comment_unclear":false,"region":"","address_unclear":false,"space":"1000","costs_rent_hidden":false,"costs_rent_comment_hidden":false,"space_units":"м²","costs_comment_hidden":false,"costs_rent":"","costs_rent_comment":""}],"25":[{"region_unclear":false,"space_unclear":false,"costs":"","costs_comment":"","costs_hidden":false,"address_hidden":false,"region_hidden":true,"space_comment":"","space":"122.8","address":"","costs_rent_comment_unclear":false,"region":"","costs_rent_comment":"","costs_rent_hidden":false,"space_comment_unclear":false,"costs_rent_comment_hidden":false,"space_units":"м²","costs_comment_hidden":false,"costs_rent":"","costs_unclear":false}],"29":[{"space_unclear":false,"costs_property_hidden":false,"address_hidden":false,"region_hidden":true,"space_comment":"","space_hidden":false,"space":"2260","address":"","region":"","costs_property":"","costs_rent_comment":"","costs_rent_hidden":false,"space_comment_hidden":false,"space_units":"м²","costs_property_comment":"","costs_rent":""}]},"intro":{"declaration_year":"2013","isnotdeclaration":"","declaration_year_unclear":false,"declaration_year_hidden":false}}