{"income":{"5":{"family_comment":"","value":"225013","value_unclear":false,"family":"","comment":""},"6":{"value":"225013","value_unclear":false,"family_hidden":false,"family_comment":"","family":"","comment":""},"7":{"source_name_unclear":false,"value":"","family_comment":"","source_name":"","family":"","comment":""},"8":{"family_comment":"","value":"","family":"","comment":""},"9":{"family_comment":"","value":"","family":"","comment":""},"10":{"family_comment":"","value":"","family":"","comment":""},"11":{"family_comment":"","value":"","comment_unclear":false,"family":"","comment":""},"12":{"family_comment":"","value":"","family":"","comment":""},"13":{"family_comment":"","value":"","family":"","comment":""},"14":{"family_comment":"","value":"","family":"","comment":""},"15":{"family_comment":"","value":"","family":"","comment":""},"16":{"family_comment":"","value":"","family":"","comment":""},"17":{"family_comment":"","value":"","family":"","comment":""},"18":{"family_comment":"","value":"","family":"","comment":""},"19":{"family_comment":"","value":"","family":"","comment":""},"20":{"value":"","family_comment":"","value_unclear":false,"family_unclear":false,"comment_unclear":false,"comment":"","family":""}},"vehicle":{"35":[{"brand_info":"2.0 куб. дм.","sum_rent_comment":"","brand":"Nissan Qashqai","sum_comment":"","brand_unclear":false,"year":"2010","sum_rent_unclear":false,"brand_info_hidden":false,"brand_info_unclear":false,"sum":"","sum_rent":""}]},"id":"vulyk_101_171","declaration":{"additional_info_text":"","notfull_lostpages":"","date":"2016-03-31T00:00:00","notfull":"","additional_info":"","url":"http://static.declarations.com.ua/declarations/chosen_ones/judges_batch/886_kolodii_nataliia_anatoliivna_2015.pdf"},"liabilities":{"54":{"sum_foreign_comment":"","sum":"","sum_comment":"","sum_comment_unclear":false,"sum_hidden":false,"sum_comment_hidden":true,"sum_unclear":false,"sum_foreign":""},"55":{"sum_foreign_comment":"","sum":"","sum_comment":"","sum_foreign":""},"56":{"sum_foreign_comment":"","sum":"","sum_comment":"","sum_comment_hidden":false,"sum_unclear":false,"sum_foreign":""},"57":{"sum_foreign_comment":"","sum":"636334","sum_comment":"","sum_hidden":false,"sum_comment_hidden":false,"sum_unclear":false,"sum_foreign":""},"58":{"sum_foreign_comment":"","sum":"5048","sum_comment":"","sum_comment_unclear":false,"sum_hidden":false,"sum_comment_hidden":false,"sum_unclear":false,"sum_foreign":""},"59":{"sum_foreign_comment":"","sum":"","sum_comment":"","sum_foreign":""},"60":{"sum_foreign_comment":"","sum":"","sum_comment":"","sum_hidden":false,"sum_comment_hidden":false,"sum_unclear":false,"sum_foreign":""},"61":{"sum_foreign_comment":"","sum":"","sum_comment":"","sum_foreign":""},"62":{"sum_foreign_comment":"","sum":"","sum_comment":"","sum_comment_unclear":false,"sum_foreign":""},"63":{"sum_foreign_comment":"","sum_comment_hidden":false,"sum":"","sum_comment":"","sum_foreign":""},"64":{"sum_foreign_comment":"","sum_comment_hidden":false,"sum":"","sum_comment":"","sum_foreign":""}},"ft_src":"636334\n5048\nсуддя господарського суду запорізької області\nЗапорізька область\nГосподарський місцевий суд\nНаталія\nКолодій Анна Костянтинівна\nДитина\nКолодій Яна Костянтинівна\nДитина\nАнатоліївна\nКолодій Наталія Анатоліївна\nКолодій\nКолодій Наталія Анатоліївна\nНаталія Анатоліївна Колодій\nНаталія Колодій\nКолодій Наталія Анатоліївна\nNissan Qashqai\n2.0 куб. дм.\n2010\n22.1\n79.4\n605000\n2015\n225013\n225013\nNissan Qashqai\n2.0 куб. дм.\n2010\n2015\nДитина\nКолодій Анна Костянтинівна\nДитина\nКолодій Яна Костянтинівна\nКолодій Наталія Анатоліївна\nНаталія Анатоліївна Колодій\nНаталія Колодій\nКолодій Наталія Анатоліївна\nНаталія\nКолодій Наталія Анатоліївна\nАнатоліївна\nГосподарський місцевий суд\nсуддя господарського суду запорізької області\nЗапорізька область\nКолодій\n5048\n636334\n225013\n225013\n22.1\n605000\n79.4\n5048\n636334\nКолодій Анна Костянтинівна\nДитина\nКолодій Яна Костянтинівна\nДитина\nНаталія\nАнатоліївна\nКолодій\nКолодій Наталія Анатоліївна\nНаталія Анатоліївна Колодій\nНаталія Колодій\nКолодій Наталія Анатоліївна\nсуддя господарського суду запорізької області\nГосподарський місцевий суд\nЗапорізька область\nКолодій Наталія Анатоліївна\n2010\nNissan Qashqai\n2.0 куб. дм.\n225013\n225013\n605000\n79.4\n22.1\n2015","general":{"inn":"","name":"Наталія","inn_unclear":false,"family":[{"inn":"","relations":"Дитина","relations_other":"","inn_hidden":true,"family_name":"Колодій Анна Костянтинівна","name_hidden":false,"name_unclear":false},{"inn":"","relations":"Дитина","relations_unclear":false,"family_name":"Колодій Яна Костянтинівна","inn_hidden":true,"relations_other":"","name_hidden":false,"name_unclear":false}],"inn_hidden":true,"family_raw":"","last_name":"Колодій","post":{"region":"Запорізька область","region_unclear":false,"post":"суддя господарського суду запорізької області","office_unclear":false,"office":"Господарський місцевий суд"},"full_name":"Колодій Наталія Анатоліївна","addresses":[{"place_district":"","place_city_hidden":true,"place_city":"","place_city_type_hidden":false,"place_district_hidden":false,"place_city_type":"","place_address_hidden":true,"place_address":"","place_hidden":true,"place":""}],"patronymic":"Анатоліївна","patronymic_hidden":false,"full_name_suggest":{"output":"Колодій Наталія Анатоліївна","input":["Колодій Наталія Анатоліївна","Наталія Анатоліївна Колодій","Наталія Колодій"]}},"source":"VULYK","estate":{"24":[{"space_unclear":false,"costs":"","costs_comment":"","address_hidden":false,"region_hidden":true,"space_comment":"","space":"22.1","address":"","region":"","costs_rent_comment":"","space_units":"м²","costs_rent":""}],"25":[{"space_unclear":false,"costs":"605000","costs_comment":"","address_hidden":false,"region_hidden":true,"space_comment":"","space_hidden":false,"space":"79.4","address":"","region":"","costs_rent_comment":"","space_comment_unclear":false,"space_units":"м²","costs_rent":""}]},"intro":{"declaration_year":"2015"}}