{"id":"vulyk_61_26","ft_src":"м. Харків\nХарківська область\n43.7\n63.1\nХарківська область\nХарківська область\nм. Харків\n88.5\n2014\n191143.42\n12180\n19200\n203083.72\n19200\n63.1\nХарківська область\n43.7\nм. Харків\nХарківська область\n88.5\nм. Харків\nХарківська область\nПодружжя\nСиротникова Л. Б\nДитина\nСиротников Д. Р\nДитина\nСиротникова К. Р\nДитина\nСиротников Л. Р\nСиротников Роман Євгенович\nРоман Євгенович Сиротников\nРоман Сиротников\nСиротников Роман Євгенович\nРоман\nСиротников Роман Євгенович\nСиротников\nХарківська область\nЗагальний місцевий суд\nсуддя московського районного суду м. харкова\nЄвгенович\nХарків\nХарківська область\n45423.86\n14400\n10800\n18333.69\n191143.42\n19200\n203083.72\n19200\n12180\n2014\n18333.69\n45423.86\n14400\n10800\nСиротникова Л. Б\nПодружжя\nСиротников Д. Р\nДитина\nСиротникова К. Р\nДитина\nСиротников Л. Р\nДитина\nЄвгенович\nСиротников\nСиротников Роман Євгенович\nРоман Євгенович Сиротников\nРоман Сиротников\nСиротников Роман Євгенович\nХарківська область\nХарків\nХарківська область\nсуддя московського районного суду м. харкова\nЗагальний місцевий суд\nСиротников Роман Євгенович\nРоман","estate":{"25":[{"costs_unclear":false,"address":"м. Харків","space_units":"м²","space_hidden":false,"space_unclear":false,"region_hidden":false,"costs_comment":"","space_comment":"","space_comment_unclear":false,"costs":"","address_unclear":false,"address_hidden":false,"costs_comment_unclear":false,"costs_rent_comment":"","space":"88.5","region_unclear":false,"region":"Харківська область","costs_rent":""}],"30":[{"costs_property_comment":"","address":"","space_units":"м²","space_hidden":false,"space_comment":"","region_hidden":false,"costs_property":"","region":"Харківська область","space_comment_unclear":false,"space_comment_hidden":false,"address_unclear":false,"address_hidden":true,"costs_rent_comment":"","space":"63.1","space_units_hidden":false,"costs_rent":""}],"31":[{"costs_property_comment":"","address":"м. Харків","space_units":"м²","space_hidden":false,"space_unclear":false,"region_hidden":false,"costs_property":"","space_comment":"","address_hidden":false,"space_comment_unclear":false,"costs_rent_comment":"","space":"43.7","region":"Харківська область","costs_rent":""}]},"source":"VULYK","income":{"5":{"family_comment":"","comment":"","family":"19200","value_unclear":false,"family_unclear":false,"comment_unclear":false,"value":"203083.72","family_comment_unclear":false},"6":{"family_comment":"","family":"","comment":"","value_unclear":true,"family_unclear":false,"value":"191143.42"},"7":{"source_name_hidden":true,"family_comment":"","comment":"","family":"","value_unclear":false,"source_name_unclear":false,"value":"","source_name":""},"8":{"family_comment":"","value":"","family":"","comment":""},"9":{"family_comment":"","value":"","family":"","comment":""},"10":{"family_comment":"","value":"12180","family":"","comment":"","value_unclear":false},"11":{"family":"","family_comment":"","comment":"","value_hidden":false,"value_unclear":false,"value":""},"12":{"family":"19200","family_comment":"","value":"","comment":"","value_hidden":false},"13":{"family_comment":"","value":"","family":"","comment":""},"14":{"family_comment":"","value":"","family":"","comment":""},"15":{"family_comment":"","value":"","family":"","comment":""},"16":{"family_comment":"","value":"","family":"","comment":""},"17":{"family_comment":"","value":"","family":"","comment":""},"18":{"family_comment":"","value":"","family":"","comment":""},"19":{"family_comment":"","value":"","family_unclear":false,"family":"","comment":""},"20":{"family_comment":"","value":"","family_unclear":false,"family":"","comment":""}},"general":{"family":[{"inn":"","family_name":"Сиротникова Л. Б","relations_other":"","relations_hidden":false,"relations_unclear":false,"name_unclear":false,"inn_hidden":true,"name_hidden":false,"relations":"Подружжя"},{"inn":"","family_name":"Сиротников Д. Р","relations_other":"","name_unclear":false,"inn_hidden":false,"name_hidden":false,"relations":"Дитина"},{"inn":"","family_name":"Сиротникова К. Р","relations_other":"","name_unclear":false,"inn_hidden":false,"name_hidden":false,"relations":"Дитина"},{"inn":"","family_name":"Сиротников Л. Р","relations_other":"","name_unclear":false,"inn_hidden":false,"name_hidden":false,"relations":"Дитина"}],"family_raw":"","name":"Роман","full_name_suggest":{"input":["Сиротников Роман Євгенович","Роман Євгенович Сиротников","Роман Сиротников"],"output":"Сиротников Роман Євгенович"},"name_unclear":false,"patronymic":"Євгенович","inn_hidden":true,"patronymic_unclear":false,"patronymic_hidden":false,"inn":"","inn_unclear":false,"last_name":"Сиротников","full_name":"Сиротников Роман Євгенович","post":{"post_hidden":false,"office":"Загальний місцевий суд","post_unclear":true,"post":"суддя московського районного суду м. харкова","region_hidden":false,"region":"Харківська область","region_unclear":false,"office_hidden":false},"addresses":[{"place_city_type_hidden":false,"place_district_hidden":true,"place_address_unclear":false,"place":"Харківська область","place_city":"Харків","place_city_type":"Місто","place_city_hidden":false,"place_district":"","place_district_unclear":false,"place_address":"","place_address_hidden":true,"place_hidden":true}],"last_name_unclear":false},"liabilities":{"54":{"sum_comment_unclear":false,"sum_comment":"","sum":"","sum_foreign_comment":"","sum_foreign":"","sum_unclear":false},"55":{"sum_comment":"","sum_foreign_comment":"","sum_foreign":"","sum":""},"56":{"sum_comment":"","sum_foreign_comment":"","sum_foreign":"","sum_unclear":false,"sum":"14400"},"57":{"sum_comment":"","sum":"45423.86","sum_foreign_comment":"","sum_foreign":"","sum_unclear":false,"sum_comment_hidden":false},"58":{"sum_comment":"","sum_foreign_comment":"","sum_foreign":"","sum_unclear":false,"sum":"18333.69"},"59":{"sum_comment":"","sum_foreign_comment":"","sum_foreign":"","sum":""},"60":{"sum_comment":"","sum_hidden":false,"sum":"","sum_foreign_comment":"","sum_foreign":"","sum_foreign_hidden":false},"61":{"sum_comment":"","sum_foreign_comment":"","sum_foreign":"","sum":""},"62":{"sum_comment":"","sum_foreign_comment":"","sum_foreign":"","sum_unclear":false,"sum":"10800"},"63":{"sum_comment":"","sum_hidden":false,"sum":"","sum_foreign_comment":"","sum_foreign":"","sum_unclear":false},"64":{"sum_comment":"","sum_foreign_comment":"","sum_foreign":"","sum_hidden":false,"sum":""}},"declaration":{"notfull_lostpages":"","additional_info_text":"","additional_info":"","date":"2015-03-27T00:00:00","notfull":"","url":"http://static.declarations.com.ua/declarations/chosen_ones/mega_batch/syrotnykov_roman_ievhenovych.pdf"},"intro":{"declaration_year_hidden":false,"isnotdeclaration":"","declaration_year":"2014"}}