{"income":{"5":{"value":"229761","family_comment":"","value_unclear":false,"family_hidden":false,"value_hidden":false,"family_unclear":false,"family":"","comment":""},"6":{"family_comment":"","value":"217581","family":"","comment":"","value_hidden":false},"7":{"value":"","family_comment":"","source_name":"","family":"","comment":"","source_name_hidden":false},"8":{"value":"","family_hidden":false,"value_hidden":false,"family_comment":"","family":"","comment":""},"9":{"family_comment":"","value":"","value_unclear":false,"family":"","comment":""},"10":{"family_comment":"","value":"12180","family":"","comment":"","value_hidden":false},"11":{"family_comment":"","value":"","family":"","comment":""},"12":{"family_comment":"","value":"","family":"","comment":""},"13":{"family_comment":"","value":"","family":"","comment":""},"14":{"family_comment":"","value":"","family":"","comment":""},"15":{"family_comment":"","value":"","family":"","comment":""},"16":{"value":"","value_unclear":false,"family_hidden":false,"family_comment":"","family":"","comment":""},"17":{"value":"","family_hidden":false,"value_hidden":false,"family_comment":"","family":"","comment":""},"18":{"value":"","family_hidden":false,"value_hidden":false,"family_comment":"","family":"","comment":""},"19":{"family_comment":"","value":"","family":"","comment":""},"20":{"value":"","value_unclear":false,"comment_hidden":false,"value_hidden":false,"family_comment":"","comment_unclear":false,"comment":"","family":""}},"vehicle":{"35":[{"brand_info":"1500 куб. см., 119 кВт","sum_rent_comment":"","sum_rent_hidden":false,"year":"2004","brand_info_hidden":false,"brand_info_unclear":false,"sum_rent":"","sum":"2004","brand":"Nissan Almera","sum_comment":"","brand_unclear":false,"brand_hidden":false},{"year_hidden":false,"brand_info":"2000 куб. см., 180 кВт","sum_rent_comment":"","brand":"Nissan X-Trail","sum_comment":"","brand_unclear":false,"year":"2010","brand_hidden":false,"brand_info_unclear":false,"sum":"2010","sum_rent":""}],"41":[{"brand_info":"2900 куб. см.","sum_rent_comment":"","brand":"УАЗ 452-290","sum_comment":"","brand_unclear":false,"year":"2004","brand_hidden":true,"brand_info_unclear":false,"sum":"","sum_rent":""}]},"id":"vulyk_30_47","banks":{"45":[{"sum_foreign_comment":"","sum":"25000","sum_comment":"","sum_comment_unclear":false,"sum_hidden":false,"sum_foreign_units":"UAH","sum_foreign_hidden":false,"sum_units":"UAH","sum_comment_hidden":false,"sum_unclear":false,"sum_foreign":""},{"sum_foreign_comment":"","sum_units":"","sum_comment":"","sum_foreign_units":"","sum":"","sum_foreign":""},{"sum_foreign_comment":"","sum_units":"","sum_comment":"","sum_foreign_units":"","sum":"","sum_foreign":""}],"46":[{"sum_foreign_comment":"","sum_units":"UAH","sum_comment":"","sum_hidden":false,"sum_foreign_units":"UAH","sum_foreign_hidden":false,"sum_comment_hidden":false,"sum_unclear":false,"sum":"","sum_foreign":""},{"sum_foreign_comment":"","sum_units":"","sum_comment":"","sum_foreign_units":"","sum":"","sum_foreign":""}],"47":[{"sum_foreign_comment":"","sum_units":"UAH","sum_comment":"","sum_hidden":false,"sum_foreign_units":"UAH","sum":"","sum_foreign_hidden":false,"sum_foreign":""}],"48":[{"sum_foreign_comment":"","sum_units":"UAH","sum_comment":"","sum_hidden":false,"sum_foreign_units":"UAH","sum":"","sum_foreign_hidden":false,"sum_foreign":""}],"49":[{"sum_foreign_comment":"","sum_units":"UAH","sum_comment":"","sum_hidden":false,"sum_foreign_units":"UAH","sum":"","sum_foreign_hidden":false,"sum_foreign":""}],"50":[{"sum_foreign_comment":"","sum_units":"UAH","sum_comment":"","sum_hidden":false,"sum_foreign_units":"UAH","sum":"","sum_foreign_hidden":false,"sum_foreign":""}],"51":[{"sum_foreign_comment":"","sum_units":"UAH","sum_comment":"","sum_hidden":false,"sum_foreign_units":"UAH","sum_comment_hidden":true,"sum_unclear":false,"sum":"8000","sum_foreign":""},{"sum_foreign_comment":"","sum_units":"","sum_comment":"","sum_foreign_units":"","sum":"","sum_foreign":""}],"52":[{"sum_foreign_comment":"","sum_units":"UAH","sum_comment":"","sum_hidden":false,"sum_foreign_units":"UAH","sum":"","sum_foreign":""}],"53":[{"sum_foreign_comment":"","sum_units":"UAH","sum_comment":"","sum_foreign_units":"UAH","sum":"","sum_foreign":""}]},"declaration":{"additional_info_text":"","notfull_lostpages":"","date":"2015-03-30T00:00:00","notfull":"","additional_info":"","url":"http://static.declarations.com.ua/declarations/chosen_ones/mega_batch/shershak_mykola_ivanovych.pdf"},"liabilities":{"54":{"sum_foreign_comment":"","sum":"","sum_comment":"","sum_comment_unclear":false,"sum_comment_hidden":false,"sum_unclear":false,"sum_foreign":""},"55":{"sum_foreign_comment":"","sum_comment_hidden":false,"sum":"","sum_comment":"","sum_foreign":""},"56":{"sum_foreign_comment":"","sum":"","sum_comment":"","sum_comment_unclear":false,"sum_unclear":false,"sum_foreign":""},"57":{"sum_foreign_comment":"","sum_foreign_hidden":false,"sum_comment":"","sum_comment_unclear":false,"sum_hidden":false,"sum_comment_hidden":false,"sum_unclear":false,"sum":"","sum_foreign":""},"58":{"sum_foreign_comment":"","sum_foreign_hidden":false,"sum_comment":"","sum_comment_unclear":false,"sum_hidden":false,"sum_comment_hidden":false,"sum_unclear":false,"sum":"","sum_foreign":""},"59":{"sum_foreign_comment":"","sum_foreign_hidden":false,"sum_comment":"","sum_hidden":false,"sum":"","sum_foreign":""},"60":{"sum_foreign_comment":"","sum":"","sum_comment":"","sum_comment_hidden":false,"sum_unclear":false,"sum_foreign":""},"61":{"sum_foreign_comment":"","sum_comment_hidden":false,"sum":"","sum_comment":"","sum_foreign":""},"62":{"sum_foreign_comment":"","sum":"","sum_comment":"","sum_foreign":""},"63":{"sum_foreign_comment":"","sum_comment_hidden":false,"sum":"","sum_comment":"","sum_foreign":""},"64":{"sum_foreign_comment":"","sum_foreign_hidden":false,"sum_comment":"","sum_hidden":false,"sum":"","sum_foreign":""}},"ft_src":"заступник голови зарічного районного суду м. сум\nСумська область\nЗагальний місцевий суд\nМикола\nШершак Алла Андріївна\nПодружжя\nШершак Єва Миколаївна\nДитина\nІванович\nШершак Микола Іванович\nМикола Іванович Шершак\nМикола Шершак\nШершак Микола Іванович\nШершак Микола Іванович\nШершак\nСумська область\nУАЗ 452-290\n2900 куб. см.\n2004\n1500 куб. см., 119 кВт\n2004\nNissan Almera\n2004\nNissan X-Trail\n2010\n2000 куб. см., 180 кВт\n2010\n8000\n25000\n2014\n1500 куб. см., 119 кВт\n2004\nNissan Almera\n2004\n2000 куб. см., 180 кВт\n2010\n2010\nNissan X-Trail\n2900 куб. см.\n2004\nУАЗ 452-290\n25000\n8000\n0.2\n2006 рік придбання\nСумська область\n0.56\n2012 рік придбання\nСумська область\n148\nСумська область\nПодружжя\nШершак Алла Андріївна\nДитина\nШершак Єва Миколаївна\nШершак Микола Іванович\nМикола Іванович Шершак\nМикола Шершак\nШершак Микола Іванович\nШершак Микола Іванович\nМикола\nІванович\nЗагальний місцевий суд\nзаступник голови зарічного районного суду м. сум\nСумська область\nШершак\nСумська область\n217581\n229761\n12180\n2014\n2006 рік придбання\nСумська область\n0.2\n2012 рік придбання\n0.56\nСумська область\nСумська область\n148\nШершак Алла Андріївна\nПодружжя\nШершак Єва Миколаївна\nДитина\nІванович\nШершак\nМикола\nШершак Микола Іванович\nМикола Іванович Шершак\nМикола Шершак\nШершак Микола Іванович\nСумська область\nСумська область\nЗагальний місцевий суд\nзаступник голови зарічного районного суду м. сум\nШершак Микола Іванович\n217581\n12180\n229761\n2004\n2900 куб. см.\nУАЗ 452-290\nNissan Almera\n2004\n1500 куб. см., 119 кВт\n2004\n2010\n2010\nNissan X-Trail\n2000 куб. см., 180 кВт\n12180\n229761\n217581\n2006 рік придбання\nСумська область\n0.2\n2012 рік придбання\nСумська область\n0.56\nСумська область\n148\n25000\n8000\n2014","general":{"inn":"","name":"Микола","patronymic_unclear":false,"family":[{"inn":"","inn_hidden":true,"relations_hidden":false,"family_name":"Шершак Алла Андріївна","relations_other":"","relations":"Подружжя","name_hidden":false,"name_unclear":false},{"inn":"","relations":"Дитина","relations_unclear":false,"family_name":"Шершак Єва Миколаївна","inn_hidden":false,"relations_other":"","name_hidden":false,"name_unclear":false}],"patronymic":"Іванович","inn_hidden":true,"family_raw":"","inn_unclear":false,"post":{"post_unclear":false,"post":"заступник голови зарічного районного суду м. сум","candidate":"","office_hidden":false,"region":"Сумська область","post_hidden":false,"office":"Загальний місцевий суд","office_unclear":false},"full_name_suggest":{"output":"Шершак Микола Іванович","input":["Шершак Микола Іванович","Микола Іванович Шершак","Микола Шершак"]},"full_name":"Шершак Микола Іванович","addresses":[{"place_district":"","place_city_hidden":true,"place_city":"","place_city_unclear":false,"place_district_hidden":true,"place_city_type":"","place_address_hidden":true,"place_city_type_hidden":true,"place_address":"","place_hidden":false,"place":"Сумська область"}],"last_name":"Шершак","last_name_unclear":false,"name_unclear":false},"source":"VULYK","estate":{"23":[{"space_unclear":true,"costs":"","costs_comment":"","address_hidden":true,"region_hidden":false,"space_comment":"2006 рік придбання","space_hidden":false,"space":"0.2","address":"","region":"Сумська область","space_units_unclear":false,"space_units":"га","costs_rent":"","costs_rent_comment":""},{"space_unclear":false,"costs":"","costs_comment":"","address_hidden":false,"region_hidden":false,"space_comment":"2012 рік придбання","space":"0.56","address":"","costs_comment_unclear":true,"region":"Сумська область","space_units_unclear":false,"space_units":"га","costs_rent":"","costs_rent_comment":""},{"costs_rent":"","region":"","costs":"","costs_rent_comment":"","costs_comment":"","region_hidden":false,"space_comment":"","space_units":"","space":"","address":""},{"costs_rent":"","region":"","costs":"","costs_rent_comment":"","costs_comment":"","region_hidden":false,"space_comment":"","space_units":"","space":"","address":""},{"costs_rent":"","region":"","costs":"","costs_rent_comment":"","costs_comment":"","region_hidden":false,"space_comment":"","space_units":"","space":"","address":""},{"costs_rent":"","region":"","costs":"","costs_rent_comment":"","costs_comment":"","region_hidden":false,"space_comment":"","space_units":"","space":"","address":""},{"costs_rent":"","costs":"","costs_rent_comment":"","costs_comment":"","region_hidden":false,"space_comment":"","space_units":"","space":"","address":""}],"24":[{"region_unclear":false,"space_hidden":false,"costs":"","costs_comment":"","address_hidden":true,"region_hidden":false,"space_comment":"","space":"148","address":"","costs_comment_unclear":true,"region":"Сумська область","costs_rent_comment":"","space_units":"м²","costs_rent":""}],"25":[{"space_unclear":false,"costs":"","costs_comment":"","address_hidden":false,"region_hidden":true,"space_comment":"","space_hidden":false,"space":"","address":"","region":"","address_unclear":false,"costs_rent_comment":"","space_units":"м²","costs_rent":""}]},"intro":{"declaration_year":"2014","declaration_year_unclear":false,"declaration_year_hidden":false}}