{"income":{"5":{"value":"206870","family_comment":"","comment_unclear":false,"family_unclear":false,"value_unclear":false,"comment":"","family":"18199"},"6":{"family_comment":"","value":"206870","comment_unclear":false,"family":"","comment":""},"7":{"family_comment":"","value":"","source_name":"","family":"","comment":""},"8":{"family_comment":"","value":"","family":"","comment":""},"9":{"family_comment":"","value":"","value_unclear":false,"family":"","comment":""},"10":{"family_comment":"","value":"","value_unclear":false,"family":"","comment":""},"11":{"family_comment":"","value":"","family":"","comment":""},"12":{"family_comment":"","value":"","family":"","comment":""},"13":{"family_comment":"","value":"","family":"","comment":""},"14":{"family_comment":"","value":"","family":"","comment":""},"15":{"family_comment":"","value":"","family":"","comment":""},"16":{"family_comment":"","value":"","family":"","comment":""},"17":{"family_comment":"","value":"","value_unclear":false,"family":"","comment":""},"18":{"family_comment":"","value":"","value_unclear":false,"family":"","comment":""},"19":{"family_comment":"","value":"","family":"","comment":""},"20":{"value":"","family_comment":"пенсія","comment_unclear":false,"family_unclear":false,"value_unclear":false,"comment":"","family":"18199"}},"vehicle":{"35":[{"year_hidden":false,"brand_info":"1798 куб. см. 88 кВт","sum_rent_comment":"користування","year":"2008","sum_hidden":false,"brand_info_hidden":false,"brand_info_unclear":false,"year_unclear":false,"sum_rent":"","sum":"","brand":"Mazda 6","sum_comment":"","brand_unclear":false,"brand_hidden":false}]},"id":"vulyk_84_153","declaration":{"additional_info_text":"","notfull_lostpages":"","date":"2015-03-20T00:00:00","notfull":"","additional_info":"","url":"http://static.declarations.com.ua/declarations/chosen_ones/judges_batch/2567_postupailo_volodymyr_vasylovych.pdf"},"liabilities":{"54":{"sum_foreign_comment":"","sum_comment":"","sum":"","sum_comment_hidden":false,"sum_foreign":""},"55":{"sum_foreign_comment":"","sum":"","sum_comment":"","sum_foreign":""},"56":{"sum_foreign_comment":"","sum":"","sum_comment":"","sum_foreign":""},"57":{"sum_foreign_comment":"","sum_comment":"","sum":"","sum_comment_hidden":false,"sum_foreign":""},"58":{"sum_foreign_comment":"","sum_comment":"","sum":"","sum_comment_hidden":false,"sum_foreign":""},"59":{"sum_foreign_comment":"","sum":"","sum_comment":"","sum_foreign":""},"60":{"sum_foreign_comment":"","sum":"","sum_comment":"","sum_foreign":""},"61":{"sum_foreign_comment":"","sum":"","sum_comment":"","sum_foreign":""},"62":{"sum_foreign_comment":"","sum":"","sum_comment":"","sum_foreign":""},"63":{"sum_foreign_comment":"","sum_comment":"","sum":"","sum_comment_hidden":false,"sum_foreign":""},"64":{"sum_foreign_comment":"","sum_comment":"","sum":"","sum_comment_hidden":false,"sum_foreign":""}},"ft_src":"Mazda 6\n1798 куб. см. 88 кВт\nкористування\n2008\nКіровоградська область\nКіровоград\n37.18\nКіровоградська область\nкористування\nКіровоград\n42\nкористування\nКіровоград\n50.1\nКіровоградська область\n2014\n206870\n18199\n206870\n18199\nпенсія\n1798 куб. см. 88 кВт\nMazda 6\nкористування\n2008\n2014\nПоступайло Володимир Васильович\nВолодимир Васильович Поступайло\nВолодимир Поступайло\nПоступайло Володимир Васильович\nВолодимир\nПодружжя\nПоступайло К. Ю. 04. 06. 1983\nДитина\nПоступайло А. В. 14. 09. 2006\nПоступайло Володимир Васильович\nВасильович\nсуддя кіровського районного суд м. кіровограда\nЗагальний місцевий суд\nКіровоградська область\nПоступайло\nКіровоград\nКіровоградська область\n206870\n18199\nпенсія\n206870\n18199\nКіровоград\nКіровоградська область\n37.18\nкористування\n42\nКіровоградська область\nКіровоград\nКіровоград\n50.1\nкористування\nКіровоградська область\nПоступайло К. Ю. 04. 06. 1983\nПодружжя\nПоступайло А. В. 14. 09. 2006\nДитина\nВасильович\nПоступайло\nВолодимир\nПоступайло Володимир Васильович\nВолодимир Васильович Поступайло\nВолодимир Поступайло\nПоступайло Володимир Васильович\nКіровоградська область\nКіровоград\nКіровоградська область\nсуддя кіровського районного суд м. кіровограда\nЗагальний місцевий суд\nПоступайло Володимир Васильович","general":{"inn":"","name":"Володимир","last_name":"Поступайло","family":[{"inn":"","inn_hidden":false,"inn_unclear":false,"relations_hidden":false,"relations_other":"","relations":"Подружжя","name_hidden":false,"family_name":"Поступайло К. Ю. 04. 06. 1983","name_unclear":false},{"inn":"","inn_hidden":false,"family_name":"Поступайло А. В. 14. 09. 2006","relations_other":"","relations":"Дитина","name_hidden":false,"name_unclear":false}],"inn_hidden":true,"family_raw":"","inn_unclear":false,"post":{"post_unclear":false,"region_unclear":false,"post":"суддя кіровського районного суд м. кіровограда","candidate":"","office_hidden":false,"region":"Кіровоградська область","post_hidden":false,"office":"Загальний місцевий суд","office_unclear":false,"region_hidden":false},"full_name":"Поступайло Володимир Васильович","addresses":[{"place_city_type_unclear":false,"place_city_type_hidden":false,"place_district_hidden":false,"place_city_type":"Місто","place_address_hidden":false,"place_address_unclear":false,"place_address":"","place":"Кіровоградська область","place_district":"","place_unclear":false,"place_hidden":false,"place_city_unclear":false,"place_city_hidden":false,"place_city":"Кіровоград","place_district_unclear":false}],"patronymic":"Васильович","full_name_suggest":{"output":"Поступайло Володимир Васильович","input":["Поступайло Володимир Васильович","Володимир Васильович Поступайло","Володимир Поступайло"]}},"source":"VULYK","estate":{"25":[{"region_unclear":false,"space_hidden":false,"costs":"","costs_comment":"","address_hidden":false,"region_hidden":false,"space_comment":"користування","space":"42","address":"Кіровоград","costs_comment_unclear":false,"costs_rent_comment_unclear":false,"region":"Кіровоградська область","address_unclear":false,"costs_rent_comment":"","space_units":"м²","costs_rent":""},{"costs_rent":"","region":"Кіровоградська область","costs":"","costs_rent_comment":"","costs_comment":"","region_hidden":false,"space_comment":"користування","space_units":"м²","space":"50.1","address":"Кіровоград"}],"31":[{"space_unclear":false,"address_hidden":false,"region_hidden":false,"space_comment":"","space":"37.18","address":"Кіровоград","region":"Кіровоградська область","costs_property":"","costs_rent_comment":"","address_unclear":false,"space_units":"м²","costs_property_comment":"","costs_rent":""}]},"intro":{"declaration_year":"2014","isnotdeclaration":"","declaration_year_unclear":false}}