{"income":{"5":{"family_comment":"","value":"375826","value_unclear":false,"family":"25255","comment":""},"6":{"value":"279326","value_unclear":false,"family_hidden":false,"family_comment":"","family":"25255","comment":""},"7":{"source_name_unclear":false,"value":"","family_comment":"","source_name":"","family":"","comment":""},"8":{"family_comment":"","value":"","family":"","comment":""},"9":{"family_comment":"","value":"","family":"","comment":""},"10":{"family_comment":"","value":"","family":"","comment":""},"11":{"family_comment":"","value":"","comment_unclear":false,"family":"","comment":""},"12":{"family_comment":"","value":"","family":"","comment":""},"13":{"family_comment":"","value":"","family":"","comment":""},"14":{"family_comment":"","value":"","family":"","comment":""},"15":{"family_comment":"","value":"","family":"","comment":""},"16":{"family_comment":"","value":"","family":"","comment":""},"17":{"family_comment":"","value":"","family":"","comment":""},"18":{"family_comment":"","value":"","family":"","comment":""},"19":{"family_comment":"","value":"","family":"","comment":""},"20":{"value":"96500","family_comment":"","value_unclear":false,"family_unclear":false,"comment_unclear":false,"comment":"пенсія","family":""}},"vehicle":{"35":[{"brand_info":"1999 куб. см.","sum_rent_comment":"","brand":"Kia Magentis","sum_comment":"","brand_unclear":false,"year":"2006","sum_rent_unclear":false,"brand_info_hidden":false,"brand_info_unclear":false,"sum":"","sum_rent":""},{"brand_info":"1.2 куб. дм.","sum_rent_comment":"","brand":"ВАЗ 2101","sum_comment":"","year":"1981","brand_info_unclear":false,"sum":"","sum_rent":""}]},"id":"vulyk_101_66","declaration":{"additional_info_text":"","notfull_lostpages":"","date":"2016-03-25T00:00:00","notfull":"","additional_info":"","url":"http://static.declarations.com.ua/declarations/chosen_ones/judges_batch/731_stankevych_volodymyr_andriiovych_2015.pdf"},"liabilities":{"54":{"sum_foreign_comment":"","sum":"","sum_comment":"","sum_comment_unclear":false,"sum_hidden":false,"sum_comment_hidden":false,"sum_unclear":false,"sum_foreign":""},"55":{"sum_foreign_comment":"","sum":"","sum_comment":"","sum_foreign":""},"56":{"sum_foreign_comment":"","sum":"","sum_comment":"","sum_comment_hidden":false,"sum_unclear":false,"sum_foreign":""},"57":{"sum_foreign_comment":"","sum":"","sum_comment":"","sum_hidden":false,"sum_comment_hidden":false,"sum_unclear":false,"sum_foreign":""},"58":{"sum_foreign_comment":"","sum":"","sum_comment":"","sum_comment_unclear":false,"sum_hidden":false,"sum_comment_hidden":false,"sum_unclear":false,"sum_foreign":""},"59":{"sum_foreign_comment":"","sum":"","sum_comment":"","sum_foreign":""},"60":{"sum_foreign_comment":"","sum":"","sum_comment":"","sum_hidden":false,"sum_comment_hidden":false,"sum_unclear":false,"sum_foreign":""},"61":{"sum_foreign_comment":"","sum":"","sum_comment":"","sum_foreign":""},"62":{"sum_foreign_comment":"","sum":"","sum_comment":"","sum_comment_unclear":false,"sum_foreign":""},"63":{"sum_foreign_comment":"","sum_comment_hidden":false,"sum":"","sum_comment":"","sum_foreign":""},"64":{"sum_foreign_comment":"","sum_comment_hidden":false,"sum":"","sum_comment":"","sum_foreign":""}},"ft_src":"суддя апеляційного суду одеської області\nОдеська область\nЗагальний апеляційний суд\nВолодимир\nСтанкевич Світлана Зіновіївна\nПодружжя\nСтанкевич Андрій Володимирович\nДитина\nСтанкевич Наталія Володимирівна\nДитина\nАндрійович\nСтанкевич Володимир Андрійович\nСтанкевич\nСтанкевич Володимир Андрійович\nВолодимир Андрійович Станкевич\nВолодимир Станкевич\nСтанкевич Володимир Андрійович\nKia Magentis\n1999 куб. см.\n2006\n1.2 куб. дм.\n1981\nВАЗ 2101\n.0614\nпаркінг\n14.4\n49.35\n25.4\n268.2\n16.45\n25.4\n2015\n25255\n279326\n25255\n375826\nпенсія\n96500\n1999 куб. см.\n2006\nKia Magentis\n1.2 куб. дм.\n1981\nВАЗ 2101\n.0614\n14.4\nпаркінг\n268.2\n49.35\n25.4\n16.45\n25.4\nСтанкевич Володимир Андрійович\nВолодимир Андрійович Станкевич\nВолодимир Станкевич\nСтанкевич Володимир Андрійович\nВолодимир\nСтанкевич Володимир Андрійович\nАндрійович\nсуддя апеляційного суду одеської області\nОдеська область\nЗагальний апеляційний суд\nСтанкевич\nПодружжя\nСтанкевич Світлана Зіновіївна\nДитина\nСтанкевич Андрій Володимирович\nДитина\nСтанкевич Наталія Володимирівна\n279326\n25255\n96500\nпенсія\n375826\n25255\n2015\nСтанкевич Світлана Зіновіївна\nПодружжя\nСтанкевич Андрій Володимирович\nДитина\nСтанкевич Наталія Володимирівна\nДитина\nВолодимир\nАндрійович\nСтанкевич\nСтанкевич Володимир Андрійович\nВолодимир Андрійович Станкевич\nВолодимир Станкевич\nСтанкевич Володимир Андрійович\nсуддя апеляційного суду одеської області\nОдеська область\nЗагальний апеляційний суд\nСтанкевич Володимир Андрійович\n2006\nKia Magentis\n1999 куб. см.\n1981\n1.2 куб. дм.\nВАЗ 2101\nпенсія\n96500\n25255\n375826\n279326\n25255\n49.35\n25.4\n.0614\n268.2\n16.45\n25.4\nпаркінг\n14.4\n2015","general":{"inn":"","name":"Володимир","inn_unclear":false,"family":[{"inn":"","relations":"Подружжя","relations_other":"","inn_hidden":true,"family_name":"Станкевич Світлана Зіновіївна","name_hidden":true,"name_unclear":false},{"inn":"","relations":"Дитина","relations_unclear":false,"family_name":"Станкевич Андрій Володимирович","inn_hidden":true,"relations_other":"","name_hidden":false,"name_unclear":false},{"inn":"","relations":"Дитина","relations_other":"","inn_hidden":true,"family_name":"Станкевич Наталія Володимирівна","name_hidden":false,"name_unclear":false}],"inn_hidden":true,"family_raw":"","last_name":"Станкевич","post":{"region":"Одеська область","region_unclear":false,"post":"суддя апеляційного суду одеської області","office_unclear":false,"office":"Загальний апеляційний суд"},"full_name":"Станкевич Володимир Андрійович","addresses":[{"place_district":"","place_address_hidden":true,"place_city":"","place_city_type_hidden":false,"place_district_hidden":false,"place_city_type":"","place_city_hidden":true,"place_address":"","place_hidden":true,"place":""}],"patronymic":"Андрійович","patronymic_hidden":false,"full_name_suggest":{"output":"Станкевич Володимир Андрійович","input":["Станкевич Володимир Андрійович","Володимир Андрійович Станкевич","Володимир Станкевич"]}},"source":"VULYK","estate":{"23":[{"space_unclear":false,"costs":"","costs_comment":"","address_hidden":false,"region_hidden":true,"space_comment":"","space_hidden":false,"space":".0614","address":"","costs_comment_unclear":false,"region":"","space_units_unclear":false,"space_units":"га","costs_rent":"","costs_rent_comment":""}],"25":[{"space_unclear":false,"costs":"","costs_comment":"","address_hidden":false,"region_hidden":true,"space_comment":"","space_hidden":false,"space":"16.45","address":"","region":"","costs_rent_comment":"","space_comment_unclear":false,"space_units":"м²","costs_rent":""},{"space_unclear":false,"costs":"","costs_comment":"","space_comment":"","space_hidden":false,"space":"25.4","address":"","region":"","costs_rent_comment":"","space_comment_unclear":false,"space_units":"м²","costs_rent":""}],"26":[{"costs_rent":"","region":"","costs":"","costs_rent_comment":"","costs_comment":"","address_hidden":false,"region_hidden":true,"space_comment":"","space_units":"м²","space":"268.2","address":""}],"27":[{"space_hidden":false,"costs":"","costs_comment":"","address_hidden":false,"region_hidden":true,"space_comment":"паркінг","space":"14.4","address":"","region":"","costs_rent_comment":"","space_units":"м²","costs_rent":""}],"31":[{"space_unclear":false,"address_hidden":false,"region_hidden":true,"space_comment":"","space_hidden":false,"space":"49.35","address":"","costs_rent_comment_unclear":false,"region":"","costs_property":"","costs_rent_comment":"","space_units":"м²","costs_property_comment":"","costs_rent":""},{"costs_rent":"","region":"","costs_property":"","costs_rent_comment":"","space_comment":"","costs_property_comment":"","space_units":"м²","space":"25.4","address":""}]},"intro":{"declaration_year":"2015"}}