{"id":"vulyk_109_100","ft_src":"2008\nСантей\nПричiп, довж. 362\nПричiп бортовий ПР, довж. 500\n1800\n2003\n120, об'єм 3956, потужність 249 (183),  довжина 472\nToyota Land Cruiser\n2008\n149000\n444\n33\n612\n87\n2015\n247521.52\n947521.52\n700000\n120, об'єм 3956, потужність 249 (183),  довжина 472\nToyota Land Cruiser\n2008\n149000\nПричiп, довж. 362\n2008\nСантей\nПричiп бортовий ПР, довж. 500\n2003\n1800\n2015\nГридасов Юрій Володимирович\nЮрій Володимирович Гридасов\nЮрій Гридасов\nГридасов Юрій Володимирович\nЮрій\nПодружжя\nГридасова С. Ю. 04. 04. 1969\nДитина\nГридасов Д. Ю. 15. 10. 1992\nДитина\nГридасова А. Ю. 31. 01. 2000\nГридасов Юрій Володимирович\nВолодимирович\nГосподарський місцевий суд\nХерсонська область\nсуддя господарського суду херсонської області\nГридасов\nПАТ КБ Правексбанк\n181206.31\n247521.52\n947521.52\n700000\n444\n612\n87\n33\nПАТ КБ Правексбанк\n181206.31\nПодружжя\nГридасова С. Ю. 04. 04. 1969\nДитина\nГридасов Д. Ю. 15. 10. 1992\nДитина\nГридасова А. Ю. 31. 01. 2000\nВолодимирович\nГридасов\nЮрій\nГридасов Юрій Володимирович\nЮрій Володимирович Гридасов\nЮрій Гридасов\nГридасов Юрій Володимирович\nХерсонська область\nГосподарський місцевий суд\nсуддя господарського суду херсонської області\nГридасов Юрій Володимирович","estate":{"23":[{"address":"","space_units":"м²","costs_rent_unclear":false,"costs_comment":"","space_unclear":false,"region_hidden":true,"space_comment":"","address_hidden":false,"costs":"","costs_rent_comment":"","space":"444","region":"","costs_rent":""}],"24":[{"costs":"","address":"","space_units":"м²","costs_rent_comment":"","space":"87","space_comment":"","region_hidden":true,"costs_comment":"","region":"","address_hidden":false,"costs_rent":""}],"27":[{"address":"","space_units":"м²","costs_rent_unclear":false,"costs_comment":"","space_unclear":false,"region_hidden":true,"space_comment":"","address_hidden":false,"costs":"","costs_rent_comment":"","space":"33","region":"","costs_rent":""}],"29":[{"costs_property_comment":"","address":"","space_units":"м²","space_unclear":false,"region_hidden":true,"costs_property":"","space_comment":"","address_hidden":false,"costs_rent_comment":"","space":"612","region":"","costs_rent":""}]},"vehicle":{"35":[{"sum_comment_unclear":false,"brand_info":"120, об'єм 3956, потужність 249 (183),  довжина 472","sum_rent_comment":"","brand_unclear":false,"brand_hidden":false,"year":"2008","sum_comment":"","brand_info_hidden":false,"sum_rent":"","brand":"Toyota Land Cruiser","year_unclear":false,"brand_info_unclear":false,"sum":"149000"}],"39":[{"sum_comment":"","brand_info_hidden":false,"brand_info":"Причiп, довж. 362","sum":"","sum_rent_comment":"","brand_hidden":false,"brand":"Сантей","sum_rent":"","year":"2008"},{"sum_comment":"","brand_info":"Причiп бортовий ПР, довж. 500","sum":"1800","sum_rent_comment":"","year":"2003","brand":"","sum_rent":""}]},"source":"VULYK","income":{"5":{"family_comment":"","value":"947521.52","family":"","comment":""},"6":{"family_comment":"","value":"247521.52","family":"","comment":""},"7":{"source_name_hidden":false,"family_comment":"","comment":"","family":"","comment_hidden":false,"value":"","source_name":""},"8":{"family_comment":"","family_hidden":false,"value":"","family":"","comment":""},"9":{"family_comment":"","family":"","comment":"","value_unclear":false,"family_unclear":false,"value":""},"10":{"family_comment":"","value":"","family":"","comment":""},"11":{"family_comment":"","value":"","family":"","comment":""},"12":{"family_comment":"","value":"","family":"","comment":""},"13":{"family_comment":"","value":"","family":"","comment":""},"14":{"family_comment":"","value":"","family":"","comment":""},"15":{"family_comment":"","value":"","family":"","comment":""},"16":{"family_comment":"","value":"700000","family":"","comment":""},"17":{"family_comment":"","value":"","family":"","comment":""},"18":{"family_comment":"","value":"","family":"","comment":""},"19":{"family_comment":"","value":"","family":"","comment":""},"20":{"family_comment":"","family":"","comment":"","value_unclear":false,"family_hidden":false,"value":""}},"general":{"family_raw":"","name":"Юрій","full_name_suggest":{"input":["Гридасов Юрій Володимирович","Юрій Володимирович Гридасов","Юрій Гридасов"],"output":"Гридасов Юрій Володимирович"},"patronymic":"Володимирович","inn_hidden":true,"addresses":[{"place_city_type_hidden":false,"place_city_type":"","place_city_hidden":false,"place_hidden":true,"place_district":"","place_district_hidden":false,"place":"","place_address":"","place_address_hidden":false,"place_city":""}],"inn":"","inn_unclear":false,"last_name":"Гридасов","full_name":"Гридасов Юрій Володимирович","family":[{"inn":"","family_name":"Гридасова С. Ю. 04. 04. 1969","relations_hidden":false,"name_unclear":false,"relations":"Подружжя","inn_hidden":false,"name_hidden":false,"relations_other":""},{"inn":"","family_name":"Гридасов Д. Ю. 15. 10. 1992","relations_other":"","name_unclear":false,"inn_hidden":false,"name_hidden":false,"relations":"Дитина"},{"inn":"","family_name":"Гридасова А. Ю. 31. 01. 2000","relations_other":"","name_unclear":false,"inn_hidden":false,"name_hidden":false,"relations":"Дитина"}],"post":{"office":"Господарський місцевий суд","post":"суддя господарського суду херсонської області","office_unclear":false,"region_hidden":false,"region":"Херсонська область","office_hidden":false,"region_unclear":false},"name_hidden":false},"liabilities":{"54":{"sum_comment":"","sum_hidden":false,"sum":"","sum_foreign_comment":"","sum_foreign":"","sum_unclear":false,"sum_comment_hidden":false},"55":{"sum_comment":"","sum_comment_unclear":false,"sum_foreign_comment":"","sum":"","sum_foreign":""},"56":{"sum_comment":"","sum_foreign_comment":"","sum_foreign":"","sum":""},"57":{"sum_comment":"ПАТ КБ Правексбанк","sum_foreign_comment":"","sum_foreign":"","sum":"181206.31","sum_comment_hidden":false},"58":{"sum_comment":"","sum_foreign_comment":"","sum_foreign":"","sum":"","sum_comment_hidden":false},"59":{"sum_comment":"","sum_foreign_comment":"","sum_foreign":"","sum":""},"60":{"sum_comment":"","sum_foreign_comment":"","sum_foreign":"","sum":""},"61":{"sum_comment":"","sum_foreign_comment":"","sum_foreign":"","sum":""},"62":{"sum_comment":"","sum_foreign_comment":"","sum_foreign":"","sum":""},"63":{"sum_comment":"","sum_foreign_comment":"","sum_foreign":"","sum":""},"64":{"sum_comment":"","sum_foreign_comment":"","sum_foreign":"","sum":""}},"declaration":{"notfull_lostpages":"","additional_info_text":"","additional_info":"","date":"2016-03-24T00:00:00","notfull":"","url":"http://static.declarations.com.ua/declarations/chosen_ones/judges_batch/2557_hrydasov_iurii_volodymyrovych_2015.pdf"},"intro":{"isnotdeclaration":"","declaration_year":"2015"}}