{"income":{"5":{"value":"240306.53","comment_hidden":false,"family_comment":"","family":"29275","comment":"","family_comment_hidden":false},"6":{"value":"240306.53","family_comment":"","comment_hidden":false,"family_hidden":false,"family_unclear":false,"family_comment_hidden":false,"comment":"","family":"29275"},"7":{"value":"","comment_hidden":false,"family_comment_hidden":false,"family_comment":"","source_name":"","family":"","comment":"","source_name_hidden":false},"8":{"family_comment":"","value":"","family":"","comment":""},"9":{"value":"","family_comment":"","value_unclear":false,"family_unclear":false,"comment_unclear":false,"comment":"","family":""},"10":{"family_comment":"","family_unclear":false,"value":"","family":"","comment":""},"11":{"family_comment":"","value":"","family":"","comment":""},"12":{"family_comment":"","value":"","family":"","comment":""},"13":{"family_comment":"","value":"","family":"","comment":""},"14":{"family_comment":"","value":"","family":"","comment":""},"15":{"family_comment":"","value":"","comment_unclear":false,"family":"","comment":""},"16":{"family_comment":"","value":"","comment_unclear":false,"family":"","comment":""},"17":{"family_comment":"","value":"","family":"","comment":""},"18":{"family_comment":"","value":"","family":"","comment":""},"19":{"family_comment":"","value":"","family":"","comment":""},"20":{"value":"","family_comment":"","value_unclear":false,"family_unclear":false,"family_comment_unclear":false,"family_comment_hidden":false,"comment":"","family":""}},"vehicle":{"40":[{"brand_info":"1.8","sum_rent_comment":"","brand":"Chevrolet Lacetti","sum_comment":"","brand_unclear":false,"year":"2005","brand_info_unclear":false,"sum":"","sum_rent":""}]},"id":"vulyk_73_160","declaration":{"additional_info_text":"","notfull_lostpages":"","date":"2014-03-31T00:00:00","notfull":"","additional_info":"","url":"http://static.declarations.com.ua/declarations/chosen_ones/judges_batch/873_stefurak_ievhen_mykolaiovych.pdf"},"liabilities":{"54":{"sum_foreign_comment":"","sum_foreign_hidden":false,"sum_comment":"","sum_comment_unclear":false,"sum_hidden":false,"sum_comment_hidden":false,"sum_unclear":false,"sum":"","sum_foreign":""},"55":{"sum_foreign_comment":"","sum_comment_hidden":false,"sum":"","sum_comment":"","sum_foreign":""},"56":{"sum_foreign_comment":"","sum":"","sum_comment":"","sum_comment_unclear":false,"sum_foreign":""},"57":{"sum_foreign_comment":"","sum":"","sum_comment":"","sum_hidden":false,"sum_comment_hidden":false,"sum_unclear":false,"sum_foreign":""},"58":{"sum_foreign_comment":"","sum":"","sum_comment":"","sum_hidden":false,"sum_comment_hidden":false,"sum_foreign":""},"59":{"sum_foreign_comment":"","sum":"","sum_comment":"","sum_comment_unclear":false,"sum_unclear":false,"sum_foreign":""},"60":{"sum_foreign_comment":"","sum":"","sum_comment":"","sum_hidden":false,"sum_comment_hidden":false,"sum_unclear":false,"sum_foreign":""},"61":{"sum_foreign_comment":"","sum":"","sum_comment":"","sum_foreign":""},"62":{"sum_foreign_comment":"","sum":"","sum_comment":"","sum_foreign":"6053"},"63":{"sum_foreign_comment":"","sum":"","sum_comment":"","sum_hidden":false,"sum_comment_hidden":false,"sum_foreign":""},"64":{"sum_foreign_comment":"","sum":"","sum_comment":"","sum_foreign":""}},"ft_src":"6053\nсуддя апеляційного суду івано-франківської області\nІвано-Франківська область\nЗагальний апеляційний суд\nЄвген\nСтефурак Н. Я. 20. 01. 1971\nПодружжя\nСтефурак Я. Є. 16. 05. 1994\nДитина\nСтефурак О. Є. 13. 05. 1997\nДитина\nСтефурак Н. Є. 28. 11. 1999\nДитина\nСтефурак М. Є. 16. 06. 2005\nДитина\nСтефурак Т. Є. 10. 10. 2006\nДитина\nМиколайович\nСтефурак Євген Миколайович\nЄвген Миколайович Стефурак\nЄвген Стефурак\nСтефурак Євген Миколайович\nСтефурак\nСтефурак Євген Миколайович\n2005\nChevrolet Lacetti\n1.8\n48.8\n106.5\n267.3\n1518\n2013\n29275\n240306.53\n29275\n240306.53\n1.8\nChevrolet Lacetti\n2005\n2013\nСтефурак Євген Миколайович\nЄвген Миколайович Стефурак\nЄвген Стефурак\nСтефурак Євген Миколайович\nЄвген\nПодружжя\nСтефурак Н. Я. 20. 01. 1971\nДитина\nСтефурак Я. Є. 16. 05. 1994\nДитина\nСтефурак О. Є. 13. 05. 1997\nСтефурак Н. Є. 28. 11. 1999\nДитина\nСтефурак М. Є. 16. 06. 2005\nДитина\nСтефурак Т. Є. 10. 10. 2006\nДитина\nСтефурак Євген Миколайович\nМиколайович\nЗагальний апеляційний суд\nІвано-Франківська область\nсуддя апеляційного суду івано-франківської області\nСтефурак\n6053\n29275\n240306.53\n240306.53\n29275\n48.8\n267.3\n106.5\n1518\n6053\nПодружжя\nСтефурак Н. Я. 20. 01. 1971\nДитина\nСтефурак Я. Є. 16. 05. 1994\nДитина\nСтефурак О. Є. 13. 05. 1997\nДитина\nСтефурак Н. Є. 28. 11. 1999\nСтефурак М. Є. 16. 06. 2005\nДитина\nСтефурак Т. Є. 10. 10. 2006\nДитина\nМиколайович\nСтефурак\nЄвген\nСтефурак Євген Миколайович\nЄвген Миколайович Стефурак\nЄвген Стефурак\nСтефурак Євген Миколайович\nІвано-Франківська область\nЗагальний апеляційний суд\nсуддя апеляційного суду івано-франківської області\nСтефурак Євген Миколайович\n2005\n1.8\nChevrolet Lacetti\n240306.53\n29275\n240306.53\n29275\n106.5\n267.3\n48.8\n1518\n2013","general":{"inn":"","name":"Євген","family":[{"inn":"","relations":"Подружжя","inn_unclear":false,"relations_hidden":false,"inn_hidden":true,"relations_other":"","name_hidden":false,"family_name":"Стефурак Н. Я. 20. 01. 1971","name_unclear":false},{"inn":"","relations":"Дитина","inn_unclear":false,"family_name":"Стефурак Я. Є. 16. 05. 1994","inn_hidden":false,"relations_other":"","name_hidden":false,"name_unclear":false},{"inn":"","relations":"Дитина","relations_other":"","inn_hidden":false,"family_name":"Стефурак О. Є. 13. 05. 1997","name_hidden":false,"name_unclear":false},{"inn":"","family_name":"Стефурак Н. Є. 28. 11. 1999","relations":"Дитина","inn_hidden":false,"relations_other":""},{"inn":"","family_name":"Стефурак М. Є. 16. 06. 2005","relations":"Дитина","inn_hidden":true},{"inn":"","family_name":"Стефурак Т. Є. 10. 10. 2006","relations":"Дитина"}],"patronymic":"Миколайович","inn_hidden":true,"family_raw":"","last_name":"Стефурак","post":{"post_unclear":false,"region_unclear":false,"post":"суддя апеляційного суду івано-франківської області","office":"Загальний апеляційний суд","region":"Івано-Франківська область","post_hidden":false,"office_hidden":false,"office_unclear":false,"region_hidden":false},"last_name_unclear":false,"full_name":"Стефурак Євген Миколайович","addresses":[{"place_district":"","place_city_hidden":true,"place_city":"","place_city_type_hidden":false,"place_district_hidden":false,"place_city_type":"","place_address_hidden":true,"place_address":"","place_hidden":true,"place":""}],"full_name_suggest":{"output":"Стефурак Євген Миколайович","input":["Стефурак Євген Миколайович","Євген Миколайович Стефурак","Євген Стефурак"]},"name_unclear":false},"source":"VULYK","estate":{"29":[{"space_unclear":false,"address_hidden":true,"region_hidden":true,"space_comment":"","space":"1518","address":"","region":"","costs_property":"","costs_rent_comment":"","space_units":"м²","costs_property_comment":"","costs_rent":""}],"30":[{"space_unclear":false,"address_hidden":true,"region_hidden":true,"space_comment":"","space_hidden":false,"space":"267.3","address":"","region":"","costs_property":"","costs_rent_comment":"","space_comment_unclear":false,"space_units":"м²","costs_property_comment":"","costs_rent":""}],"31":[{"space_unclear":false,"address_hidden":true,"region_hidden":true,"space_comment":"","space":"106.5","address":"","region":"","costs_property":"","costs_rent_comment":"","space_units":"м²","costs_property_comment":"","costs_rent":""}],"33":[{"space_hidden":false,"address_hidden":true,"region_hidden":true,"space_comment":"","space":"48.8","address":"","region":"","costs_property":"","costs_rent_comment":"","space_units":"м²","costs_property_comment":"","costs_rent":""}]},"intro":{"declaration_year":"2013"}}