{"income":{"5":{"value":"279531","family_comment":"","value_unclear":false,"family_hidden":false,"value_hidden":false,"family_unclear":false,"comment_unclear":false,"comment":"","family":"19940"},"6":{"value":"274357","family_comment":"","value_unclear":false,"family_hidden":false,"value_hidden":false,"family_unclear":false,"comment_unclear":false,"comment":"","family":""},"7":{"source_name_unclear":false,"value":"","family_comment":"","source_name":"","family":"","comment":""},"8":{"family_comment":"","value":"","family":"","comment":""},"9":{"value":"","value_unclear":false,"comment_hidden":false,"family_comment":"","comment_unclear":false,"comment":"","family":""},"10":{"value":"","comment_unclear":false,"value_hidden":false,"family_comment":"","family":"","comment":""},"11":{"family_comment":"","value":"","family":"","comment":""},"12":{"family_comment":"","value":"","family":"","comment":""},"13":{"family_comment":"","value":"","family":"","comment":""},"14":{"family_comment":"","value":"","family":"","comment":""},"15":{"family_comment":"","value":"","family":"","comment":""},"16":{"family_comment":"","value":"","family":"","comment":""},"17":{"family_comment":"","value":"","family":"","comment":""},"18":{"value":"","family_hidden":false,"value_hidden":false,"family_comment":"","family":"","comment":""},"19":{"family_comment":"","value":"","family":"","comment":""},"20":{"value":"5174","family_comment":"","value_unclear":false,"family_hidden":false,"value_hidden":false,"family_unclear":false,"family":"19940","comment":""}},"vehicle":{"35":[{"year_hidden":false,"brand_info":"1896","sum_rent_comment":"","year":"2000","brand_info_unclear":false,"year_unclear":false,"sum_rent":"","sum":"","brand":"Volkswagen Passat","sum_comment":"","brand_unclear":false,"brand_hidden":false}]},"id":"vulyk_66_92","declaration":{"additional_info_text":"","notfull_lostpages":"","date":"2015-03-19T00:00:00","notfull":"","additional_info":"","url":"http://static.declarations.com.ua/declarations/chosen_ones/mega_batch/savin_oleksandr_ivanovych.pdf"},"liabilities":{"54":{"sum_foreign_comment":"","sum":"","sum_comment":"","sum_comment_unclear":false,"sum_comment_hidden":false,"sum_unclear":false,"sum_foreign":""},"55":{"sum_foreign_comment":"","sum":"","sum_comment":"","sum_foreign":""},"56":{"sum_foreign_comment":"","sum_foreign_hidden":false,"sum_comment":"","sum_hidden":false,"sum_comment_hidden":false,"sum":"","sum_foreign":""},"57":{"sum_foreign_comment":"","sum":"7381","sum_comment":"","sum_comment_unclear":false,"sum_hidden":false,"sum_comment_hidden":false,"sum_unclear":false,"sum_foreign":""},"58":{"sum_foreign_comment":"","sum":"","sum_comment":"","sum_comment_unclear":false,"sum_unclear":false,"sum_foreign":""},"59":{"sum_foreign_comment":"","sum_foreign_hidden":false,"sum_comment":"","sum_comment_unclear":false,"sum_hidden":false,"sum":"","sum_foreign":""},"60":{"sum_foreign_comment":"","sum":"","sum_comment":"","sum_comment_unclear":false,"sum_foreign":""},"61":{"sum_foreign_comment":"","sum":"","sum_comment":"","sum_foreign":""},"62":{"sum_foreign_comment":"","sum_foreign_hidden":false,"sum_comment":"","sum_hidden":false,"sum":"","sum_unclear":false,"sum_foreign":""},"63":{"sum_foreign_comment":"","sum":"","sum_comment":"","sum_comment_unclear":false,"sum_comment_hidden":false,"sum_unclear":false,"sum_foreign":""},"64":{"sum_foreign_comment":"","sum":"","sum_comment":"","sum_comment_unclear":false,"sum_foreign":""}},"ft_src":"7381\nсуддя южноукраїнського міського суду миколаївської області\nМиколаївська область\nЗагальний місцевий суд\nОлександр\nСавіна Наталія Степанівна\nПодружжя\nІванович\nСавін\nСавін Олександр Іванович\nСавін Олександр Іванович\nОлександр Іванович Савін\nОлександр Савін\nСавін Олександр Іванович\n1896\nVolkswagen Passat\n2000\n70\n70\n1/2\n69.5\n277.5\n1/2\n69.5\n2014\n274357\n19940\n279531\n19940\n5174\n1896\nVolkswagen Passat\n2000\n70\n277.5\n69.5\n1/2\n70\n69.5\n1/2\nСавін Олександр Іванович\nОлександр Іванович Савін\nОлександр Савін\nСавін Олександр Іванович\nСавін Олександр Іванович\nПодружжя\nСавіна Наталія Степанівна\nОлександр\nСавін\nЗагальний місцевий суд\nсуддя южноукраїнського міського суду миколаївської області\nМиколаївська область\nІванович\n7381\n274357\n5174\n19940\n279531\n19940\n2014\n7381\nСавіна Наталія Степанівна\nПодружжя\nІванович\nСавін\nОлександр\nСавін Олександр Іванович\nОлександр Іванович Савін\nОлександр Савін\nСавін Олександр Іванович\nМиколаївська область\nсуддя южноукраїнського міського суду миколаївської області\nЗагальний місцевий суд\nСавін Олександр Іванович\nVolkswagen Passat\n1896\n2000\n5174\n19940\n279531\n19940\n274357\n1/2\n69.5\n70\n277.5\n69.5\n1/2\n70\n2014","general":{"inn":"","name":"Олександр","last_name_hidden":false,"family":[{"inn":"","inn_hidden":false,"relations_hidden":false,"family_name":"Савіна Наталія Степанівна","relations_other":"","relations":"Подружжя","name_hidden":false,"name_unclear":false}],"patronymic":"Іванович","inn_hidden":false,"family_raw":"","inn_unclear":false,"post":{"post_unclear":false,"post":"суддя южноукраїнського міського суду миколаївської області","candidate":"","office_hidden":false,"region":"Миколаївська область","office":"Загальний місцевий суд","office_unclear":false},"last_name_unclear":false,"full_name":"Савін Олександр Іванович","last_name":"Савін","full_name_suggest":{"output":"Савін Олександр Іванович","input":["Савін Олександр Іванович","Олександр Іванович Савін","Олександр Савін"]}},"source":"VULYK","estate":{"23":[{"space_unclear":false,"costs":"","costs_comment":"","costs_hidden":false,"address_hidden":false,"region_hidden":false,"space_comment":"","space_hidden":false,"space":"70","space_units_hidden":false,"region":"","address_unclear":false,"space_units_unclear":false,"space_units":"м²","address":"","costs_rent":"","costs_rent_comment":""}],"24":[{"space_unclear":false,"costs":"","costs_comment":"","costs_hidden":false,"address_hidden":false,"region_hidden":false,"space_comment":"","space_hidden":false,"space":"277.5","address":"","region":"","address_unclear":false,"costs_rent_comment":"","costs_rent_hidden":false,"space_comment_unclear":false,"space_units":"м²","costs_rent":""}],"25":[{"region_unclear":false,"space_hidden":false,"costs":"","costs_comment":"","costs_hidden":false,"address_hidden":false,"region_hidden":false,"space_comment":"1/2","space_unclear":false,"space":"69.5","space_units_hidden":false,"region":"","address_unclear":false,"costs_rent_comment":"","space_comment_unclear":false,"space_units":"м²","address":"","costs_rent":""}],"27":[{"space_unclear":false,"costs":"","costs_comment":"","costs_hidden":false,"address_hidden":false,"region_hidden":false,"space_comment":"","space_hidden":false,"space":"70","space_units_hidden":false,"region":"","costs_rent_comment":"","space_comment_unclear":false,"space_units":"м²","address":"","costs_rent":""}],"31":[{"space_unclear":false,"address_hidden":false,"region_hidden":false,"space_comment":"1/2","space_hidden":false,"space":"69.5","address":"","region":"","costs_property":"","costs_rent_comment":"","space_comment_unclear":false,"space_comment_hidden":false,"space_units":"м²","costs_property_comment":"","costs_rent":""}]},"intro":{"declaration_year":"2014","isnotdeclaration":"","declaration_year_unclear":false}}