{"income":{"5":{"family_comment":"","value":"210458","family":"14265","comment":""},"6":{"family_comment":"","value":"210458","family_hidden":false,"comment":"","family":"14265"},"7":{"family_comment":"","value":"","source_name":"","family":"","comment":""},"8":{"family_comment":"","value":"","family":"","comment":""},"9":{"value":"","value_unclear":false,"family_hidden":false,"family_comment":"","family":"","comment":""},"10":{"value":"","family_comment":"","family_hidden":false,"value_hidden":false,"family_unclear":false,"family":"","comment":""},"11":{"family_comment":"","value":"","family":"","comment":""},"12":{"family_comment":"","value":"","family":"","comment":""},"13":{"family_comment":"","value":"","family":"","comment":""},"14":{"family_comment":"","value":"","family":"","comment":""},"15":{"family_comment":"","value":"","family":"","comment":""},"16":{"family_comment":"","value":"","family":"","comment":""},"17":{"family_comment":"","value":"","family":"","comment":""},"18":{"family_comment":"","value":"","family":"","comment":""},"19":{"family_comment":"","value":"","family":"","comment":""},"20":{"value":"","comment_unclear":false,"family_comment":"","family":"","comment":"","family_comment_unclear":false}},"vehicle":{"35":[{"brand_info":"1800 куб. см.","sum_rent_comment":"","brand":"Honda Civic","sum_comment":"","brand_unclear":false,"year":"2008","brand_hidden":false,"brand_info_unclear":false,"sum":"","sum_rent":"","sum_unclear":false}]},"id":"vulyk_75_151","declaration":{"additional_info_text":"","notfull_lostpages":"","date":"2014-03-31T00:00:00","notfull":"","additional_info":"","url":"http://static.declarations.com.ua/declarations/chosen_ones/judges_batch/1784_kobal_mykhailo_ivanovych.pdf"},"liabilities":{"54":{"sum_foreign_comment":"","sum":"","sum_comment":"","sum_foreign":""},"55":{"sum_foreign_comment":"","sum":"","sum_comment":"","sum_foreign":""},"56":{"sum_foreign_comment":"","sum":"472","sum_comment":"","sum_foreign":""},"57":{"sum_foreign_comment":"","sum":"30093","sum_comment":"","sum_foreign":""},"58":{"sum_foreign_comment":"","sum":"887","sum_comment":"","sum_foreign":""},"59":{"sum_foreign_comment":"","sum":"","sum_comment":"","sum_comment_unclear":false,"sum_unclear":false,"sum_foreign":""},"60":{"sum_foreign_comment":"","sum":"","sum_comment":"","sum_foreign":""},"61":{"sum_foreign_comment":"","sum":"","sum_comment":"","sum_foreign":""},"62":{"sum_foreign_comment":"","sum":"5960","sum_comment":"","sum_unclear":false,"sum_foreign":""},"63":{"sum_foreign_comment":"","sum":"","sum_comment":"","sum_foreign":""},"64":{"sum_foreign_comment":"","sum":"","sum_comment":"","sum_foreign":""}},"ft_src":"30093\n5960\n887\n472\nсуддя київського апеляційного адміністративного суду\nм. Київ\nАпеляційний адміністративний суд\nКобаль Михайло Іванович\nМихайло\nКобаль Н. О\nПодружжя\nКобаль Михайло Іванович\nМихайло Іванович Кобаль\nМихайло Кобаль\nКобаль Михайло Іванович\nКобаль\nІванович\nHonda Civic\n1800 куб. см.\n2008\n9800\n43\n63.9\n2013\n14265\n210458\n14265\n210458\n1800 куб. см.\n2008\nHonda Civic\n2013\nАпеляційний адміністративний суд\nсуддя київського апеляційного адміністративного суду\nм. Київ\nКобаль\nКобаль Михайло Іванович\nМихайло Іванович Кобаль\nМихайло Кобаль\nКобаль Михайло Іванович\nМихайло\nПодружжя\nКобаль Н. О\nКобаль Михайло Іванович\nІванович\n887\n30093\n472\n5960\n210458\n14265\n210458\n14265\n9800\n43\n63.9\n887\n30093\n472\n5960\nКобаль Н. О\nПодружжя\nКобаль\nІванович\nсуддя київського апеляційного адміністративного суду\nм. Київ\nАпеляційний адміністративний суд\nКобаль Михайло Іванович\nКобаль Михайло Іванович\nМихайло Іванович Кобаль\nМихайло Кобаль\nКобаль Михайло Іванович\nМихайло\n2008\nHonda Civic\n1800 куб. см.\n14265\n210458\n14265\n210458\n63.9\n9800\n43\n2013","general":{"inn":"","inn_hidden":false,"last_name":"Кобаль","post":{"office":"Апеляційний адміністративний суд","region":"м. Київ","post":"суддя київського апеляційного адміністративного суду"},"name":"Михайло","full_name":"Кобаль Михайло Іванович","family_raw":"","family":[{"inn":"","inn_hidden":false,"relations_hidden":false,"family_name":"Кобаль Н. О","relations_other":"","relations":"Подружжя","name_hidden":false,"name_unclear":false}],"full_name_suggest":{"output":"Кобаль Михайло Іванович","input":["Кобаль Михайло Іванович","Михайло Іванович Кобаль","Михайло Кобаль"]},"patronymic":"Іванович"},"source":"VULYK","estate":{"23":[{"costs":"","costs_comment":"","address_hidden":false,"region_hidden":false,"space_comment":"","space":"9800","address":"","region":"","costs_rent_comment":"","space_units":"м²","space_units_hidden":false,"costs_rent":""},{"costs_rent":"","region":"","costs":"","costs_rent_comment":"","costs_comment":"","region_hidden":false,"space_comment":"","space_units":"м²","space":"43","address":""}],"31":[{"space_unclear":false,"address_hidden":true,"region_hidden":false,"space_comment":"","space":"63.9","address":"","region":"","costs_property":"","costs_rent_comment":"","space_units":"м²","costs_property_comment":"","costs_rent":""}]},"intro":{"declaration_year":"2013","isnotdeclaration":""}}