{"income":{"5":{"family_comment":"","value":"220848.08","family_hidden":false,"comment":"","family":"63830"},"6":{"family_comment":"","value":"207450.08","family_hidden":false,"comment":"","family":"63830"},"7":{"family_comment":"","value":"","source_name":"","family":"","comment":""},"8":{"family_comment":"","value":"","family":"","comment":""},"9":{"family_comment":"","value":"","family":"","comment":""},"10":{"family_comment":"","value":"13398","family":"","comment":""},"11":{"family_comment":"","value":"","family":"","comment":""},"12":{"family_comment":"","value":"","family":"","comment":""},"13":{"family_comment":"","value":"","family":"","comment":""},"14":{"family_comment":"","value":"","family":"","comment":""},"15":{"family_comment":"","value":"","family":"","comment":""},"16":{"family_comment":"","value":"","family":"","comment":""},"17":{"family_comment":"","value":"","family":"","comment":""},"18":{"family_comment":"","value":"","family":"","comment":""},"19":{"family_comment":"","value":"","family":"","comment":""},"20":{"family_comment":"","value":"","family":"","comment":""}},"vehicle":{"35":[{"brand_info":"1991 куб. см., 104.3 кВт , 432.5 см","sum_rent_comment":"","brand":"Hyundai Tucson","sum_comment":"","year":"2008","brand_info_hidden":false,"sum":"","sum_rent":""}],"40":[{"year_hidden":false,"brand_info":"2771 куб. см., 145.22 кВт , 480.3 см","sum_rent_comment":"","brand":"Skoda Superb","sum_comment":"","year":"2003","brand_hidden":false,"brand_info_hidden":false,"sum":"","sum_rent":""}]},"id":"vulyk_105_23","banks":{"52":[{"sum_foreign_comment":"","sum_units":"UAH","sum_comment":"","sum_foreign_units":"UAH","sum":"1406988","sum_foreign":""}],"53":[{"sum_foreign_comment":"","sum_units":"UAH","sum_comment":"","sum_foreign_units":"UAH","sum":"829074.8","sum_foreign":""}]},"declaration":{"date":"2015-03-31T00:00:00","additional_info_text":"","additional_info":"","url":"http://static.declarations.com.ua/declarations/chosen_ones/judges_batch/4598_mykhalska_iuliia_borysivna.pdf"},"liabilities":{"54":{"sum_foreign_comment":"","sum_comment_hidden":false,"sum":"","sum_comment":"","sum_foreign":""},"55":{"sum_foreign_comment":"","sum":"","sum_comment":"","sum_foreign":""},"56":{"sum_foreign_comment":"","sum":"","sum_comment":"","sum_foreign":""},"57":{"sum_foreign_comment":"","sum":"","sum_comment":"","sum_comment_unclear":false,"sum_comment_hidden":false,"sum_foreign":""},"58":{"sum_foreign_comment":"","sum":"","sum_comment":"","sum_foreign":""},"59":{"sum_foreign_comment":"","sum":"","sum_comment":"","sum_foreign":""},"60":{"sum_foreign_comment":"","sum":"","sum_comment":"","sum_foreign":""},"61":{"sum_foreign_comment":"","sum":"","sum_comment":"","sum_foreign":""},"62":{"sum_foreign_comment":"","sum":"","sum_hidden":false,"sum_comment":"","sum_foreign":""},"63":{"sum_foreign_comment":"","sum":"","sum_comment":"","sum_foreign":""},"64":{"sum_foreign_comment":"","sum":"","sum_comment":"","sum_foreign":""}},"ft_src":"Михальська Юлія Борисівна\nсуддя київського апеляційного господарського суду\nм. Київ\nАпеляційний господарський суд\nЮлія\nМихальський Ю. А\nПодружжя\nМихальський Д. Ю\nДитина\nМихальська Юлія Борисівна\nЮлія Борисівна Михальська\nЮлія Михальська\nМихальська Юлія Борисівна\nМихальська\nБорисівна\n1991 куб. см., 104.3 кВт , 432.5 см\n2008\nHyundai Tucson\n2771 куб. см., 145.22 кВт , 480.3 см\nSkoda Superb\n2003\n1406988\n829074.8\n2014\nHyundai Tucson\n1991 куб. см., 104.3 кВт , 432.5 см\n2008\n2771 куб. см., 145.22 кВт , 480.3 см\n2003\nSkoda Superb\n829074.8\n1406988\n2014\nсуддя київського апеляційного господарського суду\nАпеляційний господарський суд\nм. Київ\nМихальська\nМихальська Юлія Борисівна\nЮлія Борисівна Михальська\nЮлія Михальська\nМихальська Юлія Борисівна\nМихальська Юлія Борисівна\nЮлія\nБорисівна\nПодружжя\nМихальський Ю. А\nДитина\nМихальський Д. Ю\n207450.08\n63830\n220848.08\n63830\n13398\n71.8\n16.85\n71.8\n16.85\nМихальський Ю. А\nПодружжя\nМихальський Д. Ю\nДитина\nБорисівна\nМихальська\nм. Київ\nсуддя київського апеляційного господарського суду\nАпеляційний господарський суд\nМихальська Юлія Борисівна\nМихальська Юлія Борисівна\nЮлія Борисівна Михальська\nЮлія Михальська\nМихальська Юлія Борисівна\nЮлія\n63830\n207450.08\n13398\n63830\n220848.08\nHyundai Tucson\n1991 куб. см., 104.3 кВт , 432.5 см\n2008\nSkoda Superb\n2771 куб. см., 145.22 кВт , 480.3 см\n2003\n13398\n63830\n220848.08\n63830\n207450.08\n71.8\n16.85\n1406988\n829074.8\n2014","general":{"inn":"","inn_hidden":true,"last_name":"Михальська","post":{"post_unclear":false,"region_unclear":false,"region":"м. Київ","office_hidden":false,"office":"Апеляційний господарський суд","post":"суддя київського апеляційного господарського суду","office_unclear":false},"name":"Юлія","full_name":"Михальська Юлія Борисівна","family_raw":"","addresses":[{"place_district":"","place_city_hidden":true,"place_city":"","place_city_type_hidden":false,"place_district_hidden":true,"place_city_type":"","place_address_hidden":false,"place_address":"","place_hidden":true,"place":""}],"family":[{"inn":"","inn_hidden":true,"relations_hidden":false,"family_name":"Михальський Ю. А","relations_other":"","relations":"Подружжя","name_hidden":false,"name_unclear":false},{"inn":"","relations":"Дитина","relations_other":"","inn_hidden":false,"family_name":"Михальський Д. Ю","name_hidden":false,"name_unclear":false}],"full_name_suggest":{"output":"Михальська Юлія Борисівна","input":["Михальська Юлія Борисівна","Юлія Борисівна Михальська","Юлія Михальська"]},"patronymic":"Борисівна"},"source":"VULYK","estate":{"31":[{"space_hidden":false,"address_hidden":true,"region_hidden":true,"space_comment":"","space":"71.8","address":"","region":"","costs_property":"","costs_rent_comment":"","space_units":"м²","costs_property_comment":"","costs_rent":""},{"costs_rent":"","costs_property":"","costs_rent_comment":"","region_hidden":false,"space_comment":"","costs_property_comment":"","space_units":"м²","space":"16.85","address":""}]},"intro":{"declaration_year":"2014"}}