{"income":{"5":{"value":"236796","family_comment":"","value_unclear":true,"value_hidden":true,"family_unclear":false,"family":"7808","comment":""},"6":{"value":"225770","family_hidden":false,"value_hidden":true,"family_comment":"","family_comment_hidden":false,"comment":"","family":""},"7":{"value":"","value_unclear":false,"family_hidden":false,"value_hidden":false,"family_comment":"","source_name":"","family":"","comment":"","source_name_hidden":false},"8":{"value":"","comment_hidden":false,"family_hidden":false,"value_hidden":false,"family_comment":"","family":"","comment":""},"9":{"value":"151","family_comment":"","comment_hidden":false,"family_hidden":false,"value_hidden":false,"family_unclear":false,"family":"","comment":""},"10":{"value":"12617","comment_hidden":false,"family_hidden":false,"value_hidden":false,"family_comment":"","family":"","comment":""},"11":{"value":"","value_unclear":false,"comment_hidden":false,"family_hidden":false,"value_hidden":false,"family_comment":"","family":"","comment":""},"12":{"value":"","comment_hidden":false,"family_hidden":false,"value_hidden":false,"family_comment":"","family":"7808","comment":""},"13":{"value":"","comment_hidden":false,"family_hidden":false,"value_hidden":false,"family_comment":"","family":"","comment":""},"14":{"value":"","comment_hidden":false,"family_hidden":false,"value_hidden":false,"family_comment":"","family":"","comment":""},"15":{"value":"","comment_hidden":false,"family_hidden":false,"value_hidden":false,"family_comment":"","family":"","comment":""},"16":{"value":"","comment_hidden":false,"family_hidden":false,"value_hidden":false,"family_comment":"","family":"","comment":""},"17":{"value":"","comment_hidden":false,"family_hidden":false,"value_hidden":false,"family_comment":"","family":"","comment":""},"18":{"value":"","value_unclear":false,"comment_hidden":false,"family_hidden":false,"value_hidden":false,"family_comment":"","family":"","comment":""},"19":{"value":"","comment_hidden":false,"family_hidden":false,"value_hidden":false,"family_comment":"","family":"","comment":""},"20":{"value":"10875","value_unclear":false,"family_comment":"","comment_unclear":false,"comment":"","family":""}},"id":"vulyk_76_178","banks":{"45":[{"sum_units":"UAH","sum_foreign":"","sum_hidden":true,"sum":"4764","sum_units_hidden":false,"sum_foreign_comment":"","sum_foreign_hidden":false,"sum_comment":"","sum_foreign_units":"UAH","sum_units_unclear":false,"sum_comment_hidden":true,"sum_unclear":true}],"46":[{"sum_foreign_comment":"","sum_units":"UAH","sum_comment":"","sum_hidden":false,"sum_foreign_units":"UAH","sum_foreign_hidden":false,"sum_units_unclear":false,"sum_comment_hidden":false,"sum_unclear":true,"sum":"1800","sum_foreign":""}]},"declaration":{"additional_info_text":"","notfull_lostpages":"","date":"2014-12-17T00:00:00","notfull":"","additional_info":"","url":"http://static.declarations.com.ua/declarations/chosen_ones/judges_batch/379_piskun_oksana_pavlivna.pdf"},"liabilities":{"54":{"sum_foreign_comment":"","sum_foreign_hidden":false,"sum_comment":"","sum_hidden":false,"sum_comment_hidden":false,"sum":"","sum_foreign":""},"55":{"sum_foreign_comment":"","sum":"","sum_hidden":false,"sum_comment":"","sum_foreign":""},"56":{"sum_foreign_comment":"","sum":"","sum_comment":"","sum_foreign":""},"57":{"sum_foreign_comment":"","sum_foreign_hidden":false,"sum_comment":"","sum_hidden":false,"sum_comment_hidden":false,"sum_unclear":false,"sum":"","sum_foreign":""},"58":{"sum_foreign_comment":"","sum_foreign_hidden":false,"sum_comment":"","sum_hidden":false,"sum_comment_hidden":false,"sum_unclear":false,"sum":"","sum_foreign":""},"59":{"sum_foreign_comment":"","sum":"","sum_hidden":false,"sum_comment":"","sum_foreign":""},"60":{"sum_foreign_comment":"","sum_foreign_hidden":false,"sum_comment":"","sum_hidden":false,"sum_comment_hidden":false,"sum_unclear":false,"sum":"","sum_foreign":""},"61":{"sum_foreign_comment":"","sum":"","sum_hidden":false,"sum_comment":"","sum_foreign":""},"62":{"sum_foreign_comment":"","sum":"","sum_comment":"","sum_hidden":false,"sum_comment_hidden":false,"sum_foreign":""},"63":{"sum_foreign_comment":"","sum":"","sum_hidden":false,"sum_comment":"","sum_foreign":""},"64":{"sum_foreign_comment":"","sum":"","sum_hidden":false,"sum_comment":"","sum_foreign":""}},"ft_src":"суддя апеляційного суду, секретар судової палати апеляційного суду дніпропетровського суду з розгляду кримінальних справ\nДніпропетровська область\nЗагальний апеляційний суд\nОксана\nПіскун С. А\nПодружжя\nПіскун В. С\nДитина\nПіскун Є. С\nДитина\nПавлівна\nПіскун Оксана Павлівна\nОксана Павлівна Піскун\nОксана Піскун\nПіскун Оксана Павлівна\nПіскун Оксана Павлівна\nПіскун\n13.1\n63.1\n1800\n4764\n2013\n13.1\n63.1\nПіскун Оксана Павлівна\nОксана Павлівна Піскун\nОксана Піскун\nПіскун Оксана Павлівна\nПіскун Оксана Павлівна\nПодружжя\nПіскун С. А\nДитина\nПіскун В. С\nДитина\nПіскун Є. С\nОксана\nПавлівна\nЗагальний апеляційний суд\nсуддя апеляційного суду, секретар судової палати апеляційного суду дніпропетровського суду з розгляду кримінальних справ\nДніпропетровська область\nПіскун\n225770\n10875\n7808\n236796\n7808\n151\n12617\n4764\n1800\n2013\n225770\n151\n12617\n7808\n236796\n10875\n7808\nПіскун С. А\nПодружжя\nДитина\nПіскун В. С\nПіскун Є. С\nДитина\nПавлівна\nПіскун\nОксана\nПіскун Оксана Павлівна\nОксана Павлівна Піскун\nОксана Піскун\nПіскун Оксана Павлівна\nДніпропетровська область\nсуддя апеляційного суду, секретар судової палати апеляційного суду дніпропетровського суду з розгляду кримінальних справ\nЗагальний апеляційний суд\nПіскун Оксана Павлівна\n151\n12617\n10875\n236796\n7808\n7808\n225770\n13.1\n63.1\n4764\n1800\n2013","general":{"inn":"","name":"Оксана","inn_unclear":false,"family":[{"inn":"","inn_hidden":true,"relations_unclear":false,"relations_hidden":false,"relations_other":"","relations":"Подружжя","name_hidden":false,"family_name":"Піскун С. А","name_unclear":false},{"inn":"","inn_hidden":false,"relations_unclear":false,"relations_hidden":false,"relations_other":"","relations":"Дитина","name_hidden":false,"family_name":"Піскун В. С","name_unclear":false},{"inn":"","relations":"Дитина","relations_other":"","inn_hidden":false,"family_name":"Піскун Є. С","name_hidden":false,"name_unclear":false}],"inn_hidden":true,"family_raw":"","last_name":"Піскун","post":{"post_unclear":false,"post":"суддя апеляційного суду, секретар судової палати апеляційного суду дніпропетровського суду з розгляду кримінальних справ","candidate":"","office_hidden":false,"region":"Дніпропетровська область","office":"Загальний апеляційний суд","office_unclear":false,"region_hidden":false},"full_name_suggest":{"output":"Піскун Оксана Павлівна","input":["Піскун Оксана Павлівна","Оксана Павлівна Піскун","Оксана Піскун"]},"full_name":"Піскун Оксана Павлівна","addresses":[{"place_city_type_unclear":false,"place_address":"","place_district_hidden":true,"place_city_type":"","place_city_hidden":true,"place_city_type_hidden":true,"place":"","place_district":"","place_unclear":false,"place_city":"","place_city_unclear":false,"place_hidden":true,"place_address_hidden":true}],"patronymic":"Павлівна","last_name_unclear":false,"name_unclear":false},"source":"VULYK","estate":{"25":[{"space_unclear":false,"costs":"","costs_comment":"","address_hidden":false,"region_hidden":true,"space_comment":"","space_hidden":false,"space":"63.1","address":"","region":"","costs_rent_comment":"","space_comment_unclear":false,"space_comment_hidden":false,"space_units":"м²","costs_rent":""}],"31":[{"space_unclear":false,"address_hidden":false,"region_hidden":true,"space_comment":"","space_hidden":false,"space":"13.1","address":"","region":"","costs_property":"","costs_rent_comment":"","space_comment_unclear":false,"space_units":"м²","costs_property_comment":"","costs_rent":""}]},"intro":{"declaration_year":"2013","isnotdeclaration":"","declaration_year_unclear":false,"declaration_year_hidden":false}}