{"income":{"5":{"family_comment":"","value":"262793","value_unclear":false,"family":"","comment":""},"6":{"value":"256145","value_unclear":false,"family_hidden":false,"family_comment":"","family":"","comment":""},"7":{"source_name_unclear":true,"value":"545","family_comment":"","source_name":"НШСУ","family":"","comment":""},"8":{"family_comment":"","value":"","family":"","comment":""},"9":{"family_comment":"","value":"2930","family":"","comment":""},"10":{"family_comment":"","value":"","family":"","comment":""},"11":{"family_comment":"","value":"","comment_unclear":false,"family":"","comment":""},"12":{"family_comment":"","value":"","family":"","comment":""},"13":{"family_comment":"","value":"","family":"","comment":""},"14":{"family_comment":"","value":"","family":"","comment":""},"15":{"family_comment":"","value":"3173","family":"","comment":""},"16":{"family_comment":"","value":"3173","family":"","comment":""},"17":{"family_comment":"","value":"","family":"","comment":""},"18":{"family_comment":"","value":"","family":"","comment":""},"19":{"family_comment":"","value":"","family":"","comment":""},"20":{"value":"","family_comment":"","value_unclear":false,"family_unclear":false,"comment_unclear":false,"comment":"","family":""}},"vehicle":{"35":[{"brand_info":"","sum_rent_comment":"","brand":"Volkswagen Tiguan","sum_comment":"","brand_unclear":false,"year":"2012","sum_rent_unclear":false,"brand_info_hidden":false,"brand_info_unclear":false,"sum":"","sum_rent":""}]},"id":"vulyk_101_26","declaration":{"additional_info_text":"","notfull_lostpages":"","date":"2016-03-25T00:00:00","notfull":"","additional_info":"","url":"http://static.declarations.com.ua/declarations/chosen_ones/judges_batch/690_kadehrob_albina_ivanivna_2015.pdf"},"liabilities":{"54":{"sum_foreign_comment":"","sum":"","sum_comment":"","sum_comment_unclear":false,"sum_hidden":false,"sum_comment_hidden":false,"sum_unclear":false,"sum_foreign":""},"55":{"sum_foreign_comment":"","sum":"","sum_comment":"","sum_foreign":""},"56":{"sum_foreign_comment":"","sum":"","sum_comment":"","sum_comment_hidden":false,"sum_unclear":false,"sum_foreign":""},"57":{"sum_foreign_comment":"","sum":"32063","sum_comment":"","sum_hidden":false,"sum_comment_hidden":false,"sum_unclear":false,"sum_foreign":""},"58":{"sum_foreign_comment":"","sum":"3669","sum_comment":"","sum_comment_unclear":false,"sum_hidden":false,"sum_comment_hidden":false,"sum_unclear":false,"sum_foreign":""},"59":{"sum_foreign_comment":"","sum":"","sum_comment":"","sum_foreign":""},"60":{"sum_foreign_comment":"","sum":"","sum_comment":"","sum_hidden":false,"sum_comment_hidden":false,"sum_unclear":false,"sum_foreign":""},"61":{"sum_foreign_comment":"","sum":"","sum_comment":"","sum_foreign":""},"62":{"sum_foreign_comment":"","sum":"","sum_comment":"","sum_comment_unclear":false,"sum_foreign":""},"63":{"sum_foreign_comment":"","sum_comment_hidden":false,"sum":"","sum_comment":"","sum_foreign":""},"64":{"sum_foreign_comment":"","sum_comment_hidden":false,"sum":"","sum_comment":"","sum_foreign":""}},"ft_src":"32063\n3669\nсуддя апеляційного суду одеської області\nОдеська область\nЗагальний апеляційний суд\nАльбіна\nІванівна\nКадегроб Альбіна Іванівна\nКадегроб\nКадегроб Альбіна Іванівна\nАльбіна Іванівна Кадегроб\nАльбіна Кадегроб\nКадегроб Альбіна Іванівна\nVolkswagen Tiguan\n2012\n.1\n2015\n256145\n3173\n2930\nНШСУ\n545\n262793\n3173\nVolkswagen Tiguan\n2012\n2015\nКадегроб Альбіна Іванівна\nАльбіна Іванівна Кадегроб\nАльбіна Кадегроб\nКадегроб Альбіна Іванівна\nАльбіна\nКадегроб Альбіна Іванівна\nКадегроб\nЗагальний апеляційний суд\nсуддя апеляційного суду одеської області\nОдеська область\nІванівна\n3669\n32063\n545\nНШСУ\n256145\n3173\n262793\n3173\n2930\n.1\n3669\n32063\nІванівна\nКадегроб\nАльбіна\nКадегроб Альбіна Іванівна\nАльбіна Іванівна Кадегроб\nАльбіна Кадегроб\nКадегроб Альбіна Іванівна\nсуддя апеляційного суду одеської області\nЗагальний апеляційний суд\nОдеська область\nКадегроб Альбіна Іванівна\n2012\nVolkswagen Tiguan\n3173\n2930\n262793\n3173\n545\nНШСУ\n256145\n.1\n2015","general":{"inn":"","name":"Альбіна","inn_unclear":false,"patronymic":"Іванівна","inn_hidden":true,"family_raw":"","last_name":"Кадегроб","post":{"region":"Одеська область","region_unclear":false,"post":"суддя апеляційного суду одеської області","office_unclear":false,"office":"Загальний апеляційний суд"},"full_name":"Кадегроб Альбіна Іванівна","addresses":[{"place_district":"","place_city_hidden":true,"place_city":"","place_city_type_hidden":false,"place_district_hidden":false,"place_city_type":"","place_address_hidden":true,"place_address":"","place_hidden":true,"place":""}],"patronymic_hidden":false,"full_name_suggest":{"output":"Кадегроб Альбіна Іванівна","input":["Кадегроб Альбіна Іванівна","Альбіна Іванівна Кадегроб","Альбіна Кадегроб"]}},"source":"VULYK","estate":{"23":[{"space_unclear":false,"costs":"","costs_comment":"","address_hidden":false,"region_hidden":true,"space_comment":"","space_hidden":false,"space":".1","address":"","costs_comment_unclear":false,"region":"","space_units_unclear":false,"space_units":"га","costs_rent":"","costs_rent_comment":""}]},"intro":{"declaration_year":"2015"}}