{"income":{"5":{"family_comment":"","value":"264105","family":"277654","comment":""},"6":{"family_comment":"","value":"250707","family":"241309","comment":""},"7":{"family_comment":"","value":"","source_name":"","family":"6667","comment":""},"8":{"family_comment":"","value":"","family":"","comment":""},"9":{"value":"","comment_unclear":false,"family_comment":"","family":"","comment":"","family_comment_unclear":false},"10":{"family_comment":"","value":"13398","family":"13398","comment":""},"11":{"family_comment":"","value":"","family":"","comment":""},"12":{"family_comment":"","value":"","family":"","comment":""},"13":{"family_comment":"","value":"","family":"","comment":""},"14":{"family_comment":"","value":"","family":"","comment":""},"15":{"family_comment":"","value":"","family":"16280","comment":""},"16":{"family_comment":"","value":"","family":"","comment":""},"17":{"family_comment":"","value":"","family":"","comment":""},"18":{"family_comment":"","value":"","family":"","comment":""},"19":{"value":"","family_comment":"","value_unclear":false,"family_unclear":false,"family":"","comment":""},"20":{"value":"","family_comment":"","value_unclear":false,"comment_hidden":false,"family_comment_hidden":false,"family_unclear":false,"family_comment_unclear":false,"comment_unclear":false,"comment":"","family":""}},"vehicle":{"40":[{"year_hidden":false,"brand_info":"2987 куб. см., 165 кВт","sum_rent_comment":"","brand":"Mercedes-Benz GL 350","sum_comment":"","year":"2010","brand_hidden":false,"brand_info_hidden":false,"brand_info_unclear":false,"sum":"","sum_rent":""},{"brand_info":"1995 куб. см., 103 кВт","sum_rent_comment":"","brand":"Suzuki Grand Vitara","sum_comment":"","year":"2005","brand_info_hidden":false,"sum":"","sum_rent":""}]},"id":"vulyk_106_53","declaration":{"additional_info_text":"","notfull_lostpages":"","date":"2016-03-30T00:00:00","notfull":"","additional_info":"","url":"http://static.declarations.com.ua/declarations/chosen_ones/judges_batch/2192_kostiv_tetiana_serhiivna.pdf"},"liabilities":{"54":{"sum_foreign_comment":"","sum":"","sum_comment":"","sum_comment_unclear":false,"sum_hidden":false,"sum_comment_hidden":false,"sum_foreign":""},"55":{"sum_foreign_comment":"","sum":"","sum_hidden":false,"sum_comment":"","sum_foreign":""},"56":{"sum_foreign_comment":"","sum":"","sum_comment":"","sum_hidden":false,"sum_comment_hidden":false,"sum_unclear":false,"sum_foreign":""},"57":{"sum_foreign_comment":"","sum":"","sum_comment":"","sum_hidden":false,"sum_comment_hidden":false,"sum_foreign":""},"58":{"sum_foreign_comment":"","sum":"","sum_comment":"","sum_hidden":false,"sum_comment_hidden":false,"sum_foreign":""},"59":{"sum_foreign_comment":"","sum":"","sum_comment":"","sum_foreign":""},"60":{"sum_foreign_comment":"","sum":"","sum_comment":"","sum_hidden":false,"sum_comment_hidden":false,"sum_foreign":""},"61":{"sum_foreign_comment":"","sum":"","sum_comment":"","sum_foreign":""},"62":{"sum_foreign_comment":"","sum":"","sum_comment":"","sum_comment_hidden":false,"sum_unclear":false,"sum_foreign":""},"63":{"sum_foreign_comment":"","sum":"","sum_comment":"","sum_foreign":""},"64":{"sum_foreign_comment":"","sum":"","sum_comment":"","sum_foreign":""}},"ft_src":"суддя, заступник голови львівського апеляційного господарського суду\nЛьвівська область\nАпеляційний господарський суд\nТетяна\nКостів М. В\nПодружжя\nКостів Г. М\nІнше\nсвекруха\nСергіївна\nКостів Тетяна Сергіївна\nТетяна Сергіївна Костів\nТетяна Костів\nКостів Тетяна Сергіївна\nКостів Тетяна Сергіївна\nКостів\n2987 куб. см., 165 кВт\nMercedes-Benz GL 350\n2010\n1995 куб. см., 103 кВт\n2005\nSuzuki Grand Vitara\n19\n500\n2270\n590\n1200\n175\n54\n2015\n241309\n250707\n16280\n13398\n13398\n6667\n277654\n264105\n2987 куб. см., 165 кВт\n2010\nMercedes-Benz GL 350\nSuzuki Grand Vitara\n1995 куб. см., 103 кВт\n2005\n500\n2270\n590\n1200\n19\n175\n54\nКостів Тетяна Сергіївна\nТетяна Сергіївна Костів\nТетяна Костів\nКостів Тетяна Сергіївна\nКостів Тетяна Сергіївна\nПодружжя\nКостів М. В\nІнше\nсвекруха\nКостів Г. М\nТетяна\nКостів\nЛьвівська область\nАпеляційний господарський суд\nсуддя, заступник голови львівського апеляційного господарського суду\nСергіївна\n6667\n250707\n241309\n16280\n264105\n277654\n13398\n13398\n2015\nКостів М. В\nПодружжя\nсвекруха\nКостів Г. М\nІнше\nСергіївна\nКостів\nТетяна\nКостів Тетяна Сергіївна\nТетяна Сергіївна Костів\nТетяна Костів\nКостів Тетяна Сергіївна\nЛьвівська область\nАпеляційний господарський суд\nсуддя, заступник голови львівського апеляційного господарського суду\nКостів Тетяна Сергіївна\nMercedes-Benz GL 350\n2987 куб. см., 165 кВт\n2010\nSuzuki Grand Vitara\n1995 куб. см., 103 кВт\n2005\n16280\n13398\n13398\n277654\n264105\n6667\n241309\n250707\n54\n175\n500\n2270\n590\n1200\n19\n2015","general":{"inn":"","name":"Тетяна","inn_unclear":false,"family":[{"inn":"","inn_hidden":true,"relations_unclear":false,"relations_hidden":false,"relations_other":"","relations":"Подружжя","name_hidden":true,"family_name":"Костів М. В","name_unclear":false},{"inn":"","relations":"Інше","relations_unclear":false,"family_name":"Костів Г. М","inn_hidden":false,"relations_other":"свекруха","name_hidden":false,"name_unclear":false}],"inn_hidden":true,"family_raw":"","last_name":"Костів","post":{"region_unclear":false,"region":"Львівська область","post":"суддя, заступник голови львівського апеляційного господарського суду","office":"Апеляційний господарський суд","office_unclear":false,"post_hidden":false},"full_name":"Костів Тетяна Сергіївна","addresses":[{"place_district":"","place_city_hidden":true,"place_city":"","place_city_type_hidden":true,"place_district_hidden":true,"place_city_type":"","place_address_hidden":true,"place_address":"","place_hidden":true,"place":""}],"patronymic":"Сергіївна","full_name_suggest":{"output":"Костів Тетяна Сергіївна","input":["Костів Тетяна Сергіївна","Тетяна Сергіївна Костів","Тетяна Костів"]},"name_unclear":false},"source":"VULYK","estate":{"25":[{"costs":"","costs_comment":"","address_hidden":true,"region_hidden":true,"space_comment":"","space":"54","address":"","region":"","costs_rent_comment":"","space_comment_unclear":false,"space_units":"м²","costs_rent":""}],"27":[{"space_hidden":false,"costs":"","costs_comment":"","address_hidden":true,"region_hidden":true,"space_comment":"","space":"19","address":"","region":"","costs_rent_comment":"","space_units":"м²","costs_rent":""}],"29":[{"region_unclear":false,"costs_property_comment":"","address_hidden":true,"region_hidden":true,"space_comment":"","space":"500","address":"","costs_rent_comment_unclear":false,"region":"","costs_property":"","costs_rent_comment":"","space_comment_unclear":false,"address_unclear":false,"space_units":"м²","space_units_unclear":false,"costs_rent":""},{"costs_rent":"","region":"","costs_property":"","costs_rent_comment":"","address_hidden":true,"region_hidden":false,"space_comment":"","costs_property_comment":"","space_units":"м²","space":"2270","address":""},{"costs_rent":"","region":"","costs_property":"","costs_rent_comment":"","address_hidden":true,"region_hidden":false,"space_comment":"","costs_property_comment":"","space_units":"м²","space":"590","address":""},{"costs_rent":"","costs_property":"","costs_rent_comment":"","address_hidden":true,"space_comment":"","costs_property_comment":"","space_units":"м²","space":"1200","address":""}],"30":[{"space_unclear":false,"address_hidden":true,"region_hidden":true,"space_comment":"","space_hidden":false,"space":"175","address":"","region":"","costs_property":"","costs_rent_comment":"","space_comment_unclear":false,"space_units":"м²","costs_property_comment":"","costs_rent":""}]},"intro":{"declaration_year":"2015","isnotdeclaration":""}}