{"income":{"5":{"family_comment":"","value":"309632","family":"","comment":""},"6":{"value":"202869","family_comment":"","value_unclear":false,"comment_hidden":false,"family_unclear":false,"family":"","comment":""},"7":{"family_comment":"","value":"16792","source_name":"Національний юридичний університет ім. Ярослава Мудрого","family":"","comment":""},"8":{"family_comment":"","value":"","family":"","comment":""},"9":{"family_comment":"","family_unclear":false,"value":"","family":"","comment":""},"10":{"family_comment":"","value":"","value_unclear":false,"family":"","comment":""},"11":{"family_comment":"","value":"","family":"","comment":""},"12":{"family_comment":"","value":"","family":"","comment":""},"13":{"family_comment":"","value":"","family":"","comment":""},"14":{"family_comment":"","value":"","family":"","comment":""},"15":{"family_comment":"","value":"12933","family":"","comment":""},"16":{"family_comment":"","value":"","family":"","comment":""},"17":{"family_comment":"","value":"","family":"","comment":""},"18":{"family_comment":"","value":"","family":"","comment":""},"19":{"family_comment":"","value":"","family":"","comment":""},"20":{"value":"77038","family":"","value_unclear":false,"family_hidden":false,"family_comment":"","comment_unclear":false,"comment":"","family_comment_unclear":false}},"vehicle":{"35":[{"year_hidden":false,"brand_info":"2494 куб. см.","sum_rent_comment":"","year":"2012","brand_info_hidden":false,"brand_info_unclear":false,"sum_rent":"","sum":"","brand":"Toyota Camry","sum_comment":"","brand_unclear":false,"brand_hidden":false}]},"id":"vulyk_97_107","declaration":{"additional_info_text":"","notfull_lostpages":"","date":"2015-03-30T00:00:00","notfull":"","additional_info":"","url":"http://static.declarations.com.ua/declarations/chosen_ones/judges_batch/4008_nurullaiev_ilkin_sadahat_ohly.pdf"},"liabilities":{"54":{"sum_foreign_comment":"","sum":"14288","sum_comment":"","sum_comment_unclear":false,"sum_hidden":false,"sum_comment_hidden":false,"sum_unclear":false,"sum_foreign":""},"55":{"sum_foreign_comment":"","sum":"","sum_comment":"","sum_foreign":""},"56":{"sum_foreign_comment":"","sum":"","sum_comment":"","sum_foreign":""},"57":{"sum_foreign_comment":"","sum":"","sum_comment":"","sum_comment_unclear":false,"sum_hidden":false,"sum_comment_hidden":false,"sum_unclear":false,"sum_foreign":""},"58":{"sum_foreign_comment":"","sum":"","sum_comment":"","sum_comment_unclear":false,"sum_hidden":false,"sum_comment_hidden":false,"sum_unclear":false,"sum_foreign":""},"59":{"sum_foreign_comment":"","sum":"","sum_comment":"","sum_foreign":""},"60":{"sum_foreign_comment":"","sum":"","sum_comment":"","sum_comment_unclear":false,"sum_hidden":false,"sum_comment_hidden":false,"sum_foreign":""},"61":{"sum_foreign_comment":"","sum":"","sum_comment":"","sum_foreign":""},"62":{"sum_foreign_comment":"","sum":"","sum_comment":"","sum_unclear":false,"sum_foreign":""},"63":{"sum_foreign_comment":"","sum":"","sum_hidden":false,"sum_comment":"","sum_foreign":""},"64":{"sum_foreign_comment":"","sum":"","sum_comment":"","sum_foreign":""}},"ft_src":"14288\nХарків\n61177\nХарківська область\nсуддя харківського окружного адміністративного суду\nХарківська область\nАдміністративний місцевий суд\nІлькін\nНуруллаєва Раміля Рашид кизи\nПодружжя\nНуруллаєва Сабіна Ількін кизи\nДитина\nНуруллаєва Лейла Ількінівна\nДитина\nСадагат Огли\nНуруллаєв Ількін Садагат Огли\nІлькін Садагат Огли Нуруллаєв\nІлькін Нуруллаєв\nНуруллаєв Ількін Садагат Огли\nНуруллаєв Ількін Садагат Огли\nНуруллаєв\n2494 куб. см.\nToyota Camry\n2012\n32.2\nХарківська область\nм. Харків\nм. Харків\nХарківська область\n534.1\nм. Харків\nХарківська область\n2000\n65\nм. Харків\nХарківська область\n2014\n202869\n12933\n16792\nНаціональний юридичний університет ім. Ярослава Мудрого\n309632\n77038\n2494 куб. см.\nToyota Camry\n2012\n2014\nНуруллаєв Ількін Садагат Огли\nІлькін Садагат Огли Нуруллаєв\nІлькін Нуруллаєв\nНуруллаєв Ількін Садагат Огли\nІлькін\nПодружжя\nНуруллаєва Раміля Рашид кизи\nДитина\nНуруллаєва Сабіна Ількін кизи\nДитина\nНуруллаєва Лейла Ількінівна\nНуруллаєв Ількін Садагат Огли\nНуруллаєв\nАдміністративний місцевий суд\nХарківська область\nсуддя харківського окружного адміністративного суду\nСадагат Огли\nХарківська область\n61177\nХарків\n14288\nНаціональний юридичний університет ім. Ярослава Мудрого\n16792\n202869\n77038\n12933\n309632\n2000\nХарківська область\nм. Харків\n534.1\nХарківська область\nм. Харків\n32.2\nХарківська область\nм. Харків\n65\nм. Харків\nХарківська область\n14288\nПодружжя\nНуруллаєва Раміля Рашид кизи\nНуруллаєва Сабіна Ількін кизи\nДитина\nДитина\nНуруллаєва Лейла Ількінівна\nСадагат Огли\nНуруллаєв\nІлькін\nНуруллаєв Ількін Садагат Огли\nІлькін Садагат Огли Нуруллаєв\nІлькін Нуруллаєв\nНуруллаєв Ількін Садагат Огли\n61177\nХарків\nХарківська область\nХарківська область\nАдміністративний місцевий суд\nсуддя харківського окружного адміністративного суду\nНуруллаєв Ількін Садагат Огли\n2012\nToyota Camry\n2494 куб. см.\n12933\n77038\n309632\nНаціональний юридичний університет ім. Ярослава Мудрого\n16792\n202869\nм. Харків\nХарківська область\n32.2\nм. Харків\nХарківська область\n534.1\nм. Харків\nХарківська область\n65\nм. Харків\nХарківська область\n2000\n2014","general":{"name_hidden":false,"name":"Ількін","last_name_hidden":false,"inn":"","family":[{"inn":"","relations":"Подружжя","relations_other":"","inn_hidden":true,"family_name":"Нуруллаєва Раміля Рашид кизи","name_hidden":true,"name_unclear":true},{"inn_hidden":true,"inn":"","name_hidden":false,"family_name":"Нуруллаєва Сабіна Ількін кизи","relations":"Дитина","name_unclear":true},{"inn":"","relations":"Дитина","relations_other":"","inn_hidden":true,"family_name":"Нуруллаєва Лейла Ількінівна","name_hidden":false,"name_unclear":false}],"patronymic":"Садагат Огли","inn_hidden":true,"family_raw":"","inn_unclear":false,"post":{"region_unclear":false,"region":"Харківська область","post":"суддя харківського окружного адміністративного суду","office":"Адміністративний місцевий суд","office_unclear":false,"post_hidden":false},"full_name":"Нуруллаєв Ількін Садагат Огли","addresses":[{"place_district":"","place_city_hidden":false,"place_city":"Харків","place_city_unclear":false,"place_district_hidden":false,"place_city_type":"Місто","place_address_hidden":true,"place_city_type_hidden":false,"place_address":"61177","place_hidden":false,"place":"Харківська область"}],"last_name":"Нуруллаєв","patronymic_hidden":false,"full_name_suggest":{"output":"Нуруллаєв Ількін Садагат Огли","input":["Нуруллаєв Ількін Садагат Огли","Ількін Садагат Огли Нуруллаєв","Ількін Нуруллаєв"]}},"source":"VULYK","estate":{"25":[{"region_unclear":false,"space_unclear":false,"costs":"","costs_comment":"","address_hidden":true,"region_hidden":false,"space_comment":"","space_hidden":false,"space":"65","address":"м. Харків","region":"Харківська область","costs_rent_comment":"","space_comment_unclear":false,"space_comment_hidden":false,"space_units":"м²","costs_rent":""}],"29":[{"region_unclear":false,"space_unclear":false,"address_hidden":true,"region_hidden":false,"space_comment":"","space":"2000","address":"м. Харків","region":"Харківська область","costs_property":"","costs_rent_comment":"","space_comment_unclear":false,"address_unclear":false,"space_units":"м²","costs_property_comment":"","costs_rent":""}],"30":[{"address_hidden":true,"region_hidden":false,"space_comment":"","space":"534.1","address":"м. Харків","region":"Харківська область","costs_property":"","costs_rent_comment":"","address_unclear":false,"space_units":"м²","costs_property_comment":"","costs_rent":""}],"31":[{"space_unclear":false,"address_hidden":true,"region_hidden":false,"space_comment":"","space_hidden":false,"space":"32.2","address":"м. Харків","region":"Харківська область","costs_property":"","costs_rent_comment":"","space_comment_hidden":false,"space_units":"м²","costs_property_comment":"","costs_rent":""}]},"intro":{"declaration_year":"2014","isnotdeclaration":""}}