{"income":{"5":{"value":"47317.4","family_comment":"","value_unclear":false,"comment_hidden":false,"family_hidden":false,"value_hidden":false,"family_unclear":false,"family":"","comment":""},"6":{"value":"47317.4","family_comment":"","value_unclear":false,"family_hidden":false,"family_unclear":false,"comment_unclear":false,"comment":"","family":""},"7":{"source_name_unclear":false,"value":"","value_hidden":false,"family_comment":"","source_name":"","family":"","comment":"","source_name_hidden":false},"8":{"value":"","family_hidden":false,"value_hidden":false,"family_comment":"","family":"","comment":""},"9":{"value":"","family_comment":"","value_unclear":false,"family_hidden":false,"value_hidden":false,"family_unclear":false,"family":"","comment":""},"10":{"family_comment":"","value":"","family":"","comment":""},"11":{"family_comment":"","value":"","family":"","comment":""},"12":{"family_comment":"","value":"","family":"","comment":""},"13":{"family_comment":"","value":"","family":"","comment":""},"14":{"family_comment":"","value":"","family":"","comment":""},"15":{"family_comment":"","value":"","family":"","comment":""},"16":{"value":"","family_comment":"","value_unclear":false,"family_unclear":false,"family":"","comment":""},"17":{"family_comment":"","value":"","family":"","comment":""},"18":{"family_comment":"","value":"","family":"","comment":""},"19":{"family_comment":"","value":"","comment_unclear":false,"family":"","comment":""},"20":{"value":"","family_comment":"","value_unclear":false,"comment_hidden":false,"family_hidden":false,"family":"","value_hidden":false,"family_unclear":false,"comment_unclear":false,"comment":"","family_comment_unclear":false}},"vehicle":{"35":[{"brand_info":"2967","sum_rent_comment":"","brand":"Volkswagen Touareg","sum_comment":"","brand_unclear":false,"year":"2010","brand_info_unclear":false,"sum":"","sum_rent":""}]},"id":"vulyk_63_137","banks":{"45":[{"sum_foreign_comment":"","sum_units":"UAH","sum_comment":"","sum_foreign_unclear":false,"sum_foreign_units":"UAH","sum_foreign_hidden":false,"sum_hidden":false,"sum_comment_hidden":false,"sum_unclear":false,"sum":"228524.17","sum_foreign":""}]},"declaration":{"additional_info_text":"","notfull_lostpages":"","date":"2015-03-27T00:00:00","notfull":"","additional_info":"","url":"http://static.declarations.com.ua/declarations/chosen_ones/mega_batch/kuzmenko_nataliia_leonidivna.pdf"},"liabilities":{"54":{"sum_foreign_comment":"","sum":"","sum_comment":"","sum_unclear":false,"sum_foreign":""},"55":{"sum_foreign_comment":"","sum":"","sum_comment":"","sum_foreign":""},"56":{"sum_foreign_comment":"","sum":"","sum_comment":"","sum_unclear":false,"sum_foreign":""},"57":{"sum_foreign_comment":"","sum":"","sum_comment":"","sum_comment_hidden":false,"sum_unclear":false,"sum_foreign":""},"58":{"sum_foreign_comment":"","sum_comment_hidden":false,"sum":"","sum_comment":"","sum_foreign":""},"59":{"sum_foreign_comment":"","sum":"","sum_comment":"","sum_foreign":""},"60":{"sum_foreign_comment":"","sum":"","sum_comment":"","sum_comment_unclear":false,"sum_foreign":""},"61":{"sum_foreign_comment":"","sum":"","sum_comment":"","sum_unclear":false,"sum_foreign":""},"62":{"sum_foreign_comment":"","sum":"","sum_comment":"","sum_unclear":false,"sum_foreign":""},"63":{"sum_foreign_comment":"","sum":"","sum_comment":"","sum_hidden":false,"sum_comment_hidden":false,"sum_unclear":false,"sum_foreign":""},"64":{"sum_foreign_comment":"","sum_comment_hidden":false,"sum":"","sum_comment":"","sum_foreign":""}},"ft_src":"суддя приморського районного суду м. одеси\nОдеська область\nЗагальний місцевий суд\nНаталія\nКузьменко О. Г\nДитина\nКузьменко М. С\nДитина\nЛеонідівна\nКузьменко\nКузьменко Наталія Леонідівна\nКузьменко Наталія Леонідівна\nНаталія Леонідівна Кузьменко\nНаталія Кузьменко\nКузьменко Наталія Леонідівна\n2010\nVolkswagen Touareg\n2967\n228524.17\n2014\n2967\n2010\nVolkswagen Touareg\n228524.17\n600\n172.36\nЛеонідівна\nКузьменко Наталія Леонідівна\nНаталія Леонідівна Кузьменко\nНаталія Кузьменко\nКузьменко Наталія Леонідівна\nНаталія\nДитина\nКузьменко О. Г\nДитина\nКузьменко М. С\nКузьменко Наталія Леонідівна\nЗагальний місцевий суд\nОдеська область\nсуддя приморського районного суду м. одеси\nКузьменко\n47317.4\n47317.4\n2014\n600\n172.36\nДитина\nКузьменко О. Г\nДитина\nКузьменко М. С\nЛеонідівна\nКузьменко\nКузьменко Наталія Леонідівна\nНаталія Леонідівна Кузьменко\nНаталія Кузьменко\nКузьменко Наталія Леонідівна\nНаталія\nОдеська область\nсуддя приморського районного суду м. одеси\nЗагальний місцевий суд\nКузьменко Наталія Леонідівна\n47317.4\n47317.4\n2010\n2967\nVolkswagen Touareg\n47317.4\n47317.4\n172.36\n600\n228524.17\n2014","general":{"name_hidden":false,"name":"Наталія","patronymic_unclear":false,"last_name_hidden":false,"inn":"","family":[{"inn":"","inn_hidden":true,"relations_unclear":false,"relations_hidden":false,"relations_other":"","relations":"Дитина","name_hidden":true,"inn_unclear":false,"family_name":"Кузьменко О. Г","name_unclear":false},{"inn":"","relations":"Дитина","relations_unclear":false,"family_name":"Кузьменко М. С","inn_hidden":true,"relations_other":"","name_hidden":false,"inn_unclear":false,"name_unclear":false}],"patronymic":"Леонідівна","inn_hidden":true,"family_raw":"","inn_unclear":false,"post":{"post_unclear":false,"region_unclear":false,"region":"Одеська область","office_hidden":false,"region_hidden":false,"post":"суддя приморського районного суду м. одеси","office_unclear":false,"office":"Загальний місцевий суд"},"last_name_unclear":false,"full_name":"Кузьменко Наталія Леонідівна","addresses":[{"place_city_type_unclear":false,"place_address":"","place_district_hidden":true,"place_city_type":"","place_address_hidden":true,"place_address_unclear":false,"place_city_type_hidden":true,"place":"","place_district":"","place_unclear":false,"place_city":"","place_city_unclear":false,"place_hidden":true,"place_city_hidden":true,"place_district_unclear":false}],"last_name":"Кузьменко","full_name_suggest":{"output":"Кузьменко Наталія Леонідівна","input":["Кузьменко Наталія Леонідівна","Наталія Леонідівна Кузьменко","Наталія Кузьменко"]},"name_unclear":false},"source":"VULYK","estate":{"23":[{"space_unclear":false,"costs":"","costs_comment":"","costs_hidden":false,"address_hidden":true,"region_hidden":true,"space_comment":"","space_hidden":false,"space":"600","address":"","region":"","space_units_unclear":false,"costs_rent_hidden":false,"space_units":"м²","space_units_hidden":false,"costs_rent":"","costs_rent_comment":""}],"25":[{"region_unclear":false,"space_unclear":false,"costs":"","costs_comment":"","costs_hidden":false,"address_hidden":true,"region_hidden":true,"space_comment":"","space_hidden":false,"space":"172.36","space_units_hidden":false,"region":"","address_unclear":false,"costs_rent_comment":"","costs_rent_hidden":false,"space_comment_unclear":false,"costs_rent_comment_hidden":false,"space_units":"м²","address":"","costs_comment_hidden":false,"costs_rent":""}]},"intro":{"declaration_year":"2014","isnotdeclaration":"","declaration_year_unclear":false}}