{"income":{"5":{"family_comment":"","value":"240993","family":"15350","comment":""},"6":{"family_comment":"","value":"227595","value_unclear":false,"family":"","comment":""},"7":{"value":"","family_comment":"","source_name":"","family":"","comment":"","source_name_hidden":false},"8":{"family_comment":"","value":"","family":"","comment":""},"9":{"family_comment":"","value":"","family":"","comment":""},"10":{"family_comment":"","value":"13398","family":"","comment":""},"11":{"family_comment":"","value":"","comment_hidden":false,"family":"","comment":""},"12":{"family_comment":"","value":"","family":"","comment":""},"13":{"family_comment":"","value":"","family":"","comment":""},"14":{"family_comment":"","value":"","family":"","comment":""},"15":{"value":"","family_comment":"","value_unclear":false,"family_unclear":false,"family":"","comment":""},"16":{"family_comment":"","value":"","family":"","comment":""},"17":{"family_comment":"","value":"","family":"","comment":""},"18":{"family_comment":"","value":"","family":"","comment":""},"19":{"family_comment":"","value":"","family":"","comment":""},"20":{"family_comment":"пенсія, стипендія","value":"","comment_unclear":false,"family":"15350","comment":""}},"vehicle":{"35":[{"brand_info":"1.6 л","sum_rent_comment":"","brand":"Seat","sum_comment":"власність","year":"1995","brand_hidden":false,"brand_info_unclear":false,"sum":"","sum_rent":""}]},"id":"vulyk_104_110","banks":{"45":[{"sum_foreign_comment":"","sum_units":"UAH","sum_comment":"","sum_hidden":false,"sum_foreign_units":"UAH","sum_foreign_hidden":false,"sum_comment_hidden":false,"sum_unclear":false,"sum":"3463","sum_foreign":""}]},"declaration":{"date":"2016-03-24T00:00:00","additional_info_text":"","additional_info":"","url":"http://static.declarations.com.ua/declarations/chosen_ones/judges_batch/1908_zimina_veronika_borysivna_2015.pdf"},"liabilities":{"54":{"sum_foreign_comment":"","sum_foreign_hidden":false,"sum_comment":"","sum_hidden":false,"sum_comment_hidden":false,"sum_unclear":false,"sum":"","sum_foreign":""},"55":{"sum_foreign_comment":"","sum":"","sum_comment":"","sum_foreign":""},"56":{"sum_foreign_comment":"","sum":"","sum_comment":"","sum_unclear":false,"sum_foreign":""},"57":{"sum_foreign_comment":"","sum_foreign_hidden":false,"sum_comment":"","sum_comment_unclear":false,"sum_comment_hidden":false,"sum":"","sum_foreign":""},"58":{"sum_foreign_comment":"","sum":"","sum_comment":"","sum_unclear":false,"sum_foreign":""},"59":{"sum_foreign_comment":"","sum":"","sum_comment":"","sum_foreign":""},"60":{"sum_foreign_comment":"","sum_foreign_hidden":false,"sum_comment":"","sum_comment_hidden":false,"sum":"","sum_foreign":""},"61":{"sum_foreign_comment":"","sum":"","sum_comment":"","sum_foreign":""},"62":{"sum_foreign_comment":"","sum":"","sum_comment":"","sum_foreign":""},"63":{"sum_foreign_comment":"","sum":"","sum_comment":"","sum_foreign":""},"64":{"sum_foreign_comment":"","sum":"","sum_comment":"","sum_foreign":""}},"ft_src":"Зіміна Вероніка Борисівна\nсуддя апеляційного суду київської області\nКиївська область\nЗагальний апеляційний суд\nВероніка\nМарченко А. В. 26. 10. 1993\nДитина\nЗіміна Вероніка Борисівна\nВероніка Борисівна Зіміна\nВероніка Зіміна\nЗіміна Вероніка Борисівна\nЗіміна\nБорисівна\nвласність\n1995\nSeat\n1.6 л\n3463\n2015\n1.6 л\nSeat\n1995\nвласність\n3463\n2015\nДитина\nМарченко А. В. 26. 10. 1993\nЗіміна\nЗіміна Вероніка Борисівна\nВероніка Борисівна Зіміна\nВероніка Зіміна\nЗіміна Вероніка Борисівна\nЗіміна Вероніка Борисівна\nВероніка\nБорисівна\nЗагальний апеляційний суд\nсуддя апеляційного суду київської області\nКиївська область\n227595\n15350\nпенсія, стипендія\n240993\n15350\n13398\n.15\nвласність\nвласність\n.25\n46.4\nвласність\n45.5\n45.5\nвласність\nвласність\n77.7\nвласність\n.15\nвласність\n.25\n45.5\nвласність\n46.4\nвласність\n45.5\nвласність\n77.7\nДитина\nМарченко А. В. 26. 10. 1993\nБорисівна\nЗіміна\nсуддя апеляційного суду київської області\nЗагальний апеляційний суд\nКиївська область\nЗіміна Вероніка Борисівна\nЗіміна Вероніка Борисівна\nВероніка Борисівна Зіміна\nВероніка Зіміна\nЗіміна Вероніка Борисівна\nВероніка\n227595\n13398\n15350\n240993\n15350\nпенсія, стипендія\nвласність\n1995\n1.6 л\nSeat\n13398\n15350\nпенсія, стипендія\n15350\n240993\n227595\n45.5\n.15\nвласність\nвласність\n.25\n46.4\nвласність\n45.5\nвласність\nвласність\n77.7\n3463\n2015","general":{"inn":"","inn_hidden":true,"last_name":"Зіміна","post":{"region":"Київська область","region_unclear":false,"post":"суддя апеляційного суду київської області","office_unclear":false,"office":"Загальний апеляційний суд"},"name":"Вероніка","full_name":"Зіміна Вероніка Борисівна","family_raw":"","addresses":[{"place_district":"","place_city_hidden":true,"place_city":"","place_city_type_hidden":false,"place_district_hidden":false,"place_city_type":"","place_address_hidden":true,"place_address":"","place_hidden":true,"place":""}],"family":[{"inn":"","relations":"Дитина","relations_other":"","inn_hidden":true,"family_name":"Марченко А. В. 26. 10. 1993","name_hidden":false,"name_unclear":false}],"full_name_suggest":{"output":"Зіміна Вероніка Борисівна","input":["Зіміна Вероніка Борисівна","Вероніка Борисівна Зіміна","Вероніка Зіміна"]},"patronymic":"Борисівна"},"source":"VULYK","estate":{"23":[{"space_hidden":false,"costs":"","costs_comment":"власність","address_hidden":false,"region_hidden":true,"space_comment":"","space":".15","address":"","region":"","costs_rent_comment":"","space_comment_unclear":false,"space_units":"га","costs_rent":""},{"costs_rent":"","costs_rent_comment_unclear":false,"region":"","costs":"","costs_rent_comment":"","costs_comment":"власність","space_comment_unclear":false,"space_comment":"","space_units":"га","space":".25","address":""}],"24":[{"space_hidden":false,"costs":"","costs_comment":"власність","address_hidden":false,"region_hidden":true,"space_comment":"","space":"46.4","address":"","region":"","costs_rent_comment":"","space_comment_unclear":false,"space_units":"м²","costs_rent":""}],"25":[{"costs":"","costs_comment":"власність","address_hidden":false,"region_hidden":true,"space_comment":"","space":"45.5","address":"","costs_unclear":false,"region":"","costs_rent_comment":"","space_comment_unclear":false,"space_units":"м²","costs_rent":""},{"costs_rent":"","space_comment_unclear":false,"region":"","costs":"","costs_rent_comment":"","costs_comment":"власність","costs_unclear":false,"space_comment":"","space_units":"м²","space":"77.7","address":""}],"31":[{"space_unclear":false,"address_hidden":false,"region_hidden":true,"space_comment":"","space_hidden":false,"space":"45.5","address":"","region":"","costs_property":"","costs_rent_comment":"","space_units":"м²","costs_property_comment":"","costs_rent":""}]},"intro":{"declaration_year":"2015","isnotdeclaration":""}}