{"income":{"5":{"family_comment":"","family_unclear":false,"value":"236482","family":"76243","comment":""},"6":{"family_comment":"","family_unclear":false,"value":"223084","family":"62599","comment":""},"7":{"value":"","comment_hidden":false,"family_comment":"","source_name":"","family":"","comment":""},"8":{"family_comment":"","value":"","family":"","comment":""},"9":{"family_comment":"","value":"","family":"","comment":""},"10":{"family_comment":"","value":"13398","family":"","comment":""},"11":{"family_comment":"","value":"","value_unclear":false,"family":"","comment":""},"12":{"family_comment":"","value":"","family":"","comment":""},"13":{"family_comment":"","value":"","family":"","comment":""},"14":{"family_comment":"","value":"","family":"","comment":""},"15":{"family_comment":"","value":"","value_unclear":false,"family":"","comment":""},"16":{"family_comment":"","family_unclear":false,"value":"","family":"","comment":""},"17":{"family_comment":"","value":"","family":"","comment":""},"18":{"family_comment":"","value":"","family_hidden":false,"comment":"","family":""},"19":{"family_comment":"","value":"","family":"","comment":""},"20":{"value":"","comment_unclear":false,"comment_hidden":false,"family_comment":"пенсія","family":"13644","comment":"","family_comment_hidden":false}},"vehicle":{"35":[{"brand_info":"2.0 куб. дм.","sum_rent_comment":"","year":"2008","brand_info_hidden":false,"brand_info_unclear":false,"year_unclear":false,"sum_rent":"","sum":"","brand":"Nissan Qashqai","sum_comment":"","brand_unclear":false,"brand_hidden":false}],"40":[{"brand_info":"2.7 куб. дм.","sum_rent_comment":"","brand":"Chrysler 300C","sum_comment":"","year":"2008","brand_hidden":false,"brand_info_hidden":false,"brand_info_unclear":false,"year_unclear":false,"sum":"","sum_rent":""}]},"id":"vulyk_68_53","declaration":{"additional_info_text":"","notfull_lostpages":"","date":"2015-03-27T00:00:00","notfull":"","additional_info":"","url":"http://static.declarations.com.ua/declarations/chosen_ones/mega_batch/yakimets_hanna_hryhorivna.pdf"},"liabilities":{"54":{"sum_foreign_comment":"","sum":"","sum_comment":"","sum_comment_unclear":false,"sum_hidden":false,"sum_comment_hidden":false,"sum_unclear":false,"sum_foreign":""},"55":{"sum_foreign_comment":"","sum":"","sum_hidden":false,"sum_comment":"","sum_foreign":""},"56":{"sum_foreign_comment":"","sum_foreign_hidden":false,"sum_comment":"","sum":"","sum_unclear":false,"sum_foreign":""},"57":{"sum_foreign_comment":"","sum":"","sum_comment":"","sum_comment_unclear":false,"sum_hidden":false,"sum_comment_hidden":false,"sum_unclear":false,"sum_foreign":""},"58":{"sum_foreign_comment":"","sum":"","sum_comment":"","sum_hidden":false,"sum_comment_hidden":false,"sum_unclear":false,"sum_foreign":""},"59":{"sum_foreign_comment":"","sum":"","sum_comment":"","sum_foreign":""},"60":{"sum_foreign_comment":"","sum":"","sum_comment":"","sum_comment_unclear":false,"sum_hidden":false,"sum_comment_hidden":false,"sum_unclear":false,"sum_foreign":""},"61":{"sum_foreign_comment":"","sum":"","sum_hidden":false,"sum_comment":"","sum_foreign":""},"62":{"sum_foreign_comment":"","sum":"","sum_comment":"","sum_unclear":false,"sum_foreign":""},"63":{"sum_foreign_comment":"","sum":"","sum_comment":"","sum_hidden":false,"sum_comment_hidden":false,"sum_unclear":false,"sum_foreign":""},"64":{"sum_foreign_comment":"","sum":"","sum_comment":"","sum_hidden":false,"sum_comment_hidden":false,"sum_foreign":""}},"ft_src":"суддя\nЛьвівська область\nАпеляційний господарський суд\nГанна\nЯкімець Б. Ю\nДитина\nБанах К. І\nБатьки\nГригорівна\nЯкімець Ганна Григорівна\nГанна Григорівна Якімець\nГанна Якімець\nЯкімець Ганна Григорівна\nЯкімець Ганна Григорівна\nЯкімець\n2.0 куб. дм.\nNissan Qashqai\n2008\n2.7 куб. дм.\nChrysler 300C\n2008\n178\n1650\n2014\n62599\n223084\n13398\n76243\n236482\nпенсія\n13644\n2.0 куб. дм.\nNissan Qashqai\n2008\n2.7 куб. дм.\n2008\nChrysler 300C\n1650\n178\nЯкімець Ганна Григорівна\nГанна Григорівна Якімець\nГанна Якімець\nЯкімець Ганна Григорівна\nЯкімець Ганна Григорівна\nДитина\nЯкімець Б. Ю\nБатьки\nБанах К. І\nГанна\nГригорівна\nАпеляційний господарський суд\nЛьвівська область\nсуддя\nЯкімець\n223084\n62599\nпенсія\n13644\n236482\n76243\n13398\n2014\nДитина\nЯкімець Б. Ю\nБанах К. І\nБатьки\nГригорівна\nЯкімець\nГанна\nЯкімець Ганна Григорівна\nГанна Григорівна Якімець\nГанна Якімець\nЯкімець Ганна Григорівна\nЛьвівська область\nАпеляційний господарський суд\nсуддя\nЯкімець Ганна Григорівна\n2008\nNissan Qashqai\n2.0 куб. дм.\nChrysler 300C\n2.7 куб. дм.\n2008\n13398\nпенсія\n13644\n76243\n236482\n62599\n223084\n178\n1650\n2014","general":{"inn":"","name":"Ганна","inn_unclear":false,"family":[{"inn":"","inn_hidden":true,"relations_unclear":false,"relations_hidden":false,"relations_other":"","relations":"Дитина","name_hidden":false,"inn_unclear":false,"family_name":"Якімець Б. Ю","name_unclear":false},{"inn":"","inn_hidden":false,"inn_unclear":false,"relations_hidden":false,"relations_other":"","relations":"Батьки","name_hidden":false,"family_name":"Банах К. І","name_unclear":false}],"inn_hidden":true,"family_raw":"","last_name":"Якімець","post":{"post_unclear":false,"region_unclear":false,"post":"суддя","office":"Апеляційний господарський суд","region":"Львівська область","post_hidden":false,"office_hidden":false,"office_unclear":false,"region_hidden":false},"full_name_suggest":{"output":"Якімець Ганна Григорівна","input":["Якімець Ганна Григорівна","Ганна Григорівна Якімець","Ганна Якімець"]},"full_name":"Якімець Ганна Григорівна","patronymic":"Григорівна","last_name_unclear":false,"name_unclear":false},"source":"VULYK","estate":{"23":[{"costs":"","costs_comment":"","address_hidden":false,"region_hidden":true,"space_comment":"","space":"","address":"","region":"","costs_rent_comment":"","space_comment_hidden":false,"space_units":"м²","costs_rent":""}],"24":[{"region_unclear":false,"space_unclear":false,"costs":"","costs_comment":"","address_hidden":false,"region_hidden":true,"space_comment":"","space":"","address":"","region":"","costs_rent_comment":"","space_units":"м²","costs_rent":""}],"29":[{"space_unclear":false,"address_hidden":false,"region_hidden":false,"space_comment":"","space_units_hidden":false,"space_hidden":false,"space":"1650","address":"","region":"","costs_property":"","space_units_unclear":false,"space_units":"м²","costs_property_comment":"","costs_rent":"","costs_rent_comment":""}],"30":[{"space_unclear":false,"address_hidden":false,"region_hidden":false,"space_comment":"","space_hidden":false,"space":"178","address":"","region":"","costs_property":"","costs_rent_comment":"","space_units":"м²","costs_property_comment":"","costs_rent":""}]},"intro":{"declaration_year":"2014","isnotdeclaration":""}}