{"income":{"5":{"family_comment":"","family_unclear":false,"value":"191443","family":"45153","comment":""},"6":{"family_comment":"","family_unclear":false,"value":"191443","family":"45153","comment":""},"7":{"value":"","comment_hidden":false,"family_comment":"","source_name":"","family":"","comment":""},"8":{"family_comment":"","value":"","family":"","comment":""},"9":{"family_comment":"","value":"","family":"","comment":""},"10":{"family_comment":"","value":"","family":"","comment":""},"11":{"family_comment":"","value":"","value_unclear":false,"family":"","comment":""},"12":{"family_comment":"","value":"","family":"","comment":""},"13":{"family_comment":"","value":"","family":"","comment":""},"14":{"family_comment":"","value":"","family":"","comment":""},"15":{"family_comment":"","value":"","value_unclear":false,"family":"","comment":""},"16":{"family_comment":"","family_unclear":false,"value":"","family":"","comment":""},"17":{"family_comment":"","value":"","family":"","comment":""},"18":{"family_comment":"","value":"","family_hidden":false,"comment":"","family":""},"19":{"family_comment":"","value":"","family":"","comment":""},"20":{"value":"","comment_unclear":false,"comment_hidden":false,"family_comment":"","family":"","comment":"","family_comment_hidden":false}},"vehicle":{"35":[{"brand_info":"1294 куб. см.","sum_rent_comment":"","year":"1989","brand_info_hidden":false,"brand_info_unclear":false,"year_unclear":false,"sum_rent":"","sum":"","brand":"ВАЗ 21063","sum_comment":"","brand_unclear":false,"brand_hidden":false}]},"id":"vulyk_68_107","declaration":{"additional_info_text":"","notfull_lostpages":"","date":"2015-03-16T00:00:00","notfull":"","additional_info":"","url":"http://static.declarations.com.ua/declarations/chosen_ones/mega_batch/demochko_dmytro_oleksandrovych.pdf"},"liabilities":{"54":{"sum_foreign_comment":"","sum":"","sum_comment":"","sum_comment_unclear":false,"sum_hidden":false,"sum_comment_hidden":false,"sum_unclear":false,"sum_foreign":""},"55":{"sum_foreign_comment":"","sum":"","sum_hidden":false,"sum_comment":"","sum_foreign":""},"56":{"sum_foreign_comment":"","sum_foreign_hidden":false,"sum_comment":"","sum":"","sum_unclear":false,"sum_foreign":""},"57":{"sum_foreign_comment":"","sum":"","sum_comment":"","sum_comment_unclear":false,"sum_hidden":false,"sum_comment_hidden":false,"sum_unclear":false,"sum_foreign":""},"58":{"sum_foreign_comment":"","sum":"","sum_comment":"","sum_hidden":false,"sum_comment_hidden":false,"sum_unclear":false,"sum_foreign":""},"59":{"sum_foreign_comment":"","sum":"","sum_comment":"","sum_foreign":""},"60":{"sum_foreign_comment":"","sum":"","sum_comment":"","sum_comment_unclear":false,"sum_hidden":false,"sum_comment_hidden":false,"sum_unclear":false,"sum_foreign":""},"61":{"sum_foreign_comment":"","sum":"","sum_hidden":false,"sum_comment":"","sum_foreign":""},"62":{"sum_foreign_comment":"","sum":"","sum_comment":"","sum_unclear":false,"sum_foreign":""},"63":{"sum_foreign_comment":"","sum":"","sum_comment":"","sum_hidden":false,"sum_comment_hidden":false,"sum_unclear":false,"sum_foreign":""},"64":{"sum_foreign_comment":"","sum":"","sum_comment":"","sum_hidden":false,"sum_comment_hidden":false,"sum_foreign":""}},"ft_src":"суддя першотравневого районного суду донецької області\nДонецька область\nЗагальний місцевий суд\nДмитро\nМурашко К. В\nПодружжя\nОлександрович\nДемочко Дмитро Олександрович\nДмитро Олександрович Демочко\nДмитро Демочко\nДемочко Дмитро Олександрович\nДемочко Дмитро Олександрович\nДемочко\n1294 куб. см.\nВАЗ 21063\n1989\n.0621\n22.65\n106\n2014\n45153\n191443\n45153\n191443\n1294 куб. см.\nВАЗ 21063\n1989\n.0621\n106\n22.65\nПодружжя\nМурашко К. В\nДемочко Дмитро Олександрович\nДмитро Олександрович Демочко\nДмитро Демочко\nДемочко Дмитро Олександрович\nДемочко Дмитро Олександрович\nДмитро\nОлександрович\nЗагальний місцевий суд\nДонецька область\nсуддя першотравневого районного суду донецької області\nДемочко\n191443\n45153\n191443\n45153\n2014\nПодружжя\nМурашко К. В\nОлександрович\nДемочко\nДмитро\nДемочко Дмитро Олександрович\nДмитро Олександрович Демочко\nДмитро Демочко\nДемочко Дмитро Олександрович\nДонецька область\nЗагальний місцевий суд\nсуддя першотравневого районного суду донецької області\nДемочко Дмитро Олександрович\n1989\nВАЗ 21063\n1294 куб. см.\n45153\n191443\n45153\n191443\n22.65\n.0621\n106\n2014","general":{"inn":"","name":"Дмитро","inn_unclear":false,"family":[{"inn":"","inn_hidden":true,"relations_unclear":false,"relations_hidden":false,"relations_other":"","relations":"Подружжя","name_hidden":true,"inn_unclear":false,"family_name":"Мурашко К. В","name_unclear":false}],"inn_hidden":true,"family_raw":"","last_name":"Демочко","post":{"post_unclear":false,"region_unclear":false,"post":"суддя першотравневого районного суду донецької області","office":"Загальний місцевий суд","region":"Донецька область","post_hidden":false,"office_hidden":false,"office_unclear":false,"region_hidden":false},"full_name_suggest":{"output":"Демочко Дмитро Олександрович","input":["Демочко Дмитро Олександрович","Дмитро Олександрович Демочко","Дмитро Демочко"]},"full_name":"Демочко Дмитро Олександрович","addresses":[{"place_city_type_hidden":true,"place_district_hidden":true,"place_city_type":"","place_city_hidden":true,"place_address_unclear":false,"place_address":"","place_hidden":true,"place":"","place_district":"","place_unclear":false,"place_city":"","place_address_hidden":true}],"patronymic":"Олександрович","last_name_unclear":false,"name_unclear":false},"source":"VULYK","estate":{"23":[{"costs":"","costs_comment":"","address_hidden":false,"region_hidden":true,"space_comment":"","space":".0621","address":"","region":"","costs_rent_comment":"","space_comment_hidden":false,"space_units":"га","costs_rent":""}],"24":[{"region_unclear":false,"space_unclear":false,"costs":"","costs_comment":"","address_hidden":false,"region_hidden":true,"space_comment":"","space":"106","address":"","region":"","costs_rent_comment":"","space_units":"м²","costs_rent":""}],"31":[{"space_unclear":false,"address_hidden":false,"region_hidden":true,"space_comment":"","space_hidden":false,"space":"22.65","address":"","region":"","costs_property":"","costs_rent_comment":"","space_units":"м²","costs_property_comment":"","costs_rent":""}]},"intro":{"declaration_year":"2014","isnotdeclaration":""}}