{"income":{"5":{"family_comment":"","value":"203118","family":"83821","comment":""},"6":{"value":"203118","family_comment":"","value_unclear":false,"comment_hidden":false,"family_unclear":false,"family":"72683","comment":""},"7":{"family_comment":"","value":"","source_name":"","family":"","comment":""},"8":{"family_comment":"","value":"","family":"","comment":""},"9":{"family_comment":"","family_unclear":false,"value":"","family":"","comment":""},"10":{"family_comment":"","value":"","value_unclear":false,"family":"","comment":""},"11":{"family_comment":"","value":"","family":"","comment":""},"12":{"family_comment":"","value":"","family":"","comment":""},"13":{"family_comment":"","value":"","family":"","comment":""},"14":{"family_comment":"","value":"","family":"","comment":""},"15":{"family_comment":"","value":"","family":"","comment":""},"16":{"family_comment":"","value":"","family":"","comment":""},"17":{"family_comment":"","value":"","family":"","comment":""},"18":{"family_comment":"","value":"","family":"","comment":""},"19":{"family_comment":"","value":"","family":"","comment":""},"20":{"value":"","family":"11138","value_unclear":false,"family_hidden":false,"family_comment":"","comment_unclear":false,"comment":"","family_comment_unclear":false}},"vehicle":{"35":[{"year_hidden":false,"brand_info":"1451 куб. см., 53 кВт , право керування","sum_rent_comment":"","year":"2006","brand_info_hidden":false,"brand_info_unclear":false,"sum_rent":"","sum":"","brand":"ВАЗ 21070","sum_comment":"","brand_unclear":false,"brand_hidden":false}],"40":[{"brand_info":"1598 куб. см., 73.55 кВт , право керування","sum_rent_comment":"","brand":"Ford Focus","sum_comment":"","brand_unclear":false,"year":"2008","brand_info_unclear":false,"year_unclear":false,"sum":"","sum_rent":""}]},"id":"vulyk_97_68","declaration":{"additional_info_text":"","notfull_lostpages":"","date":"2015-03-27T00:00:00","notfull":"","additional_info":"","url":"http://static.declarations.com.ua/declarations/chosen_ones/judges_batch/3897_turzhanskyi_volodymyr_vasylovych.pdf"},"liabilities":{"54":{"sum_foreign_comment":"","sum":"","sum_comment":"","sum_comment_unclear":false,"sum_hidden":false,"sum_comment_hidden":false,"sum_unclear":false,"sum_foreign":""},"55":{"sum_foreign_comment":"","sum":"","sum_comment":"","sum_foreign":""},"56":{"sum_foreign_comment":"","sum":"","sum_comment":"","sum_foreign":""},"57":{"sum_foreign_comment":"","sum":"","sum_comment":"","sum_comment_unclear":false,"sum_hidden":false,"sum_comment_hidden":false,"sum_unclear":false,"sum_foreign":""},"58":{"sum_foreign_comment":"","sum":"","sum_comment":"","sum_comment_unclear":false,"sum_hidden":false,"sum_comment_hidden":false,"sum_unclear":false,"sum_foreign":""},"59":{"sum_foreign_comment":"","sum":"","sum_comment":"","sum_foreign":""},"60":{"sum_foreign_comment":"","sum":"293","sum_comment":"","sum_comment_unclear":false,"sum_hidden":false,"sum_comment_hidden":false,"sum_foreign":""},"61":{"sum_foreign_comment":"","sum":"","sum_comment":"","sum_foreign":""},"62":{"sum_foreign_comment":"","sum":"","sum_comment":"","sum_unclear":false,"sum_foreign":""},"63":{"sum_foreign_comment":"","sum":"4125","sum_hidden":false,"sum_comment":"","sum_foreign":""},"64":{"sum_foreign_comment":"","sum":"143","sum_comment":"","sum_foreign":""}},"ft_src":"143\n4125\n293\nсуддя кельменецького районного суду чернівецької області\nЧернівецька область\nЗагальний місцевий суд\nВолодимир\nТуржанська О. А\nПодружжя\nТуржанська О. В\nДитина\nТуржанська В. В\nДонька дружини\nІнше\nВасильович\nТуржанський Володимир Васильович\nВолодимир Васильович Туржанський\nВолодимир Туржанський\nТуржанський Володимир Васильович\nТуржанський Володимир Васильович\nТуржанський\n1451 куб. см., 53 кВт , право керування\nВАЗ 21070\n2006\nFord Focus\n1598 куб. см., 73.55 кВт , право керування\n2008\n28\n219\n830\n2035\n219\n2014\n72683\n203118\n83821\n203118\n11138\n1451 куб. см., 53 кВт , право керування\nВАЗ 21070\n2006\n1598 куб. см., 73.55 кВт , право керування\nFord Focus\n2008\n2014\nТуржанський Володимир Васильович\nВолодимир Васильович Туржанський\nВолодимир Туржанський\nТуржанський Володимир Васильович\nВолодимир\nПодружжя\nТуржанська О. А\nДитина\nТуржанська О. В\nІнше\nТуржанська В. В\nДонька дружини\nТуржанський Володимир Васильович\nТуржанський\nЗагальний місцевий суд\nЧернівецька область\nсуддя кельменецького районного суду чернівецької області\nВасильович\n143\n293\n4125\n203118\n72683\n11138\n203118\n83821\n830\n2035\n219\n219\n28\n143\n293\n4125\nПодружжя\nТуржанська О. А\nТуржанська О. В\nДитина\nІнше\nТуржанська В. В\nДонька дружини\nВасильович\nТуржанський\nВолодимир\nТуржанський Володимир Васильович\nВолодимир Васильович Туржанський\nВолодимир Туржанський\nТуржанський Володимир Васильович\nЧернівецька область\nЗагальний місцевий суд\nсуддя кельменецького районного суду чернівецької області\nТуржанський Володимир Васильович\n2006\nВАЗ 21070\n1451 куб. см., 53 кВт , право керування\n2008\n1598 куб. см., 73.55 кВт , право керування\nFord Focus\n11138\n83821\n203118\n203118\n72683\n219\n219\n28\n830\n2035\n2014","general":{"name_hidden":false,"name":"Володимир","last_name_hidden":false,"inn":"","family":[{"inn":"","relations":"Подружжя","relations_other":"","inn_hidden":true,"family_name":"Туржанська О. А","name_hidden":true,"name_unclear":false},{"inn_hidden":true,"inn":"","name_hidden":false,"family_name":"Туржанська О. В","relations":"Дитина","name_unclear":false},{"inn":"","relations":"Інше","relations_other":"Донька дружини","inn_hidden":true,"family_name":"Туржанська В. В","name_hidden":false,"name_unclear":false}],"patronymic":"Васильович","inn_hidden":true,"family_raw":"","inn_unclear":false,"post":{"region_unclear":false,"region":"Чернівецька область","post":"суддя кельменецького районного суду чернівецької області","office":"Загальний місцевий суд","office_unclear":false,"post_hidden":false},"full_name":"Туржанський Володимир Васильович","addresses":[{"place_district":"","place_city_hidden":true,"place_city":"","place_city_unclear":false,"place_district_hidden":false,"place_city_type":"","place_address_hidden":true,"place_city_type_hidden":false,"place_address":"","place_hidden":true,"place":""}],"last_name":"Туржанський","patronymic_hidden":false,"full_name_suggest":{"output":"Туржанський Володимир Васильович","input":["Туржанський Володимир Васильович","Володимир Васильович Туржанський","Володимир Туржанський"]}},"source":"VULYK","estate":{"24":[{"region_unclear":false,"space_unclear":false,"costs":"","costs_comment":"","address_hidden":false,"region_hidden":true,"space_comment":"","space_hidden":false,"space":"219","address":"","region":"","address_unclear":false,"costs_rent_comment":"","space_comment_unclear":false,"space_units":"м²","costs_rent":""}],"29":[{"region_unclear":false,"space_unclear":false,"address_hidden":false,"region_hidden":true,"space_comment":"","space":"830","address":"","region":"","costs_property":"","costs_rent_comment":"","space_comment_unclear":false,"address_unclear":false,"space_units":"м²","costs_property_comment":"","costs_rent":""},{"address_hidden":false,"region_hidden":false,"space_comment":"","space":"2035","address":"","region":"","costs_property":"","costs_rent_comment":"","address_unclear":false,"space_units":"м²","costs_property_comment":"","costs_rent":""}],"30":[{"address_hidden":false,"region_hidden":true,"space_comment":"","space":"219","address":"","region":"","costs_property":"","costs_rent_comment":"","address_unclear":false,"space_units":"м²","costs_property_comment":"","costs_rent":""}],"33":[{"space_hidden":false,"address_hidden":false,"region_hidden":true,"space_comment":"","space":"28","address":"","region":"","costs_property":"","costs_rent_comment":"","space_units":"м²","costs_property_comment":"","costs_rent":""}]},"intro":{"declaration_year":"2014","isnotdeclaration":""}}