{"income":{"5":{"value":"232670.41","family_comment":"","value_unclear":false,"family_hidden":false,"value_hidden":false,"family_unclear":false,"comment_unclear":false,"comment":"","family":"45010.45"},"6":{"value":"220490.41","family_comment":"","value_unclear":false,"family_hidden":false,"value_hidden":false,"family_unclear":false,"comment_unclear":false,"comment":"","family":"45010.45"},"7":{"source_name_unclear":false,"value":"","family_comment":"","source_name":"","family":"","comment":""},"8":{"family_comment":"","value":"","family":"","comment":""},"9":{"value":"","value_unclear":false,"comment_hidden":false,"family_comment":"","comment_unclear":false,"comment":"","family":""},"10":{"value":"12180","comment_unclear":false,"value_hidden":false,"family_comment":"","family":"","comment":""},"11":{"family_comment":"","value":"","family":"","comment":""},"12":{"family_comment":"","value":"","family":"","comment":""},"13":{"family_comment":"","value":"","family":"","comment":""},"14":{"family_comment":"","value":"","family":"","comment":""},"15":{"family_comment":"","value":"","family":"","comment":""},"16":{"family_comment":"","value":"","family":"","comment":""},"17":{"family_comment":"","value":"","family":"","comment":""},"18":{"value":"","family_hidden":false,"value_hidden":false,"family_comment":"","family":"","comment":""},"19":{"family_comment":"","value":"","family":"","comment":""},"20":{"value":"","family_comment":"","value_unclear":false,"family_hidden":false,"value_hidden":false,"family_unclear":false,"family":"","comment":""}},"vehicle":{"35":[{"year_hidden":false,"brand_info":"1596","sum_rent_comment":"","year":"2008","brand_info_unclear":false,"year_unclear":false,"sum_rent":"","sum":"","brand":"Ford Focus","sum_comment":"","brand_unclear":false,"brand_hidden":false}],"40":[{"brand_info":"1598","sum_rent_comment":"","brand":"Toyota Corolla","sum_comment":"","brand_unclear":false,"year":"2009","brand_info_unclear":false,"year_unclear":false,"sum":"","sum_rent":""}]},"id":"vulyk_66_150","declaration":{"additional_info_text":"","notfull_lostpages":"","date":"2015-03-30T00:00:00","notfull":"","additional_info":"","url":"http://static.declarations.com.ua/declarations/chosen_ones/mega_batch/pidchenko_iurii_oleksiiovych.pdf"},"liabilities":{"54":{"sum_foreign_comment":"","sum":"","sum_comment":"","sum_comment_unclear":false,"sum_comment_hidden":false,"sum_unclear":false,"sum_foreign":""},"55":{"sum_foreign_comment":"","sum":"","sum_comment":"","sum_foreign":""},"56":{"sum_foreign_comment":"","sum_foreign_hidden":false,"sum_comment":"","sum_hidden":false,"sum_comment_hidden":false,"sum":"","sum_foreign":""},"57":{"sum_foreign_comment":"","sum":"","sum_comment":"","sum_comment_unclear":false,"sum_hidden":false,"sum_comment_hidden":false,"sum_unclear":false,"sum_foreign":""},"58":{"sum_foreign_comment":"","sum":"","sum_comment":"","sum_comment_unclear":false,"sum_unclear":false,"sum_foreign":""},"59":{"sum_foreign_comment":"","sum_foreign_hidden":false,"sum_comment":"","sum_comment_unclear":false,"sum_hidden":false,"sum":"","sum_foreign":""},"60":{"sum_foreign_comment":"","sum":"","sum_comment":"","sum_comment_unclear":false,"sum_foreign":""},"61":{"sum_foreign_comment":"","sum":"","sum_comment":"","sum_foreign":""},"62":{"sum_foreign_comment":"","sum_foreign_hidden":false,"sum_comment":"","sum_hidden":false,"sum":"","sum_unclear":false,"sum_foreign":""},"63":{"sum_foreign_comment":"","sum":"","sum_comment":"","sum_comment_unclear":false,"sum_comment_hidden":false,"sum_unclear":false,"sum_foreign":""},"64":{"sum_foreign_comment":"","sum":"","sum_comment":"","sum_comment_unclear":false,"sum_foreign":""}},"ft_src":"м. Київ\nсуддя господарського суду м. києва\nм. Київ\nГосподарський місцевий суд\nЮрій\nПідченко І. Ю\nПодружжя\nПідченко О. Ю\nДитина\nПідченко А. Ю\nДитина\nОлексійович\nПідченко Юрій Олексійович\nЮрій Олексійович Підченко\nЮрій Підченко\nПідченко Юрій Олексійович\nПідченко Юрій Олексійович\nПідченко\n1596\nFord Focus\n2008\n1598\nToyota Corolla\n2009\nм. Донецьк\nДонецька область\n16.5\n64.95\nДонецька область\nм. Донецьк\nм. Донецьк\n22\nДонецька область\nм. Донецьк\nДонецька область\n.0832\nм. Донецьк\n21.65\nДонецька область\n2014\n45010.45\n220490.41\n12180\n45010.45\n232670.41\n1596\nFord Focus\n2008\n1598\n2009\nToyota Corolla\n16.5\nДонецька область\nм. Донецьк\n22\nДонецька область\nм. Донецьк\n64.95\nДонецька область\nм. Донецьк\n21.65\nДонецька область\nм. Донецьк\n.0832\nДонецька область\nм. Донецьк\nГосподарський місцевий суд\nсуддя господарського суду м. києва\nм. Київ\nПодружжя\nПідченко І. Ю\nДитина\nПідченко О. Ю\nДитина\nПідченко А. Ю\nПідченко Юрій Олексійович\nЮрій Олексійович Підченко\nЮрій Підченко\nПідченко Юрій Олексійович\nПідченко Юрій Олексійович\nЮрій\nПідченко\nОлексійович\nм. Київ\n220490.41\n45010.45\n232670.41\n45010.45\n12180\n2014\nПідченко І. Ю\nПодружжя\nПідченко О. Ю\nДитина\nПідченко А. Ю\nДитина\nОлексійович\nПідченко\nЮрій\nПідченко Юрій Олексійович\nЮрій Олексійович Підченко\nЮрій Підченко\nПідченко Юрій Олексійович\nм. Київ\nм. Київ\nсуддя господарського суду м. києва\nГосподарський місцевий суд\nПідченко Юрій Олексійович\nFord Focus\n1596\n2008\n2009\n1598\nToyota Corolla\n12180\n232670.41\n45010.45\n220490.41\n45010.45\nм. Донецьк\nДонецька область\n64.95\n21.65\nм. Донецьк\nДонецька область\nм. Донецьк\nДонецька область\n22\nм. Донецьк\nДонецька область\n16.5\nм. Донецьк\nДонецька область\n.0832\n2014","general":{"inn":"","name":"Юрій","last_name_hidden":false,"family":[{"inn":"","inn_hidden":false,"relations_hidden":false,"family_name":"Підченко І. Ю","relations_other":"","relations":"Подружжя","name_hidden":false,"name_unclear":false},{"inn":"","inn_hidden":false,"relations_unclear":false,"relations_hidden":false,"relations_other":"","relations":"Дитина","name_hidden":false,"family_name":"Підченко О. Ю","name_unclear":false},{"inn":"","inn_hidden":false,"relations_hidden":false,"family_name":"Підченко А. Ю","relations_other":"","relations":"Дитина","name_hidden":false,"name_unclear":false}],"patronymic":"Олексійович","inn_hidden":false,"family_raw":"","inn_unclear":false,"post":{"post_unclear":false,"post":"суддя господарського суду м. києва","candidate":"","office_hidden":false,"region":"м. Київ","office":"Господарський місцевий суд","office_unclear":false},"full_name_suggest":{"output":"Підченко Юрій Олексійович","input":["Підченко Юрій Олексійович","Юрій Олексійович Підченко","Юрій Підченко"]},"full_name":"Підченко Юрій Олексійович","addresses":[{"place_city_type_unclear":false,"place_address":"","place_district_hidden":false,"place_city_type":"","place_address_hidden":false,"place_address_unclear":false,"place_city_type_hidden":false,"place":"м. Київ","place_district":"","place_unclear":false,"place_city":"","place_city_unclear":false,"place_hidden":false,"place_city_hidden":false,"place_district_unclear":false}],"last_name":"Підченко","last_name_unclear":false},"source":"VULYK","estate":{"25":[{"region_unclear":false,"space_hidden":false,"costs":"","costs_comment":"","costs_hidden":false,"address_hidden":false,"region_hidden":false,"space_comment":"","space_unclear":false,"space":"21.65","space_units_hidden":false,"region":"Донецька область","address_unclear":false,"costs_rent_comment":"","space_comment_unclear":false,"space_units":"м²","address":"м. Донецьк","costs_rent":""}],"27":[{"space_unclear":false,"costs":"","costs_comment":"","costs_hidden":false,"address_hidden":false,"region_hidden":false,"space_comment":"","space_hidden":false,"space":"22","space_units_hidden":false,"region":"Донецька область","costs_rent_comment":"","space_comment_unclear":false,"space_units":"м²","address":"м. Донецьк","costs_rent":""}],"29":[{"space_unclear":false,"address_hidden":false,"region_hidden":false,"space_comment":"","space_hidden":false,"space":".0832","address":"м. Донецьк","region":"Донецька область","costs_property":"","costs_rent_comment":"","space_units":"га","costs_property_comment":"","costs_rent":""}],"31":[{"space_unclear":false,"address_hidden":false,"region_hidden":false,"space_comment":"","space_hidden":false,"space":"64.95","address":"м. Донецьк","region":"Донецька область","costs_property":"","costs_rent_comment":"","space_comment_unclear":false,"space_comment_hidden":false,"space_units":"м²","costs_property_comment":"","costs_rent":""}],"33":[{"space_hidden":false,"address_hidden":false,"region_hidden":false,"space_comment":"","space":"16.5","address":"м. Донецьк","region":"Донецька область","costs_property":"","costs_rent_comment":"","space_units":"м²","costs_property_comment":"","costs_rent":""}]},"intro":{"declaration_year":"2014","isnotdeclaration":"","declaration_year_unclear":false}}