{"income":{"5":{"family_comment":"","value":"249499","family":"6700","comment":""},"6":{"family_comment":"","value":"236101","family":"","comment":"","family_comment_unclear":false},"7":{"value":"","comment_hidden":false,"family_comment":"","source_name":"","family":"","comment":"","source_name_hidden":false},"8":{"family_comment":"","value":"","family":"","comment":""},"9":{"family_comment":"","value":"","family":"","comment":""},"10":{"value":"13398","value_unclear":false,"value_hidden":false,"family_comment":"","family":"","comment":""},"11":{"family_comment":"","value":"","family":"","comment":""},"12":{"family_comment":"","value":"","family":"","comment":""},"13":{"family_comment":"","value":"","family":"","comment":""},"14":{"family_comment":"","value":"","family":"","comment":""},"15":{"family_comment":"","value":"","family":"","comment":""},"16":{"family_comment":"","value":"","family":"","comment":""},"17":{"family_comment":"","value":"","family":"6700","comment":""},"18":{"family_comment":"","value":"","family":"","comment":""},"19":{"family_comment":"","value":"","family":"","comment":""},"20":{"family_comment":"","value":"","comment_unclear":false,"family":"","comment":""}},"vehicle":{"40":[{"brand_info":"800 куб. см.","sum_rent_comment":"","brand":"Daewoo Matiz","sum_comment":"","brand_unclear":false,"year":"2008","sum":"","sum_rent":""}]},"id":"vulyk_86_3","declaration":{"additional_info_text":"","notfull_lostpages":"","date":"2015-03-24T00:00:00","notfull":"","additional_info":"","url":"http://static.declarations.com.ua/declarations/chosen_ones/judges_batch/2706_presniakova_anzhelika_anatoliivna.pdf"},"liabilities":{"54":{"sum_foreign_comment":"","sum":"","sum_comment":"","sum_unclear":false,"sum_foreign":""},"55":{"sum_foreign_comment":"","sum":"","sum_comment":"","sum_foreign":""},"56":{"sum_foreign_comment":"","sum":"","sum_hidden":false,"sum_comment":"","sum_foreign":""},"57":{"sum_foreign_comment":"","sum":"1758","sum_comment":"","sum_unclear":false,"sum_foreign":""},"58":{"sum_foreign_comment":"","sum":"4664","sum_comment":"","sum_unclear":false,"sum_foreign":""},"59":{"sum_foreign_comment":"","sum":"","sum_comment":"","sum_foreign":""},"60":{"sum_foreign_comment":"","sum_comment_hidden":false,"sum":"1594","sum_comment":"","sum_foreign":""},"61":{"sum_foreign_comment":"","sum":"","sum_comment":"","sum_foreign":""},"62":{"sum_foreign_comment":"","sum":"17520","sum_comment":"","sum_foreign":""},"63":{"sum_foreign_comment":"","sum":"29807","sum_comment":"","sum_foreign":""},"64":{"sum_foreign_comment":"","sum":"19179","sum_comment":"","sum_foreign":""}},"ft_src":"1758\n17520\n4664\n29807\n1594\n19179\nсуддя апеляційного суду донецької області\nДонецька область\nЗагальний апеляційний суд\nАнжеліка\nПрєсняков О. О\nПодружжя\nАнатоліївна\nПреснякова Анжеліка Анатоліївна\nАнжеліка Анатоліївна Преснякова\nАнжеліка Преснякова\nПреснякова Анжеліка Анатоліївна\nПреснякова Анжеліка Анатоліївна\nПреснякова\n2008\n800 куб. см.\nDaewoo Matiz\n34.7\n1/3 частина\n13.6\n247.6\n1400\n1/3 частина\n13.6\n2014\n236101\n13398\n6700\n249499\n6700\n800 куб. см.\nDaewoo Matiz\n2008\n2014\nПреснякова Анжеліка Анатоліївна\nАнжеліка Анатоліївна Преснякова\nАнжеліка Преснякова\nПреснякова Анжеліка Анатоліївна\nПреснякова Анжеліка Анатоліївна\nПодружжя\nПрєсняков О. О\nАнжеліка\nПреснякова\nЗагальний апеляційний суд\nДонецька область\nсуддя апеляційного суду донецької області\nАнатоліївна\n4664\n19179\n29807\n1594\n17520\n1758\n236101\n6700\n249499\n6700\n13398\n1400\n1/3 частина\n13.6\n247.6\n13.6\n1/3 частина\n34.7\n4664\n17520\n19179\n1758\n1594\n29807\nПрєсняков О. О\nПодружжя\nАнатоліївна\nПреснякова\nАнжеліка\nПреснякова Анжеліка Анатоліївна\nАнжеліка Анатоліївна Преснякова\nАнжеліка Преснякова\nПреснякова Анжеліка Анатоліївна\nДонецька область\nЗагальний апеляційний суд\nсуддя апеляційного суду донецької області\nПреснякова Анжеліка Анатоліївна\n2008\n800 куб. см.\nDaewoo Matiz\n13398\n6700\n249499\n6700\n236101\n1/3 частина\n13.6\n1/3 частина\n13.6\n34.7\n247.6\n1400\n2014","general":{"inn":"","name":"Анжеліка","patronymic_unclear":false,"family":[{"inn":"","inn_hidden":true,"relations_hidden":false,"family_name":"Прєсняков О. О","relations_other":"","relations":"Подружжя","name_hidden":true,"name_unclear":false}],"patronymic":"Анатоліївна","inn_hidden":true,"family_raw":"","inn_unclear":false,"post":{"post_unclear":false,"post":"суддя апеляційного суду донецької області","candidate":"","office_hidden":false,"region":"Донецька область","office":"Загальний апеляційний суд","office_unclear":false,"region_hidden":false},"full_name":"Преснякова Анжеліка Анатоліївна","addresses":[{"place_district":"","place_unclear":false,"place_city":"","place_city_type_hidden":true,"place_district_hidden":true,"place_city_type":"","place_city_hidden":true,"place_address_hidden":true,"place_address":"","place_hidden":true,"place":""}],"last_name":"Преснякова","full_name_suggest":{"output":"Преснякова Анжеліка Анатоліївна","input":["Преснякова Анжеліка Анатоліївна","Анжеліка Анатоліївна Преснякова","Анжеліка Преснякова"]}},"source":"VULYK","estate":{"25":[{"space_unclear":false,"costs":"","costs_comment":"","address_hidden":true,"region_hidden":true,"space_comment":"1/3 частина","space_hidden":false,"space":"13.6","address":"","region":"","address_unclear":false,"costs_rent_comment":"","space_units":"м²","costs_rent":""}],"29":[{"space_unclear":false,"address_hidden":true,"region_hidden":true,"space_comment":"","space":"1400","address":"","region":"","costs_property":"","costs_rent_comment":"","space_units":"м²","costs_property_comment":"","costs_rent":""}],"31":[{"space_unclear":false,"address_hidden":true,"region_hidden":true,"space_comment":"1/3 частина","space_hidden":false,"space":"13.6","address":"","region":"","costs_property":"","costs_rent_comment":"","space_units":"м²","costs_property_comment":"","costs_rent":""}],"33":[{"space_hidden":false,"address_hidden":true,"region_hidden":true,"space_comment":"","space":"34.7","address":"","region":"","costs_property":"","costs_rent_comment":"","space_units":"м²","costs_property_comment":"","costs_rent":""}],"34":[{"costs_rent":"","region":"","costs_property":"","costs_rent_comment":"","address_hidden":true,"region_hidden":true,"space_comment":"","costs_property_comment":"","space_units":"м²","space":"247.6","address":""}]},"intro":{"declaration_year":"2014","declaration_year_unclear":false}}