{"id":"vulyk_104_163","ft_src":"2008\nToyota Camry\n2400 куб. см., 175 к.с., 1 /2 частина у власності\nToyota Camry\n2400 куб. см., 175 к.с., 1 /2 частина у власності\n2008\n1229\n328\n1229\n328\n2015\n58495\n227678\n3855\n13398\n115\n79076\n241082\n16611\n6\n2400 куб. см., 175 к.с., 1 /2 частина у власності\nToyota Camry\n2008\nToyota Camry\n2400 куб. см., 175 к.с., 1 /2 частина у власності\n2008\n2015\nПодружжя\nОнуфрієва Світлана Вікторівна 01. 03. 1968\nДитина\nОнуфрієв Олег Вікторович 28. 04. 1991\nОнуфрієв\nОнуфрієв Віктор Миколайович\nВіктор Миколайович Онуфрієв\nВіктор Онуфрієв\nОнуфрієв Віктор Миколайович\nОнуфрієв Віктор Миколайович\nВіктор\nМиколайович\nЗагальний апеляційний суд\nсуддя апеляційного суду кіровоградської області\nКіровоградська область\n13262\n16077\n115\n227678\n58495\n6\n16611\n241082\n79076\n13398\n3855\n1229\n1229\n328\n328\n13262\n16077\nПодружжя\nОнуфрієва Світлана Вікторівна 01. 03. 1968\nДитина\nОнуфрієв Олег Вікторович 28. 04. 1991\nМиколайович\nОнуфрієв\nсуддя апеляційного суду кіровоградської області\nЗагальний апеляційний суд\nКіровоградська область\nОнуфрієв Віктор Миколайович\nОнуфрієв Віктор Миколайович\nВіктор Миколайович Онуфрієв\nВіктор Онуфрієв\nОнуфрієв Віктор Миколайович\nВіктор","estate":{"23":[{"address":"","space_units":"м²","space_hidden":false,"space_comment":"","region_hidden":true,"costs_comment":"","address_hidden":false,"space":"1229","space_comment_unclear":false,"costs_rent_comment":"","costs":"","region":"","costs_rent":""}],"24":[{"address":"","space_units":"м²","space_hidden":false,"space_comment":"","region_hidden":true,"costs_comment":"","address_hidden":false,"space":"328","space_comment_unclear":false,"costs_rent_comment":"","costs":"","region":"","costs_rent":""}],"29":[{"costs_property_comment":"","address":"","space_units":"м²","space_unclear":false,"region_hidden":true,"costs_property":"","space_comment":"","address_hidden":true,"costs_rent_comment":"","space":"1229","region":"","costs_rent":""}],"30":[{"costs_property_comment":"","address":"","space_units":"м²","space_hidden":false,"space_comment":"","region_hidden":true,"costs_property":"","region":"","address_hidden":true,"space_comment_unclear":false,"costs_rent_comment":"","space":"328","costs_rent":""}]},"vehicle":{"35":[{"sum_comment":"","brand_info":"2400 куб. см., 175 к.с., 1 /2 частина у власності","sum":"","sum_rent_comment":"","year":"2008","brand":"Toyota Camry","sum_rent":"","brand_info_unclear":false,"brand_hidden":false}],"40":[{"sum_comment":"","brand_info_hidden":false,"brand_info":"2400 куб. см., 175 к.с., 1 /2 частина у власності","sum":"","sum_rent_comment":"","brand_hidden":false,"brand":"Toyota Camry","sum_rent":"","brand_info_unclear":false,"year":"2008"}]},"source":"VULYK","income":{"5":{"family_comment":"","value":"241082","family":"79076","comment":""},"6":{"family_comment":"","value":"227678","family":"58495","comment":"","value_unclear":false},"7":{"source_name_hidden":false,"family_comment":"","comment":"","family":"115","value":"","source_name":""},"8":{"family_comment":"","value":"","family":"","comment":""},"9":{"family_comment":"","value":"","family":"","comment":""},"10":{"family_comment":"","value":"13398","family":"3855","comment":""},"11":{"family_comment":"","value":"","family":"","comment":"","comment_hidden":false},"12":{"family_comment":"","value":"","family":"","comment":""},"13":{"family_comment":"","value":"","family":"","comment":""},"14":{"family_comment":"","value":"","family":"","comment":""},"15":{"family_comment":"","family":"","comment":"","value_unclear":false,"family_unclear":false,"value":""},"16":{"family_comment":"","value":"","family":"","comment":""},"17":{"family_comment":"","value":"","family":"","comment":""},"18":{"family_comment":"","value":"","family":"","comment":""},"19":{"family_comment":"","value":"","family":"","comment":""},"20":{"family_comment":"","comment_unclear":false,"value":"6","family":"16611","comment":""}},"general":{"inn":"","addresses":[{"place_city_type_hidden":false,"place_city_type":"","place_city_hidden":true,"place_hidden":true,"place_district":"","place_district_hidden":false,"place":"","place_address":"","place_address_hidden":true,"place_city":""}],"last_name":"Онуфрієв","full_name":"Онуфрієв Віктор Миколайович","family":[{"inn":"","family_name":"Онуфрієва Світлана Вікторівна 01. 03. 1968","relations_other":"","name_unclear":false,"inn_hidden":true,"name_hidden":false,"relations":"Подружжя"},{"inn":"","family_name":"Онуфрієв Олег Вікторович 28. 04. 1991","relations_other":"","name_unclear":false,"inn_hidden":false,"name_hidden":false,"relations":"Дитина"}],"patronymic":"Миколайович","inn_hidden":true,"name":"Віктор","post":{"office":"Загальний апеляційний суд","region_unclear":false,"post":"суддя апеляційного суду кіровоградської області","region":"Кіровоградська область","office_unclear":false},"family_raw":"","full_name_suggest":{"input":["Онуфрієв Віктор Миколайович","Віктор Миколайович Онуфрієв","Віктор Онуфрієв"],"output":"Онуфрієв Віктор Миколайович"}},"liabilities":{"54":{"sum_comment":"","sum_hidden":false,"sum":"","sum_foreign_comment":"","sum_foreign":"","sum_unclear":false,"sum_foreign_hidden":false,"sum_comment_hidden":false},"55":{"sum_comment":"","sum_foreign_comment":"","sum_foreign":"","sum":""},"56":{"sum_comment":"","sum_foreign_comment":"","sum_foreign":"","sum_unclear":false,"sum":""},"57":{"sum_comment_unclear":false,"sum_comment":"","sum":"","sum_foreign_comment":"","sum_foreign":"","sum_foreign_hidden":false,"sum_comment_hidden":false},"58":{"sum_comment":"","sum_foreign_comment":"","sum_foreign":"","sum_unclear":false,"sum":""},"59":{"sum_comment":"","sum_foreign_comment":"","sum_foreign":"","sum":""},"60":{"sum_comment":"","sum":"","sum_foreign_comment":"","sum_foreign":"","sum_foreign_hidden":false,"sum_comment_hidden":false},"61":{"sum_comment":"","sum_foreign_comment":"","sum_foreign":"","sum":""},"62":{"sum_comment":"","sum_foreign_comment":"","sum_foreign":"","sum":""},"63":{"sum_comment":"","sum_foreign_comment":"","sum_foreign":"","sum":"13262"},"64":{"sum_comment":"","sum_foreign_comment":"","sum_foreign":"","sum":"16077"}},"declaration":{"additional_info_text":"","additional_info":"","date":"2016-03-31T00:00:00","url":"http://static.declarations.com.ua/declarations/chosen_ones/judges_batch/1961_onufriiev_viktor_mykolaiovych_2015.pdf"},"intro":{"isnotdeclaration":"","declaration_year":"2015"}}