{"income":{"5":{"value":"186619","family_comment":"","value_unclear":false,"family_unclear":false,"family":"","comment":""},"6":{"value":"185716","family_comment":"","value_unclear":false,"family_unclear":false,"family":"","comment":""},"7":{"value":"","value_unclear":false,"family_comment":"","source_name":"","family":"","comment":""},"8":{"family_comment":"","value":"","family":"","comment":""},"9":{"family_comment":"","value":"","value_unclear":false,"family":"","comment":""},"10":{"family_comment":"","value":"","comment_unclear":false,"family":"","comment":""},"11":{"family_comment":"","value":"","family":"","comment":""},"12":{"family_comment":"","value":"","family":"","comment":""},"13":{"family_comment":"","value":"","family":"","comment":""},"14":{"family_comment":"","value":"","family":"","comment":""},"15":{"family_comment":"","value":"","family":"","comment":""},"16":{"family_comment":"","value":"","family":"","comment":""},"17":{"family_comment":"","value":"","family":"","comment":""},"18":{"family_comment":"","value":"","family":"","comment":""},"19":{"family_comment":"","value":"","family":"","comment":""},"20":{"family_comment":"","value":"903","family":"","comment":""}},"id":"vulyk_55_113","banks":{"45":[{"sum_foreign_comment":"","sum_units":"UAH","sum_comment":"","sum_comment_unclear":false,"sum_foreign_units":"UAH","sum_foreign_comment_unclear":false,"sum_units_unclear":false,"sum_comment_hidden":false,"sum_unclear":false,"sum":"2000","sum_foreign":""},{"sum_foreign_comment":"","sum_units":"","sum_comment":"","sum_comment_unclear":false,"sum_foreign_units":"","sum":"","sum_unclear":false,"sum_foreign":""},{"sum_foreign_comment":"","sum_units":"","sum_comment":"","sum_foreign_units":"","sum":"","sum_unclear":false,"sum_foreign":""}],"46":[{"sum_foreign_comment":"","sum_units":"UAH","sum_comment":"","sum_comment_unclear":false,"sum_foreign_units":"UAH","sum":"2000","sum_foreign":""}],"47":[{"sum_foreign_comment":"","sum_units":"UAH","sum_comment":"","sum_comment_unclear":false,"sum_hidden":false,"sum_foreign_units":"UAH","sum":"","sum_foreign":""}],"48":[{"sum_foreign_comment":"","sum_units":"UAH","sum_comment":"","sum_foreign_units":"UAH","sum":"","sum_foreign":""}],"49":[{"sum_foreign_comment":"","sum_units":"UAH","sum_comment":"","sum_foreign_units":"UAH","sum":"","sum_foreign":""},{"sum_foreign_comment":"","sum_units":"","sum_comment":"","sum":"","sum_foreign":""}],"50":[{"sum_foreign_comment":"","sum_units":"UAH","sum_comment":"","sum_foreign_units":"UAH","sum":"","sum_foreign":""}],"51":[{"sum_units":"UAH","sum_hidden":false,"sum_units_hidden":false,"sum_foreign":"","sum_foreign_comment":"","sum":"","sum_comment":"","sum_comment_unclear":false,"sum_foreign_units":"UAH","sum_units_unclear":false,"sum_comment_hidden":false,"sum_unclear":false},{"sum_foreign_comment":"","sum_units":"","sum_comment":"","sum_foreign_units":"","sum":"","sum_foreign":""}],"52":[{"sum_foreign_comment":"","sum_units":"UAH","sum_comment":"","sum_comment_unclear":false,"sum_foreign_units":"UAH","sum":"","sum_foreign":""},{"sum_foreign_comment":"","sum_units":"","sum_comment":"","sum_foreign_units":"","sum":"","sum_foreign":""}],"53":[{"sum_foreign_comment":"","sum_units":"UAH","sum_comment":"","sum_hidden":false,"sum_foreign_units":"UAH","sum":"","sum_unclear":false,"sum_foreign":""},{"sum_foreign_comment":"","sum_units":"","sum_comment":"","sum_comment_unclear":false,"sum_foreign_units":"","sum":"","sum_foreign":""},{"sum_foreign_comment":"","sum_units":"","sum_comment":"","sum_foreign_units":"","sum":"","sum_foreign":""},{"sum_foreign_comment":"","sum_units":"","sum_comment":"","sum_foreign_units":"","sum":"","sum_foreign":""}]},"declaration":{"additional_info_text":"","notfull_lostpages":"","date":"2015-03-24T00:00:00","notfull":"","additional_info":"","url":"http://static.declarations.com.ua/declarations/chosen_ones/mega_batch/starokozhko_volodymyr_petrovych.pdf"},"liabilities":{"54":{"sum_foreign_comment":"","sum":"","sum_comment":"","sum_hidden":false,"sum_comment_hidden":false,"sum_foreign":""},"55":{"sum_foreign_comment":"","sum_foreign_hidden":false,"sum_comment":"","sum_hidden":false,"sum":"","sum_foreign":""},"56":{"sum_foreign_comment":"","sum":"","sum_comment":"","sum_unclear":false,"sum_foreign":""},"57":{"sum_foreign_comment":"","sum":"","sum_comment":"","sum_comment_unclear":false,"sum_hidden":false,"sum_comment_hidden":false,"sum_unclear":false,"sum_foreign":""},"58":{"sum_foreign_comment":"","sum":"","sum_comment":"","sum_hidden":false,"sum_comment_hidden":false,"sum_unclear":false,"sum_foreign":""},"59":{"sum_foreign_comment":"","sum":"","sum_comment":"","sum_foreign":""},"60":{"sum_foreign_comment":"","sum":"","sum_comment":"","sum_hidden":false,"sum_comment_hidden":false,"sum_foreign":""},"61":{"sum_foreign_comment":"","sum":"","sum_comment":"","sum_foreign":""},"62":{"sum_foreign_comment":"","sum":"","sum_comment":"","sum_foreign":""},"63":{"sum_foreign_comment":"","sum":"","sum_comment":"","sum_unclear":false,"sum_foreign":""},"64":{"sum_foreign_comment":"","sum":"","sum_comment":"","sum_unclear":false,"sum_foreign":""}},"ft_src":"заступник голови хорольського районного суду полтавської області\nПолтавська область\nЗагальний місцевий суд\nВолодимир\nСтарокожко Т. В. 18. 12. 1974\nПодружжя\nСтарокожко О. В. 24. 07. 2003\nДитина\nПетрович\nСтарокожко\nСтарокожко Володимир Петрович\nСтарокожко Володимир Петрович\nВолодимир Петрович Старокожко\nВолодимир Старокожко\nСтарокожко Володимир Петрович\n903\n186619\n185716\n2000\n2000\nПолтавська область\nу власності\nселище Диканька\n2000\nу власності дружини Старокожко Т. В. з 24. 10. 14\nДиканський район, с. Михайлівка, Степова, 8а\nПолтавська область\n21.9\nу власності дружини Старокожко Т. В. з 24. 10. 14\nДиканський район, с. Михайлівка, вул.Степова, 8а\n.2499\nПолтавська область\nПолтавська область\nоренда\nм. Хорол, вул. Жовтнева, 27/2\n60\n1/4 частина від 54м. (у власності\n54\nселище Диканька, вул. Леніна, 6а, кв. 29\nПолтавська область\n2014\n185716\n186619\n903\n2000\n2000\n2014\nПодружжя\nСтарокожко Т. В. 18. 12. 1974\nДитина\nСтарокожко О. В. 24. 07. 2003\nСтарокожко Володимир Петрович\nВолодимир Петрович Старокожко\nВолодимир Старокожко\nСтарокожко Володимир Петрович\nВолодимир\nСтарокожко Володимир Петрович\nПетрович\nЗагальний місцевий суд\nзаступник голови хорольського районного суду полтавської області\nПолтавська область\nСтарокожко\n185716\n903\n186619\n2000\nу власності\nселище Диканька\nПолтавська область\n.2499\nу власності дружини Старокожко Т. В. з 24. 10. 14\nПолтавська область\nДиканський район, с. Михайлівка, вул.Степова, 8а\n60\nоренда\nм. Хорол, вул. Жовтнева, 27/2\nПолтавська область\n21.9\nу власності дружини Старокожко Т. В. з 24. 10. 14\nПолтавська область\nДиканський район, с. Михайлівка, Степова, 8а\n54\n1/4 частина від 54м. (у власності\nПолтавська область\nселище Диканька, вул. Леніна, 6а, кв. 29\nСтарокожко Т. В. 18. 12. 1974\nПодружжя\nСтарокожко О. В. 24. 07. 2003\nДитина\nПетрович\nСтарокожко\nСтарокожко Володимир Петрович\nВолодимир Петрович Старокожко\nВолодимир Старокожко\nСтарокожко Володимир Петрович\nПолтавська область\nзаступник голови хорольського районного суду полтавської області\nЗагальний місцевий суд\nСтарокожко Володимир Петрович\nВолодимир\nу власності дружини Старокожко Т. В. з 24. 10. 14\nДиканський район, с. Михайлівка, Степова, 8а\nПолтавська область\n21.9\nу власності\nселище Диканька\nПолтавська область\n2000\nоренда\nм. Хорол, вул. Жовтнева, 27/2\nПолтавська область\n60\n1/4 частина від 54м. (у власності\nселище Диканька, вул. Леніна, 6а, кв. 29\nПолтавська область\n54\nу власності дружини Старокожко Т. В. з 24. 10. 14\nДиканський район, с. Михайлівка, вул.Степова, 8а\nПолтавська область\n.2499\n2000\n2000\n2014","general":{"name_hidden":false,"name":"Володимир","patronymic_unclear":false,"last_name_hidden":true,"inn":"","family":[{"inn":"","inn_hidden":false,"relations_unclear":false,"relations_hidden":false,"relations_other":"","relations":"Подружжя","name_hidden":false,"family_name":"Старокожко Т. В. 18. 12. 1974","name_unclear":false},{"inn":"","relations":"Дитина","relations_other":"","inn_hidden":false,"family_name":"Старокожко О. В. 24. 07. 2003","name_hidden":false,"name_unclear":false}],"patronymic":"Петрович","inn_hidden":false,"family_raw":"","inn_unclear":false,"post":{"post_unclear":false,"post":"заступник голови хорольського районного суду полтавської області","post_hidden":false,"region":"Полтавська область","region_hidden":false,"office":"Загальний місцевий суд","office_hidden":false,"office_unclear":false},"last_name_unclear":false,"full_name":"Старокожко Володимир Петрович","addresses":[{"place_city_type_unclear":true,"place_address":"","place_district_hidden":false,"place_city_type":"","place_address_hidden":false,"place_address_unclear":true,"place_city_type_hidden":false,"place":"","place_district":"","place_city_hidden":false,"place_city":"","place_city_unclear":true,"place_hidden":false}],"last_name":"Старокожко","patronymic_hidden":false,"full_name_suggest":{"output":"Старокожко Володимир Петрович","input":["Старокожко Володимир Петрович","Володимир Петрович Старокожко","Володимир Старокожко"]}},"source":"VULYK","estate":{"23":[{"space_hidden":false,"costs":"","costs_comment":"","address_hidden":false,"region_hidden":false,"space_comment":"у власності","space":"2000","address":"селище Диканька","region":"Полтавська область","address_unclear":false,"costs_rent_comment":"","space_units":"м²","costs_rent":""},{"costs_rent":"","region":"","costs":"","costs_rent_comment":"","costs_comment":"","region_hidden":false,"space_comment":"","space_units":"","space":"","address":""},{"costs_rent":"","region":"","costs":"","costs_rent_comment":"","costs_comment":"","space_comment":"","space_units":"","space":"","address":""},{"costs_rent":"","costs":"","costs_rent_comment":"","costs_comment":"","space_comment":"","space_units":"","space":"","address":""}],"24":[{"space_hidden":false,"costs":"","costs_comment":"","address_hidden":false,"region_hidden":false,"space_comment":"оренда","space":"60","address":"м. Хорол, вул. Жовтнева, 27/2","region":"Полтавська область","address_unclear":false,"costs_rent_comment":"","space_units":"м²","costs_rent":""}],"25":[{"region_unclear":false,"space_unclear":false,"costs":"","costs_comment":"","costs_hidden":false,"address_hidden":false,"region_hidden":false,"space_comment":"1/4 частина від 54м. (у власності","space_hidden":false,"space":"54","address":"селище Диканька, вул. Леніна, 6а, кв. 29","costs_unclear":false,"region":"Полтавська область","address_unclear":false,"costs_rent_comment":"","space_comment_unclear":false,"space_comment_hidden":false,"space_units":"м²","costs_rent":""}],"29":[{"space_unclear":false,"address_hidden":false,"address_unclear":true,"space_comment":"у власності дружини Старокожко Т. В. з 24. 10. 14","space":".2499","address":"Диканський район, с. Михайлівка, вул.Степова, 8а","region":"Полтавська область","costs_property":"","costs_rent_comment":"","region_hidden":false,"space_comment_hidden":false,"space_units":"га","costs_property_comment":"","costs_rent":""}],"30":[{"space_unclear":false,"address_hidden":false,"region_hidden":false,"space_comment":"у власності дружини Старокожко Т. В. з 24. 10. 14","space":"21.9","address":"Диканський район, с. Михайлівка, Степова, 8а","region":"Полтавська область","costs_property":"","costs_rent_comment":"","address_unclear":true,"space_units":"м²","costs_property_comment":"","costs_rent":""}]},"intro":{"declaration_year":"2014","isnotdeclaration":""}}