{"id":"vulyk_84_35","ft_src":"Дніпропетровська область\n18000\nм. Дніпропетровськ\n28\n2014\n211869.52\n12180\n224049.52\n211869.52\n224049.52\n12180\nСтуковенков Валерій Петрович\nВалерій Петрович Стуковенков\nВалерій Стуковенков\nСтуковенков Валерій Петрович\nВалерій\nПодружжя\nДитина\nСтуковенков Валерій Петрович\nПетрович\nсуддя ленінського районного суду м. дніпропетровська\nЗагальний місцевий суд\nДніпропетровська область\nСтуковенков\nДніпропетровськ\nДніпропетровська область\n28\n18000\nДніпропетровська область\nм. Дніпропетровськ\n2014\nПодружжя\nДитина\nПетрович\nСтуковенков\nВалерій\nСтуковенков Валерій Петрович\nВалерій Петрович Стуковенков\nВалерій Стуковенков\nСтуковенков Валерій Петрович\nДніпропетровська область\nДніпропетровськ\nДніпропетровська область\nсуддя ленінського районного суду м. дніпропетровська\nЗагальний місцевий суд\nСтуковенков Валерій Петрович","estate":{"25":[{"address":"м. Дніпропетровськ","space_units":"м²","space_hidden":false,"space_comment":"","region_hidden":false,"costs_comment":"","address_hidden":true,"costs":"18000","address_unclear":false,"costs_rent_comment_unclear":false,"costs_comment_unclear":false,"costs_rent_comment":"","space":"28","region_unclear":false,"region":"Дніпропетровська область","costs_rent":""}]},"source":"VULYK","income":{"5":{"family_comment":"","family":"","comment":"","value_unclear":false,"family_unclear":false,"comment_unclear":false,"value":"224049.52"},"6":{"family_comment":"","comment_unclear":false,"value":"211869.52","family":"","comment":""},"7":{"family":"","family_comment":"","value":"","comment":"","source_name":""},"8":{"family_comment":"","value":"","family":"","comment":""},"9":{"family_comment":"","value":"","family":"","comment":"","value_unclear":false},"10":{"family_comment":"","value":"12180","family":"","comment":"","value_unclear":false},"11":{"family_comment":"","value":"","family":"","comment":""},"12":{"family_comment":"","value":"","family":"","comment":""},"13":{"family_comment":"","value":"","family":"","comment":""},"14":{"family_comment":"","value":"","family":"","comment":""},"15":{"family_comment":"","value":"","family":"","comment":""},"16":{"family_comment":"","value":"","family":"","comment":""},"17":{"family_comment":"","value":"","family":"","comment":"","value_unclear":false},"18":{"family_comment":"","value":"","family":"","comment":"","value_unclear":false},"19":{"family_comment":"","value":"","family":"","comment":""},"20":{"family_comment":"","family":"","comment":"","value_unclear":false,"family_unclear":false,"comment_unclear":false,"value":""}},"general":{"family_raw":"","name":"Валерій","full_name_suggest":{"input":["Стуковенков Валерій Петрович","Валерій Петрович Стуковенков","Валерій Стуковенков"],"output":"Стуковенков Валерій Петрович"},"patronymic":"Петрович","inn_hidden":true,"addresses":[{"place_city_type_hidden":false,"place_district_hidden":false,"place_address_unclear":false,"place":"Дніпропетровська область","place_city":"Дніпропетровськ","place_unclear":false,"place_city_type_unclear":false,"place_city_type":"Місто","place_city_hidden":false,"place_city_unclear":false,"place_district":"","place_district_unclear":false,"place_address":"","place_address_hidden":true,"place_hidden":false}],"inn":"","inn_unclear":false,"last_name":"Стуковенков","full_name":"Стуковенков Валерій Петрович","family":[{"inn":"","inn_unclear":false,"family_name":"","relations_other":"","relations_hidden":false,"name_unclear":false,"inn_hidden":true,"name_hidden":true,"relations":"Подружжя"},{"inn":"","family_name":"","relations_other":"","name_unclear":false,"inn_hidden":false,"name_hidden":false,"relations":"Дитина"}],"post":{"post_hidden":false,"office":"Загальний місцевий суд","region_hidden":false,"post":"суддя ленінського районного суду м. дніпропетровська","candidate":"","region_unclear":false,"region":"Дніпропетровська область","office_hidden":false,"post_unclear":false,"office_unclear":false}},"liabilities":{"54":{"sum_comment":"","sum_foreign_comment":"","sum_foreign":"","sum":"","sum_comment_hidden":false},"55":{"sum_comment":"","sum_foreign_comment":"","sum_foreign":"","sum":""},"56":{"sum_comment":"","sum_foreign_comment":"","sum_foreign":"","sum":""},"57":{"sum_comment":"","sum_foreign_comment":"","sum_foreign":"","sum":"","sum_comment_hidden":false},"58":{"sum_comment":"","sum_foreign_comment":"","sum_foreign":"","sum":"","sum_comment_hidden":false},"59":{"sum_comment":"","sum_foreign_comment":"","sum_foreign":"","sum":""},"60":{"sum_comment":"","sum_foreign_comment":"","sum_foreign":"","sum":""},"61":{"sum_comment":"","sum_foreign_comment":"","sum_foreign":"","sum":""},"62":{"sum_comment":"","sum_foreign_comment":"","sum_foreign":"","sum":""},"63":{"sum_comment":"","sum_foreign_comment":"","sum_foreign":"","sum":"","sum_comment_hidden":false},"64":{"sum_comment":"","sum_foreign_comment":"","sum_foreign":"","sum":"","sum_comment_hidden":false}},"declaration":{"notfull_lostpages":"","additional_info_text":"","additional_info":"","date":"2015-03-11T00:00:00","notfull":"","url":"http://static.declarations.com.ua/declarations/chosen_ones/judges_batch/2449_stukovenkov_valerii_petorovych.pdf"},"intro":{"isnotdeclaration":"","declaration_year_unclear":false,"declaration_year":"2014"}}