{"income":{"5":{"value":"222155","family_unclear":false,"family_hidden":false,"family_comment":"","family":"28716","comment":""},"6":{"value":"222155","family_comment":"","value_unclear":false,"family_hidden":false,"family_unclear":false,"family":"28716","comment":""},"7":{"value":"","family_hidden":false,"value_hidden":false,"family_comment":"","source_name":"","family":"","comment":"","source_name_hidden":false},"8":{"family_comment":"","value":"","family":"","comment":""},"9":{"family_comment":"","value":"","family":"","comment":""},"10":{"family_comment":"","value":"","value_unclear":false,"family":"","comment":""},"11":{"family_comment":"","value":"","family":"","comment":""},"12":{"family_comment":"","value":"","family":"","comment":""},"13":{"family_comment":"","value":"","family":"","comment":""},"14":{"family_comment":"","value":"","family":"","comment":""},"15":{"family_comment":"","value":"","family":"","comment":""},"16":{"family_comment":"","value":"","family":"","comment":""},"17":{"family_comment":"","value":"","family":"","comment":""},"18":{"family_comment":"","value":"","family":"","comment":""},"19":{"family_comment":"","value":"","family":"","comment":""},"20":{"value":"","family_comment":"","value_unclear":false,"family_unclear":false,"comment_unclear":false,"comment":"","family":""}},"vehicle":{"40":[{"brand_info":"2378 куб. см.","sum_rent_comment":"","brand":"Mitsubishi Outlander","sum_comment":"","brand_unclear":false,"year":"2006","brand_info_unclear":false,"year_unclear":false,"sum":"","sum_rent":""}]},"id":"vulyk_74_13","banks":{"45":[{"sum_foreign_comment":"","sum":"2284","sum_comment":"","sum_comment_unclear":false,"sum_hidden":false,"sum_foreign_units":"UAH","sum_foreign_hidden":false,"sum_units":"UAH","sum_comment_hidden":false,"sum_unclear":false,"sum_foreign":""}]},"declaration":{"additional_info_text":"","notfull_lostpages":"","date":"2014-03-20T00:00:00","notfull":"","additional_info":"","url":"http://static.declarations.com.ua/declarations/chosen_ones/judges_batch/1771_vivdychenko_tetiana_romanivna.pdf"},"liabilities":{"54":{"sum_foreign_comment":"","sum":"","sum_comment":"","sum_comment_unclear":false,"sum_comment_hidden":false,"sum_foreign":""},"55":{"sum_foreign_comment":"","sum":"","sum_comment":"","sum_hidden":false,"sum_unclear":false,"sum_foreign":""},"56":{"sum_foreign_comment":"","sum":"","sum_comment":"","sum_hidden":false,"sum_unclear":false,"sum_foreign":""},"57":{"sum_foreign_comment":"","sum":"","sum_comment":"","sum_comment_unclear":false,"sum_comment_hidden":false,"sum_foreign":""},"58":{"sum_foreign_comment":"","sum_comment_hidden":false,"sum":"","sum_comment":"","sum_foreign":""},"59":{"sum_foreign_comment":"","sum":"","sum_comment":"","sum_foreign":""},"60":{"sum_foreign_comment":"","sum":"","sum_hidden":false,"sum_comment":"","sum_foreign":""},"61":{"sum_foreign_comment":"","sum":"","sum_comment":"","sum_foreign":""},"62":{"sum_foreign_comment":"","sum":"","sum_comment":"","sum_foreign":""},"63":{"sum_foreign_comment":"","sum":"","sum_comment":"","sum_comment_unclear":false,"sum_unclear":false,"sum_foreign":""},"64":{"sum_foreign_comment":"","sum":"","sum_comment":"","sum_comment_unclear":false,"sum_unclear":false,"sum_foreign":""}},"ft_src":"суддя київського апеляційного адміністративного суду\nм. Київ\nАпеляційний адміністративний суд\nВівдиченко Тетяна Романівна\nВівдиченко\nТетяна\nВівдиченко В. А\nПодружжя\nВівдиченко Тетяна Романівна\nТетяна Романівна Вівдиченко\nТетяна Вівдиченко\nВівдиченко Тетяна Романівна\nРоманівна\nMitsubishi Outlander\n2378 куб. см.\n2006\n.062\n.25\n50.2\n121.6\n2284\n2013\n2378 куб. см.\nMitsubishi Outlander\n2006\n2013\nАпеляційний адміністративний суд\nм. Київ\nсуддя київського апеляційного адміністративного суду\nРоманівна\nВівдиченко Тетяна Романівна\nТетяна Романівна Вівдиченко\nТетяна Вівдиченко\nВівдиченко Тетяна Романівна\nТетяна\nПодружжя\nВівдиченко В. А\nВівдиченко Тетяна Романівна\nВівдиченко\n28716\n222155\n222155\n28716\n.062\n.25\n50.2\n121.6\n2284\n28716\n222155\n28716\n222155\nПодружжя\nВівдиченко В. А\nРоманівна\nВівдиченко\nм. Київ\nАпеляційний адміністративний суд\nсуддя київського апеляційного адміністративного суду\nВівдиченко Тетяна Романівна\nВівдиченко Тетяна Романівна\nТетяна Романівна Вівдиченко\nТетяна Вівдиченко\nВівдиченко Тетяна Романівна\nТетяна\n2006\n2378 куб. см.\nMitsubishi Outlander\n222155\n28716\n222155\n28716\n50.2\n121.6\n.062\n.25\n2284\n2013","general":{"inn":"","family_raw":"","last_name":"Вівдиченко","post":{"region_unclear":false,"region":"м. Київ","post":"суддя київського апеляційного адміністративного суду","office":"Апеляційний адміністративний суд","office_unclear":false,"post_hidden":false},"name":"Тетяна","full_name":"Вівдиченко Тетяна Романівна","inn_hidden":false,"family":[{"inn":"","relations":"Подружжя","relations_other":"","inn_hidden":true,"family_name":"Вівдиченко В. А","name_hidden":false,"name_unclear":false}],"full_name_suggest":{"output":"Вівдиченко Тетяна Романівна","input":["Вівдиченко Тетяна Романівна","Тетяна Романівна Вівдиченко","Тетяна Вівдиченко"]},"patronymic":"Романівна"},"source":"VULYK","estate":{"25":[{"space_hidden":false,"costs":"","costs_comment":"","address_hidden":false,"region_hidden":true,"space_comment":"","space_unclear":false,"space":"50.2","address":"","region":"","costs_rent_comment":"","space_units":"м²","costs_rent":""},{"costs_rent":"","region":"","costs":"","costs_rent_comment":"","costs_comment":"","region_hidden":false,"space_comment":"","space_units":"м²","space":"121.6","address":""}],"29":[{"costs_rent":"","region":"","costs_property":"","costs_rent_comment":"","address_hidden":false,"region_hidden":false,"space_comment":"","costs_property_comment":"","space_units":"га","space":".062","address":""},{"costs_rent":"","region":"","costs_property":"","costs_rent_comment":"","region_hidden":false,"space_comment":"","costs_property_comment":"","space_units":"га","space":".25","address":""}]},"intro":{"declaration_year":"2013","isnotdeclaration":"","declaration_year_unclear":false}}