{"income":{"5":{"value":"295782","value_unclear":false,"family_hidden":false,"family_comment":"","family":"33804","comment":""},"6":{"family_comment":"","value":"295782","family":"","comment":""},"7":{"family_comment":"","value":"","source_name":"","family":"","comment":""},"8":{"family_comment":"","value":"","family":"","comment":""},"9":{"family_comment":"","value":"","family":"","comment":""},"10":{"family_comment":"","value":"","family":"","comment":""},"11":{"family_comment":"","value":"","family_hidden":false,"comment":"","family":""},"12":{"family_comment":"","value":"","family":"","comment":""},"13":{"family_comment":"","value":"","family":"","comment":""},"14":{"family_comment":"","value":"","family":"","comment":""},"15":{"family_comment":"","value":"","family":"","comment":""},"16":{"family_comment":"","value":"","family":"","comment":""},"17":{"family_comment":"","value":"","family":"","comment":"","family_comment_unclear":false},"18":{"family_comment":"","value":"","family":"","comment":""},"19":{"family_comment":"","value":"","family":"","comment":""},"20":{"value":"","family_unclear":false,"family_hidden":false,"family_comment":"","family":"33804","comment":""}},"vehicle":{"35":[{"brand_info":"2996, 170","sum":"","brand":"Mercedes-Benz E300","sum_comment":"","brand_unclear":false,"year":"2010","brand_hidden":false,"brand_info_hidden":false,"brand_info_unclear":false,"sum_rent_comment":"","sum_rent":""},{"brand_info":"1500, 80","sum_rent_comment":"","brand":"Daewoo Nexia","sum_comment":"","year":"1995","sum":"","sum_rent":""}],"40":[{"year_hidden":false,"brand_info":"1997 куб. см., 103 кВт","sum_rent_comment":"","brand":"Nissan X-Trail 2. 0 Wagon","sum_comment":"","year":"2012","brand_hidden":false,"brand_info_unclear":false,"sum":"","sum_rent":""}]},"id":"vulyk_103_70","declaration":{"date":"2016-03-10T00:00:00","additional_info_text":"","additional_info":"","url":"http://static.declarations.com.ua/declarations/chosen_ones/judges_batch/1294_zhyvotov_hennadii_oleksiiovych.pdf"},"liabilities":{"54":{"sum_foreign_comment":"","sum_foreign_hidden":false,"sum_comment":"","sum_foreign_comment_hidden":false,"sum_hidden":false,"sum_foreign_comment_unclear":false,"sum_comment_hidden":false,"sum_unclear":false,"sum":"","sum_foreign":""},"55":{"sum_foreign_comment":"","sum":"","sum_comment":"","sum_foreign":""},"56":{"sum_foreign_comment":"","sum":"","sum_comment":"","sum_foreign":""},"57":{"sum_foreign_comment":"","sum_foreign_hidden":false,"sum_comment":"","sum_foreign_comment_hidden":false,"sum_hidden":false,"sum_comment_hidden":false,"sum":"","sum_foreign":""},"58":{"sum_foreign_comment":"","sum_foreign_hidden":false,"sum_comment":"","sum_foreign_comment_hidden":false,"sum_hidden":false,"sum_comment_hidden":false,"sum":"","sum_foreign":""},"59":{"sum_foreign_comment":"","sum_foreign_hidden":false,"sum_comment":"","sum_foreign_comment_hidden":false,"sum_hidden":false,"sum_comment_hidden":false,"sum":"","sum_foreign":""},"60":{"sum_foreign_comment":"","sum":"","sum_comment":"","sum_hidden":false,"sum_comment_hidden":false,"sum_foreign":""},"61":{"sum_foreign_comment":"","sum":"","sum_comment":"","sum_foreign":""},"62":{"sum_foreign_comment":"","sum_comment_hidden":false,"sum":"","sum_comment":"","sum_foreign":""},"63":{"sum_foreign_comment":"","sum":"","sum_comment":"","sum_foreign":""},"64":{"sum_foreign_comment":"","sum":"","sum_comment":"","sum_foreign":""}},"ft_src":"Животов Геннадій Олексійович\nсуддя вищого спецiалiзованого суду україни з розгляду цивiльних і кримiнальних справ\nЗагальнодержавний регіон\nВищий спеціалізований суд з розгляду цивільних і кримінальних справ\nГеннадій\nЖивотова Тамара Кіндратіївна\nБатьки\nЖивотова Ріта Іванівна\nПодружжя\nЖивотова Тамара Геннадіївна\nДитина\nЖивотов Геннадій Олексійович\nГеннадій Олексійович Животов\nГеннадій Животов\nЖивотов Геннадій Олексійович\nЖивотов\nОлексійович\nMercedes-Benz E300\n2996, 170\n2010\n1500, 80\n1995\nDaewoo Nexia\n1997 куб. см., 103 кВт\nNissan X-Trail 2. 0 Wagon\n2012\n24\n831\n92.6\nорендоване паркомісце\n15\n2737\n69\n87.8\n69\n87.8\n2015\n295782\n33804\n295782\n33804\n2996, 170\n2010\nMercedes-Benz E300\n1500, 80\n1995\nDaewoo Nexia\n1997 куб. см., 103 кВт\n2012\nNissan X-Trail 2. 0 Wagon\n24\n15\nорендоване паркомісце\n69\n87.8\n2737\n831\n92.6\n69\n87.8\nЖивотов\nЖивотов Геннадій Олексійович\nГеннадій Олексійович Животов\nГеннадій Животов\nЖивотов Геннадій Олексійович\nЖивотов Геннадій Олексійович\nОлексійович\nБатьки\nЖивотова Тамара Кіндратіївна\nЖивотова Ріта Іванівна\nПодружжя\nДитина\nЖивотова Тамара Геннадіївна\nГеннадій\nВищий спеціалізований суд з розгляду цивільних і кримінальних справ\nсуддя вищого спецiалiзованого суду україни з розгляду цивiльних і кримiнальних справ\nЗагальнодержавний регіон\n295782\n33804\n295782\n33804\n2015\nБатьки\nЖивотова Тамара Кіндратіївна\nПодружжя\nЖивотова Ріта Іванівна\nДитина\nЖивотова Тамара Геннадіївна\nЖивотов\nОлексійович\nсуддя вищого спецiалiзованого суду україни з розгляду цивiльних і кримiнальних справ\nВищий спеціалізований суд з розгляду цивільних і кримінальних справ\nЗагальнодержавний регіон\nЖивотов Геннадій Олексійович\nЖивотов Геннадій Олексійович\nГеннадій Олексійович Животов\nГеннадій Животов\nЖивотов Геннадій Олексійович\nГеннадій\nMercedes-Benz E300\n2996, 170\n2010\nDaewoo Nexia\n1500, 80\n1995\nNissan X-Trail 2. 0 Wagon\n1997 куб. см., 103 кВт\n2012\n33804\n295782\n33804\n295782\n69\n87.8\n2737\n92.6\n24\nорендоване паркомісце\n15\n69\n87.8\n831\n2015","general":{"inn":"","inn_hidden":true,"last_name":"Животов","post":{"region":"Загальнодержавний регіон","region_unclear":false,"post":"суддя вищого спецiалiзованого суду україни з розгляду цивiльних і кримiнальних справ","office_unclear":false,"office":"Вищий спеціалізований суд з розгляду цивільних і кримінальних справ"},"name":"Геннадій","full_name":"Животов Геннадій Олексійович","family_raw":"","addresses":[{"place_district":"","place_city_hidden":true,"place_city":"","place_city_type_hidden":false,"place_district_hidden":false,"place_city_type":"","place_address_hidden":true,"place_address":"","place_hidden":true,"place":""}],"family":[{"inn":"","relations":"Батьки","relations_hidden":false,"inn_hidden":true,"relations_other":"","name_hidden":true,"family_name":"Животова Тамара Кіндратіївна","name_unclear":false},{"inn":"","family_name":"Животова Ріта Іванівна","relations":"Подружжя","inn_hidden":false,"relations_other":""},{"inn":"","relations":"Дитина","relations_other":"","inn_hidden":false,"family_name":"Животова Тамара Геннадіївна","name_unclear":false}],"full_name_suggest":{"output":"Животов Геннадій Олексійович","input":["Животов Геннадій Олексійович","Геннадій Олексійович Животов","Геннадій Животов"]},"patronymic":"Олексійович"},"source":"VULYK","estate":{"23":[{"costs_rent":"","region":"","costs":"","costs_rent_comment":"","costs_comment":"","address_hidden":false,"region_hidden":true,"space_comment":"","space_units":"м²","space":"2737","address":""}],"24":[{"space_hidden":false,"costs":"","costs_comment":"","address_hidden":false,"region_hidden":true,"space_comment":"","space_unclear":false,"space":"92.6","address":"","region":"","costs_rent_comment":"","space_units":"м²","costs_rent":""}],"25":[{"costs":"","costs_comment":"","address_hidden":false,"region_hidden":true,"space_comment":"","space":"69","address":"","region":"","costs_rent_comment":"","space_comment_unclear":false,"space_comment_hidden":false,"space_units":"м²","costs_rent":""},{"costs_rent":"","region":"","costs":"","costs_rent_comment":"","costs_comment":"","region_hidden":false,"space_comment":"","space_units":"м²","space":"87.8","address":""}],"27":[{"costs_rent":"","region":"","costs":"","costs_rent_comment":"","costs_comment":"","address_hidden":false,"region_hidden":true,"space_comment":"","space_units":"м²","space":"24","address":""}],"28":[{"space_hidden":false,"costs":"","costs_comment":"","address_hidden":false,"region_hidden":true,"space_comment":"орендоване паркомісце","space_unclear":false,"space":"15","address":"","region":"","costs_rent_comment":"","space_units":"м²","costs_rent":""}],"29":[{"space_hidden":false,"address_hidden":true,"region_hidden":true,"space_comment":"","space":"831","address":"","region":"","costs_property":"","costs_rent_comment":"","space_units":"м²","costs_property_comment":"","costs_rent":""}],"31":[{"space_hidden":false,"address_hidden":true,"region_hidden":true,"space_comment":"","space":"69","address":"","costs_property":"","costs_rent_comment":"","address_unclear":false,"space_units":"м²","costs_property_comment":"","costs_rent":""},{"costs_rent":"","address_hidden":true,"space_hidden":false,"costs_property":"","costs_rent_comment":"","space_comment_unclear":false,"space_comment":"","costs_property_comment":"","space_units":"м²","space":"87.8","address":""}]},"intro":{"declaration_year":"2015"}}