{"income":{"5":{"value":"209291","family_comment":"","value_unclear":false,"comment_hidden":false,"family_hidden":false,"value_hidden":false,"family_unclear":false,"family_comment_hidden":false,"comment":"","family":"331828"},"6":{"value":"196681","family_comment":"","value_unclear":false,"family_hidden":false,"family_unclear":false,"family":"","comment":""},"7":{"source_name_unclear":false,"value":"","family_hidden":false,"family_comment":"","source_name":"","family":"","comment":"","source_name_hidden":false},"8":{"family_comment":"","value":"","family":"","comment":""},"9":{"value":"","value_unclear":false,"family_hidden":false,"family_comment":"","family":"","comment":""},"10":{"value":"12180","value_unclear":false,"family_hidden":false,"value_hidden":false,"family_comment":"","comment_unclear":false,"comment":"","family":""},"11":{"family_comment":"","value":"","family":"","comment":""},"12":{"family_comment":"","value":"","family":"","comment":""},"13":{"family_comment":"","value":"","family":"","comment":""},"14":{"family_comment":"","value":"","family":"","comment":""},"15":{"family_comment":"","value":"","family_hidden":false,"comment":"","family":""},"16":{"value":"","value_unclear":false,"family_hidden":false,"family_comment":"","family":"","comment":""},"17":{"family_comment":"","value":"","family_hidden":false,"comment":"","family":"331828"},"18":{"family_comment":"","value":"","value_unclear":false,"family":"","comment":""},"19":{"family_comment":"","value":"","family":"","comment":""},"20":{"value":"430","family_comment":"","value_unclear":false,"family_hidden":false,"family_unclear":false,"comment_unclear":false,"comment":"","family":""}},"vehicle":{"35":[{"brand_info":"2354 куб см","sum_rent_comment":"","brand_info_unclear":false,"year":"2012","sum_rent_unclear":false,"brand_info_hidden":false,"sum_rent_comment_unclear":false,"sum_hidden":false,"sum_rent":"","sum":"","brand":"Honda Accord","sum_comment":"","brand_unclear":false,"brand_hidden":false}],"40":[{"year_hidden":false,"brand_info":"1800 куб см","sum_rent_comment":"","year":"2007","brand_info_hidden":false,"brand_info_unclear":false,"year_unclear":false,"sum_rent":"","sum":"","brand":"Honda Civic","sum_comment":"","brand_unclear":false,"brand_hidden":false}]},"id":"vulyk_72_315","declaration":{"additional_info_text":"","notfull_lostpages":"","date":"2015-03-31T00:00:00","notfull":"","additional_info":"","url":"http://static.declarations.com.ua/declarations/chosen_ones/epic_batch/rumiantsev_oleksii_pavlovych.pdf"},"liabilities":{"54":{"sum_foreign_comment":"","sum":"528","sum_comment":"","sum_comment_hidden":false,"sum_unclear":false,"sum_foreign":""},"55":{"sum_foreign_comment":"","sum":"","sum_comment":"","sum_foreign":""},"56":{"sum_foreign_comment":"","sum":"","sum_hidden":false,"sum_comment":"","sum_foreign":""},"57":{"sum_foreign_comment":"","sum":"","sum_comment":"","sum_comment_unclear":false,"sum_hidden":false,"sum_comment_hidden":false,"sum_unclear":false,"sum_foreign":""},"58":{"sum_foreign_comment":"","sum":"","sum_comment":"","sum_comment_unclear":false,"sum_hidden":false,"sum_comment_hidden":false,"sum_unclear":false,"sum_foreign":""},"59":{"sum_foreign_comment":"","sum_foreign_hidden":false,"sum_comment":"","sum_foreign_unclear":false,"sum_comment_hidden":false,"sum":"","sum_foreign":""},"60":{"sum_foreign_comment":"","sum_foreign_hidden":false,"sum_comment":"","sum_hidden":false,"sum":"15039","sum_foreign":""},"61":{"sum_foreign_comment":"","sum_foreign_hidden":false,"sum_comment":"","sum_hidden":false,"sum":"","sum_foreign":""},"62":{"sum_foreign_comment":"","sum_foreign_hidden":false,"sum_comment":"","sum_hidden":false,"sum":"","sum_foreign":""},"63":{"sum_foreign_comment":"","sum_foreign_hidden":false,"sum_comment":"","sum_comment_unclear":false,"sum_hidden":false,"sum_comment_hidden":false,"sum_unclear":false,"sum":"","sum_foreign":""},"64":{"sum_foreign_comment":"","sum_foreign_hidden":false,"sum_comment":"","sum_hidden":false,"sum":"","sum_foreign":""}},"ft_src":"528\n15039\nДніпропетровськ\n49107\nДніпропетровська область\nсуддя самарського районного суду м. дніпропетровська\nДніпропетровська область\nЗагальний місцевий суд\nОлексій\nРумянцева Т. В\nПодружжя\nРумянцев П. О\nДитина\nРумянцев М. О\nДитина\nРумянцев І. О\nДитина\nПавлович\nРумянцев\nРумянцев Олексій Павлович\nРумянцев Олексій Павлович\nОлексій Павлович Румянцев\nОлексій Румянцев\nРумянцев Олексій Павлович\n2354 куб см\nHonda Accord\n2012\n1800 куб см\nHonda Civic\n2007\n.2\n98.4\n46\n443.5\n32\n2014\n196681\n12180\n331828\n209291\n331828\n430\n2354 куб см\nHonda Accord\n2012\n1800 куб см\nHonda Civic\n2007\n443.5\n32\n.2\n98.4\n46\nПодружжя\nРумянцева Т. В\nДитина\nРумянцев П. О\nДитина\nРумянцев М. О\nДитина\nРумянцев І. О\nРумянцев Олексій Павлович\nОлексій Павлович Румянцев\nОлексій Румянцев\nРумянцев Олексій Павлович\nОлексій\nРумянцев Олексій Павлович\nРумянцев\nДніпропетровська область\nЗагальний місцевий суд\nсуддя самарського районного суду м. дніпропетровська\nПавлович\nДніпропетровськ\n49107\nДніпропетровська область\n528\n15039\n196681\n430\n331828\n209291\n331828\n12180\n2014\n528\n15039\nРумянцева Т. В\nПодружжя\nРумянцев П. О\nДитина\nРумянцев М. О\nДитина\nРумянцев І. О\nДитина\nПавлович\nРумянцев\nРумянцев Олексій Павлович\nОлексій Павлович Румянцев\nОлексій Румянцев\nРумянцев Олексій Павлович\nДніпропетровська область\nДніпропетровськ\n49107\nДніпропетровська область\nЗагальний місцевий суд\nсуддя самарського районного суду м. дніпропетровська\nРумянцев Олексій Павлович\nОлексій\n2012\nHonda Accord\n2354 куб см\nHonda Civic\n1800 куб см\n2007\n12180\n430\n209291\n331828\n331828\n196681\n46\n98.4\n443.5\n32\n.2\n2014","general":{"inn":"","name":"Олексій","patronymic_unclear":false,"family":[{"inn":"","inn_hidden":true,"relations_unclear":false,"relations_hidden":false,"relations_other":"","relations":"Подружжя","name_hidden":false,"inn_unclear":false,"family_name":"Румянцева Т. В","name_unclear":false},{"inn":"","inn_hidden":false,"relations_hidden":false,"family_name":"Румянцев П. О","relations_other":"","relations":"Дитина","name_hidden":false,"name_unclear":false},{"inn":"","inn_hidden":false,"relations_hidden":false,"family_name":"Румянцев М. О","relations_other":"","relations":"Дитина","name_hidden":false,"name_unclear":false},{"inn":"","relations":"Дитина","relations_other":"","inn_hidden":false,"family_name":"Румянцев І. О","name_hidden":false}],"patronymic":"Павлович","inn_hidden":true,"family_raw":"","inn_unclear":false,"post":{"post_unclear":false,"region_unclear":false,"post":"суддя самарського районного суду м. дніпропетровська","candidate":"","office_hidden":false,"region":"Дніпропетровська область","post_hidden":false,"office":"Загальний місцевий суд","office_unclear":false,"region_hidden":false},"last_name_unclear":false,"full_name":"Румянцев Олексій Павлович","addresses":[{"place_city_type_hidden":false,"place_district_hidden":false,"place_city_type":"Місто","place_city_hidden":false,"place_address_unclear":false,"place_address":"49107","place":"Дніпропетровська область","place_district":"","place_unclear":false,"place_city":"Дніпропетровськ","place_city_unclear":false,"place_hidden":false,"place_address_hidden":true,"place_district_unclear":false}],"last_name":"Румянцев","patronymic_hidden":false,"full_name_suggest":{"output":"Румянцев Олексій Павлович","input":["Румянцев Олексій Павлович","Олексій Павлович Румянцев","Олексій Румянцев"]},"name_unclear":false},"source":"VULYK","estate":{"23":[{"space_hidden":false,"costs":"","costs_rent_unclear":false,"costs_comment":"","costs_hidden":false,"address_hidden":false,"region_hidden":true,"space_comment":"","space_unclear":false,"space":"","address":"","region":"","address_unclear":false,"costs_rent_comment":"","costs_rent_hidden":false,"space_units":"м²","space_units_hidden":false,"costs_rent":""}],"24":[{"space_hidden":false,"costs":"","costs_comment":"","address_hidden":true,"region_hidden":true,"space_comment":"","space":"98.4","address":"","region":"","address_unclear":false,"costs_rent_comment":"","space_units":"м²","costs_rent":""}],"25":[{"space_unclear":false,"costs":"","costs_rent_unclear":false,"costs_comment":"","costs_hidden":false,"space_hidden":false,"costs_comment_unclear":false,"costs_rent_comment_unclear":false,"region":"","space_comment_hidden":false,"space_comment_unclear":false,"costs_rent_comment_hidden":false,"costs_rent":"","costs_comment_hidden":false,"address_hidden":true,"region_hidden":true,"space_comment":"","space":"32","address":"","address_unclear":false,"costs_rent_comment":"","costs_rent_hidden":false,"space_units":"м²"}],"29":[{"space_hidden":false,"costs_property_comment":"","address_hidden":true,"region_hidden":true,"space_comment":"","space_unclear":false,"space":".2","address":"","region":"","costs_property":"","costs_rent_comment":"","address_unclear":false,"space_units":"га","space_units_unclear":false,"costs_rent":""}],"30":[{"region_unclear":false,"space_unclear":false,"address_hidden":true,"region_hidden":true,"space_comment":"","space_hidden":false,"space":"443.5","address":"","region":"","costs_property":"","costs_rent_comment":"","space_units":"м²","costs_property_comment":"","costs_rent":""}],"31":[{"space_unclear":false,"address_hidden":true,"region_hidden":true,"space_comment":"","space_units_hidden":false,"space_hidden":false,"space":"46","address":"","region":"","address_unclear":false,"costs_rent_comment":"","costs_property":"","space_units":"м²","costs_property_comment":"","costs_rent":""}]},"intro":{"declaration_year":"2014","isnotdeclaration":"","declaration_year_unclear":false}}