{"income":{"5":{"family_comment":"","value":"229172","family":"20352","comment":""},"6":{"value":"228521","family_comment":"","value_unclear":false,"comment_hidden":false,"family_unclear":false,"family":"","comment":""},"7":{"family_comment":"","value":"","source_name":"","family":"","comment":""},"8":{"family_comment":"","value":"","family":"","comment":""},"9":{"family_comment":"","family_unclear":false,"value":"651","family":"","comment":""},"10":{"family_comment":"","value":"","value_unclear":false,"family":"","comment":""},"11":{"family_comment":"","value":"","family":"","comment":""},"12":{"family_comment":"","value":"","family":"","comment":""},"13":{"family_comment":"","value":"","family":"","comment":""},"14":{"family_comment":"","value":"","family":"","comment":""},"15":{"family_comment":"","value":"","family":"","comment":""},"16":{"family_comment":"","value":"","family":"","comment":""},"17":{"family_comment":"","value":"","family":"","comment":""},"18":{"family_comment":"","value":"","family":"","comment":""},"19":{"family_comment":"","value":"","family":"","comment":""},"20":{"value":"","comment_unclear":false,"family_hidden":false,"family_comment":"","value_unclear":false,"family":"20352","comment":"","family_comment_unclear":false}},"id":"vulyk_97_91","banks":{"45":[{"sum_foreign_comment":"","sum_units":"UAH","sum_comment":"","sum_comment_unclear":false,"sum_hidden":true,"sum_foreign_units":"UAH","sum_comment_hidden":true,"sum_unclear":true,"sum":"6057","sum_foreign":""}]},"declaration":{"additional_info_text":"","notfull_lostpages":"","date":"2014-03-18T00:00:00","notfull":"","additional_info":"","url":"http://static.declarations.com.ua/declarations/chosen_ones/judges_batch/3992_spiridonov_mykhailo_oleksandrovych.pdf"},"liabilities":{"54":{"sum_foreign_comment":"","sum":"","sum_comment":"","sum_comment_unclear":false,"sum_hidden":false,"sum_comment_hidden":false,"sum_unclear":false,"sum_foreign":""},"55":{"sum_foreign_comment":"","sum":"","sum_comment":"","sum_foreign":""},"56":{"sum_foreign_comment":"","sum":"","sum_comment":"","sum_foreign":""},"57":{"sum_foreign_comment":"","sum":"","sum_comment":"","sum_comment_unclear":false,"sum_hidden":false,"sum_comment_hidden":false,"sum_unclear":false,"sum_foreign":""},"58":{"sum_foreign_comment":"","sum":"","sum_comment":"","sum_comment_unclear":false,"sum_hidden":false,"sum_comment_hidden":false,"sum_unclear":false,"sum_foreign":""},"59":{"sum_foreign_comment":"","sum":"","sum_comment":"","sum_foreign":""},"60":{"sum_foreign_comment":"","sum":"","sum_comment":"","sum_comment_unclear":false,"sum_hidden":false,"sum_comment_hidden":false,"sum_foreign":""},"61":{"sum_foreign_comment":"","sum":"","sum_comment":"","sum_foreign":""},"62":{"sum_foreign_comment":"","sum":"","sum_comment":"","sum_unclear":false,"sum_foreign":""},"63":{"sum_foreign_comment":"","sum":"","sum_foreign":"","sum_comment":"","sum_hidden":false},"64":{"sum_foreign_comment":"","sum":"","sum_comment":"","sum_foreign":""}},"ft_src":"72.5\nХарківська область\nм. Харків\nм. Дергачі\nХарківська область\n62\nм. Дергачі\nХарківська область\n500\n6057\n2014\n2014\nСпірідонов Михайло Олександрович\nМихайло Олександрович Спірідонов\nМихайло Спірідонов\nСпірідонов Михайло Олександрович\nМихайло\nПодружжя\nАндрієнко Ю.А.\nДитина\nСпірідонов Я. М\nДитина\nСпірідонова Т. М\nСпірідонова М. М\nДитина\nСпірідонов Михайло Олександрович\nСпірідонов\nАдміністративний місцевий суд\nХарківська область\nсуддя харківського окружного адміністративного суду\nОлександрович\nХарківська область\nДергачі\n228521\n20352\n229172\n20352\n651\n500\nХарківська область\nм. Дергачі\n62\nХарківська область\nм. Дергачі\n72.5\nХарківська область\nм. Харків\n6057\n228521\n651\n20352\n229172\n20352\nПодружжя\nАндрієнко Ю.А.\nСпірідонов Я. М\nДитина\nДитина\nСпірідонова Т. М\nСпірідонова М. М\nДитина\nОлександрович\nСпірідонов\nМихайло\nСпірідонов Михайло Олександрович\nМихайло Олександрович Спірідонов\nМихайло Спірідонов\nСпірідонов Михайло Олександрович\nДергачі\nХарківська область\nХарківська область\nАдміністративний місцевий суд\nсуддя харківського окружного адміністративного суду\nСпірідонов Михайло Олександрович","general":{"name_hidden":false,"name":"Михайло","last_name_hidden":false,"inn":"","last_name":"Спірідонов","family":[{"inn":"","relations":"Подружжя","relations_other":"","inn_hidden":true,"family_name":"Андрієнко Ю.А.","name_hidden":true,"name_unclear":true},{"inn":"","relations":"Дитина","name_hidden":false,"inn_hidden":true,"family_name":"Спірідонов Я. М","name_unclear":false},{"inn":"","relations":"Дитина","relations_other":"","inn_hidden":true,"family_name":"Спірідонова Т. М","name_hidden":false,"name_unclear":true},{"inn":"","inn_hidden":true,"relations":"Дитина","family_name":"Спірідонова М. М"}],"inn_hidden":true,"family_raw":"","inn_unclear":false,"post":{"region_unclear":false,"post":"суддя харківського окружного адміністративного суду","post_hidden":false,"region":"Харківська область","office":"Адміністративний місцевий суд","office_unclear":false},"full_name":"Спірідонов Михайло Олександрович","addresses":[{"place_district":"","place_address_hidden":true,"place_city":"Дергачі","place_city_unclear":true,"place_district_hidden":false,"place_city_type":"Місто","place_city_hidden":false,"place_city_type_hidden":false,"place_address":"","place_hidden":false,"place":"Харківська область"}],"patronymic":"Олександрович","patronymic_hidden":false,"full_name_suggest":{"output":"Спірідонов Михайло Олександрович","input":["Спірідонов Михайло Олександрович","Михайло Олександрович Спірідонов","Михайло Спірідонов"]}},"source":"VULYK","estate":{"29":[{"region_unclear":false,"space_unclear":true,"address_hidden":true,"region_hidden":false,"space_comment":"","space":"500","address":"м. Дергачі","region":"Харківська область","costs_property":"","costs_rent_comment":"","space_comment_unclear":false,"address_unclear":true,"space_units":"м²","costs_property_comment":"","costs_rent":""}],"30":[{"address_hidden":true,"region_hidden":false,"space_comment":"","space":"62","address":"м. Дергачі","region":"Харківська область","costs_property":"","costs_rent_comment":"","address_unclear":true,"space_units":"м²","costs_property_comment":"","costs_rent":""}],"31":[{"space_unclear":true,"address_hidden":true,"region_hidden":false,"space_comment":"","space_hidden":false,"space":"72.5","address":"м. Харків","region":"Харківська область","costs_property":"","costs_rent_comment":"","space_comment_hidden":false,"space_units":"м²","costs_property_comment":"","costs_rent":""}]},"intro":{"declaration_year":"2014","isnotdeclaration":""}}