{"income":{"5":{"value":"213051","family_comment":"","value_unclear":false,"comment_hidden":false,"family_hidden":false,"value_hidden":false,"family_unclear":false,"family_comment_hidden":false,"comment":"","family":"80921"},"6":{"value":"210360","family_comment":"","value_unclear":false,"family_hidden":false,"family_unclear":false,"family":"76687","comment":""},"7":{"source_name_unclear":false,"value":"","family_hidden":false,"family_comment":"","source_name":"","family":"","comment":"","source_name_hidden":false},"8":{"family_comment":"","value":"","family":"","comment":""},"9":{"value":"2691","value_unclear":false,"family_hidden":false,"family_comment":"","family":"","comment":""},"10":{"value":"","value_unclear":false,"family_hidden":false,"value_hidden":false,"family_comment":"","comment_unclear":false,"comment":"","family":""},"11":{"family_comment":"","value":"","family":"","comment":""},"12":{"family_comment":"","value":"","family":"","comment":""},"13":{"family_comment":"","value":"","family":"","comment":""},"14":{"family_comment":"","value":"","family":"","comment":""},"15":{"family_comment":"","value":"","family_hidden":false,"comment":"","family":""},"16":{"value":"","value_unclear":false,"family_hidden":false,"family_comment":"","family":"","comment":""},"17":{"family_comment":"","value":"","family_hidden":false,"comment":"","family":""},"18":{"family_comment":"","value":"","value_unclear":false,"family":"","comment":""},"19":{"family_comment":"","value":"","family":"4234","comment":""},"20":{"value":"","family_comment":"","value_unclear":false,"family_hidden":false,"family_unclear":false,"comment_unclear":false,"comment":"","family":"4234"}},"id":"vulyk_72_78","banks":{"45":[{"sum_foreign_comment":"","sum_units":"UAH","sum_comment":"Ощадбанк","sum_comment_unclear":true,"sum_hidden":false,"sum_foreign_units":"UAH","sum_comment_hidden":false,"sum_unclear":true,"sum":"1073","sum_foreign":""},{"sum_foreign_comment":"","sum_units":"UAH","sum_comment":"КС Галицьке кредитне товариство","sum_comment_unclear":true,"sum_foreign_units":"UAH","sum":"30000","sum_foreign":""}]},"declaration":{"additional_info_text":"","notfull_lostpages":"","date":"2015-03-25T00:00:00","notfull":"","additional_info":"","url":"http://static.declarations.com.ua/declarations/chosen_ones/epic_batch/malakhova-onufer_anhelina_mykolaivna.pdf"},"liabilities":{"54":{"sum_foreign_comment":"","sum":"","sum_comment":"","sum_comment_hidden":false,"sum_unclear":false,"sum_foreign":""},"55":{"sum_foreign_comment":"","sum":"","sum_comment":"","sum_foreign":""},"56":{"sum_foreign_comment":"","sum":"","sum_hidden":false,"sum_comment":"","sum_foreign":""},"57":{"sum_foreign_comment":"","sum":"","sum_comment":"","sum_comment_unclear":false,"sum_hidden":false,"sum_comment_hidden":false,"sum_unclear":false,"sum_foreign":""},"58":{"sum_foreign_comment":"","sum":"","sum_comment":"","sum_comment_unclear":false,"sum_hidden":false,"sum_comment_hidden":false,"sum_unclear":false,"sum_foreign":""},"59":{"sum_foreign_comment":"","sum_foreign_hidden":false,"sum_comment":"","sum_foreign_unclear":false,"sum_comment_hidden":false,"sum":"","sum_foreign":""},"60":{"sum_foreign_comment":"","sum_foreign_hidden":false,"sum_comment":"","sum_hidden":false,"sum":"120","sum_foreign":""},"61":{"sum_foreign_comment":"","sum_foreign_hidden":false,"sum_comment":"","sum_hidden":false,"sum":"","sum_foreign":""},"62":{"sum_foreign_comment":"","sum_foreign_hidden":false,"sum_comment":"","sum_hidden":false,"sum":"","sum_foreign":""},"63":{"sum_foreign_comment":"","sum_foreign_hidden":false,"sum_comment":"","sum_comment_unclear":false,"sum_hidden":false,"sum_comment_hidden":false,"sum_unclear":false,"sum":"","sum_foreign":""},"64":{"sum_foreign_comment":"","sum_foreign_hidden":false,"sum_comment":"","sum_hidden":false,"sum":"","sum_foreign":""}},"ft_src":"120\n2870612028\nзаступник голови городоцького районного суду львівської області\nЛьвівська область\nЗагальний місцевий суд\nАнгеліна\nМалахов С. І\nПодружжя\nМалахова Є. С\nДитина\nМиколаївна\nМалахова-Онуфер\nМалахова-Онуфер Ангеліна Миколаївна\nМалахова-Онуфер Ангеліна Миколаївна\nАнгеліна Миколаївна Малахова-Онуфер\nАнгеліна Малахова-Онуфер\nМалахова-Онуфер Ангеліна Миколаївна\n27300\n31.3\nОщадбанк\n1073\nКС Галицьке кредитне товариство\n30000\n2014\n27300\n31.3\nПодружжя\nМалахов С. І\nДитина\nМалахова Є. С\nМалахова-Онуфер Ангеліна Миколаївна\nАнгеліна Миколаївна Малахова-Онуфер\nАнгеліна Малахова-Онуфер\nМалахова-Онуфер Ангеліна Миколаївна\nАнгеліна\n2870612028\nМалахова-Онуфер Ангеліна Миколаївна\nМалахова-Онуфер\nЛьвівська область\nЗагальний місцевий суд\nзаступник голови городоцького районного суду львівської області\nМиколаївна\n120\n210360\n76687\n4234\n213051\n80921\n2691\n4234\n1073\nОщадбанк\n30000\nКС Галицьке кредитне товариство\n2014\n120\n76687\n210360\n2691\n80921\n213051\n4234\n4234\nМалахов С. І\nПодружжя\nМалахова Є. С\nДитина\n2870612028\nМиколаївна\nМалахова-Онуфер\nМалахова-Онуфер Ангеліна Миколаївна\nАнгеліна Миколаївна Малахова-Онуфер\nАнгеліна Малахова-Онуфер\nМалахова-Онуфер Ангеліна Миколаївна\nЛьвівська область\nЗагальний місцевий суд\nзаступник голови городоцького районного суду львівської області\nМалахова-Онуфер Ангеліна Миколаївна\nАнгеліна\n4234\n2691\n4234\n213051\n80921\n210360\n76687\n31.3\n27300\nОщадбанк\n1073\nКС Галицьке кредитне товариство\n30000\n2014","general":{"inn":"2870612028","name":"Ангеліна","patronymic_unclear":false,"family":[{"inn":"","inn_hidden":true,"relations_unclear":false,"relations_hidden":false,"relations_other":"","relations":"Подружжя","name_hidden":false,"inn_unclear":false,"family_name":"Малахов С. І","name_unclear":false},{"inn":"","inn_hidden":true,"relations_hidden":false,"family_name":"Малахова Є. С","relations_other":"","relations":"Дитина","name_hidden":false,"name_unclear":false}],"patronymic":"Миколаївна","inn_hidden":false,"family_raw":"","inn_unclear":false,"post":{"post_unclear":false,"region_unclear":false,"post":"заступник голови городоцького районного суду львівської області","candidate":"","office_hidden":false,"region":"Львівська область","post_hidden":false,"office":"Загальний місцевий суд","office_unclear":false,"region_hidden":false},"last_name_unclear":false,"full_name":"Малахова-Онуфер Ангеліна Миколаївна","addresses":[{"place_city_type_hidden":true,"place_district_hidden":true,"place_city_type":"","place_city_hidden":true,"place_address_unclear":false,"place_address":"","place":"","place_district":"","place_unclear":false,"place_city":"","place_city_unclear":false,"place_hidden":true,"place_address_hidden":true,"place_district_unclear":false}],"last_name":"Малахова-Онуфер","patronymic_hidden":false,"full_name_suggest":{"output":"Малахова-Онуфер Ангеліна Миколаївна","input":["Малахова-Онуфер Ангеліна Миколаївна","Ангеліна Миколаївна Малахова-Онуфер","Ангеліна Малахова-Онуфер"]},"name_unclear":false},"source":"VULYK","estate":{"29":[{"space_hidden":false,"costs_property_comment":"","address_hidden":true,"region_hidden":true,"space_comment":"","space_unclear":false,"space":"27300","address":"","region":"","costs_property":"","costs_rent_comment":"","address_unclear":false,"space_units":"м²","space_units_unclear":false,"costs_rent":""}],"34":[{"space_hidden":false,"address_hidden":true,"region_hidden":true,"space_comment":"","space":"31.3","address":"","region":"","costs_property":"","costs_rent_comment":"","space_units":"м²","costs_property_comment":"","costs_rent":""}]},"intro":{"declaration_year":"2014","isnotdeclaration":"","declaration_year_unclear":false}}