{"income":{"5":{"value":"215589","family_comment":"","value_unclear":false,"family_unclear":false,"family":"","comment":""},"6":{"family_comment":"","value":"215589","value_unclear":false,"family":"","comment":""},"7":{"value":"","value_unclear":false,"family_comment":"","source_name":"","family":"","comment":""},"8":{"family_comment":"","value":"","family":"","comment":""},"9":{"value":"","family_comment":"","value_unclear":false,"family_unclear":false,"family":"","comment":""},"10":{"family_comment":"","value":"","comment_unclear":false,"family":"","comment":""},"11":{"family_comment":"","value":"","family":"","comment":""},"12":{"family_comment":"","value":"","family":"","comment":""},"13":{"family_comment":"","value":"","value_unclear":false,"family":"","comment":""},"14":{"family_comment":"","value":"","family":"","comment":""},"15":{"family_comment":"","value":"","family":"","comment":""},"16":{"family_comment":"","family_unclear":false,"value":"","family":"","comment":""},"17":{"family_comment":"","family_unclear":false,"value":"","family":"","comment":""},"18":{"family_comment":"","value":"","family":"","comment":""},"19":{"family_comment":"","value":"","family":"","comment":""},"20":{"value":"","family_comment":"","value_unclear":false,"family_hidden":false,"value_hidden":false,"family_unclear":false,"comment_unclear":false,"comment":"","family":""}},"id":"vulyk_100_83","declaration":{"additional_info_text":"","notfull_lostpages":"","date":"2015-03-30T00:00:00","notfull":"","additional_info":"","url":"http://static.declarations.com.ua/declarations/chosen_ones/judges_batch/4283_druchkova_svitlana_petrivna.pdf"},"liabilities":{"54":{"sum_foreign_comment":"","sum":"","sum_comment":"","sum_comment_hidden":false,"sum_unclear":false,"sum_foreign":""},"55":{"sum_foreign_comment":"","sum":"","sum_comment":"","sum_foreign":""},"56":{"sum_foreign_comment":"","sum":"","sum_comment":"","sum_unclear":false,"sum_foreign":""},"57":{"sum_foreign_comment":"","sum":"18000","sum_comment":"","sum_comment_unclear":false,"sum_comment_hidden":false,"sum_unclear":false,"sum_foreign":""},"58":{"sum_foreign_comment":"","sum":"24000","sum_comment":"","sum_comment_hidden":false,"sum_unclear":false,"sum_foreign":""},"59":{"sum_foreign_comment":"","sum":"","sum_comment":"","sum_foreign":""},"60":{"sum_foreign_comment":"","sum_comment_hidden":false,"sum":"","sum_comment":"","sum_foreign":""},"61":{"sum_foreign_comment":"","sum":"","sum_comment":"","sum_foreign":""},"62":{"sum_foreign_comment":"","sum":"","sum_comment":"","sum_unclear":false,"sum_foreign":""},"63":{"sum_foreign_comment":"","sum_comment_hidden":false,"sum":"","sum_comment":"","sum_foreign":""},"64":{"sum_foreign_comment":"","sum_comment_hidden":false,"sum":"","sum_comment":"","sum_foreign":""}},"ft_src":"18000\n24000\nПетрівна\nДручкова Світлана Петрівна\nсуддя хмельницького міськрайонного суду хмельницької області\nХмельницька область\nЗагальний місцевий суд\nСвітлана\nДручкова Світлана Петрівна\nСвітлана Петрівна Дручкова\nСвітлана Дручкова\nДручкова Світлана Петрівна\nДручкова\n215589\n215589\n2014\n215589\n215589\n215589\n215589\nЗагальний місцевий суд\nХмельницька область\nсуддя хмельницького міськрайонного суду хмельницької області\nПетрівна\nДручкова Світлана Петрівна\nСвітлана Петрівна Дручкова\nСвітлана Дручкова\nДручкова Світлана Петрівна\nДручкова Світлана Петрівна\nСвітлана\nДручкова\n18000\n24000\n2014\n24000\n18000\nПетрівна\nДручкова\nХмельницька область\nЗагальний місцевий суд\nсуддя хмельницького міськрайонного суду хмельницької області\nДручкова Світлана Петрівна\nДручкова Світлана Петрівна\nСвітлана Петрівна Дручкова\nСвітлана Дручкова\nДручкова Світлана Петрівна\nСвітлана\n2014","general":{"inn":"","inn_hidden":true,"last_name":"Дручкова","post":{"post_unclear":false,"region_unclear":false,"post":"суддя хмельницького міськрайонного суду хмельницької області","office":"Загальний місцевий суд","region":"Хмельницька область","post_hidden":false,"office_unclear":false},"name":"Світлана","full_name":"Дручкова Світлана Петрівна","family_raw":"","addresses":[{"place_district":"","place_city_hidden":true,"place_city":"","place_city_unclear":false,"place_district_hidden":false,"place_city_type":"","place_address_hidden":true,"place_city_type_hidden":false,"place_address":"","place_hidden":true,"place":""}],"full_name_suggest":{"output":"Дручкова Світлана Петрівна","input":["Дручкова Світлана Петрівна","Світлана Петрівна Дручкова","Світлана Дручкова"]},"patronymic":"Петрівна"},"source":"VULYK","intro":{"declaration_year":"2014"}}