{"income":{"5":{"value":"252360.24","comment_hidden":false,"family_comment":"","family":"","comment":"","family_comment_hidden":false},"6":{"value":"227496.16","family_comment":"","comment_hidden":false,"family_hidden":false,"family_unclear":false,"family_comment_hidden":false,"comment":"","family":""},"7":{"value":"","comment_hidden":false,"family_comment_hidden":false,"family_comment":"","source_name":"","family":"","comment":"","source_name_hidden":false},"8":{"family_comment":"","value":"","family":"","comment":""},"9":{"value":"24864.16","family_comment":"","value_unclear":false,"family_unclear":false,"comment_unclear":false,"comment":"","family":""},"10":{"family_comment":"","family_unclear":false,"value":"","family":"","comment":""},"11":{"family_comment":"","value":"","family":"","comment":""},"12":{"family_comment":"","value":"","family":"","comment":""},"13":{"family_comment":"","value":"","family":"","comment":""},"14":{"family_comment":"","value":"","family":"","comment":""},"15":{"family_comment":"","value":"","comment_unclear":false,"family":"","comment":""},"16":{"family_comment":"","value":"","comment_unclear":false,"family":"","comment":""},"17":{"family_comment":"","value":"","family":"","comment":""},"18":{"family_comment":"","value":"","family":"","comment":""},"19":{"family_comment":"","value":"","family":"","comment":""},"20":{"value":"","family_comment":"","value_unclear":false,"family_unclear":false,"family_comment_unclear":false,"family_comment_hidden":false,"comment":"","family":""}},"vehicle":{"35":[{"brand_info":"1498 куб. см., 107 к.с., 76.8 кВт","sum_rent_comment":"","brand":"Subaru Impreza","sum_comment":"","brand_unclear":false,"year":"2009","sum_hidden":false,"brand_info_unclear":false,"sum":"","sum_rent":""}]},"id":"vulyk_73_164","banks":{"45":[{"sum_foreign_comment":"","sum_units":"UAH","sum_comment":"","sum_comment_unclear":false,"sum_hidden":false,"sum_foreign_units":"UAH","sum_comment_hidden":false,"sum_unclear":false,"sum":"304591","sum_foreign":""}],"46":[{"sum_foreign_comment":"","sum_units":"UAH","sum_comment":"","sum_foreign_units":"UAH","sum":"103979","sum_foreign":""}]},"declaration":{"additional_info_text":"","notfull_lostpages":"","date":"2014-03-28T00:00:00","notfull":"","additional_info":"","url":"http://static.declarations.com.ua/declarations/chosen_ones/judges_batch/865_iasenovenko_liudmyla_vasylivna.pdf"},"liabilities":{"54":{"sum_foreign_comment":"","sum_foreign_hidden":false,"sum_comment":"","sum_comment_unclear":false,"sum_hidden":false,"sum_comment_hidden":false,"sum_unclear":false,"sum":"7997.92","sum_foreign":""},"55":{"sum_foreign_comment":"","sum_comment_hidden":false,"sum":"","sum_comment":"","sum_foreign":""},"56":{"sum_foreign_comment":"","sum":"","sum_comment":"","sum_comment_unclear":false,"sum_foreign":""},"57":{"sum_foreign_comment":"","sum":"","sum_comment":"","sum_hidden":false,"sum_comment_hidden":false,"sum_unclear":false,"sum_foreign":""},"58":{"sum_foreign_comment":"","sum":"","sum_comment":"","sum_hidden":false,"sum_comment_hidden":false,"sum_foreign":""},"59":{"sum_foreign_comment":"","sum":"","sum_comment":"","sum_comment_unclear":false,"sum_unclear":false,"sum_foreign":""},"60":{"sum_foreign_comment":"","sum":"","sum_comment":"","sum_hidden":false,"sum_comment_hidden":false,"sum_unclear":false,"sum_foreign":""},"61":{"sum_foreign_comment":"","sum":"","sum_comment":"","sum_foreign":""},"62":{"sum_foreign_comment":"","sum":"","sum_comment":"","sum_foreign":""},"63":{"sum_foreign_comment":"","sum":"","sum_comment":"","sum_hidden":false,"sum_comment_hidden":false,"sum_foreign":""},"64":{"sum_foreign_comment":"","sum":"","sum_comment":"","sum_foreign":""}},"ft_src":"7997.92\nсуддя апеляційного суду івано-франківської області\nІвано-Франківська область\nЗагальний апеляційний суд\nЛюдмила\nВасилівна\nЯсеновенко\nЯсеновенко Людмила Василівна\nЯсеновенко Людмила Василівна\nЛюдмила Василівна Ясеновенко\nЛюдмила Ясеновенко\nЯсеновенко Людмила Василівна\nSubaru Impreza\n1498 куб. см., 107 к.с., 76.8 кВт\n2009\n61.1\n103979\n304591\n2013\n1498 куб. см., 107 к.с., 76.8 кВт\nSubaru Impreza\n2009\n2013\nЯсеновенко Людмила Василівна\nЛюдмила Василівна Ясеновенко\nЛюдмила Ясеновенко\nЯсеновенко Людмила Василівна\nЛюдмила\nЯсеновенко Людмила Василівна\nВасилівна\nЗагальний апеляційний суд\nІвано-Франківська область\nсуддя апеляційного суду івано-франківської області\nЯсеновенко\n7997.92\n227496.16\n252360.24\n24864.16\n61.1\n304591\n103979\n7997.92\n227496.16\n24864.16\n252360.24\nЛюдмила\nВасилівна\nЯсеновенко\nЯсеновенко Людмила Василівна\nЛюдмила Василівна Ясеновенко\nЛюдмила Ясеновенко\nЯсеновенко Людмила Василівна\nІвано-Франківська область\nЗагальний апеляційний суд\nсуддя апеляційного суду івано-франківської області\nЯсеновенко Людмила Василівна\n2009\n1498 куб. см., 107 к.с., 76.8 кВт\nSubaru Impreza\n24864.16\n252360.24\n227496.16\n61.1\n304591\n103979\n2013","general":{"inn":"","name":"Людмила","patronymic":"Василівна","inn_hidden":true,"family_raw":"","last_name":"Ясеновенко","post":{"post_unclear":false,"region_unclear":false,"post":"суддя апеляційного суду івано-франківської області","office":"Загальний апеляційний суд","region":"Івано-Франківська область","post_hidden":false,"office_hidden":false,"office_unclear":false,"region_hidden":false},"last_name_unclear":false,"full_name":"Ясеновенко Людмила Василівна","addresses":[{"place_district":"","place_city_hidden":true,"place_city":"","place_city_type_hidden":false,"place_district_hidden":true,"place_city_type":"","place_address_hidden":true,"place_address":"","place_hidden":true,"place":""}],"full_name_suggest":{"output":"Ясеновенко Людмила Василівна","input":["Ясеновенко Людмила Василівна","Людмила Василівна Ясеновенко","Людмила Ясеновенко"]},"name_unclear":false},"source":"VULYK","estate":{"25":[{"space_unclear":false,"costs":"","costs_comment":"","costs_hidden":false,"address_hidden":false,"region_hidden":true,"space_comment":"","space_hidden":false,"space":"61.1","address":"","region":"","costs_rent_comment":"","space_comment_hidden":false,"space_units":"м²","costs_rent":""}]},"intro":{"declaration_year":"2013"}}