{"income":{"5":{"value":"243925","family_unclear":false,"family_hidden":false,"family_comment":"","family":"97820","comment":""},"6":{"family_comment":"","value":"243925","family_hidden":false,"comment":"","family":"97820"},"7":{"family_comment":"","value":"","source_name":"","family":"","comment":""},"8":{"family_comment":"","value":"","family":"","comment":""},"9":{"value":"","comment_unclear":false,"family_hidden":false,"family_comment":"","family":"","comment":""},"10":{"family_comment":"","value":"","family":"","comment":""},"11":{"family_comment":"","value":"","family":"","comment":""},"12":{"family_comment":"","value":"","family":"","comment":""},"13":{"family_comment":"","value":"","family":"","comment":""},"14":{"family_comment":"","value":"","family":"","comment":""},"15":{"family_comment":"","value":"","value_unclear":false,"family":"","comment":""},"16":{"family_comment":"","value":"","family":"","comment":""},"17":{"family_comment":"","value":"","family":"","comment":""},"18":{"family_comment":"","value":"","family":"","comment":""},"19":{"family_comment":"","value":"","family":"","comment":""},"20":{"value":"","comment_unclear":false,"comment_hidden":false,"family_hidden":false,"value_hidden":false,"family_comment":"","value_unclear":false,"family":"","comment":"","family_comment_hidden":false}},"vehicle":{"35":[{"brand_info":"1595 куб. см.","sum_rent_comment":"","brand":"Skoda Octavia A5","sum_comment":"кредит на 3 роки виплачено","year":"2011","brand_info_hidden":false,"sum":"","sum_rent":""}]},"id":"vulyk_41_43","banks":{"45":[{"sum_foreign_comment":"","sum_units":"UAH","sum_comment":"","sum_foreign_unclear":false,"sum_foreign_units":"UAH","sum_hidden":false,"sum_comment_hidden":false,"sum":"","sum_foreign":""},{"sum_foreign_comment":"","sum_units":"","sum_comment":"","sum_foreign_unclear":false,"sum_foreign_units":"","sum":"","sum_foreign":""}],"46":[{"sum_foreign_comment":"","sum_units":"UAH","sum_comment":"","sum_foreign_units":"UAH","sum_comment_hidden":false,"sum_unclear":false,"sum":"","sum_foreign":""},{"sum_foreign_comment":"","sum_units":"","sum_comment":"","sum_foreign_units":"","sum":"","sum_unclear":false,"sum_foreign":""}],"47":[{"sum_foreign_comment":"","sum_units":"UAH","sum_comment":"","sum_foreign_units":"UAH","sum":"","sum_foreign":""},{"sum_foreign_comment":"","sum_units":"","sum_comment":"","sum_foreign_units":"","sum":"","sum_foreign":""}],"48":[{"sum_foreign_comment":"","sum_units":"UAH","sum_comment":"","sum_foreign_units":"UAH","sum":"","sum_foreign":""}],"49":[{"sum_foreign_comment":"","sum_units":"UAH","sum_comment":"","sum_foreign_units":"UAH","sum":"","sum_foreign":""}],"50":[{"sum_foreign_comment":"","sum_units":"UAH","sum_comment":"","sum_foreign_units":"UAH","sum":"","sum_foreign":""}],"51":[{"sum_foreign_comment":"","sum_units":"UAH","sum_comment":"","sum_hidden":false,"sum_foreign_units":"UAH","sum_comment_hidden":true,"sum_unclear":false,"sum":"27741","sum_foreign":""},{"sum_foreign_comment":"","sum_units":"","sum_comment":"","sum_foreign_units":"","sum":"","sum_foreign":""}],"52":[{"sum_foreign_comment":"","sum_units":"UAH","sum_comment":"","sum_foreign_units":"UAH","sum_comment_hidden":false,"sum_unclear":false,"sum":"","sum_foreign":""}],"53":[{"sum_foreign_comment":"","sum_units":"UAH","sum_comment":"","sum_foreign_units":"UAH","sum_comment_hidden":false,"sum":"","sum_foreign":""},{"sum_foreign_comment":"","sum_units":"","sum_comment":"","sum_foreign_units":"","sum":"","sum_foreign":""},{"sum_foreign_comment":"","sum_units":"","sum_comment":"","sum_foreign_units":"","sum":"","sum_foreign":""}]},"declaration":{"date":"2015-03-30T00:00:00","additional_info_text":"","additional_info":"","url":"http://static.declarations.com.ua/declarations/chosen_ones/mega_batch/shevchenko_viktor_serhiiovych.pdf"},"liabilities":{"54":{"sum_foreign_comment":"","sum_comment_hidden":false,"sum":"","sum_comment":"","sum_foreign":""},"55":{"sum_foreign_comment":"","sum":"","sum_comment":"","sum_foreign":""},"56":{"sum_foreign_comment":"","sum":"","sum_hidden":false,"sum_comment":"","sum_foreign":""},"57":{"sum_foreign_comment":"","sum":"","sum_comment":"","sum_comment_hidden":false,"sum_unclear":false,"sum_foreign":""},"58":{"sum_foreign_comment":"","sum_comment_hidden":false,"sum":"","sum_comment":"","sum_foreign":""},"59":{"sum_foreign_comment":"","sum":"","sum_comment":"","sum_foreign":""},"60":{"sum_foreign_comment":"","sum_comment_hidden":false,"sum":"","sum_comment":"","sum_foreign":""},"61":{"sum_foreign_comment":"","sum":"","sum_comment":"","sum_foreign":""},"62":{"sum_foreign_comment":"","sum":"","sum_comment":"","sum_foreign":""},"63":{"sum_foreign_comment":"","sum":"","sum_comment":"","sum_comment_hidden":false,"sum_unclear":false,"sum_foreign":""},"64":{"sum_foreign_comment":"","sum_comment_hidden":false,"sum":"","sum_comment":"","sum_foreign":""}},"ft_src":"голова тростянецького районного суду сумської області\nСумська область\nЗагальний місцевий суд\nВіктор\nШевченко О. В\nПодружжя\nШевченко Т. В\nДитина\nШевченко Д. В\nДитина\nСергійович\nШевченко Віктор Сергійович\nВіктор Сергійович Шевченко\nВіктор Шевченко\nШевченко Віктор Сергійович\nШевченко\nШевченко Віктор Сергійович\nкредит на 3 роки виплачено\n1595 куб. см.\n2011\nSkoda Octavia A5\n27741\n2014\nSkoda Octavia A5\n1595 куб. см.\n2011\nкредит на 3 роки виплачено\n27741\n57.06\nприватизація на 4 чл.сім'ї\n65.8\nордер на 4 чл.сім'ї\n59.8\n598\n547\n192\n57.06\nприватизація на 4 чл.сім'ї\n65.8\nордер на 4 чл.сім'ї\n23.7\nПодружжя\nШевченко О. В\nДитина\nШевченко Т. В\nДитина\nШевченко Д. В\nШевченко Віктор Сергійович\nВіктор Сергійович Шевченко\nВіктор Шевченко\nШевченко Віктор Сергійович\nШевченко Віктор Сергійович\nВіктор\nСергійович\nЗагальний місцевий суд\nголова тростянецького районного суду сумської області\nСумська область\nШевченко\n243925\n97820\n243925\n97820\n2014\n547\n192\n59.8\n598\n23.7\nприватизація на 4 чл.сім'ї\n57.06\nордер на 4 чл.сім'ї\n65.8\nприватизація на 4 чл.сім'ї\n57.06\nордер на 4 чл.сім'ї\n65.8\nШевченко О. В\nПодружжя\nШевченко Т. В\nДитина\nШевченко Д. В\nДитина\nСергійович\nШевченко\nВіктор\nШевченко Віктор Сергійович\nВіктор Сергійович Шевченко\nВіктор Шевченко\nШевченко Віктор Сергійович\nСумська область\nголова тростянецького районного суду сумської області\nЗагальний місцевий суд\nШевченко Віктор Сергійович\n97820\n243925\n97820\n243925\nкредит на 3 роки виплачено\nSkoda Octavia A5\n1595 куб. см.\n2011\n243925\n97820\n97820\n243925\nприватизація на 4 чл.сім'ї\n57.06\nордер на 4 чл.сім'ї\n65.8\n598\n192\n23.7\n59.8\nприватизація на 4 чл.сім'ї\n57.06\n65.8\nордер на 4 чл.сім'ї\n547\n27741\n2014","general":{"inn":"","name":"Віктор","family":[{"inn":"","relations":"Подружжя","relations_hidden":false,"inn_hidden":true,"family_name":"Шевченко О. В","name_hidden":false,"name_unclear":false},{"inn":"","relations":"Дитина","relations_other":"","inn_hidden":true,"family_name":"Шевченко Т. В","name_hidden":false,"name_unclear":false},{"inn":"","relations":"Дитина","relations_other":"","inn_hidden":true,"family_name":"Шевченко Д. В","name_hidden":false,"name_unclear":false}],"patronymic":"Сергійович","inn_hidden":true,"family_raw":"","last_name":"Шевченко","post":{"post_unclear":false,"post":"голова тростянецького районного суду сумської області","post_hidden":false,"region":"Сумська область","region_hidden":false,"office":"Загальний місцевий суд","office_hidden":false},"last_name_unclear":false,"full_name":"Шевченко Віктор Сергійович","addresses":[{"place_district":"","place_city_hidden":true,"place_city":"","place_city_type_hidden":false,"place_district_hidden":true,"place_city_type":"","place_address_hidden":false,"place_address":"","place_hidden":true,"place":""}],"patronymic_hidden":false,"full_name_suggest":{"output":"Шевченко Віктор Сергійович","input":["Шевченко Віктор Сергійович","Віктор Сергійович Шевченко","Віктор Шевченко"]},"name_unclear":false},"source":"VULYK","estate":{"23":[{"region_unclear":false,"space_unclear":false,"costs":"","costs_comment":"","address_hidden":false,"region_hidden":true,"space_comment":"","space":"598","address":"","costs_comment_unclear":false,"region":"","space_units_unclear":false,"space_comment_hidden":false,"space_units":"м²","costs_rent":"","costs_rent_comment":""},{"costs_rent":"","space_unclear":false,"region":"","costs":"","costs_rent_comment":"","costs_comment":"","space_comment":"","space_units":"","space":"","address":""},{"costs_rent":"","region":"","costs":"","costs_rent_comment":"","costs_comment":"","space_comment":"","space_units":"","space":"","address":""}],"24":[{"region_unclear":false,"space_unclear":false,"costs":"","costs_comment":"","address_hidden":false,"region_hidden":true,"space_comment":"","space":"192","address":"","region":"","costs_rent_comment":"","space_units":"м²","costs_rent":""}],"25":[{"region_unclear":false,"space_hidden":false,"costs":"","costs_comment":"","address_hidden":false,"region_hidden":true,"space_comment":"приватизація на 4 чл.сім'ї","space_unclear":false,"space":"57.06","address":"","costs_comment_unclear":true,"region":"","costs_rent_comment":"","costs_unclear":true,"space_units":"м²","costs_rent":""},{"space_unclear":false,"costs":"","costs_comment":"","region_hidden":false,"space_comment":"ордер на 4 чл.сім'ї","space":"65.8","address":"","costs_comment_unclear":true,"region":"","costs_rent_comment":"","costs_unclear":true,"space_units":"м²","costs_rent":""}],"29":[{"space_unclear":false,"costs_property_comment":"","address_hidden":false,"region_hidden":true,"space_comment":"","space":"547","address":"","region":"","costs_property":"","costs_rent_comment":"","space_units":"м²","space_units_unclear":false,"costs_rent":""}],"31":[{"space_hidden":false,"address_hidden":false,"region_hidden":true,"space_comment":"приватизація на 4 чл.сім'ї","space":"57.06","address":"","region":"","costs_property":"","costs_rent_comment":"","space_comment_unclear":true,"space_units":"м²","costs_property_comment":"","costs_rent":""},{"costs_rent":"","region":"","costs_property":"","costs_rent_comment":"","space_comment_unclear":true,"space_comment":"ордер на 4 чл.сім'ї","costs_property_comment":"","space_units":"м²","space":"65.8","address":""}],"33":[{"costs_rent":"","region":"","costs_property":"","costs_rent_comment":"","address_hidden":false,"region_hidden":true,"space_comment":"","costs_property_comment":"","space_units":"м²","space":"59.8","address":""}],"34":[{"costs_rent":"","region":"","costs_property":"","costs_rent_comment":"","address_hidden":false,"region_hidden":true,"space_comment":"","costs_property_comment":"","space_units":"м²","space":"23.7","address":""}]},"intro":{"declaration_year":"2014"}}