{"id":"vulyk_96_29","ft_src":"мопед, 49 куб. см.\n1999\nHonda Tact\n2008\nпричіп\nПФ-01 Фермер\n1690 куб. см., 58.5 кВт\nChevrolet Niva\n2007\n2012\n1798 куб. см., 112 кВт\nSkoda Octavia A5\nКиївська область\nм. Богуслав\n36\nБогуславський р-н, с. Калинівка\nКиївська область\n72.8\nКиївська область\nм. Богуслав\n31\n1570\nБогуславський р-н, с. Калинівка\nКиївська область\nКанівський р-н, Копіюватська с/р\n52065\nЧеркаська область\nКиївська область\nм. Богуслав\n48.72\nм. Богуслав\n24.36\nКиївська область\n2015\n254009\n923\nБогуславський гуманітарний коледж ім. І. С. Нечуя-Левицького\n23549\n266190\n11258\n23549\n1690 куб. см., 58.5 кВт\nChevrolet Niva\n2007\nSkoda Octavia A5\n1798 куб. см., 112 кВт\n2012\nмопед, 49 куб. см.\n1999\nHonda Tact\nпричіп\n2008\nПФ-01 Фермер\n2015\nТітов Микола Борисович\nМикола Борисович Тітов\nМикола Тітов\nТітов Микола Борисович\nТітов Микола Борисович\nМикола\nТітов\nКиївська область\nголова богуславського районного суду київської області\nЗагальний місцевий суд\nБорисович\n09700\nКиївська область\nБогуслав\nБогуславський\nПодружжя\nТітова Наталія Миколаївна\nДитина\nТітов Андрій Миколайович\n923\nБогуславський гуманітарний коледж ім. І. С. Нечуя-Левицького\n254009\n23549\n266190\n23549\n11258\n24.36\nм. Богуслав\nКиївська область\n31\nм. Богуслав\nКиївська область\n1570\nКиївська область\nБогуславський р-н, с. Калинівка\nЧеркаська область\n52065\nКанівський р-н, Копіюватська с/р\nм. Богуслав\n36\nКиївська область\n72.8\nБогуславський р-н, с. Калинівка\nКиївська область\nм. Богуслав\nКиївська область\n48.72\nТітова Наталія Миколаївна\nПодружжя\nДитина\nТітов Андрій Миколайович\nМикола\nБорисович\nТітов\nТітов Микола Борисович\nМикола Борисович Тітов\nМикола Тітов\nТітов Микола Борисович\nКиївська область\nБогуслав\n09700\nБогуславський\nголова богуславського районного суду київської області\nКиївська область\nЗагальний місцевий суд\nТітов Микола Борисович","estate":{"23":[{"address":"Богуславський р-н, с. Калинівка","space_units":"м²","costs_rent_unclear":false,"space_hidden":false,"space_unclear":false,"region_hidden":false,"space_units_unclear":false,"costs_comment":"","space_comment_unclear":false,"space":"1570","address_unclear":false,"space_comment":"","address_hidden":true,"costs_rent_comment":"","costs":"","region_unclear":false,"region":"Київська область","costs_rent":""},{"costs":"","address":"Канівський р-н, Копіюватська с/р","space_units":"м²","costs_rent_comment":"","space":"52065","space_comment":"","region_hidden":false,"costs_comment":"","region":"Черкаська область","address_hidden":false,"costs_rent":""}],"24":[{"address":"Богуславський р-н, с. Калинівка","space_units":"м²","space_hidden":false,"space_unclear":false,"region_hidden":false,"costs_comment":"","space_comment":"","address_hidden":false,"space":"72.8","space_comment_unclear":false,"costs_rent_comment":"","costs":"","region":"Київська область","costs_rent":""}],"25":[{"costs":"","costs_unclear":false,"address":"м. Богуслав","space_units":"м²","space_hidden":false,"space_comment":"","region_hidden":false,"costs_comment":"","space_comment_unclear":false,"space_comment_hidden":false,"space_unclear":false,"address_unclear":false,"address_hidden":true,"costs_rent_comment":"","space":"24.36","costs_rent":"","region":"Київська область","costs_rent_comment_unclear":false}],"29":[{"costs_property_comment":"","address":"м. Богуслав","space_units":"м²","space_unclear":false,"region_hidden":false,"costs_property":"","space_comment":"","address_hidden":true,"address_unclear":false,"costs_rent_comment":"","space":"36","region_unclear":false,"region":"Київська область","costs_rent":""}],"31":[{"costs_property_comment":"","address":"м. Богуслав","space_units":"м²","space_hidden":false,"space_unclear":false,"region_hidden":false,"costs_property":"","space_comment":"","address_hidden":true,"address_unclear":false,"costs_rent_comment":"","space":"48.72","region":"Київська область","costs_rent":""}],"33":[{"costs_property_comment":"","address":"м. Богуслав","space_units":"м²","costs_rent_comment":"","space":"31","region":"Київська область","region_hidden":false,"costs_property":"","space_comment":"","address_hidden":true,"costs_rent":""}]},"vehicle":{"35":[{"year_hidden":false,"brand_info":"1690 куб. см., 58.5 кВт","sum_rent_comment":"","brand_unclear":false,"brand_hidden":false,"year":"2007","brand":"Chevrolet Niva","brand_info_hidden":false,"sum_rent":"","sum_comment":"","year_unclear":false,"sum_unclear":false,"sum":""}],"39":[{"sum_comment":"","brand_info":"мопед, 49 куб. см.","sum":"","sum_rent_comment":"","year":"1999","brand":"Honda Tact","sum_rent":""},{"sum_comment":"","brand_info":"причіп","sum":"","sum_rent_comment":"","year":"2008","brand":"ПФ-01 Фермер","sum_rent":"","brand_hidden":false}],"40":[{"sum_comment":"","brand_info_hidden":false,"brand_info":"1798 куб. см., 112 кВт","sum":"","sum_rent_comment":"","year":"2012","brand":"Skoda Octavia A5","sum_rent":"","year_unclear":false}]},"source":"VULYK","income":{"5":{"family_comment":"","value":"266190","family_unclear":false,"family":"23549","comment":""},"6":{"family_comment":"","family":"","comment":"","value_unclear":false,"family_unclear":false,"value":"254009"},"7":{"source_name_hidden":false,"family_comment":"","family":"","comment":"","value_unclear":false,"family_unclear":false,"value":"923","source_name":"Богуславський гуманітарний коледж ім. І. С. Нечуя-Левицького"},"8":{"family_comment":"","value":"","family":"","comment":""},"9":{"family_comment":"","value":"","family":"","comment":""},"10":{"family_comment":"","value":"","family":"","comment":"","value_unclear":false},"11":{"family_comment":"","value":"","family":"","comment":""},"12":{"family_comment":"","value":"","family":"","comment":""},"13":{"family_comment":"","value":"","family":"","comment":""},"14":{"family_comment":"","value":"","family":"","comment":""},"15":{"family_comment":"","value":"","family":"","comment":""},"16":{"family_comment":"","value":"","family":"","comment":""},"17":{"family_comment":"","value":"","family":"","comment":""},"18":{"family_comment":"","value":"","family":"","comment":""},"19":{"family_comment":"","value":"11258","family":"","comment":""},"20":{"family_comment":"","comment":"","family":"23549","value_unclear":false,"comment_hidden":false,"comment_unclear":false,"value":""}},"general":{"family":[{"inn":"","inn_unclear":false,"family_name":"Тітова Наталія Миколаївна","relations_other":"","relations_hidden":false,"name_unclear":false,"inn_hidden":true,"name_hidden":true,"relations":"Подружжя"},{"inn":"","family_name":"Тітов Андрій Миколайович","relations_other":"","name_unclear":false,"inn_hidden":false,"name_hidden":false,"relations":"Дитина"}],"family_raw":"","name":"Микола","full_name_suggest":{"input":["Тітов Микола Борисович","Микола Борисович Тітов","Микола Тітов"],"output":"Тітов Микола Борисович"},"patronymic":"Борисович","inn_hidden":true,"patronymic_hidden":false,"inn":"","addresses":[{"place_city_type_hidden":false,"place_city_type":"Місто","place_city_hidden":false,"place_hidden":false,"place_district":"Богуславський","place_district_hidden":false,"place":"Київська область","place_address":"09700","place_address_hidden":true,"place_city":"Богуслав"}],"last_name":"Тітов","full_name":"Тітов Микола Борисович","post":{"office_unclear":false,"post":"голова богуславського районного суду київської області","region":"Київська область","office":"Загальний місцевий суд"}},"liabilities":{"54":{"sum_comment":"","sum_hidden":false,"sum":"","sum_foreign_comment":"","sum_foreign":"","sum_comment_hidden":false},"55":{"sum_comment":"","sum_foreign_comment":"","sum_foreign":"","sum":""},"56":{"sum_comment":"","sum_foreign_comment":"","sum_foreign":"","sum_unclear":false,"sum":""},"57":{"sum_comment":"","sum_foreign_comment":"","sum_foreign":"","sum":"","sum_comment_hidden":false},"58":{"sum_comment":"","sum":"","sum_foreign_comment":"","sum_foreign":"","sum_unclear":false,"sum_comment_hidden":false},"59":{"sum_comment":"","sum_foreign_comment":"","sum_foreign":"","sum":""},"60":{"sum_comment":"","sum_foreign_comment":"","sum_foreign":"","sum":"","sum_comment_hidden":false},"61":{"sum_comment":"","sum_foreign_comment":"","sum_foreign":"","sum":""},"62":{"sum_comment":"","sum_foreign_comment":"","sum_foreign":"","sum":""},"63":{"sum_comment":"","sum_foreign_comment":"","sum_foreign":"","sum":"","sum_comment_hidden":false},"64":{"sum_comment":"","sum_foreign_comment":"","sum_foreign":"","sum":"","sum_comment_hidden":false}},"declaration":{"notfull_lostpages":"","additional_info_text":"","additional_info":"","date":"2016-03-29T00:00:00","notfull":"","url":"http://static.declarations.com.ua/declarations/chosen_ones/judges_batch/243_titov_mykola_borysovych_2015.pdf"},"intro":{"isnotdeclaration":"","declaration_year":"2015"}}