{"income":{"5":{"value":"248558.81","family_unclear":false,"family_hidden":false,"family_comment":"","family":"73256.15","comment":""},"6":{"family_comment":"","value":"235160.81","family_hidden":false,"comment":"","family":"70618.92"},"7":{"family_comment":"","value":"","source_name":"","family":"","comment":""},"8":{"family_comment":"","value":"","family":"","comment":""},"9":{"value":"","comment_unclear":false,"family_hidden":false,"family_comment":"","family":"","comment":""},"10":{"family_comment":"","value":"13398","family":"2637.23","comment":""},"11":{"family_comment":"","value":"","family":"","comment":""},"12":{"family_comment":"","value":"","family":"","comment":""},"13":{"family_comment":"","value":"","family":"","comment":""},"14":{"family_comment":"","value":"","family":"","comment":""},"15":{"family_comment":"","value":"","value_unclear":false,"family":"","comment":""},"16":{"family_comment":"","value":"","family":"","comment":""},"17":{"family_comment":"","value":"","family":"","comment":""},"18":{"family_comment":"","value":"","family":"","comment":""},"19":{"family_comment":"","value":"","family":"","comment":""},"20":{"value":"","comment_unclear":false,"comment_hidden":false,"family_hidden":false,"value_hidden":false,"family_comment":"","value_unclear":false,"family":"","comment":"","family_comment_hidden":false}},"vehicle":{"40":[{"brand_info":"1591 куб. см., 130 к. с","sum_rent_comment":"","brand":"Hyundai Elantra","sum_comment":"","year":"2013","brand_info_hidden":false,"sum":"","sum_rent":""}]},"id":"vulyk_41_131","banks":{"45":[{"sum_foreign_comment":"","sum_units":"UAH","sum_comment":"","sum_foreign_unclear":false,"sum_foreign_units":"UAH","sum_hidden":false,"sum_comment_hidden":false,"sum":"","sum_foreign":""},{"sum_foreign_comment":"","sum_units":"","sum_comment":"","sum_foreign_unclear":false,"sum_foreign_units":"","sum":"","sum_foreign":""}],"46":[{"sum_foreign_comment":"","sum_units":"UAH","sum_comment":"","sum_foreign_units":"UAH","sum_comment_hidden":false,"sum_unclear":false,"sum":"","sum_foreign":""},{"sum_foreign_comment":"","sum_units":"","sum_comment":"","sum_foreign_units":"","sum":"","sum_unclear":false,"sum_foreign":""}],"47":[{"sum_foreign_comment":"","sum_units":"UAH","sum_comment":"","sum_foreign_units":"UAH","sum":"","sum_foreign":""},{"sum_foreign_comment":"","sum_units":"","sum_comment":"","sum_foreign_units":"","sum":"","sum_foreign":""}],"48":[{"sum_foreign_comment":"","sum_units":"UAH","sum_comment":"","sum_foreign_units":"UAH","sum":"","sum_foreign":""}],"49":[{"sum_foreign_comment":"","sum_units":"UAH","sum_comment":"","sum_foreign_units":"UAH","sum":"","sum_foreign":""}],"50":[{"sum_foreign_comment":"","sum_units":"UAH","sum_comment":"","sum_foreign_units":"UAH","sum":"","sum_foreign":""}],"51":[{"sum_foreign_comment":"","sum_units":"UAH","sum_comment":"","sum_hidden":false,"sum_foreign_units":"UAH","sum_comment_hidden":false,"sum_unclear":false,"sum":"","sum_foreign":""},{"sum_foreign_comment":"","sum_units":"","sum_comment":"","sum_foreign_units":"","sum":"","sum_foreign":""}],"52":[{"sum_foreign_comment":"","sum_units":"UAH","sum_comment":"","sum_foreign_units":"UAH","sum_comment_hidden":false,"sum_unclear":false,"sum":"","sum_foreign":""}],"53":[{"sum_foreign_comment":"","sum_units":"UAH","sum_comment":"","sum_foreign_units":"UAH","sum_comment_hidden":false,"sum":"","sum_foreign":""},{"sum_foreign_comment":"","sum_units":"","sum_comment":"","sum_foreign_units":"","sum":"","sum_foreign":""},{"sum_foreign_comment":"","sum_units":"","sum_comment":"","sum_foreign_units":"","sum":"","sum_foreign":""}]},"declaration":{"date":"2015-03-25T00:00:00","additional_info_text":"","additional_info":"","url":"http://static.declarations.com.ua/declarations/chosen_ones/mega_batch/serbin_valentyn_vitaliiovych.pdf"},"liabilities":{"54":{"sum_foreign_comment":"","sum_comment_hidden":false,"sum":"","sum_comment":"","sum_foreign":""},"55":{"sum_foreign_comment":"","sum":"","sum_comment":"","sum_foreign":""},"56":{"sum_foreign_comment":"","sum":"2700","sum_hidden":false,"sum_comment":"","sum_foreign":""},"57":{"sum_foreign_comment":"","sum":"","sum_comment":"","sum_comment_hidden":false,"sum_unclear":false,"sum_foreign":""},"58":{"sum_foreign_comment":"","sum_comment_hidden":false,"sum":"","sum_comment":"","sum_foreign":""},"59":{"sum_foreign_comment":"","sum":"","sum_comment":"","sum_foreign":""},"60":{"sum_foreign_comment":"","sum_comment_hidden":false,"sum":"","sum_comment":"","sum_foreign":""},"61":{"sum_foreign_comment":"","sum":"","sum_comment":"","sum_foreign":""},"62":{"sum_foreign_comment":"","sum":"6300","sum_comment":"","sum_foreign":""},"63":{"sum_foreign_comment":"","sum":"","sum_comment":"","sum_comment_hidden":false,"sum_unclear":false,"sum_foreign":""},"64":{"sum_foreign_comment":"","sum_comment_hidden":false,"sum":"","sum_comment":"","sum_foreign":""}},"ft_src":"6300\n2700\nсуддя апеляційного суду дніпропетровської області\nДніпропетровська область\nЗагальний апеляційний суд\nВалентин\nСербіна (Солод) Віта Володимирівна\nПодружжя\nСербін Богдан Валентинович\nДитина\nСербін Володимир Валентинович\nДитина\nВіталійович\nСербін Валентин Віталійович\nВалентин Віталійович Сербін\nВалентин Сербін\nСербін Валентин Віталійович\nСербін\nСербін Валентин Віталійович\n1591 куб. см., 130 к. с\n2013\nHyundai Elantra\n2014\nHyundai Elantra\n1591 куб. см., 130 к. с\n2013\n88\n49.7\nПодружжя\nСербіна (Солод) Віта Володимирівна\nДитина\nСербін Богдан Валентинович\nДитина\nСербін Володимир Валентинович\nСербін Валентин Віталійович\nВалентин Віталійович Сербін\nВалентин Сербін\nСербін Валентин Віталійович\nСербін Валентин Віталійович\nВалентин\nВіталійович\nЗагальний апеляційний суд\nсуддя апеляційного суду дніпропетровської області\nДніпропетровська область\nСербін\n2700\n6300\n235160.81\n70618.92\n248558.81\n73256.15\n13398\n2637.23\n2014\n2700\n6300\n88\n49.7\nСербіна (Солод) Віта Володимирівна\nПодружжя\nСербін Богдан Валентинович\nДитина\nСербін Володимир Валентинович\nДитина\nВіталійович\nСербін\nВалентин\nСербін Валентин Віталійович\nВалентин Віталійович Сербін\nВалентин Сербін\nСербін Валентин Віталійович\nДніпропетровська область\nсуддя апеляційного суду дніпропетровської області\nЗагальний апеляційний суд\nСербін Валентин Віталійович\n70618.92\n235160.81\n2637.23\n13398\n73256.15\n248558.81\nHyundai Elantra\n1591 куб. см., 130 к. с\n2013\n2637.23\n13398\n248558.81\n73256.15\n70618.92\n235160.81\n88\n49.7\n2014","general":{"inn":"","name":"Валентин","family":[{"inn":"","relations":"Подружжя","relations_hidden":false,"inn_hidden":false,"family_name":"Сербіна (Солод) Віта Володимирівна","name_hidden":false,"name_unclear":false},{"inn":"","relations":"Дитина","relations_other":"","inn_hidden":false,"family_name":"Сербін Богдан Валентинович","name_hidden":true,"name_unclear":false},{"inn":"","relations":"Дитина","relations_other":"","inn_hidden":false,"family_name":"Сербін Володимир Валентинович","name_hidden":false,"name_unclear":false}],"patronymic":"Віталійович","inn_hidden":true,"family_raw":"","last_name":"Сербін","post":{"post_unclear":false,"post":"суддя апеляційного суду дніпропетровської області","post_hidden":false,"region":"Дніпропетровська область","region_hidden":false,"office":"Загальний апеляційний суд","office_hidden":false},"last_name_unclear":false,"full_name":"Сербін Валентин Віталійович","addresses":[{"place_district":"","place_city_hidden":true,"place_city":"","place_city_type_hidden":false,"place_district_hidden":true,"place_city_type":"","place_address_hidden":false,"place_address":"","place_hidden":true,"place":""}],"patronymic_hidden":false,"full_name_suggest":{"output":"Сербін Валентин Віталійович","input":["Сербін Валентин Віталійович","Валентин Віталійович Сербін","Валентин Сербін"]},"name_unclear":false},"source":"VULYK","estate":{"23":[{"region_unclear":false,"space_unclear":false,"costs":"","costs_comment":"","address_hidden":false,"region_hidden":false,"space_comment":"","space":"","address":"","costs_comment_unclear":false,"region":"","space_units_unclear":false,"space_comment_hidden":false,"space_units":"м²","costs_rent":"","costs_rent_comment":""},{"costs_rent":"","space_unclear":false,"region":"","costs":"","costs_rent_comment":"","costs_comment":"","space_comment":"","space_units":"","space":"","address":""},{"costs_rent":"","region":"","costs":"","costs_rent_comment":"","costs_comment":"","space_comment":"","space_units":"","space":"","address":""}],"25":[{"region_unclear":false,"space_hidden":false,"costs":"","costs_comment":"","address_hidden":false,"region_hidden":true,"space_comment":"","space_unclear":false,"space":"49.7","address":"","costs_comment_unclear":false,"region":"","costs_rent_comment":"","costs_unclear":false,"space_units":"м²","costs_rent":""}],"31":[{"space_hidden":false,"address_hidden":false,"region_hidden":true,"space_comment":"","space":"88","address":"","region":"","costs_property":"","costs_rent_comment":"","space_comment_unclear":false,"space_units":"м²","costs_property_comment":"","costs_rent":""}]},"intro":{"declaration_year":"2014"}}