{"income":{"5":{"value":"258550.01","family_unclear":false,"family_hidden":false,"family_comment":"","family":"","comment":""},"6":{"value":"241910","family_comment":"","value_unclear":false,"family_hidden":false,"family_unclear":false,"family":"","comment":""},"7":{"value":"4023.04","family_hidden":false,"value_hidden":false,"family_comment":"","source_name":"","family":"","comment":"","source_name_hidden":false},"8":{"family_comment":"","value":"","family":"","comment":""},"9":{"family_comment":"","value":"","family":"","comment":""},"10":{"family_comment":"","value":"","value_unclear":false,"family":"","comment":""},"11":{"family_comment":"","value":"","family":"","comment":""},"12":{"family_comment":"","value":"","family":"","comment":""},"13":{"family_comment":"","value":"","family":"","comment":""},"14":{"family_comment":"","value":"","family":"","comment":""},"15":{"family_comment":"","value":"","family":"","comment":""},"16":{"family_comment":"","value":"","family":"","comment":""},"17":{"family_comment":"","value":"","family":"","comment":""},"18":{"family_comment":"","value":"","family":"","comment":""},"19":{"family_comment":"","value":"","family":"","comment":""},"20":{"value":"","family_comment":"","value_unclear":false,"family_unclear":false,"comment_unclear":false,"comment":"","family":""}},"id":"vulyk_74_168","declaration":{"additional_info_text":"","notfull_lostpages":"","date":"2014-03-25T00:00:00","notfull":"","additional_info":"","url":"http://static.declarations.com.ua/declarations/chosen_ones/judges_batch/1525_minenkova_nadiia_oleksandrivna.pdf"},"liabilities":{"54":{"sum_foreign_comment":"","sum":"","sum_comment":"","sum_comment_unclear":false,"sum_comment_hidden":false,"sum_foreign":""},"55":{"sum_foreign_comment":"","sum":"","sum_comment":"","sum_hidden":false,"sum_unclear":false,"sum_foreign":""},"56":{"sum_foreign_comment":"","sum":"","sum_comment":"","sum_hidden":false,"sum_unclear":false,"sum_foreign":""},"57":{"sum_foreign_comment":"","sum":"","sum_comment":"","sum_comment_unclear":false,"sum_comment_hidden":false,"sum_foreign":""},"58":{"sum_foreign_comment":"","sum_comment_hidden":false,"sum":"","sum_comment":"","sum_foreign":""},"59":{"sum_foreign_comment":"","sum":"","sum_comment":"","sum_foreign":""},"60":{"sum_foreign_comment":"","sum":"","sum_hidden":false,"sum_comment":"","sum_foreign":""},"61":{"sum_foreign_comment":"","sum":"","sum_comment":"","sum_foreign":""},"62":{"sum_foreign_comment":"","sum":"","sum_comment":"","sum_foreign":""},"63":{"sum_foreign_comment":"","sum":"","sum_comment":"","sum_comment_unclear":false,"sum_unclear":false,"sum_foreign":""},"64":{"sum_foreign_comment":"","sum":"","sum_comment":"","sum_comment_unclear":false,"sum_unclear":false,"sum_foreign":""}},"ft_src":"Олександрівна\nМіненкова Надія Олександрівна\nсуддя апеляційного суду харківської області\nХарківська область\nЗагальний апеляційний суд\nНадія\nМіненкова Надія Олександрівна\nНадія Олександрівна Міненкова\nНадія Міненкова\nМіненкова Надія Олександрівна\nМіненкова\n258550.01\n4023.04\n241910\nприватизація\n72\n2013\n241910\n4023.04\n258550.01\n4023.04\n241910\n258550.01\nЗагальний апеляційний суд\nХарківська область\nсуддя апеляційного суду харківської області\nОлександрівна\nМіненкова Надія Олександрівна\nНадія Олександрівна Міненкова\nНадія Міненкова\nМіненкова Надія Олександрівна\nНадія\nМіненкова Надія Олександрівна\nМіненкова\n72\nприватизація\n2013\nОлександрівна\nМіненкова\nХарківська область\nЗагальний апеляційний суд\nсуддя апеляційного суду харківської області\nМіненкова Надія Олександрівна\nМіненкова Надія Олександрівна\nНадія Олександрівна Міненкова\nНадія Міненкова\nМіненкова Надія Олександрівна\nНадія\nприватизація\n72\n2013","general":{"inn":"","inn_hidden":true,"last_name":"Міненкова","post":{"region_unclear":false,"region":"Харківська область","post":"суддя апеляційного суду харківської області","office":"Загальний апеляційний суд","office_unclear":false,"post_hidden":false},"name":"Надія","full_name":"Міненкова Надія Олександрівна","family_raw":"","addresses":[{"place_district":"","place_city_hidden":true,"place_city":"","place_city_type_hidden":false,"place_district_hidden":true,"place_city_type":"","place_address_hidden":true,"place_address":"","place_hidden":true,"place":""}],"full_name_suggest":{"output":"Міненкова Надія Олександрівна","input":["Міненкова Надія Олександрівна","Надія Олександрівна Міненкова","Надія Міненкова"]},"patronymic":"Олександрівна"},"source":"VULYK","estate":{"24":[{"region_unclear":false,"space_hidden":false,"costs":"","costs_comment":"","address_hidden":true,"region_hidden":true,"space_comment":"приватизація","space":"72","address":"","region":"","space_units_unclear":false,"space_units":"м²","costs_rent":"","costs_rent_comment":""}]},"intro":{"declaration_year":"2013","isnotdeclaration":"","declaration_year_unclear":false}}