{"income":{"5":{"value":"274683","family_comment":"","family_hidden":false,"value_hidden":false,"family_unclear":false,"family":"192467","comment":""},"6":{"value":"221306","value_unclear":false,"comment_hidden":false,"family_hidden":false,"value_hidden":false,"family_comment":"","family_comment_hidden":false,"comment":"","family":"114709"},"7":{"source_name_unclear":false,"value":"","family_comment":"","source_name":"","family":"","comment":"","source_name_hidden":false},"8":{"family_comment":"","value":"","comment_hidden":false,"family":"","comment":""},"9":{"value":"14831","family_hidden":false,"value_hidden":false,"family_comment":"","family":"","comment":""},"10":{"value":"","comment_hidden":false,"family_hidden":false,"value_hidden":false,"family_comment":"","family_comment_hidden":false,"comment":"","family":"100"},"11":{"family_comment":"","value":"","family_hidden":false,"comment":"","family":""},"12":{"family_comment":"","value":"","family_hidden":false,"comment":"","family":""},"13":{"family_comment":"","value":"","family":"","comment":""},"14":{"family_comment":"","value":"","family":"","comment":""},"15":{"value":"","comment_hidden":false,"family_comment":"","family":"","comment":"","family_comment_hidden":false},"16":{"family_comment":"","family_unclear":false,"value":"","family":"","comment":""},"17":{"family_comment":"","value":"","family":"","comment":""},"18":{"family_comment":"","value":"","family":"","comment":""},"19":{"family_comment":"","value":"","family":"","comment":""},"20":{"value":"38546","family_comment":"","comment_unclear":false,"family_hidden":false,"family_unclear":false,"family":"77658","comment":""}},"vehicle":{"40":[{"year_hidden":false,"brand_info":"1.6 л","sum_rent_comment":"","brand":"Ford Sierra","sum_comment":"","year":"1986","brand_hidden":false,"sum":"","sum_rent":""},{"brand_info":"4.2 л","sum_rent_comment":"","brand":"Audi Q7","sum_comment":"","year":"2008","sum":"","sum_rent":""}]},"id":"vulyk_77_17","declaration":{"additional_info_text":"","notfull_lostpages":"8","date":"2015-03-25T00:00:00","notfull":"1","additional_info":"","url":"http://static.declarations.com.ua/declarations/chosen_ones/judges_batch/1962_matviichuk_vasyl_vasylovych.pdf"},"liabilities":{"54":{"sum_foreign_comment":"","sum":"","sum_comment":"","sum_comment_unclear":false,"sum_foreign":""},"55":{"sum_foreign_comment":"","sum":"","sum_comment":"","sum_foreign":""},"56":{"sum_foreign_comment":"","sum":"","sum_comment":"","sum_unclear":false,"sum_foreign":""},"57":{"sum_foreign_comment":"","sum":"","sum_comment":"","sum_foreign":""},"58":{"sum_foreign_comment":"","sum":"","sum_comment":"","sum_foreign":""},"59":{"sum_foreign_comment":"","sum":"","sum_comment":"","sum_foreign":""},"60":{"sum_foreign_comment":"","sum":"9000","sum_comment":"","sum_foreign":""},"61":{"sum_foreign_comment":"","sum":"","sum_comment":"","sum_foreign":""},"62":{"sum_foreign_comment":"","sum":"","sum_hidden":false,"sum_comment":"","sum_foreign":""},"63":{"sum_foreign_comment":"","sum":"","sum_comment":"","sum_foreign":""},"64":{"sum_foreign_comment":"","sum":"","sum_comment":"","sum_foreign":""}},"ft_src":"9000\n1\n8\nсуддя господарського суду вінницької області\nВінницька область\nГосподарський місцевий суд\nВасиль\nМатвійчук Т. В\nПодружжя\nМатвійчук В. В\nДитина\nМатвійчук В. В\nДитина\nВасильович\nМатвійчук Василь Васильович\nВасиль Васильович Матвійчук\nВасиль Матвійчук\nМатвійчук Василь Васильович\nМатвійчук Василь Васильович\nМатвійчук\n1986\nFord Sierra\n1.6 л\n4.2 л\n2008\nAudi Q7\n1900\n794\n82.4\n8\n1\n2014\n114709\n221306\n14831\n100\n192467\n274683\n77658\n38546\n1.6 л\n1986\nFord Sierra\n4.2 л\n2008\nAudi Q7\n8\n1\n2014\nМатвійчук Василь Васильович\nВасиль Васильович Матвійчук\nВасиль Матвійчук\nМатвійчук Василь Васильович\nВасиль\nПодружжя\nМатвійчук Т. В\nДитина\nМатвійчук В. В\nДитина\nМатвійчук В. В\nМатвійчук Василь Васильович\nМатвійчук\nГосподарський місцевий суд\nсуддя господарського суду вінницької області\nВінницька область\nВасильович\n9000\n221306\n114709\n38546\n77658\n274683\n192467\n14831\n100\n1900\n794\n82.4\n9000\nПодружжя\nМатвійчук Т. В\nДитина\nМатвійчук В. В\nДитина\nМатвійчук В. В\nВасильович\nМатвійчук\nВасиль\nМатвійчук Василь Васильович\nВасиль Васильович Матвійчук\nВасиль Матвійчук\nМатвійчук Василь Васильович\nсуддя господарського суду вінницької області\nВінницька область\nГосподарський місцевий суд\nМатвійчук Василь Васильович\n1986\nFord Sierra\n1.6 л\nAudi Q7\n4.2 л\n2008\n14831\n100\n38546\n77658\n274683\n192467\n221306\n114709\n82.4\n1900\n794\n2014","general":{"inn":"","name":"Василь","inn_unclear":false,"family":[{"inn":"","relations":"Подружжя","inn_unclear":false,"relations_hidden":false,"inn_hidden":true,"relations_other":"","name_hidden":true,"family_name":"Матвійчук Т. В","name_unclear":false},{"inn":"","relations":"Дитина","relations_other":"","inn_hidden":false,"family_name":"Матвійчук В. В","name_hidden":false,"name_unclear":false},{"inn":"","relations":"Дитина","relations_other":"","inn_hidden":false,"family_name":"Матвійчук В. В","name_hidden":false,"name_unclear":false}],"inn_hidden":true,"family_raw":"","last_name":"Матвійчук","post":{"office":"Господарський місцевий суд","region":"Вінницька область","post":"суддя господарського суду вінницької області"},"full_name_suggest":{"output":"Матвійчук Василь Васильович","input":["Матвійчук Василь Васильович","Василь Васильович Матвійчук","Василь Матвійчук"]},"full_name":"Матвійчук Василь Васильович","addresses":[{"place_city_type_hidden":false,"place_district_hidden":false,"place_city_type":"","place_city_hidden":false,"place_address_unclear":false,"place_address":"","place":"","place_district":"","place_unclear":false,"place_city":"","place_city_unclear":false,"place_hidden":true,"place_address_hidden":false,"place_district_unclear":false}],"patronymic":"Васильович","last_name_unclear":false},"source":"VULYK","estate":{"23":[{"space_hidden":true,"costs":"","costs_comment":"","costs_hidden":false,"address_hidden":true,"region_hidden":false,"space_comment":"","space":"1900","space_units_hidden":false,"region":"","address_unclear":false,"costs_rent_comment":"","costs_rent_hidden":false,"space_units":"м²","address":"","costs_rent":""},{"space_hidden":true,"costs":"","costs_comment":"","address_hidden":false,"region_hidden":false,"space_comment":"","space":"","address":"","region":"","costs_rent_comment":"","space_units":"","costs_rent":""}],"24":[{"space_hidden":false,"costs":"","costs_comment":"","costs_hidden":false,"address_hidden":true,"region_hidden":false,"space_comment":"","space":"","address":"","region":"","address_unclear":false,"costs_rent_comment":"","costs_rent_hidden":false,"costs_rent_comment_hidden":false,"space_units":"м²","costs_comment_hidden":false,"costs_rent":""}],"25":[{"space_unclear":false,"costs":"","costs_comment":"","costs_hidden":false,"address_hidden":true,"region_hidden":true,"space_comment":"","space_hidden":true,"space":"82.4","address":"","region":"","address_unclear":false,"costs_rent_comment":"","costs_rent_hidden":false,"space_units":"м²","costs_rent":""},{"costs_rent":"","space_hidden":true,"costs":"","costs_rent_comment":"","costs_comment":"","space_comment":"","space_units":"","space":"","address":""}],"29":[{"space_hidden":true,"address_unclear":false,"address_hidden":true,"region_hidden":true,"space_comment":"","space_units_hidden":false,"space_units_unclear":false,"address":"","costs_property_comment_hidden":false,"region":"","costs_property":"","space":"794","space_comment_unclear":false,"costs_rent_comment_hidden":false,"space_units":"м²","costs_property_comment":"","costs_rent":"","costs_rent_comment":""},{"costs_rent":"","space_hidden":true,"region":"","costs_property":"","costs_rent_comment":"","space_comment":"","costs_property_comment":"","space_units":"","space":"","address":""}]},"intro":{"declaration_year":"2014","isnotdeclaration":"","declaration_year_unclear":false}}