{"id":"vulyk_102_79","ft_src":"2011\n4461 куб. см., 4.5 L\nToyota Land Cruiser 200 VX\n3456 куб. см.\n2008\nLexus RX 350\n1/3\n79.9\n128.3\n1/3\n79.9\n52756\n59202\n2015\n4461 куб. см., 4.5 L\nToyota Land Cruiser 200 VX\n2011\n3456 куб. см.\n2008\nLexus RX 350\n2015\nЛьвов Богдан Юрійович\nБогдан Юрійович Львов\nБогдан Львов\nЛьвов Богдан Юрійович\nЛьвов Богдан Юрійович\nБогдан\nЮрійович\nсуддя вищого господарського суду україни, голова суду\nЗагальнодержавний регіон\nВищий господарський суд\nЛьвов\nПодружжя\nЛьвова І. О\n35700\n1753\n367\nНаціональна школа суддів України\n328002\n68974\nВартість почесної відзнаки Національної школи суддів України\n401\n328770\n87083\n18109\n79.9\n1/3\n128.3\n79.9\n1/3\n59202\n52756\n35700\n1753\n68974\n328002\n18109\nНаціональна школа суддів України\n367\n87083\n328770\nВартість почесної відзнаки Національної школи суддів України\n401\nЛьвова І. О\nПодружжя\nБогдан\nЮрійович\nЛьвов\nЛьвов Богдан Юрійович\nБогдан Юрійович Львов\nБогдан Львов\nЛьвов Богдан Юрійович\nсуддя вищого господарського суду україни, голова суду\nЗагальнодержавний регіон\nВищий господарський суд\nЛьвов Богдан Юрійович","estate":{"25":[{"address":"","space_units":"м²","costs_comment":"","space_comment":"1/3","region_hidden":true,"region":"","address_hidden":false,"space":"79.9","address_unclear":false,"costs_rent_comment":"","costs":"","costs_rent":""}],"31":[{"costs_property_comment":"","address":"","space_units":"м²","costs_rent_comment":"","space":"79.9","region":"","region_hidden":true,"costs_property":"","space_comment":"1/3","address_hidden":false,"costs_rent":""},{"costs_property_comment":"","address":"","space_units":"м²","costs_rent_comment":"","space":"128.3","region_hidden":false,"costs_property":"","space_comment":"","costs_rent":""}]},"vehicle":{"35":[{"sum_comment":"","brand_info":"4461 куб. см., 4.5 L","sum":"","sum_rent_comment":"","year":"2011","brand":"Toyota Land Cruiser 200 VX","sum_rent":"","brand_info_unclear":false,"year_unclear":false}],"40":[{"sum_comment":"","brand_info":"3456 куб. см.","sum":"","sum_rent_comment":"","year":"2008","brand":"Lexus RX 350","sum_rent":"","brand_info_unclear":false}]},"source":"VULYK","income":{"5":{"family_comment":"","value":"328770","family":"87083","comment":""},"6":{"family_comment":"","value":"328002","family":"68974","comment":""},"7":{"source_name_hidden":false,"family_comment":"","family":"","value_hidden":false,"comment":"","comment_hidden":false,"value":"367","source_name":"Національна школа суддів України"},"8":{"family_comment":"","value":"","family":"18109","comment":""},"9":{"family_comment":"","family":"","comment":"","comment_hidden":false,"value":"","family_comment_unclear":false},"10":{"family_comment":"","value":"","family":"","comment":""},"11":{"family_comment":"","value":"","family":"","comment":"","comment_hidden":false},"12":{"family_comment":"","value":"","family":"","comment":""},"13":{"family_comment":"","value":"","family":"","comment":""},"14":{"family_comment":"","value":"","family":"","comment":""},"15":{"family_comment":"","value":"","family":"","comment":""},"16":{"family_comment":"","value":"","family":"","comment":""},"17":{"family_comment":"","value":"","family":"","comment":""},"18":{"family_comment":"","value":"","family":"","comment":""},"19":{"family_comment":"","value":"","family":"","comment":""},"20":{"family_comment":"","value":"401","family":"","comment":"Вартість почесної відзнаки Національної школи суддів України","comment_hidden":false}},"banks":{"45":[{"sum_comment_unclear":false,"sum_units":"UAH","sum_foreign_units":"UAH","sum_hidden":false,"sum":"59202","sum_foreign_comment":"","sum_comment":"","sum_unclear":false,"sum_foreign":"","sum_comment_hidden":false}],"51":[{"sum_comment_unclear":false,"sum_units":"UAH","sum_foreign_units":"UAH","sum_hidden":false,"sum":"52756","sum_foreign_comment_hidden":false,"sum_foreign_comment":"","sum_comment":"","sum_unclear":false,"sum_foreign":"","sum_comment_hidden":true}]},"declaration":{"additional_info_text":"","additional_info":"","date":"2016-03-23T00:00:00","url":"http://static.declarations.com.ua/declarations/chosen_ones/judges_batch/1153_lvov_bohdan_iuriiovych.pdf"},"general":{"family":[{"inn":"","family_name":"Львова І. О","name_unclear":false,"inn_hidden":true,"name_hidden":true,"relations":"Подружжя"}],"family_raw":"","name":"Богдан","full_name_suggest":{"input":["Львов Богдан Юрійович","Богдан Юрійович Львов","Богдан Львов"],"output":"Львов Богдан Юрійович"},"patronymic":"Юрійович","inn_hidden":true,"patronymic_hidden":false,"inn":"","addresses":[{"place_city_type_hidden":false,"place_city_type":"","place_city_hidden":true,"place_hidden":true,"place_district":"","place_district_hidden":false,"place":"","place_address":"","place_address_hidden":true,"place_city":""}],"last_name":"Львов","full_name":"Львов Богдан Юрійович","post":{"office_unclear":false,"region_unclear":false,"post":"суддя вищого господарського суду україни, голова суду","region":"Загальнодержавний регіон","office":"Вищий господарський суд"}},"liabilities":{"54":{"sum_comment":"","sum_hidden":false,"sum":"35700","sum_foreign_comment":"","sum_foreign":"","sum_comment_hidden":true},"55":{"sum_comment":"","sum_foreign_comment":"","sum_foreign":"","sum":""},"56":{"sum_comment":"","sum_foreign_comment":"","sum_foreign":"","sum":""},"57":{"sum_comment":"","sum_foreign_comment":"","sum_foreign":"","sum":"","sum_comment_hidden":false},"58":{"sum_comment":"","sum_foreign_comment":"","sum_foreign":"","sum":"","sum_comment_hidden":false},"59":{"sum_comment":"","sum_foreign_comment":"","sum_foreign":"","sum":"","sum_comment_hidden":false},"60":{"sum_comment":"","sum_hidden":false,"sum":"1753","sum_foreign_comment":"","sum_foreign":"","sum_comment_hidden":true},"61":{"sum_comment":"","sum_foreign_comment":"","sum_foreign":"","sum":""},"62":{"sum_comment":"","sum_foreign_comment":"","sum_foreign":"","sum_unclear":false,"sum":""},"63":{"sum_comment":"","sum_hidden":false,"sum":"","sum_foreign_comment":"","sum_foreign":"","sum_comment_hidden":false},"64":{"sum_comment":"","sum_foreign_comment":"","sum_foreign":"","sum":"","sum_comment_hidden":false}},"intro":{"declaration_year":"2015"}}