{"income":{"5":{"family_comment":"","family_unclear":false,"value":"281537.96","family":"","comment":""},"6":{"family_comment":"","family_unclear":false,"value":"258444.51","family":"","comment":""},"7":{"value":"","comment_hidden":false,"family_comment":"","source_name":"","family":"","comment":""},"8":{"family_comment":"","value":"","family":"","comment":""},"9":{"family_comment":"","value":"","family":"","comment":""},"10":{"family_comment":"","value":"","family":"","comment":""},"11":{"family_comment":"","value":"","value_unclear":false,"family":"","comment":""},"12":{"family_comment":"","value":"","family":"","comment":""},"13":{"family_comment":"","value":"","family":"","comment":""},"14":{"family_comment":"","value":"","family":"","comment":""},"15":{"family_comment":"","value":"23093.45","value_unclear":false,"family":"","comment":""},"16":{"family_comment":"","family_unclear":false,"value":"","family":"","comment":""},"17":{"family_comment":"","value":"","family":"","comment":""},"18":{"family_comment":"","value":"","family_hidden":false,"comment":"","family":""},"19":{"family_comment":"","value":"","family":"","comment":""},"20":{"value":"","comment_unclear":false,"comment_hidden":false,"family_comment":"","family":"","comment":"","family_comment_hidden":false}},"vehicle":{"35":[{"brand_info":"2.2 -16 V","sum_rent_comment":"","year":"2007","brand_info_hidden":false,"brand_info_unclear":false,"year_unclear":false,"sum_rent":"","sum":"","brand":"Opel Vectra","sum_comment":"","brand_unclear":false,"brand_hidden":false}]},"id":"vulyk_68_104","declaration":{"additional_info_text":"","notfull_lostpages":"","date":"2015-03-31T00:00:00","notfull":"","additional_info":"","url":"http://static.declarations.com.ua/declarations/chosen_ones/mega_batch/lemish_oleksii_mykolaiovych.pdf"},"liabilities":{"54":{"sum_foreign_comment":"","sum":"","sum_comment":"","sum_comment_unclear":false,"sum_hidden":false,"sum_comment_hidden":false,"sum_unclear":false,"sum_foreign":""},"55":{"sum_foreign_comment":"","sum":"","sum_hidden":false,"sum_comment":"","sum_foreign":""},"56":{"sum_foreign_comment":"","sum_foreign_hidden":false,"sum_comment":"","sum":"","sum_unclear":false,"sum_foreign":""},"57":{"sum_foreign_comment":"","sum":"","sum_comment":"","sum_comment_unclear":false,"sum_hidden":false,"sum_comment_hidden":false,"sum_unclear":false,"sum_foreign":""},"58":{"sum_foreign_comment":"","sum":"","sum_comment":"","sum_hidden":false,"sum_comment_hidden":false,"sum_unclear":false,"sum_foreign":""},"59":{"sum_foreign_comment":"","sum":"","sum_comment":"","sum_foreign":""},"60":{"sum_foreign_comment":"","sum":"","sum_comment":"","sum_comment_unclear":false,"sum_hidden":false,"sum_comment_hidden":false,"sum_unclear":false,"sum_foreign":""},"61":{"sum_foreign_comment":"","sum":"","sum_hidden":false,"sum_comment":"","sum_foreign":""},"62":{"sum_foreign_comment":"","sum":"","sum_comment":"","sum_unclear":false,"sum_foreign":""},"63":{"sum_foreign_comment":"","sum":"","sum_comment":"","sum_hidden":false,"sum_comment_hidden":false,"sum_unclear":false,"sum_foreign":""},"64":{"sum_foreign_comment":"","sum":"","sum_comment":"","sum_hidden":false,"sum_comment_hidden":false,"sum_foreign":""}},"ft_src":"суддя ужгородського міськрайонного суду\nЗакарпатська область\nЗагальний місцевий суд\nОлексій\nЛеміш Дарія Іванівна 05. 10. 1957\nПодружжя\nМиколайович\nЛеміш Олексій Миколайович\nОлексій Миколайович Леміш\nОлексій Леміш\nЛеміш Олексій Миколайович\nЛеміш Олексій Миколайович\nЛеміш\n2.2 -16 V\nOpel Vectra\n2007\n.0595\n405\n.0483\n2014\n258444.51\n23093.45\n281537.96\n2.2 -16 V\nOpel Vectra\n2007\n.0595\n.0483\n405\nПодружжя\nЛеміш Дарія Іванівна 05. 10. 1957\nЛеміш Олексій Миколайович\nОлексій Миколайович Леміш\nОлексій Леміш\nЛеміш Олексій Миколайович\nЛеміш Олексій Миколайович\nОлексій\nМиколайович\nЗагальний місцевий суд\nЗакарпатська область\nсуддя ужгородського міськрайонного суду\nЛеміш\n258444.51\n23093.45\n281537.96\n2014\nПодружжя\nЛеміш Дарія Іванівна 05. 10. 1957\nМиколайович\nЛеміш\nОлексій\nЛеміш Олексій Миколайович\nОлексій Миколайович Леміш\nОлексій Леміш\nЛеміш Олексій Миколайович\nЗакарпатська область\nЗагальний місцевий суд\nсуддя ужгородського міськрайонного суду\nЛеміш Олексій Миколайович\n2007\nOpel Vectra\n2.2 -16 V\n23093.45\n281537.96\n258444.51\n405\n.0595\n.0483\n2014","general":{"inn":"","name":"Олексій","inn_unclear":false,"family":[{"inn":"","inn_hidden":true,"relations_unclear":false,"relations_hidden":false,"relations_other":"","relations":"Подружжя","name_hidden":false,"inn_unclear":false,"family_name":"Леміш Дарія Іванівна 05. 10. 1957","name_unclear":false}],"inn_hidden":true,"family_raw":"","last_name":"Леміш","post":{"post_unclear":false,"region_unclear":false,"post":"суддя ужгородського міськрайонного суду","office":"Загальний місцевий суд","region":"Закарпатська область","post_hidden":false,"office_hidden":false,"office_unclear":false,"region_hidden":false},"full_name_suggest":{"output":"Леміш Олексій Миколайович","input":["Леміш Олексій Миколайович","Олексій Миколайович Леміш","Олексій Леміш"]},"full_name":"Леміш Олексій Миколайович","addresses":[{"place_city_type_hidden":false,"place_district_hidden":true,"place_city_type":"","place_city_hidden":false,"place_address_unclear":false,"place_address":"","place_hidden":true,"place":"","place_district":"","place_unclear":false,"place_city":"","place_address_hidden":false}],"patronymic":"Миколайович","last_name_unclear":false,"name_unclear":false},"source":"VULYK","estate":{"23":[{"costs":"","costs_comment":"","address_hidden":false,"region_hidden":true,"space_comment":"","space":".0595","address":"","region":"","costs_rent_comment":"","space_comment_hidden":false,"space_units":"га","costs_rent":""}],"29":[{"space_unclear":false,"address_hidden":false,"region_hidden":true,"space_comment":"","space_units_hidden":false,"space_hidden":false,"space":".0483","address":"","region":"","costs_property":"","space_units_unclear":false,"space_units":"га","costs_property_comment":"","costs_rent":"","costs_rent_comment":""}],"30":[{"space_unclear":false,"address_hidden":false,"region_hidden":true,"space_comment":"","space_hidden":false,"space":"405","address":"","region":"","costs_property":"","costs_rent_comment":"","space_units":"м²","costs_property_comment":"","costs_rent":""}]},"intro":{"declaration_year":"2014","isnotdeclaration":""}}