{"income":{"5":{"value":"217925","value_unclear":true,"value_hidden":false,"family_comment":"","family":"128607","comment":""},"6":{"value":"217925","family_comment":"","value_unclear":false,"family_unclear":false,"family":"124619","comment":""},"7":{"source_name_unclear":false,"value":"","family_hidden":false,"family_comment":"","source_name":"","family":"","comment":""},"8":{"family_comment":"","value":"","family":"","comment":""},"9":{"family_comment":"","value":"","family":"3988","comment":""},"10":{"family_comment":"","value":"","family":"","comment":""},"11":{"family_comment":"","value":"","family":"","comment":""},"12":{"family_comment":"","value":"","family":"","comment":""},"13":{"family_comment":"","value":"","family":"","comment":""},"14":{"family_comment":"","value":"","family":"","comment":""},"15":{"family_comment":"","value":"","family":"","comment":""},"16":{"family_comment":"","value":"","comment_unclear":false,"family":"","comment":""},"17":{"family_comment":"","family_unclear":false,"value":"","family":"","comment":""},"18":{"family_comment":"","value":"","family":"","comment":""},"19":{"value":"","family_hidden":false,"value_hidden":false,"family_comment":"","family":"","comment":""},"20":{"family_comment":"","value":"","comment_unclear":false,"family":"20615","comment":""}},"vehicle":{"40":[{"brand_info":"1.6","sum_rent_comment":"","brand":"Opel Kadett","sum_comment":"","brand_unclear":false,"year":"1986","brand_info_unclear":false,"year_unclear":false,"sum":"","sum_rent":""},{"brand_info":"1.6","sum_rent_comment":"","brand":"Hyundai Elantra","sum_comment":"","year":"","brand_info_unclear":false,"year_unclear":false,"sum":"","sum_rent":""}]},"id":"vulyk_67_100","banks":{"51":[{"sum_foreign_comment":"","sum_units":"UAH","sum_comment":"","sum_comment_unclear":false,"sum_hidden":true,"sum_foreign_units":"UAH","sum_comment_hidden":true,"sum_unclear":false,"sum":"24800","sum_foreign":""}]},"declaration":{"additional_info_text":"","notfull_lostpages":"","date":"2015-03-30T00:00:00","notfull":"","additional_info":"","url":"http://static.declarations.com.ua/declarations/chosen_ones/mega_batch/kovalchuk_olena_kostiantynivna.pdf"},"liabilities":{"54":{"sum_foreign_comment":"","sum_foreign_hidden":false,"sum_comment":"","sum_comment_unclear":false,"sum_hidden":false,"sum":"","sum_unclear":false,"sum_foreign":""},"55":{"sum_foreign_comment":"","sum":"","sum_comment":"","sum_foreign":""},"56":{"sum_foreign_comment":"","sum_foreign_hidden":false,"sum_comment":"","sum_hidden":false,"sum":"","sum_unclear":false,"sum_foreign":""},"57":{"sum_foreign_comment":"","sum_foreign_hidden":false,"sum_comment":"","sum_comment_unclear":false,"sum_hidden":false,"sum_comment_hidden":false,"sum_unclear":false,"sum":"","sum_foreign":""},"58":{"sum_foreign_comment":"","sum_foreign_hidden":false,"sum_comment":"","sum_comment_unclear":false,"sum_hidden":false,"sum_comment_hidden":false,"sum_unclear":false,"sum":"","sum_foreign":""},"59":{"sum_foreign_comment":"","sum":"","sum_hidden":false,"sum_comment":"","sum_foreign":""},"60":{"sum_foreign_comment":"","sum":"711","sum_comment":"","sum_foreign":""},"61":{"sum_foreign_comment":"","sum_foreign_hidden":false,"sum_comment":"","sum_hidden":false,"sum":"","sum_foreign":""},"62":{"sum_foreign_comment":"","sum":"40000","sum_hidden":false,"sum_comment":"","sum_foreign":""},"63":{"sum_foreign_comment":"","sum":"","sum_comment":"","sum_comment_unclear":false,"sum_hidden":false,"sum_unclear":false,"sum_foreign":""},"64":{"sum_foreign_comment":"","sum":"","sum_comment":"","sum_hidden":false,"sum_unclear":false,"sum_foreign":""}},"ft_src":"40000\n711\nсуддя хмельницького окружного адміністративного суду\nХмельницька область\nАдміністративний місцевий суд\nОлена\nКовальчук В. В\nПодружжя\nКовальчук О. В\nДитина\nКовальчук О. В\nДитина\nКостянтинівна\nКовальчук Олена Костянтинівна\nКовальчук\nКовальчук Олена Костянтинівна\nОлена Костянтинівна Ковальчук\nОлена Ковальчук\nКовальчук Олена Костянтинівна\n1.6\nOpel Kadett\n1986\n1.6\nHyundai Elantra\n24800\n2014\n1.6\n1986\nOpel Kadett\n1.6\nHyundai Elantra\n24800\n1500\nУкраїна\n21\nУкраїна\n97.9\nУкраїна\n97.9\n900\nУкраїна\n400\nУкраїна\nАдміністративний місцевий суд\nсуддя хмельницького окружного адміністративного суду\nХмельницька область\nПодружжя\nКовальчук В. В\nДитина\nКовальчук О. В\nДитина\nКовальчук О. В\nКовальчук Олена Костянтинівна\nОлена Костянтинівна Ковальчук\nОлена Ковальчук\nКовальчук Олена Костянтинівна\nКовальчук Олена Костянтинівна\nОлена\nКовальчук\nКостянтинівна\n711\n40000\n124619\n217925\n20615\n217925\n128607\n3988\n2014\n40000\n711\nУкраїна\n21\nУкраїна\n1500\nУкраїна\n900\nУкраїна\n400\nУкраїна\n97.9\n97.9\nПодружжя\nКовальчук В. В\nДитина\nКовальчук О. В\nКовальчук О. В\nДитина\nКостянтинівна\nКовальчук\nОлена\nКовальчук Олена Костянтинівна\nОлена Костянтинівна Ковальчук\nОлена Ковальчук\nКовальчук Олена Костянтинівна\nХмельницька область\nсуддя хмельницького окружного адміністративного суду\nАдміністративний місцевий суд\nКовальчук Олена Костянтинівна\n124619\n217925\n128607\n217925\n3988\n20615\n1986\n1.6\nOpel Kadett\n1.6\nHyundai Elantra\n20615\n217925\n128607\n3988\n217925\n124619\nУкраїна\n97.9\nУкраїна\n1500\nУкраїна\n21\n97.9\nУкраїна\n900\nУкраїна\n400\n24800\n2014","general":{"inn":"","name":"Олена","patronymic_unclear":false,"last_name_hidden":false,"family":[{"inn":"","inn_hidden":true,"relations_unclear":false,"relations_hidden":false,"relations_other":"","relations":"Подружжя","name_hidden":true,"inn_unclear":false,"family_name":"Ковальчук В. В","name_unclear":false},{"inn":"","inn_hidden":false,"relations_unclear":false,"relations_hidden":false,"relations_other":"","relations":"Дитина","name_hidden":true,"inn_unclear":false,"family_name":"Ковальчук О. В","name_unclear":false},{"inn":"","relations":"Дитина","relations_unclear":false,"family_name":"Ковальчук О. В","inn_hidden":false,"relations_other":"","name_hidden":true,"name_unclear":false}],"patronymic":"Костянтинівна","inn_hidden":true,"family_raw":"","inn_unclear":false,"post":{"post_unclear":false,"post":"суддя хмельницького окружного адміністративного суду","post_hidden":false,"region":"Хмельницька область","region_hidden":false,"office":"Адміністративний місцевий суд","office_hidden":false,"office_unclear":false},"last_name_unclear":false,"full_name":"Ковальчук Олена Костянтинівна","addresses":[{"place_city_type_hidden":true,"place_district_hidden":true,"place_city_type":"","place_city_hidden":true,"place_address_unclear":false,"place_address":"","place":"","place_district":"","place_unclear":false,"place_city":"","place_city_unclear":false,"place_hidden":true,"place_address_hidden":true,"place_district_unclear":false}],"last_name":"Ковальчук","full_name_suggest":{"output":"Ковальчук Олена Костянтинівна","input":["Ковальчук Олена Костянтинівна","Олена Костянтинівна Ковальчук","Олена Ковальчук"]},"name_unclear":false},"source":"VULYK","estate":{"23":[{"space_hidden":false,"costs":"","costs_comment":"","costs_hidden":false,"address_hidden":true,"region_hidden":true,"space_comment":"","space_unclear":false,"space":"1500","address":"Україна","region":"","address_unclear":false,"space_units_unclear":false,"costs_rent_hidden":false,"space_comment_unclear":false,"space_units":"м²","costs_rent":"","costs_rent_comment":""}],"25":[{"space_unclear":false,"costs":"","costs_comment":"","costs_hidden":false,"address_hidden":true,"region_hidden":true,"space_comment":"","space":"97.9","address":"","region":"","address_unclear":false,"space_units_unclear":false,"space_comment_unclear":false,"space_units":"м²","costs_rent":"","costs_rent_comment":""}],"29":[{"region_unclear":false,"space_unclear":false,"address_hidden":true,"region_hidden":true,"space_comment":"","space_units_hidden":false,"space_hidden":false,"space":"900","address":"Україна","region":"","costs_property":"","costs_rent_comment":"","space_units":"м²","costs_property_comment":"","costs_rent":""},{"costs_rent":"","region":"","costs_property":"","costs_rent_comment":"","address_hidden":true,"region_hidden":true,"space_comment":"","costs_property_comment":"","space_units":"м²","space":"400","address":"Україна"}],"31":[{"space_hidden":false,"address_hidden":true,"region_hidden":true,"space_comment":"","space_unclear":false,"space":"97.9","address":"Україна","region":"","costs_property":"","costs_rent_comment":"","space_comment_unclear":false,"address_unclear":false,"space_units":"м²","costs_property_comment":"","costs_rent":""}],"33":[{"costs_rent":"","region":"","costs_property":"","costs_rent_comment":"","address_hidden":true,"region_hidden":true,"space_comment":"","costs_property_comment":"","space_units":"м²","space":"21","address":"Україна"}]},"intro":{"declaration_year":"2014","isnotdeclaration":"","declaration_year_hidden":false}}