{"income":{"5":{"value":"206504.28","family_comment":"","value_unclear":false,"comment_hidden":false,"family_hidden":false,"value_hidden":false,"family_unclear":false,"family":"249121","comment":""},"6":{"value":"206504.28","family_comment":"","value_unclear":false,"family_hidden":false,"family_unclear":false,"comment_unclear":false,"comment":"","family":"143229"},"7":{"source_name_unclear":false,"value":"","value_hidden":false,"family_comment":"","source_name":"","family":"","comment":"","source_name_hidden":true},"8":{"value":"","family_hidden":false,"value_hidden":false,"family_comment":"","family":"","comment":""},"9":{"value":"","family_comment":"","value_unclear":false,"family_hidden":false,"value_hidden":false,"family_unclear":false,"family":"105892","comment":""},"10":{"family_comment":"","value":"","family":"","comment":""},"11":{"family_comment":"","value":"","family":"","comment":""},"12":{"family_comment":"","value":"","family":"","comment":""},"13":{"family_comment":"","value":"","family":"","comment":""},"14":{"family_comment":"","value":"","family":"","comment":""},"15":{"family_comment":"","value":"","family":"","comment":""},"16":{"value":"","family_comment":"","value_unclear":false,"family_unclear":false,"family":"","comment":""},"17":{"family_comment":"","value":"","family":"","comment":""},"18":{"family_comment":"","value":"","family":"","comment":""},"19":{"family_comment":"","value":"","comment_unclear":false,"family":"","comment":""},"20":{"value":"","family_comment":"","value_unclear":false,"comment_hidden":false,"family_hidden":false,"family":"","value_hidden":false,"family_unclear":false,"comment_unclear":false,"comment":"","family_comment_unclear":false}},"vehicle":{"35":[{"brand_info":"1598 куб. см.","sum_rent_comment":"","brand":"Nissan Juke","sum_comment":"","brand_unclear":false,"year":"2012","brand_info_unclear":false,"sum":"","sum_rent":""}]},"id":"vulyk_63_81","banks":{"51":[{"sum_foreign_comment":"","sum_units":"UAH","sum_comment":"","sum_foreign_unclear":false,"sum_foreign_units":"UAH","sum_foreign_hidden":false,"sum_hidden":false,"sum_comment_hidden":false,"sum_unclear":false,"sum":"600000","sum_foreign":""}]},"declaration":{"additional_info_text":"","notfull_lostpages":"","date":"2015-03-19T00:00:00","notfull":"","additional_info":"","url":"http://static.declarations.com.ua/declarations/chosen_ones/mega_batch/kotliarova_iryna_iuriivna.pdf"},"liabilities":{"54":{"sum_foreign_comment":"","sum":"","sum_comment":"","sum_unclear":false,"sum_foreign":""},"55":{"sum_foreign_comment":"","sum":"","sum_comment":"","sum_foreign":""},"56":{"sum_foreign_comment":"","sum":"8700","sum_comment":"","sum_unclear":false,"sum_foreign":""},"57":{"sum_foreign_comment":"","sum":"","sum_comment":"","sum_comment_hidden":false,"sum_unclear":false,"sum_foreign":""},"58":{"sum_foreign_comment":"","sum_comment_hidden":false,"sum":"","sum_comment":"","sum_foreign":""},"59":{"sum_foreign_comment":"","sum":"","sum_comment":"","sum_foreign":""},"60":{"sum_foreign_comment":"","sum":"","sum_comment":"","sum_comment_unclear":false,"sum_foreign":""},"61":{"sum_foreign_comment":"","sum":"","sum_comment":"","sum_unclear":false,"sum_foreign":""},"62":{"sum_foreign_comment":"","sum":"18300","sum_comment":"","sum_unclear":false,"sum_foreign":""},"63":{"sum_foreign_comment":"","sum":"","sum_comment":"","sum_hidden":false,"sum_comment_hidden":false,"sum_unclear":false,"sum_foreign":""},"64":{"sum_foreign_comment":"","sum_comment_hidden":false,"sum":"","sum_comment":"","sum_foreign":""}},"ft_src":"18300\n8700\nсуддя кам'янобрідського районного суду луганської області\nЛуганська область\nЗагальний місцевий суд\nІрина\nКотляров В. В\nПодружжя\nКотлярова А. В\nДитина\nКотлярова В. В\nДитина\nЮріївна\nКотлярова\nКотлярова Ірина Юріївна\nКотлярова Ірина Юріївна\nІрина Юріївна Котлярова\nІрина Котлярова\nКотлярова Ірина Юріївна\n2012\nNissan Juke\n1598 куб. см.\n600000\n2014\n1598 куб. см.\n2012\nNissan Juke\n600000\n.0835\n.15\n238\n69.2\nЮріївна\nКотлярова Ірина Юріївна\nІрина Юріївна Котлярова\nІрина Котлярова\nКотлярова Ірина Юріївна\nІрина\nПодружжя\nКотляров В. В\nДитина\nКотлярова А. В\nДитина\nКотлярова В. В\nКотлярова Ірина Юріївна\nЗагальний місцевий суд\nЛуганська область\nсуддя кам'янобрідського районного суду луганської області\nКотлярова\n8700\n18300\n206504.28\n143229\n206504.28\n249121\n105892\n2014\n8700\n18300\n238\n.0835\n.15\n69.2\nПодружжя\nКотляров В. В\nДитина\nКотлярова А. В\nДитина\nКотлярова В. В\nЮріївна\nКотлярова\nКотлярова Ірина Юріївна\nІрина Юріївна Котлярова\nІрина Котлярова\nКотлярова Ірина Юріївна\nІрина\nЛуганська область\nсуддя кам'янобрідського районного суду луганської області\nЗагальний місцевий суд\nКотлярова Ірина Юріївна\n143229\n206504.28\n249121\n206504.28\n105892\n2012\n1598 куб. см.\nNissan Juke\n206504.28\n249121\n105892\n206504.28\n143229\n238\n69.2\n.0835\n.15\n600000\n2014","general":{"name_hidden":false,"name":"Ірина","patronymic_unclear":false,"last_name_hidden":false,"inn":"","family":[{"inn":"","inn_hidden":true,"relations_unclear":false,"relations_hidden":false,"relations_other":"","relations":"Подружжя","name_hidden":false,"inn_unclear":true,"family_name":"Котляров В. В","name_unclear":false},{"inn":"","relations":"Дитина","relations_unclear":false,"family_name":"Котлярова А. В","inn_hidden":true,"relations_other":"","name_hidden":false,"inn_unclear":false,"name_unclear":false},{"inn":"","relations":"Дитина","inn_unclear":false,"family_name":"Котлярова В. В","inn_hidden":true,"relations_other":"","name_hidden":false,"name_unclear":false}],"patronymic":"Юріївна","inn_hidden":true,"family_raw":"","inn_unclear":true,"post":{"post_unclear":true,"region_unclear":true,"region":"Луганська область","office_hidden":false,"region_hidden":false,"post":"суддя кам'янобрідського районного суду луганської області","office_unclear":true,"office":"Загальний місцевий суд"},"last_name_unclear":false,"full_name":"Котлярова Ірина Юріївна","addresses":[{"place_city_type_unclear":false,"place_address":"","place_district_hidden":true,"place_city_type":"","place_address_hidden":true,"place_address_unclear":false,"place_city_type_hidden":true,"place":"","place_district":"","place_unclear":false,"place_city":"","place_city_unclear":true,"place_hidden":true,"place_city_hidden":true,"place_district_unclear":false}],"last_name":"Котлярова","full_name_suggest":{"output":"Котлярова Ірина Юріївна","input":["Котлярова Ірина Юріївна","Ірина Юріївна Котлярова","Ірина Котлярова"]},"name_unclear":false},"source":"VULYK","estate":{"25":[{"region_unclear":true,"space_unclear":true,"costs":"","costs_comment":"","costs_hidden":false,"address_hidden":true,"region_hidden":true,"space_comment":"","space_hidden":false,"space":"69.2","space_units_hidden":false,"region":"","address_unclear":false,"costs_rent_comment":"","costs_rent_hidden":false,"space_comment_unclear":false,"costs_rent_comment_hidden":false,"space_units":"м²","address":"","costs_comment_hidden":false,"costs_rent":""}],"29":[{"space_hidden":false,"costs_property_comment":"","address_hidden":true,"region_hidden":true,"space_comment":"","space_unclear":false,"space":".0835","address":"","region":"","costs_property":"","costs_rent_comment":"","address_unclear":false,"space_units":"га","space_units_unclear":false,"costs_rent":""},{"costs_rent":"","region":"","costs_property":"","costs_rent_comment":"","region_hidden":false,"space_comment":"","costs_property_comment":"","space_units":"га","space":".15","address":""}],"30":[{"space_unclear":false,"address_hidden":true,"region_hidden":true,"space_comment":"","space_hidden":false,"space":"238","address":"","region":"","costs_property":"","costs_rent_comment":"","space_units":"м²","costs_property_comment":"","costs_rent":""}]},"intro":{"declaration_year":"2014","isnotdeclaration":"","declaration_year_unclear":false}}