{"income":{"5":{"family_comment":"","value":"255960","family":"4945","comment":""},"6":{"family_comment":"","value":"242562","family":"","comment":"","family_comment_unclear":false},"7":{"value":"","comment_hidden":false,"family_comment":"","source_name":"","family":"","comment":"","source_name_hidden":false},"8":{"family_comment":"","value":"","family":"","comment":""},"9":{"family_comment":"","value":"","family":"","comment":""},"10":{"value":"13398","value_unclear":false,"value_hidden":false,"family_comment":"","family":"","comment":""},"11":{"family_comment":"","value":"","family":"","comment":""},"12":{"family_comment":"","value":"","family":"","comment":""},"13":{"family_comment":"","value":"","family":"","comment":""},"14":{"family_comment":"","value":"","family":"","comment":""},"15":{"family_comment":"","value":"","family":"","comment":""},"16":{"family_comment":"","value":"","family":"","comment":""},"17":{"family_comment":"","value":"","family":"","comment":""},"18":{"family_comment":"","value":"","family":"","comment":""},"19":{"family_comment":"","value":"","family":"","comment":""},"20":{"family_comment":"стипендія","value":"","comment_unclear":false,"family":"4945","comment":""}},"id":"vulyk_86_24","banks":{"51":[{"sum_foreign_comment":"","sum_units":"UAH","sum_comment":"","sum_foreign_units":"UAH","sum_comment_hidden":false,"sum":"18768","sum_foreign":""}]},"declaration":{"additional_info_text":"","notfull_lostpages":"","date":"2015-03-26T00:00:00","notfull":"","additional_info":"","url":"http://static.declarations.com.ua/declarations/chosen_ones/judges_batch/2727_zaitseva_svitlana_andriivna.pdf"},"liabilities":{"54":{"sum_foreign_comment":"","sum":"","sum_comment":"","sum_unclear":false,"sum_foreign":""},"55":{"sum_foreign_comment":"","sum":"","sum_comment":"","sum_foreign":""},"56":{"sum_foreign_comment":"","sum":"","sum_hidden":false,"sum_comment":"","sum_foreign":""},"57":{"sum_foreign_comment":"","sum":"","sum_comment":"","sum_unclear":false,"sum_foreign":""},"58":{"sum_foreign_comment":"","sum":"","sum_comment":"","sum_unclear":false,"sum_foreign":""},"59":{"sum_foreign_comment":"","sum":"","sum_comment":"","sum_foreign":""},"60":{"sum_foreign_comment":"","sum_comment_hidden":false,"sum":"","sum_comment":"","sum_foreign":""},"61":{"sum_foreign_comment":"","sum":"","sum_comment":"","sum_foreign":""},"62":{"sum_foreign_comment":"","sum":"","sum_comment":"","sum_foreign":""},"63":{"sum_foreign_comment":"","sum":"","sum_comment":"","sum_foreign":""},"64":{"sum_foreign_comment":"","sum":"","sum_comment":"","sum_foreign":""}},"ft_src":"суддя апеляційного суду донецької області\nДонецька область\nЗагальний апеляційний суд\nСвітлана\nЗайцева А. Г\nДитина\nАндріївна\nЗайцева Світлана Андріївна\nСвітлана Андріївна Зайцева\nСвітлана Зайцева\nЗайцева Світлана Андріївна\nЗайцева Світлана Андріївна\nЗайцева\n560\n24.27\nбезоплатне\n24.27\n18768\n2014\n2014\nЗайцева Світлана Андріївна\nСвітлана Андріївна Зайцева\nСвітлана Зайцева\nЗайцева Світлана Андріївна\nЗайцева Світлана Андріївна\nДитина\nЗайцева А. Г\nСвітлана\nЗайцева\nЗагальний апеляційний суд\nДонецька область\nсуддя апеляційного суду донецької області\nАндріївна\n242562\n4945\nстипендія\n255960\n4945\n13398\n560\n24.27\n24.27\nбезоплатне\n18768\n242562\n13398\n4945\n255960\n4945\nстипендія\nЗайцева А. Г\nДитина\nАндріївна\nЗайцева\nСвітлана\nЗайцева Світлана Андріївна\nСвітлана Андріївна Зайцева\nСвітлана Зайцева\nЗайцева Світлана Андріївна\nДонецька область\nЗагальний апеляційний суд\nсуддя апеляційного суду донецької області\nЗайцева Світлана Андріївна\n13398\n4945\nстипендія\n4945\n255960\n242562\n24.27\n560\nбезоплатне\n24.27\n18768\n2014","general":{"inn":"","name":"Світлана","patronymic_unclear":false,"family":[{"inn":"","inn_hidden":false,"relations_hidden":false,"family_name":"Зайцева А. Г","relations_other":"","relations":"Дитина","name_hidden":false,"name_unclear":false}],"patronymic":"Андріївна","inn_hidden":true,"family_raw":"","inn_unclear":false,"post":{"post_unclear":false,"post":"суддя апеляційного суду донецької області","candidate":"","office_hidden":false,"region":"Донецька область","office":"Загальний апеляційний суд","office_unclear":false,"region_hidden":false},"full_name":"Зайцева Світлана Андріївна","addresses":[{"place_district":"","place_unclear":false,"place_city":"","place_city_type_hidden":false,"place_district_hidden":false,"place_city_type":"","place_city_hidden":false,"place_address_hidden":true,"place_address":"","place_hidden":true,"place":""}],"last_name":"Зайцева","full_name_suggest":{"output":"Зайцева Світлана Андріївна","input":["Зайцева Світлана Андріївна","Світлана Андріївна Зайцева","Світлана Зайцева"]}},"source":"VULYK","estate":{"23":[{"costs":"","costs_comment":"","address_hidden":false,"region_hidden":true,"space_comment":"","space":"560","address":"","region":"","address_unclear":false,"costs_rent_comment":"","space_units":"м²","costs_rent":""}],"25":[{"space_unclear":false,"costs":"","costs_comment":"","address_hidden":false,"region_hidden":true,"space_comment":"безоплатне","space_hidden":false,"space":"24.27","address":"","region":"","address_unclear":false,"costs_rent_comment":"","space_units":"м²","costs_rent":""}],"31":[{"space_unclear":false,"address_hidden":true,"region_hidden":true,"space_comment":"","space_hidden":false,"space":"24.27","address":"","region":"","costs_property":"","costs_rent_comment":"","space_units":"м²","costs_property_comment":"","costs_rent":""}]},"intro":{"declaration_year":"2014","declaration_year_unclear":false}}