{"income":{"5":{"value":"26734.53","family_comment":"","value_unclear":false,"comment_hidden":false,"family_hidden":true,"value_hidden":false,"family_unclear":false,"family_comment_hidden":false,"comment":"","family":""},"6":{"value":"23629.2","family_comment":"","value_unclear":false,"family_hidden":true,"family_unclear":false,"family":"","comment":""},"7":{"source_name_unclear":false,"value":"","family_hidden":false,"family_comment":"","source_name":"","family":"","comment":"","source_name_hidden":false},"8":{"family_comment":"","value":"","family":"","comment":""},"9":{"value":"872.82","value_unclear":false,"family_hidden":false,"family_comment":"","family":"","comment":""},"10":{"value":"","value_unclear":false,"family_hidden":false,"value_hidden":false,"family_comment":"","comment_unclear":false,"comment":"","family":""},"11":{"family_comment":"","value":"","family":"","comment":""},"12":{"family_comment":"","value":"","family":"","comment":""},"13":{"family_comment":"","value":"","family":"","comment":""},"14":{"family_comment":"","value":"","family":"","comment":""},"15":{"family_comment":"","value":"","family_hidden":false,"comment":"","family":""},"16":{"value":"","value_unclear":false,"family_hidden":false,"family_comment":"","family":"","comment":""},"17":{"family_comment":"","value":"","family_hidden":false,"comment":"","family":""},"18":{"family_comment":"","value":"","value_unclear":false,"family":"","comment":""},"19":{"family_comment":"","value":"","family":"","comment":""},"20":{"value":"2232.51","family_comment":"","value_unclear":false,"family_hidden":false,"family_unclear":false,"comment_unclear":false,"comment":"","family":""}},"vehicle":{"40":[{"year_hidden":true,"brand_info":"","sum_rent_comment":"","year":"","brand_info_hidden":true,"brand_info_unclear":false,"year_unclear":false,"sum_rent":"","sum":"","brand":"","sum_comment":"","brand_unclear":false,"brand_hidden":true}]},"id":"vulyk_72_255","declaration":{"additional_info_text":"","notfull_lostpages":"","date":"2015-03-27T00:00:00","notfull":"","additional_info":"","url":"http://static.declarations.com.ua/declarations/chosen_ones/epic_batch/astakhova_oleksandra_oleksandrivna.pdf"},"liabilities":{"54":{"sum_foreign_comment":"","sum":"","sum_comment":"","sum_comment_hidden":false,"sum_unclear":false,"sum_foreign":""},"55":{"sum_foreign_comment":"","sum":"","sum_comment":"","sum_foreign":""},"56":{"sum_foreign_comment":"","sum":"","sum_hidden":false,"sum_comment":"","sum_foreign":""},"57":{"sum_foreign_comment":"","sum":"10728","sum_comment":"","sum_comment_unclear":false,"sum_hidden":false,"sum_comment_hidden":false,"sum_unclear":false,"sum_foreign":""},"58":{"sum_foreign_comment":"","sum":"608.64","sum_comment":"","sum_comment_unclear":false,"sum_hidden":false,"sum_comment_hidden":false,"sum_unclear":false,"sum_foreign":""},"59":{"sum_foreign_comment":"","sum_foreign_hidden":false,"sum_comment":"","sum_foreign_unclear":false,"sum_comment_hidden":false,"sum":"","sum_foreign":""},"60":{"sum_foreign_comment":"","sum_foreign_hidden":false,"sum_comment":"","sum_hidden":false,"sum":"","sum_foreign":""},"61":{"sum_foreign_comment":"","sum_foreign_hidden":false,"sum_comment":"","sum_hidden":false,"sum":"","sum_foreign":""},"62":{"sum_foreign_comment":"","sum_foreign_hidden":false,"sum_comment":"","sum_hidden":false,"sum":"","sum_foreign":""},"63":{"sum_foreign_comment":"","sum_foreign_hidden":false,"sum_comment":"","sum_comment_unclear":false,"sum_hidden":true,"sum_comment_hidden":false,"sum_unclear":false,"sum":"","sum_foreign":""},"64":{"sum_foreign_comment":"","sum_foreign_hidden":false,"sum_comment":"","sum_hidden":true,"sum":"","sum_foreign":""}},"ft_src":"10728\n608.64\nКиїв\nм. Київ\nсуддя дніпровського районного суду міста києва\nм. Київ\nЗагальний місцевий суд\nОлександра\nОлександрівна\nАстахова\nАстахова Олександра Олександрівна\nАстахова Олександра Олександрівна\nОлександра Олександрівна Астахова\nОлександра Астахова\nАстахова Олександра Олександрівна\nЛебедівська с/р. с. т. 'Глядин' Вишгородського району\n1016\n2014\n23629.2\n872.82\n26734.53\n2232.51\n1016\nЛебедівська с/р. с. т. 'Глядин' Вишгородського району\nАстахова Олександра Олександрівна\nОлександра Олександрівна Астахова\nОлександра Астахова\nАстахова Олександра Олександрівна\nОлександра\nАстахова Олександра Олександрівна\nАстахова\nм. Київ\nЗагальний місцевий суд\nсуддя дніпровського районного суду міста києва\nОлександрівна\nКиїв\nм. Київ\n608.64\n10728\n23629.2\n2232.51\n26734.53\n872.82\n2014\n608.64\n10728\nОлександрівна\nАстахова\nАстахова Олександра Олександрівна\nОлександра Олександрівна Астахова\nОлександра Астахова\nАстахова Олександра Олександрівна\nм. Київ\nКиїв\nм. Київ\nЗагальний місцевий суд\nсуддя дніпровського районного суду міста києва\nАстахова Олександра Олександрівна\nОлександра\n872.82\n2232.51\n26734.53\n23629.2\nЛебедівська с/р. с. т. 'Глядин' Вишгородського району\n1016\n2014","general":{"inn":"","name":"Олександра","patronymic_unclear":false,"family":[{"inn":"","inn_hidden":true,"relations_unclear":false,"relations_hidden":true,"relations_other":"","relations":"","name_hidden":true,"inn_unclear":false,"family_name":"","name_unclear":false}],"patronymic":"Олександрівна","inn_hidden":true,"family_raw":"","inn_unclear":false,"post":{"post_unclear":false,"region_unclear":false,"post":"суддя дніпровського районного суду міста києва","candidate":"","office_hidden":false,"region":"м. Київ","post_hidden":false,"office":"Загальний місцевий суд","office_unclear":false,"region_hidden":false},"last_name_unclear":false,"full_name":"Астахова Олександра Олександрівна","addresses":[{"place_city_type_hidden":false,"place_district_hidden":false,"place_city_type":"Місто","place_city_hidden":false,"place_address_unclear":false,"place_address":"","place":"м. Київ","place_district":"","place_unclear":false,"place_city":"Київ","place_city_unclear":false,"place_hidden":false,"place_address_hidden":true,"place_district_unclear":false}],"last_name":"Астахова","patronymic_hidden":false,"full_name_suggest":{"output":"Астахова Олександра Олександрівна","input":["Астахова Олександра Олександрівна","Олександра Олександрівна Астахова","Олександра Астахова"]},"name_unclear":false},"source":"VULYK","estate":{"23":[{"space_hidden":false,"costs":"","costs_rent_unclear":false,"costs_comment":"","costs_hidden":false,"address_hidden":false,"region_hidden":false,"space_comment":"","space_unclear":false,"space":"1016","address":"Лебедівська с/р. с. т. 'Глядин' Вишгородського району","region":"","address_unclear":true,"costs_rent_comment":"","costs_rent_hidden":false,"space_units":"м²","space_units_hidden":false,"costs_rent":""}]},"intro":{"declaration_year":"2014","isnotdeclaration":"","declaration_year_unclear":false}}