{"id":"vulyk_97_193","ft_src":"об'єм двигуна 2890\n2001\nГАЗ 33621\nNissan Qashqai\nоб'єм двигуна 1997\n2012\n1983\nМотоцикл, об'єм двигуна 348\nІЖ Планета-3\n24.5\n59349\n440\n35200\n100.8\n21\n16.85\n1/3 частина\n16.85\nПублічне акціонерне товариство Укроптбакалія\n538\nПАТ Державний ощадний банк України, ПАТ КБ Приватбанк, ПАТ Український професійний банк\n17618\nПАТ Державний ощадний банк України, ПАТ Укрсоцбанк\n5801\n2014\nоб'єм двигуна 1997\nNissan Qashqai\n2012\nМотоцикл, об'єм двигуна 348\n1983\nІЖ Планета-3\nоб'єм двигуна 2890\n2001\nГАЗ 33621\n2014\nЛавриненко Любов Миколаївна\nЛюбов Миколаївна Лавриненко\nЛюбов Лавриненко\nЛавриненко Любов Миколаївна\nЛюбов\nБатьки\nПавленко Т. Ф\nДитина\nМартиненко (Лавриненко) В. М\nІнше\nЛавриненко М. В\nСпільне проживання\nЛавриненко Любов Миколаївна\nЛавриненко\nГосподарський місцевий суд\nЧернігівська область\nсуддя господарського суду чернігівської області\nМиколаївна\nСтрахове товариство з додатковою відповідальністю Глобус\n360\n203020\n96573\nпенсія\nпенсія\n54462\n25168\n269694\n140997\n14000\n9901\n30\n500\n104\nоренда земельного паю\n2311\n4622\nоренда земельного паю\n24.5\n100.8\n16.85\n1/3 частина\n35200\n59349\n440\n21\n16.85\n5801\nПАТ Державний ощадний банк України, ПАТ Укрсоцбанк\nПАТ Державний ощадний банк України, ПАТ КБ Приватбанк, ПАТ Український професійний банк\n17618\n538\nПублічне акціонерне товариство Укроптбакалія\nСтрахове товариство з додатковою відповідальністю Глобус\n360\n96573\n203020\n30\n9901\n104\n500\n140997\n269694\n14000\n4622\nоренда земельного паю\nоренда земельного паю\n2311\nпенсія\nпенсія\n25168\n54462\nБатьки\nПавленко Т. Ф\nМартиненко (Лавриненко) В. М\nДитина\nІнше\nЛавриненко М. В\nСпільне проживання\nМиколаївна\nЛавриненко\nЛюбов\nЛавриненко Любов Миколаївна\nЛюбов Миколаївна Лавриненко\nЛюбов Лавриненко\nЛавриненко Любов Миколаївна\nЧернігівська область\nГосподарський місцевий суд\nсуддя господарського суду чернігівської області\nЛавриненко Любов Миколаївна","estate":{"23":[{"address":"","space_units":"м²","costs_rent_unclear":false,"costs_comment":"","space_unclear":false,"region_hidden":true,"space_comment":"","address_hidden":false,"costs":"","address_unclear":false,"costs_rent_comment":"","space":"35200","region_unclear":false,"region":"","costs_rent":""}],"25":[{"address":"","space_units":"м²","space_hidden":false,"space_unclear":false,"region_hidden":true,"costs_rent_comment":"","space_comment":"1/3 частина","address_hidden":false,"space_comment_hidden":false,"costs":"","space_comment_unclear":false,"costs_comment":"","space":"16.85","region_unclear":false,"region":"","costs_rent":""}],"27":[{"address":"","space_units":"м²","costs_comment":"","region":"","region_hidden":true,"space_comment":"","address_hidden":false,"costs":"","costs_rent_comment":"","space":"24.5","region_unclear":false,"costs_rent":""}],"29":[{"costs_property_comment":"","address":"","space_units":"м²","space_unclear":false,"region_hidden":true,"costs_property":"","space_comment":"","address_hidden":false,"address_unclear":false,"space_comment_unclear":false,"costs_rent_comment":"","space":"59349","region_unclear":false,"region":"","costs_rent":""},{"costs_property_comment":"","address":"","space_units":"м²","space_comment":"","region_hidden":false,"costs_property":"","region":"","address_hidden":false,"address_unclear":false,"costs_rent_comment":"","space":"440","costs_rent":""}],"30":[{"costs_property_comment":"","address":"","space_units":"м²","space_comment":"","region_hidden":true,"costs_property":"","region":"","address_hidden":false,"address_unclear":false,"costs_rent_comment":"","space":"100.8","costs_rent":""}],"31":[{"costs_property_comment":"","address":"","space_units":"м²","space_hidden":false,"space_unclear":false,"region_hidden":true,"costs_property":"","space_comment":"","address_hidden":false,"space_comment_hidden":false,"costs_rent_comment":"","space":"21","region":"","costs_rent":""},{"costs_property_comment":"","address":"","space_units":"м²","costs_rent_comment":"","space":"16.85","region":"","costs_property":"","space_comment":"","address_hidden":false,"costs_rent":""}]},"vehicle":{"40":[{"sum_comment":"","brand_info":"об'єм двигуна 1997","brand_unclear":false,"sum_rent_comment":"","year":"2012","brand":"Nissan Qashqai","sum_rent":"","brand_info_unclear":false,"year_unclear":false,"sum":""}],"41":[{"sum_comment":"","brand_info":"об'єм двигуна 2890","sum":"","sum_rent_comment":"","year":"2001","brand":"ГАЗ 33621","sum_rent":""}],"44":[{"sum_comment":"","brand_info":"Мотоцикл, об'єм двигуна 348","sum":"","sum_rent_comment":"","year":"1983","brand":"ІЖ Планета-3","sum_rent":"","brand_hidden":false}]},"source":"VULYK","income":{"5":{"family_comment":"","value":"269694","family":"140997","comment":""},"6":{"family_comment":"","family":"96573","comment":"","value_unclear":false,"family_unclear":false,"comment_hidden":false,"value":"203020"},"7":{"family":"","family_comment":"","value":"","comment":"","source_name":""},"8":{"family_comment":"","value":"","family":"","comment":""},"9":{"family_comment":"","value":"9901","family_unclear":false,"family":"30","comment":""},"10":{"family_comment":"","value":"","family":"500","comment":"","value_unclear":false},"11":{"family_comment":"","value":"","family":"104","comment":""},"12":{"family_comment":"","value":"","family":"","comment":""},"13":{"family_comment":"","value":"","family":"","comment":""},"14":{"family_comment":"","value":"","family":"","comment":""},"15":{"family_comment":"","value":"","family":"","comment":""},"16":{"family_comment":"","value":"","family":"14000","comment":""},"17":{"family_comment":"","value":"","family":"","comment":""},"18":{"family_comment":"","value":"","family":"","comment":""},"19":{"family_comment":"оренда земельного паю","value":"2311","family":"4622","comment":"оренда земельного паю"},"20":{"family_comment":"пенсія","comment":"пенсія","family":"25168","value_unclear":false,"comment_unclear":false,"value":"54462","family_hidden":false,"family_comment_unclear":false}},"banks":{"45":[{"sum_comment_unclear":true,"sum_units":"UAH","sum_foreign_units":"UAH","sum_hidden":false,"sum":"5801","sum_foreign_comment":"","sum_comment":"ПАТ Державний ощадний банк України, ПАТ Укрсоцбанк","sum_unclear":true,"sum_foreign":"","sum_comment_hidden":false}],"51":[{"sum_comment_unclear":true,"sum_units":"UAH","sum_foreign_units":"UAH","sum_hidden":false,"sum":"17618","sum_foreign_comment":"","sum_comment":"ПАТ Державний ощадний банк України, ПАТ КБ Приватбанк, ПАТ Український професійний банк","sum_unclear":true,"sum_foreign":"","sum_comment_hidden":false}],"52":[{"sum_comment_unclear":true,"sum_units":"UAH","sum_foreign_units":"UAH","sum":"538","sum_foreign_comment":"","sum_comment":"Публічне акціонерне товариство Укроптбакалія","sum_foreign":"","sum_comment_hidden":false}]},"declaration":{"notfull_lostpages":"","additional_info_text":"","additional_info":"","date":"2015-03-25T00:00:00","notfull":"","url":"http://static.declarations.com.ua/declarations/chosen_ones/judges_batch/4108_lavrynenko_liubov_mykolaivna.pdf"},"general":{"family":[{"inn":"","family_name":"Павленко Т. Ф","relations_other":"","name_unclear":false,"inn_hidden":true,"name_hidden":true,"relations":"Батьки"},{"inn":"","family_name":"Мартиненко (Лавриненко) В. М","name_unclear":true,"inn_hidden":false,"name_hidden":false,"relations":"Дитина"},{"inn":"","family_name":"Лавриненко М. В","relations_other":"Спільне проживання","name_unclear":false,"inn_hidden":false,"name_hidden":false,"relations":"Інше"}],"family_raw":"","name":"Любов","full_name_suggest":{"input":["Лавриненко Любов Миколаївна","Любов Миколаївна Лавриненко","Любов Лавриненко"],"output":"Лавриненко Любов Миколаївна"},"patronymic":"Миколаївна","inn_hidden":true,"addresses":[{"place_city_type":"","place_city_type_hidden":false,"place_hidden":true,"place_city_hidden":false,"place_district_hidden":false,"place_district":"","place_city_unclear":false,"place":"","place_city":"","place_address_hidden":true,"place_address":""}],"last_name_hidden":false,"patronymic_hidden":false,"inn":"","inn_unclear":false,"last_name":"Лавриненко","full_name":"Лавриненко Любов Миколаївна","post":{"post_hidden":false,"office":"Господарський місцевий суд","post":"суддя господарського суду чернігівської області","office_unclear":false,"region_unclear":false,"region":"Чернігівська область"},"name_hidden":false},"liabilities":{"54":{"sum_comment_unclear":false,"sum_comment":"","sum_hidden":false,"sum":"","sum_foreign_comment":"","sum_foreign":"","sum_unclear":false,"sum_comment_hidden":false},"55":{"sum_comment":"","sum_foreign_comment":"","sum_foreign":"","sum":""},"56":{"sum_comment":"","sum_foreign_comment":"","sum_foreign":"","sum":""},"57":{"sum_comment_unclear":false,"sum_comment":"","sum_hidden":false,"sum":"","sum_foreign_comment":"","sum_foreign":"","sum_unclear":false,"sum_comment_hidden":false},"58":{"sum_comment_unclear":false,"sum_comment":"","sum_hidden":false,"sum":"","sum_foreign_comment":"","sum_foreign":"","sum_unclear":false,"sum_comment_hidden":false},"59":{"sum_comment":"","sum_foreign_comment":"","sum_foreign":"","sum":""},"60":{"sum_comment_unclear":true,"sum_comment":"Страхове товариство з додатковою відповідальністю Глобус","sum_hidden":false,"sum":"360","sum_foreign_comment":"","sum_foreign":"","sum_comment_hidden":false},"61":{"sum_comment":"","sum_foreign_comment":"","sum_foreign":"","sum":""},"62":{"sum_comment":"","sum_foreign_comment":"","sum_foreign":"","sum_unclear":false,"sum":""},"63":{"sum_comment":"","sum_foreign_comment":"","sum_foreign":"","sum_hidden":false,"sum":""},"64":{"sum_comment":"","sum_foreign_comment":"","sum_foreign":"","sum":""}},"intro":{"isnotdeclaration":"","declaration_year":"2014"}}