{"income":{"5":{"value":"231814","comment_hidden":false,"family_comment":"","family":"","comment":"","family_comment_hidden":false},"6":{"value":"231790","family_comment":"","comment_hidden":false,"family_hidden":false,"family_unclear":false,"family_comment_hidden":false,"comment":"","family":""},"7":{"value":"","comment_hidden":false,"family_comment_hidden":false,"family_comment":"","source_name":"","family":"","comment":"","source_name_hidden":false},"8":{"family_comment":"","value":"","family":"","comment":""},"9":{"value":"","family_comment":"","value_unclear":false,"family_unclear":false,"comment_unclear":false,"comment":"","family":""},"10":{"family_comment":"","family_unclear":false,"value":"","family":"","comment":""},"11":{"family_comment":"","value":"","family":"","comment":""},"12":{"family_comment":"","value":"","family":"","comment":""},"13":{"family_comment":"","value":"","family":"","comment":""},"14":{"family_comment":"","value":"","family":"","comment":""},"15":{"family_comment":"","value":"","comment_unclear":false,"family":"","comment":""},"16":{"family_comment":"","value":"","comment_unclear":false,"family":"","comment":""},"17":{"family_comment":"","value":"","family":"","comment":""},"18":{"family_comment":"","value":"","family":"","comment":""},"19":{"family_comment":"","value":"","family":"","comment":""},"20":{"value":"24","family_comment":"","value_unclear":false,"family_unclear":false,"family_comment_unclear":false,"family_comment_hidden":false,"comment":"","family":""}},"vehicle":{"35":[{"brand_info":"3456 куб.см.","sum_rent_comment":"","brand":"Lexus RX 350","sum_comment":"","brand_unclear":false,"year":"2012","sum_hidden":false,"brand_info_unclear":false,"sum":"","sum_rent":""}]},"id":"vulyk_73_37","declaration":{"additional_info_text":"","notfull_lostpages":"","date":"2014-03-20T00:00:00","notfull":"","additional_info":"","url":"http://static.declarations.com.ua/declarations/chosen_ones/judges_batch/1402_kolomys_viktoriia_viktorivna.pdf"},"liabilities":{"54":{"sum_foreign_comment":"","sum_foreign_hidden":false,"sum_comment":"","sum_comment_unclear":false,"sum_hidden":false,"sum_comment_hidden":false,"sum_unclear":false,"sum":"27653","sum_foreign":""},"55":{"sum_foreign_comment":"","sum_comment_hidden":false,"sum":"","sum_comment":"","sum_foreign":""},"56":{"sum_foreign_comment":"","sum":"","sum_comment":"","sum_comment_unclear":false,"sum_foreign":""},"57":{"sum_foreign_comment":"","sum":"50000","sum_comment":"","sum_hidden":false,"sum_comment_hidden":false,"sum_unclear":false,"sum_foreign":""},"58":{"sum_foreign_comment":"","sum":"","sum_comment":"","sum_hidden":false,"sum_comment_hidden":false,"sum_foreign":""},"59":{"sum_foreign_comment":"","sum":"","sum_comment":"","sum_comment_unclear":false,"sum_unclear":false,"sum_foreign":""},"60":{"sum_foreign_comment":"","sum":"","sum_comment":"","sum_hidden":false,"sum_comment_hidden":false,"sum_unclear":false,"sum_foreign":""},"61":{"sum_foreign_comment":"","sum":"","sum_comment":"","sum_foreign":""},"62":{"sum_foreign_comment":"","sum":"","sum_comment":"","sum_foreign":""},"63":{"sum_foreign_comment":"","sum":"","sum_comment":"","sum_hidden":false,"sum_comment_hidden":false,"sum_foreign":""},"64":{"sum_foreign_comment":"","sum":"","sum_comment":"","sum_foreign":""}},"ft_src":"50000\n27653\nсуддя, заступник голови рівненського апеляційного господарського суду\nРівненська область\nАпеляційний господарський суд\nВікторія\nДитина\nДитина\nВікторівна\nКоломис Вікторія Вікторівна\nВікторія Вікторівна Коломис\nВікторія Коломис\nКоломис Вікторія Вікторівна\nКоломис\nКоломис Вікторія Вікторівна\nLexus RX 350\n3456 куб.см.\n2012\n977\n94\n58.6\n2013\n231790\n231814\n24\n3456 куб.см.\nLexus RX 350\n2012\n2013\nКоломис Вікторія Вікторівна\nВікторія Вікторівна Коломис\nВікторія Коломис\nКоломис Вікторія Вікторівна\nВікторія\nДитина\nДитина\nКоломис Вікторія Вікторівна\nВікторівна\nАпеляційний господарський суд\nРівненська область\nсуддя, заступник голови рівненського апеляційного господарського суду\nКоломис\n27653\n50000\n231790\n24\n231814\n977\n94\n58.6\n50000\n27653\nДитина\nДитина\nВікторівна\nКоломис\nВікторія\nКоломис Вікторія Вікторівна\nВікторія Вікторівна Коломис\nВікторія Коломис\nКоломис Вікторія Вікторівна\nРівненська область\nАпеляційний господарський суд\nсуддя, заступник голови рівненського апеляційного господарського суду\nКоломис Вікторія Вікторівна\n2012\n3456 куб.см.\nLexus RX 350\n24\n231814\n231790\n94\n977\n58.6\n2013","general":{"inn":"","name":"Вікторія","family":[{"inn":"","relations":"Дитина","inn_unclear":false,"relations_hidden":false,"inn_hidden":true,"relations_other":"","name_hidden":true,"family_name":"","name_unclear":false},{"inn":"","relations":"Дитина","inn_unclear":false,"family_name":"","inn_hidden":false,"relations_other":"","name_hidden":true,"name_unclear":false}],"patronymic":"Вікторівна","inn_hidden":true,"family_raw":"","last_name":"Коломис","post":{"post_unclear":false,"region_unclear":false,"post":"суддя, заступник голови рівненського апеляційного господарського суду","office":"Апеляційний господарський суд","region":"Рівненська область","post_hidden":false,"office_hidden":false,"office_unclear":false,"region_hidden":false},"last_name_unclear":false,"full_name":"Коломис Вікторія Вікторівна","addresses":[{"place_district":"","place_city_hidden":true,"place_city":"","place_city_type_hidden":false,"place_district_hidden":false,"place_city_type":"","place_address_hidden":true,"place_address":"","place_hidden":true,"place":""}],"full_name_suggest":{"output":"Коломис Вікторія Вікторівна","input":["Коломис Вікторія Вікторівна","Вікторія Вікторівна Коломис","Вікторія Коломис"]},"name_unclear":false},"source":"VULYK","estate":{"23":[{"space_hidden":false,"costs":"","costs_comment":"","costs_hidden":false,"address_hidden":true,"region_hidden":true,"space_comment":"","space_unclear":false,"space":"977","address":"","region":"","space_units_unclear":false,"costs_unclear":false,"space_units":"м²","costs_rent":"","costs_rent_comment":""}],"25":[{"space_unclear":false,"costs":"","costs_comment":"","costs_hidden":false,"address_hidden":true,"region_hidden":true,"space_comment":"","space_hidden":false,"space":"58.6","address":"","region":"","costs_rent_comment":"","space_comment_hidden":false,"space_units":"м²","costs_rent":""}],"31":[{"space_unclear":false,"address_hidden":true,"region_hidden":true,"space_comment":"","space":"94","address":"","region":"","costs_property":"","costs_rent_comment":"","space_units":"м²","costs_property_comment":"","costs_rent":""}]},"intro":{"declaration_year":"2013"}}