{"income":{"5":{"value":"196283","value_unclear":false,"family_hidden":false,"family_comment":"","family":"92262","comment":""},"6":{"family_comment":"","value":"181283","value_unclear":false,"family":"87914","comment":""},"7":{"source_name_unclear":false,"value":"","family_comment":"","source_name":"","family":"320","comment":"","source_name_hidden":false},"8":{"family_comment":"","value":"","family":"","comment":""},"9":{"family_comment":"","value":"15000","comment_unclear":false,"family":"4028","comment":""},"10":{"family_comment":"","value":"","family":"","comment":""},"11":{"family_comment":"","family_unclear":false,"value":"","family":"","comment":""},"12":{"family_comment":"","value":"","family":"","comment":""},"13":{"family_comment":"","value":"","family":"","comment":""},"14":{"family_comment":"","value":"","family":"","comment":""},"15":{"family_comment":"","value":"","family":"","comment":""},"16":{"family_comment":"","value":"","family":"","comment":""},"17":{"family_comment":"","value":"","family":"","comment":""},"18":{"family_comment":"","value":"","family":"","comment":""},"19":{"family_comment":"","value":"","family":"","comment":""},"20":{"value":"","value_unclear":false,"family_comment":"","comment_unclear":false,"comment":"","family":""}},"vehicle":{"35":[{"year_hidden":false,"brand_info":"1968 куб. см., 103 кВт","sum_rent_comment":"","year":"2012","brand_info_hidden":false,"brand_info_unclear":false,"year_unclear":false,"sum_rent":"","sum":"","brand":"Volkswagen Passat","sum_comment":"","brand_unclear":false,"brand_hidden":false}]},"id":"vulyk_94_62","banks":{"45":[{"sum_foreign_comment":"","sum_unclear":false,"sum_units":"UAH","sum_comment":"","sum_hidden":false,"sum_foreign_units":"UAH","sum_units_unclear":false,"sum_comment_hidden":false,"sum_units_hidden":false,"sum":"80000","sum_foreign":""}],"51":[{"sum_foreign_comment":"","sum_units":"UAH","sum_comment":"","sum_hidden":false,"sum_foreign_units":"UAH","sum_comment_hidden":false,"sum_unclear":false,"sum":"27404","sum_foreign":""}]},"declaration":{"additional_info_text":"","notfull_lostpages":"","date":"2015-03-31T00:00:00","notfull":"","additional_info":"","url":"http://static.declarations.com.ua/declarations/chosen_ones/judges_batch/3708_kydysiuk_roman_anatoliiovych.pdf"},"liabilities":{"54":{"sum_foreign_comment":"","sum":"14780","sum_comment":"","sum_comment_unclear":false,"sum_comment_hidden":false,"sum_unclear":false,"sum_foreign":""},"55":{"sum_foreign_comment":"","sum":"","sum_comment":"","sum_foreign":""},"56":{"sum_foreign_comment":"","sum":"","sum_comment":"","sum_unclear":false,"sum_foreign":""},"57":{"sum_foreign_comment":"","sum":"","sum_comment":"","sum_hidden":false,"sum_unclear":false,"sum_foreign":""},"58":{"sum_foreign_comment":"","sum":"","sum_comment":"","sum_hidden":false,"sum_unclear":false,"sum_foreign":""},"59":{"sum_foreign_comment":"","sum":"","sum_comment":"","sum_foreign":""},"60":{"sum_foreign_comment":"","sum_comment_hidden":false,"sum":"","sum_comment":"","sum_foreign":""},"61":{"sum_foreign_comment":"","sum":"","sum_comment":"","sum_foreign":""},"62":{"sum_foreign_comment":"","sum":"","sum_hidden":false,"sum_comment":"","sum_foreign":""},"63":{"sum_foreign_comment":"","sum_comment_hidden":false,"sum":"","sum_comment":"","sum_foreign":""},"64":{"sum_foreign_comment":"","sum":"","sum_comment":"","sum_unclear":false,"sum_foreign":""}},"ft_src":"14780\nсуддя господарського суду львівської області\nЛьвівська область\nГосподарський місцевий суд\nРоман\nКидисюк Х. М\nПодружжя\nАнатолійович\nКидисюк Роман Анатолійович\nРоман Анатолійович Кидисюк\nРоман Кидисюк\nКидисюк Роман Анатолійович\nКидисюк Роман Анатолійович\nКидисюк\n1968 куб. см., 103 кВт\nVolkswagen Passat\n2012\n27404\n80000\n2014\n1968 куб. см., 103 кВт\nVolkswagen Passat\n2012\n80000\n27404\n2014\nКидисюк Роман Анатолійович\nРоман Анатолійович Кидисюк\nРоман Кидисюк\nКидисюк Роман Анатолійович\nКидисюк Роман Анатолійович\nПодружжя\nКидисюк Х. М\nРоман\nКидисюк\nГосподарський місцевий суд\nЛьвівська область\nсуддя господарського суду львівської області\nАнатолійович\n14780\n320\n181283\n87914\n196283\n92262\n15000\n4028\n78.2\n14780\n78.2\nКидисюк Х. М\nПодружжя\nАнатолійович\nКидисюк\nРоман\nКидисюк Роман Анатолійович\nРоман Анатолійович Кидисюк\nРоман Кидисюк\nКидисюк Роман Анатолійович\nЛьвівська область\nГосподарський місцевий суд\nсуддя господарського суду львівської області\nКидисюк Роман Анатолійович\n87914\n181283\n4028\n15000\n320\n92262\n196283\nVolkswagen Passat\n1968 куб. см., 103 кВт\n2012\n4028\n15000\n196283\n92262\n320\n87914\n181283\n78.2\n80000\n27404\n2014","general":{"inn":"","name":"Роман","last_name":"Кидисюк","family":[{"inn":"","relations":"Подружжя","relations_hidden":false,"inn_hidden":true,"family_name":"Кидисюк Х. М","name_hidden":false,"name_unclear":false}],"inn_hidden":true,"family_raw":"","inn_unclear":false,"post":{"post_unclear":false,"region_unclear":false,"post":"суддя господарського суду львівської області","candidate":"","post_hidden":false,"region":"Львівська область","office":"Господарський місцевий суд","office_unclear":false},"full_name":"Кидисюк Роман Анатолійович","addresses":[{"place_district":"","place_city_hidden":true,"place_city":"","place_city_type_hidden":true,"place_district_hidden":true,"place_city_type":"","place_address_hidden":true,"place_address":"","place_hidden":false,"place":""}],"patronymic":"Анатолійович","patronymic_hidden":false,"full_name_suggest":{"output":"Кидисюк Роман Анатолійович","input":["Кидисюк Роман Анатолійович","Роман Анатолійович Кидисюк","Роман Кидисюк"]}},"source":"VULYK","estate":{"25":[{"region_unclear":false,"space_unclear":false,"costs":"","costs_comment":"","address_hidden":true,"region_hidden":true,"space_comment":"","space_hidden":false,"space":"78.2","address":"","region":"","address_unclear":false,"costs_rent_comment":"","costs_rent_hidden":false,"space_comment_unclear":false,"costs_rent_comment_hidden":false,"space_units":"м²","costs_rent":""}]},"intro":{"declaration_year":"2014","isnotdeclaration":""}}