{"income":{"5":{"value":"239987","comment_hidden":false,"family_comment":"","family":"22945","comment":"","family_comment_hidden":false},"6":{"value":"220353","family_comment":"","comment_hidden":false,"family_hidden":false,"family_unclear":false,"family_comment_hidden":false,"comment":"","family":"22945"},"7":{"value":"","comment_hidden":false,"family_comment_hidden":false,"family_comment":"","source_name":"","family":"","comment":"","source_name_hidden":false},"8":{"family_comment":"","value":"","family":"","comment":""},"9":{"value":"45","family_comment":"","value_unclear":false,"family_unclear":false,"comment_unclear":false,"comment":"","family":""},"10":{"family_comment":"","family_unclear":false,"value":"12617","family":"","comment":""},"11":{"family_comment":"","value":"","family":"","comment":""},"12":{"family_comment":"","value":"","family":"","comment":""},"13":{"family_comment":"","value":"","family":"","comment":""},"14":{"family_comment":"","value":"","family":"","comment":""},"15":{"family_comment":"","value":"3627.23","comment_unclear":false,"family":"","comment":""},"16":{"family_comment":"","value":"","comment_unclear":false,"family":"","comment":""},"17":{"family_comment":"","value":"","family":"","comment":""},"18":{"family_comment":"","value":"","family":"","comment":""},"19":{"family_comment":"","value":"","family":"","comment":""},"20":{"value":"3345","family_comment":"","value_unclear":false,"family_unclear":false,"family_comment_unclear":false,"family_comment_hidden":false,"comment":"","family":""}},"vehicle":{"35":[{"brand_info":"1.8 л","sum_rent_comment":"","brand":"Mitsubishi ASX","sum_comment":"","brand_unclear":false,"year":"2011","sum_hidden":false,"brand_info_unclear":false,"sum":"","sum_rent":""}]},"id":"vulyk_73_144","banks":{"45":[{"sum_foreign_comment":"","sum_units":"UAH","sum_comment":"","sum_comment_unclear":false,"sum_hidden":false,"sum_foreign_units":"UAH","sum_comment_hidden":false,"sum_unclear":false,"sum":"9000","sum_foreign":""}],"46":[{"sum_foreign_comment":"","sum_units":"UAH","sum_comment":"","sum_foreign_units":"UAH","sum":"9000","sum_foreign":""}]},"declaration":{"additional_info_text":"","notfull_lostpages":"","date":"2014-03-24T00:00:00","notfull":"","additional_info":"","url":"http://static.declarations.com.ua/declarations/chosen_ones/judges_batch/1133_kordiuk_halyna_tarasivna.pdf"},"liabilities":{"54":{"sum_foreign_comment":"","sum_foreign_hidden":false,"sum_comment":"","sum_comment_unclear":false,"sum_hidden":false,"sum_comment_hidden":false,"sum_unclear":false,"sum":"7880","sum_foreign":""},"55":{"sum_foreign_comment":"","sum_comment_hidden":false,"sum":"","sum_comment":"","sum_foreign":""},"56":{"sum_foreign_comment":"","sum":"11316","sum_comment":"","sum_comment_unclear":false,"sum_foreign":""},"57":{"sum_foreign_comment":"","sum":"","sum_comment":"","sum_hidden":false,"sum_comment_hidden":false,"sum_unclear":false,"sum_foreign":""},"58":{"sum_foreign_comment":"","sum":"","sum_comment":"","sum_hidden":false,"sum_comment_hidden":false,"sum_foreign":""},"59":{"sum_foreign_comment":"","sum":"","sum_comment":"","sum_comment_unclear":false,"sum_unclear":false,"sum_foreign":""},"60":{"sum_foreign_comment":"","sum":"3200","sum_comment":"","sum_hidden":false,"sum_comment_hidden":false,"sum_unclear":false,"sum_foreign":""},"61":{"sum_foreign_comment":"","sum":"","sum_comment":"","sum_foreign":""},"62":{"sum_foreign_comment":"","sum":"5409","sum_comment":"","sum_foreign":""},"63":{"sum_foreign_comment":"","sum":"","sum_comment":"","sum_hidden":false,"sum_comment_hidden":false,"sum_foreign":""},"64":{"sum_foreign_comment":"","sum":"","sum_comment":"","sum_foreign":""}},"ft_src":"5409\n7880\n11316\n3200\nсуддя львівського апеляційного господарського суду\nЛьвівська область\nАпеляційний господарський суд\nГалина\nКордюк М. М\nПодружжя\nКордюк М. М\nДитина\nТарасівна\nКордюк Галина Тарасівна\nГалина Тарасівна Кордюк\nГалина Кордюк\nКордюк Галина Тарасівна\nКордюк\nКордюк Галина Тарасівна\nMitsubishi ASX\n1.8 л\n2011\nдоговір дарування\n553\n77.16\n96\nприватизація\n71.6\n9000\n9000\n2013\n1.8 л\nMitsubishi ASX\n2011\n2013\nКордюк Галина Тарасівна\nГалина Тарасівна Кордюк\nГалина Кордюк\nКордюк Галина Тарасівна\nГалина\nПодружжя\nКордюк М. М\nДитина\nКордюк М. М\nКордюк Галина Тарасівна\nТарасівна\nАпеляційний господарський суд\nЛьвівська область\nсуддя львівського апеляційного господарського суду\nКордюк\n7880\n3200\n11316\n5409\n22945\n220353\n3345\n3627.23\n239987\n22945\n45\n12617\n553\nдоговір дарування\n77.16\n96\n71.6\nприватизація\n9000\n9000\n11316\n5409\n7880\n3200\n22945\n220353\n3627.23\n45\n12617\n22945\n239987\n3345\nПодружжя\nКордюк М. М\nДитина\nКордюк М. М\nТарасівна\nКордюк\nГалина\nКордюк Галина Тарасівна\nГалина Тарасівна Кордюк\nГалина Кордюк\nКордюк Галина Тарасівна\nЛьвівська область\nАпеляційний господарський суд\nсуддя львівського апеляційного господарського суду\nКордюк Галина Тарасівна\n2011\n1.8 л\nMitsubishi ASX\n3627.23\n45\n12617\n3345\n239987\n22945\n220353\n22945\n96\n77.16\nприватизація\n71.6\nдоговір дарування\n553\n9000\n9000\n2013","general":{"inn":"","name":"Галина","family":[{"inn":"","relations":"Подружжя","inn_unclear":false,"relations_hidden":false,"inn_hidden":true,"relations_other":"","name_hidden":false,"family_name":"Кордюк М. М","name_unclear":false},{"inn":"","relations":"Дитина","inn_unclear":false,"family_name":"Кордюк М. М","inn_hidden":false,"relations_other":"","name_hidden":false,"name_unclear":false}],"patronymic":"Тарасівна","inn_hidden":false,"family_raw":"","last_name":"Кордюк","post":{"post_unclear":false,"region_unclear":false,"post":"суддя львівського апеляційного господарського суду","office":"Апеляційний господарський суд","region":"Львівська область","post_hidden":false,"office_hidden":false,"office_unclear":false,"region_hidden":false},"last_name_unclear":false,"full_name":"Кордюк Галина Тарасівна","addresses":[{"place_district":"","place_city_hidden":true,"place_city":"","place_city_type_hidden":false,"place_district_hidden":false,"place_city_type":"","place_address_hidden":true,"place_address":"","place_hidden":false,"place":""}],"full_name_suggest":{"output":"Кордюк Галина Тарасівна","input":["Кордюк Галина Тарасівна","Галина Тарасівна Кордюк","Галина Кордюк"]},"name_unclear":false},"source":"VULYK","estate":{"23":[{"space_hidden":false,"costs":"","costs_comment":"","costs_hidden":false,"address_hidden":true,"region_hidden":false,"space_comment":"договір дарування","space_unclear":false,"space":"553","address":"","region":"","space_units_unclear":false,"costs_unclear":false,"space_units":"м²","costs_rent":"","costs_rent_comment":""}],"25":[{"space_unclear":false,"costs":"","costs_comment":"","costs_hidden":false,"address_hidden":true,"region_hidden":false,"space_comment":"приватизація","space_hidden":false,"space":"71.6","address":"","region":"","costs_rent_comment":"","space_comment_hidden":false,"space_units":"м²","costs_rent":""}],"30":[{"space_unclear":false,"address_hidden":true,"region_hidden":false,"space_comment":"","space_hidden":false,"space":"77.16","address":"","region":"","costs_property":"","costs_rent_comment":"","space_comment_unclear":false,"space_units":"м²","costs_property_comment":"","costs_rent":""}],"31":[{"space_unclear":false,"address_hidden":true,"region_hidden":false,"space_comment":"","space":"96","address":"","region":"","costs_property":"","costs_rent_comment":"","space_units":"м²","costs_property_comment":"","costs_rent":""}]},"intro":{"declaration_year":"2013"}}