{"income":{"5":{"value":"224523.69","family_unclear":false,"family_hidden":false,"family_comment":"","family":"","comment":""},"6":{"value":"224523.69","family_comment":"","value_unclear":false,"family_hidden":false,"family_unclear":false,"family":"","comment":""},"7":{"value":"","family_hidden":false,"value_hidden":false,"family_comment":"","source_name":"","family":"","comment":"","source_name_hidden":false},"8":{"family_comment":"","value":"","family":"","comment":""},"9":{"family_comment":"","value":"","family":"","comment":""},"10":{"family_comment":"","value":"","value_unclear":false,"family":"","comment":""},"11":{"family_comment":"","value":"","family":"","comment":""},"12":{"family_comment":"","value":"","family":"","comment":""},"13":{"family_comment":"","value":"","family":"","comment":""},"14":{"family_comment":"","value":"","family":"","comment":""},"15":{"family_comment":"","value":"","family":"","comment":""},"16":{"family_comment":"","value":"","family":"","comment":""},"17":{"family_comment":"","value":"","family":"","comment":""},"18":{"family_comment":"","value":"","family":"","comment":""},"19":{"family_comment":"","value":"","family":"","comment":""},"20":{"value":"","family_comment":"","value_unclear":false,"family_unclear":false,"comment_unclear":false,"comment":"","family":""}},"id":"vulyk_74_174","declaration":{"additional_info_text":"","notfull_lostpages":"","date":"2014-03-28T00:00:00","notfull":"","additional_info":"","url":"http://static.declarations.com.ua/declarations/chosen_ones/judges_batch/1519_kostenko_tetiana_mykolaivna.pdf"},"liabilities":{"54":{"sum_foreign_comment":"","sum":"","sum_comment":"","sum_comment_unclear":false,"sum_comment_hidden":false,"sum_foreign":""},"55":{"sum_foreign_comment":"","sum":"","sum_comment":"","sum_hidden":false,"sum_unclear":false,"sum_foreign":""},"56":{"sum_foreign_comment":"","sum":"","sum_comment":"","sum_hidden":false,"sum_unclear":false,"sum_foreign":""},"57":{"sum_foreign_comment":"","sum":"","sum_comment":"","sum_comment_unclear":false,"sum_comment_hidden":false,"sum_foreign":""},"58":{"sum_foreign_comment":"","sum_comment_hidden":false,"sum":"","sum_comment":"","sum_foreign":""},"59":{"sum_foreign_comment":"","sum":"","sum_comment":"","sum_foreign":""},"60":{"sum_foreign_comment":"","sum":"","sum_hidden":false,"sum_comment":"","sum_foreign":""},"61":{"sum_foreign_comment":"","sum":"","sum_comment":"","sum_foreign":""},"62":{"sum_foreign_comment":"","sum":"","sum_comment":"","sum_foreign":""},"63":{"sum_foreign_comment":"","sum":"","sum_comment":"","sum_comment_unclear":false,"sum_unclear":false,"sum_foreign":""},"64":{"sum_foreign_comment":"","sum":"","sum_comment":"","sum_comment_unclear":false,"sum_unclear":false,"sum_foreign":""}},"ft_src":"Миколаївна\nКостенко Тетяна Миколаївна\nсуддя апеляційного суду харківської області\nХарківська область\nЗагальний апеляційний суд\nТетяна\nКостенко Тетяна Миколаївна\nТетяна Миколаївна Костенко\nТетяна Костенко\nКостенко Тетяна Миколаївна\nКостенко\n224523.69\n224523.69\n619\n67.1\n2013\n224523.69\n224523.69\n224523.69\n224523.69\nЗагальний апеляційний суд\nХарківська область\nсуддя апеляційного суду харківської області\nМиколаївна\nКостенко Тетяна Миколаївна\nТетяна Миколаївна Костенко\nТетяна Костенко\nКостенко Тетяна Миколаївна\nТетяна\nКостенко Тетяна Миколаївна\nКостенко\n619\n67.1\n2013\nМиколаївна\nКостенко\nХарківська область\nЗагальний апеляційний суд\nсуддя апеляційного суду харківської області\nКостенко Тетяна Миколаївна\nКостенко Тетяна Миколаївна\nТетяна Миколаївна Костенко\nТетяна Костенко\nКостенко Тетяна Миколаївна\nТетяна\n67.1\n619\n2013","general":{"inn":"","inn_hidden":true,"last_name":"Костенко","post":{"region_unclear":false,"region":"Харківська область","post":"суддя апеляційного суду харківської області","office":"Загальний апеляційний суд","office_unclear":false,"post_hidden":false},"name":"Тетяна","full_name":"Костенко Тетяна Миколаївна","family_raw":"","addresses":[{"place_district":"","place_city_hidden":true,"place_city":"","place_city_type_hidden":false,"place_district_hidden":false,"place_city_type":"","place_address_hidden":true,"place_address":"","place_hidden":true,"place":""}],"full_name_suggest":{"output":"Костенко Тетяна Миколаївна","input":["Костенко Тетяна Миколаївна","Тетяна Миколаївна Костенко","Тетяна Костенко"]},"patronymic":"Миколаївна"},"source":"VULYK","estate":{"23":[{"space_hidden":false,"costs":"","costs_comment":"","address_hidden":false,"region_hidden":true,"space_comment":"","space_unclear":false,"space":"619","address":"","region":"","space_units_unclear":false,"space_comment_unclear":false,"space_units":"м²","costs_rent":"","costs_rent_comment":""}],"25":[{"space_hidden":false,"costs":"","costs_comment":"","address_hidden":false,"region_hidden":true,"space_comment":"","space_unclear":false,"space":"67.1","address":"","region":"","costs_rent_comment":"","space_units":"м²","costs_rent":""}]},"intro":{"declaration_year":"2013","isnotdeclaration":"","declaration_year_unclear":false}}