{"income":{"5":{"value":"225874.64","family_comment":"","value_unclear":false,"family":"276276","family_unclear":false,"comment_unclear":false,"comment":"","family_comment_unclear":false},"6":{"value":"225874.64","family_comment":"","value_unclear":false,"family_unclear":false,"family":"276276","comment":""},"7":{"source_name_unclear":false,"value":"","value_unclear":false,"family_comment":"","source_name":"","family":"","comment":"","source_name_hidden":false},"8":{"family_comment":"","value":"","family":"","comment":""},"9":{"family_comment":"","value":"","family":"","comment":""},"10":{"family_comment":"","value":"","value_unclear":false,"family":"","comment":""},"11":{"value":"","value_unclear":false,"value_hidden":false,"family_comment":"","family":"","comment":""},"12":{"family_comment":"","value":"","family":"","comment":"","value_hidden":false},"13":{"family_comment":"","value":"","family":"","comment":""},"14":{"family_comment":"","value":"","family":"","comment":""},"15":{"family_comment":"","value":"","family":"","comment":""},"16":{"family_comment":"","value":"","family":"","comment":""},"17":{"family_comment":"","value":"","family":"","comment":""},"18":{"family_comment":"","value":"","family":"","comment":""},"19":{"family_comment":"","family_unclear":false,"value":"","family":"","comment":""},"20":{"family_comment":"","family_unclear":false,"value":"","family":"","comment":""}},"vehicle":{"40":[{"brand_info":"2000 куб. см.","sum":"","brand":"Toyota Rav 4","sum_comment":"","brand_unclear":false,"year":"2007","brand_hidden":false,"brand_info_hidden":false,"brand_info_unclear":false,"sum_rent_comment":"","sum_rent":""}]},"id":"vulyk_61_146","declaration":{"additional_info_text":"","notfull_lostpages":"","date":"2015-02-27T00:00:00","notfull":"","additional_info":"","url":"http://static.declarations.com.ua/declarations/chosen_ones/mega_batch/lutsenko_liudmyla_volodymyrivna.pdf"},"liabilities":{"54":{"sum_foreign_comment":"","sum":"","sum_comment":"","sum_comment_unclear":false,"sum_unclear":false,"sum_foreign":""},"55":{"sum_foreign_comment":"","sum":"","sum_comment":"","sum_foreign":""},"56":{"sum_foreign_comment":"","sum":"25000","sum_comment":"","sum_unclear":false,"sum_foreign":""},"57":{"sum_foreign_comment":"","sum":"","sum_comment":"","sum_comment_hidden":false,"sum_unclear":false,"sum_foreign":""},"58":{"sum_foreign_comment":"","sum":"","sum_comment":"","sum_unclear":false,"sum_foreign":""},"59":{"sum_foreign_comment":"","sum":"15000","sum_comment":"","sum_foreign":""},"60":{"sum_foreign_comment":"","sum_foreign_hidden":false,"sum_comment":"","sum_hidden":false,"sum":"","sum_foreign":""},"61":{"sum_foreign_comment":"","sum":"","sum_comment":"","sum_foreign":""},"62":{"sum_foreign_comment":"","sum":"20000","sum_comment":"","sum_unclear":false,"sum_foreign":""},"63":{"sum_foreign_comment":"","sum":"","sum_comment":"","sum_hidden":false,"sum_unclear":false,"sum_foreign":""},"64":{"sum_foreign_comment":"","sum":"","sum_hidden":false,"sum_comment":"","sum_foreign":""}},"ft_src":"15000\n20000\n25000\nсуддя вінницького міського суду вінницької області\nВінницька область\nЗагальний місцевий суд\nЛюдмила\nЛуценко В. В\nПодружжя\nЛуценко О. В\nДитина\nЛуценко В. В\nДитина\nПлахотнюк Р. П\nБатьки\nВолодимирівна\nЛуценко\nЛуценко Людмила Володимирівна\nЛуценко Людмила Володимирівна\nЛюдмила Володимирівна Луценко\nЛюдмила Луценко\nЛуценко Людмила Володимирівна\nToyota Rav 4\n2000 куб. см.\n2007\n65\n20\nспадщина\n.6417\nдоговір дарування\n61.3\n2014\n276276\n225874.64\n276276\n225874.64\n2000 куб. см.\n2007\nToyota Rav 4\n.6417\nспадщина\n20\n61.3\nдоговір дарування\n65\nПодружжя\nЛуценко В. В\nДитина\nЛуценко О. В\nДитина\nЛуценко В. В\nБатьки\nПлахотнюк Р. П\nЛуценко Людмила Володимирівна\nЛюдмила Володимирівна Луценко\nЛюдмила Луценко\nЛуценко Людмила Володимирівна\nЛюдмила\nЛуценко Людмила Володимирівна\nЛуценко\nВінницька область\nЗагальний місцевий суд\nсуддя вінницького міського суду вінницької області\nВолодимирівна\n15000\n25000\n20000\n276276\n225874.64\n225874.64\n276276\n2014\n25000\n20000\n15000\nЛуценко В. В\nПодружжя\nЛуценко О. В\nДитина\nЛуценко В. В\nДитина\nПлахотнюк Р. П\nБатьки\nВолодимирівна\nЛуценко\nЛуценко Людмила Володимирівна\nЛюдмила Володимирівна Луценко\nЛюдмила Луценко\nЛуценко Людмила Володимирівна\nВінницька область\nсуддя вінницького міського суду вінницької області\nЗагальний місцевий суд\nЛуценко Людмила Володимирівна\nЛюдмила\nToyota Rav 4\n2000 куб. см.\n2007\n225874.64\n276276\n225874.64\n276276\n65\n.6417\nспадщина\n20\nдоговір дарування\n61.3\n2014","general":{"inn":"","name":"Людмила","patronymic_unclear":false,"family":[{"inn":"","inn_hidden":true,"relations_unclear":false,"relations_hidden":false,"relations_other":"","relations":"Подружжя","name_hidden":false,"family_name":"Луценко В. В","name_unclear":false},{"inn":"","relations":"Дитина","relations_other":"","inn_hidden":false,"family_name":"Луценко О. В","name_hidden":false,"name_unclear":false},{"inn":"","relations":"Дитина","relations_other":"","inn_hidden":false,"family_name":"Луценко В. В","name_hidden":false,"name_unclear":false},{"inn":"","relations":"Батьки","relations_other":"","inn_hidden":false,"family_name":"Плахотнюк Р. П","name_hidden":false,"name_unclear":false}],"patronymic":"Володимирівна","inn_hidden":true,"family_raw":"","inn_unclear":false,"post":{"post_unclear":false,"region_unclear":false,"post":"суддя вінницького міського суду вінницької області","office":"Загальний місцевий суд","region":"Вінницька область","post_hidden":false,"office_hidden":false,"region_hidden":false},"last_name_unclear":false,"full_name":"Луценко Людмила Володимирівна","addresses":[{"place_address":"","place_district_hidden":true,"place_city_type":"","place_city_hidden":true,"place_address_unclear":false,"place_city_type_hidden":true,"place_hidden":true,"place":"","place_district":"","place_address_hidden":true,"place_city":"","place_district_unclear":false}],"last_name":"Луценко","patronymic_hidden":false,"full_name_suggest":{"output":"Луценко Людмила Володимирівна","input":["Луценко Людмила Володимирівна","Людмила Володимирівна Луценко","Людмила Луценко"]},"name_unclear":false},"source":"VULYK","estate":{"23":[{"region_unclear":false,"space_unclear":false,"costs":"","costs_comment":"","address_hidden":true,"region_hidden":true,"space_comment":"спадщина","space":".6417","address":"","region":"","address_unclear":false,"costs_rent_comment":"","space_comment_unclear":false,"space_units":"га","space_units_unclear":false,"costs_rent":""}],"26":[{"space_hidden":false,"costs":"","costs_comment":"","address_hidden":true,"region_hidden":true,"space_comment":"договір дарування","space":"61.3","address":"","region":"","costs_rent_comment":"","space_units":"м²","costs_rent":""}],"31":[{"space_unclear":false,"address_hidden":true,"region_hidden":true,"space_comment":"","space_hidden":false,"space":"65","address":"","region":"","costs_property":"","costs_rent_comment":"","space_comment_unclear":false,"space_units":"м²","costs_property_comment":"","costs_rent":""}],"33":[{"space_unclear":false,"address_hidden":true,"region_hidden":true,"space_comment":"","space":"20","address":"","region":"","costs_property":"","costs_rent_comment":"","space_units":"м²","costs_property_comment":"","costs_rent":""}]},"intro":{"declaration_year":"2014","isnotdeclaration":"","declaration_year_hidden":false}}