{"income":{"5":{"family_comment":"","value":"194907","family":"","comment":""},"6":{"family_comment":"","value":"186137","family":"","comment":""},"7":{"value":"367","comment_hidden":false,"family_comment":"","source_name":"","family":"","comment":"","source_name_hidden":false},"8":{"family_comment":"","value":"","family":"","comment":"","family_hidden":false},"9":{"value":"3","family_comment":"","value_unclear":false,"family_unclear":false,"family":"","comment":""},"10":{"family_comment":"","value":"","family":"","comment":""},"11":{"family_comment":"","value":"","family":"","comment":""},"12":{"family_comment":"","value":"","family":"","comment":""},"13":{"family_comment":"","value":"8400","family":"","comment":""},"14":{"family_comment":"","value":"","family":"","comment":""},"15":{"family_comment":"","value":"","family":"","comment":""},"16":{"family_comment":"","value":"","family":"","comment":""},"17":{"family_comment":"","value":"","family":"","comment":""},"18":{"family_comment":"","value":"","family":"","comment":""},"19":{"family_comment":"","value":"","family":"","comment":""},"20":{"value":"","value_unclear":false,"family_hidden":false,"family_comment":"","family":"","comment":""}},"vehicle":{"35":[{"brand_info":"FL, 1.4, Stile AT","sum_rent_comment":"","year":"2013","brand_info_hidden":false,"brand_info_unclear":false,"year_unclear":false,"sum_rent":"","sum":"","brand":"Hyundai i20","sum_comment":"","brand_unclear":false,"brand_hidden":false,"sum_comment_unclear":false}]},"id":"vulyk_109_68","declaration":{"additional_info_text":"","notfull_lostpages":"","date":"2016-03-30T00:00:00","notfull":"","additional_info":"","url":"http://static.declarations.com.ua/declarations/chosen_ones/judges_batch/2525_soloviova_anastasiia_ievhenivna_2015.pdf"},"liabilities":{"54":{"sum_foreign_comment":"","sum":"10920","sum_comment":"","sum_hidden":false,"sum_comment_hidden":false,"sum_unclear":false,"sum_foreign":""},"55":{"sum_foreign_comment":"","sum":"","sum_comment":"","sum_comment_unclear":false,"sum_foreign":""},"56":{"sum_foreign_comment":"","sum":"","sum_comment":"","sum_foreign":""},"57":{"sum_foreign_comment":"","sum_comment":"ПАТ АБ 'Укргазбанк' відділення у м. Дніпропетровськ","sum":"27565","sum_comment_hidden":false,"sum_foreign":""},"58":{"sum_foreign_comment":"","sum_comment":"","sum":"8435","sum_comment_hidden":false,"sum_foreign":""},"59":{"sum_foreign_comment":"","sum":"","sum_comment":"","sum_foreign":""},"60":{"sum_foreign_comment":"","sum":"","sum_comment":"","sum_foreign":""},"61":{"sum_foreign_comment":"","sum":"","sum_comment":"","sum_foreign":""},"62":{"sum_foreign_comment":"","sum":"","sum_comment":"","sum_foreign":""},"63":{"sum_foreign_comment":"","sum":"","sum_comment":"","sum_foreign":""},"64":{"sum_foreign_comment":"","sum":"","sum_comment":"","sum_foreign":""}},"ft_src":"FL, 1.4, Stile AT\nHyundai i20\n2013\n53.72\n2015\n186137\n8400\n367\n194907\n3\nFL, 1.4, Stile AT\nHyundai i20\n2013\n2015\nСоловйова Анастасія Євгенівна\nАнастасія Євгенівна Соловйова\nАнастасія Соловйова\nСоловйова Анастасія Євгенівна\nАнастасія\nДитина\nПопкова П. О\nСоловйова Анастасія Євгенівна\nЄвгенівна\nГосподарський місцевий суд\nДніпропетровська область\nсуддя господарського суду дніпропетровської області\nСоловйова\n8435\nПАТ АБ 'Укргазбанк' відділення у м. Дніпропетровськ\n27565\n10920\n367\n186137\n8400\n194907\n3\n53.72\n8435\nПАТ АБ 'Укргазбанк' відділення у м. Дніпропетровськ\n27565\n10920\nДитина\nПопкова П. О\nЄвгенівна\nСоловйова\nАнастасія\nСоловйова Анастасія Євгенівна\nАнастасія Євгенівна Соловйова\nАнастасія Соловйова\nСоловйова Анастасія Євгенівна\nДніпропетровська область\nГосподарський місцевий суд\nсуддя господарського суду дніпропетровської області\nСоловйова Анастасія Євгенівна","general":{"name_hidden":false,"name":"Анастасія","inn":"","last_name":"Соловйова","family":[{"inn":"","relations":"Дитина","relations_hidden":false,"inn_hidden":true,"family_name":"Попкова П. О","relations_other":"","name_hidden":true,"name_unclear":false}],"inn_hidden":true,"family_raw":"","inn_unclear":false,"post":{"region_unclear":false,"region":"Дніпропетровська область","post":"суддя господарського суду дніпропетровської області","region_hidden":false,"office":"Господарський місцевий суд","office_hidden":false,"office_unclear":false},"full_name":"Соловйова Анастасія Євгенівна","addresses":[{"place_district":"","place_address_hidden":true,"place_city":"","place_address":"","place_district_hidden":true,"place_city_type":"","place_city_hidden":true,"place_city_type_hidden":true,"place_hidden":false,"place":""}],"patronymic":"Євгенівна","full_name_suggest":{"output":"Соловйова Анастасія Євгенівна","input":["Соловйова Анастасія Євгенівна","Анастасія Євгенівна Соловйова","Анастасія Соловйова"]}},"source":"VULYK","estate":{"25":[{"space_unclear":false,"costs":"","costs_comment":"","address_hidden":false,"region_hidden":true,"space_comment":"","space_hidden":false,"space":"53.72","space_units_hidden":false,"region":"","costs_rent_comment":"","space_units":"м²","address":"","costs_rent":""}]},"intro":{"declaration_year":"2015","isnotdeclaration":""}}