{"income":{"5":{"value":"21048","family_comment":"","value_unclear":false,"comment_hidden":false,"family_hidden":false,"value_hidden":false,"family_unclear":false,"family_comment_hidden":false,"comment":"","family":"219153"},"6":{"value":"","family_comment":"","value_unclear":false,"family_hidden":false,"family_unclear":false,"family":"199524","comment":""},"7":{"source_name_unclear":false,"value":"","family_hidden":false,"family_comment":"","source_name":"","family":"","comment":"","source_name_hidden":false},"8":{"family_comment":"","value":"","family":"","comment":""},"9":{"value":"","value_unclear":false,"family_hidden":false,"family_comment":"","family":"","comment":""},"10":{"value":"","value_unclear":false,"family_hidden":false,"value_hidden":false,"family_comment":"","comment_unclear":false,"comment":"","family":""},"11":{"family_comment":"","value":"","family":"","comment":""},"12":{"family_comment":"","value":"","family":"","comment":""},"13":{"family_comment":"","value":"","family":"","comment":""},"14":{"family_comment":"","value":"","family":"","comment":""},"15":{"family_comment":"","value":"","family_hidden":false,"comment":"","family":""},"16":{"value":"","value_unclear":false,"family_hidden":false,"family_comment":"","family":"","comment":""},"17":{"family_comment":"","value":"","family_hidden":false,"comment":"","family":""},"18":{"family_comment":"","value":"","value_unclear":false,"family":"","comment":""},"19":{"family_comment":"","value":"","family":"","comment":""},"20":{"value":"","family_comment":"","value_unclear":false,"family_hidden":false,"family_unclear":false,"comment_unclear":false,"comment":"","family":"19629"}},"vehicle":{"40":[{"year_hidden":false,"brand_info":"1368 куб. см., 95 к.с., 70 кВт , 439 см","sum_rent_comment":"","year":"2013","brand_info_hidden":false,"brand_info_unclear":false,"year_unclear":false,"sum_rent":"","sum":"","brand":"Fiat Nuovo Doblo Panorama","sum_comment":"","brand_unclear":false,"brand_hidden":false}]},"id":"vulyk_72_154","declaration":{"additional_info_text":"","notfull_lostpages":"","date":"2015-03-12T00:00:00","notfull":"","additional_info":"","url":"http://static.declarations.com.ua/declarations/chosen_ones/epic_batch/shumko_alina_volodymyrivna.pdf"},"liabilities":{"54":{"sum_foreign_comment":"","sum":"","sum_comment":"","sum_comment_hidden":false,"sum_unclear":false,"sum_foreign":""},"55":{"sum_foreign_comment":"","sum":"","sum_comment":"","sum_foreign":""},"56":{"sum_foreign_comment":"","sum":"","sum_hidden":false,"sum_comment":"","sum_foreign":""},"57":{"sum_foreign_comment":"","sum":"","sum_comment":"","sum_comment_unclear":false,"sum_hidden":false,"sum_comment_hidden":false,"sum_unclear":false,"sum_foreign":""},"58":{"sum_foreign_comment":"","sum":"","sum_comment":"","sum_comment_unclear":false,"sum_hidden":false,"sum_comment_hidden":false,"sum_unclear":false,"sum_foreign":""},"59":{"sum_foreign_comment":"","sum_foreign_hidden":false,"sum_comment":"","sum_foreign_unclear":false,"sum_comment_hidden":false,"sum":"","sum_foreign":""},"60":{"sum_foreign_comment":"","sum_foreign_hidden":false,"sum_comment":"","sum_hidden":false,"sum":"","sum_foreign":""},"61":{"sum_foreign_comment":"","sum_foreign_hidden":false,"sum_comment":"","sum_hidden":false,"sum":"","sum_foreign":""},"62":{"sum_foreign_comment":"","sum_foreign_hidden":false,"sum_comment":"","sum_hidden":false,"sum":"","sum_foreign":""},"63":{"sum_foreign_comment":"","sum_foreign_hidden":false,"sum_comment":"","sum_comment_unclear":false,"sum_hidden":false,"sum_comment_hidden":false,"sum_unclear":false,"sum":"","sum_foreign":""},"64":{"sum_foreign_comment":"","sum_foreign_hidden":false,"sum_comment":"","sum_hidden":false,"sum":"","sum_foreign":""}},"ft_src":"Київ\n02222\nм. Київ\nсуддя голосіївського районного суду м. києва\nм. Київ\nЗагальний місцевий суд\nАліна\nШумко Г. В\nПодружжя\nШумко І. Г\nДитина\nШумко І. Г\nДитина\nМатвєєв С. С\nДитина\nВолодимирівна\nШумко\nШумко Аліна Володимирівна\nШумко Аліна Володимирівна\nАліна Володимирівна Шумко\nАліна Шумко\nШумко Аліна Володимирівна\n1368 куб. см., 95 к.с., 70 кВт , 439 см\nFiat Nuovo Doblo Panorama\n2013\nЧеркаська область\nм. Черкаси, вул. Котовського, АК 'Переможець'\n21\nм. Київ\nвул. Градинська\n102.5\nЧеркаська область\nм. Черкаси, вул. Рябоконя, ділянка СГК 'Надія'\n1161\n48.2\nвул. Автозаводська\nм. Київ\n2014\n199524\n219153\n21048\n19629\n1368 куб. см., 95 к.с., 70 кВт , 439 см\nFiat Nuovo Doblo Panorama\n2013\n21\nЧеркаська область\nм. Черкаси, вул. Котовського, АК 'Переможець'\nм. Київ\nвул. Градинська\n102.5\nвул. Автозаводська\n48.2\nм. Київ\nм. Черкаси, вул. Рябоконя, ділянка СГК 'Надія'\nЧеркаська область\n1161\nПодружжя\nШумко Г. В\nДитина\nШумко І. Г\nДитина\nШумко І. Г\nДитина\nМатвєєв С. С\nШумко Аліна Володимирівна\nАліна Володимирівна Шумко\nАліна Шумко\nШумко Аліна Володимирівна\nАліна\nШумко Аліна Володимирівна\nШумко\nм. Київ\nЗагальний місцевий суд\nсуддя голосіївського районного суду м. києва\nВолодимирівна\nКиїв\n02222\nм. Київ\n199524\n19629\n21048\n219153\n2014\nШумко Г. В\nПодружжя\nШумко І. Г\nДитина\nШумко І. Г\nДитина\nМатвєєв С. С\nДитина\nВолодимирівна\nШумко\nШумко Аліна Володимирівна\nАліна Володимирівна Шумко\nАліна Шумко\nШумко Аліна Володимирівна\nм. Київ\nКиїв\n02222\nм. Київ\nЗагальний місцевий суд\nсуддя голосіївського районного суду м. києва\nШумко Аліна Володимирівна\nАліна\nFiat Nuovo Doblo Panorama\n1368 куб. см., 95 к.с., 70 кВт , 439 см\n2013\n19629\n21048\n219153\n199524\nм. Київ\nвул. Градинська\n102.5\n48.2\nвул. Автозаводська\nм. Київ\nм. Черкаси, вул. Котовського, АК 'Переможець'\nЧеркаська область\n21\nм. Черкаси, вул. Рябоконя, ділянка СГК 'Надія'\nЧеркаська область\n1161\n2014","general":{"inn":"","name":"Аліна","patronymic_unclear":false,"family":[{"inn":"","inn_hidden":true,"relations_unclear":false,"relations_hidden":false,"relations_other":"","relations":"Подружжя","name_hidden":false,"inn_unclear":false,"family_name":"Шумко Г. В","name_unclear":false},{"inn":"","inn_hidden":false,"relations_hidden":false,"family_name":"Шумко І. Г","relations_other":"","relations":"Дитина","name_hidden":false,"name_unclear":false},{"inn":"","inn_hidden":false,"relations_hidden":false,"family_name":"Шумко І. Г","relations_other":"","relations":"Дитина","name_hidden":false,"name_unclear":false},{"inn":"","relations":"Дитина","relations_other":"","inn_hidden":false,"family_name":"Матвєєв С. С","name_hidden":false}],"patronymic":"Володимирівна","inn_hidden":true,"family_raw":"","inn_unclear":false,"post":{"post_unclear":false,"region_unclear":false,"post":"суддя голосіївського районного суду м. києва","candidate":"","office_hidden":false,"region":"м. Київ","post_hidden":false,"office":"Загальний місцевий суд","office_unclear":false,"region_hidden":false},"last_name_unclear":false,"full_name":"Шумко Аліна Володимирівна","addresses":[{"place_city_type_hidden":false,"place_district_hidden":false,"place_city_type":"Місто","place_city_hidden":false,"place_address_unclear":false,"place_address":"02222","place":"м. Київ","place_district":"","place_unclear":false,"place_city":"Київ","place_city_unclear":false,"place_hidden":false,"place_address_hidden":true,"place_district_unclear":false}],"last_name":"Шумко","patronymic_hidden":false,"full_name_suggest":{"output":"Шумко Аліна Володимирівна","input":["Шумко Аліна Володимирівна","Аліна Володимирівна Шумко","Аліна Шумко"]},"name_unclear":false},"source":"VULYK","estate":{"25":[{"space_unclear":false,"costs":"","costs_rent_unclear":false,"costs_comment":"","costs_hidden":false,"space_hidden":false,"costs_comment_unclear":false,"costs_rent_comment_unclear":false,"region":"м. Київ","space_comment_hidden":false,"space_comment_unclear":false,"costs_rent_comment_hidden":false,"costs_rent":"","costs_comment_hidden":false,"address_hidden":true,"region_hidden":false,"space_comment":"","space":"48.2","address":"вул. Автозаводська","address_unclear":false,"costs_rent_comment":"","costs_rent_hidden":false,"space_units":"м²"}],"29":[{"space_hidden":false,"costs_property_comment":"","address_hidden":true,"region_hidden":false,"space_comment":"","space_unclear":false,"space":"1161","address":"м. Черкаси, вул. Рябоконя, ділянка СГК 'Надія'","region":"Черкаська область","costs_property":"","costs_rent_comment":"","address_unclear":true,"space_units":"м²","space_units_unclear":false,"costs_rent":""}],"31":[{"space_unclear":false,"address_hidden":true,"region_hidden":false,"space_comment":"","space_units_hidden":false,"space_hidden":false,"space":"102.5","address":"вул. Градинська","region":"м. Київ","address_unclear":false,"costs_rent_comment":"","costs_property":"","space_units":"м²","costs_property_comment":"","costs_rent":""}],"33":[{"costs_rent":"","region":"Черкаська область","costs_property":"","costs_rent_comment":"","address_hidden":true,"region_hidden":false,"space_comment":"","costs_property_comment":"","space_units":"м²","space":"21","address":"м. Черкаси, вул. Котовського, АК 'Переможець'"}]},"intro":{"declaration_year":"2014","isnotdeclaration":"","declaration_year_unclear":false}}