{"income":{"5":{"value":"10035","family_comment":"","value_unclear":false,"family_unclear":false,"comment_unclear":false,"comment":"","family":""},"6":{"family_comment":"","value":"","comment_unclear":false,"family":"","comment":""},"7":{"family_comment":"","value":"","source_name":"","family":"","comment":""},"8":{"family_comment":"","value":"","family":"","comment":""},"9":{"family_comment":"","value":"","value_unclear":false,"family":"","comment":""},"10":{"family_comment":"","value":"","value_unclear":false,"family":"","comment":""},"11":{"family_comment":"","value":"","family":"","comment":""},"12":{"family_comment":"","value":"","family":"","comment":""},"13":{"family_comment":"","value":"","family":"","comment":""},"14":{"family_comment":"","value":"","family":"","comment":""},"15":{"family_comment":"","value":"","family":"","comment":""},"16":{"family_comment":"","value":"","family":"","comment":""},"17":{"family_comment":"","value":"","value_unclear":false,"family":"","comment":""},"18":{"family_comment":"","value":"","value_unclear":false,"family":"","comment":""},"19":{"family_comment":"","value":"","family":"","comment":""},"20":{"value":"10035","family_comment":"","value_unclear":false,"family_unclear":false,"comment_unclear":false,"comment":"","family":""}},"vehicle":{"35":[{"year_hidden":false,"brand_info":"","sum_rent_comment":"","year":"2012","sum_hidden":false,"brand_info_hidden":false,"brand_info_unclear":false,"year_unclear":false,"sum_rent":"","sum":"","brand":"Volkswagen Tiguan","sum_comment":"","brand_unclear":false,"brand_hidden":false}]},"id":"vulyk_84_2","declaration":{"additional_info_text":"","notfull_lostpages":"","date":"2015-03-31T00:00:00","notfull":"","additional_info":"","url":"http://static.declarations.com.ua/declarations/chosen_ones/judges_batch/2416_shubochkina_tetiana_viktorivna.pdf"},"liabilities":{"54":{"sum_foreign_comment":"","sum_comment_hidden":false,"sum":"","sum_comment":"","sum_foreign":""},"55":{"sum_foreign_comment":"","sum":"","sum_comment":"","sum_foreign":""},"56":{"sum_foreign_comment":"","sum":"1746","sum_comment":"","sum_foreign":""},"57":{"sum_foreign_comment":"","sum_comment_hidden":false,"sum":"","sum_comment":"","sum_foreign":""},"58":{"sum_foreign_comment":"","sum_comment_hidden":false,"sum":"","sum_comment":"","sum_foreign":""},"59":{"sum_foreign_comment":"","sum":"","sum_comment":"","sum_foreign":""},"60":{"sum_foreign_comment":"","sum":"","sum_comment":"","sum_foreign":""},"61":{"sum_foreign_comment":"","sum":"","sum_comment":"","sum_foreign":""},"62":{"sum_foreign_comment":"","sum":"","sum_comment":"","sum_foreign":""},"63":{"sum_foreign_comment":"","sum_comment_hidden":false,"sum":"","sum_comment":"","sum_foreign":""},"64":{"sum_foreign_comment":"","sum_comment_hidden":false,"sum":"","sum_comment":"","sum_foreign":""}},"ft_src":"1746\nЛуганськ\n91016\nЛуганська область\nсуддя лутугінського районного суду луганської області\nЛуганська область\nЗагальний місцевий суд\nТетяна\nШубочкіна П. О\nДитина\nВікторівна\nШубочкіна Тетяна Вікторівна\nТетяна Вікторівна Шубочкіна\nТетяна Шубочкіна\nШубочкіна Тетяна Вікторівна\nШубочкіна Тетяна Вікторівна\nШубочкіна\nVolkswagen Tiguan\n2012\nЛуганська область\nм. Луганськ\n40\n.0067\nЛуганська область\nм. Луганськ\n59.3\n2014\n10035\n10035\nVolkswagen Tiguan\n2012\n2014\nШубочкіна Тетяна Вікторівна\nТетяна Вікторівна Шубочкіна\nТетяна Шубочкіна\nШубочкіна Тетяна Вікторівна\nТетяна\nДитина\nШубочкіна П. О\nШубочкіна Тетяна Вікторівна\nВікторівна\nсуддя лутугінського районного суду луганської області\nЗагальний місцевий суд\nЛуганська область\nШубочкіна\nЛуганськ\n91016\nЛуганська область\n1746\n10035\n10035\n.0067\n40\nЛуганська область\nм. Луганськ\n59.3\nЛуганська область\nм. Луганськ\n1746\nШубочкіна П. О\nДитина\nВікторівна\nШубочкіна\nТетяна\nШубочкіна Тетяна Вікторівна\nТетяна Вікторівна Шубочкіна\nТетяна Шубочкіна\nШубочкіна Тетяна Вікторівна\nЛуганська область\nЛуганськ\n91016\nЛуганська область\nсуддя лутугінського районного суду луганської області\nЗагальний місцевий суд\nШубочкіна Тетяна Вікторівна\nVolkswagen Tiguan\n2012\n10035\n10035\nм. Луганськ\nЛуганська область\n59.3\n40\nм. Луганськ\nЛуганська область\n.0067\n2014","general":{"inn":"","name":"Тетяна","inn_unclear":false,"family":[{"inn":"","inn_hidden":true,"inn_unclear":false,"relations_hidden":false,"relations_other":"","relations":"Дитина","name_hidden":true,"family_name":"Шубочкіна П. О","name_unclear":false}],"inn_hidden":true,"family_raw":"","last_name":"Шубочкіна","post":{"post_unclear":false,"region_unclear":false,"post":"суддя лутугінського районного суду луганської області","candidate":"","office_hidden":false,"region":"Луганська область","post_hidden":false,"office":"Загальний місцевий суд","office_unclear":false,"region_hidden":false},"full_name":"Шубочкіна Тетяна Вікторівна","addresses":[{"place_city_type_unclear":false,"place_address":"91016","place_district_hidden":true,"place_city_type":"Місто","place_address_hidden":true,"place_address_unclear":false,"place_city_type_hidden":false,"place":"Луганська область","place_district":"","place_unclear":false,"place_city":"Луганськ","place_city_unclear":false,"place_hidden":false,"place_city_hidden":false,"place_district_unclear":false}],"patronymic":"Вікторівна","full_name_suggest":{"output":"Шубочкіна Тетяна Вікторівна","input":["Шубочкіна Тетяна Вікторівна","Тетяна Вікторівна Шубочкіна","Тетяна Шубочкіна"]}},"source":"VULYK","estate":{"23":[{"region_unclear":false,"costs":"","costs_comment":"","address_hidden":true,"region_hidden":false,"space_comment":"","space":".0067","address":"м. Луганськ","region":"Луганська область","address_unclear":false,"costs_rent_comment":"","space_comment_unclear":false,"space_units":"га","costs_rent":"40"}],"25":[{"region_unclear":false,"space_hidden":false,"costs":"","costs_comment":"","address_hidden":true,"region_hidden":false,"space_comment":"","space":"59.3","address":"м. Луганськ","costs_comment_unclear":false,"costs_rent_comment_unclear":false,"region":"Луганська область","address_unclear":false,"costs_rent_comment":"","space_units":"м²","costs_rent":""}]},"intro":{"declaration_year":"2014","isnotdeclaration":"","declaration_year_unclear":false}}