{"income":{"5":{"value":"456716.33","family_comment":"","value_unclear":false,"family_hidden":false,"value_hidden":false,"family_unclear":false,"family":"16675.39","comment":""},"6":{"value":"205314.86","family_comment":"","value_unclear":false,"family_unclear":false,"family":"16675.39","comment":""},"7":{"source_name_unclear":false,"value":"2749.85","comment_hidden":false,"family_comment":"","source_name":"Національна школа суддів України, Львівська комерційна академія","family":"","comment":"","source_name_hidden":false},"8":{"family_comment":"","value":"","family":"","comment":""},"9":{"value":"21484.05","family_comment":"","value_unclear":false,"family_hidden":false,"family_unclear":false,"family":"","comment":"","family_comment_unclear":false},"10":{"family_comment":"","value":"","family":"","comment":""},"11":{"family_comment":"","value":"1792.57","family":"","comment":""},"12":{"family_comment":"","value":"","family":"","comment":""},"13":{"family_comment":"","value":"","family":"","comment":""},"14":{"family_comment":"","value":"","family":"","comment":""},"15":{"family_comment":"","value":"","family":"","comment":""},"16":{"family_comment":"","value":"225375","family":"","comment":""},"17":{"family_comment":"","value":"","family":"","comment":""},"18":{"family_comment":"","value":"","family":"","comment":""},"19":{"family_comment":"","value":"","family":"","comment":""},"20":{"value":"","family_comment":"","value_unclear":false,"family_comment_hidden":false,"family_unclear":false,"family_comment_unclear":false,"comment_unclear":false,"comment":"","family":""}},"vehicle":{"35":[{"year_hidden":false,"brand_info":"2500 куб. см.","sum_rent_comment":"","year":"2009","brand_info_hidden":false,"brand_info_unclear":false,"sum_rent":"","sum":"","brand":"Subaru Forester","sum_comment":"","brand_unclear":false,"brand_hidden":false}],"40":[{"brand_info":"2000 куб. см.","sum_rent_comment":"","brand":"Nissan Qashqai","sum_comment":"","year":"2008","brand_info_unclear":false,"sum":"","sum_rent":""}]},"id":"vulyk_93_44","banks":{"45":[{"sum_units":"UAH","sum_foreign":"","sum_hidden":false,"sum":"292265","sum_units_hidden":true,"sum_foreign_comment":"","sum_foreign_hidden":false,"sum_comment":"","sum_comment_unclear":false,"sum_foreign_units":"UAH","sum_units_unclear":false,"sum_comment_hidden":false,"sum_unclear":false}],"46":[{"sum_foreign_comment":"","sum":"212265","sum_comment":"","sum_hidden":false,"sum_foreign_units":"UAH","sum_foreign_hidden":false,"sum_units":"UAH","sum_comment_hidden":false,"sum_units_hidden":true,"sum_foreign":""}]},"declaration":{"additional_info_text":"","notfull_lostpages":"","date":"2015-03-31T00:00:00","notfull":"","additional_info":"","url":"http://static.declarations.com.ua/declarations/chosen_ones/judges_batch/3490_komornyi_oleksandr_ihorovych.pdf"},"liabilities":{"54":{"sum_foreign_comment":"","sum":"120","sum_hidden":false,"sum_comment":"","sum_foreign":""},"55":{"sum_foreign_comment":"","sum":"","sum_comment":"","sum_foreign":""},"56":{"sum_foreign_comment":"","sum":"12000","sum_comment":"","sum_foreign":""},"57":{"sum_foreign_comment":"","sum":"","sum_comment":"","sum_hidden":false,"sum_comment_hidden":false,"sum_unclear":false,"sum_foreign":""},"58":{"sum_foreign_comment":"","sum":"","sum_comment":"","sum_comment_unclear":false,"sum_hidden":false,"sum_unclear":false,"sum_foreign":""},"59":{"sum_foreign_comment":"","sum":"","sum_comment":"","sum_foreign":""},"60":{"sum_foreign_comment":"","sum":"","sum_hidden":false,"sum_comment":"","sum_foreign":""},"61":{"sum_foreign_comment":"","sum":"","sum_comment":"","sum_foreign":""},"62":{"sum_foreign_comment":"","sum":"11000","sum_comment":"","sum_foreign":""},"63":{"sum_foreign_comment":"","sum":"","sum_comment":"","sum_foreign":""},"64":{"sum_foreign_comment":"","sum":"","sum_comment":"","sum_foreign":""}},"ft_src":"11000\n120\n12000\nКоморний Олександр Ігорович\nсуддя львівського окружного адміністративного суду\nЛьвівська область\nАдміністративний місцевий суд\nОлександр\nКоморна Л. М\nПодружжя\nКоморний О. О\nДитина\nКоморний Олександр Ігорович\nОлександр Ігорович Коморний\nОлександр Коморний\nКоморний Олександр Ігорович\nКоморний\nІгорович\n2500 куб. см.\nSubaru Forester\n2009\n2000 куб. см.\n2008\nNissan Qashqai\n1/6 спільна власність\n89.8\n2/6 спільна власність\n89.8\n190.6\n.1175\n104\n212265\n292265\n2014\n2500 куб. см.\nSubaru Forester\n2009\n2000 куб. см.\nNissan Qashqai\n2008\n.1175\n190.6\n89.8\n2/6 спільна власність\n89.8\n1/6 спільна власність\n104\nКоморний\nПодружжя\nКоморна Л. М\nДитина\nКоморний О. О\nКоморний Олександр Ігорович\nОлександр Ігорович Коморний\nОлександр Коморний\nКоморний Олександр Ігорович\nКоморний Олександр Ігорович\nОлександр\nІгорович\nЛьвівська область\nАдміністративний місцевий суд\nсуддя львівського окружного адміністративного суду\n120\n12000\n11000\n2749.85\nНаціональна школа суддів України, Львівська комерційна академія\n16675.39\n205314.86\n456716.33\n16675.39\n225375\n21484.05\n1792.57\n292265\n212265\n2014\n120\n12000\n11000\n16675.39\n205314.86\n21484.05\n1792.57\nНаціональна школа суддів України, Львівська комерційна академія\n2749.85\n16675.39\n456716.33\n225375\nПодружжя\nКоморна Л. М\nДитина\nКоморний О. О\nКоморний\nІгорович\nЛьвівська область\nАдміністративний місцевий суд\nсуддя львівського окружного адміністративного суду\nКоморний Олександр Ігорович\nКоморний Олександр Ігорович\nОлександр Ігорович Коморний\nОлександр Коморний\nКоморний Олександр Ігорович\nОлександр\nSubaru Forester\n2500 куб. см.\n2009\n2008\n2000 куб. см.\nNissan Qashqai\n1792.57\n21484.05\n456716.33\n16675.39\n225375\n2749.85\nНаціональна школа суддів України, Львівська комерційна академія\n205314.86\n16675.39\n2/6 спільна власність\n89.8\n190.6\n1/6 спільна власність\n89.8\n104\n.1175\n292265\n212265\n2014","general":{"inn":"","inn_hidden":true,"last_name":"Коморний","post":{"post_unclear":false,"region_unclear":false,"region":"Львівська область","candidate":"","post":"суддя львівського окружного адміністративного суду","office":"Адміністративний місцевий суд","office_unclear":false},"name":"Олександр","full_name":"Коморний Олександр Ігорович","family_raw":"","addresses":[{"place_district":"","place_city_hidden":true,"place_city":"","place_city_type_hidden":true,"place_district_hidden":true,"place_city_type":"","place_address_hidden":true,"place_address":"","place_hidden":true,"place":""}],"family":[{"inn":"","relations":"Подружжя","relations_hidden":false,"inn_hidden":true,"relations_other":"","name_hidden":true,"family_name":"Коморна Л. М","name_unclear":false},{"inn":"","relations":"Дитина","relations_other":"","inn_hidden":true,"family_name":"Коморний О. О","name_hidden":false,"name_unclear":false}],"full_name_suggest":{"output":"Коморний Олександр Ігорович","input":["Коморний Олександр Ігорович","Олександр Ігорович Коморний","Олександр Коморний"]},"patronymic":"Ігорович"},"source":"VULYK","estate":{"25":[{"space_hidden":false,"costs":"","costs_comment":"","address_hidden":true,"region_hidden":true,"space_comment":"","space_unclear":false,"space":"104","address":"","costs_rent_comment_unclear":false,"region":"","costs_rent_comment":"","space_units":"м²","costs_rent":""}],"28":[{"space_unclear":false,"costs":"","costs_comment":"","address_hidden":true,"region_hidden":true,"space_comment":"1/6 спільна власність","space":"89.8","address":"","region":"","costs_rent_comment":"","space_units":"м²","costs_rent":""}],"29":[{"space_unclear":false,"address_hidden":true,"region_hidden":true,"space_comment":"","space":".1175","address":"","region":"","costs_property":"","costs_rent_comment":"","space_comment_unclear":false,"space_units":"га","costs_property_comment":"","costs_rent":""}],"30":[{"space_unclear":true,"address_hidden":true,"region_hidden":true,"space_comment":"","space":"190.6","address":"","region":"","costs_property":"","costs_rent_comment":"","space_units":"м²","costs_property_comment":"","costs_rent":""}],"31":[{"space_hidden":false,"address_hidden":true,"region_hidden":true,"space_comment":"2/6 спільна власність","space":"89.8","address":"","region":"","costs_property":"","costs_rent_comment":"","space_comment_unclear":false,"space_units":"м²","costs_property_comment":"","costs_rent":""}]},"intro":{"declaration_year":"2014","isnotdeclaration":""}}