{"income":{"5":{"value":"206871","family_comment":"","value_unclear":false,"family_unclear":false,"comment_unclear":false,"comment":"","family":"23430"},"6":{"family_comment":"","value":"194691","comment_unclear":false,"family":"","comment":""},"7":{"family_comment":"","value":"","source_name":"","family":"","comment":""},"8":{"family_comment":"","value":"","family":"","comment":""},"9":{"family_comment":"","value":"","value_unclear":false,"family":"","comment":""},"10":{"family_comment":"","value":"12180","value_unclear":false,"family":"","comment":""},"11":{"family_comment":"","value":"","family":"","comment":""},"12":{"family_comment":"","value":"","family":"","comment":""},"13":{"family_comment":"","value":"","family":"","comment":""},"14":{"family_comment":"","value":"","family":"","comment":""},"15":{"family_comment":"","value":"","family":"","comment":""},"16":{"family_comment":"","value":"","family":"","comment":""},"17":{"family_comment":"","value":"","value_unclear":false,"family":"","comment":""},"18":{"family_comment":"","value":"","value_unclear":false,"family":"","comment":""},"19":{"family_comment":"","value":"","family":"","comment":""},"20":{"value":"","family_comment":"","value_unclear":false,"family_unclear":false,"comment_unclear":false,"comment":"","family":"23430"}},"vehicle":{"40":[{"brand_info":"1975 куб. см.","sum_rent_comment":"","brand":"Hyundai Tucson","sum_comment":"","brand_unclear":false,"year":"2006","brand_hidden":false,"brand_info_hidden":false,"year_unclear":false,"sum":"","sum_rent":""}]},"id":"vulyk_84_25","declaration":{"additional_info_text":"","notfull_lostpages":"","date":"2015-03-23T00:00:00","notfull":"","additional_info":"","url":"http://static.declarations.com.ua/declarations/chosen_ones/judges_batch/2439_novik_dmytro_ivanovych.pdf"},"liabilities":{"54":{"sum_foreign_comment":"","sum_comment_hidden":false,"sum":"","sum_comment":"","sum_foreign":""},"55":{"sum_foreign_comment":"","sum":"","sum_comment":"","sum_foreign":""},"56":{"sum_foreign_comment":"","sum":"6446","sum_comment":"","sum_foreign":""},"57":{"sum_foreign_comment":"","sum_comment_hidden":false,"sum":"","sum_comment":"","sum_foreign":""},"58":{"sum_foreign_comment":"","sum_comment_hidden":false,"sum":"","sum_comment":"","sum_foreign":""},"59":{"sum_foreign_comment":"","sum":"","sum_comment":"","sum_foreign":""},"60":{"sum_foreign_comment":"","sum":"","sum_comment":"","sum_foreign":""},"61":{"sum_foreign_comment":"","sum":"","sum_comment":"","sum_foreign":""},"62":{"sum_foreign_comment":"","sum":"","sum_comment":"","sum_foreign":""},"63":{"sum_foreign_comment":"","sum_comment_hidden":false,"sum":"","sum_comment":"","sum_foreign":""},"64":{"sum_foreign_comment":"","sum_comment_hidden":false,"sum":"","sum_comment":"","sum_foreign":""}},"ft_src":"6446\nДніпропетровськ\n49000\nДніпропетровська область\nсуддя магдалинівського районного суду дніпропетровської області\nДніпропетровська область\nЗагальний місцевий суд\nДмитро\nНовік А. В\nПодружжя\nНовік К. Д\nДитина\nНовік А. Д\nДитина\nІванович\nНовік Дмитро Іванович\nДмитро Іванович Новік\nДмитро Новік\nНовік Дмитро Іванович\nНовік Дмитро Іванович\nНовік\nHyundai Tucson\n1975 куб. см.\n2006\nДніпропетровська область\nм. Новомосковськ\n70.7\nДніпропетровська область\nм. Дніпропетровськ\n43.1\n2014\n194691\n12180\n23430\n206871\n23430\nHyundai Tucson\n1975 куб. см.\n2006\n2014\nНовік Дмитро Іванович\nДмитро Іванович Новік\nДмитро Новік\nНовік Дмитро Іванович\nДмитро\nПодружжя\nНовік А. В\nДитина\nНовік К. Д\nДитина\nНовік А. Д\nНовік Дмитро Іванович\nІванович\nсуддя магдалинівського районного суду дніпропетровської області\nЗагальний місцевий суд\nДніпропетровська область\nНовік\nДніпропетровськ\n49000\nДніпропетровська область\n6446\n194691\n23430\n206871\n23430\n12180\nм. Новомосковськ\nДніпропетровська область\n70.7\n43.1\nДніпропетровська область\nм. Дніпропетровськ\n6446\nНовік А. В\nПодружжя\nНовік К. Д\nДитина\nНовік А. Д\nДитина\nІванович\nНовік\nДмитро\nНовік Дмитро Іванович\nДмитро Іванович Новік\nДмитро Новік\nНовік Дмитро Іванович\nДніпропетровська область\nДніпропетровськ\n49000\nДніпропетровська область\nсуддя магдалинівського районного суду дніпропетровської області\nЗагальний місцевий суд\nНовік Дмитро Іванович\n2006\nHyundai Tucson\n1975 куб. см.\n12180\n23430\n206871\n23430\n194691\nм. Новомосковськ\nДніпропетровська область\n70.7\nм. Дніпропетровськ\nДніпропетровська область\n43.1\n2014","general":{"inn":"","name":"Дмитро","inn_unclear":false,"family":[{"inn":"","inn_hidden":true,"inn_unclear":false,"relations_hidden":false,"relations_other":"","relations":"Подружжя","name_hidden":false,"family_name":"Новік А. В","name_unclear":false},{"inn":"","relations":"Дитина","relations_other":"","inn_hidden":false,"family_name":"Новік К. Д","name_hidden":false,"name_unclear":false},{"inn":"","relations":"Дитина","relations_other":"","inn_hidden":false,"family_name":"Новік А. Д","name_hidden":false,"name_unclear":false}],"inn_hidden":true,"family_raw":"","last_name":"Новік","post":{"post_unclear":false,"region_unclear":false,"post":"суддя магдалинівського районного суду дніпропетровської області","candidate":"","office_hidden":false,"region":"Дніпропетровська область","post_hidden":false,"office":"Загальний місцевий суд","office_unclear":false,"region_hidden":false},"full_name":"Новік Дмитро Іванович","addresses":[{"place_city_type_unclear":false,"place_address":"49000","place_district_hidden":false,"place_city_type":"Місто","place_address_hidden":false,"place_address_unclear":false,"place_city_type_hidden":false,"place":"Дніпропетровська область","place_district":"","place_unclear":false,"place_city":"Дніпропетровськ","place_city_unclear":false,"place_hidden":false,"place_city_hidden":false,"place_district_unclear":false}],"patronymic":"Іванович","full_name_suggest":{"output":"Новік Дмитро Іванович","input":["Новік Дмитро Іванович","Дмитро Іванович Новік","Дмитро Новік"]}},"source":"VULYK","estate":{"25":[{"region_unclear":false,"space_hidden":false,"costs":"","costs_comment":"","address_hidden":false,"region_hidden":false,"space_comment":"","space":"43.1","address":"м. Дніпропетровськ","costs_comment_unclear":false,"costs_rent_comment_unclear":false,"region":"Дніпропетровська область","address_unclear":false,"costs_rent_comment":"","space_units":"м²","costs_rent":""}],"31":[{"space_unclear":false,"address_hidden":false,"region_hidden":false,"space_comment":"","space":"70.7","address":"м. Новомосковськ","region":"Дніпропетровська область","costs_property":"","costs_rent_comment":"","address_unclear":false,"space_units":"м²","costs_property_comment":"","costs_rent":""}]},"intro":{"declaration_year":"2014","isnotdeclaration":"","declaration_year_unclear":false}}