{"income":{"5":{"value":"317882","family_comment":"","comment_unclear":false,"family_unclear":false,"family":"58488","comment":""},"6":{"family_comment":"","value":"281525","family":"58488","comment":""},"7":{"source_name_unclear":false,"value":"4283","comment_unclear":false,"family_comment":"","source_name":"Львівське регіональне відділення Національної школи суддів України, Рівненський інститут Київського університету права","family":"","comment":""},"8":{"family_comment":"","value":"","family":"","comment":""},"9":{"family_comment":"","value":"3229","family":"","comment":""},"10":{"family_comment":"","value":"","family":"","comment":""},"11":{"family_comment":"","value":"","family":"","comment":""},"12":{"family_comment":"","value":"","family":"","comment":""},"13":{"family_comment":"","value":"","family":"","comment":""},"14":{"family_comment":"","value":"","family":"","comment":""},"15":{"family_comment":"","value":"","family":"","comment":""},"16":{"family_comment":"","family_unclear":false,"value":"","family":"","comment":""},"17":{"family_comment":"","value":"","family":"","comment":""},"18":{"family_comment":"","value":"","family":"","comment":""},"19":{"family_comment":"","value":"","family":"","comment":""},"20":{"value":"28745","family_comment":"","comment_unclear":false,"family_unclear":false,"family":"","comment":"","family_comment_unclear":false},"21":[{"cur":"118.81","cur_units":"USD","country":"Канада","uah_equal":"2495","country_comment":"Національний суддівський інститут Канади"}]},"vehicle":{"35":[{"brand_info":"998 куб. см.","sum_rent_comment":"","brand":"Ford Fiesta","sum_comment":"","brand_unclear":false,"year":"2014","brand_info_unclear":false,"sum":"","sum_rent":""}]},"id":"vulyk_107_55","banks":{"45":[{"sum_foreign_comment":"","sum_units":"UAH","sum_comment":"","sum_comment_unclear":false,"sum_foreign_units":"UAH","sum_comment_hidden":false,"sum_unclear":false,"sum":"55833","sum_foreign":""}],"46":[{"sum_foreign_comment":"","sum_units":"UAH","sum_comment":"","sum_foreign_units":"UAH","sum":"55833","sum_foreign":""}],"51":[{"sum_foreign_comment":"","sum_units":"UAH","sum_comment":"","sum_comment_unclear":false,"sum_foreign_units":"UAH","sum":"7108","sum_unclear":false,"sum_foreign":""}]},"declaration":{"additional_info_text":"","notfull_lostpages":"","date":"2016-03-22T00:00:00","notfull":"","additional_info":"","url":"http://static.declarations.com.ua/declarations/chosen_ones/judges_batch/2034_ivashchuk_volodymyr_iaroslavovych.pdf"},"liabilities":{"54":{"sum_foreign_comment":"","sum":"4500","sum_comment":"","sum_comment_unclear":false,"sum_comment_hidden":false,"sum_foreign":""},"55":{"sum_foreign_comment":"","sum":"","sum_comment":"","sum_foreign":""},"56":{"sum_foreign_comment":"","sum":"","sum_comment":"","sum_unclear":false,"sum_foreign":""},"57":{"sum_foreign_comment":"","sum":"170725","sum_comment":"","sum_comment_unclear":false,"sum_foreign":""},"58":{"sum_foreign_comment":"","sum":"63089","sum_comment":"","sum_comment_unclear":false,"sum_unclear":false,"sum_foreign":""},"59":{"sum_foreign_comment":"","sum":"","sum_comment":"","sum_unclear":false,"sum_foreign":""},"60":{"sum_foreign_comment":"","sum":"","sum_comment":"","sum_comment_unclear":false,"sum_comment_hidden":false,"sum_foreign":""},"61":{"sum_foreign_comment":"","sum":"","sum_comment":"","sum_foreign":""},"62":{"sum_foreign_comment":"","sum":"","sum_comment":"","sum_foreign":""},"63":{"sum_foreign_comment":"","sum":"","sum_comment":"","sum_foreign":""},"64":{"sum_foreign_comment":"","sum":"","sum_comment":"","sum_foreign":""}},"ft_src":"170725\n4500\n63089\nІващук Володимир Ярославович\nсуддя апеляційного суду рівненської області\nРівненська область\nЗагальний апеляційний суд\nВолодимир\nІващук С. С\nПодружжя\nІващук Г. В\nДитина\nІващук Володимир Ярославович\nВолодимир Ярославович Іващук\nВолодимир Іващук\nІващук Володимир Ярославович\nІващук\nЯрославович\n2014\nFord Fiesta\n998 куб. см.\n55833\n7108\n55833\n2015\n998 куб. см.\n2014\nFord Fiesta\n55833\n7108\n55833\n2015\nІващук\nПодружжя\nІващук С. С\nДитина\nІващук Г. В\nІващук Володимир Ярославович\nВолодимир Ярославович Іващук\nВолодимир Іващук\nІващук Володимир Ярославович\nВолодимир\nЯрославович\nІващук Володимир Ярославович\nЗагальний апеляційний суд\nсуддя апеляційного суду рівненської області\nРівненська область\n170725\n4500\n63089\n4283\nЛьвівське регіональне відділення Національної школи суддів України, Рівненський інститут Київського університету права\n281525\n58488\n28745\n2495\nНаціональний суддівський інститут Канади\n118.81\nКанада\n317882\n58488\n3229\n2242\nвиділена для індивід. садівництва\n1063\n202.4\n35\n59.8\n63089\n170725\n4500\n35\n59.8\nвиділена для індивід. садівництва\n1063\n2242\n202.4\nІващук С. С\nПодружжя\nІващук Г. В\nДитина\nІващук\nЯрославович\nсуддя апеляційного суду рівненської області\nРівненська область\nЗагальний апеляційний суд\nІващук Володимир Ярославович\nІващук Володимир Ярославович\nВолодимир Ярославович Іващук\nВолодимир Іващук\nІващук Володимир Ярославович\nВолодимир\n58488\n281525\n2495\nКанада\n118.81\nНаціональний суддівський інститут Канади\n4283\nЛьвівське регіональне відділення Національної школи суддів України, Рівненський інститут Київського університету права\n58488\n317882\n3229\n28745\n2014\n998 куб. см.\nFord Fiesta\n28745\n2495\nКанада\n118.81\nНаціональний суддівський інститут Канади\n4283\nЛьвівське регіональне відділення Національної школи суддів України, Рівненський інститут Київського університету права\n317882\n58488\n3229\n58488\n281525\n35\n2242\n202.4\n59.8\nвиділена для індивід. садівництва\n1063\n55833\n7108\n55833\n2015","general":{"inn":"","inn_hidden":true,"last_name":"Іващук","post":{"post_unclear":false,"office":"Загальний апеляційний суд","post":"суддя апеляційного суду рівненської області","region":"Рівненська область"},"name":"Володимир","full_name":"Іващук Володимир Ярославович","family_raw":"","addresses":[{"place_district":"","place_city_hidden":false,"place_city":"","place_city_type_hidden":false,"place_district_hidden":false,"place_city_type":"","place_address_hidden":false,"place_address":"","place_hidden":true,"place":""}],"family":[{"inn":"","relations":"Подружжя","relations_other":"","inn_hidden":true,"family_name":"Іващук С. С","name_hidden":false,"name_unclear":false},{"inn":"","relations":"Дитина","relations_other":"","inn_hidden":false,"family_name":"Іващук Г. В","name_hidden":false,"name_unclear":false}],"full_name_suggest":{"output":"Іващук Володимир Ярославович","input":["Іващук Володимир Ярославович","Володимир Ярославович Іващук","Володимир Іващук"]},"patronymic":"Ярославович"},"source":"VULYK","estate":{"23":[{"costs":"","costs_comment":"","address_hidden":false,"region_hidden":true,"space_comment":"","space":"2242","address":"","region":"","costs_rent_comment":"","space_comment_unclear":false,"space_comment_hidden":false,"space_units":"м²","costs_rent":""}],"24":[{"space_hidden":false,"costs":"","costs_comment":"","address_hidden":false,"region_hidden":true,"space_comment":"","space":"202.4","address":"","region":"","costs_rent_comment":"","space_units":"м²","costs_rent":""}],"27":[{"space_hidden":false,"costs":"","costs_comment":"","address_hidden":false,"region_hidden":true,"space_comment":"","space":"59.8","address":"","region":"","costs_rent_comment":"","space_units":"м²","costs_rent":""}],"29":[{"address_hidden":true,"region_hidden":true,"space_comment":"виділена для індивід. садівництва","space":"1063","address":"","region":"","costs_property":"","costs_rent_comment":"","costs_rent_hidden":false,"space_units":"м²","costs_property_comment":"","costs_rent":""}],"31":[{"space_unclear":false,"address_hidden":true,"region_hidden":false,"space_comment":"","space_hidden":false,"space":"35","address":"","region":"","costs_property":"","costs_rent_comment":"","space_comment_unclear":false,"space_units":"м²","costs_property_comment":"","costs_rent":""}]},"intro":{"declaration_year":"2015","isnotdeclaration":""}}