{"income":{"5":{"family_comment":"","value":"257930","value_unclear":false,"family":"","comment":""},"6":{"value":"245930","value_unclear":false,"family_hidden":false,"family_comment":"","family":"","comment":""},"7":{"source_name_unclear":false,"value":"","family_comment":"","source_name":"","family":"","comment":""},"8":{"family_comment":"","value":"","family":"","comment":""},"9":{"family_comment":"","value":"","family":"","comment":""},"10":{"family_comment":"","value":"","family":"","comment":""},"11":{"family_comment":"","value":"","comment_unclear":false,"family":"","comment":""},"12":{"family_comment":"","value":"","family":"","comment":""},"13":{"family_comment":"","value":"","family":"","comment":""},"14":{"family_comment":"","value":"","family":"","comment":""},"15":{"family_comment":"","value":"","family":"","comment":""},"16":{"family_comment":"","value":"","family":"","comment":""},"17":{"family_comment":"","value":"","family":"","comment":""},"18":{"family_comment":"","value":"","family":"","comment":""},"19":{"family_comment":"","value":"","family":"","comment":""},"20":{"value":"12000","family_comment":"","value_unclear":false,"family_unclear":false,"comment_unclear":false,"comment":"","family":""}},"vehicle":{"35":[{"brand_info":"1.6 куб. дм","sum_rent_comment":"","brand":"Kia Soul","sum_comment":"","brand_unclear":false,"year":"2012","sum_rent_unclear":false,"brand_info_hidden":false,"brand_info_unclear":false,"sum":"","sum_rent":""}]},"id":"vulyk_101_182","declaration":{"additional_info_text":"","notfull_lostpages":"","date":"2016-03-31T00:00:00","notfull":"","additional_info":"","url":"http://static.declarations.com.ua/declarations/chosen_ones/judges_batch/897_serkiz_viktor_hryhorovych_2015.pdf"},"liabilities":{"54":{"sum_foreign_comment":"","sum":"","sum_comment":"","sum_comment_unclear":false,"sum_hidden":false,"sum_comment_hidden":false,"sum_unclear":false,"sum_foreign":""},"55":{"sum_foreign_comment":"","sum":"","sum_comment":"","sum_foreign":""},"56":{"sum_foreign_comment":"","sum":"","sum_comment":"","sum_comment_hidden":false,"sum_unclear":false,"sum_foreign":""},"57":{"sum_foreign_comment":"","sum":"","sum_comment":"","sum_hidden":false,"sum_comment_hidden":false,"sum_unclear":false,"sum_foreign":""},"58":{"sum_foreign_comment":"","sum":"","sum_comment":"","sum_comment_unclear":false,"sum_hidden":false,"sum_comment_hidden":false,"sum_unclear":false,"sum_foreign":""},"59":{"sum_foreign_comment":"","sum":"","sum_comment":"","sum_foreign":""},"60":{"sum_foreign_comment":"","sum":"","sum_comment":"","sum_hidden":false,"sum_comment_hidden":false,"sum_unclear":false,"sum_foreign":""},"61":{"sum_foreign_comment":"","sum":"","sum_comment":"","sum_foreign":""},"62":{"sum_foreign_comment":"","sum":"","sum_comment":"","sum_comment_unclear":false,"sum_foreign":""},"63":{"sum_foreign_comment":"","sum_comment_hidden":false,"sum":"","sum_comment":"","sum_foreign":""},"64":{"sum_foreign_comment":"","sum_comment_hidden":false,"sum":"","sum_comment":"","sum_foreign":""}},"ft_src":"суддя господарського суду запорізької області\nЗапорізька область\nГосподарський місцевий суд\nВіктор\nГригорович\nСеркіз Віктор Григорович\nСеркіз\nСеркіз Віктор Григорович\nВіктор Григорович Серкіз\nВіктор Серкіз\nСеркіз Віктор Григорович\n12000\n257930\n245930\n2012\nKia Soul\n1.6 куб. дм\nKia Soul\n1.6 куб. дм\n2012\n2015\n245930\n257930\n12000\n1.6 куб. дм\n2012\nKia Soul\n2015\nСеркіз Віктор Григорович\nВіктор Григорович Серкіз\nВіктор Серкіз\nСеркіз Віктор Григорович\nВіктор\nСеркіз Віктор Григорович\nГригорович\nсуддя господарського суду запорізької області\nЗапорізька область\nГосподарський місцевий суд\nСеркіз\n245930\n12000\n257930\nГригорович\nСеркіз\nВіктор\nСеркіз Віктор Григорович\nВіктор Григорович Серкіз\nВіктор Серкіз\nСеркіз Віктор Григорович\nсуддя господарського суду запорізької області\nЗапорізька область\nГосподарський місцевий суд\nСеркіз Віктор Григорович\n2015","general":{"inn":"","name":"Віктор","inn_unclear":false,"patronymic":"Григорович","inn_hidden":true,"family_raw":"","last_name":"Серкіз","post":{"region":"Запорізька область","region_unclear":false,"post":"суддя господарського суду запорізької області","office_unclear":false,"office":"Господарський місцевий суд"},"full_name":"Серкіз Віктор Григорович","addresses":[{"place_district":"","place_address_hidden":true,"place_city":"","place_city_type_hidden":false,"place_district_hidden":false,"place_city_type":"","place_city_hidden":true,"place_address":"","place_hidden":true,"place":""}],"patronymic_hidden":false,"full_name_suggest":{"output":"Серкіз Віктор Григорович","input":["Серкіз Віктор Григорович","Віктор Григорович Серкіз","Віктор Серкіз"]}},"source":"VULYK","intro":{"declaration_year":"2015"}}