{"income":{"5":{"value":"181350","family_comment":"","value_unclear":false,"family_unclear":false,"family":"59160","comment":""},"6":{"family_comment":"","value":"181350","value_unclear":false,"family":"48000","comment":""},"7":{"value":"","value_unclear":false,"family_comment":"","source_name":"Рубіжанський міський суд Луганської області","family":"","comment":""},"8":{"family_comment":"","value":"","family":"","comment":""},"9":{"value":"","family_comment":"","value_unclear":false,"family_unclear":false,"family":"","comment":""},"10":{"family_comment":"","value":"","comment_unclear":false,"family":"","comment":""},"11":{"family_comment":"","value":"","family":"","comment":""},"12":{"family_comment":"","value":"","family":"","comment":""},"13":{"family_comment":"","value":"","value_unclear":false,"family":"","comment":""},"14":{"family_comment":"","value":"","family":"","comment":""},"15":{"family_comment":"","value":"","family":"","comment":""},"16":{"family_comment":"","family_unclear":false,"value":"","family":"","comment":""},"17":{"family_comment":"","family_unclear":false,"value":"","family":"","comment":""},"18":{"family_comment":"","value":"","family":"","comment":""},"19":{"family_comment":"","value":"","family":"","comment":""},"20":{"value":"","family_comment":"","value_unclear":false,"family_hidden":false,"value_hidden":false,"family_unclear":false,"comment_unclear":false,"comment":"","family":"11160"}},"id":"vulyk_100_53","declaration":{"additional_info_text":"","notfull_lostpages":"","date":"2015-03-26T00:00:00","notfull":"","additional_info":"","url":"http://static.declarations.com.ua/declarations/chosen_ones/judges_batch/4221_myroshnykova_olena_shamiliivna.pdf"},"liabilities":{"54":{"sum_foreign_comment":"","sum":"","sum_comment":"","sum_comment_hidden":false,"sum_unclear":false,"sum_foreign":""},"55":{"sum_foreign_comment":"","sum":"","sum_comment":"","sum_foreign":""},"56":{"sum_foreign_comment":"","sum":"","sum_comment":"","sum_unclear":false,"sum_foreign":""},"57":{"sum_foreign_comment":"","sum":"","sum_comment":"","sum_comment_unclear":false,"sum_comment_hidden":false,"sum_unclear":false,"sum_foreign":""},"58":{"sum_foreign_comment":"","sum":"","sum_comment":"","sum_comment_hidden":false,"sum_unclear":false,"sum_foreign":""},"59":{"sum_foreign_comment":"","sum":"","sum_comment":"","sum_foreign":""},"60":{"sum_foreign_comment":"","sum_comment_hidden":false,"sum":"","sum_comment":"","sum_foreign":""},"61":{"sum_foreign_comment":"","sum":"","sum_comment":"","sum_foreign":""},"62":{"sum_foreign_comment":"","sum":"34800","sum_comment":"","sum_unclear":false,"sum_foreign":""},"63":{"sum_foreign_comment":"","sum_comment_hidden":false,"sum":"","sum_comment":"","sum_foreign":""},"64":{"sum_foreign_comment":"","sum_comment_hidden":false,"sum":"","sum_comment":"","sum_foreign":""}},"ft_src":"34800\nРубіжне\nЛуганська область\nМирошникова Олена Шаміліївна\nсуддя рубіжанського міського суду луганської області\nЛуганська область\nЗагальний місцевий суд\nОлена\nПодружжя\nДитина\nМирошникова Олена Шаміліївна\nОлена Шаміліївна Мирошникова\nОлена Мирошникова\nМирошникова Олена Шаміліївна\nМирошникова\nШаміліївна\n11160\n181350\n59160\nРубіжанський міський суд Луганської області\n48000\n181350\n1/2 частка\nЛуганська область\nм. Рубіжне\n61.08\nХарківська область\nм. Харків\n35\nЛьвівська область\nм. Львів\n30\n2014\n48000\n181350\nРубіжанський міський суд Луганської області\n59160\n181350\n11160\nРубіжанський міський суд Луганської області\n181350\n48000\n11160\n181350\n59160\nПодружжя\nДитина\nШаміліївна\nЛуганська область\nРубіжне\nМирошникова\nМирошникова Олена Шаміліївна\nОлена Шаміліївна Мирошникова\nОлена Мирошникова\nМирошникова Олена Шаміліївна\nМирошникова Олена Шаміліївна\nОлена\nЗагальний місцевий суд\nЛуганська область\nсуддя рубіжанського міського суду луганської області\n34800\n61.08\n1/2 частка\nЛуганська область\nм. Рубіжне\nм. Харків\n35\nХарківська область\n30\nм. Львів\nЛьвівська область\n2014\n34800\nПодружжя\nДитина\nРубіжне\nЛуганська область\nШаміліївна\nМирошникова\nЛуганська область\nЗагальний місцевий суд\nсуддя рубіжанського міського суду луганської області\nМирошникова Олена Шаміліївна\nМирошникова Олена Шаміліївна\nОлена Шаміліївна Мирошникова\nОлена Мирошникова\nМирошникова Олена Шаміліївна\nОлена\n1/2 частка\nм. Рубіжне\nЛуганська область\n61.08\nм. Харків\nХарківська область\n35\nм. Львів\nЛьвівська область\n30\n2014","general":{"inn":"","inn_hidden":true,"last_name":"Мирошникова","post":{"post_unclear":false,"region_unclear":false,"post":"суддя рубіжанського міського суду луганської області","office":"Загальний місцевий суд","region":"Луганська область","post_hidden":false,"office_unclear":false},"name":"Олена","full_name":"Мирошникова Олена Шаміліївна","family_raw":"","addresses":[{"place_district":"","place_city_hidden":false,"place_city":"Рубіжне","place_city_unclear":false,"place_district_hidden":false,"place_city_type":"Місто","place_address_hidden":true,"place_city_type_hidden":false,"place_address":"","place_hidden":true,"place":"Луганська область"}],"family":[{"inn_hidden":true,"inn":"","name_hidden":true,"family_name":"","relations":"Подружжя","name_unclear":false},{"inn":"","relations":"Дитина","relations_other":"","inn_hidden":false,"family_name":"","name_hidden":false,"name_unclear":false}],"full_name_suggest":{"output":"Мирошникова Олена Шаміліївна","input":["Мирошникова Олена Шаміліївна","Олена Шаміліївна Мирошникова","Олена Мирошникова"]},"patronymic":"Шаміліївна"},"source":"VULYK","estate":{"31":[{"region_unclear":false,"space_unclear":false,"costs_property_comment_unclear":false,"address_hidden":true,"region_hidden":false,"space_comment":"1/2 частка","space":"61.08","address":"м. Рубіжне","region":"Луганська область","costs_property":"","costs_rent_comment":"","space_comment_unclear":true,"address_unclear":false,"space_units":"м²","costs_property_comment":"","costs_rent":""},{"costs_rent":"","region_unclear":false,"region":"Харківська область","costs_property":"","costs_rent_comment":"","region_hidden":false,"space_comment":"","costs_property_comment":"","space_units":"м²","space":"35","address":"м. Харків"},{"costs_rent":"","region":"Львівська область","costs_property":"","costs_rent_comment":"","space_comment":"","costs_property_comment":"","space_units":"м²","space":"30","address":"м. Львів"}]},"intro":{"declaration_year":"2014"}}