{"income":{"5":{"family_comment":"","value":"351535","value_unclear":false,"family":"29125","comment":""},"6":{"family_comment":"","value":"351535","value_unclear":false,"family":"29125","comment":""},"7":{"source_name_unclear":false,"value":"","family_hidden":false,"value_hidden":false,"family_comment":"","source_name":"","family":"","comment":"","source_name_hidden":false},"8":{"value":"","family_hidden":false,"value_hidden":false,"family_comment":"","family":"","comment":""},"9":{"value":"","value_unclear":false,"value_hidden":false,"family_comment":"","comment_unclear":false,"comment":"","family":""},"10":{"value":"","family_hidden":false,"value_hidden":false,"family_comment":"","family":"","comment":""},"11":{"value":"","family_hidden":false,"value_hidden":false,"family_comment":"","family":"","comment":""},"12":{"value":"","family_hidden":false,"value_hidden":false,"family_comment":"","family":"","comment":""},"13":{"value":"","family_hidden":false,"value_hidden":false,"family_comment":"","family":"","comment":""},"14":{"value":"","family_hidden":false,"value_hidden":false,"family_comment":"","family":"","comment":""},"15":{"value":"","family_hidden":false,"value_hidden":false,"family_comment":"","family":"","comment":""},"16":{"value":"","family_hidden":false,"value_hidden":false,"family_comment":"","family":"","comment":""},"17":{"value":"","family_hidden":false,"value_hidden":false,"family_comment":"","family":"","comment":""},"18":{"value":"","comment_unclear":false,"family_hidden":false,"value_hidden":false,"family_comment":"","family":"","comment":""},"19":{"value":"","family_hidden":false,"value_hidden":false,"family_comment":"","family":"","comment":""},"20":{"value":"","value_unclear":false,"family_hidden":false,"value_hidden":false,"family_comment":"","comment_unclear":false,"comment":"","family":""}},"vehicle":{"35":[{"brand_info":"2967 куб. см.","sum_rent_comment":"","sum_rent_hidden":false,"year":"2008","sum_hidden":false,"brand_info_unclear":false,"sum_rent":"","sum":"","brand":"Volkswagen Touareg","sum_comment":"","brand_unclear":false,"sum_rent_comment_hidden":false,"sum_comment_hidden":false,"sum_unclear":false}],"40":[{"brand_info":"1997 куб. см.","sum":"","brand":"Toyota Rav 4","sum_comment":"","brand_unclear":false,"year":"2012","brand_hidden":false,"brand_info_hidden":false,"brand_info_unclear":false,"sum_rent_comment":"","sum_rent":""}]},"id":"vulyk_70_192","banks":{"45":[{"sum_units":"UAH","sum_foreign":"","sum_hidden":false,"sum":"33442","sum_units_hidden":false,"sum_foreign_comment":"","sum_foreign_hidden":false,"sum_comment":"","sum_foreign_units":"UAH","sum_units_unclear":false,"sum_comment_hidden":false,"sum_unclear":false}],"46":[{"sum_foreign_comment":"","sum":"21840","sum_comment":"","sum_hidden":false,"sum_foreign_units":"UAH","sum_foreign_hidden":false,"sum_units":"UAH","sum_comment_hidden":false,"sum_unclear":false,"sum_foreign":"","sum_units_hidden":false}]},"declaration":{"additional_info_text":"Декларація є неповною, склеєною з окремих пунктів. Відсутні пункти 2, 7-22, 24, 28-34, 36-39, 41-44, 47-53, 55-64. Дата заповнення та підпис відсутні","notfull":"1","additional_info":"1","notfull_lostpages":"в наявності лише нарізки з декларації","url":"http://static.declarations.com.ua/declarations/chosen_ones/judges_batch/193_benedysiuk_ihor_mykhailovych.pdf"},"liabilities":{"54":{"sum_foreign_comment":"","sum_foreign_hidden":false,"sum_comment":"","sum_hidden":false,"sum_foreign_comment_unclear":false,"sum_comment_hidden":false,"sum":"14688","sum_foreign":""},"55":{"sum_foreign_comment":"","sum":"","sum_hidden":false,"sum_comment":"","sum_foreign":""},"56":{"sum_foreign_comment":"","sum":"","sum_comment":"","sum_foreign":""},"57":{"sum_foreign_comment":"","sum_foreign_hidden":false,"sum_comment":"","sum_hidden":false,"sum_comment_hidden":false,"sum":"","sum_foreign":""},"58":{"sum_foreign_comment":"","sum":"","sum_comment":"","sum_hidden":false,"sum_comment_hidden":false,"sum_foreign":""},"59":{"sum_foreign_comment":"","sum_foreign_hidden":false,"sum_comment":"","sum_hidden":false,"sum":"","sum_foreign":""},"60":{"sum_foreign_comment":"","sum":"","sum_comment":"","sum_comment_unclear":false,"sum_hidden":false,"sum_comment_hidden":false,"sum_foreign":""},"61":{"sum_foreign_comment":"","sum":"","sum_hidden":false,"sum_comment":"","sum_foreign":""},"62":{"sum_foreign_comment":"","sum_foreign_hidden":false,"sum_comment":"","sum_comment_hidden":false,"sum_unclear":false,"sum":"","sum_foreign":""},"63":{"sum_foreign_comment":"","sum_foreign_hidden":false,"sum_comment":"","sum_hidden":false,"sum_comment_hidden":false,"sum":"","sum_foreign":""},"64":{"sum_foreign_comment":"","sum":"","sum_comment":"","sum_hidden":false,"sum_comment_hidden":false,"sum_foreign":""}},"ft_src":"14688\n1\n1\nДекларація є неповною, склеєною з окремих пунктів. Відсутні пункти 2, 7-22, 24, 28-34, 36-39, 41-44, 47-53, 55-64. Дата заповнення та підпис відсутні\nв наявності лише нарізки з декларації\nсуддя вищого господарського суду україни\nЗагальнодержавний регіон\nВищий господарський суд\nІгор\nБенедисюк Н. М\nПодружжя\nБенедисюк Д. І\nДитина\nБенедисюк А. І\nДитина\nМихайлович\nБенедисюк Ігор Михайлович\nІгор Михайлович Бенедисюк\nІгор Бенедисюк\nБенедисюк Ігор Михайлович\nБенедисюк Ігор Михайлович\nБенедисюк\nVolkswagen Touareg\n2967 куб. см.\n2008\nToyota Rav 4\n1997 куб. см.\n2012\n2320\n635\n22.3\n245.4\n97.34\n21840\n33442\nв наявності лише нарізки з декларації\n1\n1\nДекларація є неповною, склеєною з окремих пунктів. Відсутні пункти 2, 7-22, 24, 28-34, 36-39, 41-44, 47-53, 55-64. Дата заповнення та підпис відсутні\n2013\n2967 куб. см.\nVolkswagen Touareg\n2008\n1997 куб. см.\n2012\nToyota Rav 4\nДекларація є неповною, склеєною з окремих пунктів. Відсутні пункти 2, 7-22, 24, 28-34, 36-39, 41-44, 47-53, 55-64. Дата заповнення та підпис відсутні\n1\n1\nв наявності лише нарізки з декларації\n2013\nБенедисюк Ігор Михайлович\nІгор Михайлович Бенедисюк\nІгор Бенедисюк\nБенедисюк Ігор Михайлович\nБенедисюк Ігор Михайлович\nПодружжя\nБенедисюк Н. М\nДитина\nБенедисюк Д. І\nДитина\nБенедисюк А. І\nІгор\nМихайлович\nсуддя вищого господарського суду україни\nВищий господарський суд\nЗагальнодержавний регіон\nБенедисюк\n14688\n351535\n29125\n351535\n29125\n2320\n635\n22.3\n245.4\n97.34\n33442\n21840\n14688\n29125\n351535\n29125\n351535\nПодружжя\nБенедисюк Н. М\nДитина\nБенедисюк Д. І\nДитина\nБенедисюк А. І\nМихайлович\nБенедисюк\nІгор\nБенедисюк Ігор Михайлович\nІгор Михайлович Бенедисюк\nІгор Бенедисюк\nБенедисюк Ігор Михайлович\nЗагальнодержавний регіон\nВищий господарський суд\nсуддя вищого господарського суду україни\nБенедисюк Ігор Михайлович\n2008\nVolkswagen Touareg\n2967 куб. см.\nToyota Rav 4\n1997 куб. см.\n2012\n29125\n351535\n29125\n351535\n97.34\n2320\n635\n245.4\n22.3\n33442\n21840\n2013","general":{"inn":"","name":"Ігор","inn_unclear":false,"family":[{"inn":"","relations":"Подружжя","inn_unclear":false,"relations_hidden":false,"inn_hidden":true,"relations_other":"","name_hidden":false,"family_name":"Бенедисюк Н. М","name_unclear":false},{"inn":"","relations":"Дитина","relations_hidden":false,"inn_hidden":false,"relations_other":"","name_hidden":false,"family_name":"Бенедисюк Д. І","name_unclear":false},{"inn":"","relations":"Дитина","relations_other":"","inn_hidden":false,"family_name":"Бенедисюк А. І","name_hidden":false,"name_unclear":false}],"inn_hidden":false,"family_raw":"","last_name":"Бенедисюк","post":{"post":"суддя вищого господарського суду україни","region":"Загальнодержавний регіон","candidate":"","office_hidden":false,"post_hidden":false,"office":"Вищий господарський суд","region_hidden":false},"full_name_suggest":{"output":"Бенедисюк Ігор Михайлович","input":["Бенедисюк Ігор Михайлович","Ігор Михайлович Бенедисюк","Ігор Бенедисюк"]},"full_name":"Бенедисюк Ігор Михайлович","patronymic":"Михайлович","last_name_unclear":false,"name_unclear":false},"source":"VULYK","estate":{"23":[{"region_unclear":false,"space_unclear":false,"costs":"","costs_comment":"","costs_hidden":false,"address_hidden":false,"region_hidden":true,"space_comment":"","space_hidden":false,"space_units_unclear":false,"address":"","costs_comment_unclear":false,"region":"","address_unclear":false,"space":"2320","costs_rent_hidden":false,"costs_rent_comment_hidden":false,"space_units":"м²","costs_comment_hidden":false,"costs_rent":"","costs_rent_comment":""},{"space_unclear":false,"costs":"","costs_comment":"","costs_hidden":false,"address_hidden":false,"region_hidden":false,"space_comment":"","space":"635","address":"","region":"","costs_rent_comment":"","costs_rent_hidden":false,"space_units":"м²","costs_rent":""}],"25":[{"region_unclear":false,"space_unclear":false,"costs":"","costs_comment":"","costs_hidden":false,"address_hidden":false,"region_hidden":true,"space_comment":"","space":"97.34","address":"","costs_rent_comment_unclear":false,"region":"","costs_rent_comment":"","costs_rent_hidden":false,"space_comment_unclear":false,"costs_rent_comment_hidden":false,"space_units":"м²","costs_comment_hidden":false,"costs_rent":"","costs_unclear":false}],"26":[{"space_hidden":false,"costs":"","costs_comment":"","address_hidden":false,"region_hidden":true,"space_comment":"","space":"245.4","address":"","costs_comment_unclear":false,"region":"","costs_rent_comment":"","space_units":"м²","costs_rent":""}],"27":[{"space_hidden":false,"costs":"","costs_comment":"","costs_hidden":false,"address_hidden":false,"region_hidden":true,"space_comment":"","space_unclear":false,"space":"22.3","address":"","region":"","costs_rent_comment":"","costs_rent_hidden":false,"costs_rent_comment_hidden":false,"space_units":"м²","costs_comment_hidden":false,"costs_rent":""}]},"intro":{"declaration_year":"2013","isnotdeclaration":"","declaration_year_unclear":false,"declaration_year_hidden":false}}