{"income":{"5":{"value":"236451","family_comment":"","value_unclear":false,"comment_hidden":false,"family_hidden":false,"value_hidden":false,"family_unclear":false,"family":"29056","comment":""},"6":{"value":"224271","family_comment":"","value_unclear":false,"family_hidden":false,"family_unclear":false,"comment_unclear":false,"comment":"","family":"27838"},"7":{"source_name_unclear":false,"value":"","value_hidden":false,"family_comment":"","source_name":"","family":"","comment":"","source_name_hidden":false},"8":{"value":"","family_hidden":false,"value_hidden":false,"family_comment":"","family":"","comment":""},"9":{"value":"","family_comment":"","value_unclear":false,"family_hidden":false,"value_hidden":false,"family_unclear":false,"family":"","comment":""},"10":{"family_comment":"","value":"12180","family":"1218","comment":""},"11":{"family_comment":"","value":"","family":"","comment":""},"12":{"family_comment":"","value":"","family":"","comment":""},"13":{"family_comment":"","value":"","family":"","comment":""},"14":{"family_comment":"","value":"","family":"","comment":""},"15":{"family_comment":"","value":"","family":"","comment":""},"16":{"value":"","family_comment":"","value_unclear":false,"family_unclear":false,"family":"","comment":""},"17":{"family_comment":"","value":"","family":"","comment":""},"18":{"family_comment":"","value":"","family":"","comment":""},"19":{"family_comment":"","value":"","comment_unclear":false,"family":"","comment":""},"20":{"value":"","family_comment":"","value_unclear":false,"comment_hidden":false,"family_hidden":false,"family":"","value_hidden":false,"family_unclear":false,"comment_unclear":false,"comment":"","family_comment_unclear":false}},"vehicle":{"40":[{"brand_info":"1.498.63 кВт","sum_rent_comment":"","brand":"Chevrolet Aveo SA 694","sum_comment":"","brand_unclear":false,"year":"2007","brand_info_unclear":false,"year_unclear":false,"sum":"","sum_rent":""}],"41":[{"brand_info":"2.445 л, 73.5 кВт","sum_rent_comment":"","brand":"ГАЗ 3221 'Газель'","sum_comment":"","brand_unclear":false,"year":"1999","brand_info_unclear":true,"sum":"","sum_rent":""}]},"id":"vulyk_63_107","banks":{"45":[{"sum_foreign_comment":"","sum_units":"UAH","sum_comment":"","sum_foreign_unclear":false,"sum_foreign_units":"UAH","sum_foreign_hidden":false,"sum_hidden":false,"sum_comment_hidden":false,"sum_unclear":false,"sum":"6639","sum_foreign":""}],"51":[{"sum_foreign_comment":"","sum_units":"UAH","sum_comment":"","sum_foreign_unclear":false,"sum_foreign_units":"UAH","sum_foreign_hidden":false,"sum_hidden":false,"sum_comment_hidden":false,"sum_unclear":false,"sum":"2473","sum_foreign":""}]},"declaration":{"additional_info_text":"","notfull_lostpages":"","date":"2015-03-17T00:00:00","notfull":"","additional_info":"","url":"http://static.declarations.com.ua/declarations/chosen_ones/mega_batch/mykhaliuk_oleksandr_pavlovych.pdf"},"liabilities":{"54":{"sum_foreign_comment":"","sum":"","sum_comment":"","sum_unclear":false,"sum_foreign":""},"55":{"sum_foreign_comment":"","sum":"","sum_comment":"","sum_foreign":""},"56":{"sum_foreign_comment":"","sum":"","sum_comment":"","sum_unclear":false,"sum_foreign":""},"57":{"sum_foreign_comment":"","sum":"","sum_comment":"","sum_comment_hidden":false,"sum_unclear":false,"sum_foreign":""},"58":{"sum_foreign_comment":"","sum_comment_hidden":false,"sum":"","sum_comment":"","sum_foreign":""},"59":{"sum_foreign_comment":"","sum":"","sum_comment":"","sum_foreign":""},"60":{"sum_foreign_comment":"","sum":"","sum_comment":"","sum_comment_unclear":false,"sum_foreign":""},"61":{"sum_foreign_comment":"","sum":"","sum_comment":"","sum_unclear":false,"sum_foreign":""},"62":{"sum_foreign_comment":"","sum":"","sum_comment":"","sum_unclear":false,"sum_foreign":""},"63":{"sum_foreign_comment":"","sum":"","sum_comment":"","sum_hidden":false,"sum_comment_hidden":false,"sum_unclear":false,"sum_foreign":""},"64":{"sum_foreign_comment":"","sum_comment_hidden":false,"sum":"","sum_comment":"","sum_foreign":""}},"ft_src":"голова баранівського районного суду житомирської області\nЖитомирська область\nЗагальний місцевий суд\nОлександр\nМихалюк Т. Г\nПодружжя\nМихалюк І. О\nДитина\nПавлович\nМихалюк\nМихалюк Олександр Павлович\nМихалюк Олександр Павлович\nОлександр Павлович Михалюк\nОлександр Михалюк\nМихалюк Олександр Павлович\n1999\nГАЗ 3221 'Газель'\n2.445 л, 73.5 кВт\n1.498.63 кВт\nChevrolet Aveo SA 694\n2007\n2473\n6639\n2014\n1.498.63 кВт\n2007\nChevrolet Aveo SA 694\n2.445 л, 73.5 кВт\n1999\nГАЗ 3221 'Газель'\n6639\n2473\n6863\nм. Баранівка\nЖитомирська область\n54.295\nм. Баранівка\nЖитомирська область\n176.5\nУкраїна, Житомирська обл., м. Баранівка\nЖитомирська область\nПавлович\nМихалюк Олександр Павлович\nОлександр Павлович Михалюк\nОлександр Михалюк\nМихалюк Олександр Павлович\nОлександр\nПодружжя\nМихалюк Т. Г\nДитина\nМихалюк І. О\nМихалюк Олександр Павлович\nЗагальний місцевий суд\nЖитомирська область\nголова баранівського районного суду житомирської області\nМихалюк\n224271\n27838\n236451\n29056\n12180\n1218\n2014\nм. Баранівка\nЖитомирська область\n54.295\nЖитомирська область\nУкраїна, Житомирська обл., м. Баранівка\n176.5\nЖитомирська область\nм. Баранівка\n6863\nПодружжя\nМихалюк Т. Г\nДитина\nМихалюк І. О\nПавлович\nМихалюк\nМихалюк Олександр Павлович\nОлександр Павлович Михалюк\nОлександр Михалюк\nМихалюк Олександр Павлович\nОлександр\nЖитомирська область\nголова баранівського районного суду житомирської області\nЗагальний місцевий суд\nМихалюк Олександр Павлович\n27838\n224271\n1218\n12180\n29056\n236451\n1999\n2.445 л, 73.5 кВт\nГАЗ 3221 'Газель'\n2007\n1.498.63 кВт\nChevrolet Aveo SA 694\n1218\n12180\n236451\n29056\n224271\n27838\nм. Баранівка\nЖитомирська область\n54.295\nУкраїна, Житомирська обл., м. Баранівка\nЖитомирська область\n176.5\nм. Баранівка\nЖитомирська область\n6863\n6639\n2473\n2014","general":{"name_hidden":false,"name":"Олександр","patronymic_unclear":false,"last_name_hidden":false,"inn":"","family":[{"inn":"","inn_hidden":true,"relations_unclear":false,"relations_hidden":false,"relations_other":"","relations":"Подружжя","name_hidden":true,"inn_unclear":false,"family_name":"Михалюк Т. Г","name_unclear":false},{"inn":"","relations":"Дитина","relations_unclear":false,"family_name":"Михалюк І. О","inn_hidden":false,"relations_other":"","name_hidden":true,"inn_unclear":false,"name_unclear":true}],"patronymic":"Павлович","inn_hidden":true,"family_raw":"","inn_unclear":false,"post":{"post_unclear":false,"region_unclear":false,"region":"Житомирська область","office_hidden":false,"region_hidden":false,"post":"голова баранівського районного суду житомирської області","office_unclear":false,"office":"Загальний місцевий суд"},"last_name_unclear":false,"full_name":"Михалюк Олександр Павлович","addresses":[{"place_city_type_unclear":false,"place_address":"","place_district_hidden":true,"place_city_type":"","place_address_hidden":true,"place_address_unclear":false,"place_city_type_hidden":true,"place":"","place_district":"","place_unclear":false,"place_city":"","place_city_unclear":false,"place_hidden":true,"place_city_hidden":true,"place_district_unclear":false}],"last_name":"Михалюк","full_name_suggest":{"output":"Михалюк Олександр Павлович","input":["Михалюк Олександр Павлович","Олександр Павлович Михалюк","Олександр Михалюк"]},"name_unclear":false},"source":"VULYK","estate":{"29":[{"space_hidden":false,"costs_property_comment":"","address_hidden":true,"region_hidden":false,"space_comment":"","space_unclear":false,"space":"6863","address":"м. Баранівка","region":"Житомирська область","costs_property":"","costs_rent_comment":"","address_unclear":false,"space_units":"м²","space_units_unclear":false,"costs_rent":""}],"30":[{"space_unclear":false,"address_hidden":true,"region_hidden":false,"space_comment":"","space_hidden":false,"space":"54.295","address":"м. Баранівка","region":"Житомирська область","costs_property":"","costs_rent_comment":"","space_units":"м²","costs_property_comment":"","costs_rent":""},{"costs_rent":"","region":"Житомирська область","costs_property":"","costs_rent_comment":"","space_comment":"","costs_property_comment":"","space_units":"м²","space":"176.5","address":"Україна, Житомирська обл., м. Баранівка"}]},"intro":{"declaration_year":"2014","isnotdeclaration":"","declaration_year_unclear":false}}