{"income":{"5":{"value":"192275.58","family_comment":"","value_unclear":false,"comment_hidden":false,"family_hidden":false,"value_hidden":false,"family_unclear":false,"family_comment_hidden":false,"comment":"","family":"21600"},"6":{"value":"192275.58","family_comment":"","value_unclear":false,"family_hidden":false,"family_unclear":false,"family":"","comment":""},"7":{"source_name_unclear":false,"value":"","family_hidden":false,"family_comment":"","source_name":"","family":"","comment":"","source_name_hidden":false},"8":{"family_comment":"","value":"","family":"","comment":""},"9":{"value":"","value_unclear":false,"family_hidden":false,"family_comment":"","family":"","comment":""},"10":{"value":"","value_unclear":false,"family_hidden":false,"value_hidden":false,"family_comment":"","comment_unclear":false,"comment":"","family":""},"11":{"family_comment":"","value":"","family":"","comment":""},"12":{"family_comment":"","value":"","family":"","comment":""},"13":{"family_comment":"","value":"","family":"","comment":""},"14":{"family_comment":"","value":"","family":"","comment":""},"15":{"family_comment":"","value":"","family_hidden":false,"comment":"","family":""},"16":{"value":"","value_unclear":false,"family_hidden":false,"family_comment":"","family":"","comment":""},"17":{"family_comment":"","value":"","family_hidden":false,"comment":"","family":""},"18":{"family_comment":"","value":"","value_unclear":false,"family":"","comment":""},"19":{"family_comment":"","value":"","family":"","comment":""},"20":{"value":"","family_comment":"","value_unclear":false,"family_hidden":false,"family_unclear":false,"comment_unclear":false,"comment":"","family":"21600"}},"id":"vulyk_72_325","declaration":{"additional_info_text":"","notfull_lostpages":"","date":"2015-03-31T00:00:00","notfull":"","additional_info":"","url":"http://static.declarations.com.ua/declarations/chosen_ones/epic_batch/lebedynskyi_stanislav_iosypovych.pdf"},"liabilities":{"54":{"sum_foreign_comment":"","sum":"","sum_comment":"","sum_comment_hidden":false,"sum_unclear":false,"sum_foreign":""},"55":{"sum_foreign_comment":"","sum":"","sum_comment":"","sum_foreign":""},"56":{"sum_foreign_comment":"","sum":"","sum_hidden":false,"sum_comment":"","sum_foreign":""},"57":{"sum_foreign_comment":"","sum":"","sum_comment":"","sum_comment_unclear":false,"sum_hidden":false,"sum_comment_hidden":false,"sum_unclear":false,"sum_foreign":""},"58":{"sum_foreign_comment":"","sum":"","sum_comment":"","sum_comment_unclear":false,"sum_hidden":false,"sum_comment_hidden":false,"sum_unclear":false,"sum_foreign":""},"59":{"sum_foreign_comment":"","sum_foreign_hidden":false,"sum_comment":"","sum_foreign_unclear":false,"sum_comment_hidden":false,"sum":"","sum_foreign":""},"60":{"sum_foreign_comment":"","sum_foreign_hidden":false,"sum_comment":"","sum_hidden":false,"sum":"","sum_foreign":""},"61":{"sum_foreign_comment":"","sum_foreign_hidden":false,"sum_comment":"","sum_hidden":false,"sum":"","sum_foreign":""},"62":{"sum_foreign_comment":"","sum_foreign_hidden":false,"sum_comment":"","sum_hidden":false,"sum":"","sum_foreign":""},"63":{"sum_foreign_comment":"","sum_foreign_hidden":false,"sum_comment":"","sum_comment_unclear":false,"sum_hidden":false,"sum_comment_hidden":false,"sum_unclear":false,"sum":"","sum_foreign":""},"64":{"sum_foreign_comment":"","sum_foreign_hidden":false,"sum_comment":"","sum_hidden":false,"sum":"","sum_foreign":""}},"ft_src":"суддя березівського районного суду одеської області (заступник голови суду\nОдеська область\nЗагальний місцевий суд\nСтаніслав\nЛебединська С. І\nБатьки\nЙосипович\nЛебединський Станіслав Йосипович\nСтаніслав Йосипович Лебединський\nСтаніслав Лебединський\nЛебединський Станіслав Йосипович\nЛебединський Станіслав Йосипович\nЛебединський\n21600\n192275.58\n21600\n192275.58\n64\n2014\n192275.58\n21600\n192275.58\n21600\n192275.58\n21600\n192275.58\n21600\nЛебединський Станіслав Йосипович\nСтаніслав Йосипович Лебединський\nСтаніслав Лебединський\nЛебединський Станіслав Йосипович\nЛебединський Станіслав Йосипович\nБатьки\nЛебединська С. І\nСтаніслав\nЛебединський\nОдеська область\nЗагальний місцевий суд\nсуддя березівського районного суду одеської області (заступник голови суду\nЙосипович\n64\n2014\nЛебединська С. І\nБатьки\nЙосипович\nЛебединський\nСтаніслав\nЛебединський Станіслав Йосипович\nСтаніслав Йосипович Лебединський\nСтаніслав Лебединський\nЛебединський Станіслав Йосипович\nОдеська область\nЗагальний місцевий суд\nсуддя березівського районного суду одеської області (заступник голови суду\nЛебединський Станіслав Йосипович\n64\n2014","general":{"inn":"","name":"Станіслав","patronymic_unclear":false,"family":[{"inn":"","inn_hidden":false,"relations_unclear":false,"relations_hidden":false,"relations_other":"","relations":"Батьки","name_hidden":false,"inn_unclear":false,"family_name":"Лебединська С. І","name_unclear":false}],"patronymic":"Йосипович","inn_hidden":false,"family_raw":"","inn_unclear":false,"post":{"post_unclear":false,"region_unclear":false,"post":"суддя березівського районного суду одеської області (заступник голови суду","candidate":"","office_hidden":false,"region":"Одеська область","post_hidden":false,"office":"Загальний місцевий суд","office_unclear":false,"region_hidden":false},"full_name_suggest":{"output":"Лебединський Станіслав Йосипович","input":["Лебединський Станіслав Йосипович","Станіслав Йосипович Лебединський","Станіслав Лебединський"]},"full_name":"Лебединський Станіслав Йосипович","last_name":"Лебединський","patronymic_hidden":false,"last_name_unclear":false,"name_unclear":false},"source":"VULYK","estate":{"31":[{"space_unclear":false,"address_hidden":false,"region_hidden":false,"space_comment":"","space_units_hidden":false,"space_hidden":false,"space":"64","address":"","region":"","address_unclear":false,"costs_rent_comment":"","costs_property":"","space_units":"м²","costs_property_comment":"","costs_rent":""}]},"intro":{"declaration_year":"2014","isnotdeclaration":"","declaration_year_unclear":false}}