{"income":{"5":{"value":"209036","family_comment":"","value_unclear":false,"family_hidden":false,"value_hidden":false,"family_unclear":false,"family_comment_hidden":false,"comment":"","family":"22386"},"6":{"value":"209036","family_comment":"","value_unclear":false,"family_hidden":false,"family_unclear":false,"family":"","comment":""},"7":{"family_comment":"","value":"","source_name":"","family":"","comment":""},"8":{"family_comment":"","value":"","family":"","comment":""},"9":{"family_comment":"","value":"","family":"","comment":""},"10":{"family_comment":"","family_unclear":false,"value":"","family":"","comment":""},"11":{"family_comment":"","value":"","family":"","comment":""},"12":{"family_comment":"","value":"","family":"","comment":""},"13":{"family_comment":"","value":"","family":"","comment":""},"14":{"family_comment":"","value":"","comment_unclear":false,"family":"","comment":""},"15":{"family_comment":"","value":"","family":"","comment":""},"16":{"family_comment":"","value":"","family":"","comment":""},"17":{"family_comment":"","value":"","family":"","comment":""},"18":{"family_comment":"","value":"","family":"","comment":""},"19":{"family_comment":"","value":"","family":"","comment":""},"20":{"value":"","family_comment":"","value_unclear":false,"family_unclear":false,"comment_unclear":false,"comment":"","family":"22386"}},"vehicle":{"35":[{"brand_info":"1498 куб. см., 86 к. с., 432.5 см","sum_rent_comment":"","brand_info_unclear":false,"year":"2007","sum_rent_unclear":false,"brand_info_hidden":false,"sum_rent_comment_unclear":false,"sum_rent":"","sum":"","brand":"Chevrolet Aveo","sum_comment":"","brand_hidden":false,"sum_rent_comment_hidden":false,"sum_unclear":false}]},"id":"vulyk_35_82","banks":{"45":[{"sum_foreign_comment":"","sum_units":"UAH","sum_comment":"","sum_comment_unclear":false,"sum_hidden":false,"sum_foreign_units":"UAH","sum_comment_hidden":false,"sum_unclear":false,"sum":"","sum_foreign":""},{"sum_foreign_comment":"","sum_units":"","sum_comment":"","sum_foreign_units":"","sum":"","sum_foreign":""},{"sum_foreign_comment":"","sum_units":"","sum_comment":"","sum_foreign_units":"","sum":"","sum_foreign":""}],"46":[{"sum_foreign_comment":"","sum_units":"UAH","sum_comment":"","sum_hidden":false,"sum_foreign_units":"UAH","sum_comment_hidden":false,"sum":"","sum_foreign":""},{"sum_foreign_comment":"","sum_units":"","sum_comment":"","sum_foreign_units":"","sum":"","sum_foreign":""}],"47":[{"sum_foreign_comment":"","sum_units":"UAH","sum_comment":"","sum_foreign_units":"UAH","sum":"","sum_foreign":""}],"48":[{"sum_foreign_comment":"","sum_units":"UAH","sum_comment":"","sum_foreign_units":"UAH","sum":"","sum_foreign":""}],"49":[{"sum_foreign_comment":"","sum_units":"UAH","sum_comment":"","sum_hidden":false,"sum_foreign_units":"UAH","sum":"","sum_foreign":""}],"50":[{"sum_foreign_comment":"","sum_units":"UAH","sum_comment":"","sum_foreign_units":"UAH","sum":"","sum_foreign":""}],"51":[{"sum_foreign_comment":"","sum_units":"UAH","sum_comment":"","sum_comment_unclear":false,"sum_foreign_units":"UAH","sum_comment_hidden":false,"sum":"","sum_foreign":""},{"sum_foreign_comment":"","sum_units":"","sum_comment":"","sum_foreign_units":"","sum":"","sum_foreign":""}],"52":[{"sum_foreign_comment":"","sum_units":"UAH","sum_comment":"","sum_foreign_units":"UAH","sum":"","sum_foreign":""}],"53":[{"sum_foreign_comment":"","sum_units":"UAH","sum_comment":"","sum_foreign_units":"UAH","sum":"","sum_foreign":""}]},"declaration":{"additional_info_text":"","notfull_lostpages":"","date":"2015-03-23T00:00:00","notfull":"","additional_info":"","url":"http://static.declarations.com.ua/declarations/chosen_ones/mega_batch/shymchyk_roman_vasylovych.pdf"},"liabilities":{"54":{"sum_foreign_comment":"","sum":"227","sum_comment":"","sum_comment_unclear":false,"sum_hidden":false,"sum_comment_hidden":false,"sum_unclear":false,"sum_foreign":""},"55":{"sum_foreign_comment":"","sum":"","sum_comment":"","sum_foreign":""},"56":{"sum_foreign_comment":"","sum":"","sum_comment":"","sum_unclear":false,"sum_foreign":""},"57":{"sum_foreign_comment":"","sum":"24977","sum_comment":"","sum_comment_unclear":false,"sum_hidden":false,"sum_comment_hidden":false,"sum_unclear":false,"sum_foreign":""},"58":{"sum_foreign_comment":"","sum":"27283","sum_comment":"","sum_hidden":false,"sum_comment_hidden":false,"sum_foreign":""},"59":{"sum_foreign_comment":"","sum":"","sum_comment":"","sum_foreign":""},"60":{"sum_foreign_comment":"","sum_comment_hidden":false,"sum":"","sum_comment":"","sum_foreign":""},"61":{"sum_foreign_comment":"","sum":"","sum_comment":"","sum_foreign":""},"62":{"sum_foreign_comment":"","sum":"650","sum_comment":"","sum_foreign":""},"63":{"sum_foreign_comment":"","sum":"","sum_comment":"","sum_hidden":false,"sum_comment_hidden":false,"sum_foreign":""},"64":{"sum_foreign_comment":"","sum":"","sum_comment":"","sum_hidden":false,"sum_comment_hidden":false,"sum_foreign":""}},"ft_src":"24977\n650\n227\n27283\nзаступник голови жашківського районного суду\nЧеркаська область\nЗагальний місцевий суд\nРоман\nШимчик О. І\nПодружжя\nШимчик В. Р.\nДитина\nШимчик В. Р.\nДитина\nВасильович\nШимчик Роман Васильович\nРоман Васильович Шимчик\nРоман Шимчик\nШимчик Роман Васильович\nШимчик\nШимчик Роман Васильович\n1498 куб. см., 86 к. с., 432.5 см\n2007\nChevrolet Aveo\n2014\n1498 куб. см., 86 к. с., 432.5 см\nChevrolet Aveo\n2007\n24\nм. Жашків, вул. Леніна 15\nЧеркаська область\n342\nм. Жашків, пров. Боженка 13\nЧеркаська область\nм. Жашків, ТОВ 'Дубрава' №2122\n1100\nЧеркаська область\n30\nЧеркаська область\nм. Жашків, вул. Леніна 32Г\n62\nЧеркаська область\nм. Жашків, пров. Боженка 13\n18.98\nЧеркаська область\nм. Жашків, вул. Леніна 26, кв. 31\nПодружжя\nШимчик О. І\nДитина\nШимчик В. Р.\nДитина\nШимчик В. Р.\nШимчик Роман Васильович\nРоман Васильович Шимчик\nРоман Шимчик\nШимчик Роман Васильович\nШимчик Роман Васильович\nРоман\nШимчик\nзаступник голови жашківського районного суду\nЗагальний місцевий суд\nЧеркаська область\nВасильович\n24977\n650\n27283\n227\n209036\n22386\n209036\n22386\n2014\n27283\n24977\n650\n227\nм. Жашків, вул. Леніна 26, кв. 31\nЧеркаська область\n18.98\nм. Жашків, вул. Леніна 32Г\nЧеркаська область\n30\nм. Жашків, вул. Леніна 15\n24\nЧеркаська область\nм. Жашків, пров. Боженка 13\n342\nЧеркаська область\nЧеркаська область\nм. Жашків, ТОВ 'Дубрава' №2122\n1100\nм. Жашків, пров. Боженка 13\n62\nЧеркаська область\nШимчик О. І\nПодружжя\nШимчик В. Р.\nДитина\nШимчик В. Р.\nДитина\nВасильович\nШимчик\nРоман\nШимчик Роман Васильович\nРоман Васильович Шимчик\nРоман Шимчик\nШимчик Роман Васильович\nЧеркаська область\nЗагальний місцевий суд\nзаступник голови жашківського районного суду\nШимчик Роман Васильович\n209036\n22386\n209036\n22386\n2007\nChevrolet Aveo\n1498 куб. см., 86 к. с., 432.5 см\n22386\n209036\n22386\n209036\nм. Жашків, вул. Леніна 26, кв. 31\nЧеркаська область\n18.98\nм. Жашків, вул. Леніна 15\nЧеркаська область\n24\nм. Жашків, пров. Боженка 13\nЧеркаська область\n342\nм. Жашків, ТОВ 'Дубрава' №2122\nЧеркаська область\n1100\nм. Жашків, пров. Боженка 13\nЧеркаська область\n62\nм. Жашків, вул. Леніна 32Г\nЧеркаська область\n30\n2014","general":{"inn":"","name":"Роман","patronymic_unclear":false,"last_name_hidden":false,"family":[{"inn":"","inn_hidden":true,"relations_hidden":false,"family_name":"Шимчик О. І","relations_other":"","relations":"Подружжя","name_hidden":false,"name_unclear":false},{"inn":"","relations":"Дитина","relations_other":"","inn_hidden":true,"family_name":"Шимчик В. Р.","name_hidden":false,"name_unclear":false},{"inn":"","relations":"Дитина","relations_other":"","inn_hidden":true,"family_name":"Шимчик В. Р.","name_hidden":false,"name_unclear":false}],"patronymic":"Васильович","inn_hidden":true,"family_raw":"","last_name":"Шимчик","post":{"post_unclear":false,"region_unclear":false,"post":"заступник голови жашківського районного суду","candidate":"","office_hidden":false,"region":"Черкаська область","post_hidden":false,"office":"Загальний місцевий суд","office_unclear":false},"last_name_unclear":false,"full_name":"Шимчик Роман Васильович","addresses":[{"place_district":"","place_city_hidden":true,"place_city":"","place_city_type_hidden":false,"place_district_hidden":true,"place_city_type":"","place_address_hidden":false,"place_address":"","place_hidden":true,"place":""}],"full_name_suggest":{"output":"Шимчик Роман Васильович","input":["Шимчик Роман Васильович","Роман Васильович Шимчик","Роман Шимчик"]}},"source":"VULYK","estate":{"23":[{"space_unclear":false,"costs":"","costs_comment":"","address_hidden":false,"region_hidden":false,"space_comment":"","space":"24","address":"м. Жашків, вул. Леніна 15","region":"Черкаська область","address_unclear":false,"costs_rent_comment":"","space_units":"м²","costs_rent":""},{"space_unclear":false,"costs":"","costs_comment":"","address_hidden":false,"region_hidden":false,"space_comment":"","space":"342","address":"м. Жашків, пров. Боженка 13","region":"Черкаська область","address_unclear":false,"costs_rent_comment":"","space_units":"м²","costs_rent":""},{"space":"1100","region":"Черкаська область","costs":"","costs_rent_comment":"","costs_comment":"","address_unclear":true,"space_comment":"","space_units":"м²","costs_rent":"","address":"м. Жашків, ТОВ 'Дубрава' №2122"},{"costs_rent":"","costs":"","costs_rent_comment":"","costs_comment":"","space_comment":"","space_units":"","space":"","address":""}],"24":[{"region_unclear":false,"space_unclear":false,"costs":"","costs_comment":"","address_hidden":false,"region_hidden":false,"space_comment":"","space_hidden":false,"space":"62","address":"м. Жашків, пров. Боженка 13","region":"Черкаська область","address_unclear":false,"costs_rent_comment":"","space_comment_hidden":false,"space_units":"м²","costs_rent":""}],"29":[{"space_hidden":false,"costs_property_comment":"","address_hidden":false,"region_hidden":false,"space_comment":"","space":"30","address":"м. Жашків, вул. Леніна 32Г","region":"Черкаська область","costs_property":"","costs_rent_comment":"","address_unclear":true,"space_units":"м²","space_units_unclear":false,"costs_rent":""}],"31":[{"space_unclear":false,"address_hidden":false,"region_hidden":false,"space_comment":"","space_hidden":false,"space":"18.98","address":"м. Жашків, вул. Леніна 26, кв. 31","region":"Черкаська область","costs_property":"","costs_rent_comment":"","space_units":"м²","costs_property_comment":"","costs_rent":""}]},"intro":{"declaration_year":"2014","isnotdeclaration":"","declaration_year_unclear":false,"declaration_year_hidden":false}}