{"income":{"5":{"family_comment":"","family_unclear":false,"value":"157452","family":"48052","comment":""},"6":{"value":"157452","family_comment":"","value_unclear":false,"family_unclear":false,"family":"","comment":""},"7":{"source_name_unclear":false,"value":"","family_comment":"","source_name":"","family":"","comment":"","source_name_hidden":false},"8":{"family_comment":"","value":"","family":"","comment":""},"9":{"family_comment":"","family_unclear":false,"value":"","family":"","comment":""},"10":{"family_comment":"","value":"","family":"","comment":""},"11":{"family_comment":"","value":"","family":"","comment":""},"12":{"family_comment":"","value":"","family":"","comment":""},"13":{"family_comment":"","value":"","family":"","comment":""},"14":{"family_comment":"","value":"","family":"","comment":""},"15":{"family_comment":"","value":"","family":"","comment":""},"16":{"family_comment":"","family_unclear":false,"value":"","family":"","comment":""},"17":{"family_comment":"","family_unclear":false,"value":"","family":"","comment":""},"18":{"family_comment":"","value":"","family":"","comment":""},"19":{"family_comment":"","value":"","family":"","comment":""},"20":{"family_comment":"","value":"","comment_unclear":false,"family":"48052","comment":""}},"vehicle":{"35":[{"brand_info":"1.6 л, КВт-59.5","sum":"","brand":"ВАЗ 2115","sum_comment":"","brand_unclear":false,"year":"2007","brand_hidden":false,"brand_info_hidden":false,"brand_info_unclear":false,"sum_rent_comment":"","sum_rent":""}]},"id":"vulyk_95_20","banks":{"45":[{"sum_units":"UAH","sum_foreign_comment_hidden":false,"sum_hidden":true,"sum_foreign_units_hidden":false,"sum":"4811","sum_units_hidden":false,"sum_foreign_comment":"","sum_foreign_hidden":false,"sum_comment":"","sum_comment_unclear":false,"sum_foreign_units":"UAH","sum_foreign":"","sum_comment_hidden":false}],"51":[{"sum_units":"UAH","sum_foreign_comment_hidden":false,"sum_hidden":true,"sum_foreign_units_hidden":false,"sum":"13000","sum_foreign":"","sum_foreign_comment":"","sum_foreign_hidden":false,"sum_comment":"","sum_foreign_units":"UAH","sum_comment_hidden":false,"sum_unclear":false}]},"declaration":{"additional_info_text":"","notfull_lostpages":"","date":"2016-03-23T00:00:00","notfull":"","additional_info":"","url":"http://static.declarations.com.ua/declarations/chosen_ones/judges_batch/21_zorkina_iuliia_volodymyrivna.pdf"},"liabilities":{"54":{"sum_foreign_comment":"","sum":"3925","sum_comment":"","sum_hidden":true,"sum_comment_hidden":false,"sum_unclear":true,"sum_foreign":""},"55":{"sum_foreign_comment":"","sum":"","sum_comment":"","sum_foreign":""},"56":{"sum_foreign_comment":"","sum":"","sum_comment":"","sum_foreign":""},"57":{"sum_foreign_comment":"","sum":"","sum_comment":"","sum_hidden":false,"sum_comment_hidden":false,"sum_unclear":false,"sum_foreign":""},"58":{"sum_foreign_comment":"","sum":"","sum_comment":"","sum_hidden":false,"sum_comment_hidden":false,"sum_unclear":false,"sum_foreign":""},"59":{"sum_foreign_comment":"","sum":"","sum_comment":"","sum_foreign":""},"60":{"sum_foreign_comment":"","sum":"","sum_comment":"","sum_hidden":false,"sum_comment_hidden":false,"sum_foreign":""},"61":{"sum_foreign_comment":"","sum":"","sum_comment":"","sum_foreign":""},"62":{"sum_foreign_comment":"","sum":"","sum_comment":"","sum_unclear":false,"sum_foreign":""},"63":{"sum_foreign_comment":"","sum":"","sum_comment":"","sum_unclear":false,"sum_foreign":""},"64":{"sum_foreign_comment":"","sum":"","sum_comment":"","sum_foreign":""}},"ft_src":"3925\nХарків\nХарківська область\nЗоркіна Юлія Володимирівна\nсуддя харківського окружного адміністративного суду\nХарківська область\nАдміністративний місцевий суд\nЮлія\nПанаріна Т. Г\nБатьки\nЗоркіна Юлія Володимирівна\nЮлія Володимирівна Зоркіна\nЮлія Зоркіна\nЗоркіна Юлія Володимирівна\nЗоркіна\nВолодимирівна\nВАЗ 2115\n1.6 л, КВт-59.5\n2007\nчастка у власності\nХарківська область\nЧугуїв\n20.9\nХарківська область\nХарків\n35\nХарківська область\nчастка у власності\nм. Чугуїв\n20.9\nХарківська область\nХарківська область\nу користуванні\nХарків\n35\n13000\n4811\n2015\nВАЗ 2115\n1.6 л, КВт-59.5\n2007\n2015\nВолодимирівна\nБатьки\nПанаріна Т. Г\nЗоркіна Юлія Володимирівна\nЮлія Володимирівна Зоркіна\nЮлія Зоркіна\nЗоркіна Юлія Володимирівна\nЮлія\nХарків\nХарківська область\nЗоркіна Юлія Володимирівна\nЗоркіна\nАдміністративний місцевий суд\nсуддя харківського окружного адміністративного суду\nХарківська область\n3925\n157452\n48052\n157452\n48052\nчастка у власності\nЧугуїв\nХарківська область\n20.9\nХарків\nХарківська область\n35\n20.9\nчастка у власності\nм. Чугуїв\nХарківська область\n35\nу користуванні\nХарків\nХарківська область\nХарківська область\n4811\n13000\n3925\n157452\n48052\n157452\n48052\nПанаріна Т. Г\nБатьки\nХарківська область\nХарків\nВолодимирівна\nЗоркіна\nХарківська область\nАдміністративний місцевий суд\nсуддя харківського окружного адміністративного суду\nЗоркіна Юлія Володимирівна\nЗоркіна Юлія Володимирівна\nЮлія Володимирівна Зоркіна\nЮлія Зоркіна\nЗоркіна Юлія Володимирівна\nЮлія\nВАЗ 2115\n1.6 л, КВт-59.5\n2007\n48052\n48052\n157452\n157452\nчастка у власності\nЧугуїв\nХарківська область\n20.9\nХарків\nХарківська область\n35\nчастка у власності\nм. Чугуїв\nХарківська область\n20.9\nу користуванні\nХарків\nХарківська область\n35\nХарківська область\n4811\n13000\n2015","general":{"inn":"","inn_hidden":true,"last_name":"Зоркіна","post":{"post":"суддя харківського окружного адміністративного суду","region":"Харківська область","candidate":"","office_hidden":false,"office":"Адміністративний місцевий суд","office_unclear":false},"name":"Юлія","full_name":"Зоркіна Юлія Володимирівна","family_raw":"","addresses":[{"place_address":"","place_district_hidden":false,"place_city_type":"Місто","place_city_hidden":false,"place_address_unclear":false,"place_city_type_hidden":false,"place_city":"Харків","place":"Харківська область","place_district":"","place_address_hidden":true,"place_hidden":false,"place_city_unclear":false}],"family":[{"inn":"","inn_hidden":true,"inn_unclear":false,"relations_hidden":false,"relations_other":"","relations":"Батьки","name_hidden":true,"family_name":"Панаріна Т. Г","name_unclear":false}],"full_name_suggest":{"output":"Зоркіна Юлія Володимирівна","input":["Зоркіна Юлія Володимирівна","Юлія Володимирівна Зоркіна","Юлія Зоркіна"]},"patronymic":"Володимирівна"},"source":"VULYK","estate":{"25":[{"space_unclear":false,"costs":"","costs_comment":"","address_hidden":true,"region_hidden":false,"space_comment":"частка у власності","space_hidden":false,"space":"20.9","address":"м. Чугуїв","region":"Харківська область","address_unclear":false,"costs_rent_comment":"","space_comment_unclear":false,"space_units":"м²","costs_rent":""},{"space_hidden":false,"costs":"","costs_comment":"","address_hidden":false,"region_hidden":false,"space_comment":"у користуванні","space":"35","address":"Харків","region":"Харківська область","address_unclear":false,"costs_rent_comment":"","space_units":"м²","costs_rent":""}],"31":[{"space_unclear":false,"address_hidden":true,"region_hidden":false,"space_comment":"частка у власності","space":"20.9","address":"Чугуїв","region":"Харківська область","costs_property":"","costs_rent_comment":"","space_comment_unclear":false,"space_units":"м²","costs_property_comment":"","costs_rent":""},{"address_hidden":false,"region_hidden":false,"space_comment":"","space":"35","address":"Харків","region":"Харківська область","costs_property":"","costs_rent_comment":"","space_comment_unclear":false,"space_units":"м²","costs_property_comment":"","costs_rent":""}],"32":[{"address_hidden":false,"region_hidden":false,"space_comment":"","space":"","address":"","region":"Харківська область","costs_property":"","costs_rent_comment":"","address_unclear":false,"space_units":"м²","costs_property_comment":"","costs_rent":""}]},"intro":{"declaration_year":"2015","isnotdeclaration":""}}