{"income":{"5":{"value":"214563","family_comment":"","value_unclear":false,"family_hidden":false,"value_hidden":false,"family_unclear":false,"comment_unclear":false,"comment":"","family":""},"6":{"value":"202551","family_comment":"","value_unclear":false,"family_hidden":false,"value_hidden":false,"family_unclear":false,"comment_unclear":false,"comment":"","family":""},"7":{"source_name_unclear":false,"value":"","family_comment":"","source_name":"","family":"","comment":""},"8":{"family_comment":"","value":"","family":"","comment":""},"9":{"value":"","value_unclear":false,"comment_hidden":false,"family_comment":"","comment_unclear":false,"comment":"","family":""},"10":{"value":"","comment_unclear":false,"value_hidden":false,"family_comment":"","family":"","comment":""},"11":{"family_comment":"","value":"","family":"","comment":""},"12":{"family_comment":"","value":"","family":"","comment":""},"13":{"family_comment":"","value":"","family":"","comment":""},"14":{"family_comment":"","value":"","family":"","comment":""},"15":{"family_comment":"","value":"","family":"","comment":""},"16":{"family_comment":"","value":"","family":"","comment":""},"17":{"family_comment":"","value":"","family":"","comment":""},"18":{"value":"","family_hidden":false,"value_hidden":false,"family_comment":"","family":"","comment":""},"19":{"family_comment":"","value":"","family":"","comment":""},"20":{"value":"12012","family_comment":"","value_unclear":false,"family_hidden":false,"value_hidden":false,"family_unclear":false,"family":"","comment":"щомісячна допомога при народженні дитини"}},"vehicle":{"35":[{"year_hidden":false,"brand_info":"1998 куб. см., право користування","sum_rent_comment":"","year":"2003","brand_info_unclear":false,"year_unclear":false,"sum_rent":"","sum":"","brand":"Toyota Rav 4","sum_comment":"","brand_unclear":false,"brand_hidden":false}],"40":[{"brand_info":"1998 куб. см., право користування","sum_rent_comment":"","brand":"Toyota Rav 4","sum_comment":"","brand_unclear":false,"year":"2003","brand_info_unclear":false,"year_unclear":false,"sum":"","sum_rent":""}]},"id":"vulyk_66_151","declaration":{"additional_info_text":"","notfull_lostpages":"","date":"2015-03-30T00:00:00","notfull":"","additional_info":"","url":"http://static.declarations.com.ua/declarations/chosen_ones/mega_batch/otvinovskyi_pavlo_leonidovych.pdf"},"liabilities":{"54":{"sum_foreign_comment":"","sum":"","sum_comment":"","sum_comment_unclear":false,"sum_comment_hidden":false,"sum_unclear":false,"sum_foreign":""},"55":{"sum_foreign_comment":"","sum":"","sum_comment":"","sum_foreign":""},"56":{"sum_foreign_comment":"","sum_foreign_hidden":false,"sum_comment":"","sum_hidden":false,"sum_comment_hidden":false,"sum":"25000","sum_foreign":""},"57":{"sum_foreign_comment":"","sum":"","sum_comment":"","sum_comment_unclear":false,"sum_hidden":false,"sum_comment_hidden":false,"sum_unclear":false,"sum_foreign":""},"58":{"sum_foreign_comment":"","sum":"","sum_comment":"","sum_comment_unclear":false,"sum_unclear":false,"sum_foreign":""},"59":{"sum_foreign_comment":"","sum_foreign_hidden":false,"sum_comment":"","sum_comment_unclear":false,"sum_hidden":false,"sum":"","sum_foreign":""},"60":{"sum_foreign_comment":"","sum":"","sum_comment":"","sum_comment_unclear":false,"sum_foreign":""},"61":{"sum_foreign_comment":"","sum":"","sum_comment":"","sum_foreign":""},"62":{"sum_foreign_comment":"","sum_foreign_hidden":false,"sum_comment":"","sum_hidden":false,"sum":"","sum_unclear":false,"sum_foreign":""},"63":{"sum_foreign_comment":"","sum":"","sum_comment":"","sum_comment_unclear":false,"sum_comment_hidden":false,"sum_unclear":false,"sum_foreign":""},"64":{"sum_foreign_comment":"","sum":"","sum_comment":"","sum_comment_unclear":false,"sum_foreign":""}},"ft_src":"25000\nсуддя подільського районного суду м. києва\nм. Київ\nЗагальний місцевий суд\nПавло\nОтвіновська Т. А., 28. 04. 1982\nПодружжя\nОтвіновська П. П., 14. 09. 2007\nДитина\nОтвіновська К. П., 27. 12. 2012\nДитина\nЛеонідович\nОтвіновський Павло Леонідович\nПавло Леонідович Отвіновський\nПавло Отвіновський\nОтвіновський Павло Леонідович\nОтвіновський Павло Леонідович\nОтвіновський\n1998 куб. см., право користування\nToyota Rav 4\n2003\n1998 куб. см., право користування\nToyota Rav 4\n2003\n28\n1/3 ч.\n43.9\n28\n2014\n202551\n214563\nщомісячна допомога при народженні дитини\n12012\n1998 куб. см., право користування\nToyota Rav 4\n2003\n1998 куб. см., право користування\n2003\nToyota Rav 4\n28\n43.9\n1/3 ч.\n28\nЗагальний місцевий суд\nсуддя подільського районного суду м. києва\nм. Київ\nПодружжя\nОтвіновська Т. А., 28. 04. 1982\nДитина\nОтвіновська П. П., 14. 09. 2007\nДитина\nОтвіновська К. П., 27. 12. 2012\nОтвіновський Павло Леонідович\nПавло Леонідович Отвіновський\nПавло Отвіновський\nОтвіновський Павло Леонідович\nОтвіновський Павло Леонідович\nПавло\nОтвіновський\nЛеонідович\n25000\n202551\n12012\nщомісячна допомога при народженні дитини\n214563\n2014\n25000\nОтвіновська Т. А., 28. 04. 1982\nПодружжя\nОтвіновська П. П., 14. 09. 2007\nДитина\nОтвіновська К. П., 27. 12. 2012\nДитина\nЛеонідович\nОтвіновський\nПавло\nОтвіновський Павло Леонідович\nПавло Леонідович Отвіновський\nПавло Отвіновський\nОтвіновський Павло Леонідович\nм. Київ\nсуддя подільського районного суду м. києва\nЗагальний місцевий суд\nОтвіновський Павло Леонідович\nToyota Rav 4\n1998 куб. см., право користування\n2003\n2003\n1998 куб. см., право користування\nToyota Rav 4\n12012\nщомісячна допомога при народженні дитини\n214563\n202551\n28\n1/3 ч.\n43.9\n28\n2014","general":{"inn":"","name":"Павло","last_name_hidden":false,"family":[{"inn":"","inn_hidden":true,"relations_hidden":false,"family_name":"Отвіновська Т. А., 28. 04. 1982","relations_other":"","relations":"Подружжя","name_hidden":false,"name_unclear":false},{"inn":"","inn_hidden":false,"relations_unclear":false,"relations_hidden":false,"relations_other":"","relations":"Дитина","name_hidden":false,"family_name":"Отвіновська П. П., 14. 09. 2007","name_unclear":false},{"inn":"","inn_hidden":false,"relations_hidden":false,"family_name":"Отвіновська К. П., 27. 12. 2012","relations_other":"","relations":"Дитина","name_hidden":false,"name_unclear":false}],"patronymic":"Леонідович","inn_hidden":true,"family_raw":"","inn_unclear":false,"post":{"post_unclear":false,"post":"суддя подільського районного суду м. києва","candidate":"","office_hidden":false,"region":"м. Київ","office":"Загальний місцевий суд","office_unclear":false},"full_name_suggest":{"output":"Отвіновський Павло Леонідович","input":["Отвіновський Павло Леонідович","Павло Леонідович Отвіновський","Павло Отвіновський"]},"full_name":"Отвіновський Павло Леонідович","addresses":[{"place_city_type_unclear":false,"place_address":"","place_district_hidden":true,"place_city_type":"","place_address_hidden":true,"place_address_unclear":false,"place_city_type_hidden":true,"place":"","place_district":"","place_unclear":false,"place_city":"","place_city_unclear":false,"place_hidden":true,"place_city_hidden":true,"place_district_unclear":false}],"last_name":"Отвіновський","last_name_unclear":false},"source":"VULYK","estate":{"25":[{"region_unclear":false,"space_hidden":false,"costs":"","costs_comment":"","costs_hidden":false,"address_hidden":true,"region_hidden":true,"space_comment":"","space_unclear":false,"space":"28","space_units_hidden":false,"region":"","address_unclear":false,"costs_rent_comment":"","space_comment_unclear":false,"space_units":"м²","address":"","costs_rent":""}],"31":[{"space_unclear":false,"address_hidden":true,"region_hidden":true,"space_comment":"","space_hidden":false,"space":"28","address":"","region":"","costs_property":"","costs_rent_comment":"","space_comment_unclear":false,"space_comment_hidden":false,"space_units":"м²","costs_property_comment":"","costs_rent":""},{"costs_rent":"","region":"","costs_property":"","costs_rent_comment":"","address_hidden":true,"region_hidden":true,"space_comment":"1/3 ч.","costs_property_comment":"","space_units":"","space":"43.9","address":""}]},"intro":{"declaration_year":"2014","isnotdeclaration":"","declaration_year_unclear":false}}