{"id":"vulyk_97_198","ft_src":"1396\nHyundai Accent\n2013\n23\n301\n27.5\n54\n54\nВАТ 'Одеський завод поршневих кілець', ПАТ 'Універмаг Україна', ВАТ 'Чорномор'\n76\nВАТ 'Чорномор'\n89\nАТ 'Ощадбанк'\n1182\nАТ Ощадбанк, ПАТ Укрсоцбанк\n2475\n2014\n1396\nHyundai Accent\n2013\n2014\nМихайлюк Сергій Іванович\nСергій Іванович Михайлюк\nСергій Михайлюк\nМихайлюк Сергій Іванович\nСергій\nПодружжя\nМихайлюк А. В\nДитина\nМихайлюк С. С\nМихайлюк Сергій Іванович\nМихайлюк\nГосподарський місцевий суд\nЧернігівська область\nсуддя господарського суду чернігівської області\nІванович\n35895\nПАТ 'Укрсоцбанк', ПАТ 'Приватбанк'\n34195\nПАТ 'Укрсоцбанк', ПАТ 'Приватбанк',\n8006\nСК 'Арсенал Страхування'\n1260\nАТ Дельта банк\n205324\n62693\n9462\n217504\n72155\n12180\n1806\n23\n54\n301\n54\n27.5\n2475\nАТ Ощадбанк, ПАТ Укрсоцбанк\nАТ 'Ощадбанк'\n1182\n89\nВАТ 'Чорномор'\n76\nВАТ 'Одеський завод поршневих кілець', ПАТ 'Універмаг Україна', ВАТ 'Чорномор'\nПАТ 'Укрсоцбанк', ПАТ 'Приватбанк'\n35895\nПАТ 'Укрсоцбанк', ПАТ 'Приватбанк',\n34195\nСК 'Арсенал Страхування'\n8006\nАТ Дельта банк\n1260\n62693\n205324\n1806\n12180\n72155\n217504\n9462\nПодружжя\nМихайлюк А. В\nМихайлюк С. С\nДитина\nІванович\nМихайлюк\nСергій\nМихайлюк Сергій Іванович\nСергій Іванович Михайлюк\nСергій Михайлюк\nМихайлюк Сергій Іванович\nЧернігівська область\nГосподарський місцевий суд\nсуддя господарського суду чернігівської області\nМихайлюк Сергій Іванович","estate":{"24":[{"address":"","space_units":"м²","space_hidden":false,"space_unclear":false,"region_hidden":true,"costs_rent_comment":"","space_comment":"","address_hidden":false,"costs":"","address_unclear":false,"space_comment_unclear":false,"costs_comment":"","space":"","region_unclear":false,"region":"","costs_rent":""}],"25":[{"address":"","space_units":"м²","space_hidden":false,"space_unclear":false,"region_hidden":true,"costs_rent_comment":"","space_comment":"","address_hidden":true,"space_comment_hidden":false,"costs":"","space_comment_unclear":false,"costs_comment":"","space":"54","region_unclear":false,"region":"","costs_rent":""}],"27":[{"address":"","space_units":"м²","costs_comment":"","region":"","region_hidden":true,"space_comment":"","address_hidden":true,"costs":"","costs_rent_comment":"","space":"23","region_unclear":false,"costs_rent":""}],"29":[{"costs_property_comment":"","address":"","space_units":"м²","space_unclear":false,"region_hidden":true,"costs_property":"","space_comment":"","address_hidden":true,"address_unclear":false,"space_comment_unclear":false,"costs_rent_comment":"","space":"301","region_unclear":false,"region":"","costs_rent":""}],"30":[{"costs_property_comment":"","address":"","space_units":"м²","space_comment":"","region_hidden":true,"costs_property":"","region":"","address_hidden":false,"address_unclear":false,"costs_rent_comment":"","space":"","costs_rent":""}],"31":[{"costs_property_comment":"","address":"","space_units":"м²","space_hidden":false,"space_unclear":false,"region_hidden":true,"costs_property":"","space_comment":"","address_hidden":true,"space_comment_hidden":false,"costs_rent_comment":"","space":"54","region":"","costs_rent":""}],"32":[{"costs_property_comment":"","address":"","space_units":"м²","space_hidden":false,"space_comment":"","region_hidden":true,"costs_property":"","region":"","address_hidden":true,"address_unclear":false,"costs_rent_comment":"","space":"27.5","costs_rent":""}]},"vehicle":{"35":[{"year_hidden":false,"brand_info":"1396","brand_unclear":false,"sum_rent_comment":"","brand_hidden":false,"year":"2013","sum_comment":"","brand_info_hidden":false,"sum_rent":"","brand":"Hyundai Accent","brand_info_unclear":false,"sum":""}]},"source":"VULYK","income":{"5":{"family_comment":"","value":"217504","family":"72155","comment":""},"6":{"family_comment":"","family":"62693","comment":"","value_unclear":false,"family_unclear":false,"comment_hidden":false,"value":"205324"},"7":{"family":"","family_comment":"","value":"","comment":"","source_name":""},"8":{"family_comment":"","value":"","family":"","comment":""},"9":{"family_comment":"","value":"","family_unclear":false,"family":"","comment":""},"10":{"family_comment":"","value":"12180","family":"1806","comment":"","value_unclear":false},"11":{"family_comment":"","value":"","family":"","comment":""},"12":{"family_comment":"","value":"","family":"","comment":""},"13":{"family_comment":"","value":"","family":"","comment":""},"14":{"family_comment":"","value":"","family":"","comment":""},"15":{"family_comment":"","value":"","family":"","comment":""},"16":{"family_comment":"","value":"","family":"","comment":""},"17":{"family_comment":"","value":"","family":"","comment":""},"18":{"family_comment":"","value":"","family":"","comment":""},"19":{"family_comment":"","value":"","family":"","comment":""},"20":{"family_comment":"","comment":"","family":"9462","value_unclear":false,"comment_unclear":false,"value":"","family_hidden":false,"family_comment_unclear":false}},"banks":{"45":[{"sum_comment_unclear":false,"sum_units":"UAH","sum_foreign_units":"UAH","sum_hidden":false,"sum":"2475","sum_foreign_comment":"","sum_comment":"АТ Ощадбанк, ПАТ Укрсоцбанк","sum_unclear":false,"sum_foreign":"","sum_comment_hidden":false}],"47":[{"sum_units":"UAH","sum_comment":"ВАТ 'Одеський завод поршневих кілець', ПАТ 'Універмаг Україна', ВАТ 'Чорномор'","sum_foreign_units":"UAH","sum":"76","sum_foreign_comment":"","sum_foreign":"","sum_comment_hidden":false}],"51":[{"sum_comment_unclear":false,"sum_units":"UAH","sum_foreign_units":"UAH","sum_hidden":false,"sum":"1182","sum_foreign_comment":"","sum_comment":"АТ 'Ощадбанк'","sum_unclear":false,"sum_foreign":"","sum_comment_hidden":false}],"52":[{"sum_comment_unclear":true,"sum_units":"UAH","sum_foreign_units":"UAH","sum":"89","sum_foreign_comment":"","sum_comment":"ВАТ 'Чорномор'","sum_foreign":"","sum_comment_hidden":false}]},"declaration":{"notfull_lostpages":"","additional_info_text":"","additional_info":"","date":"2015-03-25T00:00:00","notfull":"","url":"http://static.declarations.com.ua/declarations/chosen_ones/judges_batch/4113_mykhailiuk_serhii_ivanovych.pdf"},"general":{"family":[{"inn":"","family_name":"Михайлюк А. В","relations_other":"","name_unclear":false,"inn_hidden":true,"name_hidden":true,"relations":"Подружжя"},{"inn":"","family_name":"Михайлюк С. С","name_unclear":true,"inn_hidden":true,"name_hidden":false,"relations":"Дитина"}],"family_raw":"","name":"Сергій","full_name_suggest":{"input":["Михайлюк Сергій Іванович","Сергій Іванович Михайлюк","Сергій Михайлюк"],"output":"Михайлюк Сергій Іванович"},"patronymic":"Іванович","inn_hidden":true,"addresses":[{"place_city_type":"","place_city_type_hidden":true,"place_hidden":true,"place_city_hidden":true,"place_district_hidden":true,"place_district":"","place_city_unclear":false,"place":"","place_city":"","place_address_hidden":true,"place_address":""}],"last_name_hidden":false,"patronymic_hidden":false,"inn":"","inn_unclear":false,"last_name":"Михайлюк","full_name":"Михайлюк Сергій Іванович","post":{"post_hidden":false,"office":"Господарський місцевий суд","post":"суддя господарського суду чернігівської області","office_unclear":false,"region_unclear":false,"region":"Чернігівська область"},"name_hidden":false},"liabilities":{"54":{"sum_comment_unclear":false,"sum_comment":"СК 'Арсенал Страхування'","sum_hidden":false,"sum":"8006","sum_foreign_comment":"","sum_foreign":"","sum_unclear":false,"sum_comment_hidden":false},"55":{"sum_comment":"","sum_foreign_comment":"","sum_foreign":"","sum":""},"56":{"sum_comment":"","sum_foreign_comment":"","sum_foreign":"","sum":""},"57":{"sum_comment_unclear":false,"sum_comment":"ПАТ 'Укрсоцбанк', ПАТ 'Приватбанк',","sum_hidden":false,"sum":"34195","sum_foreign_comment":"","sum_foreign":"","sum_unclear":false,"sum_comment_hidden":false},"58":{"sum_comment_unclear":false,"sum_comment":"ПАТ 'Укрсоцбанк', ПАТ 'Приватбанк'","sum_hidden":false,"sum":"35895","sum_foreign_comment":"","sum_foreign":"","sum_unclear":false,"sum_comment_hidden":false},"59":{"sum_comment":"","sum_foreign_comment":"","sum_foreign":"","sum":""},"60":{"sum_comment_unclear":false,"sum_comment":"","sum_hidden":false,"sum":"","sum_foreign_comment":"","sum_foreign":"","sum_comment_hidden":false},"61":{"sum_comment":"","sum_foreign_comment":"","sum_foreign":"","sum":""},"62":{"sum_comment":"","sum_foreign_comment":"","sum_foreign":"","sum_unclear":false,"sum":""},"63":{"sum_comment":"АТ Дельта банк","sum_foreign_comment":"","sum_foreign":"","sum_hidden":false,"sum":"1260"},"64":{"sum_comment":"","sum_foreign_comment":"","sum_foreign":"","sum":""}},"intro":{"isnotdeclaration":"","declaration_year":"2014"}}