{"income":{"5":{"value":"290330","family_comment":"","value_unclear":false,"value_hidden":false,"family_unclear":false,"family":"236181","comment":""},"6":{"value":"290306","family_hidden":false,"value_hidden":false,"family_comment":"","family":"","comment":"","family_comment_hidden":false},"7":{"value":"","value_unclear":false,"family_hidden":false,"value_hidden":false,"family_comment":"","source_name":"","family":"","comment":"","source_name_hidden":false},"8":{"value":"","comment_hidden":false,"family_hidden":false,"value_hidden":false,"family_comment":"","family":"","comment":""},"9":{"value":"","family_comment":"","comment_hidden":false,"family_hidden":false,"value_hidden":false,"family_unclear":false,"family":"1026","comment":""},"10":{"value":"","comment_hidden":false,"family_hidden":false,"value_hidden":false,"family_comment":"","family":"","comment":""},"11":{"value":"","value_unclear":false,"comment_hidden":false,"family_hidden":false,"value_hidden":false,"family_comment":"","family":"","comment":""},"12":{"value":"","comment_hidden":false,"family_hidden":false,"value_hidden":false,"family_comment":"","family":"","comment":""},"13":{"value":"","comment_hidden":false,"family_hidden":false,"value_hidden":false,"family_comment":"","family":"","comment":""},"14":{"value":"","comment_hidden":false,"family_hidden":false,"value_hidden":false,"family_comment":"","family":"","comment":""},"15":{"value":"","comment_hidden":false,"family_hidden":false,"value_hidden":false,"family_comment":"","family":"28810","comment":""},"16":{"value":"","comment_hidden":false,"family_hidden":false,"value_hidden":false,"family_comment":"","family":"60000","comment":""},"17":{"value":"","comment_hidden":false,"family_hidden":false,"value_hidden":false,"family_comment":"","family":"","comment":""},"18":{"value":"","value_unclear":false,"comment_hidden":false,"family_hidden":false,"value_hidden":false,"family_comment":"","family":"","comment":""},"19":{"value":"","comment_hidden":false,"family_hidden":false,"value_hidden":false,"family_comment":"","family":"","comment":""},"20":{"value":"24","value_unclear":true,"family_comment":"","comment_unclear":false,"comment":"","family":"146345"}},"vehicle":{"39":[{"brand_info":"мопед, об'єм циліндрів 48","sum_rent_comment":"","brand":"Mustang","sum_comment":"","brand_unclear":true,"year":"2008","brand_hidden":false,"sum":"","sum_rent":""}],"40":[{"year_hidden":false,"brand_info":"Об'єм циліндрів 2700 , потужність 136","sum":"","brand":"Toyota Venza","sum_comment":"","brand_unclear":false,"year":"2013","brand_hidden":false,"brand_info_unclear":false,"sum_rent_comment":"","sum_rent":""},{"brand_info":"Об'єм циліндрів 1500 , потужність 77","sum_rent_comment":"","brand":"Daihatsu Terios","sum_comment":"","year":"2011","brand_info_unclear":false,"sum":"","sum_rent":""}]},"id":"vulyk_1_635","banks":{"51":[{"sum_foreign_comment":"","sum_units":"UAH","sum_comment":"","sum_hidden":false,"sum_foreign_units":"UAH","sum_foreign":"","sum_comment_hidden":false,"sum_units_hidden":false,"sum":"10176","sum_unclear":false}]},"declaration":{"additional_info_text":"","notfull_lostpages":"","date":"2014-03-24T00:00:00","notfull":"","additional_info":"","url":"http://static.declarations.com.ua/declarations/chosen_ones/judges_batch/313_furyk_iurii_petrovych.pdf"},"liabilities":{"54":{"sum_foreign_comment":"","sum":"","sum_comment":"","sum_hidden":false,"sum_comment_hidden":false,"sum_foreign_hidden":false,"sum_foreign":""},"55":{"sum_foreign_comment":"","sum":"","sum_foreign":"","sum_comment":"","sum_hidden":false},"56":{"sum_foreign_comment":"","sum":"","sum_comment":"","sum_foreign":""},"57":{"sum_foreign_comment":"","sum_unclear":false,"sum":"","sum_comment":"","sum_hidden":false,"sum_comment_hidden":false,"sum_foreign_hidden":false,"sum_foreign":""},"58":{"sum_foreign_comment":"","sum_unclear":false,"sum":"","sum_comment":"","sum_hidden":false,"sum_comment_hidden":false,"sum_foreign_hidden":false,"sum_foreign":""},"59":{"sum_foreign_comment":"","sum":"","sum_foreign":"","sum_comment":"","sum_hidden":false},"60":{"sum_foreign_comment":"","sum_unclear":false,"sum":"28354","sum_comment":"","sum_hidden":false,"sum_comment_hidden":false,"sum_foreign_hidden":false,"sum_foreign":""},"61":{"sum_foreign_comment":"","sum":"","sum_foreign":"","sum_comment":"","sum_hidden":false},"62":{"sum_foreign_comment":"","sum":"","sum_comment":"","sum_hidden":false,"sum_comment_hidden":false,"sum_foreign":""},"63":{"sum_foreign_comment":"","sum":"","sum_foreign":"","sum_comment":"","sum_hidden":false},"64":{"sum_foreign_comment":"","sum":"","sum_foreign":"","sum_comment":"","sum_hidden":false}},"ft_src":"Mustang\nмопед, об'єм циліндрів 48\n2008\nToyota Venza\nОб'єм циліндрів 2700 , потужність 136\n2013\nОб'єм циліндрів 1500 , потужність 77\n2011\nDaihatsu Terios\n86\n108\n80\n108\n10176\n2013\nОб'єм циліндрів 2700 , потужність 136\nToyota Venza\n2013\nОб'єм циліндрів 1500 , потужність 77\nDaihatsu Terios\n2011\nмопед, об'єм циліндрів 48\n2008\nMustang\n86\n108\n80\n108\nБатьки\nФурик Марія Петрівна\nДитина\nФурик Всеволод Юрійович\nПодружжя\nФурик Валентина Борисівна\nТкаченко Микола Сергійович\nІнше\nсин дружини\nФурик Юрій Петрович\nЮрій Петрович Фурик\nЮрій Фурик\nФурик Юрій Петрович\nФурик Юрій Петрович\nЮрій\nПетрович\nВищий спеціалізований суд з розгляду цивільних і кримінальних справ\nсуддя вищого спеціалізованого суду україни з розгляду цивільних і кримінальних справ\nЗагальнодержавний регіон\nФурик\n28354\n290306\n24\n146345\n28810\n290330\n236181\n60000\n1026\n10176\n2013\n28354\n290306\n28810\n1026\n236181\n290330\n60000\n146345\n24\nФурик Марія Петрівна\nБатьки\nДитина\nФурик Всеволод Юрійович\nФурик Валентина Борисівна\nПодружжя\nІнше\nсин дружини\nТкаченко Микола Сергійович\nПетрович\nФурик\nЮрій\nФурик Юрій Петрович\nЮрій Петрович Фурик\nЮрій Фурик\nФурик Юрій Петрович\nЗагальнодержавний регіон\nсуддя вищого спеціалізованого суду україни з розгляду цивільних і кримінальних справ\nВищий спеціалізований суд з розгляду цивільних і кримінальних справ\nФурик Юрій Петрович","general":{"inn":"","name":"Юрій","last_name":"Фурик","family":[{"inn":"","inn_hidden":true,"relations_unclear":false,"relations_hidden":false,"relations_other":"","relations":"Батьки","name_hidden":false,"family_name":"Фурик Марія Петрівна","name_unclear":false},{"inn":"","inn_hidden":false,"relations_unclear":false,"relations_hidden":false,"relations_other":"","relations":"Дитина","name_hidden":false,"family_name":"Фурик Всеволод Юрійович","name_unclear":false},{"inn":"","inn_hidden":false,"family_name":"Фурик Валентина Борисівна","relations_other":"","relations":"Подружжя","name_hidden":false,"name_unclear":false},{"inn":"","relations_other":"син дружини","relations":"Інше","inn_hidden":false,"family_name":"Ткаченко Микола Сергійович"}],"inn_hidden":true,"family_raw":"","inn_unclear":false,"post":{"post_unclear":false,"post":"суддя вищого спеціалізованого суду україни з розгляду цивільних і кримінальних справ","candidate":"","office_hidden":false,"region":"Загальнодержавний регіон","region_hidden":false,"office":"Вищий спеціалізований суд з розгляду цивільних і кримінальних справ","office_unclear":false},"full_name_suggest":{"output":"Фурик Юрій Петрович","input":["Фурик Юрій Петрович","Юрій Петрович Фурик","Юрій Фурик"]},"full_name":"Фурик Юрій Петрович","patronymic":"Петрович","last_name_unclear":false,"name_unclear":false},"source":"VULYK","estate":{"25":[{"space_unclear":false,"costs":"","costs_comment":"","address_hidden":false,"region_hidden":true,"space_comment":"","space_hidden":false,"space":"80","address":"","region":"","costs_rent_comment":"","space_comment_unclear":false,"space_comment_hidden":false,"space_units":"м²","costs_rent":""},{"space_unclear":false,"costs":"","costs_comment":"","address_hidden":false,"region_hidden":false,"space_comment":"","space":"108","address":"","region":"","address_unclear":false,"costs_rent_comment":"","space_comment_hidden":false,"space_units":"м²","costs_rent":""}],"31":[{"space_unclear":false,"address_hidden":false,"region_hidden":true,"space_comment":"","space_hidden":false,"space":"86","address":"","region":"","costs_property":"","costs_rent_comment":"","space_comment_unclear":false,"space_units":"м²","costs_property_comment":"","costs_rent":""},{"costs_rent":"","region":"","costs_property":"","costs_rent_comment":"","space_comment_unclear":false,"region_hidden":false,"space_comment":"","costs_property_comment":"","space_units":"м²","space":"108","address":""}]},"intro":{"declaration_year":"2013","isnotdeclaration":"","declaration_year_unclear":false,"declaration_year_hidden":false}}