{"income":{"5":{"value":"190490","family_comment":"","value_unclear":false,"family":"54522","family_unclear":false,"comment_unclear":false,"comment":"","family_comment_unclear":false},"6":{"value":"178310","family_comment":"","value_unclear":false,"family_unclear":false,"family":"53304","comment":""},"7":{"source_name_unclear":false,"value":"","value_unclear":false,"family_comment":"","source_name":"","family":"","comment":"","source_name_hidden":false},"8":{"family_comment":"","value":"","family":"","comment":""},"9":{"family_comment":"","value":"","family":"","comment":""},"10":{"family_comment":"","value":"12180","value_unclear":false,"family":"1218","comment":""},"11":{"value":"","value_unclear":false,"value_hidden":false,"family_comment":"","family":"","comment":""},"12":{"family_comment":"","value":"","family":"","comment":"","value_hidden":false},"13":{"family_comment":"","value":"","family":"","comment":""},"14":{"family_comment":"","value":"","family":"","comment":""},"15":{"family_comment":"","value":"","family":"","comment":""},"16":{"family_comment":"","value":"","family":"","comment":""},"17":{"family_comment":"","value":"","family":"","comment":""},"18":{"family_comment":"","value":"","family":"","comment":""},"19":{"family_comment":"","family_unclear":false,"value":"","family":"","comment":""},"20":{"family_comment":"","family_unclear":false,"value":"","family":"","comment":""}},"vehicle":{"35":[{"year_hidden":false,"brand_info":"1984 куб. см.","sum_rent_comment":"","year":"2008","sum_hidden":false,"brand_info_hidden":false,"brand_info_unclear":false,"year_unclear":false,"sum_rent":"","sum":"","brand":"Seat Cordoba","sum_comment":"","brand_unclear":false,"brand_hidden":false}]},"id":"vulyk_61_126","declaration":{"additional_info_text":"","notfull_lostpages":"","date":"2015-03-12T00:00:00","notfull":"","additional_info":"","url":"http://static.declarations.com.ua/declarations/chosen_ones/mega_batch/boiko_valerii_mykhailovych.pdf"},"liabilities":{"54":{"sum_foreign_comment":"","sum":"","sum_comment":"","sum_comment_unclear":false,"sum_unclear":false,"sum_foreign":""},"55":{"sum_foreign_comment":"","sum":"","sum_comment":"","sum_foreign":""},"56":{"sum_foreign_comment":"","sum":"","sum_comment":"","sum_unclear":false,"sum_foreign":""},"57":{"sum_foreign_comment":"","sum":"","sum_comment":"","sum_comment_hidden":false,"sum_unclear":false,"sum_foreign":""},"58":{"sum_foreign_comment":"","sum":"","sum_comment":"","sum_unclear":false,"sum_foreign":""},"59":{"sum_foreign_comment":"","sum":"","sum_comment":"","sum_foreign":""},"60":{"sum_foreign_comment":"","sum_foreign_hidden":false,"sum_comment":"","sum_hidden":false,"sum":"","sum_foreign":""},"61":{"sum_foreign_comment":"","sum":"","sum_comment":"","sum_foreign":""},"62":{"sum_foreign_comment":"","sum":"3000","sum_comment":"","sum_unclear":false,"sum_foreign":""},"63":{"sum_foreign_comment":"","sum":"5950","sum_comment":"","sum_hidden":false,"sum_unclear":false,"sum_foreign":""},"64":{"sum_foreign_comment":"","sum":"","sum_hidden":false,"sum_comment":"","sum_foreign":""}},"ft_src":"3000\n5950\nсуддя вінницького міського суду вінницької області\nВінницька область\nЗагальний місцевий суд\nВалерій\nБойко О. О\nПодружжя\nБойко А. В\nДитина\nБойко О. В\nДитина\nМихайлович\nБойко\nБойко Валерій Михайлович\nБойко Валерій Михайлович\nВалерій Михайлович Бойко\nВалерій Бойко\nБойко Валерій Михайлович\n1984 куб. см.\nSeat Cordoba\n2008\n73.8\n.09\n2014\n53304\n178310\n1218\n12180\n54522\n190490\n1984 куб. см.\nSeat Cordoba\n2008\n.09\n73.8\nПодружжя\nБойко О. О\nДитина\nБойко А. В\nДитина\nБойко О. В\nБойко Валерій Михайлович\nВалерій Михайлович Бойко\nВалерій Бойко\nБойко Валерій Михайлович\nВалерій\nБойко Валерій Михайлович\nБойко\nВінницька область\nЗагальний місцевий суд\nсуддя вінницького міського суду вінницької області\nМихайлович\n5950\n3000\n53304\n178310\n190490\n54522\n12180\n1218\n2014\n3000\n5950\nБойко О. О\nПодружжя\nБойко А. В\nДитина\nБойко О. В\nДитина\nМихайлович\nБойко\nБойко Валерій Михайлович\nВалерій Михайлович Бойко\nВалерій Бойко\nБойко Валерій Михайлович\nВінницька область\nсуддя вінницького міського суду вінницької області\nЗагальний місцевий суд\nБойко Валерій Михайлович\nВалерій\nSeat Cordoba\n1984 куб. см.\n2008\n1218\n12180\n190490\n54522\n178310\n53304\n73.8\n.09\n2014","general":{"inn":"","name":"Валерій","patronymic_unclear":false,"family":[{"inn":"","inn_hidden":true,"relations_unclear":false,"relations_hidden":false,"relations_other":"","relations":"Подружжя","name_hidden":false,"family_name":"Бойко О. О","name_unclear":false},{"inn":"","relations":"Дитина","relations_other":"","inn_hidden":false,"family_name":"Бойко А. В","name_hidden":false,"name_unclear":false},{"inn":"","relations":"Дитина","relations_other":"","inn_hidden":false,"family_name":"Бойко О. В","name_hidden":false,"name_unclear":false}],"patronymic":"Михайлович","inn_hidden":true,"family_raw":"","inn_unclear":false,"post":{"post_unclear":false,"region_unclear":false,"post":"суддя вінницького міського суду вінницької області","office":"Загальний місцевий суд","region":"Вінницька область","post_hidden":false,"office_hidden":false,"region_hidden":false},"last_name_unclear":false,"full_name":"Бойко Валерій Михайлович","addresses":[{"place_address":"","place_district_hidden":true,"place_city_type":"","place_city_hidden":true,"place_address_unclear":false,"place_city_type_hidden":true,"place_hidden":true,"place":"","place_district":"","place_address_hidden":true,"place_city":"","place_district_unclear":false}],"last_name":"Бойко","patronymic_hidden":false,"full_name_suggest":{"output":"Бойко Валерій Михайлович","input":["Бойко Валерій Михайлович","Валерій Михайлович Бойко","Валерій Бойко"]},"name_unclear":false},"source":"VULYK","estate":{"29":[{"space_hidden":false,"costs_property":"","address_hidden":true,"region_hidden":true,"space_comment":"","space_units_hidden":false,"space_unclear":false,"space_units_unclear":false,"address":"","region":"","address_unclear":false,"space":".09","space_comment_hidden":false,"space_units":"га","costs_property_comment":"","costs_rent":"","costs_rent_comment":""}],"31":[{"space_unclear":false,"address_hidden":true,"region_hidden":true,"space_comment":"","space_hidden":false,"space":"73.8","address":"","region":"","costs_property":"","costs_rent_comment":"","space_comment_unclear":false,"space_units":"м²","costs_property_comment":"","costs_rent":""}]},"intro":{"declaration_year":"2014","isnotdeclaration":"","declaration_year_hidden":false}}