{"income":{"5":{"value":"241113.07","family_comment":"","value_unclear":false,"family_hidden":false,"value_hidden":false,"family_unclear":false,"family":"","comment":""},"6":{"value":"206293.07","family_comment":"","value_unclear":false,"family_unclear":false,"family":"","comment":""},"7":{"source_name_unclear":false,"value":"","comment_hidden":false,"family_comment":"","source_name":"","family":"","comment":"","source_name_hidden":false},"8":{"family_comment":"","value":"","family":"","comment":""},"9":{"value":"","family_comment":"","value_unclear":false,"family_hidden":false,"family_unclear":false,"family":"","comment":"","family_comment_unclear":false},"10":{"family_comment":"","value":"12180","family":"","comment":""},"11":{"family_comment":"","value":"","family":"","comment":""},"12":{"family_comment":"","value":"","family":"","comment":""},"13":{"family_comment":"","value":"","family":"","comment":""},"14":{"family_comment":"","value":"","family":"","comment":""},"15":{"family_comment":"","value":"","family":"","comment":""},"16":{"family_comment":"","value":"","family":"","comment":""},"17":{"family_comment":"","value":"","family":"","comment":""},"18":{"family_comment":"","value":"","family":"","comment":""},"19":{"family_comment":"","value":"","family":"","comment":""},"20":{"value":"22640","family_unclear":false,"comment_unclear":true,"family_comment":"","value_unclear":false,"family_comment_unclear":false,"family_comment_hidden":false,"comment":"кредит в банку ПАТ ' банк'","family":""}},"id":"vulyk_93_65","declaration":{"additional_info_text":"","notfull_lostpages":"","date":"2015-03-27T00:00:00","notfull":"","additional_info":"","url":"http://static.declarations.com.ua/declarations/chosen_ones/judges_batch/3511_veremchuk_oleh_anatoliiovych.pdf"},"liabilities":{"54":{"sum_foreign_comment":"","sum":"","sum_foreign":"","sum_comment":"","sum_hidden":false},"55":{"sum_foreign_comment":"","sum":"","sum_comment":"","sum_foreign":""},"56":{"sum_foreign_comment":"","sum":"","sum_comment":"","sum_foreign":""},"57":{"sum_foreign_comment":"","sum":"2544","sum_comment":"","sum_hidden":true,"sum_comment_hidden":false,"sum_unclear":false,"sum_foreign":""},"58":{"sum_foreign_comment":"","sum":"2046","sum_comment":"","sum_comment_unclear":false,"sum_hidden":true,"sum_unclear":false,"sum_foreign":""},"59":{"sum_foreign_comment":"","sum":"","sum_comment":"","sum_foreign":""},"60":{"sum_foreign_comment":"","sum":"","sum_foreign":"","sum_comment":"","sum_hidden":false},"61":{"sum_foreign_comment":"","sum":"","sum_comment":"","sum_foreign":""},"62":{"sum_foreign_comment":"","sum":"","sum_comment":"","sum_foreign":""},"63":{"sum_foreign_comment":"","sum":"","sum_comment":"","sum_foreign":""},"64":{"sum_foreign_comment":"","sum":"","sum_comment":"","sum_foreign":""}},"ft_src":"6008\nкористування\n55.8\n2014\n206293.07\n12180\n241113.07\nкредит в банку ПАТ ' банк'\n22640\n55.8\n6008\nкористування\nВеремчук\nПодружжя\nВеремчук Л. Є., 21. 02. 1975\nДитина\nВеремчук О. О.,\nДитина\nВеремчук А. О., 18. 02. 2005\nВеремчук Олег Анатолійович\nОлег Анатолійович Веремчук\nОлег Веремчук\nВеремчук Олег Анатолійович\nВеремчук Олег Анатолійович\nОлег\nАнатолійович\nЛьвівська область\nЗагальний місцевий суд\nсуддя сокальського районного суду львівської області\n2046\n2544\n206293.07\n22640\nкредит в банку ПАТ ' банк'\n241113.07\n12180\n2014\n2046\n2544\nПодружжя\nВеремчук Л. Є., 21. 02. 1975\nДитина\nВеремчук О. О.,\nДитина\nВеремчук А. О., 18. 02. 2005\nВеремчук\nАнатолійович\nЛьвівська область\nЗагальний місцевий суд\nсуддя сокальського районного суду львівської області\nВеремчук Олег Анатолійович\nВеремчук Олег Анатолійович\nОлег Анатолійович Веремчук\nОлег Веремчук\nВеремчук Олег Анатолійович\nОлег","general":{"inn_hidden":true,"inn":"","last_name":"Веремчук","post":{"post_unclear":false,"region_unclear":false,"post":"суддя сокальського районного суду львівської області","candidate":"","region":"Львівська область","office":"Загальний місцевий суд","office_unclear":false},"name":"Олег","full_name":"Веремчук Олег Анатолійович","family_raw":"","addresses":[{"place_district":"","place_address_hidden":false,"place_city":"","place_address":"","place_district_hidden":false,"place_city_type":"","place_city_hidden":false,"place_city_type_hidden":false,"place_hidden":true,"place":""}],"family":[{"inn":"","relations":"Подружжя","relations_hidden":false,"inn_hidden":true,"family_name":"Веремчук Л. Є., 21. 02. 1975","relations_other":"","name_hidden":false,"name_unclear":false},{"inn":"","relations":"Дитина","relations_other":"","inn_hidden":true,"family_name":"Веремчук О. О.,","name_hidden":false,"name_unclear":true},{"inn":"","relations":"Дитина","relations_other":"","inn_hidden":false,"family_name":"Веремчук А. О., 18. 02. 2005","name_hidden":false,"name_unclear":true}],"full_name_suggest":{"output":"Веремчук Олег Анатолійович","input":["Веремчук Олег Анатолійович","Олег Анатолійович Веремчук","Олег Веремчук"]},"patronymic":"Анатолійович"},"source":"VULYK","estate":{"24":[{"space_unclear":false,"costs":"","costs_comment":"","address_hidden":true,"region_hidden":true,"space_comment":"","space":"55.8","address":"","region":"","costs_rent_comment":"користування","space_comment_unclear":false,"space_units":"м²","costs_rent":"6008"}]},"intro":{"declaration_year":"2014","isnotdeclaration":""}}