{"income":{"5":{"value":"227193.2","family_comment":"","value_unclear":false,"family_unclear":false,"family":"","comment":""},"6":{"family_comment":"","value":"207739.88","value_unclear":false,"family":"","comment":""},"7":{"value":"4200","value_unclear":false,"family_comment":"","source_name":"Рада адвокатів Київської області","family":"","comment":""},"8":{"family_comment":"","value":"","family":"","comment":""},"9":{"value":"","family_comment":"","value_unclear":false,"family_unclear":false,"family":"","comment":""},"10":{"family_comment":"","value":"","comment_unclear":false,"family":"","comment":""},"11":{"family_comment":"","value":"","family":"","comment":""},"12":{"family_comment":"","value":"","family":"","comment":""},"13":{"family_comment":"","value":"","value_unclear":false,"family":"","comment":""},"14":{"family_comment":"","value":"","family":"","comment":""},"15":{"family_comment":"","value":"","family":"","comment":""},"16":{"family_comment":"","family_unclear":false,"value":"","family":"","comment":""},"17":{"family_comment":"","family_unclear":false,"value":"","family":"","comment":""},"18":{"family_comment":"","value":"","family":"","comment":""},"19":{"family_comment":"","value":"","family":"","comment":""},"20":{"value":"15253.32","family_comment":"","value_unclear":false,"family_hidden":false,"value_hidden":false,"family_unclear":false,"comment_unclear":false,"comment":"","family":""}},"vehicle":{"35":[{"brand_info":"1998 , власн","sum_rent_comment":"","brand_info_unclear":false,"year":"2008","brand_info_hidden":false,"sum_rent_comment_unclear":false,"sum_rent":"","sum":"","brand":"Toyota Rav 4","sum_comment":"","brand_unclear":false,"brand_hidden":false}]},"id":"vulyk_100_11","declaration":{"additional_info_text":"","notfull_lostpages":"","date":"2015-03-31T00:00:00","notfull":"","additional_info":"","url":"http://static.declarations.com.ua/declarations/chosen_ones/judges_batch/4129_petryshyn_nataliia_mykolaivna.pdf"},"liabilities":{"54":{"sum_foreign_comment":"","sum":"","sum_comment":"","sum_comment_hidden":false,"sum_unclear":false,"sum_foreign":""},"55":{"sum_foreign_comment":"","sum":"","sum_comment":"","sum_foreign":""},"56":{"sum_foreign_comment":"","sum":"","sum_comment":"","sum_unclear":false,"sum_foreign":""},"57":{"sum_foreign_comment":"","sum":"","sum_comment":"","sum_comment_unclear":false,"sum_comment_hidden":false,"sum_unclear":false,"sum_foreign":""},"58":{"sum_foreign_comment":"","sum":"","sum_comment":"","sum_comment_hidden":false,"sum_unclear":false,"sum_foreign":""},"59":{"sum_foreign_comment":"","sum":"","sum_comment":"","sum_foreign":""},"60":{"sum_foreign_comment":"","sum_comment_hidden":false,"sum":"","sum_comment":"","sum_foreign":""},"61":{"sum_foreign_comment":"","sum":"","sum_comment":"","sum_foreign":""},"62":{"sum_foreign_comment":"","sum":"","sum_comment":"","sum_unclear":false,"sum_foreign":""},"63":{"sum_foreign_comment":"","sum_comment_hidden":false,"sum":"","sum_comment":"","sum_foreign":""},"64":{"sum_foreign_comment":"","sum_comment_hidden":false,"sum":"","sum_comment":"","sum_foreign":""}},"ft_src":"Петришин Наталія Миколаївна\nсуддя броварського міськрайонного суду київської області\nКиївська область\nЗагальний місцевий суд\nНаталія\nПетришин Л. Л. 25. 12. 1975\nПодружжя\nПетришин К. Л. 26. 06. 2007\nДитина\nПетришин В. Л. 20. 04. 2011\nДитина\nПетришин Наталія Миколаївна\nНаталія Миколаївна Петришин\nНаталія Петришин\nПетришин Наталія Миколаївна\nПетришин\nМиколаївна\n1998 , власн\nToyota Rav 4\n2008\n1200\nкористування\n111\n2014\n207739.88\nРада адвокатів Київської області\n4200\n227193.2\n15253.32\n1998 , власн\nToyota Rav 4\n2008\n1200\n111\nкористування\nПодружжя\nПетришин Л. Л. 25. 12. 1975\nДитина\nПетришин К. Л. 26. 06. 2007\nДитина\nПетришин В. Л. 20. 04. 2011\nМиколаївна\nПетришин\nПетришин Наталія Миколаївна\nНаталія Миколаївна Петришин\nНаталія Петришин\nПетришин Наталія Миколаївна\nПетришин Наталія Миколаївна\nНаталія\nЗагальний місцевий суд\nКиївська область\nсуддя броварського міськрайонного суду київської області\n4200\nРада адвокатів Київської області\n207739.88\n15253.32\n227193.2\n2014\nПетришин Л. Л. 25. 12. 1975\nПодружжя\nДитина\nПетришин К. Л. 26. 06. 2007\nДитина\nПетришин В. Л. 20. 04. 2011\nМиколаївна\nПетришин\nКиївська область\nЗагальний місцевий суд\nсуддя броварського міськрайонного суду київської області\nПетришин Наталія Миколаївна\nПетришин Наталія Миколаївна\nНаталія Миколаївна Петришин\nНаталія Петришин\nПетришин Наталія Миколаївна\nНаталія\n2008\nToyota Rav 4\n1998 , власн\n15253.32\n227193.2\n4200\nРада адвокатів Київської області\n207739.88\nкористування\n111\n1200\n2014","general":{"inn":"","inn_hidden":true,"last_name":"Петришин","post":{"post_unclear":false,"region_unclear":false,"post":"суддя броварського міськрайонного суду київської області","office":"Загальний місцевий суд","region":"Київська область","post_hidden":false,"office_unclear":false},"name":"Наталія","full_name":"Петришин Наталія Миколаївна","family_raw":"","addresses":[{"place_district":"","place_city_hidden":true,"place_city":"","place_city_unclear":false,"place_district_hidden":false,"place_city_type":"","place_address_hidden":false,"place_city_type_hidden":false,"place_address":"","place_hidden":false,"place":""}],"family":[{"inn_hidden":true,"inn":"","name_hidden":false,"family_name":"Петришин Л. Л. 25. 12. 1975","relations":"Подружжя","name_unclear":false},{"inn":"","relations":"Дитина","relations_other":"","inn_hidden":true,"family_name":"Петришин К. Л. 26. 06. 2007","name_hidden":false,"name_unclear":false},{"inn":"","relations":"Дитина","relations_other":"","inn_hidden":true,"family_name":"Петришин В. Л. 20. 04. 2011","name_hidden":false,"name_unclear":false}],"full_name_suggest":{"output":"Петришин Наталія Миколаївна","input":["Петришин Наталія Миколаївна","Наталія Миколаївна Петришин","Наталія Петришин"]},"patronymic":"Миколаївна"},"source":"VULYK","estate":{"23":[{"space_unclear":false,"costs":"","costs_comment":"","address_hidden":false,"region_hidden":true,"space_comment":"","space":"1200","address":"","costs_comment_unclear":false,"region":"","address_unclear":false,"costs_rent_comment":"","space_comment_unclear":false,"space_units":"м²","costs_rent":""}],"25":[{"space_unclear":false,"costs":"","costs_comment":"","address_hidden":false,"region_hidden":true,"space_comment":"користування","space":"111","address":"","costs_comment_unclear":false,"region":"","address_unclear":false,"costs_rent_comment":"","space_comment_unclear":false,"space_units":"м²","costs_rent":""}]},"intro":{"declaration_year":"2014"}}