{"income":{"5":{"value":"253911","family_comment":"","value_unclear":false,"family_hidden":false,"value_hidden":false,"family_unclear":false,"family":"11356","comment":""},"6":{"value":"245390","family_comment":"","value_unclear":false,"family_unclear":false,"family":"3900","comment":""},"7":{"source_name_unclear":false,"value":"300","comment_hidden":false,"family_comment":"","source_name":"","family":"","comment":"","source_name_hidden":true},"8":{"family_comment":"","value":"","family":"","comment":""},"9":{"value":"149","family_comment":"","value_unclear":false,"family_hidden":false,"family_unclear":false,"family":"","comment":"","family_comment_unclear":false},"10":{"family_comment":"","value":"","family":"","comment":""},"11":{"family_comment":"","value":"8000","family":"","comment":""},"12":{"family_comment":"","value":"","family":"","comment":""},"13":{"family_comment":"","value":"","family":"","comment":""},"14":{"family_comment":"","value":"","family":"","comment":""},"15":{"family_comment":"","value":"","family":"7456","comment":""},"16":{"family_comment":"","value":"","family":"","comment":""},"17":{"family_comment":"","value":"","family":"","comment":""},"18":{"family_comment":"","value":"","family":"","comment":""},"19":{"family_comment":"","value":"","family":"","comment":""},"20":{"value":"72","family_comment":"","value_unclear":false,"family_comment_hidden":false,"family_unclear":false,"family_comment_unclear":false,"comment_unclear":false,"comment":"","family":""}},"vehicle":{"35":[{"year_hidden":false,"brand_info":"2461 куб. см.","sum_rent_comment":"","year":"2007","brand_info_hidden":false,"brand_info_unclear":false,"sum_rent":"","sum":"","brand":"Volkswagen Multivan","sum_comment":"","brand_unclear":false,"brand_hidden":false}],"40":[{"brand_info":"2179 куб. см.","sum_rent_comment":"","brand":"Land Rover Freelander","sum_comment":"","year":"2013","brand_info_unclear":false,"sum":"","sum_rent":""}]},"id":"vulyk_93_174","banks":{"45":[{"sum_units":"UAH","sum_foreign":"","sum_hidden":false,"sum":"1","sum_units_hidden":false,"sum_foreign_comment":"","sum_foreign_hidden":false,"sum_comment":"","sum_comment_unclear":false,"sum_foreign_units":"UAH","sum_units_unclear":false,"sum_comment_hidden":false,"sum_unclear":false}],"51":[{"sum_units":"UAH","sum_hidden":false,"sum_units_hidden":false,"sum_foreign":"","sum_foreign_comment":"","sum":"81902","sum_comment":"","sum_comment_unclear":false,"sum_foreign_units":"UAH","sum_units_unclear":false,"sum_comment_hidden":false,"sum_unclear":false}]},"declaration":{"additional_info_text":"","notfull_lostpages":"","date":"2015-03-27T00:00:00","notfull":"","additional_info":"","url":"http://static.declarations.com.ua/declarations/chosen_ones/judges_batch/3620_muraviov_oleksii_valentynovych.pdf"},"liabilities":{"54":{"sum_foreign_comment":"","sum":"","sum_hidden":false,"sum_comment":"","sum_foreign":""},"55":{"sum_foreign_comment":"","sum":"","sum_comment":"","sum_foreign":""},"56":{"sum_foreign_comment":"","sum":"","sum_comment":"","sum_foreign":""},"57":{"sum_foreign_comment":"","sum":"","sum_comment":"","sum_hidden":false,"sum_comment_hidden":false,"sum_unclear":false,"sum_foreign":""},"58":{"sum_foreign_comment":"","sum":"","sum_comment":"","sum_comment_unclear":false,"sum_hidden":false,"sum_unclear":false,"sum_foreign":""},"59":{"sum_foreign_comment":"","sum":"","sum_comment":"","sum_foreign":""},"60":{"sum_foreign_comment":"","sum":"23247","sum_hidden":false,"sum_comment":"","sum_foreign":""},"61":{"sum_foreign_comment":"","sum":"","sum_comment":"","sum_foreign":""},"62":{"sum_foreign_comment":"","sum":"","sum_comment":"","sum_foreign":""},"63":{"sum_foreign_comment":"","sum":"","sum_comment":"","sum_foreign":""},"64":{"sum_foreign_comment":"","sum":"","sum_comment":"","sum_foreign":""}},"ft_src":"23247\nМуравйов Олексій Валентинович\nсуддя вищого адміністративного суду україни – секретар судової палати\nЗагальнодержавний регіон\nВищий адміністративний суд України\nОлексій\nПодружжя\nСин дружини\nІнше\nДитина\nМуравйов Олексій Валентинович\nОлексій Валентинович Муравйов\nОлексій Муравйов\nМуравйов Олексій Валентинович\nМуравйов\nВалентинович\n2461 куб. см.\nVolkswagen Multivan\n2007\n2179 куб. см.\n2013\nLand Rover Freelander\n4/5\n488\n1/5\n361\n4/5\n123.4\n1/2\n70.78\n4/5\n361\n1/5\n488\n1/5\n123.4\n81902\n1\n2014\n2461 куб. см.\nVolkswagen Multivan\n2007\n2179 куб. см.\nLand Rover Freelander\n2013\n4/5\n361\n1/5\n123.4\n488\n1/5\n488\n4/5\n361\n1/5\n123.4\n4/5\n70.78\n1/2\nМуравйов\nПодружжя\nІнше\nСин дружини\nДитина\nМуравйов Олексій Валентинович\nОлексій Валентинович Муравйов\nОлексій Муравйов\nМуравйов Олексій Валентинович\nМуравйов Олексій Валентинович\nОлексій\nВалентинович\nЗагальнодержавний регіон\nВищий адміністративний суд України\nсуддя вищого адміністративного суду україни – секретар судової палати\n23247\n300\n3900\n245390\n72\n7456\n253911\n11356\n149\n8000\n1\n81902\n2014\n23247\n3900\n245390\n7456\n149\n8000\n300\n11356\n253911\n72\nПодружжя\nІнше\nСин дружини\nДитина\nМуравйов\nВалентинович\nЗагальнодержавний регіон\nВищий адміністративний суд України\nсуддя вищого адміністративного суду україни – секретар судової палати\nМуравйов Олексій Валентинович\nМуравйов Олексій Валентинович\nОлексій Валентинович Муравйов\nОлексій Муравйов\nМуравйов Олексій Валентинович\nОлексій\nVolkswagen Multivan\n2461 куб. см.\n2007\n2013\n2179 куб. см.\nLand Rover Freelander\n8000\n7456\n149\n72\n253911\n11356\n300\n245390\n3900\n4/5\n123.4\n1/2\n70.78\n1/5\n488\n1/5\n361\n4/5\n361\n1/5\n123.4\n4/5\n488\n1\n81902\n2014","general":{"inn":"","inn_hidden":true,"last_name":"Муравйов","post":{"post_unclear":false,"region_unclear":false,"region":"Загальнодержавний регіон","candidate":"","post":"суддя вищого адміністративного суду україни – секретар судової палати","office":"Вищий адміністративний суд України","office_unclear":false},"name":"Олексій","full_name":"Муравйов Олексій Валентинович","family_raw":"","addresses":[{"place_district":"","place_city_hidden":true,"place_city":"","place_city_type_hidden":true,"place_district_hidden":true,"place_city_type":"","place_address_hidden":true,"place_address":"","place_hidden":true,"place":""}],"family":[{"inn":"","relations":"Подружжя","relations_hidden":false,"inn_hidden":true,"relations_other":"","name_hidden":true,"family_name":"","name_unclear":false},{"inn":"","relations":"Інше","relations_other":"Син дружини","inn_hidden":false,"family_name":"","name_hidden":false,"name_unclear":false},{"inn":"","relations":"Дитина","relations_other":"","inn_hidden":false,"family_name":"","name_hidden":false,"name_unclear":false}],"full_name_suggest":{"output":"Муравйов Олексій Валентинович","input":["Муравйов Олексій Валентинович","Олексій Валентинович Муравйов","Олексій Муравйов"]},"patronymic":"Валентинович"},"source":"VULYK","estate":{"23":[{"space_unclear":false,"costs":"","costs_comment":"","address_hidden":true,"region_hidden":true,"space_comment":"1/5","space":"488","address":"","region":"","costs_rent_comment":"","space_comment_unclear":false,"space_units":"м²","costs_rent":""}],"24":[{"space_unclear":false,"costs":"","costs_comment":"","address_hidden":true,"region_hidden":true,"space_comment":"1/5","space":"361","address":"","region":"","costs_rent_comment":"","space_comment_unclear":false,"space_units":"м²","costs_rent":""}],"25":[{"space_hidden":false,"costs":"","costs_comment":"","address_hidden":true,"region_hidden":true,"space_comment":"1/5","space_unclear":false,"space":"123.4","address":"","costs_rent_comment_unclear":false,"region":"","costs_rent_comment":"","space_units":"м²","costs_rent":""}],"29":[{"space_unclear":false,"address_hidden":true,"region_hidden":true,"space_comment":"4/5","space":"488","address":"","region":"","costs_property":"","costs_rent_comment":"","space_comment_unclear":false,"space_units":"м²","costs_property_comment":"","costs_rent":""}],"30":[{"space_unclear":false,"address_hidden":true,"region_hidden":true,"space_comment":"4/5","space":"361","address":"","region":"","costs_property":"","costs_rent_comment":"","space_units":"м²","costs_property_comment":"","costs_rent":""}],"31":[{"space_hidden":false,"address_hidden":true,"region_hidden":true,"space_comment":"4/5","space":"123.4","address":"","region":"","costs_property":"","costs_rent_comment":"","space_comment_unclear":false,"space_units":"м²","costs_property_comment":"","costs_rent":""},{"costs_rent":"","region":"","costs_property":"","costs_rent_comment":"","region_hidden":false,"space_comment":"1/2","costs_property_comment":"","space_units":"м²","space":"70.78","address":""}]},"intro":{"declaration_year":"2014","isnotdeclaration":""}}