{"income":{"5":{"value":"195196","family_comment":"","value_unclear":false,"family_hidden":false,"value_hidden":false,"family_unclear":false,"family":"4452","comment":"","family_comment_unclear":false},"6":{"value":"181301","family_comment":"","value_unclear":false,"comment_hidden":false,"family_hidden":false,"value_hidden":false,"family_unclear":false,"family":"2276","comment":""},"7":{"value":"","value_hidden":false,"family_comment":"","source_name":"","family":"","comment":"","source_name_hidden":false},"8":{"family_comment":"","value":"","family":"","comment":""},"9":{"value":"","comment_hidden":false,"value_hidden":false,"family_comment":"","family":"","comment":""},"10":{"value":"","value_unclear":false,"value_hidden":false,"family_comment":"","family":"","comment":""},"11":{"family_comment":"","value":"","family":"","comment":""},"12":{"family_comment":"","value":"","family":"2176","comment":""},"13":{"family_comment":"","value":"","family_hidden":false,"comment":"","family":""},"14":{"family_comment":"","value":"","family":"","comment":""},"15":{"family_comment":"","family_unclear":false,"value":"","family":"","comment":""},"16":{"family_comment":"","value":"13895","value_unclear":false,"family":"","comment":""},"17":{"family_comment":"","value":"","family":"","comment":""},"18":{"family_comment":"","value":"","family":"","comment":""},"19":{"family_comment":"","value":"","comment_unclear":false,"family":"","comment":""},"20":{"value":"","comment_unclear":false,"family_hidden":false,"value_hidden":false,"family_comment":"","family":"","comment":""}},"vehicle":{"35":[{"year_hidden":false,"brand_info":"","sum_rent_comment":"","brand_info_unclear":false,"sum_rent_hidden":false,"year":"2011","sum_hidden":false,"brand_info_hidden":true,"sum_rent_comment_unclear":false,"year_unclear":false,"sum_rent":"","sum":"","brand":"","sum_comment":"","sum_comment_unclear":false,"brand_hidden":true,"sum_unclear":false,"brand_unclear":false}]},"id":"vulyk_64_88","banks":{"47":[{"sum_foreign_comment":"","sum_units":"UAH","sum_comment":"","sum_comment_unclear":false,"sum_foreign_units":"UAH","sum_comment_hidden":false,"sum":"210","sum_foreign":""}]},"declaration":{"additional_info_text":"","notfull_lostpages":"","date":"2015-03-31T00:00:00","notfull":"","additional_info":"","url":"http://static.declarations.com.ua/declarations/chosen_ones/mega_batch/hlynianchuk_vitalii_dmytrovych.pdf"},"liabilities":{"54":{"sum_foreign_comment":"","sum":"","sum_comment":"","sum_foreign_comment_hidden":false,"sum_hidden":false,"sum_comment_hidden":false,"sum_unclear":false,"sum_foreign":""},"55":{"sum_foreign_comment":"","sum":"","sum_comment":"","sum_comment_unclear":false,"sum_foreign":""},"56":{"sum_foreign_comment":"","sum":"","sum_comment":"","sum_unclear":false,"sum_foreign":""},"57":{"sum_foreign_comment":"","sum":"","sum_comment":"","sum_hidden":false,"sum_unclear":false,"sum_foreign":""},"58":{"sum_foreign_comment":"","sum":"","sum_comment":"","sum_unclear":false,"sum_foreign":""},"59":{"sum_foreign_comment":"","sum":"","sum_comment":"","sum_comment_unclear":false,"sum_comment_hidden":false,"sum_unclear":false,"sum_foreign":""},"60":{"sum_foreign_comment":"","sum":"","sum_comment":"","sum_foreign":""},"61":{"sum_foreign_comment":"","sum":"","sum_comment":"","sum_foreign":""},"62":{"sum_foreign_comment":"","sum":"","sum_comment":"","sum_unclear":false,"sum_foreign":""},"63":{"sum_foreign_comment":"","sum":"","sum_comment":"","sum_unclear":false,"sum_foreign":""},"64":{"sum_foreign_comment":"","sum":"","sum_comment":"","sum_comment_unclear":false,"sum_unclear":false,"sum_foreign":""}},"ft_src":"суддя любешівського районного суду волинської області\nВолинська область\nЗагальний місцевий суд\nВіталій\nГлинянчук О. П\nПодружжя\nГлинянчук С. В\nДитина\nГлинянчук В. В\nДитина\nДмитрович\nГлинянчук Віталій Дмитрович\nГлинянчук\nГлинянчук Віталій Дмитрович\nВіталій Дмитрович Глинянчук\nВіталій Глинянчук\nГлинянчук Віталій Дмитрович\n2011\n210\n2014\n2011\n210\n1596\nЗагальний місцевий суд\nВолинська область\nсуддя любешівського районного суду волинської області\nПодружжя\nГлинянчук О. П\nДитина\nГлинянчук С. В\nДитина\nГлинянчук В. В\nГлинянчук Віталій Дмитрович\nВіталій Дмитрович Глинянчук\nВіталій Глинянчук\nГлинянчук Віталій Дмитрович\nГлинянчук Віталій Дмитрович\nВіталій\nГлинянчук\nДмитрович\n2276\n181301\n2176\n195196\n4452\n13895\n2014\n1596\nПодружжя\nГлинянчук О. П\nДитина\nГлинянчук С. В\nГлинянчук В. В\nДитина\nДмитрович\nГлинянчук\nВіталій\nГлинянчук Віталій Дмитрович\nВіталій Дмитрович Глинянчук\nВіталій Глинянчук\nГлинянчук Віталій Дмитрович\nВолинська область\nЗагальний місцевий суд\nсуддя любешівського районного суду волинської області\nГлинянчук Віталій Дмитрович\n2276\n181301\n4452\n195196\n13895\n2176\n2011\n195196\n4452\n13895\n2176\n181301\n2276\n1596\n210\n2014","general":{"inn":"","name":"Віталій","last_name_hidden":false,"family":[{"inn":"","inn_hidden":true,"relations_unclear":false,"relations_hidden":false,"relations_other":"","relations":"Подружжя","name_hidden":false,"inn_unclear":false,"family_name":"Глинянчук О. П","name_unclear":false},{"inn":"","inn_hidden":true,"relations_unclear":false,"relations_hidden":false,"relations_other":"","relations":"Дитина","name_hidden":false,"family_name":"Глинянчук С. В","name_unclear":false},{"inn":"","relations":"Дитина","relations_other":"","inn_hidden":true,"family_name":"Глинянчук В. В","name_hidden":false,"name_unclear":false}],"patronymic":"Дмитрович","inn_hidden":true,"family_raw":"","inn_unclear":false,"post":{"post_unclear":false,"post":"суддя любешівського районного суду волинської області","candidate":"","office_hidden":false,"region":"Волинська область","post_hidden":false,"office":"Загальний місцевий суд","office_unclear":false,"region_hidden":false},"last_name_unclear":false,"full_name":"Глинянчук Віталій Дмитрович","addresses":[{"place_city_type_unclear":false,"place_address":"","place_district_hidden":true,"place_city_type":"","place_city_hidden":true,"place_city_type_hidden":true,"place":"","place_district":"","place_unclear":false,"place_city":"","place_city_unclear":false,"place_hidden":true,"place_address_hidden":true}],"last_name":"Глинянчук","patronymic_hidden":false,"full_name_suggest":{"output":"Глинянчук Віталій Дмитрович","input":["Глинянчук Віталій Дмитрович","Віталій Дмитрович Глинянчук","Віталій Глинянчук"]},"name_unclear":false},"source":"VULYK","estate":{"29":[{"region_unclear":false,"space_unclear":false,"costs_rent_unclear":false,"costs_property_hidden":false,"address_hidden":false,"region_hidden":true,"space_comment":"","space_hidden":false,"space":"1596","address":"","region":"","costs_property":"","costs_rent_comment":"","costs_rent_hidden":false,"address_unclear":false,"space_units":"м²","costs_property_comment":"","costs_rent":""}]},"intro":{"declaration_year":"2014","isnotdeclaration":"","declaration_year_unclear":false,"declaration_year_hidden":false}}