{"income":{"5":{"value":"206161.88","family_comment":"","value_unclear":false,"family_unclear":false,"family":"","comment":""},"6":{"family_comment":"","value":"181161.88","value_unclear":false,"family":"","comment":""},"7":{"value":"","value_unclear":false,"family_comment":"","source_name":"","family":"","comment":""},"8":{"family_comment":"","value":"","family":"","comment":""},"9":{"value":"","family_comment":"","value_unclear":false,"family_unclear":false,"family":"","comment":""},"10":{"family_comment":"","value":"","comment_unclear":false,"family":"","comment":""},"11":{"family_comment":"","value":"","family":"","comment":""},"12":{"family_comment":"","value":"","family":"","comment":""},"13":{"family_comment":"","value":"","value_unclear":false,"family":"","comment":""},"14":{"family_comment":"","value":"","family":"","comment":""},"15":{"family_comment":"","value":"","family":"","comment":""},"16":{"family_comment":"","family_unclear":false,"value":"","family":"","comment":""},"17":{"family_comment":"","family_unclear":false,"value":"","family":"","comment":""},"18":{"family_comment":"","value":"","family":"","comment":""},"19":{"family_comment":"","value":"","family":"","comment":""},"20":{"value":"25000","family_comment":"","value_unclear":false,"family_hidden":false,"value_hidden":false,"family_unclear":false,"comment_unclear":false,"comment":"","family":""}},"id":"vulyk_100_85","banks":{"45":[{"sum_foreign_comment":"","sum_units":"UAH","sum_comment":"","sum_comment_unclear":false,"sum_foreign_units":"UAH","sum_units_unclear":false,"sum_comment_hidden":false,"sum_unclear":false,"sum":"981.64","sum_foreign":""}],"46":[{"sum_foreign_comment":"","sum_units":"UAH","sum_comment":"","sum_comment_unclear":false,"sum_foreign_units":"UAH","sum":"75.09","sum_unclear":false,"sum_foreign":""}]},"declaration":{"additional_info_text":"","notfull_lostpages":"","date":"2015-03-30T00:00:00","notfull":"","additional_info":"","url":"http://static.declarations.com.ua/declarations/chosen_ones/judges_batch/4285_zavorotna_oksana_leonidivna.pdf"},"liabilities":{"54":{"sum_foreign_comment":"","sum":"","sum_comment":"","sum_comment_hidden":false,"sum_unclear":false,"sum_foreign":""},"55":{"sum_foreign_comment":"","sum":"","sum_comment":"","sum_foreign":""},"56":{"sum_foreign_comment":"","sum":"7957.95","sum_comment":"","sum_unclear":false,"sum_foreign":""},"57":{"sum_foreign_comment":"","sum":"55984.67","sum_comment":"","sum_comment_unclear":false,"sum_comment_hidden":false,"sum_unclear":false,"sum_foreign":""},"58":{"sum_foreign_comment":"","sum":"5716.14","sum_comment":"","sum_comment_hidden":false,"sum_unclear":false,"sum_foreign":""},"59":{"sum_foreign_comment":"","sum":"5040","sum_comment":"","sum_foreign":""},"60":{"sum_foreign_comment":"","sum_comment_hidden":false,"sum":"","sum_comment":"","sum_foreign":""},"61":{"sum_foreign_comment":"","sum":"","sum_comment":"","sum_foreign":""},"62":{"sum_foreign_comment":"","sum":"","sum_comment":"","sum_unclear":false,"sum_foreign":""},"63":{"sum_foreign_comment":"","sum_comment_hidden":false,"sum":"","sum_comment":"","sum_foreign":""},"64":{"sum_foreign_comment":"","sum_comment_hidden":false,"sum":"","sum_comment":"","sum_foreign":""}},"ft_src":"5040\n55984.67\n5716.14\n7957.95\nЛеонідівна\nЗаворотна Оксана Леонідівна\nсуддя хмельницького міськрайонного суду хмельницької області\nХмельницька область\nЗагальний місцевий суд\nОксана\nЗаворотна Оксана Леонідівна\nОксана Леонідівна Заворотна\nОксана Заворотна\nЗаворотна Оксана Леонідівна\nЗаворотна\n25000\n206161.88\n181161.88\n75.09\n981.64\n100\n298.8\n2014\n181161.88\n206161.88\n25000\n981.64\n75.09\n100\n298.8\nЗагальний місцевий суд\nХмельницька область\nсуддя хмельницького міськрайонного суду хмельницької області\nЛеонідівна\nЗаворотна Оксана Леонідівна\nОксана Леонідівна Заворотна\nОксана Заворотна\nЗаворотна Оксана Леонідівна\nЗаворотна Оксана Леонідівна\nОксана\nЗаворотна\n5040\n55984.67\n7957.95\n5716.14\n181161.88\n25000\n206161.88\n2014\n5716.14\n55984.67\n7957.95\n5040\nЛеонідівна\nЗаворотна\nХмельницька область\nЗагальний місцевий суд\nсуддя хмельницького міськрайонного суду хмельницької області\nЗаворотна Оксана Леонідівна\nЗаворотна Оксана Леонідівна\nОксана Леонідівна Заворотна\nОксана Заворотна\nЗаворотна Оксана Леонідівна\nОксана\n100\n298.8\n981.64\n75.09\n2014","general":{"inn":"","inn_hidden":true,"last_name":"Заворотна","post":{"post_unclear":false,"region_unclear":false,"post":"суддя хмельницького міськрайонного суду хмельницької області","office":"Загальний місцевий суд","region":"Хмельницька область","post_hidden":false,"office_unclear":false},"name":"Оксана","full_name":"Заворотна Оксана Леонідівна","family_raw":"","addresses":[{"place_district":"","place_city_hidden":true,"place_city":"","place_city_unclear":false,"place_district_hidden":false,"place_city_type":"","place_address_hidden":true,"place_city_type_hidden":false,"place_address":"","place_hidden":true,"place":""}],"full_name_suggest":{"output":"Заворотна Оксана Леонідівна","input":["Заворотна Оксана Леонідівна","Оксана Леонідівна Заворотна","Оксана Заворотна"]},"patronymic":"Леонідівна"},"source":"VULYK","estate":{"23":[{"space_unclear":false,"costs":"","costs_comment":"","address_hidden":false,"region_hidden":true,"space_comment":"","space":"100","address":"","costs_comment_unclear":false,"region":"","address_unclear":false,"costs_rent_comment":"","space_comment_unclear":false,"space_units":"м²","costs_rent":""}],"24":[{"space_unclear":false,"costs":"","costs_comment":"","address_hidden":false,"region_hidden":true,"space_comment":"","space":"298.8","address":"","region":"","costs_rent_comment":"","space_comment_unclear":false,"space_units":"м²","costs_rent":""}]},"intro":{"declaration_year":"2014"}}