{"id":"vulyk_101_154","ft_src":"Volkswagen Caddy\n1896 куб. см., 77 кВт\n2005\n1896 куб. см., 77 кВт\nVolkswagen Caddy\n2005\n47.8\n47.8\n55.7\n2015\n28343\n170526\n45543\n170526\n17200\nVolkswagen Caddy\n1896 куб. см., 77 кВт\n2005\n1896 куб. см., 77 кВт\n2005\nVolkswagen Caddy\n2015\nПодружжя\nМельничук С. Д\nДитина\nМельничук В. Ю\nДитина\nМельничук В. Ю\nМельничук Юрій Володимирович\nЮрій Володимирович Мельничук\nЮрій Мельничук\nМельничук Юрій Володимирович\nЮрій\nМельничук Юрій Володимирович\nВолодимирович\nЗагальний місцевий суд\nсуддя уманського міськрайонного суду черкаської області\nЧеркаська область\nМельничук\n370\nПрАТ СК 'Провідна'\n170526\n28343\n17200\n170526\n45543\n47.8\n47.8\n55.7\nПрАТ СК 'Провідна'\n370\nМельничук С. Д\nПодружжя\nМельничук В. Ю\nДитина\nМельничук В. Ю\nДитина\nЮрій\nВолодимирович\nМельничук\nМельничук Юрій Володимирович\nЮрій Володимирович Мельничук\nЮрій Мельничук\nМельничук Юрій Володимирович\nсуддя уманського міськрайонного суду черкаської області\nЗагальний місцевий суд\nЧеркаська область\nМельничук Юрій Володимирович","estate":{"25":[{"address":"","space_units":"м²","space_hidden":false,"space_unclear":false,"region_hidden":true,"costs_comment":"","space_comment":"","address_hidden":false,"space":"47.8","space_comment_unclear":false,"costs_rent_comment":"","costs":"","region":"","costs_rent":""},{"address":"","space_units":"м²","space_hidden":false,"space_unclear":false,"costs_comment":"","space_comment":"","space_comment_unclear":false,"space":"55.7","costs_rent_comment":"","costs":"","region":"","costs_rent":""}],"31":[{"costs_property_comment":"","address":"","space_units":"м²","space_hidden":false,"space_unclear":false,"region_hidden":true,"costs_property":"","space_comment":"","address_hidden":false,"costs_rent_comment_unclear":false,"costs_rent_comment":"","space":"47.8","region":"","costs_rent":""}]},"vehicle":{"35":[{"sum_comment":"","brand_info_hidden":false,"sum_rent":"","sum":"","brand_unclear":false,"year":"2005","brand":"Volkswagen Caddy","brand_info":"1896 куб. см., 77 кВт","sum_rent_comment":"","brand_info_unclear":false,"sum_rent_unclear":false}],"40":[{"sum_comment":"","brand_info_hidden":false,"brand_info":"1896 куб. см., 77 кВт","sum":"","sum_rent_comment":"","brand_hidden":false,"brand":"Volkswagen Caddy","sum_rent":"","brand_info_unclear":false,"year":"2005"}]},"source":"VULYK","income":{"5":{"family_comment":"","value":"170526","family":"45543","comment":"","value_unclear":false},"6":{"family_comment":"","family":"28343","comment":"","value_unclear":false,"family_hidden":false,"value":"170526"},"7":{"family_comment":"","comment":"","family":"","source_name_unclear":false,"value":"","source_name":""},"8":{"family_comment":"","value":"","family":"","comment":""},"9":{"family_comment":"","value":"","family":"","comment":""},"10":{"family_comment":"","value":"","family":"","comment":""},"11":{"family_comment":"","comment_unclear":false,"value":"","family":"","comment":""},"12":{"family_comment":"","value":"","family":"","comment":""},"13":{"family_comment":"","value":"","family":"","comment":""},"14":{"family_comment":"","value":"","family":"","comment":""},"15":{"family_comment":"","value":"","family":"","comment":""},"16":{"family_comment":"","value":"","family":"","comment":""},"17":{"family_comment":"","value":"","family":"","comment":""},"18":{"family_comment":"","value":"","family":"","comment":""},"19":{"family_comment":"","value":"","family":"","comment":""},"20":{"family_comment":"","family":"17200","comment":"","value_unclear":false,"family_unclear":false,"comment_unclear":false,"value":""}},"general":{"family":[{"inn":"","family_name":"Мельничук С. Д","relations_other":"","name_unclear":false,"inn_hidden":true,"name_hidden":true,"relations":"Подружжя"},{"inn":"","family_name":"Мельничук В. Ю","relations_other":"","relations_unclear":false,"name_unclear":false,"inn_hidden":false,"name_hidden":false,"relations":"Дитина"},{"inn":"","family_name":"Мельничук В. Ю","relations_other":"","name_unclear":false,"inn_hidden":false,"name_hidden":false,"relations":"Дитина"}],"family_raw":"","name":"Юрій","full_name_suggest":{"input":["Мельничук Юрій Володимирович","Юрій Володимирович Мельничук","Юрій Мельничук"],"output":"Мельничук Юрій Володимирович"},"patronymic":"Володимирович","inn_hidden":true,"addresses":[{"place_city_type_hidden":false,"place_city_type":"","place_city_hidden":true,"place_hidden":true,"place_district":"","place_district_hidden":false,"place":"","place_address":"","place_address_hidden":true,"place_city":""}],"patronymic_hidden":false,"inn":"","inn_unclear":false,"last_name":"Мельничук","full_name":"Мельничук Юрій Володимирович","post":{"office":"Загальний місцевий суд","region_unclear":false,"post":"суддя уманського міськрайонного суду черкаської області","region":"Черкаська область","office_unclear":false}},"liabilities":{"54":{"sum_comment_unclear":false,"sum_comment":"","sum_hidden":false,"sum":"","sum_foreign_comment":"","sum_foreign":"","sum_unclear":false,"sum_comment_hidden":false},"55":{"sum_comment":"","sum_foreign_comment":"","sum_foreign":"","sum":""},"56":{"sum_comment":"","sum":"","sum_foreign_comment":"","sum_foreign":"","sum_unclear":false,"sum_comment_hidden":false},"57":{"sum_comment":"","sum_hidden":false,"sum":"","sum_foreign_comment":"","sum_foreign":"","sum_unclear":false,"sum_comment_hidden":false},"58":{"sum_comment_unclear":false,"sum_comment":"","sum_hidden":false,"sum":"","sum_foreign_comment":"","sum_foreign":"","sum_unclear":false,"sum_comment_hidden":false},"59":{"sum_comment":"","sum_foreign_comment":"","sum_foreign":"","sum":""},"60":{"sum_comment":"ПрАТ СК 'Провідна'","sum_hidden":false,"sum":"370","sum_foreign_comment":"","sum_foreign":"","sum_unclear":false,"sum_comment_hidden":false},"61":{"sum_comment":"","sum_foreign_comment":"","sum_foreign":"","sum":""},"62":{"sum_comment":"","sum_comment_unclear":false,"sum_foreign_comment":"","sum":"","sum_foreign":""},"63":{"sum_comment":"","sum_foreign_comment":"","sum_foreign":"","sum":"","sum_comment_hidden":false},"64":{"sum_comment":"","sum_foreign_comment":"","sum_foreign":"","sum":"","sum_comment_hidden":false}},"declaration":{"notfull_lostpages":"","additional_info_text":"","additional_info":"","date":"2016-03-11T00:00:00","notfull":"","url":"http://static.declarations.com.ua/declarations/chosen_ones/judges_batch/869_melnychuk_iurii_volodymyrovych_2015.pdf"},"intro":{"declaration_year":"2015"}}