{"income":{"5":{"value":"264647","family_comment":"","value_unclear":false,"family_hidden":false,"value_hidden":false,"family_unclear":false,"comment_unclear":false,"comment":"","family":"8649947"},"6":{"value":"","family_comment":"","comment_unclear":false,"family_hidden":false,"value_hidden":false,"family_unclear":false,"value_unclear":false,"comment":"","family":"160161"},"7":{"source_name_unclear":false,"value":"","family_comment":"","source_name":"","family":"","comment":""},"8":{"family_comment":"","value":"","family":"","comment":""},"9":{"value":"264647","value_unclear":false,"comment_hidden":false,"family_comment":"","comment_unclear":false,"comment":"","family":"7507433"},"10":{"value":"","comment_unclear":false,"value_hidden":false,"family_comment":"","family":"","comment":""},"11":{"family_comment":"","value":"","family":"","comment":""},"12":{"family_comment":"","value":"","family":"","comment":""},"13":{"family_comment":"","value":"","family":"","comment":""},"14":{"family_comment":"","value":"","family":"","comment":""},"15":{"family_comment":"","value":"","family":"","comment":""},"16":{"family_comment":"","value":"","family":"982353","comment":""},"17":{"family_comment":"","value":"","family":"","comment":""},"18":{"value":"","family_hidden":false,"value_hidden":false,"family_comment":"","family":"","comment":""},"19":{"family_comment":"","value":"","family":"","comment":""},"20":{"value":"","family_comment":"","value_unclear":false,"family_hidden":false,"value_hidden":false,"family_unclear":false,"family":"","comment":""}},"vehicle":{"35":[{"year_hidden":false,"brand_info":"CT V-3993 (власність","sum_rent_comment":"","year":"2012","brand_info_unclear":false,"year_unclear":false,"sum_rent":"","sum":"","brand":"Bentley Continental","sum_comment":"","brand_unclear":false,"brand_hidden":false},{"brand_info":"4999 , користування","sum_rent_comment":"","brand":"Land Rover","sum_comment":"","brand_unclear":true,"year":"2010","brand_info_unclear":false,"year_unclear":false,"sum":"","sum_rent":""}],"40":[{"brand_info":"4999 , власність","sum_rent_comment":"","brand":"Land Rover","sum_comment":"","brand_unclear":true,"year":"2010","brand_info_unclear":false,"year_unclear":false,"sum":"","sum_rent":""}]},"id":"vulyk_66_84","banks":{"45":[{"sum_foreign_comment":"","sum_units":"UAH","sum_comment":"","sum_comment_unclear":false,"sum_hidden":false,"sum_foreign_units":"UAH","sum_foreign":"","sum_comment_hidden":false,"sum_units_hidden":false,"sum":"4375773","sum_unclear":false}],"46":[{"sum_foreign_comment":"","sum":"1170320","sum_comment":"","sum_foreign_units":"UAH","sum_units":"UAH","sum_foreign":""}],"51":[{"sum_foreign_comment":"","sum":"1265587","sum_comment":"","sum_comment_unclear":false,"sum_foreign_units":"UAH","sum_units_unclear":false,"sum_comment_hidden":false,"sum_units":"UAH","sum_foreign":""}],"52":[{"sum_foreign_comment":"","sum_units":"UAH","sum_comment":"","sum_comment_unclear":true,"sum_hidden":false,"sum_foreign_units":"UAH","sum_foreign":"","sum_comment_hidden":false,"sum_units_hidden":false,"sum":"206706","sum_unclear":false}]},"declaration":{"additional_info_text":"","notfull_lostpages":"","date":"2015-03-31T00:00:00","notfull":"","additional_info":"","url":"http://static.declarations.com.ua/declarations/chosen_ones/mega_batch/dzharty_viktoriia_vasylivna.pdf"},"liabilities":{"54":{"sum_foreign_comment":"","sum":"","sum_comment":"","sum_comment_unclear":false,"sum_comment_hidden":false,"sum_unclear":false,"sum_foreign":""},"55":{"sum_foreign_comment":"","sum":"","sum_comment":"","sum_foreign":""},"56":{"sum_foreign_comment":"","sum":"","sum_comment":"","sum_hidden":false,"sum_comment_hidden":false,"sum_foreign_hidden":false,"sum_foreign":""},"57":{"sum_foreign_comment":"","sum":"","sum_comment":"","sum_comment_unclear":false,"sum_hidden":false,"sum_comment_hidden":false,"sum_unclear":false,"sum_foreign":""},"58":{"sum_foreign_comment":"","sum":"","sum_comment":"","sum_comment_unclear":false,"sum_unclear":false,"sum_foreign":""},"59":{"sum_foreign_comment":"","sum":"","sum_comment":"","sum_comment_unclear":false,"sum_hidden":false,"sum_foreign_hidden":false,"sum_foreign":""},"60":{"sum_foreign_comment":"","sum":"","sum_comment":"","sum_comment_unclear":false,"sum_foreign":""},"61":{"sum_foreign_comment":"","sum":"","sum_comment":"","sum_foreign":""},"62":{"sum_foreign_comment":"","sum_unclear":false,"sum":"","sum_comment":"","sum_hidden":false,"sum_foreign_hidden":false,"sum_foreign":""},"63":{"sum_foreign_comment":"","sum":"68213819","sum_comment":"","sum_comment_unclear":true,"sum_comment_hidden":false,"sum_unclear":false,"sum_foreign":""},"64":{"sum_foreign_comment":"","sum":"126369","sum_comment":"","sum_comment_unclear":true,"sum_foreign":""}},"ft_src":"CT V-3993 (власність\nBentley Continental\n2012\n4999 , користування\nLand Rover\n2010\n4999 , власність\nLand Rover\n2010\n1170320\n206706\n1265587\n4375773\n2014\nCT V-3993 (власність\nBentley Continental\n2012\n4999 , користування\n2010\nLand Rover\n4999 , власність\n2010\nLand Rover\n4375773\n1265587\n1170320\n206706\n28.3\nу власності\nДонецька область\nм. Донецьк\n16.9\nвласність\nКримська Автономна Республіка\nм. Ялта\nм. Ялта\n172.8\nвласність\nКримська Автономна Республіка\n268\nу власності\nДонецька область\nм. Донецьк\nу користуванні\nм. Київ\n1000\nу власності\nм. Київ\nвласність\n1000\nвласність\nм. Київ\nвласність\n2049\nвласність\nвласність\nКиївська область\n14.5\nу власності\nм. Київ\n611\nу власності\nу власності\nКиївська область\n386\nу власності\nм. Київ\nГосподарський місцевий суд\nсуддя господарського суду м. києва\nм. Київ\nПодружжя\nОмельченко В. П\nДитина\nОмельченко В. В\nДитина\nДжарти В. В\nДитина\nОмельченко В. В\nДжарти Вікторія Василівна\nВікторія Василівна Джарти\nВікторія Джарти\nДжарти Вікторія Василівна\nДжарти Вікторія Василівна\nВікторія\nДжарти\nВасилівна\nКиїв\nм. Київ\n68213819\n126369\n160161\n264647\n8649947\n982353\n264647\n7507433\n2014\n126369\n68213819\nу власності\nм. Донецьк\n28.3\nДонецька область\nу власності\nм. Київ\n14.5\nу власності\nу власності\n611\nКиївська область\nвласність\nм. Ялта\nКримська Автономна Республіка\n16.9\nвласність\nм. Ялта\n172.8\nКримська Автономна Республіка\nу власності\nвласність\nм. Київ\n1000\nвласність\nвласність\n1000\nм. Київ\nвласність\nвласність\n2049\nКиївська область\nу власності\n386\nм. Київ\nу власності\nм. Донецьк\n268\nДонецька область\nу користуванні\nм. Київ\nОмельченко В. П\nПодружжя\nОмельченко В. В\nДитина\nДжарти В. В\nДитина\nОмельченко В. В\nДитина\nВасилівна\nДжарти\nВікторія\nДжарти Вікторія Василівна\nВікторія Василівна Джарти\nВікторія Джарти\nДжарти Вікторія Василівна\nм. Київ\nКиїв\nм. Київ\nсуддя господарського суду м. києва\nГосподарський місцевий суд\nДжарти Вікторія Василівна\n160161\n8649947\n264647\n982353\n7507433\n264647","general":{"inn":"","name":"Вікторія","last_name_hidden":false,"last_name":"Джарти","family":[{"inn":"","inn_hidden":true,"relations_hidden":false,"family_name":"Омельченко В. П","relations_other":"","relations":"Подружжя","name_hidden":true,"name_unclear":false},{"inn":"","inn_hidden":true,"relations_unclear":false,"relations_hidden":false,"relations_other":"","relations":"Дитина","name_hidden":false,"family_name":"Омельченко В. В","name_unclear":false},{"inn":"","inn_hidden":true,"relations_hidden":false,"family_name":"Джарти В. В","relations_other":"","relations":"Дитина","name_hidden":true,"name_unclear":false},{"inn":"","inn_hidden":false,"family_name":"Омельченко В. В","relations_other":"","relations":"Дитина","name_hidden":false,"name_unclear":false}],"inn_hidden":true,"family_raw":"","inn_unclear":false,"post":{"post_unclear":false,"post":"суддя господарського суду м. києва","candidate":"","office_hidden":false,"region":"м. Київ","office":"Господарський місцевий суд","office_unclear":false},"full_name_suggest":{"output":"Джарти Вікторія Василівна","input":["Джарти Вікторія Василівна","Вікторія Василівна Джарти","Вікторія Джарти"]},"full_name":"Джарти Вікторія Василівна","addresses":[{"place_city_type_unclear":false,"place_city_type_hidden":false,"place_district_hidden":false,"place_city_type":"Місто","place_address_hidden":true,"place_address_unclear":false,"place_address":"","place":"м. Київ","place_district":"","place_unclear":false,"place_hidden":true,"place_city_unclear":false,"place_city_hidden":false,"place_city":"Київ","place_district_unclear":false}],"patronymic":"Василівна","last_name_unclear":false},"source":"VULYK","estate":{"23":[{"space_unclear":false,"costs":"","costs_comment":"","costs_hidden":false,"address_hidden":true,"region_hidden":true,"space_comment":"власність","space_hidden":false,"space":"1000","address":"власність","region":"м. Київ","address_unclear":false,"space_units_unclear":false,"space_units":"м²","space_units_hidden":false,"costs_rent":"","costs_rent_comment":""},{"costs_rent":"","region":"Київська область","costs":"","costs_rent_comment":"","costs_comment":"","address_hidden":false,"space_comment":"власність","space_units":"м²","space":"2049","address":"власність"}],"24":[{"space_hidden":false,"costs":"","costs_comment":"","costs_hidden":false,"address_hidden":true,"region_hidden":true,"space_comment":"у власності","space_unclear":false,"space":"611","address":"у власності","region":"Київська область","address_unclear":false,"costs_rent_comment":"","costs_rent_hidden":false,"space_comment_unclear":false,"space_units":"м²","costs_rent":""}],"25":[{"region_unclear":false,"space_hidden":false,"costs":"","costs_comment":"","costs_hidden":false,"address_hidden":true,"region_hidden":false,"space_comment":"у власності","space_unclear":false,"space":"268","address":"м. Донецьк","region":"Донецька область","address_unclear":false,"costs_rent_comment":"","space_comment_unclear":false,"space_units":"м²","space_units_hidden":false,"costs_rent":""},{"space_unclear":false,"costs":"","costs_comment":"","costs_hidden":false,"address_hidden":true,"region_hidden":true,"space_comment":"у користуванні","space_hidden":true,"space":"","address":"","costs_comment_unclear":false,"region":"м. Київ","costs_rent_comment":"","space_units":"м²","costs_rent":""}],"27":[{"space_unclear":false,"costs":"","costs_comment":"","costs_hidden":false,"address_hidden":true,"region_hidden":false,"space_comment":"у власності","space_hidden":false,"space":"28.3","address":"м. Донецьк","region":"Донецька область","costs_rent_comment":"","space_comment_unclear":false,"space_units":"м²","space_units_hidden":false,"costs_rent":""}],"28":[{"space_hidden":false,"costs":"","costs_comment":"","costs_hidden":false,"address_hidden":true,"region_hidden":false,"space_comment":"власність","space":"16.9","address":"м. Ялта","region":"Кримська Автономна Республіка","address_unclear":false,"costs_rent_comment":"","space_units":"м²","costs_rent":""},{"costs_rent":"","region":"Кримська Автономна Республіка","costs":"","costs_rent_comment":"","costs_comment":"","address_hidden":false,"space_comment":"власність","space_units":"м²","space":"172.8","address":"м. Ялта"}],"29":[{"space_unclear":false,"address_hidden":true,"region_hidden":true,"space_comment":"у власності","space_hidden":false,"space":"1000","address":"власність","region":"м. Київ","costs_property":"","costs_rent_comment":"","space_units":"м²","costs_property_comment":"","costs_rent":""}],"31":[{"space_unclear":false,"address_hidden":true,"region_hidden":true,"space_comment":"у власності","space_hidden":false,"space":"386","address":"","region":"м. Київ","costs_property":"","costs_rent_comment":"","space_comment_unclear":false,"space_comment_hidden":false,"space_units":"м²","costs_property_comment":"","costs_rent":""}],"33":[{"space_hidden":false,"address_hidden":true,"region_hidden":true,"space_comment":"у власності","space":"14.5","address":"","region":"м. Київ","costs_property":"","costs_rent_comment":"","space_units":"м²","costs_property_comment":"","costs_rent":""}]},"intro":{"declaration_year":"2014","isnotdeclaration":"","declaration_year_unclear":false}}