{"income":{"5":{"family_comment":"","value":"225871","family":"465000","comment":""},"6":{"family_comment":"","value":"222423","family":"","comment":""},"7":{"value":"","comment_hidden":false,"family_comment":"","source_name":"","family":"","comment":"","source_name_hidden":false},"8":{"family_comment":"","value":"","family_hidden":false,"comment":"","family":""},"9":{"value":"","family_comment":"","value_unclear":false,"family_unclear":false,"family":"","comment":""},"10":{"family_comment":"","value":"","family":"","comment":""},"11":{"family_comment":"","value":"","family":"","comment":""},"12":{"family_comment":"","value":"","family":"","comment":""},"13":{"family_comment":"","value":"","family":"","comment":""},"14":{"family_comment":"","value":"","family":"","comment":""},"15":{"family_comment":"","value":"","family":"","comment":""},"16":{"family_comment":"","value":"","family":"","comment":""},"17":{"family_comment":"","value":"","family":"465000","comment":""},"18":{"family_comment":"","value":"","family":"","comment":""},"19":{"family_comment":"","value":"3448","family":"","comment":""},"20":{"value":"","value_unclear":false,"family_hidden":false,"family_comment":"","family":"","comment":""}},"vehicle":{"40":[{"brand_info":"1396 куб. см.","sum_rent_comment":"","brand":"Hyundai i30","sum_comment":"","year":"2008","brand_info_unclear":false,"sum":"","sum_rent":""},{"brand_info":"2700 куб. см.","sum_rent_comment":"","brand":"SsangYong Rexton","sum_comment":"","year":"2008","sum":"","sum_rent":""}],"41":[{"brand_info":"1998 куб. см.","sum_rent_comment":"","brand":"Ford Transit","sum_comment":"","brand_unclear":false,"year":"2006","sum":"","sum_rent":""}]},"id":"vulyk_109_115","declaration":{"additional_info_text":"","notfull_lostpages":"","date":"2015-03-28T00:00:00","notfull":"","additional_info":"","url":"http://static.declarations.com.ua/declarations/chosen_ones/judges_batch/2572_hladiuk_iurii_vasylovych_2015.pdf"},"liabilities":{"54":{"sum_foreign_comment":"","sum":"","sum_comment":"","sum_hidden":false,"sum_comment_hidden":false,"sum_unclear":false,"sum_foreign":""},"55":{"sum_foreign_comment":"","sum":"","sum_comment":"","sum_comment_unclear":false,"sum_foreign":""},"56":{"sum_foreign_comment":"","sum":"3698","sum_comment":"","sum_foreign":""},"57":{"sum_foreign_comment":"","sum_comment_hidden":false,"sum":"","sum_comment":"","sum_foreign":""},"58":{"sum_foreign_comment":"","sum_comment_hidden":false,"sum":"","sum_comment":"","sum_foreign":""},"59":{"sum_foreign_comment":"","sum":"","sum_comment":"","sum_foreign":""},"60":{"sum_foreign_comment":"","sum":"","sum_comment":"","sum_foreign":""},"61":{"sum_foreign_comment":"","sum":"","sum_comment":"","sum_foreign":""},"62":{"sum_foreign_comment":"","sum":"","sum_comment":"","sum_foreign":""},"63":{"sum_foreign_comment":"","sum":"","sum_comment":"","sum_foreign":""},"64":{"sum_foreign_comment":"","sum":"","sum_comment":"","sum_foreign":""}},"ft_src":"3698\nсуддя господарського суду хмельницької області\nХмельницька область\nГосподарський місцевий суд\nЮрій\nПотапова М. В\nПодружжя\nПотапова Т. Ю\nДитина\nВасильович\nГладюк Юрій Васильович\nЮрій Васильович Гладюк\nЮрій Гладюк\nГладюк Юрій Васильович\nГладюк Юрій Васильович\nГладюк\n2006\n1998 куб. см.\nFord Transit\n1396 куб. см.\n2008\nHyundai i30\n2700 куб. см.\n2008\nSsangYong Rexton\n19.9\n.0784\n.9\n3.4\n.0407\n.1\n66\n46.6\n2015\n222423\n465000\n225871\n465000\n3448\n1396 куб. см.\n2008\nHyundai i30\n2700 куб. см.\n2008\nSsangYong Rexton\n1998 куб. см.\n2006\nFord Transit\n2015\nГладюк Юрій Васильович\nЮрій Васильович Гладюк\nЮрій Гладюк\nГладюк Юрій Васильович\nЮрій\nПодружжя\nПотапова М. В\nДитина\nПотапова Т. Ю\nГладюк Юрій Васильович\nВасильович\nГосподарський місцевий суд\nХмельницька область\nсуддя господарського суду хмельницької області\nГладюк\n3698\n222423\n465000\n225871\n465000\n3448\n.0784\n.9\n3.4\n.0407\n.1\n66\n46.6\n19.9\n3698\nПодружжя\nПотапова М. В\nДитина\nПотапова Т. Ю\nВасильович\nГладюк\nЮрій\nГладюк Юрій Васильович\nЮрій Васильович Гладюк\nЮрій Гладюк\nГладюк Юрій Васильович\nХмельницька область\nГосподарський місцевий суд\nсуддя господарського суду хмельницької області\nГладюк Юрій Васильович\n2006\n1998 куб. см.\nFord Transit\n2008\n1396 куб. см.\nHyundai i30\nSsangYong Rexton\n2700 куб. см.\n2008\n3448\n465000\n225871\n465000\n222423\n46.6\n.0784\n.9\n3.4\n66\n19.9\n.0407\n.1\n2015","general":{"name_hidden":false,"name":"Юрій","inn":"","family":[{"inn":"","relations":"Подружжя","relations_hidden":false,"inn_hidden":true,"relations_other":"","name_hidden":false,"family_name":"Потапова М. В","name_unclear":false},{"inn":"","relations":"Дитина","relations_other":"","inn_hidden":true,"family_name":"Потапова Т. Ю","name_hidden":false,"name_unclear":false}],"patronymic":"Васильович","inn_hidden":true,"family_raw":"","inn_unclear":false,"post":{"region_unclear":false,"region":"Хмельницька область","post":"суддя господарського суду хмельницької області","region_hidden":false,"office":"Господарський місцевий суд","office_hidden":false,"office_unclear":false},"full_name":"Гладюк Юрій Васильович","addresses":[{"place_district":"","place_city_hidden":true,"place_city":"","place_city_type_hidden":true,"place_district_hidden":true,"place_city_type":"","place_address_hidden":true,"place_address":"","place_hidden":true,"place":""}],"last_name":"Гладюк","full_name_suggest":{"output":"Гладюк Юрій Васильович","input":["Гладюк Юрій Васильович","Юрій Васильович Гладюк","Юрій Гладюк"]}},"source":"VULYK","estate":{"23":[{"space_unclear":false,"costs":"","costs_rent_unclear":false,"costs_comment":"","address_hidden":true,"region_hidden":true,"space_comment":"","space":".0784","address":"","region":"","costs_rent_comment":"","space_units":"га","costs_rent":""},{"space_hidden":false,"costs":"","costs_rent_unclear":false,"costs_comment":"","address_hidden":true,"region_hidden":true,"space_comment":"","space":".9","address":"","region":"","costs_rent_comment":"","space_units":"га","costs_rent":""},{"costs_rent":"","region":"","costs":"","costs_rent_comment":"","costs_comment":"","region_hidden":false,"space_comment":"","space_units":"га","space":"3.4","address":""}],"24":[{"costs_rent":"","region":"","costs":"","costs_rent_comment":"","costs_comment":"","address_hidden":true,"region_hidden":true,"space_comment":"","space_units":"м²","space":"66","address":""}],"25":[{"space_unclear":false,"costs":"","costs_comment":"","address_hidden":true,"region_hidden":true,"space_comment":"","space_hidden":false,"space":"46.6","address":"","region":"","costs_rent_comment":"","space_units":"м²","space_units_hidden":false,"costs_rent":""}],"29":[{"space_unclear":false,"address_hidden":true,"region_hidden":true,"space_comment":"","space":".0407","address":"","region":"","costs_property":"","costs_rent_comment":"","space_units":"га","costs_property_comment":"","costs_rent":""},{"costs_rent":"","costs_property":"","costs_rent_comment":"","space_comment":"","costs_property_comment":"","space_units":"га","space":".1","address":""}],"33":[{"costs_rent":"","costs_property":"","costs_rent_comment":"","address_hidden":true,"region_hidden":true,"space_comment":"","costs_property_comment":"","space_units":"м²","space":"19.9","address":""}]},"intro":{"declaration_year":"2015","isnotdeclaration":""}}