{"income":{"5":{"value":"234945","family_comment":"","value_unclear":false,"family_unclear":false,"comment_unclear":false,"comment":"","family":"361236"},"6":{"family_comment":"","value":"206196","comment_unclear":false,"family":"48767","comment":""},"7":{"family_comment":"","value":"","source_name":"","family":"","comment":""},"8":{"family_comment":"","value":"","family":"","comment":""},"9":{"family_comment":"","value":"","value_unclear":false,"family":"","comment":""},"10":{"family_comment":"","value":"20704","value_unclear":false,"family":"","comment":""},"11":{"family_comment":"","value":"","family":"","comment":""},"12":{"family_comment":"","value":"","family":"","comment":""},"13":{"family_comment":"","value":"","family":"","comment":""},"14":{"family_comment":"","value":"","family":"","comment":""},"15":{"family_comment":"","value":"","family":"298636","comment":""},"16":{"family_comment":"","value":"","family":"","comment":""},"17":{"family_comment":"","value":"","value_unclear":false,"family":"","comment":""},"18":{"family_comment":"","value":"","value_unclear":false,"family":"","comment":""},"19":{"family_comment":"","value":"","family":"","comment":""},"20":{"value":"20225","family_comment":"","value_unclear":false,"family_unclear":false,"comment_unclear":false,"comment":"","family":"13833"}},"vehicle":{"39":[{"year_hidden":false,"brand_info":"2 метра","sum_rent_comment":"","brand":"автопричіп легковий","sum_comment":"","brand_unclear":false,"year":"2013","brand_info_unclear":true,"sum":"5000","sum_rent":""}],"40":[{"brand_info":"2000 куб. см.","sum_rent_comment":"","brand":"Volkswagen Jetta","sum_comment":"","brand_unclear":false,"year":"2009","brand_hidden":false,"brand_info_hidden":false,"year_unclear":false,"sum":"","sum_rent":""}]},"id":"vulyk_84_155","declaration":{"additional_info_text":"","notfull_lostpages":"","date":"2015-03-24T00:00:00","notfull":"","additional_info":"","url":"http://static.declarations.com.ua/declarations/chosen_ones/judges_batch/2569_burko_ruslan_volodymyrovych.pdf"},"liabilities":{"54":{"sum_foreign_comment":"","sum_comment_hidden":false,"sum":"","sum_comment":"","sum_foreign":""},"55":{"sum_foreign_comment":"","sum":"","sum_comment":"","sum_foreign":""},"56":{"sum_foreign_comment":"","sum":"","sum_comment":"","sum_foreign":""},"57":{"sum_foreign_comment":"","sum_comment_hidden":false,"sum":"","sum_comment":"","sum_foreign":""},"58":{"sum_foreign_comment":"","sum_comment_hidden":false,"sum":"","sum_comment":"","sum_foreign":""},"59":{"sum_foreign_comment":"","sum":"","sum_comment":"","sum_foreign":""},"60":{"sum_foreign_comment":"","sum":"350","sum_comment":"","sum_foreign":""},"61":{"sum_foreign_comment":"","sum":"","sum_comment":"","sum_foreign":""},"62":{"sum_foreign_comment":"","sum":"21100","sum_comment":"","sum_foreign":""},"63":{"sum_foreign_comment":"","sum_comment_hidden":false,"sum":"298636","sum_comment":"","sum_foreign":""},"64":{"sum_foreign_comment":"","sum_comment_hidden":false,"sum":"12894","sum_comment":"","sum_foreign":""}},"ft_src":"21100\n12894\n298636\n350\nКіровоград\nКіровоградська область\nсуддя кіровського районного суд м. кіровограда\nКіровоградська область\nЗагальний місцевий суд\nРуслан\nБурко (Тупчій) Л. В\nПодружжя\nБурко Р. Р\nДитина\nБурко Д. Р\nДитина\nВолодимирович\nБурко Руслан Володимирович\nРуслан Володимирович Бурко\nРуслан Бурко\nБурко Руслан Володимирович\nБурко Руслан Володимирович\nБурко\nавтопричіп легковий\n2 метра\n2013\n5000\nVolkswagen Jetta\n2000 куб. см.\n2009\nКіровоградська область\nм. Кіровоград\n18\nКіровоградська область\nм. Кіровоград\n47\nКіровоградська область\nм. Кіровоград\n47\nКіровоградська область\nм. Кіровоград\n1000\nКіровоградська область\nм. Кіровоград\n500\nКіровоградська область\nм. Кіровоград\n47\n2014\n48767\n206196\n298636\n20704\n361236\n234945\n13833\n20225\nVolkswagen Jetta\n2000 куб. см.\n2009\n2 метра\nавтопричіп легковий\n2013\n5000\n2014\nБурко Руслан Володимирович\nРуслан Володимирович Бурко\nРуслан Бурко\nБурко Руслан Володимирович\nРуслан\nПодружжя\nБурко (Тупчій) Л. В\nДитина\nБурко Р. Р\nДитина\nБурко Д. Р\nБурко Руслан Володимирович\nВолодимирович\nсуддя кіровського районного суд м. кіровограда\nЗагальний місцевий суд\nКіровоградська область\nБурко\nКіровоград\nКіровоградська область\n12894\n350\n21100\n298636\n206196\n48767\n20225\n13833\n298636\n234945\n361236\n20704\nм. Кіровоград\n1000\nКіровоградська область\nм. Кіровоград\nКіровоградська область\n500\nм. Кіровоград\nКіровоградська область\n47\n47\nм. Кіровоград\nКіровоградська область\n47\nКіровоградська область\nм. Кіровоград\n18\nм. Кіровоград\nКіровоградська область\n12894\n21100\n350\n298636\nБурко (Тупчій) Л. В\nПодружжя\nБурко Р. Р\nДитина\nБурко Д. Р\nДитина\nВолодимирович\nБурко\nРуслан\nБурко Руслан Володимирович\nРуслан Володимирович Бурко\nРуслан Бурко\nБурко Руслан Володимирович\nКіровоградська область\nКіровоград\nКіровоградська область\nсуддя кіровського районного суд м. кіровограда\nЗагальний місцевий суд\nБурко Руслан Володимирович\n5000\n2013\nавтопричіп легковий\n2 метра\n2009\nVolkswagen Jetta\n2000 куб. см.\n298636\n20704\n20225\n13833\n234945\n361236\n48767\n206196\nм. Кіровоград\nКіровоградська область\n47\nм. Кіровоград\nКіровоградська область\n47\nм. Кіровоград\nКіровоградська область\n47\nм. Кіровоград\nКіровоградська область\n1000\nм. Кіровоград\nКіровоградська область\n18\nм. Кіровоград\nКіровоградська область\n500\n2014","general":{"inn":"","name":"Руслан","inn_unclear":false,"family":[{"inn":"","inn_hidden":true,"inn_unclear":false,"relations_hidden":false,"relations_other":"","relations":"Подружжя","name_hidden":false,"family_name":"Бурко (Тупчій) Л. В","name_unclear":true},{"inn":"","relations":"Дитина","relations_other":"","inn_hidden":false,"family_name":"Бурко Р. Р","name_hidden":false,"name_unclear":true},{"inn":"","relations":"Дитина","relations_other":"","inn_hidden":false,"family_name":"Бурко Д. Р","name_hidden":false,"name_unclear":true}],"inn_hidden":true,"family_raw":"","last_name":"Бурко","post":{"post_unclear":false,"region_unclear":false,"post":"суддя кіровського районного суд м. кіровограда","candidate":"","office_hidden":false,"region":"Кіровоградська область","post_hidden":false,"office":"Загальний місцевий суд","office_unclear":false,"region_hidden":false},"full_name":"Бурко Руслан Володимирович","addresses":[{"place_city_type_unclear":false,"place_address":"","place_district_hidden":false,"place_city_type":"Місто","place_address_hidden":true,"place_address_unclear":false,"place_city_type_hidden":false,"place":"Кіровоградська область","place_district":"","place_unclear":false,"place_city":"Кіровоград","place_city_unclear":false,"place_hidden":false,"place_city_hidden":false,"place_district_unclear":false}],"patronymic":"Володимирович","full_name_suggest":{"output":"Бурко Руслан Володимирович","input":["Бурко Руслан Володимирович","Руслан Володимирович Бурко","Руслан Бурко"]}},"source":"VULYK","estate":{"25":[{"region_unclear":false,"space_hidden":false,"costs":"","costs_comment":"","address_hidden":true,"region_hidden":false,"space_comment":"","space":"47","address":"м. Кіровоград","costs_comment_unclear":false,"costs_rent_comment_unclear":false,"region":"Кіровоградська область","address_unclear":false,"costs_rent_comment":"","space_units":"м²","costs_rent":""}],"29":[{"region_unclear":false,"address_hidden":true,"region_hidden":false,"space_comment":"","space":"1000","address":"м. Кіровоград","region":"Кіровоградська область","costs_property":"","costs_rent_comment":"","address_unclear":false,"space_units":"м²","costs_property_comment":"","costs_rent":""}],"31":[{"space_unclear":false,"address_hidden":true,"region_hidden":false,"space_comment":"","space":"47","address":"м. Кіровоград","region":"Кіровоградська область","costs_property":"","costs_rent_comment":"","address_unclear":false,"space_units":"м²","costs_property_comment":"","costs_rent":""},{"costs_rent":"","region":"Кіровоградська область","costs_property":"","costs_rent_comment":"","address_unclear":false,"space_comment":"","costs_property_comment":"","space_units":"м²","space":"47","address":"м. Кіровоград"}],"32":[{"space_unclear":false,"address_hidden":true,"region_hidden":false,"space_comment":"","space":"500","address":"м. Кіровоград","region":"Кіровоградська область","costs_property":"","costs_rent_comment":"","address_unclear":false,"space_units":"м²","costs_property_comment":"","costs_rent":""}],"33":[{"costs_rent":"","region":"Кіровоградська область","costs_property":"","costs_rent_comment":"","address_hidden":false,"region_hidden":false,"space_comment":"","costs_property_comment":"","space_units":"м²","space":"18","address":"м. Кіровоград"}]},"intro":{"declaration_year":"2014","isnotdeclaration":"","declaration_year_unclear":false}}