{"income":{"5":{"family_comment":"","value":"276235.61","family":"","comment":""},"6":{"family_comment":"","value":"252184.02","value_unclear":false,"family":"","comment":""},"7":{"value":"","family_comment":"","source_name":"","family":"","comment":"","source_name_hidden":false},"8":{"family_comment":"","value":"","family":"","comment":""},"9":{"family_comment":"","value":"","family":"","comment":""},"10":{"family_comment":"","value":"","family":"","comment":""},"11":{"family_comment":"","value":"","comment_hidden":false,"family":"","comment":""},"12":{"family_comment":"","value":"","family":"","comment":""},"13":{"family_comment":"","value":"","family":"","comment":""},"14":{"family_comment":"","value":"","family":"","comment":""},"15":{"value":"","family_comment":"","value_unclear":false,"family_unclear":false,"family":"","comment":""},"16":{"family_comment":"","value":"","family":"","comment":""},"17":{"family_comment":"","value":"","family":"","comment":""},"18":{"family_comment":"","value":"","family":"","comment":""},"19":{"family_comment":"","value":"5031.9","family":"","comment":""},"20":{"family_comment":"","value":"19019.69","comment_unclear":false,"family":"","comment":""}},"vehicle":{"35":[{"brand_info":"1975 куб. см., 4325 мм, 142 к. с., 6000 об/х","sum_rent_comment":"","brand":"Hyundai Tucson","sum_comment":"договір купівлі-продажу від 08. 06. 2012","year":"2011","brand_hidden":false,"brand_info_unclear":false,"sum":"169900","sum_rent":""}]},"id":"vulyk_104_81","banks":{"45":[{"sum_foreign_comment":"","sum_units":"UAH","sum_comment":"Ощадбанк СРСР","sum_hidden":false,"sum_foreign_units":"UAH","sum_foreign_hidden":false,"sum_comment_hidden":false,"sum_unclear":false,"sum":"12717.09","sum_foreign":""}]},"declaration":{"date":"2016-04-20T00:00:00","additional_info_text":"","additional_info":"","url":"http://static.declarations.com.ua/declarations/chosen_ones/judges_batch/1879_datsenko_liubov_mykhailivna_2015.pdf"},"liabilities":{"54":{"sum_foreign_comment":"","sum_foreign_hidden":false,"sum_comment":"","sum_hidden":false,"sum_comment_hidden":false,"sum_unclear":false,"sum":"","sum_foreign":""},"55":{"sum_foreign_comment":"","sum":"","sum_comment":"","sum_foreign":""},"56":{"sum_foreign_comment":"","sum":"","sum_comment":"","sum_unclear":false,"sum_foreign":""},"57":{"sum_foreign_comment":"","sum_foreign_hidden":false,"sum_comment":"","sum_comment_unclear":false,"sum_comment_hidden":false,"sum":"","sum_foreign":""},"58":{"sum_foreign_comment":"","sum":"","sum_comment":"","sum_unclear":false,"sum_foreign":""},"59":{"sum_foreign_comment":"","sum":"","sum_comment":"","sum_foreign":""},"60":{"sum_foreign_comment":"","sum_foreign_hidden":false,"sum_comment":"","sum_comment_hidden":false,"sum":"","sum_foreign":""},"61":{"sum_foreign_comment":"","sum":"","sum_comment":"","sum_foreign":""},"62":{"sum_foreign_comment":"","sum":"","sum_comment":"","sum_foreign":""},"63":{"sum_foreign_comment":"","sum":"","sum_comment":"","sum_foreign":""},"64":{"sum_foreign_comment":"","sum":"","sum_comment":"","sum_foreign":""}},"ft_src":"Даценко Любов Михайлівна\nсуддя апеляційного суду київської області\nКиївська область\nЗагальний апеляційний суд\nЛюбов\nДаценко Любов Михайлівна\nЛюбов Михайлівна Даценко\nЛюбов Даценко\nДаценко Любов Михайлівна\nДаценко\nМихайлівна\nдоговір купівлі-продажу від 08. 06. 2012\n2011\nHyundai Tucson\n1975 куб. см., 4325 мм, 142 к. с., 6000 об/х\n169900\nОщадбанк СРСР\n12717.09\n2015\n1975 куб. см., 4325 мм, 142 к. с., 6000 об/х\n169900\nHyundai Tucson\n2011\nдоговір купівлі-продажу від 08. 06. 2012\n12717.09\nОщадбанк СРСР\n2015\nДаценко Любов Михайлівна\nЛюбов Михайлівна Даценко\nЛюбов Даценко\nДаценко Любов Михайлівна\nДаценко Любов Михайлівна\nМихайлівна\nЛюбов\nДаценко\nЗагальний апеляційний суд\nсуддя апеляційного суду київської області\nКиївська область\n252184.02\n19019.69\n276235.61\n5031.9\n3.9586\nуцспадкована земельна частка/пай\nбезоплатна приватизація\n1.0629\nбезоплатна приватизація\nбезоплатна приватизація\n.12\nбезоплатна приватизація\n111.1\nспадщина від 01. 11. 2006р\n27.6\nсвідотцтво про право власності від 07. 04. 1999\nуцспадкована земельна частка/пай\n3.9586\nбезоплатна приватизація\nбезоплатна приватизація\n1.0629\nбезоплатна приватизація\nбезоплатна приватизація\n.12\nспадщина від 01. 11. 2006р\n111.1\nсвідотцтво про право власності від 07. 04. 1999\n27.6\nДаценко\nМихайлівна\nсуддя апеляційного суду київської області\nЗагальний апеляційний суд\nКиївська область\nДаценко Любов Михайлівна\nДаценко Любов Михайлівна\nЛюбов Михайлівна Даценко\nЛюбов Даценко\nДаценко Любов Михайлівна\nЛюбов\n252184.02\n276235.61\n5031.9\n19019.69\nдоговір купівлі-продажу від 08. 06. 2012\n2011\n1975 куб. см., 4325 мм, 142 к. с., 6000 об/х\nHyundai Tucson\n169900\n5031.9\n19019.69\n276235.61\n252184.02\nсвідотцтво про право власності від 07. 04. 1999\n27.6\nуцспадкована земельна частка/пай\n3.9586\nбезоплатна приватизація\nбезоплатна приватизація\n1.0629\nбезоплатна приватизація\nбезоплатна приватизація\n.12\nспадщина від 01. 11. 2006р\n111.1\nОщадбанк СРСР\n12717.09\n2015","general":{"inn":"","inn_hidden":true,"last_name":"Даценко","post":{"region":"Київська область","region_unclear":false,"post":"суддя апеляційного суду київської області","office_unclear":false,"office":"Загальний апеляційний суд"},"name":"Любов","full_name":"Даценко Любов Михайлівна","family_raw":"","addresses":[{"place_district":"","place_city_hidden":true,"place_city":"","place_city_type_hidden":false,"place_district_hidden":false,"place_city_type":"","place_address_hidden":true,"place_address":"","place_hidden":true,"place":""}],"full_name_suggest":{"output":"Даценко Любов Михайлівна","input":["Даценко Любов Михайлівна","Любов Михайлівна Даценко","Любов Даценко"]},"patronymic":"Михайлівна"},"source":"VULYK","estate":{"23":[{"space_hidden":false,"costs":"","costs_comment":"","address_hidden":false,"region_hidden":true,"space_comment":"уцспадкована земельна частка/пай","space":"3.9586","address":"","region":"","costs_rent_comment":"","space_comment_unclear":false,"space_units":"га","costs_rent":""},{"costs_rent":"","costs_rent_comment_unclear":false,"region":"","costs":"","costs_rent_comment":"","costs_comment":"безоплатна приватизація","space_comment_unclear":false,"space_comment":"безоплатна приватизація","space_units":"га","space":"1.0629","address":""},{"costs_rent":"","region":"","costs":"","costs_rent_comment":"","costs_comment":"безоплатна приватизація","space_comment_unclear":false,"space_comment":"безоплатна приватизація","space_units":"га","space":".12","address":""}],"24":[{"space_hidden":false,"costs":"","costs_comment":"","address_hidden":false,"region_hidden":true,"space_comment":"спадщина від 01. 11. 2006р","space":"111.1","address":"","region":"","costs_rent_comment":"","space_comment_unclear":false,"space_units":"м²","costs_rent":""}],"25":[{"costs":"","costs_comment":"","address_hidden":false,"region_hidden":true,"space_comment":"свідотцтво про право власності від 07. 04. 1999","space":"27.6","address":"","costs_unclear":false,"region":"","costs_rent_comment":"","space_comment_unclear":false,"space_units":"м²","costs_rent":""}]},"intro":{"declaration_year":"2015","isnotdeclaration":""}}