{"income":{"5":{"family_comment":"","family_unclear":false,"value":"177179","family":"","comment":""},"6":{"value":"177179","family_comment":"","value_unclear":false,"family_unclear":false,"family":"","comment":""},"7":{"source_name_unclear":false,"value":"","family_comment":"","source_name":"","family":"","comment":"","source_name_hidden":false},"8":{"family_comment":"","value":"","family":"","comment":""},"9":{"family_comment":"","family_unclear":false,"value":"","family":"","comment":""},"10":{"family_comment":"","value":"","family":"","comment":""},"11":{"family_comment":"","value":"","family":"","comment":""},"12":{"family_comment":"","value":"","family":"","comment":""},"13":{"family_comment":"","value":"","family":"","comment":""},"14":{"family_comment":"","value":"","family":"","comment":""},"15":{"family_comment":"","value":"","family":"","comment":""},"16":{"family_comment":"","family_unclear":false,"value":"","family":"","comment":""},"17":{"family_comment":"","family_unclear":false,"value":"","family":"","comment":""},"18":{"family_comment":"","value":"","family":"","comment":""},"19":{"family_comment":"","value":"","family":"","comment":""},"20":{"family_comment":"","value":"","comment_unclear":false,"family":"","comment":""}},"vehicle":{"35":[{"brand_info":"1390 куб. см.","sum":"","brand":"Volkswagen Polo","sum_comment":"","brand_unclear":false,"year":"2013","brand_hidden":false,"brand_info_hidden":false,"brand_info_unclear":false,"sum_rent_comment":"","sum_rent":""}]},"id":"vulyk_95_30","declaration":{"additional_info_text":"","notfull_lostpages":"","date":"2016-03-14T00:00:00","notfull":"","additional_info":"","url":"http://static.declarations.com.ua/declarations/chosen_ones/judges_batch/31_poliakh_nataliia_anatoliivna.pdf"},"liabilities":{"54":{"sum_foreign_comment":"","sum":"","sum_comment":"","sum_hidden":false,"sum_comment_hidden":false,"sum_unclear":false,"sum_foreign":""},"55":{"sum_foreign_comment":"","sum":"","sum_comment":"","sum_foreign":""},"56":{"sum_foreign_comment":"","sum":"","sum_comment":"","sum_foreign":""},"57":{"sum_foreign_comment":"","sum":"50902","sum_comment":"","sum_hidden":true,"sum_comment_hidden":false,"sum_unclear":true,"sum_foreign":""},"58":{"sum_foreign_comment":"","sum":"4120","sum_comment":"","sum_hidden":true,"sum_comment_hidden":false,"sum_unclear":false,"sum_foreign":""},"59":{"sum_foreign_comment":"","sum":"","sum_comment":"","sum_foreign":""},"60":{"sum_foreign_comment":"","sum":"","sum_comment":"","sum_hidden":false,"sum_comment_hidden":false,"sum_foreign":""},"61":{"sum_foreign_comment":"","sum":"","sum_comment":"","sum_foreign":""},"62":{"sum_foreign_comment":"","sum":"","sum_comment":"","sum_unclear":false,"sum_foreign":""},"63":{"sum_foreign_comment":"","sum":"","sum_comment":"","sum_unclear":false,"sum_foreign":""},"64":{"sum_foreign_comment":"","sum":"","sum_comment":"","sum_foreign":""}},"ft_src":"Volkswagen Polo\n1390 куб. см.\n2013\nХарківська область\nм. Харків\n16.8\nм. Харків\n50.9\nХарківська область\n2015\n177179\n177179\nVolkswagen Polo\n1390 куб. см.\n2013\n16.8\nм. Харків\nХарківська область\n50.9\nм. Харків\nХарківська область\nАнатоліївна\nПолях\nПолях Наталія Анатоліївна\nНаталія Анатоліївна Полях\nНаталія Полях\nПолях Наталія Анатоліївна\nНаталія\nХарків\n61103\nХарківська область\nПолях Наталія Анатоліївна\nАдміністративний місцевий суд\nсуддя харківського окружного адміністративного суду\nХарківська область\n4120\n50902\n177179\n177179\n2015\n4120\n50902\nАнатоліївна\nХарківська область\nХарків\n61103\nПолях\nХарківська область\nАдміністративний місцевий суд\nсуддя харківського окружного адміністративного суду\nПолях Наталія Анатоліївна\nПолях Наталія Анатоліївна\nНаталія Анатоліївна Полях\nНаталія Полях\nПолях Наталія Анатоліївна\nНаталія","general":{"inn":"","inn_hidden":true,"last_name":"Полях","post":{"post":"суддя харківського окружного адміністративного суду","region":"Харківська область","candidate":"","office_hidden":false,"office":"Адміністративний місцевий суд","office_unclear":false},"name":"Наталія","full_name":"Полях Наталія Анатоліївна","family_raw":"","addresses":[{"place_address":"61103","place_district_hidden":false,"place_city_type":"Місто","place_city_hidden":false,"place_address_unclear":false,"place_city_type_hidden":false,"place_city":"Харків","place":"Харківська область","place_district":"","place_address_hidden":true,"place_hidden":false,"place_city_unclear":false}],"full_name_suggest":{"output":"Полях Наталія Анатоліївна","input":["Полях Наталія Анатоліївна","Наталія Анатоліївна Полях","Наталія Полях"]},"patronymic":"Анатоліївна"},"source":"VULYK","estate":{"25":[{"space_unclear":false,"costs":"","costs_comment":"","address_hidden":true,"region_hidden":false,"space_comment":"","space_hidden":false,"space":"50.9","address":"м. Харків","region":"Харківська область","address_unclear":false,"costs_rent_comment":"","space_comment_unclear":false,"space_units":"м²","costs_rent":""}],"27":[{"costs":"","costs_comment":"","address_hidden":true,"region_hidden":false,"space_comment":"","space":"16.8","address":"м. Харків","region":"Харківська область","address_unclear":false,"costs_rent_comment":"","space_units":"м²","costs_rent":""}]},"intro":{"declaration_year":"2015","isnotdeclaration":""}}