{"income":{"5":{"family_comment":"","value":"272037","family":"39032","comment":""},"6":{"family_comment":"","value":"243741","family":"29612","comment":""},"7":{"family_comment":"","value":"","source_name":"","family":"","comment":""},"8":{"family_comment":"","value":"","family":"","comment":""},"9":{"value":"","comment_unclear":false,"family_comment":"","family":"","comment":"","family_comment_unclear":false},"10":{"family_comment":"путівка","value":"","family":"4284","comment":""},"11":{"family_comment":"","value":"","family":"","comment":""},"12":{"family_comment":"","value":"","family":"","comment":""},"13":{"family_comment":"","value":"","family":"","comment":""},"14":{"family_comment":"","value":"28296","family":"","comment":""},"15":{"family_comment":"","value":"","family":"","comment":""},"16":{"family_comment":"","value":"","family":"","comment":""},"17":{"family_comment":"","value":"","family":"","comment":""},"18":{"family_comment":"","value":"","family":"","comment":""},"19":{"value":"","family_comment":"","value_unclear":false,"family_unclear":false,"family":"","comment":""},"20":{"value":"","family_comment":"за рішенням суду","value_unclear":false,"comment_hidden":false,"family_comment_hidden":false,"family_unclear":false,"family_comment_unclear":false,"comment_unclear":false,"comment":"","family":"5136"}},"vehicle":{"40":[{"year_hidden":false,"brand_info":"1500 куб. см., 56.63 кВт","sum_rent_comment":"","brand":"ВАЗ 2105","sum_comment":"","year":"1995","brand_hidden":false,"brand_info_hidden":false,"brand_info_unclear":false,"sum":"","sum_rent":""},{"brand_info":"1998 куб. см, 105.91 кВт","sum_rent_comment":"","brand":"Kia Magentis","sum_comment":"","year":"2008","brand_info_hidden":false,"sum":"","sum_rent":""}]},"id":"vulyk_106_147","banks":{"45":[{"sum_foreign_comment":"","sum_units":"UAH","sum_comment":"","sum_foreign_comment_hidden":false,"sum_hidden":false,"sum_foreign_units":"UAH","sum_comment_hidden":false,"sum":"16671","sum_foreign":""}],"46":[{"sum_foreign_comment":"","sum_units":"UAH","sum_comment":"","sum_foreign_units":"UAH","sum":"10122","sum_foreign":""}],"51":[{"sum_foreign_comment":"","sum_units":"UAH","sum_comment":"","sum_comment_unclear":false,"sum_foreign_comment_hidden":false,"sum_foreign_units":"UAH","sum_comment_hidden":false,"sum":"1081","sum_foreign":""}]},"declaration":{"additional_info_text":"","notfull_lostpages":"","date":"2016-03-25T00:00:00","notfull":"","additional_info":"","url":"http://static.declarations.com.ua/declarations/chosen_ones/judges_batch/2286_ivanenko_tetiana_volodymyrivna.pdf"},"liabilities":{"54":{"sum_foreign_comment":"","sum":"120","sum_comment":"СК 'Інгосстрах'","sum_comment_unclear":false,"sum_hidden":false,"sum_comment_hidden":false,"sum_foreign":""},"55":{"sum_foreign_comment":"","sum":"","sum_hidden":false,"sum_comment":"","sum_foreign":""},"56":{"sum_foreign_comment":"","sum":"","sum_comment":"","sum_hidden":false,"sum_comment_hidden":false,"sum_unclear":false,"sum_foreign":""},"57":{"sum_foreign_comment":"","sum":"","sum_comment":"","sum_hidden":false,"sum_comment_hidden":false,"sum_foreign":""},"58":{"sum_foreign_comment":"","sum":"","sum_comment":"","sum_hidden":false,"sum_comment_hidden":false,"sum_foreign":""},"59":{"sum_foreign_comment":"","sum":"","sum_comment":"","sum_foreign":""},"60":{"sum_foreign_comment":"","sum":"120","sum_comment":"СК 'Інгосстрах'","sum_hidden":false,"sum_comment_hidden":false,"sum_foreign":""},"61":{"sum_foreign_comment":"","sum":"","sum_comment":"","sum_foreign":""},"62":{"sum_foreign_comment":"","sum":"22700","sum_comment":"","sum_comment_hidden":false,"sum_unclear":false,"sum_foreign":""},"63":{"sum_foreign_comment":"","sum":"","sum_comment":"","sum_foreign":""},"64":{"sum_foreign_comment":"","sum":"","sum_comment":"","sum_foreign":""}},"ft_src":"22700\nСК 'Інгосстрах'\n120\nСК 'Інгосстрах'\n120\nсуддя житомирського апеляційного адміністративного суду\nЖитомирська область\nАпеляційний адміністративний суд\nТетяна\nДєдух С. М\nПодружжя\nДєдух А. С\nДитина\nДєдух І. С\nДитина\nВолодимирівна\nІваненко Тетяна Володимирівна\nТетяна Володимирівна Іваненко\nТетяна Іваненко\nІваненко Тетяна Володимирівна\nІваненко Тетяна Володимирівна\nІваненко\nЖитомир\nЖитомирська область\n1500 куб. см., 56.63 кВт\nВАЗ 2105\n1995\n1998 куб. см, 105.91 кВт\n2008\nKia Magentis\n10122\n1081\n16671\n2015\n1500 куб. см., 56.63 кВт\n1995\nВАЗ 2105\nKia Magentis\n1998 куб. см, 105.91 кВт\n2008\n16671\n1081\n10122\n2500\nЖитомирська область\nс. Хомутець\n1.7\nпай\nс. Новий Дорогинь\nЖитомирська область\nІваненко Тетяна Володимирівна\nТетяна Володимирівна Іваненко\nТетяна Іваненко\nІваненко Тетяна Володимирівна\nІваненко Тетяна Володимирівна\nПодружжя\nДєдух С. М\nДитина\nДєдух А. С\nДитина\nДєдух І. С\nТетяна\nІваненко\nЖитомирська область\nАпеляційний адміністративний суд\nсуддя житомирського апеляційного адміністративного суду\nВолодимирівна\nЖитомирська область\nЖитомир\nСК 'Інгосстрах'\n120\nСК 'Інгосстрах'\n120\n22700\n243741\n29612\n5136\nза рішенням суду\n28296\n272037\n39032\n4284\nпутівка\n2015\nСК 'Інгосстрах'\n120\n22700\nСК 'Інгосстрах'\n120\nЖитомирська область\nс. Хомутець\n2500\nпай\nс. Новий Дорогинь\nЖитомирська область\n1.7\nДєдух С. М\nПодружжя\nДєдух А. С\nДитина\nДєдух І. С\nДитина\nВолодимирівна\nІваненко\nТетяна\nІваненко Тетяна Володимирівна\nТетяна Володимирівна Іваненко\nТетяна Іваненко\nІваненко Тетяна Володимирівна\nЖитомир\nЖитомирська область\nЖитомирська область\nАпеляційний адміністративний суд\nсуддя житомирського апеляційного адміністративного суду\nІваненко Тетяна Володимирівна\n29612\n243741\n28296\n4284\nпутівка\n39032\n272037\n5136\nза рішенням суду\nВАЗ 2105\n1500 куб. см., 56.63 кВт\n1995\nKia Magentis\n1998 куб. см, 105.91 кВт\n2008\n28296\n4284\nпутівка\nза рішенням суду\n5136\n39032\n272037\n29612\n243741\n2500\nс. Хомутець\nЖитомирська область\nпай\nс. Новий Дорогинь\nЖитомирська область\n1.7\n16671\n1081\n10122\n2015","general":{"inn":"","name":"Тетяна","inn_unclear":false,"family":[{"inn":"","inn_hidden":true,"relations_unclear":false,"relations_hidden":false,"relations_other":"","relations":"Подружжя","name_hidden":true,"family_name":"Дєдух С. М","name_unclear":false},{"inn":"","relations":"Дитина","relations_unclear":false,"family_name":"Дєдух А. С","inn_hidden":false,"relations_other":"","name_hidden":false,"name_unclear":false},{"inn_hidden":false,"inn":"","name_hidden":false,"family_name":"Дєдух І. С","relations":"Дитина","name_unclear":false}],"inn_hidden":true,"family_raw":"","last_name":"Іваненко","post":{"region_unclear":false,"region":"Житомирська область","post":"суддя житомирського апеляційного адміністративного суду","office":"Апеляційний адміністративний суд","office_unclear":false,"post_hidden":false},"full_name":"Іваненко Тетяна Володимирівна","addresses":[{"place_district":"","place_city_hidden":false,"place_city":"Житомир","place_city_type_hidden":false,"place_district_hidden":true,"place_city_type":"Місто","place_address_hidden":true,"place_address":"","place_hidden":false,"place":"Житомирська область"}],"patronymic":"Володимирівна","full_name_suggest":{"output":"Іваненко Тетяна Володимирівна","input":["Іваненко Тетяна Володимирівна","Тетяна Володимирівна Іваненко","Тетяна Іваненко"]},"name_unclear":false},"source":"VULYK","estate":{"23":[{"region_unclear":false,"space_hidden":false,"costs":"","costs_comment":"","address_hidden":true,"region_hidden":false,"space_comment":"","space_unclear":false,"space":"2500","address":"с. Хомутець","costs_comment_unclear":false,"costs_rent_comment_unclear":false,"region":"Житомирська область","address_unclear":false,"costs_rent_comment":"","space_comment_unclear":false,"space_comment_hidden":false,"space_units":"м²","costs_rent":""}],"29":[{"region_unclear":false,"costs_property_comment":"","address_hidden":false,"region_hidden":false,"space_comment":"пай","space":"1.7","address":"с. Новий Дорогинь","costs_rent_comment_unclear":false,"region":"Житомирська область","costs_property":"","costs_rent_comment":"","space_comment_unclear":false,"address_unclear":false,"space_units":"га","space_units_unclear":false,"costs_rent":""}]},"intro":{"declaration_year":"2015","isnotdeclaration":""}}