{"income":{"5":{"family_comment":"","value":"222497.53","family":"20355.6","comment":""},"6":{"family_comment":"","value":"194311.53","family":"","comment":"","family_comment_unclear":false},"7":{"value":"","comment_hidden":false,"family_comment":"","source_name":"","family":"","comment":"","source_name_hidden":false},"8":{"family_comment":"","value":"","family":"","comment":""},"9":{"family_comment":"","value":"","family":"","comment":""},"10":{"value":"13398","value_unclear":false,"value_hidden":false,"family_comment":"","family":"","comment":""},"11":{"family_comment":"","value":"","family":"","comment":""},"12":{"family_comment":"","value":"","family":"","comment":""},"13":{"family_comment":"","value":"3400","family":"","comment":""},"14":{"family_comment":"","value":"","family":"","comment":""},"15":{"family_comment":"","value":"11388","family":"20355.6","comment":""},"16":{"family_comment":"","value":"","family":"","comment":""},"17":{"family_comment":"","value":"","family":"","comment":""},"18":{"family_comment":"","value":"","family":"","comment":""},"19":{"family_comment":"","value":"","family":"","comment":""},"20":{"family_comment":"","value":"","comment_unclear":false,"family":"","comment":""}},"vehicle":{"35":[{"brand_info":"1994 куб. см. (користування","sum_rent_comment":"","brand":"Subaru Impreza","sum_comment":"","brand_unclear":false,"year":"2010","brand_info_unclear":false,"year_unclear":false,"sum":"","sum_rent":""}],"40":[{"brand_info":"3456 куб. см.","sum_rent_comment":"","brand":"Toyota Aurion","sum_comment":"","brand_unclear":false,"year":"2008","sum":"","sum_rent":""}]},"id":"vulyk_86_55","declaration":{"additional_info_text":"","notfull_lostpages":"","date":"2015-03-18T00:00:00","notfull":"","additional_info":"","url":"http://static.declarations.com.ua/declarations/chosen_ones/judges_batch/2758_khaladzhy_olha_volodymyrivna.pdf"},"liabilities":{"54":{"sum_foreign_comment":"","sum":"","sum_comment":"","sum_unclear":false,"sum_foreign":""},"55":{"sum_foreign_comment":"","sum":"","sum_comment":"","sum_foreign":""},"56":{"sum_foreign_comment":"","sum":"7500","sum_hidden":false,"sum_comment":"","sum_foreign":""},"57":{"sum_foreign_comment":"","sum":"","sum_comment":"","sum_unclear":false,"sum_foreign":""},"58":{"sum_foreign_comment":"","sum":"","sum_comment":"","sum_unclear":false,"sum_foreign":""},"59":{"sum_foreign_comment":"","sum":"","sum_comment":"","sum_foreign":""},"60":{"sum_foreign_comment":"","sum_comment_hidden":false,"sum":"","sum_comment":"","sum_foreign":""},"61":{"sum_foreign_comment":"","sum":"","sum_comment":"","sum_foreign":""},"62":{"sum_foreign_comment":"","sum":"","sum_comment":"","sum_foreign":""},"63":{"sum_foreign_comment":"","sum":"","sum_comment":"","sum_foreign":""},"64":{"sum_foreign_comment":"","sum":"","sum_comment":"","sum_foreign":""}},"ft_src":"7500\nсуддя апеляційного суду донецької області\nДонецька область\nЗагальний апеляційний суд\nОльга\nКорнієнко О. Б\nПодружжя\nМоденко М. А\nДитина\nКорнієнко Д. О\nДитина\nВолодимирівна\nХаладжи Ольга Володимирівна\nОльга Володимирівна Халаджи\nОльга Халаджи\nХаладжи Ольга Володимирівна\nХаладжи Ольга Володимирівна\nХаладжи\n1994 куб. см. (користування\nSubaru Impreza\n2010\n2008\n3456 куб. см.\nToyota Aurion\n2014\n194311.53\n20355.6\n11388\n3400\n13398\n20355.6\n222497.53\n1994 куб. см. (користування\n2010\nSubaru Impreza\n3456 куб. см.\nToyota Aurion\n2008\n2014\nХаладжи Ольга Володимирівна\nОльга Володимирівна Халаджи\nОльга Халаджи\nХаладжи Ольга Володимирівна\nХаладжи Ольга Володимирівна\nПодружжя\nКорнієнко О. Б\nДитина\nМоденко М. А\nКорнієнко Д. О\nДитина\nОльга\nХаладжи\nЗагальний апеляційний суд\nДонецька область\nсуддя апеляційного суду донецької області\nВолодимирівна\n7500\n194311.53\n3400\n11388\n20355.6\n222497.53\n20355.6\n13398\n7500\nКорнієнко О. Б\nПодружжя\nМоденко М. А\nДитина\nДитина\nКорнієнко Д. О\nВолодимирівна\nХаладжи\nОльга\nХаладжи Ольга Володимирівна\nОльга Володимирівна Халаджи\nОльга Халаджи\nХаладжи Ольга Володимирівна\nДонецька область\nЗагальний апеляційний суд\nсуддя апеляційного суду донецької області\nХаладжи Ольга Володимирівна\n2010\n1994 куб. см. (користування\nSubaru Impreza\n2008\n3456 куб. см.\nToyota Aurion\n20355.6\n11388\n13398\n20355.6\n222497.53\n194311.53\n3400\n2014","general":{"inn":"","name":"Ольга","patronymic_unclear":false,"family":[{"inn":"","inn_hidden":true,"relations_hidden":false,"family_name":"Корнієнко О. Б","relations_other":"","relations":"Подружжя","name_hidden":false,"name_unclear":false},{"inn":"","relations":"Дитина","relations_other":"","inn_hidden":false,"family_name":"Моденко М. А","name_hidden":false,"name_unclear":false},{"inn":"","family_name":"Корнієнко Д. О","relations":"Дитина","inn_hidden":false,"name_unclear":false}],"patronymic":"Володимирівна","inn_hidden":true,"family_raw":"","inn_unclear":false,"post":{"post_unclear":false,"post":"суддя апеляційного суду донецької області","candidate":"","office_hidden":false,"region":"Донецька область","office":"Загальний апеляційний суд","office_unclear":false,"region_hidden":false},"full_name":"Халаджи Ольга Володимирівна","addresses":[{"place_district":"","place_unclear":false,"place_city":"","place_city_type_hidden":true,"place_district_hidden":true,"place_city_type":"","place_city_hidden":true,"place_address_hidden":true,"place_address":"","place_hidden":true,"place":""}],"last_name":"Халаджи","full_name_suggest":{"output":"Халаджи Ольга Володимирівна","input":["Халаджи Ольга Володимирівна","Ольга Володимирівна Халаджи","Ольга Халаджи"]}},"source":"VULYK","estate":{"25":[{"space_unclear":false,"costs":"","costs_comment":"","address_hidden":true,"region_hidden":true,"space_comment":"","space_hidden":true,"space":"","address":"","region":"","address_unclear":false,"costs_rent_comment":"","space_units":"м²","costs_rent":""}]},"intro":{"declaration_year":"2014","declaration_year_unclear":false}}