{"income":{"5":{"value":"324719.29","family_comment":"","value_unclear":false,"family":"59132.52","family_unclear":false,"comment_unclear":false,"comment":"","family_comment_unclear":false},"6":{"value":"264838.84","family_comment":"","value_unclear":false,"family_unclear":false,"family":"39000","comment":""},"7":{"source_name_unclear":false,"value":"","value_unclear":false,"family_comment":"","source_name":"","family":"","comment":"","source_name_hidden":false},"8":{"family_comment":"","value":"","family":"","comment":""},"9":{"family_comment":"","value":"","family":"","comment":""},"10":{"family_comment":"","value":"","value_unclear":false,"family":"","comment":""},"11":{"value":"","value_unclear":false,"value_hidden":false,"family_comment":"","family":"","comment":""},"12":{"family_comment":"","value":"","family":"","comment":"","value_hidden":false},"13":{"family_comment":"","value":"","family":"","comment":""},"14":{"family_comment":"","value":"","family":"","comment":""},"15":{"family_comment":"","value":"59880.45","family":"20132.52","comment":""},"16":{"family_comment":"","value":"","family":"","comment":""},"17":{"family_comment":"","value":"","family":"","comment":""},"18":{"family_comment":"","value":"","family":"","comment":""},"19":{"family_comment":"","family_unclear":false,"value":"","family":"","comment":""},"20":{"family_comment":"","family_unclear":false,"value":"","family":"","comment":""}},"vehicle":{"35":[{"year_hidden":false,"brand_info":"1800 куб. см.","sum_rent_comment":"","year":"2008","sum_hidden":false,"brand_info_hidden":false,"brand_info_unclear":false,"year_unclear":false,"sum_rent":"","sum":"","brand":"Volkswagen Passat","sum_comment":"","brand_unclear":false,"brand_hidden":false}]},"id":"vulyk_61_14","declaration":{"additional_info_text":"","notfull_lostpages":"","date":"2015-03-27T00:00:00","notfull":"","additional_info":"","url":"http://static.declarations.com.ua/declarations/chosen_ones/mega_batch/bobuiok_anatolii_dmytrovych.pdf"},"liabilities":{"54":{"sum_foreign_comment":"","sum":"","sum_comment":"","sum_comment_unclear":false,"sum_unclear":false,"sum_foreign":""},"55":{"sum_foreign_comment":"","sum":"","sum_comment":"","sum_foreign":""},"56":{"sum_foreign_comment":"","sum":"","sum_comment":"","sum_unclear":false,"sum_foreign":""},"57":{"sum_foreign_comment":"","sum":"","sum_comment":"","sum_comment_hidden":false,"sum_unclear":false,"sum_foreign":""},"58":{"sum_foreign_comment":"","sum":"","sum_comment":"","sum_unclear":false,"sum_foreign":""},"59":{"sum_foreign_comment":"","sum":"","sum_comment":"","sum_foreign":""},"60":{"sum_foreign_comment":"","sum_foreign_hidden":false,"sum_comment":"","sum_hidden":false,"sum":"","sum_foreign":""},"61":{"sum_foreign_comment":"","sum":"","sum_comment":"","sum_foreign":""},"62":{"sum_foreign_comment":"","sum":"","sum_comment":"","sum_unclear":false,"sum_foreign":""},"63":{"sum_foreign_comment":"","sum":"","sum_comment":"","sum_hidden":false,"sum_unclear":false,"sum_foreign":""},"64":{"sum_foreign_comment":"","sum":"","sum_hidden":false,"sum_comment":"","sum_foreign":""}},"ft_src":"голова біляївського районного суду одеської області\nОдеська область\nЗагальний місцевий суд\nАнатолій\nПодружжя\nДмитрович\nБобуйок\nБобуйок Анатолій Дмитрович\nБобуйок Анатолій Дмитрович\nАнатолій Дмитрович Бобуйок\nАнатолій Бобуйок\nБобуйок Анатолій Дмитрович\n1800 куб. см.\nVolkswagen Passat\n2008\n47.7\n1200\n215.2\n500\n1600\n55.5\n2014\n39000\n264838.84\n20132.52\n59880.45\n59132.52\n324719.29\n1800 куб. см.\nVolkswagen Passat\n2008\n500\n1600\n1200\n215.2\n47.7\n55.5\nПодружжя\nБобуйок Анатолій Дмитрович\nАнатолій Дмитрович Бобуйок\nАнатолій Бобуйок\nБобуйок Анатолій Дмитрович\nАнатолій\nБобуйок Анатолій Дмитрович\nБобуйок\nОдеська область\nЗагальний місцевий суд\nголова біляївського районного суду одеської області\nДмитрович\n39000\n264838.84\n59880.45\n20132.52\n324719.29\n59132.52\n2014\nПодружжя\nДмитрович\nБобуйок\nБобуйок Анатолій Дмитрович\nАнатолій Дмитрович Бобуйок\nАнатолій Бобуйок\nБобуйок Анатолій Дмитрович\nОдеська область\nголова біляївського районного суду одеської області\nЗагальний місцевий суд\nБобуйок Анатолій Дмитрович\nАнатолій\nVolkswagen Passat\n1800 куб. см.\n2008\n20132.52\n59880.45\n324719.29\n59132.52\n264838.84\n39000\n47.7\n500\n1600\n215.2\n55.5\n1200\n2014","general":{"inn":"","name":"Анатолій","patronymic_unclear":false,"family":[{"inn":"","inn_hidden":true,"relations_unclear":false,"relations_hidden":false,"relations_other":"","relations":"Подружжя","name_hidden":true,"family_name":"","name_unclear":false}],"patronymic":"Дмитрович","inn_hidden":true,"family_raw":"","inn_unclear":false,"post":{"post_unclear":false,"region_unclear":false,"post":"голова біляївського районного суду одеської області","office":"Загальний місцевий суд","region":"Одеська область","post_hidden":false,"office_hidden":false,"region_hidden":false},"last_name_unclear":false,"full_name":"Бобуйок Анатолій Дмитрович","addresses":[{"place_address":"","place_district_hidden":true,"place_city_type":"","place_city_hidden":true,"place_address_unclear":false,"place_city_type_hidden":true,"place_hidden":true,"place":"","place_district":"","place_address_hidden":true,"place_city":"","place_district_unclear":true}],"last_name":"Бобуйок","patronymic_hidden":false,"full_name_suggest":{"output":"Бобуйок Анатолій Дмитрович","input":["Бобуйок Анатолій Дмитрович","Анатолій Дмитрович Бобуйок","Анатолій Бобуйок"]},"name_unclear":false},"source":"VULYK","estate":{"23":[{"region_unclear":false,"space_unclear":false,"costs":"","costs_comment":"","address_hidden":false,"region_hidden":true,"space_comment":"","space":"500","address":"","region":"","address_unclear":false,"costs_rent_comment":"","space_comment_unclear":false,"space_units":"м²","space_units_unclear":false,"costs_rent":""},{"costs_rent":"","region":"","costs":"","costs_rent_comment":"","costs_comment":"","address_hidden":false,"region_hidden":false,"space_comment":"","space_units":"м²","space":"1600","address":""}],"25":[{"region_unclear":false,"space_hidden":false,"costs":"","costs_comment":"","address_hidden":false,"region_hidden":true,"space_comment":"","space_unclear":false,"space":"55.5","address":"","costs_comment_unclear":false,"costs_unclear":false,"region":"","address_unclear":false,"costs_rent_comment":"","space_comment_unclear":false,"space_units":"м²","costs_rent":""}],"26":[{"space_hidden":false,"costs":"","costs_comment":"","address_hidden":false,"region_hidden":true,"space_comment":"","space":"215.2","address":"","region":"","costs_rent_comment":"","space_units":"м²","costs_rent":""}],"29":[{"space_hidden":false,"costs_property":"","address_hidden":false,"region_hidden":true,"space_comment":"","space_units_hidden":false,"space_unclear":false,"space_units_unclear":false,"address":"","region":"","address_unclear":false,"space":"1200","space_comment_hidden":false,"space_units":"м²","costs_property_comment":"","costs_rent":"","costs_rent_comment":""}],"31":[{"space_unclear":false,"address_hidden":false,"region_hidden":true,"space_comment":"","space_hidden":false,"space":"47.7","address":"","region":"","costs_property":"","costs_rent_comment":"","space_comment_unclear":false,"space_units":"м²","costs_property_comment":"","costs_rent":""}]},"intro":{"declaration_year":"2014","isnotdeclaration":"","declaration_year_hidden":false}}