{"id":"vulyk_101_22","ft_src":"Volkswagen Touareg\n2967, 240 к. с\n2012\n600\n528\n2015\n264278\nНаціональна школа суддів України\n4087\n268365\nVolkswagen Touareg\n2967, 240 к. с\n2012\n2015\nДжулай Олександр Борисович\nОлександр Борисович Джулай\nОлександр Джулай\nДжулай Олександр Борисович\nОлександр\nДжулай Олександр Борисович\nДжулай\nЗагальний апеляційний суд\nсуддя апеляційного суду одеської області, секретар судової палати з розгляду кримінальних справ апеляційного суду одеської області\nОдеська область\nБорисович\n4087\nНаціональна школа суддів України\n264278\n268365\n600\n528\nБорисович\nДжулай\nОлександр\nДжулай Олександр Борисович\nОлександр Борисович Джулай\nОлександр Джулай\nДжулай Олександр Борисович\nсуддя апеляційного суду одеської області, секретар судової палати з розгляду кримінальних справ апеляційного суду одеської області\nЗагальний апеляційний суд\nОдеська область\nДжулай Олександр Борисович","estate":{"23":[{"address":"","space_units":"м²","space_hidden":false,"space_unclear":false,"region_hidden":true,"costs_comment":"","space_comment":"","address_hidden":false,"space_units_unclear":false,"space":"600","costs_comment_unclear":false,"costs_rent_comment":"","costs":"","region":"","costs_rent":""}],"24":[{"address":"","space_units":"м²","costs_comment":"","space_unclear":false,"region_hidden":true,"space_comment":"","address_hidden":false,"costs":"","costs_rent_comment":"","space":"528","region":"","costs_rent":""}]},"vehicle":{"35":[{"sum_comment":"","brand_info_hidden":false,"sum_rent":"","sum":"","brand_unclear":false,"year":"2012","brand":"Volkswagen Touareg","brand_info":"2967, 240 к. с","sum_rent_comment":"","brand_info_unclear":false,"sum_rent_unclear":false}]},"source":"VULYK","income":{"5":{"family_comment":"","value":"268365","family":"","comment":"","value_unclear":false},"6":{"family_comment":"","family":"","comment":"","value_unclear":false,"family_hidden":false,"value":"264278"},"7":{"family_comment":"","comment":"","family":"","source_name_unclear":false,"value":"4087","source_name":"Національна школа суддів України"},"8":{"family_comment":"","value":"","family":"","comment":""},"9":{"family_comment":"","value":"","family":"","comment":""},"10":{"family_comment":"","value":"","family":"","comment":""},"11":{"family_comment":"","comment_unclear":false,"value":"","family":"","comment":""},"12":{"family_comment":"","value":"","family":"","comment":""},"13":{"family_comment":"","value":"","family":"","comment":""},"14":{"family_comment":"","value":"","family":"","comment":""},"15":{"family_comment":"","value":"","family":"","comment":""},"16":{"family_comment":"","value":"","family":"","comment":""},"17":{"family_comment":"","value":"","family":"","comment":""},"18":{"family_comment":"","value":"","family":"","comment":""},"19":{"family_comment":"","value":"","family":"","comment":""},"20":{"family_comment":"","family":"","comment":"","value_unclear":false,"family_unclear":false,"comment_unclear":false,"value":""}},"general":{"family_raw":"","name":"Олександр","full_name_suggest":{"input":["Джулай Олександр Борисович","Олександр Борисович Джулай","Олександр Джулай"],"output":"Джулай Олександр Борисович"},"patronymic":"Борисович","inn_hidden":true,"addresses":[{"place_city_type_hidden":false,"place_city_type":"","place_city_hidden":true,"place_hidden":true,"place_district":"","place_district_hidden":false,"place":"","place_address":"","place_address_hidden":true,"place_city":""}],"patronymic_hidden":false,"inn":"","inn_unclear":false,"last_name":"Джулай","full_name":"Джулай Олександр Борисович","post":{"office":"Загальний апеляційний суд","region_unclear":false,"post":"суддя апеляційного суду одеської області, секретар судової палати з розгляду кримінальних справ апеляційного суду одеської області","region":"Одеська область","office_unclear":false}},"liabilities":{"54":{"sum_comment_unclear":false,"sum_comment":"","sum_hidden":false,"sum":"","sum_foreign_comment":"","sum_foreign":"","sum_unclear":false,"sum_comment_hidden":false},"55":{"sum_comment":"","sum_foreign_comment":"","sum_foreign":"","sum":""},"56":{"sum_comment":"","sum":"","sum_foreign_comment":"","sum_foreign":"","sum_unclear":false,"sum_comment_hidden":false},"57":{"sum_comment":"","sum_hidden":false,"sum":"","sum_foreign_comment":"","sum_foreign":"","sum_unclear":false,"sum_comment_hidden":false},"58":{"sum_comment_unclear":false,"sum_comment":"","sum_hidden":false,"sum":"","sum_foreign_comment":"","sum_foreign":"","sum_unclear":false,"sum_comment_hidden":false},"59":{"sum_comment":"","sum_foreign_comment":"","sum_foreign":"","sum":""},"60":{"sum_comment":"","sum_hidden":false,"sum":"","sum_foreign_comment":"","sum_foreign":"","sum_unclear":false,"sum_comment_hidden":false},"61":{"sum_comment":"","sum_foreign_comment":"","sum_foreign":"","sum":""},"62":{"sum_comment":"","sum_comment_unclear":false,"sum_foreign_comment":"","sum":"","sum_foreign":""},"63":{"sum_comment":"","sum_foreign_comment":"","sum_foreign":"","sum":"","sum_comment_hidden":false},"64":{"sum_comment":"","sum_foreign_comment":"","sum_foreign":"","sum":"","sum_comment_hidden":false}},"declaration":{"notfull_lostpages":"","additional_info_text":"","additional_info":"","date":"2016-03-31T00:00:00","notfull":"","url":"http://static.declarations.com.ua/declarations/chosen_ones/judges_batch/686_dzhulai_oleksandr_borysovych_2015.pdf"},"intro":{"declaration_year":"2015"}}