{"income":{"5":{"family_comment":"","family_unclear":false,"value":"169415","family":"63717","comment":""},"6":{"value":"169415","family_comment":"","value_unclear":false,"family_unclear":true,"family":"56496","comment":""},"7":{"source_name_unclear":false,"value":"","family_comment":"","source_name":"","family":"","comment":"","source_name_hidden":false},"8":{"family_comment":"","value":"","family":"","comment":""},"9":{"family_comment":"","family_unclear":false,"value":"","family":"233","comment":""},"10":{"family_comment":"","value":"","family":"","comment":""},"11":{"family_comment":"","value":"","family":"","comment":""},"12":{"family_comment":"","value":"","family":"","comment":""},"13":{"family_comment":"","value":"","family":"","comment":""},"14":{"family_comment":"","value":"","family":"","comment":""},"15":{"family_comment":"","value":"","family":"6988","comment":""},"16":{"family_comment":"","family_unclear":false,"value":"","family":"","comment":""},"17":{"family_comment":"","family_unclear":false,"value":"","family":"","comment":""},"18":{"family_comment":"","value":"","family":"","comment":""},"19":{"family_comment":"","value":"","family":"","comment":""},"20":{"family_comment":"","value":"","comment_unclear":false,"family":"","comment":""}},"vehicle":{"35":[{"brand_info":"1999 куб. см.","sum":"","brand":"Mazda 6","sum_comment":"","brand_unclear":false,"year":"2011","brand_hidden":false,"brand_info_hidden":false,"brand_info_unclear":false,"sum_rent_comment":"","sum_rent":""},{"brand_info":"1386 куб. см.","sum":"","brand":"Nissan Note","sum_comment":"","brand_unclear":true,"year":"2007","sum_rent_comment":"","sum_rent":""}],"40":[{"brand_info":"1386 куб. см.","sum":"","brand":"Nissan Note","sum_comment":"","brand_unclear":false,"year":"2007","brand_hidden":false,"brand_info_hidden":false,"brand_info_unclear":false,"sum_rent_comment":"","sum_rent":""},{"brand_info":"1999 куб. см.","sum":"","brand":"Mazda 6","sum_comment":"","year":"2011","sum_rent_comment":"","sum_rent":""}]},"id":"vulyk_95_24","banks":{"45":[{"sum_units":"UAH","sum_foreign_comment_hidden":false,"sum_hidden":true,"sum_foreign_units_hidden":false,"sum":"15340","sum_units_hidden":false,"sum_foreign_comment":"","sum_foreign_hidden":false,"sum_comment":"","sum_comment_unclear":false,"sum_foreign_units":"UAH","sum_foreign":"","sum_comment_hidden":false}],"51":[{"sum_units":"UAH","sum_foreign_comment_hidden":false,"sum_hidden":true,"sum_foreign_units_hidden":false,"sum":"16337","sum_foreign":"","sum_foreign_comment":"","sum_foreign_hidden":false,"sum_comment":"","sum_foreign_units":"UAH","sum_comment_hidden":false,"sum_unclear":false}]},"declaration":{"additional_info_text":"","notfull_lostpages":"","date":"2016-02-04T00:00:00","notfull":"","additional_info":"","url":"http://static.declarations.com.ua/declarations/chosen_ones/judges_batch/25_chudnykh_svitlana_oleksandrivna.pdf"},"liabilities":{"54":{"sum_foreign_comment":"","sum":"","sum_comment":"","sum_hidden":false,"sum_comment_hidden":false,"sum_unclear":false,"sum_foreign":""},"55":{"sum_foreign_comment":"","sum":"","sum_comment":"","sum_foreign":""},"56":{"sum_foreign_comment":"","sum":"","sum_comment":"","sum_foreign":""},"57":{"sum_foreign_comment":"","sum":"","sum_comment":"","sum_hidden":false,"sum_comment_hidden":false,"sum_unclear":false,"sum_foreign":""},"58":{"sum_foreign_comment":"","sum":"","sum_comment":"","sum_hidden":false,"sum_comment_hidden":false,"sum_unclear":false,"sum_foreign":""},"59":{"sum_foreign_comment":"","sum":"","sum_comment":"","sum_foreign":""},"60":{"sum_foreign_comment":"","sum":"","sum_comment":"","sum_hidden":false,"sum_comment_hidden":false,"sum_foreign":""},"61":{"sum_foreign_comment":"","sum":"","sum_comment":"","sum_foreign":""},"62":{"sum_foreign_comment":"","sum":"","sum_comment":"","sum_unclear":false,"sum_foreign":""},"63":{"sum_foreign_comment":"","sum":"","sum_comment":"","sum_unclear":false,"sum_foreign":""},"64":{"sum_foreign_comment":"","sum":"","sum_comment":"","sum_foreign":""}},"ft_src":"Mazda 6\n1999 куб. см.\n2011\n2007\n1386 куб. см.\nNissan Note\nNissan Note\n1386 куб. см.\n2007\n1999 куб. см.\n2011\nMazda 6\nм. Харків\n750\nХарківська область\nХарківська область\nм. Харків\n126.55\nм. Харків\n65.2\nХарківська область\nХарківська область\nм. Харків\n16.3\n16337\n15340\n2015\nMazda 6\n1999 куб. см.\n2011\n1386 куб. см.\nNissan Note\n2007\nNissan Note\n1386 куб. см.\n2007\n1999 куб. см.\n2011\nMazda 6\n2015\nОлександрівна\nПодружжя\nЧудних Є. А\nЧудних Світлана Олександрівна\nСвітлана Олександрівна Чудних\nСвітлана Чудних\nЧудних Світлана Олександрівна\nСвітлана\nХарків\n61107\nХарківська область\nЧудних Світлана Олександрівна\nЧудних\nАдміністративний місцевий суд\nсуддя харківського окружного адміністративного суду\nХарківська область\n169415\n56496\n6988\n169415\n63717\n233\n750\nм. Харків\nХарківська область\n126.55\nм. Харків\nХарківська область\n65.2\nм. Харків\nХарківська область\n16.3\nм. Харків\nХарківська область\n15340\n16337\n56496\n169415\n6988\n233\n63717\n169415\nЧудних Є. А\nПодружжя\nХарківська область\nХарків\n61107\nОлександрівна\nЧудних\nХарківська область\nАдміністративний місцевий суд\nсуддя харківського окружного адміністративного суду\nЧудних Світлана Олександрівна\nЧудних Світлана Олександрівна\nСвітлана Олександрівна Чудних\nСвітлана Чудних\nЧудних Світлана Олександрівна\nСвітлана","general":{"inn":"","inn_hidden":true,"last_name":"Чудних","post":{"post":"суддя харківського окружного адміністративного суду","region":"Харківська область","candidate":"","office_hidden":false,"office":"Адміністративний місцевий суд","office_unclear":false},"name":"Світлана","full_name":"Чудних Світлана Олександрівна","family_raw":"","addresses":[{"place_address":"61107","place_district_hidden":false,"place_city_type":"Місто","place_city_hidden":false,"place_address_unclear":false,"place_city_type_hidden":false,"place_city":"Харків","place":"Харківська область","place_district":"","place_address_hidden":true,"place_hidden":false,"place_city_unclear":false}],"family":[{"inn":"","inn_hidden":true,"inn_unclear":false,"relations_hidden":false,"relations_other":"","relations":"Подружжя","name_hidden":true,"family_name":"Чудних Є. А","name_unclear":false}],"full_name_suggest":{"output":"Чудних Світлана Олександрівна","input":["Чудних Світлана Олександрівна","Світлана Олександрівна Чудних","Світлана Чудних"]},"patronymic":"Олександрівна"},"source":"VULYK","estate":{"23":[{"region_unclear":false,"space_unclear":false,"costs_comment_hidden":false,"costs_comment":"","address_hidden":true,"region_hidden":false,"space_comment":"","space":"750","address":"м. Харків","region":"Харківська область","address_unclear":false,"costs_rent_comment":"","costs":"","space_units":"м²","costs_rent":""}],"24":[{"costs":"","costs_comment":"","address_hidden":true,"region_hidden":false,"space_comment":"","space":"126.55","address":"м. Харків","region":"Харківська область","address_unclear":false,"costs_rent_comment":"","space_units":"м²","costs_rent":""}],"25":[{"space_unclear":false,"costs":"","costs_comment":"","address_hidden":true,"region_hidden":false,"space_comment":"","space_hidden":false,"space":"65.2","address":"м. Харків","region":"Харківська область","address_unclear":false,"costs_rent_comment":"","space_comment_unclear":false,"space_units":"м²","costs_rent":""},{"space_hidden":false,"costs":"","costs_comment":"","address_hidden":false,"region_hidden":false,"space_comment":"","space":"16.3","address":"м. Харків","region":"Харківська область","address_unclear":false,"costs_rent_comment":"","space_units":"м²","costs_rent":""}]},"intro":{"declaration_year":"2015","isnotdeclaration":""}}