{"income":{"5":{"value":"267350","value_unclear":false,"family_hidden":false,"value_hidden":false,"family_comment":"","family":"35135","comment":""},"6":{"value":"217276","value_unclear":false,"family_hidden":false,"family_comment":"","family":"35135","comment":""},"7":{"value":"","comment_hidden":false,"family_comment":"","source_name":"Косівський районний суд, Косівське відділення Пенсійоного Фонду в Косівському районі, Косівський інститут прикладного та декоративного мистецтва Львівської національної академії мистецтв","family":"","comment":"","source_name_hidden":false},"8":{"family_comment":"","value":"","family":"","comment":""},"9":{"family_comment":"","value":"","family":"","comment":""},"10":{"family_comment":"","family_unclear":false,"value":"","family":"","comment":""},"11":{"family_comment":"","value":"","family":"","comment":""},"12":{"family_comment":"","value":"","family":"","comment":""},"13":{"family_comment":"","value":"","family":"","comment":""},"14":{"family_comment":"","value":"","family":"","comment":""},"15":{"family_comment":"","value":"","family":"","comment":""},"16":{"family_comment":"","value":"","family":"","comment":""},"17":{"family_comment":"","value":"","family":"","comment":""},"18":{"family_comment":"","value":"","family":"","comment":""},"19":{"family_comment":"","value":"","family":"","comment":""},"20":{"value":"50074","family_comment":"","family_hidden":false,"family_unclear":false,"family":"","comment":"","family_comment_unclear":false}},"id":"vulyk_45_69","banks":{"45":[{"sum_foreign_comment":"","sum_units":"UAH","sum_comment":"","sum_comment_unclear":false,"sum_foreign_units":"UAH","sum_comment_hidden":false,"sum_unclear":false,"sum":"","sum_foreign":""},{"sum_foreign_comment":"","sum_units":"","sum_comment":"","sum_foreign_units":"","sum":"","sum_foreign":""}],"46":[{"sum_foreign_comment":"","sum_units":"UAH","sum_comment":"","sum_comment_unclear":false,"sum_foreign_units":"UAH","sum":"","sum_unclear":false,"sum_foreign":""}],"47":[{"sum_foreign_comment":"","sum_units":"UAH","sum_comment":"","sum_foreign_units":"UAH","sum":"","sum_foreign":""}],"48":[{"sum_foreign_comment":"","sum_units":"UAH","sum_comment":"","sum_foreign_units":"UAH","sum":"","sum_foreign":""}],"49":[{"sum_foreign_comment":"","sum_units":"UAH","sum_comment":"","sum_foreign_units":"UAH","sum":"","sum_foreign":""}],"50":[{"sum_foreign_comment":"","sum_units":"UAH","sum_comment":"","sum_foreign_units":"UAH","sum":"","sum_foreign":""}],"51":[{"sum_foreign_comment":"","sum_units":"UAH","sum_comment":"","sum_foreign_units":"UAH","sum_comment_hidden":false,"sum":"","sum_foreign":""},{"sum_foreign_comment":"","sum_units":"","sum_comment":"","sum_foreign_units":"","sum":"","sum_foreign":""}],"52":[{"sum_foreign_comment":"","sum_units":"UAH","sum_comment":"","sum_comment_unclear":false,"sum_foreign_units":"UAH","sum":"","sum_unclear":false,"sum_foreign":""}],"53":[{"sum_foreign_comment":"","sum_units":"UAH","sum_comment":"","sum_foreign_comment_hidden":false,"sum_hidden":false,"sum_foreign_units":"UAH","sum_comment_hidden":false,"sum_foreign_hidden":false,"sum":"","sum_foreign":""}]},"declaration":{"additional_info_text":"","notfull_lostpages":"","date":"2015-03-30T00:00:00","notfull":"","additional_info":"","url":"http://static.declarations.com.ua/declarations/chosen_ones/mega_batch/turianskyi_ihor_ievhenovych.pdf"},"liabilities":{"54":{"sum_foreign_comment":"","sum":"","sum_comment":"","sum_comment_unclear":false,"sum_comment_hidden":false,"sum_unclear":false,"sum_foreign":""},"55":{"sum_foreign_comment":"","sum":"","sum_comment":"","sum_foreign":""},"56":{"sum_foreign_comment":"","sum":"2065","sum_comment":"","sum_comment_unclear":false,"sum_unclear":false,"sum_foreign":""},"57":{"sum_foreign_comment":"","sum":"42215","sum_comment":"","sum_comment_unclear":false,"sum_hidden":false,"sum_comment_hidden":false,"sum_foreign":""},"58":{"sum_foreign_comment":"","sum":"460","sum_comment":"","sum_comment_unclear":false,"sum_hidden":false,"sum_comment_hidden":false,"sum_foreign":""},"59":{"sum_foreign_comment":"","sum":"","sum_comment":"","sum_foreign":""},"60":{"sum_foreign_comment":"","sum":"","sum_comment":"","sum_comment_unclear":false,"sum_comment_hidden":false,"sum_foreign":""},"61":{"sum_foreign_comment":"","sum":"","sum_comment":"","sum_foreign":""},"62":{"sum_foreign_comment":"","sum":"","sum_comment":"","sum_foreign":""},"63":{"sum_foreign_comment":"","sum":"","sum_comment":"","sum_comment_unclear":false,"sum_comment_hidden":false,"sum_unclear":false,"sum_foreign":""},"64":{"sum_foreign_comment":"","sum":"","sum_comment":"","sum_comment_unclear":false,"sum_comment_hidden":false,"sum_unclear":false,"sum_foreign":""}},"ft_src":"42215\n460\n2065\nсуддя косівського районного суду івано-франківської області\nІвано-Франківська область\nЗагальний місцевий суд\nІгор\nТурянська Ж. Д\nПодружжя\nТурянська Т. І\nДитина\nТурянська В. І\nДитина\nЄвгенійович\nТурянський Ігор Євгенійович\nІгор Євгенійович Турянський\nІгор Турянський\nТурянський Ігор Євгенійович\nТурянський Ігор Євгенійович\nТурянський\n50074\n267350\n35135\nКосівський районний суд, Косівське відділення Пенсійоного Фонду в Косівському районі, Косівський інститут прикладного та декоративного мистецтва Львівської національної академії мистецтв\n217276\n35135\n600\n48.1\n48.1\n2014\n35135\n217276\nКосівський районний суд, Косівське відділення Пенсійоного Фонду в Косівському районі, Косівський інститут прикладного та декоративного мистецтва Львівської національної академії мистецтв\n35135\n267350\n50074\n2014\nПодружжя\nТурянська Ж. Д\nДитина\nТурянська Т. І\nДитина\nТурянська В. І\nТурянський Ігор Євгенійович\nІгор Євгенійович Турянський\nІгор Турянський\nТурянський Ігор Євгенійович\nТурянський Ігор Євгенійович\nІгор\nТурянський\nЗагальний місцевий суд\nсуддя косівського районного суду івано-франківської області\nІвано-Франківська область\nЄвгенійович\n42215\n2065\n460\nКосівський районний суд, Косівське відділення Пенсійоного Фонду в Косівському районі, Косівський інститут прикладного та декоративного мистецтва Львівської національної академії мистецтв\n217276\n35135\n50074\n267350\n35135\n600\n48.1\n48.1\n460\n42215\n2065\nТурянська Ж. Д\nПодружжя\nТурянська Т. І\nДитина\nТурянська В. І\nДитина\nЄвгенійович\nТурянський\nІгор\nТурянський Ігор Євгенійович\nІгор Євгенійович Турянський\nІгор Турянський\nТурянський Ігор Євгенійович\nІвано-Франківська область\nсуддя косівського районного суду івано-франківської області\nЗагальний місцевий суд\nТурянський Ігор Євгенійович\n48.1\n600\n48.1\n2014","general":{"inn":"","name":"Ігор","last_name_hidden":false,"family":[{"inn":"","inn_hidden":true,"relations_unclear":false,"relations_hidden":false,"relations_other":"","relations":"Подружжя","name_hidden":false,"family_name":"Турянська Ж. Д","name_unclear":false},{"inn":"","relations":"Дитина","relations_other":"","inn_hidden":false,"family_name":"Турянська Т. І","name_hidden":false,"name_unclear":false},{"inn":"","relations":"Дитина","relations_other":"","inn_hidden":false,"family_name":"Турянська В. І","name_unclear":false}],"patronymic":"Євгенійович","inn_hidden":true,"family_raw":"","inn_unclear":false,"post":{"post_unclear":false,"post":"суддя косівського районного суду івано-франківської області","post_hidden":false,"region":"Івано-Франківська область","region_hidden":false,"office":"Загальний місцевий суд","office_hidden":false,"office_unclear":false},"full_name":"Турянський Ігор Євгенійович","addresses":[{"place_district":"","place_city_hidden":true,"place_city":"","place_city_type_hidden":true,"place_district_hidden":true,"place_city_type":"","place_address_hidden":true,"place_address":"","place_hidden":true,"place":""}],"last_name":"Турянський","full_name_suggest":{"output":"Турянський Ігор Євгенійович","input":["Турянський Ігор Євгенійович","Ігор Євгенійович Турянський","Ігор Турянський"]}},"source":"VULYK","estate":{"23":[{"space_unclear":false,"costs":"","costs_comment":"","costs_hidden":false,"address_hidden":false,"region_hidden":true,"space_comment":"","space":"600","address":"","region":"","space_units_unclear":false,"space_units":"м²","costs_rent":"","costs_rent_comment":""},{"costs":"","costs_comment":"","costs_hidden":false,"address_hidden":false,"region_hidden":false,"space_comment":"","space":"","address":"","region":"","costs_rent_comment":"","space_units":"","costs_rent":""},{"costs_rent":"","space_unclear":false,"region":"","costs":"","costs_rent_comment":"","costs_comment":"","address_hidden":false,"space_comment":"","space_units":"","space":"","address":""},{"costs_rent":"","region":"","costs":"","costs_rent_comment":"","costs_comment":"","space_comment":"","space_units":"","space":"","address":""},{"costs_rent":"","region":"","costs":"","costs_rent_comment":"","costs_comment":"","space_comment":"","space_units":"","space":"","address":""},{"costs_rent":"","region":"","costs":"","costs_rent_comment":"","costs_comment":"","space_comment":"","space_units":"","space":"","address":""}],"25":[{"space_unclear":false,"costs":"","costs_comment":"","address_hidden":false,"region_hidden":true,"space_comment":"","space_hidden":false,"space":"48.1","address":"","region":"","address_unclear":false,"costs_rent_comment":"","costs_rent_hidden":false,"space_comment_hidden":false,"space_units":"м²","space_units_hidden":false,"costs_rent":""}],"31":[{"space_unclear":false,"address_hidden":true,"region_hidden":true,"space_comment":"","space_hidden":false,"space":"48.1","address":"","region":"","costs_property":"","costs_rent_comment":"","space_units":"м²","costs_property_comment":"","costs_rent":""}]},"intro":{"declaration_year":"2014","isnotdeclaration":""}}