{"income":{"5":{"value":"181307.61","family_comment":"","value_unclear":false,"family_hidden":false,"value_hidden":false,"family_unclear":false,"family":"","comment":""},"6":{"value":"181307.61","value_unclear":false,"family_hidden":false,"value_hidden":false,"family_comment":"","comment_unclear":false,"comment":"","family":""},"7":{"value":"","value_hidden":false,"family_comment":"","source_name":"","family":"","comment":"","source_name_hidden":false},"8":{"family_comment":"","value":"","family":"","comment":""},"9":{"family_comment":"","value":"","comment_unclear":false,"family":"","comment":""},"10":{"family_comment":"","value":"","value_unclear":false,"family":"","comment":""},"11":{"family_comment":"","value":"","family":"","comment":""},"12":{"family_comment":"","value":"","family":"","comment":""},"13":{"family_comment":"","value":"","family":"","comment":""},"14":{"family_comment":"","value":"","family":"","comment":""},"15":{"family_comment":"","value":"","family":"","comment":""},"16":{"family_comment":"","value":"","family":"","comment":""},"17":{"family_comment":"","value":"","family":"","comment":""},"18":{"family_comment":"","value":"","family":"","comment":""},"19":{"value":"","value_unclear":false,"comment_hidden":false,"family_hidden":false,"value_hidden":false,"family_comment":"","family_comment_hidden":false,"comment":"","family":""},"20":{"value":"","family_comment":"","value_unclear":false,"family_hidden":false,"value_hidden":false,"family_unclear":false,"comment_unclear":false,"comment":"","family":""}},"vehicle":{"35":[{"brand_info":"3456 куб. см.","sum_rent_comment":"","year":"2010","brand_info_hidden":false,"brand_info_unclear":false,"year_unclear":false,"sum_rent":"","sum":"204000","brand":"Lexus RX 350","sum_comment":"","brand_unclear":false,"brand_hidden":false}]},"id":"vulyk_65_53","declaration":{"additional_info_text":"","notfull_lostpages":"","date":"2015-03-23T00:00:00","notfull":"","additional_info":"","url":"http://static.declarations.com.ua/declarations/chosen_ones/mega_batch/feduleieva_iuliia_oleksandrivna.pdf"},"liabilities":{"54":{"sum_foreign_comment":"","sum":"","sum_comment":"","sum_comment_unclear":false,"sum_hidden":false,"sum_comment_hidden":false,"sum_foreign":""},"55":{"sum_foreign_comment":"","sum":"","sum_comment":"","sum_foreign":""},"56":{"sum_foreign_comment":"","sum":"","sum_comment":"","sum_unclear":false,"sum_foreign":""},"57":{"sum_foreign_comment":"","sum":"","sum_comment":"","sum_comment_unclear":false,"sum_unclear":false,"sum_foreign":""},"58":{"sum_foreign_comment":"","sum":"5552.45","sum_comment":"","sum_comment_unclear":false,"sum_unclear":false,"sum_foreign":""},"59":{"sum_foreign_comment":"","sum":"2285.95","sum_comment":"","sum_foreign":""},"60":{"sum_foreign_comment":"","sum":"","sum_comment":"","sum_comment_unclear":false,"sum_foreign":""},"61":{"sum_foreign_comment":"","sum":"","sum_comment":"","sum_foreign":""},"62":{"sum_foreign_comment":"","sum":"","sum_comment":"","sum_foreign":""},"63":{"sum_foreign_comment":"","sum":"","sum_comment":"","sum_foreign":""},"64":{"sum_foreign_comment":"","sum":"","sum_comment":"","sum_unclear":false,"sum_foreign":""}},"ft_src":"2285.95\n5552.45\nОдеса\n65020\nОдеська область\nсуддя київського районого суду міста одеси\nОдеська область\nЗагальний місцевий суд\nЮлія\nДитина\nОлександрівна\nФедулеєва\nФедулеєва Юлія Олександрівна\nФедулеєва Юлія Олександрівна\nЮлія Олександрівна Федулеєва\nЮлія Федулеєва\nФедулеєва Юлія Олександрівна\n181307.61\n181307.61\n2010\nLexus RX 350\n204000\n3456 куб. см.\n3456 куб. см.\nLexus RX 350\n2010\n204000\n2014\n181307.61\n181307.61\n3456 куб. см.\nLexus RX 350\n2010\n204000\n181307.61\n181307.61\nЗагальний місцевий суд\nОдеська область\nсуддя київського районого суду міста одеси\nФедулеєва Юлія Олександрівна\nЮлія Олександрівна Федулеєва\nЮлія Федулеєва\nФедулеєва Юлія Олександрівна\nЮлія\nДитина\nФедулеєва Юлія Олександрівна\nФедулеєва\nОлександрівна\n65020\nОдеська область\nОдеса\n2285.95\n5552.45\n2014\n5552.45\n2285.95\nДитина\nОлександрівна\nФедулеєва\nЮлія\nФедулеєва Юлія Олександрівна\nЮлія Олександрівна Федулеєва\nЮлія Федулеєва\nФедулеєва Юлія Олександрівна\n65020\nОдеса\nОдеська область\nОдеська область\nЗагальний місцевий суд\nсуддя київського районого суду міста одеси\nФедулеєва Юлія Олександрівна\n2014","general":{"name_hidden":false,"name":"Юлія","last_name_hidden":false,"inn":"","family":[{"inn":"","inn_hidden":false,"inn_unclear":false,"relations_hidden":false,"relations_other":"","relations":"Дитина","name_hidden":true,"family_name":"","name_unclear":false}],"patronymic":"Олександрівна","inn_hidden":true,"family_raw":"","inn_unclear":false,"post":{"post_unclear":false,"region_unclear":false,"post":"суддя київського районого суду міста одеси","office":"Загальний місцевий суд","region":"Одеська область","post_hidden":false,"office_hidden":false,"office_unclear":false,"region_hidden":false},"last_name_unclear":false,"full_name":"Федулеєва Юлія Олександрівна","addresses":[{"place_district":"","place_address_hidden":true,"place_city":"Одеса","place_city_type_hidden":false,"place_district_hidden":true,"place_city_type":"Місто","place_city_hidden":false,"place_address_unclear":false,"place_address":"65020","place_hidden":true,"place":"Одеська область"}],"last_name":"Федулеєва","patronymic_hidden":false,"full_name_suggest":{"output":"Федулеєва Юлія Олександрівна","input":["Федулеєва Юлія Олександрівна","Юлія Олександрівна Федулеєва","Юлія Федулеєва"]},"name_unclear":false},"source":"VULYK","intro":{"declaration_year":"2014","isnotdeclaration":"","declaration_year_hidden":false}}