{"id":"vulyk_100_52","ft_src":"Nissan TIIDA\n2011\n2013\nToyota Corolla\nм. Сєвєродонецьк\n30\nЛуганська область\nЛуганська область\nм. Сєвєродонецьк\n30\n1/2 частина\nЛуганська область\nм. Сєвєродонецьк\n58.6\nм. Сєвєродонецьк\n63.9\nЛуганська область\n2014\n98065\n202327\n100312\n202327\n2247\nNissan TIIDA\n2011\nToyota Corolla\n2013\n30\nЛуганська область\nм. Сєвєродонецьк\nм. Сєвєродонецьк\n30\nЛуганська область\n58.6\n1/2 частина\nЛуганська область\nм. Сєвєродонецьк\n63.9\nЛуганська область\nм. Сєвєродонецьк\nПодружжя\nДитина\nВ'ячеславівна\nЛуганська область\n93400\nСєвєродонецьк\nОдношевна\nОдношевна Валерія В'ячеславівна\nВалерія В'ячеславівна Одношевна\nВалерія Одношевна\nОдношевна Валерія В'ячеславівна\nОдношевна Валерія В'ячеславівна\nВалерія\nЗагальний місцевий суд\nЛуганська область\nсуддя рубіжанський міського суду луганської області\n30696\nПУМБ\n351\n350\n18549\nПУМБ\n202327\n98065\n202327\n100312\n2247\n2014\n351\n350\nПУМБ\n30696\nПУМБ\n18549\nПодружжя\nДитина\n93400\nСєвєродонецьк\nЛуганська область\nВ'ячеславівна\nОдношевна\nЛуганська область\nЗагальний місцевий суд\nсуддя рубіжанський міського суду луганської області\nОдношевна Валерія В'ячеславівна\nОдношевна Валерія В'ячеславівна\nВалерія В'ячеславівна Одношевна\nВалерія Одношевна\nОдношевна Валерія В'ячеславівна\nВалерія","estate":{"23":[{"address":"м. Сєвєродонецьк","space_units":"м²","costs_comment":"","space_unclear":false,"region_hidden":false,"space_comment":"","address_hidden":true,"costs":"","address_unclear":false,"space_comment_unclear":false,"costs_comment_unclear":false,"costs_rent_comment":"","space":"30","region":"Луганська область","costs_rent":""}],"25":[{"address":"м. Сєвєродонецьк","space_units":"м²","costs_comment":"","space_unclear":false,"region_hidden":false,"space_comment":"","address_hidden":true,"costs":"","address_unclear":false,"space_comment_unclear":false,"costs_comment_unclear":false,"costs_rent_comment":"","space":"63.9","region":"Луганська область","costs_rent":""}],"29":[{"costs_property_comment":"","address":"м. Сєвєродонецьк","space_units":"м²","space_unclear":false,"region_hidden":false,"costs_property":"","space_comment":"","address_hidden":true,"address_unclear":false,"costs_rent_comment":"","space":"30","region_unclear":false,"region":"Луганська область","costs_rent":""}],"31":[{"costs_property_comment":"","address":"м. Сєвєродонецьк","space_units":"м²","space_unclear":false,"region_hidden":false,"costs_property":"","space_comment":"1/2 частина","address_hidden":true,"address_unclear":false,"space_comment_unclear":false,"costs_rent_comment":"","space":"58.6","costs_property_comment_unclear":false,"region_unclear":false,"region":"Луганська область","costs_rent":""}]},"vehicle":{"35":[{"brand_info":"","sum_rent_comment":"","brand_unclear":false,"sum_rent_comment_unclear":false,"brand_hidden":false,"sum_comment":"","brand_info_hidden":false,"sum_rent":"","brand":"Nissan TIIDA","brand_info_unclear":false,"year":"2011","sum":""}],"40":[{"sum_comment":"","brand_info_hidden":false,"brand_info":"","sum":"","sum_rent_comment":"","year":"2013","brand":"Toyota Corolla","sum_rent":"","brand_info_unclear":false}]},"source":"VULYK","income":{"5":{"family_comment":"","family":"100312","comment":"","value_unclear":false,"family_unclear":false,"value":"202327"},"6":{"family_comment":"","value":"202327","family":"98065","comment":"","value_unclear":false},"7":{"family_comment":"","comment":"","family":"","value_unclear":false,"value":"","source_name":""},"8":{"family_comment":"","value":"","family":"","comment":""},"9":{"family_comment":"","family":"2247","comment":"","value_unclear":false,"family_unclear":false,"value":""},"10":{"family_comment":"","comment_unclear":false,"value":"","family":"","comment":""},"11":{"family_comment":"","value":"","family":"","comment":""},"12":{"family_comment":"","value":"","family":"","comment":""},"13":{"family_comment":"","value":"","family":"","comment":"","value_unclear":false},"14":{"family_comment":"","value":"","family":"","comment":""},"15":{"family_comment":"","value":"","family":"","comment":""},"16":{"family_comment":"","value":"","family_unclear":false,"family":"","comment":""},"17":{"family_comment":"","value":"","family_unclear":false,"family":"","comment":""},"18":{"family_comment":"","value":"","family":"","comment":""},"19":{"family_comment":"","value":"","family":"","comment":""},"20":{"family":"","family_comment":"","comment":"","value_hidden":false,"value_unclear":false,"value":"","comment_unclear":false,"family_unclear":false,"family_hidden":false}},"general":{"inn":"","addresses":[{"place_city_type":"Місто","place_city_type_hidden":false,"place_hidden":false,"place_city_hidden":false,"place_district_hidden":false,"place_district":"","place_city_unclear":false,"place":"Луганська область","place_city":"Сєвєродонецьк","place_address_hidden":true,"place_address":"93400"}],"last_name":"Одношевна","full_name":"Одношевна Валерія В'ячеславівна","family":[{"inn":"","family_name":"","name_unclear":false,"inn_hidden":true,"name_hidden":true,"relations":"Подружжя"},{"inn":"","family_name":"","relations_other":"","name_unclear":false,"inn_hidden":true,"name_hidden":true,"relations":"Дитина"}],"patronymic":"В'ячеславівна","inn_hidden":true,"name":"Валерія","post":{"post_hidden":false,"office":"Загальний місцевий суд","post":"суддя рубіжанський міського суду луганської області","office_unclear":false,"region_unclear":false,"region":"Луганська область","post_unclear":false},"family_raw":"","full_name_suggest":{"input":["Одношевна Валерія В'ячеславівна","Валерія В'ячеславівна Одношевна","Валерія Одношевна"],"output":"Одношевна Валерія В'ячеславівна"}},"liabilities":{"54":{"sum_comment":"","sum":"351","sum_foreign_comment":"","sum_foreign":"","sum_unclear":false,"sum_comment_hidden":false},"55":{"sum_comment":"","sum_foreign_comment":"","sum_foreign":"","sum":""},"56":{"sum_comment":"","sum_foreign_comment":"","sum_foreign":"","sum_unclear":false,"sum":""},"57":{"sum_comment_unclear":false,"sum_comment":"","sum":"","sum_foreign_comment":"","sum_foreign":"","sum_unclear":false,"sum_comment_hidden":false},"58":{"sum_comment":"","sum":"","sum_foreign_comment":"","sum_foreign":"","sum_unclear":false,"sum_comment_hidden":false},"59":{"sum_comment":"","sum_foreign_comment":"","sum_foreign":"","sum":""},"60":{"sum_comment":"","sum_foreign_comment":"","sum_foreign":"","sum":"350","sum_comment_hidden":false},"61":{"sum_comment":"","sum_foreign_comment":"","sum_foreign":"","sum":""},"62":{"sum_comment":"","sum_foreign_comment":"","sum_foreign":"","sum_unclear":false,"sum":""},"63":{"sum_comment":"ПУМБ","sum_foreign_comment":"","sum_foreign":"","sum":"30696","sum_comment_hidden":false},"64":{"sum_comment":"ПУМБ","sum_foreign_comment":"","sum_foreign":"","sum":"18549","sum_comment_hidden":false}},"declaration":{"notfull_lostpages":"","additional_info_text":"","additional_info":"","date":"2015-03-27T00:00:00","notfull":"","url":"http://static.declarations.com.ua/declarations/chosen_ones/judges_batch/4220_odnoshevna_valeriia_v’yacheslavivna.pdf"},"intro":{"declaration_year":"2014"}}