{"income":{"5":{"family_comment":"","value":"237728","family":"12000","comment":""},"6":{"value":"237728","family_comment":"","value_unclear":false,"comment_hidden":false,"family_unclear":false,"family":"","comment":""},"7":{"family_comment":"","value":"","source_name":"","family":"","comment":""},"8":{"family_comment":"","value":"","family":"","comment":""},"9":{"family_comment":"","family_unclear":false,"value":"","family":"","comment":""},"10":{"family_comment":"","value":"","value_unclear":false,"family":"","comment":""},"11":{"family_comment":"","value":"","family":"","comment":""},"12":{"family_comment":"","value":"","family":"","comment":""},"13":{"family_comment":"","value":"","family":"","comment":""},"14":{"family_comment":"","value":"","family":"","comment":""},"15":{"family_comment":"","value":"","family":"","comment":""},"16":{"family_comment":"","value":"","family":"","comment":""},"17":{"family_comment":"","value":"","family":"","comment":""},"18":{"family_comment":"","value":"","family":"","comment":""},"19":{"family_comment":"","value":"","family":"","comment":""},"20":{"value":"","family":"12000","value_unclear":false,"family_hidden":false,"family_comment":"","comment_unclear":false,"comment":"","family_comment_unclear":false}},"vehicle":{"35":[{"year_hidden":false,"brand_info":"1569","sum_rent_comment":"","year":"1981","brand_info_hidden":false,"brand_info_unclear":false,"sum_rent":"","sum":"","brand":"ВАЗ 2121","sum_comment":"","brand_unclear":false,"brand_hidden":false},{"brand_info":"1690","sum_rent_comment":"","brand":"ВАЗ 2123","sum_comment":"","brand_unclear":false,"year":"2005","brand_info_hidden":false,"brand_info_unclear":false,"year_unclear":false,"sum":"","sum_rent":""}]},"id":"vulyk_97_18","banks":{"45":[{"sum_foreign_comment":"","sum_units":"UAH","sum_comment":"","sum_comment_unclear":false,"sum_hidden":false,"sum_foreign_units":"UAH","sum_comment_hidden":false,"sum_unclear":false,"sum":"1600","sum_foreign":""}],"46":[{"sum_foreign_comment":"","sum_units":"UAH","sum_comment":"","sum_foreign_units":"UAH","sum_comment_hidden":false,"sum":"1600","sum_foreign":""}]},"declaration":{"additional_info_text":"","notfull_lostpages":"","date":"2015-03-30T00:00:00","notfull":"","additional_info":"","url":"http://static.declarations.com.ua/declarations/chosen_ones/judges_batch/3846_bondar_iurii_oleksandrovych.pdf"},"liabilities":{"54":{"sum_foreign_comment":"","sum":"","sum_comment":"","sum_comment_unclear":false,"sum_hidden":false,"sum_comment_hidden":false,"sum_unclear":false,"sum_foreign":""},"55":{"sum_foreign_comment":"","sum":"","sum_comment":"","sum_foreign":""},"56":{"sum_foreign_comment":"","sum":"","sum_comment":"","sum_foreign":""},"57":{"sum_foreign_comment":"","sum":"","sum_comment":"","sum_comment_unclear":false,"sum_hidden":false,"sum_comment_hidden":false,"sum_unclear":false,"sum_foreign":""},"58":{"sum_foreign_comment":"","sum":"2400","sum_comment":"","sum_comment_unclear":false,"sum_hidden":false,"sum_comment_hidden":false,"sum_unclear":false,"sum_foreign":""},"59":{"sum_foreign_comment":"","sum":"","sum_comment":"","sum_foreign":""},"60":{"sum_foreign_comment":"","sum":"","sum_comment":"","sum_comment_unclear":false,"sum_hidden":false,"sum_comment_hidden":false,"sum_foreign":""},"61":{"sum_foreign_comment":"","sum":"","sum_comment":"","sum_foreign":""},"62":{"sum_foreign_comment":"","sum":"","sum_comment":"","sum_unclear":false,"sum_foreign":""},"63":{"sum_foreign_comment":"","sum":"","sum_hidden":false,"sum_comment":"","sum_foreign":""},"64":{"sum_foreign_comment":"","sum":"","sum_comment":"","sum_foreign":""}},"ft_src":"2400\nсуддя новопсковського районного суду луганської області\nЛуганська область\nЗагальний місцевий суд\nЮрій\nБондар Т. А\nПодружжя\nБондар Д. Ю\nДитина\nБондар А. Ю\nДитина\nОлександрович\nБондар Юрій Олександрович\nЮрій Олександрович Бондар\nЮрій Бондар\nБондар Юрій Олександрович\nБондар Юрій Олександрович\nБондар\n1569\nВАЗ 2121\n1981\nВАЗ 2123\n1690\n2005\n14\n5.32\n75.4\n74.1\n75.4\n74.1\n1600\n1600\n2014\n1569\nВАЗ 2121\n1981\nВАЗ 2123\n1690\n2005\n2014\nБондар Юрій Олександрович\nЮрій Олександрович Бондар\nЮрій Бондар\nБондар Юрій Олександрович\nЮрій\nПодружжя\nБондар Т. А\nДитина\nБондар Д. Ю\nДитина\nБондар А. Ю\nБондар Юрій Олександрович\nБондар\nЗагальний місцевий суд\nЛуганська область\nсуддя новопсковського районного суду луганської області\nОлександрович\n2400\n237728\n12000\n237728\n12000\n14\n75.4\n74.1\n5.32\n75.4\n74.1\n1600\n1600\n2400\n237728\n12000\n237728\n12000\nПодружжя\nБондар Т. А\nБондар Д. Ю\nДитина\nДитина\nБондар А. Ю\nОлександрович\nБондар\nЮрій\nБондар Юрій Олександрович\nЮрій Олександрович Бондар\nЮрій Бондар\nБондар Юрій Олександрович\nЛуганська область\nЗагальний місцевий суд\nсуддя новопсковського районного суду луганської області\nБондар Юрій Олександрович\n1981\nВАЗ 2121\n1569\n2005\nВАЗ 2123\n1690\n12000\n12000\n237728\n237728\n74.1\n74.1\n75.4\n14\n75.4\n5.32\n1600\n1600\n2014","general":{"name_hidden":false,"name":"Юрій","last_name_hidden":false,"inn":"","family":[{"inn":"","relations":"Подружжя","relations_other":"","inn_hidden":true,"family_name":"Бондар Т. А","name_hidden":true,"name_unclear":false},{"inn_hidden":false,"inn":"","name_hidden":false,"family_name":"Бондар Д. Ю","relations":"Дитина","name_unclear":false},{"inn":"","relations":"Дитина","relations_other":"","inn_hidden":false,"family_name":"Бондар А. Ю","name_hidden":false,"name_unclear":false}],"patronymic":"Олександрович","inn_hidden":true,"family_raw":"","inn_unclear":false,"post":{"region_unclear":false,"region":"Луганська область","post":"суддя новопсковського районного суду луганської області","office":"Загальний місцевий суд","office_unclear":false,"post_hidden":false},"full_name":"Бондар Юрій Олександрович","addresses":[{"place_district":"","place_city_hidden":true,"place_city":"","place_city_unclear":false,"place_district_hidden":false,"place_city_type":"","place_address_hidden":true,"place_city_type_hidden":false,"place_address":"","place_hidden":true,"place":""}],"last_name":"Бондар","patronymic_hidden":false,"full_name_suggest":{"output":"Бондар Юрій Олександрович","input":["Бондар Юрій Олександрович","Юрій Олександрович Бондар","Юрій Бондар"]}},"source":"VULYK","estate":{"24":[{"region_unclear":false,"space_unclear":false,"costs":"","costs_comment":"","address_hidden":false,"region_hidden":true,"space_comment":"","space_hidden":false,"space":"75.4","address":"","region":"","address_unclear":false,"costs_rent_comment":"","space_comment_unclear":false,"space_units":"м²","costs_rent":""}],"25":[{"region_unclear":false,"space_unclear":false,"costs":"","costs_comment":"","address_hidden":false,"region_hidden":true,"space_comment":"","space_hidden":false,"space":"74.1","address":"","region":"","costs_rent_comment":"","space_comment_unclear":false,"space_comment_hidden":false,"space_units":"м²","costs_rent":""}],"27":[{"region_unclear":false,"costs":"","costs_comment":"","address_hidden":false,"region_hidden":true,"space_comment":"","space":"14","address":"","region":"","costs_rent_comment":"","space_units":"м²","costs_rent":""}],"29":[{"region_unclear":false,"space_unclear":false,"address_hidden":false,"region_hidden":true,"space_comment":"","space":"5.32","address":"","region":"","costs_property":"","costs_rent_comment":"","space_comment_unclear":false,"address_unclear":false,"space_units":"га","costs_property_comment":"","costs_rent":""}],"30":[{"address_hidden":false,"region_hidden":true,"space_comment":"","space":"75.4","address":"","region":"","costs_property":"","costs_rent_comment":"","address_unclear":false,"space_units":"м²","costs_property_comment":"","costs_rent":""}],"31":[{"space_unclear":false,"address_hidden":false,"region_hidden":true,"space_comment":"","space_hidden":false,"space":"74.1","address":"","region":"","costs_property":"","costs_rent_comment":"","space_comment_hidden":false,"space_units":"м²","costs_property_comment":"","costs_rent":""}]},"intro":{"declaration_year":"2014","isnotdeclaration":""}}