{"income":{"5":{"value":"403022","family_comment":"","value_unclear":false,"family_unclear":false,"family":"","comment":""},"6":{"value":"242584","family_comment":"","value_unclear":false,"family_unclear":false,"family":"","comment":""},"7":{"value":"","value_unclear":false,"family_comment":"","source_name":"","family":"","comment":""},"8":{"family_comment":"","value":"","family":"","comment":""},"9":{"family_comment":"","value":"148258","value_unclear":false,"family":"","comment":""},"10":{"family_comment":"","value":"12180","comment_unclear":false,"family":"","comment":""},"11":{"family_comment":"","value":"","family":"","comment":""},"12":{"family_comment":"","value":"","family":"","comment":""},"13":{"family_comment":"","value":"","family":"","comment":""},"14":{"family_comment":"","value":"","family":"","comment":""},"15":{"family_comment":"","value":"","family":"","comment":""},"16":{"family_comment":"","value":"","family":"","comment":""},"17":{"family_comment":"","value":"","family":"","comment":""},"18":{"family_comment":"","value":"","family":"","comment":""},"19":{"family_comment":"","value":"","family":"","comment":""},"20":{"family_comment":"","value":"","family":"","comment":""}},"vehicle":{"35":[{"brand_info":"1.6 MPI, 75 кВт","sum_rent_comment":"","brand":"Volkswagen Passat","sum_comment":"","year":"2005","brand_hidden":false,"brand_info_hidden":false,"sum_hidden":false,"sum":"136000","sum_rent":""}],"40":[{"brand_info":"Intence 2.0 AT. Об'єм - 2.0 , потужність - 110.3 кВт","sum_rent_comment":"","year":"2009","brand_info_hidden":false,"brand_info_unclear":false,"sum_rent":"","sum":"","brand":"Mitsubishi Lancer","sum_comment":"","sum_comment_unclear":false,"brand_hidden":false,"brand_unclear":false}]},"id":"vulyk_55_93","banks":{"45":[{"sum_foreign_comment":"","sum_units":"UAH","sum_comment":"","sum_comment_unclear":false,"sum_foreign_units":"UAH","sum_foreign_comment_unclear":false,"sum_units_unclear":false,"sum_comment_hidden":false,"sum_unclear":false,"sum":"434595","sum_foreign":""},{"sum_foreign_comment":"","sum_units":"UAH","sum_comment":"","sum_comment_unclear":false,"sum_foreign_units":"UAH","sum":"253999","sum_unclear":false,"sum_foreign":""},{"sum_foreign_comment":"","sum_units":"","sum_comment":"","sum_foreign_units":"","sum":"","sum_unclear":false,"sum_foreign":""}],"46":[{"sum_foreign_comment":"","sum_units":"UAH","sum_comment":"","sum_comment_unclear":false,"sum_foreign_units":"UAH","sum":"106497","sum_foreign":""}],"47":[{"sum_foreign_comment":"","sum_units":"UAH","sum_comment":"","sum_comment_unclear":false,"sum_hidden":false,"sum_foreign_units":"UAH","sum":"","sum_foreign":""}],"48":[{"sum_foreign_comment":"","sum_units":"UAH","sum_comment":"","sum_foreign_units":"UAH","sum":"","sum_foreign":""}],"49":[{"sum_foreign_comment":"","sum_units":"UAH","sum_comment":"","sum_foreign_units":"UAH","sum":"","sum_foreign":""},{"sum_foreign_comment":"","sum_units":"","sum_comment":"","sum":"","sum_foreign":""}],"50":[{"sum_foreign_comment":"","sum_units":"UAH","sum_comment":"","sum_foreign_units":"UAH","sum":"","sum_foreign":""}],"51":[{"sum_units":"UAH","sum_hidden":false,"sum_units_hidden":false,"sum_foreign":"","sum_foreign_comment":"","sum":"","sum_comment":"","sum_comment_unclear":false,"sum_foreign_units":"UAH","sum_units_unclear":false,"sum_comment_hidden":false,"sum_unclear":false},{"sum_foreign_comment":"","sum_units":"","sum_comment":"","sum_foreign_units":"","sum":"","sum_foreign":""}],"52":[{"sum_foreign_comment":"","sum_units":"UAH","sum_comment":"","sum_comment_unclear":false,"sum_foreign_units":"UAH","sum":"","sum_foreign":""},{"sum_foreign_comment":"","sum_units":"","sum_comment":"","sum_foreign_units":"","sum":"","sum_foreign":""}],"53":[{"sum_foreign_comment":"","sum_units":"UAH","sum_comment":"","sum_hidden":false,"sum_foreign_units":"UAH","sum":"","sum_unclear":false,"sum_foreign":""},{"sum_foreign_comment":"","sum_units":"","sum_comment":"","sum_comment_unclear":false,"sum_foreign_units":"","sum":"","sum_foreign":""},{"sum_foreign_comment":"","sum_units":"","sum_comment":"","sum_foreign_units":"","sum":"","sum_foreign":""},{"sum_foreign_comment":"","sum_units":"","sum_comment":"","sum_foreign_units":"","sum":"","sum_foreign":""}]},"declaration":{"additional_info_text":"","notfull_lostpages":"","date":"2015-03-20T00:00:00","notfull":"","additional_info":"","url":"http://static.declarations.com.ua/declarations/chosen_ones/mega_batch/savchenko_viktor_oleksiiovych.pdf"},"liabilities":{"54":{"sum_foreign_comment":"","sum":"","sum_comment":"","sum_hidden":false,"sum_comment_hidden":false,"sum_foreign":""},"55":{"sum_foreign_comment":"","sum_foreign_hidden":false,"sum_comment":"","sum_hidden":false,"sum":"","sum_foreign":""},"56":{"sum_foreign_comment":"","sum":"","sum_comment":"","sum_unclear":false,"sum_foreign":""},"57":{"sum_foreign_comment":"","sum":"","sum_comment":"","sum_comment_unclear":false,"sum_hidden":false,"sum_comment_hidden":false,"sum_unclear":false,"sum_foreign":""},"58":{"sum_foreign_comment":"","sum":"","sum_comment":"","sum_hidden":false,"sum_comment_hidden":false,"sum_unclear":false,"sum_foreign":""},"59":{"sum_foreign_comment":"","sum":"","sum_comment":"","sum_foreign":""},"60":{"sum_foreign_comment":"","sum":"","sum_comment":"","sum_hidden":false,"sum_comment_hidden":false,"sum_foreign":""},"61":{"sum_foreign_comment":"","sum":"","sum_comment":"","sum_foreign":""},"62":{"sum_foreign_comment":"","sum":"","sum_comment":"","sum_foreign":""},"63":{"sum_foreign_comment":"","sum":"","sum_comment":"","sum_unclear":false,"sum_foreign":""},"64":{"sum_foreign_comment":"","sum":"","sum_comment":"","sum_unclear":false,"sum_foreign":""}},"ft_src":"Дніпродзержинськ\nДніпропетровська область\nсуддя баглійського районного суду м. дніпродзержинська, дніпропетровської області\nДніпропетровська область\nЗагальний місцевий суд\nВіктор\nСавченко Катерина Вікторівна\nДитина\nОлексійович\nСавченко\nСавченко Віктор Олексійович\nСавченко Віктор Олексійович\nВіктор Олексійович Савченко\nВіктор Савченко\nСавченко Віктор Олексійович\n136000\n2005\nVolkswagen Passat\n1.6 MPI, 75 кВт\nIntence 2.0 AT. Об'єм - 2.0 , потужність - 110.3 кВт\nMitsubishi Lancer\n2009\n106497\n434595\n253999\n2014\n1.6 MPI, 75 кВт\n136000\n2005\nVolkswagen Passat\nIntence 2.0 AT. Об'єм - 2.0 , потужність - 110.3 кВт\nMitsubishi Lancer\n2009\n434595\n253999\n106497\n71.9\nм. Дніпродзержинськ\nДніпропетровська область\n38.7\nспадщина у 2006 р\nМиколаївська область\nм. Южноукраїнськ\nДитина\nСавченко Катерина Вікторівна\nСавченко Віктор Олексійович\nВіктор Олексійович Савченко\nВіктор Савченко\nСавченко Віктор Олексійович\nВіктор\nСавченко Віктор Олексійович\nОлексійович\nЗагальний місцевий суд\nсуддя баглійського районного суду м. дніпродзержинська, дніпропетровської області\nДніпропетровська область\nСавченко\nДніпродзержинськ\nДніпропетровська область\n242584\n403022\n12180\n148258\n2014\nм. Дніпродзержинськ\nДніпропетровська область\n71.9\nспадщина у 2006 р\n38.7\nм. Южноукраїнськ\nМиколаївська область\nСавченко Катерина Вікторівна\nДитина\nОлексійович\nСавченко\nСавченко Віктор Олексійович\nВіктор Олексійович Савченко\nВіктор Савченко\nСавченко Віктор Олексійович\nДніпропетровська область\nДніпродзержинськ\nДніпропетровська область\nсуддя баглійського районного суду м. дніпродзержинська, дніпропетровської області\nЗагальний місцевий суд\nСавченко Віктор Олексійович\nВіктор\n242584\n12180\n403022\n148258\n2005\n136000\nVolkswagen Passat\n1.6 MPI, 75 кВт\nMitsubishi Lancer\nIntence 2.0 AT. Об'єм - 2.0 , потужність - 110.3 кВт\n2009\n12180\n403022\n148258\n242584\nм. Дніпродзержинськ\nДніпропетровська область\n71.9\nспадщина у 2006 р\nм. Южноукраїнськ\nМиколаївська область\n38.7\n106497\n434595\n253999\n2014","general":{"name_hidden":false,"name":"Віктор","patronymic_unclear":false,"last_name_hidden":false,"inn":"","family":[{"inn":"","inn_hidden":true,"relations_unclear":false,"relations_hidden":false,"relations_other":"","relations":"Дитина","name_hidden":false,"family_name":"Савченко Катерина Вікторівна","name_unclear":false}],"patronymic":"Олексійович","inn_hidden":true,"family_raw":"","inn_unclear":false,"post":{"post_unclear":false,"post":"суддя баглійського районного суду м. дніпродзержинська, дніпропетровської області","post_hidden":false,"region":"Дніпропетровська область","region_hidden":false,"office":"Загальний місцевий суд","office_hidden":false,"office_unclear":false},"last_name_unclear":false,"full_name":"Савченко Віктор Олексійович","addresses":[{"place_city_type_unclear":false,"place_address":"","place_district_hidden":false,"place_city_type":"Місто","place_address_hidden":true,"place_address_unclear":false,"place_city_type_hidden":false,"place":"Дніпропетровська область","place_district":"","place_city_hidden":false,"place_city":"Дніпродзержинськ","place_city_unclear":false,"place_hidden":false}],"last_name":"Савченко","patronymic_hidden":false,"full_name_suggest":{"output":"Савченко Віктор Олексійович","input":["Савченко Віктор Олексійович","Віктор Олексійович Савченко","Віктор Савченко"]}},"source":"VULYK","estate":{"23":[{"space_hidden":false,"costs":"","costs_comment":"","address_hidden":false,"region_hidden":false,"space_comment":"","space":"","address":"","region":"","address_unclear":false,"costs_rent_comment":"","space_units":"м²","costs_rent":""},{"costs_rent":"","region":"","costs":"","costs_rent_comment":"","costs_comment":"","region_hidden":false,"space_comment":"","space_units":"","space":"","address":""},{"costs_rent":"","region":"","costs":"","costs_rent_comment":"","costs_comment":"","space_comment":"","space_units":"","space":"","address":""},{"costs_rent":"","costs":"","costs_rent_comment":"","costs_comment":"","space_comment":"","space_units":"","space":"","address":""}],"25":[{"region_unclear":false,"space_unclear":false,"costs":"","costs_comment":"","costs_hidden":false,"address_hidden":true,"region_hidden":false,"space_comment":"спадщина у 2006 р","space_hidden":false,"space":"38.7","address":"м. Южноукраїнськ","costs_unclear":false,"region":"Миколаївська область","address_unclear":false,"costs_rent_comment":"","space_comment_unclear":false,"space_comment_hidden":false,"space_units":"м²","costs_rent":""}],"31":[{"region_unclear":false,"space_unclear":false,"address_hidden":true,"region_hidden":false,"space_comment":"","space_hidden":false,"space":"71.9","address":"м. Дніпродзержинськ","region":"Дніпропетровська область","costs_property":"","space_units_unclear":false,"space_comment_unclear":false,"space_units":"м²","costs_property_comment":"","costs_rent":"","costs_rent_comment":""}]},"intro":{"declaration_year":"2014","isnotdeclaration":""}}