{"income":{"5":{"family_comment":"","value":"180916","family":"101394","comment":""},"6":{"value":"180916","family_comment":"","value_unclear":false,"comment_hidden":false,"family_unclear":false,"family":"6600","comment":""},"7":{"family_comment":"","value":"","source_name":"","family":"","comment":""},"8":{"family_comment":"","value":"","family":"","comment":""},"9":{"family_comment":"","family_unclear":false,"value":"","family":"19048","comment":""},"10":{"family_comment":"","value":"","value_unclear":false,"family":"","comment":""},"11":{"family_comment":"","value":"","family":"","comment":""},"12":{"family_comment":"","value":"","family":"","comment":""},"13":{"family_comment":"","value":"","family":"","comment":""},"14":{"family_comment":"","value":"","family":"","comment":""},"15":{"family_comment":"","value":"","family":"","comment":""},"16":{"family_comment":"","value":"","family":"","comment":""},"17":{"family_comment":"","value":"","family":"","comment":""},"18":{"family_comment":"","value":"","family":"","comment":""},"19":{"family_comment":"","value":"","family":"1204","comment":""},"20":{"value":"","comment_unclear":false,"family_hidden":false,"family_comment":"","value_unclear":false,"family":"74542","comment":"","family_comment_unclear":false}},"vehicle":{"40":[{"brand_info":"TF69 Y, 1498 куб. см., 63 кВт , 423.7 см","sum_rent_comment":"","brand":"Daewoo /FSO Lanos","sum_comment":"","brand_unclear":false,"year":"2007","brand_info_unclear":false,"year_unclear":false,"sum":"","sum_rent":""}],"44":[{"brand_info":"причіп легковий-В, 296 см","sum":"","brand":"ПГМФ/8302","sum_comment":"","year":"2009","brand_hidden":false,"sum_rent_comment":"","sum_rent":""}]},"id":"vulyk_97_16","banks":{"51":[{"sum_foreign_comment":"","sum_units":"UAH","sum_comment":"ПАТ Державний ощадний банк України, ПАТ Полікомбанк","sum_comment_unclear":false,"sum_hidden":false,"sum_foreign_units":"UAH","sum_comment_hidden":false,"sum_unclear":false,"sum":"123785","sum_foreign":""}]},"declaration":{"additional_info_text":"У п. 2 наведено дві адреси. Друга: Чернігівська обл, м. Корюківка","notfull_lostpages":"","date":"2015-03-31T00:00:00","notfull":"","additional_info":"1","url":"http://static.declarations.com.ua/declarations/chosen_ones/judges_batch/3844_synko_olena_oleksandrivna.pdf"},"liabilities":{"54":{"sum_foreign_comment":"","sum":"","sum_comment":"","sum_comment_unclear":false,"sum_hidden":false,"sum_comment_hidden":false,"sum_unclear":false,"sum_foreign":""},"55":{"sum_foreign_comment":"","sum":"","sum_comment":"","sum_foreign":""},"56":{"sum_foreign_comment":"","sum":"","sum_comment":"","sum_foreign":""},"57":{"sum_foreign_comment":"","sum":"","sum_comment":"","sum_comment_unclear":false,"sum_hidden":false,"sum_comment_hidden":false,"sum_unclear":false,"sum_foreign":""},"58":{"sum_foreign_comment":"","sum":"","sum_comment":"","sum_comment_unclear":false,"sum_hidden":false,"sum_comment_hidden":false,"sum_unclear":false,"sum_foreign":""},"59":{"sum_foreign_comment":"","sum":"","sum_comment":"","sum_foreign":""},"60":{"sum_foreign_comment":"","sum":"","sum_comment":"","sum_comment_unclear":false,"sum_hidden":false,"sum_comment_hidden":false,"sum_foreign":""},"61":{"sum_foreign_comment":"","sum":"","sum_comment":"","sum_foreign":""},"62":{"sum_foreign_comment":"","sum":"","sum_comment":"","sum_unclear":false,"sum_foreign":""},"63":{"sum_foreign_comment":"","sum":"","sum_foreign":"","sum_comment":"","sum_hidden":false},"64":{"sum_foreign_comment":"","sum":"","sum_comment":"","sum_foreign":""}},"ft_src":"Daewoo /FSO Lanos\nTF69 Y, 1498 куб. см., 63 кВт , 423.7 см\n2007\n2009\nпричіп легковий-В, 296 см\nПГМФ/8302\nм. Чернігів, гаражний кооператив\n33.32\nЧернігівська область\nм. Чернігів, гаражний кооператив\nЧернігівська область\n19.72\n1/2 земельної ділянки\nЧернігівський район, Краснянська сільська рада\nЧернігівська область\n37100\n1/2 земельної ділянки\nЧернігівський район, Краснянська сільська рада\nЧернігівська область\n14200\nЧернігівська область\n1/2 земельної ділянки\nЧернігівський район, с. Золотинка, провулок Комка, 6\n2500\nЧернігівська область\n1/2 земельної ділянки\nЧернігівський район, с. Золотинка\n521\nЧернігівська область\n1/2 земельної ділянки\nЧернігівський район, с. Золотинка\n780\nЧернігівська область\nЧернігівський район, Іванівська сільська рада\n1000\nЧернігівський район, Улянівська сільська рада\n1000\nЧернігівська область\n1/2\nЧернігівський район, с. Золотинка\nЧернігівська область\n53.6\n62.73\nЧернігівська область\nм. Чернігів\nЧернігівська область\nм. Чернігів\n65.8\n38.9\nм. Корюківка\nЧернігівська область\nПАТ Державний ощадний банк України, ПАТ Полікомбанк\n123785\n1\nУ п. 2 наведено дві адреси. Друга: Чернігівська обл, м. Корюківка\n2014\nTF69 Y, 1498 куб. см., 63 кВт , 423.7 см\nDaewoo /FSO Lanos\n2007\nпричіп легковий-В, 296 см\n2009\nПГМФ/8302\nУ п. 2 наведено дві адреси. Друга: Чернігівська обл, м. Корюківка\n1\n2014\nСинько Олена Олександрівна\nОлена Олександрівна Синько\nОлена Синько\nСинько Олена Олександрівна\nОлена\nБатьки\nСинько О. М\nБатьки\nСинько Н. Г\nБрат/Сестра\nСинько В. О\nСинько Олена Олександрівна\nСинько\nЗагальний місцевий суд\nЧернігівська область\nсуддя корюківського районного суду чернігівської області\nОлександрівна\nЧернігівська область\n14000\nЧернігів\n180916\n6600\n74542\n180916\n101394\n19048\n1204\n33.32\nЧернігівська область\nм. Чернігів, гаражний кооператив\n53.6\n1/2\nЧернігівська область\nЧернігівський район, с. Золотинка\n38.9\nм. Корюківка\nЧернігівська область\n37100\n1/2 земельної ділянки\nЧернігівська область\nЧернігівський район, Краснянська сільська рада\n14200\n1/2 земельної ділянки\nЧернігівська область\nЧернігівський район, Краснянська сільська рада\n2500\n1/2 земельної ділянки\nЧернігівська область\nЧернігівський район, с. Золотинка, провулок Комка, 6\n521\n1/2 земельної ділянки\nЧернігівська область\nЧернігівський район, с. Золотинка\n780\n1/2 земельної ділянки\nЧернігівська область\nЧернігівський район, с. Золотинка\n1000\nЧернігівська область\nЧернігівський район, Іванівська сільська рада\n1000\nЧернігівський район, Улянівська сільська рада\nЧернігівська область\n19.72\nЧернігівська область\nм. Чернігів, гаражний кооператив\n62.73\nЧернігівська область\nм. Чернігів\n65.8\nЧернігівська область\nм. Чернігів\nПАТ Державний ощадний банк України, ПАТ Полікомбанк\n123785\n6600\n180916\n19048\n101394\n180916\n1204\n74542\nБатьки\nСинько О. М\nСинько Н. Г\nБатьки\nБрат/Сестра\nСинько В. О\nОлександрівна\nСинько\nОлена\nСинько Олена Олександрівна\nОлена Олександрівна Синько\nОлена Синько\nСинько Олена Олександрівна\n14000\nЧернігів\nЧернігівська область\nЧернігівська область\nЗагальний місцевий суд\nсуддя корюківського районного суду чернігівської області\nСинько Олена Олександрівна","general":{"name_hidden":false,"name":"Олена","last_name_hidden":false,"inn":"","last_name":"Синько","family":[{"inn":"","relations":"Батьки","relations_other":"","inn_hidden":true,"family_name":"Синько О. М","name_hidden":true,"name_unclear":false},{"inn":"","relations":"Батьки","name_hidden":false,"inn_hidden":false,"family_name":"Синько Н. Г","name_unclear":false},{"inn":"","relations":"Брат/Сестра","relations_other":"","inn_hidden":false,"family_name":"Синько В. О","name_hidden":false,"name_unclear":false}],"inn_hidden":true,"family_raw":"","inn_unclear":false,"post":{"region_unclear":false,"post":"суддя корюківського районного суду чернігівської області","post_hidden":false,"region":"Чернігівська область","office":"Загальний місцевий суд","office_unclear":false},"full_name":"Синько Олена Олександрівна","addresses":[{"place_district":"","place_address_hidden":true,"place_city":"Чернігів","place_city_unclear":false,"place_district_hidden":false,"place_city_type":"Місто","place_city_hidden":false,"place_city_type_hidden":false,"place_address":"14000","place_hidden":false,"place":"Чернігівська область"}],"patronymic":"Олександрівна","patronymic_hidden":false,"full_name_suggest":{"output":"Синько Олена Олександрівна","input":["Синько Олена Олександрівна","Олена Олександрівна Синько","Олена Синько"]}},"source":"VULYK","estate":{"23":[{"region_unclear":false,"space_unclear":false,"costs":"","costs_rent_unclear":false,"costs_comment":"","address_hidden":false,"region_hidden":false,"space_comment":"","space":"1000","address":"Чернігівський район, Улянівська сільська рада","region":"Чернігівська область","address_unclear":false,"costs_rent_comment":"","space_units":"м²","costs_rent":""}],"25":[{"region_unclear":false,"space_hidden":false,"costs":"","costs_comment":"","address_hidden":true,"region_hidden":false,"space_comment":"","space_unclear":false,"space":"38.9","address":"м. Корюківка","region":"Чернігівська область","costs_rent_comment":"","space_comment_unclear":false,"space_comment_hidden":false,"space_units":"м²","costs_rent":""}],"27":[{"region_unclear":false,"costs":"","costs_comment":"","address_hidden":false,"region_hidden":false,"space_comment":"","space":"33.32","address":"м. Чернігів, гаражний кооператив","region":"Чернігівська область","costs_rent_comment":"","space_units":"м²","costs_rent":""}],"29":[{"region_unclear":false,"space_unclear":false,"address_hidden":false,"region_hidden":false,"space_comment":"1/2 земельної ділянки","space":"37100","address":"Чернігівський район, Краснянська сільська рада","region":"Чернігівська область","costs_property":"","costs_rent_comment":"","space_comment_unclear":false,"address_unclear":false,"space_units":"м²","costs_property_comment":"","costs_rent":""},{"address_hidden":false,"region_hidden":false,"space_comment":"1/2 земельної ділянки","space":"14200","address":"Чернігівський район, Краснянська сільська рада","region":"Чернігівська область","costs_property":"","costs_rent_comment":"","address_unclear":false,"space_units":"м²","costs_property_comment":"","costs_rent":""},{"costs_rent":"","region":"Чернігівська область","costs_property":"","costs_rent_comment":"","region_hidden":false,"space_comment":"1/2 земельної ділянки","costs_property_comment":"","space_units":"м²","space":"2500","address":"Чернігівський район, с. Золотинка, провулок Комка, 6"},{"costs_rent":"","region":"Чернігівська область","costs_property":"","costs_rent_comment":"","space_comment":"1/2 земельної ділянки","costs_property_comment":"","space_units":"м²","space":"521","address":"Чернігівський район, с. Золотинка"},{"costs_rent":"","region":"Чернігівська область","costs_property":"","costs_rent_comment":"","space_comment":"1/2 земельної ділянки","costs_property_comment":"","space_units":"м²","space":"780","address":"Чернігівський район, с. Золотинка"},{"costs_rent":"","region":"Чернігівська область","costs_property":"","costs_rent_comment":"","space_comment":"","costs_property_comment":"","space_units":"м²","space":"1000","address":"Чернігівський район, Іванівська сільська рада"}],"30":[{"address_hidden":false,"region_hidden":false,"space_comment":"1/2","space":"53.6","address":"Чернігівський район, с. Золотинка","region":"Чернігівська область","costs_property":"","costs_rent_comment":"","address_unclear":false,"space_units":"м²","costs_property_comment":"","costs_rent":""}],"31":[{"space_unclear":false,"address_hidden":true,"region_hidden":false,"space_comment":"","space_hidden":false,"space":"62.73","address":"м. Чернігів","region":"Чернігівська область","costs_property":"","costs_rent_comment":"","space_comment_hidden":false,"space_units":"м²","costs_property_comment":"","costs_rent":""},{"costs_rent":"","region":"Чернігівська область","costs_property":"","costs_rent_comment":"","address_hidden":false,"space_comment":"","costs_property_comment":"","space_units":"м²","space":"65.8","address":"м. Чернігів"}],"33":[{"space_hidden":false,"address_hidden":true,"region_hidden":false,"space_comment":"","space":"19.72","address":"м. Чернігів, гаражний кооператив","region":"Чернігівська область","costs_property":"","costs_rent_comment":"","space_units":"м²","costs_property_comment":"","costs_rent":""}]},"intro":{"declaration_year":"2014","isnotdeclaration":""}}