{"income":{"5":{"value":"308995","family_comment":"","value_unclear":false,"comment_hidden":false,"family_hidden":false,"value_hidden":false,"family_unclear":false,"family":"931","comment":""},"6":{"value":"181395","family_comment":"","comment_unclear":false,"family_hidden":false,"family_unclear":false,"value_unclear":false,"comment":"","family":""},"7":{"source_name_unclear":false,"value":"","value_hidden":false,"family_comment":"","source_name":"","family":"","comment":"","source_name_hidden":false},"8":{"value":"","family_hidden":false,"value_hidden":false,"family_comment":"","family":"","comment":""},"9":{"value":"","family_comment":"","value_unclear":false,"family_hidden":false,"value_hidden":false,"family_unclear":false,"family":"","comment":""},"10":{"family_comment":"","value":"","family":"","comment":""},"11":{"family_comment":"","value":"","family":"","comment":""},"12":{"family_comment":"","value":"","family":"","comment":""},"13":{"family_comment":"","value":"","family":"","comment":""},"14":{"family_comment":"","value":"","family":"","comment":""},"15":{"family_comment":"","value":"","family":"","comment":""},"16":{"value":"127600","family_comment":"","value_unclear":false,"family_unclear":false,"family":"","comment":""},"17":{"family_comment":"","value":"","family":"","comment":""},"18":{"family_comment":"","value":"","family":"","comment":""},"19":{"family_comment":"","value":"","comment_unclear":false,"family":"","comment":""},"20":{"value":"","family_comment":"допомога по догляду за дитиною до досягнення нею трирічного віку працюючим жінкам","comment_unclear":false,"comment_hidden":false,"family_hidden":false,"value_hidden":false,"family_unclear":false,"value_unclear":false,"family":"931","comment":"","family_comment_unclear":false}},"id":"vulyk_63_67","declaration":{"additional_info_text":"","notfull_lostpages":"","date":"2015-03-25T00:00:00","notfull":"","additional_info":"","url":"http://static.declarations.com.ua/declarations/chosen_ones/mega_batch/meiechko_oleksandr_mykhailovych.pdf"},"liabilities":{"54":{"sum_foreign_comment":"","sum":"","sum_comment":"","sum_unclear":false,"sum_foreign":""},"55":{"sum_foreign_comment":"","sum":"","sum_comment":"","sum_foreign":""},"56":{"sum_foreign_comment":"","sum":"","sum_comment":"","sum_unclear":false,"sum_foreign":""},"57":{"sum_foreign_comment":"","sum":"","sum_comment":"","sum_comment_hidden":false,"sum_unclear":false,"sum_foreign":""},"58":{"sum_foreign_comment":"","sum_comment":"","sum":"","sum_comment_hidden":false,"sum_foreign":""},"59":{"sum_foreign_comment":"","sum":"","sum_comment":"","sum_foreign":""},"60":{"sum_foreign_comment":"","sum":"","sum_comment":"","sum_comment_unclear":false,"sum_foreign":""},"61":{"sum_foreign_comment":"","sum":"","sum_comment":"","sum_unclear":false,"sum_foreign":""},"62":{"sum_foreign_comment":"","sum":"","sum_comment":"","sum_unclear":false,"sum_foreign":""},"63":{"sum_foreign_comment":"","sum":"","sum_comment":"","sum_hidden":false,"sum_comment_hidden":false,"sum_unclear":false,"sum_foreign":""},"64":{"sum_foreign_comment":"","sum_comment":"","sum":"","sum_comment_hidden":false,"sum_foreign":""}},"ft_src":"2014\n181395\n931\n308995\n127600\nдопомога по догляду за дитиною до досягнення нею трирічного віку працюючим жінкам\n931\n181395\nдопомога по догляду за дитиною до досягнення нею трирічного віку працюючим жінкам\n931\n308995\n931\n127600\nМеєчко Олександр Михайлович\nОлександр Михайлович Меєчко\nОлександр Меєчко\nМеєчко Олександр Михайлович\nОлександр\nМеєчко Олександр Михайлович\nМихайлович\nЗагальний місцевий суд\nОдеська область\nсуддя фрунзівського районного суду одеської області\nМеєчко\n2014\nМеєчко Олександр Михайлович\nОлександр Михайлович Меєчко\nОлександр Меєчко\nМеєчко Олександр Михайлович\nМихайлович\nМеєчко\nОдеська область\nсуддя фрунзівського районного суду одеської області\nЗагальний місцевий суд\nМеєчко Олександр Михайлович\nОлександр","general":{"name_hidden":false,"name":"Олександр","patronymic_unclear":false,"last_name_hidden":true,"inn":"","last_name":"Меєчко","patronymic":"Михайлович","inn_hidden":false,"family_raw":"","inn_unclear":false,"post":{"post_unclear":false,"region_unclear":false,"post":"суддя фрунзівського районного суду одеської області","office_hidden":false,"region":"Одеська область","region_hidden":false,"office":"Загальний місцевий суд","office_unclear":false},"full_name_suggest":{"output":"Меєчко Олександр Михайлович","input":["Меєчко Олександр Михайлович","Олександр Михайлович Меєчко","Олександр Меєчко"]},"full_name":"Меєчко Олександр Михайлович","last_name_unclear":false,"name_unclear":false},"source":"VULYK","intro":{"declaration_year":"2014","isnotdeclaration":"","declaration_year_unclear":false}}