{"id":"vulyk_89_10","ft_src":"47.2\n86.9\n2014\n241110.18\n37098.21\n257105.36\n37098.21\nпенсія\n15995.18\n47.2\n86.9\nМихайлівна\nШевченко О. В\nПодружжя\nМіронова Галина Михайлівна\nГалина Михайлівна Міронова\nГалина Міронова\nМіронова Галина Михайлівна\nМіронова Галина Михайлівна\nГалина\nМіронова\nДонецька область\nсуддя донецького апеляційного адміністративного суду\nАпеляційний адміністративний суд\n241110.18\nпенсія\n15995.18\n37098.21\n257105.36\n37098.21\n2014\nШевченко О. В\nПодружжя\nМихайлівна\nМіронова\nсуддя донецького апеляційного адміністративного суду\nДонецька область\nАпеляційний адміністративний суд\nМіронова Галина Михайлівна\nМіронова Галина Михайлівна\nГалина Михайлівна Міронова\nГалина Міронова\nМіронова Галина Михайлівна\nГалина","estate":{"31":[{"costs_property_comment":"","address":"","space_units":"м²","space_hidden":false,"space_comment":"","region_hidden":true,"costs_property":"","region":"","address_hidden":true,"costs_rent_comment":"","space":"47.2","costs_rent":""},{"costs_property_comment":"","address":"","space_units":"м²","costs_rent_comment":"","space":"86.9","region_hidden":false,"costs_property":"","space_comment":"","costs_rent":""}]},"source":"VULYK","income":{"5":{"family":"37098.21","family_comment":"","comment":"","value_hidden":false,"family_hidden":false,"value":"257105.36"},"6":{"family_comment":"","value":"241110.18","family":"","comment":""},"7":{"family":"","family_comment":"","value":"","comment":"","source_name":""},"8":{"family_comment":"","value":"","family":"","comment":""},"9":{"family_comment":"","value":"","family":"","comment":""},"10":{"family_comment":"","value":"","family":"","comment":""},"11":{"family_comment":"","value":"","family":"","comment":""},"12":{"family_comment":"","value":"","family":"","comment":""},"13":{"family_comment":"","value":"","family":"","comment":""},"14":{"family_comment":"","value":"","family":"","comment":""},"15":{"family_comment":"","value":"","family":"","comment":""},"16":{"family_comment":"","value":"","family":"","comment":""},"17":{"family_comment":"","value":"","family":"","comment":""},"18":{"family_comment":"","value":"","family":"","comment":""},"19":{"family_comment":"","value":"","family":"","comment":""},"20":{"family_comment":"","value":"15995.18","family":"37098.21","comment":"пенсія"}},"general":{"inn":"","addresses":[{"place_city_type_hidden":false,"place_city_type":"","place_city_hidden":false,"place_hidden":true,"place_district":"","place_district_hidden":false,"place":"","place_address":"","place_address_hidden":true,"place_city":""}],"last_name":"Міронова","full_name":"Міронова Галина Михайлівна","family":[{"inn":"","name_hidden":true,"family_name":"Шевченко О. В","inn_hidden":true,"relations":"Подружжя"}],"patronymic":"Михайлівна","inn_hidden":true,"name":"Галина","post":{"office":"Апеляційний адміністративний суд","region":"Донецька область","post":"суддя донецького апеляційного адміністративного суду"},"family_raw":"","full_name_suggest":{"input":["Міронова Галина Михайлівна","Галина Михайлівна Міронова","Галина Міронова"],"output":"Міронова Галина Михайлівна"}},"liabilities":{"54":{"sum_comment":"","sum_foreign_comment":"","sum_foreign":"","sum":""},"55":{"sum_comment":"","sum_foreign_comment":"","sum_foreign":"","sum":""},"56":{"sum_comment":"","sum_foreign_comment":"","sum_foreign":"","sum_unclear":false,"sum":""},"57":{"sum_comment":"","sum_foreign_comment":"","sum_foreign":"","sum":""},"58":{"sum_comment":"","sum_foreign_comment":"","sum_foreign":"","sum":""},"59":{"sum_comment":"","sum_foreign_comment":"","sum_foreign":"","sum":""},"60":{"sum_comment":"","sum_foreign_comment":"","sum_foreign":"","sum":""},"61":{"sum_comment":"","sum_foreign_comment":"","sum_foreign":"","sum":""},"62":{"sum_comment":"","sum_foreign_comment":"","sum_foreign":"","sum_unclear":false,"sum":""},"63":{"sum_comment":"","sum_foreign_comment":"","sum_foreign":"","sum":""},"64":{"sum_comment":"","sum_foreign_comment":"","sum_foreign":"","sum":""}},"declaration":{"notfull_lostpages":"","date":"2015-03-23T00:00:00","notfull":"","url":"http://static.declarations.com.ua/declarations/chosen_ones/judges_batch/3013_mironova_halyna_mykhailivna.pdf"},"intro":{"declaration_year":"2014"}}