{"income":{"5":{"family_comment":"","value":"267213","family":"33845","comment":""},"6":{"value":"253815","comment_hidden":false,"family_comment":"","family":"31984","comment":"","family_comment_hidden":false},"7":{"value":"","comment_unclear":false,"family_comment":"","source_name":"","family":"","comment":""},"8":{"family_comment":"","value":"","family":"","comment":""},"9":{"family_comment":"","value":"","family":"","comment":""},"10":{"family_comment":"","value":"13398","family_hidden":false,"comment":"","family":"1861"},"11":{"family_comment":"","value":"","family":"","comment":""},"12":{"family_comment":"","value":"","family":"","comment":""},"13":{"family_comment":"","value":"","family":"","comment":""},"14":{"family_comment":"","value":"","family":"","comment":""},"15":{"family_comment":"","value":"","family":"","comment":""},"16":{"family_comment":"","value":"","family":"","comment":""},"17":{"family_comment":"","value":"","family":"","comment":""},"18":{"family_comment":"","value":"","family":"","comment":""},"19":{"family_comment":"","value":"","family":"","comment":""},"20":{"value":"","value_unclear":false,"family_hidden":false,"family_comment":"","family":"","comment":""}},"id":"vulyk_83_31","declaration":{"additional_info_text":"","notfull_lostpages":"","date":"2015-03-26T00:00:00","notfull":"","additional_info":"","url":"http://static.declarations.com.ua/declarations/chosen_ones/judges_batch/2301_murashko_serhii_ivanovych.pdf"},"liabilities":{"54":{"sum_foreign_comment":"","sum":"","sum_comment":"","sum_foreign":""},"55":{"sum_foreign_comment":"","sum":"","sum_comment":"","sum_foreign":""},"56":{"sum_foreign_comment":"","sum":"","sum_comment":"","sum_foreign":""},"57":{"sum_foreign_comment":"","sum":"","sum_comment":"","sum_foreign":""},"58":{"sum_foreign_comment":"","sum":"","sum_comment":"","sum_foreign":""},"59":{"sum_foreign_comment":"","sum":"","sum_comment":"","sum_foreign":""},"60":{"sum_foreign_comment":"","sum":"","sum_comment":"","sum_foreign":""},"61":{"sum_foreign_comment":"","sum":"","sum_comment":"","sum_foreign":""},"62":{"sum_foreign_comment":"","sum":"","sum_comment":"","sum_foreign":""},"63":{"sum_foreign_comment":"","sum":"","sum_comment":"","sum_foreign":""},"64":{"sum_foreign_comment":"","sum":"","sum_comment":"","sum_foreign":""}},"ft_src":"суддя апеляційного суду кіровоградської області\nКіровоградська область\nЗагальний апеляційний суд\nСергій\nМурашко Н. А\nПодружжя\nІванович\nМурашко Сергій Іванович\nСергій Іванович Мурашко\nСергій Мурашко\nМурашко Сергій Іванович\nМурашко Сергій Іванович\nМурашко\n1861\n13398\n33845\n267213\n253815\n31984\n1000\n53.1\n2014\n31984\n253815\n1861\n13398\n33845\n267213\n1000\n53.1\nПодружжя\nМурашко Н. А\nМурашко Сергій Іванович\nСергій Іванович Мурашко\nСергій Мурашко\nМурашко Сергій Іванович\nМурашко Сергій Іванович\nСергій\nІванович\nЗагальний апеляційний суд\nКіровоградська область\nсуддя апеляційного суду кіровоградської області\nМурашко\n253815\n31984\n267213\n33845\n13398\n1861\n2014\nМурашко Н. А\nПодружжя\nІванович\nМурашко\nСергій\nМурашко Сергій Іванович\nСергій Іванович Мурашко\nСергій Мурашко\nМурашко Сергій Іванович\nКіровоградська область\nЗагальний апеляційний суд\nсуддя апеляційного суду кіровоградської області\nМурашко Сергій Іванович\n53.1\n1000\n2014","general":{"inn":"","name":"Сергій","inn_unclear":false,"family":[{"inn":"","inn_hidden":true,"relations_hidden":false,"family_name":"Мурашко Н. А","relations_other":"","relations":"Подружжя","name_hidden":true,"name_unclear":false}],"inn_hidden":true,"family_raw":"","last_name":"Мурашко","post":{"post_unclear":false,"post":"суддя апеляційного суду кіровоградської області","candidate":"","region":"Кіровоградська область","office":"Загальний апеляційний суд","office_unclear":false},"full_name_suggest":{"output":"Мурашко Сергій Іванович","input":["Мурашко Сергій Іванович","Сергій Іванович Мурашко","Сергій Мурашко"]},"full_name":"Мурашко Сергій Іванович","addresses":[{"place_city_type_unclear":false,"place_address":"","place_district_hidden":true,"place_city_type":"","place_address_hidden":true,"place_address_unclear":false,"place_city_type_hidden":true,"place":"","place_district":"","place_city_hidden":true,"place_city":"","place_city_unclear":false,"place_hidden":true}],"patronymic":"Іванович","last_name_unclear":false},"source":"VULYK","estate":{"25":[{"region_unclear":false,"space_hidden":false,"costs":"","costs_comment":"","address_hidden":false,"region_hidden":true,"space_comment":"","space_unclear":false,"space":"53.1","address":"","region":"","costs_rent_comment":"","space_comment_unclear":false,"space_units":"м²","costs_rent":""}],"29":[{"address_hidden":false,"region_hidden":true,"space_comment":"","space":"1000","address":"","region":"","costs_property":"","costs_rent_comment":"","space_comment_unclear":false,"space_units":"м²","costs_property_comment":"","costs_rent":""}]},"intro":{"declaration_year":"2014"}}