{"income":{"5":{"value":"185963.36","family_comment":"","value_unclear":false,"family_unclear":false,"family":"","comment":""},"6":{"value":"185965.36","family_comment":"","value_unclear":false,"family_unclear":false,"family":"","comment":""},"7":{"family_comment":"","value":"","source_name":"","family":"","comment":""},"8":{"family_comment":"","value":"","family":"","comment":""},"9":{"family_comment":"","value":"","family":"","comment":""},"10":{"family_comment":"","value":"","family":"","comment":""},"11":{"family_comment":"","value":"","family":"","comment":""},"12":{"family_comment":"","value":"","family":"","comment":""},"13":{"family_comment":"","value":"","family":"","comment":""},"14":{"family_comment":"","value":"","family":"","comment":""},"15":{"family_comment":"","value":"","value_unclear":false,"family":"","comment":""},"16":{"family_comment":"","value":"","family":"","comment":""},"17":{"family_comment":"","value":"","family":"","comment":""},"18":{"family_comment":"","value":"","family":"","comment":""},"19":{"family_comment":"","value":"","family":"","comment":""},"20":{"value":"","family_comment":"","value_unclear":false,"family_unclear":false,"family":"","comment":"","family_comment_unclear":false}},"vehicle":{"35":[{"brand_info":"","sum_rent_comment":"","brand":"Mitsubishi Pajero Sport","sum_comment":"","brand_unclear":false,"year":"2011","brand_info_unclear":false,"sum":"","sum_rent":""}]},"id":"vulyk_99_6","declaration":{"date":"2016-03-23T00:00:00","notfull":"","url":"http://static.declarations.com.ua/declarations/chosen_ones/judges_batch/555_berezka_oleksandr_mykolaiovych_2015.pdf","notfull_lostpages":""},"liabilities":{"54":{"sum_foreign_comment":"","sum":"","sum_comment":"","sum_comment_unclear":false,"sum_comment_hidden":false,"sum_foreign":""},"55":{"sum_foreign_comment":"","sum":"","sum_comment":"","sum_foreign":""},"56":{"sum_foreign_comment":"","sum":"","sum_comment":"","sum_foreign":""},"57":{"sum_foreign_comment":"","sum_comment_hidden":false,"sum":"","sum_comment":"","sum_foreign":""},"58":{"sum_foreign_comment":"","sum_comment_hidden":false,"sum":"","sum_comment":"","sum_foreign":""},"59":{"sum_foreign_comment":"","sum":"","sum_comment":"","sum_comment_hidden":false,"sum_unclear":false,"sum_foreign":""},"60":{"sum_foreign_comment":"","sum_comment_hidden":false,"sum":"","sum_comment":"","sum_foreign":""},"61":{"sum_foreign_comment":"","sum":"","sum_comment":"","sum_foreign":""},"62":{"sum_foreign_comment":"","sum":"","sum_comment":"","sum_foreign":""},"63":{"sum_foreign_comment":"","sum_comment_hidden":false,"sum":"","sum_comment":"","sum_foreign":""},"64":{"sum_foreign_comment":"","sum_comment_hidden":false,"sum":"","sum_comment":"","sum_foreign":""}},"ft_src":"Березка Олександр Миколайович\nсуддя старобільського районного суду луганської області\nЛуганська область\nЗагальний місцевий суд\nОлександр\nБерезка Олександр Миколайович\nОлександр Миколайович Березка\nОлександр Березка\nБерезка Олександр Миколайович\nБерезка\nМиколайович\n2011\nMitsubishi Pajero Sport\n45.7\n63.3\n2015\n185965.36\n185963.36\nMitsubishi Pajero Sport\n2011\n2015\nБерезка\nБерезка Олександр Миколайович\nОлександр Миколайович Березка\nОлександр Березка\nБерезка Олександр Миколайович\nОлександр\nМиколайович\nБерезка Олександр Миколайович\nЗагальний місцевий суд\nсуддя старобільського районного суду луганської області\nЛуганська область\n185965.36\n185963.36\n45.7\n63.3\nБерезка\nМиколайович\nсуддя старобільського районного суду луганської області\nЛуганська область\nЗагальний місцевий суд\nБерезка Олександр Миколайович\nБерезка Олександр Миколайович\nОлександр Миколайович Березка\nОлександр Березка\nБерезка Олександр Миколайович\nОлександр\n2011\nMitsubishi Pajero Sport\n185963.36\n185965.36\n45.7\n63.3\n2015","general":{"inn":"","inn_hidden":true,"last_name":"Березка","post":{"post_unclear":false,"office":"Загальний місцевий суд","post":"суддя старобільського районного суду луганської області","region":"Луганська область"},"name":"Олександр","full_name":"Березка Олександр Миколайович","family_raw":"","addresses":[{"place_district":"","place_city_hidden":true,"place_city":"","place_city_type_hidden":false,"place_district_hidden":false,"place_city_type":"","place_address_hidden":true,"place_address":"","place_hidden":true,"place":""}],"full_name_suggest":{"output":"Березка Олександр Миколайович","input":["Березка Олександр Миколайович","Олександр Миколайович Березка","Олександр Березка"]},"patronymic":"Миколайович"},"source":"VULYK","estate":{"25":[{"space_hidden":false,"costs":"","costs_comment":"","address_hidden":false,"region_hidden":true,"space_comment":"","space_unclear":false,"space":"45.7","address":"","region":"","costs_rent_comment":"","space_units":"м²","costs_rent":""},{"costs_rent":"","region":"","costs":"","costs_rent_comment":"","costs_comment":"","address_hidden":false,"space_comment":"","space_units":"м²","space":"63.3","address":""}]},"intro":{"declaration_year":"2015"}}