{"income":{"5":{"value":"233055","value_unclear":false,"family_hidden":false,"family_comment":"","family":"11988","comment":""},"6":{"family_comment":"","value":"233055","value_unclear":false,"family":"","comment":""},"7":{"source_name_unclear":false,"value":"","family_comment":"","source_name":"","family":"","comment":"","source_name_hidden":false},"8":{"family_comment":"","value":"","family":"","comment":""},"9":{"family_comment":"","value":"","comment_unclear":false,"family":"","comment":""},"10":{"family_comment":"","value":"","family":"","comment":""},"11":{"family_comment":"","family_unclear":false,"value":"","family":"","comment":""},"12":{"family_comment":"","value":"","family":"","comment":""},"13":{"family_comment":"","value":"","family":"","comment":""},"14":{"family_comment":"","value":"","family":"","comment":""},"15":{"family_comment":"","value":"","family":"","comment":""},"16":{"family_comment":"","value":"","family":"","comment":""},"17":{"family_comment":"","value":"","family":"","comment":""},"18":{"family_comment":"","value":"","family":"","comment":""},"19":{"family_comment":"","value":"","family":"","comment":""},"20":{"value":"","value_unclear":false,"family_comment":"пенсія","comment_unclear":false,"comment":"","family":"11988"}},"id":"vulyk_94_165","banks":{"45":[{"sum_foreign_comment":"","sum_unclear":false,"sum_units":"UAH","sum_comment":"","sum_hidden":false,"sum_foreign_units":"UAH","sum_units_unclear":false,"sum_comment_hidden":false,"sum_units_hidden":false,"sum":"512","sum_foreign":""}],"51":[{"sum_foreign_comment":"","sum_units":"UAH","sum_comment":"","sum_hidden":false,"sum_foreign_units":"UAH","sum_comment_hidden":false,"sum_unclear":false,"sum":"1277","sum_foreign":""}]},"declaration":{"additional_info_text":"","notfull_lostpages":"","date":"2015-03-23T00:00:00","notfull":"","additional_info":"","url":"http://static.declarations.com.ua/declarations/chosen_ones/judges_batch/3811_skliarenko_valentyna_mykolaivna.pdf"},"liabilities":{"54":{"sum_foreign_comment":"","sum":"","sum_comment":"","sum_comment_unclear":false,"sum_comment_hidden":false,"sum_unclear":false,"sum_foreign":""},"55":{"sum_foreign_comment":"","sum":"","sum_comment":"","sum_foreign":""},"56":{"sum_foreign_comment":"","sum":"","sum_comment":"","sum_unclear":false,"sum_foreign":""},"57":{"sum_foreign_comment":"","sum":"","sum_comment":"","sum_hidden":false,"sum_unclear":false,"sum_foreign":""},"58":{"sum_foreign_comment":"","sum":"","sum_comment":"","sum_hidden":false,"sum_unclear":false,"sum_foreign":""},"59":{"sum_foreign_comment":"","sum":"","sum_comment":"","sum_foreign":""},"60":{"sum_foreign_comment":"","sum_comment_hidden":false,"sum":"","sum_comment":"","sum_foreign":""},"61":{"sum_foreign_comment":"","sum":"","sum_comment":"","sum_foreign":""},"62":{"sum_foreign_comment":"","sum":"","sum_hidden":false,"sum_comment":"","sum_foreign":""},"63":{"sum_foreign_comment":"","sum_comment_hidden":false,"sum":"","sum_comment":"","sum_foreign":""},"64":{"sum_foreign_comment":"","sum":"","sum_comment":"","sum_unclear":false,"sum_foreign":""}},"ft_src":"Білозір'я\nСело\nЧеркаська область\nЧеркаський\nсуддя придніпровського районного суду м. черкаси\nЧеркаська область\nЗагальний місцевий суд\nВалентина\nСкляренко Марія Петрівна\nБатьки\nМиколаївна\nСкляренко Валентина Миколаївна\nВалентина Миколаївна Скляренко\nВалентина Скляренко\nСкляренко Валентина Миколаївна\nСкляренко Валентина Миколаївна\nСкляренко\nпенсія\n11988\n233055\n11988\n233055\n1277\n512\nЧеркаський р-н, с. Белозір'я\n.15\nЧеркаська область\nЧеркаська область\nЧеркаський р-н, с. Белозір'я\n110.4\nЧеркаська область\nЧеркаський р-н, с. Белозір'я\n.318\n88.4\nм. Черкаси\nЧеркаська область\n2014\n233055\n11988\n233055\nпенсія\n11988\n512\n1277\n2014\nСкляренко Валентина Миколаївна\nВалентина Миколаївна Скляренко\nВалентина Скляренко\nСкляренко Валентина Миколаївна\nСкляренко Валентина Миколаївна\nБатьки\nСкляренко Марія Петрівна\nВалентина\nСкляренко\nЗагальний місцевий суд\nЧеркаська область\nсуддя придніпровського районного суду м. черкаси\nМиколаївна\nЧеркаська область\nСело\nЧеркаський\nБілозір'я\n233055\nпенсія\n11988\n233055\n11988\n.15\nЧеркаська область\nЧеркаський р-н, с. Белозір'я\n.318\nЧеркаська область\nЧеркаський р-н, с. Белозір'я\nЧеркаський р-н, с. Белозір'я\nЧеркаська область\n110.4\n88.4\nЧеркаська область\nм. Черкаси\nСкляренко Марія Петрівна\nБатьки\nМиколаївна\nСкляренко\nВалентина\nСкляренко Валентина Миколаївна\nВалентина Миколаївна Скляренко\nВалентина Скляренко\nСкляренко Валентина Миколаївна\nСело\nБілозір'я\nЧеркаська область\nЧеркаський\nЧеркаська область\nЗагальний місцевий суд\nсуддя придніпровського районного суду м. черкаси\nСкляренко Валентина Миколаївна\nЧеркаський р-н, с. Белозір'я\nЧеркаська область\n110.4\nЧеркаський р-н, с. Белозір'я\nЧеркаська область\n.15\nм. Черкаси\nЧеркаська область\n88.4\nЧеркаський р-н, с. Белозір'я\nЧеркаська область\n.318\n512\n1277\n2014","general":{"inn":"","name":"Валентина","last_name":"Скляренко","family":[{"inn":"","relations":"Батьки","relations_hidden":false,"inn_hidden":true,"family_name":"Скляренко Марія Петрівна","name_hidden":true,"name_unclear":false}],"inn_hidden":true,"family_raw":"","inn_unclear":false,"post":{"post_unclear":false,"region_unclear":false,"post":"суддя придніпровського районного суду м. черкаси","candidate":"","post_hidden":false,"region":"Черкаська область","office":"Загальний місцевий суд","office_unclear":false},"full_name":"Скляренко Валентина Миколаївна","addresses":[{"place_district":"Черкаський","place_city_hidden":false,"place_city":"Білозір'я","place_city_type_hidden":false,"place_district_hidden":false,"place_city_type":"Село","place_address_hidden":true,"place_address":"","place_hidden":false,"place":"Черкаська область"}],"patronymic":"Миколаївна","patronymic_hidden":false,"full_name_suggest":{"output":"Скляренко Валентина Миколаївна","input":["Скляренко Валентина Миколаївна","Валентина Миколаївна Скляренко","Валентина Скляренко"]}},"source":"VULYK","estate":{"23":[{"region_unclear":false,"space_unclear":false,"costs":"","costs_comment":"","address_hidden":false,"region_hidden":false,"space_comment":"","space_hidden":false,"space":".15","address":"Черкаський р-н, с. Белозір'я","region":"Черкаська область","address_unclear":false,"space_units_unclear":false,"costs_rent_hidden":false,"costs_rent_comment_hidden":false,"space_units":"га","costs_rent":"","costs_rent_comment":""}],"25":[{"region_unclear":false,"space_unclear":false,"costs":"","costs_comment":"","address_hidden":true,"region_hidden":false,"space_comment":"","space_hidden":false,"space":"88.4","address":"м. Черкаси","region":"Черкаська область","address_unclear":false,"costs_rent_comment":"","costs_rent_hidden":false,"space_comment_unclear":false,"costs_rent_comment_hidden":false,"space_units":"м²","costs_rent":""}],"29":[{"costs_rent":"","region":"Черкаська область","costs_property":"","costs_rent_comment":"","address_hidden":false,"region_hidden":false,"space_comment":"","costs_property_comment":"","space_units":"га","space":".318","address":"Черкаський р-н, с. Белозір'я"}],"30":[{"space_hidden":false,"address_hidden":false,"region_hidden":false,"space_comment":"","space":"110.4","address":"Черкаський р-н, с. Белозір'я","region":"Черкаська область","costs_property":"","costs_rent_comment":"","space_units":"м²","costs_property_comment":"","costs_rent":""}]},"intro":{"declaration_year":"2014","isnotdeclaration":""}}