{"id":"vulyk_103_42","ft_src":"причіп легковий\n10000\n2014\nЛев 183121\nToyota Prado 150\n525000\n3956 куб. см.\n2013\n61.3\n1500\n231.7\n500\n600\n4365\n80.6\n2015\n263377\n105100\n263377\n105100\n3956 куб. см.\n2013\n525000\nToyota Prado 150\nпричіп легковий\n2014\n10000\nЛев 183121\n500\n600\n4365\n1500\n231.7\n61.3\n80.6\nМаляренко\nМаляренко Артем Васильович\nАртем Васильович Маляренко\nАртем Маляренко\nМаляренко Артем Васильович\nМаляренко Артем Васильович\nВасильович\nПодружжя\nМаляренко С. М\nМаляренко Ф. А\nДитина\nДитина\nМаляренко С. А\nАртем\nВищий спеціалізований суд з розгляду цивільних і кримінальних справ\nсуддя вищого спецiалiзованого суду україни з розгляду цивiльних і кримiнальних справ\nЗагальнодержавний регіон\n263377\n105100\n263377\n105100\n2015\nПодружжя\nМаляренко С. М\nДитина\nМаляренко Ф. А\nДитина\nМаляренко С. А\nМаляренко\nВасильович\nсуддя вищого спецiалiзованого суду україни з розгляду цивiльних і кримiнальних справ\nВищий спеціалізований суд з розгляду цивільних і кримінальних справ\nЗагальнодержавний регіон\nМаляренко Артем Васильович\nМаляренко Артем Васильович\nАртем Васильович Маляренко\nАртем Маляренко\nМаляренко Артем Васильович\nАртем","estate":{"23":[{"costs":"","address":"","space_units":"м²","costs_rent_comment":"","space":"500","space_comment":"","region_hidden":true,"costs_comment":"","region":"","address_hidden":false,"costs_rent":""},{"space":"600","address":"","space_units":"м²","costs_rent_comment":"","costs":"","costs_comment":"","region_hidden":false,"space_comment":"","region":"","space_comment_unclear":false,"costs_rent":""},{"costs":"","address":"","space_units":"м²","costs_rent_comment":"","space":"4365","space_comment":"","costs_comment":"","region":"","costs_rent":""}],"25":[{"address":"","space_units":"м²","costs_comment":"","region_hidden":true,"space_comment":"","address_hidden":false,"space_comment_hidden":false,"space":"80.6","space_comment_unclear":false,"costs_rent_comment":"","costs":"","region":"","costs_rent":""}],"26":[{"costs":"","address":"","space_units":"м²","costs_rent_comment":"","space":"231.7","space_comment":"","region_hidden":true,"costs_comment":"","region":"","address_hidden":false,"costs_rent":""}],"29":[{"costs_property_comment":"","address":"","space_units":"м²","space_hidden":false,"space_comment":"","region_hidden":true,"costs_property":"","region":"","address_hidden":true,"costs_rent_comment":"","space":"1500","costs_rent":""}],"31":[{"costs_property_comment":"","address":"","space_units":"м²","space_hidden":false,"region_hidden":true,"costs_property":"","space_comment":"","address_hidden":true,"address_unclear":false,"costs_rent_comment":"","space":"61.3","costs_rent":""}]},"vehicle":{"35":[{"sum_comment":"","brand_info_hidden":false,"brand_info":"3956 куб. см.","sum":"525000","brand_unclear":false,"brand_hidden":false,"brand":"Toyota Prado 150","sum_rent":"","brand_info_unclear":false,"sum_rent_comment":"","year":"2013"}],"39":[{"sum_comment":"","brand_info_hidden":false,"brand_info":"причіп легковий","sum":"10000","sum_rent_comment":"","year":"2014","brand":"Лев 183121","sum_rent":""}]},"source":"VULYK","income":{"5":{"family_comment":"","family":"105100","comment":"","value_unclear":false,"family_hidden":false,"value":"263377"},"6":{"family_comment":"","value":"263377","family":"","comment":""},"7":{"family":"","family_comment":"","value":"","comment":"","source_name":""},"8":{"family_comment":"","value":"","family":"","comment":""},"9":{"family_comment":"","value":"","family":"","comment":""},"10":{"family_comment":"","value":"","family":"","comment":""},"11":{"family_comment":"","family_hidden":false,"value":"","family":"","comment":""},"12":{"family_comment":"","value":"","family":"","comment":""},"13":{"family_comment":"","value":"","family":"","comment":""},"14":{"family_comment":"","value":"","family":"","comment":""},"15":{"family_comment":"","value":"","family":"","comment":""},"16":{"family_comment":"","value":"","family":"","comment":""},"17":{"family_comment":"","value":"","family":"105100","comment":"","family_comment_unclear":false},"18":{"family_comment":"","value":"","family":"","comment":""},"19":{"family_comment":"","value":"","family":"","comment":""},"20":{"family_comment":"","family":"","comment":"","family_unclear":false,"family_hidden":false,"value":""}},"general":{"inn":"","addresses":[{"place_city_type_hidden":false,"place_city_type":"","place_city_hidden":true,"place_hidden":true,"place_district":"","place_district_hidden":false,"place":"","place_city":"","place_address_hidden":true,"place_address":""}],"last_name":"Маляренко","full_name":"Маляренко Артем Васильович","family":[{"inn":"","family_name":"Маляренко С. М","relations_hidden":false,"name_unclear":false,"relations":"Подружжя","inn_hidden":true,"name_hidden":true,"relations_other":""},{"inn":"","family_name":"Маляренко Ф. А","inn_hidden":true,"relations_other":"","relations":"Дитина"},{"inn":"","family_name":"Маляренко С. А","relations_other":"","name_unclear":false,"inn_hidden":true,"relations":"Дитина"}],"patronymic":"Васильович","inn_hidden":true,"name":"Артем","post":{"office":"Вищий спеціалізований суд з розгляду цивільних і кримінальних справ","region_unclear":false,"post":"суддя вищого спецiалiзованого суду україни з розгляду цивiльних і кримiнальних справ","region":"Загальнодержавний регіон","office_unclear":false},"family_raw":"","full_name_suggest":{"input":["Маляренко Артем Васильович","Артем Васильович Маляренко","Артем Маляренко"],"output":"Маляренко Артем Васильович"}},"liabilities":{"54":{"sum_foreign_comment_hidden":false,"sum_foreign_comment_unclear":false,"sum_hidden":false,"sum":"","sum_foreign_comment":"","sum_comment":"","sum_unclear":false,"sum_foreign":"","sum_comment_hidden":false,"sum_foreign_hidden":false},"55":{"sum_comment":"","sum_foreign_comment":"","sum_foreign":"","sum":""},"56":{"sum_comment":"","sum_foreign_comment":"","sum_foreign":"","sum":""},"57":{"sum_comment":"","sum_hidden":false,"sum":"","sum_foreign_comment":"","sum_foreign":"","sum_comment_hidden":false,"sum_foreign_hidden":false,"sum_foreign_comment_hidden":false},"58":{"sum_comment":"","sum_hidden":false,"sum":"","sum_foreign_comment":"","sum_foreign":"","sum_comment_hidden":false,"sum_foreign_hidden":false,"sum_foreign_comment_hidden":false},"59":{"sum_comment":"","sum_hidden":false,"sum":"","sum_foreign_comment":"","sum_foreign":"","sum_comment_hidden":false,"sum_foreign_hidden":false,"sum_foreign_comment_hidden":false},"60":{"sum_comment":"","sum_hidden":false,"sum":"","sum_foreign_comment":"","sum_foreign":"","sum_comment_hidden":false},"61":{"sum_comment":"","sum_foreign_comment":"","sum_foreign":"","sum":""},"62":{"sum_comment":"","sum_foreign_comment":"","sum_foreign":"","sum":"","sum_comment_hidden":false},"63":{"sum_comment":"","sum_foreign_comment":"","sum_foreign":"","sum":""},"64":{"sum_comment":"","sum_foreign_comment":"","sum_foreign":"","sum":""}},"declaration":{"additional_info_text":"","additional_info":"","date":"2016-03-31T00:00:00","url":"http://static.declarations.com.ua/declarations/chosen_ones/judges_batch/1266_maliarenko_artem_vasylovych.pdf"},"intro":{"declaration_year":"2015"}}