{"income":{"5":{"value":"219280.04","family_comment":"","value_unclear":false,"family_hidden":false,"value_hidden":false,"family_unclear":false,"family":"38407.82","comment":"","family_comment_unclear":false},"6":{"value":"219280.04","family_comment":"","value_unclear":false,"comment_hidden":false,"family_hidden":false,"value_hidden":false,"family_unclear":false,"family":"38407.82","comment":""},"7":{"value":"","value_hidden":false,"family_comment":"","source_name":"","family":"","comment":"","source_name_hidden":false},"8":{"family_comment":"","value":"","family":"","comment":""},"9":{"value":"","comment_hidden":false,"value_hidden":false,"family_comment":"","family":"","comment":""},"10":{"value":"","value_unclear":false,"value_hidden":false,"family_comment":"","family":"","comment":""},"11":{"family_comment":"","value":"","family":"","comment":""},"12":{"family_comment":"","value":"","family":"","comment":""},"13":{"family_comment":"","value":"","family_hidden":false,"comment":"","family":""},"14":{"family_comment":"","value":"","family":"","comment":""},"15":{"family_comment":"","family_unclear":false,"value":"","family":"","comment":""},"16":{"family_comment":"","value":"","value_unclear":false,"family":"","comment":""},"17":{"family_comment":"","value":"","family":"","comment":""},"18":{"family_comment":"","value":"","family":"","comment":""},"19":{"family_comment":"","value":"","comment_unclear":false,"family":"","comment":""},"20":{"value":"","comment_unclear":false,"family_hidden":false,"value_hidden":false,"family_comment":"","family":"","comment":""}},"vehicle":{"35":[{"year_hidden":false,"brand_info":"2.2 куб. см.","sum_rent_comment":"","brand_info_unclear":false,"sum_rent_hidden":false,"year":"2012","sum_hidden":false,"brand_info_hidden":false,"sum_rent_comment_unclear":false,"year_unclear":false,"sum_rent":"","sum":"","brand":"Hyundai Santa FE","sum_comment":"","sum_comment_unclear":false,"brand_hidden":false,"sum_unclear":false,"brand_unclear":false}],"40":[{"year_hidden":false,"brand_info":"0.8 куб. см.","sum_rent_comment":"","year":"2007","brand_info_hidden":false,"brand_info_unclear":false,"sum_rent":"","sum":"","brand":"Daewoo Matiz","sum_comment":"","brand_unclear":false,"brand_hidden":false}]},"id":"vulyk_64_31","declaration":{"additional_info_text":"","notfull_lostpages":"","date":"2015-03-30T00:00:00","notfull":"","additional_info":"","url":"http://static.declarations.com.ua/declarations/chosen_ones/mega_batch/marulina_liubov_oleksandrivna.pdf"},"liabilities":{"54":{"sum_foreign_comment":"","sum":"","sum_comment":"","sum_foreign_comment_hidden":false,"sum_hidden":false,"sum_comment_hidden":false,"sum_unclear":false,"sum_foreign":""},"55":{"sum_foreign_comment":"","sum":"","sum_comment":"","sum_comment_unclear":false,"sum_foreign":""},"56":{"sum_foreign_comment":"","sum":"","sum_comment":"","sum_unclear":false,"sum_foreign":""},"57":{"sum_foreign_comment":"","sum":"","sum_comment":"","sum_hidden":false,"sum_unclear":false,"sum_foreign":""},"58":{"sum_foreign_comment":"","sum":"","sum_comment":"","sum_unclear":false,"sum_foreign":""},"59":{"sum_foreign_comment":"","sum":"","sum_comment":"","sum_comment_unclear":false,"sum_comment_hidden":false,"sum_unclear":false,"sum_foreign":""},"60":{"sum_foreign_comment":"","sum":"","sum_comment":"","sum_foreign":""},"61":{"sum_foreign_comment":"","sum":"","sum_comment":"","sum_foreign":""},"62":{"sum_foreign_comment":"","sum":"","sum_comment":"","sum_unclear":false,"sum_foreign":""},"63":{"sum_foreign_comment":"","sum":"","sum_comment":"","sum_unclear":false,"sum_foreign":""},"64":{"sum_foreign_comment":"","sum":"","sum_comment":"","sum_comment_unclear":false,"sum_unclear":false,"sum_foreign":""}},"ft_src":"суддя окружного адміністративного суду міста києва\nм. Київ\nАдміністративний місцевий суд\nЛюбов\nПодружжя\nОлександрівна\nМаруліна Любов Олександрівна\nМаруліна\nМаруліна Любов Олександрівна\nЛюбов Олександрівна Маруліна\nЛюбов Маруліна\nМаруліна Любов Олександрівна\n2.2 куб. см.\nHyundai Santa FE\n2012\n0.8 куб. см.\nDaewoo Matiz\n2007\n25\n39.4\n2014\n38407.82\n219280.04\n38407.82\n219280.04\n2.2 куб. см.\nHyundai Santa FE\n2012\n0.8 куб. см.\nDaewoo Matiz\n2007\n25\n39.4\nАдміністративний місцевий суд\nм. Київ\nсуддя окружного адміністративного суду міста києва\nПодружжя\nМаруліна Любов Олександрівна\nЛюбов Олександрівна Маруліна\nЛюбов Маруліна\nМаруліна Любов Олександрівна\nМаруліна Любов Олександрівна\nЛюбов\nМаруліна\nОлександрівна\n38407.82\n219280.04\n219280.04\n38407.82\n2014\nПодружжя\nОлександрівна\nМаруліна\nЛюбов\nМаруліна Любов Олександрівна\nЛюбов Олександрівна Маруліна\nЛюбов Маруліна\nМаруліна Любов Олександрівна\nм. Київ\nАдміністративний місцевий суд\nсуддя окружного адміністративного суду міста києва\nМаруліна Любов Олександрівна\nHyundai Santa FE\n2.2 куб. см.\n2012\n2007\nDaewoo Matiz\n0.8 куб. см.\n219280.04\n38407.82\n219280.04\n38407.82\n25\n39.4\n2014","general":{"inn":"","name":"Любов","last_name_hidden":false,"family":[{"inn":"","inn_hidden":true,"relations_unclear":false,"relations_hidden":false,"relations_other":"","relations":"Подружжя","name_hidden":true,"inn_unclear":false,"family_name":"","name_unclear":false}],"patronymic":"Олександрівна","inn_hidden":true,"family_raw":"","inn_unclear":false,"post":{"post_unclear":false,"post":"суддя окружного адміністративного суду міста києва","candidate":"","office_hidden":false,"region":"м. Київ","post_hidden":false,"office":"Адміністративний місцевий суд","office_unclear":false,"region_hidden":false},"last_name_unclear":false,"full_name":"Маруліна Любов Олександрівна","addresses":[{"place_city_type_unclear":false,"place_address":"","place_district_hidden":false,"place_city_type":"","place_city_hidden":false,"place_city_type_hidden":false,"place":"","place_district":"","place_unclear":false,"place_city":"","place_city_unclear":false,"place_hidden":true,"place_address_hidden":false}],"last_name":"Маруліна","patronymic_hidden":false,"full_name_suggest":{"output":"Маруліна Любов Олександрівна","input":["Маруліна Любов Олександрівна","Любов Олександрівна Маруліна","Любов Маруліна"]},"name_unclear":false},"source":"VULYK","estate":{"25":[{"region_unclear":false,"space_unclear":false,"costs":"","costs_rent_unclear":false,"costs_comment":"","costs_hidden":false,"address_hidden":false,"region_hidden":true,"space_comment":"","space_hidden":false,"space":"39.4","space_units_hidden":false,"costs_rent_comment_unclear":false,"region":"","costs_rent_comment":"","costs_rent_hidden":false,"space_comment_unclear":false,"space_units":"м²","address":"","costs_rent":"","costs_unclear":false}],"31":[{"region_unclear":false,"address_hidden":false,"region_hidden":true,"space_comment":"","space":"25","address":"","region":"","costs_property":"","costs_rent_comment":"","space_comment_hidden":false,"space_units":"м²","costs_property_comment":"","costs_rent":""}]},"intro":{"declaration_year":"2014","isnotdeclaration":"","declaration_year_unclear":false,"declaration_year_hidden":false}}