{"income":{"5":{"value":"241529","family_comment":"","value_unclear":true,"family_unclear":true,"family":"61110","comment":""},"6":{"family_comment":"","value":"232979","value_unclear":true,"family":"56434","comment":""},"7":{"family_comment":"","value":"","source_name":"","family":"","comment":""},"8":{"family_comment":"","value":"","family":"","comment":""},"9":{"family_comment":"","value":"","value_unclear":false,"family":"4676","comment":""},"10":{"family_comment":"","value":"","family":"","comment":""},"11":{"family_comment":"","value":"","family":"","comment":""},"12":{"family_comment":"","value":"","family":"","comment":""},"13":{"family_comment":"","value":"","family":"","comment":""},"14":{"family_comment":"","value":"8550","family":"","comment":""},"15":{"family_comment":"","value":"","family":"","comment":""},"16":{"family_comment":"","value":"","family":"","comment":""},"17":{"family_comment":"","value":"","family":"","comment":""},"18":{"family_comment":"","value":"","family":"","comment":""},"19":{"family_comment":"","value":"","family":"","comment":""},"20":{"family_comment":"","value":"","value_unclear":false,"family":"","comment":""}},"vehicle":{"35":[{"brand_info":"1558","sum_rent_comment":"","brand":"Chevrolet Lacetti","sum_comment":"","brand_unclear":false,"year":"2007","brand_info_unclear":false,"sum":"","sum_rent":""}]},"id":"vulyk_98_56","banks":{"51":[{"sum_foreign_comment":"","sum_units":"UAH","sum_comment":"","sum_hidden":false,"sum_foreign_units":"UAH","sum_comment_hidden":true,"sum_unclear":true,"sum":"61256","sum_foreign":""}]},"declaration":{"date":"2015-03-30T00:00:00","url":"http://static.declarations.com.ua/declarations/chosen_ones/judges_batch/4553_korsun_vitalii_leonidovych.pdf"},"liabilities":{"54":{"sum_foreign_comment":"","sum":"637","sum_comment":"","sum_comment_unclear":false,"sum_hidden":false,"sum_comment_hidden":true,"sum_unclear":true,"sum_foreign":""},"55":{"sum_foreign_comment":"","sum":"","sum_comment":"","sum_foreign":""},"56":{"sum_foreign_comment":"","sum":"","sum_comment":"","sum_unclear":false,"sum_foreign":""},"57":{"sum_foreign_comment":"","sum":"","sum_comment":"","sum_comment_unclear":false,"sum_hidden":false,"sum_comment_hidden":false,"sum_unclear":false,"sum_foreign":""},"58":{"sum_foreign_comment":"","sum":"","sum_comment":"","sum_hidden":false,"sum_comment_hidden":false,"sum_unclear":false,"sum_foreign":""},"59":{"sum_foreign_comment":"","sum":"","sum_comment":"","sum_comment_unclear":false,"sum_foreign":""},"60":{"sum_foreign_comment":"","sum":"","sum_comment":"","sum_hidden":false,"sum_comment_hidden":false,"sum_foreign":""},"61":{"sum_foreign_comment":"","sum":"","sum_comment":"","sum_foreign":""},"62":{"sum_foreign_comment":"","sum":"","sum_comment":"","sum_comment_hidden":false,"sum_unclear":false,"sum_foreign":""},"63":{"sum_foreign_comment":"","sum":"","sum_comment":"","sum_comment_unclear":false,"sum_comment_hidden":false,"sum_foreign":""},"64":{"sum_foreign_comment":"","sum_comment_hidden":false,"sum":"","sum_comment":"","sum_foreign":""}},"ft_src":"637\nсуддя господарського суду запорізької області\nЗапорізька область\nГосподарський місцевий суд\nВіталій\nКорсун Л. А. 18. 10. 67\nПодружжя\nЛеонідович\nКорсун Віталій Леонідович\nВіталій Леонідович Корсун\nВіталій Корсун\nКорсун Віталій Леонідович\nКорсун Віталій Леонідович\nКорсун\n2007\nChevrolet Lacetti\n1558\n26.995\n66.4\n1/2 від 38,4\n38.4\n26.995\n61256\n2014\n1558\n2007\nChevrolet Lacetti\n2014\nГосподарський місцевий суд\nсуддя господарського суду запорізької області\nЗапорізька область\nКорсун Віталій Леонідович\nВіталій Леонідович Корсун\nВіталій Корсун\nКорсун Віталій Леонідович\nКорсун Віталій Леонідович\nПодружжя\nКорсун Л. А. 18. 10. 67\nВіталій\nКорсун\nЛеонідович\n637\n232979\n56434\n8550\n61110\n241529\n4676\n38.4\n1/2 від 38,4\n26.995\n66.4\n26.995\n61256\n637\n56434\n232979\n8550\n4676\n61110\n241529\nПодружжя\nКорсун Л. А. 18. 10. 67\nЛеонідович\nКорсун\nВіталій\nКорсун Віталій Леонідович\nВіталій Леонідович Корсун\nВіталій Корсун\nКорсун Віталій Леонідович\nсуддя господарського суду запорізької області\nЗапорізька область\nГосподарський місцевий суд\nКорсун Віталій Леонідович\n2007\n1558\nChevrolet Lacetti\n4676\n8550\n241529\n61110\n56434\n232979\n26.995\n66.4\n26.995\n1/2 від 38,4\n38.4\n61256\n2014","general":{"inn":"","name":"Віталій","last_name_hidden":false,"family":[{"inn":"","relations":"Подружжя","relations_other":"","inn_hidden":true,"family_name":"Корсун Л. А. 18. 10. 67","name_hidden":false,"name_unclear":false}],"patronymic":"Леонідович","inn_hidden":true,"family_raw":"","inn_unclear":false,"post":{"post_unclear":false,"office":"Господарський місцевий суд","post":"суддя господарського суду запорізької області","region":"Запорізька область"},"full_name_suggest":{"output":"Корсун Віталій Леонідович","input":["Корсун Віталій Леонідович","Віталій Леонідович Корсун","Віталій Корсун"]},"full_name":"Корсун Віталій Леонідович","addresses":[{"place_district":"","place_city_hidden":true,"place_city":"","place_city_type_hidden":false,"place_district_hidden":false,"place_city_type":"","place_address_hidden":true,"place_address":"","place_hidden":true,"place":""}],"last_name":"Корсун","patronymic_hidden":false,"last_name_unclear":false},"source":"VULYK","estate":{"24":[{"costs_rent":"","region":"","costs":"","costs_rent_comment":"","costs_comment":"","address_hidden":false,"region_hidden":true,"space_comment":"1/2 від 38,4","space_units":"м²","space":"38.4","address":""}],"25":[{"space_unclear":false,"costs":"","costs_comment":"","address_hidden":false,"region_hidden":true,"space_comment":"","space":"26.995","address":"","region":"","address_unclear":false,"costs_rent_comment":"","space_units":"м²","costs_rent":""}],"31":[{"region_unclear":false,"address_hidden":false,"region_hidden":true,"space_comment":"","space":"26.995","address":"","region":"","costs_property":"","costs_rent_comment":"","space_units":"м²","costs_property_comment":"","costs_rent":""},{"costs_rent":"","region":"","costs_property":"","costs_rent_comment":"","space_comment":"","costs_property_comment":"","space_units":"м²","space":"66.4","address":""}]},"intro":{"declaration_year":"2014"}}