{"income":{"5":{"value":"237198.17","family_comment":"","family_hidden":false,"value_hidden":false,"family_unclear":false,"family":"","comment":""},"6":{"value":"212868.17","comment_unclear":false,"family_comment":"","family":"","comment":"","family_comment_unclear":false},"7":{"family_comment":"","value":"","source_name":"","family":"","comment":""},"8":{"family_comment":"","value":"","family":"","comment":""},"9":{"family_comment":"","value":"","family":"","comment":""},"10":{"family_comment":"","value":"12180","family":"","comment":""},"11":{"family_comment":"","value":"","family":"","comment":"","family_comment_unclear":false},"12":{"family_comment":"","value":"","family":"","comment":""},"13":{"family_comment":"","value":"","family":"","comment":""},"14":{"family_comment":"","value":"","family":"","comment":""},"15":{"family_comment":"","value":"","family":"","comment":""},"16":{"family_comment":"","value":"","family":"","comment":""},"17":{"family_comment":"","value":"","family":"","comment":""},"18":{"family_comment":"","value":"","family":"","comment":""},"19":{"family_comment":"","value":"","family":"","comment":"","value_hidden":false},"20":{"family_comment":"","value":"12150","comment_unclear":false,"family":"","comment":"щомісячна одноразова допомога при народженні дитини"}},"vehicle":{"40":[{"brand_info":"обєм 2.4","sum_rent_comment":"","brand":"Suzuki Grand Vitara","sum_comment":"","year":"2008","brand_info_unclear":false,"sum":"","sum_rent":""}]},"id":"vulyk_51_181","banks":{"45":[{"sum_foreign_comment":"","sum_units":"UAH","sum_comment":"","sum_comment_unclear":false,"sum_hidden":false,"sum_foreign_units":"UAH","sum_comment_hidden":false,"sum":"","sum_foreign":""},{"sum_foreign_comment":"","sum":"","sum_comment":"","sum_foreign_units":"","sum_units":"","sum_foreign":""},{"sum_foreign_comment":"","sum":"","sum_comment":"","sum_foreign_units":"","sum_units":"","sum_foreign":""},{"sum_foreign_comment":"","sum":"","sum_comment":"","sum_foreign_units":"","sum_units":"","sum_foreign":""},{"sum_foreign_comment":"","sum_unclear":false,"sum":"","sum_comment":"","sum_foreign_units":"","sum_units":"","sum_foreign":""}],"46":[{"sum_foreign_comment":"","sum":"","sum_comment":"","sum_foreign_units":"UAH","sum_units":"UAH","sum_foreign":""}],"47":[{"sum_foreign_comment":"","sum":"","sum_comment":"","sum_foreign_units":"UAH","sum_units":"UAH","sum_foreign":""}],"48":[{"sum_foreign_comment":"","sum":"","sum_comment":"","sum_foreign_units":"UAH","sum_units":"UAH","sum_foreign":""}],"49":[{"sum_foreign_comment":"","sum":"","sum_comment":"","sum_foreign_units":"UAH","sum_units":"UAH","sum_foreign":""}],"50":[{"sum_foreign_comment":"","sum":"","sum_comment":"","sum_foreign_units":"UAH","sum_units":"UAH","sum_foreign":""}],"51":[{"sum_foreign_comment":"","sum":"","sum_comment":"","sum_foreign_units":"UAH","sum_comment_hidden":false,"sum_units":"UAH","sum_foreign":""},{"sum_foreign_comment":"","sum":"","sum_comment":"","sum_foreign_units":"","sum_units":"","sum_foreign":""},{"sum_foreign_comment":"","sum":"","sum_comment":"","sum_foreign_units":"","sum_units":"","sum_foreign":""}],"52":[{"sum_foreign_comment":"","sum":"","sum_comment":"","sum_foreign_units":"UAH","sum_comment_hidden":false,"sum_units":"UAH","sum_foreign":""}],"53":[{"sum_foreign_comment":"","sum":"","sum_comment":"","sum_foreign_units":"UAH","sum_units":"UAH","sum_foreign":""}]},"declaration":{"additional_info_text":"","notfull_lostpages":"","date":"2015-03-31T00:00:00","notfull":"","additional_info":"","url":"http://static.declarations.com.ua/declarations/chosen_ones/mega_batch/bondarchuk_v’yacheslav_volodymyrovych.pdf"},"liabilities":{"54":{"sum_foreign_comment":"","sum_comment":"","sum":"","sum_comment_hidden":false,"sum_foreign":""},"55":{"sum_foreign_comment":"","sum":"","sum_comment":"","sum_foreign":""},"56":{"sum_foreign_comment":"","sum":"","sum_comment":"","sum_foreign":""},"57":{"sum_foreign_comment":"","sum":"10509.35","sum_comment":"","sum_hidden":false,"sum_comment_hidden":false,"sum_foreign":""},"58":{"sum_foreign_comment":"","sum_comment":"","sum":"1907.38","sum_comment_hidden":false,"sum_foreign":""},"59":{"sum_foreign_comment":"","sum":"","sum_comment":"","sum_foreign":""},"60":{"sum_foreign_comment":"","sum":"","sum_comment":"","sum_foreign":""},"61":{"sum_foreign_comment":"","sum":"","sum_comment":"","sum_foreign":""},"62":{"sum_foreign_comment":"","sum":"","sum_comment":"","sum_foreign":""},"63":{"sum_foreign_comment":"","sum_comment":"","sum":"","sum_comment_hidden":false,"sum_foreign":""},"64":{"sum_foreign_comment":"","sum":"","sum_comment":"","sum_foreign":""}},"ft_src":"обєм 2.4\n2008\nSuzuki Grand Vitara\n2014\nобєм 2.4\nSuzuki Grand Vitara\n2008\n.15\nЖитомирська область\nЖитомирський р-н\nдоговір 4. 01. 1998\nЖитомирська область\nм. Житомир\n60.8\nБондарчук\nБондарчук В'ячеслав Володимирович\nВ'ячеслав Володимирович Бондарчук\nВ'ячеслав Бондарчук\nБондарчук В'ячеслав Володимирович\nВ'ячеслав\nВолодимирович\nЖитомирська область\nЖитомир\nБондарчук В'ячеслав Володимирович\nЗагальний місцевий суд\nсуддя корольовського районного суду м. житомира\nЖитомирська область\nПодружжя\nБондарчук Н. В., 30. 08. 1976 р. н\nДитина\nБондарчук Б. В., 29. 11. 1999 р. н\nДитина\nБондарчук С. В., 5. 07. 2013 р. н\n10509.35\n1907.38\n212868.17\nщомісячна одноразова допомога при народженні дитини\n12150\n237198.17\n12180\n2014\n1907.38\n10509.35\nЖитомирський р-н\nЖитомирська область\n.15\nдоговір 4. 01. 1998\nЖитомирська область\nм. Житомир\n60.8\nБондарчук Н. В., 30. 08. 1976 р. н\nПодружжя\nБондарчук Б. В., 29. 11. 1999 р. н\nДитина\nБондарчук С. В., 5. 07. 2013 р. н\nДитина\nВолодимирович\nЖитомирська область\nЖитомир\nБондарчук\nЖитомирська область\nЗагальний місцевий суд\nсуддя корольовського районного суду м. житомира\nБондарчук В'ячеслав Володимирович\nБондарчук В'ячеслав Володимирович\nВ'ячеслав Володимирович Бондарчук\nВ'ячеслав Бондарчук\nБондарчук В'ячеслав Володимирович\nВ'ячеслав\n212868.17\n12180\n237198.17\nщомісячна одноразова допомога при народженні дитини\n12150","general":{"inn":"","inn_hidden":true,"last_name":"Бондарчук","post":{"post":"суддя корольовського районного суду м. житомира","region":"Житомирська область","office_hidden":false,"office":"Загальний місцевий суд","office_unclear":false,"region_hidden":false},"name":"В'ячеслав","full_name":"Бондарчук В'ячеслав Володимирович","family_raw":"","addresses":[{"place_district":"","place_address_hidden":true,"place_city":"Житомир","place_address":"","place_district_hidden":false,"place_city_type":"Місто","place_city_hidden":false,"place_city_type_hidden":false,"place_hidden":false,"place":"Житомирська область"}],"family":[{"inn":"","inn_hidden":false,"family_name":"Бондарчук Н. В., 30. 08. 1976 р. н","relations_other":"","relations":"Подружжя","name_hidden":false,"name_unclear":false},{"inn":"","inn_hidden":false,"relations_hidden":false,"family_name":"Бондарчук Б. В., 29. 11. 1999 р. н","relations_other":"","relations":"Дитина","name_hidden":false,"name_unclear":false},{"inn":"","inn_hidden":false,"family_name":"Бондарчук С. В., 5. 07. 2013 р. н","relations_other":"","relations":"Дитина","name_hidden":false,"name_unclear":false}],"full_name_suggest":{"output":"Бондарчук В'ячеслав Володимирович","input":["Бондарчук В'ячеслав Володимирович","В'ячеслав Володимирович Бондарчук","В'ячеслав Бондарчук"]},"patronymic":"Володимирович"},"source":"VULYK","estate":{"23":[{"costs":"","costs_comment":"","costs_hidden":false,"address_hidden":false,"region_hidden":false,"space_comment":"","space":"","address":"","region":"","address_unclear":false,"costs_rent_comment":"","costs_rent_hidden":false,"space_units":"м²","costs_rent":""},{"costs":"","costs_comment":"","costs_hidden":false,"region_hidden":false,"space_comment":"","space":"","address":"","region":"","costs_rent_comment":"","costs_rent_hidden":false,"space_units":"","costs_rent":""},{"costs_rent":"","region":"","costs":"","costs_rent_comment":"","costs_comment":"","address_unclear":false,"space_comment":"","space_units":"","space":"","address":""},{"costs_rent":"","region":"","costs":"","costs_rent_comment":"","costs_comment":"","space_comment":"","space_units":"","space":"","address":""}],"29":[{"address_hidden":false,"region_hidden":false,"space_comment":"","space":".15","address":"Житомирський р-н","region":"Житомирська область","costs_property":"","costs_rent_comment":"","address_unclear":false,"space_units":"га","costs_property_comment":"","costs_rent":""}],"31":[{"space_unclear":false,"costs_property_hidden":false,"address_hidden":false,"region_hidden":false,"space_comment":"договір 4. 01. 1998","space_hidden":false,"space":"60.8","address":"м. Житомир","region":"Житомирська область","costs_property":"","costs_rent_comment":"","costs_rent_hidden":false,"address_unclear":false,"space_units":"м²","costs_property_comment":"","costs_rent":""}]},"intro":{"declaration_year":"2014","isnotdeclaration":""}}