{"income":{"5":{"value":"244639","family_comment":"","value_unclear":false,"family_unclear":false,"comment_unclear":false,"comment":"","family":""},"6":{"family_comment":"","value":"232459","comment_unclear":false,"family":"","comment":""},"7":{"family_comment":"","value":"","source_name":"","family":"","comment":""},"8":{"family_comment":"","value":"","family":"","comment":""},"9":{"family_comment":"","value":"","value_unclear":false,"family":"","comment":""},"10":{"family_comment":"","value":"","value_unclear":false,"family":"","comment":""},"11":{"family_comment":"","value":"","family":"","comment":""},"12":{"family_comment":"","value":"","family":"","comment":""},"13":{"family_comment":"","value":"","family":"","comment":""},"14":{"family_comment":"","value":"","family":"","comment":""},"15":{"family_comment":"","value":"","family":"","comment":""},"16":{"family_comment":"","value":"","family":"","comment":""},"17":{"family_comment":"","value":"","value_unclear":false,"family":"","comment":""},"18":{"family_comment":"","value":"","value_unclear":false,"family":"","comment":""},"19":{"family_comment":"","value":"","family":"","comment":""},"20":{"value":"","family_comment":"","value_unclear":false,"family_unclear":false,"comment_unclear":false,"comment":"","family":""}},"vehicle":{"40":[{"brand_info":"1500 куб. см.","sum_rent_comment":"","brand":"ВАЗ 2109","sum_comment":"","brand_unclear":false,"year":"1992","brand_hidden":false,"brand_info_hidden":false,"year_unclear":false,"sum":"","sum_rent":""}]},"id":"vulyk_84_1","declaration":{"additional_info_text":"","notfull_lostpages":"","date":"2015-03-16T00:00:00","notfull":"","additional_info":"","url":"http://static.declarations.com.ua/declarations/chosen_ones/judges_batch/2415_hodovanets_ivan_alimovych.pdf"},"liabilities":{"54":{"sum_foreign_comment":"","sum_comment_hidden":false,"sum":"","sum_comment":"","sum_foreign":""},"55":{"sum_foreign_comment":"","sum":"","sum_comment":"","sum_foreign":""},"56":{"sum_foreign_comment":"","sum":"","sum_comment":"","sum_foreign":""},"57":{"sum_foreign_comment":"","sum_comment_hidden":false,"sum":"","sum_comment":"","sum_foreign":""},"58":{"sum_foreign_comment":"","sum_comment_hidden":false,"sum":"","sum_comment":"","sum_foreign":""},"59":{"sum_foreign_comment":"","sum":"","sum_comment":"","sum_foreign":""},"60":{"sum_foreign_comment":"","sum":"","sum_comment":"","sum_foreign":""},"61":{"sum_foreign_comment":"","sum":"","sum_comment":"","sum_foreign":""},"62":{"sum_foreign_comment":"","sum":"","sum_comment":"","sum_foreign":""},"63":{"sum_foreign_comment":"","sum_comment_hidden":false,"sum":"","sum_comment":"","sum_foreign":""},"64":{"sum_foreign_comment":"","sum_comment_hidden":false,"sum":"","sum_comment":"","sum_foreign":""}},"ft_src":"Устинівка\nКіровоградська область\nСМТ\nсуддя устинівського районного суду кіровоградської області\nКіровоградська область\nЗагальний місцевий суд\nІван\nГодованець С. В\nПодружжя\nГодованець О. І\nДитина\nГодованець Д. І\nДитина\nАлімович\nГодованець Іван Алімович\nІван Алімович Годованець\nІван Годованець\nГодованець Іван Алімович\nГодованець Іван Алімович\nГодованець\nВАЗ 2109\n1500 куб. см.\n1992\nКіровоградська область\n62\nсмт Устинівка, вул. Островського\n72\n2014\n232459\n244639\nВАЗ 2109\n1500 куб. см.\n1992\n2014\nГодованець Іван Алімович\nІван Алімович Годованець\nІван Годованець\nГодованець Іван Алімович\nІван\nПодружжя\nГодованець С. В\nДитина\nГодованець О. І\nДитина\nГодованець Д. І\nГодованець Іван Алімович\nАлімович\nсуддя устинівського районного суду кіровоградської області\nЗагальний місцевий суд\nКіровоградська область\nГодованець\nСМТ\nУстинівка\nКіровоградська область\n232459\n244639\nКіровоградська область\n62\n72\nсмт Устинівка, вул. Островського\nГодованець С. В\nПодружжя\nГодованець О. І\nДитина\nГодованець Д. І\nДитина\nАлімович\nГодованець\nІван\nГодованець Іван Алімович\nІван Алімович Годованець\nІван Годованець\nГодованець Іван Алімович\nКіровоградська область\nУстинівка\nСМТ\nКіровоградська область\nсуддя устинівського районного суду кіровоградської області\nЗагальний місцевий суд\nГодованець Іван Алімович\n1992\nВАЗ 2109\n1500 куб. см.\n244639\n232459\nКіровоградська область\n62\nсмт Устинівка, вул. Островського\n72\n2014","general":{"inn":"","name":"Іван","inn_unclear":false,"family":[{"inn":"","inn_hidden":true,"inn_unclear":false,"relations_hidden":false,"relations_other":"","relations":"Подружжя","name_hidden":true,"family_name":"Годованець С. В","name_unclear":false},{"inn":"","relations":"Дитина","relations_other":"","inn_hidden":false,"family_name":"Годованець О. І","name_hidden":false,"name_unclear":false},{"inn":"","relations":"Дитина","relations_other":"","inn_hidden":false,"family_name":"Годованець Д. І","name_hidden":false,"name_unclear":false}],"inn_hidden":true,"family_raw":"","last_name":"Годованець","post":{"post_unclear":false,"region_unclear":false,"post":"суддя устинівського районного суду кіровоградської області","candidate":"","office_hidden":false,"region":"Кіровоградська область","post_hidden":false,"office":"Загальний місцевий суд","office_unclear":false,"region_hidden":false},"full_name":"Годованець Іван Алімович","addresses":[{"place_city_type_unclear":false,"place_address":"","place_district_hidden":false,"place_city_type":"СМТ","place_address_hidden":true,"place_address_unclear":false,"place_city_type_hidden":false,"place":"Кіровоградська область","place_district":"","place_unclear":false,"place_city":"Устинівка","place_city_unclear":false,"place_hidden":true,"place_city_hidden":false,"place_district_unclear":false}],"patronymic":"Алімович","full_name_suggest":{"output":"Годованець Іван Алімович","input":["Годованець Іван Алімович","Іван Алімович Годованець","Іван Годованець"]}},"source":"VULYK","estate":{"31":[{"space_unclear":false,"address_hidden":true,"region_hidden":true,"space_comment":"","space":"62","address":"","region":"Кіровоградська область","costs_property":"","costs_rent_comment":"","address_unclear":false,"space_units":"м²","costs_property_comment":"","costs_rent":""},{"costs_rent":"","region":"","costs_property":"","costs_rent_comment":"","address_unclear":true,"space_comment":"","costs_property_comment":"","space_units":"м²","space":"72","address":"смт Устинівка, вул. Островського"}]},"intro":{"declaration_year":"2014","isnotdeclaration":"","declaration_year_unclear":false}}