{"income":{"5":{"family_comment":"","value":"222152","family_hidden":false,"comment":"","family":"42194"},"6":{"family_comment":"","value":"208754","family_hidden":false,"comment":"","family":"38272"},"7":{"family_comment":"","value":"","source_name":"","family":"","comment":""},"8":{"family_comment":"","value":"","family":"","comment":""},"9":{"family_comment":"","value":"","family":"","comment":""},"10":{"family_comment":"","value":"13398","family":"3922","comment":""},"11":{"family_comment":"","value":"","family":"","comment":""},"12":{"family_comment":"","value":"","family":"","comment":""},"13":{"family_comment":"","value":"","family":"","comment":""},"14":{"family_comment":"","value":"","family":"","comment":""},"15":{"family_comment":"","value":"","family":"","comment":""},"16":{"family_comment":"","value":"","family":"","comment":""},"17":{"family_comment":"","value":"","family":"","comment":""},"18":{"family_comment":"","value":"","family":"","comment":""},"19":{"family_comment":"","value":"","family":"","comment":""},"20":{"family_comment":"","value":"","family":"","comment":""}},"vehicle":{"40":[{"year_hidden":false,"brand_info":"1994 куб. см., 116 кВт , 456 см","sum_rent_comment":"","brand":"Subaru Forester","sum_comment":"","year":"2007","brand_hidden":false,"brand_info_hidden":false,"sum":"","sum_rent":""}]},"id":"vulyk_105_67","declaration":{"date":"2015-03-30T00:00:00","additional_info_text":"","additional_info":"","url":"http://static.declarations.com.ua/declarations/chosen_ones/judges_batch/4642_ostapenko_oleh_mykolaiovych.pdf"},"liabilities":{"54":{"sum_foreign_comment":"","sum_comment_hidden":false,"sum":"","sum_comment":"","sum_foreign":""},"55":{"sum_foreign_comment":"","sum":"","sum_comment":"","sum_foreign":""},"56":{"sum_foreign_comment":"","sum":"","sum_comment":"","sum_foreign":""},"57":{"sum_foreign_comment":"","sum":"","sum_comment":"","sum_comment_unclear":false,"sum_comment_hidden":false,"sum_foreign":""},"58":{"sum_foreign_comment":"","sum":"","sum_comment":"","sum_foreign":""},"59":{"sum_foreign_comment":"","sum":"","sum_comment":"","sum_foreign":""},"60":{"sum_foreign_comment":"","sum":"","sum_comment":"","sum_foreign":""},"61":{"sum_foreign_comment":"","sum":"","sum_comment":"","sum_foreign":""},"62":{"sum_foreign_comment":"","sum":"","sum_hidden":false,"sum_comment":"","sum_foreign":""},"63":{"sum_foreign_comment":"","sum":"","sum_comment":"","sum_foreign":""},"64":{"sum_foreign_comment":"","sum":"","sum_comment":"","sum_foreign":""}},"ft_src":"Остапенко Олег Миколайович\nсуддя київського апеляційного господарського суду\nм. Київ\nАпеляційний господарський суд\nОлег\nОстапенко Ю. О\nПодружжя\nОстапенко Олег Миколайович\nОлег Миколайович Остапенко\nОлег Остапенко\nОстапенко Олег Миколайович\nОстапенко\nМиколайович\n1994 куб. см., 116 кВт , 456 см\nSubaru Forester\n2007\n1200 кв. м\n.12\n1/2 від 116 кв. м\n116\n2014\n38272\n208754\n3922\n13398\n42194\n222152\n1994 куб. см., 116 кВт , 456 см\n2007\nSubaru Forester\n2014\nсуддя київського апеляційного господарського суду\nАпеляційний господарський суд\nм. Київ\nОстапенко\nОстапенко Олег Миколайович\nОлег Миколайович Остапенко\nОлег Остапенко\nОстапенко Олег Миколайович\nОстапенко Олег Миколайович\nОлег\nМиколайович\nПодружжя\nОстапенко Ю. О\n208754\n38272\n222152\n42194\n13398\n3922\n.12\n1200 кв. м\n116\n1/2 від 116 кв. м\nОстапенко Ю. О\nПодружжя\nМиколайович\nОстапенко\nм. Київ\nсуддя київського апеляційного господарського суду\nАпеляційний господарський суд\nОстапенко Олег Миколайович\nОстапенко Олег Миколайович\nОлег Миколайович Остапенко\nОлег Остапенко\nОстапенко Олег Миколайович\nОлег\nSubaru Forester\n1994 куб. см., 116 кВт , 456 см\n2007\n3922\n13398\n42194\n222152\n38272\n208754\n1/2 від 116 кв. м\n116\n1200 кв. м\n.12\n2014","general":{"inn":"","inn_hidden":true,"last_name":"Остапенко","post":{"post_unclear":false,"region_unclear":false,"region":"м. Київ","office_hidden":false,"office":"Апеляційний господарський суд","post":"суддя київського апеляційного господарського суду","office_unclear":false},"name":"Олег","full_name":"Остапенко Олег Миколайович","family_raw":"","addresses":[{"place_district":"","place_city_hidden":false,"place_city":"","place_city_type_hidden":false,"place_district_hidden":false,"place_city_type":"","place_address_hidden":false,"place_address":"","place_hidden":true,"place":""}],"family":[{"inn":"","inn_hidden":true,"relations_hidden":false,"family_name":"Остапенко Ю. О","relations_other":"","relations":"Подружжя","name_hidden":false,"name_unclear":false}],"full_name_suggest":{"output":"Остапенко Олег Миколайович","input":["Остапенко Олег Миколайович","Олег Миколайович Остапенко","Олег Остапенко"]},"patronymic":"Миколайович"},"source":"VULYK","estate":{"23":[{"costs_rent":"","region":"","costs":"","costs_rent_comment":"","costs_comment":"","address_hidden":false,"region_hidden":true,"space_comment":"1200 кв. м","space_units":"га","space":".12","address":""}],"25":[{"space_hidden":false,"costs":"","costs_comment":"","address_hidden":false,"region_hidden":true,"space_comment":"1/2 від 116 кв. м","space":"116","address":"","region":"","costs_rent_comment":"","space_units":"м²","costs_rent":""}]},"intro":{"declaration_year":"2014"}}