{"income":{"5":{"value":"198589","family_comment":"","value_unclear":false,"family_unclear":false,"family":"2523","comment":""},"6":{"value":"170069","family_comment":"","value_unclear":false,"family_unclear":false,"family":"1266.41","comment":""},"7":{"family_comment":"","value":"","source_name":"","family":"","comment":""},"8":{"family_comment":"","value":"","family":"","comment":""},"9":{"family_comment":"","value":"","value_unclear":false,"family":"","comment":""},"10":{"family_comment":"","value":"12180","value_unclear":false,"family":"","comment":""},"11":{"family_comment":"","value":"","family":"","comment":""},"12":{"family_comment":"","value":"","family":"","comment":""},"13":{"family_comment":"","value":"","value_unclear":false,"family":"","comment":""},"14":{"family_comment":"","value":"","family":"","comment":""},"15":{"family_comment":"","value":"","family":"","comment":""},"16":{"family_comment":"","value":"","family":"","comment":""},"17":{"family_comment":"","value":"","family":"","comment":""},"18":{"family_comment":"","value":"","family":"","comment":""},"19":{"family_comment":"","value":"","family":"","comment":""},"20":{"family_comment":"","family_unclear":false,"value":"16340","family":"1257","comment":""}},"vehicle":{"40":[{"brand_info":"1968 куб. см. 140 кВт","sum_rent_comment":"","brand":"Volkswagen Passat","sum_comment":"","brand_unclear":false,"year":"2013","brand_info_hidden":false,"brand_info_unclear":false,"year_unclear":false,"sum":"","sum_rent":""}]},"id":"vulyk_85_42","declaration":{"additional_info_text":"","notfull_lostpages":"","date":"2015-03-14T00:00:00","notfull":"","additional_info":"","url":"http://static.declarations.com.ua/declarations/chosen_ones/judges_batch/2645_hryshchenko_ievhen_ihorovych.pdf"},"liabilities":{"54":{"sum_foreign_comment":"","sum":"","sum_comment":"","sum_comment_unclear":false,"sum_foreign":""},"55":{"sum_foreign_comment":"","sum":"","sum_comment":"","sum_foreign":""},"56":{"sum_foreign_comment":"","sum":"","sum_comment":"","sum_unclear":false,"sum_foreign":""},"57":{"sum_foreign_comment":"","sum":"","sum_comment":"","sum_foreign":""},"58":{"sum_foreign_comment":"","sum_comment_hidden":false,"sum":"","sum_comment":"","sum_foreign":""},"59":{"sum_foreign_comment":"","sum":"","sum_comment":"","sum_foreign":""},"60":{"sum_foreign_comment":"","sum":"","sum_comment":"","sum_foreign":""},"61":{"sum_foreign_comment":"","sum":"","sum_comment":"","sum_foreign":""},"62":{"sum_foreign_comment":"","sum":"","sum_comment":"","sum_unclear":false,"sum_foreign":""},"63":{"sum_foreign_comment":"","sum":"","sum_comment":"","sum_unclear":false,"sum_foreign":""},"64":{"sum_foreign_comment":"","sum":"","sum_comment":"","sum_foreign":""}},"ft_src":"суддя донецького окружного адміністративного суду\nДонецька область\nАдміністративний місцевий суд\nЄвген\nПодружжя\nДитина\nІгорович\nГрищенко Євген Ігорович\nЄвген Ігорович Грищенко\nЄвген Грищенко\nГрищенко Євген Ігорович\nГрищенко\nГрищенко Євген Ігорович\nVolkswagen Passat\n1968 куб. см. 140 кВт\n2013\n91.3\n2014\n1266.41\n170069\n12180\n2523\n198589\n1257\n16340\n1968 куб. см. 140 кВт\n2013\nVolkswagen Passat\n91.3\nГрищенко Євген Ігорович\nЄвген Ігорович Грищенко\nЄвген Грищенко\nГрищенко Євген Ігорович\nЄвген\nПодружжя\nДитина\nГрищенко Євген Ігорович\nГрищенко\nАдміністративний місцевий суд\nсуддя донецького окружного адміністративного суду\nДонецька область\nІгорович\n170069\n1266.41\n16340\n1257\n198589\n2523\n12180\n2014\nПодружжя\nДитина\nІгорович\nГрищенко\nЄвген\nГрищенко Євген Ігорович\nЄвген Ігорович Грищенко\nЄвген Грищенко\nГрищенко Євген Ігорович\nсуддя донецького окружного адміністративного суду\nДонецька область\nАдміністративний місцевий суд\nГрищенко Євген Ігорович\n2013\nVolkswagen Passat\n1968 куб. см. 140 кВт\n12180\n1257\n16340\n198589\n2523\n170069\n1266.41\n91.3\n2014","general":{"inn":"","name":"Євген","last_name_hidden":false,"family":[{"inn":"","inn_hidden":false,"relations_unclear":false,"relations_hidden":false,"relations_other":"","relations":"Подружжя","name_hidden":false,"family_name":"","name_unclear":false},{"inn":"","relations":"Дитина","relations_other":"","inn_hidden":false,"family_name":"","name_hidden":false,"name_unclear":false}],"patronymic":"Ігорович","inn_hidden":true,"family_raw":"","last_name":"Грищенко","post":{"post_unclear":false,"post_hidden":false,"post":"суддя донецького окружного адміністративного суду","region":"Донецька область","office":"Адміністративний місцевий суд"},"last_name_unclear":false,"full_name":"Грищенко Євген Ігорович","addresses":[{"place_district":"","place_city_hidden":false,"place_city":"","place_city_type_hidden":false,"place_district_hidden":false,"place_city_type":"","place_address_hidden":false,"place_address":"","place_hidden":true,"place":""}],"full_name_suggest":{"output":"Грищенко Євген Ігорович","input":["Грищенко Євген Ігорович","Євген Ігорович Грищенко","Євген Грищенко"]}},"source":"VULYK","estate":{"31":[{"space_unclear":false,"address_hidden":false,"region_hidden":true,"space_comment":"","space":"91.3","address":"","region":"","costs_property":"","costs_rent_comment":"","space_units":"м²","costs_property_comment":"","costs_rent":""}]},"intro":{"declaration_year":"2014","isnotdeclaration":""}}