{"income":{"5":{"family_comment":"","value":"207298","family_hidden":false,"comment":"","family":"112822"},"6":{"value":"193882","value_unclear":false,"family_hidden":false,"family_comment":"","family":"102554","comment":""},"7":{"value":"","value_unclear":false,"family_comment":"","source_name":"","family":"","comment":""},"8":{"family_comment":"","value":"","family":"","comment":""},"9":{"family_comment":"","value":"18","family":"","comment":""},"10":{"value":"13398","family_comment":"","comment_unclear":false,"family_unclear":false,"family":"10268","comment":"","family_comment_unclear":false},"11":{"family_comment":"","value":"","value_unclear":false,"family":"","comment":""},"12":{"family_comment":"","value":"","family":"","comment":""},"13":{"family_comment":"","value":"","family":"","comment":""},"14":{"family_comment":"","value":"","family":"","comment":""},"15":{"value":"","family_comment":"","comment_unclear":false,"family_unclear":false,"family":"","comment":""},"16":{"family_comment":"","value":"","family":"","comment":""},"17":{"family_comment":"","value":"","family":"","comment":""},"18":{"family_comment":"","family_unclear":false,"value":"","family":"","comment":""},"19":{"family_comment":"","value":"","family":"","comment":""},"20":{"family_comment":"","family_unclear":false,"value":"","family":"","comment":""}},"vehicle":{"35":[{"brand_info":"98 KW, 133 RS","sum_rent_comment":"","year":"1999","brand_info_hidden":false,"brand_info_unclear":false,"year_unclear":false,"sum_rent":"","sum":"","brand":"Honda CR-V","sum_comment":"","sum_comment_unclear":false,"brand_hidden":false,"brand_unclear":false}]},"id":"vulyk_92_52","declaration":{"additional_info_text":"","notfull_lostpages":"","date":"2015-03-23T00:00:00","notfull":"","additional_info":"","url":"http://static.declarations.com.ua/declarations/chosen_ones/judges_batch/3300_shynkar_tetiana_ihorivna.pdf"},"liabilities":{"54":{"sum_foreign_comment":"","sum":"7500","sum_comment":"","sum_hidden":false,"sum_unclear":false,"sum_foreign":""},"55":{"sum_foreign_comment":"","sum":"","sum_comment":"","sum_unclear":false,"sum_foreign":""},"56":{"sum_foreign_comment":"","sum":"","sum_comment":"","sum_comment_unclear":false,"sum_hidden":false,"sum_unclear":false,"sum_foreign":""},"57":{"sum_foreign_comment":"","sum":"","sum_comment":"","sum_hidden":false,"sum_comment_hidden":false,"sum_foreign":""},"58":{"sum_foreign_comment":"","sum":"","sum_comment":"","sum_foreign":""},"59":{"sum_foreign_comment":"","sum":"","sum_comment":"","sum_comment_unclear":false,"sum_foreign":""},"60":{"sum_foreign_comment":"","sum":"7447","sum_comment":"","sum_foreign":""},"61":{"sum_foreign_comment":"","sum":"","sum_comment":"","sum_foreign":""},"62":{"sum_foreign_comment":"","sum":"","sum_comment":"","sum_comment_unclear":false,"sum_hidden":false,"sum_unclear":false,"sum_foreign":""},"63":{"sum_foreign_comment":"","sum":"10099","sum_comment":"","sum_foreign":""},"64":{"sum_foreign_comment":"","sum":"23635","sum_comment":"","sum_foreign":""}},"ft_src":"7500\n23635\n10099\n7447\nЛьвівська область\nсуддя львівського апеляційного адміністративного суду\nЛьвівська область\nАпеляційний адміністративний суд\nТетяна\nШинкар Л. Є\nПодружжя\nШинкар С. Л\nДитина\nІгорівна\nШинкар Тетяна Ігорівна\nТетяна Ігорівна Шинкар\nТетяна Шинкар\nШинкар Тетяна Ігорівна\nШинкар Тетяна Ігорівна\nШинкар\n98 KW, 133 RS\nHonda CR-V\n1999\n41.4\n985\n800\n20.7\n2014\n102554\n193882\n18\n10268\n13398\n112822\n207298\n98 KW, 133 RS\nHonda CR-V\n1999\n985\n800\n41.4\n20.7\nПодружжя\nШинкар Л. Є\nДитина\nШинкар С. Л\nШинкар Тетяна Ігорівна\nТетяна Ігорівна Шинкар\nТетяна Шинкар\nШинкар Тетяна Ігорівна\nШинкар Тетяна Ігорівна\nТетяна\nШинкар\nАпеляційний адміністративний суд\nсуддя львівського апеляційного адміністративного суду\nЛьвівська область\nІгорівна\nЛьвівська область\n23635\n7447\n10099\n7500\n193882\n102554\n207298\n112822\n18\n13398\n10268\n2014\n23635\n7500\n7447\n10099\nПодружжя\nШинкар Л. Є\nДитина\nШинкар С. Л\nІгорівна\nШинкар\nТетяна\nШинкар Тетяна Ігорівна\nТетяна Ігорівна Шинкар\nТетяна Шинкар\nШинкар Тетяна Ігорівна\nЛьвівська область\nЛьвівська область\nАпеляційний адміністративний суд\nсуддя львівського апеляційного адміністративного суду\nШинкар Тетяна Ігорівна\n1999\nHonda CR-V\n98 KW, 133 RS\n18\n13398\n10268\n112822\n207298\n193882\n102554\n41.4\n20.7\n985\n800\n2014","general":{"inn":"","name":"Тетяна","patronymic_unclear":false,"family":[{"inn":"","relations":"Подружжя","inn_unclear":false,"relations_hidden":false,"inn_hidden":true,"relations_other":"","name_hidden":false,"family_name":"Шинкар Л. Є","name_unclear":false},{"inn":"","relations":"Дитина","inn_unclear":false,"relations_hidden":false,"inn_hidden":true,"relations_other":"","name_hidden":false,"family_name":"Шинкар С. Л","name_unclear":false}],"patronymic":"Ігорівна","inn_hidden":true,"family_raw":"","inn_unclear":false,"post":{"post_unclear":false,"post":"суддя львівського апеляційного адміністративного суду","office_hidden":false,"region":"Львівська область","office":"Апеляційний адміністративний суд","office_unclear":false,"region_hidden":false},"full_name":"Шинкар Тетяна Ігорівна","addresses":[{"place_district":"","place_address_hidden":false,"place_city":"","place_city_type_hidden":false,"place_district_hidden":false,"place_city_type":"","place_city_hidden":false,"place_address_unclear":false,"place_address":"","place_hidden":true,"place":"Львівська область"}],"last_name":"Шинкар","full_name_suggest":{"output":"Шинкар Тетяна Ігорівна","input":["Шинкар Тетяна Ігорівна","Тетяна Ігорівна Шинкар","Тетяна Шинкар"]}},"source":"VULYK","estate":{"25":[{"space_hidden":false,"costs":"","costs_comment":"","address_hidden":false,"region_hidden":true,"space_comment":"","space":"20.7","address":"","region":"","address_unclear":false,"costs_rent_comment":"","space_comment_unclear":false,"space_units":"м²","costs_rent":""}],"29":[{"space_unclear":false,"space_units_unclear":false,"address_hidden":false,"region_hidden":true,"space_comment":"","space_units_hidden":false,"space":"985","address":"","region":"","costs_property":"","costs_rent_comment":"","space_units":"м²","costs_property_comment":"","costs_rent":""},{"address_hidden":false,"region_hidden":true,"space_comment":"","space":"800","address":"","region":"","costs_property":"","costs_rent_comment":"","address_unclear":false,"space_units":"м²","costs_property_comment":"","costs_rent":""}],"31":[{"space_unclear":false,"address_hidden":false,"region_hidden":true,"space_comment":"","space_hidden":false,"space":"41.4","address":"","region":"","costs_property":"","costs_rent_comment":"","address_unclear":false,"space_units":"м²","costs_property_comment":"","costs_rent":""}]},"intro":{"declaration_year":"2014","isnotdeclaration":""}}