{"income":{"5":{"value":"255574","family_comment":"","value_unclear":false,"comment_hidden":false,"family_hidden":false,"value_hidden":false,"family_unclear":false,"family_comment_hidden":false,"comment":"","family":"17110"},"6":{"value":"255574","family_comment":"","value_unclear":false,"family_hidden":false,"family_unclear":false,"family":"","comment":""},"7":{"source_name_unclear":false,"value":"","family_hidden":false,"family_comment":"","source_name":"","family":"","comment":"","source_name_hidden":false},"8":{"family_comment":"","value":"","family":"","comment":""},"9":{"value":"","value_unclear":false,"family_hidden":false,"family_comment":"","family":"","comment":""},"10":{"value":"","value_unclear":false,"family_hidden":false,"value_hidden":false,"family_comment":"","comment_unclear":false,"comment":"","family":""},"11":{"family_comment":"","value":"","family":"","comment":""},"12":{"family_comment":"","value":"","family":"","comment":""},"13":{"family_comment":"","value":"","family":"","comment":""},"14":{"family_comment":"","value":"","family":"","comment":""},"15":{"family_comment":"","value":"","family_hidden":false,"comment":"","family":""},"16":{"value":"","value_unclear":false,"family_hidden":false,"family_comment":"","family":"","comment":""},"17":{"family_comment":"","value":"","family_hidden":false,"comment":"","family":""},"18":{"family_comment":"","value":"","value_unclear":false,"family":"","comment":""},"19":{"family_comment":"","value":"","family":"","comment":""},"20":{"value":"","family_comment":"","value_unclear":false,"family_hidden":false,"family_unclear":false,"comment_unclear":false,"comment":"","family":"17110"}},"id":"vulyk_72_135","declaration":{"additional_info_text":"","notfull_lostpages":"","date":"2015-03-31T00:00:00","notfull":"","additional_info":"","url":"http://static.declarations.com.ua/declarations/chosen_ones/epic_batch/plakhotniuk_kateryna_hryhorivna.pdf"},"liabilities":{"54":{"sum_foreign_comment":"","sum":"","sum_comment":"","sum_comment_hidden":false,"sum_unclear":false,"sum_foreign":""},"55":{"sum_foreign_comment":"","sum":"","sum_comment":"","sum_foreign":""},"56":{"sum_foreign_comment":"","sum":"","sum_hidden":false,"sum_comment":"","sum_foreign":""},"57":{"sum_foreign_comment":"","sum":"","sum_comment":"","sum_comment_unclear":false,"sum_hidden":false,"sum_comment_hidden":false,"sum_unclear":false,"sum_foreign":""},"58":{"sum_foreign_comment":"","sum":"","sum_comment":"","sum_comment_unclear":false,"sum_hidden":false,"sum_comment_hidden":false,"sum_unclear":false,"sum_foreign":""},"59":{"sum_foreign_comment":"","sum_foreign_hidden":false,"sum_comment":"","sum_foreign_unclear":false,"sum_comment_hidden":false,"sum":"","sum_foreign":""},"60":{"sum_foreign_comment":"","sum_foreign_hidden":false,"sum_comment":"","sum_hidden":false,"sum":"","sum_foreign":""},"61":{"sum_foreign_comment":"","sum_foreign_hidden":false,"sum_comment":"","sum_hidden":false,"sum":"","sum_foreign":""},"62":{"sum_foreign_comment":"","sum_foreign_hidden":false,"sum_comment":"","sum_hidden":false,"sum":"","sum_foreign":""},"63":{"sum_foreign_comment":"","sum_foreign_hidden":false,"sum_comment":"","sum_comment_unclear":false,"sum_hidden":false,"sum_comment_hidden":false,"sum_unclear":false,"sum":"","sum_foreign":""},"64":{"sum_foreign_comment":"","sum_foreign_hidden":false,"sum_comment":"","sum_hidden":false,"sum":"","sum_foreign":""}},"ft_src":"3295\nм. Київ\nсуддя голосіївського районного суду міста києва\nм. Київ\nЗагальний місцевий суд\nКатерина\nПлахотнюк Д. Д\nДитина\nГригорівна\nПлахотнюк\nПлахотнюк Катерина Григорівна\nПлахотнюк Катерина Григорівна\nКатерина Григорівна Плахотнюк\nКатерина Плахотнюк\nПлахотнюк Катерина Григорівна\n17110\n255574\n17110\n255574\nКиївська область\nКиєво-Святошинський р-н, с. Крюківщина, вул. Мічуріна\n1200\nКиївська область\nнезавершене будівництво\nКиєво-Святошинський р-н, с. Крюківщина, вул. Мічуріна\n146\nм. Київ\nм.Київ, вул. Ахматовой\n82.2\nнезавершене буд-во\nКиєво-Святошинський р-н, с. Крюківщина, вул. Мічуріна\nКиївська область\n146\nКиївська область\nКиєво-Святошинський р-н, с. Крюківщина, вул. Мічуріна\nкористування\n1200\nкористування\n82.2\nм.Київ, вул. Ахматовой\nм. Київ\n2014\n255574\n17110\n255574\n17110\n255574\n17110\n255574\n17110\nДитина\nПлахотнюк Д. Д\nПлахотнюк Катерина Григорівна\nКатерина Григорівна Плахотнюк\nКатерина Плахотнюк\nПлахотнюк Катерина Григорівна\nКатерина\nПлахотнюк Катерина Григорівна\nПлахотнюк\nм. Київ\nЗагальний місцевий суд\nсуддя голосіївського районного суду міста києва\nГригорівна\nм. Київ\n3295\nнезавершене буд-во\nКиївська область\n146\nКиєво-Святошинський р-н, с. Крюківщина, вул. Мічуріна\nм.Київ, вул. Ахматовой\nкористування\n82.2\nм. Київ\n1200\nКиєво-Святошинський р-н, с. Крюківщина, вул. Мічуріна\nКиївська область\nкористування\nКиєво-Святошинський р-н, с. Крюківщина, вул. Мічуріна\nКиївська область\n1200\n146\nнезавершене будівництво\nКиївська область\nКиєво-Святошинський р-н, с. Крюківщина, вул. Мічуріна\nм. Київ\nм.Київ, вул. Ахматовой\n82.2\n2014\nПлахотнюк Д. Д\nДитина\nГригорівна\nПлахотнюк\nПлахотнюк Катерина Григорівна\nКатерина Григорівна Плахотнюк\nКатерина Плахотнюк\nПлахотнюк Катерина Григорівна\nм. Київ\n3295\nм. Київ\nЗагальний місцевий суд\nсуддя голосіївського районного суду міста києва\nПлахотнюк Катерина Григорівна\nКатерина\nм. Київ\nм.Київ, вул. Ахматовой\n82.2\nКиївська область\nКиєво-Святошинський р-н, с. Крюківщина, вул. Мічуріна\nкористування\n1200\nнезавершене будівництво\nКиєво-Святошинський р-н, с. Крюківщина, вул. Мічуріна\nКиївська область\n146\nнезавершене буд-во\nКиєво-Святошинський р-н, с. Крюківщина, вул. Мічуріна\nКиївська область\n146\nкористування\n82.2\nм.Київ, вул. Ахматовой\nм. Київ\nКиєво-Святошинський р-н, с. Крюківщина, вул. Мічуріна\nКиївська область\n1200\n2014","general":{"inn":"","name":"Катерина","patronymic_unclear":false,"family":[{"inn":"","inn_hidden":false,"relations_unclear":false,"relations_hidden":false,"relations_other":"","relations":"Дитина","name_hidden":false,"inn_unclear":false,"family_name":"Плахотнюк Д. Д","name_unclear":false}],"patronymic":"Григорівна","inn_hidden":true,"family_raw":"","inn_unclear":false,"post":{"post_unclear":false,"region_unclear":false,"post":"суддя голосіївського районного суду міста києва","candidate":"","office_hidden":false,"region":"м. Київ","post_hidden":false,"office":"Загальний місцевий суд","office_unclear":false,"region_hidden":false},"last_name_unclear":false,"full_name":"Плахотнюк Катерина Григорівна","addresses":[{"place_city_type_hidden":false,"place_district_hidden":false,"place_city_type":"","place_city_hidden":false,"place_address_unclear":false,"place_address":"","place":"м. Київ","place_district":"3295","place_unclear":false,"place_city":"","place_city_unclear":false,"place_hidden":false,"place_address_hidden":false,"place_district_unclear":false}],"last_name":"Плахотнюк","patronymic_hidden":false,"full_name_suggest":{"output":"Плахотнюк Катерина Григорівна","input":["Плахотнюк Катерина Григорівна","Катерина Григорівна Плахотнюк","Катерина Плахотнюк"]},"name_unclear":false},"source":"VULYK","estate":{"23":[{"space_hidden":false,"costs":"","costs_rent_unclear":false,"costs_comment":"","costs_hidden":false,"address_hidden":false,"region_hidden":false,"space_comment":"","space_unclear":false,"space":"1200","address":"Києво-Святошинський р-н, с. Крюківщина, вул. Мічуріна","region":"Київська область","address_unclear":false,"costs_rent_comment":"користування","costs_rent_hidden":false,"space_units":"м²","space_units_hidden":false,"costs_rent":""}],"24":[{"space_hidden":false,"costs":"","costs_comment":"","address_hidden":false,"region_hidden":false,"space_comment":"незавершене будівництво","space":"146","address":"Києво-Святошинський р-н, с. Крюківщина, вул. Мічуріна","region":"Київська область","address_unclear":false,"costs_rent_comment":"","space_units":"м²","costs_rent":""}],"25":[{"space_unclear":false,"costs":"","costs_rent_unclear":false,"costs_comment":"","costs_hidden":false,"space_hidden":false,"costs_comment_unclear":false,"costs_rent_comment_unclear":false,"region":"м. Київ","space_comment_hidden":false,"space_comment_unclear":false,"costs_rent_comment_hidden":false,"costs_rent":"","costs_comment_hidden":false,"address_hidden":false,"region_hidden":false,"space_comment":"","space":"82.2","address":"м.Київ, вул. Ахматовой","address_unclear":false,"costs_rent_comment":"користування","costs_rent_hidden":false,"space_units":"м²"}],"29":[{"space_hidden":false,"costs_property_comment":"","address_hidden":false,"region_hidden":false,"space_comment":"","space_unclear":false,"space":"1200","address":"Києво-Святошинський р-н, с. Крюківщина, вул. Мічуріна","region":"Київська область","costs_property":"","costs_rent_comment":"","address_unclear":false,"space_units":"м²","space_units_unclear":false,"costs_rent":""}],"30":[{"region_unclear":false,"space_unclear":false,"address_hidden":false,"region_hidden":false,"space_comment":"незавершене буд-во","space_hidden":false,"space":"146","address":"Києво-Святошинський р-н, с. Крюківщина, вул. Мічуріна","region":"Київська область","costs_property":"","costs_rent_comment":"","space_units":"м²","costs_property_comment":"","costs_rent":""}],"31":[{"space_unclear":false,"address_hidden":false,"region_hidden":false,"space_comment":"","space_units_hidden":false,"space_hidden":false,"space":"82.2","address":"м.Київ, вул. Ахматовой","region":"м. Київ","address_unclear":false,"costs_rent_comment":"","costs_property":"","space_units":"м²","costs_property_comment":"","costs_rent":""}]},"intro":{"declaration_year":"2014","isnotdeclaration":"","declaration_year_unclear":false}}