{"income":{"5":{"family_comment":"","value":"287033.61","family":"28560.8","comment":""},"6":{"family_comment":"","value":"229370.92","value_unclear":false,"family":"28560.8","comment":""},"7":{"value":"","family_comment":"","source_name":"","family":"","comment":"","source_name_hidden":false},"8":{"family_comment":"","value":"","family":"","comment":""},"9":{"family_comment":"","value":"","family":"","comment":""},"10":{"family_comment":"","value":"","family":"","comment":""},"11":{"family_comment":"","value":"","comment_hidden":false,"family":"","comment":""},"12":{"family_comment":"","value":"","family":"","comment":""},"13":{"family_comment":"","value":"","family":"","comment":""},"14":{"family_comment":"","value":"","family":"","comment":""},"15":{"value":"","family_comment":"","value_unclear":false,"family_unclear":false,"family":"","comment":""},"16":{"family_comment":"","value":"","family":"","comment":""},"17":{"family_comment":"","value":"","family":"","comment":""},"18":{"family_comment":"","value":"","family":"","comment":""},"19":{"family_comment":"","value":"","family":"","comment":""},"20":{"family_comment":"","value":"57662.69","comment_unclear":false,"family":"","comment":""}},"vehicle":{"35":[{"brand_info":"1.6","sum_rent_comment":"","brand":"Nissan Note","sum_comment":"","year":"2007","brand_hidden":false,"brand_info_unclear":false,"sum":"","sum_rent":""},{"brand_info":"","sum":"","brand":"Land Rover Range Rover Evoque","sum_comment":"","year":"2014","sum_rent_comment":"","sum_rent":"","sum_unclear":false}]},"id":"vulyk_104_26","declaration":{"date":"2016-03-30T00:00:00","additional_info_text":"","additional_info":"","url":"http://static.declarations.com.ua/declarations/chosen_ones/judges_batch/1824_tarasenko_karolina_vitaliivna_2015.pdf"},"liabilities":{"54":{"sum_foreign_comment":"","sum_foreign_hidden":true,"sum_comment":"","sum_hidden":false,"sum_comment_hidden":false,"sum_unclear":false,"sum":"50862.04","sum_foreign":""},"55":{"sum_foreign_comment":"","sum":"","sum_comment":"","sum_foreign":""},"56":{"sum_foreign_comment":"","sum":"","sum_comment":"","sum_unclear":false,"sum_foreign":""},"57":{"sum_foreign_comment":"","sum_foreign_hidden":true,"sum_comment":"","sum_comment_unclear":false,"sum_comment_hidden":false,"sum":"179900","sum_foreign":""},"58":{"sum_foreign_comment":"","sum":"","sum_comment":"","sum_unclear":false,"sum_foreign":""},"59":{"sum_foreign_comment":"","sum":"","sum_comment":"","sum_foreign":""},"60":{"sum_foreign_comment":"","sum_foreign_hidden":false,"sum_comment":"","sum_comment_hidden":false,"sum":"","sum_foreign":""},"61":{"sum_foreign_comment":"","sum":"","sum_comment":"","sum_foreign":""},"62":{"sum_foreign_comment":"","sum":"","sum_comment":"","sum_foreign":""},"63":{"sum_foreign_comment":"","sum":"","sum_comment":"","sum_foreign":""},"64":{"sum_foreign_comment":"","sum":"","sum_comment":"","sum_foreign":""}},"ft_src":"179900\n50862.04\nТарасенко Кароліна Віталіївна\nсуддя київського апеляційного господарського суду\nм. Київ\nАпеляційний господарський суд\nКароліна\nТарасенко Віталій\nДитина\nШакун Олександр Миколайович\nц. чоловік\nІнше\nТарасенко Кароліна Віталіївна\nКароліна Віталіївна Тарасенко\nКароліна Тарасенко\nТарасенко Кароліна Віталіївна\nТарасенко\nВіталіївна\n2007\nNissan Note\n1.6\n2014\nLand Rover Range Rover Evoque\nу власності\n27.9\nу власності\n27.8\nу користуванні\n74.5\n2015\n28560.8\n229370.92\n28560.8\n287033.61\n57662.69\n1.6\nNissan Note\n2007\nLand Rover Range Rover Evoque\n2014\n2015\nДитина\nТарасенко Віталій\nІнше\nШакун Олександр Миколайович\nц. чоловік\nТарасенко\nТарасенко Кароліна Віталіївна\nКароліна Віталіївна Тарасенко\nКароліна Тарасенко\nТарасенко Кароліна Віталіївна\nТарасенко Кароліна Віталіївна\nКароліна\nВіталіївна\nАпеляційний господарський суд\nсуддя київського апеляційного господарського суду\nм. Київ\n50862.04\n179900\n229370.92\n28560.8\n57662.69\n287033.61\n28560.8\n27.9\nу власності\n27.8\nу власності\n74.5\nу користуванні\n179900\n50862.04\nДитина\nТарасенко Віталій\nІнше\nШакун Олександр Миколайович\nц. чоловік\nВіталіївна\nТарасенко\nсуддя київського апеляційного господарського суду\nАпеляційний господарський суд\nм. Київ\nТарасенко Кароліна Віталіївна\nТарасенко Кароліна Віталіївна\nКароліна Віталіївна Тарасенко\nКароліна Тарасенко\nТарасенко Кароліна Віталіївна\nКароліна\n2007\n1.6\nNissan Note\nLand Rover Range Rover Evoque\n2014\n57662.69\n28560.8\n287033.61\n28560.8\n229370.92\nу власності\n27.9\nу власності\n27.8\nу користуванні\n74.5\n2015","general":{"inn":"","inn_hidden":true,"last_name":"Тарасенко","post":{"region":"м. Київ","region_unclear":false,"post":"суддя київського апеляційного господарського суду","office_unclear":false,"office":"Апеляційний господарський суд"},"name":"Кароліна","full_name":"Тарасенко Кароліна Віталіївна","family_raw":"","addresses":[{"place_district":"","place_city_hidden":true,"place_city":"","place_city_type_hidden":false,"place_district_hidden":false,"place_city_type":"","place_address_hidden":true,"place_address":"","place_hidden":true,"place":""}],"family":[{"inn":"","relations":"Дитина","relations_other":"","inn_hidden":true,"family_name":"Тарасенко Віталій","name_hidden":true,"name_unclear":false},{"inn":"","relations":"Інше","relations_other":"ц. чоловік","inn_hidden":false,"family_name":"Шакун Олександр Миколайович","name_hidden":false,"name_unclear":false}],"full_name_suggest":{"output":"Тарасенко Кароліна Віталіївна","input":["Тарасенко Кароліна Віталіївна","Кароліна Віталіївна Тарасенко","Кароліна Тарасенко"]},"patronymic":"Віталіївна"},"source":"VULYK","estate":{"25":[{"costs":"","costs_comment":"","address_hidden":false,"region_hidden":true,"space_comment":"у власності","space":"27.8","address":"","costs_unclear":false,"region":"","costs_rent_comment":"","space_comment_unclear":false,"space_units":"м²","costs_rent":""},{"costs_rent":"","space_comment_unclear":false,"region":"","costs":"","costs_rent_comment":"","costs_comment":"","costs_unclear":false,"space_comment":"у користуванні","space_units":"м²","space":"74.5","address":""}],"31":[{"space_unclear":false,"address_hidden":false,"region_hidden":true,"space_comment":"у власності","space_hidden":false,"space":"27.9","address":"","region":"","costs_property":"","costs_rent_comment":"","space_units":"м²","costs_property_comment":"","costs_rent":""}]},"intro":{"declaration_year":"2015","isnotdeclaration":""}}