{"id":"vulyk_104_1","ft_src":"Hyundai Accent\n1.4 куб. см.\n2008\nм. Дніпропетровськ\nДніпропетровська область\n87.6\n2015\n34016.17\n208261.74\n13780\n34016.17\n222041.74\nHyundai Accent\n1.4 куб. см.\n2008\n2015\nПодружжя\nМащук Л. В. 16. 11. 1980\nДитина\nМащук Ю. В. 29. 08. 2000\nДитина\nМащук П. В. 22. 08. 2005\nМащук\nМащук Віталій Юрійович\nВіталій Юрійович Мащук\nВіталій Мащук\nМащук Віталій Юрійович\nМащук Віталій Юрійович\nДніпропетровська область\nДніпропетровськ\nВіталій\nЮрійович\nЗагальний місцевий суд\nголова красногвардійського районного суду м. дніпропетровська\nДніпропетровська область\n208261.74\n34016.17\n222041.74\n34016.17\n13780\n87.6\nм. Дніпропетровськ\nДніпропетровська область\nПодружжя\nМащук Л. В. 16. 11. 1980\nДитина\nМащук Ю. В. 29. 08. 2000\nМащук П. В. 22. 08. 2005\nДитина\nДніпропетровська область\nДніпропетровськ\nЮрійович\nМащук\nголова красногвардійського районного суду м. дніпропетровська\nЗагальний місцевий суд\nДніпропетровська область\nМащук Віталій Юрійович\nМащук Віталій Юрійович\nВіталій Юрійович Мащук\nВіталій Мащук\nМащук Віталій Юрійович\nВіталій","estate":{"31":[{"costs_property_comment":"","address":"м. Дніпропетровськ","space_units":"м²","space_hidden":false,"space_unclear":false,"region_hidden":false,"costs_property":"","space_comment":"","address_hidden":true,"costs_rent_comment":"","space":"87.6","region":"Дніпропетровська область","costs_rent":""}]},"vehicle":{"40":[{"sum_comment":"","brand_info_hidden":false,"brand_info":"1.4 куб. см.","sum":"","sum_rent_comment":"","brand_hidden":false,"brand":"Hyundai Accent","sum_rent":"","brand_info_unclear":false,"year":"2008"}]},"source":"VULYK","income":{"5":{"family_comment":"","value":"222041.74","family":"34016.17","comment":""},"6":{"family_comment":"","value":"208261.74","family":"34016.17","comment":"","value_unclear":false},"7":{"source_name_hidden":false,"family_comment":"","comment":"","family":"","value":"","source_name":""},"8":{"family_comment":"","value":"","family":"","comment":""},"9":{"family_comment":"","value":"","family":"","comment":""},"10":{"family_comment":"","value":"13780","family":"","comment":""},"11":{"family_comment":"","value":"","family":"","comment":"","comment_hidden":false},"12":{"family_comment":"","value":"","family":"","comment":""},"13":{"family_comment":"","value":"","family":"","comment":""},"14":{"family_comment":"","value":"","family":"","comment":""},"15":{"family_comment":"","family":"","comment":"","value_unclear":false,"family_unclear":false,"value":""},"16":{"family_comment":"","value":"","family":"","comment":""},"17":{"family_comment":"","value":"","family":"","comment":""},"18":{"family_comment":"","value":"","family":"","comment":""},"19":{"family_comment":"","value":"","family":"","comment":""},"20":{"family_comment":"","comment_unclear":false,"value":"","family":"","comment":""}},"general":{"inn":"","addresses":[{"place_city_type_hidden":false,"place_city_type":"Місто","place_city_hidden":false,"place_hidden":false,"place_district":"","place_district_hidden":false,"place":"Дніпропетровська область","place_address":"","place_address_hidden":true,"place_city":"Дніпропетровськ"}],"last_name":"Мащук","full_name":"Мащук Віталій Юрійович","family":[{"inn":"","family_name":"Мащук Л. В. 16. 11. 1980","relations_other":"","name_unclear":false,"inn_hidden":true,"name_hidden":false,"relations":"Подружжя"},{"inn":"","family_name":"Мащук Ю. В. 29. 08. 2000","relations_other":"","name_unclear":false,"inn_hidden":true,"name_hidden":false,"relations":"Дитина"},{"inn":"","family_name":"Мащук П. В. 22. 08. 2005","relations_other":"","name_unclear":false,"inn_hidden":true,"relations":"Дитина"}],"patronymic":"Юрійович","inn_hidden":true,"name":"Віталій","post":{"office":"Загальний місцевий суд","region_unclear":false,"post":"голова красногвардійського районного суду м. дніпропетровська","region":"Дніпропетровська область","office_unclear":false},"family_raw":"","full_name_suggest":{"input":["Мащук Віталій Юрійович","Віталій Юрійович Мащук","Віталій Мащук"],"output":"Мащук Віталій Юрійович"}},"liabilities":{"54":{"sum_comment":"","sum_hidden":false,"sum":"","sum_foreign_comment":"","sum_foreign":"","sum_unclear":false,"sum_foreign_hidden":false,"sum_comment_hidden":false},"55":{"sum_comment":"","sum_foreign_comment":"","sum_foreign":"","sum":""},"56":{"sum_comment":"","sum_foreign_comment":"","sum_foreign":"","sum_unclear":false,"sum":""},"57":{"sum_comment_unclear":false,"sum_comment":"","sum":"","sum_foreign_comment":"","sum_foreign":"","sum_foreign_hidden":false,"sum_comment_hidden":false},"58":{"sum_comment":"","sum_foreign_comment":"","sum_foreign":"","sum_unclear":false,"sum":""},"59":{"sum_comment":"","sum_foreign_comment":"","sum_foreign":"","sum":""},"60":{"sum_comment":"","sum":"","sum_foreign_comment":"","sum_foreign":"","sum_foreign_hidden":false,"sum_comment_hidden":false},"61":{"sum_comment":"","sum_foreign_comment":"","sum_foreign":"","sum":""},"62":{"sum_comment":"","sum_foreign_comment":"","sum_foreign":"","sum":""},"63":{"sum_comment":"","sum_foreign_comment":"","sum_foreign":"","sum":""},"64":{"sum_comment":"","sum_foreign_comment":"","sum_foreign":"","sum":""}},"declaration":{"additional_info_text":"","additional_info":"","date":"2016-03-18T00:00:00","url":"http://static.declarations.com.ua/declarations/chosen_ones/judges_batch/1799_mashchuk_vitalii_iuriiovych_2015.pdf"},"intro":{"isnotdeclaration":"","declaration_year":"2015"}}