{"income":{"5":{"value":"261526.1","family_comment":"","value_unclear":false,"family_hidden":false,"family_unclear":false,"family":"122205.2","comment":""},"6":{"value":"261526.1","value_unclear":false,"family_hidden":false,"family_comment":"","family":"","comment":""},"7":{"source_name_unclear":false,"value":"","family_hidden":false,"family_comment":"","source_name":"","family":"","comment":"","source_name_hidden":false},"8":{"family_comment":"","value":"","family":"","comment":""},"9":{"family_comment":"","family_unclear":false,"value":"","family":"","comment":""},"10":{"family_comment":"","value":"","family":"","comment":""},"11":{"family_comment":"","value":"","comment_unclear":false,"family":"","comment":""},"12":{"family_comment":"","value":"","family":"","comment":""},"13":{"family_comment":"","value":"","family":"","comment":""},"14":{"family_comment":"","value":"","family":"","comment":""},"15":{"family_comment":"","value":"","family":"","comment":""},"16":{"family_comment":"","value":"","family":"","comment":""},"17":{"family_comment":"","value":"","family":"","comment":"","family_comment_unclear":false},"18":{"family_comment":"","value":"","family":"","comment":""},"19":{"family_comment":"","value":"","comment_unclear":false,"family":"","comment":""},"20":{"value":"","family_comment":"","comment_unclear":false,"comment_hidden":false,"family_unclear":false,"family":"122205.2","comment":""}},"vehicle":{"39":[{"brand_info":"мопед, об'єм цил. 48","sum_rent_comment":"","brand":"Мустанг","sum_comment":"","brand_unclear":false,"year":"2008","sum":"","sum_rent":""}],"40":[{"year_hidden":false,"brand_info":"2700 куб. см., 136 кВт ,","sum_rent_comment":"","year":"2013","brand_info_hidden":false,"brand_info_unclear":false,"year_unclear":false,"sum_rent":"","sum":"","brand":"Toyota Venza","sum_comment":"","brand_unclear":false,"brand_hidden":false},{"brand_info":"1500 куб. см. 77","sum_rent_comment":"","brand":"Daihatsu Terios","sum_comment":"","brand_unclear":false,"year":"","brand_info_unclear":false,"sum":"","sum_rent":""}]},"id":"vulyk_8_196","banks":{"45":[{"sum_foreign_comment":"","sum_units":"UAH","sum_comment":"","sum_foreign_unclear":false,"sum_foreign_units":"UAH","sum_hidden":false,"sum_comment_hidden":false,"sum_unclear":false,"sum":"","sum_foreign":""},{"sum_foreign_comment":"","sum_units":"","sum_comment":"","sum_hidden":false,"sum_foreign_units":"","sum":"","sum_unclear":false,"sum_foreign":""},{"sum_foreign_comment":"","sum_units":"","sum_comment":"","sum_foreign_units":"","sum":"","sum_unclear":false,"sum_foreign":""},{"sum_foreign_comment":"","sum_units":"","sum_comment":"","sum_foreign_units":"","sum":"","sum_foreign":""}],"46":[{"sum_foreign_comment":"","sum_units":"UAH","sum_comment":"","sum_foreign_comment_hidden":false,"sum_hidden":false,"sum_foreign_units":"UAH","sum_foreign_hidden":false,"sum_comment_hidden":false,"sum_unclear":false,"sum":"","sum_foreign":""}],"47":[{"sum_foreign_comment":"","sum_units":"UAH","sum_comment":"","sum_foreign_units":"UAH","sum_comment_hidden":false,"sum":"","sum_foreign":""}],"48":[{"sum_foreign_comment":"","sum_units":"UAH","sum_comment":"","sum_foreign_units":"UAH","sum":"","sum_foreign":""}],"49":[{"sum_foreign_comment":"","sum_units":"UAH","sum_comment":"","sum_foreign_units":"UAH","sum":"","sum_foreign":""}],"50":[{"sum_foreign_comment":"","sum_units":"UAH","sum_comment":"","sum_foreign_units":"UAH","sum":"","sum_foreign":""}],"51":[{"sum_foreign_comment":"","sum_units":"UAH","sum_comment":"","sum_comment_unclear":false,"sum_hidden":false,"sum_foreign_units":"UAH","sum_comment_hidden":false,"sum_unclear":false,"sum":"","sum_foreign":""},{"sum_foreign_comment":"","sum_units":"","sum_comment":"","sum_hidden":false,"sum_foreign_units":"","sum":"","sum_foreign":""}],"52":[{"sum_foreign_comment":"","sum_units":"UAH","sum_comment":"","sum_comment_unclear":false,"sum_hidden":false,"sum_foreign_units":"UAH","sum_comment_hidden":false,"sum_unclear":false,"sum":"","sum_foreign":""}],"53":[{"sum_foreign_comment":"","sum_units":"UAH","sum_comment":"","sum_foreign_units":"UAH","sum_comment_hidden":false,"sum":"","sum_foreign":""}]},"declaration":{"additional_info_text":"","notfull_lostpages":"","date":"2015-03-20T00:00:00","notfull":"","additional_info":"","url":"http://static.declarations.com.ua/declarations/chosen_ones/batch_16/furyk_iurii_petrovych.pdf"},"liabilities":{"54":{"sum_foreign_comment":"","sum_foreign_hidden":false,"sum_comment":"","sum_hidden":false,"sum_comment_hidden":false,"sum":"","sum_foreign":""},"55":{"sum_foreign_comment":"","sum":"","sum_comment":"","sum_foreign":""},"56":{"sum_foreign_comment":"","sum":"","sum_comment":"","sum_unclear":false,"sum_foreign":""},"57":{"sum_foreign_comment":"","sum_comment_hidden":false,"sum":"","sum_comment":"","sum_foreign":""},"58":{"sum_foreign_comment":"","sum":"","sum_comment":"","sum_foreign":""},"59":{"sum_foreign_comment":"","sum":"","sum_comment":"","sum_comment_unclear":false,"sum_foreign":""},"60":{"sum_foreign_comment":"","sum_foreign_hidden":false,"sum_comment":"","sum_hidden":false,"sum_comment_hidden":false,"sum":"","sum_foreign":""},"61":{"sum_foreign_comment":"","sum":"","sum_comment":"","sum_foreign":""},"62":{"sum_foreign_comment":"","sum":"","sum_comment":"","sum_foreign":""},"63":{"sum_foreign_comment":"","sum":"","sum_comment":"","sum_foreign":""},"64":{"sum_foreign_comment":"","sum":"","sum_comment":"","sum_foreign":""}},"ft_src":"суддя вищого спеціалізованого суду україни з розгляду цивільних і кримінальних справ\nЗагальнодержавний регіон\nВищий спецiалiзований суд України з розгляду цивiльних i кримiнальних справ\nЮрій\nФурик Марія Петрівна\nБатьки\nФурик Всеволод Юрійович\nДитина\nФурик Валентина Борисівна\nПодружжя\nТкаченко Микола Сергійович\nсин дружини\nІнше\nПетрович\nФурик Юрій Петрович\nЮрій Петрович Фурик\nЮрій Фурик\nФурик Юрій Петрович\nФурик Юрій Петрович\nФурик\n2008\nмопед, об'єм цил. 48\nМустанг\n2700 куб. см., 136 кВт ,\nToyota Venza\n2013\nDaihatsu Terios\n1500 куб. см. 77\n2014\n2700 куб. см., 136 кВт ,\nToyota Venza\n2013\n1500 куб. см. 77\nDaihatsu Terios\nмопед, об'єм цил. 48\nМустанг\n2008\n108\n86\n80\n108\nБатьки\nФурик Марія Петрівна\nДитина\nФурик Всеволод Юрійович\nПодружжя\nФурик Валентина Борисівна\nІнше\nТкаченко Микола Сергійович\nсин дружини\nФурик Юрій Петрович\nЮрій Петрович Фурик\nЮрій Фурик\nФурик Юрій Петрович\nФурик Юрій Петрович\nЮрій\nФурик\nВищий спецiалiзований суд України з розгляду цивiльних i кримiнальних справ\nсуддя вищого спеціалізованого суду україни з розгляду цивільних і кримінальних справ\nЗагальнодержавний регіон\nПетрович\n261526.1\n122205.2\n122205.2\n261526.1\n2014\n108\n86\n80\n108\nФурик Марія Петрівна\nБатьки\nФурик Всеволод Юрійович\nДитина\nФурик Валентина Борисівна\nПодружжя\nсин дружини\nТкаченко Микола Сергійович\nІнше\nПетрович\nФурик\nЮрій\nФурик Юрій Петрович\nЮрій Петрович Фурик\nЮрій Фурик\nФурик Юрій Петрович\nЗагальнодержавний регіон\nсуддя вищого спеціалізованого суду україни з розгляду цивільних і кримінальних справ\nВищий спецiалiзований суд України з розгляду цивiльних i кримiнальних справ\nФурик Юрій Петрович\n261526.1\n122205.2\n261526.1\n122205.2\n2008\nмопед, об'єм цил. 48\nМустанг\nToyota Venza\n2700 куб. см., 136 кВт ,\n2013\n1500 куб. см. 77\nDaihatsu Terios\n122205.2\n261526.1\n122205.2\n261526.1\n108\n86\n80\n108\n2014","general":{"inn":"","name":"Юрій","patronymic_unclear":false,"last_name_hidden":false,"family":[{"inn":"","inn_hidden":true,"relations_hidden":false,"family_name":"Фурик Марія Петрівна","relations_other":"","relations":"Батьки","name_hidden":false,"name_unclear":false},{"inn":"","relations":"Дитина","inn_unclear":false,"family_name":"Фурик Всеволод Юрійович","inn_hidden":false,"relations_other":"","name_hidden":false,"name_unclear":false},{"inn":"","relations":"Подружжя","relations_other":"","inn_hidden":false,"family_name":"Фурик Валентина Борисівна","name_hidden":false,"name_unclear":false},{"inn":"","relations":"Інше","relations_other":"син дружини","inn_hidden":false,"family_name":"Ткаченко Микола Сергійович","name_hidden":false}],"patronymic":"Петрович","inn_hidden":true,"family_raw":"","inn_unclear":false,"post":{"post_unclear":false,"post":"суддя вищого спеціалізованого суду україни з розгляду цивільних і кримінальних справ","post_hidden":false,"region":"Загальнодержавний регіон","region_hidden":false,"office":"Вищий спецiалiзований суд України з розгляду цивiльних i кримiнальних справ","office_hidden":false,"office_unclear":false},"full_name":"Фурик Юрій Петрович","addresses":[{"place_district":"","place_city_hidden":false,"place_city":"","place_city_type_hidden":false,"place_district_hidden":false,"place_city_type":"","place_address_hidden":false,"place_address":"","place_hidden":true,"place":""}],"last_name":"Фурик","full_name_suggest":{"output":"Фурик Юрій Петрович","input":["Фурик Юрій Петрович","Юрій Петрович Фурик","Юрій Фурик"]}},"source":"VULYK","estate":{"23":[{"space_unclear":false,"costs":"","costs_comment":"","address_hidden":false,"region_hidden":false,"space_comment":"","space":"","address":"","costs_comment_unclear":false,"region":"","address_unclear":false,"costs_rent_comment":"","space_comment_unclear":false,"space_comment_hidden":false,"space_units":"м²","space_units_hidden":false,"costs_rent":""},{"space_unclear":false,"costs":"","costs_comment":"","address_hidden":false,"region_hidden":false,"space_comment":"","space":"","address":"","region":"","costs_rent_comment":"","space_comment_unclear":false,"space_units":"","costs_rent":""},{"space":"","region":"","costs":"","costs_rent_comment":"","costs_comment":"","space_comment":"","space_units_unclear":false,"space_units":"","costs_rent":"","address":""},{"costs_rent":"","region":"","costs":"","costs_rent_comment":"","costs_comment":"","address_hidden":false,"space_comment":"","space_units":"","space":"","address":""}],"25":[{"region_unclear":false,"space_unclear":false,"costs":"","costs_comment":"","address_hidden":false,"region_hidden":true,"space_comment":"","space":"80","address":"","costs_comment_unclear":false,"region":"","costs_rent_comment":"","space_comment_unclear":false,"space_units":"м²","costs_rent":""},{"space_unclear":false,"costs":"","costs_comment":"","address_hidden":false,"region_hidden":false,"space_comment":"","space":"108","address":"","region":"","costs_rent_comment":"","space_comment_unclear":false,"space_units":"м²","costs_rent":""}],"31":[{"space_unclear":false,"address_hidden":false,"region_hidden":true,"space_comment":"","space_hidden":false,"space":"108","address":"","region":"","costs_property":"","costs_rent_comment":"","address_unclear":false,"space_units":"м²","costs_property_comment":"","costs_rent":""},{"space_unclear":false,"address_hidden":false,"region_hidden":false,"space_comment":"","space":"86","address":"","region":"","costs_property":"","costs_rent_comment":"","space_units":"м²","costs_property_comment":"","costs_rent":""}]},"intro":{"declaration_year":"2014","isnotdeclaration":""}}