{"income":{"5":{"value":"242550","family_unclear":false,"family_hidden":false,"family_comment":"","family":"7060","comment":""},"6":{"value":"229933","family_comment":"","value_unclear":false,"family_hidden":false,"family_unclear":false,"family":"7060","comment":""},"7":{"value":"","family_hidden":false,"value_hidden":false,"family_comment":"","source_name":"","family":"","comment":"","source_name_hidden":false},"8":{"family_comment":"","value":"","family":"","comment":""},"9":{"family_comment":"","value":"","family":"","comment":""},"10":{"family_comment":"","value":"12617","value_unclear":false,"family":"","comment":""},"11":{"family_comment":"","value":"","family":"","comment":""},"12":{"family_comment":"","value":"","family":"","comment":""},"13":{"family_comment":"","value":"","family":"","comment":""},"14":{"family_comment":"","value":"","family":"","comment":""},"15":{"family_comment":"","value":"","family":"","comment":""},"16":{"family_comment":"","value":"","family":"","comment":""},"17":{"family_comment":"","value":"","family":"","comment":""},"18":{"family_comment":"","value":"","family":"","comment":""},"19":{"family_comment":"","value":"","family":"","comment":""},"20":{"value":"","family_comment":"","value_unclear":false,"family_unclear":false,"comment_unclear":false,"comment":"","family":""}},"vehicle":{"40":[{"brand_info":"1998 куб. см., 150 к. с., 429.5 см","sum_rent_comment":"","brand":"Mitsubishi ASX","sum_comment":"","brand_unclear":false,"year":"2013","brand_info_unclear":false,"year_unclear":false,"sum":"","sum_rent":""}]},"id":"vulyk_74_25","declaration":{"additional_info_text":"","notfull_lostpages":"","date":"2014-12-12T00:00:00","notfull":"","additional_info":"","url":"http://static.declarations.com.ua/declarations/chosen_ones/judges_batch/1756_panteliienko_vitaliiovych_olehovych.pdf"},"liabilities":{"54":{"sum_foreign_comment":"","sum":"","sum_comment":"","sum_comment_unclear":false,"sum_comment_hidden":false,"sum_foreign":""},"55":{"sum_foreign_comment":"","sum":"","sum_comment":"","sum_hidden":false,"sum_unclear":false,"sum_foreign":""},"56":{"sum_foreign_comment":"","sum":"","sum_comment":"","sum_hidden":false,"sum_unclear":false,"sum_foreign":""},"57":{"sum_foreign_comment":"","sum":"","sum_comment":"","sum_comment_unclear":false,"sum_comment_hidden":false,"sum_foreign":""},"58":{"sum_foreign_comment":"","sum_comment_hidden":false,"sum":"","sum_comment":"","sum_foreign":""},"59":{"sum_foreign_comment":"","sum":"","sum_comment":"","sum_foreign":""},"60":{"sum_foreign_comment":"","sum":"","sum_hidden":false,"sum_comment":"","sum_foreign":""},"61":{"sum_foreign_comment":"","sum":"","sum_comment":"","sum_foreign":""},"62":{"sum_foreign_comment":"","sum":"","sum_comment":"","sum_foreign":""},"63":{"sum_foreign_comment":"","sum":"","sum_comment":"","sum_comment_unclear":false,"sum_unclear":false,"sum_foreign":""},"64":{"sum_foreign_comment":"","sum":"","sum_comment":"","sum_comment_unclear":false,"sum_unclear":false,"sum_foreign":""}},"ft_src":"суддя київського апеляційного господарського суду\nм. Київ\nАпеляційний господарський суд\nПантелієнко Віталій Олегович\nПантелієнко\nВіталій\nПантелієнко В. В\nДитина\nПантелієнко Віталій Олегович\nВіталій Олегович Пантелієнко\nВіталій Пантелієнко\nПантелієнко Віталій Олегович\nОлегович\nMitsubishi ASX\n1998 куб. см., 150 к. с., 429.5 см\n2013\n897\n72.4\n2013\n7060\n229933\n12617\n7060\n242550\n1998 куб. см., 150 к. с., 429.5 см\nMitsubishi ASX\n2013\n2013\nАпеляційний господарський суд\nм. Київ\nсуддя київського апеляційного господарського суду\nОлегович\nПантелієнко Віталій Олегович\nВіталій Олегович Пантелієнко\nВіталій Пантелієнко\nПантелієнко Віталій Олегович\nВіталій\nДитина\nПантелієнко В. В\nПантелієнко Віталій Олегович\nПантелієнко\n7060\n229933\n242550\n7060\n12617\n897\n72.4\nДитина\nПантелієнко В. В\nОлегович\nПантелієнко\nм. Київ\nАпеляційний господарський суд\nсуддя київського апеляційного господарського суду\nПантелієнко Віталій Олегович\nПантелієнко Віталій Олегович\nВіталій Олегович Пантелієнко\nВіталій Пантелієнко\nПантелієнко Віталій Олегович\nВіталій\n2013\n1998 куб. см., 150 к. с., 429.5 см\nMitsubishi ASX\n12617\n242550\n7060\n229933\n7060\n72.4\n897\n2013","general":{"inn":"","family_raw":"","last_name":"Пантелієнко","post":{"region_unclear":false,"region":"м. Київ","post":"суддя київського апеляційного господарського суду","office":"Апеляційний господарський суд","office_unclear":false,"post_hidden":false},"name":"Віталій","full_name":"Пантелієнко Віталій Олегович","inn_hidden":false,"family":[{"inn":"","relations":"Дитина","relations_other":"","inn_hidden":false,"family_name":"Пантелієнко В. В","name_hidden":false,"name_unclear":false}],"full_name_suggest":{"output":"Пантелієнко Віталій Олегович","input":["Пантелієнко Віталій Олегович","Віталій Олегович Пантелієнко","Віталій Пантелієнко"]},"patronymic":"Олегович"},"source":"VULYK","estate":{"23":[{"space_hidden":false,"costs":"","costs_comment":"","address_hidden":false,"region_hidden":false,"space_comment":"","space_unclear":false,"space":"897","address":"","region":"","space_units_unclear":false,"space_comment_unclear":false,"space_units":"м²","costs_rent":"","costs_rent_comment":""}],"25":[{"space_hidden":false,"costs":"","costs_comment":"","address_hidden":false,"region_hidden":false,"space_comment":"","space_unclear":false,"space":"72.4","address":"","region":"","costs_rent_comment":"","space_units":"м²","costs_rent":""}]},"intro":{"declaration_year":"2013","isnotdeclaration":"","declaration_year_unclear":false}}