{"income":{"5":{"value":"1286599","family_unclear":false,"family_hidden":false,"family_comment":"","family":"4344","comment":""},"6":{"value":"207982","family_comment":"","value_unclear":false,"family_hidden":false,"family_unclear":false,"family":"","comment":""},"7":{"value":"","family_hidden":false,"value_hidden":false,"family_comment":"","source_name":"","family":"","comment":"","source_name_hidden":false},"8":{"family_comment":"","value":"","family":"","comment":""},"9":{"family_comment":"","value":"","family":"","comment":""},"10":{"family_comment":"","value":"12617","value_unclear":false,"family":"","comment":""},"11":{"family_comment":"","value":"1066000","family":"","comment":""},"12":{"family_comment":"","value":"","family":"","comment":""},"13":{"family_comment":"","value":"","family":"","comment":""},"14":{"family_comment":"","value":"","family":"","comment":""},"15":{"family_comment":"","value":"","family":"","comment":""},"16":{"family_comment":"","value":"","family":"","comment":""},"17":{"family_comment":"","value":"","family":"","comment":""},"18":{"family_comment":"","value":"","family":"","comment":""},"19":{"family_comment":"","value":"","family":"","comment":""},"20":{"value":"","family_comment":"","value_unclear":false,"family_unclear":false,"comment_unclear":false,"comment":"","family":""}},"vehicle":{"35":[{"brand_info":"1.6 л","sum_rent_comment":"","year":"2007","brand_info_hidden":false,"brand_info_unclear":false,"year_unclear":false,"sum_rent":"","sum":"","brand":"Nissan Note","sum_comment":"","brand_unclear":false,"brand_hidden":false}]},"id":"vulyk_74_59","declaration":{"additional_info_text":"","notfull_lostpages":"","date":"2014-12-10T00:00:00","notfull":"","additional_info":"","url":"http://static.declarations.com.ua/declarations/chosen_ones/judges_batch/1722_tarasenko_karolina_vitaliivna.pdf"},"liabilities":{"54":{"sum_foreign_comment":"","sum":"","sum_comment":"","sum_comment_unclear":false,"sum_comment_hidden":false,"sum_foreign":""},"55":{"sum_foreign_comment":"","sum":"","sum_comment":"","sum_hidden":false,"sum_unclear":false,"sum_foreign":""},"56":{"sum_foreign_comment":"","sum":"","sum_comment":"","sum_hidden":false,"sum_unclear":false,"sum_foreign":""},"57":{"sum_foreign_comment":"","sum":"902000","sum_comment":"","sum_comment_unclear":false,"sum_comment_hidden":false,"sum_foreign":""},"58":{"sum_foreign_comment":"","sum_comment_hidden":false,"sum":"","sum_comment":"","sum_foreign":""},"59":{"sum_foreign_comment":"","sum":"","sum_comment":"","sum_foreign":""},"60":{"sum_foreign_comment":"","sum":"","sum_hidden":false,"sum_comment":"","sum_foreign":""},"61":{"sum_foreign_comment":"","sum":"","sum_comment":"","sum_foreign":""},"62":{"sum_foreign_comment":"","sum":"","sum_comment":"","sum_foreign":""},"63":{"sum_foreign_comment":"","sum":"","sum_comment":"","sum_comment_unclear":false,"sum_unclear":false,"sum_foreign":""},"64":{"sum_foreign_comment":"","sum":"","sum_comment":"","sum_comment_unclear":false,"sum_unclear":false,"sum_foreign":""}},"ft_src":"902000\nсуддя київського апеляційного господарського суду\nм. Київ\nАпеляційний господарський суд\nТарасенко Кароліна Віталіївна\nТарасенко\nКароліна\nТарасенко Віталій\nДитина\nТарасенко Кароліна Віталіївна\nКароліна Віталіївна Тарасенко\nКароліна Тарасенко\nТарасенко Кароліна Віталіївна\nВіталіївна\n1.6 л\nNissan Note\n2007\n27.9\n27.9\n2013\n207982\n1066000\n12617\n4344\n1286599\n1.6 л\nNissan Note\n2007\n2013\nАпеляційний господарський суд\nм. Київ\nсуддя київського апеляційного господарського суду\nВіталіївна\nТарасенко Кароліна Віталіївна\nКароліна Віталіївна Тарасенко\nКароліна Тарасенко\nТарасенко Кароліна Віталіївна\nКароліна\nДитина\nТарасенко Віталій\nТарасенко Кароліна Віталіївна\nТарасенко\n902000\n207982\n1286599\n4344\n12617\n1066000\n27.9\n27.9\n902000\nДитина\nТарасенко Віталій\nВіталіївна\nТарасенко\nм. Київ\nАпеляційний господарський суд\nсуддя київського апеляційного господарського суду\nТарасенко Кароліна Віталіївна\nТарасенко Кароліна Віталіївна\nКароліна Віталіївна Тарасенко\nКароліна Тарасенко\nТарасенко Кароліна Віталіївна\nКароліна\nNissan Note\n1.6 л\n2007\n1066000\n12617\n1286599\n4344\n207982\n27.9\n27.9\n2013","general":{"inn":"","family_raw":"","last_name":"Тарасенко","post":{"region_unclear":false,"region":"м. Київ","post":"суддя київського апеляційного господарського суду","office":"Апеляційний господарський суд","office_unclear":false,"post_hidden":false},"name":"Кароліна","full_name":"Тарасенко Кароліна Віталіївна","inn_hidden":false,"family":[{"inn":"","relations":"Дитина","relations_other":"","inn_hidden":false,"family_name":"Тарасенко Віталій","name_hidden":false,"name_unclear":false}],"full_name_suggest":{"output":"Тарасенко Кароліна Віталіївна","input":["Тарасенко Кароліна Віталіївна","Кароліна Віталіївна Тарасенко","Кароліна Тарасенко"]},"patronymic":"Віталіївна"},"source":"VULYK","estate":{"25":[{"space_hidden":false,"costs":"","costs_comment":"","address_hidden":false,"region_hidden":false,"space_comment":"","space_unclear":false,"space":"27.9","address":"","region":"","costs_rent_comment":"","space_units":"м²","costs_rent":""}],"31":[{"space_unclear":false,"address_hidden":false,"region_hidden":false,"space_comment":"","space":"27.9","address":"","region":"","costs_property":"","costs_rent_comment":"","address_unclear":false,"space_units":"м²","costs_property_comment":"","costs_rent":""}]},"intro":{"declaration_year":"2013","isnotdeclaration":"","declaration_year_unclear":false}}