{"income":{"5":{"value":"294968","family_comment":"","value_unclear":false,"family_hidden":false,"value_hidden":false,"family_unclear":false,"family":"84937","comment":"","family_comment_unclear":false},"6":{"family_comment":"","family_unclear":false,"value":"241297","family":"48128","comment":""},"7":{"source_name_unclear":false,"value":"","family_comment":"","source_name":"","family":"","comment":"","source_name_hidden":false},"8":{"family_comment":"","value":"","family":"","comment":""},"9":{"family_comment":"","family_unclear":false,"value":"","family":"","comment":""},"10":{"family_comment":"","value":"","family":"","comment":""},"11":{"family_comment":"","value":"","family":"","comment":""},"12":{"family_comment":"","value":"","family":"","comment":""},"13":{"family_comment":"","value":"","family":"","comment":""},"14":{"family_comment":"","value":"","family":"","comment":""},"15":{"family_comment":"","value":"53671","family":"36809","comment":""},"16":{"value":"","value_unclear":false,"value_hidden":false,"family_comment":"","family":"","comment":""},"17":{"family_comment":"","value":"","family":"","comment":""},"18":{"family_comment":"","value":"","family":"","comment":""},"19":{"family_comment":"","value":"","family":"","comment":""},"20":{"value":"","family_comment":"","value_unclear":false,"comment_hidden":false,"family_hidden":false,"family":"","value_hidden":false,"family_unclear":false,"comment_unclear":false,"comment":"","family_comment_unclear":false}},"vehicle":{"40":[{"brand_info":"1798","sum":"","brand":"Skoda Octavia","sum_comment":"","brand_unclear":false,"year":"2011","brand_hidden":false,"brand_info_hidden":false,"brand_info_unclear":false,"sum_rent_comment":"","sum_rent":""},{"brand_info":"H, 1.4","sum_rent_comment":"","brand":"Opel Astra","sum_comment":"","year":"2008","brand_hidden":false,"brand_info_unclear":false,"sum":"","sum_rent":""}]},"id":"vulyk_62_10","banks":{"45":[{"sum_units":"UAH","sum_hidden":false,"sum_foreign_units_hidden":false,"sum":"160000","sum_foreign":"","sum_foreign_comment":"","sum_foreign_hidden":false,"sum_comment":"","sum_comment_unclear":false,"sum_foreign_units":"UAH","sum_comment_hidden":false,"sum_unclear":false}],"51":[{"sum_units":"UAH","sum_hidden":false,"sum_foreign_units_hidden":false,"sum":"77300","sum_foreign":"","sum_foreign_comment":"","sum_foreign_hidden":false,"sum_comment":"","sum_comment_unclear":false,"sum_foreign_units":"UAH","sum_comment_hidden":false,"sum_unclear":false}]},"declaration":{"additional_info_text":"","notfull_lostpages":"","date":"2015-03-31T00:00:00","notfull":"","additional_info":"","url":"http://static.declarations.com.ua/declarations/chosen_ones/mega_batch/alforova_tetiana_mykhailivna.pdf"},"liabilities":{"54":{"sum_foreign_comment":"","sum":"","sum_comment":"","sum_hidden":false,"sum_comment_hidden":false,"sum_foreign":""},"55":{"sum_foreign_comment":"","sum":"","sum_comment":"","sum_hidden":false,"sum_comment_hidden":false,"sum_unclear":false,"sum_foreign":""},"56":{"sum_foreign_comment":"","sum":"","sum_comment":"","sum_hidden":false,"sum_unclear":false,"sum_foreign":""},"57":{"sum_foreign_comment":"","sum":"","sum_comment":"","sum_hidden":false,"sum_comment_hidden":false,"sum_unclear":false,"sum_foreign":""},"58":{"sum_foreign_comment":"","sum_foreign_hidden":false,"sum_comment":"","sum_hidden":false,"sum_comment_hidden":false,"sum_unclear":false,"sum":"","sum_foreign":""},"59":{"sum_foreign_comment":"","sum":"","sum_comment":"","sum_foreign":""},"60":{"sum_foreign_comment":"","sum_foreign_hidden":false,"sum_comment":"","sum_hidden":false,"sum_comment_hidden":false,"sum_unclear":false,"sum":"","sum_foreign":""},"61":{"sum_foreign_comment":"","sum_foreign_hidden":false,"sum_comment":"","sum_hidden":false,"sum":"","sum_foreign":""},"62":{"sum_foreign_comment":"","sum":"","sum_comment":"","sum_unclear":false,"sum_foreign":""},"63":{"sum_foreign_comment":"","sum":"","sum_comment":"","sum_hidden":false,"sum_comment_hidden":false,"sum_unclear":false,"sum_foreign":""},"64":{"sum_foreign_comment":"","sum":"","sum_comment":"","sum_comment_unclear":false,"sum_hidden":false,"sum_comment_hidden":false,"sum_foreign":""}},"ft_src":"суддя фрунзенського райсуду м. харкова\nХарківська область\nЗагальний місцевий суд\nТетяна\nАлфьоров Є. А\nПодружжя\nАлфьоров А. Є\nДитина\nАлфьоров М. Є\nДитина\nМихайлівна\nАлфьорова Тетяна Михайлівна\nТетяна Михайлівна Алфьорова\nТетяна Алфьорова\nАлфьорова Тетяна Михайлівна\nАлфьорова Тетяна Михайлівна\nАлфьорова\nSkoda Octavia\n1798\n2011\n2008\nOpel Astra\nH, 1.4\n77300\n160000\n2014\n1798\n2011\nSkoda Octavia\nH, 1.4\n2008\nOpel Astra\n160000\n77300\n700\n139.3\n28.3\n38.9\nПодружжя\nАлфьоров Є. А\nДитина\nАлфьоров А. Є\nДитина\nАлфьоров М. Є\nАлфьорова Тетяна Михайлівна\nТетяна Михайлівна Алфьорова\nТетяна Алфьорова\nАлфьорова Тетяна Михайлівна\nАлфьорова Тетяна Михайлівна\nТетяна\nМихайлівна\nЗагальний місцевий суд\nсуддя фрунзенського райсуду м. харкова\nХарківська область\nАлфьорова\n241297\n48128\n53671\n36809\n294968\n84937\n2014\n38.9\n139.3\n28.3\n700\nПодружжя\nАлфьоров Є. А\nАлфьоров А. Є\nДитина\nАлфьоров М. Є\nДитина\nМихайлівна\nАлфьорова\nТетяна\nАлфьорова Тетяна Михайлівна\nТетяна Михайлівна Алфьорова\nТетяна Алфьорова\nАлфьорова Тетяна Михайлівна\nХарківська область\nсуддя фрунзенського райсуду м. харкова\nЗагальний місцевий суд\nАлфьорова Тетяна Михайлівна\n48128\n241297\n36809\n53671\n84937\n294968\nSkoda Octavia\n1798\n2011\n2008\nH, 1.4\nOpel Astra\n36809\n53671\n294968\n84937\n48128\n241297\n139.3\n38.9\n28.3\n700\n160000\n77300\n2014","general":{"inn":"","name":"Тетяна","inn_unclear":false,"family":[{"inn":"","inn_hidden":true,"relations_unclear":false,"relations_hidden":false,"relations_other":"","relations":"Подружжя","name_hidden":true,"inn_unclear":false,"family_name":"Алфьоров Є. А","name_unclear":false},{"inn":"","inn_hidden":false,"relations_hidden":false,"family_name":"Алфьоров А. Є","relations_other":"","relations":"Дитина","name_hidden":false,"name_unclear":false},{"inn":"","relations":"Дитина","relations_other":"","inn_hidden":false,"family_name":"Алфьоров М. Є","name_hidden":false,"name_unclear":false}],"inn_hidden":true,"family_raw":"","last_name":"Алфьорова","post":{"post_unclear":false,"post":"суддя фрунзенського райсуду м. харкова","post_hidden":false,"region":"Харківська область","region_hidden":false,"office":"Загальний місцевий суд","office_hidden":false,"office_unclear":false},"full_name_suggest":{"output":"Алфьорова Тетяна Михайлівна","input":["Алфьорова Тетяна Михайлівна","Тетяна Михайлівна Алфьорова","Тетяна Алфьорова"]},"full_name":"Алфьорова Тетяна Михайлівна","addresses":[{"place_city_type_unclear":false,"place_address":"","place_district_hidden":true,"place_city_type":"","place_address_hidden":true,"place_address_unclear":false,"place_city_type_hidden":true,"place":"","place_district":"","place_unclear":false,"place_city":"","place_city_unclear":false,"place_hidden":true,"place_city_hidden":true,"place_district_unclear":false}],"patronymic":"Михайлівна","last_name_unclear":false,"name_unclear":false},"source":"VULYK","estate":{"29":[{"region_unclear":false,"space_hidden":false,"address_hidden":true,"region_hidden":true,"space_comment":"","space_unclear":false,"space":"700","address":"","region":"","costs_property":"","costs_rent_comment":"","address_unclear":false,"space_units":"м²","costs_property_comment":"","costs_rent":""}],"30":[{"space_hidden":false,"address_hidden":true,"region_hidden":true,"space_comment":"","space_unclear":false,"space":"139.3","address":"","region":"","costs_property":"","costs_rent_comment":"","space_comment_unclear":false,"address_unclear":false,"space_units":"м²","costs_property_comment":"","costs_rent":""}],"33":[{"space_hidden":false,"address_hidden":true,"region_hidden":true,"space_comment":"","space":"38.9","address":"","region":"","costs_property":"","costs_rent_comment":"","address_unclear":false,"space_units":"м²","costs_property_comment":"","costs_rent":""}],"34":[{"space_unclear":false,"address_hidden":true,"region_hidden":true,"space_comment":"","space_hidden":false,"space":"28.3","address":"","region":"","costs_property":"","costs_rent_comment":"","space_units":"м²","costs_property_comment":"","costs_rent":""}]},"intro":{"declaration_year":"2014","isnotdeclaration":"","declaration_year_unclear":false,"declaration_year_hidden":false}}