{"income":{"5":{"family_comment":"","value":"281568.59","family":"71334","comment":""},"6":{"value":"245865.67","family_comment":"","value_unclear":false,"comment_hidden":false,"family_unclear":false,"family":"","comment":""},"7":{"family_comment":"","value":"","source_name":"","family":"","comment":""},"8":{"family_comment":"","value":"","family":"","comment":""},"9":{"family_comment":"","family_unclear":false,"value":"35.92","family":"","comment":""},"10":{"family_comment":"","value":"","value_unclear":false,"family":"","comment":""},"11":{"family_comment":"","value":"","family":"","comment":""},"12":{"family_comment":"","value":"","family":"","comment":""},"13":{"family_comment":"","value":"","family":"","comment":""},"14":{"family_comment":"","value":"","family":"","comment":""},"15":{"family_comment":"","value":"","family":"","comment":""},"16":{"family_comment":"","value":"35667","family":"71334","comment":""},"17":{"family_comment":"","value":"","family":"","comment":""},"18":{"family_comment":"","value":"","family":"","comment":""},"19":{"family_comment":"","value":"","family":"","comment":""},"20":{"value":"","family":"","value_unclear":false,"family_hidden":false,"family_comment":"","comment_unclear":false,"comment":"","family_comment_unclear":false}},"vehicle":{"35":[{"year_hidden":false,"brand_info":"об'єм 2.2","sum_rent_comment":"","year":"2008","brand_info_hidden":false,"brand_info_unclear":false,"sum_rent":"","sum":"","brand":"Hyundai Santa FE","sum_comment":"","brand_unclear":false,"brand_hidden":false}]},"id":"vulyk_97_41","declaration":{"additional_info_text":"","notfull_lostpages":"","date":"2015-03-27T00:00:00","notfull":"","additional_info":"","url":"http://static.declarations.com.ua/declarations/chosen_ones/judges_batch/3869_osedach_mykola_mykolaiovych.pdf"},"liabilities":{"54":{"sum_foreign_comment":"","sum":"","sum_comment":"","sum_comment_unclear":false,"sum_hidden":false,"sum_comment_hidden":false,"sum_unclear":false,"sum_foreign":""},"55":{"sum_foreign_comment":"","sum":"","sum_comment":"","sum_foreign":""},"56":{"sum_foreign_comment":"","sum":"","sum_comment":"","sum_foreign":""},"57":{"sum_foreign_comment":"","sum":"","sum_comment":"","sum_comment_unclear":false,"sum_hidden":false,"sum_comment_hidden":false,"sum_unclear":false,"sum_foreign":""},"58":{"sum_foreign_comment":"","sum":"","sum_comment":"","sum_comment_unclear":false,"sum_hidden":false,"sum_comment_hidden":false,"sum_unclear":false,"sum_foreign":""},"59":{"sum_foreign_comment":"","sum":"","sum_comment":"","sum_foreign":""},"60":{"sum_foreign_comment":"","sum":"","sum_comment":"","sum_comment_unclear":false,"sum_hidden":false,"sum_comment_hidden":false,"sum_foreign":""},"61":{"sum_foreign_comment":"","sum":"","sum_comment":"","sum_foreign":""},"62":{"sum_foreign_comment":"","sum":"","sum_comment":"","sum_unclear":false,"sum_foreign":""},"63":{"sum_foreign_comment":"","sum":"","sum_hidden":false,"sum_comment":"","sum_foreign":""},"64":{"sum_foreign_comment":"","sum":"","sum_comment":"","sum_foreign":""}},"ft_src":"суддя апеляційного суду чернігівської області\nЧернігівська область\nЗагальний апеляційний суд\nМикола\nОседач Н. Г. 14. 09. 1975\nПодружжя\nОседач В. М. 25. 06. 1997\nДитина\nОседач Д. М. 06. 11. 2006\nДитина\nМиколайович\nОседач Микола Миколайович\nМикола Миколайович Оседач\nМикола Оседач\nОседач Микола Миколайович\nОседач Микола Миколайович\nОседач\nоб'єм 2.2\nHyundai Santa FE\n2008\n1200\n1700\n105\n58\n2014\n245865.67\n35.92\n71334\n281568.59\n71334\n35667\nоб'єм 2.2\nHyundai Santa FE\n2008\n2014\nОседач Микола Миколайович\nМикола Миколайович Оседач\nМикола Оседач\nОседач Микола Миколайович\nМикола\nПодружжя\nОседач Н. Г. 14. 09. 1975\nДитина\nОседач В. М. 25. 06. 1997\nДитина\nОседач Д. М. 06. 11. 2006\nОседач Микола Миколайович\nОседач\nЗагальний апеляційний суд\nЧернігівська область\nсуддя апеляційного суду чернігівської області\nМиколайович\n245865.67\n281568.59\n71334\n35667\n71334\n35.92\n1200\n1700\n58\n105\nПодружжя\nОседач Н. Г. 14. 09. 1975\nОседач В. М. 25. 06. 1997\nДитина\nДитина\nОседач Д. М. 06. 11. 2006\nМиколайович\nОседач\nМикола\nОседач Микола Миколайович\nМикола Миколайович Оседач\nМикола Оседач\nОседач Микола Миколайович\nЧернігівська область\nЗагальний апеляційний суд\nсуддя апеляційного суду чернігівської області\nОседач Микола Миколайович\n2008\nHyundai Santa FE\nоб'єм 2.2\n35.92\n71334\n281568.59\n71334\n35667\n245865.67\n105\n1200\n1700\n58\n2014","general":{"name_hidden":false,"name":"Микола","last_name_hidden":false,"inn":"","family":[{"inn":"","relations":"Подружжя","relations_other":"","inn_hidden":true,"family_name":"Оседач Н. Г. 14. 09. 1975","name_hidden":false,"name_unclear":false},{"inn_hidden":false,"inn":"","name_hidden":false,"family_name":"Оседач В. М. 25. 06. 1997","relations":"Дитина","name_unclear":false},{"inn":"","relations":"Дитина","relations_other":"","inn_hidden":true,"family_name":"Оседач Д. М. 06. 11. 2006","name_hidden":false,"name_unclear":false}],"patronymic":"Миколайович","inn_hidden":true,"family_raw":"","inn_unclear":false,"post":{"region_unclear":false,"region":"Чернігівська область","post":"суддя апеляційного суду чернігівської області","office":"Загальний апеляційний суд","office_unclear":false,"post_hidden":false},"full_name":"Оседач Микола Миколайович","addresses":[{"place_district":"","place_city_hidden":true,"place_city":"","place_city_unclear":false,"place_district_hidden":false,"place_city_type":"","place_address_hidden":true,"place_city_type_hidden":false,"place_address":"","place_hidden":true,"place":""}],"last_name":"Оседач","patronymic_hidden":false,"full_name_suggest":{"output":"Оседач Микола Миколайович","input":["Оседач Микола Миколайович","Микола Миколайович Оседач","Микола Оседач"]}},"source":"VULYK","estate":{"23":[{"region_unclear":false,"space_unclear":false,"costs":"","costs_rent_unclear":false,"costs_comment":"","address_hidden":false,"region_hidden":true,"space_comment":"","space":"1200","address":"","region":"","address_unclear":false,"costs_rent_comment":"","space_units":"м²","costs_rent":""},{"region_unclear":false,"costs":"","costs_rent_unclear":false,"costs_comment":"","region_hidden":false,"space_comment":"","space":"1700","address":"","region":"","address_unclear":false,"costs_rent_comment":"","space_units":"м²","costs_rent":""}],"24":[{"region_unclear":false,"space_unclear":false,"costs":"","costs_comment":"","address_hidden":false,"region_hidden":true,"space_comment":"","space_hidden":false,"space":"58","address":"","region":"","address_unclear":false,"costs_rent_comment":"","space_comment_unclear":false,"space_units":"м²","costs_rent":""}],"31":[{"space_unclear":false,"address_hidden":true,"region_hidden":true,"space_comment":"","space_hidden":false,"space":"105","address":"","region":"","costs_property":"","costs_rent_comment":"","space_comment_hidden":false,"space_units":"м²","costs_property_comment":"","costs_rent":""}]},"intro":{"declaration_year":"2014","isnotdeclaration":""}}