{"income":{"5":{"value":"356258","value_unclear":false,"value_hidden":false,"family_comment":"","family":"60850","comment":""},"6":{"value":"258011","family_comment":"","value_unclear":false,"family_unclear":false,"family":"60850","comment":""},"7":{"source_name_unclear":false,"value":"","family_hidden":false,"family_comment":"","source_name":"","family":"","comment":""},"8":{"family_comment":"","value":"","family":"","comment":""},"9":{"family_comment":"","value":"2869","family":"","comment":""},"10":{"family_comment":"","value":"","family":"","comment":""},"11":{"family_comment":"","value":"","family":"","comment":""},"12":{"family_comment":"","value":"","family":"","comment":""},"13":{"family_comment":"","value":"","family":"","comment":""},"14":{"family_comment":"","value":"","family":"","comment":""},"15":{"family_comment":"","value":"","family":"","comment":""},"16":{"family_comment":"","value":"","comment_unclear":false,"family":"","comment":""},"17":{"family_comment":"","family_unclear":false,"value":"","family":"","comment":""},"18":{"family_comment":"","value":"","family":"","comment":""},"19":{"value":"","family_hidden":false,"value_hidden":false,"family_comment":"","family":"","comment":""},"20":{"family_comment":"","value":"95378","comment_unclear":false,"family":"","comment":""}},"vehicle":{"35":[{"brand_info":"1500 куб. см., спільна сумісна з дружиною","sum_rent_comment":"","year":"2004","sum_rent_unclear":false,"brand_info_hidden":false,"brand_info_unclear":false,"year_unclear":false,"sum_rent":"","sum":"","brand":"Daewoo Nexia","sum_comment":"","sum_comment_unclear":false,"brand_hidden":false,"sum_unclear":false,"brand_unclear":false}],"40":[{"brand_info":"1500 куб. см., спільна сумісна з декларантом","sum_rent_comment":"","brand":"Daewoo Nexia","sum_comment":"","brand_unclear":false,"year":"2004","brand_info_unclear":false,"year_unclear":false,"sum":"","sum_rent":""}]},"id":"vulyk_67_162","banks":{"45":[{"sum_foreign_comment":"","sum":"108675","sum_comment":"","sum_comment_unclear":false,"sum_hidden":false,"sum_foreign_units":"UAH","sum_foreign_hidden":false,"sum_units":"UAH","sum_comment_hidden":false,"sum_unclear":false,"sum_foreign":""}],"46":[{"sum_foreign_comment":"","sum_units":"UAH","sum_comment":"","sum_foreign_units":"UAH","sum":"92480","sum_foreign":""}]},"declaration":{"additional_info_text":"Декларація уточнена","notfull_lostpages":"","date":"2015-07-28T00:00:00","notfull":"","additional_info":"1","url":"http://static.declarations.com.ua/declarations/chosen_ones/mega_batch/kryvka_volodymyr_pavlovych.pdf"},"liabilities":{"54":{"sum_foreign_comment":"","sum_foreign_hidden":false,"sum_comment":"","sum_comment_unclear":false,"sum_hidden":false,"sum":"","sum_unclear":false,"sum_foreign":""},"55":{"sum_foreign_comment":"","sum":"","sum_comment":"","sum_foreign":""},"56":{"sum_foreign_comment":"","sum_foreign_hidden":false,"sum_comment":"","sum_hidden":false,"sum":"","sum_unclear":false,"sum_foreign":""},"57":{"sum_foreign_comment":"","sum_foreign_hidden":false,"sum_comment":"","sum_comment_unclear":false,"sum_hidden":false,"sum_comment_hidden":false,"sum_unclear":false,"sum":"17288","sum_foreign":""},"58":{"sum_foreign_comment":"","sum_foreign_hidden":false,"sum_comment":"","sum_comment_unclear":false,"sum_hidden":false,"sum_comment_hidden":false,"sum_unclear":false,"sum":"66183","sum_foreign":""},"59":{"sum_foreign_comment":"","sum":"","sum_hidden":false,"sum_comment":"","sum_foreign":""},"60":{"sum_foreign_comment":"","sum":"","sum_comment":"","sum_foreign":""},"61":{"sum_foreign_comment":"","sum_foreign_hidden":false,"sum_comment":"","sum_hidden":false,"sum":"","sum_foreign":""},"62":{"sum_foreign_comment":"","sum":"","sum_hidden":false,"sum_comment":"","sum_foreign":""},"63":{"sum_foreign_comment":"","sum":"","sum_comment":"","sum_comment_unclear":false,"sum_hidden":false,"sum_unclear":false,"sum_foreign":""},"64":{"sum_foreign_comment":"","sum":"","sum_comment":"","sum_hidden":false,"sum_unclear":false,"sum_foreign":""}},"ft_src":"17288\n66183\nДекларація уточнена\n1\n2397103412\nголова суду, суддя міжгірського районного суду закарпатської області\nЗакарпатська область\nЗагальний місцевий суд\nВолодимир\n2457211242\nКривка М. Я\nПодружжя\nПавлович\nКривка Володимир Павлович\nКривка\nКривка Володимир Павлович\nВолодимир Павлович Кривка\nВолодимир Кривка\nКривка Володимир Павлович\n1500 куб. см., спільна сумісна з дружиною\nDaewoo Nexia\n2004\n1500 куб. см., спільна сумісна з декларантом\nDaewoo Nexia\n2004\n92480\n108675\n1\nДекларація уточнена\n2014\n1500 куб. см., спільна сумісна з дружиною\nDaewoo Nexia\n2004\n1500 куб. см., спільна сумісна з декларантом\n2004\nDaewoo Nexia\nДекларація уточнена\n1\n108675\n92480\n132\nспільна сумісна з декларантом\n51\nспільна сумісна з дружиною і дітьми\n59.2\n1/3 частина квартири, спадщина\n398\nспільна сумісна з дружиною\n398\nспільна сумісна з декларантом\n132\nспільна сумісна з дружиною\n51\nспільна сумісна з декларантом і дітьми\nЗагальний місцевий суд\nголова суду, суддя міжгірського районного суду закарпатської області\nЗакарпатська область\nПодружжя\nКривка М. Я\n2457211242\nКривка Володимир Павлович\nВолодимир Павлович Кривка\nВолодимир Кривка\nКривка Володимир Павлович\nКривка Володимир Павлович\n2397103412\nВолодимир\nКривка\nПавлович\n17288\n66183\n60850\n258011\n95378\n356258\n60850\n2869\n2014\n66183\n17288\nспільна сумісна з декларантом\n398\nспільна сумісна з дружиною\n132\nспільна сумісна з декларантом і дітьми\n51\nспільна сумісна з декларантом\n132\nспільна сумісна з дружиною\n398\nспільна сумісна з дружиною і дітьми\n51\n1/3 частина квартири, спадщина\n59.2\n2457211242\nПодружжя\nКривка М. Я\n2397103412\nПавлович\nКривка\nВолодимир\nКривка Володимир Павлович\nВолодимир Павлович Кривка\nВолодимир Кривка\nКривка Володимир Павлович\nЗакарпатська область\nголова суду, суддя міжгірського районного суду закарпатської області\nЗагальний місцевий суд\nКривка Володимир Павлович\n60850\n258011\n60850\n356258\n2869\n95378\n2004\nDaewoo Nexia\n1500 куб. см., спільна сумісна з дружиною\n2004\n1500 куб. см., спільна сумісна з декларантом\nDaewoo Nexia\n95378\n356258\n60850\n2869\n258011\n60850\nспільна сумісна з декларантом і дітьми\n51\nспільна сумісна з дружиною\n398\nспільна сумісна з дружиною\n132\nспільна сумісна з декларантом\n132\nспільна сумісна з дружиною і дітьми\n51\n1/3 частина квартири, спадщина\n59.2\nспільна сумісна з декларантом\n398\n108675\n92480\n2014","general":{"inn":"2397103412","name":"Володимир","patronymic_unclear":false,"last_name_hidden":false,"family":[{"inn":"2457211242","inn_hidden":false,"relations_unclear":false,"relations_hidden":false,"relations_other":"","relations":"Подружжя","name_hidden":false,"inn_unclear":false,"family_name":"Кривка М. Я","name_unclear":false}],"patronymic":"Павлович","inn_hidden":false,"family_raw":"","inn_unclear":false,"post":{"post_unclear":false,"post":"голова суду, суддя міжгірського районного суду закарпатської області","post_hidden":false,"region":"Закарпатська область","region_hidden":false,"office":"Загальний місцевий суд","office_hidden":false,"office_unclear":false},"last_name_unclear":false,"full_name":"Кривка Володимир Павлович","addresses":[{"place_city_type_hidden":false,"place_district_hidden":false,"place_city_type":"","place_city_hidden":true,"place_address_unclear":false,"place_address":"","place":"","place_district":"","place_unclear":false,"place_city":"","place_city_unclear":false,"place_hidden":false,"place_address_hidden":true,"place_district_unclear":false}],"last_name":"Кривка","full_name_suggest":{"output":"Кривка Володимир Павлович","input":["Кривка Володимир Павлович","Володимир Павлович Кривка","Володимир Кривка"]},"name_unclear":false},"source":"VULYK","estate":{"23":[{"space_hidden":false,"costs":"","costs_comment":"","costs_hidden":false,"address_hidden":false,"region_hidden":true,"space_comment":"спільна сумісна з дружиною","space_unclear":false,"space":"398","address":"","region":"","address_unclear":false,"space_units_unclear":false,"costs_rent_hidden":false,"space_comment_unclear":false,"space_units":"м²","costs_rent":"","costs_rent_comment":""}],"24":[{"space_hidden":false,"costs":"","costs_comment":"","costs_hidden":false,"address_hidden":false,"region_hidden":true,"space_comment":"спільна сумісна з дружиною","space":"132","address":"","region":"","costs_rent_comment":"","space_comment_unclear":false,"space_units":"м²","costs_rent":""}],"25":[{"space_unclear":false,"costs":"","costs_comment":"","costs_hidden":false,"address_hidden":false,"region_hidden":true,"space_comment":"спільна сумісна з дружиною і дітьми","space":"51","address":"","region":"","address_unclear":false,"space_units_unclear":false,"space_comment_unclear":false,"space_units":"м²","costs_rent":"","costs_rent_comment":""},{"costs_rent":"","region":"","costs":"","costs_rent_comment":"","costs_comment":"","region_hidden":false,"space_comment":"1/3 частина квартири, спадщина","space_units":"м²","space":"59.2","address":""}],"29":[{"region_unclear":false,"space_unclear":false,"address_hidden":true,"region_hidden":true,"space_comment":"спільна сумісна з декларантом","space_units_hidden":false,"space_hidden":false,"space":"398","address":"","region":"","costs_property":"","costs_rent_comment":"","space_units":"м²","costs_property_comment":"","costs_rent":""}],"30":[{"region_unclear":false,"space_hidden":false,"address_hidden":true,"region_hidden":true,"space_comment":"спільна сумісна з декларантом","space":"132","address":"","region":"","costs_property":"","costs_rent_comment":"","space_comment_unclear":false,"space_units":"м²","costs_property_comment":"","costs_rent":""}],"31":[{"space_hidden":false,"address_hidden":true,"region_hidden":true,"space_comment":"спільна сумісна з декларантом і дітьми","space_unclear":false,"space":"51","address":"","region":"","costs_property":"","costs_rent_comment":"","space_comment_unclear":false,"address_unclear":false,"space_units":"м²","costs_property_comment":"","costs_rent":""}]},"intro":{"declaration_year":"2014","isnotdeclaration":"","declaration_year_hidden":false}}