{"income":{"5":{"value":"253858.23","value_unclear":false,"family_hidden":false,"family_comment":"","family":"120843.32","comment":""},"6":{"family_comment":"","value":"203259.98","value_unclear":false,"family":"88504.05","comment":""},"7":{"source_name_unclear":true,"value":"48443.08","family_comment":"","source_name":"ЛНУ ім І. Франка, Львівський державний університет внутрішніх справ , Інститут післядипломної освіти","family":"","comment":"","source_name_hidden":false},"8":{"family_comment":"","value":"","family":"","comment":""},"9":{"family_comment":"","value":"2155.17","comment_unclear":false,"family":"","comment":""},"10":{"family_comment":"","value":"","family":"","comment":""},"11":{"family_comment":"","family_unclear":false,"value":"","family":"","comment":""},"12":{"family_comment":"","value":"","family":"","comment":""},"13":{"family_comment":"","value":"","family":"","comment":""},"14":{"family_comment":"","value":"","family":"32339.27","comment":""},"15":{"family_comment":"","value":"","family":"","comment":""},"16":{"family_comment":"","value":"","family":"","comment":""},"17":{"family_comment":"","value":"","family":"","comment":""},"18":{"family_comment":"","value":"","family":"","comment":""},"19":{"family_comment":"","value":"","family":"","comment":""},"20":{"value":"","value_unclear":false,"family_comment":"","comment_unclear":false,"comment":"","family":""}},"vehicle":{"35":[{"year_hidden":false,"brand_info":"1799 куб. см.","sum_rent_comment":"","year":"2008","brand_info_hidden":false,"brand_info_unclear":false,"year_unclear":false,"sum_rent":"","sum":"","brand":"Chevrolet Lacetti","sum_comment":"","brand_unclear":false,"brand_hidden":false}]},"id":"vulyk_94_65","banks":{"45":[{"sum_foreign_comment":"","sum_units":"UAH","sum_comment":"","sum_hidden":false,"sum_foreign_units":"UAH","sum_foreign":"","sum_units_unclear":false,"sum_comment_hidden":false,"sum_units_hidden":false,"sum":"15000","sum_unclear":false}],"46":[{"sum_foreign_comment":"","sum_unclear":false,"sum":"15000","sum_comment":"","sum_foreign_units":"UAH","sum_comment_hidden":false,"sum_units":"UAH","sum_foreign":""}]},"declaration":{"additional_info_text":"","notfull_lostpages":"","date":"2015-03-30T00:00:00","notfull":"","additional_info":"","url":"http://static.declarations.com.ua/declarations/chosen_ones/judges_batch/3711_kossak_stepan_mykhailovych.pdf"},"liabilities":{"54":{"sum_foreign_comment":"","sum":"","sum_comment":"","sum_comment_unclear":false,"sum_comment_hidden":false,"sum_unclear":false,"sum_foreign":""},"55":{"sum_foreign_comment":"","sum":"","sum_comment":"","sum_foreign":""},"56":{"sum_foreign_comment":"","sum":"","sum_comment":"","sum_unclear":false,"sum_foreign":""},"57":{"sum_foreign_comment":"","sum":"","sum_comment":"","sum_hidden":false,"sum_unclear":false,"sum_foreign":""},"58":{"sum_foreign_comment":"","sum":"","sum_comment":"","sum_hidden":false,"sum_unclear":false,"sum_foreign":""},"59":{"sum_foreign_comment":"","sum":"","sum_comment":"","sum_foreign":""},"60":{"sum_foreign_comment":"","sum_comment":"","sum":"","sum_comment_hidden":false,"sum_foreign":""},"61":{"sum_foreign_comment":"","sum":"","sum_comment":"","sum_foreign":""},"62":{"sum_foreign_comment":"","sum":"","sum_foreign":"","sum_comment":"","sum_hidden":false},"63":{"sum_foreign_comment":"","sum_comment":"","sum":"","sum_comment_hidden":false,"sum_foreign":""},"64":{"sum_foreign_comment":"","sum":"","sum_comment":"","sum_unclear":false,"sum_foreign":""}},"ft_src":"1799 куб. см.\nChevrolet Lacetti\n2008\n1/2 частина від 58,7 кв. м\n58.7\n.051\n1/2 частина від 77,5 кв. м\n38.75\n1/12 частина від 95,3 кв. м\n95.3\n1/4 частина від 0,1076 га\n.1076\n53.1\n15000\n15000\n2014\n1799 куб. см.\nChevrolet Lacetti\n2008\n2014\nПодружжя\nРедько Ірина Олександрівна\nДитина\nКоссак-редько Олександр Степанович\nДитина\nКоссак-редько Степан Степанович\nКоссак Степан Михайлович\nСтепан Михайлович Коссак\nСтепан Коссак\nКоссак Степан Михайлович\nКоссак Степан Михайлович\nСтепан\nМихайлович\nГосподарський місцевий суд\nЛьвівська область\nсуддя господарського суду львівської області\nКоссак\n48443.08\nЛНУ ім І. Франка, Львівський державний університет внутрішніх справ , Інститут післядипломної освіти\n203259.98\n88504.05\n32339.27\n253858.23\n120843.32\n2155.17\n.1076\n1/4 частина від 0,1076 га\n.051\n38.75\n1/2 частина від 77,5 кв. м\n95.3\n1/12 частина від 95,3 кв. м\n58.7\n1/2 частина від 58,7 кв. м\n53.1\n15000\n15000\n88504.05\n203259.98\n32339.27\nЛНУ ім І. Франка, Львівський державний університет внутрішніх справ , Інститут післядипломної освіти\n48443.08\n120843.32\n253858.23\n2155.17\nРедько Ірина Олександрівна\nПодружжя\nКоссак-редько Олександр Степанович\nДитина\nКоссак-редько Степан Степанович\nДитина\nМихайлович\nКоссак\nСтепан\nКоссак Степан Михайлович\nСтепан Михайлович Коссак\nСтепан Коссак\nКоссак Степан Михайлович\nЛьвівська область\nГосподарський місцевий суд\nсуддя господарського суду львівської області\nКоссак Степан Михайлович","general":{"inn":"","name":"Степан","last_name":"Коссак","family":[{"inn":"","inn_hidden":true,"relations_hidden":false,"family_name":"Редько Ірина Олександрівна","relations":"Подружжя","name_hidden":false,"name_unclear":false},{"inn":"","inn_hidden":true,"relations_unclear":false,"family_name":"Коссак-редько Олександр Степанович","relations_other":"","relations":"Дитина","name_hidden":false,"name_unclear":false},{"inn":"","inn_hidden":true,"relations_unclear":false,"family_name":"Коссак-редько Степан Степанович","relations_other":"","relations":"Дитина","name_hidden":false,"name_unclear":false}],"inn_hidden":true,"family_raw":"","inn_unclear":false,"post":{"post_unclear":false,"region_unclear":false,"post":"суддя господарського суду львівської області","candidate":"","post_hidden":false,"region":"Львівська область","office":"Господарський місцевий суд","office_unclear":false},"full_name":"Коссак Степан Михайлович","addresses":[{"place_district":"","place_address_hidden":true,"place_city":"","place_address":"","place_district_hidden":true,"place_city_type":"","place_city_hidden":true,"place_city_type_hidden":false,"place_hidden":true,"place":""}],"patronymic":"Михайлович","patronymic_hidden":false,"full_name_suggest":{"output":"Коссак Степан Михайлович","input":["Коссак Степан Михайлович","Степан Михайлович Коссак","Степан Коссак"]}},"source":"VULYK","estate":{"23":[{"region_unclear":false,"space_hidden":false,"costs":"","costs_comment":"","address_hidden":true,"region_hidden":true,"space_comment":"1/4 частина від 0,1076 га","space_unclear":false,"space":".1076","address":"","region":"","address_unclear":false,"space_units_unclear":false,"costs_rent_hidden":false,"costs_rent_comment_hidden":false,"space_units":"га","costs_rent":"","costs_rent_comment":""}],"24":[{"space_unclear":false,"costs":"","costs_comment":"","address_hidden":true,"region_hidden":true,"space_comment":"1/2 частина від 77,5 кв. м","space_hidden":false,"space":"38.75","address":"","region":"","costs_rent_comment":"","costs_rent_hidden":false,"costs_rent_comment_hidden":false,"space_units":"м²","costs_rent":""},{"space_unclear":true,"costs":"","costs_comment":"","address_hidden":false,"region_hidden":false,"space_comment":"1/12 частина від 95,3 кв. м","space_hidden":false,"space":"95.3","address":"","region":"","costs_rent_comment":"","space_units":"м²","costs_rent":""}],"25":[{"region_unclear":false,"space_unclear":false,"costs":"","costs_comment":"","address_hidden":true,"region_hidden":true,"space_comment":"","space_hidden":false,"space":"53.1","address":"","region":"","address_unclear":false,"costs_rent_comment":"","costs_rent_hidden":false,"space_comment_unclear":false,"costs_rent_comment_hidden":false,"space_units":"м²","costs_rent":""}],"29":[{"costs_rent":"","region":"","costs_property":"","costs_rent_comment":"","address_hidden":true,"region_hidden":true,"space_comment":"","costs_property_comment":"","space_units":"га","space":".051","address":""}],"31":[{"space_hidden":false,"costs_property_hidden":false,"address_hidden":true,"region_hidden":true,"space_comment":"1/2 частина від 58,7 кв. м","space_unclear":false,"space":"58.7","address":"","costs_property_comment_hidden":false,"region":"","costs_property":"","costs_rent_comment":"","costs_rent_hidden":false,"space_comment_unclear":false,"costs_rent_comment_hidden":false,"space_units":"м²","costs_property_comment":"","costs_rent":""}]},"intro":{"declaration_year":"2014","isnotdeclaration":""}}