{"income":{"5":{"value":"233069","value_unclear":false,"value_hidden":false,"family_comment":"","family":"38053","comment":""},"6":{"value":"232166","family_comment":"","value_unclear":false,"family_unclear":false,"family":"38053","comment":""},"7":{"source_name_unclear":false,"value":"","family_hidden":false,"family_comment":"","source_name":"","family":"","comment":""},"8":{"family_comment":"","value":"","family":"","comment":""},"9":{"family_comment":"","value":"","family":"","comment":""},"10":{"family_comment":"","value":"","family":"","comment":""},"11":{"family_comment":"","value":"","family":"","comment":""},"12":{"family_comment":"","value":"","family":"","comment":""},"13":{"family_comment":"","value":"","family":"","comment":""},"14":{"family_comment":"","value":"","family":"","comment":""},"15":{"family_comment":"","value":"","family":"","comment":""},"16":{"family_comment":"","value":"","comment_unclear":false,"family":"","comment":""},"17":{"family_comment":"","family_unclear":false,"value":"","family":"","comment":""},"18":{"family_comment":"","value":"","family":"","comment":""},"19":{"value":"","family_hidden":false,"value_hidden":false,"family_comment":"","family":"","comment":""},"20":{"family_comment":"","value":"903","comment_unclear":false,"family":"","comment":""}},"vehicle":{"35":[{"brand_info":"2.7 л","sum_rent_comment":"","year":"2008","sum_rent_unclear":false,"brand_info_hidden":false,"brand_info_unclear":false,"year_unclear":false,"sum_rent":"","sum":"","brand":"Hyundai Santa FE","sum_comment":"","sum_comment_unclear":false,"brand_hidden":false,"sum_unclear":false,"brand_unclear":false},{"brand_info":"2.0 л","sum_rent_comment":"","brand":"Audi 80","sum_comment":"","sum_comment_unclear":false,"year":"1998","brand_info_unclear":false,"sum":"","sum_rent":""}]},"id":"vulyk_67_108","declaration":{"additional_info_text":"","notfull_lostpages":"","date":"2015-03-25T00:00:00","notfull":"","additional_info":"","url":"http://static.declarations.com.ua/declarations/chosen_ones/mega_batch/shpak_viktor_oleksandrovych.pdf"},"liabilities":{"54":{"sum_foreign_comment":"","sum_foreign_hidden":false,"sum_comment":"","sum_comment_unclear":false,"sum_hidden":false,"sum":"","sum_unclear":false,"sum_foreign":""},"55":{"sum_foreign_comment":"","sum":"","sum_comment":"","sum_foreign":""},"56":{"sum_foreign_comment":"","sum_foreign_hidden":false,"sum_comment":"","sum_hidden":false,"sum":"","sum_unclear":false,"sum_foreign":""},"57":{"sum_foreign_comment":"","sum_foreign_hidden":false,"sum_comment":"","sum_comment_unclear":false,"sum_hidden":false,"sum_comment_hidden":false,"sum_unclear":false,"sum":"","sum_foreign":""},"58":{"sum_foreign_comment":"","sum_foreign_hidden":false,"sum_comment":"","sum_comment_unclear":false,"sum_hidden":false,"sum_comment_hidden":false,"sum_unclear":false,"sum":"","sum_foreign":""},"59":{"sum_foreign_comment":"","sum":"","sum_hidden":false,"sum_comment":"","sum_foreign":""},"60":{"sum_foreign_comment":"","sum":"","sum_comment":"","sum_foreign":""},"61":{"sum_foreign_comment":"","sum_foreign_hidden":false,"sum_comment":"","sum_hidden":false,"sum":"","sum_foreign":""},"62":{"sum_foreign_comment":"","sum":"","sum_hidden":false,"sum_comment":"","sum_foreign":""},"63":{"sum_foreign_comment":"","sum":"","sum_comment":"","sum_comment_unclear":false,"sum_hidden":false,"sum_unclear":false,"sum_foreign":""},"64":{"sum_foreign_comment":"","sum":"","sum_comment":"","sum_hidden":false,"sum_unclear":false,"sum_foreign":""}},"ft_src":"суддя господарського суду хмельницької області\nХмельницька область\nГосподарський місцевий суд\nВіктор\nШпак А. В\nПодружжя\nШпак А. В\nДитина\nОлександрович\nШпак Віктор Олександрович\nШпак\nШпак Віктор Олександрович\nВіктор Олександрович Шпак\nВіктор Шпак\nШпак Віктор Олександрович\n2.7 л\nHyundai Santa FE\n2008\n1998\nAudi 80\n2.0 л\n20.4\nПлоща не вказана\n62.9\n34.8\n40.53\n2014\n38053\n232166\n38053\n233069\n903\n2.7 л\nHyundai Santa FE\n2008\nAudi 80\n2.0 л\n1998\n20.4\nПлоща не вказана\n62.9\n34.8\n40.53\nГосподарський місцевий суд\nсуддя господарського суду хмельницької області\nХмельницька область\nПодружжя\nШпак А. В\nДитина\nШпак А. В\nШпак Віктор Олександрович\nВіктор Олександрович Шпак\nВіктор Шпак\nШпак Віктор Олександрович\nШпак Віктор Олександрович\nВіктор\nШпак\nОлександрович\n38053\n232166\n903\n233069\n38053\n2014\nПодружжя\nШпак А. В\nДитина\nШпак А. В\nОлександрович\nШпак\nВіктор\nШпак Віктор Олександрович\nВіктор Олександрович Шпак\nВіктор Шпак\nШпак Віктор Олександрович\nХмельницька область\nсуддя господарського суду хмельницької області\nГосподарський місцевий суд\nШпак Віктор Олександрович\n2008\nHyundai Santa FE\n2.7 л\n1998\n2.0 л\nAudi 80\n903\n233069\n38053\n232166\n38053\n62.9\n34.8\n40.53\nПлоща не вказана\n20.4\n2014","general":{"inn":"","name":"Віктор","patronymic_unclear":false,"last_name_hidden":false,"family":[{"inn":"","inn_hidden":true,"relations_unclear":false,"relations_hidden":false,"relations_other":"","relations":"Подружжя","name_hidden":true,"inn_unclear":false,"family_name":"Шпак А. В","name_unclear":false},{"inn":"","inn_hidden":false,"relations_unclear":false,"relations_hidden":false,"relations_other":"","relations":"Дитина","name_hidden":false,"inn_unclear":false,"family_name":"Шпак А. В","name_unclear":false}],"patronymic":"Олександрович","inn_hidden":true,"family_raw":"","inn_unclear":false,"post":{"post_unclear":false,"post":"суддя господарського суду хмельницької області","post_hidden":false,"region":"Хмельницька область","region_hidden":false,"office":"Господарський місцевий суд","office_hidden":false,"office_unclear":false},"last_name_unclear":false,"full_name":"Шпак Віктор Олександрович","addresses":[{"place_city_type_hidden":true,"place_district_hidden":true,"place_city_type":"","place_city_hidden":true,"place_address_unclear":false,"place_address":"","place":"","place_district":"","place_unclear":false,"place_city":"","place_city_unclear":false,"place_hidden":true,"place_address_hidden":true,"place_district_unclear":false}],"last_name":"Шпак","full_name_suggest":{"output":"Шпак Віктор Олександрович","input":["Шпак Віктор Олександрович","Віктор Олександрович Шпак","Віктор Шпак"]},"name_unclear":false},"source":"VULYK","estate":{"25":[{"space_unclear":false,"costs":"","costs_comment":"","costs_hidden":false,"address_hidden":true,"region_hidden":true,"space_comment":"","space":"62.9","address":"","region":"","address_unclear":false,"space_units_unclear":false,"space_comment_unclear":false,"space_units":"м²","costs_rent":"","costs_rent_comment":""},{"costs_rent":"","region":"","costs":"","costs_rent_comment":"","costs_comment":"","region_hidden":false,"space_comment":"","space_units":"м²","space":"34.8","address":""},{"costs_rent":"","space_unclear":true,"region":"","costs":"","costs_rent_comment":"","costs_comment":"","space_comment":"","space_units":"м²","space":"40.53","address":""}],"27":[{"costs":"","costs_comment":"","costs_hidden":false,"address_hidden":true,"region_hidden":true,"space_comment":"","space":"20.4","address":"","region":"","costs_rent_comment":"","space_units":"м²","costs_rent":""}],"30":[{"region_unclear":true,"space_hidden":true,"address_hidden":true,"region_hidden":true,"space_comment":"Площа не вказана","space":"","address":"","region":"","costs_property":"","costs_rent_comment":"","space_comment_unclear":false,"space_units":"м²","costs_property_comment":"","costs_rent":""}]},"intro":{"declaration_year":"2014","isnotdeclaration":"","declaration_year_hidden":false}}