{"income":{"5":{"value":"185512","family_comment":"","value_unclear":false,"family_hidden":false,"value_hidden":false,"family_unclear":false,"family":"37798","comment":"","family_comment_unclear":false},"6":{"family_comment":"","family_unclear":false,"value":"183700","family":"24803","comment":""},"7":{"source_name_unclear":false,"value":"1837","family_comment":"","source_name":"","family":"","comment":"","source_name_hidden":false},"8":{"family_comment":"","value":"","family":"","comment":""},"9":{"family_comment":"","family_unclear":false,"value":"5","family":"","comment":""},"10":{"family_comment":"","value":"","family":"2472","comment":""},"11":{"family_comment":"","value":"","family":"","comment":""},"12":{"family_comment":"","value":"","family":"","comment":""},"13":{"family_comment":"","value":"","family":"","comment":""},"14":{"family_comment":"","value":"","family":"","comment":""},"15":{"family_comment":"","value":"","family":"","comment":""},"16":{"value":"","value_unclear":false,"value_hidden":false,"family_comment":"","family":"","comment":""},"17":{"family_comment":"","value":"","family":"","comment":""},"18":{"family_comment":"","value":"","family":"","comment":""},"19":{"family_comment":"","value":"","family":"","comment":""},"20":{"value":"","family_comment":"стипендiя","value_unclear":false,"comment_hidden":false,"family_hidden":false,"family":"10522","value_hidden":false,"family_unclear":false,"comment_unclear":false,"comment":"","family_comment_unclear":false}},"vehicle":{"40":[{"brand_info":"1596 куб. см., 75 кВт","sum":"","brand":"Ford Fusion","sum_comment":"","brand_unclear":false,"year":"2010","brand_hidden":false,"brand_info_hidden":false,"brand_info_unclear":false,"sum_rent_comment":"","sum_rent":""}]},"id":"vulyk_62_119","declaration":{"additional_info_text":"","notfull_lostpages":"","date":"2015-03-30T00:00:00","notfull":"","additional_info":"","url":"http://static.declarations.com.ua/declarations/chosen_ones/mega_batch/truskavetskyi_vasyl_petrovych.pdf"},"liabilities":{"54":{"sum_foreign_comment":"","sum":"","sum_comment":"","sum_hidden":false,"sum_comment_hidden":false,"sum_foreign":""},"55":{"sum_foreign_comment":"","sum":"","sum_comment":"","sum_hidden":false,"sum_comment_hidden":false,"sum_unclear":false,"sum_foreign":""},"56":{"sum_foreign_comment":"","sum":"1390","sum_comment":"","sum_hidden":false,"sum_unclear":false,"sum_foreign":""},"57":{"sum_foreign_comment":"","sum":"","sum_comment":"","sum_hidden":false,"sum_comment_hidden":false,"sum_unclear":false,"sum_foreign":""},"58":{"sum_foreign_comment":"","sum_foreign_hidden":false,"sum_comment":"","sum_hidden":false,"sum_comment_hidden":false,"sum_unclear":false,"sum":"","sum_foreign":""},"59":{"sum_foreign_comment":"","sum":"","sum_comment":"","sum_foreign":""},"60":{"sum_foreign_comment":"","sum_foreign_hidden":false,"sum_comment":"","sum_hidden":false,"sum_comment_hidden":false,"sum_unclear":false,"sum":"448","sum_foreign":""},"61":{"sum_foreign_comment":"","sum_foreign_hidden":false,"sum_comment":"","sum_hidden":false,"sum":"","sum_foreign":""},"62":{"sum_foreign_comment":"","sum":"1390","sum_comment":"","sum_unclear":false,"sum_foreign":""},"63":{"sum_foreign_comment":"","sum":"","sum_comment":"","sum_hidden":false,"sum_comment_hidden":false,"sum_unclear":false,"sum_foreign":""},"64":{"sum_foreign_comment":"","sum":"","sum_comment":"","sum_comment_unclear":false,"sum_hidden":false,"sum_comment_hidden":false,"sum_foreign":""}},"ft_src":"1390\n1390\n448\nсуддя господарського суду рівненської області\nРівненська область\nГосподарський місцевий суд\nВасиль\nПодружжя\nДитина\nПетрович\nТрускавецький Василь Петрович\nВасиль Петрович Трускавецький\nВасиль Трускавецький\nТрускавецький Василь Петрович\nТрускавецький Василь Петрович\nТрускавецький\nFord Fusion\n1596 куб. см., 75 кВт\n2010\n67.6\n2014\n24803\n183700\n2472\n1837\n37798\n185512\n5\nстипендiя\n10522\n1596 куб. см., 75 кВт\n2010\nFord Fusion\n67.6\nПодружжя\nДитина\nТрускавецький Василь Петрович\nВасиль Петрович Трускавецький\nВасиль Трускавецький\nТрускавецький Василь Петрович\nТрускавецький Василь Петрович\nВасиль\nПетрович\nГосподарський місцевий суд\nсуддя господарського суду рівненської області\nРівненська область\nТрускавецький\n448\n1390\n1390\n1837\n183700\n24803\nстипендiя\n10522\n185512\n37798\n2472\n5\n2014\n1390\n1390\n448\nПодружжя\nДитина\nПетрович\nТрускавецький\nВасиль\nТрускавецький Василь Петрович\nВасиль Петрович Трускавецький\nВасиль Трускавецький\nТрускавецький Василь Петрович\nРівненська область\nсуддя господарського суду рівненської області\nГосподарський місцевий суд\nТрускавецький Василь Петрович\nFord Fusion\n1596 куб. см., 75 кВт\n2010\n2472\nстипендiя\n10522\n185512\n37798\n1837\n5\n24803\n183700\n67.6\n2014","general":{"inn":"","name":"Василь","inn_unclear":false,"family":[{"inn":"","inn_hidden":true,"relations_unclear":false,"relations_hidden":false,"relations_other":"","relations":"Подружжя","name_hidden":true,"inn_unclear":false,"family_name":"","name_unclear":false},{"inn":"","inn_hidden":false,"relations_hidden":false,"family_name":"","relations_other":"","relations":"Дитина","name_hidden":false,"name_unclear":false}],"inn_hidden":true,"family_raw":"","last_name":"Трускавецький","post":{"post_unclear":false,"post":"суддя господарського суду рівненської області","post_hidden":false,"region":"Рівненська область","region_hidden":false,"office":"Господарський місцевий суд","office_hidden":false,"office_unclear":false},"full_name_suggest":{"output":"Трускавецький Василь Петрович","input":["Трускавецький Василь Петрович","Василь Петрович Трускавецький","Василь Трускавецький"]},"full_name":"Трускавецький Василь Петрович","addresses":[{"place_city_type_unclear":false,"place_address":"","place_district_hidden":true,"place_city_type":"","place_address_hidden":true,"place_address_unclear":false,"place_city_type_hidden":true,"place":"","place_district":"","place_unclear":false,"place_city":"","place_city_unclear":false,"place_hidden":true,"place_city_hidden":true,"place_district_unclear":false}],"patronymic":"Петрович","last_name_unclear":false,"name_unclear":false},"source":"VULYK","estate":{"24":[{"space_unclear":false,"costs":"","costs_comment":"","address_hidden":true,"region_hidden":true,"space_comment":"","space_hidden":false,"space_units_unclear":false,"address":"","region":"","address_unclear":false,"space":"67.6","space_comment_unclear":false,"space_units":"м²","space_units_hidden":false,"costs_rent":"","costs_rent_comment":""}]},"intro":{"declaration_year":"2014","isnotdeclaration":"","declaration_year_unclear":false,"declaration_year_hidden":false}}