{"income":{"5":{"value":"267603","value_unclear":false,"family_hidden":false,"family_comment":"","family":"321200","comment":""},"6":{"family_comment":"","value":"267603","family":"","comment":""},"7":{"family_comment":"","value":"","source_name":"","family":"","comment":""},"8":{"family_comment":"","value":"","family":"","comment":""},"9":{"family_comment":"","value":"","family":"","comment":""},"10":{"family_comment":"","value":"","family":"","comment":""},"11":{"family_comment":"","value":"","family_hidden":false,"comment":"","family":""},"12":{"family_comment":"","value":"","family":"","comment":""},"13":{"family_comment":"","value":"","family":"","comment":""},"14":{"family_comment":"","value":"","family":"","comment":""},"15":{"family_comment":"","value":"","family":"49500","comment":""},"16":{"family_comment":"","value":"","family":"","comment":""},"17":{"family_comment":"","value":"","family":"271700","comment":"","family_comment_unclear":false},"18":{"family_comment":"","value":"","family":"","comment":""},"19":{"family_comment":"","value":"","family":"","comment":""},"20":{"value":"","family_unclear":false,"family_hidden":false,"family_comment":"","family":"","comment":""}},"vehicle":{"35":[{"brand_info":"2.4 , 2362","sum":"","brand":"Toyota Camry","sum_comment":"","brand_unclear":false,"year":"2008","brand_hidden":false,"brand_info_hidden":false,"brand_info_unclear":false,"sum_rent_comment":"","sum_rent":""}],"39":[{"brand_info":"мотоцикл, 650","sum_rent_comment":"","brand":"Днепр (КМЗ) МТ-11","sum_comment":"","year":"1986","brand_info_hidden":false,"sum":"","sum_rent":""}],"40":[{"year_hidden":false,"brand_info":"1998","sum_rent_comment":"","brand":"Mazda CX-5","sum_comment":"","year":"2013","brand_hidden":false,"brand_info_unclear":false,"sum":"","sum_rent":""}]},"id":"vulyk_103_10","banks":{"45":[{"sum_foreign_comment":"","sum_units":"UAH","sum_comment":"","sum_hidden":false,"sum_foreign_units":"UAH","sum_comment_hidden":true,"sum_unclear":false,"sum":"5129","sum_foreign":""}]},"declaration":{"date":"2016-03-31T00:00:00","additional_info_text":"","additional_info":"","url":"http://static.declarations.com.ua/declarations/chosen_ones/judges_batch/1234_studenets_volodymyr_ivanovych.pdf"},"liabilities":{"54":{"sum_foreign_comment":"","sum_foreign_hidden":false,"sum_comment":"","sum_foreign_comment_hidden":false,"sum_hidden":false,"sum_foreign_comment_unclear":false,"sum_comment_hidden":false,"sum_unclear":false,"sum":"9480","sum_foreign":""},"55":{"sum_foreign_comment":"","sum":"","sum_comment":"","sum_foreign":""},"56":{"sum_foreign_comment":"","sum":"","sum_comment":"","sum_foreign":""},"57":{"sum_foreign_comment":"","sum_foreign_hidden":false,"sum_comment":"","sum_foreign_comment_hidden":false,"sum_hidden":false,"sum_comment_hidden":false,"sum":"","sum_foreign":""},"58":{"sum_foreign_comment":"","sum_foreign_hidden":false,"sum_comment":"","sum_foreign_comment_hidden":false,"sum_hidden":false,"sum_comment_hidden":false,"sum":"","sum_foreign":""},"59":{"sum_foreign_comment":"","sum_foreign_hidden":false,"sum_comment":"","sum_foreign_comment_hidden":false,"sum_hidden":false,"sum_comment_hidden":false,"sum":"","sum_foreign":""},"60":{"sum_foreign_comment":"","sum":"","sum_comment":"","sum_hidden":false,"sum_comment_hidden":false,"sum_foreign":""},"61":{"sum_foreign_comment":"","sum":"","sum_comment":"","sum_foreign":""},"62":{"sum_foreign_comment":"","sum_comment_hidden":false,"sum":"","sum_comment":"","sum_foreign":""},"63":{"sum_foreign_comment":"","sum":"","sum_comment":"","sum_foreign":""},"64":{"sum_foreign_comment":"","sum":"","sum_comment":"","sum_foreign":""}},"ft_src":"9480\nСтуденець Володимир Іванович\nсуддя вищого господарського суду україни\nЗагальнодержавний регіон\nВищий господарський суд\nВолодимир\nМаценко С. О\nПодружжя\nСтуденець Володимир Іванович\nВолодимир Іванович Студенець\nВолодимир Студенець\nСтуденець Володимир Іванович\nСтуденець\nІванович\nмотоцикл, 650\n1986\nДнепр (КМЗ) МТ-11\nToyota Camry\n2.4 , 2362\n2008\n1998\nMazda CX-5\n2013\n278.9\n642\n176\n55.3\n5129\n2015\n2.4 , 2362\n2008\nToyota Camry\n1998\n2013\nMazda CX-5\nмотоцикл, 650\n1986\nДнепр (КМЗ) МТ-11\n642\n176\n278.9\n55.3\nСтуденець\nСтуденець Володимир Іванович\nВолодимир Іванович Студенець\nВолодимир Студенець\nСтуденець Володимир Іванович\nСтуденець Володимир Іванович\nІванович\nПодружжя\nМаценко С. О\nВолодимир\nВищий господарський суд\nсуддя вищого господарського суду україни\nЗагальнодержавний регіон\n9480\n267603\n271700\n49500\n267603\n321200\n5129\n2015\n9480\n267603\n49500\n321200\n267603\n271700\nПодружжя\nМаценко С. О\nСтуденець\nІванович\nсуддя вищого господарського суду україни\nВищий господарський суд\nЗагальнодержавний регіон\nСтуденець Володимир Іванович\nСтуденець Володимир Іванович\nВолодимир Іванович Студенець\nВолодимир Студенець\nСтуденець Володимир Іванович\nВолодимир\nДнепр (КМЗ) МТ-11\nмотоцикл, 650\n1986\nToyota Camry\n2.4 , 2362\n2008\nMazda CX-5\n1998\n2013\n49500\n267603\n321200\n271700\n267603\n278.9\n55.3\n642\n176\n5129\n2015","general":{"inn":"","inn_hidden":true,"last_name":"Студенець","post":{"region":"Загальнодержавний регіон","region_unclear":false,"post":"суддя вищого господарського суду україни","office_unclear":false,"office":"Вищий господарський суд"},"name":"Володимир","full_name":"Студенець Володимир Іванович","family_raw":"","addresses":[{"place_district":"","place_city_hidden":true,"place_city":"","place_city_type_hidden":false,"place_district_hidden":false,"place_city_type":"","place_address_hidden":true,"place_address":"","place_hidden":true,"place":""}],"family":[{"inn":"","relations":"Подружжя","relations_hidden":false,"inn_hidden":true,"relations_other":"","name_hidden":true,"family_name":"Маценко С. О","name_unclear":false}],"full_name_suggest":{"output":"Студенець Володимир Іванович","input":["Студенець Володимир Іванович","Володимир Іванович Студенець","Володимир Студенець"]},"patronymic":"Іванович"},"source":"VULYK","estate":{"25":[{"costs":"","costs_comment":"","address_hidden":false,"region_hidden":true,"space_comment":"","space":"55.3","address":"","region":"","costs_rent_comment":"","space_comment_unclear":false,"space_comment_hidden":false,"space_units":"м²","costs_rent":""}],"29":[{"space_hidden":false,"address_hidden":true,"region_hidden":true,"space_comment":"","space":"642","address":"","region":"","costs_property":"","costs_rent_comment":"","space_units":"м²","costs_property_comment":"","costs_rent":""},{"costs_rent":"","costs_property":"","costs_rent_comment":"","space_comment":"","costs_property_comment":"","space_units":"м²","space":"176","address":""}],"30":[{"space_unclear":false,"address_hidden":true,"region_hidden":true,"space_comment":"","space_hidden":false,"space":"278.9","address":"","costs_property":"","costs_rent_comment":"","space_units":"м²","costs_property_comment":"","costs_rent":""}]},"intro":{"declaration_year":"2015"}}