{"id":"vulyk_83_9","ft_src":"4.4 л\n1997\nBMW 740\nКіровоградська область\nм. Кіровоград\n114.6\n2014\n260264\n13398\n347062\n73400\n4.4 л\nBMW 740\n1997\n114.6\nКіровоградська область\nм. Кіровоград\nБубличенко Валентина Петрівна\nВалентина Петрівна Бубличенко\nВалентина Бубличенко\nБубличенко Валентина Петрівна\nВалентина\nБубличенко Валентина Петрівна\nПетрівна\nЗагальний апеляційний суд\nКіровоградська область\nсуддя апеляційного суду кіровоградської області\nБубличенко\n15137\n76300\n5489\n260264\n73400\n347062\n13398\n2014\n15137\n76300\n5489\nПетрівна\nБубличенко\nВалентина\nБубличенко Валентина Петрівна\nВалентина Петрівна Бубличенко\nВалентина Бубличенко\nБубличенко Валентина Петрівна\nКіровоградська область\nЗагальний апеляційний суд\nсуддя апеляційного суду кіровоградської області\nБубличенко Валентина Петрівна","estate":{"25":[{"address":"м. Кіровоград","space_units":"м²","space_hidden":false,"space_unclear":false,"region_hidden":false,"costs_comment":"","space_comment":"","address_hidden":false,"costs":"","space_comment_unclear":false,"costs_rent_comment":"","space":"114.6","region_unclear":false,"region":"Кіровоградська область","costs_rent":""}]},"vehicle":{"35":[{"sum_comment":"","brand_info":"4.4 л","sum":"","sum_rent_comment":"","year":"1997","brand":"BMW 740","sum_rent":"","brand_info_unclear":false}]},"source":"VULYK","income":{"5":{"family_comment":"","value":"347062","family":"","comment":""},"6":{"family_comment":"","family":"","comment":"","comment_hidden":false,"value":"260264","family_comment_hidden":false},"7":{"family_comment":"","comment":"","family":"","comment_unclear":false,"value":"","source_name":""},"8":{"family_comment":"","value":"","family":"","comment":""},"9":{"family_comment":"","value":"","family":"","comment":""},"10":{"family_comment":"","family_hidden":false,"value":"13398","family":"","comment":""},"11":{"family_comment":"","value":"","family":"","comment":""},"12":{"family_comment":"","value":"","family":"","comment":""},"13":{"family_comment":"","value":"","family":"","comment":""},"14":{"family_comment":"","value":"","family":"","comment":""},"15":{"family_comment":"","value":"","family":"","comment":""},"16":{"family_comment":"","value":"","family":"","comment":""},"17":{"family_comment":"","value":"","family":"","comment":""},"18":{"family_comment":"","value":"","family":"","comment":""},"19":{"family_comment":"","value":"","family":"","comment":""},"20":{"family_comment":"","family":"","comment":"","value_unclear":false,"family_hidden":false,"value":"73400"}},"general":{"family_raw":"","name":"Валентина","full_name_suggest":{"input":["Бубличенко Валентина Петрівна","Валентина Петрівна Бубличенко","Валентина Бубличенко"],"output":"Бубличенко Валентина Петрівна"},"patronymic":"Петрівна","inn_hidden":true,"addresses":[{"place_city_type_hidden":false,"place_district_hidden":false,"place_address_unclear":false,"place":"","place_city":"","place_city_type_unclear":false,"place_city_type":"","place_city_hidden":false,"place_district":"","place_city_unclear":false,"place_address":"","place_address_hidden":false,"place_hidden":true}],"inn":"","inn_unclear":false,"last_name":"Бубличенко","full_name":"Бубличенко Валентина Петрівна","post":{"office":"Загальний апеляційний суд","post":"суддя апеляційного суду кіровоградської області","candidate":"","office_unclear":false,"region":"Кіровоградська область","post_unclear":false},"last_name_unclear":false},"liabilities":{"54":{"sum_comment":"","sum_foreign_comment":"","sum_foreign":"","sum":""},"55":{"sum_comment":"","sum_foreign_comment":"","sum_foreign":"","sum":""},"56":{"sum_comment":"","sum_foreign_comment":"","sum_foreign":"","sum":"5489"},"57":{"sum_comment":"","sum_foreign_comment":"","sum_foreign":"","sum":"76300"},"58":{"sum_comment":"","sum_foreign_comment":"","sum_foreign":"","sum":"15137"},"59":{"sum_comment":"","sum_foreign_comment":"","sum_foreign":"","sum":""},"60":{"sum_comment":"","sum_foreign_comment":"","sum_foreign":"","sum":""},"61":{"sum_comment":"","sum_foreign_comment":"","sum_foreign":"","sum":""},"62":{"sum_comment":"","sum_foreign_comment":"","sum_foreign":"","sum":""},"63":{"sum_comment":"","sum_foreign_comment":"","sum_foreign":"","sum":""},"64":{"sum_comment":"","sum_foreign_comment":"","sum_foreign":"","sum":""}},"declaration":{"notfull_lostpages":"","additional_info_text":"","additional_info":"","date":"2015-03-27T00:00:00","notfull":"","url":"http://static.declarations.com.ua/declarations/chosen_ones/judges_batch/2278_bublychenko_valentyna_petrivna.pdf"},"intro":{"declaration_year":"2014"}}