{"income":{"5":{"family_comment":"","value":"238936","family":"73660","comment":""},"6":{"value":"238936","family_comment":"","value_unclear":false,"comment_hidden":false,"family_unclear":false,"family":"73660","comment":""},"7":{"family_comment":"","value":"","source_name":"","family":"","comment":""},"8":{"family_comment":"","value":"","family":"","comment":""},"9":{"family_comment":"","family_unclear":false,"value":"","family":"","comment":""},"10":{"family_comment":"","value":"","value_unclear":false,"family":"","comment":""},"11":{"family_comment":"","value":"","family":"","comment":""},"12":{"family_comment":"","value":"","family":"","comment":""},"13":{"family_comment":"","value":"","family":"","comment":""},"14":{"family_comment":"","value":"","family":"","comment":""},"15":{"family_comment":"","value":"","family":"","comment":""},"16":{"family_comment":"","value":"","family":"","comment":""},"17":{"family_comment":"","value":"","family":"","comment":""},"18":{"family_comment":"","value":"","family":"","comment":""},"19":{"family_comment":"","value":"","family":"","comment":""},"20":{"value":"","family":"","value_unclear":false,"family_hidden":false,"family_comment":"","comment_unclear":false,"comment":"","family_comment_unclear":false}},"id":"vulyk_97_63","declaration":{"additional_info_text":"","notfull_lostpages":"","date":"2015-03-30T00:00:00","notfull":"","additional_info":"","url":"http://static.declarations.com.ua/declarations/chosen_ones/judges_batch/3891_kharechko_liubov_kostiantynivna.pdf"},"liabilities":{"54":{"sum_foreign_comment":"","sum":"","sum_comment":"","sum_comment_unclear":false,"sum_hidden":false,"sum_comment_hidden":false,"sum_unclear":false,"sum_foreign":""},"55":{"sum_foreign_comment":"","sum":"","sum_comment":"","sum_foreign":""},"56":{"sum_foreign_comment":"","sum":"","sum_comment":"","sum_foreign":""},"57":{"sum_foreign_comment":"","sum":"","sum_comment":"","sum_comment_unclear":false,"sum_hidden":false,"sum_comment_hidden":false,"sum_unclear":false,"sum_foreign":""},"58":{"sum_foreign_comment":"","sum":"","sum_comment":"","sum_comment_unclear":false,"sum_hidden":false,"sum_comment_hidden":false,"sum_unclear":false,"sum_foreign":""},"59":{"sum_foreign_comment":"","sum":"","sum_comment":"","sum_foreign":""},"60":{"sum_foreign_comment":"","sum":"","sum_comment":"","sum_comment_unclear":false,"sum_hidden":false,"sum_comment_hidden":false,"sum_foreign":""},"61":{"sum_foreign_comment":"","sum":"","sum_comment":"","sum_foreign":""},"62":{"sum_foreign_comment":"","sum":"","sum_comment":"","sum_unclear":false,"sum_foreign":""},"63":{"sum_foreign_comment":"","sum":"","sum_hidden":false,"sum_comment":"","sum_foreign":""},"64":{"sum_foreign_comment":"","sum":"","sum_comment":"","sum_foreign":""}},"ft_src":"суддя апеляційного суду чернігівської області\nЧернігівська область\nЗагальний апеляційний суд\nЛюбов\nХаречко В'ячеслав Валерійович\nПодружжя\nХаречко Віталій В'ячеславович\nДитина\nХаречко Валерій В'ячеславович\nДитина\nКостянтинівна\nХаречко Любов Костянтинівна\nЛюбов Костянтинівна Харечко\nЛюбов Харечко\nХаречко Любов Костянтинівна\nХаречко Любов Костянтинівна\nХаречко\n73660\n238936\n238936\n73660\n84.9\n2000\n18\n2014\n73660\n238936\n73660\n238936\n2000\n84.9\n18\nХаречко Любов Костянтинівна\nЛюбов Костянтинівна Харечко\nЛюбов Харечко\nХаречко Любов Костянтинівна\nЛюбов\nПодружжя\nХаречко В'ячеслав Валерійович\nДитина\nХаречко Віталій В'ячеславович\nДитина\nХаречко Валерій В'ячеславович\nХаречко Любов Костянтинівна\nХаречко\nЗагальний апеляційний суд\nЧернігівська область\nсуддя апеляційного суду чернігівської області\nКостянтинівна\n238936\n73660\n238936\n73660\n2014\nПодружжя\nХаречко В'ячеслав Валерійович\nХаречко Віталій В'ячеславович\nДитина\nДитина\nХаречко Валерій В'ячеславович\nКостянтинівна\nХаречко\nЛюбов\nХаречко Любов Костянтинівна\nЛюбов Костянтинівна Харечко\nЛюбов Харечко\nХаречко Любов Костянтинівна\nЧернігівська область\nЗагальний апеляційний суд\nсуддя апеляційного суду чернігівської області\nХаречко Любов Костянтинівна\n84.9\n18\n2000\n2014","general":{"name_hidden":false,"name":"Любов","last_name_hidden":false,"inn":"","family":[{"inn":"","relations":"Подружжя","relations_other":"","inn_hidden":true,"family_name":"Харечко В'ячеслав Валерійович","name_hidden":true,"name_unclear":false},{"inn_hidden":false,"inn":"","name_hidden":false,"family_name":"Харечко Віталій В'ячеславович","relations":"Дитина","name_unclear":false},{"inn":"","relations":"Дитина","relations_other":"","inn_hidden":false,"family_name":"Харечко Валерій В'ячеславович","name_hidden":false,"name_unclear":false}],"patronymic":"Костянтинівна","inn_hidden":true,"family_raw":"","inn_unclear":false,"post":{"region_unclear":false,"region":"Чернігівська область","post":"суддя апеляційного суду чернігівської області","office":"Загальний апеляційний суд","office_unclear":false,"post_hidden":false},"full_name":"Харечко Любов Костянтинівна","addresses":[{"place_district":"","place_city_hidden":true,"place_city":"","place_city_unclear":false,"place_district_hidden":true,"place_city_type":"","place_address_hidden":true,"place_city_type_hidden":true,"place_address":"","place_hidden":true,"place":""}],"last_name":"Харечко","patronymic_hidden":false,"full_name_suggest":{"output":"Харечко Любов Костянтинівна","input":["Харечко Любов Костянтинівна","Любов Костянтинівна Харечко","Любов Харечко"]}},"source":"VULYK","estate":{"28":[{"costs_rent":"","region":"","costs":"","costs_rent_comment":"","costs_comment":"","address_hidden":true,"region_hidden":true,"space_comment":"","space_units":"м²","space":"18","address":""}],"29":[{"region_unclear":false,"space_unclear":false,"address_hidden":true,"region_hidden":true,"space_comment":"","space":"2000","address":"","region":"","costs_property":"","costs_rent_comment":"","space_comment_unclear":false,"address_unclear":false,"space_units":"м²","costs_property_comment":"","costs_rent":""}],"31":[{"space_unclear":false,"address_hidden":true,"region_hidden":true,"space_comment":"","space_hidden":false,"space":"84.9","address":"","region":"","costs_property":"","costs_rent_comment":"","space_comment_hidden":false,"space_units":"м²","costs_property_comment":"","costs_rent":""}]},"intro":{"declaration_year":"2014","isnotdeclaration":""}}