{"income":{"5":{"family_comment":"","family_unclear":false,"value":"179707","family":"","comment":""},"6":{"value":"179707","family_comment":"","value_unclear":false,"family_unclear":false,"family":"","comment":""},"7":{"value":"","family_comment":"","value_unclear":false,"family_unclear":false,"source_name":"","family":"","comment":"","source_name_hidden":false},"8":{"family_comment":"","value":"","family":"","comment":""},"9":{"family_comment":"","value":"","family":"","comment":""},"10":{"family_comment":"","value":"","value_unclear":false,"family":"","comment":""},"11":{"family_comment":"","value":"","family":"","comment":""},"12":{"family_comment":"","value":"","family":"","comment":""},"13":{"family_comment":"","value":"","family":"","comment":""},"14":{"family_comment":"","value":"","family":"","comment":""},"15":{"family_comment":"","value":"","family":"","comment":""},"16":{"family_comment":"","value":"","family":"","comment":""},"17":{"family_comment":"","value":"","family":"","comment":""},"18":{"family_comment":"","value":"","family":"","comment":""},"19":{"family_comment":"","value":"","family":"","comment":""},"20":{"value":"","value_unclear":false,"comment_hidden":false,"family_comment":"","comment_unclear":false,"comment":"","family":""}},"id":"vulyk_96_102","declaration":{"additional_info_text":"","notfull_lostpages":"","date":"2016-03-28T00:00:00","notfull":"","additional_info":"","url":"http://static.declarations.com.ua/declarations/chosen_ones/judges_batch/316_koliiev_serhii_leonidovych_2015.pdf"},"liabilities":{"54":{"sum_foreign_comment":"","sum":"","sum_comment":"","sum_hidden":false,"sum_comment_hidden":false,"sum_foreign":""},"55":{"sum_foreign_comment":"","sum":"","sum_comment":"","sum_foreign":""},"56":{"sum_foreign_comment":"","sum":"","sum_comment":"","sum_unclear":false,"sum_foreign":""},"57":{"sum_foreign_comment":"","sum_comment_hidden":false,"sum":"","sum_comment":"","sum_foreign":""},"58":{"sum_foreign_comment":"","sum":"","sum_comment":"","sum_comment_hidden":false,"sum_unclear":false,"sum_foreign":""},"59":{"sum_foreign_comment":"","sum":"","sum_comment":"","sum_foreign":""},"60":{"sum_foreign_comment":"","sum_comment_hidden":false,"sum":"","sum_comment":"","sum_foreign":""},"61":{"sum_foreign_comment":"","sum":"","sum_comment":"","sum_foreign":""},"62":{"sum_foreign_comment":"","sum":"25500","sum_comment":"","sum_foreign":""},"63":{"sum_foreign_comment":"","sum_comment_hidden":false,"sum":"","sum_comment":"","sum_foreign":""},"64":{"sum_foreign_comment":"","sum_comment_hidden":false,"sum":"","sum_comment":"","sum_foreign":""}},"ft_src":"25500\nсуддя хмельницького міськрайонного суду хмельницької області\nХмельницька область\nЗагальний місцевий суд\nСергій\nКолієва А. О. 05. 01. 1980\nПодружжя\nКолієв І. С. 24. 10. 2008\nДитина\nЛеонідович\nКолієв Сергій Леонідович\nКолієв\nКолієв Сергій Леонідович\nСергій Леонідович Колієв\nСергій Колієв\nКолієв Сергій Леонідович\n179707\n179707\nоренда\n78.8\n65.8\n2015\n179707\n179707\n179707\n179707\nКолієв Сергій Леонідович\nСергій Леонідович Колієв\nСергій Колієв\nКолієв Сергій Леонідович\nКолієв Сергій Леонідович\nСергій\nКолієв\nХмельницька область\nсуддя хмельницького міськрайонного суду хмельницької області\nЗагальний місцевий суд\nЛеонідович\nПодружжя\nКолієва А. О. 05. 01. 1980\nДитина\nКолієв І. С. 24. 10. 2008\n25500\nоренда\n78.8\n65.8\n2015\n25500\nКолієва А. О. 05. 01. 1980\nПодружжя\nДитина\nКолієв І. С. 24. 10. 2008\nСергій\nЛеонідович\nКолієв\nКолієв Сергій Леонідович\nСергій Леонідович Колієв\nСергій Колієв\nКолієв Сергій Леонідович\nсуддя хмельницького міськрайонного суду хмельницької області\nХмельницька область\nЗагальний місцевий суд\nКолієв Сергій Леонідович\nоренда\n78.8\n65.8\n2015","general":{"inn":"","name":"Сергій","family":[{"inn":"","inn_hidden":true,"inn_unclear":false,"relations_hidden":false,"relations_other":"","relations":"Подружжя","name_hidden":false,"family_name":"Колієва А. О. 05. 01. 1980","name_unclear":false},{"inn":"","relations":"Дитина","relations_other":"","inn_hidden":false,"family_name":"Колієв І. С. 24. 10. 2008","name_hidden":false,"name_unclear":false}],"patronymic":"Леонідович","inn_hidden":true,"family_raw":"","last_name":"Колієв","post":{"office":"Загальний місцевий суд","region":"Хмельницька область","office_unclear":false,"post":"суддя хмельницького міськрайонного суду хмельницької області"},"full_name":"Колієв Сергій Леонідович","addresses":[{"place_district":"","place_city_hidden":true,"place_city":"","place_city_type_hidden":false,"place_district_hidden":false,"place_city_type":"","place_address_hidden":true,"place_address":"","place_hidden":true,"place":""}],"patronymic_hidden":false,"full_name_suggest":{"output":"Колієв Сергій Леонідович","input":["Колієв Сергій Леонідович","Сергій Леонідович Колієв","Сергій Колієв"]}},"source":"VULYK","estate":{"25":[{"space_comment_unclear":false,"space_unclear":false,"costs":"","costs_comment":"","address_hidden":false,"region_hidden":true,"space_comment":"","space_hidden":false,"space":"65.8","address":"","costs_rent_comment_unclear":false,"region":"","address_unclear":false,"costs_rent_comment":"","costs_unclear":false,"space_comment_hidden":false,"space_units":"м²","costs_rent":""}],"31":[{"space_unclear":false,"address_hidden":true,"region_hidden":true,"space_comment":"оренда","space_hidden":false,"space":"78.8","address":"","region":"","costs_property":"","costs_rent_comment":"","address_unclear":false,"space_units":"м²","costs_property_comment":"","costs_rent":""}]},"intro":{"declaration_year":"2015","isnotdeclaration":""}}