{"income":{"5":{"value":"209832","family_comment":"","value_unclear":false,"family_hidden":false,"value_hidden":false,"family_unclear":false,"comment_unclear":false,"comment":"","family":""},"6":{"value":"198362","family_unclear":false,"family_hidden":false,"family_comment":"","family":"","comment":""},"7":{"value":"","family_hidden":false,"value_hidden":false,"family_comment":"","source_name":"","family":"","comment":""},"8":{"family_comment":"","value":"","family":"","comment":""},"9":{"family_comment":"","value":"","value_unclear":false,"family":"","comment":""},"10":{"family_comment":"","family_unclear":false,"value":"11470","family":"","comment":""},"11":{"family_comment":"","value":"","family":"","comment":""},"12":{"family_comment":"","value":"","family":"","comment":""},"13":{"family_comment":"","value":"","family":"","comment":""},"14":{"family_comment":"","value":"","family":"","comment":""},"15":{"family_comment":"","value":"","family":"","comment":""},"16":{"family_comment":"","value":"","family":"","comment":""},"17":{"family_comment":"","value":"","family":"","comment":""},"18":{"family_comment":"","value":"","family":"","comment":""},"19":{"family_comment":"","value":"","family":"","comment":""},"20":{"value":"","value_unclear":false,"family_comment":"","comment_unclear":false,"comment":"","family":""}},"id":"vulyk_71_16","declaration":{"additional_info_text":"","notfull_lostpages":"","date":"2014-03-20T00:00:00","notfull":"","additional_info":"","url":"http://static.declarations.com.ua/declarations/chosen_ones/judges_batch/619_ivanova_alla_pylypivna.pdf"},"liabilities":{"54":{"sum_foreign_comment":"","sum":"","sum_comment":"","sum_comment_unclear":false,"sum_comment_hidden":false,"sum_unclear":false,"sum_foreign":""},"55":{"sum_foreign_comment":"","sum":"","sum_comment":"","sum_foreign":""},"56":{"sum_foreign_comment":"","sum":"665","sum_comment":"","sum_comment_unclear":false,"sum_unclear":false,"sum_foreign":""},"57":{"sum_foreign_comment":"","sum":"","sum_comment":"","sum_comment_hidden":false,"sum_unclear":false,"sum_foreign":""},"58":{"sum_foreign_comment":"","sum":"","sum_comment":"","sum_comment_hidden":false,"sum_unclear":false,"sum_foreign":""},"59":{"sum_foreign_comment":"","sum_comment_hidden":false,"sum":"","sum_comment":"","sum_foreign":""},"60":{"sum_foreign_comment":"","sum_comment_hidden":false,"sum":"","sum_comment":"","sum_foreign":""},"61":{"sum_foreign_comment":"","sum":"","sum_comment":"","sum_foreign":""},"62":{"sum_foreign_comment":"","sum":"","sum_comment":"","sum_foreign":""},"63":{"sum_foreign_comment":"","sum":"","sum_comment":"","sum_unclear":false,"sum_foreign":""},"64":{"sum_foreign_comment":"","sum":"","sum_comment":"","sum_unclear":false,"sum_foreign":""}},"ft_src":"665\nсуддя апеляційного суду донецької області\nДонецька область\nЗагальний апеляційний суд\nАлла\nПилипівна\nІванова\nІванова Алла Пилипівна\nІванова Алла Пилипівна\nАлла Пилипівна Іванова\nАлла Іванова\nІванова Алла Пилипівна\n11470\n209832\n198362\n2013\n198362\n11470\n209832\n198362\n209832\n11470\nІванова Алла Пилипівна\nАлла Пилипівна Іванова\nАлла Іванова\nІванова Алла Пилипівна\nАлла\nІванова Алла Пилипівна\nІванова\nЗагальний апеляційний суд\nДонецька область\nсуддя апеляційного суду донецької області\nПилипівна\n665\n2013\n665\nАлла\nПилипівна\nІванова\nІванова Алла Пилипівна\nАлла Пилипівна Іванова\nАлла Іванова\nІванова Алла Пилипівна\nДонецька область\nЗагальний апеляційний суд\nсуддя апеляційного суду донецької області\nІванова Алла Пилипівна\n2013","general":{"inn":"","name":"Алла","inn_unclear":false,"patronymic":"Пилипівна","inn_hidden":true,"family_raw":"","last_name":"Іванова","post":{"post_unclear":false,"region_unclear":false,"post":"суддя апеляційного суду донецької області","office":"Загальний апеляційний суд","region":"Донецька область","post_hidden":false,"office_unclear":false},"last_name_unclear":false,"full_name":"Іванова Алла Пилипівна","addresses":[{"place_district":"","place_unclear":false,"place_city":"","place_city_type_hidden":false,"place_district_hidden":false,"place_city_type":"","place_city_hidden":true,"place_address_hidden":true,"place_address":"","place_hidden":true,"place":""}],"patronymic_hidden":false,"full_name_suggest":{"output":"Іванова Алла Пилипівна","input":["Іванова Алла Пилипівна","Алла Пилипівна Іванова","Алла Іванова"]},"name_unclear":false},"source":"VULYK","intro":{"declaration_year":"2013","isnotdeclaration":""}}