{"income":{"5":{"value":"194818","family_comment":"","value_unclear":false,"family_unclear":false,"family":"46786","comment":""},"6":{"family_comment":"","value":"194818","value_unclear":false,"family":"","comment":""},"7":{"value":"","value_unclear":false,"family_comment":"","source_name":"","family":"","comment":""},"8":{"family_comment":"","value":"","family":"","comment":""},"9":{"value":"","family_comment":"","value_unclear":false,"family_unclear":false,"family":"","comment":""},"10":{"family_comment":"","value":"","comment_unclear":false,"family":"","comment":""},"11":{"family_comment":"","value":"","family":"","comment":""},"12":{"family_comment":"","value":"","family":"","comment":""},"13":{"family_comment":"","value":"","value_unclear":false,"family":"","comment":""},"14":{"family_comment":"","value":"","family":"","comment":""},"15":{"family_comment":"","value":"","family":"","comment":""},"16":{"family_comment":"","family_unclear":false,"value":"","family":"","comment":""},"17":{"family_comment":"","family_unclear":false,"value":"","family":"","comment":""},"18":{"family_comment":"","value":"","family":"","comment":""},"19":{"family_comment":"","value":"","family":"","comment":""},"20":{"value":"","family_comment":"","value_unclear":false,"family_hidden":false,"value_hidden":false,"family_unclear":false,"comment_unclear":false,"comment":"","family":"46786"}},"id":"vulyk_100_38","declaration":{"additional_info_text":"","notfull_lostpages":"розділ 4","date":"2015-03-27T00:00:00","notfull":"1","additional_info":"","url":"http://static.declarations.com.ua/declarations/chosen_ones/judges_batch/4206_oliinyk_viktoriia_mykolaivna.pdf"},"liabilities":{"54":{"sum_foreign_comment":"","sum":"","sum_comment":"","sum_comment_hidden":false,"sum_unclear":false,"sum_foreign":""},"55":{"sum_foreign_comment":"","sum":"","sum_comment":"","sum_foreign":""},"56":{"sum_foreign_comment":"","sum":"","sum_comment":"","sum_unclear":false,"sum_foreign":""},"57":{"sum_foreign_comment":"","sum":"","sum_comment":"","sum_comment_unclear":false,"sum_comment_hidden":false,"sum_unclear":false,"sum_foreign":""},"58":{"sum_foreign_comment":"","sum":"","sum_comment":"","sum_comment_hidden":false,"sum_unclear":false,"sum_foreign":""},"59":{"sum_foreign_comment":"","sum":"","sum_comment":"","sum_foreign":""},"60":{"sum_foreign_comment":"","sum_comment_hidden":false,"sum":"","sum_comment":"","sum_foreign":""},"61":{"sum_foreign_comment":"","sum":"","sum_comment":"","sum_foreign":""},"62":{"sum_foreign_comment":"","sum":"","sum_comment":"","sum_unclear":false,"sum_foreign":""},"63":{"sum_foreign_comment":"","sum_comment_hidden":false,"sum":"","sum_comment":"","sum_foreign":""},"64":{"sum_foreign_comment":"","sum_comment_hidden":false,"sum":"","sum_comment":"","sum_foreign":""}},"ft_src":"1\nрозділ 4\nСєвєродонецьк\n93400\nЛуганська область\nОлійник Вікторія Миколаївна\nсуддя Сєвєродонецького міського суду луганської області\nЛуганська область\nЗагальний місцевий суд\nВікторія\nОлійник М. Г\nБатьки\nОлійник В. Н\nБатьки\nОлійник Вікторія Миколаївна\nВікторія Миколаївна Олійник\nВікторія Олійник\nОлійник Вікторія Миколаївна\nОлійник\nМиколаївна\n46786\n194818\n46786\n194818\nперебуває у власності\nНовоайдарський р-н\n1200\nЛуганська область\nперебуває в іншому праві користування\nЛуганська область\n1200\nперебуває в іншому праві користування\nЛуганська область\n64\nперебуває у власності\n64\nЛуганська область\nрозділ 4\n1\n2014\n194818\n46786\n194818\n46786\nрозділ 4\n1\n194818\n46786\n194818\n46786\nБатьки\nОлійник М. Г\nБатьки\nОлійник В. Н\nМиколаївна\nЛуганська область\n93400\nСєвєродонецьк\nОлійник\nОлійник Вікторія Миколаївна\nВікторія Миколаївна Олійник\nВікторія Олійник\nОлійник Вікторія Миколаївна\nОлійник Вікторія Миколаївна\nВікторія\nЗагальний місцевий суд\nЛуганська область\nсуддя Сєвєродонецького міського суду луганської області\n1200\nперебуває у власності\nЛуганська область\nНовоайдарський р-н\nперебуває в іншому праві користування\n1200\nЛуганська область\nперебуває в іншому праві користування\n64\nЛуганська область\n64\nперебуває у власності\nЛуганська область\n2014\nОлійник М. Г\nБатьки\nБатьки\nОлійник В. Н\n93400\nСєвєродонецьк\nЛуганська область\nМиколаївна\nОлійник\nЛуганська область\nЗагальний місцевий суд\nсуддя Сєвєродонецького міського суду луганської області\nОлійник Вікторія Миколаївна\nОлійник Вікторія Миколаївна\nВікторія Миколаївна Олійник\nВікторія Олійник\nОлійник Вікторія Миколаївна\nВікторія\nЛуганська область\nперебуває в іншому праві користування\n64\nНовоайдарський р-н\nЛуганська область\n1200\nперебуває у власності\nЛуганська область\n64\nперебуває у власності\nЛуганська область\nперебуває в іншому праві користування\n1200\n2014","general":{"inn":"","inn_hidden":true,"last_name":"Олійник","post":{"post_unclear":false,"region_unclear":false,"post":"суддя Сєвєродонецького міського суду луганської області","office":"Загальний місцевий суд","region":"Луганська область","post_hidden":false,"office_unclear":false},"name":"Вікторія","full_name":"Олійник Вікторія Миколаївна","family_raw":"","addresses":[{"place_district":"","place_city_hidden":false,"place_city":"Сєвєродонецьк","place_city_unclear":false,"place_district_hidden":false,"place_city_type":"Місто","place_address_hidden":true,"place_city_type_hidden":false,"place_address":"93400","place_hidden":false,"place":"Луганська область"}],"family":[{"inn_hidden":true,"inn":"","name_hidden":true,"family_name":"Олійник М. Г","relations":"Батьки","name_unclear":false},{"inn":"","relations":"Батьки","relations_other":"","inn_hidden":false,"family_name":"Олійник В. Н","name_hidden":false,"name_unclear":false}],"full_name_suggest":{"output":"Олійник Вікторія Миколаївна","input":["Олійник Вікторія Миколаївна","Вікторія Миколаївна Олійник","Вікторія Олійник"]},"patronymic":"Миколаївна"},"source":"VULYK","estate":{"23":[{"space_unclear":false,"costs":"","costs_comment":"перебуває у власності","address_hidden":true,"region_hidden":false,"space_comment":"","space":"1200","address":"Новоайдарський р-н","costs_comment_unclear":false,"region":"Луганська область","address_unclear":true,"costs_rent_comment":"","space_comment_unclear":false,"space_units":"м²","costs_rent":""}],"25":[{"space_unclear":false,"costs":"","costs_comment":"перебуває у власності","address_hidden":true,"region_hidden":true,"space_comment":"","space":"64","address":"","costs_comment_unclear":false,"region":"Луганська область","address_unclear":true,"costs_rent_comment":"","space_comment_unclear":false,"space_units":"м²","costs_rent":""}],"29":[{"region_unclear":false,"space_unclear":false,"address_hidden":true,"region_hidden":true,"space_comment":"","space":"1200","address":"","region":"Луганська область","costs_property":"","costs_rent_comment":"","address_unclear":true,"space_units":"м²","costs_property_comment":"перебуває в іншому праві користування","costs_rent":""}],"31":[{"region_unclear":false,"space_unclear":false,"costs_property_comment_unclear":false,"address_hidden":true,"region_hidden":true,"space_comment":"","space":"64","address":"","region":"Луганська область","costs_property":"","costs_rent_comment":"","space_comment_unclear":false,"address_unclear":true,"space_units":"м²","costs_property_comment":"перебуває в іншому праві користування","costs_rent":""}]},"intro":{"declaration_year":"2014"}}