{"income":{"5":{"value":"209333.34","family_comment":"","value_unclear":false,"family_unclear":false,"family":"","comment":""},"6":{"family_comment":"","family_unclear":false,"value":"209333.34","family":"","comment":""},"7":{"source_name_unclear":false,"value":"","family_comment":"","source_name":"","family":"","comment":""},"8":{"family_comment":"","value":"","family":"","comment":""},"9":{"value":"","family_comment":"","comment_hidden":false,"family_unclear":false,"family":"","comment":"","family_comment_hidden":false},"10":{"family_comment":"","value":"","family":"","comment":""},"11":{"family_comment":"","value":"","family":"","comment":""},"12":{"family_comment":"","value":"","family":"","comment":""},"13":{"family_comment":"","value":"","family":"","comment":""},"14":{"family_comment":"","value":"","family":"","comment":""},"15":{"family_comment":"","value":"","family":"","comment":""},"16":{"family_comment":"","value":"","family":"","comment":""},"17":{"family_comment":"","value":"","family":"","comment":""},"18":{"family_comment":"","value":"","family":"","comment":""},"19":{"family_comment":"","value":"","family":"","comment":""},"20":{"value":"","value_unclear":false,"comment_hidden":false,"family_comment":"","comment_unclear":false,"comment":"","family":""}},"id":"vulyk_108_140","declaration":{"additional_info_text":"","notfull_lostpages":"","date":"2016-03-10T00:00:00","notfull":"","additional_info":"","url":"http://static.declarations.com.ua/declarations/chosen_ones/judges_batch/2439_honcharenko_vadym_mykolaiovych_2015.pdf"},"liabilities":{"54":{"sum_foreign_comment":"","sum":"","sum_foreign":"","sum_comment":"","sum_hidden":false},"55":{"sum_foreign_comment":"","sum":"","sum_comment":"","sum_foreign":""},"56":{"sum_foreign_comment":"","sum":"","sum_comment":"","sum_unclear":false,"sum_foreign":""},"57":{"sum_foreign_comment":"","sum":"","sum_comment":"","sum_hidden":false,"sum_comment_hidden":false,"sum_foreign":""},"58":{"sum_foreign_comment":"","sum_comment":"","sum":"","sum_comment_hidden":false,"sum_foreign":""},"59":{"sum_foreign_comment":"","sum":"","sum_comment":"","sum_unclear":false,"sum_foreign":""},"60":{"sum_foreign_comment":"","sum_comment":"","sum":"","sum_comment_hidden":false,"sum_foreign":""},"61":{"sum_foreign_comment":"","sum_comment":"","sum":"","sum_comment_hidden":false,"sum_foreign":""},"62":{"sum_foreign_comment":"","sum":"","sum_comment":"","sum_foreign":""},"63":{"sum_foreign_comment":"","sum":"","sum_comment":"","sum_hidden":false,"sum_comment_hidden":false,"sum_unclear":false,"sum_foreign":""},"64":{"sum_foreign_comment":"","sum":"","sum_comment":"","sum_comment_hidden":false,"sum_unclear":false,"sum_foreign":""}},"ft_src":"м. Дніпропетровськ\n124\nДніпропетровська область\n2015\n209333.34\n209333.34\n124\nм. Дніпропетровськ\nДніпропетровська область\nЗагальний місцевий суд\nДніпропетровська область\nголова жовтневого районного суду м. дніпропетровська\nГончаренко\nДніпропетровськ\nДніпропетровська область\nГончаренко Вадим Миколайович\nВадим Миколайович Гончаренко\nВадим Гончаренко\nГончаренко Вадим Миколайович\nВадим\nГончаренко Вадим Миколайович\nМиколайович\n209333.34\n209333.34\n2015\nГончаренко\nМиколайович\nДніпропетровська область\nДніпропетровськ\nДніпропетровська область\nголова жовтневого районного суду м. дніпропетровська\nЗагальний місцевий суд\nГончаренко Вадим Миколайович\nГончаренко Вадим Миколайович\nВадим Миколайович Гончаренко\nВадим Гончаренко\nГончаренко Вадим Миколайович\nВадим","general":{"inn_hidden":true,"inn":"","inn_unclear":false,"post":{"post_unclear":false,"post":"голова жовтневого районного суду м. дніпропетровська","office_hidden":false,"region":"Дніпропетровська область","office":"Загальний місцевий суд","office_unclear":false},"name":"Вадим","full_name":"Гончаренко Вадим Миколайович","family_raw":"","addresses":[{"place_address":"","place_district_hidden":true,"place_city_type":"Місто","place_city_hidden":false,"place_address_unclear":false,"place_city_type_hidden":false,"place_city":"Дніпропетровськ","place":"Дніпропетровська область","place_district":"","place_unclear":false,"place_hidden":false,"place_address_hidden":true}],"last_name":"Гончаренко","full_name_suggest":{"output":"Гончаренко Вадим Миколайович","input":["Гончаренко Вадим Миколайович","Вадим Миколайович Гончаренко","Вадим Гончаренко"]},"patronymic":"Миколайович"},"source":"VULYK","estate":{"25":[{"space_unclear":false,"costs":"","costs_comment":"","address_hidden":true,"region_hidden":false,"space_comment":"","space":"124","address":"м. Дніпропетровськ","region":"Дніпропетровська область","costs_rent_comment":"","space_comment_unclear":false,"space_units":"м²","space_units_unclear":false,"costs_rent":""}]},"intro":{"declaration_year":"2015","isnotdeclaration":"","declaration_year_hidden":false}}