{"id":"vulyk_106_157","ft_src":"998 куб. см.\nFord Focus\n2013\nРівненський р-н, с. Обарів\n43.8\nРівненська область\nм. Рівне\nРівненська область\n920\n183.5\nРівненський р-н, с. Обарів\nРівненська область\nРівненський р-н, с. Обарів\n21.9\nРівненська область\nРівненський р-н, с. Обарів\n1.3\nРівненська область\n600\nм. Житомир\n11.5\nЖитомирська область\nРівненська область\nРівненський р-н, с. Обарів\n847\nРівненський р-н, с. Обарів\n474\nРівненська область\nРівненський р-н, с. Обарів\n474\nРівненська область\nРівненський р-н, с. Обарів\n790\nРівненська область\nзі слів\nРівненська область\nм. Рівне\n30.7\n2015\n13730\n195806\n169\n13398\n13899\nзі слів\n217752\nпенсія\n8548\n998 куб. см.\n2013\nFord Focus\n43.8\nРівненський р-н, с. Обарів\nРівненська область\nРівненський р-н, с. Обарів\n21.9\nРівненська область\n1.3\nРівненська область\nРівненський р-н, с. Обарів\n600\n11.5\nЖитомирська область\nм. Житомир\n847\nРівненська область\nРівненський р-н, с. Обарів\n474\nРівненська область\nРівненський р-н, с. Обарів\n474\nРівненський р-н, с. Обарів\nРівненська область\n790\nРівненський р-н, с. Обарів\nРівненська область\n920\nм. Рівне\nРівненська область\n183.5\nРівненський р-н, с. Обарів\nРівненська область\nзі слів\nм. Рівне\nРівненська область\n30.7\nШевчук Світлана Михайлівна\nСвітлана Михайлівна Шевчук\nСвітлана Шевчук\nШевчук Світлана Михайлівна\nШевчук Світлана Михайлівна\nПодружжя\nШевчук С. М\nСвітлана\nШевчук\nЖитомирська область\nАпеляційний адміністративний суд\nсуддя житомирського апеляційного адміністративного суду\nМихайлівна\nЖитомирська область\nЖитомир\n18000\n193476\n195806\n13730\n8548\nпенсія\n217752\n13899\nзі слів\n13398\n169\n2015\n18000\n193476\nШевчук С. М\nПодружжя\nМихайлівна\nШевчук\nСвітлана\nШевчук Світлана Михайлівна\nСвітлана Михайлівна Шевчук\nСвітлана Шевчук\nШевчук Світлана Михайлівна\nЖитомир\nЖитомирська область\nЖитомирська область\nАпеляційний адміністративний суд\nсуддя житомирського апеляційного адміністративного суду\nШевчук Світлана Михайлівна","estate":{"23":[{"address":"Рівненський р-н, с. Обарів","space_units":"м²","space_hidden":false,"space_unclear":false,"region_hidden":false,"costs_comment":"","space_comment_unclear":false,"space_comment_hidden":false,"space":"847","address_unclear":false,"space_comment":"","costs_rent_comment_unclear":false,"costs_comment_unclear":false,"costs_rent_comment":"","costs":"","region_unclear":false,"region":"Рівненська область","address_hidden":true,"costs_rent":""},{"address":"Рівненський р-н, с. Обарів","space_units":"м²","costs_comment":"","space_unclear":false,"region_hidden":false,"space_comment":"","address_hidden":false,"costs":"","address_unclear":false,"costs_comment_unclear":false,"costs_rent_comment":"","space":"474","region":"Рівненська область","costs_rent":""},{"costs":"","address":"Рівненський р-н, с. Обарів","space_units":"м²","costs_rent_comment":"","space":"474","space_comment":"","costs_comment":"","region":"Рівненська область","costs_rent":""},{"costs":"","address":"Рівненський р-н, с. Обарів","space_units":"м²","costs_rent_comment":"","space":"790","space_comment":"","costs_comment":"","region":"Рівненська область","costs_rent":""}],"24":[{"address":"Рівненський р-н, с. Обарів","space_units":"м²","space_hidden":false,"space_unclear":false,"region_hidden":false,"costs_rent_comment":"","space_comment":"","address_hidden":false,"space_comment_hidden":false,"costs":"","space_comment_unclear":false,"costs_comment":"","space":"183.5","region":"Рівненська область","costs_rent":""}],"27":[{"address":"Рівненський р-н, с. Обарів","space_units":"м²","space_hidden":false,"space_comment":"","region_hidden":false,"costs_comment":"","address_hidden":false,"space":"43.8","costs_rent_comment":"","costs":"","region":"Рівненська область","costs_rent":""}],"28":[{"costs":"","address":"Рівненський р-н, с. Обарів","space_units":"м²","costs_rent_comment":"","space":"21.9","space_comment":"","region_hidden":false,"costs_comment":"","region":"Рівненська область","address_hidden":false,"costs_rent":""},{"costs":"","address":"Рівненський р-н, с. Обарів","space_units":"м²","costs_rent_comment":"","space":"1.3","space_comment":"","costs_comment":"","region":"Рівненська область","costs_rent":""},{"costs":"","address":"м. Житомир","space_units":"м²","costs_rent_comment":"","space":"11.5","space_comment":"","costs_comment":"","region":"Житомирська область","costs_rent":"600"}],"29":[{"costs_property_comment":"","address":"м. Рівне","space_units":"м²","space_comment":"","region_hidden":false,"costs_property":"","region":"Рівненська область","address_hidden":true,"space_units_unclear":false,"address_unclear":false,"costs_rent_comment_unclear":false,"costs_rent_comment":"","space":"920","region_unclear":false,"space_comment_unclear":false,"costs_rent":""}],"31":[{"costs_property_comment":"","address":"м. Рівне","space_units":"м²","space_hidden":false,"space_unclear":false,"region_hidden":false,"costs_property":"","space_comment":"зі слів","address_hidden":true,"space_comment_unclear":false,"costs_rent_comment":"","space":"30.7","region":"Рівненська область","costs_rent":""}]},"vehicle":{"40":[{"year_hidden":false,"brand_info_hidden":false,"brand_info":"998 куб. см.","sum":"","sum_rent_comment":"","brand_hidden":false,"sum_comment":"","sum_rent":"","brand":"Ford Focus","year":"2013","brand_info_unclear":false}]},"source":"VULYK","income":{"5":{"family_comment":"зі слів","value":"217752","family":"13899","comment":""},"6":{"family_comment":"","value":"195806","family":"13730","comment":""},"7":{"family":"","family_comment":"","value":"","comment":"","source_name":""},"8":{"family_comment":"","value":"","family":"","comment":""},"9":{"family_comment":"","comment":"","family":"","comment_unclear":false,"value":"","family_comment_unclear":false},"10":{"family_comment":"","value":"13398","family":"169","comment":""},"11":{"family_comment":"","value":"","family":"","comment":""},"12":{"family_comment":"","value":"","family":"","comment":""},"13":{"family_comment":"","value":"","family":"","comment":""},"14":{"family_comment":"","value":"","family":"","comment":""},"15":{"family_comment":"","value":"","family":"","comment":""},"16":{"family_comment":"","value":"","family":"","comment":""},"17":{"family_comment":"","value":"","family":"","comment":""},"18":{"family_comment":"","value":"","family":"","comment":""},"19":{"family_comment":"","family":"","comment":"","value_unclear":false,"family_unclear":false,"value":""},"20":{"family_comment":"","family":"","comment":"пенсія","value_unclear":false,"value":"8548","comment_hidden":false,"comment_unclear":false,"family_unclear":false,"family_comment_hidden":false,"family_comment_unclear":false}},"general":{"family":[{"inn":"","family_name":"Шевчук С. М","relations_other":"","relations_hidden":false,"relations_unclear":false,"name_unclear":false,"inn_hidden":true,"name_hidden":true,"relations":"Подружжя"}],"family_raw":"","name":"Світлана","full_name_suggest":{"input":["Шевчук Світлана Михайлівна","Світлана Михайлівна Шевчук","Світлана Шевчук"],"output":"Шевчук Світлана Михайлівна"},"name_unclear":false,"patronymic":"Михайлівна","inn_hidden":true,"addresses":[{"place_city_type_hidden":false,"place_city_type":"Місто","place_city_hidden":false,"place_hidden":false,"place_district":"","place_district_hidden":false,"place":"Житомирська область","place_city":"Житомир","place_address_hidden":true,"place_address":""}],"inn":"","inn_unclear":false,"last_name":"Шевчук","full_name":"Шевчук Світлана Михайлівна","post":{"post_hidden":false,"office":"Апеляційний адміністративний суд","post":"суддя житомирського апеляційного адміністративного суду","office_unclear":false,"region_unclear":false,"region":"Житомирська область"}},"liabilities":{"54":{"sum_comment_unclear":false,"sum_comment":"","sum_hidden":false,"sum":"","sum_foreign_comment":"","sum_foreign":"","sum_comment_hidden":false},"55":{"sum_comment":"","sum_foreign_comment":"","sum_foreign":"","sum_hidden":false,"sum":""},"56":{"sum_comment":"","sum_hidden":false,"sum":"18000","sum_foreign_comment":"","sum_foreign":"","sum_unclear":false,"sum_comment_hidden":false},"57":{"sum_comment":"","sum_hidden":false,"sum":"","sum_foreign_comment":"","sum_foreign":"","sum_comment_hidden":false},"58":{"sum_comment":"","sum_hidden":false,"sum":"","sum_foreign_comment":"","sum_foreign":"","sum_comment_hidden":false},"59":{"sum_comment":"","sum_foreign_comment":"","sum_foreign":"","sum":""},"60":{"sum_comment":"","sum_hidden":false,"sum":"","sum_foreign_comment":"","sum_foreign":"","sum_comment_hidden":false},"61":{"sum_comment":"","sum_foreign_comment":"","sum_foreign":"","sum":""},"62":{"sum_comment":"","sum":"193476","sum_foreign_comment":"","sum_foreign":"","sum_unclear":false,"sum_comment_hidden":true},"63":{"sum_comment":"","sum_foreign_comment":"","sum_foreign":"","sum":""},"64":{"sum_comment":"","sum_foreign_comment":"","sum_foreign":"","sum":""}},"declaration":{"notfull_lostpages":"","additional_info_text":"","additional_info":"","date":"2016-03-23T00:00:00","notfull":"","url":"http://static.declarations.com.ua/declarations/chosen_ones/judges_batch/2296_shevchuk_svitlana_mykhailivna.pdf"},"intro":{"isnotdeclaration":"","declaration_year":"2015"}}