{"income":{"5":{"value":"259663.61","comment_hidden":false,"family_comment":"","family":"16347","comment":"","family_comment_hidden":false},"6":{"value":"211360.24","family_comment":"","comment_hidden":false,"family_hidden":false,"family_unclear":false,"family_comment_hidden":false,"comment":"","family":"16347"},"7":{"value":"","comment_hidden":false,"family_comment_hidden":false,"family_comment":"","source_name":"","family":"","comment":"","source_name_hidden":true},"8":{"family_comment":"","value":"","family":"","comment":""},"9":{"value":"87.8","family_comment":"","value_unclear":false,"family_unclear":false,"comment_unclear":false,"comment":"","family":""},"10":{"family_comment":"","family_unclear":false,"value":"","family":"","comment":""},"11":{"family_comment":"","value":"","family":"","comment":""},"12":{"family_comment":"","value":"","family":"","comment":""},"13":{"family_comment":"","value":"","family":"","comment":""},"14":{"family_comment":"","value":"","family":"","comment":""},"15":{"family_comment":"","value":"","comment_unclear":false,"family":"","comment":""},"16":{"family_comment":"","value":"","comment_unclear":false,"family":"","comment":""},"17":{"family_comment":"","value":"","family":"","comment":""},"18":{"family_comment":"","value":"","family":"","comment":""},"19":{"family_comment":"","value":"","family":"","comment":""},"20":{"value":"48215.57","family_comment":"","value_unclear":false,"family_unclear":false,"family_comment_unclear":false,"family_comment_hidden":false,"comment":"","family":""}},"vehicle":{"35":[{"brand_info":"1.4 л, 80 кВт, 4324 мм","sum_rent_comment":"","brand":"Chevrolet Aveo","sum_comment":"","brand_unclear":false,"year":"2005","sum_hidden":false,"brand_info_unclear":true,"sum":"","sum_rent":""}]},"id":"vulyk_73_58","banks":{"45":[{"sum_foreign_comment":"","sum_units":"UAH","sum_comment":"","sum_comment_unclear":false,"sum_hidden":false,"sum_foreign_units":"UAH","sum_comment_hidden":false,"sum_unclear":false,"sum":"8771.45","sum_foreign":""}],"46":[{"sum_foreign_comment":"","sum_units":"UAH","sum_comment":"","sum_foreign_units":"UAH","sum":"8120","sum_foreign":""}]},"declaration":{"additional_info_text":"","notfull_lostpages":"","date":"2014-12-10T00:00:00","notfull":"","additional_info":"","url":"http://static.declarations.com.ua/declarations/chosen_ones/judges_batch/1346_hladysheva_tetiana_iakivna.pdf"},"liabilities":{"54":{"sum_foreign_comment":"","sum_foreign_hidden":false,"sum_comment":"","sum_comment_unclear":false,"sum_hidden":false,"sum_comment_hidden":false,"sum_unclear":false,"sum":"","sum_foreign":""},"55":{"sum_foreign_comment":"","sum_comment_hidden":false,"sum":"","sum_comment":"","sum_foreign":""},"56":{"sum_foreign_comment":"","sum":"","sum_comment":"","sum_comment_unclear":false,"sum_foreign":""},"57":{"sum_foreign_comment":"","sum":"","sum_comment":"","sum_hidden":false,"sum_comment_hidden":false,"sum_unclear":false,"sum_foreign":""},"58":{"sum_foreign_comment":"","sum":"","sum_comment":"","sum_hidden":false,"sum_comment_hidden":false,"sum_foreign":""},"59":{"sum_foreign_comment":"","sum":"","sum_comment":"","sum_comment_unclear":false,"sum_unclear":false,"sum_foreign":""},"60":{"sum_foreign_comment":"","sum":"","sum_comment":"","sum_hidden":false,"sum_comment_hidden":false,"sum_unclear":false,"sum_foreign":""},"61":{"sum_foreign_comment":"","sum":"","sum_comment":"","sum_foreign":""},"62":{"sum_foreign_comment":"","sum":"","sum_comment":"","sum_foreign":""},"63":{"sum_foreign_comment":"","sum":"","sum_comment":"","sum_hidden":false,"sum_comment_hidden":false,"sum_foreign":""},"64":{"sum_foreign_comment":"","sum":"","sum_comment":"","sum_foreign":""}},"ft_src":"суддя одеського апеляційного господарського суду\nОдеська область\nАпеляційний господарський суд\nТетяна\nГладишева О. О., 26. 04. 1989 р. н\nДитина\nЯківна\nГладишева Тетяна Яківна\nТетяна Яківна Гладишева\nТетяна Гладишева\nГладишева Тетяна Яківна\nГладишева\nГладишева Тетяна Яківна\nChevrolet Aveo\n1.4 л, 80 кВт, 4324 мм\n2005\n118.4\n8120\n8771.45\n2013\n1.4 л, 80 кВт, 4324 мм\nChevrolet Aveo\n2005\n2013\nГладишева Тетяна Яківна\nТетяна Яківна Гладишева\nТетяна Гладишева\nГладишева Тетяна Яківна\nТетяна\nДитина\nГладишева О. О., 26. 04. 1989 р. н\nГладишева Тетяна Яківна\nЯківна\nАпеляційний господарський суд\nОдеська область\nсуддя одеського апеляційного господарського суду\nГладишева\n16347\n211360.24\n48215.57\n259663.61\n16347\n87.8\n118.4\n8771.45\n8120\n16347\n211360.24\n87.8\n16347\n259663.61\n48215.57\nДитина\nГладишева О. О., 26. 04. 1989 р. н\nЯківна\nГладишева\nТетяна\nГладишева Тетяна Яківна\nТетяна Яківна Гладишева\nТетяна Гладишева\nГладишева Тетяна Яківна\nОдеська область\nАпеляційний господарський суд\nсуддя одеського апеляційного господарського суду\nГладишева Тетяна Яківна\n2005\n1.4 л, 80 кВт, 4324 мм\nChevrolet Aveo\n87.8\n48215.57\n259663.61\n16347\n211360.24\n16347\n118.4\n8771.45\n8120\n2013","general":{"inn":"","name":"Тетяна","family":[{"inn":"","relations":"Дитина","inn_unclear":false,"relations_hidden":false,"inn_hidden":true,"relations_other":"","name_hidden":false,"family_name":"Гладишева О. О., 26. 04. 1989 р. н","name_unclear":false}],"patronymic":"Яківна","inn_hidden":true,"family_raw":"","last_name":"Гладишева","post":{"post_unclear":false,"region_unclear":false,"post":"суддя одеського апеляційного господарського суду","office":"Апеляційний господарський суд","region":"Одеська область","post_hidden":false,"office_hidden":false,"office_unclear":false,"region_hidden":false},"last_name_unclear":false,"full_name":"Гладишева Тетяна Яківна","addresses":[{"place_district":"","place_city_hidden":true,"place_city":"","place_city_type_hidden":true,"place_district_hidden":true,"place_city_type":"","place_address_hidden":true,"place_address":"","place_hidden":true,"place":""}],"full_name_suggest":{"output":"Гладишева Тетяна Яківна","input":["Гладишева Тетяна Яківна","Тетяна Яківна Гладишева","Тетяна Гладишева"]},"name_unclear":false},"source":"VULYK","estate":{"31":[{"space_unclear":false,"address_hidden":true,"region_hidden":true,"space_comment":"","space":"118.4","address":"","region":"","costs_property":"","costs_rent_comment":"","space_units":"м²","costs_property_comment":"","costs_rent":""}]},"intro":{"declaration_year":"2013"}}