{"income":{"5":{"value":"260469.97","family_comment":"","value_unclear":false,"family_hidden":false,"value_hidden":false,"family_unclear":false,"family":"","comment":"","family_comment_unclear":false},"6":{"value":"248289.97","family_comment":"","value_unclear":false,"comment_hidden":false,"family_hidden":false,"value_hidden":false,"family_unclear":false,"family":"","comment":""},"7":{"value":"","value_hidden":false,"family_comment":"","source_name":"","family":"","comment":"","source_name_hidden":false},"8":{"family_comment":"","value":"","family":"","comment":""},"9":{"value":"","comment_hidden":false,"value_hidden":false,"family_comment":"","family":"","comment":""},"10":{"value":"12180","value_unclear":false,"value_hidden":false,"family_comment":"","family":"","comment":""},"11":{"family_comment":"","value":"","family":"","comment":""},"12":{"family_comment":"","value":"","family":"","comment":""},"13":{"family_comment":"","value":"","family_hidden":false,"comment":"","family":""},"14":{"family_comment":"","value":"","family":"","comment":""},"15":{"family_comment":"","family_unclear":false,"value":"","family":"","comment":""},"16":{"family_comment":"","value":"","value_unclear":false,"family":"","comment":""},"17":{"family_comment":"","value":"","family":"","comment":""},"18":{"family_comment":"","value":"","family":"","comment":""},"19":{"family_comment":"","value":"","comment_unclear":false,"family":"","comment":""},"20":{"value":"24000","comment_unclear":false,"family_hidden":false,"value_hidden":false,"family_comment":"","family":"","comment":"пенсія"}},"id":"vulyk_64_172","declaration":{"additional_info_text":"","notfull_lostpages":"","date":"2015-03-25T00:00:00","notfull":"","additional_info":"","url":"http://static.declarations.com.ua/declarations/chosen_ones/mega_batch/vorobiova_valentyna_mykolaivna.pdf"},"liabilities":{"54":{"sum_foreign_comment":"","sum":"","sum_comment":"","sum_foreign_comment_hidden":false,"sum_hidden":false,"sum_comment_hidden":false,"sum_unclear":false,"sum_foreign":""},"55":{"sum_foreign_comment":"","sum":"","sum_comment":"","sum_comment_unclear":false,"sum_foreign":""},"56":{"sum_foreign_comment":"","sum":"7200","sum_comment":"","sum_unclear":false,"sum_foreign":""},"57":{"sum_foreign_comment":"","sum":"","sum_comment":"","sum_hidden":false,"sum_unclear":false,"sum_foreign":""},"58":{"sum_foreign_comment":"","sum":"","sum_comment":"","sum_unclear":false,"sum_foreign":""},"59":{"sum_foreign_comment":"","sum":"","sum_comment":"","sum_comment_unclear":false,"sum_comment_hidden":false,"sum_unclear":false,"sum_foreign":""},"60":{"sum_foreign_comment":"","sum":"","sum_comment":"","sum_foreign":""},"61":{"sum_foreign_comment":"","sum":"","sum_comment":"","sum_foreign":""},"62":{"sum_foreign_comment":"","sum":"","sum_comment":"","sum_unclear":false,"sum_foreign":""},"63":{"sum_foreign_comment":"","sum":"","sum_comment":"","sum_unclear":false,"sum_foreign":""},"64":{"sum_foreign_comment":"","sum":"","sum_comment":"","sum_comment_unclear":false,"sum_unclear":false,"sum_foreign":""}},"ft_src":"7200\nсуддя васильківського міськрайонного суду київської області\nКиївська область\nЗагальний місцевий суд\nВалентина\nМиколаївна\nВоробйова\nВоробйова Валентина Миколаївна\nВоробйова Валентина Миколаївна\nВалентина Миколаївна Воробйова\nВалентина Воробйова\nВоробйова Валентина Миколаївна\n12180\n24000\nпенсія\n260469.97\n248289.97\n50.2\n2014\n248289.97\n12180\n260469.97\nпенсія\n24000\n50.2\nЗагальний місцевий суд\nКиївська область\nсуддя васильківського міськрайонного суду київської області\nВоробйова Валентина Миколаївна\nВалентина Миколаївна Воробйова\nВалентина Воробйова\nВоробйова Валентина Миколаївна\nВалентина\nВоробйова Валентина Миколаївна\nВоробйова\nМиколаївна\n7200\n248289.97\n24000\nпенсія\n260469.97\n12180\n2014\n7200\nВалентина\nМиколаївна\nВоробйова\nВоробйова Валентина Миколаївна\nВалентина Миколаївна Воробйова\nВалентина Воробйова\nВоробйова Валентина Миколаївна\nКиївська область\nЗагальний місцевий суд\nсуддя васильківського міськрайонного суду київської області\nВоробйова Валентина Миколаївна\n50.2\n2014","general":{"inn":"","name":"Валентина","last_name_hidden":false,"last_name":"Воробйова","patronymic":"Миколаївна","inn_hidden":false,"family_raw":"","inn_unclear":false,"post":{"post_unclear":false,"post":"суддя васильківського міськрайонного суду київської області","candidate":"","office_hidden":false,"region":"Київська область","post_hidden":false,"office":"Загальний місцевий суд","office_unclear":false,"region_hidden":false},"last_name_unclear":false,"full_name":"Воробйова Валентина Миколаївна","patronymic_hidden":false,"full_name_suggest":{"output":"Воробйова Валентина Миколаївна","input":["Воробйова Валентина Миколаївна","Валентина Миколаївна Воробйова","Валентина Воробйова"]},"name_unclear":false},"source":"VULYK","estate":{"25":[{"region_unclear":false,"space_unclear":false,"costs":"","costs_rent_unclear":false,"costs_comment":"","costs_hidden":false,"address_hidden":false,"region_hidden":false,"space_comment":"","space_hidden":false,"space":"50.2","space_units_hidden":false,"costs_rent_comment_unclear":false,"region":"","costs_rent_comment":"","costs_rent_hidden":false,"space_comment_unclear":false,"space_units":"м²","address":"","costs_rent":"","costs_unclear":false}]},"intro":{"declaration_year":"2014","isnotdeclaration":"","declaration_year_unclear":false,"declaration_year_hidden":false}}