{"income":{"5":{"value":"243456","value_unclear":false,"value_hidden":false,"family_comment":"","family":"110102","comment":""},"6":{"value":"243225","family_comment":"","value_unclear":false,"family_unclear":false,"family":"110044","comment":""},"7":{"source_name_unclear":false,"value":"","family_hidden":false,"family_comment":"","source_name":"","family":"","comment":""},"8":{"family_comment":"","value":"","family":"","comment":""},"9":{"family_comment":"","value":"231","family":"58","comment":""},"10":{"family_comment":"","value":"","family":"","comment":""},"11":{"family_comment":"","value":"","family":"","comment":""},"12":{"family_comment":"","value":"","family":"","comment":""},"13":{"family_comment":"","value":"","family":"","comment":""},"14":{"family_comment":"","value":"","family":"","comment":""},"15":{"family_comment":"","value":"","family":"","comment":""},"16":{"family_comment":"","value":"","comment_unclear":false,"family":"","comment":""},"17":{"family_comment":"","family_unclear":false,"value":"","family":"","comment":""},"18":{"family_comment":"","value":"","family":"","comment":""},"19":{"value":"","family_hidden":false,"value_hidden":false,"family_comment":"","family":"","comment":""},"20":{"family_comment":"","value":"","comment_unclear":false,"family":"","comment":""}},"vehicle":{"35":[{"brand_info":"1587 куб. см.","sum_rent_comment":"","year":"2011","sum_rent_unclear":false,"brand_info_hidden":false,"brand_info_unclear":false,"year_unclear":false,"sum_rent":"","sum":"","brand":"Geely MK","sum_comment":"","sum_comment_unclear":false,"brand_hidden":false,"sum_unclear":false,"brand_unclear":false}],"40":[{"brand_info":"1500 куб. см.","sum_rent_comment":"","brand":"ВАЗ 2107","sum_comment":"","brand_unclear":false,"year":"1992","brand_info_unclear":false,"year_unclear":false,"sum":"","sum_rent":""},{"brand_info":"1598 куб. см.","sum_rent_comment":"","brand":"Chevrolet Lacetti","sum_comment":"","year":"2006","brand_info_unclear":false,"year_unclear":false,"sum":"","sum_rent":""}]},"id":"vulyk_67_15","banks":{"51":[{"sum_foreign_comment":"","sum_units":"UAH","sum_comment":"","sum_comment_unclear":false,"sum_hidden":false,"sum_foreign_units":"UAH","sum_comment_hidden":false,"sum_unclear":false,"sum":"4370","sum_foreign":""}]},"declaration":{"additional_info_text":"","notfull_lostpages":"","date":"2015-03-30T00:00:00","notfull":"","additional_info":"","url":"http://static.declarations.com.ua/declarations/chosen_ones/mega_batch/ushak_iryna_heorhiivna.pdf"},"liabilities":{"54":{"sum_foreign_comment":"","sum_foreign_hidden":false,"sum_comment":"","sum_comment_unclear":false,"sum_hidden":false,"sum":"","sum_unclear":false,"sum_foreign":""},"55":{"sum_foreign_comment":"","sum":"","sum_comment":"","sum_foreign":""},"56":{"sum_foreign_comment":"","sum_foreign_hidden":false,"sum_comment":"","sum_hidden":false,"sum":"7600","sum_unclear":false,"sum_foreign":""},"57":{"sum_foreign_comment":"","sum_foreign_hidden":false,"sum_comment":"","sum_comment_unclear":false,"sum_hidden":false,"sum_comment_hidden":false,"sum_unclear":false,"sum":"","sum_foreign":""},"58":{"sum_foreign_comment":"","sum_foreign_hidden":false,"sum_comment":"","sum_comment_unclear":false,"sum_hidden":false,"sum_comment_hidden":false,"sum_unclear":false,"sum":"","sum_foreign":""},"59":{"sum_foreign_comment":"","sum":"","sum_hidden":false,"sum_comment":"","sum_foreign":""},"60":{"sum_foreign_comment":"","sum":"","sum_comment":"","sum_foreign":""},"61":{"sum_foreign_comment":"","sum_foreign_hidden":false,"sum_comment":"","sum_hidden":false,"sum":"","sum_foreign":""},"62":{"sum_foreign_comment":"","sum":"","sum_hidden":false,"sum_comment":"","sum_foreign":""},"63":{"sum_foreign_comment":"","sum":"5000","sum_comment":"","sum_comment_unclear":true,"sum_hidden":false,"sum_unclear":false,"sum_foreign":""},"64":{"sum_foreign_comment":"","sum":"981","sum_comment":"","sum_hidden":false,"sum_unclear":false,"sum_foreign":""}},"ft_src":"981\n5000\n7600\nКам'яниця\nУжгородський\nЗакарпатська область\nСело\nсуддя господарського суду закарпатської області\nЗакарпатська область\nГосподарський місцевий суд\nІрина\nУшак А. С\nПодружжя\nГудзак Є. А\nДитина\nУшак Я. А\nДитина\nГеоргіївна\nУшак Ірина Георгіївна\nУшак\nУшак Ірина Георгіївна\nІрина Георгіївна Ушак\nІрина Ушак\nУшак Ірина Георгіївна\n1587 куб. см.\nGeely MK\n2011\n1500 куб. см.\nВАЗ 2107\n1992\n2006\n1598 куб. см.\nChevrolet Lacetti\n4370\n2014\n1587 куб. см.\nGeely MK\n2011\n1500 куб. см.\n1992\nВАЗ 2107\n1598 куб. см.\n2006\nChevrolet Lacetti\n4370\n250\nЗакарпатська область\nс. Кам'яниця\n130\nс. Кам'яниця\nЗакарпатська область\n180\nс. Гута\nЗакарпатська область\n100\nс. Гута\nЗакарпатська область\n113\nс. Гута\nЗакарпатська область\n113\nс. Гута\nЗакарпатська область\n131\nс. Кам'яниця\nЗакарпатська область\n69\nЗакарпатська область\nм. Ужгород\nГосподарський місцевий суд\nсуддя господарського суду закарпатської області\nЗакарпатська область\nПодружжя\nУшак А. С\nДитина\nГудзак Є. А\nДитина\nУшак Я. А\nУшак Ірина Георгіївна\nІрина Георгіївна Ушак\nІрина Ушак\nУшак Ірина Георгіївна\nУшак Ірина Георгіївна\nІрина\nУшак\nГеоргіївна\nСело\nКам'яниця\nЗакарпатська область\nУжгородський\n5000\n981\n7600\n110044\n243225\n243456\n110102\n231\n58\n2014\n981\n7600\n5000\nс. Кам'яниця\n250\nЗакарпатська область\nс. Кам'яниця\n130\nЗакарпатська область\nс. Гута\n180\nЗакарпатська область\nс. Гута\nЗакарпатська область\n100\nЗакарпатська область\nс. Гута\n113\nЗакарпатська область\nс. Гута\n113\nс. Кам'яниця\n131\nЗакарпатська область\nм. Ужгород\n69\nЗакарпатська область\nПодружжя\nУшак А. С\nДитина\nГудзак Є. А\nУшак Я. А\nДитина\nГеоргіївна\nУшак\nІрина\nУшак Ірина Георгіївна\nІрина Георгіївна Ушак\nІрина Ушак\nУшак Ірина Георгіївна\nЗакарпатська область\nКам'яниця\nУжгородський\nСело\nЗакарпатська область\nсуддя господарського суду закарпатської області\nГосподарський місцевий суд\nУшак Ірина Георгіївна\n110044\n243225\n110102\n243456\n58\n231\n2011\nGeely MK\n1587 куб. см.\n1992\n1500 куб. см.\nВАЗ 2107\n2006\n1598 куб. см.\nChevrolet Lacetti\n243456\n110102\n58\n231\n243225\n110044\nм. Ужгород\nЗакарпатська область\n69\nс. Кам'яниця\nЗакарпатська область\n250\nс. Кам'яниця\nЗакарпатська область\n130\nс. Гута\nЗакарпатська область\n180\nс. Кам'яниця\nЗакарпатська область\n131\nЗакарпатська область\nс. Гута\n100\nс. Гута\nЗакарпатська область\n113\nс. Гута\nЗакарпатська область\n113\n4370\n2014","general":{"inn":"","name":"Ірина","patronymic_unclear":false,"last_name_hidden":false,"family":[{"inn":"","inn_hidden":true,"relations_unclear":false,"relations_hidden":false,"relations_other":"","relations":"Подружжя","name_hidden":true,"inn_unclear":false,"family_name":"Ушак А. С","name_unclear":false},{"inn":"","inn_hidden":true,"relations_unclear":false,"relations_hidden":false,"relations_other":"","relations":"Дитина","name_hidden":false,"inn_unclear":false,"family_name":"Гудзак Є. А","name_unclear":true},{"inn":"","relations":"Дитина","relations_unclear":false,"family_name":"Ушак Я. А","inn_hidden":true,"relations_other":"","name_hidden":false,"name_unclear":false}],"patronymic":"Георгіївна","inn_hidden":true,"family_raw":"","inn_unclear":false,"post":{"post_unclear":false,"post":"суддя господарського суду закарпатської області","post_hidden":false,"region":"Закарпатська область","region_hidden":false,"office":"Господарський місцевий суд","office_hidden":false,"office_unclear":false},"last_name_unclear":false,"full_name":"Ушак Ірина Георгіївна","addresses":[{"place_city_type_hidden":false,"place_district_hidden":false,"place_city_type":"Село","place_city_hidden":false,"place_address_unclear":false,"place_address":"","place":"Закарпатська область","place_district":"Ужгородський","place_unclear":false,"place_city":"Кам'яниця","place_city_unclear":false,"place_hidden":false,"place_address_hidden":true,"place_district_unclear":false}],"last_name":"Ушак","full_name_suggest":{"output":"Ушак Ірина Георгіївна","input":["Ушак Ірина Георгіївна","Ірина Георгіївна Ушак","Ірина Ушак"]},"name_unclear":false},"source":"VULYK","estate":{"23":[{"space_hidden":false,"costs":"","costs_comment":"","costs_hidden":false,"address_hidden":true,"region_hidden":false,"space_comment":"","space_unclear":false,"space":"250","address":"с. Кам'яниця","region":"Закарпатська область","address_unclear":false,"space_units_unclear":false,"costs_rent_hidden":false,"space_comment_unclear":false,"space_units":"м²","costs_rent":"","costs_rent_comment":""},{"space_unclear":false,"costs":"","costs_comment":"","address_hidden":false,"region_hidden":true,"space_comment":"","space":"130","address":"с. Кам'яниця","region":"Закарпатська область","costs_rent_comment":"","space_comment_unclear":false,"space_units":"м²","space_units_unclear":false,"costs_rent":""},{"space_unclear":false,"costs":"","costs_comment":"","address_hidden":false,"region_hidden":true,"space_comment":"","space":"180","address":"с. Гута","region":"Закарпатська область","costs_rent_comment":"","space_units":"м²","space_units_unclear":false,"costs_rent":""}],"24":[{"space_hidden":false,"costs":"","costs_comment":"","costs_hidden":false,"address_hidden":true,"region_hidden":false,"space_comment":"","space":"131","address":"с. Кам'яниця","region":"Закарпатська область","costs_rent_comment":"","space_comment_unclear":false,"space_units":"м²","costs_rent":""}],"25":[{"space_unclear":false,"costs":"","costs_comment":"","costs_hidden":false,"address_hidden":true,"region_hidden":false,"space_comment":"","space":"69","address":"м. Ужгород","region":"Закарпатська область","address_unclear":false,"space_units_unclear":false,"space_comment_unclear":false,"space_units":"м²","costs_rent":"","costs_rent_comment":""}],"29":[{"region_unclear":false,"space_unclear":false,"address_hidden":true,"region_hidden":true,"space_comment":"","space_units_hidden":false,"space_hidden":false,"space":"100","address":"с. Гута","region":"Закарпатська область","costs_property":"","costs_rent_comment":"","space_units":"м²","costs_property_comment":"","costs_rent":""},{"costs_rent":"","region":"Закарпатська область","costs_property":"","costs_rent_comment":"","address_hidden":false,"region_hidden":false,"space_comment":"","costs_property_comment":"","space_units":"м²","space":"113","address":"с. Гута"},{"costs_rent":"","region":"Закарпатська область","costs_property":"","costs_rent_comment":"","address_hidden":false,"space_comment":"","costs_property_comment":"","space_units":"м²","space":"113","address":"с. Гута"}]},"intro":{"declaration_year":"2014","isnotdeclaration":"","declaration_year_hidden":false}}