{"income":{"5":{"family_comment":"","value":"280751.62","value_unclear":false,"family":"18693.33","comment":""},"6":{"value":"280751.62","value_unclear":false,"family_hidden":false,"family_comment":"","family":"","comment":""},"7":{"source_name_unclear":false,"value":"","family_comment":"","source_name":"","family":"","comment":""},"8":{"family_comment":"","value":"","family":"","comment":""},"9":{"family_comment":"","value":"","family":"","comment":""},"10":{"family_comment":"","value":"","family":"","comment":""},"11":{"family_comment":"","value":"","comment_unclear":false,"family":"","comment":""},"12":{"family_comment":"","value":"","family":"","comment":""},"13":{"family_comment":"","value":"","family":"","comment":""},"14":{"family_comment":"","value":"","family":"","comment":""},"15":{"family_comment":"","value":"","family":"","comment":""},"16":{"family_comment":"","value":"","family":"","comment":""},"17":{"family_comment":"","value":"","family":"","comment":""},"18":{"family_comment":"","value":"","family":"","comment":""},"19":{"family_comment":"","value":"","family":"","comment":""},"20":{"value":"","family_comment":"","value_unclear":false,"family_unclear":false,"comment_unclear":false,"comment":"","family":"18693.33"}},"vehicle":{"40":[{"brand_info":"1995 куб. см.","sum_rent_comment":"","brand":"BMW 320","sum_comment":"","year":"2006","brand_hidden":false,"brand_info_hidden":false,"brand_info_unclear":false,"sum":"","sum_rent":""},{"brand_info":"2497 куб. см.","sum_rent_comment":"","brand":"BMW 523","sum_comment":"","year":"2008","brand_info_unclear":false,"sum":"","sum_rent":""}]},"id":"vulyk_101_23","declaration":{"additional_info_text":"","notfull_lostpages":"","date":"2016-03-30T00:00:00","notfull":"","additional_info":"","url":"http://static.declarations.com.ua/declarations/chosen_ones/judges_batch/687_dyrdin_oleksandr_dmytrovych_2015.pdf"},"liabilities":{"54":{"sum_foreign_comment":"","sum":"","sum_comment":"","sum_comment_unclear":false,"sum_hidden":false,"sum_comment_hidden":false,"sum_unclear":false,"sum_foreign":""},"55":{"sum_foreign_comment":"","sum":"","sum_comment":"","sum_foreign":""},"56":{"sum_foreign_comment":"","sum":"6298","sum_comment":"","sum_comment_hidden":false,"sum_unclear":false,"sum_foreign":""},"57":{"sum_foreign_comment":"","sum":"","sum_comment":"","sum_hidden":false,"sum_comment_hidden":false,"sum_unclear":false,"sum_foreign":""},"58":{"sum_foreign_comment":"","sum":"","sum_comment":"","sum_comment_unclear":false,"sum_hidden":false,"sum_comment_hidden":false,"sum_unclear":false,"sum_foreign":""},"59":{"sum_foreign_comment":"","sum":"","sum_comment":"","sum_foreign":""},"60":{"sum_foreign_comment":"","sum":"","sum_comment":"","sum_hidden":false,"sum_comment_hidden":false,"sum_unclear":false,"sum_foreign":""},"61":{"sum_foreign_comment":"","sum":"","sum_comment":"","sum_foreign":""},"62":{"sum_foreign_comment":"","sum":"60000","sum_comment":"приблизно","sum_comment_unclear":false,"sum_foreign":""},"63":{"sum_foreign_comment":"","sum_comment_hidden":false,"sum":"","sum_comment":"","sum_foreign":""},"64":{"sum_foreign_comment":"","sum_comment_hidden":false,"sum":"","sum_comment":"","sum_foreign":""}},"ft_src":"приблизно\n60000\n6298\nсуддя апеляційного суду одеської області\nОдеська область\nЗагальний апеляційний суд\nОлександр\nДирдіна Наталя Андріївна\nПодружжя\nДмитрович\nДирдін Олександр Дмитрович\nДирдін\nДирдін Олександр Дмитрович\nОлександр Дмитрович Дирдін\nОлександр Дирдін\nДирдін Олександр Дмитрович\n1995 куб. см.\nBMW 320\n2006\n2497 куб. см.\n2008\nBMW 523\n119.7\n248.9\n45.3\n2015\n280751.62\n18693.33\n280751.62\n18693.33\n1995 куб. см.\n2006\nBMW 320\n2497 куб. см.\nBMW 523\n2008\n248.9\n119.7\n45.3\nДирдін Олександр Дмитрович\nОлександр Дмитрович Дирдін\nОлександр Дирдін\nДирдін Олександр Дмитрович\nОлександр\nДирдін Олександр Дмитрович\nДмитрович\nсуддя апеляційного суду одеської області\nОдеська область\nЗагальний апеляційний суд\nДирдін\nПодружжя\nДирдіна Наталя Андріївна\n6298\n60000\nприблизно\n280751.62\n18693.33\n280751.62\n18693.33\n2015\n6298\nприблизно\n60000\nДирдіна Наталя Андріївна\nПодружжя\nОлександр\nДмитрович\nДирдін\nДирдін Олександр Дмитрович\nОлександр Дмитрович Дирдін\nОлександр Дирдін\nДирдін Олександр Дмитрович\nсуддя апеляційного суду одеської області\nОдеська область\nЗагальний апеляційний суд\nДирдін Олександр Дмитрович\nBMW 320\n1995 куб. см.\n2006\n2008\n2497 куб. см.\nBMW 523\n18693.33\n18693.33\n280751.62\n280751.62\n119.7\n248.9\n45.3\n2015","general":{"inn":"","name":"Олександр","inn_unclear":false,"family":[{"inn":"","relations":"Подружжя","relations_other":"","inn_hidden":true,"family_name":"Дирдіна Наталя Андріївна","name_hidden":true,"name_unclear":false}],"inn_hidden":true,"family_raw":"","last_name":"Дирдін","post":{"region":"Одеська область","region_unclear":false,"post":"суддя апеляційного суду одеської області","office_unclear":false,"office":"Загальний апеляційний суд"},"full_name":"Дирдін Олександр Дмитрович","addresses":[{"place_district":"","place_address_hidden":true,"place_city":"","place_city_type_hidden":false,"place_district_hidden":false,"place_city_type":"","place_city_hidden":true,"place_address":"","place_hidden":true,"place":""}],"patronymic":"Дмитрович","patronymic_hidden":false,"full_name_suggest":{"output":"Дирдін Олександр Дмитрович","input":["Дирдін Олександр Дмитрович","Олександр Дмитрович Дирдін","Олександр Дирдін"]}},"source":"VULYK","estate":{"25":[{"space_unclear":false,"costs":"","costs_comment":"","address_hidden":false,"region_hidden":true,"space_comment":"","space_hidden":false,"space":"45.3","address":"","region":"","costs_rent_comment":"","space_comment_unclear":false,"space_units":"м²","costs_rent":""}],"30":[{"costs_rent":"","region":"","costs_property":"","costs_rent_comment":"","address_hidden":false,"region_hidden":true,"space_comment":"","costs_property_comment":"","space_units":"м²","space":"248.9","address":""}],"31":[{"space_unclear":false,"address_hidden":false,"region_hidden":true,"space_comment":"","space_hidden":false,"space":"119.7","address":"","costs_rent_comment_unclear":false,"region":"","costs_property":"","costs_rent_comment":"","space_units":"м²","costs_property_comment":"","costs_rent":""}]},"intro":{"declaration_year":"2015"}}