{"income":{"5":{"family_comment":"","value":"288749.87","family":"","comment":""},"6":{"family_comment":"","value":"252406.91","family":"","comment":""},"7":{"value":"","comment_hidden":false,"family_comment":"","source_name":"","family":"","comment":"","source_name_hidden":false},"8":{"family_comment":"","value":"","family_hidden":false,"comment":"","family":""},"9":{"value":"36342.96","family_comment":"","value_unclear":false,"family_unclear":false,"family":"","comment":"Промінвестбанк"},"10":{"family_comment":"","value":"","family":"","comment":""},"11":{"family_comment":"","value":"","family":"","comment":""},"12":{"family_comment":"","value":"","family":"","comment":""},"13":{"family_comment":"","value":"","family":"","comment":""},"14":{"family_comment":"","value":"","family":"","comment":""},"15":{"family_comment":"","value":"","family":"","comment":""},"16":{"family_comment":"","value":"","family":"","comment":""},"17":{"family_comment":"","value":"","family":"","comment":""},"18":{"family_comment":"","value":"","family":"","comment":""},"19":{"family_comment":"","value":"","family":"","comment":""},"20":{"value":"","value_unclear":false,"family_hidden":false,"family_comment":"","family":"","comment":""}},"id":"vulyk_109_89","banks":{"45":[{"sum_foreign_comment":"","sum_unclear":false,"sum_units":"UAH","sum_comment":"","sum_foreign_units":"UAH","sum_comment_hidden":false,"sum_units_hidden":false,"sum":"213727","sum_foreign":""}]},"declaration":{"additional_info_text":"","notfull_lostpages":"","date":"2016-03-25T00:00:00","notfull":"","additional_info":"","url":"http://static.declarations.com.ua/declarations/chosen_ones/judges_batch/2546_marishchenko_larysa_oleksandrivna_2015.pdf"},"liabilities":{"54":{"sum_foreign_comment":"","sum":"","sum_comment":"","sum_hidden":false,"sum_comment_hidden":false,"sum_unclear":false,"sum_foreign":""},"55":{"sum_foreign_comment":"","sum":"","sum_comment":"","sum_comment_unclear":false,"sum_foreign":""},"56":{"sum_foreign_comment":"","sum":"2834.4","sum_comment":"","sum_foreign":""},"57":{"sum_foreign_comment":"","sum_comment_hidden":false,"sum":"","sum_comment":"","sum_foreign":""},"58":{"sum_foreign_comment":"","sum_comment_hidden":false,"sum":"","sum_comment":"","sum_foreign":""},"59":{"sum_foreign_comment":"","sum":"","sum_comment":"","sum_foreign":""},"60":{"sum_foreign_comment":"","sum":"","sum_comment":"","sum_foreign":""},"61":{"sum_foreign_comment":"","sum":"","sum_comment":"","sum_foreign":""},"62":{"sum_foreign_comment":"","sum":"","sum_comment":"","sum_foreign":""},"63":{"sum_foreign_comment":"","sum":"","sum_comment":"","sum_foreign":""},"64":{"sum_foreign_comment":"","sum":"","sum_comment":"","sum_foreign":""}},"ft_src":"2834.4\nсуддя господарського суду житомирської області\nЖитомирська область\nГосподарський місцевий суд\nЛариса\nОлександрівна\nМаріщенко Лариса Олександрівна\nЛариса Олександрівна Маріщенко\nЛариса Маріщенко\nМаріщенко Лариса Олександрівна\nМаріщенко Лариса Олександрівна\nМаріщенко\n83.9\n66.1\n213727\n2015\n2015\nМаріщенко Лариса Олександрівна\nЛариса Олександрівна Маріщенко\nЛариса Маріщенко\nМаріщенко Лариса Олександрівна\nМаріщенко Лариса Олександрівна\nЛариса\nМаріщенко\nГосподарський місцевий суд\nЖитомирська область\nсуддя господарського суду житомирської області\nОлександрівна\n2834.4\n252406.91\n288749.87\nПромінвестбанк\n36342.96\n83.9\n66.1\n213727\n2834.4\n252406.91\n288749.87\nПромінвестбанк\n36342.96\nОлександрівна\nМаріщенко\nЛариса\nМаріщенко Лариса Олександрівна\nЛариса Олександрівна Маріщенко\nЛариса Маріщенко\nМаріщенко Лариса Олександрівна\nЖитомирська область\nГосподарський місцевий суд\nсуддя господарського суду житомирської області\nМаріщенко Лариса Олександрівна\n288749.87\nПромінвестбанк\n36342.96\n252406.91\n83.9\n66.1\n213727\n2015","general":{"name_hidden":false,"name":"Лариса","inn":"","inn_unclear":false,"patronymic":"Олександрівна","inn_hidden":true,"family_raw":"","last_name":"Маріщенко","post":{"region_unclear":false,"region":"Житомирська область","post":"суддя господарського суду житомирської області","region_hidden":false,"office":"Господарський місцевий суд","office_hidden":false,"office_unclear":false},"full_name":"Маріщенко Лариса Олександрівна","addresses":[{"place_district":"","place_city_hidden":true,"place_city":"","place_city_type_hidden":true,"place_district_hidden":true,"place_city_type":"","place_address_hidden":true,"place_address":"","place_hidden":true,"place":""}],"full_name_suggest":{"output":"Маріщенко Лариса Олександрівна","input":["Маріщенко Лариса Олександрівна","Лариса Олександрівна Маріщенко","Лариса Маріщенко"]}},"source":"VULYK","estate":{"25":[{"space_unclear":false,"costs":"","costs_comment":"","address_hidden":false,"region_hidden":true,"space_comment":"","space_hidden":false,"space":"83.9","address":"","region":"","costs_rent_comment":"","space_units":"м²","space_units_hidden":false,"costs_rent":""},{"costs_rent":"","region":"","costs":"","costs_rent_comment":"","costs_comment":"","address_hidden":false,"region_hidden":false,"space_comment":"","space_units":"","space":"66.1","address":""}]},"intro":{"declaration_year":"2015","isnotdeclaration":""}}