{"income":{"5":{"value":"138717","value_unclear":false,"comment_hidden":false,"family_comment":"","family":"879486","comment":""},"6":{"family_comment":"","value":"68009","family":"","comment":"","value_hidden":false},"7":{"family_comment":"","value":"","source_name":"","family":"","comment":""},"8":{"family_comment":"","value":"","family":"","comment":""},"9":{"family_comment":"","value":"","comment_hidden":false,"family":"","comment":""},"10":{"family_comment":"","value":"","family":"","comment":""},"11":{"family_comment":"","value":"","family":"","comment":""},"12":{"family_comment":"","value":"","family":"","comment":""},"13":{"family_comment":"","value":"","family":"","comment":""},"14":{"family_comment":"","value":"","family":"","comment":""},"15":{"family_comment":"","value":"","family":"","comment":"","family_comment_hidden":false},"16":{"family_comment":"","value":"","family":"","comment":""},"17":{"family_comment":"","value":"","family":"879486","comment":""},"18":{"family_comment":"","value":"","family":"","comment":"","value_hidden":false},"19":{"family_comment":"","value":"","family":"","comment":""},"20":{"family_comment":"","value":"70708","family":"","comment":"","family_comment_unclear":false}},"id":"vulyk_78_53","banks":{"51":[{"sum_foreign_comment":"","sum_units":"UAH","sum_comment":"","sum_foreign_units":"UAH","sum":"50000","sum_foreign":""}]},"declaration":{"additional_info_text":"","notfull_lostpages":"","date":"2015-03-27T00:00:00","notfull":"","additional_info":"","url":"http://static.declarations.com.ua/declarations/chosen_ones/judges_batch/2120_nezdymovska_(medushevska)_anna_oleksiivna.pdf"},"liabilities":{"54":{"sum_foreign_comment":"","sum_foreign_hidden":false,"sum_comment":"","sum_comment_unclear":false,"sum_hidden":false,"sum_comment_hidden":false,"sum":"","sum_foreign":""},"55":{"sum_foreign_comment":"","sum":"","sum_comment":"","sum_foreign":""},"56":{"sum_foreign_comment":"","sum":"","sum_comment":"","sum_foreign":""},"57":{"sum_foreign_comment":"","sum":"","sum_comment":"","sum_foreign":""},"58":{"sum_foreign_comment":"","sum":"","sum_comment":"","sum_unclear":false,"sum_foreign":""},"59":{"sum_foreign_comment":"","sum":"","sum_comment":"","sum_foreign":""},"60":{"sum_foreign_comment":"","sum":"","sum_comment":"","sum_comment_unclear":false,"sum_comment_hidden":false,"sum_foreign":""},"61":{"sum_foreign_comment":"","sum":"","sum_comment":"","sum_foreign":""},"62":{"sum_foreign_comment":"","sum":"","sum_hidden":false,"sum_comment":"","sum_foreign":""},"63":{"sum_foreign_comment":"","sum_foreign_hidden":false,"sum_comment":"","sum":"","sum_unclear":false,"sum_foreign":""},"64":{"sum_foreign_comment":"","sum_foreign_hidden":false,"sum_comment":"","sum_hidden":false,"sum":"","sum_foreign":""}},"ft_src":"суддя печерського районного суду міста києва\nм. Київ\nЗагальний місцевий суд\nАнна\nНездимовський В. В\nПодружжя\nНездимовська А. В\nДитина\nОлексіївна\nНездимовська Анна Олексіївна\nАнна Олексіївна Нездимовська\nАнна Нездимовська\nНездимовська Анна Олексіївна\nНездимовська\nНездимовська Анна Олексіївна\n70708\n138717\n879486\n879486\n68009\n50000\n2014\n2014\nПодружжя\nНездимовський В. В\nДитина\nНездимовська А. В\nНездимовська Анна Олексіївна\nАнна Олексіївна Нездимовська\nАнна Нездимовська\nНездимовська Анна Олексіївна\nНездимовська Анна Олексіївна\nАнна\nОлексіївна\nЗагальний місцевий суд\nсуддя печерського районного суду міста києва\nм. Київ\nНездимовська\n68009\n70708\n879486\n138717\n879486\n50000\n68009\n879486\n138717\n879486\n70708\nПодружжя\nНездимовський В. В\nДитина\nНездимовська А. В\nОлексіївна\nНездимовська\nАнна\nНездимовська Анна Олексіївна\nАнна Олексіївна Нездимовська\nАнна Нездимовська\nНездимовська Анна Олексіївна\nм. Київ\nсуддя печерського районного суду міста києва\nЗагальний місцевий суд\nНездимовська Анна Олексіївна\n50000\n2014","general":{"inn":"","name":"Анна","family":[{"inn":"","relations":"Подружжя","relations_other":"","inn_hidden":true,"family_name":"Нездимовський В. В","name_hidden":true,"name_unclear":false},{"inn":"","relations":"Дитина","relations_other":"","inn_hidden":true,"family_name":"Нездимовська А. В","name_hidden":false,"name_unclear":false}],"patronymic":"Олексіївна","inn_hidden":true,"family_raw":"","last_name":"Нездимовська","post":{"post_unclear":false,"post":"суддя печерського районного суду міста києва","post_hidden":false,"region":"м. Київ","region_hidden":false,"office":"Загальний місцевий суд","office_hidden":false},"last_name_unclear":false,"full_name":"Нездимовська Анна Олексіївна","addresses":[{"place_district":"","place_city_hidden":true,"place_city":"","place_city_type_hidden":true,"place_district_hidden":true,"place_city_type":"","place_address_hidden":true,"place_address":"","place_hidden":true,"place":""}],"full_name_suggest":{"output":"Нездимовська Анна Олексіївна","input":["Нездимовська Анна Олексіївна","Анна Олексіївна Нездимовська","Анна Нездимовська"]},"name_unclear":false},"source":"VULYK","intro":{"declaration_year":"2014"}}