{"income":{"5":{"value":"196107","family_comment":"","value_unclear":false,"comment_hidden":false,"family_hidden":false,"value_hidden":false,"family_unclear":false,"family":"106350","comment":""},"6":{"value":"196107","family_comment":"","value_unclear":false,"family_hidden":false,"family_unclear":false,"comment_unclear":false,"comment":"","family":"106350"},"7":{"source_name_unclear":false,"value":"","value_hidden":false,"family_comment":"","source_name":"","family":"","comment":"","source_name_hidden":false},"8":{"value":"","family_hidden":false,"value_hidden":false,"family_comment":"","family":"","comment":""},"9":{"value":"","family_comment":"","value_unclear":false,"family_hidden":false,"value_hidden":false,"family_unclear":false,"family":"","comment":""},"10":{"family_comment":"","value":"","family":"","comment":""},"11":{"family_comment":"","value":"","family":"","comment":""},"12":{"family_comment":"","value":"","family":"","comment":""},"13":{"family_comment":"","value":"","family":"","comment":""},"14":{"family_comment":"","value":"","family":"","comment":""},"15":{"family_comment":"","value":"","family":"","comment":""},"16":{"value":"","family_comment":"","value_unclear":false,"family_unclear":false,"family":"","comment":""},"17":{"family_comment":"","value":"","family":"","comment":""},"18":{"family_comment":"","value":"","family":"","comment":""},"19":{"family_comment":"","value":"","comment_unclear":false,"family":"","comment":""},"20":{"value":"","family_comment":"","value_unclear":false,"comment_hidden":false,"family_hidden":false,"family":"","value_hidden":false,"family_unclear":false,"comment_unclear":false,"comment":"","family_comment_unclear":false}},"id":"vulyk_63_189","declaration":{"additional_info_text":"","notfull_lostpages":"","date":"2015-03-26T00:00:00","notfull":"","additional_info":"","url":"http://static.declarations.com.ua/declarations/chosen_ones/mega_batch/klochko_volodymyr_mykolaiovych.pdf"},"liabilities":{"54":{"sum_foreign_comment":"","sum":"","sum_comment":"","sum_unclear":false,"sum_foreign":""},"55":{"sum_foreign_comment":"","sum":"","sum_comment":"","sum_foreign":""},"56":{"sum_foreign_comment":"","sum":"","sum_comment":"","sum_unclear":false,"sum_foreign":""},"57":{"sum_foreign_comment":"","sum":"","sum_comment":"","sum_comment_hidden":false,"sum_unclear":false,"sum_foreign":""},"58":{"sum_foreign_comment":"","sum_comment_hidden":false,"sum":"","sum_comment":"","sum_foreign":""},"59":{"sum_foreign_comment":"","sum":"","sum_comment":"","sum_foreign":""},"60":{"sum_foreign_comment":"","sum":"","sum_comment":"","sum_comment_unclear":false,"sum_foreign":""},"61":{"sum_foreign_comment":"","sum":"","sum_comment":"","sum_unclear":false,"sum_foreign":""},"62":{"sum_foreign_comment":"","sum":"","sum_comment":"","sum_unclear":false,"sum_foreign":""},"63":{"sum_foreign_comment":"","sum":"","sum_comment":"","sum_hidden":false,"sum_comment_hidden":false,"sum_unclear":false,"sum_foreign":""},"64":{"sum_foreign_comment":"","sum_comment_hidden":false,"sum":"","sum_comment":"","sum_foreign":""}},"ft_src":"09100\nКиївська область\nсуддя сквирського районного суду київської області\nКиївська область\nЗагальний місцевий суд\nВолодимир\nКлочко Ю. А., 18. 02. 1986 р. н\nПодружжя\nКлочко З. В., 18. 09. 2014 р. н\nДитина\nМиколайович\nКлочко\nКлочко Володимир Миколайович\nКлочко Володимир Миколайович\nВолодимир Миколайович Клочко\nВолодимир Клочко\nКлочко Володимир Миколайович\n196107\n106350\n196107\n106350\n59.6\nКиївська область\n2014\n106350\n196107\n106350\n196107\n59.6\nКиївська область\nМиколайович\nКлочко Володимир Миколайович\nВолодимир Миколайович Клочко\nВолодимир Клочко\nКлочко Володимир Миколайович\nВолодимир\nПодружжя\nКлочко Ю. А., 18. 02. 1986 р. н\nДитина\nКлочко З. В., 18. 09. 2014 р. н\nКлочко Володимир Миколайович\nЗагальний місцевий суд\nКиївська область\nсуддя сквирського районного суду київської області\nКлочко\n09100\nКиївська область\n196107\n106350\n196107\n106350\n2014\nПодружжя\nКлочко Ю. А., 18. 02. 1986 р. н\nДитина\nКлочко З. В., 18. 09. 2014 р. н\nМиколайович\nКлочко\nКлочко Володимир Миколайович\nВолодимир Миколайович Клочко\nВолодимир Клочко\nКлочко Володимир Миколайович\nВолодимир\nКиївська область\n09100\nКиївська область\nсуддя сквирського районного суду київської області\nЗагальний місцевий суд\nКлочко Володимир Миколайович\n59.6\nКиївська область\n2014","general":{"name_hidden":false,"name":"Володимир","patronymic_unclear":false,"last_name_hidden":false,"inn":"","family":[{"inn":"","inn_hidden":true,"relations_unclear":false,"relations_hidden":false,"relations_other":"","relations":"Подружжя","name_hidden":false,"inn_unclear":false,"family_name":"Клочко Ю. А., 18. 02. 1986 р. н","name_unclear":false},{"inn":"","relations":"Дитина","relations_unclear":false,"family_name":"Клочко З. В., 18. 09. 2014 р. н","inn_hidden":true,"relations_other":"","name_hidden":false,"inn_unclear":false,"name_unclear":false}],"patronymic":"Миколайович","inn_hidden":true,"family_raw":"","inn_unclear":false,"post":{"post_unclear":false,"region_unclear":false,"region":"Київська область","office_hidden":false,"region_hidden":false,"post":"суддя сквирського районного суду київської області","office_unclear":false,"office":"Загальний місцевий суд"},"last_name_unclear":false,"full_name":"Клочко Володимир Миколайович","addresses":[{"place_city_type_unclear":false,"place_address":"09100","place_district_hidden":true,"place_city_type":"","place_address_hidden":true,"place_address_unclear":false,"place_city_type_hidden":true,"place":"Київська область","place_district":"","place_unclear":false,"place_city":"","place_city_unclear":false,"place_hidden":false,"place_city_hidden":true,"place_district_unclear":false}],"last_name":"Клочко","full_name_suggest":{"output":"Клочко Володимир Миколайович","input":["Клочко Володимир Миколайович","Володимир Миколайович Клочко","Володимир Клочко"]},"name_unclear":false},"source":"VULYK","estate":{"25":[{"region_unclear":false,"space_unclear":false,"costs":"","costs_comment":"","costs_hidden":false,"address_hidden":true,"region_hidden":false,"space_comment":"","space_hidden":false,"space":"59.6","space_units_hidden":false,"region":"Київська область","address_unclear":false,"costs_rent_comment":"","costs_rent_hidden":false,"space_comment_unclear":false,"costs_rent_comment_hidden":false,"space_units":"м²","address":"","costs_comment_hidden":false,"costs_rent":""}]},"intro":{"declaration_year":"2014","isnotdeclaration":"","declaration_year_unclear":false}}