{"income":{"5":{"value":"269917","family_comment":"","value_unclear":false,"family_hidden":false,"value_hidden":false,"family_unclear":false,"family":"25000","comment":"","family_comment_unclear":false},"6":{"value":"239339","family_comment":"","value_unclear":false,"family_hidden":false,"value_hidden":false,"family_unclear":false,"family":"25000","comment":""},"7":{"value":"","family_comment":"","family_unclear":false,"source_name":"","family":"","comment":""},"8":{"family_comment":"","value":"","family":"","comment":""},"9":{"family_comment":"","value":"","family":"","comment":""},"10":{"value":"","value_unclear":false,"family_hidden":false,"family_comment":"","family":"","comment":""},"11":{"value":"","value_unclear":false,"family_hidden":false,"family_comment":"","family":"","comment":""},"12":{"family_comment":"","value":"","family":"","comment":""},"13":{"family_comment":"","value":"","family":"","comment":""},"14":{"family_comment":"","value":"","family":"","comment":""},"15":{"family_comment":"","value":"","family":"","comment":""},"16":{"value":"","value_unclear":false,"family_hidden":false,"value_hidden":false,"family_comment":"","family":"","comment":""},"17":{"family_comment":"","value":"","family_hidden":false,"comment":"","family":""},"18":{"family_comment":"","value":"","family":"","comment":""},"19":{"family_comment":"","value":"","family":"","comment":""},"20":{"value":"30578","family_comment":"","comment_hidden":false,"value_hidden":false,"family_unclear":false,"family":"","comment":""}},"vehicle":{"35":[{"brand_info":"1000 куб. см.","sum_rent_comment":"","sum_rent_hidden":false,"year":"1986","sum_hidden":false,"brand_info_hidden":false,"brand_info_unclear":false,"year_unclear":false,"sum_rent":"","sum":"","brand":"Fiat Uno","sum_comment":"","sum_comment_unclear":false,"brand_hidden":false,"sum_unclear":false,"brand_unclear":false},{"brand_info":"1600 куб. см.","sum_rent_comment":"","brand":"Nissan Almera","sum_comment":"","sum_rent_hidden":false,"year":"2008","sum_hidden":false,"sum":"","sum_rent":"","brand_unclear":false},{"brand_info":"1600 куб. см.","sum_rent_comment":"","brand":"ВАЗ 2121 Нива","sum_comment":"","year":"1991","sum":"","sum_rent":""}]},"id":"vulyk_23_195","banks":{"45":[{"sum_foreign_comment":"","sum_units":"UAH","sum_comment":"","sum_foreign_units":"UAH","sum":"","sum_foreign":""}],"46":[{"sum_foreign_comment":"","sum_units":"UAH","sum_comment":"","sum_foreign_units":"UAH","sum":"","sum_foreign":""}],"47":[{"sum_foreign_comment":"","sum_units":"UAH","sum_comment":"","sum_comment_unclear":false,"sum_hidden":false,"sum_foreign_units":"UAH","sum_comment_hidden":false,"sum":"","sum_foreign":""}],"48":[{"sum_foreign_comment":"","sum_units":"UAH","sum_comment":"","sum_foreign_units":"UAH","sum":"","sum_foreign":""}],"49":[{"sum_foreign_comment":"","sum_units":"UAH","sum_comment":"","sum_foreign_units":"UAH","sum":"","sum_foreign":""}],"50":[{"sum_foreign_comment":"","sum_units":"UAH","sum_comment":"","sum_foreign_units":"UAH","sum":"","sum_foreign":""}],"51":[{"sum_foreign_comment":"","sum_units":"UAH","sum_comment":"","sum_comment_unclear":false,"sum_hidden":false,"sum_foreign_units":"UAH","sum_comment_hidden":false,"sum_unclear":false,"sum":"","sum_foreign":""}],"52":[{"sum_foreign_comment":"","sum_units":"UAH","sum_comment":"","sum_comment_unclear":false,"sum_hidden":false,"sum_foreign_units":"UAH","sum_comment_hidden":false,"sum":"","sum_foreign":""}],"53":[{"sum_foreign_comment":"","sum_units":"UAH","sum_comment":"","sum_hidden":false,"sum_foreign_units":"UAH","sum_comment_hidden":false,"sum_unclear":false,"sum":"","sum_foreign":""}]},"declaration":{"additional_info_text":"","notfull_lostpages":"","date":"2015-03-24T00:00:00","notfull":"","additional_info":"","url":"http://static.declarations.com.ua/declarations/chosen_ones/mega_batch/ternovenko_alona_volodymyrivna.pdf"},"liabilities":{"54":{"sum_foreign_comment":"","sum":"","sum_comment":"","sum_comment_unclear":false,"sum_foreign":""},"55":{"sum_foreign_comment":"","sum":"","sum_comment":"","sum_foreign":""},"56":{"sum_foreign_comment":"","sum":"68200","sum_comment":"","sum_foreign_hidden":false,"sum_foreign":""},"57":{"sum_foreign_comment":"","sum":"17000","sum_hidden":false,"sum_comment":"","sum_foreign":""},"58":{"sum_foreign_comment":"","sum":"1890","sum_comment":"","sum_hidden":false,"sum_unclear":false,"sum_foreign":""},"59":{"sum_foreign_comment":"","sum":"","sum_comment":"","sum_foreign":""},"60":{"sum_foreign_comment":"","sum":"","sum_comment":"","sum_comment_unclear":false,"sum_hidden":false,"sum_foreign":""},"61":{"sum_foreign_comment":"","sum":"","sum_hidden":false,"sum_comment":"","sum_foreign":""},"62":{"sum_foreign_comment":"","sum":"","sum_comment":"","sum_foreign":""},"63":{"sum_foreign_comment":"","sum":"","sum_comment":"","sum_comment_unclear":false,"sum_foreign":""},"64":{"sum_foreign_comment":"","sum":"","sum_comment":"","sum_comment_unclear":false,"sum_foreign":""}},"ft_src":"17000\n1890\n68200\nголова ульянівського районного суду кіровоградської області\nКіровоградська область\nЗагальний місцевий суд\nАльона\nТерновенко Р. М. 11. 12. 1984\nПодружжя\nЗапорощук О. О., 11. 02. 99\nДитина\nТерновенко А. Р, 08. 02. 2013\nДитина\nТерновенко М. Р. 08. 02. 2013\nДитина\nВолодимирівна\nТерновенко Альона Володимирівна\nАльона Володимирівна Терновенко\nАльона Терновенко\nТерновенко Альона Володимирівна\nТерновенко Альона Володимирівна\nТерновенко\n1000 куб. см.\nFiat Uno\n1986\n1600 куб. см.\nNissan Almera\n2008\n1600 куб. см.\n1991\nВАЗ 2121 Нива\n2014\n1000 куб. см.\nFiat Uno\n1986\n1600 куб. см.\n2008\nNissan Almera\n1600 куб. см.\nВАЗ 2121 Нива\n1991\n33\n7\n67\n7\nТерновенко Альона Володимирівна\nАльона Володимирівна Терновенко\nАльона Терновенко\nТерновенко Альона Володимирівна\nТерновенко Альона Володимирівна\nПодружжя\nТерновенко Р. М. 11. 12. 1984\nДитина\nЗапорощук О. О., 11. 02. 99\nДитина\nТерновенко А. Р, 08. 02. 2013\nДитина\nТерновенко М. Р. 08. 02. 2013\nАльона\nВолодимирівна\nЗагальний місцевий суд\nКіровоградська область\nголова ульянівського районного суду кіровоградської області\nТерновенко\n17000\n68200\n1890\n25000\n239339\n30578\n269917\n25000\n2014\n1890\n17000\n68200\n33\n7\n67\n7\nТерновенко Р. М. 11. 12. 1984\nПодружжя\nЗапорощук О. О., 11. 02. 99\nДитина\nТерновенко А. Р, 08. 02. 2013\nДитина\nТерновенко М. Р. 08. 02. 2013\nДитина\nВолодимирівна\nТерновенко\nАльона\nТерновенко Альона Володимирівна\nАльона Володимирівна Терновенко\nАльона Терновенко\nТерновенко Альона Володимирівна\nКіровоградська область\nЗагальний місцевий суд\nголова ульянівського районного суду кіровоградської області\nТерновенко Альона Володимирівна\n25000\n239339\n25000\n269917\n30578\n1986\nFiat Uno\n1000 куб. см.\n2008\nNissan Almera\n1600 куб. см.\nВАЗ 2121 Нива\n1600 куб. см.\n1991\n30578\n269917\n25000\n239339\n25000\n7\n67\n7\n33\n2014","general":{"inn":"","name":"Альона","last_name_hidden":false,"family":[{"inn":"","inn_hidden":true,"relations_hidden":false,"family_name":"Терновенко Р. М. 11. 12. 1984","relations_other":"","relations":"Подружжя","name_hidden":false,"name_unclear":false},{"inn":"","inn_hidden":false,"relations_hidden":false,"family_name":"Запорощук О. О., 11. 02. 99","relations_other":"","relations":"Дитина","name_hidden":false,"name_unclear":true},{"inn":"","inn_hidden":false,"relations_hidden":false,"family_name":"Терновенко А. Р, 08. 02. 2013","relations_other":"","relations":"Дитина","name_hidden":false,"name_unclear":false},{"inn_hidden":false,"inn":"","name_hidden":false,"family_name":"Терновенко М. Р. 08. 02. 2013","relations":"Дитина","name_unclear":false}],"patronymic":"Володимирівна","inn_hidden":false,"family_raw":"","inn_unclear":false,"post":{"post_unclear":false,"region_unclear":false,"post":"голова ульянівського районного суду кіровоградської області","office":"Загальний місцевий суд","region":"Кіровоградська область","post_hidden":false,"office_hidden":false,"office_unclear":false,"region_hidden":false},"full_name_suggest":{"output":"Терновенко Альона Володимирівна","input":["Терновенко Альона Володимирівна","Альона Володимирівна Терновенко","Альона Терновенко"]},"full_name":"Терновенко Альона Володимирівна","last_name":"Терновенко","patronymic_hidden":false,"last_name_unclear":true,"name_unclear":false},"source":"VULYK","estate":{"23":[{"region_unclear":false,"space_unclear":false,"costs":"","costs_comment":"","address_hidden":false,"region_hidden":false,"space_comment":"","space":"","address":"","region":"","address_unclear":false,"space_units_unclear":false,"space_units":"м²","costs_rent":"","costs_rent_comment":""},{"costs_rent":"","region":"","costs":"","costs_rent_comment":"","costs_comment":"","region_hidden":false,"space_comment":"","space_units":"","space":"","address":""},{"costs_rent":"","costs":"","costs_rent_comment":"","costs_comment":"","space_comment":"","space_units":"","space":"","address":""}],"25":[{"space_unclear":false,"costs":"","costs_rent_unclear":false,"costs_comment":"","costs_hidden":false,"address_hidden":true,"region_hidden":true,"space_comment":"","space_hidden":false,"space":"67","address":"","costs_unclear":false,"region":"","costs_rent_comment":"","costs_rent_hidden":false,"space_comment_unclear":false,"space_comment_hidden":false,"space_units":"м²","costs_rent":""},{"space_unclear":true,"costs":"","costs_rent_unclear":false,"costs_comment":"","address_hidden":false,"region_hidden":false,"space_comment":"","space":"7","address":"","region":"","costs_rent_comment":"","space_comment_unclear":false,"space_units":"м²","costs_rent":""}],"27":[{"space_hidden":false,"costs":"","costs_comment":"","address_hidden":true,"region_hidden":true,"space_comment":"","space":"33","address":"","region":"","costs_rent_comment":"","space_units":"м²","costs_rent":""}],"31":[{"space_unclear":true,"address_hidden":false,"region_hidden":false,"space_comment":"","space_hidden":false,"space":"7","address":"","region":"","costs_property":"","costs_rent_comment":"","space_units":"м²","costs_property_comment":"","costs_rent":""}]},"intro":{"declaration_year":"2014","declaration_year_unclear":false}}