{"income":{"5":{"value":"241761","family_comment":"","value_unclear":false,"family_hidden":false,"value_hidden":false,"family_unclear":false,"comment_unclear":false,"comment":"","family":"44820"},"6":{"value":"229144","family_unclear":false,"family_hidden":false,"family_comment":"","family":"28132","comment":""},"7":{"value":"","family_hidden":false,"value_hidden":false,"family_comment":"","source_name":"","family":"","comment":""},"8":{"family_comment":"","value":"","family":"","comment":""},"9":{"family_comment":"","value":"","value_unclear":false,"family":"","comment":""},"10":{"family_comment":"","family_unclear":false,"value":"12617","family":"1352","comment":""},"11":{"family_comment":"","value":"","family":"","comment":""},"12":{"family_comment":"","value":"","family":"","comment":""},"13":{"family_comment":"","value":"","family":"","comment":""},"14":{"family_comment":"","value":"","family":"","comment":""},"15":{"family_comment":"","value":"","family":"15336","comment":""},"16":{"family_comment":"","value":"","family":"","comment":""},"17":{"family_comment":"","value":"","family":"","comment":""},"18":{"family_comment":"","value":"","family":"","comment":""},"19":{"family_comment":"","value":"","family":"","comment":""},"20":{"value":"","value_unclear":false,"family_comment":"","comment_unclear":false,"comment":"","family":""}},"id":"vulyk_71_12","declaration":{"additional_info_text":"","notfull_lostpages":"","date":"2014-03-04T00:00:00","notfull":"","additional_info":"","url":"http://static.declarations.com.ua/declarations/chosen_ones/judges_batch/623_klentsar_volodymyr_borysovych.pdf"},"liabilities":{"54":{"sum_foreign_comment":"","sum":"","sum_comment":"","sum_comment_unclear":false,"sum_comment_hidden":false,"sum_unclear":false,"sum_foreign":""},"55":{"sum_foreign_comment":"","sum":"","sum_comment":"","sum_foreign":""},"56":{"sum_foreign_comment":"","sum":"","sum_comment":"","sum_comment_unclear":false,"sum_unclear":false,"sum_foreign":""},"57":{"sum_foreign_comment":"","sum":"","sum_comment":"","sum_comment_hidden":false,"sum_unclear":false,"sum_foreign":""},"58":{"sum_foreign_comment":"","sum":"","sum_comment":"","sum_comment_hidden":false,"sum_unclear":false,"sum_foreign":""},"59":{"sum_foreign_comment":"","sum_comment_hidden":false,"sum":"","sum_comment":"","sum_foreign":""},"60":{"sum_foreign_comment":"","sum_comment_hidden":false,"sum":"","sum_comment":"","sum_foreign":""},"61":{"sum_foreign_comment":"","sum":"","sum_comment":"","sum_foreign":""},"62":{"sum_foreign_comment":"","sum":"","sum_comment":"","sum_foreign":""},"63":{"sum_foreign_comment":"","sum":"","sum_comment":"","sum_unclear":false,"sum_foreign":""},"64":{"sum_foreign_comment":"","sum":"","sum_comment":"","sum_unclear":false,"sum_foreign":""}},"ft_src":"суддя апеляційного суду донецької області\nДонецька область\nЗагальний апеляційний суд\nВолодимир\nКленцарь О. В\nПодружжя\nБорисович\nКленцарь Володимир Борисович\nВолодимир Борисович Кленцарь\nВолодимир Кленцарь\nКленцарь Володимир Борисович\nКленцарь Володимир Борисович\nКленцарь\n15336\n1352\n12617\n241761\n44820\n229144\n28132\n.15\n58\n2013\n28132\n229144\n15336\n1352\n12617\n44820\n241761\n229144\n28132\n15336\n241761\n44820\n12617\n1352\nПодружжя\nКленцарь О. В\nКленцарь Володимир Борисович\nВолодимир Борисович Кленцарь\nВолодимир Кленцарь\nКленцарь Володимир Борисович\nКленцарь Володимир Борисович\nВолодимир\nБорисович\nЗагальний апеляційний суд\nДонецька область\nсуддя апеляційного суду донецької області\nКленцарь\n.15\n58\n2013\nКленцарь О. В\nПодружжя\nБорисович\nКленцарь\nВолодимир\nКленцарь Володимир Борисович\nВолодимир Борисович Кленцарь\nВолодимир Кленцарь\nКленцарь Володимир Борисович\nДонецька область\nЗагальний апеляційний суд\nсуддя апеляційного суду донецької області\nКленцарь Володимир Борисович\n58\n.15\n2013","general":{"inn":"","name":"Володимир","family":[{"inn":"","inn_hidden":true,"relations_hidden":false,"family_name":"Кленцарь О. В","relations_other":"","relations":"Подружжя","name_hidden":false,"name_unclear":false}],"patronymic":"Борисович","inn_hidden":true,"family_raw":"","inn_unclear":false,"post":{"post_unclear":false,"region_unclear":false,"post":"суддя апеляційного суду донецької області","office":"Загальний апеляційний суд","region":"Донецька область","post_hidden":false,"office_unclear":false},"full_name_suggest":{"output":"Кленцарь Володимир Борисович","input":["Кленцарь Володимир Борисович","Володимир Борисович Кленцарь","Володимир Кленцарь"]},"full_name":"Кленцарь Володимир Борисович","addresses":[{"place_district":"","place_unclear":false,"place_city":"","place_city_type_hidden":true,"place_district_hidden":true,"place_city_type":"","place_city_hidden":true,"place_address_hidden":true,"place_address":"","place_hidden":true,"place":""}],"last_name":"Кленцарь","patronymic_hidden":false,"last_name_unclear":false,"name_unclear":false},"source":"VULYK","estate":{"23":[{"space_hidden":false,"costs":"","costs_comment":"","costs_hidden":false,"address_hidden":true,"region_hidden":true,"space_comment":"","space_unclear":false,"space":".15","address":"","costs_comment_unclear":false,"region":"","costs_rent_comment":"","costs_rent_hidden":false,"space_comment_unclear":false,"space_units":"га","costs_rent":""}],"24":[{"region_unclear":false,"space_unclear":false,"costs":"","costs_comment":"","address_hidden":false,"region_hidden":true,"space_comment":"","space":"","address":"","costs_comment_unclear":false,"region":"","costs_rent_comment":"","space_comment_unclear":false,"space_units":"м²","costs_rent":""}],"25":[{"region_unclear":false,"space_unclear":false,"costs":"","costs_rent_unclear":false,"costs_comment":"","costs_hidden":false,"address_hidden":true,"region_hidden":true,"space_comment":"","space_hidden":false,"space":"58","address":"","costs_unclear":false,"region":"","address_unclear":false,"costs_rent_comment":"","costs_rent_hidden":false,"space_comment_unclear":false,"space_units":"м²","costs_rent":""}]},"intro":{"declaration_year":"2013","isnotdeclaration":""}}