{"income":{"5":{"family_comment":"","value":"373673","value_unclear":false,"family":"","comment":""},"6":{"value":"236941","value_unclear":false,"family_hidden":false,"family_comment":"","family":"","comment":""},"7":{"source_name_unclear":false,"value":"","family_comment":"","source_name":"","family":"","comment":""},"8":{"family_comment":"","value":"","family":"","comment":""},"9":{"family_comment":"","value":"1732","family":"","comment":""},"10":{"family_comment":"","value":"","family":"","comment":""},"11":{"family_comment":"","value":"","comment_unclear":false,"family":"","comment":""},"12":{"family_comment":"","value":"","family":"","comment":""},"13":{"family_comment":"","value":"","family":"","comment":""},"14":{"family_comment":"","value":"","family":"","comment":""},"15":{"family_comment":"","value":"","family":"","comment":""},"16":{"family_comment":"","value":"","family":"","comment":""},"17":{"family_comment":"","value":"","family":"","comment":""},"18":{"family_comment":"","value":"","family":"","comment":""},"19":{"family_comment":"","value":"","family":"","comment":""},"20":{"value":"135000","family_comment":"","value_unclear":false,"family_unclear":false,"comment_unclear":false,"comment":"","family":""}},"vehicle":{"35":[{"brand_info":"2998","sum_rent_comment":"","brand":"Mitsubishi Outlander","sum_comment":"","brand_unclear":false,"year":"2007","sum_rent_unclear":false,"brand_info_hidden":false,"brand_info_unclear":false,"sum":"","sum_rent":""}]},"id":"vulyk_101_65","declaration":{"additional_info_text":"","notfull_lostpages":"","date":"2015-03-23T00:00:00","notfull":"","additional_info":"","url":"http://static.declarations.com.ua/declarations/chosen_ones/judges_batch/730_sydorenko_iryna_petrivna_2015.pdf"},"liabilities":{"54":{"sum_foreign_comment":"","sum":"","sum_comment":"","sum_comment_unclear":false,"sum_hidden":false,"sum_comment_hidden":false,"sum_unclear":false,"sum_foreign":""},"55":{"sum_foreign_comment":"","sum":"","sum_comment":"","sum_foreign":""},"56":{"sum_foreign_comment":"","sum":"","sum_comment":"","sum_comment_hidden":false,"sum_unclear":false,"sum_foreign":""},"57":{"sum_foreign_comment":"","sum":"","sum_comment":"","sum_hidden":false,"sum_comment_hidden":false,"sum_unclear":false,"sum_foreign":""},"58":{"sum_foreign_comment":"","sum":"","sum_comment":"","sum_comment_unclear":false,"sum_hidden":false,"sum_comment_hidden":false,"sum_unclear":false,"sum_foreign":""},"59":{"sum_foreign_comment":"","sum":"","sum_comment":"","sum_foreign":""},"60":{"sum_foreign_comment":"","sum":"","sum_comment":"","sum_hidden":false,"sum_comment_hidden":false,"sum_unclear":false,"sum_foreign":""},"61":{"sum_foreign_comment":"","sum":"","sum_comment":"","sum_foreign":""},"62":{"sum_foreign_comment":"","sum":"","sum_comment":"","sum_comment_unclear":false,"sum_foreign":""},"63":{"sum_foreign_comment":"","sum_comment_hidden":false,"sum":"","sum_comment":"","sum_foreign":""},"64":{"sum_foreign_comment":"","sum_comment_hidden":false,"sum":"","sum_comment":"","sum_foreign":""}},"ft_src":"суддя апеляційного суду одеської області\nОдеська область\nЗагальний апеляційний суд\nІрина\nПетрівна\nСидоренко Ірина Петрівна\nСидоренко\nСидоренко Ірина Петрівна\nІрина Петрівна Сидоренко\nІрина Сидоренко\nСидоренко Ірина Петрівна\nMitsubishi Outlander\n2998\n2007\n.0934\n30\n120\n236941\n1732\n373673\n135000\nMitsubishi Outlander\n2998\n2007\nСидоренко Ірина Петрівна\nІрина Петрівна Сидоренко\nІрина Сидоренко\nСидоренко Ірина Петрівна\nІрина\nСидоренко Ірина Петрівна\nСидоренко\nЗагальний апеляційний суд\nсуддя апеляційного суду одеської області\nОдеська область\nПетрівна\n236941\n135000\n373673\n1732\n.0934\n30\n120\nПетрівна\nСидоренко\nІрина\nСидоренко Ірина Петрівна\nІрина Петрівна Сидоренко\nІрина Сидоренко\nСидоренко Ірина Петрівна\nсуддя апеляційного суду одеської області\nЗагальний апеляційний суд\nОдеська область\nСидоренко Ірина Петрівна\n2007\nMitsubishi Outlander\n2998\n1732\n135000\n373673\n236941\n.0934\n120\n30","general":{"inn":"","name":"Ірина","inn_unclear":false,"patronymic":"Петрівна","inn_hidden":true,"family_raw":"","last_name":"Сидоренко","post":{"region":"Одеська область","region_unclear":false,"post":"суддя апеляційного суду одеської області","office_unclear":false,"office":"Загальний апеляційний суд"},"full_name":"Сидоренко Ірина Петрівна","addresses":[{"place_district":"","place_city_hidden":true,"place_city":"","place_city_type_hidden":false,"place_district_hidden":false,"place_city_type":"","place_address_hidden":true,"place_address":"","place_hidden":true,"place":""}],"patronymic_hidden":false,"full_name_suggest":{"output":"Сидоренко Ірина Петрівна","input":["Сидоренко Ірина Петрівна","Ірина Петрівна Сидоренко","Ірина Сидоренко"]}},"source":"VULYK","estate":{"23":[{"space_unclear":false,"costs":"","costs_comment":"","address_hidden":false,"region_hidden":true,"space_comment":"","space_hidden":false,"space":".0934","address":"","costs_comment_unclear":false,"region":"","space_units_unclear":false,"space_units":"га","costs_rent":"","costs_rent_comment":""}],"24":[{"space_unclear":false,"costs":"","costs_comment":"","address_hidden":false,"region_hidden":true,"space_comment":"","space":"120","address":"","region":"","costs_rent_comment":"","space_units":"м²","costs_rent":""}],"27":[{"space_hidden":false,"costs":"","costs_comment":"","address_hidden":false,"region_hidden":true,"space_comment":"","space":"30","address":"","region":"","costs_rent_comment":"","space_units":"м²","costs_rent":""}]},"intro":{"declaration_year":""}}