{"income":{"5":{"value":"85509","family_comment":"","value_unclear":false,"value_hidden":false,"family_unclear":false,"family":"254993","comment":""},"6":{"value":"67089","family_hidden":false,"value_hidden":false,"family_comment":"","family_comment_hidden":false,"comment":"","family":"94946"},"7":{"value":"","value_unclear":false,"family_hidden":false,"value_hidden":false,"family_comment":"","source_name":"","family":"","comment":"","source_name_hidden":false},"8":{"value":"","comment_hidden":false,"family_hidden":false,"value_hidden":false,"family_comment":"","family":"","comment":""},"9":{"value":"","family_comment":"","comment_hidden":false,"family_hidden":false,"value_hidden":false,"family_unclear":false,"family":"","comment":""},"10":{"value":"","comment_hidden":false,"family_hidden":false,"value_hidden":false,"family_comment":"","family":"5834","comment":""},"11":{"value":"","value_unclear":false,"comment_hidden":false,"family_hidden":false,"value_hidden":false,"family_comment":"","family":"150000","comment":""},"12":{"value":"","comment_hidden":false,"family_hidden":false,"value_hidden":false,"family_comment":"","family":"","comment":""},"13":{"value":"","comment_hidden":false,"family_hidden":false,"value_hidden":false,"family_comment":"","family":"","comment":""},"14":{"value":"","comment_hidden":false,"family_hidden":false,"value_hidden":false,"family_comment":"","family":"","comment":""},"15":{"value":"","comment_hidden":false,"family_hidden":false,"value_hidden":false,"family_comment":"","family":"4213","comment":""},"16":{"value":"","comment_hidden":false,"family_hidden":false,"value_hidden":false,"family_comment":"","family":"","comment":""},"17":{"value":"","comment_hidden":false,"family_hidden":false,"value_hidden":false,"family_comment":"","family":"","comment":""},"18":{"value":"","value_unclear":false,"comment_hidden":false,"family_hidden":false,"value_hidden":false,"family_comment":"","family":"","comment":""},"19":{"value":"","comment_hidden":false,"family_hidden":false,"value_hidden":false,"family_comment":"","family":"","comment":""},"20":{"value":"18420","value_unclear":false,"family_comment":"","comment_unclear":false,"comment":"","family":""}},"vehicle":{"35":[{"brand_info":"3956 куб. см.","sum_rent_comment":"","sum_rent_hidden":false,"year":"2010","sum_rent_unclear":false,"brand_info_hidden":false,"brand_info_unclear":false,"year_unclear":false,"sum_hidden":false,"sum_rent":"","sum":"","brand":"Toyota Land Cruiser 150","sum_comment":"","brand_unclear":false,"sum_rent_comment_hidden":false,"sum_comment_hidden":false,"sum_unclear":false}],"40":[{"year_hidden":false,"brand_info":"1798 куб. см.","sum_rent_comment":"","brand":"Toyota Avensis","sum_comment":"","brand_unclear":false,"year":"2010","brand_hidden":false,"brand_info_unclear":false,"sum":"","sum_rent":""}]},"id":"vulyk_1_208","declaration":{"additional_info_text":"","notfull_lostpages":"","date":"2014-03-31T00:00:00","notfull":"","additional_info":"","url":"http://static.declarations.com.ua/declarations/chosen_ones/judges_batch/273_stupak_olha_v_iacheslavivna.pdf"},"liabilities":{"54":{"sum_foreign_comment":"","sum_foreign_hidden":false,"sum_comment":"","sum_hidden":false,"sum_comment_hidden":false,"sum":"20000","sum_foreign":""},"55":{"sum_foreign_comment":"","sum":"","sum_hidden":false,"sum_comment":"","sum_foreign":""},"56":{"sum_foreign_comment":"","sum":"","sum_comment":"","sum_foreign":""},"57":{"sum_foreign_comment":"","sum_foreign_hidden":false,"sum_comment":"","sum_hidden":false,"sum_comment_hidden":false,"sum_unclear":false,"sum":"","sum_foreign":""},"58":{"sum_foreign_comment":"","sum_foreign_hidden":false,"sum_comment":"","sum_hidden":false,"sum_comment_hidden":false,"sum_unclear":false,"sum":"","sum_foreign":""},"59":{"sum_foreign_comment":"","sum":"","sum_hidden":false,"sum_comment":"","sum_foreign":""},"60":{"sum_foreign_comment":"","sum_foreign_hidden":false,"sum_comment":"","sum_hidden":false,"sum_comment_hidden":false,"sum_unclear":false,"sum":"10452","sum_foreign":""},"61":{"sum_foreign_comment":"","sum":"","sum_hidden":false,"sum_comment":"","sum_foreign":""},"62":{"sum_foreign_comment":"","sum":"","sum_comment":"","sum_hidden":false,"sum_comment_hidden":false,"sum_foreign":""},"63":{"sum_foreign_comment":"","sum":"","sum_hidden":false,"sum_comment":"","sum_foreign":""},"64":{"sum_foreign_comment":"","sum":"","sum_hidden":false,"sum_comment":"","sum_foreign":""}},"ft_src":"20000\n10452\nсуддя вищого спеціалізованого суду україни з розгляду цивільних і кримінальних справ\nЗагальнодержавний регіон\nВищий спеціалізований суд з розгляду цивільних і кримінальних справ\nОльга\nСтупак Ю. В\nПодружжя\nСтупак Б. Ю\nДитина\nСтупак Д. Ю\nДитина\nСтупак С. Ю\nДитина\nВ'ячеславівна\nСтупак Ольга В'ячеславівна\nОльга В'ячеславівна Ступак\nОльга Ступак\nСтупак Ольга В'ячеславівна\nСтупак Ольга В'ячеславівна\nСтупак\n3956 куб. см.\n2010\nToyota Land Cruiser 150\nToyota Avensis\n1798 куб. см.\n2010\n108\n2013\n94946\n67089\n4213\n150000\n5834\n254993\n85509\n18420\n3956 куб. см.\nToyota Land Cruiser 150\n2010\n1798 куб. см.\nToyota Avensis\n2010\n108\nПодружжя\nСтупак Ю. В\nДитина\nСтупак Б. Ю\nДитина\nСтупак Д. Ю\nСтупак С. Ю\nДитина\nСтупак Ольга В'ячеславівна\nОльга В'ячеславівна Ступак\nОльга Ступак\nСтупак Ольга В'ячеславівна\nСтупак Ольга В'ячеславівна\nОльга\nВ'ячеславівна\nВищий спеціалізований суд з розгляду цивільних і кримінальних справ\nсуддя вищого спеціалізованого суду україни з розгляду цивільних і кримінальних справ\nЗагальнодержавний регіон\nСтупак\n20000\n10452\n67089\n94946\n18420\n4213\n85509\n254993\n5834\n150000\n2013\n20000\n10452\nСтупак Ю. В\nПодружжя\nДитина\nСтупак Б. Ю\nСтупак Д. Ю\nДитина\nДитина\nСтупак С. Ю\nВ'ячеславівна\nСтупак\nОльга\nСтупак Ольга В'ячеславівна\nОльга В'ячеславівна Ступак\nОльга Ступак\nСтупак Ольга В'ячеславівна\nЗагальнодержавний регіон\nсуддя вищого спеціалізованого суду україни з розгляду цивільних і кримінальних справ\nВищий спеціалізований суд з розгляду цивільних і кримінальних справ\nСтупак Ольга В'ячеславівна\n2010\nToyota Land Cruiser 150\n3956 куб. см.\n2010\nToyota Avensis\n1798 куб. см.\n150000\n4213\n5834\n18420\n85509\n254993\n67089\n94946\n108\n2013","general":{"inn":"","name":"Ольга","inn_unclear":false,"family":[{"inn":"","inn_hidden":false,"relations_unclear":false,"relations_hidden":false,"relations_other":"","relations":"Подружжя","name_hidden":false,"family_name":"Ступак Ю. В","name_unclear":false},{"inn":"","inn_hidden":false,"relations_unclear":false,"relations_hidden":false,"relations_other":"","relations":"Дитина","name_hidden":false,"family_name":"Ступак Б. Ю","name_unclear":false},{"inn":"","relations":"Дитина","relations_other":"","inn_hidden":false,"family_name":"Ступак Д. Ю","name_hidden":false,"name_unclear":false},{"inn":"","family_name":"Ступак С. Ю","relations":"Дитина","inn_hidden":false,"relations_other":""}],"inn_hidden":false,"family_raw":"","last_name":"Ступак","post":{"post_unclear":false,"post":"суддя вищого спеціалізованого суду україни з розгляду цивільних і кримінальних справ","candidate":"","office_hidden":false,"region":"Загальнодержавний регіон","office":"Вищий спеціалізований суд з розгляду цивільних і кримінальних справ","office_unclear":false,"region_hidden":false},"full_name_suggest":{"output":"Ступак Ольга В'ячеславівна","input":["Ступак Ольга В'ячеславівна","Ольга В'ячеславівна Ступак","Ольга Ступак"]},"full_name":"Ступак Ольга В'ячеславівна","patronymic":"В'ячеславівна","last_name_unclear":false,"name_unclear":false},"source":"VULYK","estate":{"25":[{"space_unclear":false,"costs":"","costs_comment":"","address_hidden":false,"region_hidden":false,"space_comment":"","space_hidden":false,"space":"108","address":"","region":"","costs_rent_comment":"","space_comment_unclear":false,"space_comment_hidden":false,"space_units":"м²","costs_rent":""}]},"intro":{"declaration_year":"2013","isnotdeclaration":"","declaration_year_unclear":false,"declaration_year_hidden":false}}