{"income":{"5":{"value":"251942","family_comment":"","value_unclear":false,"family_unclear":false,"family":"42658","comment":""},"6":{"family_comment":"","value":"251942","value_unclear":false,"family":"42658","comment":""},"7":{"value":"","value_unclear":false,"family_comment":"","source_name":"","family":"","comment":""},"8":{"family_comment":"","value":"","family":"","comment":""},"9":{"value":"","family_comment":"","value_unclear":false,"family_unclear":false,"family":"","comment":""},"10":{"family_comment":"","value":"","comment_unclear":false,"family":"","comment":""},"11":{"family_comment":"","value":"","family":"","comment":""},"12":{"family_comment":"","value":"","family":"","comment":""},"13":{"family_comment":"","value":"","value_unclear":false,"family":"","comment":""},"14":{"family_comment":"","value":"","family":"","comment":""},"15":{"family_comment":"","value":"","family":"","comment":""},"16":{"family_comment":"","family_unclear":false,"value":"","family":"","comment":""},"17":{"family_comment":"","family_unclear":false,"value":"","family":"","comment":""},"18":{"family_comment":"","value":"","family":"","comment":""},"19":{"family_comment":"","value":"","family":"","comment":""},"20":{"value":"","family_comment":"","value_unclear":false,"family_hidden":false,"value_hidden":false,"family_unclear":false,"comment_unclear":false,"comment":"","family":""}},"vehicle":{"36":[{"brand_info":"","sum_rent_comment":"","brand":"","sum_comment":"","brand_unclear":true,"year":"","brand_info_unclear":false,"sum":"","sum_rent":""}],"40":[{"brand_info":"1600, власність","sum_rent_comment":"","brand":"ВАЗ 21101","sum_comment":"","year":"2007","brand_info_hidden":false,"brand_info_unclear":false,"sum":"","sum_rent":""}],"41":[{"brand_info":"власність","sum_rent_comment":"","brand":"КамАЗ 5511","sum_comment":"","year":"1982","sum":"","sum_rent":""}]},"id":"vulyk_100_19","declaration":{"additional_info_text":"","notfull_lostpages":"","date":"2015-03-31T00:00:00","notfull":"","additional_info":"","url":"http://static.declarations.com.ua/declarations/chosen_ones/judges_batch/4137_lopatynska_svitlana_petrivna.pdf"},"liabilities":{"54":{"sum_foreign_comment":"","sum":"","sum_comment":"","sum_comment_hidden":false,"sum_unclear":false,"sum_foreign":""},"55":{"sum_foreign_comment":"","sum":"","sum_comment":"","sum_foreign":""},"56":{"sum_foreign_comment":"","sum":"22660","sum_comment":"","sum_unclear":true,"sum_foreign":""},"57":{"sum_foreign_comment":"","sum":"","sum_comment":"","sum_comment_unclear":false,"sum_comment_hidden":false,"sum_unclear":false,"sum_foreign":""},"58":{"sum_foreign_comment":"","sum":"","sum_comment":"","sum_comment_hidden":false,"sum_unclear":false,"sum_foreign":""},"59":{"sum_foreign_comment":"","sum":"","sum_comment":"","sum_foreign":""},"60":{"sum_foreign_comment":"","sum_comment_hidden":false,"sum":"","sum_comment":"","sum_foreign":""},"61":{"sum_foreign_comment":"","sum":"","sum_comment":"","sum_foreign":""},"62":{"sum_foreign_comment":"","sum":"","sum_comment":"","sum_unclear":false,"sum_foreign":""},"63":{"sum_foreign_comment":"","sum_comment_hidden":false,"sum":"","sum_comment":"","sum_foreign":""},"64":{"sum_foreign_comment":"","sum_comment_hidden":false,"sum":"","sum_comment":"","sum_foreign":""}},"ft_src":"22660\nЛопатинська Світлана Петрівна\nсуддя броварського міськрайонного суду київської області\nКиївська область\nЗагальний місцевий суд\nСвітлана\nЛопатинський А. М. 09. 07. 1966\nПодружжя\nЛопатинська С. В. 18. 09. 1998\nДитина\nЛопатинська Світлана Петрівна\nСвітлана Петрівна Лопатинська\nСвітлана Лопатинська\nЛопатинська Світлана Петрівна\nЛопатинська\nПетрівна\nвласність\n1982\nКамАЗ 5511\n2007\n1600, власність\nВАЗ 21101\nкористування\n545\n18\nвласність\n2500\nвласність\n48\nвласність\n23\nвласність\n1200\n10\nкористування\n80\nвласність\n3460\n10\nкористування\n8950\n80\n2014\n42658\n251942\n42658\n251942\nВАЗ 21101\n1600, власність\n2007\nвласність\nКамАЗ 5511\n1982\n18\nкористування\n545\n10\nвласність\n3460\n8950\n80\nкористування\nвласність\n23\n1200\nвласність\nвласність\n2500\n10\n80\nкористування\n48\nвласність\nПодружжя\nЛопатинський А. М. 09. 07. 1966\nДитина\nЛопатинська С. В. 18. 09. 1998\nПетрівна\nЛопатинська\nЛопатинська Світлана Петрівна\nСвітлана Петрівна Лопатинська\nСвітлана Лопатинська\nЛопатинська Світлана Петрівна\nЛопатинська Світлана Петрівна\nСвітлана\nЗагальний місцевий суд\nКиївська область\nсуддя броварського міськрайонного суду київської області\n22660\n251942\n42658\n251942\n42658\n2014\n22660\nЛопатинський А. М. 09. 07. 1966\nПодружжя\nДитина\nЛопатинська С. В. 18. 09. 1998\nПетрівна\nЛопатинська\nКиївська область\nЗагальний місцевий суд\nсуддя броварського міськрайонного суду київської області\nЛопатинська Світлана Петрівна\nЛопатинська Світлана Петрівна\nСвітлана Петрівна Лопатинська\nСвітлана Лопатинська\nЛопатинська Світлана Петрівна\nСвітлана\nКамАЗ 5511\nвласність\n1982\n2007\n1600, власність\nВАЗ 21101\n251942\n42658\n42658\n251942\n10\nкористування\n80\nвласність\n1200\nвласність\n48\n545\nкористування\n18\nвласність\n23\n3460\nвласність\n10\nкористування\n8950\n80\nвласність\n2500\n2014","general":{"inn":"","inn_hidden":true,"last_name":"Лопатинська","post":{"post_unclear":false,"region_unclear":false,"post":"суддя броварського міськрайонного суду київської області","office":"Загальний місцевий суд","region":"Київська область","post_hidden":false,"office_unclear":false},"name":"Світлана","full_name":"Лопатинська Світлана Петрівна","family_raw":"","addresses":[{"place_district":"","place_city_hidden":true,"place_city":"","place_city_unclear":false,"place_district_hidden":false,"place_city_type":"","place_address_hidden":true,"place_city_type_hidden":false,"place_address":"","place_hidden":true,"place":""}],"family":[{"inn_hidden":true,"inn":"","name_hidden":false,"family_name":"Лопатинський А. М. 09. 07. 1966","relations":"Подружжя","name_unclear":false},{"inn":"","relations":"Дитина","relations_other":"","inn_hidden":true,"family_name":"Лопатинська С. В. 18. 09. 1998","name_hidden":false,"name_unclear":false}],"full_name_suggest":{"output":"Лопатинська Світлана Петрівна","input":["Лопатинська Світлана Петрівна","Світлана Петрівна Лопатинська","Світлана Лопатинська"]},"patronymic":"Петрівна"},"source":"VULYK","estate":{"23":[{"space_unclear":false,"costs":"","costs_comment":"","address_hidden":false,"region_hidden":true,"space_comment":"власність","space":"1200","address":"","costs_comment_unclear":false,"region":"","address_unclear":false,"costs_rent_comment":"","space_comment_unclear":false,"space_units":"м²","costs_rent":""}],"25":[{"space_unclear":false,"costs":"","costs_comment":"","address_hidden":false,"region_hidden":true,"space_comment":"власність","space":"10","address":"","costs_comment_unclear":false,"region":"","address_unclear":false,"costs_rent_comment":"","space_comment_unclear":false,"space_units":"м²","costs_rent":"3460"},{"costs_rent":"8950","region":"","costs":"","costs_rent_comment":"","costs_comment":"","region_hidden":false,"space_comment":"користування","space_units":"м²","space":"80","address":""}],"27":[{"space_unclear":false,"costs":"","costs_comment":"","address_hidden":false,"region_hidden":true,"space_comment":"користування","space":"18","address":"","region":"","address_unclear":true,"costs_rent_comment":"","space_units":"м²","costs_rent":"545"}],"29":[{"region_unclear":false,"space_unclear":false,"address_hidden":false,"region_hidden":true,"space_comment":"власність","space":"2500","address":"","region":"","costs_property":"","costs_rent_comment":"","address_unclear":false,"space_units":"м²","costs_property_comment":"","costs_rent":""}],"31":[{"region_unclear":false,"space_unclear":false,"costs_property_comment_unclear":false,"address_hidden":false,"region_hidden":true,"space_comment":"","space":"10","address":"","region":"","costs_property":"","costs_rent_comment":"","space_comment_unclear":false,"address_unclear":false,"space_units":"м²","costs_property_comment":"","costs_rent":""},{"costs_rent":"","region_unclear":false,"region":"","costs_property":"","costs_rent_comment":"","region_hidden":false,"space_comment":"користування","costs_property_comment":"","space_units":"м²","space":"80","address":""}],"32":[{"costs_rent":"","region":"","costs_property":"","costs_rent_comment":"","address_hidden":false,"region_hidden":true,"space_comment":"власність","costs_property_comment":"","space_units":"м²","space":"48","address":""}],"33":[{"space_unclear":false,"address_hidden":false,"region_hidden":true,"space_comment":"власність","space":"23","address":"","region":"","costs_property":"","costs_rent_comment":"","address_unclear":false,"space_units":"м²","costs_property_comment":"","costs_rent":""}]},"intro":{"declaration_year":"2014"}}