{"income":{"5":{"value":"200563","family_comment":"","value_unclear":false,"family_hidden":false,"value_hidden":false,"family_unclear":false,"family":"13874","comment":"","family_comment_unclear":false},"6":{"value":"200563","family_comment":"","value_unclear":false,"comment_hidden":false,"family_hidden":false,"value_hidden":false,"family_unclear":false,"family":"","comment":""},"7":{"value":"","value_hidden":false,"family_comment":"","source_name":"","family":"","comment":"","source_name_hidden":false},"8":{"family_comment":"","value":"","family":"","comment":""},"9":{"value":"","comment_hidden":false,"value_hidden":false,"family_comment":"","family":"","comment":""},"10":{"value":"","value_unclear":false,"value_hidden":false,"family_comment":"","family":"","comment":""},"11":{"family_comment":"","value":"","family":"","comment":""},"12":{"family_comment":"","value":"","family":"","comment":""},"13":{"family_comment":"","value":"","family_hidden":false,"comment":"","family":""},"14":{"family_comment":"","value":"","family":"","comment":""},"15":{"family_comment":"","family_unclear":false,"value":"","family":"","comment":""},"16":{"family_comment":"","value":"","value_unclear":false,"family":"","comment":""},"17":{"family_comment":"","value":"","family":"13874","comment":""},"18":{"family_comment":"","value":"","family":"","comment":""},"19":{"family_comment":"","value":"","comment_unclear":false,"family":"","comment":""},"20":{"value":"","comment_unclear":false,"family_hidden":false,"value_hidden":false,"family_comment":"","family":"","comment":""}},"vehicle":{"35":[{"year_hidden":false,"brand_info":"1584 куб. см., 72 кВт","sum_rent_comment":"","brand_info_unclear":false,"sum_rent_hidden":false,"year":"2004","sum_hidden":false,"brand_info_hidden":false,"sum_rent_comment_unclear":false,"year_unclear":false,"sum_rent":"","sum":"","brand":"Mitsubishi Lancer","sum_comment":"","sum_comment_unclear":false,"brand_hidden":false,"sum_unclear":false,"brand_unclear":false}],"40":[{"year_hidden":false,"brand_info":"1328 куб. см., 67 кВт","sum_rent_comment":"","year":"2006","brand_info_hidden":false,"brand_info_unclear":false,"sum_rent":"","sum":"","brand":"Suzuki Swift","sum_comment":"","brand_unclear":false,"brand_hidden":false}]},"id":"vulyk_64_76","banks":{"45":[{"sum_foreign_comment":"","sum_units":"UAH","sum_comment":"","sum_comment_unclear":false,"sum_foreign_units":"UAH","sum_comment_hidden":false,"sum_unclear":false,"sum":"2706","sum_foreign":""}]},"declaration":{"additional_info_text":"","notfull_lostpages":"","date":"2015-03-30T00:00:00","notfull":"","additional_info":"","url":"http://static.declarations.com.ua/declarations/chosen_ones/mega_batch/medvediev_kostiantyn_viktorovych.pdf"},"liabilities":{"54":{"sum_foreign_comment":"","sum":"312","sum_comment":"","sum_foreign_comment_hidden":false,"sum_hidden":false,"sum_comment_hidden":false,"sum_unclear":false,"sum_foreign":""},"55":{"sum_foreign_comment":"","sum":"","sum_comment":"","sum_comment_unclear":false,"sum_foreign":""},"56":{"sum_foreign_comment":"","sum":"7350","sum_comment":"","sum_unclear":false,"sum_foreign":""},"57":{"sum_foreign_comment":"","sum":"","sum_comment":"","sum_hidden":false,"sum_unclear":false,"sum_foreign":""},"58":{"sum_foreign_comment":"","sum":"","sum_comment":"","sum_unclear":false,"sum_foreign":""},"59":{"sum_foreign_comment":"","sum":"","sum_comment":"","sum_comment_unclear":false,"sum_comment_hidden":false,"sum_unclear":false,"sum_foreign":""},"60":{"sum_foreign_comment":"","sum":"1077","sum_comment":"","sum_foreign":""},"61":{"sum_foreign_comment":"","sum":"","sum_comment":"","sum_foreign":""},"62":{"sum_foreign_comment":"","sum":"3100","sum_comment":"","sum_unclear":false,"sum_foreign":""},"63":{"sum_foreign_comment":"","sum":"","sum_comment":"","sum_unclear":false,"sum_foreign":""},"64":{"sum_foreign_comment":"","sum":"","sum_comment":"","sum_comment_unclear":false,"sum_unclear":false,"sum_foreign":""}},"ft_src":"3100\n312\n7350\n1077\nсуддя васильківського міськрайонного суду київської області\nКиївська область\nЗагальний місцевий суд\nКостянтин\nМедведєва Н. П\nПодружжя\nМедведєв І. К\nДитина\nВікторович\nМедведєв Костянтин Вікторович\nКостянтин Вікторович Медведєв\nКостянтин Медведєв\nМедведєв Костянтин Вікторович\nМедведєв Костянтин Вікторович\nМедведєв\n1584 куб. см., 72 кВт\nMitsubishi Lancer\n2004\n1328 куб. см., 67 кВт\nSuzuki Swift\n2006\n2706\n2014\n1584 куб. см., 72 кВт\nMitsubishi Lancer\n2004\n1328 куб. см., 67 кВт\nSuzuki Swift\n2006\n2706\n20000\n34.5\n1/2 квартири=34.5\n34.5\n1/2 квартири\n41.42\n34.5\n1/2 квартири=34.5\nМедведєв Костянтин Вікторович\nКостянтин Вікторович Медведєв\nКостянтин Медведєв\nМедведєв Костянтин Вікторович\nМедведєв Костянтин Вікторович\nПодружжя\nМедведєва Н. П\nДитина\nМедведєв І. К\nКостянтин\nМедведєв\nЗагальний місцевий суд\nКиївська область\nсуддя васильківського міськрайонного суду київської області\nВікторович\n1077\n7350\n3100\n312\n200563\n13874\n200563\n13874\n2014\n7350\n3100\n312\n1077\n20000\n1/2 квартири=34.5\n34.5\n1/2 квартири\n34.5\n41.42\n1/2 квартири=34.5\n34.5\nПодружжя\nМедведєва Н. П\nДитина\nМедведєв І. К\nВікторович\nМедведєв\nКостянтин\nМедведєв Костянтин Вікторович\nКостянтин Вікторович Медведєв\nКостянтин Медведєв\nМедведєв Костянтин Вікторович\nКиївська область\nЗагальний місцевий суд\nсуддя васильківського міськрайонного суду київської області\nМедведєв Костянтин Вікторович\n200563\n13874\n200563\n13874\nMitsubishi Lancer\n1584 куб. см., 72 кВт\n2004\n2006\nSuzuki Swift\n1328 куб. см., 67 кВт\n200563\n13874\n13874\n200563\n1/2 квартири\n34.5\n1/2 квартири=34.5\n34.5\n41.42\n1/2 квартири=34.5\n34.5\n20000\n2706\n2014","general":{"inn":"","name":"Костянтин","last_name_hidden":false,"family":[{"inn":"","inn_hidden":false,"relations_unclear":false,"relations_hidden":false,"relations_other":"","relations":"Подружжя","name_hidden":false,"inn_unclear":false,"family_name":"Медведєва Н. П","name_unclear":false},{"inn":"","inn_hidden":false,"relations_unclear":false,"relations_hidden":false,"relations_other":"","relations":"Дитина","name_hidden":false,"family_name":"Медведєв І. К","name_unclear":false}],"patronymic":"Вікторович","inn_hidden":false,"family_raw":"","inn_unclear":false,"post":{"post_unclear":false,"post":"суддя васильківського міськрайонного суду київської області","candidate":"","office_hidden":false,"region":"Київська область","post_hidden":false,"office":"Загальний місцевий суд","office_unclear":false,"region_hidden":false},"full_name_suggest":{"output":"Медведєв Костянтин Вікторович","input":["Медведєв Костянтин Вікторович","Костянтин Вікторович Медведєв","Костянтин Медведєв"]},"full_name":"Медведєв Костянтин Вікторович","last_name":"Медведєв","patronymic_hidden":false,"last_name_unclear":false,"name_unclear":false},"source":"VULYK","estate":{"23":[{"space_unclear":false,"costs":"","costs_rent_unclear":false,"costs_comment":"","costs_hidden":false,"space_hidden":false,"space_units_unclear":false,"space_units_hidden":false,"costs_unclear":false,"region":"","space_comment_unclear":false,"space_comment_hidden":false,"costs_rent":"","region_unclear":false,"costs_rent_comment_unclear":false,"address_hidden":true,"region_hidden":false,"space_comment":"","space":"20000","address":"","address_unclear":false,"costs_rent_comment":"","costs_rent_hidden":false,"space_units":"м²"}],"25":[{"region_unclear":false,"space_unclear":false,"costs":"","costs_rent_unclear":false,"costs_comment":"","costs_hidden":false,"address_hidden":true,"region_hidden":false,"space_comment":"","space_hidden":false,"space":"41.42","space_units_hidden":false,"costs_rent_comment_unclear":false,"region":"","costs_rent_comment":"","costs_rent_hidden":false,"space_comment_unclear":false,"space_units":"м²","address":"","costs_rent":"","costs_unclear":false},{"region_unclear":false,"space_unclear":false,"costs":"","costs_comment":"","address_hidden":true,"region_hidden":false,"space_comment":"1/2 квартири=34.5","space":"34.5","address":"","space_comment_unclear":false,"region":"","costs_rent_comment":"","costs_unclear":false,"space_units":"м²","costs_rent":""}],"30":[{"region_unclear":false,"space_unclear":false,"costs_property_hidden":false,"address_hidden":false,"region_hidden":false,"space_comment":"1/2 квартири=34.5","space_hidden":false,"space":"34.5","address":"","region":"","costs_property":"","costs_rent_comment":"","costs_rent_hidden":false,"space_comment_unclear":false,"address_unclear":false,"space_units":"м²","costs_property_comment":"","costs_rent":""}],"31":[{"region_unclear":false,"address_hidden":false,"region_hidden":false,"space_comment":"1/2 квартири","space":"34.5","address":"","region":"","costs_property":"","costs_rent_comment":"","space_comment_hidden":false,"space_units":"м²","costs_property_comment":"","costs_rent":""}]},"intro":{"declaration_year":"2014","isnotdeclaration":"","declaration_year_unclear":false,"declaration_year_hidden":false}}