{"income":{"5":{"value":"324655","family_comment":"","value_unclear":false,"family_hidden":false,"value_hidden":false,"family_unclear":false,"family":"","comment":""},"6":{"value":"260263","value_unclear":false,"family_hidden":false,"value_hidden":false,"family_comment":"","comment_unclear":false,"comment":"","family":""},"7":{"value":"","value_hidden":false,"family_comment":"","source_name":"","family":"","comment":"","source_name_hidden":false},"8":{"family_comment":"","value":"","family":"","comment":""},"9":{"family_comment":"","value":"","comment_unclear":false,"family":"","comment":""},"10":{"family_comment":"","value":"","value_unclear":false,"family":"","comment":""},"11":{"family_comment":"","value":"","family":"","comment":""},"12":{"family_comment":"","value":"","family":"","comment":""},"13":{"family_comment":"","value":"","family":"","comment":""},"14":{"family_comment":"","value":"","family":"","comment":""},"15":{"family_comment":"","value":"","family":"","comment":""},"16":{"family_comment":"","value":"","family":"","comment":""},"17":{"family_comment":"","value":"","family":"","comment":""},"18":{"family_comment":"","value":"","family":"","comment":""},"19":{"value":"","value_unclear":false,"comment_hidden":false,"family_hidden":false,"value_hidden":false,"family_comment":"","family_comment_hidden":false,"comment":"","family":""},"20":{"value":"64392","family_comment":"","value_unclear":false,"family_hidden":false,"value_hidden":false,"family_unclear":false,"comment_unclear":false,"comment":"пенсія","family":""}},"vehicle":{"35":[{"brand_info":"2362 куб. см., 167 л. с","sum_rent_comment":"","year":"2007","brand_info_hidden":false,"brand_info_unclear":false,"year_unclear":false,"sum_rent":"","sum":"","brand":"Toyota Camry","sum_comment":"","brand_unclear":false,"brand_hidden":false}]},"id":"vulyk_65_124","banks":{"51":[{"sum_foreign_comment":"","sum_units":"UAH","sum_comment":"","sum_comment_unclear":true,"sum_foreign_units":"UAH","sum":"1520","sum_foreign":""},{"sum_foreign_comment":"","sum_units":"UAH","sum_comment":"","sum_foreign_units":"UAH","sum":"134177","sum_foreign":""}]},"declaration":{"additional_info_text":"","notfull_lostpages":"","date":"2015-03-31T00:00:00","notfull":"","additional_info":"","url":"http://static.declarations.com.ua/declarations/chosen_ones/mega_batch/livinskyi_ihor_volodymyrovych.pdf"},"liabilities":{"54":{"sum_foreign_comment":"","sum":"6600","sum_comment":"","sum_comment_unclear":false,"sum_hidden":false,"sum_comment_hidden":false,"sum_foreign":""},"55":{"sum_foreign_comment":"","sum":"","sum_comment":"","sum_foreign":""},"56":{"sum_foreign_comment":"","sum":"","sum_comment":"","sum_unclear":false,"sum_foreign":""},"57":{"sum_foreign_comment":"","sum":"","sum_comment":"","sum_comment_unclear":false,"sum_unclear":false,"sum_foreign":""},"58":{"sum_foreign_comment":"","sum":"","sum_comment":"","sum_comment_unclear":false,"sum_unclear":false,"sum_foreign":""},"59":{"sum_foreign_comment":"","sum":"","sum_comment":"","sum_foreign":""},"60":{"sum_foreign_comment":"","sum":"","sum_comment":"","sum_comment_unclear":false,"sum_foreign":""},"61":{"sum_foreign_comment":"","sum":"","sum_comment":"","sum_foreign":""},"62":{"sum_foreign_comment":"","sum":"","sum_comment":"","sum_foreign":""},"63":{"sum_foreign_comment":"","sum":"","sum_comment":"","sum_foreign":""},"64":{"sum_foreign_comment":"","sum":"","sum_comment":"","sum_unclear":false,"sum_foreign":""}},"ft_src":"6600\nсуддя апеляційного суду миколаївської області\nМиколаївська область\nЗагальний апеляційний суд\nІгор\nЛівінська О. А., 19. 02. 1966\nПодружжя\nВолодимирович\nЛівінський\nЛівінський Ігор Володимирович\nЛівінський Ігор Володимирович\nІгор Володимирович Лівінський\nІгор Лівінський\nЛівінський Ігор Володимирович\n2362 куб. см., 167 л. с\nToyota Camry\n2007\n1520\n134177\n2014\n2362 куб. см., 167 л. с\nToyota Camry\n2007\n1520\n134177\n2500\n24\nправо користування\n21\nправо користування\n48.7\nправо користування\n48.7\nЗагальний апеляційний суд\nМиколаївська область\nсуддя апеляційного суду миколаївської області\nЛівінський Ігор Володимирович\nІгор Володимирович Лівінський\nІгор Лівінський\nЛівінський Ігор Володимирович\nІгор\nПодружжя\nЛівінська О. А., 19. 02. 1966\nЛівінський Ігор Володимирович\nЛівінський\nВолодимирович\n6600\n260263\nпенсія\n64392\n324655\n2014\n6600\n48.7\nправо користування\n24\nправо користування\n21\n2500\nправо користування\n48.7\nЛівінська О. А., 19. 02. 1966\nПодружжя\nВолодимирович\nЛівінський\nІгор\nЛівінський Ігор Володимирович\nІгор Володимирович Лівінський\nІгор Лівінський\nЛівінський Ігор Володимирович\nМиколаївська область\nЗагальний апеляційний суд\nсуддя апеляційного суду миколаївської області\nЛівінський Ігор Володимирович\n260263\n324655\nпенсія\n64392\n2007\nToyota Camry\n2362 куб. см., 167 л. с\n64392\nпенсія\n324655\n260263\n48.7\n48.7\nправо користування\nправо користування\n24\nправо користування\n21\n2500\n1520\n134177\n2014","general":{"name_hidden":false,"name":"Ігор","last_name_hidden":false,"inn":"","family":[{"inn":"","inn_hidden":true,"inn_unclear":false,"relations_hidden":false,"relations_other":"","relations":"Подружжя","name_hidden":false,"family_name":"Лівінська О. А., 19. 02. 1966","name_unclear":false}],"patronymic":"Володимирович","inn_hidden":true,"family_raw":"","inn_unclear":false,"post":{"post_unclear":false,"region_unclear":false,"post":"суддя апеляційного суду миколаївської області","office":"Загальний апеляційний суд","region":"Миколаївська область","post_hidden":false,"office_hidden":false,"office_unclear":false,"region_hidden":false},"last_name_unclear":false,"full_name":"Лівінський Ігор Володимирович","addresses":[{"place_district":"","place_address_hidden":true,"place_city":"","place_city_type_hidden":true,"place_district_hidden":true,"place_city_type":"","place_city_hidden":true,"place_address_unclear":false,"place_address":"","place_hidden":true,"place":""}],"last_name":"Лівінський","patronymic_hidden":false,"full_name_suggest":{"output":"Лівінський Ігор Володимирович","input":["Лівінський Ігор Володимирович","Ігор Володимирович Лівінський","Ігор Лівінський"]},"name_unclear":false},"source":"VULYK","estate":{"25":[{"space_unclear":false,"costs":"","costs_comment":"","address_hidden":false,"region_hidden":true,"space_comment":"право користування","space_hidden":false,"space":"48.7","address":"","costs_rent_comment_unclear":false,"region":"","address_unclear":false,"costs_rent_comment":"","space_comment_unclear":false,"space_units":"м²","space_units_hidden":false,"costs_rent":""}],"27":[{"region_unclear":false,"space_hidden":false,"costs":"","costs_comment":"","address_hidden":false,"region_hidden":true,"space_comment":"право користування","space":"24","space_units_hidden":false,"region":"","costs_rent_comment":"","space_units":"м²","address":"","costs_rent":""},{"costs_rent":"","region":"","costs":"","costs_rent_comment":"","costs_comment":"","space_comment":"право користування","space_units":"м²","space":"21","address":""}],"29":[{"space_unclear":false,"address_hidden":false,"region_hidden":true,"space_comment":"","space_units_hidden":false,"space":"2500","address":"","region":"","address_unclear":false,"costs_rent_comment":"","costs_property":"","space_units":"м²","costs_property_comment":"","costs_rent":""}],"31":[{"space_unclear":false,"address_hidden":false,"region_hidden":true,"space_comment":"","space":"48.7","address":"","region":"","costs_property":"","costs_rent_comment":"","space_comment_unclear":false,"space_units":"м²","costs_property_comment":"","costs_rent":""}]},"intro":{"declaration_year":"2014","isnotdeclaration":"","declaration_year_hidden":false}}