{"income":{"5":{"value":"262011.47","family_comment":"","value_unclear":false,"family_hidden":false,"value_hidden":false,"family_unclear":false,"family":"140241.01","comment":"","family_comment_unclear":false},"6":{"family_comment":"","family_unclear":false,"value":"262011.47","family":"140241.11","comment":""},"7":{"source_name_unclear":false,"value":"","family_comment":"","source_name":"","family":"","comment":"","source_name_hidden":false},"8":{"family_comment":"","value":"","family":"","comment":""},"9":{"family_comment":"","family_unclear":false,"value":"","family":"","comment":""},"10":{"family_comment":"","value":"","family":"","comment":""},"11":{"family_comment":"","value":"","family":"","comment":""},"12":{"family_comment":"","value":"","family":"","comment":""},"13":{"family_comment":"","value":"","family":"","comment":""},"14":{"family_comment":"","value":"","family":"","comment":""},"15":{"family_comment":"","value":"","family":"","comment":""},"16":{"value":"","value_unclear":false,"value_hidden":false,"family_comment":"","family":"","comment":""},"17":{"family_comment":"","value":"","family":"","comment":""},"18":{"family_comment":"","value":"","family":"","comment":""},"19":{"family_comment":"","value":"","family":"","comment":""},"20":{"value":"","family_comment":"","value_unclear":false,"comment_hidden":false,"family_hidden":false,"family":"","value_hidden":false,"family_unclear":false,"comment_unclear":false,"comment":"","family_comment_unclear":false}},"vehicle":{"40":[{"brand_info":"двигун - 2000 куб. см.","sum":"","brand":"BMW 320","sum_comment":"","brand_unclear":false,"year":"2008","brand_hidden":false,"brand_info_hidden":false,"brand_info_unclear":false,"sum_rent_comment":"","sum_rent":""}]},"id":"vulyk_62_43","declaration":{"additional_info_text":"","notfull_lostpages":"","date":"2015-03-31T00:00:00","notfull":"","additional_info":"","url":"http://static.declarations.com.ua/declarations/chosen_ones/mega_batch/domuschi_stepan_dmytrovych.pdf"},"liabilities":{"54":{"sum_foreign_comment":"","sum":"","sum_comment":"","sum_hidden":false,"sum_comment_hidden":false,"sum_foreign":""},"55":{"sum_foreign_comment":"","sum":"","sum_comment":"","sum_hidden":false,"sum_comment_hidden":false,"sum_unclear":false,"sum_foreign":""},"56":{"sum_foreign_comment":"","sum":"","sum_comment":"","sum_hidden":false,"sum_unclear":false,"sum_foreign":""},"57":{"sum_foreign_comment":"","sum":"","sum_comment":"","sum_hidden":false,"sum_comment_hidden":false,"sum_unclear":false,"sum_foreign":""},"58":{"sum_foreign_comment":"","sum_foreign_hidden":false,"sum_comment":"","sum_hidden":false,"sum_comment_hidden":false,"sum_unclear":false,"sum":"","sum_foreign":""},"59":{"sum_foreign_comment":"","sum":"","sum_comment":"","sum_foreign":""},"60":{"sum_foreign_comment":"","sum_foreign_hidden":false,"sum_comment":"","sum_hidden":false,"sum_comment_hidden":false,"sum_unclear":false,"sum":"","sum_foreign":""},"61":{"sum_foreign_comment":"","sum_foreign_hidden":false,"sum_comment":"","sum_hidden":false,"sum":"","sum_foreign":""},"62":{"sum_foreign_comment":"","sum":"","sum_comment":"","sum_unclear":false,"sum_foreign":""},"63":{"sum_foreign_comment":"","sum":"","sum_comment":"","sum_hidden":false,"sum_comment_hidden":false,"sum_unclear":false,"sum_foreign":""},"64":{"sum_foreign_comment":"","sum":"","sum_comment":"","sum_comment_unclear":false,"sum_hidden":false,"sum_comment_hidden":false,"sum_foreign":""}},"ft_src":"суддя одеського апеляційного адміністративного суду\nОдеська область\nАпеляційний адміністративний суд\nСтепан\nМоїсєєва І. Г\nПодружжя\nМоїсєєв Д. А\nДитина\nДмитрович\nДомусчі Степан Дмитрович\nСтепан Дмитрович Домусчі\nСтепан Домусчі\nДомусчі Степан Дмитрович\nДомусчі Степан Дмитрович\nДомусчі\nBMW 320\nдвигун - 2000 куб. см.\n2008\n80.5\n43.4\n1000\n2014\n140241.11\n262011.47\n140241.01\n262011.47\nдвигун - 2000 куб. см.\n2008\nBMW 320\n1000\n80.5\n43.4\nПодружжя\nМоїсєєва І. Г\nДитина\nМоїсєєв Д. А\nДомусчі Степан Дмитрович\nСтепан Дмитрович Домусчі\nСтепан Домусчі\nДомусчі Степан Дмитрович\nДомусчі Степан Дмитрович\nСтепан\nДмитрович\nАпеляційний адміністративний суд\nсуддя одеського апеляційного адміністративного суду\nОдеська область\nДомусчі\n262011.47\n140241.11\n262011.47\n140241.01\n2014\nПодружжя\nМоїсєєва І. Г\nМоїсєєв Д. А\nДитина\nДмитрович\nДомусчі\nСтепан\nДомусчі Степан Дмитрович\nСтепан Дмитрович Домусчі\nСтепан Домусчі\nДомусчі Степан Дмитрович\nОдеська область\nсуддя одеського апеляційного адміністративного суду\nАпеляційний адміністративний суд\nДомусчі Степан Дмитрович\nBMW 320\nдвигун - 2000 куб. см.\n2008\n262011.47\n140241.01\n140241.11\n262011.47\n80.5\n43.4\n1000\n2014","general":{"inn":"","name":"Степан","inn_unclear":true,"family":[{"inn":"","inn_hidden":true,"relations_unclear":false,"relations_hidden":false,"relations_other":"","relations":"Подружжя","name_hidden":false,"inn_unclear":true,"family_name":"Моїсєєва І. Г","name_unclear":true},{"inn":"","inn_hidden":false,"relations_hidden":false,"family_name":"Моїсєєв Д. А","relations_other":"","relations":"Дитина","name_hidden":false,"name_unclear":true}],"inn_hidden":true,"family_raw":"","last_name":"Домусчі","post":{"post_unclear":false,"post":"суддя одеського апеляційного адміністративного суду","post_hidden":false,"region":"Одеська область","region_hidden":false,"office":"Апеляційний адміністративний суд","office_hidden":true,"office_unclear":true},"full_name_suggest":{"output":"Домусчі Степан Дмитрович","input":["Домусчі Степан Дмитрович","Степан Дмитрович Домусчі","Степан Домусчі"]},"full_name":"Домусчі Степан Дмитрович","addresses":[{"place_city_type_unclear":true,"place_address":"","place_district_hidden":true,"place_city_type":"","place_address_hidden":true,"place_address_unclear":true,"place_city_type_hidden":true,"place":"","place_district":"","place_unclear":true,"place_city":"","place_city_unclear":true,"place_hidden":true,"place_city_hidden":true,"place_district_unclear":true}],"patronymic":"Дмитрович","last_name_unclear":false,"name_unclear":false},"source":"VULYK","estate":{"29":[{"region_unclear":true,"space_hidden":false,"address_hidden":true,"region_hidden":true,"space_comment":"","space_unclear":false,"space":"1000","address":"","region":"","costs_property":"","costs_rent_comment":"","address_unclear":true,"space_units":"м²","costs_property_comment":"","costs_rent":""}],"31":[{"region_unclear":true,"space_hidden":false,"address_hidden":true,"region_hidden":true,"space_comment":"","space_unclear":false,"space":"80.5","costs_property_unclear":false,"region":"","costs_property":"","costs_rent_comment":"","space_comment_unclear":false,"address_unclear":true,"space_units":"м²","costs_property_comment":"","costs_rent":"","address":""},{"region_unclear":true,"space_hidden":false,"address_hidden":true,"region_hidden":true,"space_comment":"","space_units_hidden":false,"space":"43.4","address":"","region":"","address_unclear":true,"costs_rent_comment":"","costs_property":"","space_units":"м²","costs_property_comment":"","costs_rent":""}]},"intro":{"declaration_year":"2014","isnotdeclaration":"","declaration_year_unclear":false,"declaration_year_hidden":false}}