{"income":{"5":{"family_comment":"","value":"225006","value_unclear":false,"family":"40349","comment":""},"6":{"value":"214686","value_unclear":false,"family_hidden":false,"family_comment":"","family":"1083","comment":""},"7":{"source_name_unclear":false,"value":"","family_comment":"","source_name":"","family":"","comment":""},"8":{"family_comment":"","value":"","family":"","comment":""},"9":{"family_comment":"","value":"","family":"","comment":""},"10":{"family_comment":"","value":"","family":"","comment":""},"11":{"family_comment":"","value":"","comment_unclear":false,"family":"","comment":""},"12":{"family_comment":"","value":"","family":"","comment":""},"13":{"family_comment":"","value":"","family":"","comment":""},"14":{"family_comment":"","value":"","family":"","comment":""},"15":{"family_comment":"","value":"","family":"","comment":""},"16":{"family_comment":"","value":"","family":"","comment":""},"17":{"family_comment":"","value":"","family":"","comment":""},"18":{"family_comment":"","value":"","family":"","comment":""},"19":{"family_comment":"","value":"","family":"","comment":""},"20":{"value":"10320","family_comment":"","value_unclear":false,"family_unclear":false,"comment_unclear":false,"comment":"","family":"39266"}},"id":"vulyk_101_53","declaration":{"additional_info_text":"","notfull_lostpages":"","date":"2016-03-30T00:00:00","notfull":"","additional_info":"","url":"http://static.declarations.com.ua/declarations/chosen_ones/judges_batch/718_komlieva_olena_serhiivna_2015.pdf"},"liabilities":{"54":{"sum_foreign_comment":"","sum":"","sum_comment":"","sum_comment_unclear":false,"sum_hidden":false,"sum_comment_hidden":false,"sum_unclear":false,"sum_foreign":""},"55":{"sum_foreign_comment":"","sum":"","sum_comment":"","sum_foreign":""},"56":{"sum_foreign_comment":"","sum":"","sum_comment":"","sum_comment_hidden":false,"sum_unclear":false,"sum_foreign":""},"57":{"sum_foreign_comment":"","sum":"","sum_comment":"","sum_hidden":false,"sum_comment_hidden":false,"sum_unclear":false,"sum_foreign":""},"58":{"sum_foreign_comment":"","sum":"","sum_comment":"","sum_comment_unclear":false,"sum_hidden":false,"sum_comment_hidden":false,"sum_unclear":false,"sum_foreign":""},"59":{"sum_foreign_comment":"","sum":"","sum_comment":"","sum_foreign":""},"60":{"sum_foreign_comment":"","sum":"","sum_comment":"","sum_hidden":false,"sum_comment_hidden":false,"sum_unclear":false,"sum_foreign":""},"61":{"sum_foreign_comment":"","sum":"","sum_comment":"","sum_foreign":""},"62":{"sum_foreign_comment":"","sum":"","sum_comment":"","sum_comment_unclear":false,"sum_foreign":""},"63":{"sum_foreign_comment":"","sum_comment_hidden":false,"sum":"","sum_comment":"","sum_foreign":""},"64":{"sum_foreign_comment":"","sum_comment_hidden":false,"sum":"","sum_comment":"","sum_foreign":""}},"ft_src":"суддя апеляційного суду одеської області\nОдеська область\nЗагальний апеляційний суд\nОлена\nШурупов В. В\nПодружжя\nШурупова Н. В\nДитина\nШурупова Т. В\nДитина\nСергіївна\nКомлєва Олена Сергіївна\nКомлєва\nКомлєва Олена Сергіївна\nОлена Сергіївна Комлєва\nОлена Комлєва\nКомлєва Олена Сергіївна\n10320\n39266\n40349\n225006\n214686\n1083\n.0868\n2015\n1083\n214686\n40349\n225006\n39266\n10320\n.0868\nПодружжя\nШурупов В. В\nДитина\nШурупова Н. В\nДитина\nШурупова Т. В\nКомлєва Олена Сергіївна\nОлена Сергіївна Комлєва\nОлена Комлєва\nКомлєва Олена Сергіївна\nОлена\nКомлєва Олена Сергіївна\nСергіївна\nЗагальний апеляційний суд\nсуддя апеляційного суду одеської області\nОдеська область\nКомлєва\n214686\n1083\n39266\n10320\n225006\n40349\n2015\nШурупов В. В\nПодружжя\nШурупова Н. В\nДитина\nШурупова Т. В\nДитина\nОлена\nСергіївна\nКомлєва\nКомлєва Олена Сергіївна\nОлена Сергіївна Комлєва\nОлена Комлєва\nКомлєва Олена Сергіївна\nсуддя апеляційного суду одеської області\nЗагальний апеляційний суд\nОдеська область\nКомлєва Олена Сергіївна\n.0868\n2015","general":{"inn":"","name":"Олена","inn_unclear":false,"family":[{"inn":"","relations":"Подружжя","relations_other":"","inn_hidden":true,"family_name":"Шурупов В. В","name_hidden":true,"name_unclear":false},{"inn":"","relations":"Дитина","relations_unclear":false,"family_name":"Шурупова Н. В","inn_hidden":false,"relations_other":"","name_hidden":false,"name_unclear":false},{"inn":"","relations":"Дитина","relations_other":"","inn_hidden":false,"family_name":"Шурупова Т. В","name_hidden":false,"name_unclear":false}],"inn_hidden":true,"family_raw":"","last_name":"Комлєва","post":{"region":"Одеська область","region_unclear":false,"post":"суддя апеляційного суду одеської області","office_unclear":false,"office":"Загальний апеляційний суд"},"full_name":"Комлєва Олена Сергіївна","addresses":[{"place_district":"","place_city_hidden":true,"place_city":"","place_city_type_hidden":false,"place_district_hidden":false,"place_city_type":"","place_address_hidden":true,"place_address":"","place_hidden":true,"place":""}],"patronymic":"Сергіївна","patronymic_hidden":false,"full_name_suggest":{"output":"Комлєва Олена Сергіївна","input":["Комлєва Олена Сергіївна","Олена Сергіївна Комлєва","Олена Комлєва"]}},"source":"VULYK","estate":{"23":[{"space_unclear":false,"costs":"","costs_comment":"","address_hidden":false,"region_hidden":true,"space_comment":"","space_hidden":false,"space":".0868","address":"","costs_comment_unclear":false,"region":"","space_units_unclear":false,"space_units":"га","costs_rent":"","costs_rent_comment":""}]},"intro":{"declaration_year":"2015"}}