{"income":{"5":{"family_comment":"","value":"251944","family":"","comment":""},"6":{"family_comment":"","value":"238576","value_unclear":false,"family":"","comment":""},"7":{"value":"","family_comment":"","source_name":"","family":"","comment":"","source_name_hidden":false},"8":{"family_comment":"","value":"","family":"","comment":""},"9":{"family_comment":"","value":"","family":"","comment":""},"10":{"family_comment":"","value":"13398","family":"","comment":""},"11":{"family_comment":"","value":"","comment_hidden":false,"family":"","comment":""},"12":{"family_comment":"","value":"","family":"","comment":""},"13":{"family_comment":"","value":"","family":"","comment":""},"14":{"family_comment":"","value":"","family":"","comment":""},"15":{"value":"","family_comment":"","value_unclear":false,"family_unclear":false,"family":"","comment":""},"16":{"family_comment":"","value":"","family":"","comment":""},"17":{"family_comment":"","value":"","family":"","comment":""},"18":{"family_comment":"","value":"","family":"","comment":""},"19":{"family_comment":"","value":"","family":"","comment":""},"20":{"family_comment":"","value":"","comment_unclear":false,"family":"","comment":""}},"id":"vulyk_104_41","declaration":{"date":"2016-03-14T00:00:00","additional_info_text":"","additional_info":"","url":"http://static.declarations.com.ua/declarations/chosen_ones/judges_batch/1839_korshun_nina_mykolaivna_2015.pdf"},"liabilities":{"54":{"sum_foreign_comment":"","sum_foreign_hidden":false,"sum_comment":"","sum_hidden":false,"sum_comment_hidden":false,"sum_unclear":false,"sum":"","sum_foreign":""},"55":{"sum_foreign_comment":"","sum":"","sum_comment":"","sum_foreign":""},"56":{"sum_foreign_comment":"","sum":"","sum_comment":"","sum_unclear":false,"sum_foreign":""},"57":{"sum_foreign_comment":"","sum_foreign_hidden":false,"sum_comment":"","sum_comment_unclear":false,"sum_comment_hidden":false,"sum":"","sum_foreign":""},"58":{"sum_foreign_comment":"","sum":"","sum_comment":"","sum_unclear":false,"sum_foreign":""},"59":{"sum_foreign_comment":"","sum":"","sum_comment":"","sum_foreign":""},"60":{"sum_foreign_comment":"","sum_foreign_hidden":false,"sum_comment":"","sum_comment_hidden":false,"sum":"","sum_foreign":""},"61":{"sum_foreign_comment":"","sum":"","sum_comment":"","sum_foreign":""},"62":{"sum_foreign_comment":"","sum":"","sum_comment":"","sum_foreign":""},"63":{"sum_foreign_comment":"","sum":"","sum_comment":"","sum_foreign":""},"64":{"sum_foreign_comment":"","sum":"","sum_comment":"","sum_foreign":""}},"ft_src":"Коршун Ніна Миколаївна\nсуддя\nм. Київ\nАпеляційний господарський суд\nНіна\nКоршун Ніна Миколаївна\nНіна Миколаївна Коршун\nНіна Коршун\nКоршун Ніна Миколаївна\nКоршун\nМиколаївна\n13398\n251944\n238576\nсвідоцтво про право власності\n.12\nза дог. дарування\n96\n2015\n238576\n13398\n251944\n238576\n251944\n13398\nКоршун Ніна Миколаївна\nНіна Миколаївна Коршун\nНіна Коршун\nКоршун Ніна Миколаївна\nКоршун Ніна Миколаївна\nМиколаївна\nНіна\nКоршун\nАпеляційний господарський суд\nсуддя\nм. Київ\n.12\nсвідоцтво про право власності\n96\nза дог. дарування\n2015\nКоршун\nМиколаївна\nсуддя\nАпеляційний господарський суд\nм. Київ\nКоршун Ніна Миколаївна\nКоршун Ніна Миколаївна\nНіна Миколаївна Коршун\nНіна Коршун\nКоршун Ніна Миколаївна\nНіна\nза дог. дарування\n96\nсвідоцтво про право власності\n.12\n2015","general":{"inn":"","inn_hidden":true,"last_name":"Коршун","post":{"region":"м. Київ","region_unclear":false,"post":"суддя","office_unclear":false,"office":"Апеляційний господарський суд"},"name":"Ніна","full_name":"Коршун Ніна Миколаївна","family_raw":"","addresses":[{"place_district":"","place_city_hidden":true,"place_city":"","place_city_type_hidden":false,"place_district_hidden":false,"place_city_type":"","place_address_hidden":true,"place_address":"","place_hidden":true,"place":""}],"full_name_suggest":{"output":"Коршун Ніна Миколаївна","input":["Коршун Ніна Миколаївна","Ніна Миколаївна Коршун","Ніна Коршун"]},"patronymic":"Миколаївна"},"source":"VULYK","estate":{"23":[{"space_hidden":false,"costs":"","costs_comment":"","address_hidden":false,"region_hidden":true,"space_comment":"свідоцтво про право власності","space":".12","address":"","region":"","costs_rent_comment":"","space_comment_unclear":false,"space_units":"га","costs_rent":""}],"25":[{"costs":"","costs_comment":"","address_hidden":false,"region_hidden":true,"space_comment":"за дог. дарування","space":"96","address":"","costs_unclear":false,"region":"","costs_rent_comment":"","space_comment_unclear":false,"space_units":"м²","costs_rent":""}]},"intro":{"declaration_year":"2015","isnotdeclaration":""}}