{"income":{"5":{"value":"199776.6","family_unclear":false,"family_hidden":false,"family_comment":"","family":"72750","comment":""},"6":{"value":"187159.6","family_comment":"","value_unclear":false,"family_hidden":false,"family_unclear":false,"family":"72750","comment":""},"7":{"value":"","family_hidden":false,"value_hidden":false,"family_comment":"","source_name":"","family":"","comment":"","source_name_hidden":false},"8":{"family_comment":"","value":"","family":"","comment":""},"9":{"family_comment":"","value":"","family":"","comment":""},"10":{"family_comment":"","value":"12617","value_unclear":false,"family":"","comment":""},"11":{"family_comment":"","value":"","family":"","comment":""},"12":{"family_comment":"","value":"","family":"","comment":""},"13":{"family_comment":"","value":"","family":"","comment":""},"14":{"family_comment":"","value":"","family":"","comment":""},"15":{"family_comment":"","value":"","family":"","comment":""},"16":{"family_comment":"","value":"","family":"","comment":""},"17":{"family_comment":"","value":"","family":"","comment":""},"18":{"family_comment":"","value":"","family":"","comment":""},"19":{"family_comment":"","value":"","family":"","comment":""},"20":{"value":"","family_comment":"","value_unclear":false,"family_unclear":false,"comment_unclear":false,"comment":"","family":""}},"vehicle":{"35":[{"brand_info":"1991 куб. см., 104.3 кВт , 4325 мм","sum_rent_comment":"","year":"2008","brand_info_hidden":false,"brand_info_unclear":false,"year_unclear":false,"sum_rent":"","sum":"","brand":"Hyundai Tucson","sum_comment":"","brand_unclear":false,"brand_hidden":false}],"40":[{"brand_info":"2771 куб. см., 145.22 кВт , 480.3 см","sum_rent_comment":"","brand":"Skoda Superb","sum_comment":"","brand_unclear":false,"year":"2003","brand_info_unclear":false,"year_unclear":false,"sum":"","sum_rent":""}]},"id":"vulyk_74_66","banks":{"52":[{"sum_foreign_comment":"","sum_foreign_hidden":false,"sum_comment":"","sum_foreign_units":"UAH","sum_units":"UAH","sum":"1406988","sum_foreign":""}],"53":[{"sum_foreign_comment":"","sum_units":"UAH","sum_comment":"","sum_foreign_units":"UAH","sum_comment_hidden":true,"sum":"829074.8","sum_foreign":""}]},"declaration":{"additional_info_text":"","notfull_lostpages":"","date":"2014-12-09T00:00:00","notfull":"","additional_info":"","url":"http://static.declarations.com.ua/declarations/chosen_ones/judges_batch/1715_mykhalska_iuliia_borysivna.pdf"},"liabilities":{"54":{"sum_foreign_comment":"","sum":"","sum_comment":"","sum_comment_unclear":false,"sum_comment_hidden":false,"sum_foreign":""},"55":{"sum_foreign_comment":"","sum":"","sum_comment":"","sum_hidden":false,"sum_unclear":false,"sum_foreign":""},"56":{"sum_foreign_comment":"","sum":"","sum_comment":"","sum_hidden":false,"sum_unclear":false,"sum_foreign":""},"57":{"sum_foreign_comment":"","sum":"","sum_comment":"","sum_comment_unclear":false,"sum_comment_hidden":false,"sum_foreign":""},"58":{"sum_foreign_comment":"","sum_comment_hidden":false,"sum":"","sum_comment":"","sum_foreign":""},"59":{"sum_foreign_comment":"","sum":"","sum_comment":"","sum_foreign":""},"60":{"sum_foreign_comment":"","sum":"","sum_hidden":false,"sum_comment":"","sum_foreign":""},"61":{"sum_foreign_comment":"","sum":"","sum_comment":"","sum_foreign":""},"62":{"sum_foreign_comment":"","sum":"","sum_comment":"","sum_foreign":""},"63":{"sum_foreign_comment":"","sum":"","sum_comment":"","sum_comment_unclear":false,"sum_unclear":false,"sum_foreign":""},"64":{"sum_foreign_comment":"","sum":"","sum_comment":"","sum_comment_unclear":false,"sum_unclear":false,"sum_foreign":""}},"ft_src":"Михальська Юлія Борисівна\nсуддя київського апеляційного господарського суду\nм. Київ\nАпеляційний господарський суд\nЮлія\nМихальський Ю. А\nПодружжя\nМихальський Д. Ю\nДитина\nМихальська Юлія Борисівна\nЮлія Борисівна Михальська\nЮлія Михальська\nМихальська Юлія Борисівна\nМихальська\nБорисівна\n1991 куб. см., 104.3 кВт , 4325 мм\nHyundai Tucson\n2008\nSkoda Superb\n2771 куб. см., 145.22 кВт , 480.3 см\n2003\n71.8\n16.85\n1406988\n829074.8\n2013\n1991 куб. см., 104.3 кВт , 4325 мм\nHyundai Tucson\n2008\n2771 куб. см., 145.22 кВт , 480.3 см\nSkoda Superb\n2003\n2013\nАпеляційний господарський суд\nм. Київ\nсуддя київського апеляційного господарського суду\nБорисівна\nМихальська Юлія Борисівна\nЮлія Борисівна Михальська\nЮлія Михальська\nМихальська Юлія Борисівна\nЮлія\nМихальська Юлія Борисівна\nМихальська\nПодружжя\nМихальський Ю. А\nДитина\nМихальський Д. Ю\n72750\n187159.6\n199776.6\n72750\n12617\n71.8\n16.85\n829074.8\n1406988\n72750\n187159.6\n12617\n72750\n199776.6\nПодружжя\nМихальський Ю. А\nДитина\nМихальський Д. Ю\nБорисівна\nМихальська\nм. Київ\nАпеляційний господарський суд\nсуддя київського апеляційного господарського суду\nМихальська Юлія Борисівна\nМихальська Юлія Борисівна\nЮлія Борисівна Михальська\nЮлія Михальська\nМихальська Юлія Борисівна\nЮлія\nHyundai Tucson\n1991 куб. см., 104.3 кВт , 4325 мм\n2008\n2003\n2771 куб. см., 145.22 кВт , 480.3 см\nSkoda Superb\n12617\n199776.6\n72750\n187159.6\n72750\n71.8\n16.85\n1406988\n829074.8\n2013","general":{"inn":"","inn_hidden":true,"last_name":"Михальська","post":{"region_unclear":false,"region":"м. Київ","post":"суддя київського апеляційного господарського суду","office":"Апеляційний господарський суд","office_unclear":false,"post_hidden":false},"name":"Юлія","full_name":"Михальська Юлія Борисівна","family_raw":"","addresses":[{"place_district":"","place_city_hidden":false,"place_city":"","place_city_type_hidden":false,"place_district_hidden":false,"place_city_type":"","place_address_hidden":false,"place_address":"","place_hidden":true,"place":""}],"family":[{"inn":"","relations":"Подружжя","relations_other":"","inn_hidden":true,"family_name":"Михальський Ю. А","name_hidden":true,"name_unclear":false},{"inn":"","relations":"Дитина","relations_other":"","inn_hidden":true,"family_name":"Михальський Д. Ю","name_hidden":true,"name_unclear":false}],"full_name_suggest":{"output":"Михальська Юлія Борисівна","input":["Михальська Юлія Борисівна","Юлія Борисівна Михальська","Юлія Михальська"]},"patronymic":"Борисівна"},"source":"VULYK","estate":{"31":[{"space_unclear":false,"address_hidden":false,"region_hidden":true,"space_comment":"","space":"71.8","address":"","region":"","costs_property":"","costs_rent_comment":"","address_unclear":false,"space_units":"м²","costs_property_comment":"","costs_rent":""},{"space_unclear":false,"address_hidden":false,"region_hidden":true,"space_comment":"","space":"16.85","address":"","region":"","costs_property":"","costs_rent_comment":"","space_units":"м²","costs_property_comment":"","costs_rent":""}]},"intro":{"declaration_year":"2013","isnotdeclaration":"","declaration_year_unclear":false}}