{"income":{"5":{"family_comment":"","value":"252037","family":"323766","comment":""},"6":{"family_comment":"","value":"238639","value_unclear":false,"family":"237656","comment":""},"7":{"value":"","family_comment":"","source_name":"","family":"","comment":"","source_name_hidden":false},"8":{"family_comment":"","value":"","family":"","comment":""},"9":{"family_comment":"","value":"","family":"","comment":""},"10":{"family_comment":"","value":"13398","family":"12180","comment":""},"11":{"family_comment":"","value":"","comment_hidden":false,"family":"","comment":""},"12":{"family_comment":"","value":"","family":"","comment":""},"13":{"family_comment":"","value":"","family":"","comment":""},"14":{"family_comment":"","value":"","family":"","comment":""},"15":{"value":"","family_comment":"","value_unclear":false,"family_unclear":false,"family":"","comment":""},"16":{"family_comment":"","value":"","family":"","comment":""},"17":{"family_comment":"","value":"","family":"","comment":""},"18":{"family_comment":"","value":"","family":"","comment":""},"19":{"family_comment":"","value":"","family":"","comment":""},"20":{"family_comment":"","value":"","comment_unclear":false,"family":"73930","comment":""}},"vehicle":{"35":[{"brand_info":"","sum_rent_comment":"","brand":"Hyundai Santa FE","sum_comment":"","year":"2012","brand_hidden":false,"brand_info_unclear":false,"sum":"","sum_rent":""}]},"id":"vulyk_104_180","declaration":{"date":"2016-03-25T00:00:00","additional_info_text":"","additional_info":"","url":"http://static.declarations.com.ua/declarations/chosen_ones/judges_batch/1978_derevinskyi_serhii_mykolaiovych_2015.pdf"},"liabilities":{"54":{"sum_foreign_comment":"","sum_unclear":false,"sum":"","sum_comment":"","sum_hidden":false,"sum_comment_hidden":false,"sum_foreign_hidden":false,"sum_foreign":""},"55":{"sum_foreign_comment":"","sum":"","sum_comment":"","sum_foreign":""},"56":{"sum_foreign_comment":"","sum":"58780","sum_comment":"","sum_unclear":false,"sum_foreign":""},"57":{"sum_foreign_comment":"","sum":"","sum_comment":"","sum_comment_unclear":false,"sum_comment_hidden":false,"sum_foreign_hidden":false,"sum_foreign":""},"58":{"sum_foreign_comment":"","sum":"","sum_comment":"","sum_unclear":false,"sum_foreign":""},"59":{"sum_foreign_comment":"","sum":"","sum_comment":"","sum_foreign":""},"60":{"sum_foreign_comment":"","sum":"","sum_comment":"","sum_comment_hidden":false,"sum_foreign_hidden":false,"sum_foreign":""},"61":{"sum_foreign_comment":"","sum":"","sum_comment":"","sum_foreign":""},"62":{"sum_foreign_comment":"","sum":"","sum_comment":"","sum_foreign":""},"63":{"sum_foreign_comment":"","sum":"59261","sum_comment":"Укрсиббанк, відділення № 46, м. Кіровоград","sum_foreign":""},"64":{"sum_foreign_comment":"","sum":"7739","sum_comment":"","sum_foreign":""}},"ft_src":"2012\nHyundai Santa FE\n576.3\n40\n123.9\n2015\n237656\n238639\n12180\n13398\n323766\n252037\n73930\nHyundai Santa FE\n2012\n2015\nПодружжя\nДеревінська Л. В. 06. 09. 1960\nБатьки\nДеревінська Р. М. 11. 02. 1941\nДеревінський\nДеревінський Сергій Миколайович\nСергій Миколайович Деревінський\nСергій Деревінський\nДеревінський Сергій Миколайович\nДеревінський Сергій Миколайович\nСергій\nМиколайович\nЗагальний апеляційний суд\nсуддя апеляційного суду кіровоградської області\nКіровоградська область\nУкрсиббанк, відділення № 46, м. Кіровоград\n59261\n58780\n7739\n238639\n237656\n73930\n252037\n323766\n13398\n12180\n576.3\n123.9\n40\n58780\nУкрсиббанк, відділення № 46, м. Кіровоград\n59261\n7739\nПодружжя\nДеревінська Л. В. 06. 09. 1960\nБатьки\nДеревінська Р. М. 11. 02. 1941\nМиколайович\nДеревінський\nсуддя апеляційного суду кіровоградської області\nЗагальний апеляційний суд\nКіровоградська область\nДеревінський Сергій Миколайович\nДеревінський Сергій Миколайович\nСергій Миколайович Деревінський\nСергій Деревінський\nДеревінський Сергій Миколайович\nСергій","general":{"inn":"","inn_hidden":true,"last_name":"Деревінський","post":{"region":"Кіровоградська область","office":"Загальний апеляційний суд","post":"суддя апеляційного суду кіровоградської області","office_unclear":false,"region_unclear":false},"name":"Сергій","full_name":"Деревінський Сергій Миколайович","family_raw":"","addresses":[{"place_district":"","place_address_hidden":true,"place_city":"","place_address":"","place_district_hidden":false,"place_city_type":"","place_city_hidden":true,"place_city_type_hidden":false,"place_hidden":true,"place":""}],"family":[{"inn":"","relations":"Подружжя","relations_other":"","inn_hidden":true,"family_name":"Деревінська Л. В. 06. 09. 1960","name_hidden":false,"name_unclear":false},{"inn":"","relations":"Батьки","relations_other":"","inn_hidden":false,"family_name":"Деревінська Р. М. 11. 02. 1941","name_hidden":false,"name_unclear":false}],"full_name_suggest":{"output":"Деревінський Сергій Миколайович","input":["Деревінський Сергій Миколайович","Сергій Миколайович Деревінський","Сергій Деревінський"]},"patronymic":"Миколайович"},"source":"VULYK","estate":{"23":[{"space_hidden":false,"costs":"","costs_comment":"","address_hidden":false,"region_hidden":true,"space_comment":"","space":"576.3","address":"","region":"","costs_rent_comment":"","space_comment_unclear":false,"space_units":"м²","costs_rent":""}],"24":[{"space_hidden":false,"costs":"","costs_comment":"","address_hidden":false,"region_hidden":true,"space_comment":"","space":"123.9","address":"","region":"","costs_rent_comment":"","space_comment_unclear":false,"space_units":"м²","costs_rent":""}],"30":[{"space_hidden":false,"address_hidden":false,"region_hidden":true,"space_comment":"","space":"40","address":"","region":"","costs_property":"","costs_rent_comment":"","space_comment_unclear":false,"space_units":"м²","costs_property_comment":"","costs_rent":""}]},"intro":{"declaration_year":"2015","isnotdeclaration":""}}