{"income":{"5":{"value":"206401","family_comment":"","value_unclear":false,"comment_hidden":false,"family_hidden":false,"value_hidden":false,"family_unclear":false,"family_comment_hidden":false,"comment":"","family":"114655"},"6":{"value":"187875","family_comment":"","value_unclear":false,"family_hidden":false,"family_unclear":false,"family":"114655","comment":""},"7":{"source_name_unclear":false,"value":"","family_hidden":false,"family_comment":"","source_name":"","family":"","comment":"","source_name_hidden":false},"8":{"family_comment":"","value":"","family":"","comment":""},"9":{"value":"","value_unclear":false,"family_hidden":false,"family_comment":"","family":"","comment":""},"10":{"value":"12180","value_unclear":false,"family_hidden":false,"value_hidden":false,"family_comment":"","comment_unclear":false,"comment":"","family":""},"11":{"family_comment":"","value":"","family":"","comment":""},"12":{"family_comment":"","value":"","family":"","comment":""},"13":{"family_comment":"","value":"","family":"","comment":""},"14":{"family_comment":"","value":"","family":"","comment":""},"15":{"family_comment":"","value":"","family_hidden":false,"comment":"","family":""},"16":{"value":"","value_unclear":false,"family_hidden":false,"family_comment":"","family":"","comment":""},"17":{"family_comment":"","value":"","family_hidden":false,"comment":"","family":""},"18":{"family_comment":"","value":"","value_unclear":false,"family":"","comment":""},"19":{"family_comment":"","value":"6346","family":"","comment":""},"20":{"value":"","family_comment":"","value_unclear":false,"family_hidden":false,"family_unclear":false,"comment_unclear":false,"comment":"","family":""}},"vehicle":{"35":[{"brand_info":"об'єм циліндрів - 1500 , потужність - 105 к. с","sum_rent_comment":"","brand_info_unclear":false,"year":"2013","sum_rent_unclear":false,"brand_info_hidden":false,"sum_rent_comment_unclear":false,"sum_hidden":false,"sum_rent":"","sum":"237500","brand":"Renault Fluence","sum_comment":"","brand_unclear":false,"brand_hidden":false}],"40":[{"year_hidden":false,"brand_info":"об'єм циліндрів двигуна - 1997 куб. см., потужність 140 к. с","sum_rent_comment":"","year":"2012","brand_info_hidden":false,"brand_info_unclear":false,"year_unclear":false,"sum_rent":"","sum":"","brand":"Ford Kuga","sum_comment":"","brand_unclear":false,"brand_hidden":false}]},"id":"vulyk_72_318","declaration":{"additional_info_text":"","notfull_lostpages":"","date":"2015-03-30T00:00:00","notfull":"","additional_info":"","url":"http://static.declarations.com.ua/declarations/chosen_ones/epic_batch/baibara_hryhorii_antonovych.pdf"},"liabilities":{"54":{"sum_foreign_comment":"","sum":"","sum_comment":"","sum_comment_hidden":false,"sum_unclear":false,"sum_foreign":""},"55":{"sum_foreign_comment":"","sum":"","sum_comment":"","sum_foreign":""},"56":{"sum_foreign_comment":"","sum":"15000","sum_hidden":false,"sum_comment":"","sum_foreign":""},"57":{"sum_foreign_comment":"","sum":"","sum_comment":"","sum_comment_unclear":false,"sum_hidden":false,"sum_comment_hidden":false,"sum_unclear":false,"sum_foreign":""},"58":{"sum_foreign_comment":"","sum":"","sum_comment":"","sum_comment_unclear":false,"sum_hidden":false,"sum_comment_hidden":false,"sum_unclear":false,"sum_foreign":""},"59":{"sum_foreign_comment":"","sum_foreign_hidden":false,"sum_comment":"","sum_foreign_unclear":false,"sum_comment_hidden":false,"sum":"","sum_foreign":""},"60":{"sum_foreign_comment":"","sum_foreign_hidden":false,"sum_comment":"","sum_hidden":false,"sum":"","sum_foreign":""},"61":{"sum_foreign_comment":"","sum_foreign_hidden":false,"sum_comment":"","sum_hidden":false,"sum":"","sum_foreign":""},"62":{"sum_foreign_comment":"","sum_foreign_hidden":false,"sum_comment":"","sum_hidden":false,"sum":"11000","sum_foreign":""},"63":{"sum_foreign_comment":"","sum_foreign_hidden":false,"sum_comment":"","sum_comment_unclear":false,"sum_hidden":false,"sum_comment_hidden":false,"sum_unclear":false,"sum":"","sum_foreign":""},"64":{"sum_foreign_comment":"","sum_foreign_hidden":false,"sum_comment":"","sum_hidden":false,"sum":"","sum_foreign":""}},"ft_src":"11000\n15000\nсуддя дніпровського районного суду м. дніпродзержинська дніпропетровської області\nДніпропетровська область\nЗагальний місцевий суд\nГригорій\nБайбара Т. В., 15. 06. 1973 р. н\nПодружжя\nБайбара І. Г., 01. 02. 1999 р. н\nДитина\nБайбара А. Г., 08. 12. 2000 р. н\nДитина\nАнтонович\nБайбара\nБайбара Григорій Антонович\nБайбара Григорій Антонович\nГригорій Антонович Байбара\nГригорій Байбара\nБайбара Григорій Антонович\nоб'єм циліндрів - 1500 , потужність - 105 к. с\nRenault Fluence\n2013\n237500\nоб'єм циліндрів двигуна - 1997 куб. см., потужність 140 к. с\nFord Kuga\n2012\n41400\n1421\n68.4\n50.6\n2014\n114655\n187875\n12180\n114655\n206401\n6346\nоб'єм циліндрів - 1500 , потужність - 105 к. с\nRenault Fluence\n2013\n237500\nоб'єм циліндрів двигуна - 1997 куб. см., потужність 140 к. с\nFord Kuga\n2012\n41400\n1421\n68.4\n50.6\nПодружжя\nБайбара Т. В., 15. 06. 1973 р. н\nДитина\nБайбара І. Г., 01. 02. 1999 р. н\nДитина\nБайбара А. Г., 08. 12. 2000 р. н\nБайбара Григорій Антонович\nГригорій Антонович Байбара\nГригорій Байбара\nБайбара Григорій Антонович\nГригорій\nБайбара Григорій Антонович\nБайбара\nДніпропетровська область\nЗагальний місцевий суд\nсуддя дніпровського районного суду м. дніпродзержинська дніпропетровської області\nАнтонович\n15000\n11000\n187875\n114655\n206401\n114655\n12180\n6346\n2014\n15000\n11000\nБайбара Т. В., 15. 06. 1973 р. н\nПодружжя\nБайбара І. Г., 01. 02. 1999 р. н\nДитина\nБайбара А. Г., 08. 12. 2000 р. н\nДитина\nАнтонович\nБайбара\nБайбара Григорій Антонович\nГригорій Антонович Байбара\nГригорій Байбара\nБайбара Григорій Антонович\nДніпропетровська область\nЗагальний місцевий суд\nсуддя дніпровського районного суду м. дніпродзержинська дніпропетровської області\nБайбара Григорій Антонович\nГригорій\n2013\nRenault Fluence\n237500\nоб'єм циліндрів - 1500 , потужність - 105 к. с\nFord Kuga\nоб'єм циліндрів двигуна - 1997 куб. см., потужність 140 к. с\n2012\n6346\n12180\n206401\n114655\n187875\n114655\n68.4\n41400\n1421\n50.6\n2014","general":{"inn":"","name":"Григорій","patronymic_unclear":false,"family":[{"inn":"","inn_hidden":true,"relations_unclear":false,"relations_hidden":false,"relations_other":"","relations":"Подружжя","name_hidden":false,"inn_unclear":false,"family_name":"Байбара Т. В., 15. 06. 1973 р. н","name_unclear":false},{"inn":"","inn_hidden":true,"relations_hidden":false,"family_name":"Байбара І. Г., 01. 02. 1999 р. н","relations_other":"","relations":"Дитина","name_hidden":false,"name_unclear":false},{"inn":"","inn_hidden":false,"relations_hidden":false,"family_name":"Байбара А. Г., 08. 12. 2000 р. н","relations_other":"","relations":"Дитина","name_hidden":false,"name_unclear":false}],"patronymic":"Антонович","inn_hidden":true,"family_raw":"","inn_unclear":false,"post":{"post_unclear":false,"region_unclear":false,"post":"суддя дніпровського районного суду м. дніпродзержинська дніпропетровської області","candidate":"","office_hidden":false,"region":"Дніпропетровська область","post_hidden":false,"office":"Загальний місцевий суд","office_unclear":false,"region_hidden":false},"last_name_unclear":false,"full_name":"Байбара Григорій Антонович","addresses":[{"place_city_type_hidden":true,"place_district_hidden":true,"place_city_type":"","place_city_hidden":true,"place_address_unclear":false,"place_address":"","place":"","place_district":"","place_unclear":false,"place_city":"","place_city_unclear":false,"place_hidden":true,"place_address_hidden":true,"place_district_unclear":false}],"last_name":"Байбара","patronymic_hidden":false,"full_name_suggest":{"output":"Байбара Григорій Антонович","input":["Байбара Григорій Антонович","Григорій Антонович Байбара","Григорій Байбара"]},"name_unclear":false},"source":"VULYK","estate":{"23":[{"space_hidden":false,"costs":"","costs_rent_unclear":false,"costs_comment":"","costs_hidden":false,"address_hidden":true,"region_hidden":true,"space_comment":"","space_unclear":false,"space":"41400","address":"","region":"","address_unclear":false,"costs_rent_comment":"","costs_rent_hidden":false,"space_units":"м²","space_units_hidden":false,"costs_rent":""},{"costs":"","costs_comment":"","address_hidden":false,"region_hidden":false,"space_comment":"","space":"1421","address":"","region":"","address_unclear":false,"costs_rent_comment":"","space_units":"м²","costs_rent":""}],"25":[{"space_unclear":false,"costs":"","costs_rent_unclear":false,"costs_comment":"","costs_hidden":false,"space_hidden":false,"costs_comment_unclear":false,"costs_rent_comment_unclear":false,"region":"","space_comment_hidden":false,"space_comment_unclear":false,"costs_rent_comment_hidden":false,"costs_rent":"","costs_comment_hidden":false,"address_hidden":true,"region_hidden":true,"space_comment":"","space":"50.6","address":"","address_unclear":false,"costs_rent_comment":"","costs_rent_hidden":false,"space_units":"м²"}],"28":[{"space_hidden":false,"costs":"","costs_comment":"","address_hidden":true,"region_hidden":true,"space_comment":"","space_unclear":false,"space":"","address":"","region":"","costs_rent_comment":"","space_units":"м²","costs_rent":""}],"31":[{"space_unclear":false,"address_hidden":true,"region_hidden":true,"space_comment":"","space_units_hidden":false,"space_hidden":false,"space":"68.4","address":"","region":"","address_unclear":false,"costs_rent_comment":"","costs_property":"","space_units":"м²","costs_property_comment":"","costs_rent":""}]},"intro":{"declaration_year":"2014","isnotdeclaration":"","declaration_year_unclear":false}}