{"income":{"5":{"family_comment":"","value":"222966","family":"50412","comment":""},"6":{"family_comment":"","value":"210349","family_hidden":false,"comment":"","family":"50412"},"7":{"family_comment":"","value":"","source_name":"","family":"","comment":""},"8":{"family_comment":"","value":"","family":"","comment":""},"9":{"value":"","value_unclear":false,"family_hidden":false,"family_comment":"","family":"","comment":""},"10":{"value":"12617","family_comment":"","family_hidden":false,"value_hidden":false,"family_unclear":false,"family":"","comment":""},"11":{"family_comment":"","value":"","family":"","comment":""},"12":{"family_comment":"","value":"","family":"","comment":""},"13":{"family_comment":"","value":"","family":"","comment":""},"14":{"family_comment":"","value":"","family":"","comment":""},"15":{"family_comment":"","value":"","family":"","comment":""},"16":{"family_comment":"","value":"","family":"","comment":""},"17":{"family_comment":"","value":"","family":"","comment":""},"18":{"family_comment":"","value":"","family":"","comment":""},"19":{"family_comment":"","value":"","family":"","comment":""},"20":{"value":"","comment_unclear":false,"family_comment":"","family":"","comment":"","family_comment_unclear":false}},"vehicle":{"40":[{"brand_info":"2.5 л","sum_rent_comment":"","brand":"Subaru Outback","sum_comment":"","year":"2008","brand_info_unclear":false,"sum":"","sum_rent":""},{"brand_info":"2.7 л","sum_rent_comment":"","brand":"Toyota Land Cruiser Prado","sum_comment":"","brand_unclear":false,"year":"2007","sum":"","sum_rent":""}]},"id":"vulyk_75_135","banks":{"45":[{"sum_foreign_comment":"","sum_units":"UAH","sum_comment":"","sum_comment_unclear":false,"sum_foreign_units":"UAH","sum":"13600","sum_unclear":false,"sum_foreign":""}],"51":[{"sum_foreign_comment":"","sum_units":"UAH","sum_comment":"","sum_foreign_units":"UAH","sum":"40000","sum_foreign":""}]},"declaration":{"additional_info_text":"","notfull_lostpages":"","date":"2014-03-19T00:00:00","notfull":"","additional_info":"","url":"http://static.declarations.com.ua/declarations/chosen_ones/judges_batch/1800_pylypenko_olena_ievheniivna.pdf"},"liabilities":{"54":{"sum_foreign_comment":"","sum":"","sum_comment":"","sum_foreign":""},"55":{"sum_foreign_comment":"","sum":"","sum_comment":"","sum_foreign":""},"56":{"sum_foreign_comment":"","sum":"","sum_comment":"","sum_foreign":""},"57":{"sum_foreign_comment":"","sum":"","sum_comment":"","sum_foreign":""},"58":{"sum_foreign_comment":"","sum":"","sum_comment":"","sum_foreign":""},"59":{"sum_foreign_comment":"","sum":"","sum_comment":"","sum_comment_unclear":false,"sum_unclear":false,"sum_foreign":""},"60":{"sum_foreign_comment":"","sum":"","sum_comment":"","sum_foreign":""},"61":{"sum_foreign_comment":"","sum":"","sum_comment":"","sum_foreign":""},"62":{"sum_foreign_comment":"","sum":"36848","sum_comment":"","sum_unclear":true,"sum_foreign":""},"63":{"sum_foreign_comment":"","sum":"","sum_comment":"","sum_foreign":""},"64":{"sum_foreign_comment":"","sum":"","sum_comment":"","sum_foreign":""}},"ft_src":"36848\nПилипенко Олена Євгеніївна\nсуддя київського апеляційного адміністративного суду\nм. Київ\nАпеляційний адміністративний суд\nОлена\nПилипенко С. А\nПодружжя\nПилипенко Олена Євгеніївна\nОлена Євгеніївна Пилипенко\nОлена Пилипенко\nПилипенко Олена Євгеніївна\nПилипенко\nЄвгеніївна\n2.5 л\n2008\nSubaru Outback\n2007\n2.7 л\nToyota Land Cruiser Prado\n40000\n13600\n2013\n2.5 л\n2008\nSubaru Outback\n2.7 л\nToyota Land Cruiser Prado\n2007\n13600\n40000\n2013\nПилипенко\nЄвгеніївна\nПодружжя\nПилипенко С. А\nПилипенко Олена Євгеніївна\nОлена Євгеніївна Пилипенко\nОлена Пилипенко\nПилипенко Олена Євгеніївна\nОлена\nПилипенко Олена Євгеніївна\nАпеляційний адміністративний суд\nсуддя київського апеляційного адміністративного суду\nм. Київ\n36848\n210349\n50412\n222966\n50412\n12617\n54\n276.8\n138\n17.7\n.2094\n36848\n54\n138\n276.8\n17.7\n.2094\nПилипенко С. А\nПодружжя\nПилипенко\nЄвгеніївна\nсуддя київського апеляційного адміністративного суду\nм. Київ\nАпеляційний адміністративний суд\nПилипенко Олена Євгеніївна\nПилипенко Олена Євгеніївна\nОлена Євгеніївна Пилипенко\nОлена Пилипенко\nПилипенко Олена Євгеніївна\nОлена\n50412\n210349\n12617\n50412\n222966\n2008\n2.5 л\nSubaru Outback\n2007\n2.7 л\nToyota Land Cruiser Prado\n12617\n50412\n222966\n50412\n210349\n138\n276.8\n54\n17.7\n.2094\n13600\n40000\n2013","general":{"inn":"","inn_hidden":true,"last_name":"Пилипенко","post":{"office":"Апеляційний адміністративний суд","region":"м. Київ","post":"суддя київського апеляційного адміністративного суду"},"name":"Олена","full_name":"Пилипенко Олена Євгеніївна","family_raw":"","addresses":[{"place_district":"","place_address_hidden":true,"place_city":"","place_city_type_hidden":true,"place_district_hidden":true,"place_city_type":"","place_city_hidden":true,"place_address":"","place_hidden":true,"place":""}],"family":[{"inn":"","inn_hidden":true,"relations_hidden":false,"family_name":"Пилипенко С. А","relations_other":"","relations":"Подружжя","name_hidden":true,"name_unclear":false}],"full_name_suggest":{"output":"Пилипенко Олена Євгеніївна","input":["Пилипенко Олена Євгеніївна","Олена Євгеніївна Пилипенко","Олена Пилипенко"]},"patronymic":"Євгеніївна"},"source":"VULYK","estate":{"29":[{"space_units_unclear":false,"address_hidden":false,"region_hidden":true,"space_comment":"","space":".2094","address":"","region":"","costs_property":"","costs_rent_comment":"","space_units":"га","costs_property_comment":"","costs_rent":""}],"30":[{"costs_rent":"","region":"","costs_property":"","costs_rent_comment":"","region_hidden":true,"space_comment":"","costs_property_comment":"","space_units":"м²","space":"276.8","address":""}],"31":[{"space_unclear":false,"address_hidden":false,"region_hidden":true,"space_comment":"","space":"138","address":"","region":"","costs_property":"","costs_rent_comment":"","space_units":"м²","costs_property_comment":"","costs_rent":""}],"33":[{"costs_rent":"","region":"","costs_property":"","costs_rent_comment":"","region_hidden":true,"space_comment":"","costs_property_comment":"","space_units":"м²","space":"54","address":""}],"34":[{"costs_rent":"","region":"","costs_property":"","costs_rent_comment":"","address_hidden":false,"region_hidden":true,"space_comment":"","costs_property_comment":"","space_units":"м²","space":"17.7","address":""}]},"intro":{"declaration_year":"2013","isnotdeclaration":""}}