{"income":{"5":{"family_comment":"","value":"294681.41","family":"","comment":""},"6":{"family_comment":"","value":"282764.31","family":"","comment":""},"7":{"value":"","comment_hidden":false,"value_hidden":false,"family_comment":"","source_name":"","family":"","comment":"","source_name_hidden":false},"8":{"family_comment":"","value":"","family":"","comment":""},"9":{"value":"","comment_hidden":false,"family_comment":"","family":"","comment":"","family_comment_unclear":false},"10":{"family_comment":"","value":"","family":"","comment":""},"11":{"family_comment":"","value":"","comment_hidden":false,"family":"","comment":""},"12":{"family_comment":"","value":"","family":"","comment":""},"13":{"family_comment":"","value":"","family":"","comment":""},"14":{"family_comment":"","value":"","family":"","comment":""},"15":{"family_comment":"","value":"","family":"","comment":""},"16":{"family_comment":"","value":"","family":"","comment":""},"17":{"family_comment":"","value":"","family":"","comment":""},"18":{"family_comment":"","value":"","family":"","comment":""},"19":{"family_comment":"","value":"","family":"","comment":""},"20":{"family_comment":"","value":"11917.1","comment_hidden":false,"family":"","comment":"пенсія"}},"vehicle":{"35":[{"brand_info":"3.0 , об'єм двигуна 2995","sum_rent_comment":"","brand":"Toyota Camry","sum_comment":"","year":"2006","brand_info_unclear":false,"year_unclear":false,"sum":"","sum_rent":""}]},"id":"vulyk_102_59","banks":{"45":[{"sum_foreign_comment":"","sum_units":"UAH","sum_comment":"зарплатна картка","sum_comment_unclear":false,"sum_hidden":false,"sum_foreign_units":"UAH","sum_comment_hidden":true,"sum_unclear":false,"sum":"19317.8","sum_foreign":""},{"sum_foreign_comment":"","sum_units":"UAH","sum_comment":"пенсійна картка","sum_comment_unclear":false,"sum_hidden":false,"sum_comment_hidden":false,"sum_unclear":false,"sum":"158.84","sum_foreign":""}]},"declaration":{"date":"2016-03-25T00:00:00","additional_info_text":"","additional_info":"","url":"http://static.declarations.com.ua/declarations/chosen_ones/judges_batch/1133_iemelianova_valentyna_ivanivna.pdf"},"liabilities":{"54":{"sum_foreign_comment":"","sum":"","sum_comment":"","sum_hidden":false,"sum_comment_hidden":false,"sum_foreign":""},"55":{"sum_foreign_comment":"","sum":"","sum_comment":"","sum_foreign":""},"56":{"sum_foreign_comment":"","sum":"","sum_comment":"","sum_foreign":""},"57":{"sum_foreign_comment":"","sum_comment_hidden":true,"sum":"80000","sum_comment":"","sum_foreign":""},"58":{"sum_foreign_comment":"","sum_comment_hidden":false,"sum":"","sum_comment":"","sum_foreign":""},"59":{"sum_foreign_comment":"","sum_comment_hidden":false,"sum":"","sum_comment":"","sum_foreign":""},"60":{"sum_foreign_comment":"","sum":"","sum_comment":"","sum_hidden":false,"sum_comment_hidden":false,"sum_foreign":""},"61":{"sum_foreign_comment":"","sum":"","sum_comment":"","sum_foreign":""},"62":{"sum_foreign_comment":"","sum":"","sum_comment":"","sum_unclear":false,"sum_foreign":""},"63":{"sum_foreign_comment":"","sum":"","sum_comment":"","sum_hidden":false,"sum_comment_hidden":false,"sum_foreign":""},"64":{"sum_foreign_comment":"","sum_comment_hidden":false,"sum":"","sum_comment":"","sum_foreign":""}},"ft_src":"80000\nЄмельянова Валентина Іванівна\nІванівна\nЄмельянова Валентина Іванівна\nВалентина Іванівна Ємельянова\nВалентина Ємельянова\nЄмельянова Валентина Іванівна\nВалентина\nсуддя вищого адміністративного суду україни\nЗагальнодержавний регіон\nВищий адміністративний суд\nЄмельянова\n2006\n3.0 , об'єм двигуна 2995\nToyota Camry\nоренда паркомісця\n1/2 квартири\n33.5\n89.4\nкористування\n55\nзарплатна картка\n19317.8\nпенсійна картка\n158.84\n2015\n3.0 , об'єм двигуна 2995\nToyota Camry\n2006\n2015\nЄмельянова Валентина Іванівна\nВалентина Іванівна Ємельянова\nВалентина Ємельянова\nЄмельянова Валентина Іванівна\nВалентина\nІванівна\nЄмельянова Валентина Іванівна\nЄмельянова\nсуддя вищого адміністративного суду україни\nЗагальнодержавний регіон\nВищий адміністративний суд\n80000\n282764.31\nпенсія\n11917.1\n294681.41\nоренда паркомісця\n33.5\n1/2 квартири\n89.4\nкористування\n55\n19317.8\nзарплатна картка\nпенсійна картка\n158.84\n80000\n282764.31\n294681.41\nпенсія\n11917.1\nІванівна\nЄмельянова\nсуддя вищого адміністративного суду україни\nЗагальнодержавний регіон\nВищий адміністративний суд\nЄмельянова Валентина Іванівна\nЄмельянова Валентина Іванівна\nВалентина Іванівна Ємельянова\nВалентина Ємельянова\nЄмельянова Валентина Іванівна\nВалентина\n2006\n3.0 , об'єм двигуна 2995\nToyota Camry\nпенсія\n11917.1\n294681.41\n282764.31\n1/2 квартири\n33.5\n89.4\n55\nкористування\nоренда паркомісця\nзарплатна картка\n19317.8\nпенсійна картка\n158.84\n2015","general":{"inn":"","inn_hidden":true,"last_name":"Ємельянова","post":{"region":"Загальнодержавний регіон","region_unclear":false,"post":"суддя вищого адміністративного суду україни","office_unclear":false,"office":"Вищий адміністративний суд"},"name":"Валентина","full_name":"Ємельянова Валентина Іванівна","family_raw":"","addresses":[{"place_district":"","place_city_hidden":true,"place_city":"","place_city_type_hidden":true,"place_district_hidden":true,"place_city_type":"","place_address_hidden":true,"place_address":"","place_hidden":true,"place":""}],"patronymic_hidden":false,"full_name_suggest":{"output":"Ємельянова Валентина Іванівна","input":["Ємельянова Валентина Іванівна","Валентина Іванівна Ємельянова","Валентина Ємельянова"]},"patronymic":"Іванівна"},"source":"VULYK","estate":{"25":[{"costs":"","costs_comment":"","address_hidden":true,"region_hidden":true,"space_comment":"1/2 квартири","space":"33.5","address":"","region":"","address_unclear":false,"costs_rent_comment":"","space_units":"м²","costs_rent":""},{"costs_rent":"","region":"","costs":"","costs_rent_comment":"","costs_comment":"","region_hidden":false,"space_comment":"","space_units":"м²","space":"89.4","address":""},{"costs_rent":"","region":"","costs":"","costs_rent_comment":"користування","costs_comment":"","space_comment":"","space_units":"м²","space":"55","address":""}],"34":[{"address_hidden":true,"region_hidden":true,"space_comment":"","space":"","address":"оренда паркомісця","region":"","costs_property":"","costs_rent_comment":"","address_unclear":false,"space_units":"м²","costs_property_comment":"","costs_rent":""}]},"intro":{"declaration_year":"2015"}}