{"income":{"5":{"value":"201289","family_comment":"","value_unclear":false,"family_unclear":false,"family":"","comment":""},"6":{"family_comment":"","value":"185280","value_unclear":false,"family":"","comment":""},"7":{"value":"","value_unclear":false,"family_comment":"","source_name":"","family":"","comment":""},"8":{"family_comment":"","value":"","family":"","comment":""},"9":{"value":"15259","family_comment":"","value_unclear":false,"family_unclear":false,"family":"","comment":""},"10":{"family_comment":"","value":"","comment_unclear":false,"family":"","comment":""},"11":{"family_comment":"","value":"","family":"","comment":""},"12":{"family_comment":"","value":"","family":"","comment":""},"13":{"family_comment":"","value":"","value_unclear":false,"family":"","comment":""},"14":{"family_comment":"","value":"","family":"","comment":""},"15":{"family_comment":"","value":"750","family":"","comment":""},"16":{"family_comment":"","family_unclear":false,"value":"","family":"","comment":""},"17":{"family_comment":"","family_unclear":false,"value":"","family":"","comment":""},"18":{"family_comment":"","value":"","family":"","comment":""},"19":{"family_comment":"","value":"","family":"","comment":""},"20":{"value":"","family_comment":"","value_unclear":false,"family_hidden":false,"value_hidden":false,"family_unclear":false,"comment_unclear":false,"comment":"","family":""}},"id":"vulyk_100_80","banks":{"45":[{"sum_foreign_comment":"","sum_units":"UAH","sum_comment":"Приватбанк","sum_comment_unclear":false,"sum_foreign_units":"UAH","sum_units_unclear":false,"sum_comment_hidden":false,"sum_unclear":false,"sum":"10979","sum_foreign":""}],"46":[{"sum_foreign_comment":"","sum_units":"UAH","sum_comment":"","sum_comment_unclear":false,"sum_foreign_units":"UAH","sum":"10051","sum_unclear":false,"sum_foreign":""}]},"declaration":{"additional_info_text":"","notfull_lostpages":"","date":"2015-03-31T00:00:00","notfull":"","additional_info":"","url":"http://static.declarations.com.ua/declarations/chosen_ones/judges_batch/4280_burka_svitlana_volodymyrivna.pdf"},"liabilities":{"54":{"sum_foreign_comment":"","sum":"120","sum_comment":"","sum_comment_hidden":false,"sum_unclear":false,"sum_foreign":""},"55":{"sum_foreign_comment":"","sum":"","sum_comment":"","sum_foreign":""},"56":{"sum_foreign_comment":"","sum":"","sum_comment":"","sum_unclear":false,"sum_foreign":""},"57":{"sum_foreign_comment":"","sum":"","sum_comment":"","sum_comment_unclear":false,"sum_comment_hidden":false,"sum_unclear":false,"sum_foreign":""},"58":{"sum_foreign_comment":"","sum":"","sum_comment":"","sum_comment_hidden":false,"sum_unclear":false,"sum_foreign":""},"59":{"sum_foreign_comment":"","sum":"","sum_comment":"","sum_foreign":""},"60":{"sum_foreign_comment":"","sum_comment_hidden":false,"sum":"","sum_comment":"","sum_foreign":""},"61":{"sum_foreign_comment":"","sum":"","sum_comment":"","sum_foreign":""},"62":{"sum_foreign_comment":"","sum":"","sum_comment":"","sum_unclear":false,"sum_foreign":""},"63":{"sum_foreign_comment":"","sum_comment_hidden":false,"sum":"","sum_comment":"","sum_foreign":""},"64":{"sum_foreign_comment":"","sum_comment_hidden":false,"sum":"","sum_comment":"","sum_foreign":""}},"ft_src":"120\nВолодимирівна\nБурка Світлана Володимирівна\nсуддя хмельницького міськрайонного суду хмельницької області\nХмельницька область\nЗагальний місцевий суд\nСвітлана\nБурка Світлана Володимирівна\nСвітлана Володимирівна Бурка\nСвітлана Бурка\nБурка Світлана Володимирівна\nБурка\n750\n201289\n15259\n185280\n10051\nПриватбанк\n10979\n1/4 від 51,2 кв. м\n51.2\n2014\n185280\n750\n201289\n15259\nПриватбанк\n10979\n10051\n51.2\n1/4 від 51,2 кв. м\nЗагальний місцевий суд\nХмельницька область\nсуддя хмельницького міськрайонного суду хмельницької області\nВолодимирівна\nБурка Світлана Володимирівна\nСвітлана Володимирівна Бурка\nСвітлана Бурка\nБурка Світлана Володимирівна\nБурка Світлана Володимирівна\nСвітлана\nБурка\n120\n185280\n750\n201289\n15259\n2014\n120\nВолодимирівна\nБурка\nХмельницька область\nЗагальний місцевий суд\nсуддя хмельницького міськрайонного суду хмельницької області\nБурка Світлана Володимирівна\nБурка Світлана Володимирівна\nСвітлана Володимирівна Бурка\nСвітлана Бурка\nБурка Світлана Володимирівна\nСвітлана\n1/4 від 51,2 кв. м\n51.2\nПриватбанк\n10979\n10051\n2014","general":{"inn":"","inn_hidden":true,"last_name":"Бурка","post":{"post_unclear":false,"region_unclear":false,"post":"суддя хмельницького міськрайонного суду хмельницької області","office":"Загальний місцевий суд","region":"Хмельницька область","post_hidden":false,"office_unclear":false},"name":"Світлана","full_name":"Бурка Світлана Володимирівна","family_raw":"","addresses":[{"place_district":"","place_city_hidden":true,"place_city":"","place_city_unclear":false,"place_district_hidden":false,"place_city_type":"","place_address_hidden":true,"place_city_type_hidden":false,"place_address":"","place_hidden":true,"place":""}],"full_name_suggest":{"output":"Бурка Світлана Володимирівна","input":["Бурка Світлана Володимирівна","Світлана Володимирівна Бурка","Світлана Бурка"]},"patronymic":"Володимирівна"},"source":"VULYK","estate":{"25":[{"space_unclear":false,"costs":"","costs_comment":"","address_hidden":false,"region_hidden":true,"space_comment":"1/4 від 51,2 кв. м","space":"51.2","address":"","costs_comment_unclear":false,"region":"","address_unclear":false,"costs_rent_comment":"","space_comment_unclear":false,"space_units":"м²","costs_rent":""}]},"intro":{"declaration_year":"2014"}}