{"income":{"5":{"value":"217763","family_comment":"","value_unclear":false,"family":"11625","family_unclear":false,"comment_unclear":false,"comment":"","family_comment_unclear":false},"6":{"value":"217763","family_comment":"","value_unclear":false,"family_unclear":false,"family":"11625","comment":""},"7":{"source_name_unclear":false,"value":"","value_unclear":false,"family_comment":"","source_name":"","family":"","comment":"","source_name_hidden":false},"8":{"family_comment":"","value":"","family":"","comment":""},"9":{"family_comment":"","value":"","family":"","comment":""},"10":{"family_comment":"","value":"","value_unclear":false,"family":"","comment":""},"11":{"value":"","value_unclear":false,"value_hidden":false,"family_comment":"","family":"","comment":""},"12":{"family_comment":"","value":"","family":"","comment":"","value_hidden":false},"13":{"family_comment":"","value":"","family":"","comment":""},"14":{"family_comment":"","value":"","family":"","comment":""},"15":{"family_comment":"","value":"","family":"","comment":""},"16":{"family_comment":"","value":"","family":"","comment":""},"17":{"family_comment":"","value":"","family":"","comment":""},"18":{"family_comment":"","value":"","family":"","comment":""},"19":{"family_comment":"","family_unclear":false,"value":"","family":"","comment":""},"20":{"family_comment":"","family_unclear":false,"value":"","family":"","comment":""}},"vehicle":{"40":[{"brand_info":"1498 куб. см.","sum":"","brand":"Chevrolet Aveo","sum_comment":"","brand_unclear":false,"year":"2005","brand_hidden":false,"brand_info_hidden":false,"brand_info_unclear":false,"sum_rent_comment":"","sum_rent":""}]},"id":"vulyk_61_56","declaration":{"additional_info_text":"","notfull_lostpages":"","date":"2015-03-27T00:00:00","notfull":"","additional_info":"","url":"http://static.declarations.com.ua/declarations/chosen_ones/mega_batch/dranikov_serhii_mykhailovych.pdf"},"liabilities":{"54":{"sum_foreign_comment":"","sum":"","sum_comment":"","sum_comment_unclear":false,"sum_unclear":false,"sum_foreign":""},"55":{"sum_foreign_comment":"","sum":"","sum_comment":"","sum_foreign":""},"56":{"sum_foreign_comment":"","sum":"","sum_comment":"","sum_unclear":false,"sum_foreign":""},"57":{"sum_foreign_comment":"","sum":"","sum_comment":"","sum_comment_hidden":false,"sum_unclear":false,"sum_foreign":""},"58":{"sum_foreign_comment":"","sum":"","sum_comment":"","sum_unclear":false,"sum_foreign":""},"59":{"sum_foreign_comment":"","sum":"","sum_comment":"","sum_foreign":""},"60":{"sum_foreign_comment":"","sum_foreign_hidden":false,"sum_comment":"","sum_hidden":false,"sum":"","sum_foreign":""},"61":{"sum_foreign_comment":"","sum":"","sum_comment":"","sum_foreign":""},"62":{"sum_foreign_comment":"","sum":"","sum_comment":"","sum_unclear":false,"sum_foreign":""},"63":{"sum_foreign_comment":"","sum":"","sum_comment":"","sum_hidden":false,"sum_unclear":false,"sum_foreign":""},"64":{"sum_foreign_comment":"","sum":"","sum_hidden":false,"sum_comment":"","sum_foreign":""}},"ft_src":"суддя біляївського районного суду одеської області\nОдеська область\nЗагальний місцевий суд\nСергій\nДружина\nПодружжя\nДонька\nДитина\nСин\nДитина\nМихайлович\nДраніков\nДраніков Сергій Михайлович\nДраніков Сергій Михайлович\nСергій Михайлович Драніков\nСергій Драніков\nДраніков Сергій Михайлович\nChevrolet Aveo\n1498 куб. см.\n2005\n62.2\n34.78\n33.1\n2014\n11625\n217763\n11625\n217763\n1498 куб. см.\n2005\nChevrolet Aveo\n62.2\n34.78\n33.1\nПодружжя\nДружина\nДитина\nДонька\nДитина\nСин\nДраніков Сергій Михайлович\nСергій Михайлович Драніков\nСергій Драніков\nДраніков Сергій Михайлович\nСергій\nДраніков Сергій Михайлович\nДраніков\nОдеська область\nЗагальний місцевий суд\nсуддя біляївського районного суду одеської області\nМихайлович\n11625\n217763\n217763\n11625\n2014\nДружина\nПодружжя\nДонька\nДитина\nСин\nДитина\nМихайлович\nДраніков\nДраніков Сергій Михайлович\nСергій Михайлович Драніков\nСергій Драніков\nДраніков Сергій Михайлович\nОдеська область\nсуддя біляївського районного суду одеської області\nЗагальний місцевий суд\nДраніков Сергій Михайлович\nСергій\nChevrolet Aveo\n1498 куб. см.\n2005\n217763\n11625\n217763\n11625\n62.2\n34.78\n33.1\n2014","general":{"inn":"","name":"Сергій","patronymic_unclear":false,"family":[{"inn":"","inn_hidden":true,"relations_unclear":false,"relations_hidden":false,"relations_other":"","relations":"Подружжя","name_hidden":true,"family_name":"Дружина","name_unclear":false},{"inn":"","relations":"Дитина","relations_other":"","inn_hidden":false,"family_name":"Донька","name_hidden":false,"name_unclear":false},{"inn":"","relations":"Дитина","relations_other":"","inn_hidden":false,"family_name":"Син","name_hidden":false,"name_unclear":false}],"patronymic":"Михайлович","inn_hidden":true,"family_raw":"","inn_unclear":false,"post":{"post_unclear":false,"region_unclear":false,"post":"суддя біляївського районного суду одеської області","office":"Загальний місцевий суд","region":"Одеська область","post_hidden":false,"office_hidden":false,"region_hidden":false},"last_name_unclear":false,"full_name":"Драніков Сергій Михайлович","addresses":[{"place_address":"","place_district_hidden":true,"place_city_type":"","place_city_hidden":true,"place_address_unclear":false,"place_city_type_hidden":true,"place_hidden":true,"place":"","place_district":"","place_address_hidden":true,"place_city":"","place_district_unclear":false}],"last_name":"Драніков","patronymic_hidden":false,"full_name_suggest":{"output":"Драніков Сергій Михайлович","input":["Драніков Сергій Михайлович","Сергій Михайлович Драніков","Сергій Драніков"]},"name_unclear":false},"source":"VULYK","estate":{"31":[{"space_unclear":false,"address_hidden":true,"region_hidden":true,"space_comment":"","space_hidden":false,"space":"62.2","address":"","region":"","costs_property":"","costs_rent_comment":"","space_comment_unclear":false,"space_units":"м²","costs_property_comment":"","costs_rent":""},{"costs_rent":"","region":"","costs_property":"","costs_rent_comment":"","address_hidden":false,"region_hidden":false,"space_comment":"","costs_property_comment":"","space_units":"м²","space":"34.78","address":""},{"costs_rent":"","costs_property":"","costs_rent_comment":"","space_comment":"","costs_property_comment":"","space_units":"м²","space":"33.1","address":""}]},"intro":{"declaration_year":"2014","isnotdeclaration":"","declaration_year_hidden":false}}