{"income":{"5":{"family_comment":"","family_unclear":false,"value":"211864","family":"28877","comment":""},"6":{"family_comment":"","family_unclear":false,"value":"211864","family":"28877","comment":""},"7":{"value":"","comment_hidden":false,"family_comment":"","source_name":"","family":"","comment":""},"8":{"family_comment":"","value":"","family":"","comment":""},"9":{"family_comment":"","value":"","family":"","comment":""},"10":{"family_comment":"","value":"","family":"","comment":""},"11":{"family_comment":"","value":"","value_unclear":false,"family":"","comment":""},"12":{"family_comment":"","value":"","family":"","comment":""},"13":{"family_comment":"","value":"","family":"","comment":""},"14":{"family_comment":"","value":"","family":"","comment":""},"15":{"family_comment":"","value":"","value_unclear":false,"family":"","comment":""},"16":{"family_comment":"","family_unclear":false,"value":"","family":"","comment":""},"17":{"family_comment":"","value":"","family":"","comment":""},"18":{"family_comment":"","value":"","family_hidden":false,"comment":"","family":""},"19":{"family_comment":"","value":"","family":"","comment":""},"20":{"value":"","comment_unclear":false,"comment_hidden":false,"family_comment":"","family":"","comment":"","family_comment_hidden":false}},"vehicle":{"35":[{"brand_info":"1497","sum_rent_comment":"","year":"2011","brand_info_hidden":false,"brand_info_unclear":false,"year_unclear":false,"sum_rent":"","sum":"","brand":"ЗАЗ Forza","sum_comment":"","brand_unclear":false,"brand_hidden":false}],"40":[{"brand_info":"1497","sum_rent_comment":"","brand":"ЗАЗ Forza","sum_comment":"","year":"2011","brand_hidden":false,"brand_info_hidden":false,"brand_info_unclear":false,"year_unclear":false,"sum":"","sum_rent":""}]},"id":"vulyk_68_47","declaration":{"additional_info_text":"","notfull_lostpages":"","date":"2015-03-30T00:00:00","notfull":"","additional_info":"","url":"http://static.declarations.com.ua/declarations/chosen_ones/mega_batch/tustanovskyi_andrii_oleksandrovych.pdf"},"liabilities":{"54":{"sum_foreign_comment":"","sum":"4000","sum_comment":"","sum_comment_unclear":true,"sum_hidden":false,"sum_comment_hidden":false,"sum_unclear":false,"sum_foreign":""},"55":{"sum_foreign_comment":"","sum":"","sum_hidden":false,"sum_comment":"","sum_foreign":""},"56":{"sum_foreign_comment":"","sum_foreign_hidden":false,"sum_comment":"","sum":"","sum_unclear":false,"sum_foreign":""},"57":{"sum_foreign_comment":"","sum":"22725","sum_comment":"","sum_comment_unclear":true,"sum_hidden":false,"sum_comment_hidden":false,"sum_unclear":false,"sum_foreign":""},"58":{"sum_foreign_comment":"","sum":"15935","sum_comment":"","sum_hidden":false,"sum_comment_hidden":false,"sum_unclear":false,"sum_foreign":""},"59":{"sum_foreign_comment":"","sum":"","sum_comment":"","sum_foreign":""},"60":{"sum_foreign_comment":"","sum":"","sum_comment":"","sum_comment_unclear":false,"sum_hidden":false,"sum_comment_hidden":false,"sum_unclear":false,"sum_foreign":""},"61":{"sum_foreign_comment":"","sum":"","sum_hidden":false,"sum_comment":"","sum_foreign":""},"62":{"sum_foreign_comment":"","sum":"","sum_comment":"","sum_unclear":false,"sum_foreign":""},"63":{"sum_foreign_comment":"","sum":"1762","sum_comment":"","sum_hidden":false,"sum_comment_hidden":false,"sum_unclear":false,"sum_foreign":""},"64":{"sum_foreign_comment":"","sum":"6006","sum_comment":"","sum_hidden":false,"sum_comment_hidden":false,"sum_foreign":""}},"ft_src":"22725\n4000\n6006\n15935\n1762\nзаступник голови веселинівського районного суду миколаївської області\nМиколаївська область\nЗагальний місцевий суд\nАндрій\n2922450076\nТустановська Ілона Вікторівна\nПодружжя\nТустановський Денис Андрійович\nДитина\nТустановський Олександр Андрійович\nДитина\nОлександрович\nТустановський Андрій Олександрович\nАндрій Олександрович Тустановський\nАндрій Тустановський\nТустановський Андрій Олександрович\nТустановський Андрій Олександрович\nТустановський\n1497\nЗАЗ Forza\n2011\n1497\nЗАЗ Forza\n2011\n959\nсмт Веселинове, вул. Пирогова, 33\nМиколаївська область\nсмт Веселинове, вул. Пирогова, 33\nМиколаївська область\n187.6\nМиколаївська область\nсмт Веселинове, вул. Пирогова, 33\n952\nсмт Веселинове, вул. Пирогова, 33\nМиколаївська область\n187.6\n2014\n28877\n211864\n28877\n211864\n1497\nЗАЗ Forza\n2011\n1497\n2011\nЗАЗ Forza\n959\nМиколаївська область\nсмт Веселинове, вул. Пирогова, 33\nсмт Веселинове, вул. Пирогова, 33\nМиколаївська область\n952\n187.6\nсмт Веселинове, вул. Пирогова, 33\nМиколаївська область\n187.6\nсмт Веселинове, вул. Пирогова, 33\nМиколаївська область\nПодружжя\nТустановська Ілона Вікторівна\n2922450076\nДитина\nТустановський Денис Андрійович\nДитина\nТустановський Олександр Андрійович\nТустановський Андрій Олександрович\nАндрій Олександрович Тустановський\nАндрій Тустановський\nТустановський Андрій Олександрович\nТустановський Андрій Олександрович\nАндрій\nОлександрович\nЗагальний місцевий суд\nМиколаївська область\nзаступник голови веселинівського районного суду миколаївської області\nТустановський\n1762\n6006\n22725\n15935\n4000\n211864\n28877\n211864\n28877\n2014\n15935\n22725\n6006\n4000\n1762\n2922450076\nПодружжя\nТустановська Ілона Вікторівна\nТустановський Денис Андрійович\nДитина\nТустановський Олександр Андрійович\nДитина\nОлександрович\nТустановський\nАндрій\nТустановський Андрій Олександрович\nАндрій Олександрович Тустановський\nАндрій Тустановський\nТустановський Андрій Олександрович\nМиколаївська область\nЗагальний місцевий суд\nзаступник голови веселинівського районного суду миколаївської області\nТустановський Андрій Олександрович\n2011\nЗАЗ Forza\n1497\nЗАЗ Forza\n1497\n2011\n28877\n211864\n28877\n211864\nсмт Веселинове, вул. Пирогова, 33\nМиколаївська область\n187.6\nсмт Веселинове, вул. Пирогова, 33\nМиколаївська область\n959\nсмт Веселинове, вул. Пирогова, 33\nМиколаївська область\n187.6\nсмт Веселинове, вул. Пирогова, 33\nМиколаївська область\n952\n2014","general":{"inn":"","name":"Андрій","inn_unclear":false,"family":[{"inn":"2922450076","inn_hidden":false,"relations_unclear":false,"relations_hidden":false,"relations_other":"","relations":"Подружжя","name_hidden":false,"inn_unclear":false,"family_name":"Тустановська Ілона Вікторівна","name_unclear":true},{"inn":"","inn_hidden":false,"inn_unclear":false,"relations_hidden":false,"relations_other":"","relations":"Дитина","name_hidden":false,"family_name":"Тустановський Денис Андрійович","name_unclear":true},{"inn":"","relations":"Дитина","relations_other":"","inn_hidden":false,"family_name":"Тустановський Олександр Андрійович","name_hidden":false,"name_unclear":false}],"inn_hidden":true,"family_raw":"","last_name":"Тустановський","post":{"post_unclear":false,"region_unclear":false,"post":"заступник голови веселинівського районного суду миколаївської області","office":"Загальний місцевий суд","region":"Миколаївська область","post_hidden":false,"office_hidden":false,"office_unclear":false,"region_hidden":false},"full_name_suggest":{"output":"Тустановський Андрій Олександрович","input":["Тустановський Андрій Олександрович","Андрій Олександрович Тустановський","Андрій Тустановський"]},"full_name":"Тустановський Андрій Олександрович","addresses":[{"place_city_type_hidden":true,"place_district_hidden":true,"place_city_type":"","place_city_hidden":true,"place_address_unclear":false,"place_address":"","place_hidden":true,"place":"","place_district":"","place_unclear":false,"place_city":"","place_address_hidden":true}],"patronymic":"Олександрович","last_name_unclear":false,"name_unclear":false},"source":"VULYK","estate":{"23":[{"costs":"","costs_comment":"","address_hidden":false,"region_hidden":false,"space_comment":"","space":"959","address":"смт Веселинове, вул. Пирогова, 33","region":"Миколаївська область","costs_rent_comment":"","space_comment_hidden":false,"space_units":"м²","costs_rent":""}],"24":[{"region_unclear":false,"space_unclear":false,"costs":"","costs_comment":"","address_hidden":false,"region_hidden":false,"space_comment":"","space":"187.6","address":"смт Веселинове, вул. Пирогова, 33","region":"Миколаївська область","costs_rent_comment":"","space_units":"м²","costs_rent":""}],"29":[{"space_unclear":false,"address_hidden":false,"region_hidden":false,"space_comment":"","space_units_hidden":false,"space_hidden":false,"space":"952","address":"смт Веселинове, вул. Пирогова, 33","region":"Миколаївська область","costs_property":"","space_units_unclear":false,"space_units":"м²","costs_property_comment":"","costs_rent":"","costs_rent_comment":""}],"30":[{"space_unclear":false,"address_hidden":false,"region_hidden":false,"space_comment":"","space_hidden":false,"space":"187.6","address":"смт Веселинове, вул. Пирогова, 33","region":"Миколаївська область","costs_property":"","costs_rent_comment":"","space_units":"м²","costs_property_comment":"","costs_rent":""}]},"intro":{"declaration_year":"2014","isnotdeclaration":""}}