{"id":"vulyk_99_74","ft_src":"7/18\n26.6\n60.5\n2015\n11145\n171290\n19679\n171323\n33\n8534\n171290\n11145\n8534\n33\n171323\n19679\nВергелес\nВергелес Андрій Валерійович\nАндрій Валерійович Вергелес\nАндрій Вергелес\nВергелес Андрій Валерійович\nАндрій\nВалерійович\nВергелес Андрій Валерійович\nАдміністративний місцевий суд\nсуддя вінницького окружного адміністративного суду\nВінницька область\nПодружжя\nВергелес Ю. В\nІнше\nДонька дружини\nУшакова А. М\n6118\n2158\n17949\n15118\n11984\n26.6\n7/18\n60.5\n2015\n6118\n15118\n2158\n17949\n11984\nВергелес Ю. В\nПодружжя\nДонька дружини\nУшакова А. М\nІнше\nВалерійович\nВергелес\nсуддя вінницького окружного адміністративного суду\nВінницька область\nАдміністративний місцевий суд\nВергелес Андрій Валерійович\nВергелес Андрій Валерійович\nАндрій Валерійович Вергелес\nАндрій Вергелес\nВергелес Андрій Валерійович\nАндрій","estate":{"25":[{"address":"","space_units":"м²","space_hidden":false,"space_unclear":false,"region_hidden":true,"costs_comment":"","space_comment":"","address_hidden":false,"space":"60.5","costs_rent_comment":"","costs":"","region":"","costs_rent":""}],"31":[{"costs_property_comment":"","address":"","space_units":"м²","costs_rent_comment":"","space":"26.6","region":"","region_hidden":true,"costs_property":"","space_comment":"7/18","address_hidden":false,"costs_rent":""}]},"source":"VULYK","income":{"5":{"family_comment":"","family":"19679","comment":"","value_unclear":false,"family_unclear":false,"value":"171323"},"6":{"family_comment":"","family":"11145","comment":"","value_unclear":false,"family_unclear":false,"value":"171290"},"7":{"family":"","family_comment":"","value":"","comment":"","source_name":""},"8":{"family_comment":"","value":"","family":"","comment":""},"9":{"family_comment":"","value":"","family":"","comment":""},"10":{"family_comment":"","value":"","family":"","comment":""},"11":{"family_comment":"","value":"","family":"","comment":""},"12":{"family_comment":"","value":"","family":"8534","comment":""},"13":{"family_comment":"","value":"","family":"","comment":""},"14":{"family_comment":"","value":"","family":"","comment":""},"15":{"family_comment":"","value":"","family":"","comment":"","value_unclear":false},"16":{"family_comment":"","value":"","family":"","comment":""},"17":{"family_comment":"","value":"","family":"","comment":""},"18":{"family_comment":"","value":"","family":"","comment":""},"19":{"family_comment":"","value":"","family":"","comment":""},"20":{"family_comment":"","family":"","comment":"","value_unclear":false,"family_unclear":false,"value":"33","family_comment_unclear":false}},"general":{"inn":"","addresses":[{"place_city_type_hidden":false,"place_city_type":"","place_city_hidden":true,"place_hidden":true,"place_district":"","place_district_hidden":false,"place":"","place_address":"","place_address_hidden":true,"place_city":""}],"last_name":"Вергелес","full_name":"Вергелес Андрій Валерійович","family":[{"inn":"","family_name":"Вергелес Ю. В","name_unclear":false,"inn_hidden":true,"name_hidden":true,"relations":"Подружжя"},{"inn":"","family_name":"Ушакова А. М","relations_other":"Донька дружини","name_unclear":false,"inn_hidden":true,"relations":"Інше"}],"patronymic":"Валерійович","inn_hidden":true,"name":"Андрій","post":{"office":"Адміністративний місцевий суд","region":"Вінницька область","post_unclear":false,"post":"суддя вінницького окружного адміністративного суду"},"family_raw":"","full_name_suggest":{"input":["Вергелес Андрій Валерійович","Андрій Валерійович Вергелес","Андрій Вергелес"],"output":"Вергелес Андрій Валерійович"}},"liabilities":{"54":{"sum_comment_unclear":false,"sum_comment":"","sum":"2158","sum_foreign_comment":"","sum_foreign":"","sum_comment_hidden":true},"55":{"sum_comment":"","sum_foreign_comment":"","sum_foreign":"","sum":""},"56":{"sum_comment":"","sum_foreign_comment":"","sum_foreign":"","sum":""},"57":{"sum_comment":"","sum_foreign_comment":"","sum_foreign":"","sum":"15118","sum_comment_hidden":true},"58":{"sum_comment":"","sum_foreign_comment":"","sum_foreign":"","sum":"6118","sum_comment_hidden":true},"59":{"sum_comment":"","sum":"","sum_foreign_comment":"","sum_foreign":"","sum_unclear":false,"sum_comment_hidden":false},"60":{"sum_comment":"","sum_foreign_comment":"","sum_foreign":"","sum":"","sum_comment_hidden":false},"61":{"sum_comment":"","sum_foreign_comment":"","sum_foreign":"","sum":""},"62":{"sum_comment":"","sum_foreign_comment":"","sum_foreign":"","sum":""},"63":{"sum_comment":"","sum_foreign_comment":"","sum_foreign":"","sum":"17949","sum_comment_hidden":true},"64":{"sum_comment":"","sum_foreign_comment":"","sum_foreign":"","sum":"11984","sum_comment_hidden":true}},"declaration":{"notfull_lostpages":"","date":"2016-03-31T00:00:00","notfull":"","url":"http://static.declarations.com.ua/declarations/chosen_ones/judges_batch/623_verheles_andrii_valeriiovych_2015.pdf"},"intro":{"declaration_year":"2015"}}