{"income":{"5":{"family_comment":"","family_unclear":false,"value":"237635.28","family":"274992.2","comment":""},"6":{"family_comment":"","family_unclear":false,"value":"213434.15","family":"262812.2","comment":""},"7":{"value":"","comment_hidden":false,"family_comment":"","source_name":"","family":"","comment":""},"8":{"family_comment":"","value":"","family":"","comment":""},"9":{"family_comment":"","value":"","family":"","comment":""},"10":{"family_comment":"","value":"13398","family":"12180","comment":""},"11":{"family_comment":"","value":"","value_unclear":false,"family":"","comment":""},"12":{"family_comment":"","value":"","family":"","comment":""},"13":{"family_comment":"","value":"","family":"","comment":""},"14":{"family_comment":"","value":"","family":"","comment":""},"15":{"family_comment":"","value":"10803.13","value_unclear":false,"family":"","comment":""},"16":{"family_comment":"","family_unclear":false,"value":"","family":"","comment":""},"17":{"family_comment":"","value":"","family":"","comment":""},"18":{"family_comment":"","value":"","family_hidden":false,"comment":"","family":""},"19":{"family_comment":"","value":"","family":"","comment":""},"20":{"value":"","comment_unclear":false,"comment_hidden":false,"family_comment":"","family":"","comment":"","family_comment_hidden":false}},"vehicle":{"40":[{"brand_info":"об'єм дв. 2.967","sum_rent_comment":"","brand":"Volkswagen Touareg","sum_comment":"","year":"2010","brand_hidden":false,"brand_info_hidden":false,"brand_info_unclear":false,"year_unclear":false,"sum":"","sum_rent":""}]},"id":"vulyk_68_181","banks":{"45":[{"sum_foreign_comment":"","sum_units":"UAH","sum_units_hidden":false,"sum_comment":"","sum_comment_unclear":false,"sum_hidden":false,"sum_foreign_units":"UAH","sum_comment_hidden":false,"sum_unclear":false,"sum":"44101","sum_foreign":""}]},"declaration":{"additional_info_text":"","notfull_lostpages":"","date":"2015-03-20T00:00:00","notfull":"","additional_info":"","url":"http://static.declarations.com.ua/declarations/chosen_ones/mega_batch/bonk_tetiana_bohdanivna.pdf"},"liabilities":{"54":{"sum_foreign_comment":"","sum":"","sum_comment":"","sum_comment_unclear":false,"sum_hidden":false,"sum_comment_hidden":false,"sum_unclear":false,"sum_foreign":""},"55":{"sum_foreign_comment":"","sum":"","sum_hidden":false,"sum_comment":"","sum_foreign":""},"56":{"sum_foreign_comment":"","sum_foreign_hidden":false,"sum_comment":"","sum":"","sum_unclear":false,"sum_foreign":""},"57":{"sum_foreign_comment":"","sum":"","sum_comment":"","sum_comment_unclear":false,"sum_hidden":false,"sum_comment_hidden":false,"sum_unclear":false,"sum_foreign":""},"58":{"sum_foreign_comment":"","sum":"","sum_comment":"","sum_hidden":false,"sum_comment_hidden":false,"sum_unclear":false,"sum_foreign":""},"59":{"sum_foreign_comment":"","sum":"","sum_comment":"","sum_foreign":""},"60":{"sum_foreign_comment":"","sum":"","sum_comment":"","sum_comment_unclear":false,"sum_hidden":false,"sum_comment_hidden":false,"sum_unclear":false,"sum_foreign":""},"61":{"sum_foreign_comment":"","sum":"","sum_hidden":false,"sum_comment":"","sum_foreign":""},"62":{"sum_foreign_comment":"","sum":"","sum_comment":"","sum_unclear":false,"sum_foreign":""},"63":{"sum_foreign_comment":"","sum":"","sum_comment":"","sum_hidden":false,"sum_comment_hidden":false,"sum_unclear":false,"sum_foreign":""},"64":{"sum_foreign_comment":"","sum":"","sum_comment":"","sum_hidden":false,"sum_comment_hidden":false,"sum_foreign":""}},"ft_src":"суддя львівського апеляційного господарського суду\nЛьвівська область\nАпеляційний господарський суд\nТетяна\nДонченко Ю. В\nПодружжя\nДонченко Н. Ю\nДитина\nБогданівна\nБонк Тетяна Богданівна\nТетяна Богданівна Бонк\nТетяна Бонк\nБонк Тетяна Богданівна\nБонк Тетяна Богданівна\nБонк\nоб'єм дв. 2.967\nVolkswagen Touareg\n2010\n44101\n2014\nоб'єм дв. 2.967\n2010\nVolkswagen Touareg\n44101\n23.2\n18.2\n86\n1000\nПодружжя\nДонченко Ю. В\nДитина\nДонченко Н. Ю\nБонк Тетяна Богданівна\nТетяна Богданівна Бонк\nТетяна Бонк\nБонк Тетяна Богданівна\nБонк Тетяна Богданівна\nТетяна\nБогданівна\nАпеляційний господарський суд\nЛьвівська область\nсуддя львівського апеляційного господарського суду\nБонк\n213434.15\n262812.2\n10803.13\n237635.28\n274992.2\n13398\n12180\n2014\n23.2\n86\n18.2\n1000\nПодружжя\nДонченко Ю. В\nДонченко Н. Ю\nДитина\nБогданівна\nБонк\nТетяна\nБонк Тетяна Богданівна\nТетяна Богданівна Бонк\nТетяна Бонк\nБонк Тетяна Богданівна\nЛьвівська область\nАпеляційний господарський суд\nсуддя львівського апеляційного господарського суду\nБонк Тетяна Богданівна\n262812.2\n213434.15\n10803.13\n12180\n13398\n274992.2\n237635.28\nVolkswagen Touareg\nоб'єм дв. 2.967\n2010\n10803.13\n12180\n13398\n274992.2\n237635.28\n262812.2\n213434.15\n86\n18.2\n23.2\n1000\n44101\n2014","general":{"inn":"","name":"Тетяна","inn_unclear":false,"family":[{"inn":"","inn_hidden":true,"relations_unclear":false,"relations_hidden":false,"relations_other":"","relations":"Подружжя","name_hidden":false,"inn_unclear":false,"family_name":"Донченко Ю. В","name_unclear":false},{"inn":"","inn_hidden":false,"inn_unclear":false,"relations_hidden":false,"relations_other":"","relations":"Дитина","name_hidden":false,"family_name":"Донченко Н. Ю","name_unclear":false}],"inn_hidden":true,"family_raw":"","last_name":"Бонк","post":{"post_unclear":false,"region_unclear":false,"post":"суддя львівського апеляційного господарського суду","office":"Апеляційний господарський суд","region":"Львівська область","post_hidden":false,"office_hidden":false,"office_unclear":false,"region_hidden":false},"full_name_suggest":{"output":"Бонк Тетяна Богданівна","input":["Бонк Тетяна Богданівна","Тетяна Богданівна Бонк","Тетяна Бонк"]},"full_name":"Бонк Тетяна Богданівна","addresses":[{"place_city_type_hidden":false,"place_district_hidden":false,"place_city_type":"","place_city_hidden":false,"place_address_unclear":false,"place_address":"","place_hidden":true,"place":"","place_district":"","place_unclear":false,"place_city":"","place_address_hidden":false}],"patronymic":"Богданівна","last_name_unclear":false,"name_unclear":false},"source":"VULYK","estate":{"27":[{"costs_rent":"","region":"","costs":"","costs_rent_comment":"","costs_comment":"","address_hidden":false,"region_hidden":true,"space_comment":"","space_units":"м²","space":"18.2","address":""}],"29":[{"space_unclear":false,"address_hidden":false,"region_hidden":true,"space_comment":"","space_units_hidden":false,"space_hidden":false,"space":"1000","address":"","region":"","costs_property":"","space_units_unclear":false,"space_units":"м²","costs_property_comment":"","costs_rent":"","costs_rent_comment":""}],"31":[{"space_unclear":false,"address_hidden":false,"region_hidden":true,"space_comment":"","space_hidden":false,"space":"86","address":"","region":"","costs_property":"","costs_rent_comment":"","space_units":"м²","costs_property_comment":"","costs_rent":""}],"33":[{"space_unclear":true,"address_hidden":false,"region_hidden":true,"space_comment":"","space":"23.2","address":"","region":"","costs_property":"","costs_rent_comment":"","space_comment_unclear":false,"space_units":"м²","costs_property_comment":"","costs_rent":""}]},"intro":{"declaration_year":"2014","isnotdeclaration":""}}