{"income":{"5":{"value":"274901","value_unclear":false,"family_hidden":false,"family_comment":"","family":"","comment":""},"6":{"family_comment":"","value":"274901","family":"","comment":""},"7":{"family_comment":"","value":"","source_name":"","family":"","comment":""},"8":{"family_comment":"","value":"","family":"","comment":""},"9":{"family_comment":"","value":"","family":"","comment":""},"10":{"family_comment":"","value":"","family":"","comment":""},"11":{"family_comment":"","value":"","family_hidden":false,"comment":"","family":""},"12":{"family_comment":"","value":"","family":"","comment":""},"13":{"family_comment":"","value":"","family":"","comment":""},"14":{"family_comment":"","value":"","family":"","comment":""},"15":{"family_comment":"","value":"","family":"","comment":""},"16":{"family_comment":"","value":"","family":"","comment":""},"17":{"family_comment":"","value":"","family":"","comment":"","family_comment_unclear":false},"18":{"family_comment":"","value":"","family":"","comment":""},"19":{"family_comment":"","value":"","family":"","comment":""},"20":{"value":"","family_unclear":false,"family_hidden":false,"family_comment":"","family":"","comment":""}},"id":"vulyk_103_14","declaration":{"date":"2016-03-31T00:00:00","additional_info_text":"","additional_info":"","url":"http://static.declarations.com.ua/declarations/chosen_ones/judges_batch/1238_chervynska_maryna_ievhenivna.pdf"},"liabilities":{"54":{"sum_foreign_comment":"","sum_foreign_hidden":false,"sum_comment":"","sum_foreign_comment_hidden":false,"sum_hidden":false,"sum_foreign_comment_unclear":false,"sum_comment_hidden":false,"sum_unclear":false,"sum":"","sum_foreign":""},"55":{"sum_foreign_comment":"","sum":"","sum_comment":"","sum_foreign":""},"56":{"sum_foreign_comment":"","sum":"","sum_comment":"","sum_foreign":""},"57":{"sum_foreign_comment":"","sum_foreign_hidden":false,"sum_comment":"","sum_foreign_comment_hidden":false,"sum_hidden":false,"sum_comment_hidden":false,"sum":"","sum_foreign":""},"58":{"sum_foreign_comment":"","sum_foreign_hidden":false,"sum_comment":"","sum_foreign_comment_hidden":false,"sum_hidden":false,"sum_comment_hidden":false,"sum":"","sum_foreign":""},"59":{"sum_foreign_comment":"","sum_foreign_hidden":false,"sum_comment":"","sum_foreign_comment_hidden":false,"sum_hidden":false,"sum_comment_hidden":false,"sum":"","sum_foreign":""},"60":{"sum_foreign_comment":"","sum":"","sum_comment":"","sum_hidden":false,"sum_comment_hidden":false,"sum_foreign":""},"61":{"sum_foreign_comment":"","sum":"","sum_comment":"","sum_foreign":""},"62":{"sum_foreign_comment":"","sum_comment_hidden":false,"sum":"","sum_comment":"","sum_foreign":""},"63":{"sum_foreign_comment":"","sum":"","sum_comment":"","sum_foreign":""},"64":{"sum_foreign_comment":"","sum":"","sum_comment":"","sum_foreign":""}},"ft_src":"Червинська Марина Євгенівна\nзаступник голови вссу\nЗагальнодержавний регіон\nВищий спеціалізований суд з розгляду цивільних і кримінальних справ\nМарина\nГасан М. О\nДитина\nЧервинська Марина Євгенівна\nМарина Євгенівна Червинська\nМарина Червинська\nЧервинська Марина Євгенівна\nЧервинська\nЄвгенівна\n274901\n274901\nавтостоянка (паркомісце\nпаркомісце\n157\n2015\n274901\n274901\nавтостоянка (паркомісце\nпаркомісце\n157\nЧервинська\nЧервинська Марина Євгенівна\nМарина Євгенівна Червинська\nМарина Червинська\nЧервинська Марина Євгенівна\nЧервинська Марина Євгенівна\nЄвгенівна\nДитина\nГасан М. О\nМарина\nВищий спеціалізований суд з розгляду цивільних і кримінальних справ\nзаступник голови вссу\nЗагальнодержавний регіон\n274901\n274901\n2015\nДитина\nГасан М. О\nЧервинська\nЄвгенівна\nзаступник голови вссу\nВищий спеціалізований суд з розгляду цивільних і кримінальних справ\nЗагальнодержавний регіон\nЧервинська Марина Євгенівна\nЧервинська Марина Євгенівна\nМарина Євгенівна Червинська\nМарина Червинська\nЧервинська Марина Євгенівна\nМарина\n157\nавтостоянка (паркомісце\nпаркомісце\n2015","general":{"inn":"","inn_hidden":true,"last_name":"Червинська","post":{"region":"Загальнодержавний регіон","region_unclear":false,"post":"заступник голови вссу","office_unclear":false,"office":"Вищий спеціалізований суд з розгляду цивільних і кримінальних справ"},"name":"Марина","full_name":"Червинська Марина Євгенівна","family_raw":"","addresses":[{"place_district":"","place_city_hidden":true,"place_city":"","place_city_type_hidden":false,"place_district_hidden":false,"place_city_type":"","place_address_hidden":true,"place_address":"","place_hidden":true,"place":""}],"family":[{"inn":"","relations":"Дитина","relations_hidden":false,"inn_hidden":true,"relations_other":"","name_hidden":true,"family_name":"Гасан М. О","name_unclear":false}],"full_name_suggest":{"output":"Червинська Марина Євгенівна","input":["Червинська Марина Євгенівна","Марина Євгенівна Червинська","Марина Червинська"]},"patronymic":"Євгенівна"},"source":"VULYK","estate":{"25":[{"costs":"","costs_comment":"","address_hidden":false,"region_hidden":true,"space_comment":"","space":"157","address":"","region":"","costs_rent_comment":"","space_comment_unclear":false,"space_comment_hidden":false,"space_units":"м²","costs_rent":""}],"28":[{"space_hidden":true,"costs":"","costs_comment":"","address_hidden":false,"region_hidden":true,"space_comment":"автостоянка (паркомісце","space_unclear":false,"space":"","address":"паркомісце","region":"","costs_rent_comment":"","space_units":"м²","costs_rent":""}]},"intro":{"declaration_year":"2015"}}