{"income":{"5":{"family_comment":"","value":"282077.15","family":"","comment":""},"6":{"family_comment":"","value":"282077.15","family":"","comment":""},"7":{"value":"","comment_hidden":false,"value_hidden":false,"family_comment":"","source_name":"","family":"","comment":"","source_name_hidden":false},"8":{"family_comment":"","value":"","family":"","comment":""},"9":{"value":"","comment_hidden":false,"family_comment":"","family":"","comment":"","family_comment_unclear":false},"10":{"family_comment":"","value":"","family":"","comment":""},"11":{"family_comment":"","value":"","comment_hidden":false,"family":"","comment":""},"12":{"family_comment":"","value":"","family":"","comment":""},"13":{"family_comment":"","value":"","family":"","comment":""},"14":{"family_comment":"","value":"","family":"","comment":""},"15":{"family_comment":"","value":"","family":"","comment":""},"16":{"family_comment":"","value":"","family":"","comment":""},"17":{"family_comment":"","value":"","family":"","comment":""},"18":{"family_comment":"","value":"","family":"","comment":""},"19":{"family_comment":"","value":"","family":"","comment":""},"20":{"family_comment":"","value":"","comment_hidden":false,"family":"","comment":""}},"vehicle":{"35":[{"brand_info":"4 цил., 1.4 куб. дм.","sum_rent_comment":"","brand":"Audi A3","sum_comment":"","year":"2013","brand_info_unclear":false,"year_unclear":false,"sum":"","sum_rent":""}]},"id":"vulyk_102_55","banks":{"45":[{"sum_foreign_comment":"","sum_units":"UAH","sum_comment":"","sum_comment_unclear":false,"sum_hidden":false,"sum_foreign_units":"UAH","sum_comment_hidden":true,"sum_unclear":false,"sum":"20188.89","sum_foreign":""}]},"declaration":{"date":"2016-03-29T00:00:00","additional_info_text":"","additional_info":"","url":"http://static.declarations.com.ua/declarations/chosen_ones/judges_batch/1129_biluha_serhii_volodymyrovych.pdf"},"liabilities":{"54":{"sum_foreign_comment":"","sum":"","sum_comment":"","sum_hidden":false,"sum_comment_hidden":false,"sum_foreign":""},"55":{"sum_foreign_comment":"","sum":"","sum_comment":"","sum_foreign":""},"56":{"sum_foreign_comment":"","sum":"","sum_comment":"","sum_foreign":""},"57":{"sum_foreign_comment":"","sum_comment_hidden":false,"sum":"","sum_comment":"","sum_foreign":""},"58":{"sum_foreign_comment":"","sum_comment_hidden":false,"sum":"","sum_comment":"","sum_foreign":""},"59":{"sum_foreign_comment":"","sum_comment_hidden":false,"sum":"","sum_comment":"","sum_foreign":""},"60":{"sum_foreign_comment":"","sum":"","sum_comment":"","sum_hidden":false,"sum_comment_hidden":false,"sum_foreign":""},"61":{"sum_foreign_comment":"","sum":"","sum_comment":"","sum_foreign":""},"62":{"sum_foreign_comment":"","sum":"","sum_comment":"","sum_unclear":false,"sum_foreign":""},"63":{"sum_foreign_comment":"","sum":"","sum_comment":"","sum_hidden":false,"sum_comment_hidden":false,"sum_foreign":""},"64":{"sum_foreign_comment":"","sum_comment_hidden":false,"sum":"","sum_comment":"","sum_foreign":""}},"ft_src":"Білуга Сергій Володимирович\nВолодимирович\nБілуга Сергій Володимирович\nСергій Володимирович Білуга\nСергій Білуга\nБілуга Сергій Володимирович\nСергій\nсуддя вищого адміністративного суду україни\nЗагальнодержавний регіон\nВищий адміністративний суд\nБілуга\n2013\n4 цил., 1.4 куб. дм.\nAudi A3\n78.7\n20188.89\n2015\n4 цил., 1.4 куб. дм.\nAudi A3\n2013\n2015\nБілуга Сергій Володимирович\nСергій Володимирович Білуга\nСергій Білуга\nБілуга Сергій Володимирович\nСергій\nВолодимирович\nБілуга Сергій Володимирович\nБілуга\nсуддя вищого адміністративного суду україни\nЗагальнодержавний регіон\nВищий адміністративний суд\n282077.15\n282077.15\n78.7\n20188.89\n282077.15\n282077.15\nВолодимирович\nБілуга\nсуддя вищого адміністративного суду україни\nЗагальнодержавний регіон\nВищий адміністративний суд\nБілуга Сергій Володимирович\nБілуга Сергій Володимирович\nСергій Володимирович Білуга\nСергій Білуга\nБілуга Сергій Володимирович\nСергій\n2013\n4 цил., 1.4 куб. дм.\nAudi A3\n282077.15\n282077.15\n78.7\n20188.89\n2015","general":{"inn":"","inn_hidden":true,"last_name":"Білуга","post":{"region":"Загальнодержавний регіон","region_unclear":false,"post":"суддя вищого адміністративного суду україни","office_unclear":false,"office":"Вищий адміністративний суд"},"name":"Сергій","full_name":"Білуга Сергій Володимирович","family_raw":"","addresses":[{"place_district":"","place_city_hidden":true,"place_city":"","place_city_type_hidden":false,"place_district_hidden":false,"place_city_type":"","place_address_hidden":true,"place_address":"","place_hidden":true,"place":""}],"patronymic_hidden":false,"full_name_suggest":{"output":"Білуга Сергій Володимирович","input":["Білуга Сергій Володимирович","Сергій Володимирович Білуга","Сергій Білуга"]},"patronymic":"Володимирович"},"source":"VULYK","estate":{"25":[{"costs":"","costs_comment":"","address_hidden":false,"region_hidden":true,"space_comment":"","space":"78.7","address":"","region":"","address_unclear":false,"costs_rent_comment":"","space_units":"м²","costs_rent":""}]},"intro":{"declaration_year":"2015"}}