{"income":{"5":{"family_comment":"","value":"280897","family":"27841","comment":""},"6":{"family_comment":"","value":"280897","family":"22641","comment":""},"7":{"family_comment":"","value":"","source_name":"","family":"","comment":""},"8":{"family_comment":"","value":"","family":"","comment":""},"9":{"value":"","comment_unclear":false,"family_comment":"","family":"","comment":"","family_comment_unclear":false},"10":{"family_comment":"","value":"","family":"","comment":""},"11":{"family_comment":"","value":"","family":"","comment":""},"12":{"family_comment":"","value":"","family":"","comment":""},"13":{"family_comment":"","value":"","family":"","comment":""},"14":{"family_comment":"","value":"","family":"","comment":""},"15":{"family_comment":"","value":"","family":"","comment":""},"16":{"family_comment":"","value":"","family":"","comment":""},"17":{"family_comment":"","value":"","family":"","comment":""},"18":{"family_comment":"","value":"","family":"","comment":""},"19":{"value":"","family_comment":"","value_unclear":false,"family_unclear":false,"family":"5200","comment":""},"20":{"value":"","family_comment":"","value_unclear":false,"comment_hidden":false,"family_comment_hidden":false,"family_unclear":false,"family_comment_unclear":false,"comment_unclear":false,"comment":"","family":""}},"vehicle":{"40":[{"year_hidden":false,"brand_info":"2.5","sum_rent_comment":"","brand":"Mercedes-Benz","sum_comment":"","year":"1992","brand_hidden":false,"brand_info_hidden":false,"brand_info_unclear":false,"sum":"","sum_rent":""}]},"id":"vulyk_106_5","declaration":{"additional_info_text":"","notfull_lostpages":"","date":"2016-03-28T00:00:00","notfull":"","additional_info":"","url":"http://static.declarations.com.ua/declarations/chosen_ones/judges_batch/2144_matkovska_liubov_oleksiivna.pdf"},"liabilities":{"54":{"sum_foreign_comment":"","sum":"","sum_comment":"","sum_comment_unclear":false,"sum_hidden":false,"sum_comment_hidden":false,"sum_foreign":""},"55":{"sum_foreign_comment":"","sum":"","sum_hidden":false,"sum_comment":"","sum_foreign":""},"56":{"sum_foreign_comment":"","sum":"","sum_comment":"","sum_hidden":false,"sum_comment_hidden":false,"sum_unclear":false,"sum_foreign":""},"57":{"sum_foreign_comment":"","sum":"","sum_comment":"","sum_hidden":false,"sum_comment_hidden":false,"sum_foreign":""},"58":{"sum_foreign_comment":"","sum":"","sum_comment":"","sum_hidden":false,"sum_comment_hidden":false,"sum_foreign":""},"59":{"sum_foreign_comment":"","sum":"","sum_comment":"","sum_foreign":""},"60":{"sum_foreign_comment":"","sum":"","sum_comment":"","sum_hidden":false,"sum_comment_hidden":false,"sum_foreign":""},"61":{"sum_foreign_comment":"","sum":"","sum_comment":"","sum_foreign":""},"62":{"sum_foreign_comment":"","sum":"","sum_comment":"","sum_comment_hidden":false,"sum_unclear":false,"sum_foreign":""},"63":{"sum_foreign_comment":"","sum":"","sum_comment":"","sum_foreign":""},"64":{"sum_foreign_comment":"","sum":"","sum_comment":"","sum_foreign":""}},"ft_src":"суддя апеляційного суду хмельницької області\nХмельницька область\nЗагальний апеляційний суд\nЛюбов\nМатковський В. В. 02. 06. 1962\nПодружжя\nМатковський М. В. 13. 01. 1985\nДитина\nМатковська О. В. 07. 12. 1987\nДитина\nОлексіївна\nМатковська Любов Олексіївна\nЛюбов Олексіївна Матковська\nЛюбов Матковська\nМатковська Любов Олексіївна\nМатковська Любов Олексіївна\nМатковська\n2.5\nMercedes-Benz\n1992\n2015\n22641\n280897\n27841\n280897\n5200\n2.5\n1992\nMercedes-Benz\nМатковська Любов Олексіївна\nЛюбов Олексіївна Матковська\nЛюбов Матковська\nМатковська Любов Олексіївна\nМатковська Любов Олексіївна\nПодружжя\nМатковський В. В. 02. 06. 1962\nДитина\nМатковський М. В. 13. 01. 1985\nДитина\nМатковська О. В. 07. 12. 1987\nЛюбов\nМатковська\nХмельницька область\nЗагальний апеляційний суд\nсуддя апеляційного суду хмельницької області\nОлексіївна\n280897\n22641\n280897\n27841\n5200\n2015\nМатковський В. В. 02. 06. 1962\nПодружжя\nМатковський М. В. 13. 01. 1985\nДитина\nМатковська О. В. 07. 12. 1987\nДитина\nОлексіївна\nМатковська\nЛюбов\nМатковська Любов Олексіївна\nЛюбов Олексіївна Матковська\nЛюбов Матковська\nМатковська Любов Олексіївна\nХмельницька область\nЗагальний апеляційний суд\nсуддя апеляційного суду хмельницької області\nМатковська Любов Олексіївна\nMercedes-Benz\n2.5\n1992\n5200\n27841\n280897\n22641\n280897\n2015","general":{"inn":"","name":"Любов","inn_unclear":false,"family":[{"inn":"","inn_hidden":true,"relations_unclear":false,"relations_hidden":false,"relations_other":"","relations":"Подружжя","name_hidden":false,"family_name":"Матковський В. В. 02. 06. 1962","name_unclear":false},{"inn":"","relations":"Дитина","relations_unclear":false,"family_name":"Матковський М. В. 13. 01. 1985","inn_hidden":false,"relations_other":"","name_hidden":false,"name_unclear":false},{"inn_hidden":false,"inn":"","name_hidden":false,"family_name":"Матковська О. В. 07. 12. 1987","relations":"Дитина","name_unclear":false}],"inn_hidden":true,"family_raw":"","last_name":"Матковська","post":{"region_unclear":false,"region":"Хмельницька область","post":"суддя апеляційного суду хмельницької області","office":"Загальний апеляційний суд","office_unclear":false,"post_hidden":false},"full_name":"Матковська Любов Олексіївна","addresses":[{"place_district":"","place_city_hidden":true,"place_city":"","place_city_type_hidden":true,"place_district_hidden":true,"place_city_type":"","place_address_hidden":true,"place_address":"","place_hidden":true,"place":""}],"patronymic":"Олексіївна","full_name_suggest":{"output":"Матковська Любов Олексіївна","input":["Матковська Любов Олексіївна","Любов Олексіївна Матковська","Любов Матковська"]},"name_unclear":false},"source":"VULYK","estate":{"23":[{"region_unclear":false,"space_hidden":true,"costs":"","costs_comment":"","address_hidden":true,"region_hidden":true,"space_comment":"","space_unclear":false,"space":"","address":"","costs_comment_unclear":false,"costs_rent_comment_unclear":false,"region":"","address_unclear":false,"costs_rent_comment":"","space_comment_unclear":false,"space_comment_hidden":true,"space_units":"м²","costs_rent":""}],"24":[{"space_unclear":false,"costs":"","costs_comment":"","address_hidden":true,"region_hidden":true,"space_comment":"","space_hidden":true,"space":"","address":"","region":"","costs_rent_comment":"","space_comment_unclear":false,"space_comment_hidden":true,"space_units":"м²","costs_rent":""}],"31":[{"space_unclear":false,"address_hidden":true,"region_hidden":true,"space_comment":"","space_hidden":true,"space":"","address":"","region":"","costs_property":"","costs_rent_comment":"","space_comment_unclear":false,"space_units":"м²","costs_property_comment":"","costs_rent":""}]},"intro":{"declaration_year":"2015","isnotdeclaration":""}}