{"income":{"5":{"value":"203154","family_comment":"","value_unclear":false,"comment_hidden":false,"family_hidden":false,"family":"26231","value_hidden":false,"family_unclear":false,"comment_unclear":false,"comment":"","family_comment_unclear":false},"6":{"value":"190974","family_unclear":false,"family_hidden":false,"family_comment":"","family":"","comment":""},"7":{"family_comment":"","value":"","source_name":"","family":"","comment":""},"8":{"family_comment":"","value":"","value_unclear":false,"family":"","comment":""},"9":{"value":"","family_unclear":false,"family_hidden":false,"family_comment":"","family":"1500","comment":""},"10":{"family_comment":"","value":"12180","value_unclear":false,"family":"","comment":""},"11":{"value":"","value_unclear":false,"family_hidden":false,"value_hidden":false,"family_comment":"","family":"","comment":""},"12":{"family_comment":"","value":"","family":"","comment":""},"13":{"family_comment":"","value":"","value_unclear":false,"family":"","comment":""},"14":{"family_comment":"","value":"","family":"","comment":""},"15":{"family_comment":"","value":"","value_unclear":false,"family":"","comment":""},"16":{"family_comment":"","value":"","family":"","comment":""},"17":{"family_comment":"","value":"","family":"","comment":""},"18":{"family_comment":"","value":"","family":"","comment":""},"19":{"family_comment":"","value":"","family":"","comment":""},"20":{"family_comment":"","value":"","value_unclear":false,"family":"24731","comment":""}},"vehicle":{"35":[{"brand_info":"1598 к. см","sum_rent_comment":"","brand_info_unclear":false,"year":"2007","sum_hidden":false,"sum_rent_comment_unclear":false,"sum_rent":"","sum":"","brand":"Chevrolet Aveo","sum_comment":"","brand_unclear":false,"brand_hidden":false,"sum_unclear":false}]},"id":"vulyk_54_165","banks":{"45":[{"sum_foreign_comment":"","sum_units":"UAH","sum_comment":"","sum_comment_unclear":false,"sum_hidden":false,"sum_foreign_units":"UAH","sum_units_unclear":false,"sum_comment_hidden":false,"sum_unclear":false,"sum":"","sum_foreign":""},{"sum_foreign_comment":"","sum_units":"","sum_comment":"","sum_comment_unclear":false,"sum_foreign_units":"","sum":"","sum_foreign":""},{"sum_foreign_comment":"","sum_units":"","sum_comment":"","sum_foreign_units":"","sum":"","sum_foreign":""}],"46":[{"sum_foreign_comment":"","sum_units":"UAH","sum_comment":"","sum_comment_unclear":false,"sum_foreign_units":"UAH","sum":"","sum_foreign":""},{"sum_foreign_comment":"","sum_units":"","sum_comment":"","sum_foreign_units":"","sum":"","sum_foreign":""}],"47":[{"sum_foreign_comment":"","sum_units":"UAH","sum_comment":"","sum_comment_unclear":false,"sum_foreign_units":"UAH","sum":"","sum_foreign":""},{"sum_foreign_comment":"","sum_units":"","sum_comment":"","sum":"","sum_foreign":""}],"48":[{"sum_foreign_comment":"","sum_units":"UAH","sum_comment":"","sum_foreign_units":"UAH","sum":"","sum_foreign":""}],"49":[{"sum_foreign_comment":"","sum_units":"UAH","sum_comment":"","sum_comment_unclear":false,"sum_foreign_units":"UAH","sum":"","sum_foreign":""}],"50":[{"sum_foreign_comment":"","sum_units":"UAH","sum_comment":"","sum_foreign_units":"UAH","sum":"","sum_foreign":""}],"51":[{"sum_foreign_comment":"","sum_units":"UAH","sum_comment":"","sum_comment_unclear":false,"sum_hidden":false,"sum_foreign_units":"UAH","sum_comment_hidden":false,"sum":"8463","sum_foreign":""},{"sum_foreign_comment":"","sum_units":"","sum_comment":"","sum_foreign_units":"","sum":"","sum_foreign":""},{"sum_foreign_comment":"","sum_units":"","sum_comment":"","sum_foreign_units":"","sum":"","sum_foreign":""}],"52":[{"sum_foreign_comment":"","sum_units":"UAH","sum_comment":"","sum_comment_unclear":false,"sum_foreign_units":"UAH","sum":"1665","sum_foreign":""}],"53":[{"sum_foreign_comment":"","sum_units":"UAH","sum_comment":"","sum_foreign_units":"UAH","sum":"","sum_unclear":false,"sum_foreign":""}]},"declaration":{"additional_info_text":"","notfull_lostpages":"","date":"2015-03-25T00:00:00","notfull":"","additional_info":"","url":"http://static.declarations.com.ua/declarations/chosen_ones/mega_batch/liakhu_hennadii_oleksandrovych.pdf"},"liabilities":{"54":{"sum_foreign_comment":"","sum":"253","sum_comment":"","sum_comment_unclear":false,"sum_hidden":false,"sum_comment_hidden":false,"sum_unclear":false,"sum_foreign":""},"55":{"sum_foreign_comment":"","sum":"","sum_comment":"","sum_foreign":""},"56":{"sum_foreign_comment":"","sum":"9000","sum_comment":"","sum_foreign":""},"57":{"sum_foreign_comment":"","sum":"","sum_comment":"","sum_comment_unclear":false,"sum_comment_hidden":false,"sum_unclear":false,"sum_foreign":""},"58":{"sum_foreign_comment":"","sum":"","sum_comment":"","sum_comment_unclear":false,"sum_comment_hidden":false,"sum_unclear":false,"sum_foreign":""},"59":{"sum_foreign_comment":"","sum_foreign_hidden":false,"sum_comment":"","sum_hidden":false,"sum_comment_hidden":false,"sum":"","sum_foreign":""},"60":{"sum_foreign_comment":"","sum":"","sum_comment":"","sum_foreign":""},"61":{"sum_foreign_comment":"","sum":"","sum_comment":"","sum_foreign":""},"62":{"sum_foreign_comment":"","sum":"15000","sum_comment":"","sum_foreign":""},"63":{"sum_foreign_comment":"","sum_comment_hidden":false,"sum":"","sum_comment":"","sum_foreign":""},"64":{"sum_foreign_comment":"","sum":"","sum_comment":"","sum_foreign":""}},"ft_src":"15000\n253\n9000\nсуддя новоселицького районного суду чернівецької області\nЧернівецька область\nЗагальний місцевий суд\nГенадій\nЛяху Альвіна Олексіївна\nПодружжя\nЛяху Тетяна Генадіївна\nДитина\nЛяху Юлія Генадіївна\nДитина\nЛяху Олександр Іванович\nБатьки\nЛяху Ганна Федорівна\nБатьки\nОлександрович\nЛяху Генадій Олександрович\nГенадій Олександрович Ляху\nГенадій Ляху\nЛяху Генадій Олександрович\nЛяху Генадій Олександрович\nЛяху\n1598 к. см\nChevrolet Aveo\n2007\n8463\n1665\n2014\n1598 к. см\nChevrolet Aveo\n2007\n8463\n1665\n17066\n197.1\n103.3\nЛяху Генадій Олександрович\nГенадій Олександрович Ляху\nГенадій Ляху\nЛяху Генадій Олександрович\nЛяху Генадій Олександрович\nПодружжя\nЛяху Альвіна Олексіївна\nДитина\nЛяху Тетяна Генадіївна\nДитина\nЛяху Юлія Генадіївна\nЛяху Олександр Іванович\nБатьки\nЛяху Ганна Федорівна\nБатьки\nГенадій\nОлександрович\nЗагальний місцевий суд\nЧернівецька область\nсуддя новоселицького районного суду чернівецької області\nЛяху\n9000\n15000\n253\n190974\n24731\n203154\n26231\n12180\n1500\n2014\n9000\n15000\n253\n17066\n197.1\n103.3\nПодружжя\nЛяху Альвіна Олексіївна\nЛяху Тетяна Генадіївна\nДитина\nЛяху Юлія Генадіївна\nДитина\nБатьки\nЛяху Олександр Іванович\nЛяху Ганна Федорівна\nБатьки\nОлександрович\nЛяху\nГенадій\nЛяху Генадій Олександрович\nГенадій Олександрович Ляху\nГенадій Ляху\nЛяху Генадій Олександрович\nЧернівецька область\nЗагальний місцевий суд\nсуддя новоселицького районного суду чернівецької області\nЛяху Генадій Олександрович\n190974\n12180\n26231\n203154\n1500\n24731\n2007\nChevrolet Aveo\n1598 к. см\n12180\n24731\n203154\n26231\n1500\n190974\n197.1\n103.3\n17066\n1665\n8463\n2014","general":{"inn":"","name":"Генадій","patronymic_unclear":false,"family":[{"inn":"","inn_hidden":true,"relations_unclear":false,"relations_hidden":false,"relations_other":"","relations":"Подружжя","name_hidden":false,"inn_unclear":false,"family_name":"Ляху Альвіна Олексіївна","name_unclear":false},{"inn":"","inn_hidden":true,"relations_hidden":false,"family_name":"Ляху Тетяна Генадіївна","relations_other":"","relations":"Дитина","name_hidden":false,"name_unclear":false},{"inn":"","relations":"Дитина","relations_other":"","inn_hidden":true,"family_name":"Ляху Юлія Генадіївна","name_hidden":false,"name_unclear":false},{"inn":"","family_name":"Ляху Олександр Іванович","relations":"Батьки","inn_hidden":false,"relations_other":""},{"inn":"","family_name":"Ляху Ганна Федорівна","relations":"Батьки"}],"patronymic":"Олександрович","inn_hidden":true,"family_raw":"","inn_unclear":false,"post":{"post_unclear":false,"region_unclear":false,"post":"суддя новоселицького районного суду чернівецької області","office":"Загальний місцевий суд","region":"Чернівецька область","post_hidden":false,"office_hidden":false,"office_unclear":false,"region_hidden":false},"full_name_suggest":{"output":"Ляху Генадій Олександрович","input":["Ляху Генадій Олександрович","Генадій Олександрович Ляху","Генадій Ляху"]},"full_name":"Ляху Генадій Олександрович","last_name":"Ляху","last_name_unclear":false,"name_unclear":false},"source":"VULYK","estate":{"23":[{"space_unclear":false,"costs":"","costs_comment":"","costs_hidden":false,"address_hidden":false,"region_hidden":false,"space_comment":"","space":"","address":"","region":"","address_unclear":false,"costs_rent_comment":"","space_units":"м²","costs_rent":""},{"space":"","region":"","costs":"","costs_rent_comment":"","costs_comment":"","region_hidden":false,"address_unclear":false,"space_comment":"","space_units":"","costs_rent":"","address":""},{"costs_rent":"","region":"","costs":"","costs_rent_comment":"","costs_comment":"","space_comment":"","space_units":"","space":"","address":""},{"costs_rent":"","costs":"","costs_rent_comment":"","costs_comment":"","space_comment":"","space_units":"","space":"","address":""}],"29":[{"space_unclear":false,"costs_property_hidden":false,"address_hidden":true,"region_hidden":true,"space_comment":"","space":"17066","address":"","region":"","costs_property":"","costs_rent_comment":"","space_units":"м²","costs_property_comment":"","costs_rent":""}],"30":[{"region_unclear":false,"space_unclear":false,"address_hidden":true,"region_hidden":true,"space_comment":"","space":"197.1","address":"","region":"","costs_property":"","costs_rent_comment":"","space_units":"м²","costs_property_comment":"","costs_rent":""}],"34":[{"costs_rent":"","region":"","costs_property":"","costs_rent_comment":"","address_hidden":true,"region_hidden":true,"space_comment":"","costs_property_comment":"","space_units":"м²","space":"103.3","address":""}]},"intro":{"declaration_year":"2014","declaration_year_unclear":false}}