{"income":{"5":{"family_comment":"","value":"115836","family":"20873","comment":""},"6":{"family_comment":"","value":"115836","family":"","comment":""},"7":{"family_comment":"","value":"","source_name":"","family":"","comment":""},"8":{"family_comment":"","value":"","family":"","comment":""},"9":{"family_comment":"","value":"","family":"","comment":""},"10":{"family_comment":"","value":"","family":"","comment":""},"11":{"family_comment":"","value":"","family":"","comment":""},"12":{"family_comment":"","value":"","family":"","comment":""},"13":{"family_comment":"","value":"","family":"","comment":""},"14":{"family_comment":"","value":"","family":"","comment":""},"15":{"family_comment":"","value":"","family":"","comment":""},"16":{"family_comment":"","value":"","family":"","comment":""},"17":{"family_comment":"","value":"","family":"14230","comment":""},"18":{"family_comment":"","value":"","family":"","comment":""},"19":{"family_comment":"","value":"","family":"","comment":""},"20":{"family_comment":"пенсія сина","value":"","family":"6643","comment":""}},"vehicle":{"35":[{"brand_info":"","sum_rent_comment":"","brand":"Mitsubishi Carisma","sum_comment":"","year":"2002","brand_hidden":false,"brand_info_hidden":true,"sum":"","sum_rent":""}]},"id":"vulyk_52_19","banks":{"45":[{"sum_foreign_comment":"","sum_units":"UAH","sum_comment":"","sum_comment_unclear":false,"sum_hidden":false,"sum_foreign_units":"UAH","sum_comment_hidden":false,"sum":"","sum_foreign":""},{"sum_foreign_comment":"","sum_units":"","sum_comment":"","sum_comment_unclear":false,"sum_foreign_units":"","sum":"","sum_unclear":false,"sum_foreign":""}],"46":[{"sum_foreign_comment":"","sum_units":"UAH","sum_comment":"","sum_foreign_units":"UAH","sum_comment_hidden":false,"sum":"","sum_foreign":""}],"47":[{"sum_foreign_comment":"","sum_units":"UAH","sum_comment":"","sum_foreign_units":"UAH","sum_comment_hidden":false,"sum_unclear":false,"sum":"","sum_foreign":""}],"48":[{"sum_foreign_comment":"","sum_units":"UAH","sum_comment":"","sum_foreign_units":"UAH","sum":"","sum_foreign":""}],"49":[{"sum_foreign_comment":"","sum_units":"UAH","sum_comment":"","sum_foreign_units":"UAH","sum":"","sum_foreign":""}],"50":[{"sum_foreign_comment":"","sum_units":"UAH","sum_comment":"","sum_foreign_units":"UAH","sum":"","sum_foreign":""}],"51":[{"sum_foreign_comment":"","sum_units":"UAH","sum_comment":"","sum_foreign_units":"UAH","sum_comment_hidden":false,"sum_unclear":false,"sum":"","sum_foreign":""},{"sum_foreign_comment":"","sum_units":"","sum_comment":"","sum_foreign_units":"","sum":"","sum_foreign":""}],"52":[{"sum_foreign_comment":"","sum_units":"UAH","sum_comment":"","sum_foreign_units":"UAH","sum":"","sum_foreign":""}],"53":[{"sum_foreign_comment":"","sum_units":"UAH","sum_comment":"","sum_foreign_units":"UAH","sum":"","sum_foreign":""}]},"declaration":{"additional_info_text":"","notfull_lostpages":"","date":"2015-03-21T00:00:00","notfull":"","additional_info":"","url":"http://static.declarations.com.ua/declarations/chosen_ones/mega_batch/fomin_oleksandr_volodymyrovych.pdf"},"liabilities":{"54":{"sum_foreign_comment":"","sum":"","sum_comment":"","sum_foreign":""},"55":{"sum_foreign_comment":"","sum":"","sum_comment":"","sum_foreign":""},"56":{"sum_foreign_comment":"","sum":"","sum_hidden":false,"sum_comment":"","sum_foreign":""},"57":{"sum_foreign_comment":"","sum":"","sum_comment":"","sum_hidden":false,"sum_comment_hidden":false,"sum_foreign":""},"58":{"sum_foreign_comment":"","sum_comment_hidden":false,"sum":"","sum_comment":"","sum_foreign":""},"59":{"sum_foreign_comment":"","sum":"","sum_comment":"","sum_foreign":""},"60":{"sum_foreign_comment":"","sum":"","sum_comment":"","sum_comment_hidden":false,"sum_unclear":false,"sum_foreign":""},"61":{"sum_foreign_comment":"","sum":"","sum_comment":"","sum_foreign":""},"62":{"sum_foreign_comment":"","sum":"","sum_comment":"","sum_foreign":""},"63":{"sum_foreign_comment":"","sum_comment_hidden":false,"sum":"","sum_comment":"","sum_foreign":""},"64":{"sum_foreign_comment":"","sum":"","sum_comment":"","sum_hidden":false,"sum_comment_hidden":false,"sum_foreign":""}},"ft_src":"94707\nЛуганська область\nсуддя ровеньківського міського суду луганської області\nЛуганська область\nЗагальний місцевий суд\nОлександр\nФоміна С. В\nПодружжя\nФомін В. О\nДитина\nВолодимирович\nФомін\nФомін Олександр Володимирович\nФомін Олександр Володимирович\nОлександр Володимирович Фомін\nОлександр Фомін\nФомін Олександр Володимирович\n2002\nMitsubishi Carisma\n2014\n2002\nMitsubishi Carisma\nм. Ровеньки\n22.1\nЛуганська область\nоренда\n10\nробоче місце в салоні краси\nЛуганська область\nм. Ровеньки\n36.3\nЛуганська область\nм. Ровеньки\nФомін Олександр Володимирович\nОлександр Володимирович Фомін\nОлександр Фомін\nФомін Олександр Володимирович\nФомін Олександр Володимирович\nПодружжя\nФоміна С. В\nДитина\nФомін В. О\nОлександр\nВолодимирович\nЗагальний місцевий суд\nсуддя ровеньківського міського суду луганської області\nЛуганська область\nФомін\n94707\nЛуганська область\n115836\n14230\n6643\nпенсія сина\n115836\n20873\n2014\nм. Ровеньки\n22.1\nЛуганська область\nЛуганська область\nробоче місце в салоні краси\nм. Ровеньки\nоренда\n10\nЛуганська область\nм. Ровеньки\n36.3\nФоміна С. В\nПодружжя\nФомін В. О\nДитина\nОлександр\nВолодимирович\nФомін\nФомін Олександр Володимирович\nОлександр Володимирович Фомін\nОлександр Фомін\nФомін Олександр Володимирович\nЛуганська область\n94707\nсуддя ровеньківського міського суду луганської області\nЛуганська область\nЗагальний місцевий суд\nФомін Олександр Володимирович\n115836\n20873\n115836\n14230\n6643\nпенсія сина\n2002\nMitsubishi Carisma\n6643\nпенсія сина\n20873\n115836\n14230\n115836\nм. Ровеньки\nЛуганська область\n36.3\nробоче місце в салоні краси\nм. Ровеньки\nЛуганська область\n10\nоренда\nЛуганська область\nм. Ровеньки\n22.1\n2014","general":{"inn":"","name":"Олександр","family":[{"inn":"","relations":"Подружжя","relations_other":"","inn_hidden":false,"family_name":"Фоміна С. В","name_hidden":false,"name_unclear":false},{"inn":"","relations":"Дитина","relations_other":"","inn_hidden":false,"family_name":"Фомін В. О","name_hidden":false}],"patronymic":"Володимирович","inn_hidden":true,"family_raw":"","last_name":"Фомін","post":{"office":"Загальний місцевий суд","region":"Луганська область","post":"суддя ровеньківського міського суду луганської області"},"last_name_unclear":false,"full_name":"Фомін Олександр Володимирович","addresses":[{"place_district":"","place_city_hidden":true,"place_city":"","place_city_type_hidden":true,"place_district_hidden":true,"place_city_type":"","place_address_hidden":true,"place_address":"94707","place_hidden":false,"place":"Луганська область"}],"full_name_suggest":{"output":"Фомін Олександр Володимирович","input":["Фомін Олександр Володимирович","Олександр Володимирович Фомін","Олександр Фомін"]}},"source":"VULYK","estate":{"23":[{"costs_rent":"","region":"","costs":"","costs_rent_comment":"","costs_comment":"","address_hidden":false,"region_hidden":false,"space_comment":"","space_units":"м²","space":"","address":""},{"costs_rent":"","region":"","costs":"","costs_rent_comment":"","costs_comment":"","address_hidden":false,"space_comment":"","space_units":"","space":"","address":""},{"costs_rent":"","region":"","costs":"","costs_rent_comment":"","costs_comment":"","address_hidden":false,"space_comment":"","space_units":"","space":"","address":""},{"costs_rent":"","space_unclear":false,"region":"","costs":"","costs_rent_comment":"","costs_comment":"","space_comment":"","space_units":"","space":"","address":""},{"costs_rent":"","region":"","costs":"","costs_rent_comment":"","costs_comment":"","space_comment":"","space_units":"","space":"","address":""},{"costs_rent":"","costs":"","costs_rent_comment":"","costs_comment":"","space_comment":"","space_units":"","space":"","address":""}],"25":[{"costs":"","costs_comment":"","address_hidden":true,"region_hidden":false,"space_comment":"","space":"36.3","address":"м. Ровеньки","region":"Луганська область","costs_rent_comment":"","costs_rent_hidden":false,"space_units":"м²","costs_rent":""}],"27":[{"costs_rent":"","region":"Луганська область","costs":"","costs_rent_comment":"","costs_comment":"","address_hidden":true,"region_hidden":false,"space_comment":"","space_units":"м²","space":"22.1","address":"м. Ровеньки"}],"34":[{"costs_rent":"","region":"Луганська область","costs_property":"","costs_rent_comment":"оренда","address_hidden":false,"region_hidden":false,"space_comment":"робоче місце в салоні краси","costs_property_comment":"","space_units":"м²","space":"10","address":"м. Ровеньки"}]},"intro":{"declaration_year":"2014","isnotdeclaration":""}}