{"income":{"5":{"family_comment":"","value":"215587","value_unclear":false,"family":"","comment":""},"6":{"value":"207612","value_unclear":false,"family_hidden":false,"family_comment":"","family":"","comment":""},"7":{"source_name_unclear":false,"value":"","family_comment":"","source_name":"","family":"","comment":""},"8":{"family_comment":"","value":"","family":"","comment":""},"9":{"family_comment":"","value":"","family":"","comment":""},"10":{"family_comment":"","value":"","family":"","comment":""},"11":{"family_comment":"","value":"","comment_unclear":false,"family":"","comment":""},"12":{"family_comment":"","value":"","family":"","comment":""},"13":{"family_comment":"","value":"","family":"","comment":""},"14":{"family_comment":"","value":"","family":"","comment":""},"15":{"family_comment":"","value":"","family":"","comment":""},"16":{"family_comment":"","value":"","family":"","comment":""},"17":{"family_comment":"","value":"","family":"","comment":""},"18":{"family_comment":"","value":"","family":"","comment":""},"19":{"family_comment":"","value":"","family":"","comment":""},"20":{"value":"7975","family_comment":"","value_unclear":false,"family_unclear":false,"comment_unclear":false,"comment":"пенсія","family":""}},"vehicle":{"35":[{"brand_info":"","sum_rent_comment":"","brand":"Volkswagen Golf","sum_comment":"","brand_unclear":false,"year":"2007","sum_rent_unclear":false,"brand_info_hidden":false,"brand_info_unclear":false,"sum":"","sum_rent":""}]},"id":"vulyk_101_127","banks":{"45":[{"sum_foreign_comment":"","sum_units":"UAH","sum_comment":"","sum_comment_unclear":false,"sum_hidden":false,"sum_foreign_units":"UAH","sum_comment_hidden":false,"sum_unclear":false,"sum":"9800","sum_foreign":""}]},"declaration":{"additional_info_text":"","notfull_lostpages":"","date":"2016-03-12T00:00:00","notfull":"","additional_info":"","url":"http://static.declarations.com.ua/declarations/chosen_ones/judges_batch/799_tropak_oleksandra_vasylivna_2015.pdf"},"liabilities":{"54":{"sum_foreign_comment":"","sum":"","sum_comment":"","sum_comment_unclear":false,"sum_hidden":false,"sum_comment_hidden":false,"sum_unclear":false,"sum_foreign":""},"55":{"sum_foreign_comment":"","sum":"","sum_comment":"","sum_foreign":""},"56":{"sum_foreign_comment":"","sum":"","sum_comment":"","sum_comment_hidden":false,"sum_unclear":false,"sum_foreign":""},"57":{"sum_foreign_comment":"","sum":"","sum_comment":"","sum_hidden":false,"sum_comment_hidden":false,"sum_unclear":false,"sum_foreign":""},"58":{"sum_foreign_comment":"","sum":"","sum_comment":"","sum_comment_unclear":false,"sum_hidden":false,"sum_comment_hidden":false,"sum_unclear":false,"sum_foreign":""},"59":{"sum_foreign_comment":"","sum":"","sum_comment":"","sum_foreign":""},"60":{"sum_foreign_comment":"","sum":"","sum_comment":"","sum_hidden":false,"sum_comment_hidden":false,"sum_unclear":false,"sum_foreign":""},"61":{"sum_foreign_comment":"","sum":"","sum_comment":"","sum_foreign":""},"62":{"sum_foreign_comment":"","sum":"","sum_comment":"","sum_comment_unclear":false,"sum_foreign":""},"63":{"sum_foreign_comment":"","sum_comment_hidden":false,"sum":"","sum_comment":"","sum_foreign":""},"64":{"sum_foreign_comment":"","sum_comment_hidden":false,"sum":"","sum_comment":"","sum_foreign":""}},"ft_src":"суддя апеляційного суду львівської області\nЛьвівська область\nЗагальний апеляційний суд\nОлександра\nВасилівна\nТропак Олександра Василівна\nТропак\nТропак Олександра Василівна\nОлександра Василівна Тропак\nОлександра Тропак\nТропак Олександра Василівна\nVolkswagen Golf\n2007\n9800\n2015\nVolkswagen Golf\n2007\n9800\n2015\nТропак Олександра Василівна\nОлександра Василівна Тропак\nОлександра Тропак\nТропак Олександра Василівна\nОлександра\nТропак Олександра Василівна\nТропак\nЗагальний апеляційний суд\nсуддя апеляційного суду львівської області\nЛьвівська область\nВасилівна\n207612\nпенсія\n7975\n215587\n5807\n31\n26.55\n50.5\n5807\n31\n26.55\n50.5\nВасилівна\nТропак\nОлександра\nТропак Олександра Василівна\nОлександра Василівна Тропак\nОлександра Тропак\nТропак Олександра Василівна\nсуддя апеляційного суду львівської області\nЗагальний апеляційний суд\nЛьвівська область\nТропак Олександра Василівна\n207612\n215587\nпенсія\n7975\n2007\nVolkswagen Golf\nпенсія\n7975\n215587\n207612\n50.5\n5807\n26.55\n31\n9800\n2015","general":{"inn":"","name":"Олександра","inn_unclear":false,"patronymic":"Василівна","inn_hidden":true,"family_raw":"","last_name":"Тропак","post":{"region":"Львівська область","region_unclear":false,"post":"суддя апеляційного суду львівської області","office_unclear":false,"office":"Загальний апеляційний суд"},"full_name":"Тропак Олександра Василівна","addresses":[{"place_district":"","place_city_hidden":true,"place_city":"","place_city_type_hidden":true,"place_district_hidden":true,"place_city_type":"","place_address_hidden":true,"place_address":"","place_hidden":true,"place":""}],"patronymic_hidden":false,"full_name_suggest":{"output":"Тропак Олександра Василівна","input":["Тропак Олександра Василівна","Олександра Василівна Тропак","Олександра Тропак"]}},"source":"VULYK","estate":{"23":[{"space_unclear":false,"costs":"","costs_comment":"","address_hidden":true,"region_hidden":true,"space_comment":"","space_hidden":false,"space":"5807","address":"","costs_comment_unclear":false,"region":"","space_units_unclear":false,"space_units":"м²","costs_rent":"","costs_rent_comment":""}],"24":[{"space_unclear":false,"costs":"","costs_comment":"","address_hidden":true,"region_hidden":true,"space_comment":"","space":"26.55","address":"","region":"","costs_rent_comment":"","space_units":"м²","costs_rent":""}],"25":[{"space_unclear":false,"costs":"","costs_comment":"","address_hidden":true,"region_hidden":true,"space_comment":"","space_hidden":false,"space":"50.5","address":"","region":"","costs_rent_comment":"","space_comment_unclear":false,"space_units":"м²","costs_rent":""}],"27":[{"space_hidden":false,"costs":"","costs_comment":"","address_hidden":true,"region_hidden":true,"space_comment":"","space":"31","address":"","region":"","costs_rent_comment":"","space_units":"м²","costs_rent":""}]},"intro":{"declaration_year":"2015"}}