{"income":{"5":{"value":"251001.36","family_comment":"","value_unclear":false,"comment_hidden":false,"family_hidden":false,"family":"","value_hidden":false,"family_unclear":false,"comment_unclear":false,"comment":"","family_comment_unclear":false},"6":{"value":"239531.36","family_unclear":false,"family_hidden":false,"family_comment":"","family":"","comment":""},"7":{"family_comment":"","value":"","source_name":"","family":"","comment":""},"8":{"family_comment":"","value":"","value_unclear":false,"family":"","comment":""},"9":{"value":"","family_unclear":false,"family_hidden":false,"family_comment":"","family":"","comment":""},"10":{"family_comment":"","value":"11470","value_unclear":false,"family":"","comment":""},"11":{"value":"","value_unclear":false,"family_hidden":false,"value_hidden":false,"family_comment":"","family":"","comment":""},"12":{"family_comment":"","value":"","family":"","comment":""},"13":{"family_comment":"","value":"","value_unclear":false,"family":"","comment":""},"14":{"family_comment":"","value":"","family":"","comment":""},"15":{"family_comment":"","value":"","value_unclear":false,"family":"","comment":""},"16":{"family_comment":"","value":"","family":"","comment":""},"17":{"family_comment":"","value":"","family":"","comment":""},"18":{"family_comment":"","value":"","family":"","comment":""},"19":{"family_comment":"","value":"","family":"","comment":""},"20":{"family_comment":"","value":"","value_unclear":false,"family":"","comment":""}},"vehicle":{"35":[{"brand_info":"2000 куб.см.","sum_rent_comment":"","brand_info_unclear":false,"year":"2007","sum_hidden":false,"sum_rent_comment_unclear":false,"sum_rent":"","sum":"","brand":"Mitsubishi Lancer","sum_comment":"так","brand_unclear":false,"brand_hidden":false,"sum_unclear":false},{"brand_info":"1700 куб.см.","sum_rent_comment":"","brand":"ВАЗ-21214 Нива","sum_comment":"","year":"2011","brand_hidden":false,"year_unclear":true,"sum":"","sum_rent":""}]},"id":"vulyk_54_168","banks":{"45":[{"sum_foreign_comment":"","sum_units":"UAH","sum_comment":"","sum_comment_unclear":false,"sum_hidden":false,"sum_foreign_units":"UAH","sum_units_unclear":false,"sum_comment_hidden":false,"sum_unclear":false,"sum":"","sum_foreign":""},{"sum_foreign_comment":"","sum_units":"","sum_comment":"","sum_comment_unclear":false,"sum_foreign_units":"","sum":"","sum_foreign":""},{"sum_foreign_comment":"","sum_units":"","sum_comment":"","sum_foreign_units":"","sum":"","sum_foreign":""}],"46":[{"sum_foreign_comment":"","sum_units":"UAH","sum_comment":"","sum_comment_unclear":false,"sum_foreign_units":"UAH","sum":"","sum_foreign":""},{"sum_foreign_comment":"","sum_units":"","sum_comment":"","sum_foreign_units":"","sum":"","sum_foreign":""}],"47":[{"sum_foreign_comment":"","sum_units":"UAH","sum_comment":"","sum_comment_unclear":false,"sum_foreign_units":"UAH","sum":"","sum_foreign":""},{"sum_foreign_comment":"","sum_units":"","sum_comment":"","sum":"","sum_foreign":""}],"48":[{"sum_foreign_comment":"","sum_units":"UAH","sum_comment":"","sum_foreign_units":"UAH","sum":"","sum_foreign":""}],"49":[{"sum_foreign_comment":"","sum_units":"UAH","sum_comment":"","sum_comment_unclear":false,"sum_foreign_units":"UAH","sum":"","sum_foreign":""}],"50":[{"sum_foreign_comment":"","sum_units":"UAH","sum_comment":"","sum_foreign_units":"UAH","sum":"","sum_foreign":""}],"51":[{"sum_foreign_comment":"","sum_units":"UAH","sum_comment":"","sum_comment_unclear":false,"sum_hidden":false,"sum_foreign_units":"UAH","sum_comment_hidden":false,"sum":"","sum_foreign":""},{"sum_foreign_comment":"","sum_units":"","sum_comment":"","sum_foreign_units":"","sum":"","sum_foreign":""},{"sum_foreign_comment":"","sum_units":"","sum_comment":"","sum_foreign_units":"","sum":"","sum_foreign":""}],"52":[{"sum_foreign_comment":"","sum_units":"UAH","sum_comment":"","sum_comment_unclear":false,"sum_foreign_units":"UAH","sum":"","sum_foreign":""}],"53":[{"sum_foreign_comment":"","sum_units":"UAH","sum_comment":"","sum_foreign_units":"UAH","sum":"","sum_unclear":false,"sum_foreign":""}]},"declaration":{"additional_info_text":"","notfull_lostpages":"","date":"2014-03-18T00:00:00","notfull":"","additional_info":"","url":"http://static.declarations.com.ua/declarations/chosen_ones/mega_batch/yatsenko_volodymyr_vasylovych.pdf"},"liabilities":{"54":{"sum_foreign_comment":"","sum":"500","sum_comment":"","sum_comment_unclear":false,"sum_hidden":false,"sum_comment_hidden":false,"sum_unclear":false,"sum_foreign":""},"55":{"sum_foreign_comment":"","sum":"","sum_comment":"","sum_foreign":""},"56":{"sum_foreign_comment":"","sum":"22500","sum_comment":"","sum_foreign":""},"57":{"sum_foreign_comment":"","sum":"2500","sum_comment":"","sum_comment_unclear":false,"sum_comment_hidden":false,"sum_unclear":false,"sum_foreign":""},"58":{"sum_foreign_comment":"","sum":"450","sum_comment":"","sum_comment_unclear":false,"sum_comment_hidden":false,"sum_unclear":false,"sum_foreign":""},"59":{"sum_foreign_comment":"","sum_foreign_hidden":false,"sum_comment":"","sum_hidden":false,"sum_comment_hidden":false,"sum":"","sum_foreign":""},"60":{"sum_foreign_comment":"","sum":"","sum_comment":"","sum_foreign":""},"61":{"sum_foreign_comment":"","sum":"","sum_comment":"","sum_foreign":""},"62":{"sum_foreign_comment":"","sum":"","sum_comment":"","sum_foreign":""},"63":{"sum_foreign_comment":"","sum_comment_hidden":false,"sum":"","sum_comment":"","sum_foreign":""},"64":{"sum_foreign_comment":"","sum":"","sum_comment":"","sum_foreign":""}},"ft_src":"2500\n500\n450\n22500\nлубенський міськрайонний суд. суддя - заступник голови суду\nПолтавська область\nЗагальний місцевий суд\n2193705596\nВолодимир\n2427316640\nЯценко Тарас Володимирович\nДитина\n3488511145\nЯценко Оксана Володимирівна\nДитина\nВасильович\nЯценко Володимир Васильович\nВолодимир Васильович Яценко\nВолодимир Яценко\nЯценко Володимир Васильович\nЯценко Володимир Васильович\nЯценко\nЛубни\nвул. Достоєвського, 5, кв. 59, 315500\nПолтавська область\nтак\n2000 куб.см.\nMitsubishi Lancer\n2007\n1700 куб.см.\nВАЗ-21214 Нива\n2011\n2013\n2000 куб.см.\nтак\nMitsubishi Lancer\n2007\n1700 куб.см.\n2011\nВАЗ-21214 Нива\n59\nприватизована\nПолтавська область\nм. Лубни, вул. Достоєвського, 5, кв. 59\nДитина\nЯценко Тарас Володимирович\n2427316640\nДитина\nЯценко Оксана Володимирівна\n3488511145\nЯценко Володимир Васильович\nВолодимир Васильович Яценко\nВолодимир Яценко\nЯценко Володимир Васильович\nЯценко Володимир Васильович\n2193705596\nВолодимир\nВасильович\nЗагальний місцевий суд\nПолтавська область\nлубенський міськрайонний суд. суддя - заступник голови суду\nЯценко\nвул. Достоєвського, 5, кв. 59, 315500\nПолтавська область\nЛубни\n2500\n22500\n450\n500\n239531.36\n251001.36\n11470\n2013\n450\n2500\n22500\n500\nприватизована\n59\nПолтавська область\nм. Лубни, вул. Достоєвського, 5, кв. 59\n2427316640\nДитина\nЯценко Тарас Володимирович\n3488511145\nЯценко Оксана Володимирівна\nДитина\n2193705596\nВасильович\nЯценко\nВолодимир\nЯценко Володимир Васильович\nВолодимир Васильович Яценко\nВолодимир Яценко\nЯценко Володимир Васильович\nвул. Достоєвського, 5, кв. 59, 315500\nЛубни\nПолтавська область\nПолтавська область\nЗагальний місцевий суд\nлубенський міськрайонний суд. суддя - заступник голови суду\nЯценко Володимир Васильович\n239531.36\n11470\n251001.36\n2007\nMitsubishi Lancer\nтак\n2000 куб.см.\nВАЗ-21214 Нива\n1700 куб.см.\n2011\n11470\n251001.36\n239531.36\n59\nм. Лубни, вул. Достоєвського, 5, кв. 59\nПолтавська область\nприватизована\n2013","general":{"inn":"2193705596","name":"Володимир","patronymic_unclear":false,"family":[{"inn":"2427316640","inn_hidden":false,"relations_unclear":false,"relations_hidden":false,"relations_other":"","relations":"Дитина","name_hidden":false,"inn_unclear":false,"family_name":"Яценко Тарас Володимирович","name_unclear":false},{"inn":"3488511145","inn_hidden":false,"relations_hidden":false,"family_name":"Яценко Оксана Володимирівна","relations_other":"","relations":"Дитина","name_hidden":false,"name_unclear":false}],"patronymic":"Васильович","inn_hidden":false,"family_raw":"","inn_unclear":false,"post":{"post_unclear":false,"region_unclear":false,"post":"лубенський міськрайонний суд. суддя - заступник голови суду","office":"Загальний місцевий суд","region":"Полтавська область","post_hidden":false,"office_hidden":false,"office_unclear":false,"region_hidden":false},"full_name_suggest":{"output":"Яценко Володимир Васильович","input":["Яценко Володимир Васильович","Володимир Васильович Яценко","Володимир Яценко"]},"full_name":"Яценко Володимир Васильович","addresses":[{"place_district":"","place_city_hidden":false,"place_city":"Лубни","place_city_unclear":false,"place_district_hidden":false,"place_city_type":"Місто","place_address_hidden":false,"place_city_type_hidden":false,"place_address":"вул. Достоєвського, 5, кв. 59, 315500","place_hidden":false,"place":"Полтавська область"}],"last_name":"Яценко","last_name_unclear":false,"name_unclear":false},"source":"VULYK","estate":{"23":[{"space_unclear":false,"costs":"","costs_comment":"","costs_hidden":false,"address_hidden":false,"region_hidden":false,"space_comment":"","space":"","address":"","region":"","address_unclear":false,"costs_rent_comment":"","space_units":"м²","costs_rent":""},{"space":"","region":"","costs":"","costs_rent_comment":"","costs_comment":"","region_hidden":false,"address_unclear":false,"space_comment":"","space_units":"","costs_rent":"","address":""},{"costs_rent":"","region":"","costs":"","costs_rent_comment":"","costs_comment":"","space_comment":"","space_units":"","space":"","address":""},{"costs_rent":"","costs":"","costs_rent_comment":"","costs_comment":"","space_comment":"","space_units":"","space":"","address":""}],"25":[{"space_unclear":false,"costs":"","costs_comment":"приватизована","address_hidden":false,"region_hidden":false,"space_comment":"","space_hidden":false,"space":"59","address":"м. Лубни, вул. Достоєвського, 5, кв. 59","costs_comment_unclear":false,"region":"Полтавська область","address_unclear":false,"costs_rent_comment":"","costs_rent_hidden":false,"space_comment_unclear":false,"space_comment_hidden":false,"space_units":"м²","costs_rent":""}]},"intro":{"declaration_year":"2013","declaration_year_unclear":false}}