{"income":{"5":{"value":"232811","family_comment":"","value_unclear":false,"family":"87188","family_unclear":false,"comment_unclear":false,"comment":"","family_comment_unclear":false},"6":{"value":"232811","family_comment":"","value_unclear":false,"family_unclear":false,"family":"","comment":""},"7":{"source_name_unclear":false,"value":"","value_unclear":false,"family_comment":"","source_name":"","family":"","comment":"","source_name_hidden":false},"8":{"family_comment":"","value":"","family":"","comment":""},"9":{"family_comment":"","value":"","family":"","comment":""},"10":{"family_comment":"","value":"","value_unclear":false,"family":"","comment":""},"11":{"value":"","value_unclear":false,"value_hidden":false,"family_comment":"","family":"","comment":""},"12":{"family_comment":"","value":"","family":"","comment":"","value_hidden":false},"13":{"family_comment":"","value":"","family":"","comment":""},"14":{"family_comment":"","value":"","family":"","comment":""},"15":{"family_comment":"","value":"","family":"","comment":""},"16":{"family_comment":"","value":"","family":"","comment":""},"17":{"family_comment":"","value":"","family":"","comment":""},"18":{"family_comment":"","value":"","family":"","comment":""},"19":{"family_comment":"","family_unclear":false,"value":"","family":"","comment":""},"20":{"family_comment":"","family_unclear":false,"value":"","family":"87188","comment":""}},"vehicle":{"35":[{"year_hidden":false,"brand_info":"1796 куб. см.","sum_rent_comment":"","year":"2004","sum_hidden":false,"brand_info_hidden":false,"brand_info_unclear":false,"year_unclear":false,"sum_rent":"","sum":"","brand":"Mercedes-Benz с180","sum_comment":"","brand_unclear":false,"brand_hidden":false}],"40":[{"brand_info":"1796 куб. см.","sum":"","brand":"Mercedes-Benz с180","sum_comment":"","brand_unclear":false,"year":"2004","brand_hidden":false,"brand_info_hidden":false,"brand_info_unclear":false,"sum_rent_comment":"","sum_rent":""}]},"id":"vulyk_61_89","banks":{"51":[{"sum_foreign_comment":"","sum_units":"UAH","sum_comment":"","sum_hidden":true,"sum_foreign_units":"UAH","sum_comment_hidden":false,"sum_unclear":true,"sum":"","sum_foreign":""}]},"declaration":{"additional_info_text":"","notfull_lostpages":"","date":"2015-03-27T00:00:00","notfull":"","additional_info":"","url":"http://static.declarations.com.ua/declarations/chosen_ones/mega_batch/ivanchenko_iaroslav_mykolaiovych.pdf"},"liabilities":{"54":{"sum_foreign_comment":"","sum":"","sum_comment":"","sum_comment_unclear":false,"sum_unclear":false,"sum_foreign":""},"55":{"sum_foreign_comment":"","sum":"","sum_comment":"","sum_foreign":""},"56":{"sum_foreign_comment":"","sum":"","sum_comment":"","sum_unclear":false,"sum_foreign":""},"57":{"sum_foreign_comment":"","sum":"1209","sum_comment":"","sum_comment_hidden":false,"sum_unclear":false,"sum_foreign":""},"58":{"sum_foreign_comment":"","sum":"505","sum_comment":"","sum_unclear":false,"sum_foreign":""},"59":{"sum_foreign_comment":"","sum":"","sum_comment":"","sum_foreign":""},"60":{"sum_foreign_comment":"","sum_foreign_hidden":false,"sum_comment":"","sum_hidden":false,"sum":"","sum_foreign":""},"61":{"sum_foreign_comment":"","sum":"","sum_comment":"","sum_foreign":""},"62":{"sum_foreign_comment":"","sum":"","sum_comment":"","sum_unclear":false,"sum_foreign":""},"63":{"sum_foreign_comment":"","sum":"13800","sum_comment":"","sum_hidden":false,"sum_unclear":false,"sum_foreign":""},"64":{"sum_foreign_comment":"","sum":"","sum_hidden":false,"sum_comment":"","sum_foreign":""}},"ft_src":"1209\n505\n13800\nсуддя вінницького міського суду вінницької області\nВінницька область\nЗагальний місцевий суд\nЯрослав\nІванченко О. Є\nПодружжя\nІванченко О. Я\nДитина\nІванченко Р. Я\nДитина\nСалій Є. І\nІнше\nбатько дружини\nМиколайович\nІванченко\nІванченко Ярослав Миколайович\nІванченко Ярослав Миколайович\nЯрослав Миколайович Іванченко\nЯрослав Іванченко\nІванченко Ярослав Миколайович\n1796 куб. см.\nMercedes-Benz с180\n2004\nMercedes-Benz с180\n1796 куб. см.\n2004\n2014\n1796 куб. см.\nMercedes-Benz с180\n2004\n1796 куб. см.\n2004\nMercedes-Benz с180\n536\n173\n90\n40\n40\nПодружжя\nІванченко О. Є\nДитина\nІванченко О. Я\nДитина\nІванченко Р. Я\nІнше\nбатько дружини\nСалій Є. І\nІванченко Ярослав Миколайович\nЯрослав Миколайович Іванченко\nЯрослав Іванченко\nІванченко Ярослав Миколайович\nЯрослав\nІванченко Ярослав Миколайович\nІванченко\nВінницька область\nЗагальний місцевий суд\nсуддя вінницького міського суду вінницької області\nМиколайович\n13800\n1209\n505\n232811\n87188\n232811\n87188\n2014\n505\n1209\n13800\n90\n40\n40\n173\n536\nІванченко О. Є\nПодружжя\nІванченко О. Я\nДитина\nІванченко Р. Я\nДитина\nбатько дружини\nСалій Є. І\nІнше\nМиколайович\nІванченко\nІванченко Ярослав Миколайович\nЯрослав Миколайович Іванченко\nЯрослав Іванченко\nІванченко Ярослав Миколайович\nВінницька область\nсуддя вінницького міського суду вінницької області\nЗагальний місцевий суд\nІванченко Ярослав Миколайович\nЯрослав\n232811\n87188\n232811\n87188\nMercedes-Benz с180\n1796 куб. см.\n2004\nMercedes-Benz с180\n1796 куб. см.\n2004\n87188\n232811\n87188\n232811\n90\n40\n40\n173\n536\n2014","general":{"inn":"","name":"Ярослав","patronymic_unclear":false,"family":[{"inn":"","inn_hidden":true,"relations_unclear":false,"relations_hidden":false,"relations_other":"","relations":"Подружжя","name_hidden":true,"family_name":"Іванченко О. Є","name_unclear":true},{"inn":"","relations":"Дитина","relations_other":"","inn_hidden":false,"family_name":"Іванченко О. Я","name_hidden":false,"name_unclear":false},{"inn":"","relations":"Дитина","relations_other":"","inn_hidden":false,"family_name":"Іванченко Р. Я","name_hidden":false,"name_unclear":false},{"inn":"","relations":"Інше","relations_other":"батько дружини","inn_hidden":false,"family_name":"Салій Є. І","name_hidden":false,"name_unclear":false}],"patronymic":"Миколайович","inn_hidden":true,"family_raw":"","inn_unclear":false,"post":{"post_unclear":false,"region_unclear":false,"post":"суддя вінницького міського суду вінницької області","office":"Загальний місцевий суд","region":"Вінницька область","post_hidden":false,"office_hidden":false,"region_hidden":false},"last_name_unclear":false,"full_name":"Іванченко Ярослав Миколайович","addresses":[{"place_address":"","place_district_hidden":true,"place_city_type":"","place_city_hidden":true,"place_address_unclear":false,"place_city_type_hidden":true,"place_hidden":true,"place":"","place_district":"","place_address_hidden":true,"place_city":"","place_district_unclear":false}],"last_name":"Іванченко","patronymic_hidden":false,"full_name_suggest":{"output":"Іванченко Ярослав Миколайович","input":["Іванченко Ярослав Миколайович","Ярослав Миколайович Іванченко","Ярослав Іванченко"]},"name_unclear":false},"source":"VULYK","estate":{"23":[{"region_unclear":false,"space_unclear":true,"costs":"","costs_comment":"","address_hidden":true,"region_hidden":true,"space_comment":"","space":"","address":"","region":"","address_unclear":false,"costs_rent_comment":"","space_comment_unclear":false,"space_units":"м²","space_units_unclear":false,"costs_rent":""}],"24":[{"region_unclear":false,"space_unclear":false,"costs":"","costs_comment":"","address_hidden":true,"region_hidden":true,"space_comment":"","space_hidden":false,"space":"","address":"","region":"","address_unclear":false,"costs_rent_comment":"","space_comment_unclear":false,"space_units":"м²","costs_rent":""}],"29":[{"space_hidden":false,"costs_property":"","address_hidden":true,"region_hidden":true,"space_comment":"","space_units_hidden":false,"space_unclear":true,"space_units_unclear":false,"address":"","region":"","address_unclear":false,"space":"536","space_comment_hidden":false,"space_units":"м²","costs_property_comment":"","costs_rent":"","costs_rent_comment":""}],"30":[{"space_hidden":false,"costs_property":"","address_hidden":true,"region_hidden":true,"space_comment":"","space_units_hidden":false,"space":"173","address":"","region":"","address_unclear":false,"costs_rent_comment":"","space_comment_unclear":false,"space_comment_hidden":false,"space_units":"м²","costs_property_comment":"","costs_rent":""}],"31":[{"space_unclear":false,"address_hidden":true,"region_hidden":true,"space_comment":"","space_hidden":false,"space":"90","address":"","region":"","costs_property":"","costs_rent_comment":"","space_comment_unclear":false,"space_units":"м²","costs_property_comment":"","costs_rent":""},{"costs_rent":"","region":"","costs_property":"","costs_rent_comment":"","address_hidden":false,"region_hidden":false,"space_comment":"","costs_property_comment":"","space_units":"м²","space":"40","address":""},{"costs_rent":"","costs_property":"","costs_rent_comment":"","space_comment":"","costs_property_comment":"","space_units":"м²","space":"40","address":""}]},"intro":{"declaration_year":"2014","isnotdeclaration":"","declaration_year_hidden":false}}