{"id":"vulyk_84_43","ft_src":"ЗАЗ 968\n1.2 л\n1999\n270000\nToyota Avensis\n2006\nМиколаївська область\nВеселинівський р-н Зеленівська с/р\n2\nМиколаївська область\nВеселинівський р-н Зеленівська с/р\n2\nсмт. Веселинове, вул. Перемоги 10\n596\nМиколаївська область\nМиколаївська область\nсмт. Веселинове\n73.1\nМиколаївська область\nВеселенівський р-н с. Кудрявцівка\n72.1\nМиколаївська область\nВеселенівський р-н с. Широколанівка\n52.4\nсмт. Веселинове, вул. Перемоги 10\n114\nМиколаївська область\n1143\nOTHER\n2014\n1.2 л\nЗАЗ 968\n1999\nToyota Avensis\n2006\n270000\n2014\nКучерявенко Сергій Степанович\nСергій Степанович Кучерявенко\nСергій Кучерявенко\nКучерявенко Сергій Степанович\nСергій\nПодружжя\nКучерявенко Л. В\nЕР 089282\nКучерявенко Сергій Степанович\nСтепанович\nголова веселинівського районного суду миколаївської області\nЗагальний місцевий суд\nМиколаївська область\nКучерявенко\n226913\n7300\n951000\n246393\n951000\n12180\n2\nМиколаївська область\nВеселинівський р-н Зеленівська с/р\n596\nМиколаївська область\nсмт. Веселинове, вул. Перемоги 10\nВеселинівський р-н Зеленівська с/р\n2\nМиколаївська область\n114\nМиколаївська область\nсмт. Веселинове, вул. Перемоги 10\nсмт. Веселинове\nМиколаївська область\n73.1\nВеселенівський р-н с. Кудрявцівка\n72.1\nМиколаївська область\nВеселенівський р-н с. Широколанівка\n52.4\nМиколаївська область\nOTHER\n1143\n226913\n12180\n951000\n246393\n951000\n7300\nЕР 089282\nКучерявенко Л. В\nПодружжя\nСтепанович\nКучерявенко\nСергій\nКучерявенко Сергій Степанович\nСергій Степанович Кучерявенко\nСергій Кучерявенко\nКучерявенко Сергій Степанович\nМиколаївська область\nголова веселинівського районного суду миколаївської області\nЗагальний місцевий суд\nКучерявенко Сергій Степанович","estate":{"23":[{"address":"Веселинівський р-н Зеленівська с/р","space_units":"га","costs_comment":"","space_comment":"","region_hidden":false,"region":"Миколаївська область","address_hidden":false,"costs":"","address_unclear":false,"space_comment_unclear":false,"costs_rent_comment":"","space":"2","region_unclear":true,"costs_rent":""},{"address":"смт. Веселинове, вул. Перемоги 10","space_units":"м²","costs_comment":"","region_hidden":false,"space_comment":"","address_hidden":false,"space":"596","address_unclear":true,"space_comment_unclear":false,"costs_rent_comment":"","costs":"","region":"Миколаївська область","costs_rent":""}],"24":[{"address":"смт. Веселинове, вул. Перемоги 10","space_units":"м²","space_hidden":false,"space_unclear":false,"region_hidden":false,"costs_comment":"","space_comment":"","address_hidden":false,"costs":"","address_unclear":false,"costs_rent_comment":"","space":"114","region_unclear":true,"region":"Миколаївська область","costs_rent":""}],"29":[{"costs_property_comment":"","address":"Веселинівський р-н Зеленівська с/р","space_units":"га","space_comment":"","region_hidden":false,"costs_property":"","region":"Миколаївська область","address_hidden":false,"address_unclear":false,"costs_rent_comment":"","space":"2","region_unclear":true,"costs_rent":""}],"34":[{"costs_property_comment":"","address":"смт. Веселинове","space_units":"м²","space_unclear":false,"region_hidden":false,"costs_property":"","space_comment":"","address_hidden":false,"space_comment_hidden":false,"costs_rent_comment":"","space":"73.1","region":"Миколаївська область","costs_rent":""},{"costs_property_comment":"","address":"Веселенівський р-н с. Кудрявцівка","space_units":"м²","space_comment":"","costs_property":"","region":"Миколаївська область","address_hidden":false,"address_unclear":false,"costs_rent_comment":"","space":"72.1","region_unclear":false,"costs_rent":""},{"costs_property_comment":"","address":"Веселенівський р-н с. Широколанівка","space_units":"м²","space_comment":"","costs_property":"","region":"Миколаївська область","address_hidden":false,"address_unclear":false,"costs_rent_comment":"","space":"52.4","region_unclear":false,"costs_rent":""}]},"vehicle":{"35":[{"year_hidden":false,"brand_info":"1.2 л","sum_rent_comment":"","brand_unclear":false,"brand_hidden":false,"year":"1999","brand":"ЗАЗ 968","brand_info_hidden":false,"sum_rent":"","year_unclear":false,"sum_comment":"","sum_hidden":false,"brand_info_unclear":false,"sum":""},{"sum_comment":"","brand_info_hidden":true,"brand_info":"","sum":"270000","sum_rent_comment":"","brand_hidden":false,"brand":"Toyota Avensis","sum_rent":"","year":"2006","year_unclear":false}]},"source":"VULYK","income":{"5":{"family_comment":"","family":"951000","comment":"","value_unclear":false,"family_unclear":false,"comment_unclear":false,"value":"246393"},"6":{"family_comment":"","comment_unclear":false,"value":"226913","family":"","comment":""},"7":{"family":"","family_comment":"","value":"","comment":"","source_name":""},"8":{"family_comment":"","value":"","family":"","comment":""},"9":{"family_comment":"","value":"","family":"","comment":"","value_unclear":false},"10":{"family_comment":"","value":"12180","family":"","comment":"","value_unclear":false},"11":{"family_comment":"","value":"","family":"","comment":""},"12":{"family_comment":"","value":"","family":"","comment":""},"13":{"family_comment":"","value":"","family":"","comment":""},"14":{"family_comment":"","value":"","family":"","comment":""},"15":{"family_comment":"","value":"","family":"","comment":""},"16":{"family_comment":"","value":"","family":"","comment":""},"17":{"family_comment":"","value":"","family":"951000","comment":"","value_unclear":false},"18":{"family_comment":"","value":"","family":"","comment":"","value_unclear":false},"19":{"family_comment":"","value":"","family":"","comment":""},"20":{"family_comment":"","family":"","comment":"","value_unclear":false,"family_unclear":false,"comment_unclear":false,"value":"7300"}},"banks":{"45":[{"sum_comment_unclear":false,"sum_comment":"","sum_foreign_units":"UAH","sum":"1143","sum_foreign_comment":"","sum_foreign":"","sum_unclear":false,"sum_units":"OTHER"}]},"declaration":{"notfull_lostpages":"","additional_info_text":"","additional_info":"","date":"2015-03-20T00:00:00","notfull":"","url":"http://static.declarations.com.ua/declarations/chosen_ones/judges_batch/2457_kucheriavenko_serhii_stepanovych.pdf"},"general":{"family_raw":"","name":"Сергій","full_name_suggest":{"input":["Кучерявенко Сергій Степанович","Сергій Степанович Кучерявенко","Сергій Кучерявенко"],"output":"Кучерявенко Сергій Степанович"},"patronymic":"Степанович","inn_hidden":true,"addresses":[{"place_city_type_hidden":false,"place_district_hidden":false,"place_address_unclear":false,"place":"","place_city":"","place_unclear":false,"place_city_type_unclear":false,"place_city_type":"","place_city_hidden":false,"place_city_unclear":false,"place_district":"","place_district_unclear":false,"place_address":"","place_address_hidden":false,"place_hidden":true}],"inn":"","inn_unclear":false,"last_name":"Кучерявенко","full_name":"Кучерявенко Сергій Степанович","family":[{"inn":"ЕР 089282","inn_unclear":true,"family_name":"Кучерявенко Л. В","relations_other":"","relations_hidden":false,"name_unclear":true,"inn_hidden":false,"name_hidden":false,"relations":"Подружжя"}],"post":{"post_hidden":false,"office":"Загальний місцевий суд","region_hidden":false,"post":"голова веселинівського районного суду миколаївської області","candidate":"","region_unclear":false,"region":"Миколаївська область","office_hidden":false,"post_unclear":false,"office_unclear":false}},"liabilities":{"54":{"sum_comment":"","sum_foreign_comment":"","sum_foreign":"","sum":"","sum_comment_hidden":false},"55":{"sum_comment":"","sum_foreign_comment":"","sum_foreign":"","sum":""},"56":{"sum_comment":"","sum_foreign_comment":"","sum_foreign":"","sum":""},"57":{"sum_comment":"","sum_foreign_comment":"","sum_foreign":"","sum":"","sum_comment_hidden":false},"58":{"sum_comment":"","sum_foreign_comment":"","sum_foreign":"","sum":"","sum_comment_hidden":false},"59":{"sum_comment":"","sum_foreign_comment":"","sum_foreign":"","sum":""},"60":{"sum_comment":"","sum_foreign_comment":"","sum_foreign":"","sum":""},"61":{"sum_comment":"","sum_foreign_comment":"","sum_foreign":"","sum":""},"62":{"sum_comment":"","sum_foreign_comment":"","sum_foreign":"","sum":""},"63":{"sum_comment":"","sum_foreign_comment":"","sum_foreign":"","sum":"","sum_comment_hidden":false},"64":{"sum_comment":"","sum_foreign_comment":"","sum_foreign":"","sum":"","sum_comment_hidden":false}},"intro":{"isnotdeclaration":"","declaration_year_unclear":false,"declaration_year":"2014"}}