{"income":{"5":{"value":"350591","family_hidden":false,"value_hidden":false,"family_comment":"","family":"","comment":""},"6":{"family_comment":"","value":"250921","family":"","comment":""},"7":{"family_comment":"","value":"","source_name":"","family":"","comment":""},"8":{"family_comment":"","value":"","family":"","comment":""},"9":{"family_comment":"","value":"","family":"","comment":""},"10":{"family_comment":"","value":"","family":"","comment":""},"11":{"family_comment":"","value":"","family":"","comment":""},"12":{"family_comment":"","value":"","family":"","comment":""},"13":{"family_comment":"","value":"","family":"","comment":""},"14":{"family_comment":"","value":"","family":"","comment":""},"15":{"family_comment":"","value":"","family":"","comment":""},"16":{"family_comment":"","value":"99670","family":"","comment":""},"17":{"family_comment":"","value":"","family":"","comment":""},"18":{"family_comment":"","value":"","family":"","comment":""},"19":{"family_comment":"","value":"","family":"","comment":""},"20":{"family_comment":"","value":"","family":"","comment":""}},"id":"vulyk_89_25","declaration":{"date":"2015-03-25T00:00:00","notfull":"","url":"http://static.declarations.com.ua/declarations/chosen_ones/judges_batch/3028_khilchuk_ivan_ivanovych.pdf","notfull_lostpages":""},"liabilities":{"54":{"sum_foreign_comment":"","sum":"","sum_comment":"","sum_foreign":""},"55":{"sum_foreign_comment":"","sum":"20000","sum_comment":"","sum_foreign":""},"56":{"sum_foreign_comment":"","sum":"","sum_comment":"","sum_unclear":false,"sum_foreign":""},"57":{"sum_foreign_comment":"","sum":"","sum_comment":"","sum_foreign":""},"58":{"sum_foreign_comment":"","sum":"","sum_comment":"","sum_foreign":""},"59":{"sum_foreign_comment":"","sum":"","sum_comment":"","sum_foreign":""},"60":{"sum_foreign_comment":"","sum":"","sum_comment":"","sum_foreign":""},"61":{"sum_foreign_comment":"","sum":"","sum_comment":"","sum_foreign":""},"62":{"sum_foreign_comment":"","sum":"","sum_comment":"","sum_unclear":false,"sum_foreign":""},"63":{"sum_foreign_comment":"","sum":"","sum_comment":"","sum_foreign":""},"64":{"sum_foreign_comment":"","sum":"","sum_comment":"","sum_foreign":""}},"ft_src":"20000\nКоломия\n78200\nІвано-Франківська область\nІванович\nХільчук Іван Іванович\nсуддя коломийського міськрайонного суду івано-франківської області\nІвано-Франківська область\nЗагальний місцевий суд\nІван\nХільчук Іван Іванович\nІван Іванович Хільчук\nІван Хільчук\nХільчук Іван Іванович\nХільчук\n350591\n99670\n250921\nІвано-Франківська область\nс. Солів\n1437\nІвано-Франківська область\nс. Стружків\n4000\nм. Коломия\n800\nІвано-Франківська область\nІвано-Франківська область\nс. Сопів\n1/5 частина квартири\n4500\nм. Коломия\n86.9\nІвано-Франківська область\n2014\n250921\n350591\n99670\n1437\nІвано-Франківська область\nс. Солів\nс. Стружків\n4000\nІвано-Франківська область\nм. Коломия\n800\nІвано-Франківська область\nс. Сопів\nІвано-Франківська область\n86.9\n1/5 частина квартири\nІвано-Франківська область\n4500\nм. Коломия\nІвано-Франківська область\nсуддя коломийського міськрайонного суду івано-франківської області\nЗагальний місцевий суд\nІванович\nХільчук Іван Іванович\nІван Іванович Хільчук\nІван Хільчук\nХільчук Іван Іванович\nХільчук Іван Іванович\n78200\nІвано-Франківська область\nКоломия\nІван\nХільчук\n20000\n250921\n350591\n99670\n2014\n20000\nІванович\nІвано-Франківська область\nКоломия\n78200\nХільчук\nсуддя коломийського міськрайонного суду івано-франківської області\nІвано-Франківська область\nЗагальний місцевий суд\nХільчук Іван Іванович\nХільчук Іван Іванович\nІван Іванович Хільчук\nІван Хільчук\nХільчук Іван Іванович\nІван\n4500\n1/5 частина квартири\nм. Коломия\nІвано-Франківська область\n86.9\nс. Солів\nІвано-Франківська область\n1437\nс. Стружків\nІвано-Франківська область\n4000\nм. Коломия\nІвано-Франківська область\n800\nс. Сопів\nІвано-Франківська область\n2014","general":{"inn":"","inn_hidden":true,"last_name":"Хільчук","post":{"office":"Загальний місцевий суд","region":"Івано-Франківська область","post":"суддя коломийського міськрайонного суду івано-франківської області"},"name":"Іван","full_name":"Хільчук Іван Іванович","family_raw":"","addresses":[{"place_district":"","place_city_hidden":false,"place_city":"Коломия","place_city_type_hidden":false,"place_district_hidden":false,"place_city_type":"Місто","place_address_hidden":true,"place_address":"78200","place_hidden":false,"place":"Івано-Франківська область"}],"full_name_suggest":{"output":"Хільчук Іван Іванович","input":["Хільчук Іван Іванович","Іван Іванович Хільчук","Іван Хільчук"]},"patronymic":"Іванович"},"source":"VULYK","estate":{"23":[{"costs":"","costs_comment":"","address_hidden":false,"region_hidden":false,"space_comment":"","space":"1437","address":"с. Солів","region":"Івано-Франківська область","address_unclear":true,"costs_rent_comment":"","space_units":"м²","costs_rent":""},{"space":"4000","region":"Івано-Франківська область","costs":"","costs_rent_comment":"","costs_comment":"","address_unclear":true,"space_comment":"","space_units":"м²","costs_rent":"","address":"с. Стружків"},{"costs_rent":"","region":"Івано-Франківська область","costs":"","costs_rent_comment":"","costs_comment":"","address_hidden":true,"space_comment":"","space_units":"м²","space":"800","address":"м. Коломия"}],"25":[{"costs":"","costs_comment":"","address_hidden":true,"region_hidden":false,"space_comment":"1/5 частина квартири","space":"86.9","address":"м. Коломия","region":"Івано-Франківська область","costs_rent_comment":"","space_comment_unclear":false,"space_units":"м²","costs_rent":"4500"}],"26":[{"space_hidden":true,"costs":"","costs_comment":"","address_hidden":true,"space_comment":"","space":"","address":"с. Сопів","region":"Івано-Франківська область","address_unclear":true,"costs_rent_comment":"","space_units":"м²","costs_rent":""}]},"intro":{"declaration_year":"2014"}}