{"income":{"5":{"family_comment":"","value":"290264","family":"80044","comment":""},"6":{"family_comment":"","value":"218057","family":"74222","comment":"","family_hidden":false},"7":{"family_comment":"","value":"","source_name":"","family":"","comment":""},"8":{"family_comment":"","value":"","family":"","comment":""},"9":{"value":"92","value_unclear":false,"family_hidden":false,"family_comment":"","family":"","comment":""},"10":{"value":"","family_comment":"","family_hidden":false,"value_hidden":false,"family_unclear":false,"family":"5822","comment":""},"11":{"family_comment":"","value":"","family":"","comment":""},"12":{"family_comment":"","value":"","family":"","comment":""},"13":{"family_comment":"","value":"","family":"","comment":""},"14":{"family_comment":"","value":"","family":"","comment":""},"15":{"family_comment":"","value":"","family":"","comment":""},"16":{"family_comment":"","value":"","family":"","comment":""},"17":{"family_comment":"","value":"","family":"","comment":""},"18":{"family_comment":"","value":"","family":"","comment":""},"19":{"family_comment":"","value":"","family":"","comment":""},"20":{"value":"72115","comment_unclear":false,"family_comment":"","family":"","comment":"","family_comment_unclear":false}},"vehicle":{"40":[{"brand_info":"1498 куб. см., 109 к. с. 457 см","sum_rent_comment":"","brand":"Mitsubishi Lancer","sum_comment":"","year":"2008","brand_info_unclear":false,"sum":"","sum_rent":""}]},"id":"vulyk_75_27","banks":{"45":[{"sum_foreign_comment":"","sum_unclear":false,"sum":"4061","sum_comment":"","sum_comment_unclear":false,"sum_foreign_units":"UAH","sum_units":"UAH","sum_foreign":""}],"51":[{"sum_foreign_comment":"","sum":"2313","sum_comment":"","sum_foreign_units":"UAH","sum_units":"UAH","sum_foreign":""}]},"declaration":{"additional_info_text":"","notfull_lostpages":"3, 5, 6","date":"2015-03-26T00:00:00","notfull":"1","additional_info":"","url":"http://static.declarations.com.ua/declarations/chosen_ones/judges_batch/1908_myshkina_maryna_albertivna.pdf"},"liabilities":{"54":{"sum_foreign_comment":"","sum":"","sum_comment":"","sum_foreign":""},"55":{"sum_foreign_comment":"","sum":"","sum_comment":"","sum_foreign":""},"56":{"sum_foreign_comment":"","sum":"","sum_comment":"","sum_foreign":""},"57":{"sum_foreign_comment":"","sum":"14387","sum_comment":"","sum_foreign":""},"58":{"sum_foreign_comment":"","sum":"2910","sum_comment":"","sum_foreign":""},"59":{"sum_foreign_comment":"","sum":"","sum_comment":"","sum_comment_unclear":false,"sum_unclear":false,"sum_foreign":""},"60":{"sum_foreign_comment":"","sum":"","sum_comment":"","sum_foreign":""},"61":{"sum_foreign_comment":"","sum":"","sum_comment":"","sum_foreign":""},"62":{"sum_foreign_comment":"","sum":"","sum_comment":"","sum_unclear":false,"sum_foreign":""},"63":{"sum_foreign_comment":"","sum":"","sum_comment":"","sum_foreign":""},"64":{"sum_foreign_comment":"","sum":"","sum_comment":"","sum_foreign":""}},"ft_src":"1498 куб. см., 109 к. с. 457 см\n2008\nMitsubishi Lancer\n2313\n4061\n3, 5, 6\n1\n2014\n1498 куб. см., 109 к. с. 457 см\n2008\nMitsubishi Lancer\n3, 5, 6\n1\n4061\n2313\n2014\nМишкіна\nАльбертівна\nДитина\nАракелян Размік Мінасович\nМишкіна Марина Альбертівна\nМарина Альбертівна Мишкіна\nМарина Мишкіна\nМишкіна Марина Альбертівна\nМарина\nМишкіна Марина Альбертівна\nАпеляційний господарський суд\nсуддя, секретар палати одеського апеляційного господарського суду\nОдеська область\n2910\n14387\n218057\n74222\n72115\n290264\n80044\n92\n5822\n2340\n382.8\n116\n2910\n14387\n2340\n382.8\n116\nАракелян Размік Мінасович\nДитина\nМишкіна\nАльбертівна\nсуддя, секретар палати одеського апеляційного господарського суду\nОдеська область\nАпеляційний господарський суд\nМишкіна Марина Альбертівна\nМишкіна Марина Альбертівна\nМарина Альбертівна Мишкіна\nМарина Мишкіна\nМишкіна Марина Альбертівна\nМарина\n74222\n218057\n92\n5822\n80044\n290264\n72115","general":{"inn_hidden":true,"inn":"","last_name":"Мишкіна","post":{"office":"Апеляційний господарський суд","region":"Одеська область","post":"суддя, секретар палати одеського апеляційного господарського суду"},"name":"Марина","full_name":"Мишкіна Марина Альбертівна","family_raw":"","addresses":[{"place_district":"","place_address_hidden":false,"place_hidden":true,"place_address":"","place_district_hidden":true,"place_city_type":"","place_city_hidden":false,"place_city_type_hidden":false,"place_city":"","place":""}],"family":[{"inn":"","inn_hidden":false,"relations_hidden":false,"family_name":"Аракелян Размік Мінасович","relations_other":"","relations":"Дитина","name_hidden":false,"name_unclear":false}],"full_name_suggest":{"output":"Мишкіна Марина Альбертівна","input":["Мишкіна Марина Альбертівна","Марина Альбертівна Мишкіна","Марина Мишкіна"]},"patronymic":"Альбертівна"},"source":"VULYK","estate":{"23":[{"costs":"","costs_comment":"","address_hidden":false,"region_hidden":true,"space_comment":"","space":"2340","address":"","region":"","costs_rent_comment":"","space_units":"м²","space_units_hidden":false,"costs_rent":""}],"24":[{"costs_rent":"","region":"","costs":"","costs_rent_comment":"","costs_comment":"","region_hidden":true,"space_comment":"","space_units":"м²","space":"382.8","address":""}],"25":[{"space_unclear":false,"costs":"","costs_comment":"","address_hidden":false,"region_hidden":true,"space_comment":"","space_hidden":false,"space":"116","address":"","region":"","costs_rent_comment":"","space_units":"м²","costs_rent":""}]},"intro":{"declaration_year":"2014","isnotdeclaration":""}}