{"income":{"5":{"value":"181140","family_comment":"","value_unclear":false,"family_unclear":false,"family":"154067","comment":""},"6":{"value":"181140","family_comment":"","value_unclear":false,"family_unclear":false,"family":"105615","comment":""},"7":{"family_comment":"","value":"","source_name":"","family":"","comment":""},"8":{"family_comment":"","value":"","family":"","comment":""},"9":{"family_comment":"","value":"","value_unclear":false,"family":"48452","comment":""},"10":{"family_comment":"","value":"","value_unclear":false,"family":"","comment":""},"11":{"family_comment":"","value":"","family":"","comment":""},"12":{"family_comment":"","value":"","family":"","comment":""},"13":{"family_comment":"","value":"","value_unclear":false,"family":"","comment":""},"14":{"family_comment":"","value":"","family":"","comment":""},"15":{"family_comment":"","value":"","family":"","comment":""},"16":{"family_comment":"","value":"","family":"","comment":""},"17":{"family_comment":"","value":"","family":"","comment":""},"18":{"family_comment":"","value":"","family":"","comment":""},"19":{"family_comment":"","value":"","family":"","comment":""},"20":{"family_comment":"","family_unclear":false,"value":"","family":"","comment":""}},"vehicle":{"35":[{"year_hidden":false,"brand_info":"1386 куб. см.,56.6 кВт ,4237 мм","sum_rent_comment":"","year":"2007","brand_info_unclear":false,"sum_rent":"","sum":"","brand":"ЗАЗ Lanos TF699P","sum_comment":"","brand_unclear":true,"brand_hidden":false,"sum_comment_unclear":false}]},"id":"vulyk_85_65","banks":{"51":[{"sum_foreign_comment":"","sum_units":"UAH","sum_comment":"","sum_foreign_units":"UAH","sum_comment_hidden":false,"sum":"158934","sum_foreign":""}]},"declaration":{"additional_info_text":"","notfull_lostpages":"","date":"2015-03-31T00:00:00","notfull":"","additional_info":"","url":"http://static.declarations.com.ua/declarations/chosen_ones/judges_batch/2668_hapoliak_taras_volodymyrovych.pdf"},"liabilities":{"54":{"sum_foreign_comment":"","sum":"","sum_comment":"","sum_comment_unclear":false,"sum_foreign":""},"55":{"sum_foreign_comment":"","sum":"","sum_comment":"","sum_foreign":""},"56":{"sum_foreign_comment":"","sum":"","sum_comment":"","sum_unclear":false,"sum_foreign":""},"57":{"sum_foreign_comment":"","sum":"","sum_comment":"","sum_foreign":""},"58":{"sum_foreign_comment":"","sum_comment_hidden":false,"sum":"","sum_comment":"","sum_foreign":""},"59":{"sum_foreign_comment":"","sum":"","sum_comment":"","sum_foreign":""},"60":{"sum_foreign_comment":"","sum":"","sum_comment":"","sum_foreign":""},"61":{"sum_foreign_comment":"","sum":"","sum_comment":"","sum_foreign":""},"62":{"sum_foreign_comment":"","sum":"","sum_comment":"","sum_unclear":false,"sum_foreign":""},"63":{"sum_foreign_comment":"","sum":"","sum_comment":"","sum_unclear":false,"sum_foreign":""},"64":{"sum_foreign_comment":"","sum":"","sum_comment":"","sum_foreign":""}},"ft_src":"суддя галицького районного суду івано-франківської області\nІвано-Франківська область\nЗагальний місцевий суд\nТарас\nПодружжя\nДонька\nДитина\nВолодимирович\nГаполяк Тарас Володимирович\nТарас Володимирович Гаполяк\nТарас Гаполяк\nГаполяк Тарас Володимирович\nГаполяк\nГаполяк Тарас Володимирович\n1386 куб. см.,56.6 кВт ,4237 мм\nЗАЗ Lanos TF699P\n2007\n158934\n2014\n1386 куб. см.,56.6 кВт ,4237 мм\nЗАЗ Lanos TF699P\n2007\n158934\n800\n142.6\nбезоплатне користування\nГаполяк Тарас Володимирович\nТарас Володимирович Гаполяк\nТарас Гаполяк\nГаполяк Тарас Володимирович\nТарас\nПодружжя\nДитина\nДонька\nГаполяк Тарас Володимирович\nГаполяк\nЗагальний місцевий суд\nсуддя галицького районного суду івано-франківської області\nІвано-Франківська область\nВолодимирович\n181140\n105615\n181140\n154067\n48452\n2014\n800\nбезоплатне користування\n142.6\nПодружжя\nДонька\nДитина\nВолодимирович\nГаполяк\nТарас\nГаполяк Тарас Володимирович\nТарас Володимирович Гаполяк\nТарас Гаполяк\nГаполяк Тарас Володимирович\nсуддя галицького районного суду івано-франківської області\nІвано-Франківська область\nЗагальний місцевий суд\nГаполяк Тарас Володимирович\n105615\n181140\n48452\n154067\n181140\nЗАЗ Lanos TF699P\n1386 куб. см.,56.6 кВт ,4237 мм\n2007\n48452\n181140\n154067\n181140\n105615\nбезоплатне користування\n142.6\n800\n158934\n2014","general":{"inn":"","name":"Тарас","last_name_hidden":false,"family":[{"inn":"","inn_hidden":true,"relations_unclear":false,"relations_hidden":false,"relations_other":"","relations":"Подружжя","name_hidden":true,"family_name":"","name_unclear":false},{"inn":"","relations":"Дитина","relations_other":"","inn_hidden":false,"family_name":"Донька","name_hidden":false,"name_unclear":false}],"patronymic":"Володимирович","inn_hidden":true,"family_raw":"","last_name":"Гаполяк","post":{"post_unclear":false,"post_hidden":false,"post":"суддя галицького районного суду івано-франківської області","region":"Івано-Франківська область","office":"Загальний місцевий суд"},"last_name_unclear":false,"full_name":"Гаполяк Тарас Володимирович","addresses":[{"place_district":"","place_city_hidden":true,"place_city":"","place_city_type_hidden":true,"place_district_hidden":true,"place_city_type":"","place_address_hidden":true,"place_address":"","place_hidden":true,"place":""}],"full_name_suggest":{"output":"Гаполяк Тарас Володимирович","input":["Гаполяк Тарас Володимирович","Тарас Володимирович Гаполяк","Тарас Гаполяк"]}},"source":"VULYK","estate":{"24":[{"space_hidden":false,"costs":"","costs_comment":"","address_hidden":false,"region_hidden":true,"space_comment":"","space_unclear":false,"space":"142.6","address":"","region":"","costs_rent_comment":"безоплатне користування","space_units":"м²","costs_rent":""}],"29":[{"space_unclear":false,"address_hidden":false,"region_hidden":true,"space_comment":"","space":"800","address":"","region":"","costs_property":"","costs_rent_comment":"","space_units":"м²","costs_property_comment":"","costs_rent":""}]},"intro":{"declaration_year":"2014","isnotdeclaration":""}}