{"income":{"5":{"value":"236603.26","family_comment":"","value_unclear":false,"family_hidden":false,"value_hidden":false,"family_unclear":false,"family":"90691.25","comment":"","family_comment_unclear":false},"6":{"family_comment":"","family_unclear":false,"value":"236603.26","family":"73634.65","comment":""},"7":{"source_name_unclear":false,"value":"","family_comment":"","source_name":"","family":"","comment":"","source_name_hidden":false},"8":{"family_comment":"","value":"","family":"","comment":""},"9":{"family_comment":"","family_unclear":false,"value":"","family":"","comment":""},"10":{"family_comment":"","value":"","family":"","comment":""},"11":{"family_comment":"","value":"","family":"","comment":""},"12":{"family_comment":"","value":"","family":"","comment":""},"13":{"family_comment":"","value":"","family":"","comment":""},"14":{"family_comment":"","value":"","family":"","comment":""},"15":{"family_comment":"","value":"","family":"17056.6","comment":""},"16":{"value":"","value_unclear":false,"value_hidden":false,"family_comment":"","family":"","comment":""},"17":{"family_comment":"","value":"","family":"","comment":""},"18":{"family_comment":"","value":"","family":"","comment":""},"19":{"family_comment":"","value":"","family":"","comment":""},"20":{"value":"","family_comment":"","value_unclear":false,"comment_hidden":false,"family_hidden":false,"family":"","value_hidden":false,"family_unclear":false,"comment_unclear":false,"comment":"","family_comment_unclear":false}},"vehicle":{"40":[{"brand_info":"об'єм 1.6 куб. дм","sum":"","brand":"Toyota Corolla","sum_comment":"","brand_unclear":false,"year":"2006","brand_hidden":false,"brand_info_hidden":false,"brand_info_unclear":false,"sum_rent_comment":"","sum_rent":""},{"brand_info":"2967 куб. см.","sum_rent_comment":"","brand":"Volkswagen Touareg","sum_comment":"","year":"2013","brand_hidden":false,"brand_info_unclear":false,"sum":"","sum_rent":""}]},"id":"vulyk_62_180","banks":{"51":[{"sum_units":"UAH","sum_hidden":false,"sum_foreign_units_hidden":false,"sum":"35651.33","sum_foreign":"","sum_foreign_comment":"","sum_foreign_hidden":false,"sum_comment":"","sum_comment_unclear":false,"sum_foreign_units":"UAH","sum_comment_hidden":false,"sum_unclear":false}]},"declaration":{"additional_info_text":"","notfull_lostpages":"","date":"2015-03-30T00:00:00","notfull":"","additional_info":"","url":"http://static.declarations.com.ua/declarations/chosen_ones/mega_batch/yakovliev_oleksandr_volodymyrovych.pdf"},"liabilities":{"54":{"sum_foreign_comment":"","sum":"","sum_comment":"","sum_hidden":false,"sum_comment_hidden":false,"sum_foreign":""},"55":{"sum_foreign_comment":"","sum":"","sum_comment":"","sum_hidden":false,"sum_comment_hidden":false,"sum_unclear":false,"sum_foreign":""},"56":{"sum_foreign_comment":"","sum":"","sum_comment":"","sum_hidden":false,"sum_unclear":false,"sum_foreign":""},"57":{"sum_foreign_comment":"","sum":"","sum_comment":"","sum_hidden":false,"sum_comment_hidden":false,"sum_unclear":false,"sum_foreign":""},"58":{"sum_foreign_comment":"","sum_foreign_hidden":false,"sum_comment":"","sum_hidden":false,"sum_comment_hidden":false,"sum_unclear":false,"sum":"","sum_foreign":""},"59":{"sum_foreign_comment":"","sum":"","sum_comment":"","sum_foreign":""},"60":{"sum_foreign_comment":"","sum_foreign_hidden":false,"sum_comment":"","sum_hidden":false,"sum_comment_hidden":false,"sum_unclear":false,"sum":"","sum_foreign":""},"61":{"sum_foreign_comment":"","sum_foreign_hidden":false,"sum_comment":"","sum_hidden":false,"sum":"","sum_foreign":""},"62":{"sum_foreign_comment":"","sum":"","sum_comment":"","sum_unclear":false,"sum_foreign":""},"63":{"sum_foreign_comment":"","sum":"","sum_comment":"","sum_hidden":false,"sum_comment_hidden":false,"sum_unclear":false,"sum_foreign":""},"64":{"sum_foreign_comment":"","sum":"","sum_comment":"","sum_comment_unclear":false,"sum_hidden":false,"sum_comment_hidden":false,"sum_foreign":""}},"ft_src":"суддя одеського апеляційного адміністративного суду\nОдеська область\nАпеляційний адміністративний суд\nОлександр\nЯковлєва М\nПодружжя\nЯковлєв Є. О\nДитина\nЯковлєв В. О\nДитина\nЯковлєва Г. І\nБатьки\nВолодимирович\nЯковлєв Олександр Володимирович\nОлександр Володимирович Яковлєв\nОлександр Яковлєв\nЯковлєв Олександр Володимирович\nЯковлєв Олександр Володимирович\nЯковлєв\nToyota Corolla\nоб'єм 1.6 куб. дм\n2006\n2013\nVolkswagen Touareg\n2967 куб. см.\n35651.33\n2014\nоб'єм 1.6 куб. дм\n2006\nToyota Corolla\n2967 куб. см.\n2013\nVolkswagen Touareg\n35651.33\n600\n.352\n178.5\n239.7\n18.5\nПодружжя\nЯковлєва М\nДитина\nЯковлєв Є. О\nДитина\nЯковлєв В. О\nБатьки\nЯковлєва Г. І\nЯковлєв Олександр Володимирович\nОлександр Володимирович Яковлєв\nОлександр Яковлєв\nЯковлєв Олександр Володимирович\nЯковлєв Олександр Володимирович\nОлександр\nВолодимирович\nАпеляційний адміністративний суд\nсуддя одеського апеляційного адміністративного суду\nОдеська область\nЯковлєв\n236603.26\n73634.65\n17056.6\n236603.26\n90691.25\n2014\n.352\n600\n239.7\n18.5\n178.5\nПодружжя\nЯковлєва М\nЯковлєв Є. О\nДитина\nЯковлєв В. О\nДитина\nЯковлєва Г. І\nБатьки\nВолодимирович\nЯковлєв\nОлександр\nЯковлєв Олександр Володимирович\nОлександр Володимирович Яковлєв\nОлександр Яковлєв\nЯковлєв Олександр Володимирович\nОдеська область\nсуддя одеського апеляційного адміністративного суду\nАпеляційний адміністративний суд\nЯковлєв Олександр Володимирович\n73634.65\n236603.26\n17056.6\n90691.25\n236603.26\nToyota Corolla\nоб'єм 1.6 куб. дм\n2006\n2013\n2967 куб. см.\nVolkswagen Touareg\n17056.6\n236603.26\n90691.25\n73634.65\n236603.26\n239.7\n600\n178.5\n18.5\n.352\n35651.33\n2014","general":{"inn":"","name":"Олександр","inn_unclear":false,"family":[{"inn":"","inn_hidden":true,"relations_unclear":false,"relations_hidden":false,"relations_other":"","relations":"Подружжя","name_hidden":true,"inn_unclear":false,"family_name":"Яковлєва М","name_unclear":true},{"inn":"","inn_hidden":true,"relations_hidden":false,"family_name":"Яковлєв Є. О","relations_other":"","relations":"Дитина","name_hidden":true,"name_unclear":false},{"inn":"","relations":"Дитина","relations_other":"","inn_hidden":true,"family_name":"Яковлєв В. О","name_hidden":true,"name_unclear":false},{"inn":"","relations":"Батьки","relations_other":"","inn_hidden":true,"family_name":"Яковлєва Г. І","name_hidden":true,"name_unclear":false}],"inn_hidden":true,"family_raw":"","last_name":"Яковлєв","post":{"post_unclear":false,"post":"суддя одеського апеляційного адміністративного суду","post_hidden":false,"region":"Одеська область","region_hidden":false,"office":"Апеляційний адміністративний суд","office_hidden":false,"office_unclear":false},"full_name_suggest":{"output":"Яковлєв Олександр Володимирович","input":["Яковлєв Олександр Володимирович","Олександр Володимирович Яковлєв","Олександр Яковлєв"]},"full_name":"Яковлєв Олександр Володимирович","addresses":[{"place_city_type_unclear":false,"place_address":"","place_district_hidden":true,"place_city_type":"","place_address_hidden":true,"place_address_unclear":false,"place_city_type_hidden":true,"place":"","place_district":"","place_unclear":false,"place_city":"","place_city_unclear":false,"place_hidden":true,"place_city_hidden":true,"place_district_unclear":false}],"patronymic":"Володимирович","last_name_unclear":false,"name_unclear":false},"source":"VULYK","estate":{"23":[{"region_unclear":false,"space_unclear":false,"costs":"","costs_comment":"","costs_hidden":false,"address_hidden":false,"region_hidden":true,"space_comment":"","space":"600","address":"","region":"","address_unclear":false,"space_units_unclear":false,"space_comment_unclear":false,"space_units":"м²","space_units_hidden":false,"costs_rent":"","costs_rent_comment":""}],"24":[{"space_unclear":false,"costs":"","costs_comment":"","address_hidden":false,"region_hidden":true,"space_comment":"","space_hidden":false,"space_units_unclear":false,"address":"","region":"","address_unclear":false,"space":"178.5","space_comment_unclear":false,"space_units":"м²","space_units_hidden":false,"costs_rent":"","costs_rent_comment":""}],"29":[{"region_unclear":false,"space_hidden":false,"address_hidden":false,"region_hidden":true,"space_comment":"","space_unclear":false,"space":".352","address":"","region":"","costs_property":"","costs_rent_comment":"","address_unclear":false,"space_units":"га","costs_property_comment":"","costs_rent":""}],"30":[{"space_hidden":false,"address_hidden":false,"region_hidden":true,"space_comment":"","space_unclear":false,"space":"239.7","address":"","region":"","costs_property":"","costs_rent_comment":"","space_comment_unclear":false,"address_unclear":false,"space_units":"м²","costs_property_comment":"","costs_rent":""}],"34":[{"space_unclear":false,"address_hidden":false,"region_hidden":true,"space_comment":"","space_hidden":false,"space":"18.5","address":"","region":"","costs_property":"","costs_rent_comment":"","space_units":"м²","costs_property_comment":"","costs_rent":""}]},"intro":{"declaration_year":"2014","isnotdeclaration":"","declaration_year_unclear":false,"declaration_year_hidden":false}}