{"income":{"5":{"value":"189273","family_comment":"","value_unclear":false,"family_hidden":false,"value_hidden":false,"family_unclear":false,"family":"151102","comment":""},"6":{"value":"189273","family_comment":"","value_unclear":false,"family_unclear":false,"family":"","comment":""},"7":{"source_name_unclear":false,"value":"","comment_hidden":false,"family_comment":"","source_name":"","family":"","comment":"","source_name_hidden":false},"8":{"family_comment":"","value":"","family":"","comment":""},"9":{"value":"","family_comment":"","value_unclear":false,"family_hidden":false,"family_unclear":false,"family":"8400","comment":"","family_comment_unclear":false},"10":{"family_comment":"","value":"","family":"","comment":""},"11":{"family_comment":"","value":"","family":"","comment":""},"12":{"family_comment":"","value":"","family":"","comment":""},"13":{"family_comment":"","value":"","family":"","comment":""},"14":{"family_comment":"","value":"","family":"","comment":""},"15":{"family_comment":"","value":"","family":"","comment":""},"16":{"family_comment":"","value":"","family":"","comment":""},"17":{"family_comment":"","value":"","family":"","comment":""},"18":{"family_comment":"","value":"","family":"","comment":""},"19":{"family_comment":"","value":"","family":"142702","comment":""},"20":{"value":"","family_comment":"","value_unclear":false,"family_comment_hidden":false,"family_unclear":false,"family_comment_unclear":false,"comment_unclear":false,"comment":"","family":""}},"vehicle":{"35":[{"year_hidden":false,"brand_info":"2000 куб. см.","sum_rent_comment":"","year":"2006","brand_info_hidden":false,"brand_info_unclear":false,"sum_rent":"","sum":"","brand":"Suzuki Grand Vitara","sum_comment":"придбано у 2006 році","brand_unclear":false,"brand_hidden":false},{"brand_info":"2200 куб. см.","sum_rent_comment":"","brand":"Mercedes-Benz E 250","sum_comment":"придбано у 2013 році","year":"2012","sum":"","sum_rent":""}],"40":[{"brand_info":"1800 куб. см.","sum_rent_comment":"","brand":"Mercedes-Benz C-Class","sum_comment":"","year":"2012","brand_info_unclear":false,"sum":"","sum_rent":""}]},"id":"vulyk_93_8","declaration":{"additional_info_text":"","notfull_lostpages":"","date":"2015-03-24T00:00:00","notfull":"","additional_info":"","url":"http://static.declarations.com.ua/declarations/chosen_ones/judges_batch/3454_lepekha_hennadii_anatoliiovych.pdf"},"liabilities":{"54":{"sum_foreign_comment":"","sum":"","sum_hidden":false,"sum_comment":"","sum_foreign":""},"55":{"sum_foreign_comment":"","sum":"","sum_comment":"","sum_foreign":""},"56":{"sum_foreign_comment":"","sum":"","sum_comment":"","sum_foreign":""},"57":{"sum_foreign_comment":"","sum":"","sum_comment":"","sum_hidden":false,"sum_comment_hidden":false,"sum_unclear":false,"sum_foreign":""},"58":{"sum_foreign_comment":"","sum":"","sum_comment":"","sum_comment_unclear":false,"sum_hidden":false,"sum_unclear":false,"sum_foreign":""},"59":{"sum_foreign_comment":"","sum":"","sum_comment":"","sum_foreign":""},"60":{"sum_foreign_comment":"","sum":"","sum_hidden":false,"sum_comment":"","sum_foreign":""},"61":{"sum_foreign_comment":"","sum":"","sum_comment":"","sum_foreign":""},"62":{"sum_foreign_comment":"","sum":"101260","sum_comment":"","sum_foreign":""},"63":{"sum_foreign_comment":"","sum":"","sum_comment":"","sum_foreign":""},"64":{"sum_foreign_comment":"","sum":"","sum_comment":"","sum_foreign":""}},"ft_src":"101260\nЛепеха Геннадій Анатолійович\nсуддя господарського суду одеської області\nОдеська область\nГосподарський місцевий суд\nГеннадій\nЛепеха А. А\nПодружжя\nЛепеха Геннадій Анатолійович\nГеннадій Анатолійович Лепеха\nГеннадій Лепеха\nЛепеха Геннадій Анатолійович\nЛепеха\nАнатолійович\nпридбано у 2006 році\n2000 куб. см.\nSuzuki Grand Vitara\n2006\nпридбано у 2013 році\n2200 куб. см.\n2012\nMercedes-Benz E 250\n1800 куб. см.\n2012\nMercedes-Benz C-Class\n35\n200\nфутів\n20\nфутів\n20\n35\n46\n575\n5270\n2014\n189273\n8400\n151102\n189273\n142702\n2000 куб. см.\nпридбано у 2006 році\nSuzuki Grand Vitara\n2006\n2200 куб. см.\nпридбано у 2013 році\n2012\nMercedes-Benz E 250\n1800 куб. см.\nMercedes-Benz C-Class\n2012\n35\n200\n46\n20\nфутів\n20\nфутів\n35\n575\n5270\nЛепеха\nПодружжя\nЛепеха А. А\nЛепеха Геннадій Анатолійович\nГеннадій Анатолійович Лепеха\nГеннадій Лепеха\nЛепеха Геннадій Анатолійович\nЛепеха Геннадій Анатолійович\nГеннадій\nАнатолійович\nОдеська область\nГосподарський місцевий суд\nсуддя господарського суду одеської області\n101260\n189273\n189273\n151102\n8400\n142702\n2014\n101260\nПодружжя\nЛепеха А. А\nЛепеха\nАнатолійович\nОдеська область\nГосподарський місцевий суд\nсуддя господарського суду одеської області\nЛепеха Геннадій Анатолійович\nЛепеха Геннадій Анатолійович\nГеннадій Анатолійович Лепеха\nГеннадій Лепеха\nЛепеха Геннадій Анатолійович\nГеннадій\nSuzuki Grand Vitara\nпридбано у 2006 році\n2000 куб. см.\n2006\nпридбано у 2013 році\nMercedes-Benz E 250\n2200 куб. см.\n2012\n2012\n1800 куб. см.\nMercedes-Benz C-Class\n142702\n8400\n189273\n151102\n189273\n200\n575\n5270\n35\nфутів\n20\nфутів\n20\n35\n46\n2014","general":{"inn":"","inn_hidden":true,"last_name":"Лепеха","post":{"post_unclear":false,"region_unclear":false,"region":"Одеська область","candidate":"","post":"суддя господарського суду одеської області","office":"Господарський місцевий суд","office_unclear":false},"name":"Геннадій","full_name":"Лепеха Геннадій Анатолійович","family_raw":"","addresses":[{"place_district":"","place_city_hidden":true,"place_city":"","place_city_type_hidden":false,"place_district_hidden":true,"place_city_type":"","place_address_hidden":true,"place_address":"","place_hidden":true,"place":""}],"family":[{"inn":"","relations":"Подружжя","relations_hidden":false,"inn_hidden":true,"relations_other":"","name_hidden":false,"family_name":"Лепеха А. А","name_unclear":false}],"full_name_suggest":{"output":"Лепеха Геннадій Анатолійович","input":["Лепеха Геннадій Анатолійович","Геннадій Анатолійович Лепеха","Геннадій Лепеха"]},"patronymic":"Анатолійович"},"source":"VULYK","estate":{"29":[{"space_unclear":false,"address_hidden":true,"region_hidden":true,"space_comment":"","space":"575","address":"","region":"","costs_property":"","costs_rent_comment":"","space_comment_unclear":false,"space_units":"м²","costs_property_comment":"","costs_rent":""},{"costs_rent":"","region":"","costs_property":"","costs_rent_comment":"","region_hidden":false,"space_comment":"","costs_property_comment":"","space_units":"м²","space":"5270","address":""}],"30":[{"space_unclear":false,"address_hidden":true,"region_hidden":true,"space_comment":"","space":"200","address":"","region":"","costs_property":"","costs_rent_comment":"","space_units":"м²","costs_property_comment":"","costs_rent":""}],"32":[{"costs_rent":"","region":"","costs_property":"","costs_rent_comment":"","address_hidden":true,"region_hidden":true,"space_comment":"","costs_property_comment":"","space_units":"м²","space":"46","address":""}],"33":[{"space_hidden":false,"address_hidden":true,"region_hidden":true,"space_comment":"","space":"35","address":"","region":"","costs_property":"","costs_rent_comment":"","space_units":"м²","costs_property_comment":"","costs_rent":""}],"34":[{"costs_rent":"","costs_property":"","costs_rent_comment":"","address_hidden":true,"region_hidden":true,"space_comment":"футів","costs_property_comment":"","space_units":"","space":"20","address":""},{"costs_rent":"","costs_property":"","costs_rent_comment":"","space_comment":"футів","costs_property_comment":"","space_units":"","space":"20","address":""},{"costs_rent":"","costs_property":"","costs_rent_comment":"","space_comment":"","costs_property_comment":"","space_units":"м²","space":"35","address":""}]},"intro":{"declaration_year":"2014","isnotdeclaration":""}}