{"income":{"5":{"value":"246428","family_comment":"","value_unclear":false,"family_hidden":false,"value_hidden":false,"family_unclear":false,"family":"","comment":""},"6":{"value":"246428","value_unclear":false,"family_hidden":false,"value_hidden":false,"family_comment":"","comment_unclear":false,"comment":"","family":""},"7":{"value":"","value_hidden":false,"family_comment":"","source_name":"","family":"","comment":"","source_name_hidden":false},"8":{"family_comment":"","value":"","family":"","comment":""},"9":{"family_comment":"","value":"","comment_unclear":false,"family":"","comment":""},"10":{"family_comment":"","value":"","value_unclear":false,"family":"","comment":""},"11":{"family_comment":"","value":"","family":"","comment":""},"12":{"family_comment":"","value":"","family":"","comment":""},"13":{"family_comment":"","value":"","family":"","comment":""},"14":{"family_comment":"","value":"","family":"","comment":""},"15":{"family_comment":"","value":"","family":"","comment":""},"16":{"family_comment":"","value":"","family":"","comment":""},"17":{"family_comment":"","value":"","family":"","comment":""},"18":{"family_comment":"","value":"","family":"","comment":""},"19":{"value":"","value_unclear":false,"comment_hidden":false,"family_hidden":false,"value_hidden":false,"family_comment":"","family_comment_hidden":false,"comment":"","family":""},"20":{"value":"","family_comment":"","value_unclear":false,"family_hidden":false,"value_hidden":false,"family_unclear":false,"comment_unclear":false,"comment":"","family":""}},"id":"vulyk_65_57","banks":{"45":[{"sum_foreign_comment":"","sum_units":"UAH","sum_comment":"","sum_comment_unclear":false,"sum_hidden":false,"sum_foreign_units":"UAH","sum_units_unclear":false,"sum":"11859","sum_unclear":false,"sum_foreign":""}]},"declaration":{"additional_info_text":"","notfull_lostpages":"","date":"2015-03-31T00:00:00","notfull":"","additional_info":"","url":"http://static.declarations.com.ua/declarations/chosen_ones/mega_batch/kushnirova_tetiana_babykivna.pdf"},"liabilities":{"54":{"sum_foreign_comment":"","sum":"1600","sum_comment":"","sum_comment_unclear":false,"sum_hidden":false,"sum_comment_hidden":false,"sum_foreign":""},"55":{"sum_foreign_comment":"","sum":"","sum_comment":"","sum_foreign":""},"56":{"sum_foreign_comment":"","sum":"","sum_comment":"","sum_unclear":false,"sum_foreign":""},"57":{"sum_foreign_comment":"","sum":"","sum_comment":"","sum_comment_unclear":false,"sum_unclear":false,"sum_foreign":""},"58":{"sum_foreign_comment":"","sum":"","sum_comment":"","sum_comment_unclear":false,"sum_unclear":false,"sum_foreign":""},"59":{"sum_foreign_comment":"","sum":"","sum_comment":"","sum_foreign":""},"60":{"sum_foreign_comment":"","sum":"","sum_comment":"","sum_comment_unclear":false,"sum_foreign":""},"61":{"sum_foreign_comment":"","sum":"","sum_comment":"","sum_foreign":""},"62":{"sum_foreign_comment":"","sum":"","sum_comment":"","sum_foreign":""},"63":{"sum_foreign_comment":"","sum":"","sum_comment":"","sum_foreign":""},"64":{"sum_foreign_comment":"","sum":"","sum_comment":"","sum_unclear":false,"sum_foreign":""}},"ft_src":"1600\nсуддя апеляційного суду миколаївської області\nМиколаївська область\nЗагальний апеляційний суд\nТетяна\nБабиківна\nКушнірова\nКушнірова Тетяна Бабиківна\nКушнірова Тетяна Бабиківна\nТетяна Бабиківна Кушнірова\nТетяна Кушнірова\nКушнірова Тетяна Бабиківна\n246428\n246428\n11859\n42.2\n2014\n246428\n246428\n11859\n2014\nКушнірова Тетяна Бабиківна\nТетяна Бабиківна Кушнірова\nТетяна Кушнірова\nКушнірова Тетяна Бабиківна\nКушнірова Тетяна Бабиківна\nТетяна\nКушнірова\nЗагальний апеляційний суд\nМиколаївська область\nсуддя апеляційного суду миколаївської області\nБабиківна\n1600\n246428\n246428\n42.2\n1600\nБабиківна\nКушнірова\nТетяна\nКушнірова Тетяна Бабиківна\nТетяна Бабиківна Кушнірова\nТетяна Кушнірова\nКушнірова Тетяна Бабиківна\nМиколаївська область\nЗагальний апеляційний суд\nсуддя апеляційного суду миколаївської області\nКушнірова Тетяна Бабиківна\n42.2\n11859\n2014","general":{"name_hidden":false,"name":"Тетяна","last_name_hidden":false,"inn":"","inn_unclear":false,"patronymic":"Бабиківна","inn_hidden":false,"family_raw":"","last_name":"Кушнірова","post":{"post_unclear":false,"region_unclear":false,"post":"суддя апеляційного суду миколаївської області","office":"Загальний апеляційний суд","region":"Миколаївська область","post_hidden":false,"office_hidden":false,"office_unclear":false,"region_hidden":false},"last_name_unclear":false,"full_name":"Кушнірова Тетяна Бабиківна","patronymic_hidden":false,"full_name_suggest":{"output":"Кушнірова Тетяна Бабиківна","input":["Кушнірова Тетяна Бабиківна","Тетяна Бабиківна Кушнірова","Тетяна Кушнірова"]},"name_unclear":false},"source":"VULYK","estate":{"25":[{"space_unclear":false,"costs":"","costs_comment":"","address_hidden":false,"region_hidden":false,"space_comment":"","space_hidden":false,"space":"42.2","address":"","costs_rent_comment_unclear":false,"region":"","address_unclear":false,"costs_rent_comment":"","space_comment_unclear":false,"space_units":"м²","space_units_hidden":false,"costs_rent":""}]},"intro":{"declaration_year":"2014","isnotdeclaration":"","declaration_year_hidden":false}}