{"income":{"5":{"value":"241097.39","family_comment":"","value_unclear":false,"family_hidden":false,"value_hidden":false,"family_unclear":false,"family":"","comment":""},"6":{"value":"","value_unclear":false,"family_hidden":false,"value_hidden":false,"family_comment":"","comment_unclear":false,"comment":"","family":""},"7":{"value":"","value_hidden":false,"family_comment":"","source_name":"","family":"","comment":"","source_name_hidden":false},"8":{"family_comment":"","value":"","family":"","comment":""},"9":{"family_comment":"","value":"","comment_unclear":false,"family":"","comment":""},"10":{"family_comment":"","value":"","value_unclear":false,"family":"","comment":""},"11":{"family_comment":"","value":"","family":"","comment":""},"12":{"family_comment":"","value":"","family":"","comment":""},"13":{"family_comment":"","value":"","family":"","comment":""},"14":{"family_comment":"","value":"","family":"","comment":""},"15":{"family_comment":"","value":"","family":"","comment":""},"16":{"family_comment":"","value":"","family":"187621.73","comment":""},"17":{"family_comment":"","value":"","family":"","comment":""},"18":{"family_comment":"","value":"","family":"","comment":""},"19":{"value":"","value_unclear":false,"comment_hidden":false,"family_hidden":false,"value_hidden":false,"family_comment":"","family_comment_hidden":false,"comment":"","family":""},"20":{"value":"","family_comment":"","value_unclear":false,"family_hidden":false,"value_hidden":false,"family_unclear":false,"comment_unclear":false,"comment":"","family":""}},"vehicle":{"35":[{"brand_info":"2.0 л.","sum_rent_comment":"","year":"2014","brand_info_hidden":false,"brand_info_unclear":false,"year_unclear":false,"sum_rent":"238607.19","sum":"","brand":"Volkswagen Tiguan FL","sum_comment":"","brand_unclear":false,"brand_hidden":false}],"40":[{"brand_info":"1.8 куб. см.","sum_rent_comment":"","brand":"Hyundai Elantra","sum_comment":"","brand_unclear":false,"year":"2011","brand_hidden":false,"brand_info_unclear":false,"year_unclear":false,"sum":"","sum_rent":""}]},"id":"vulyk_65_169","declaration":{"additional_info_text":"","notfull_lostpages":"","date":"2015-03-23T00:00:00","notfull":"","additional_info":"","url":"http://static.declarations.com.ua/declarations/chosen_ones/mega_batch/ohrenych_iryna_vasylivna.pdf"},"liabilities":{"54":{"sum_foreign_comment":"","sum":"","sum_comment":"","sum_comment_unclear":false,"sum_hidden":false,"sum_comment_hidden":false,"sum_foreign":""},"55":{"sum_foreign_comment":"","sum":"","sum_comment":"","sum_foreign":""},"56":{"sum_foreign_comment":"","sum":"","sum_comment":"","sum_unclear":false,"sum_foreign":""},"57":{"sum_foreign_comment":"","sum":"","sum_comment":"","sum_comment_unclear":false,"sum_unclear":false,"sum_foreign":""},"58":{"sum_foreign_comment":"","sum":"","sum_comment":"","sum_comment_unclear":false,"sum_unclear":false,"sum_foreign":""},"59":{"sum_foreign_comment":"","sum":"","sum_comment":"","sum_foreign":""},"60":{"sum_foreign_comment":"","sum":"","sum_comment":"","sum_comment_unclear":false,"sum_foreign":""},"61":{"sum_foreign_comment":"","sum":"","sum_comment":"","sum_foreign":""},"62":{"sum_foreign_comment":"","sum":"","sum_comment":"","sum_foreign":""},"63":{"sum_foreign_comment":"","sum":"","sum_comment":"","sum_foreign":""},"64":{"sum_foreign_comment":"","sum":"","sum_comment":"","sum_unclear":false,"sum_foreign":""}},"ft_src":"Одеса\nОдеська область\nсуддя київського райсуду м. одеси\nОдеська область\nЗагальний місцевий суд\nІрина\nПодружжя\nДитина\nВасилівна\nОгренич\nОгренич Ірина Василівна\nОгренич Ірина Василівна\nІрина Василівна Огренич\nІрина Огренич\nОгренич Ірина Василівна\n2.0 л.\nVolkswagen Tiguan FL\n2014\n238607.19\nHyundai Elantra\n1.8 куб. см.\n2011\nІванівський район\nОдеська область\n58.1\nОдеська область\nІванівський район\n.0685\n2014\n241097.39\n187621.73\n2.0 л.\n238607.19\nVolkswagen Tiguan FL\n2014\n1.8 куб. см.\n2011\nHyundai Elantra\n.0685\nОдеська область\nІванівський район\n58.1\nОдеська область\nІванівський район\nЗагальний місцевий суд\nОдеська область\nсуддя київського райсуду м. одеси\nОгренич Ірина Василівна\nІрина Василівна Огренич\nІрина Огренич\nОгренич Ірина Василівна\nІрина\nПодружжя\nДитина\nОгренич Ірина Василівна\nОгренич\nВасилівна\nОдеса\nОдеська область\n241097.39\n187621.73\n2014\nПодружжя\nДитина\nВасилівна\nОгренич\nІрина\nОгренич Ірина Василівна\nІрина Василівна Огренич\nІрина Огренич\nОгренич Ірина Василівна\nОдеса\nОдеська область\nОдеська область\nЗагальний місцевий суд\nсуддя київського райсуду м. одеси\nОгренич Ірина Василівна\n2014\nVolkswagen Tiguan FL\n2.0 л.\n238607.19\n2011\nHyundai Elantra\n1.8 куб. см.\n241097.39\n187621.73\nІванівський район\nОдеська область\n58.1\nОдеська область\nІванівський район\n.0685\n2014","general":{"name_hidden":false,"name":"Ірина","last_name_hidden":false,"inn":"","family":[{"inn":"","inn_hidden":false,"inn_unclear":false,"relations_hidden":false,"relations_other":"","relations":"Подружжя","name_hidden":true,"family_name":"","name_unclear":false},{"inn":"","inn_hidden":false,"relations_unclear":false,"relations_hidden":false,"relations_other":"","relations":"Дитина","name_hidden":false,"inn_unclear":false,"family_name":"","name_unclear":false}],"patronymic":"Василівна","inn_hidden":true,"family_raw":"","inn_unclear":false,"post":{"post_unclear":false,"region_unclear":false,"post":"суддя київського райсуду м. одеси","office":"Загальний місцевий суд","region":"Одеська область","post_hidden":false,"office_hidden":false,"office_unclear":false,"region_hidden":false},"last_name_unclear":false,"full_name":"Огренич Ірина Василівна","addresses":[{"place_district":"","place_address_hidden":false,"place_city":"","place_city_type_hidden":false,"place_district_hidden":true,"place_city_type":"Місто","place_city_hidden":false,"place_address_unclear":false,"place_address":"Одеса","place_hidden":false,"place":"Одеська область"}],"last_name":"Огренич","patronymic_hidden":false,"full_name_suggest":{"output":"Огренич Ірина Василівна","input":["Огренич Ірина Василівна","Ірина Василівна Огренич","Ірина Огренич"]},"name_unclear":false},"source":"VULYK","estate":{"29":[{"space_unclear":false,"address_hidden":false,"region_hidden":false,"space_comment":"","space_units_hidden":false,"space":".0685","address":"Іванівський район","region":"Одеська область","address_unclear":false,"costs_rent_comment":"","costs_property":"","space_units":"га","costs_property_comment":"","costs_rent":""}],"30":[{"address_hidden":false,"region_hidden":false,"space_comment":"","space":"58.1","address":"Іванівський район","region":"Одеська область","costs_property":"","costs_rent_comment":"","space_comment_unclear":false,"address_unclear":false,"space_units":"м²","costs_property_comment":"","costs_rent":""}]},"intro":{"declaration_year":"2014","isnotdeclaration":"","declaration_year_hidden":false}}