{"income":{"5":{"value":"10361","family_comment":"","value_unclear":false,"family_unclear":false,"family":"101199","comment":""},"6":{"value":"","family_comment":"","value_unclear":false,"family_unclear":false,"family":"101199","comment":""},"7":{"family_comment":"","value":"","source_name":"","family":"","comment":""},"8":{"family_comment":"","value":"","family":"","comment":""},"9":{"family_comment":"","value":"","family":"","comment":""},"10":{"family_comment":"","value":"","family":"","comment":""},"11":{"family_comment":"","value":"","family":"","comment":""},"12":{"family_comment":"","value":"","family":"","comment":""},"13":{"family_comment":"","value":"","family":"","comment":""},"14":{"family_comment":"","value":"","family":"","comment":""},"15":{"family_comment":"","value":"","value_unclear":false,"family":"","comment":""},"16":{"family_comment":"","value":"","family":"","comment":""},"17":{"family_comment":"","value":"","family":"","comment":""},"18":{"family_comment":"","value":"","family":"","comment":""},"19":{"family_comment":"","value":"","family":"","comment":""},"20":{"value":"","family_comment":"","value_unclear":false,"family_unclear":false,"family":"","comment":"","family_comment_unclear":false}},"vehicle":{"35":[{"brand_info":"1591 куб. см.","sum_rent_comment":"","brand":"Hyundai Accent","sum_comment":"","brand_unclear":false,"year":"2012","brand_info_unclear":false,"sum":"","sum_rent":""}],"40":[{"brand_info":"5999 куб. см.","sum_rent_comment":"","brand":"Mercedes-Benz","sum_comment":"","brand_unclear":false,"year":"2002","brand_info_hidden":false,"brand_info_unclear":false,"sum":"","sum_rent":""},{"brand_info":"3456 куб. см.","sum":"","brand":"Toyota Highlander","sum_comment":"","year":"2014","sum_rent_comment":"","sum_rent":""}]},"id":"vulyk_99_73","declaration":{"date":"2016-03-31T00:00:00","notfull":"","notfull_lostpages":"","url":"http://static.declarations.com.ua/declarations/chosen_ones/judges_batch/622_shapovalova_tetiana_mykhailivna_2015.pdf"},"liabilities":{"54":{"sum_foreign_comment":"","sum":"","sum_comment":"","sum_comment_unclear":false,"sum_comment_hidden":false,"sum_foreign":""},"55":{"sum_foreign_comment":"","sum":"","sum_comment":"","sum_foreign":""},"56":{"sum_foreign_comment":"","sum":"","sum_comment":"","sum_foreign":""},"57":{"sum_foreign_comment":"","sum_comment":"","sum":"76327","sum_comment_hidden":true,"sum_foreign":""},"58":{"sum_foreign_comment":"","sum_comment":"","sum":"","sum_comment_hidden":false,"sum_foreign":""},"59":{"sum_foreign_comment":"","sum":"","sum_comment":"","sum_comment_hidden":false,"sum_unclear":false,"sum_foreign":""},"60":{"sum_foreign_comment":"","sum_comment":"","sum":"","sum_comment_hidden":false,"sum_foreign":""},"61":{"sum_foreign_comment":"","sum":"","sum_comment":"","sum_foreign":""},"62":{"sum_foreign_comment":"","sum":"","sum_comment":"","sum_foreign":""},"63":{"sum_foreign_comment":"","sum_comment":"","sum":"","sum_comment_hidden":false,"sum_foreign":""},"64":{"sum_foreign_comment":"","sum_comment":"","sum":"","sum_comment_hidden":false,"sum_foreign":""}},"ft_src":"2012\nHyundai Accent\n1591 куб. см.\n5999 куб. см.\nMercedes-Benz\n2002\n3456 куб. см.\n2014\nToyota Highlander\n24.9\n2015\n101199\n101199\n10361\n1591 куб. см.\nHyundai Accent\n2012\n5999 куб. см.\n2002\nMercedes-Benz\n3456 куб. см.\n2014\nToyota Highlander\n2015\nШаповалова\nШаповалова Тетяна Михайлівна\nТетяна Михайлівна Шаповалова\nТетяна Шаповалова\nШаповалова Тетяна Михайлівна\nТетяна\nМихайлівна\nШаповалова Тетяна Михайлівна\nАдміністративний місцевий суд\nсуддя вінницького окружного адміністративного суду\nВінницька область\nПодружжя\nШаповалов А. С\nДитина\nШаповалова Є. А\n76327\n101199\n10361\n101199\n24.9\n76327\nШаповалов А. С\nПодружжя\nШаповалова Є. А\nДитина\nМихайлівна\nШаповалова\nсуддя вінницького окружного адміністративного суду\nВінницька область\nАдміністративний місцевий суд\nШаповалова Тетяна Михайлівна\nШаповалова Тетяна Михайлівна\nТетяна Михайлівна Шаповалова\nТетяна Шаповалова\nШаповалова Тетяна Михайлівна\nТетяна","general":{"inn":"","inn_hidden":true,"last_name":"Шаповалова","post":{"post_unclear":false,"office":"Адміністративний місцевий суд","post":"суддя вінницького окружного адміністративного суду","region":"Вінницька область"},"name":"Тетяна","full_name":"Шаповалова Тетяна Михайлівна","family_raw":"","addresses":[{"place_district":"","place_address_hidden":true,"place_city":"","place_address":"","place_district_hidden":false,"place_city_type":"","place_city_hidden":true,"place_city_type_hidden":false,"place_hidden":true,"place":""}],"family":[{"inn":"","relations":"Подружжя","name_hidden":true,"inn_hidden":true,"family_name":"Шаповалов А. С","name_unclear":false},{"inn":"","inn_hidden":true,"family_name":"Шаповалова Є. А","relations_other":"","relations":"Дитина","name_unclear":false}],"full_name_suggest":{"output":"Шаповалова Тетяна Михайлівна","input":["Шаповалова Тетяна Михайлівна","Тетяна Михайлівна Шаповалова","Тетяна Шаповалова"]},"patronymic":"Михайлівна"},"source":"VULYK","estate":{"31":[{"costs_rent":"","region":"","costs_property":"","costs_rent_comment":"","address_hidden":false,"region_hidden":true,"space_comment":"","costs_property_comment":"","space_units":"м²","space":"24.9","address":""}]},"intro":{"declaration_year":"2015"}}