{"income":{"5":{"value":"182066","family_comment":"","value_unclear":false,"family_hidden":false,"value_hidden":false,"family_unclear":false,"family":"","comment":""},"6":{"value":"181824","value_unclear":false,"family_hidden":false,"value_hidden":false,"family_comment":"","comment_unclear":false,"comment":"","family":""},"7":{"value":"","value_hidden":false,"family_comment":"","source_name":"","family":"","comment":"","source_name_hidden":false},"8":{"family_comment":"","value":"","family":"","comment":""},"9":{"family_comment":"","value":"242","comment_unclear":false,"family":"","comment":""},"10":{"family_comment":"","value":"","value_unclear":false,"family":"","comment":""},"11":{"family_comment":"","value":"","family":"","comment":""},"12":{"family_comment":"","value":"","family":"","comment":""},"13":{"family_comment":"","value":"","family":"","comment":""},"14":{"family_comment":"","value":"","family":"","comment":""},"15":{"family_comment":"","value":"","family":"","comment":""},"16":{"family_comment":"","value":"","family":"","comment":""},"17":{"family_comment":"","value":"","family":"","comment":""},"18":{"family_comment":"","value":"","family":"","comment":""},"19":{"value":"","value_unclear":false,"comment_hidden":false,"family_hidden":false,"value_hidden":false,"family_comment":"","family_comment_hidden":false,"comment":"","family":""},"20":{"value":"","family_comment":"","value_unclear":false,"family_hidden":false,"value_hidden":false,"family_unclear":false,"comment_unclear":false,"comment":"","family":""}},"id":"vulyk_65_108","banks":{"45":[{"sum_foreign_comment":"","sum_units":"UAH","sum_comment":"","sum_comment_unclear":false,"sum_hidden":false,"sum_foreign_units":"UAH","sum_units_unclear":false,"sum":"2434","sum_unclear":false,"sum_foreign":""}],"46":[{"sum_foreign_comment":"","sum_units":"UAH","sum_comment":"","sum_foreign_units":"UAH","sum":"1000","sum_foreign":""}]},"declaration":{"additional_info_text":"","notfull_lostpages":"","date":"2015-03-31T00:00:00","notfull":"","additional_info":"","url":"http://static.declarations.com.ua/declarations/chosen_ones/mega_batch/adakhovska_vira_serhiivna.pdf"},"liabilities":{"54":{"sum_foreign_comment":"","sum":"","sum_comment":"","sum_comment_unclear":false,"sum_hidden":false,"sum_comment_hidden":false,"sum_foreign":""},"55":{"sum_foreign_comment":"","sum":"","sum_comment":"","sum_foreign":""},"56":{"sum_foreign_comment":"","sum":"","sum_comment":"","sum_unclear":false,"sum_foreign":""},"57":{"sum_foreign_comment":"","sum":"36840","sum_comment":"","sum_comment_unclear":false,"sum_unclear":false,"sum_foreign":""},"58":{"sum_foreign_comment":"","sum":"4631","sum_comment":"","sum_comment_unclear":false,"sum_unclear":false,"sum_foreign":""},"59":{"sum_foreign_comment":"","sum":"","sum_comment":"","sum_foreign":""},"60":{"sum_foreign_comment":"","sum":"","sum_comment":"","sum_comment_unclear":false,"sum_foreign":""},"61":{"sum_foreign_comment":"","sum":"","sum_comment":"","sum_foreign":""},"62":{"sum_foreign_comment":"","sum":"","sum_comment":"","sum_foreign":""},"63":{"sum_foreign_comment":"","sum":"","sum_comment":"","sum_foreign":""},"64":{"sum_foreign_comment":"","sum":"","sum_comment":"","sum_unclear":false,"sum_foreign":""}},"ft_src":"36840\n4631\nсуддя господарського суду миколаївської області\nМиколаївська область\nГосподарський місцевий суд\nВіра\nСергіївна\nАдаховська\nАдаховська Віра Сергіївна\nАдаховська Віра Сергіївна\nВіра Сергіївна Адаховська\nВіра Адаховська\nАдаховська Віра Сергіївна\n182066\n242\n181824\n1000\n2434\n2014\n181824\n182066\n242\n2434\n1000\n181824\n182066\n242\nАдаховська Віра Сергіївна\nВіра Сергіївна Адаховська\nВіра Адаховська\nАдаховська Віра Сергіївна\nАдаховська Віра Сергіївна\nВіра\nАдаховська\nГосподарський місцевий суд\nМиколаївська область\nсуддя господарського суду миколаївської області\nСергіївна\n36840\n4631\n2014\n4631\n36840\nСергіївна\nАдаховська\nВіра\nАдаховська Віра Сергіївна\nВіра Сергіївна Адаховська\nВіра Адаховська\nАдаховська Віра Сергіївна\nМиколаївська область\nГосподарський місцевий суд\nсуддя господарського суду миколаївської області\nАдаховська Віра Сергіївна\n2434\n1000\n2014","general":{"name_hidden":false,"name":"Віра","last_name_hidden":false,"inn":"","inn_unclear":false,"patronymic":"Сергіївна","inn_hidden":false,"family_raw":"","last_name":"Адаховська","post":{"post_unclear":false,"region_unclear":false,"post":"суддя господарського суду миколаївської області","office":"Господарський місцевий суд","region":"Миколаївська область","post_hidden":false,"office_hidden":false,"office_unclear":false,"region_hidden":false},"last_name_unclear":false,"full_name":"Адаховська Віра Сергіївна","patronymic_hidden":false,"full_name_suggest":{"output":"Адаховська Віра Сергіївна","input":["Адаховська Віра Сергіївна","Віра Сергіївна Адаховська","Віра Адаховська"]},"name_unclear":false},"source":"VULYK","intro":{"declaration_year":"2014","isnotdeclaration":"","declaration_year_hidden":false}}