{"income":{"5":{"family_comment":"","value":"241305","family":"88113","comment":""},"6":{"family_comment":"","value":"241175","family":"69163","comment":""},"7":{"family_comment":"","value":"","source_name":"","family":"","comment":""},"8":{"family_comment":"","value":"","family":"","comment":""},"9":{"value":"130","comment_unclear":false,"family_comment":"","family":"7406","comment":"","family_comment_unclear":false},"10":{"family_comment":"","value":"","family":"","comment":""},"11":{"family_comment":"","value":"","family":"","comment":""},"12":{"family_comment":"","value":"","family":"","comment":""},"13":{"family_comment":"","value":"","family":"","comment":""},"14":{"family_comment":"","value":"","family":"","comment":""},"15":{"family_comment":"","value":"","family":"","comment":""},"16":{"family_comment":"","value":"","family":"","comment":""},"17":{"family_comment":"","value":"","family":"","comment":""},"18":{"family_comment":"","value":"","family":"","comment":""},"19":{"value":"","family_comment":"","value_unclear":false,"family_unclear":false,"family":"","comment":""},"20":{"value":"","family_comment":"","value_unclear":false,"comment_hidden":false,"family_comment_hidden":false,"family_unclear":false,"family_comment_unclear":false,"comment_unclear":false,"comment":"","family":"11544"}},"id":"vulyk_106_34","banks":{"45":[{"sum_foreign_comment":"","sum_units":"UAH","sum_comment":"","sum_foreign_comment_hidden":false,"sum_hidden":false,"sum_foreign_units":"UAH","sum_comment_hidden":false,"sum":"245","sum_foreign":""}],"51":[{"sum_foreign_comment":"","sum_units":"UAH","sum_comment":"","sum_comment_unclear":false,"sum_foreign_comment_hidden":false,"sum_foreign_units":"UAH","sum_comment_hidden":false,"sum":"79212","sum_foreign":""}]},"declaration":{"additional_info_text":"","notfull_lostpages":"","date":"2016-03-30T00:00:00","notfull":"","additional_info":"","url":"http://static.declarations.com.ua/declarations/chosen_ones/judges_batch/2173_koval_liubov_anatoliivna.pdf"},"liabilities":{"54":{"sum_foreign_comment":"","sum":"","sum_comment":"","sum_comment_unclear":false,"sum_hidden":false,"sum_comment_hidden":false,"sum_foreign":""},"55":{"sum_foreign_comment":"","sum":"","sum_hidden":false,"sum_comment":"","sum_foreign":""},"56":{"sum_foreign_comment":"","sum":"","sum_comment":"","sum_hidden":false,"sum_comment_hidden":false,"sum_unclear":false,"sum_foreign":""},"57":{"sum_foreign_comment":"","sum":"","sum_comment":"","sum_hidden":false,"sum_comment_hidden":false,"sum_foreign":""},"58":{"sum_foreign_comment":"","sum":"","sum_comment":"","sum_hidden":false,"sum_comment_hidden":false,"sum_foreign":""},"59":{"sum_foreign_comment":"","sum":"","sum_comment":"","sum_foreign":""},"60":{"sum_foreign_comment":"","sum":"","sum_comment":"","sum_hidden":false,"sum_comment_hidden":false,"sum_foreign":""},"61":{"sum_foreign_comment":"","sum":"","sum_comment":"","sum_foreign":""},"62":{"sum_foreign_comment":"","sum":"","sum_comment":"","sum_comment_hidden":false,"sum_unclear":false,"sum_foreign":""},"63":{"sum_foreign_comment":"","sum":"","sum_comment":"","sum_foreign":""},"64":{"sum_foreign_comment":"","sum":"","sum_comment":"","sum_foreign":""}},"ft_src":"суддя дніпропетровського апеляційного господарського суду\nДніпропетровська область\nАпеляційний господарський суд\nЛюбов\nКоваль О. М\nПодружжя\nКоваль І. О\nДитина\nАнатоліївна\nКоваль Любов Анатоліївна\nЛюбов Анатоліївна Коваль\nЛюбов Коваль\nКоваль Любов Анатоліївна\nКоваль Любов Анатоліївна\nКоваль\n130\n7406\n11544\n88113\n241305\n69163\n241175\n79212\n245\n63.6\n651.5\nспільна сумісна власність\n45.3\n2015\n69163\n241175\n7406\n130\n88113\n241305\n11544\n245\n79212\n63.6\n651.5\n45.3\nспільна сумісна власність\nКоваль Любов Анатоліївна\nЛюбов Анатоліївна Коваль\nЛюбов Коваль\nКоваль Любов Анатоліївна\nКоваль Любов Анатоліївна\nПодружжя\nКоваль О. М\nДитина\nКоваль І. О\nЛюбов\nКоваль\nДніпропетровська область\nАпеляційний господарський суд\nсуддя дніпропетровського апеляційного господарського суду\nАнатоліївна\n241175\n69163\n11544\n241305\n88113\n130\n7406\n2015\nКоваль О. М\nПодружжя\nКоваль І. О\nДитина\nАнатоліївна\nКоваль\nЛюбов\nКоваль Любов Анатоліївна\nЛюбов Анатоліївна Коваль\nЛюбов Коваль\nКоваль Любов Анатоліївна\nДніпропетровська область\nАпеляційний господарський суд\nсуддя дніпропетровського апеляційного господарського суду\nКоваль Любов Анатоліївна\n63.6\nспільна сумісна власність\n45.3\n651.5\n245\n79212\n2015","general":{"inn":"","name":"Любов","inn_unclear":false,"family":[{"inn":"","inn_hidden":true,"relations_unclear":false,"relations_hidden":false,"relations_other":"","relations":"Подружжя","name_hidden":false,"family_name":"Коваль О. М","name_unclear":false},{"inn":"","relations":"Дитина","relations_unclear":false,"family_name":"Коваль І. О","inn_hidden":false,"relations_other":"","name_hidden":false,"name_unclear":false}],"inn_hidden":true,"family_raw":"","last_name":"Коваль","post":{"region_unclear":false,"region":"Дніпропетровська область","post":"суддя дніпропетровського апеляційного господарського суду","office":"Апеляційний господарський суд","office_unclear":false,"post_hidden":false},"full_name":"Коваль Любов Анатоліївна","addresses":[{"place_district":"","place_city_hidden":false,"place_city":"","place_city_type_hidden":false,"place_district_hidden":false,"place_city_type":"","place_address_hidden":false,"place_address":"","place_hidden":true,"place":""}],"patronymic":"Анатоліївна","full_name_suggest":{"output":"Коваль Любов Анатоліївна","input":["Коваль Любов Анатоліївна","Любов Анатоліївна Коваль","Любов Коваль"]},"name_unclear":false},"source":"VULYK","estate":{"25":[{"costs":"","costs_comment":"","address_hidden":false,"region_hidden":true,"space_comment":"спільна сумісна власність","space":"45.3","address":"","region":"","costs_rent_comment":"","space_comment_unclear":false,"space_units":"м²","costs_rent":""}],"31":[{"space_unclear":false,"address_hidden":true,"region_hidden":true,"space_comment":"","space_hidden":false,"space":"63.6","address":"","region":"","costs_property":"","costs_rent_comment":"","space_comment_unclear":false,"space_units":"м²","costs_property_comment":"","costs_rent":""}],"34":[{"costs_rent":"","costs_property":"","costs_rent_comment":"","address_hidden":false,"region_hidden":true,"space_comment":"","costs_property_comment":"","space_units":"м²","space":"651.5","address":""}]},"intro":{"declaration_year":"2015","isnotdeclaration":""}}