{"income":{"5":{"value":"490118","family_comment":"","value_unclear":false,"family_hidden":false,"value_hidden":false,"family_unclear":false,"family":"95248","comment":"","family_comment_unclear":false},"6":{"family_comment":"","family_unclear":false,"value":"270184","family":"93097","comment":""},"7":{"source_name_unclear":false,"value":"","family_comment":"","source_name":"","family":"","comment":"","source_name_hidden":false},"8":{"family_comment":"","value":"","family":"","comment":""},"9":{"family_comment":"","family_unclear":false,"value":"1054","family":"2151","comment":""},"10":{"family_comment":"","value":"","family":"","comment":""},"11":{"family_comment":"","value":"","family":"","comment":""},"12":{"family_comment":"","value":"","family":"","comment":""},"13":{"family_comment":"","value":"","family":"","comment":""},"14":{"family_comment":"","value":"","family":"","comment":""},"15":{"family_comment":"","value":"","family":"","comment":""},"16":{"value":"","value_unclear":false,"value_hidden":false,"family_comment":"","family":"","comment":""},"17":{"family_comment":"","value":"","family":"","comment":""},"18":{"family_comment":"","value":"","family":"","comment":""},"19":{"family_comment":"","value":"218880","family":"","comment":""},"20":{"value":"","family_comment":"","value_unclear":false,"comment_hidden":false,"family_hidden":false,"family":"","value_hidden":false,"family_unclear":false,"comment_unclear":false,"comment":"","family_comment_unclear":false}},"vehicle":{"35":[{"year_hidden":false,"brand_info":"2.0","sum_rent_comment":"","sum_rent_hidden":false,"year":"2007","sum_hidden":false,"brand_info_hidden":false,"brand_info_unclear":false,"year_unclear":false,"sum_rent":"","sum":"","brand":"Mitsubishi Outlander","sum_comment":"","brand_unclear":false,"brand_hidden":false}]},"id":"vulyk_62_179","banks":{"45":[{"sum_units":"UAH","sum_hidden":false,"sum_foreign_units_hidden":false,"sum":"1145","sum_foreign":"","sum_foreign_comment":"","sum_foreign_hidden":false,"sum_comment":"","sum_comment_unclear":false,"sum_foreign_units":"UAH","sum_comment_hidden":false,"sum_unclear":false}],"51":[{"sum_units":"UAH","sum_hidden":false,"sum_foreign_units_hidden":false,"sum":"1900","sum_foreign":"","sum_foreign_comment":"","sum_foreign_hidden":false,"sum_comment":"","sum_comment_unclear":false,"sum_foreign_units":"UAH","sum_comment_hidden":false,"sum_unclear":false}]},"declaration":{"additional_info_text":"","notfull_lostpages":"","date":"2014-03-30T00:00:00","notfull":"","additional_info":"","url":"http://static.declarations.com.ua/declarations/chosen_ones/mega_batch/hovorukha_volodymyr_ivanovych.pdf"},"liabilities":{"54":{"sum_foreign_comment":"","sum":"6820","sum_comment":"","sum_hidden":false,"sum_comment_hidden":false,"sum_foreign":""},"55":{"sum_foreign_comment":"","sum":"","sum_comment":"","sum_hidden":false,"sum_comment_hidden":false,"sum_unclear":false,"sum_foreign":""},"56":{"sum_foreign_comment":"","sum":"","sum_comment":"","sum_hidden":false,"sum_unclear":false,"sum_foreign":""},"57":{"sum_foreign_comment":"","sum":"","sum_comment":"","sum_hidden":false,"sum_comment_hidden":false,"sum_unclear":false,"sum_foreign":""},"58":{"sum_foreign_comment":"","sum_foreign_hidden":false,"sum_comment":"","sum_hidden":false,"sum_comment_hidden":false,"sum_unclear":false,"sum":"","sum_foreign":""},"59":{"sum_foreign_comment":"","sum":"","sum_comment":"","sum_foreign":""},"60":{"sum_foreign_comment":"","sum_foreign_hidden":false,"sum_comment":"","sum_hidden":false,"sum_comment_hidden":false,"sum_unclear":false,"sum":"","sum_foreign":""},"61":{"sum_foreign_comment":"","sum_foreign_hidden":false,"sum_comment":"","sum_hidden":false,"sum":"","sum_foreign":""},"62":{"sum_foreign_comment":"","sum":"","sum_comment":"","sum_unclear":false,"sum_foreign":""},"63":{"sum_foreign_comment":"","sum":"","sum_comment":"","sum_hidden":false,"sum_comment_hidden":false,"sum_unclear":false,"sum_foreign":""},"64":{"sum_foreign_comment":"","sum":"","sum_comment":"","sum_comment_unclear":false,"sum_hidden":false,"sum_comment_hidden":false,"sum_foreign":""}},"ft_src":"6820\nсуддя апеляційного суду київської області\nКиївська область\nЗагальний апеляційний суд\nВолодимир\nГоворуха Н. В\nПодружжя\nГоворуха А. В\nДитина\nІванович\nГоворуха Володимир Іванович\nВолодимир Іванович Говоруха\nВолодимир Говоруха\nГоворуха Володимир Іванович\nГоворуха Володимир Іванович\nГоворуха\n2.0\nMitsubishi Outlander\n2007\n1900\n1145\n2014\n2.0\nMitsubishi Outlander\n2007\n1145\n1900\n1802\n1/2 квартири\n32\n62\nПодружжя\nГоворуха Н. В\nДитина\nГоворуха А. В\nГоворуха Володимир Іванович\nВолодимир Іванович Говоруха\nВолодимир Говоруха\nГоворуха Володимир Іванович\nГоворуха Володимир Іванович\nВолодимир\nІванович\nЗагальний апеляційний суд\nсуддя апеляційного суду київської області\nКиївська область\nГоворуха\n6820\n270184\n93097\n490118\n95248\n1054\n2151\n218880\n2014\n6820\n1/2 квартири\n32\n1802\n62\nПодружжя\nГоворуха Н. В\nГоворуха А. В\nДитина\nІванович\nГоворуха\nВолодимир\nГоворуха Володимир Іванович\nВолодимир Іванович Говоруха\nВолодимир Говоруха\nГоворуха Володимир Іванович\nКиївська область\nсуддя апеляційного суду київської області\nЗагальний апеляційний суд\nГоворуха Володимир Іванович\n93097\n270184\n95248\n490118\n218880\n2151\n1054\nMitsubishi Outlander\n2.0\n2007\n218880\n490118\n95248\n2151\n1054\n93097\n270184\n1/2 квартири\n32\n62\n1802\n1145\n1900\n2014","general":{"inn":"","name":"Володимир","inn_unclear":false,"family":[{"inn":"","inn_hidden":true,"relations_unclear":false,"relations_hidden":false,"relations_other":"","relations":"Подружжя","name_hidden":false,"inn_unclear":false,"family_name":"Говоруха Н. В","name_unclear":false},{"inn":"","inn_hidden":false,"relations_hidden":false,"family_name":"Говоруха А. В","relations_other":"","relations":"Дитина","name_hidden":false,"name_unclear":false}],"inn_hidden":true,"family_raw":"","last_name":"Говоруха","post":{"post_unclear":false,"post":"суддя апеляційного суду київської області","post_hidden":false,"region":"Київська область","region_hidden":false,"office":"Загальний апеляційний суд","office_hidden":false,"office_unclear":false},"full_name_suggest":{"output":"Говоруха Володимир Іванович","input":["Говоруха Володимир Іванович","Володимир Іванович Говоруха","Володимир Говоруха"]},"full_name":"Говоруха Володимир Іванович","addresses":[{"place_city_type_unclear":false,"place_address":"","place_district_hidden":true,"place_city_type":"","place_address_hidden":true,"place_address_unclear":false,"place_city_type_hidden":false,"place":"","place_district":"","place_unclear":false,"place_city":"","place_city_unclear":false,"place_hidden":true,"place_city_hidden":true,"place_district_unclear":false}],"patronymic":"Іванович","last_name_unclear":false,"name_unclear":false},"source":"VULYK","estate":{"25":[{"region_unclear":false,"space_hidden":false,"costs":"","costs_comment":"","costs_hidden":false,"address_hidden":false,"region_hidden":true,"space_comment":"","space_unclear":false,"space":"62","address":"","region":"","costs_rent_comment":"","space_units":"м²","costs_rent":""}],"29":[{"region_unclear":false,"space_hidden":false,"address_hidden":false,"region_hidden":true,"space_comment":"","space_unclear":false,"space":"1802","address":"","region":"","costs_property":"","costs_rent_comment":"","address_unclear":false,"space_units":"м²","costs_property_comment":"","costs_rent":""}],"31":[{"region_unclear":false,"space_hidden":false,"address_hidden":false,"region_hidden":true,"space_comment":"1/2 квартири","space_unclear":false,"space":"32","costs_property_unclear":false,"region":"","costs_property":"","costs_rent_comment":"","space_comment_unclear":false,"address_unclear":false,"space_units":"м²","costs_property_comment":"","costs_rent":"","address":""}]},"intro":{"declaration_year":"2014","isnotdeclaration":"","declaration_year_unclear":false,"declaration_year_hidden":false}}