{"id":"vulyk_75_78","ft_src":"Hyundai Elantra\n2000 куб. см.\n2006\n68.14\n19.2\n4.67\n68.14\n2014\n64505\n255820\n18689\n84472\n275254\n4217\nпенсія\nдопомога до 9 травня учасника бойових дій\n15750\n745\n2000 куб. см.\n2006\nHyundai Elantra\n2014\nЗагальний апеляційний суд\nсуддя апеляційного суду запорізької області\nЗапорізька область\nПанкеєв\nПанкеєв Олександр Вікторович\nОлександр Вікторович Панкеєв\nОлександр Панкеєв\nПанкеєв Олександр Вікторович\nОлександр\nПодружжя\nПанкеєва М. В\nПанкеєв Олександр Вікторович\nВікторович\n255820\n64505\nпенсія\n745\nдопомога до 9 травня учасника бойових дій\n15750\n18689\n275254\n84472\n4217\n4.67\n19.2\n68.14\n68.14\nПанкеєва М. В\nПодружжя\nПанкеєв\nВікторович\nсуддя апеляційного суду запорізької області\nЗапорізька область\nЗагальний апеляційний суд\nПанкеєв Олександр Вікторович\nПанкеєв Олександр Вікторович\nОлександр Вікторович Панкеєв\nОлександр Панкеєв\nПанкеєв Олександр Вікторович\nОлександр","estate":{"25":[{"address":"","space_units":"м²","space_hidden":false,"space_unclear":false,"region_hidden":false,"costs_comment":"","space_comment":"","address_hidden":false,"space":"68.14","costs_rent_comment":"","costs":"","region":"","costs_rent":""}],"27":[{"address":"","space_units":"м²","space_hidden":false,"space_unclear":false,"region_hidden":false,"costs_comment":"","space_comment":"","space":"19.2","costs_rent_comment":"","costs":"","region":"","costs_rent":""}],"29":[{"costs_property_comment":"","costs_property":"","address":"","space_units":"га","space_comment":"","region_hidden":false,"space_units_unclear":false,"region":"","address_hidden":true,"costs_rent_comment":"","space":"4.67","costs_rent":""}],"31":[{"costs_property_comment":"","address":"","space_units":"м²","space_unclear":false,"region_hidden":false,"costs_property":"","space_comment":"","address_hidden":true,"costs_rent_comment":"","space":"68.14","region":"","costs_rent":""}]},"vehicle":{"35":[{"sum_comment":"","brand_unclear":false,"sum_rent":"","sum":"","sum_rent_comment":"","brand_hidden":false,"brand":"Hyundai Elantra","brand_info":"2000 куб. см.","brand_info_unclear":false,"year":"2006","sum_unclear":false}]},"source":"VULYK","income":{"5":{"family_comment":"","value":"275254","family":"84472","comment":""},"6":{"family_comment":"","family_hidden":false,"value":"255820","family":"64505","comment":""},"7":{"family":"","family_comment":"","value":"","comment":"","source_name":""},"8":{"family_comment":"","value":"","family":"","comment":""},"9":{"family_comment":"","family":"","comment":"","value_unclear":false,"family_hidden":false,"value":""},"10":{"family":"","family_comment":"","comment":"","value_hidden":false,"value":"","family_hidden":false,"family_unclear":false},"11":{"family_comment":"","value":"","family":"","comment":""},"12":{"family_comment":"","value":"","family":"","comment":""},"13":{"family_comment":"","value":"","family":"","comment":""},"14":{"family_comment":"","value":"","family":"","comment":""},"15":{"family_comment":"","value":"18689","family":"","comment":""},"16":{"family_comment":"","value":"","family":"","comment":""},"17":{"family_comment":"","value":"","family":"","comment":""},"18":{"family_comment":"","value":"","family":"","comment":""},"19":{"family_comment":"","value":"","family":"4217","comment":""},"20":{"family_comment":"пенсія","comment":"допомога до 9 травня учасника бойових дій","family":"15750","comment_unclear":false,"value":"745","family_comment_unclear":false}},"general":{"inn":"","inn_hidden":false,"last_name":"Панкеєв","full_name":"Панкеєв Олександр Вікторович","family":[{"inn":"","family_name":"Панкеєва М. В","relations_other":"","relations_hidden":false,"name_unclear":false,"inn_hidden":false,"name_hidden":false,"relations":"Подружжя"}],"patronymic":"Вікторович","name":"Олександр","post":{"office":"Загальний апеляційний суд","region":"Запорізька область","post":"суддя апеляційного суду запорізької області"},"family_raw":"","full_name_suggest":{"input":["Панкеєв Олександр Вікторович","Олександр Вікторович Панкеєв","Олександр Панкеєв"],"output":"Панкеєв Олександр Вікторович"}},"liabilities":{"54":{"sum_comment":"","sum_foreign_comment":"","sum_foreign":"","sum":""},"55":{"sum_comment":"","sum_foreign_comment":"","sum_foreign":"","sum":""},"56":{"sum_comment":"","sum_foreign_comment":"","sum_foreign":"","sum":""},"57":{"sum_comment":"","sum_foreign_comment":"","sum_foreign":"","sum":""},"58":{"sum_comment":"","sum_foreign_comment":"","sum_foreign":"","sum":""},"59":{"sum_comment_unclear":false,"sum_comment":"","sum":"","sum_foreign_comment":"","sum_foreign":"","sum_unclear":false},"60":{"sum_comment":"","sum_foreign_comment":"","sum_foreign":"","sum":""},"61":{"sum_comment":"","sum_foreign_comment":"","sum_foreign":"","sum":""},"62":{"sum_comment":"","sum_foreign_comment":"","sum_foreign":"","sum_unclear":false,"sum":""},"63":{"sum_comment":"","sum_foreign_comment":"","sum_foreign":"","sum":""},"64":{"sum_comment":"","sum_foreign_comment":"","sum_foreign":"","sum":""}},"declaration":{"notfull_lostpages":"","additional_info_text":"","additional_info":"","date":"2015-03-25T00:00:00","notfull":"","url":"http://static.declarations.com.ua/declarations/chosen_ones/judges_batch/1857_pankeiev_oleksandr_viktorovych.pdf"},"intro":{"isnotdeclaration":"","declaration_year":"2014"}}