{"income":{"5":{"value":"180110","family_unclear":false,"family_hidden":false,"family_comment":"","family":"83664","comment":""},"6":{"family_comment":"","value":"179762","family_hidden":false,"comment":"","family":""},"7":{"family_comment":"","value":"","source_name":"","family":"","comment":""},"8":{"family_comment":"","value":"","family":"","comment":""},"9":{"value":"","comment_unclear":false,"family_hidden":false,"family_comment":"","family":"","comment":""},"10":{"family_comment":"","value":"","family":"","comment":""},"11":{"family_comment":"","value":"","family":"","comment":""},"12":{"family_comment":"","value":"","family":"","comment":""},"13":{"family_comment":"","value":"","family":"","comment":""},"14":{"family_comment":"","value":"","family":"","comment":""},"15":{"family_comment":"","value":"","value_unclear":false,"family":"","comment":""},"16":{"family_comment":"","value":"","family":"","comment":""},"17":{"family_comment":"","value":"","family":"","comment":""},"18":{"family_comment":"","value":"","family":"","comment":""},"19":{"family_comment":"","value":"","family":"","comment":""},"20":{"value":"348","comment_unclear":false,"comment_hidden":false,"family_hidden":false,"value_hidden":false,"family_comment":"","value_unclear":false,"family":"83664","comment":"","family_comment_hidden":false}},"vehicle":{"40":[{"brand_info":"1800 куб. см. 160 кВт","sum_rent_comment":"","brand":"Volkswagen Passat B6","sum_comment":"","year":"2008","brand_info_hidden":false,"sum":"","sum_rent":""}]},"id":"vulyk_41_70","banks":{"45":[{"sum_foreign_comment":"","sum_units":"UAH","sum_comment":"","sum_foreign_unclear":false,"sum_foreign_units":"UAH","sum_hidden":false,"sum_comment_hidden":false,"sum":"","sum_foreign":""},{"sum_foreign_comment":"","sum_units":"","sum_comment":"","sum_foreign_unclear":false,"sum_foreign_units":"","sum":"","sum_foreign":""}],"46":[{"sum_foreign_comment":"","sum_units":"UAH","sum_comment":"","sum_foreign_units":"UAH","sum_comment_hidden":false,"sum_unclear":false,"sum":"","sum_foreign":""},{"sum_foreign_comment":"","sum_units":"","sum_comment":"","sum_foreign_units":"","sum":"","sum_unclear":false,"sum_foreign":""}],"47":[{"sum_foreign_comment":"","sum_units":"UAH","sum_comment":"","sum_foreign_units":"UAH","sum":"","sum_foreign":""},{"sum_foreign_comment":"","sum_units":"","sum_comment":"","sum_foreign_units":"","sum":"","sum_foreign":""}],"48":[{"sum_foreign_comment":"","sum_units":"UAH","sum_comment":"","sum_foreign_units":"UAH","sum":"","sum_foreign":""}],"49":[{"sum_foreign_comment":"","sum_units":"UAH","sum_comment":"","sum_foreign_units":"UAH","sum":"","sum_foreign":""}],"50":[{"sum_foreign_comment":"","sum_units":"UAH","sum_comment":"","sum_foreign_units":"UAH","sum":"","sum_foreign":""}],"51":[{"sum_foreign_comment":"","sum_units":"UAH","sum_comment":"","sum_hidden":false,"sum_foreign_units":"UAH","sum_comment_hidden":false,"sum_unclear":false,"sum":"","sum_foreign":""},{"sum_foreign_comment":"","sum_units":"","sum_comment":"","sum_foreign_units":"","sum":"","sum_foreign":""}],"52":[{"sum_foreign_comment":"","sum_units":"UAH","sum_comment":"","sum_foreign_units":"UAH","sum_comment_hidden":false,"sum_unclear":false,"sum":"","sum_foreign":""}],"53":[{"sum_foreign_comment":"","sum_units":"UAH","sum_comment":"","sum_foreign_units":"UAH","sum_comment_hidden":false,"sum":"","sum_foreign":""},{"sum_foreign_comment":"","sum_units":"","sum_comment":"","sum_foreign_units":"","sum":"","sum_foreign":""},{"sum_foreign_comment":"","sum_units":"","sum_comment":"","sum_foreign_units":"","sum":"","sum_foreign":""}]},"declaration":{"date":"2015-03-23T00:00:00","additional_info_text":"","additional_info":"","url":"http://static.declarations.com.ua/declarations/chosen_ones/mega_batch/kuchma_kostiantyn_serhiiovych.pdf"},"liabilities":{"54":{"sum_foreign_comment":"","sum_comment_hidden":true,"sum":"1501","sum_comment":"","sum_foreign":""},"55":{"sum_foreign_comment":"","sum":"","sum_comment":"","sum_foreign":""},"56":{"sum_foreign_comment":"","sum":"","sum_hidden":false,"sum_comment":"","sum_foreign":""},"57":{"sum_foreign_comment":"","sum":"","sum_comment":"","sum_comment_hidden":false,"sum_unclear":false,"sum_foreign":""},"58":{"sum_foreign_comment":"","sum_comment_hidden":false,"sum":"","sum_comment":"","sum_foreign":""},"59":{"sum_foreign_comment":"","sum":"","sum_comment":"","sum_foreign":""},"60":{"sum_foreign_comment":"","sum_comment_hidden":false,"sum":"","sum_comment":"","sum_foreign":""},"61":{"sum_foreign_comment":"","sum":"","sum_comment":"","sum_foreign":""},"62":{"sum_foreign_comment":"","sum":"","sum_comment":"","sum_foreign":""},"63":{"sum_foreign_comment":"","sum":"","sum_comment":"","sum_comment_hidden":false,"sum_unclear":false,"sum_foreign":""},"64":{"sum_foreign_comment":"","sum_comment_hidden":false,"sum":"","sum_comment":"","sum_foreign":""}},"ft_src":"1501\nсуддя дніпропетровського окружного адміністративного суду\nДніпропетровська область\nАдміністративний місцевий суд\nКостянтин\nКучма С. В\nБатьки\nКучма Г. І\nБатьки\nСергійович\nКучма Костянтин Сергійович\nКостянтин Сергійович Кучма\nКостянтин Кучма\nКучма Костянтин Сергійович\nКучма\nКучма Костянтин Сергійович\nДніпропетровськ\nДніпропетровська область\n1800 куб. см. 160 кВт\n2008\nVolkswagen Passat B6\n2014\nVolkswagen Passat B6\n1800 куб. см. 160 кВт\n2008\n135.7\nм. Кривий Ріг\nДніпропетровська область\n54\n1/3 частина квартири\nм. Дніпропетровськ\nДніпропетровська область\n24.1\nм. Кривий Ріг\nДніпропетровська область\n600\nм. Кривий Ріг\nДніпропетровська область\n54\n2/3 частини квартири\nм. Дніпропетровськ\nДніпропетровська область\n100.3\nДніпропетровська область\nм. Дніпропетровськ\nБатьки\nКучма С. В\nБатьки\nКучма Г. І\nКучма Костянтин Сергійович\nКостянтин Сергійович Кучма\nКостянтин Кучма\nКучма Костянтин Сергійович\nКучма Костянтин Сергійович\nКостянтин\nСергійович\nАдміністративний місцевий суд\nсуддя дніпропетровського окружного адміністративного суду\nДніпропетровська область\nКучма\nДніпропетровська область\nДніпропетровськ\n1501\n179762\n348\n83664\n180110\n83664\n2014\n1501\nм. Кривий Ріг\nДніпропетровська область\n600\nДніпропетровська область\nм. Кривий Ріг\n24.1\nДніпропетровська область\nм. Кривий Ріг\n135.7\n2/3 частини квартири\nм. Дніпропетровськ\nДніпропетровська область\n54\nДніпропетровська область\nм. Дніпропетровськ\n100.3\n1/3 частина квартири\nм. Дніпропетровськ\n54\nДніпропетровська область\nКучма С. В\nБатьки\nКучма Г. І\nБатьки\nСергійович\nКучма\nКостянтин\nКучма Костянтин Сергійович\nКостянтин Сергійович Кучма\nКостянтин Кучма\nКучма Костянтин Сергійович\nДніпропетровська область\nДніпропетровськ\nДніпропетровська область\nсуддя дніпропетровського окружного адміністративного суду\nАдміністративний місцевий суд\nКучма Костянтин Сергійович\n179762\n83664\n180110\n83664\n348\nVolkswagen Passat B6\n1800 куб. см. 160 кВт\n2008\n348\n83664\n180110\n83664\n179762\n2/3 частини квартири\nм. Дніпропетровськ\nДніпропетровська область\n54\nм. Дніпропетровськ\nДніпропетровська область\n100.3\nм. Кривий Ріг\nДніпропетровська область\n135.7\nм. Кривий Ріг\nДніпропетровська область\n24.1\n1/3 частина квартири\nм. Дніпропетровськ\nДніпропетровська область\n54\nм. Кривий Ріг\nДніпропетровська область\n600\n2014","general":{"inn":"","name":"Костянтин","family":[{"inn":"","relations":"Батьки","relations_hidden":false,"inn_hidden":true,"family_name":"Кучма С. В","name_hidden":true,"name_unclear":false},{"inn":"","relations":"Батьки","relations_other":"","inn_hidden":false,"family_name":"Кучма Г. І","name_hidden":false,"name_unclear":false}],"patronymic":"Сергійович","inn_hidden":true,"family_raw":"","last_name":"Кучма","post":{"post_unclear":false,"post":"суддя дніпропетровського окружного адміністративного суду","post_hidden":false,"region":"Дніпропетровська область","region_hidden":false,"office":"Адміністративний місцевий суд","office_hidden":false},"last_name_unclear":false,"full_name":"Кучма Костянтин Сергійович","addresses":[{"place_district":"","place_city_hidden":false,"place_city":"Дніпропетровськ","place_city_type_hidden":false,"place_district_hidden":false,"place_city_type":"Місто","place_address_hidden":true,"place_address":"","place_hidden":true,"place":"Дніпропетровська область"}],"patronymic_hidden":false,"full_name_suggest":{"output":"Кучма Костянтин Сергійович","input":["Кучма Костянтин Сергійович","Костянтин Сергійович Кучма","Костянтин Кучма"]},"name_unclear":false},"source":"VULYK","estate":{"23":[{"region_unclear":false,"space_unclear":false,"costs":"","costs_comment":"","address_hidden":false,"region_hidden":false,"space_comment":"","space":"","address":"","costs_comment_unclear":false,"region":"","space_units_unclear":false,"space_comment_hidden":false,"space_units":"м²","costs_rent":"","costs_rent_comment":""},{"costs_rent":"","space_unclear":false,"region":"","costs":"","costs_rent_comment":"","costs_comment":"","space_comment":"","space_units":"","space":"","address":""},{"costs_rent":"","region":"","costs":"","costs_rent_comment":"","costs_comment":"","space_comment":"","space_units":"","space":"","address":""}],"25":[{"region_unclear":false,"space_hidden":false,"costs":"","costs_comment":"","address_hidden":true,"region_hidden":false,"space_comment":"1/3 частина квартири","space_unclear":false,"space":"54","address":"м. Дніпропетровськ","costs_comment_unclear":false,"region":"Дніпропетровська область","costs_rent_comment":"","costs_unclear":false,"space_units":"м²","costs_rent":""}],"29":[{"space_unclear":false,"costs_property_comment":"","address_hidden":true,"region_hidden":false,"space_comment":"","space":"600","address":"м. Кривий Ріг","region":"Дніпропетровська область","costs_property":"","costs_rent_comment":"","space_units":"м²","space_units_unclear":false,"costs_rent":""}],"30":[{"costs_rent":"","region":"Дніпропетровська область","costs_property":"","costs_rent_comment":"","address_hidden":true,"region_hidden":false,"space_comment":"","costs_property_comment":"","space_units":"м²","space":"135.7","address":"м. Кривий Ріг"}],"31":[{"space_hidden":false,"address_hidden":true,"region_hidden":false,"space_comment":"2/3 частини квартири","space":"54","address":"м. Дніпропетровськ","region":"Дніпропетровська область","costs_property":"","costs_rent_comment":"","space_comment_unclear":false,"space_units":"м²","costs_property_comment":"","costs_rent":""},{"costs_rent":"","region":"Дніпропетровська область","costs_property":"","costs_rent_comment":"","space_comment_unclear":false,"space_comment":"","costs_property_comment":"","space_units":"м²","space":"100.3","address":"м. Дніпропетровськ"}],"33":[{"costs_rent":"","region":"Дніпропетровська область","costs_property":"","costs_rent_comment":"","address_hidden":true,"region_hidden":false,"space_comment":"","costs_property_comment":"","space_units":"м²","space":"24.1","address":"м. Кривий Ріг"}]},"intro":{"declaration_year":"2014"}}