{"income":{"5":{"value":"220048","family_comment":"","value_unclear":false,"family_hidden":false,"value_hidden":false,"family_unclear":false,"comment_unclear":false,"comment":"","family":"51830"},"6":{"value":"207431","family_unclear":false,"family_hidden":false,"family_comment":"","family":"39009","comment":""},"7":{"value":"","family_hidden":false,"value_hidden":false,"family_comment":"","source_name":"","family":"","comment":""},"8":{"family_comment":"","value":"","family":"","comment":""},"9":{"family_comment":"","value":"","value_unclear":false,"family":"","comment":""},"10":{"family_comment":"","family_unclear":false,"value":"12617","family":"1678","comment":""},"11":{"family_comment":"","value":"","family":"","comment":""},"12":{"family_comment":"","value":"","family":"","comment":""},"13":{"family_comment":"","value":"","family":"","comment":""},"14":{"family_comment":"","value":"","family":"","comment":""},"15":{"family_comment":"","value":"","family":"","comment":""},"16":{"family_comment":"","value":"","family":"","comment":""},"17":{"family_comment":"","value":"","family":"","comment":""},"18":{"family_comment":"","value":"","family":"","comment":""},"19":{"family_comment":"","value":"","family":"","comment":""},"20":{"value":"","value_unclear":false,"family_comment":"","comment_unclear":false,"comment":"","family":"11143"}},"id":"vulyk_71_74","declaration":{"additional_info_text":"","notfull_lostpages":"","date":"2014-03-18T00:00:00","notfull":"","additional_info":"","url":"http://static.declarations.com.ua/declarations/chosen_ones/judges_batch/561_azevych_volodymyr_bronislavovych.pdf"},"liabilities":{"54":{"sum_foreign_comment":"","sum":"","sum_comment":"","sum_comment_unclear":false,"sum_comment_hidden":false,"sum_unclear":false,"sum_foreign":""},"55":{"sum_foreign_comment":"","sum":"","sum_comment":"","sum_foreign":""},"56":{"sum_foreign_comment":"","sum":"","sum_comment":"","sum_comment_unclear":false,"sum_unclear":false,"sum_foreign":""},"57":{"sum_foreign_comment":"","sum":"","sum_comment":"","sum_comment_hidden":false,"sum_unclear":false,"sum_foreign":""},"58":{"sum_foreign_comment":"","sum":"","sum_comment":"","sum_comment_hidden":false,"sum_unclear":false,"sum_foreign":""},"59":{"sum_foreign_comment":"","sum_comment_hidden":false,"sum":"","sum_comment":"","sum_foreign":""},"60":{"sum_foreign_comment":"","sum_comment_hidden":false,"sum":"","sum_comment":"","sum_foreign":""},"61":{"sum_foreign_comment":"","sum":"","sum_comment":"","sum_foreign":""},"62":{"sum_foreign_comment":"","sum":"","sum_comment":"","sum_foreign":""},"63":{"sum_foreign_comment":"","sum":"","sum_comment":"","sum_unclear":false,"sum_foreign":""},"64":{"sum_foreign_comment":"","sum":"","sum_comment":"","sum_unclear":false,"sum_foreign":""}},"ft_src":"суддя апеляційного суду\nДонецька область\nЗагальний апеляційний суд\nВолодимир\nАзевич І. М\nПодружжя\nАзевич В. В\nДитина\nАзевич М. В\nДитина\nБроніславович\nАзевич Володимир Броніславович\nВолодимир Броніславович Азевич\nВолодимир Азевич\nАзевич Володимир Броніславович\nАзевич Володимир Броніславович\nАзевич\n1678\n12617\n11143\n220048\n51830\n207431\n39009\n33.8\n2000\n9/10\n44.1\n16.9\n2013\n39009\n207431\n1678\n12617\n51830\n220048\n11143\n207431\n39009\n11143\n220048\n51830\n12617\n1678\nПодружжя\nАзевич І. М\nДитина\nАзевич В. В\nДитина\nАзевич М. В\nАзевич Володимир Броніславович\nВолодимир Броніславович Азевич\nВолодимир Азевич\nАзевич Володимир Броніславович\nАзевич Володимир Броніславович\nВолодимир\nБроніславович\nЗагальний апеляційний суд\nДонецька область\nсуддя апеляційного суду\nАзевич\n2000\n44.1\n9/10\n33.8\n16.9\n2013\nАзевич І. М\nПодружжя\nАзевич В. В\nДитина\nАзевич М. В\nДитина\nБроніславович\nАзевич\nВолодимир\nАзевич Володимир Броніславович\nВолодимир Броніславович Азевич\nВолодимир Азевич\nАзевич Володимир Броніславович\nДонецька область\nЗагальний апеляційний суд\nсуддя апеляційного суду\nАзевич Володимир Броніславович\n33.8\n16.9\n9/10\n44.1\n2000\n2013","general":{"inn":"","name":"Володимир","family":[{"inn":"","inn_hidden":true,"relations_hidden":false,"family_name":"Азевич І. М","relations_other":"","relations":"Подружжя","name_hidden":false,"name_unclear":false},{"inn":"","inn_hidden":false,"relations_hidden":false,"family_name":"Азевич В. В","relations_other":"","relations":"Дитина","name_hidden":false,"name_unclear":false},{"inn":"","relations":"Дитина","relations_other":"","inn_hidden":false,"family_name":"Азевич М. В","name_unclear":false}],"patronymic":"Броніславович","inn_hidden":true,"family_raw":"","inn_unclear":false,"post":{"post_unclear":false,"region_unclear":false,"post":"суддя апеляційного суду","office":"Загальний апеляційний суд","region":"Донецька область","post_hidden":false,"office_unclear":false},"full_name_suggest":{"output":"Азевич Володимир Броніславович","input":["Азевич Володимир Броніславович","Володимир Броніславович Азевич","Володимир Азевич"]},"full_name":"Азевич Володимир Броніславович","addresses":[{"place_district":"","place_unclear":false,"place_city":"","place_city_type_hidden":true,"place_district_hidden":true,"place_city_type":"","place_city_hidden":true,"place_address_hidden":true,"place_address":"","place_hidden":true,"place":""}],"last_name":"Азевич","patronymic_hidden":false,"last_name_unclear":false,"name_unclear":false},"source":"VULYK","estate":{"25":[{"region_unclear":false,"space_unclear":false,"costs":"","costs_rent_unclear":false,"costs_comment":"","costs_hidden":false,"address_hidden":false,"region_hidden":true,"space_comment":"","space_hidden":false,"space":"16.9","address":"","costs_unclear":false,"region":"","address_unclear":false,"costs_rent_comment":"","costs_rent_hidden":false,"space_comment_unclear":false,"space_units":"м²","costs_rent":""}],"26":[{"space_unclear":true,"costs":"","costs_comment":"","address_hidden":false,"region_hidden":false,"space_comment":"9/10","space":"44.1","address":"","region":"","address_unclear":false,"costs_rent_comment":"","space_comment_unclear":true,"space_units":"м²","costs_rent":""}],"29":[{"space_unclear":false,"address_hidden":false,"region_hidden":true,"space_comment":"","space":"2000","address":"","region":"","costs_property":"","costs_rent_comment":"","space_units":"м²","costs_property_comment":"","costs_rent":""}],"31":[{"space_hidden":false,"costs_property_comment":"","address_hidden":false,"region_hidden":true,"space_comment":"","space":"33.8","address":"","region":"","costs_property":"","costs_rent_comment":"","space_comment_unclear":false,"space_units":"м²","space_units_hidden":false,"costs_rent":""}]},"intro":{"declaration_year":"2013","isnotdeclaration":""}}