{"income":{"5":{"value":"237751","family_unclear":false,"family_hidden":false,"family_comment":"не надано згоди","family":"","comment":""},"6":{"value":"223486","family_comment":"","value_unclear":false,"family_hidden":false,"family_unclear":false,"family":"","comment":""},"7":{"value":"867","family_hidden":false,"value_hidden":false,"family_comment":"","source_name":"","family":"","comment":"","source_name_hidden":false},"8":{"family_comment":"","value":"","family":"","comment":""},"9":{"family_comment":"","value":"","family":"","comment":""},"10":{"family_comment":"","value":"13398","value_unclear":false,"family":"","comment":""},"11":{"family_comment":"","value":"","family":"","comment":""},"12":{"family_comment":"","value":"","family":"","comment":""},"13":{"family_comment":"","value":"","family":"","comment":""},"14":{"family_comment":"","value":"","family":"","comment":""},"15":{"family_comment":"","value":"","family":"","comment":""},"16":{"family_comment":"","value":"","family":"","comment":""},"17":{"family_comment":"","value":"","family":"","comment":""},"18":{"family_comment":"","value":"","family":"","comment":""},"19":{"family_comment":"","value":"","family":"","comment":""},"20":{"value":"","family_comment":"","value_unclear":false,"family_unclear":false,"comment_unclear":false,"comment":"","family":""},"22":[{"cur":"","cur_units":"USD","country":"","uah_equal":"","country_comment":"не надано згоди"}]},"vehicle":{"40":[{"brand_info":"не надано згоди","sum_rent_comment":"","brand":"","sum_comment":"","brand_unclear":false,"year":"","brand_info_unclear":false,"year_unclear":false,"sum":"","sum_rent":""}],"41":[{"brand_info":"не надано згоди","sum_rent_comment":"","brand":"","sum_comment":"","year":"","sum":"","sum_rent":""}],"42":[{"brand_info":"не надано згоди","sum_rent_comment":"","brand":"","sum_comment":"","year":"","sum":"","sum_rent":""}],"43":[{"brand_info":"не надано згоди","sum_rent_comment":"","brand":"","sum_comment":"","sum":"","sum_rent":""}],"44":[{"brand_info":"не надано згоди","sum_rent_comment":"","brand":"","sum_comment":"","year":"","sum":"","sum_rent":""}]},"id":"vulyk_74_21","banks":{"47":[{"sum_foreign_comment":"","sum_units":"UAH","sum_comment":"","sum_foreign_units":"UAH","sum":"401","sum_foreign":""}]},"declaration":{"additional_info_text":"","notfull_lostpages":"","date":"2014-03-17T00:00:00","notfull":"","additional_info":"","url":"http://static.declarations.com.ua/declarations/chosen_ones/judges_batch/1763_babenko_kostiantyn_anatoliiovych.pdf"},"liabilities":{"54":{"sum_foreign_comment":"","sum":"","sum_comment":"","sum_comment_unclear":false,"sum_comment_hidden":false,"sum_foreign":""},"55":{"sum_foreign_comment":"","sum":"","sum_comment":"","sum_hidden":false,"sum_unclear":false,"sum_foreign":""},"56":{"sum_foreign_comment":"","sum":"","sum_comment":"","sum_hidden":false,"sum_unclear":false,"sum_foreign":""},"57":{"sum_foreign_comment":"","sum":"","sum_comment":"","sum_comment_unclear":false,"sum_comment_hidden":false,"sum_foreign":""},"58":{"sum_foreign_comment":"","sum_comment_hidden":false,"sum":"","sum_comment":"","sum_foreign":""},"59":{"sum_foreign_comment":"","sum":"","sum_comment":"","sum_foreign":""},"60":{"sum_foreign_comment":"","sum":"","sum_hidden":false,"sum_comment":"","sum_foreign":""},"61":{"sum_foreign_comment":"","sum":"","sum_comment":"","sum_foreign":""},"62":{"sum_foreign_comment":"","sum":"","sum_comment":"","sum_foreign":""},"63":{"sum_foreign_comment":"","sum":"","sum_comment":"","sum_comment_unclear":false,"sum_unclear":false,"sum_foreign":""},"64":{"sum_foreign_comment":"","sum":"не надано згоди","sum_comment":"","sum_comment_unclear":false,"sum_unclear":false,"sum_foreign":""}},"ft_src":"не надано згоди\nБабенко Костянтин Анатолійович\nсуддя київського апеляційного адміністративного суду\nм. Київ\nАпеляційний адміністративний суд\nКостянтин\nБабенко Н. О\nПодружжя\nБабенко Д. К\nДитина\nБабенко Д. К\nДитина\nБабенко Костянтин Анатолійович\nКостянтин Анатолійович Бабенко\nКостянтин Бабенко\nБабенко Костянтин Анатолійович\nБабенко\nАнатолійович\nне надано згоди\nне надано згоди\nне надано згоди\nне надано згоди\nне надано згоди\nне надано згоди\n170.7\nне надано згоди\nне надано згоди\n24606\nне надано згоди\nне надано згоди\nне надано згоди\n401\n2013\nне надано згоди\nне надано згоди\nне надано згоди\nне надано згоди\nне надано згоди\n2013\nАпеляційний адміністративний суд\nм. Київ\nсуддя київського апеляційного адміністративного суду\nАнатолійович\nБабенко Костянтин Анатолійович\nКостянтин Анатолійович Бабенко\nКостянтин Бабенко\nБабенко Костянтин Анатолійович\nКостянтин\nБабенко Костянтин Анатолійович\nБабенко\nПодружжя\nБабенко Н. О\nДитина\nБабенко Д. К\nДитина\nБабенко Д. К\nне надано згоди\n867\n223486\nне надано згоди\nне надано згоди\n237751\n13398\nне надано згоди\nне надано згоди\n24606\nне надано згоди\n170.7\nне надано згоди\nне надано згоди\nне надано згоди\n401\nне надано згоди\n223486\n13398\n867\nне надано згоди\n237751\nне надано згоди\nПодружжя\nБабенко Н. О\nДитина\nБабенко Д. К\nДитина\nБабенко Д. К\nАнатолійович\nБабенко\nм. Київ\nАпеляційний адміністративний суд\nсуддя київського апеляційного адміністративного суду\nБабенко Костянтин Анатолійович\nБабенко Костянтин Анатолійович\nКостянтин Анатолійович Бабенко\nКостянтин Бабенко\nБабенко Костянтин Анатолійович\nКостянтин\nне надано згоди\nне надано згоди\nне надано згоди\nне надано згоди\nне надано згоди\n13398\nне надано згоди\n237751\n867\nне надано згоди\n223486\nне надано згоди\n24606\n170.7\nне надано згоди\nне надано згоди\nне надано згоди\nне надано згоди\nне надано згоди\n401\n2013","general":{"inn":"","inn_hidden":true,"last_name":"Бабенко","post":{"region_unclear":false,"region":"м. Київ","post":"суддя київського апеляційного адміністративного суду","office":"Апеляційний адміністративний суд","office_unclear":false,"post_hidden":false},"name":"Костянтин","full_name":"Бабенко Костянтин Анатолійович","family_raw":"","addresses":[{"place_district":"","place_city_hidden":false,"place_city":"","place_city_type_hidden":false,"place_district_hidden":false,"place_city_type":"","place_address_hidden":false,"place_address":"","place_hidden":true,"place":""}],"family":[{"inn":"","relations":"Подружжя","relations_other":"","inn_hidden":true,"family_name":"Бабенко Н. О","name_hidden":true,"name_unclear":false},{"inn":"","relations":"Дитина","relations_other":"","inn_hidden":true,"family_name":"Бабенко Д. К","name_hidden":true,"name_unclear":false},{"inn":"","relations":"Дитина","relations_other":"","inn_hidden":true,"family_name":"Бабенко Д. К","name_hidden":true,"name_unclear":false}],"full_name_suggest":{"output":"Бабенко Костянтин Анатолійович","input":["Бабенко Костянтин Анатолійович","Костянтин Анатолійович Бабенко","Костянтин Бабенко"]},"patronymic":"Анатолійович"},"source":"VULYK","estate":{"23":[{"space_hidden":false,"costs":"","costs_comment":"","address_hidden":false,"region_hidden":true,"space_comment":"","space_unclear":false,"space":"24606","address":"","region":"","space_units_unclear":false,"space_comment_unclear":false,"space_units":"м²","costs_rent":"","costs_rent_comment":""}],"24":[{"region_unclear":false,"space_hidden":false,"costs":"","costs_comment":"","address_hidden":false,"region_hidden":true,"space_comment":"","space":"170.7","address":"","region":"","space_units_unclear":false,"space_units":"м²","costs_rent":"","costs_rent_comment":""}],"29":[{"costs_rent":"","region":"","costs_property":"","costs_rent_comment":"","address_hidden":false,"region_hidden":false,"space_comment":"не надано згоди","costs_property_comment":"","space_units":"м²","space":"","address":""}],"30":[{"space_unclear":false,"address_hidden":false,"region_hidden":false,"space_comment":"не надано згоди","space":"","address":"","region":"","costs_property":"","costs_rent_comment":"","space_comment_unclear":false,"address_unclear":false,"space_units":"м²","costs_property_comment":"","costs_rent":""}],"31":[{"space_unclear":false,"address_hidden":false,"region_hidden":false,"space_comment":"не надано згоди","space":"","address":"","region":"","costs_property":"","costs_rent_comment":"","address_unclear":false,"space_units":"м²","costs_property_comment":"","costs_rent":""}],"32":[{"costs_rent":"","region":"","costs_property":"","costs_rent_comment":"","address_hidden":false,"region_hidden":false,"space_comment":"не надано згоди","costs_property_comment":"","space_units":"м²","space":"","address":""}],"33":[{"costs_rent":"","region":"","costs_property":"","costs_rent_comment":"","address_hidden":false,"region_hidden":false,"space_comment":"не надано згоди","costs_property_comment":"","space_units":"м²","space":"","address":""}],"34":[{"costs_rent":"","region":"","costs_property":"","costs_rent_comment":"","address_hidden":false,"region_hidden":false,"space_comment":"не надано згоди","costs_property_comment":"","space_units":"м²","space":"","address":""}]},"intro":{"declaration_year":"2013","isnotdeclaration":"","declaration_year_unclear":false}}