{"income":{"5":{"value":"248079","family_comment":"","value_unclear":false,"family_hidden":false,"value_hidden":false,"family_unclear":false,"comment_unclear":false,"comment":"","family":"299282"},"6":{"value":"235334","family_unclear":false,"family_hidden":false,"family_comment":"","family":"28205","comment":""},"7":{"value":"","family_hidden":false,"value_hidden":false,"family_comment":"","source_name":"","family":"","comment":""},"8":{"family_comment":"","value":"","family":"","comment":""},"9":{"family_comment":"","value":"128","value_unclear":false,"family":"","comment":""},"10":{"family_comment":"","family_unclear":false,"value":"12617","family":"","comment":""},"11":{"family_comment":"","value":"","family":"261567","comment":""},"12":{"family_comment":"","value":"","family":"","comment":""},"13":{"family_comment":"","value":"","family":"","comment":""},"14":{"family_comment":"","value":"","family":"","comment":""},"15":{"family_comment":"","value":"","family":"","comment":""},"16":{"family_comment":"","value":"","family":"","comment":""},"17":{"family_comment":"","value":"","family":"","comment":""},"18":{"family_comment":"","value":"","family":"","comment":""},"19":{"family_comment":"","value":"","family":"","comment":""},"20":{"value":"","value_unclear":false,"family_comment":"","comment_unclear":false,"comment":"","family":"9510"}},"vehicle":{"35":[{"brand_info":"2 л.","sum_rent_comment":"","year":"2010","sum_rent_unclear":false,"brand_info_unclear":false,"year_unclear":false,"sum_rent":"","sum":"","brand":"Volkswagen Passat","sum_comment":"","brand_unclear":false,"sum_unclear":false}]},"id":"vulyk_71_162","banks":{"51":[{"sum_foreign_comment":"","sum_units":"UAH","sum_comment":"","sum_comment_unclear":false,"sum_foreign_units":"UAH","sum_comment_hidden":false,"sum_unclear":false,"sum":"2302","sum_foreign":""}]},"declaration":{"additional_info_text":"","notfull_lostpages":"","date":"2014-12-11T00:00:00","notfull":"","additional_info":"","url":"http://static.declarations.com.ua/declarations/chosen_ones/judges_batch/440_remez_valentyn_anatoliiovych.pdf"},"liabilities":{"54":{"sum_foreign_comment":"","sum":"446","sum_comment":"","sum_comment_unclear":false,"sum_comment_hidden":false,"sum_unclear":false,"sum_foreign":""},"55":{"sum_foreign_comment":"","sum":"","sum_comment":"","sum_foreign":""},"56":{"sum_foreign_comment":"","sum":"","sum_comment":"","sum_comment_unclear":false,"sum_unclear":false,"sum_foreign":""},"57":{"sum_foreign_comment":"","sum":"","sum_comment":"","sum_comment_hidden":false,"sum_unclear":false,"sum_foreign":""},"58":{"sum_foreign_comment":"","sum":"","sum_comment":"","sum_comment_hidden":false,"sum_unclear":false,"sum_foreign":""},"59":{"sum_foreign_comment":"","sum_comment_hidden":false,"sum":"","sum_comment":"","sum_foreign":""},"60":{"sum_foreign_comment":"","sum_comment_hidden":false,"sum":"","sum_comment":"","sum_foreign":""},"61":{"sum_foreign_comment":"","sum":"","sum_comment":"","sum_foreign":""},"62":{"sum_foreign_comment":"","sum":"","sum_comment":"","sum_foreign":""},"63":{"sum_foreign_comment":"","sum":"","sum_comment":"","sum_unclear":false,"sum_foreign":""},"64":{"sum_foreign_comment":"","sum":"","sum_comment":"","sum_unclear":false,"sum_foreign":""}},"ft_src":"446\nсуддя апеляційного суду дніпропетровської області\nДніпропетровська область\nЗагальний апеляційний суд\nВалентин\nРемез Л. В\nПодружжя\nРемез Я. В\nДитина\nРемез М. В\nДитина\nАнатолійович\nРемез Валентин Анатолійович\nВалентин Анатолійович Ремез\nВалентин Ремез\nРемез Валентин Анатолійович\nРемез Валентин Анатолійович\nРемез\n2 л.\nVolkswagen Passat\n2010\n24\n73.2\n39\n743\n2302\n2013\n2 л.\nVolkswagen Passat\n2010\n24\n73.2\n39\n743\nПодружжя\nРемез Л. В\nДитина\nРемез Я. В\nДитина\nРемез М. В\nРемез Валентин Анатолійович\nВалентин Анатолійович Ремез\nВалентин Ремез\nРемез Валентин Анатолійович\nРемез Валентин Анатолійович\nВалентин\nАнатолійович\nЗагальний апеляційний суд\nДніпропетровська область\nсуддя апеляційного суду дніпропетровської області\nРемез\n446\n235334\n28205\n9510\n248079\n299282\n128\n12617\n261567\n2302\n2013\n446\n28205\n235334\n128\n261567\n12617\n299282\n248079\n9510\nРемез Л. В\nПодружжя\nРемез Я. В\nДитина\nРемез М. В\nДитина\nАнатолійович\nРемез\nВалентин\nРемез Валентин Анатолійович\nВалентин Анатолійович Ремез\nВалентин Ремез\nРемез Валентин Анатолійович\nДніпропетровська область\nЗагальний апеляційний суд\nсуддя апеляційного суду дніпропетровської області\nРемез Валентин Анатолійович\n2010\nVolkswagen Passat\n2 л.\n261567\n128\n12617\n9510\n248079\n299282\n235334\n28205\n73.2\n39\n24\n743\n2302\n2013","general":{"inn":"","name":"Валентин","last_name":"Ремез","family":[{"inn":"","inn_hidden":false,"relations_hidden":false,"family_name":"Ремез Л. В","relations_other":"","relations":"Подружжя","name_hidden":false,"name_unclear":false},{"inn":"","inn_hidden":false,"relations_hidden":false,"family_name":"Ремез Я. В","relations_other":"","relations":"Дитина","name_hidden":false,"name_unclear":false},{"inn":"","relations":"Дитина","relations_other":"","inn_hidden":false,"family_name":"Ремез М. В","name_unclear":false}],"inn_hidden":false,"family_raw":"","inn_unclear":false,"post":{"post_unclear":false,"region_unclear":false,"post":"суддя апеляційного суду дніпропетровської області","office":"Загальний апеляційний суд","region":"Дніпропетровська область","post_hidden":false,"office_unclear":false},"full_name_suggest":{"output":"Ремез Валентин Анатолійович","input":["Ремез Валентин Анатолійович","Валентин Анатолійович Ремез","Валентин Ремез"]},"full_name":"Ремез Валентин Анатолійович","patronymic":"Анатолійович","patronymic_hidden":false,"last_name_unclear":false,"name_unclear":false},"source":"VULYK","estate":{"29":[{"space_unclear":false,"address_hidden":false,"region_hidden":false,"space_comment":"","space":"743","address":"","region":"","costs_property":"","costs_rent_comment":"","space_units":"м²","costs_property_comment":"","costs_rent":""}],"31":[{"space_hidden":false,"costs_property_comment":"","address_hidden":false,"region_hidden":false,"space_comment":"","space":"73.2","address":"","region":"","costs_property":"","costs_rent_comment":"","space_comment_unclear":false,"space_units":"м²","space_units_hidden":false,"costs_rent":""},{"space_hidden":false,"address_hidden":false,"region_hidden":false,"space_comment":"","space":"39","address":"","region":"","costs_property":"","costs_rent_comment":"","space_comment_unclear":false,"space_units":"м²","costs_property_comment":"","costs_rent":""}],"33":[{"space_hidden":false,"address_hidden":false,"region_hidden":false,"space_comment":"","space":"24","address":"","region":"","costs_property":"","costs_rent_comment":"","space_comment_hidden":false,"space_units":"м²","costs_property_comment":"","costs_rent":""}]},"intro":{"declaration_year":"2013","isnotdeclaration":""}}