{"income":{"5":{"family_comment":"","value":"226325","value_unclear":false,"family":"73924","comment":""},"6":{"value":"226325","value_unclear":false,"family_hidden":false,"family_comment":"","family":"73924","comment":""},"7":{"source_name_unclear":false,"value":"","family_comment":"","source_name":"","family":"","comment":""},"8":{"family_comment":"","value":"","family":"","comment":""},"9":{"family_comment":"","value":"","family":"","comment":""},"10":{"family_comment":"","value":"","family":"","comment":""},"11":{"family_comment":"","value":"","comment_unclear":false,"family":"","comment":""},"12":{"family_comment":"","value":"","family":"","comment":""},"13":{"family_comment":"","value":"","family":"","comment":""},"14":{"family_comment":"","value":"","family":"","comment":""},"15":{"family_comment":"","value":"","family":"","comment":""},"16":{"family_comment":"","value":"","family":"","comment":""},"17":{"family_comment":"","value":"","family":"","comment":""},"18":{"family_comment":"","value":"","family":"","comment":""},"19":{"family_comment":"","value":"","family":"","comment":""},"20":{"value":"","family_comment":"","value_unclear":false,"family_unclear":false,"comment_unclear":false,"comment":"","family":""}},"vehicle":{"35":[{"brand_info":"1896 куб. см.","sum_rent_comment":"","brand":"Volkswagen Golf","sum_comment":"","brand_unclear":false,"year":"2008","sum_rent_unclear":false,"brand_info_hidden":false,"brand_info_unclear":false,"sum":"","sum_rent":""}]},"id":"vulyk_101_205","banks":{"45":[{"sum_foreign_comment":"","sum_units":"UAH","sum_comment":"","sum_comment_unclear":false,"sum_hidden":false,"sum_foreign_units":"UAH","sum_comment_hidden":false,"sum_unclear":false,"sum":"9099","sum_foreign":""}],"51":[{"sum_foreign_comment":"","sum_units":"UAH","sum_comment":"","sum_hidden":false,"sum_foreign_units":"UAH","sum_comment_hidden":false,"sum_unclear":false,"sum":"2018","sum_foreign":""}]},"declaration":{"additional_info_text":"","notfull_lostpages":"","date":"2016-03-28T00:00:00","notfull":"","additional_info":"","url":"http://static.declarations.com.ua/declarations/chosen_ones/judges_batch/920_batiuk_vasyl_viktorovych_2015.pdf"},"liabilities":{"54":{"sum_foreign_comment":"","sum":"","sum_comment":"","sum_comment_unclear":false,"sum_hidden":false,"sum_comment_hidden":false,"sum_unclear":false,"sum_foreign":""},"55":{"sum_foreign_comment":"","sum":"","sum_comment":"","sum_foreign":""},"56":{"sum_foreign_comment":"","sum":"6859","sum_comment":"","sum_comment_hidden":false,"sum_unclear":false,"sum_foreign":""},"57":{"sum_foreign_comment":"","sum":"","sum_comment":"","sum_hidden":false,"sum_comment_hidden":false,"sum_unclear":false,"sum_foreign":""},"58":{"sum_foreign_comment":"","sum":"","sum_comment":"","sum_comment_unclear":false,"sum_hidden":false,"sum_comment_hidden":false,"sum_unclear":false,"sum_foreign":""},"59":{"sum_foreign_comment":"","sum":"","sum_comment":"","sum_foreign":""},"60":{"sum_foreign_comment":"","sum":"","sum_comment":"","sum_hidden":false,"sum_comment_hidden":false,"sum_unclear":false,"sum_foreign":""},"61":{"sum_foreign_comment":"","sum":"","sum_comment":"","sum_foreign":""},"62":{"sum_foreign_comment":"","sum":"3259","sum_comment":"","sum_comment_unclear":false,"sum_foreign":""},"63":{"sum_foreign_comment":"","sum_comment_hidden":false,"sum":"","sum_comment":"","sum_foreign":""},"64":{"sum_foreign_comment":"","sum_comment_hidden":false,"sum":"","sum_comment":"","sum_foreign":""}},"ft_src":"3259\n6859\nсуддя броварського міськрайонного суду київської області\nКиївська область\nЗагальний місцевий суд\nВасиль\nБатюк О. А\nПодружжя\nВікторович\nБатюк Василь Вікторович\nБатюк\nБатюк Василь Вікторович\nВасиль Вікторович Батюк\nВасиль Батюк\nБатюк Василь Вікторович\nVolkswagen Golf\n1896 куб. см.\n2008\n2018\n9099\n2015\nVolkswagen Golf\n1896 куб. см.\n2008\n9099\n2018\n2015\nПодружжя\nБатюк О. А\nБатюк Василь Вікторович\nВасиль Вікторович Батюк\nВасиль Батюк\nБатюк Василь Вікторович\nВасиль\nБатюк Василь Вікторович\nВікторович\nЗагальний місцевий суд\nсуддя броварського міськрайонного суду київської області\nКиївська область\nБатюк\n6859\n3259\n226325\n73924\n226325\n73924\n450\n158.5\n1/2, спільна власність\n158.5\n1/2 , спільна сумісна власність\n6859\n3259\n450\n1/2 , спільна сумісна власність\n158.5\n1/2, спільна власність\n158.5\nБатюк О. А\nПодружжя\nВасиль\nВікторович\nБатюк\nБатюк Василь Вікторович\nВасиль Вікторович Батюк\nВасиль Батюк\nБатюк Василь Вікторович\nсуддя броварського міськрайонного суду київської області\nЗагальний місцевий суд\nКиївська область\nБатюк Василь Вікторович\n73924\n226325\n73924\n226325\n2008\nVolkswagen Golf\n1896 куб. см.\n73924\n226325\n226325\n73924\n1/2 , спільна сумісна власність\n158.5\n450\n1/2, спільна власність\n158.5\n9099\n2018\n2015","general":{"inn":"","name":"Василь","inn_unclear":false,"family":[{"inn":"","relations":"Подружжя","relations_other":"","inn_hidden":true,"family_name":"Батюк О. А","name_hidden":true,"name_unclear":false}],"inn_hidden":true,"family_raw":"","last_name":"Батюк","post":{"region":"Київська область","region_unclear":false,"post":"суддя броварського міськрайонного суду київської області","office_unclear":false,"office":"Загальний місцевий суд"},"full_name":"Батюк Василь Вікторович","addresses":[{"place_district":"","place_city_hidden":true,"place_city":"","place_city_type_hidden":true,"place_district_hidden":false,"place_city_type":"","place_address_hidden":true,"place_address":"","place_hidden":true,"place":""}],"patronymic":"Вікторович","patronymic_hidden":false,"full_name_suggest":{"output":"Батюк Василь Вікторович","input":["Батюк Василь Вікторович","Василь Вікторович Батюк","Василь Батюк"]}},"source":"VULYK","estate":{"23":[{"space_unclear":false,"costs":"","costs_comment":"","address_hidden":true,"region_hidden":true,"space_comment":"","space_hidden":false,"space":"450","address":"","costs_comment_unclear":false,"region":"","space_units_unclear":false,"space_units":"м²","costs_rent":"","costs_rent_comment":""}],"24":[{"space_unclear":false,"costs":"","costs_comment":"","address_hidden":true,"region_hidden":true,"space_comment":"1/2, спільна власність","space":"158.5","address":"","region":"","costs_rent_comment":"","space_units":"м²","costs_rent":""}],"30":[{"costs_rent":"","region":"","costs_property":"","costs_rent_comment":"","address_hidden":true,"region_hidden":true,"space_comment":"1/2 , спільна сумісна власність","costs_property_comment":"","space_units":"м²","space":"158.5","address":""}]},"intro":{"declaration_year":"2015"}}