{"income":{"5":{"family_comment":"","family_unclear":false,"value":"200346","family":"11388","comment":""},"6":{"family_comment":"","family_unclear":false,"value":"200346","family":"","comment":""},"7":{"value":"","comment_hidden":false,"family_comment":"","source_name":"","family":"","comment":""},"8":{"family_comment":"","value":"","family":"","comment":""},"9":{"family_comment":"","value":"","family":"","comment":""},"10":{"family_comment":"","value":"","family":"","comment":""},"11":{"family_comment":"","value":"","value_unclear":false,"family":"","comment":""},"12":{"family_comment":"","value":"","family":"","comment":""},"13":{"family_comment":"","value":"","family":"","comment":""},"14":{"family_comment":"","value":"","family":"","comment":""},"15":{"family_comment":"","value":"","value_unclear":false,"family":"","comment":""},"16":{"family_comment":"","family_unclear":false,"value":"","family":"","comment":""},"17":{"family_comment":"","value":"","family":"","comment":""},"18":{"family_comment":"","value":"","family_hidden":false,"comment":"","family":""},"19":{"family_comment":"","value":"","family":"","comment":""},"20":{"value":"","comment_unclear":false,"comment_hidden":false,"family_comment":"","family":"11388","comment":"","family_comment_hidden":false}},"vehicle":{"35":[{"brand_info":"1997 куб. см.","sum_rent_comment":"","year":"2001","brand_info_hidden":false,"brand_info_unclear":false,"year_unclear":false,"sum_rent":"","sum":"","brand":"Mitsubishi Galant","sum_comment":"","brand_unclear":false,"brand_hidden":false}]},"id":"vulyk_68_9","declaration":{"additional_info_text":"","notfull_lostpages":"","date":"2015-02-09T00:00:00","notfull":"","additional_info":"","url":"http://static.declarations.com.ua/declarations/chosen_ones/mega_batch/hnoievoi_serhii_serhiiovych.pdf"},"liabilities":{"54":{"sum_foreign_comment":"","sum":"","sum_comment":"","sum_comment_unclear":false,"sum_hidden":false,"sum_comment_hidden":false,"sum_unclear":false,"sum_foreign":""},"55":{"sum_foreign_comment":"","sum":"","sum_hidden":false,"sum_comment":"","sum_foreign":""},"56":{"sum_foreign_comment":"","sum_foreign_hidden":false,"sum_comment":"","sum":"5748","sum_unclear":false,"sum_foreign":""},"57":{"sum_foreign_comment":"","sum":"","sum_comment":"","sum_comment_unclear":false,"sum_hidden":false,"sum_comment_hidden":false,"sum_unclear":false,"sum_foreign":""},"58":{"sum_foreign_comment":"","sum":"","sum_comment":"","sum_hidden":false,"sum_comment_hidden":false,"sum_unclear":false,"sum_foreign":""},"59":{"sum_foreign_comment":"","sum":"","sum_comment":"","sum_foreign":""},"60":{"sum_foreign_comment":"","sum":"","sum_comment":"","sum_comment_unclear":false,"sum_hidden":false,"sum_comment_hidden":false,"sum_unclear":false,"sum_foreign":""},"61":{"sum_foreign_comment":"","sum":"","sum_hidden":false,"sum_comment":"","sum_foreign":""},"62":{"sum_foreign_comment":"","sum":"4970","sum_comment":"","sum_unclear":false,"sum_foreign":""},"63":{"sum_foreign_comment":"","sum":"","sum_comment":"","sum_hidden":false,"sum_comment_hidden":false,"sum_unclear":false,"sum_foreign":""},"64":{"sum_foreign_comment":"","sum":"","sum_comment":"","sum_hidden":false,"sum_comment_hidden":false,"sum_foreign":""}},"ft_src":"4970\n5748\nсуддя орджонікідзевського районного суду м. маріуполя\nДонецька область\nЗагальний місцевий суд\nСергій\nКарпова О. С., 23. 10. 1976\nПодружжя\nГноєвой Є. С., 12. 03. 2009\nДитина\nКарпова Є. С., 24. 07. 2005\nДитина\nСергійович\nГноєвой Сергій Сергійович\nСергій Сергійович Гноєвой\nСергій Гноєвой\nГноєвой Сергій Сергійович\nГноєвой Сергій Сергійович\nГноєвой\n1997 куб. см.\nMitsubishi Galant\n2001\n48.2\n57.3\n2014\n200346\n11388\n200346\n11388\n1997 куб. см.\nMitsubishi Galant\n2001\n48.2\n57.3\nПодружжя\nКарпова О. С., 23. 10. 1976\nДитина\nГноєвой Є. С., 12. 03. 2009\nДитина\nКарпова Є. С., 24. 07. 2005\nГноєвой Сергій Сергійович\nСергій Сергійович Гноєвой\nСергій Гноєвой\nГноєвой Сергій Сергійович\nГноєвой Сергій Сергійович\nСергій\nСергійович\nЗагальний місцевий суд\nДонецька область\nсуддя орджонікідзевського районного суду м. маріуполя\nГноєвой\n5748\n4970\n200346\n11388\n200346\n11388\n2014\n5748\n4970\nПодружжя\nКарпова О. С., 23. 10. 1976\nГноєвой Є. С., 12. 03. 2009\nДитина\nКарпова Є. С., 24. 07. 2005\nДитина\nСергійович\nГноєвой\nСергій\nГноєвой Сергій Сергійович\nСергій Сергійович Гноєвой\nСергій Гноєвой\nГноєвой Сергій Сергійович\nДонецька область\nЗагальний місцевий суд\nсуддя орджонікідзевського районного суду м. маріуполя\nГноєвой Сергій Сергійович\n2001\nMitsubishi Galant\n1997 куб. см.\n11388\n11388\n200346\n200346\n48.2\n57.3\n2014","general":{"inn":"","name":"Сергій","inn_unclear":false,"family":[{"inn":"","inn_hidden":false,"relations_unclear":false,"relations_hidden":false,"relations_other":"","relations":"Подружжя","name_hidden":false,"inn_unclear":false,"family_name":"Карпова О. С., 23. 10. 1976","name_unclear":false},{"inn":"","inn_hidden":false,"inn_unclear":false,"relations_hidden":false,"relations_other":"","relations":"Дитина","name_hidden":false,"family_name":"Гноєвой Є. С., 12. 03. 2009","name_unclear":false},{"inn":"","relations":"Дитина","relations_other":"","inn_hidden":false,"family_name":"Карпова Є. С., 24. 07. 2005","name_hidden":false,"name_unclear":false}],"inn_hidden":true,"family_raw":"","last_name":"Гноєвой","post":{"post_unclear":false,"region_unclear":false,"post":"суддя орджонікідзевського районного суду м. маріуполя","office":"Загальний місцевий суд","region":"Донецька область","post_hidden":false,"office_hidden":false,"office_unclear":false,"region_hidden":false},"full_name_suggest":{"output":"Гноєвой Сергій Сергійович","input":["Гноєвой Сергій Сергійович","Сергій Сергійович Гноєвой","Сергій Гноєвой"]},"full_name":"Гноєвой Сергій Сергійович","addresses":[{"place_city_type_hidden":false,"place_district_hidden":false,"place_city_type":"","place_city_hidden":false,"place_address_unclear":false,"place_address":"","place_hidden":true,"place":"","place_district":"","place_unclear":false,"place_city":"","place_address_hidden":false}],"patronymic":"Сергійович","last_name_unclear":false,"name_unclear":false},"source":"VULYK","estate":{"25":[{"space_unclear":false,"costs":"","costs_comment":"","address_hidden":false,"region_hidden":true,"space_comment":"","space_hidden":false,"space":"57.3","address":"","space_comment_unclear":false,"region":"","address_unclear":false,"costs_rent_comment":"","costs_unclear":false,"space_units":"м²","space_units_hidden":false,"costs_rent":""}],"31":[{"space_unclear":false,"address_hidden":false,"region_hidden":true,"space_comment":"","space_hidden":false,"space":"48.2","address":"","region":"","costs_property":"","costs_rent_comment":"","space_units":"м²","costs_property_comment":"","costs_rent":""}]},"intro":{"declaration_year":"2014","isnotdeclaration":""}}