{"income":{"5":{"value":"188581.66","family_comment":"","value_unclear":false,"comment_hidden":false,"family_hidden":false,"value_hidden":false,"family_unclear":false,"family":"20400","comment":""},"6":{"value":"188581.66","family_comment":"","value_unclear":false,"family_hidden":false,"family_unclear":false,"comment_unclear":false,"comment":"","family":"20400"},"7":{"source_name_unclear":false,"value":"","value_hidden":false,"family_comment":"","source_name":"","family":"","comment":"","source_name_hidden":false},"8":{"value":"","family_hidden":false,"value_hidden":false,"family_comment":"","family":"","comment":""},"9":{"value":"","family_comment":"","value_unclear":false,"family_hidden":false,"value_hidden":false,"family_unclear":false,"family":"","comment":""},"10":{"family_comment":"","value":"","family":"","comment":""},"11":{"family_comment":"","value":"","family":"","comment":""},"12":{"family_comment":"","value":"","family":"","comment":""},"13":{"family_comment":"","value":"","family":"","comment":""},"14":{"family_comment":"","value":"","family":"","comment":""},"15":{"family_comment":"","value":"","family":"","comment":""},"16":{"value":"","family_comment":"","value_unclear":false,"family_unclear":false,"family":"","comment":""},"17":{"family_comment":"","value":"","family":"","comment":""},"18":{"family_comment":"","value":"","family":"","comment":""},"19":{"family_comment":"","value":"","comment_unclear":false,"family":"","comment":""},"20":{"value":"","family_comment":"","value_unclear":false,"comment_hidden":false,"family_hidden":false,"family":"","value_hidden":false,"family_unclear":false,"comment_unclear":false,"comment":"","family_comment_unclear":false}},"vehicle":{"40":[{"brand_info":"3.2 л","sum_rent_comment":"","brand":"Mitsubishi Pajero Wagon","sum_comment":"","brand_unclear":false,"year":"2009","brand_info_unclear":false,"year_unclear":false,"sum":"","sum_rent":""},{"brand_info":"1.8 л","sum_rent_comment":"","brand":"Toyota Prius","sum_comment":"","brand_unclear":false,"year":"2010","brand_info_unclear":false,"sum":"","sum_rent":""}]},"id":"vulyk_63_47","declaration":{"additional_info_text":"","notfull_lostpages":"","date":"2015-03-19T00:00:00","notfull":"","additional_info":"","url":"http://static.declarations.com.ua/declarations/chosen_ones/mega_batch/iliashuk_antonina_volodymyrivna.pdf"},"liabilities":{"54":{"sum_foreign_comment":"","sum":"","sum_comment":"","sum_unclear":false,"sum_foreign":""},"55":{"sum_foreign_comment":"","sum":"","sum_comment":"","sum_foreign":""},"56":{"sum_foreign_comment":"","sum":"","sum_comment":"","sum_unclear":false,"sum_foreign":""},"57":{"sum_foreign_comment":"","sum":"","sum_comment":"","sum_comment_hidden":false,"sum_unclear":false,"sum_foreign":""},"58":{"sum_foreign_comment":"","sum_comment_hidden":false,"sum":"","sum_comment":"","sum_foreign":""},"59":{"sum_foreign_comment":"","sum":"","sum_comment":"","sum_foreign":""},"60":{"sum_foreign_comment":"","sum":"","sum_comment":"","sum_comment_unclear":false,"sum_foreign":""},"61":{"sum_foreign_comment":"","sum":"","sum_comment":"","sum_unclear":false,"sum_foreign":""},"62":{"sum_foreign_comment":"","sum":"","sum_comment":"","sum_unclear":false,"sum_foreign":""},"63":{"sum_foreign_comment":"","sum":"","sum_comment":"","sum_hidden":false,"sum_comment_hidden":false,"sum_unclear":false,"sum_foreign":""},"64":{"sum_foreign_comment":"","sum_comment_hidden":false,"sum":"","sum_comment":"","sum_foreign":""}},"ft_src":"суддя роздільнянського районного суду одеської області\nОдеська область\nЗагальний місцевий суд\nАнтоніна\nІльяшук В. В\nПодружжя\nІльяшук А. В\nДитина\nІльяшук М. В\nДитина\nВолодимирівна\nІльяшук\nІльяшук Антоніна Володимирівна\nІльяшук Антоніна Володимирівна\nАнтоніна Володимирівна Ільяшук\nАнтоніна Ільяшук\nІльяшук Антоніна Володимирівна\n3.2 л\nMitsubishi Pajero Wagon\n2009\n2010\nToyota Prius\n1.8 л\n56.5\n54.5\n2014\n20400\n188581.66\n20400\n188581.66\n3.2 л\n2009\nMitsubishi Pajero Wagon\n1.8 л\n2010\nToyota Prius\n56.5\n54.5\nІльяшук Антоніна Володимирівна\nАнтоніна Володимирівна Ільяшук\nАнтоніна Ільяшук\nІльяшук Антоніна Володимирівна\nАнтоніна\nПодружжя\nІльяшук В. В\nДитина\nІльяшук А. В\nДитина\nІльяшук М. В\nІльяшук Антоніна Володимирівна\nІльяшук\nЗагальний місцевий суд\nОдеська область\nсуддя роздільнянського районного суду одеської області\nВолодимирівна\n188581.66\n20400\n188581.66\n20400\n2014\nПодружжя\nІльяшук В. В\nДитина\nІльяшук А. В\nДитина\nІльяшук М. В\nВолодимирівна\nІльяшук\nІльяшук Антоніна Володимирівна\nАнтоніна Володимирівна Ільяшук\nАнтоніна Ільяшук\nІльяшук Антоніна Володимирівна\nАнтоніна\nОдеська область\nсуддя роздільнянського районного суду одеської області\nЗагальний місцевий суд\nІльяшук Антоніна Володимирівна\n2009\n3.2 л\nMitsubishi Pajero Wagon\n2010\n1.8 л\nToyota Prius\n188581.66\n20400\n188581.66\n20400\n56.5\n54.5\n2014","general":{"name_hidden":false,"name":"Антоніна","patronymic_unclear":false,"last_name_hidden":false,"inn":"","family":[{"inn":"","inn_hidden":false,"relations_unclear":false,"relations_hidden":false,"relations_other":"","relations":"Подружжя","name_hidden":false,"inn_unclear":false,"family_name":"Ільяшук В. В","name_unclear":false},{"inn":"","relations":"Дитина","relations_unclear":false,"family_name":"Ільяшук А. В","inn_hidden":false,"relations_other":"","name_hidden":false,"inn_unclear":false,"name_unclear":false},{"inn":"","relations":"Дитина","inn_unclear":false,"family_name":"Ільяшук М. В","inn_hidden":false,"relations_other":"","name_hidden":false,"name_unclear":false}],"patronymic":"Володимирівна","inn_hidden":false,"family_raw":"","inn_unclear":false,"post":{"post_unclear":false,"region_unclear":false,"region":"Одеська область","office_hidden":false,"region_hidden":false,"post":"суддя роздільнянського районного суду одеської області","office_unclear":false,"office":"Загальний місцевий суд"},"last_name_unclear":false,"full_name":"Ільяшук Антоніна Володимирівна","last_name":"Ільяшук","full_name_suggest":{"output":"Ільяшук Антоніна Володимирівна","input":["Ільяшук Антоніна Володимирівна","Антоніна Володимирівна Ільяшук","Антоніна Ільяшук"]},"name_unclear":false},"source":"VULYK","estate":{"25":[{"region_unclear":false,"space_unclear":false,"costs":"","costs_comment":"","costs_hidden":false,"address_hidden":false,"region_hidden":false,"space_comment":"","space_hidden":false,"space":"54.5","space_units_hidden":false,"region":"","address_unclear":false,"costs_rent_comment":"","costs_rent_hidden":false,"space_comment_unclear":false,"costs_rent_comment_hidden":false,"space_units":"м²","address":"","costs_comment_hidden":false,"costs_rent":""}],"31":[{"space_unclear":false,"costs_property_hidden":false,"address_hidden":false,"region_hidden":false,"space_comment":"","space_hidden":false,"space":"56.5","address":"","costs_property_comment_hidden":false,"region":"","costs_property":"","space_units_unclear":false,"costs_rent_hidden":false,"space_comment_unclear":false,"costs_rent_comment_hidden":false,"space_units":"м²","costs_property_comment":"","costs_rent":"","costs_rent_comment":""}]},"intro":{"declaration_year":"2014","isnotdeclaration":"","declaration_year_unclear":false}}