{"income":{"5":{"value":"239123","comment_hidden":false,"family_comment":"","family":"309706","comment":"","family_comment_hidden":false},"6":{"value":"226506","family_comment":"","comment_hidden":false,"family_hidden":false,"family_unclear":false,"family_comment_hidden":false,"comment":"","family":"243706"},"7":{"value":"","comment_hidden":false,"family_comment_hidden":false,"family_comment":"","source_name":"","family":"","comment":"","source_name_hidden":false},"8":{"family_comment":"","value":"","family":"","comment":""},"9":{"value":"","family_comment":"","value_unclear":false,"family_unclear":false,"comment_unclear":false,"comment":"","family":""},"10":{"family_comment":"","family_unclear":false,"value":"12617","family":"","comment":""},"11":{"family_comment":"","value":"","family":"","comment":""},"12":{"family_comment":"","value":"","family":"","comment":""},"13":{"family_comment":"","value":"","family":"","comment":""},"14":{"family_comment":"","value":"","family":"","comment":""},"15":{"family_comment":"","value":"","comment_unclear":false,"family":"","comment":""},"16":{"family_comment":"","value":"","comment_unclear":false,"family":"","comment":""},"17":{"family_comment":"","value":"","family":"","comment":""},"18":{"family_comment":"","value":"","family":"","comment":""},"19":{"family_comment":"","value":"","family":"66000","comment":""},"20":{"value":"","family_comment":"","value_unclear":false,"family_unclear":false,"family_comment_unclear":false,"family_comment_hidden":false,"comment":"","family":""}},"vehicle":{"35":[{"brand_info":"1999 куб. см., 112 кВт , 468 см","sum_rent_comment":"","brand":"Mazda 6","sum_comment":"","brand_unclear":false,"year":"2005","sum_hidden":false,"brand_info_unclear":false,"sum":"","sum_rent":""},{"brand_info":"3471 куб. см., 224 кВт , 478 см","sum_rent_comment":"","brand":"Acura","sum_comment":"","year":"2008","brand_info_unclear":false,"sum":"","sum_rent":""}]},"id":"vulyk_73_127","declaration":{"additional_info_text":"","notfull_lostpages":"","date":"2014-03-25T00:00:00","notfull":"","additional_info":"","url":"http://static.declarations.com.ua/declarations/chosen_ones/judges_batch/1150_kushneryk_mar_ian_petrovych.pdf"},"liabilities":{"54":{"sum_foreign_comment":"","sum_foreign_hidden":false,"sum_comment":"","sum_comment_unclear":false,"sum_hidden":true,"sum_comment_hidden":true,"sum_unclear":false,"sum":"3070","sum_foreign":""},"55":{"sum_foreign_comment":"","sum_comment_hidden":false,"sum":"","sum_comment":"","sum_foreign":""},"56":{"sum_foreign_comment":"","sum":"","sum_comment":"","sum_comment_unclear":false,"sum_foreign":""},"57":{"sum_foreign_comment":"","sum":"159850","sum_comment":"","sum_hidden":true,"sum_comment_hidden":true,"sum_unclear":true,"sum_foreign":""},"58":{"sum_foreign_comment":"","sum":"","sum_comment":"","sum_hidden":false,"sum_comment_hidden":false,"sum_foreign":""},"59":{"sum_foreign_comment":"","sum":"","sum_comment":"","sum_comment_unclear":false,"sum_unclear":false,"sum_foreign":""},"60":{"sum_foreign_comment":"","sum":"","sum_comment":"","sum_hidden":false,"sum_comment_hidden":false,"sum_unclear":false,"sum_foreign":""},"61":{"sum_foreign_comment":"","sum":"","sum_comment":"","sum_foreign":""},"62":{"sum_foreign_comment":"","sum":"","sum_comment":"","sum_foreign":""},"63":{"sum_foreign_comment":"","sum":"","sum_comment":"","sum_hidden":false,"sum_comment_hidden":false,"sum_foreign":""},"64":{"sum_foreign_comment":"","sum":"","sum_comment":"","sum_foreign":""}},"ft_src":"159850\n3070\nсуддя львівського апеляційного адміністративного суду\nЛьвівська область\nАпеляційний адміністративний суд\nМар'ян\nКушнерик Н. П\nПодружжя\nКушнерик Р. М\nДитина\nПетрович\nКушнерик Мар'ян Петрович\nМар'ян Петрович Кушнерик\nМар'ян Кушнерик\nКушнерик Мар'ян Петрович\nКушнерик\nКушнерик Мар'ян Петрович\nMazda 6\n1999 куб. см., 112 кВт , 468 см\n2005\n3471 куб. см., 224 кВт , 478 см\n2008\nAcura\n7.3\n55\n355\n42\n120\n2013\n243706\n226506\n12617\n309706\n239123\n66000\n1999 куб. см., 112 кВт , 468 см\nMazda 6\n2005\n3471 куб. см., 224 кВт , 478 см\n2008\nAcura\n2013\nКушнерик Мар'ян Петрович\nМар'ян Петрович Кушнерик\nМар'ян Кушнерик\nКушнерик Мар'ян Петрович\nМар'ян\nПодружжя\nКушнерик Н. П\nДитина\nКушнерик Р. М\nКушнерик Мар'ян Петрович\nПетрович\nАпеляційний адміністративний суд\nЛьвівська область\nсуддя львівського апеляційного адміністративного суду\nКушнерик\n3070\n159850\n243706\n226506\n239123\n309706\n12617\n66000\n7.3\n355\n55\n42\n120\n159850\n3070\nПодружжя\nКушнерик Н. П\nДитина\nКушнерик Р. М\nПетрович\nКушнерик\nМар'ян\nКушнерик Мар'ян Петрович\nМар'ян Петрович Кушнерик\nМар'ян Кушнерик\nКушнерик Мар'ян Петрович\nЛьвівська область\nАпеляційний адміністративний суд\nсуддя львівського апеляційного адміністративного суду\nКушнерик Мар'ян Петрович\n2005\n1999 куб. см., 112 кВт , 468 см\nMazda 6\n2008\n3471 куб. см., 224 кВт , 478 см\nAcura\n66000\n12617\n239123\n309706\n226506\n243706\n55\n355\n42\n120\n7.3\n2013","general":{"inn":"","name":"Мар'ян","family":[{"inn":"","relations":"Подружжя","inn_unclear":false,"relations_hidden":false,"inn_hidden":true,"relations_other":"","name_hidden":false,"family_name":"Кушнерик Н. П","name_unclear":false},{"inn":"","relations":"Дитина","inn_unclear":false,"family_name":"Кушнерик Р. М","inn_hidden":true,"relations_other":"","name_hidden":false,"name_unclear":false}],"patronymic":"Петрович","inn_hidden":true,"family_raw":"","last_name":"Кушнерик","post":{"post_unclear":false,"region_unclear":false,"post":"суддя львівського апеляційного адміністративного суду","office":"Апеляційний адміністративний суд","region":"Львівська область","post_hidden":false,"office_hidden":false,"office_unclear":false,"region_hidden":false},"last_name_unclear":false,"full_name":"Кушнерик Мар'ян Петрович","addresses":[{"place_district":"","place_city_hidden":true,"place_city":"","place_city_type_hidden":false,"place_district_hidden":true,"place_city_type":"","place_address_hidden":true,"place_address":"","place_hidden":true,"place":""}],"full_name_suggest":{"output":"Кушнерик Мар'ян Петрович","input":["Кушнерик Мар'ян Петрович","Мар'ян Петрович Кушнерик","Мар'ян Кушнерик"]},"name_unclear":false},"source":"VULYK","estate":{"25":[{"space_unclear":false,"costs":"","costs_comment":"","costs_hidden":false,"address_hidden":true,"region_hidden":true,"space_comment":"","space_hidden":false,"space":"120","address":"","region":"","costs_rent_comment":"","space_comment_hidden":false,"space_units":"м²","costs_rent":""}],"29":[{"space_unclear":false,"address_hidden":true,"region_hidden":true,"space_comment":"","space":"7.3","address":"","region":"","costs_property":"","costs_rent_comment":"","space_units":"га","costs_property_comment":"","costs_rent":""}],"30":[{"space_unclear":false,"address_hidden":true,"region_hidden":true,"space_comment":"","space_hidden":false,"space":"355","address":"","region":"","costs_property":"","costs_rent_comment":"","space_comment_unclear":false,"space_units":"м²","costs_property_comment":"","costs_rent":""}],"31":[{"space_unclear":false,"address_hidden":true,"region_hidden":true,"space_comment":"","space":"55","address":"","region":"","costs_property":"","costs_rent_comment":"","space_units":"м²","costs_property_comment":"","costs_rent":""}],"34":[{"costs_rent":"","region":"","costs_property":"","costs_rent_comment":"","address_hidden":true,"region_hidden":true,"space_comment":"","costs_property_comment":"","space_units":"м²","space":"42","address":""}]},"intro":{"declaration_year":"2013"}}