{"income":{"5":{"family_comment":"","value":"215837","value_unclear":false,"family":"20291","comment":""},"6":{"value":"215837","value_unclear":false,"family_hidden":false,"family_comment":"","family":"","comment":""},"7":{"source_name_unclear":false,"value":"","family_comment":"","source_name":"","family":"","comment":""},"8":{"family_comment":"","value":"","family":"","comment":""},"9":{"family_comment":"","value":"","family":"","comment":""},"10":{"family_comment":"","value":"","family":"","comment":""},"11":{"family_comment":"","value":"","comment_unclear":false,"family":"","comment":""},"12":{"family_comment":"","value":"","family":"","comment":""},"13":{"family_comment":"","value":"","family":"","comment":""},"14":{"family_comment":"","value":"","family":"","comment":""},"15":{"family_comment":"","value":"","family":"20291","comment":""},"16":{"family_comment":"","value":"","family":"","comment":""},"17":{"family_comment":"","value":"","family":"","comment":""},"18":{"family_comment":"","value":"","family":"","comment":""},"19":{"family_comment":"","value":"","family":"","comment":""},"20":{"value":"","family_comment":"","value_unclear":false,"family_unclear":false,"comment_unclear":false,"comment":"","family":""}},"id":"vulyk_101_189","declaration":{"additional_info_text":"","notfull_lostpages":"","date":"2016-03-31T00:00:00","notfull":"","additional_info":"","url":"http://static.declarations.com.ua/declarations/chosen_ones/judges_batch/904_cherkaskyi_volodymyr_ivanovych_2015.pdf"},"liabilities":{"54":{"sum_foreign_comment":"","sum":"","sum_comment":"","sum_comment_unclear":false,"sum_hidden":false,"sum_comment_hidden":false,"sum_unclear":false,"sum_foreign":""},"55":{"sum_foreign_comment":"","sum":"","sum_comment":"","sum_foreign":""},"56":{"sum_foreign_comment":"","sum":"","sum_comment":"","sum_comment_hidden":false,"sum_unclear":false,"sum_foreign":""},"57":{"sum_foreign_comment":"","sum":"","sum_comment":"","sum_hidden":false,"sum_comment_hidden":false,"sum_unclear":false,"sum_foreign":""},"58":{"sum_foreign_comment":"","sum":"","sum_comment":"","sum_comment_unclear":false,"sum_hidden":false,"sum_comment_hidden":false,"sum_unclear":false,"sum_foreign":""},"59":{"sum_foreign_comment":"","sum":"","sum_comment":"","sum_foreign":""},"60":{"sum_foreign_comment":"","sum":"","sum_comment":"","sum_hidden":false,"sum_comment_hidden":false,"sum_unclear":false,"sum_foreign":""},"61":{"sum_foreign_comment":"","sum":"","sum_comment":"","sum_foreign":""},"62":{"sum_foreign_comment":"","sum":"540","sum_comment":"","sum_comment_unclear":false,"sum_foreign":""},"63":{"sum_foreign_comment":"","sum_comment_hidden":false,"sum":"","sum_comment":"","sum_foreign":""},"64":{"sum_foreign_comment":"","sum_comment_hidden":false,"sum":"","sum_comment":"","sum_foreign":""}},"ft_src":"540\nсуддя господарського суду запорізької області\nЗапорізька область\nГосподарський місцевий суд\nВолодимир\nКуксова Я. В\nПодружжя\nЧеркаська М. В\nДитина\nІванович\nЧеркаський Володимир Іванович\nЧеркаський\nЧеркаський Володимир Іванович\nВолодимир Іванович Черкаський\nВолодимир Черкаський\nЧеркаський Володимир Іванович\n20291\n20291\n215837\n215837\n1/2\n26.12\n24\n10\n71.13\n2015\n215837\n20291\n20291\n215837\n24\n10\n1/2\n26.12\n71.13\nЧеркаський Володимир Іванович\nВолодимир Іванович Черкаський\nВолодимир Черкаський\nЧеркаський Володимир Іванович\nВолодимир\nЧеркаський Володимир Іванович\nІванович\nсуддя господарського суду запорізької області\nЗапорізька область\nГосподарський місцевий суд\nЧеркаський\nПодружжя\nКуксова Я. В\nДитина\nЧеркаська М. В\n540\n215837\n20291\n215837\n20291\n2015\n540\nКуксова Я. В\nПодружжя\nЧеркаська М. В\nДитина\nВолодимир\nІванович\nЧеркаський\nЧеркаський Володимир Іванович\nВолодимир Іванович Черкаський\nВолодимир Черкаський\nЧеркаський Володимир Іванович\nсуддя господарського суду запорізької області\nЗапорізька область\nГосподарський місцевий суд\nЧеркаський Володимир Іванович\n1/2\n26.12\n71.13\n24\n10\n2015","general":{"inn":"","name":"Володимир","inn_unclear":false,"family":[{"inn":"","relations":"Подружжя","relations_other":"","inn_hidden":true,"family_name":"Куксова Я. В","name_hidden":true,"name_unclear":false},{"inn":"","relations":"Дитина","relations_unclear":false,"family_name":"Черкаська М. В","inn_hidden":true,"relations_other":"","name_hidden":false,"name_unclear":false}],"inn_hidden":true,"family_raw":"","last_name":"Черкаський","post":{"region":"Запорізька область","region_unclear":false,"post":"суддя господарського суду запорізької області","office_unclear":false,"office":"Господарський місцевий суд"},"full_name":"Черкаський Володимир Іванович","addresses":[{"place_district":"","place_address_hidden":true,"place_city":"","place_city_type_hidden":false,"place_district_hidden":false,"place_city_type":"","place_city_hidden":true,"place_address":"","place_hidden":true,"place":""}],"patronymic":"Іванович","patronymic_hidden":false,"full_name_suggest":{"output":"Черкаський Володимир Іванович","input":["Черкаський Володимир Іванович","Володимир Іванович Черкаський","Володимир Черкаський"]}},"source":"VULYK","estate":{"25":[{"space_unclear":false,"costs":"","costs_comment":"","address_hidden":false,"region_hidden":true,"space_comment":"","space_hidden":false,"space":"71.13","address":"","region":"","costs_rent_comment":"","space_comment_unclear":false,"space_units":"м²","costs_rent":""}],"26":[{"costs_rent":"","region":"","costs":"","costs_rent_comment":"","costs_comment":"","address_hidden":false,"region_hidden":true,"space_comment":"","space_units":"м²","space":"10","address":""}],"31":[{"space_unclear":false,"address_hidden":false,"region_hidden":true,"space_comment":"1/2","space_hidden":false,"space":"26.12","address":"","costs_rent_comment_unclear":false,"region":"","costs_property":"","costs_rent_comment":"","space_units":"м²","costs_property_comment":"","costs_rent":""}],"33":[{"costs_rent":"","region":"","costs_property":"","costs_rent_comment":"","address_hidden":false,"region_hidden":true,"space_comment":"","costs_property_comment":"","space_units":"м²","space":"24","address":""}]},"intro":{"declaration_year":"2015"}}