{"income":{"5":{"value":"213002","family_comment":"","value_unclear":false,"family_hidden":false,"value_hidden":false,"family_unclear":false,"family":"","comment":""},"6":{"value":"188672","value_unclear":false,"family_hidden":false,"value_hidden":false,"family_comment":"","comment_unclear":false,"comment":"","family":""},"7":{"value":"","value_hidden":false,"family_comment":"","source_name":"","family":"","comment":"","source_name_hidden":false},"8":{"family_comment":"","value":"","family":"","comment":""},"9":{"family_comment":"","value":"","comment_unclear":false,"family":"","comment":""},"10":{"family_comment":"","value":"12180","value_unclear":false,"family":"","comment":""},"11":{"family_comment":"","value":"","family":"","comment":""},"12":{"family_comment":"","value":"","family":"","comment":""},"13":{"family_comment":"","value":"","family":"","comment":""},"14":{"family_comment":"","value":"","family":"","comment":""},"15":{"family_comment":"","value":"","family":"","comment":""},"16":{"family_comment":"","value":"","family":"","comment":""},"17":{"family_comment":"","value":"","family":"","comment":""},"18":{"family_comment":"","value":"","family":"","comment":""},"19":{"value":"","value_unclear":false,"comment_hidden":false,"family_hidden":false,"value_hidden":false,"family_comment":"","family":"","comment":"","family_comment_hidden":false},"20":{"value":"12150","family_comment":"","value_unclear":false,"family_hidden":false,"value_hidden":false,"family_unclear":false,"comment_unclear":false,"comment":"","family":""}},"id":"vulyk_65_128","declaration":{"additional_info_text":"","notfull_lostpages":"","date":"2015-03-27T00:00:00","notfull":"","additional_info":"","url":"http://static.declarations.com.ua/declarations/chosen_ones/mega_batch/maksiutenko_(yantsova)_oksana_anatoliivna.pdf"},"liabilities":{"54":{"sum_foreign_comment":"","sum":"","sum_comment":"","sum_comment_unclear":false,"sum_hidden":false,"sum_comment_hidden":false,"sum_foreign":""},"55":{"sum_foreign_comment":"","sum":"","sum_comment":"","sum_foreign":""},"56":{"sum_foreign_comment":"","sum":"","sum_comment":"","sum_unclear":false,"sum_foreign":""},"57":{"sum_foreign_comment":"","sum":"","sum_comment":"","sum_comment_unclear":false,"sum_unclear":false,"sum_foreign":""},"58":{"sum_foreign_comment":"","sum":"","sum_comment":"","sum_comment_unclear":false,"sum_unclear":false,"sum_foreign":""},"59":{"sum_foreign_comment":"","sum":"","sum_comment":"","sum_foreign":""},"60":{"sum_foreign_comment":"","sum":"","sum_comment":"","sum_comment_unclear":false,"sum_foreign":""},"61":{"sum_foreign_comment":"","sum":"","sum_comment":"","sum_foreign":""},"62":{"sum_foreign_comment":"","sum":"","sum_comment":"","sum_foreign":""},"63":{"sum_foreign_comment":"","sum":"","sum_comment":"","sum_foreign":""},"64":{"sum_foreign_comment":"","sum":"","sum_comment":"","sum_unclear":false,"sum_foreign":""}},"ft_src":"право оренди\nсмт. Доманівка, вул. Кірова\n.0053\nМиколаївська область\nмаринівська с/рада Доманівського р-ну\n2\nМиколаївська область\nМиколаївська область\nм. Первомайськ, вул. Толстого\n52\n2014\n188672\n12180\n213002\n12150\n.0053\nправо оренди\nМиколаївська область\nсмт. Доманівка, вул. Кірова\n2\nМиколаївська область\nмаринівська с/рада Доманівського р-ну\n52\nМиколаївська область\nм. Первомайськ, вул. Толстого\nЗагальний місцевий суд\nМиколаївська область\nсуддя первомайського міськрайонного суду миколаївської області\nМаксютенко Оксана Анатоліївна\nОксана Анатоліївна Максютенко\nОксана Максютенко\nМаксютенко Оксана Анатоліївна\nОксана\nДитина\n17. 12. 2010\nДитина\n22. 03. 2013\nМаксютенко Оксана Анатоліївна\nМаксютенко\nАнатоліївна\n55200 вул. Толстого\nМиколаївська область\nПервомайськ\n188672\n12150\n213002\n12180\n2014\n17. 12. 2010\nДитина\nДитина\n22. 03. 2013\nАнатоліївна\nМаксютенко\nОксана\nМаксютенко Оксана Анатоліївна\nОксана Анатоліївна Максютенко\nОксана Максютенко\nМаксютенко Оксана Анатоліївна\n55200 вул. Толстого\nПервомайськ\nМиколаївська область\nМиколаївська область\nЗагальний місцевий суд\nсуддя первомайського міськрайонного суду миколаївської області\nМаксютенко Оксана Анатоліївна","general":{"name_hidden":false,"name":"Оксана","last_name_hidden":false,"inn":"","last_name":"Максютенко","family":[{"inn":"","inn_hidden":false,"inn_unclear":false,"relations_hidden":false,"relations_other":"","relations":"Дитина","name_hidden":false,"family_name":"17. 12. 2010","name_unclear":false},{"inn":"","inn_hidden":false,"relations_unclear":false,"relations_hidden":false,"relations_other":"","relations":"Дитина","name_hidden":false,"inn_unclear":false,"family_name":"22. 03. 2013","name_unclear":false}],"inn_hidden":true,"family_raw":"","inn_unclear":false,"post":{"post_unclear":false,"region_unclear":false,"post":"суддя первомайського міськрайонного суду миколаївської області","post_hidden":false,"region":"Миколаївська область","region_hidden":false,"office":"Загальний місцевий суд","office_hidden":false,"office_unclear":false},"full_name_suggest":{"output":"Максютенко Оксана Анатоліївна","input":["Максютенко Оксана Анатоліївна","Оксана Анатоліївна Максютенко","Оксана Максютенко"]},"full_name":"Максютенко Оксана Анатоліївна","addresses":[{"place_district":"","place_address_hidden":false,"place_city":"Первомайськ","place_address":"55200 вул. Толстого","place_district_hidden":false,"place_city_type":"Місто","place_city_hidden":false,"place_address_unclear":false,"place_city_type_hidden":false,"place_hidden":false,"place":"Миколаївська область"}],"patronymic":"Анатоліївна","patronymic_hidden":false,"last_name_unclear":false,"name_unclear":false},"source":"VULYK","estate":{"23":[{"space_unclear":false,"costs":"","costs_comment":"","address_hidden":false,"region_hidden":false,"space_comment":"право оренди","space_hidden":false,"space":".0053","address":"смт. Доманівка, вул. Кірова","region":"Миколаївська область","address_unclear":false,"costs_rent_comment":"","space_units":"га","costs_rent":""},{"space_unclear":false,"costs":"","costs_comment":"","address_hidden":false,"region_hidden":false,"space_comment":"","space":"2","address":"маринівська с/рада Доманівського р-ну","region":"Миколаївська область","address_unclear":true,"costs_rent_comment":"","space_units":"га","costs_rent":""}],"25":[{"space_unclear":false,"costs":"","costs_comment":"","address_hidden":false,"region_hidden":false,"space_comment":"","space_hidden":false,"space":"52","address":"м. Первомайськ, вул. Толстого","costs_rent_comment_unclear":false,"region":"Миколаївська область","address_unclear":false,"costs_rent_comment":"","space_comment_unclear":false,"space_units":"м²","space_units_hidden":false,"costs_rent":""}]},"intro":{"declaration_year":"2014","isnotdeclaration":"","declaration_year_hidden":false}}