{"income":{"5":{"value":"249505.29","value_unclear":false,"family_hidden":false,"value_hidden":false,"family_comment":"","family":"45600","comment":""},"6":{"value":"249505.29","value_unclear":false,"family_hidden":false,"family_comment":"","family":"45600","comment":""},"7":{"value":"","comment_hidden":false,"family_comment":"","source_name":"","family":"","comment":"","source_name_hidden":false},"8":{"family_comment":"","value":"","family":"","comment":""},"9":{"family_comment":"","value":"","family":"","comment":""},"10":{"family_comment":"","family_unclear":false,"value":"","family":"","comment":""},"11":{"family_comment":"","value":"","family":"","comment":""},"12":{"family_comment":"","value":"","family":"","comment":""},"13":{"family_comment":"","value":"","family":"","comment":""},"14":{"family_comment":"","value":"","family":"","comment":""},"15":{"family_comment":"","value":"","family":"","comment":""},"16":{"family_comment":"","value":"","family":"","comment":""},"17":{"family_comment":"","value":"","family":"","comment":""},"18":{"family_comment":"","value":"","family":"","comment":""},"19":{"family_comment":"","value":"","family":"","comment":""},"20":{"value":"14223.64","family_comment":"","family_hidden":false,"family_unclear":false,"family":"","comment":"кредит","family_comment_unclear":false}},"vehicle":{"40":[{"brand_info":"1.6 л","sum_rent_comment":"","brand":"Skoda Octavia","sum_comment":"","year":"2006","brand_hidden":false,"brand_info_hidden":false,"brand_info_unclear":false,"year_unclear":false,"sum":"","sum_rent":""}]},"id":"vulyk_45_121","banks":{"45":[{"sum_foreign_comment":"","sum_units":"UAH","sum_comment":"","sum_comment_unclear":false,"sum_foreign_units":"UAH","sum_comment_hidden":false,"sum_unclear":false,"sum":"","sum_foreign":""},{"sum_foreign_comment":"","sum_units":"","sum_comment":"","sum_foreign_units":"","sum":"","sum_foreign":""}],"46":[{"sum_foreign_comment":"","sum_units":"UAH","sum_comment":"","sum_comment_unclear":false,"sum_foreign_units":"UAH","sum":"","sum_unclear":false,"sum_foreign":""}],"47":[{"sum_foreign_comment":"","sum_units":"UAH","sum_comment":"","sum_foreign_units":"UAH","sum":"","sum_foreign":""}],"48":[{"sum_foreign_comment":"","sum_units":"UAH","sum_comment":"","sum_foreign_units":"UAH","sum":"","sum_foreign":""}],"49":[{"sum_foreign_comment":"","sum_units":"UAH","sum_comment":"","sum_foreign_units":"UAH","sum":"","sum_foreign":""}],"50":[{"sum_foreign_comment":"","sum_units":"UAH","sum_comment":"","sum_foreign_units":"UAH","sum":"","sum_foreign":""}],"51":[{"sum_foreign_comment":"","sum_units":"UAH","sum_comment":"","sum_foreign_units":"UAH","sum_comment_hidden":false,"sum":"","sum_foreign":""},{"sum_foreign_comment":"","sum_units":"","sum_comment":"","sum_foreign_units":"","sum":"","sum_foreign":""}],"52":[{"sum_foreign_comment":"","sum_units":"UAH","sum_comment":"","sum_comment_unclear":false,"sum_foreign_units":"UAH","sum":"","sum_unclear":false,"sum_foreign":""}],"53":[{"sum_foreign_comment":"","sum_units":"UAH","sum_comment":"","sum_foreign_comment_hidden":false,"sum_hidden":false,"sum_foreign_units":"UAH","sum_comment_hidden":false,"sum_foreign_hidden":false,"sum":"","sum_foreign":""}]},"declaration":{"additional_info_text":"","notfull_lostpages":"","date":"2015-03-30T00:00:00","notfull":"","additional_info":"","url":"http://static.declarations.com.ua/declarations/chosen_ones/mega_batch/burda_nadiia_mykolaivna.pdf"},"liabilities":{"54":{"sum_foreign_comment":"","sum":"","sum_comment":"","sum_comment_unclear":false,"sum_comment_hidden":false,"sum_unclear":false,"sum_foreign":""},"55":{"sum_foreign_comment":"","sum":"","sum_comment":"","sum_foreign":""},"56":{"sum_foreign_comment":"","sum":"","sum_comment":"","sum_comment_unclear":false,"sum_unclear":false,"sum_foreign":""},"57":{"sum_foreign_comment":"","sum":"3800","sum_comment":"","sum_comment_unclear":false,"sum_hidden":false,"sum_comment_hidden":false,"sum_foreign":""},"58":{"sum_foreign_comment":"","sum":"","sum_comment":"","sum_comment_unclear":false,"sum_hidden":false,"sum_comment_hidden":false,"sum_foreign":""},"59":{"sum_foreign_comment":"","sum":"103000","sum_comment":"","sum_foreign":""},"60":{"sum_foreign_comment":"","sum":"","sum_comment":"","sum_comment_unclear":false,"sum_comment_hidden":false,"sum_foreign":""},"61":{"sum_foreign_comment":"","sum":"","sum_comment":"","sum_foreign":""},"62":{"sum_foreign_comment":"","sum":"","sum_comment":"","sum_foreign":""},"63":{"sum_foreign_comment":"","sum":"","sum_comment":"","sum_comment_unclear":false,"sum_comment_hidden":false,"sum_unclear":false,"sum_foreign":""},"64":{"sum_foreign_comment":"","sum":"","sum_comment":"","sum_comment_unclear":false,"sum_comment_hidden":false,"sum_unclear":false,"sum_foreign":""}},"ft_src":"103000\n3800\nТернопіль\nТернопільська область\nсуддя господарського суду тернопільської області\nТернопільська область\nГосподарський місцевий суд\nНадія\nБурда В. С\nПодружжя\nМиколаївна\nБурда Надія Миколаївна\nНадія Миколаївна Бурда\nНадія Бурда\nБурда Надія Миколаївна\nБурда Надія Миколаївна\nБурда\n1.6 л\nSkoda Octavia\n2006\n2014\n1.6 л\n2006\nSkoda Octavia\n.07\nТернопільська область\nТернопільський район, Бичківська с/р\n64\n1/4 частка\nТернопільська область\nм. Тернопіль\n64\n1/4 частка\nм. Тернопіль\nТернопільська область\nПодружжя\nБурда В. С\nБурда Надія Миколаївна\nНадія Миколаївна Бурда\nНадія Бурда\nБурда Надія Миколаївна\nБурда Надія Миколаївна\nНадія\nБурда\nГосподарський місцевий суд\nсуддя господарського суду тернопільської області\nТернопільська область\nМиколаївна\nТернопільська область\nТернопіль\n103000\n3800\n249505.29\n45600\nкредит\n14223.64\n249505.29\n45600\n2014\n3800\n103000\nТернопільський район, Бичківська с/р\n.07\nТернопільська область\n1/4 частка\nм. Тернопіль\nТернопільська область\n64\n1/4 частка\nм. Тернопіль\n64\nТернопільська область\nБурда В. С\nПодружжя\nМиколаївна\nБурда\nНадія\nБурда Надія Миколаївна\nНадія Миколаївна Бурда\nНадія Бурда\nБурда Надія Миколаївна\nТернопільська область\nТернопіль\nТернопільська область\nсуддя господарського суду тернопільської області\nГосподарський місцевий суд\nБурда Надія Миколаївна\n45600\n249505.29\n45600\n249505.29\nкредит\n14223.64\nSkoda Octavia\n1.6 л\n2006\nкредит\n14223.64\n249505.29\n45600\n249505.29\n45600\n1/4 частка\nм. Тернопіль\nТернопільська область\n64\nТернопільський район, Бичківська с/р\nТернопільська область\n.07\nТернопільська область\n1/4 частка\nм. Тернопіль\n64\n2014","general":{"inn":"","name":"Надія","last_name_hidden":false,"family":[{"inn":"","inn_hidden":false,"relations_unclear":false,"relations_hidden":false,"relations_other":"","relations":"Подружжя","name_hidden":false,"family_name":"Бурда В. С","name_unclear":false}],"patronymic":"Миколаївна","inn_hidden":true,"family_raw":"","inn_unclear":false,"post":{"post_unclear":false,"post":"суддя господарського суду тернопільської області","post_hidden":false,"region":"Тернопільська область","region_hidden":false,"office":"Господарський місцевий суд","office_hidden":false,"office_unclear":false},"full_name":"Бурда Надія Миколаївна","addresses":[{"place_district":"","place_city_hidden":false,"place_city":"Тернопіль","place_city_type_hidden":false,"place_district_hidden":false,"place_city_type":"Місто","place_address_hidden":false,"place_address":"","place_hidden":false,"place":"Тернопільська область"}],"last_name":"Бурда","full_name_suggest":{"output":"Бурда Надія Миколаївна","input":["Бурда Надія Миколаївна","Надія Миколаївна Бурда","Надія Бурда"]}},"source":"VULYK","estate":{"23":[{"space_unclear":false,"costs":"","costs_comment":"","costs_hidden":false,"address_hidden":false,"region_hidden":false,"space_comment":"","space":".07","address":"Тернопільський район, Бичківська с/р","region":"Тернопільська область","space_units_unclear":false,"space_units":"га","costs_rent":"","costs_rent_comment":""},{"costs":"","costs_comment":"","costs_hidden":false,"address_hidden":false,"region_hidden":false,"space_comment":"","space":"","address":"","region":"","costs_rent_comment":"","space_units":"","costs_rent":""},{"costs_rent":"","space_unclear":false,"region":"","costs":"","costs_rent_comment":"","costs_comment":"","address_hidden":false,"space_comment":"","space_units":"","space":"","address":""},{"costs_rent":"","region":"","costs":"","costs_rent_comment":"","costs_comment":"","space_comment":"","space_units":"","space":"","address":""},{"costs_rent":"","region":"","costs":"","costs_rent_comment":"","costs_comment":"","space_comment":"","space_units":"","space":"","address":""},{"costs_rent":"","region":"","costs":"","costs_rent_comment":"","costs_comment":"","space_comment":"","space_units":"","space":"","address":""}],"25":[{"space_unclear":false,"costs":"","costs_comment":"","address_hidden":false,"region_hidden":false,"space_comment":"1/4 частка","space_hidden":false,"space":"64","address":"м. Тернопіль","region":"Тернопільська область","address_unclear":false,"costs_rent_comment":"","costs_rent_hidden":false,"space_comment_hidden":false,"space_units":"м²","space_units_hidden":false,"costs_rent":""}],"31":[{"space_unclear":false,"address_hidden":false,"region_hidden":false,"space_comment":"1/4 частка","space_hidden":false,"space":"64","address":"м. Тернопіль","region":"Тернопільська область","costs_property":"","costs_rent_comment":"","space_units":"м²","costs_property_comment":"","costs_rent":""}]},"intro":{"declaration_year":"2014","isnotdeclaration":""}}