{"id":"vulyk_102_43","ft_src":"2013\n250 CDI, V 2143\nMercedes-Benz ML-Class\n150 VX, 2982\n2012\nToyota Land Cruiser\n20.19\n42.82\nкористування\n384\nгосподарська будівля, право користування\nкористування\n151.7\nлітня кухня\n30.6\nправо власності\n1189\nправо користування\n1266\nвласність\n1266\nкористування\n1189\nкористування\n384\nгосподарська будівля, право користування\n151.7\nлітня кухня\n30.6\nвласність\n111.6\nвласність\n35.85\n311850\nкарткові рахунки\n41694\nкартковий рахунок\n29817\n2015\n250 CDI, V 2143\nMercedes-Benz ML-Class\n2013\n150 VX, 2982\n2012\nToyota Land Cruiser\n2015\nПилипчук Надія Григорівна\nНадія Григорівна Пилипчук\nНадія Пилипчук\nПилипчук Надія Григорівна\nПилипчук Надія Григорівна\nНадія\nГригорівна\nсуддя вищого адміністративного суду україни\nЗагальнодержавний регіон\nВищий адміністративний суд\nПилипчук\nПодружжя\n52463\n986\n245217\n100191\n260769\n100191\n14616\nпроценти на картковому рахунку\n936\n384\nкористування\n151.7\nгосподарська будівля, право користування\nкористування\n30.6\nлітня кухня\n35.85\nвласність\n20.19\n42.82\n1266\nвласність\nкористування\n1189\nправо власності\n1189\n1266\nправо користування\nкористування\n384\nвласність\n111.6\nгосподарська будівля, право користування\n151.7\n30.6\nлітня кухня\n29817\nкартковий рахунок\nкарткові рахунки\n41694\n311850\n52463\n986\n100191\n245217\n14616\n100191\n260769\nпроценти на картковому рахунку\n936\nПодружжя\nНадія\nГригорівна\nПилипчук\nПилипчук Надія Григорівна\nНадія Григорівна Пилипчук\nНадія Пилипчук\nПилипчук Надія Григорівна\nсуддя вищого адміністративного суду україни\nЗагальнодержавний регіон\nВищий адміністративний суд\nПилипчук Надія Григорівна","estate":{"23":[{"address":"","space_units":"м²","space_comment":"","region_hidden":true,"space_units_unclear":false,"costs_comment":"власність","address_hidden":false,"space":"1266","space_comment_unclear":false,"costs_rent_comment":"","costs":"","region":"","costs_rent":""},{"costs":"","address":"","space_units":"м²","costs_rent_comment":"користування","space":"1189","space_comment":"","region_hidden":true,"costs_comment":"","region":"","costs_rent":""}],"24":[{"costs":"","address":"","space_units":"м²","costs_rent_comment":"користування","space":"384","space_comment":"","region_hidden":true,"costs_comment":"","region":"","address_hidden":false,"costs_rent":""}],"25":[{"address":"","space_units":"м²","costs_comment":"власність","space_comment":"","region_hidden":true,"region":"","address_hidden":false,"space":"35.85","address_unclear":false,"costs_rent_comment":"","costs":"","costs_rent":""}],"28":[{"address":"","space_units":"м²","costs_comment":"","space_unclear":false,"region_hidden":true,"space_comment":"господарська будівля, право користування","address_hidden":false,"costs":"","costs_rent_comment":"користування","space":"151.7","region":"","costs_rent":""},{"address":"","space_units":"м²","costs_comment":"","space_unclear":false,"region_hidden":false,"space_comment":"літня кухня","address_hidden":false,"space":"30.6","space_comment_unclear":false,"costs_rent_comment":"","costs":"","region":"","costs_rent":""}],"29":[{"costs_property_comment":"","address":"","space_units":"м²","space_comment":"право власності","region_hidden":true,"costs_property":"","region":"","address_hidden":false,"space_comment_hidden":false,"costs_rent_comment":"","space":"1189","costs_rent":""},{"costs_property_comment":"","address":"","space_units":"м²","costs_rent_comment":"","space":"1266","region":"","region_hidden":false,"costs_property":"","space_comment":"право користування","address_hidden":false,"costs_rent":""}],"30":[{"costs_property_comment":"","address":"","space_units":"м²","costs_rent_comment":"користування","space":"384","region":"","region_hidden":true,"costs_property":"","space_comment":"","address_hidden":false,"costs_rent":""}],"31":[{"costs_property_comment":"власність","address":"","space_units":"м²","costs_rent_comment":"","space":"111.6","region":"","region_hidden":true,"costs_property":"","space_comment":"","address_hidden":false,"costs_rent":""}],"33":[{"costs_property_comment":"","address":"","space_units":"м²","costs_rent_comment":"","space":"20.19","region":"","region_hidden":true,"costs_property":"","space_comment":"","address_hidden":false,"costs_rent":""},{"costs_property_comment":"","address":"","space_units":"м²","costs_rent_comment":"","space":"42.82","region_hidden":false,"costs_property":"","space_comment":"","costs_rent":""}],"34":[{"costs_property_comment":"","address":"","space_units":"м²","space_comment":"господарська будівля, право користування","region_hidden":true,"costs_property":"","region":"","address_hidden":false,"address_unclear":false,"costs_rent_comment":"","space":"151.7","costs_rent":""},{"costs_property_comment":"","address":"","space_units":"м²","costs_rent_comment":"","space":"30.6","region_hidden":false,"costs_property":"","space_comment":"літня кухня","costs_rent":""}]},"vehicle":{"35":[{"sum_comment":"","brand_info":"250 CDI, V 2143","sum":"","sum_rent_comment":"","year":"2013","brand":"Mercedes-Benz ML-Class","sum_rent":"","brand_info_unclear":false,"year_unclear":false}],"40":[{"sum_comment":"","brand_info":"150 VX, 2982","sum":"","sum_rent_comment":"","year":"2012","brand":"Toyota Land Cruiser","sum_rent":"","brand_info_unclear":false}]},"source":"VULYK","income":{"5":{"family_comment":"","value":"260769","family":"100191","comment":""},"6":{"family_comment":"","value":"245217","family":"100191","comment":""},"7":{"source_name_hidden":false,"family_comment":"","family":"","value_hidden":false,"comment":"","comment_hidden":false,"value":"","source_name":""},"8":{"family_comment":"","value":"","family":"","comment":""},"9":{"family_comment":"","family":"","comment":"проценти на картковому рахунку","comment_hidden":false,"value":"936","family_comment_unclear":false},"10":{"family_comment":"","value":"14616","family":"","comment":""},"11":{"family_comment":"","value":"","family":"","comment":"","comment_hidden":false},"12":{"family_comment":"","value":"","family":"","comment":""},"13":{"family_comment":"","value":"","family":"","comment":""},"14":{"family_comment":"","value":"","family":"","comment":""},"15":{"family_comment":"","value":"","family":"","comment":""},"16":{"family_comment":"","value":"","family":"","comment":""},"17":{"family_comment":"","value":"","family":"","comment":""},"18":{"family_comment":"","value":"","family":"","comment":""},"19":{"family_comment":"","value":"","family":"","comment":""},"20":{"family_comment":"","value":"","family":"","comment":"","comment_hidden":false}},"banks":{"45":[{"sum_comment_unclear":true,"sum_units":"UAH","sum_foreign_units":"UAH","sum_hidden":false,"sum":"29817","sum_foreign_comment":"","sum_comment":"картковий рахунок","sum_unclear":false,"sum_foreign":"","sum_comment_hidden":true}],"51":[{"sum_comment_unclear":false,"sum_units":"UAH","sum_foreign_units":"UAH","sum_hidden":false,"sum":"41694","sum_foreign_comment_hidden":false,"sum_foreign_comment":"","sum_comment":"карткові рахунки","sum_unclear":false,"sum_foreign":"","sum_comment_hidden":true}],"52":[{"sum_comment_unclear":false,"sum_units":"UAH","sum_foreign_units":"UAH","sum_hidden":false,"sum":"311850","sum_foreign_comment":"","sum_comment":"","sum_foreign":"","sum_comment_hidden":true}]},"declaration":{"additional_info_text":"","additional_info":"","date":"2016-03-24T00:00:00","url":"http://static.declarations.com.ua/declarations/chosen_ones/judges_batch/1117_pylypchuk_nadiia_hryhorivna.pdf"},"general":{"family":[{"inn":"","family_name":"","name_unclear":false,"inn_hidden":true,"name_hidden":true,"relations":"Подружжя"}],"family_raw":"","name":"Надія","full_name_suggest":{"input":["Пилипчук Надія Григорівна","Надія Григорівна Пилипчук","Надія Пилипчук"],"output":"Пилипчук Надія Григорівна"},"patronymic":"Григорівна","inn_hidden":true,"patronymic_hidden":false,"inn":"","addresses":[{"place_city_type_hidden":false,"place_city_type":"","place_city_hidden":true,"place_hidden":true,"place_district":"","place_district_hidden":false,"place":"","place_address":"","place_address_hidden":true,"place_city":""}],"last_name":"Пилипчук","full_name":"Пилипчук Надія Григорівна","post":{"office_unclear":false,"region_unclear":false,"post":"суддя вищого адміністративного суду україни","region":"Загальнодержавний регіон","office":"Вищий адміністративний суд"}},"liabilities":{"54":{"sum_comment":"","sum_hidden":false,"sum":"52463","sum_foreign_comment":"","sum_foreign":"","sum_comment_hidden":true},"55":{"sum_comment":"","sum_foreign_comment":"","sum_foreign":"","sum":""},"56":{"sum_comment":"","sum_foreign_comment":"","sum_foreign":"","sum":""},"57":{"sum_comment":"","sum_foreign_comment":"","sum_foreign":"","sum":"","sum_comment_hidden":false},"58":{"sum_comment":"","sum_foreign_comment":"","sum_foreign":"","sum":"","sum_comment_hidden":false},"59":{"sum_comment":"","sum_foreign_comment":"","sum_foreign":"","sum":"","sum_comment_hidden":false},"60":{"sum_comment":"","sum_hidden":false,"sum":"986","sum_foreign_comment":"","sum_foreign":"","sum_comment_hidden":true},"61":{"sum_comment":"","sum_foreign_comment":"","sum_foreign":"","sum":""},"62":{"sum_comment":"","sum_foreign_comment":"","sum_foreign":"","sum_unclear":false,"sum":""},"63":{"sum_comment":"","sum_hidden":false,"sum":"","sum_foreign_comment":"","sum_foreign":"","sum_comment_hidden":false},"64":{"sum_comment":"","sum_foreign_comment":"","sum_foreign":"","sum":"","sum_comment_hidden":false}},"intro":{"declaration_year":"2015"}}