{"income":{"5":{"value":"201880","value_unclear":false,"comment_hidden":false,"family_comment":"","family":"329560","comment":""},"6":{"family_comment":"","value":"","family":"","comment":"","value_hidden":false},"7":{"family_comment":"","value":"","source_name":"","family":"","comment":""},"8":{"family_comment":"","value":"","family":"","comment":""},"9":{"family_comment":"","value":"","comment_hidden":false,"family":"","comment":""},"10":{"family_comment":"","value":"","family":"","comment":""},"11":{"family_comment":"","value":"","family":"","comment":""},"12":{"family_comment":"","value":"","family":"","comment":""},"13":{"family_comment":"","value":"","family":"","comment":""},"14":{"family_comment":"","value":"","family":"","comment":""},"15":{"family_comment":"","value":"","family":"","comment":"","family_comment_hidden":false},"16":{"family_comment":"","value":"","family":"","comment":""},"17":{"family_comment":"","value":"","family":"","comment":""},"18":{"family_comment":"","value":"","family":"","comment":"","value_hidden":false},"19":{"family_comment":"","value":"","family":"","comment":""},"20":{"family_comment":"","value":"","family":"","comment":"","family_comment_unclear":false}},"vehicle":{"40":[{"brand_info":"2354 куб. см., 122 кВт","sum_rent_comment":"","brand":"Honda CR-V","sum_comment":"","year":"2008","brand_info_hidden":false,"sum":"","sum_rent":""}]},"id":"vulyk_78_50","declaration":{"additional_info_text":"","notfull_lostpages":"","date":"2015-03-31T00:00:00","notfull":"","additional_info":"","url":"http://static.declarations.com.ua/declarations/chosen_ones/judges_batch/2117_karaban_volodymyr_mykolaiovych.pdf"},"liabilities":{"54":{"sum_foreign_comment":"","sum_foreign_hidden":false,"sum_comment":"","sum_comment_unclear":false,"sum_hidden":false,"sum_comment_hidden":false,"sum":"","sum_foreign":""},"55":{"sum_foreign_comment":"","sum":"","sum_comment":"","sum_foreign":""},"56":{"sum_foreign_comment":"","sum":"","sum_comment":"","sum_foreign":""},"57":{"sum_foreign_comment":"","sum":"","sum_comment":"","sum_foreign":""},"58":{"sum_foreign_comment":"","sum":"","sum_comment":"","sum_unclear":false,"sum_foreign":""},"59":{"sum_foreign_comment":"","sum":"","sum_comment":"","sum_foreign":""},"60":{"sum_foreign_comment":"","sum":"","sum_comment":"","sum_comment_unclear":false,"sum_comment_hidden":false,"sum_foreign":""},"61":{"sum_foreign_comment":"","sum":"","sum_comment":"","sum_foreign":""},"62":{"sum_foreign_comment":"","sum":"","sum_hidden":false,"sum_comment":"","sum_foreign":""},"63":{"sum_foreign_comment":"","sum_foreign_hidden":false,"sum_comment":"","sum":"","sum_unclear":false,"sum_foreign":""},"64":{"sum_foreign_comment":"","sum_foreign_hidden":false,"sum_comment":"","sum_hidden":false,"sum":"","sum_foreign":""}},"ft_src":"суддя печерського районного суду міста києва\nм. Київ\nЗагальний місцевий суд\nВолодимир\nКарабань М. Е., 1978\nПодружжя\nКарабань О. В., 2004\nДитина\nКарабань В. В., 2009\nДитина\nМиколайович\nКарабань Володимир Миколайович\nВолодимир Миколайович Карабань\nВолодимир Карабань\nКарабань Володимир Миколайович\nКарабань\nКарабань Володимир Миколайович\nКиїв\nм. Київ\n2354 куб. см., 122 кВт\n2008\nHonda CR-V\nм. Київ\n20\n1200\nм. Київ\n77.3\n2014\n329560\n201880\n2354 куб. см., 122 кВт\n2008\nHonda CR-V\n2014\nПодружжя\nКарабань М. Е., 1978\nДитина\nКарабань О. В., 2004\nДитина\nКарабань В. В., 2009\nКарабань Володимир Миколайович\nВолодимир Миколайович Карабань\nВолодимир Карабань\nКарабань Володимир Миколайович\nКарабань Володимир Миколайович\nВолодимир\nМиколайович\nЗагальний місцевий суд\nсуддя печерського районного суду міста києва\nм. Київ\nКарабань\nм. Київ\nКиїв\n201880\n329560\n1200\nм. Київ\n20\n77.3\nм. Київ\nПодружжя\nКарабань М. Е., 1978\nДитина\nКарабань О. В., 2004\nДитина\nКарабань В. В., 2009\nМиколайович\nКарабань\nВолодимир\nКарабань Володимир Миколайович\nВолодимир Миколайович Карабань\nВолодимир Карабань\nКарабань Володимир Миколайович\nм. Київ\nКиїв\nм. Київ\nсуддя печерського районного суду міста києва\nЗагальний місцевий суд\nКарабань Володимир Миколайович\nHonda CR-V\n2354 куб. см., 122 кВт\n2008\n201880\n329560\nм. Київ\n20\nм. Київ\n77.3\n1200\n2014","general":{"inn":"","name":"Володимир","family":[{"inn":"","relations":"Подружжя","relations_other":"","inn_hidden":false,"family_name":"Карабань М. Е., 1978","name_hidden":false,"name_unclear":false},{"inn":"","relations":"Дитина","relations_other":"","inn_hidden":false,"family_name":"Карабань О. В., 2004","name_hidden":false,"name_unclear":false},{"inn":"","relations":"Дитина","relations_other":"","inn_hidden":false,"family_name":"Карабань В. В., 2009","name_unclear":false}],"patronymic":"Миколайович","inn_hidden":true,"family_raw":"","last_name":"Карабань","post":{"post_unclear":false,"post":"суддя печерського районного суду міста києва","post_hidden":false,"region":"м. Київ","region_hidden":false,"office":"Загальний місцевий суд","office_hidden":false},"last_name_unclear":false,"full_name":"Карабань Володимир Миколайович","addresses":[{"place_district":"","place_city_hidden":false,"place_city":"Київ","place_city_type_hidden":false,"place_district_hidden":false,"place_city_type":"Місто","place_address_hidden":false,"place_address":"","place_hidden":false,"place":"м. Київ"}],"full_name_suggest":{"output":"Карабань Володимир Миколайович","input":["Карабань Володимир Миколайович","Володимир Миколайович Карабань","Володимир Карабань"]},"name_unclear":false},"source":"VULYK","estate":{"25":[{"space_hidden":false,"costs":"","costs_comment":"","address_hidden":true,"region_hidden":false,"space_comment":"","space":"77.3","address":"","region":"м. Київ","address_unclear":false,"costs_rent_comment":"","space_units":"м²","costs_rent":""}],"29":[{"space_unclear":false,"address_hidden":false,"region_hidden":true,"space_comment":"","space":"1200","address":"","region":"","costs_property":"","costs_rent_comment":"","space_units":"м²","costs_property_comment":"","costs_rent":""}],"31":[{"address_hidden":false,"region_hidden":false,"space_comment":"","space":"20","address":"","region":"м. Київ","costs_property":"","costs_rent_comment":"","address_unclear":false,"space_units":"м²","costs_property_comment":"","costs_rent":""}]},"intro":{"declaration_year":"2014"}}