{"income":{"5":{"value":"795549","family_comment":"","value_unclear":false,"family_unclear":false,"family":"273867","comment":""},"6":{"value":"180670","family_comment":"","value_unclear":false,"family_unclear":false,"family":"222064","comment":""},"7":{"value":"","value_unclear":false,"family_comment":"","source_name":"","family":"","comment":""},"8":{"family_comment":"","value":"","family":"","comment":""},"9":{"family_comment":"","value":"49","value_unclear":false,"family":"5","comment":""},"10":{"family_comment":"","value":"12180","comment_unclear":false,"family":"13398","comment":""},"11":{"family_comment":"","value":"602650","family":"","comment":""},"12":{"family_comment":"","value":"","family":"","comment":""},"13":{"family_comment":"","value":"","family":"","comment":""},"14":{"family_comment":"","value":"","family":"","comment":""},"15":{"family_comment":"","value":"","family":"","comment":""},"16":{"family_comment":"","value":"","family":"","comment":""},"17":{"family_comment":"","value":"","family":"","comment":""},"18":{"family_comment":"","value":"","family":"","comment":""},"19":{"family_comment":"","value":"","family":"38400","comment":""},"20":{"family_comment":"","value":"","family":"","comment":""}},"vehicle":{"40":[{"brand_info":"1.6 /78, 448","sum_rent_comment":"","year":"2006","brand_info_hidden":false,"brand_info_unclear":false,"sum_rent":"","sum":"","brand":"Kia Cerato","sum_comment":"","sum_comment_unclear":false,"brand_hidden":false,"brand_unclear":false},{"year_hidden":false,"brand_info":"3.2 /179, 447","sum_rent_comment":"","brand":"Suzuki Grand Vitara","sum_comment":"","brand_unclear":false,"year":"2008","brand_hidden":false,"sum":"","sum_rent":""}]},"id":"vulyk_55_97","banks":{"45":[{"sum_foreign_comment":"","sum_units":"UAH","sum_comment":"","sum_comment_unclear":true,"sum_foreign_units":"UAH","sum_foreign_comment_unclear":false,"sum_units_unclear":false,"sum_comment_hidden":false,"sum_unclear":false,"sum":"15790","sum_foreign":""},{"sum_foreign_comment":"","sum_units":"","sum_comment":"","sum_comment_unclear":false,"sum_foreign_units":"","sum":"","sum_unclear":false,"sum_foreign":""},{"sum_foreign_comment":"","sum_units":"","sum_comment":"","sum_foreign_units":"","sum":"","sum_unclear":false,"sum_foreign":""}],"46":[{"sum_foreign_comment":"","sum_units":"UAH","sum_comment":"","sum_comment_unclear":false,"sum_foreign_units":"UAH","sum":"15790","sum_foreign":""}],"47":[{"sum_foreign_comment":"","sum_units":"UAH","sum_comment":"","sum_comment_unclear":true,"sum_hidden":false,"sum_foreign_units":"UAH","sum":"3.4","sum_foreign":""}],"48":[{"sum_foreign_comment":"","sum_units":"UAH","sum_comment":"","sum_foreign_units":"UAH","sum":"","sum_foreign":""}],"49":[{"sum_foreign_comment":"","sum_units":"UAH","sum_comment":"","sum_foreign_units":"UAH","sum":"","sum_foreign":""},{"sum_foreign_comment":"","sum_units":"","sum_comment":"","sum":"","sum_foreign":""}],"50":[{"sum_foreign_comment":"","sum_units":"UAH","sum_comment":"","sum_foreign_units":"UAH","sum":"","sum_foreign":""}],"51":[{"sum_units":"UAH","sum_hidden":false,"sum_units_hidden":false,"sum_foreign":"","sum_foreign_comment":"","sum":"580","sum_comment":"АТ ОТП Банк, Дніпропетровськ","sum_comment_unclear":true,"sum_foreign_units":"UAH","sum_units_unclear":false,"sum_comment_hidden":false,"sum_unclear":false},{"sum_foreign_comment":"","sum_units":"","sum_comment":"ПАТ Банк Кредит Дніпро, м.Дніпропетровськ","sum_foreign_units":"","sum":"7370","sum_foreign":""}],"52":[{"sum_foreign_comment":"","sum_units":"UAH","sum_comment":"АСК Укрречфлот","sum_comment_unclear":true,"sum_foreign_units":"UAH","sum":"10.5","sum_foreign":""},{"sum_foreign_comment":"","sum_units":"","sum_comment":"","sum_foreign_units":"","sum":"","sum_foreign":""}],"53":[{"sum_foreign_comment":"","sum_units":"UAH","sum_comment":"","sum_hidden":false,"sum_foreign_units":"UAH","sum":"","sum_unclear":false,"sum_foreign":""},{"sum_foreign_comment":"","sum_units":"","sum_comment":"","sum_comment_unclear":false,"sum_foreign_units":"","sum":"","sum_foreign":""},{"sum_foreign_comment":"","sum_units":"","sum_comment":"","sum_foreign_units":"","sum":"","sum_foreign":""},{"sum_foreign_comment":"","sum_units":"","sum_comment":"","sum_foreign_units":"","sum":"","sum_foreign":""}]},"declaration":{"additional_info_text":"","notfull_lostpages":"","date":"2015-03-25T00:00:00","notfull":"","additional_info":"","url":"http://static.declarations.com.ua/declarations/chosen_ones/mega_batch/podobied_olena_kostiantynivna.pdf"},"liabilities":{"54":{"sum_foreign_comment":"","sum":"","sum_comment":"","sum_hidden":false,"sum_comment_hidden":false,"sum_foreign":""},"55":{"sum_foreign_comment":"","sum_foreign_hidden":false,"sum_comment":"","sum_hidden":false,"sum":"","sum_foreign":""},"56":{"sum_foreign_comment":"","sum":"","sum_comment":"","sum_unclear":false,"sum_foreign":""},"57":{"sum_foreign_comment":"","sum":"","sum_comment":"","sum_comment_unclear":false,"sum_hidden":false,"sum_comment_hidden":false,"sum_unclear":false,"sum_foreign":""},"58":{"sum_foreign_comment":"","sum":"","sum_comment":"","sum_hidden":false,"sum_comment_hidden":false,"sum_unclear":false,"sum_foreign":""},"59":{"sum_foreign_comment":"","sum":"","sum_comment":"","sum_foreign":""},"60":{"sum_foreign_comment":"","sum":"","sum_comment":"","sum_hidden":false,"sum_comment_hidden":false,"sum_foreign":""},"61":{"sum_foreign_comment":"","sum":"","sum_comment":"","sum_foreign":""},"62":{"sum_foreign_comment":"","sum":"","sum_comment":"","sum_foreign":""},"63":{"sum_foreign_comment":"","sum":"","sum_comment":"","sum_unclear":false,"sum_foreign":""},"64":{"sum_foreign_comment":"","sum":"","sum_comment":"","sum_unclear":false,"sum_foreign":""}},"ft_src":"Дніпропетровськ\n49000\nДніпропетровська область\nсуддя баглійського районного суду м. дніпродзержинська дніпропетровської області\nДніпропетровська область\nЗагальний місцевий суд\nОлена\nПодобєд І. М\nПодружжя\nПодобєд К. І\nДитина\nКостянтинівна\nПодобєд\nПодобєд Олена Костянтинівна\nПодобєд Олена Костянтинівна\nОлена Костянтинівна Подобєд\nОлена Подобєд\nПодобєд Олена Костянтинівна\n1.6 /78, 448\nKia Cerato\n2006\nSuzuki Grand Vitara\n3.2 /179, 447\n2008\n3.4\n15790\nАТ ОТП Банк, Дніпропетровськ\n580\nПАТ Банк Кредит Дніпро, м.Дніпропетровськ\n7370\n15790\nАСК Укрречфлот\n10.5\n2014\n1.6 /78, 448\nKia Cerato\n2006\n3.2 /179, 447\n2008\nSuzuki Grand Vitara\n15790\n580\nАТ ОТП Банк, Дніпропетровськ\n7370\nПАТ Банк Кредит Дніпро, м.Дніпропетровськ\n10.5\nАСК Укрречфлот\n3.4\n15790\n18.5\nДніпропетровська область\nм. Дніпропетровськ\n75.8\nм. Дніпропетровськ\nДніпропетровська область\n34.8\nм. Львів\nЛьвівська область\n75.8\nДніпропетровська область\nм. Дніпропетровськ\n88\nДніпропетровська область\nм. Дніпропетровськ\nПодружжя\nПодобєд І. М\nДитина\nПодобєд К. І\nПодобєд Олена Костянтинівна\nОлена Костянтинівна Подобєд\nОлена Подобєд\nПодобєд Олена Костянтинівна\nОлена\nПодобєд Олена Костянтинівна\nКостянтинівна\nЗагальний місцевий суд\nсуддя баглійського районного суду м. дніпродзержинська дніпропетровської області\nДніпропетровська область\nПодобєд\nДніпропетровськ\n49000\nДніпропетровська область\n180670\n222064\n795549\n273867\n602650\n12180\n13398\n49\n5\n38400\n2014\nм. Дніпропетровськ\nДніпропетровська область\n18.5\nм. Дніпропетровськ\nДніпропетровська область\n75.8\nм. Львів\nЛьвівська область\n34.8\n75.8\nм. Дніпропетровськ\nДніпропетровська область\nм. Дніпропетровськ\n88\nДніпропетровська область\nПодобєд І. М\nПодружжя\nПодобєд К. І\nДитина\nКостянтинівна\nПодобєд\nПодобєд Олена Костянтинівна\nОлена Костянтинівна Подобєд\nОлена Подобєд\nПодобєд Олена Костянтинівна\nДніпропетровська область\nДніпропетровськ\n49000\nДніпропетровська область\nсуддя баглійського районного суду м. дніпродзержинська дніпропетровської області\nЗагальний місцевий суд\nПодобєд Олена Костянтинівна\nОлена\n222064\n180670\n602650\n13398\n12180\n273867\n795549\n38400\n5\n49\nKia Cerato\n1.6 /78, 448\n2006\n2008\nSuzuki Grand Vitara\n3.2 /179, 447\n602650\n38400\n13398\n12180\n795549\n273867\n5\n49\n180670\n222064\nм. Дніпропетровськ\nДніпропетровська область\n75.8\nм. Львів\nЛьвівська область\n34.8\nм. Дніпропетровськ\nДніпропетровська область\n18.5\nм. Дніпропетровськ\nДніпропетровська область\n75.8\nм. Дніпропетровськ\nДніпропетровська область\n88\n3.4\n15790\n15790\nАСК Укрречфлот\n10.5\n580\nАТ ОТП Банк, Дніпропетровськ\nПАТ Банк Кредит Дніпро, м.Дніпропетровськ\n7370\n2014","general":{"name_hidden":false,"name":"Олена","patronymic_unclear":false,"last_name_hidden":false,"inn":"","family":[{"inn":"","inn_hidden":true,"relations_unclear":false,"relations_hidden":false,"relations_other":"","relations":"Подружжя","name_hidden":false,"family_name":"Подобєд І. М","name_unclear":false},{"inn":"","relations":"Дитина","relations_other":"","inn_hidden":false,"family_name":"Подобєд К. І","name_hidden":false,"name_unclear":false}],"patronymic":"Костянтинівна","inn_hidden":false,"family_raw":"","inn_unclear":false,"post":{"post_unclear":false,"post":"суддя баглійського районного суду м. дніпродзержинська дніпропетровської області","post_hidden":false,"region":"Дніпропетровська область","region_hidden":false,"office":"Загальний місцевий суд","office_hidden":false,"office_unclear":false},"last_name_unclear":false,"full_name":"Подобєд Олена Костянтинівна","addresses":[{"place_city_type_unclear":false,"place_address":"49000","place_district_hidden":true,"place_city_type":"Місто","place_address_hidden":false,"place_address_unclear":false,"place_city_type_hidden":true,"place":"Дніпропетровська область","place_district":"","place_city_hidden":true,"place_city":"Дніпропетровськ","place_city_unclear":false,"place_hidden":false}],"last_name":"Подобєд","patronymic_hidden":false,"full_name_suggest":{"output":"Подобєд Олена Костянтинівна","input":["Подобєд Олена Костянтинівна","Олена Костянтинівна Подобєд","Олена Подобєд"]}},"source":"VULYK","estate":{"23":[{"space_hidden":false,"costs":"","costs_comment":"","address_hidden":false,"region_hidden":false,"space_comment":"","space":"","address":"","region":"","address_unclear":false,"costs_rent_comment":"","space_units":"м²","costs_rent":""},{"costs_rent":"","region":"","costs":"","costs_rent_comment":"","costs_comment":"","region_hidden":false,"space_comment":"","space_units":"","space":"","address":""},{"costs_rent":"","region":"","costs":"","costs_rent_comment":"","costs_comment":"","space_comment":"","space_units":"","space":"","address":""},{"costs_rent":"","costs":"","costs_rent_comment":"","costs_comment":"","space_comment":"","space_units":"","space":"","address":""}],"25":[{"region_unclear":false,"space_unclear":false,"costs":"","costs_comment":"","costs_hidden":false,"address_hidden":false,"region_hidden":false,"space_comment":"","space_hidden":false,"space":"75.8","address":"м. Дніпропетровськ","costs_unclear":false,"region":"Дніпропетровська область","address_unclear":false,"costs_rent_comment":"","space_comment_unclear":false,"space_comment_hidden":false,"space_units":"м²","costs_rent":""},{"space_unclear":false,"costs":"","costs_comment":"","address_hidden":false,"region_hidden":false,"space_comment":"","space":"88","address":"м. Дніпропетровськ","region":"Дніпропетровська область","address_unclear":false,"costs_rent_comment":"","space_comment_unclear":false,"space_units":"м²","costs_rent":""}],"31":[{"region_unclear":false,"space_unclear":false,"address_hidden":false,"region_hidden":false,"space_comment":"","space_hidden":false,"space":"75.8","address":"м. Дніпропетровськ","region":"Дніпропетровська область","costs_property":"","space_units_unclear":false,"space_comment_unclear":false,"space_units":"м²","costs_property_comment":"","costs_rent":"","costs_rent_comment":""},{"space_unclear":false,"address_hidden":false,"region_hidden":false,"space_comment":"","space":"34.8","address":"м. Львів","region":"Львівська область","costs_property":"","costs_rent_comment":"","space_comment_unclear":false,"space_units":"м²","costs_property_comment":"","costs_rent":""}],"33":[{"space_unclear":false,"address_hidden":false,"region_hidden":false,"space_comment":"","space":"18.5","address":"м. Дніпропетровськ","region":"Дніпропетровська область","costs_property":"","costs_rent_comment":"","space_units":"м²","costs_property_comment":"","costs_rent":""}]},"intro":{"declaration_year":"2014","isnotdeclaration":""}}