{"income":{"5":{"value":"217054.32","family_comment":"","value_unclear":false,"family_hidden":false,"family_unclear":false,"family":"","comment":""},"6":{"family_comment":"","value":"217054.32","family":"","comment":""},"7":{"family_comment":"","value":"","source_name":"","family":"","comment":""},"8":{"family_comment":"","value":"","family":"","comment":""},"9":{"family_comment":"","value":"","family":"","comment":""},"10":{"family_comment":"","value":"","value_unclear":false,"family":"","comment":""},"11":{"family_comment":"","value":"","family":"","comment":""},"12":{"family_comment":"","value":"","family":"","comment":""},"13":{"family_comment":"","value":"","family":"","comment":""},"14":{"family_comment":"","value":"","family":"","comment":""},"15":{"family_comment":"","value":"","family":"","comment":""},"16":{"family_comment":"","value":"","family":"","comment":""},"17":{"family_comment":"","value":"","family":"","comment":""},"18":{"family_comment":"","value":"","family":"","comment":""},"19":{"family_comment":"","value":"","family":"","comment":""},"20":{"family_comment":"","value":"","family":"","comment":""}},"id":"vulyk_82_39","declaration":{"date":"2015-03-30T00:00:00","additional_info_text":"","additional_info":"","url":"http://static.declarations.com.ua/declarations/chosen_ones/judges_batch/2234_koreniuk_alla_mykolaivna.pdf"},"liabilities":{"54":{"sum_foreign_comment":"","sum_comment_hidden":false,"sum":"","sum_comment":"","sum_foreign":""},"55":{"sum_foreign_comment":"","sum":"","sum_hidden":false,"sum_comment":"","sum_foreign":""},"56":{"sum_foreign_comment":"","sum":"","sum_comment":"","sum_foreign":""},"57":{"sum_foreign_comment":"","sum":"","sum_comment":"","sum_foreign":""},"58":{"sum_foreign_comment":"","sum":"","sum_comment":"","sum_foreign":""},"59":{"sum_foreign_comment":"","sum":"","sum_comment":"","sum_foreign":""},"60":{"sum_foreign_comment":"","sum":"","sum_comment":"","sum_foreign":""},"61":{"sum_foreign_comment":"","sum":"","sum_comment":"","sum_foreign":""},"62":{"sum_foreign_comment":"","sum":"","sum_comment":"","sum_foreign":""},"63":{"sum_foreign_comment":"","sum":"","sum_comment":"","sum_foreign":""},"64":{"sum_foreign_comment":"","sum":"","sum_comment":"","sum_foreign":""}},"ft_src":"суддя дарницького районного суду міста києва\nм. Київ\nЗагальний місцевий суд\nАлла\nМиколаївна\nКоренюк\nКоренюк Алла Миколаївна\nКоренюк Алла Миколаївна\nАлла Миколаївна Коренюк\nАлла Коренюк\nКоренюк Алла Миколаївна\n217054.32\n217054.32\n1/3 частина\n69.09\n2014\n217054.32\n217054.32\n2014\nКоренюк Алла Миколаївна\nАлла Миколаївна Коренюк\nАлла Коренюк\nКоренюк Алла Миколаївна\nАлла\nКоренюк Алла Миколаївна\nКоренюк\nЗагальний місцевий суд\nм. Київ\nсуддя дарницького районного суду міста києва\nМиколаївна\n217054.32\n217054.32\n69.09\n1/3 частина\nМиколаївна\nКоренюк\nАлла\nКоренюк Алла Миколаївна\nАлла Миколаївна Коренюк\nАлла Коренюк\nКоренюк Алла Миколаївна\nм. Київ\nЗагальний місцевий суд\nсуддя дарницького районного суду міста києва\nКоренюк Алла Миколаївна\n1/3 частина\n69.09\n2014","general":{"inn":"","name":"Алла","inn_unclear":false,"patronymic":"Миколаївна","inn_hidden":true,"family_raw":"","last_name":"Коренюк","post":{"post":"суддя дарницького районного суду міста києва","region":"м. Київ","office_hidden":false,"office":"Загальний місцевий суд","office_unclear":false,"post_hidden":false,"region_hidden":false},"last_name_unclear":false,"full_name":"Коренюк Алла Миколаївна","addresses":[{"place_district":"","place_city_hidden":true,"place_city":"","place_city_type_hidden":false,"place_district_hidden":false,"place_city_type":"","place_address_hidden":false,"place_address":"","place_hidden":true,"place":""}],"full_name_suggest":{"output":"Коренюк Алла Миколаївна","input":["Коренюк Алла Миколаївна","Алла Миколаївна Коренюк","Алла Коренюк"]}},"source":"VULYK","estate":{"25":[{"space_hidden":false,"costs":"","costs_comment":"","costs_hidden":false,"address_hidden":true,"region_hidden":true,"space_comment":"1/3 частина","space_unclear":false,"space":"69.09","address":"","region":"","costs_rent_comment":"","space_comment_unclear":false,"space_units":"м²","costs_rent":""}]},"intro":{"declaration_year":"2014"}}