{"income":{"5":{"family_comment":"","value":"181647.32","family":"12932","comment":""},"6":{"family_comment":"","value":"181647.32","family":"","comment":"","family_comment_unclear":false},"7":{"value":"","comment_hidden":false,"family_comment":"","source_name":"","family":"","comment":"","source_name_hidden":false},"8":{"family_comment":"","value":"","family":"","comment":""},"9":{"family_comment":"","value":"","family":"","comment":""},"10":{"value":"","value_unclear":false,"value_hidden":false,"family_comment":"","family":"","comment":""},"11":{"family_comment":"","value":"","family":"","comment":""},"12":{"family_comment":"","value":"","family":"","comment":""},"13":{"family_comment":"","value":"","family":"","comment":""},"14":{"family_comment":"","value":"","family":"","comment":""},"15":{"family_comment":"виплати по догляду за дитиною","value":"","family":"12932","comment":""},"16":{"family_comment":"","value":"","family":"","comment":""},"17":{"family_comment":"","value":"","family":"","comment":""},"18":{"family_comment":"","value":"","family":"","comment":""},"19":{"family_comment":"","value":"","family":"","comment":""},"20":{"family_comment":"","value":"","comment_unclear":false,"family":"","comment":""}},"id":"vulyk_86_75","declaration":{"additional_info_text":"","notfull_lostpages":"","date":"2015-03-15T00:00:00","notfull":"","additional_info":"","url":"http://static.declarations.com.ua/declarations/chosen_ones/judges_batch/2778_tokariev_artem_hennadiiovych.pdf"},"liabilities":{"54":{"sum_foreign_comment":"","sum":"","sum_comment":"","sum_unclear":false,"sum_foreign":""},"55":{"sum_foreign_comment":"","sum":"","sum_comment":"","sum_foreign":""},"56":{"sum_foreign_comment":"","sum":"","sum_foreign":"","sum_comment":"","sum_hidden":false},"57":{"sum_foreign_comment":"","sum":"","sum_comment":"","sum_unclear":false,"sum_foreign":""},"58":{"sum_foreign_comment":"","sum":"","sum_comment":"","sum_unclear":false,"sum_foreign":""},"59":{"sum_foreign_comment":"","sum":"","sum_comment":"","sum_foreign":""},"60":{"sum_foreign_comment":"","sum_comment":"","sum":"","sum_comment_hidden":false,"sum_foreign":""},"61":{"sum_foreign_comment":"","sum":"","sum_comment":"","sum_foreign":""},"62":{"sum_foreign_comment":"","sum":"","sum_comment":"","sum_foreign":""},"63":{"sum_foreign_comment":"","sum":"","sum_comment":"","sum_foreign":""},"64":{"sum_foreign_comment":"","sum":"","sum_comment":"","sum_foreign":""}},"ft_src":"Донецька область\n1/3 частина\nм. Артемівськ\n68\nм. Красноармійськ\n47\nДонецька область\n2014\n181647.32\n12932\nвиплати по догляду за дитиною\n12932\n181647.32\n181647.32\n12932\nвиплати по догляду за дитиною\n181647.32\n12932\nТокарєв Артем Геннадійович\nАртем Геннадійович Токарєв\nАртем Токарєв\nТокарєв Артем Геннадійович\nТокарєв Артем Геннадійович\nПодружжя\nТокарєва О. Г\nДитина\nТокарєва М. А\nТокарєва А. А\nДитина\nАртем\nТокарєв\nЗагальний місцевий суд\nДонецька область\nсуддя красноармійського міськрайонного суду донецької області\nГеннадійович\nДонецька область\nКрасноармійськ\n68\n1/3 частина\nДонецька область\nм. Артемівськ\n47\nм. Красноармійськ\nДонецька область\n2014\nТокарєва О. Г\nПодружжя\nТокарєва М. А\nДитина\nДитина\nТокарєва А. А\nГеннадійович\nТокарєв\nАртем\nТокарєв Артем Геннадійович\nАртем Геннадійович Токарєв\nАртем Токарєв\nТокарєв Артем Геннадійович\nКрасноармійськ\nДонецька область\nДонецька область\nЗагальний місцевий суд\nсуддя красноармійського міськрайонного суду донецької області\nТокарєв Артем Геннадійович","general":{"inn":"","name":"Артем","patronymic_unclear":false,"last_name":"Токарєв","family":[{"inn":"","inn_hidden":true,"relations_hidden":false,"family_name":"Токарєва О. Г","relations_other":"","relations":"Подружжя","name_hidden":false,"name_unclear":false},{"inn":"","inn_hidden":true,"family_name":"Токарєва М. А","relations_other":"","relations":"Дитина","name_hidden":false,"name_unclear":false},{"inn":"","inn_hidden":false,"relations":"Дитина","name_unclear":false,"family_name":"Токарєва А. А"}],"inn_hidden":true,"family_raw":"","inn_unclear":false,"post":{"post_unclear":false,"post":"суддя красноармійського міськрайонного суду донецької області","candidate":"","office_hidden":false,"region":"Донецька область","region_hidden":false,"office":"Загальний місцевий суд","office_unclear":false},"full_name":"Токарєв Артем Геннадійович","addresses":[{"place_district":"","place_address_hidden":true,"place_city":"Красноармійськ","place_address":"","place_district_hidden":false,"place_city_type":"Місто","place_unclear":false,"place_city_hidden":false,"place_city_type_hidden":false,"place_hidden":false,"place":"Донецька область"}],"patronymic":"Геннадійович","full_name_suggest":{"output":"Токарєв Артем Геннадійович","input":["Токарєв Артем Геннадійович","Артем Геннадійович Токарєв","Артем Токарєв"]}},"source":"VULYK","estate":{"25":[{"space_unclear":false,"costs":"","costs_comment":"","address_hidden":true,"region_hidden":false,"space_comment":"","space_hidden":false,"space":"47","address":"м. Красноармійськ","region":"Донецька область","address_unclear":false,"costs_rent_comment":"","space_units":"м²","costs_rent":""}],"28":[{"costs":"","costs_comment":"","address_hidden":true,"region_hidden":false,"space_comment":"1/3 частина","space":"68","address":"м. Артемівськ","region":"Донецька область","address_unclear":true,"costs_rent_comment":"","space_units":"м²","costs_rent":""}]},"intro":{"declaration_year":"2014","declaration_year_unclear":false}}