{"income":{"5":{"family_comment":"","value":"314846","family_hidden":false,"comment":"","family":"93703"},"6":{"value":"249918","value_unclear":false,"family_hidden":false,"family_comment":"","family":"81115","comment":""},"7":{"value":"","value_unclear":false,"family_comment":"","source_name":"","family":"","comment":""},"8":{"family_comment":"","value":"","family":"","comment":""},"9":{"family_comment":"","value":"","family":"","comment":""},"10":{"value":"12180","family_comment":"","comment_unclear":false,"family_unclear":false,"family":"2202","comment":"","family_comment_unclear":false},"11":{"family_comment":"","value":"","value_unclear":false,"family":"","comment":""},"12":{"family_comment":"","value":"","family":"","comment":""},"13":{"family_comment":"","value":"","family":"","comment":""},"14":{"family_comment":"","value":"","family":"","comment":""},"15":{"value":"","family_comment":"","comment_unclear":false,"family_unclear":false,"family":"","comment":""},"16":{"family_comment":"","value":"","family":"","comment":""},"17":{"family_comment":"","value":"","family":"","comment":""},"18":{"family_comment":"","family_unclear":false,"value":"","family":"","comment":""},"19":{"family_comment":"","value":"","family":"","comment":""},"20":{"family_comment":"","family_unclear":false,"value":"64928","family":"12588","comment":""}},"vehicle":{"35":[{"brand_info":"1500 куб. см.","sum_rent_comment":"","year":"2006","brand_info_hidden":false,"brand_info_unclear":false,"year_unclear":false,"sum_rent":"","sum":"","brand":"Daewoo Lanos","sum_comment":"","sum_comment_unclear":false,"brand_hidden":false,"brand_unclear":false}],"40":[{"year_hidden":false,"brand_info":"1300 куб. см.","sum_rent_comment":"","year":"2006","brand_info_hidden":false,"year_unclear":false,"sum_rent":"","sum":"","brand":"Fiat Doblo","sum_comment":"","sum_comment_unclear":false,"brand_hidden":false}]},"id":"vulyk_92_147","banks":{"45":[{"sum_foreign_comment":"","sum_foreign_hidden":false,"sum_comment":"","sum_comment_unclear":false,"sum_hidden":false,"sum_foreign_units":"UAH","sum_foreign_units_hidden":false,"sum_comment_hidden":false,"sum_units":"UAH","sum":"205313","sum_foreign":""}],"46":[{"sum_foreign_comment":"","sum_units":"UAH","sum_comment":"","sum_hidden":false,"sum_foreign_units":"UAH","sum_comment_hidden":false,"sum":"94195","sum_foreign":""}],"51":[{"sum_foreign_comment":"","sum_units":"UAH","sum_comment":"","sum_hidden":false,"sum_foreign_units":"UAH","sum_foreign_units_hidden":false,"sum_foreign_hidden":false,"sum_foreign_units_unclear":false,"sum":"20649","sum_unclear":false,"sum_foreign":""}]},"declaration":{"additional_info_text":"","notfull_lostpages":"","date":"2015-03-27T00:00:00","notfull":"","additional_info":"","url":"http://static.declarations.com.ua/declarations/chosen_ones/judges_batch/3395_loizyk_mariia_vasylivna.pdf"},"liabilities":{"54":{"sum_foreign_comment":"","sum":"","sum_comment":"","sum_hidden":false,"sum_unclear":false,"sum_foreign":""},"55":{"sum_foreign_comment":"","sum":"","sum_comment":"","sum_unclear":false,"sum_foreign":""},"56":{"sum_foreign_comment":"","sum":"","sum_comment":"","sum_comment_unclear":false,"sum_hidden":false,"sum_unclear":false,"sum_foreign":""},"57":{"sum_foreign_comment":"","sum":"","sum_comment":"","sum_hidden":false,"sum_comment_hidden":false,"sum_foreign":""},"58":{"sum_foreign_comment":"","sum":"","sum_comment":"","sum_foreign":""},"59":{"sum_foreign_comment":"","sum":"","sum_comment":"","sum_comment_unclear":false,"sum_foreign":""},"60":{"sum_foreign_comment":"","sum":"","sum_comment":"","sum_foreign":""},"61":{"sum_foreign_comment":"","sum":"","sum_comment":"","sum_foreign":""},"62":{"sum_foreign_comment":"","sum":"","sum_comment":"","sum_comment_unclear":false,"sum_hidden":false,"sum_unclear":false,"sum_foreign":""},"63":{"sum_foreign_comment":"","sum":"","sum_comment":"","sum_foreign":""},"64":{"sum_foreign_comment":"","sum":"","sum_comment":"","sum_foreign":""}},"ft_src":"суддя старосамбірського районного суду львівської області\nЛьвівська область\nЗагальний місцевий суд\nМарія\nШкрамко В. М., 03. 05. 1956\nПодружжя\nШкрамко Ю. В., 02. 09. 1987\nДитина\nВасилівна\nЛойзик Марія Василівна\nМарія Василівна Лойзик\nМарія Лойзик\nЛойзик Марія Василівна\nЛойзик Марія Василівна\nЛойзик\n1500 куб. см.\nDaewoo Lanos\n2006\n1300 куб. см.\nFiat Doblo\n2006\nЛьвівська область\nм. Старий Самбір\n25\nм. Старий Самбір\n1000\nЛьвівська область\nЛьвівська область\nм. Старий Самбір\n36\nЛьвівська область\nм. Старий Самбір\n100\nм. Старий Самбір\n48.6\nЛьвівська область\n94195\n20649\n205313\n2014\n1500 куб. см.\nDaewoo Lanos\n2006\n1300 куб. см.\nFiat Doblo\n2006\n1000\nЛьвівська область\nм. Старий Самбір\n36\nм. Старий Самбір\nЛьвівська область\nм. Старий Самбір\nЛьвівська область\n100\n48.6\nЛьвівська область\nм. Старий Самбір\n25\nм. Старий Самбір\nЛьвівська область\nПодружжя\nШкрамко В. М., 03. 05. 1956\nДитина\nШкрамко Ю. В., 02. 09. 1987\nЛойзик Марія Василівна\nМарія Василівна Лойзик\nМарія Лойзик\nЛойзик Марія Василівна\nЛойзик Марія Василівна\nМарія\nЛойзик\nЗагальний місцевий суд\nсуддя старосамбірського районного суду львівської області\nЛьвівська область\nВасилівна\n249918\n81115\n64928\n12588\n314846\n93703\n12180\n2202\n205313\n20649\n94195\n2014\n81115\n249918\n2202\n12180\n93703\n314846\n12588\n64928\nПодружжя\nШкрамко В. М., 03. 05. 1956\nДитина\nШкрамко Ю. В., 02. 09. 1987\nВасилівна\nЛойзик\nМарія\nЛойзик Марія Василівна\nМарія Василівна Лойзик\nМарія Лойзик\nЛойзик Марія Василівна\nЛьвівська область\nЗагальний місцевий суд\nсуддя старосамбірського районного суду львівської області\nЛойзик Марія Василівна\n2006\nDaewoo Lanos\n1500 куб. см.\nFiat Doblo\n1300 куб. см.\n2006\n12180\n2202\n12588\n64928\n93703\n314846\n249918\n81115\nм. Старий Самбір\nЛьвівська область\n48.6\nм. Старий Самбір\nЛьвівська область\n1000\nм. Старий Самбір\nЛьвівська область\n25\nЛьвівська область\nм. Старий Самбір\n36\nм. Старий Самбір\nЛьвівська область\n100\n205313\n20649\n94195\n2014","general":{"inn":"","name":"Марія","patronymic_unclear":false,"family":[{"inn":"","relations":"Подружжя","inn_unclear":false,"relations_hidden":false,"inn_hidden":false,"relations_other":"","name_hidden":false,"family_name":"Шкрамко В. М., 03. 05. 1956","name_unclear":false},{"inn":"","relations":"Дитина","inn_unclear":false,"relations_hidden":false,"inn_hidden":true,"relations_other":"","name_hidden":false,"family_name":"Шкрамко Ю. В., 02. 09. 1987","name_unclear":false}],"patronymic":"Василівна","inn_hidden":true,"family_raw":"","inn_unclear":false,"post":{"post_unclear":false,"post":"суддя старосамбірського районного суду львівської області","office_hidden":false,"region":"Львівська область","office":"Загальний місцевий суд","office_unclear":false,"region_hidden":false},"full_name":"Лойзик Марія Василівна","addresses":[{"place_district":"","place_address_hidden":true,"place_city":"","place_city_type_hidden":true,"place_district_hidden":true,"place_city_type":"","place_city_hidden":true,"place_address_unclear":false,"place_address":"","place_hidden":true,"place":""}],"last_name":"Лойзик","full_name_suggest":{"output":"Лойзик Марія Василівна","input":["Лойзик Марія Василівна","Марія Василівна Лойзик","Марія Лойзик"]}},"source":"VULYK","estate":{"23":[{"region_unclear":false,"space_unclear":false,"costs":"","costs_comment":"","address_hidden":true,"region_hidden":false,"space_comment":"","space":"1000","address":"м. Старий Самбір","region":"Львівська область","costs_rent_comment":"","space_units":"м²","costs_rent":""}],"25":[{"space_hidden":false,"costs":"","costs_comment":"","address_hidden":true,"region_hidden":false,"space_comment":"","space":"48.6","address":"м. Старий Самбір","region":"Львівська область","address_unclear":false,"costs_rent_comment":"","space_comment_unclear":false,"space_units":"м²","costs_rent":""}],"29":[{"space_unclear":false,"space_units_unclear":false,"address_hidden":true,"region_hidden":false,"space_comment":"","space_units_hidden":false,"space":"36","address":"м. Старий Самбір","region":"Львівська область","costs_property":"","costs_rent_comment":"","space_units":"м²","costs_property_comment":"","costs_rent":""},{"address_hidden":true,"region_hidden":false,"space_comment":"","space":"100","address":"м. Старий Самбір","region":"Львівська область","costs_property":"","costs_rent_comment":"","address_unclear":false,"space_units":"м²","costs_property_comment":"","costs_rent":""}],"33":[{"costs_rent":"","region":"Львівська область","costs_property":"","costs_rent_comment":"","address_hidden":false,"region_hidden":false,"space_comment":"","costs_property_comment":"","space_units":"м²","space":"25","address":"м. Старий Самбір"}]},"intro":{"declaration_year":"2014","isnotdeclaration":""}}