{"income":{"5":{"value":"182684","family_comment":"","value_unclear":true,"family_unclear":false,"family":"","comment":""},"6":{"value":"182684","family_comment":"","value_unclear":false,"family_unclear":false,"family":"","comment":""},"7":{"family_comment":"","value":"","source_name":"Донецький окружний адміністративний суд","family":"","comment":""},"8":{"family_comment":"","value":"","family":"","comment":""},"9":{"family_comment":"","value":"","value_unclear":false,"family":"","comment":""},"10":{"family_comment":"","value":"","value_unclear":false,"family":"","comment":""},"11":{"family_comment":"","value":"","family":"","comment":""},"12":{"family_comment":"","value":"","family":"","comment":""},"13":{"family_comment":"","value":"","value_unclear":false,"family":"","comment":""},"14":{"family_comment":"","value":"","family":"","comment":""},"15":{"family_comment":"","value":"","family":"","comment":""},"16":{"family_comment":"","value":"","family":"","comment":""},"17":{"family_comment":"","value":"","family":"","comment":""},"18":{"family_comment":"","value":"","family":"","comment":""},"19":{"family_comment":"","value":"","family":"","comment":""},"20":{"family_comment":"","family_unclear":false,"value":"","family":"","comment":""}},"id":"vulyk_85_51","declaration":{"additional_info_text":"","notfull_lostpages":"","date":"2015-03-31T00:00:00","notfull":"","additional_info":"","url":"http://static.declarations.com.ua/declarations/chosen_ones/judges_batch/2654_kravchenko_tetiana_oleksandrivna.pdf"},"liabilities":{"54":{"sum_foreign_comment":"","sum":"","sum_comment":"","sum_comment_unclear":false,"sum_foreign":""},"55":{"sum_foreign_comment":"","sum":"","sum_comment":"","sum_foreign":""},"56":{"sum_foreign_comment":"","sum":"","sum_comment":"","sum_unclear":false,"sum_foreign":""},"57":{"sum_foreign_comment":"","sum":"","sum_comment":"","sum_foreign":""},"58":{"sum_foreign_comment":"","sum_comment_hidden":false,"sum":"","sum_comment":"","sum_foreign":""},"59":{"sum_foreign_comment":"","sum":"","sum_comment":"","sum_foreign":""},"60":{"sum_foreign_comment":"","sum":"","sum_comment":"","sum_foreign":""},"61":{"sum_foreign_comment":"","sum":"","sum_comment":"","sum_foreign":""},"62":{"sum_foreign_comment":"","sum":"","sum_comment":"","sum_unclear":false,"sum_foreign":""},"63":{"sum_foreign_comment":"","sum":"","sum_comment":"","sum_unclear":false,"sum_foreign":""},"64":{"sum_foreign_comment":"","sum":"","sum_comment":"","sum_foreign":""}},"ft_src":"суддя донецького окружного адміністративного суду\nДонецька область\nАдміністративний місцевий суд\nТетяна\nОлександрівна\nКравченко\nКравченко Тетяна Олександрівна\nКравченко Тетяна Олександрівна\nТетяна Олександрівна Кравченко\nТетяна Кравченко\nКравченко Тетяна Олександрівна\n182684\nДонецький окружний адміністративний суд\n182684\n2014\n182684\nДонецький окружний адміністративний суд\n182684\nДонецький окружний адміністративний суд\n182684\n182684\nАдміністративний місцевий суд\nсуддя донецького окружного адміністративного суду\nДонецька область\nКравченко Тетяна Олександрівна\nТетяна Олександрівна Кравченко\nТетяна Кравченко\nКравченко Тетяна Олександрівна\nТетяна\nКравченко Тетяна Олександрівна\nКравченко\nОлександрівна\n2014\nОлександрівна\nКравченко\nТетяна\nКравченко Тетяна Олександрівна\nТетяна Олександрівна Кравченко\nТетяна Кравченко\nКравченко Тетяна Олександрівна\nсуддя донецького окружного адміністративного суду\nДонецька область\nАдміністративний місцевий суд\nКравченко Тетяна Олександрівна\n2014","general":{"inn":"","name":"Тетяна","last_name_hidden":false,"patronymic":"Олександрівна","inn_hidden":true,"family_raw":"","last_name":"Кравченко","post":{"post_unclear":false,"post_hidden":false,"post":"суддя донецького окружного адміністративного суду","region":"Донецька область","office":"Адміністративний місцевий суд"},"full_name_suggest":{"output":"Кравченко Тетяна Олександрівна","input":["Кравченко Тетяна Олександрівна","Тетяна Олександрівна Кравченко","Тетяна Кравченко"]},"full_name":"Кравченко Тетяна Олександрівна","addresses":[{"place_district":"","place_city_hidden":true,"place_city":"","place_city_type_hidden":false,"place_district_hidden":false,"place_city_type":"","place_address_hidden":true,"place_address":"","place_hidden":true,"place":""}],"last_name_unclear":false},"source":"VULYK","intro":{"declaration_year":"2014","isnotdeclaration":""}}