{"income":{"5":{"value":"338710.9","family_unclear":false,"family_hidden":false,"family_comment":"","family":"75737.38","comment":""},"6":{"family_comment":"","value":"269404.82","family_hidden":false,"comment":"","family":"75737.38"},"7":{"family_comment":"","value":"3765.86","source_name":"Дніпропетровське регіональне відділення Національної школи суддів","family":"","comment":""},"8":{"family_comment":"","value":"","family":"","comment":""},"9":{"value":"","comment_unclear":false,"family_hidden":false,"family_comment":"","family":"","comment":""},"10":{"family_comment":"","value":"","family":"","comment":""},"11":{"family_comment":"","value":"","family":"","comment":""},"12":{"family_comment":"","value":"","family":"","comment":""},"13":{"family_comment":"","value":"","family":"","comment":""},"14":{"family_comment":"","value":"","family":"","comment":""},"15":{"family_comment":"","value":"","value_unclear":false,"family":"","comment":""},"16":{"family_comment":"","value":"","family":"","comment":""},"17":{"family_comment":"","value":"","family":"","comment":""},"18":{"family_comment":"","value":"","family":"","comment":""},"19":{"family_comment":"","value":"","family":"","comment":""},"20":{"value":"65540.22","comment_unclear":false,"comment_hidden":false,"family_hidden":false,"value_hidden":false,"family_comment":"","value_unclear":false,"family":"","comment":"пенсія за віком","family_comment_hidden":false}},"vehicle":{"40":[{"brand_info":"1998 куб. см., 147 к. с","sum_rent_comment":"","brand":"Mazda 6","sum_comment":"","year":"2007","brand_info_hidden":false,"sum":"","sum_rent":""}]},"id":"vulyk_41_136","banks":{"45":[{"sum_foreign_comment":"","sum_units":"UAH","sum_comment":"","sum_foreign_unclear":false,"sum_foreign_units":"UAH","sum_hidden":false,"sum_comment_hidden":false,"sum":"","sum_foreign":""},{"sum_foreign_comment":"","sum_units":"","sum_comment":"","sum_foreign_unclear":false,"sum_foreign_units":"","sum":"","sum_foreign":""}],"46":[{"sum_foreign_comment":"","sum_units":"UAH","sum_comment":"","sum_foreign_units":"UAH","sum_comment_hidden":false,"sum_unclear":false,"sum":"","sum_foreign":""},{"sum_foreign_comment":"","sum_units":"","sum_comment":"","sum_foreign_units":"","sum":"","sum_unclear":false,"sum_foreign":""}],"47":[{"sum_foreign_comment":"","sum_units":"UAH","sum_comment":"","sum_foreign_units":"UAH","sum":"","sum_foreign":""},{"sum_foreign_comment":"","sum_units":"","sum_comment":"","sum_foreign_units":"","sum":"","sum_foreign":""}],"48":[{"sum_foreign_comment":"","sum_units":"UAH","sum_comment":"","sum_foreign_units":"UAH","sum":"","sum_foreign":""}],"49":[{"sum_foreign_comment":"","sum_units":"UAH","sum_comment":"","sum_foreign_units":"UAH","sum":"","sum_foreign":""}],"50":[{"sum_foreign_comment":"","sum_units":"UAH","sum_comment":"","sum_foreign_units":"UAH","sum":"","sum_foreign":""}],"51":[{"sum_foreign_comment":"","sum_units":"UAH","sum_comment":"","sum_hidden":false,"sum_foreign_units":"UAH","sum_comment_hidden":false,"sum_unclear":false,"sum":"","sum_foreign":""},{"sum_foreign_comment":"","sum_units":"","sum_comment":"","sum_foreign_units":"","sum":"","sum_foreign":""}],"52":[{"sum_foreign_comment":"","sum_units":"UAH","sum_comment":"","sum_foreign_units":"UAH","sum_comment_hidden":false,"sum_unclear":false,"sum":"","sum_foreign":""}],"53":[{"sum_foreign_comment":"","sum_units":"UAH","sum_comment":"","sum_foreign_units":"UAH","sum_comment_hidden":false,"sum":"","sum_foreign":""},{"sum_foreign_comment":"","sum_units":"","sum_comment":"","sum_foreign_units":"","sum":"","sum_foreign":""},{"sum_foreign_comment":"","sum_units":"","sum_comment":"","sum_foreign_units":"","sum":"","sum_foreign":""}]},"declaration":{"date":"2015-03-30T00:00:00","additional_info_text":"","additional_info":"","url":"http://static.declarations.com.ua/declarations/chosen_ones/mega_batch/chernus_kateryna_petrivna.pdf"},"liabilities":{"54":{"sum_foreign_comment":"","sum_comment_hidden":false,"sum":"","sum_comment":"","sum_foreign":""},"55":{"sum_foreign_comment":"","sum":"","sum_comment":"","sum_foreign":""},"56":{"sum_foreign_comment":"","sum":"70000","sum_hidden":false,"sum_comment":"","sum_foreign":""},"57":{"sum_foreign_comment":"","sum":"46497","sum_comment":"","sum_comment_hidden":false,"sum_unclear":false,"sum_foreign":""},"58":{"sum_foreign_comment":"","sum_comment_hidden":false,"sum":"6154.58","sum_comment":"","sum_foreign":""},"59":{"sum_foreign_comment":"","sum":"","sum_comment":"","sum_foreign":""},"60":{"sum_foreign_comment":"","sum_comment_hidden":false,"sum":"","sum_comment":"","sum_foreign":""},"61":{"sum_foreign_comment":"","sum":"","sum_comment":"","sum_foreign":""},"62":{"sum_foreign_comment":"","sum":"","sum_comment":"","sum_foreign":""},"63":{"sum_foreign_comment":"","sum":"","sum_comment":"","sum_comment_hidden":false,"sum_unclear":false,"sum_foreign":""},"64":{"sum_foreign_comment":"","sum_comment_hidden":false,"sum":"","sum_comment":"","sum_foreign":""}},"ft_src":"46497\n6154.58\n70000\nсуддя апеляційного суду дніпропетровської області\nДніпропетровська область\nЗагальний апеляційний суд\nКатерина\nЧернусь П. О\nДитина\nЧернусь Ю. М\nІнше\nневістка\nПетрівна\nЧернусь Катерина Петрівна\nКатерина Петрівна Чернусь\nКатерина Чернусь\nЧернусь Катерина Петрівна\nЧернусь\nЧернусь Катерина Петрівна\n1998 куб. см., 147 к. с\n2007\nMazda 6\n2014\nMazda 6\n1998 куб. см., 147 к. с\n2007\n28.8\n1/2 част.\n28.8\n1/2 част.\nДитина\nЧернусь П. О\nІнше\nневістка\nЧернусь Ю. М\nЧернусь Катерина Петрівна\nКатерина Петрівна Чернусь\nКатерина Чернусь\nЧернусь Катерина Петрівна\nЧернусь Катерина Петрівна\nКатерина\nПетрівна\nЗагальний апеляційний суд\nсуддя апеляційного суду дніпропетровської області\nДніпропетровська область\nЧернусь\n46497\n70000\n6154.58\nДніпропетровське регіональне відділення Національної школи суддів\n3765.86\n269404.82\n75737.38\nпенсія за віком\n65540.22\n338710.9\n75737.38\n2014\n6154.58\n46497\n70000\n1/2 част.\n28.8\n1/2 част.\n28.8\nЧернусь П. О\nДитина\nневістка\nЧернусь Ю. М\nІнше\nПетрівна\nЧернусь\nКатерина\nЧернусь Катерина Петрівна\nКатерина Петрівна Чернусь\nКатерина Чернусь\nЧернусь Катерина Петрівна\nДніпропетровська область\nсуддя апеляційного суду дніпропетровської області\nЗагальний апеляційний суд\nЧернусь Катерина Петрівна\n75737.38\n269404.82\n3765.86\nДніпропетровське регіональне відділення Національної школи суддів\n75737.38\n338710.9\nпенсія за віком\n65540.22\nMazda 6\n1998 куб. см., 147 к. с\n2007\n65540.22\nпенсія за віком\n338710.9\n75737.38\nДніпропетровське регіональне відділення Національної школи суддів\n3765.86\n75737.38\n269404.82\n1/2 част.\n28.8\n1/2 част.\n28.8\n2014","general":{"inn":"","name":"Катерина","family":[{"inn":"","relations":"Дитина","relations_hidden":false,"inn_hidden":true,"family_name":"Чернусь П. О","name_hidden":true,"name_unclear":false},{"inn":"","relations":"Інше","relations_other":"невістка","inn_hidden":false,"family_name":"Чернусь Ю. М","name_hidden":false,"name_unclear":false}],"patronymic":"Петрівна","inn_hidden":true,"family_raw":"","last_name":"Чернусь","post":{"post_unclear":false,"post":"суддя апеляційного суду дніпропетровської області","post_hidden":false,"region":"Дніпропетровська область","region_hidden":false,"office":"Загальний апеляційний суд","office_hidden":false},"last_name_unclear":false,"full_name":"Чернусь Катерина Петрівна","addresses":[{"place_district":"","place_city_hidden":true,"place_city":"","place_city_type_hidden":false,"place_district_hidden":false,"place_city_type":"","place_address_hidden":true,"place_address":"","place_hidden":true,"place":""}],"patronymic_hidden":false,"full_name_suggest":{"output":"Чернусь Катерина Петрівна","input":["Чернусь Катерина Петрівна","Катерина Петрівна Чернусь","Катерина Чернусь"]},"name_unclear":false},"source":"VULYK","estate":{"23":[{"region_unclear":false,"space_unclear":false,"costs":"","costs_comment":"","address_hidden":false,"region_hidden":false,"space_comment":"","space":"","address":"","costs_comment_unclear":false,"region":"","space_units_unclear":false,"space_comment_hidden":false,"space_units":"м²","costs_rent":"","costs_rent_comment":""},{"costs_rent":"","space_unclear":false,"region":"","costs":"","costs_rent_comment":"","costs_comment":"","space_comment":"","space_units":"","space":"","address":""},{"costs_rent":"","region":"","costs":"","costs_rent_comment":"","costs_comment":"","space_comment":"","space_units":"","space":"","address":""}],"25":[{"region_unclear":false,"space_hidden":false,"costs":"","costs_comment":"","address_hidden":true,"region_hidden":true,"space_comment":"1/2 част.","space_unclear":false,"space":"28.8","address":"","costs_comment_unclear":false,"region":"","costs_rent_comment":"","costs_unclear":false,"space_units":"м²","costs_rent":""}],"31":[{"space_hidden":false,"address_hidden":true,"region_hidden":true,"space_comment":"1/2 част.","space":"28.8","address":"","region":"","costs_property":"","costs_rent_comment":"","space_comment_unclear":false,"space_units":"м²","costs_property_comment":"","costs_rent":""}]},"intro":{"declaration_year":"2014"}}