{"income":{"5":{"family_comment":"","family_unclear":false,"value":"268693","family":"36401","comment":""},"6":{"value":"234982","family_comment":"","comment_unclear":false,"family_unclear":false,"family":"14616","comment":""},"7":{"source_name_unclear":false,"value":"","family_comment":"","source_name":"","family":"","comment":"","source_name_hidden":false},"8":{"family_comment":"","value":"","family":"","comment":""},"9":{"family_comment":"","value":"","family":"","comment":""},"10":{"family_comment":"","value":"13398","comment_unclear":false,"family":"","comment":""},"11":{"family_comment":"","value":"","family":"","comment":""},"12":{"family_comment":"","value":"","family":"","comment":""},"13":{"family_comment":"","value":"6000","family":"","comment":""},"14":{"family_comment":"","value":"10210","family":"","comment":""},"15":{"family_comment":"","value":"3153","family":"","comment":"ремонт авто"},"16":{"value":"","comment_hidden":false,"value_hidden":false,"family_comment":"","family":"","comment":"","family_comment_unclear":false},"17":{"family_comment":"","value":"","family":"","comment":""},"18":{"family_comment":"","value":"","family":"","comment":""},"19":{"family_comment":"","value":"","family":"","comment":""},"20":{"value":"950","family_comment":"","value_unclear":false,"family":"21785","family_unclear":false,"comment_unclear":false,"comment":"","family_comment_unclear":false}},"vehicle":{"35":[{"brand_info":"1400 куб. см.","sum_rent_comment":"","year":"2013","sum_rent_unclear":false,"brand_info_hidden":false,"brand_info_unclear":false,"sum_rent":"","sum":"","brand":"Kia Rio","sum_comment":"","sum_comment_unclear":false,"brand_hidden":false,"sum_unclear":false,"brand_unclear":false},{"brand_info":"","sum_rent_comment":"","brand":"ВАЗ 21011","sum_comment":"","brand_unclear":false,"year":"1980","sum_hidden":false,"brand_info_hidden":false,"sum":"","sum_rent":""}],"40":[{"year_hidden":false,"brand_info":"2500 куб. см.","sum_rent_comment":"","year":"1991","brand_info_hidden":false,"brand_info_unclear":false,"sum_rent":"","sum":"","brand":"ГАЗ 2410 Волга","sum_comment":"","brand_hidden":false,"sum_unclear":false}]},"id":"vulyk_58_136","banks":{"45":[{"sum_foreign_comment":"","sum_units":"UAH","sum_comment":"","sum_comment_unclear":false,"sum_hidden":false,"sum_foreign_units":"UAH","sum_comment_hidden":false,"sum_units_hidden":false,"sum":"","sum_foreign":""},{"sum_foreign_comment":"","sum_units":"","sum_comment":"","sum_foreign_units":"","sum":"","sum_foreign":""}],"46":[{"sum_foreign_comment":"","sum_units":"UAH","sum_comment":"","sum_foreign_units":"UAH","sum_comment_hidden":false,"sum":"","sum_foreign":""}],"47":[{"sum_foreign_comment":"","sum_units":"UAH","sum_comment":"","sum_foreign_units":"UAH","sum_comment_hidden":false,"sum":"","sum_foreign":""}],"48":[{"sum_foreign_comment":"","sum_units":"UAH","sum_comment":"","sum_foreign_units":"UAH","sum":"","sum_foreign":""}],"49":[{"sum_foreign_comment":"","sum_units":"UAH","sum_comment":"","sum_foreign_units":"UAH","sum":"","sum_foreign":""}],"50":[{"sum_foreign_comment":"","sum_units":"UAH","sum_comment":"","sum_foreign_units":"UAH","sum":"","sum_foreign":""}],"51":[{"sum_foreign_comment":"","sum_units":"UAH","sum_comment":"","sum_foreign_units":"UAH","sum_comment_hidden":false,"sum":"","sum_foreign":""},{"sum_foreign_comment":"","sum_units":"","sum_comment":"","sum_comment_hidden":false,"sum":"","sum_foreign":""}],"52":[{"sum_foreign_comment":"","sum_units":"UAH","sum_comment":"","sum_foreign_units":"UAH","sum":"","sum_foreign":""}],"53":[{"sum_foreign_comment":"","sum_units":"UAH","sum_comment":"","sum_foreign_units":"UAH","sum":"","sum_foreign":""}]},"declaration":{"additional_info_text":"","notfull_lostpages":"","date":"2015-03-24T00:00:00","notfull":"","additional_info":"","url":"http://static.declarations.com.ua/declarations/chosen_ones/mega_batch/halatsevych_oksana_mykolaivna.pdf"},"liabilities":{"54":{"sum_foreign_comment":"","sum":"4462","sum_hidden":false,"sum_comment":"","sum_foreign":""},"55":{"sum_foreign_comment":"","sum":"","sum_hidden":false,"sum_comment":"","sum_foreign":""},"56":{"sum_foreign_comment":"","sum":"","sum_comment":"","sum_unclear":false,"sum_foreign":""},"57":{"sum_foreign_comment":"","sum":"","sum_comment":"","sum_comment_unclear":false,"sum_comment_hidden":false,"sum_unclear":false,"sum_foreign":""},"58":{"sum_foreign_comment":"","sum":"","sum_comment":"","sum_comment_unclear":false,"sum_comment_hidden":false,"sum_unclear":false,"sum_foreign":""},"59":{"sum_foreign_comment":"","sum":"","sum_comment":"","sum_foreign":""},"60":{"sum_foreign_comment":"","sum":"","sum_comment":"","sum_comment_unclear":false,"sum_unclear":false,"sum_foreign":""},"61":{"sum_foreign_comment":"","sum":"","sum_comment":"","sum_foreign":""},"62":{"sum_foreign_comment":"","sum":"","sum_comment":"","sum_foreign":""},"63":{"sum_foreign_comment":"","sum":"","sum_comment":"","sum_comment_unclear":false,"sum_comment_hidden":false,"sum_unclear":false,"sum_foreign":""},"64":{"sum_foreign_comment":"","sum":"","sum_comment":"","sum_comment_unclear":false,"sum_comment_hidden":false,"sum_unclear":false,"sum_foreign":""}},"ft_src":"4462\nсуддя апеляційного суду житомирської області\nЖитомирська область\nЗагальний апеляційний суд\nОксана\nДитина\nБатьки\nМиколаївна\nГалацевич Оксана Миколаївна\nОксана Миколаївна Галацевич\nОксана Галацевич\nГалацевич Оксана Миколаївна\nГалацевич Оксана Миколаївна\nГалацевич\n1400 куб. см.\nKia Rio\n2013\n1980\nВАЗ 21011\n2500 куб. см.\nГАЗ 2410 Волга\n1991\n2014\n1400 куб. см.\nKia Rio\n2013\n1980\nВАЗ 21011\n2500 куб. см.\nГАЗ 2410 Волга\n1991\nприватизована у 2014 році\n1500\nЖитомирська область\nЖитомирський район, с. Рудня Пошта\n506\nЖитомирська область\nм. Житомир\n1200\nЖитомирська область\nЖитомирський район\n119.7\nЖитомирська область\nс. Рудня Пошта Житомирського р-ну\n301\nЖитомирська область\nм. Житомир\nДитина\nБатьки\nГалацевич Оксана Миколаївна\nОксана Миколаївна Галацевич\nОксана Галацевич\nГалацевич Оксана Миколаївна\nГалацевич Оксана Миколаївна\nОксана\nМиколаївна\nЗагальний апеляційний суд\nсуддя апеляційного суду житомирської області\nЖитомирська область\nГалацевич\n4462\n234982\n14616\n6000\n950\n21785\nремонт авто\n3153\n10210\n268693\n36401\n13398\n2014\n4462\nприватизована у 2014 році\nЖитомирський район, с. Рудня Пошта\n1500\nЖитомирська область\nм. Житомир\nЖитомирська область\n301\nм. Житомир\nЖитомирська область\n506\nЖитомирська область\nЖитомирський район\n1200\nс. Рудня Пошта Житомирського р-ну\n119.7\nЖитомирська область\nДитина\nБатьки\nМиколаївна\nГалацевич\nОксана\nГалацевич Оксана Миколаївна\nОксана Миколаївна Галацевич\nОксана Галацевич\nГалацевич Оксана Миколаївна\nЖитомирська область\nсуддя апеляційного суду житомирської області\nЗагальний апеляційний суд\nГалацевич Оксана Миколаївна\n14616\n234982\n10210\nремонт авто\n3153\n6000\n13398\n36401\n268693\n21785\n950\n2013\nKia Rio\n1400 куб. см.\n1980\nВАЗ 21011\nГАЗ 2410 Волга\n2500 куб. см.\n1991\nремонт авто\n3153\n10210\n13398\n950\n21785\n36401\n268693\n234982\n14616\n6000\nм. Житомир\nЖитомирська область\n301\nприватизована у 2014 році\nЖитомирський район, с. Рудня Пошта\nЖитомирська область\n1500\nс. Рудня Пошта Житомирського р-ну\nЖитомирська область\n119.7\nм. Житомир\nЖитомирська область\n506\nЖитомирський район\nЖитомирська область\n1200\n2014","general":{"inn":"","name":"Оксана","inn_unclear":false,"family":[{"inn":"","inn_hidden":true,"relations_hidden":false,"family_name":"","relations_other":"","relations":"Дитина","name_hidden":true,"name_unclear":false},{"inn":"","inn_hidden":false,"relations_hidden":false,"family_name":"","relations_other":"","relations":"Батьки","name_hidden":false,"name_unclear":false}],"inn_hidden":true,"family_raw":"","last_name":"Галацевич","post":{"post_unclear":false,"post":"суддя апеляційного суду житомирської області","post_hidden":false,"region":"Житомирська область","region_hidden":false,"office":"Загальний апеляційний суд","office_hidden":false,"office_unclear":false},"full_name_suggest":{"output":"Галацевич Оксана Миколаївна","input":["Галацевич Оксана Миколаївна","Оксана Миколаївна Галацевич","Оксана Галацевич"]},"full_name":"Галацевич Оксана Миколаївна","addresses":[{"place_city_type_hidden":true,"place_district_hidden":true,"place_city_type":"","place_city_hidden":true,"place_address_unclear":false,"place_address":"","place_hidden":true,"place":"","place_district":"","place_unclear":false,"place_city":"","place_address_hidden":true,"place_district_unclear":false}],"patronymic":"Миколаївна","last_name_unclear":false},"source":"VULYK","estate":{"23":[{"space_unclear":false,"costs":"","costs_comment":"","address_hidden":true,"region_hidden":false,"space_comment":"приватизована у 2014 році","space_hidden":false,"space":"1500","address":"Житомирський район, с. Рудня Пошта","costs_comment_unclear":false,"costs_rent_comment_unclear":false,"region":"Житомирська область","address_unclear":true,"costs_rent_comment":"","costs_unclear":false,"space_units":"м²","costs_rent":""},{"costs":"","costs_comment":"","address_hidden":false,"region_hidden":false,"space_comment":"","space":"","address":"","region":"","address_unclear":false,"costs_rent_comment":"","space_units":"","costs_rent":""},{"costs":"","costs_comment":"","address_hidden":false,"region_hidden":false,"space_comment":"","space":"","address":"","region":"","address_unclear":false,"costs_rent_comment":"","space_units":"","costs_rent":""},{"costs_rent":"","region":"","costs":"","costs_rent_comment":"","costs_comment":"","space_comment":"","space_units":"","space":"","address":""},{"costs_rent":"","costs":"","costs_rent_comment":"","costs_comment":"","space_comment":"","space_units":"","space":"","address":""}],"24":[{"space_unclear":false,"costs":"","costs_comment":"","address_hidden":true,"region_hidden":false,"space_comment":"","space_hidden":false,"space":"119.7","address":"с. Рудня Пошта Житомирського р-ну","costs_comment_unclear":false,"costs_unclear":false,"region":"Житомирська область","address_unclear":true,"costs_rent_comment":"","space_comment_unclear":false,"space_units":"м²","costs_rent":""}],"29":[{"space_unclear":false,"address_hidden":true,"region_hidden":false,"space_comment":"","space_hidden":false,"space":"506","address":"м. Житомир","region":"Житомирська область","costs_property":"","costs_rent_comment":"","address_unclear":false,"space_units":"м²","costs_property_comment":"","costs_rent":""},{"costs_rent":"","region":"Житомирська область","costs_property":"","costs_rent_comment":"","address_hidden":true,"region_hidden":false,"space_comment":"","costs_property_comment":"","space_units":"м²","space":"1200","address":"Житомирський район"}],"30":[{"space_hidden":false,"address_hidden":true,"region_hidden":false,"space_comment":"","space":"301","address":"м. Житомир","region":"Житомирська область","costs_property":"","costs_rent_comment":"","address_unclear":false,"space_units":"м²","costs_property_comment":"","costs_rent":""}]},"intro":{"declaration_year":"2014","isnotdeclaration":"","declaration_year_hidden":false}}