{"income":{"5":{"value":"376508","family_comment":"","value_unclear":false,"family":"","family_unclear":false,"comment_unclear":false,"comment":"","family_comment_unclear":false},"6":{"value":"227207","family_comment":"","value_unclear":false,"family_unclear":false,"family":"","comment":""},"7":{"source_name_unclear":false,"value":"7401","value_unclear":false,"family_comment":"","source_name":"","family":"","comment":"","source_name_hidden":true},"8":{"family_comment":"","value":"","family":"","comment":""},"9":{"family_comment":"","value":"","family":"","comment":""},"10":{"family_comment":"","value":"12180","value_unclear":false,"family":"","comment":""},"11":{"value":"","value_unclear":false,"value_hidden":true,"family_comment":"","family":"","comment":""},"12":{"family_comment":"","value":"","family":"","comment":"","value_hidden":true},"13":{"family_comment":"","value":"","family":"","comment":""},"14":{"family_comment":"","value":"","family":"","comment":""},"15":{"family_comment":"","value":"","family":"","comment":""},"16":{"family_comment":"","value":"120000","family":"","comment":""},"17":{"family_comment":"","value":"","family":"","comment":""},"18":{"family_comment":"","value":"","family":"","comment":""},"19":{"family_comment":"","family_unclear":false,"value":"","family":"","comment":""},"20":{"family_comment":"","family_unclear":false,"value":"","family":"","comment":""}},"vehicle":{"35":[{"year_hidden":false,"brand_info":"","sum_rent_comment":"","year":"2007","sum_hidden":false,"brand_info_hidden":true,"brand_info_unclear":false,"year_unclear":false,"sum_rent":"","sum":"","brand":"","sum_comment":"","brand_unclear":false,"brand_hidden":true}],"40":[{"brand_info":"","sum":"","brand":"","sum_comment":"","brand_unclear":false,"year":"2013","brand_hidden":true,"brand_info_hidden":true,"brand_info_unclear":false,"sum_rent_comment":"","sum_rent":""},{"brand_info":"","sum_rent_comment":"","brand":"","sum_comment":"","brand_unclear":false,"year":"2004","brand_info_unclear":false,"sum":"","sum_rent":""}]},"id":"vulyk_61_74","declaration":{"additional_info_text":"Більшість інформації приховано","notfull_lostpages":"","date":"2015-03-30T00:00:00","notfull":"","additional_info":"1","url":"http://static.declarations.com.ua/declarations/chosen_ones/mega_batch/shtykh_tetiana_vasylivna.pdf"},"liabilities":{"54":{"sum_foreign_comment":"","sum":"","sum_comment":"","sum_comment_unclear":false,"sum_unclear":false,"sum_foreign":""},"55":{"sum_foreign_comment":"","sum":"","sum_comment":"","sum_foreign":""},"56":{"sum_foreign_comment":"","sum":"","sum_comment":"","sum_unclear":false,"sum_foreign":""},"57":{"sum_foreign_comment":"","sum":"","sum_comment":"","sum_comment_hidden":false,"sum_unclear":false,"sum_foreign":""},"58":{"sum_foreign_comment":"","sum":"","sum_comment":"","sum_unclear":false,"sum_foreign":""},"59":{"sum_foreign_comment":"","sum":"","sum_comment":"","sum_foreign":""},"60":{"sum_foreign_comment":"","sum_foreign_hidden":false,"sum_comment":"","sum_hidden":false,"sum":"","sum_foreign":""},"61":{"sum_foreign_comment":"","sum":"","sum_comment":"","sum_foreign":""},"62":{"sum_foreign_comment":"","sum":"","sum_comment":"","sum_unclear":false,"sum_foreign":""},"63":{"sum_foreign_comment":"","sum":"","sum_comment":"","sum_hidden":false,"sum_unclear":false,"sum_foreign":""},"64":{"sum_foreign_comment":"","sum":"","sum_hidden":false,"sum_comment":"","sum_foreign":""}},"ft_src":"Більшість інформації приховано\n1\nсуддя дзержинського районного суду м. харкова\nХарківська область\nЗагальний місцевий суд\nТетяна\nВолкодав Г. І\nПодружжя\nВолкодав І. Г\nДитина\nВасилівна\nШтих\nШтих Тетяна Василівна\nШтих Тетяна Василівна\nТетяна Василівна Штих\nТетяна Штих\nШтих Тетяна Василівна\n2007\n2013\n2004\n70\n1\nБільшість інформації приховано\n2014\n227207\n12180\n7401\n376508\n120000\n2007\n2013\n2004\nБільшість інформації приховано\n1\n70\nПодружжя\nВолкодав Г. І\nДитина\nВолкодав І. Г\nШтих Тетяна Василівна\nТетяна Василівна Штих\nТетяна Штих\nШтих Тетяна Василівна\nТетяна\nШтих Тетяна Василівна\nШтих\nХарківська область\nЗагальний місцевий суд\nсуддя дзержинського районного суду м. харкова\nВасилівна\n7401\n227207\n376508\n120000\n12180\n2014\nВолкодав Г. І\nПодружжя\nВолкодав І. Г\nДитина\nВасилівна\nШтих\nШтих Тетяна Василівна\nТетяна Василівна Штих\nТетяна Штих\nШтих Тетяна Василівна\nХарківська область\nсуддя дзержинського районного суду м. харкова\nЗагальний місцевий суд\nШтих Тетяна Василівна\nТетяна\n2007\n2013\n2004\n12180\n376508\n120000\n7401\n227207\n70\n2014","general":{"inn":"","name":"Тетяна","patronymic_unclear":false,"family":[{"inn":"","inn_hidden":true,"relations_unclear":false,"relations_hidden":true,"relations_other":"","relations":"Подружжя","name_hidden":true,"family_name":"Волкодав Г. І","name_unclear":false},{"inn":"","relations":"Дитина","relations_other":"","inn_hidden":false,"family_name":"Волкодав І. Г","name_hidden":false,"name_unclear":false}],"patronymic":"Василівна","inn_hidden":true,"family_raw":"","inn_unclear":false,"post":{"post_unclear":false,"region_unclear":false,"post":"суддя дзержинського районного суду м. харкова","office":"Загальний місцевий суд","region":"Харківська область","post_hidden":false,"office_hidden":false,"region_hidden":false},"last_name_unclear":false,"full_name":"Штих Тетяна Василівна","addresses":[{"place_address":"","place_district_hidden":true,"place_city_type":"","place_city_hidden":true,"place_address_unclear":false,"place_city_type_hidden":true,"place_hidden":true,"place":"","place_district":"","place_address_hidden":true,"place_city":"","place_district_unclear":false}],"last_name":"Штих","patronymic_hidden":false,"full_name_suggest":{"output":"Штих Тетяна Василівна","input":["Штих Тетяна Василівна","Тетяна Василівна Штих","Тетяна Штих"]},"name_unclear":false},"source":"VULYK","estate":{"25":[{"region_unclear":false,"space_hidden":false,"costs":"","costs_comment":"","address_hidden":false,"region_hidden":false,"space_comment":"","space_unclear":false,"space":"70","address":"","costs_comment_unclear":false,"costs_unclear":false,"region":"","address_unclear":false,"costs_rent_comment":"","space_comment_unclear":false,"space_units":"м²","costs_rent":""}]},"intro":{"declaration_year":"2014","isnotdeclaration":"","declaration_year_hidden":true}}