{"income":{"5":{"family_comment":"","value":"312125","family":"407213","comment":""},"6":{"family_comment":"","value":"304148","family":"","comment":""},"7":{"value":"7977","comment_hidden":false,"value_hidden":false,"family_comment":"","source_name":"Національна школа суддів України, Центр перепідготовки та підвищення кваліфікації працівників юстиції","family":"","comment":"","source_name_hidden":false},"8":{"family_comment":"","value":"","family":"","comment":""},"9":{"value":"","comment_hidden":false,"family_comment":"","family":"","comment":"","family_comment_unclear":false},"10":{"family_comment":"","value":"","family":"","comment":""},"11":{"family_comment":"","value":"","comment_hidden":false,"family":"","comment":""},"12":{"family_comment":"","value":"","family":"","comment":""},"13":{"family_comment":"","value":"","family":"","comment":""},"14":{"family_comment":"","value":"","family":"","comment":""},"15":{"family_comment":"","value":"","family":"","comment":""},"16":{"family_comment":"","value":"","family":"","comment":""},"17":{"family_comment":"","value":"","family":"407213","comment":""},"18":{"family_comment":"","value":"","family":"","comment":""},"19":{"family_comment":"","value":"","family":"","comment":""},"20":{"family_comment":"","value":"","comment_hidden":false,"family":"","comment":""}},"vehicle":{"35":[{"brand_info":"XL 7, 2736 куб. см.","sum_rent_comment":"","brand":"Suzuki Grand Vitara","sum_comment":"","year":"2006","brand_info_unclear":false,"year_unclear":false,"sum":"","sum_rent":""}]},"id":"vulyk_102_143","banks":{"45":[{"sum_foreign_comment":"","sum_units":"UAH","sum_comment":"","sum_comment_unclear":false,"sum_hidden":false,"sum_foreign_units":"UAH","sum_comment_hidden":false,"sum_unclear":false,"sum":"330","sum_foreign":""}]},"declaration":{"date":"2016-03-21T00:00:00","additional_info_text":"","additional_info":"","url":"http://static.declarations.com.ua/declarations/chosen_ones/judges_batch/1217_hrek_borys_mykolaiovych.pdf"},"liabilities":{"54":{"sum_foreign_comment":"","sum":"","sum_comment":"","sum_hidden":false,"sum_comment_hidden":false,"sum_foreign":""},"55":{"sum_foreign_comment":"","sum":"","sum_comment":"","sum_foreign":""},"56":{"sum_foreign_comment":"","sum":"22000","sum_comment":"","sum_foreign":""},"57":{"sum_foreign_comment":"","sum_comment":"","sum":"","sum_comment_hidden":false,"sum_foreign":""},"58":{"sum_foreign_comment":"","sum_comment":"","sum":"","sum_comment_hidden":false,"sum_foreign":""},"59":{"sum_foreign_comment":"","sum_comment":"","sum":"","sum_comment_hidden":false,"sum_foreign":""},"60":{"sum_foreign_comment":"","sum":"","sum_comment":"","sum_hidden":false,"sum_comment_hidden":false,"sum_foreign":""},"61":{"sum_foreign_comment":"","sum":"","sum_comment":"","sum_foreign":""},"62":{"sum_foreign_comment":"","sum":"49000","sum_comment":"","sum_unclear":false,"sum_foreign":""},"63":{"sum_foreign_comment":"","sum":"","sum_comment":"","sum_hidden":false,"sum_comment_hidden":false,"sum_foreign":""},"64":{"sum_foreign_comment":"","sum_comment":"","sum":"","sum_comment_hidden":false,"sum_foreign":""}},"ft_src":"2006\nXL 7, 2736 куб. см.\nSuzuki Grand Vitara\n17.6\n1/2\n86.35\n237.8\n1421\nоренда\nоренда\n1872\n1/2\n106\n330\n2015\nXL 7, 2736 куб. см.\nSuzuki Grand Vitara\n2006\n2015\nГрек Борис Миколайович\nБорис Миколайович Грек\nБорис Грек\nГрек Борис Миколайович\nГрек Борис Миколайович\nБорис\nМиколайович\nсуддя вищого господарського суду україни\nЗагальнодержавний регіон\nВищий господарський суд\nГрек\nПодружжя\nГрек Анжеліка Василівна\n22000\n49000\n7977\nНаціональна школа суддів України, Центр перепідготовки та підвищення кваліфікації працівників юстиції\n304148\n407213\n312125\n407213\n17.6\n237.8\n86.35\n1/2\n106\n1/2\n1421\n1872\nоренда\nоренда\n330\n49000\n22000\n304148\nНаціональна школа суддів України, Центр перепідготовки та підвищення кваліфікації працівників юстиції\n7977\n407213\n312125\n407213\nГрек Анжеліка Василівна\nПодружжя\nБорис\nМиколайович\nГрек\nГрек Борис Миколайович\nБорис Миколайович Грек\nБорис Грек\nГрек Борис Миколайович\nсуддя вищого господарського суду україни\nЗагальнодержавний регіон\nВищий господарський суд\nГрек Борис Миколайович","general":{"inn":"","name":"Борис","family":[{"inn":"","relations":"Подружжя","name_hidden":true,"inn_hidden":true,"family_name":"Грек Анжеліка Василівна","name_unclear":false}],"patronymic":"Миколайович","inn_hidden":true,"family_raw":"","last_name":"Грек","post":{"region":"Загальнодержавний регіон","region_unclear":false,"post":"суддя вищого господарського суду україни","office_unclear":false,"office":"Вищий господарський суд"},"full_name":"Грек Борис Миколайович","addresses":[{"place_district":"","place_address_hidden":true,"place_city":"","place_address":"","place_district_hidden":false,"place_city_type":"","place_city_hidden":true,"place_city_type_hidden":false,"place_hidden":true,"place":""}],"patronymic_hidden":false,"full_name_suggest":{"output":"Грек Борис Миколайович","input":["Грек Борис Миколайович","Борис Миколайович Грек","Борис Грек"]}},"source":"VULYK","estate":{"25":[{"costs":"","costs_comment":"","address_hidden":false,"region_hidden":true,"space_comment":"1/2","space":"106","address":"","region":"","address_unclear":false,"costs_rent_comment":"","space_units":"м²","costs_rent":""}],"29":[{"address_hidden":false,"region_hidden":true,"space_comment":"","space":"1421","address":"","region":"","costs_property":"","costs_rent_comment":"","space_comment_hidden":false,"space_units":"м²","costs_property_comment":"","costs_rent":""},{"costs_rent":"","region":"","costs_property":"","costs_rent_comment":"оренда","address_hidden":false,"region_hidden":false,"space_comment":"оренда","costs_property_comment":"","space_units":"м²","space":"1872","address":""}],"30":[{"costs_rent":"","region":"","costs_property":"","costs_rent_comment":"","address_hidden":false,"region_hidden":true,"space_comment":"","costs_property_comment":"","space_units":"м²","space":"237.8","address":""}],"31":[{"costs_rent":"","region":"","costs_property":"","costs_rent_comment":"","address_hidden":false,"region_hidden":true,"space_comment":"1/2","costs_property_comment":"","space_units":"м²","space":"86.35","address":""}],"33":[{"costs_rent":"","region":"","costs_property":"","costs_rent_comment":"","address_hidden":false,"region_hidden":true,"space_comment":"","costs_property_comment":"","space_units":"м²","space":"17.6","address":""}]},"intro":{"declaration_year":"2015"}}