{"income":{"5":{"family_comment":"","value":"221179","family":"19270","comment":""},"6":{"value":"217654","family_comment":"","value_unclear":false,"comment_hidden":false,"family_unclear":false,"family":"3677","comment":""},"7":{"family_comment":"","value":"","source_name":"","family":"","comment":""},"8":{"family_comment":"","value":"","family":"","comment":""},"9":{"family_comment":"","family_unclear":false,"value":"3525","family":"","comment":""},"10":{"family_comment":"","value":"","value_unclear":false,"family":"","comment":""},"11":{"family_comment":"","value":"","family":"","comment":""},"12":{"family_comment":"","value":"","family":"","comment":""},"13":{"family_comment":"","value":"","family":"","comment":""},"14":{"family_comment":"","value":"","family":"","comment":""},"15":{"family_comment":"","value":"","family":"","comment":""},"16":{"family_comment":"","value":"","family":"","comment":""},"17":{"family_comment":"","value":"","family":"10400","comment":""},"18":{"family_comment":"","value":"","family":"","comment":""},"19":{"family_comment":"","value":"","family":"","comment":""},"20":{"value":"","family":"5193","value_unclear":false,"family_hidden":false,"family_comment":"пенсія","comment_unclear":false,"comment":"","family_comment_unclear":false}},"vehicle":{"35":[{"year_hidden":false,"brand_info":"1400","sum_rent_comment":"","year":"2007","brand_info_hidden":false,"brand_info_unclear":false,"sum_rent":"","sum":"","brand":"Hyundai Accent","sum_comment":"","brand_unclear":false,"brand_hidden":false}]},"id":"vulyk_97_195","banks":{"45":[{"sum_foreign_comment":"","sum_units":"UAH","sum_comment":"Укрсоцбанк","sum_comment_unclear":false,"sum_hidden":false,"sum_foreign_units":"UAH","sum_comment_hidden":false,"sum_unclear":false,"sum":"26927","sum_foreign":""}],"46":[{"sum_foreign_comment":"","sum_units":"UAH","sum_comment":"Укрсоцбанк","sum_foreign_units":"UAH","sum_comment_hidden":false,"sum":"5345","sum_foreign":""}]},"declaration":{"additional_info_text":"","notfull_lostpages":"","date":"2015-03-31T00:00:00","notfull":"","additional_info":"","url":"http://static.declarations.com.ua/declarations/chosen_ones/judges_batch/4110_fetysova_iryna_arkadiivna.pdf"},"liabilities":{"54":{"sum_foreign_comment":"","sum":"","sum_comment":"","sum_comment_unclear":false,"sum_hidden":false,"sum_comment_hidden":false,"sum_unclear":false,"sum_foreign":""},"55":{"sum_foreign_comment":"","sum":"","sum_comment":"","sum_foreign":""},"56":{"sum_foreign_comment":"","sum":"","sum_comment":"","sum_foreign":""},"57":{"sum_foreign_comment":"","sum":"","sum_comment":"","sum_comment_unclear":false,"sum_hidden":false,"sum_comment_hidden":false,"sum_unclear":false,"sum_foreign":""},"58":{"sum_foreign_comment":"","sum":"","sum_comment":"","sum_comment_unclear":false,"sum_hidden":false,"sum_comment_hidden":false,"sum_unclear":false,"sum_foreign":""},"59":{"sum_foreign_comment":"","sum":"","sum_comment":"","sum_foreign":""},"60":{"sum_foreign_comment":"","sum":"","sum_comment":"","sum_comment_unclear":false,"sum_hidden":false,"sum_comment_hidden":false,"sum_foreign":""},"61":{"sum_foreign_comment":"","sum":"","sum_comment":"","sum_foreign":""},"62":{"sum_foreign_comment":"","sum":"","sum_comment":"","sum_unclear":false,"sum_foreign":""},"63":{"sum_foreign_comment":"","sum":"","sum_hidden":false,"sum_comment":"","sum_foreign":""},"64":{"sum_foreign_comment":"","sum":"","sum_comment":"","sum_foreign":""}},"ft_src":"суддя господарського суду чернігівської області\nЧернігівська область\nГосподарський місцевий суд\nІрина\nАтмалов В. Р\nспівмешканець\nІнше\nФетисова Д. В\nДитина\nФетисов А. П\nБатьки\nАркадіївна\nФетисова Ірина Аркадіївна\nІрина Аркадіївна Фетисова\nІрина Фетисова\nФетисова Ірина Аркадіївна\nФетисова Ірина Аркадіївна\nФетисова\n1400\nHyundai Accent\n2007\n23\n47.7\n80.9\n61.3\n2200\nУкрсоцбанк\n5345\nУкрсоцбанк\n26927\n2014\n1400\nHyundai Accent\n2007\n2014\nФетисова Ірина Аркадіївна\nІрина Аркадіївна Фетисова\nІрина Фетисова\nФетисова Ірина Аркадіївна\nІрина\nІнше\nАтмалов В. Р\nспівмешканець\nДитина\nФетисова Д. В\nБатьки\nФетисов А. П\nФетисова Ірина Аркадіївна\nФетисова\nГосподарський місцевий суд\nЧернігівська область\nсуддя господарського суду чернігівської області\nАркадіївна\n217654\n3677\n10400\nпенсія\n5193\n221179\n19270\n3525\n2200\n61.3\n47.7\n80.9\n23\n26927\nУкрсоцбанк\n5345\nУкрсоцбанк\n3677\n217654\n3525\n19270\n221179\n10400\nпенсія\n5193\nІнше\nАтмалов В. Р\nспівмешканець\nФетисова Д. В\nДитина\nБатьки\nФетисов А. П\nАркадіївна\nФетисова\nІрина\nФетисова Ірина Аркадіївна\nІрина Аркадіївна Фетисова\nІрина Фетисова\nФетисова Ірина Аркадіївна\nЧернігівська область\nГосподарський місцевий суд\nсуддя господарського суду чернігівської області\nФетисова Ірина Аркадіївна\n2007\nHyundai Accent\n1400\n3525\nпенсія\n5193\n19270\n221179\n10400\n217654\n3677\n47.7\n80.9\n61.3\n23\n2200\nУкрсоцбанк\n26927\nУкрсоцбанк\n5345\n2014","general":{"name_hidden":false,"name":"Ірина","last_name_hidden":false,"inn":"","family":[{"inn":"","relations":"Інше","relations_other":"співмешканець","inn_hidden":true,"family_name":"Атмалов В. Р","name_hidden":true,"name_unclear":false},{"inn_hidden":false,"inn":"","name_hidden":false,"family_name":"Фетисова Д. В","relations":"Дитина","name_unclear":false},{"inn":"","relations":"Батьки","relations_other":"","inn_hidden":false,"family_name":"Фетисов А. П","name_hidden":false,"name_unclear":false}],"patronymic":"Аркадіївна","inn_hidden":true,"family_raw":"","inn_unclear":false,"post":{"region_unclear":false,"region":"Чернігівська область","post":"суддя господарського суду чернігівської області","office":"Господарський місцевий суд","office_unclear":false,"post_hidden":false},"full_name":"Фетисова Ірина Аркадіївна","addresses":[{"place_district":"","place_city_hidden":true,"place_city":"","place_city_unclear":false,"place_district_hidden":false,"place_city_type":"","place_address_hidden":true,"place_city_type_hidden":false,"place_address":"","place_hidden":true,"place":""}],"last_name":"Фетисова","patronymic_hidden":false,"full_name_suggest":{"output":"Фетисова Ірина Аркадіївна","input":["Фетисова Ірина Аркадіївна","Ірина Аркадіївна Фетисова","Ірина Фетисова"]}},"source":"VULYK","estate":{"29":[{"region_unclear":false,"space_unclear":false,"address_hidden":true,"region_hidden":true,"space_comment":"","space":"2200","address":"","region":"","costs_property":"","costs_rent_comment":"","space_comment_unclear":false,"address_unclear":false,"space_units":"м²","costs_property_comment":"","costs_rent":""}],"30":[{"address_hidden":true,"region_hidden":true,"space_comment":"","space":"61.3","address":"","region":"","costs_property":"","costs_rent_comment":"","address_unclear":false,"space_units":"м²","costs_property_comment":"","costs_rent":""}],"31":[{"space_unclear":false,"address_hidden":true,"region_hidden":true,"space_comment":"","space_hidden":false,"space":"47.7","address":"","region":"","costs_property":"","costs_rent_comment":"","space_comment_hidden":false,"space_units":"м²","costs_property_comment":"","costs_rent":""},{"costs_rent":"","region":"","costs_property":"","costs_rent_comment":"","address_hidden":true,"space_comment":"","costs_property_comment":"","space_units":"м²","space":"80.9","address":""}],"33":[{"space_hidden":false,"address_hidden":true,"region_hidden":true,"space_comment":"","space":"23","address":"","region":"","costs_property":"","costs_rent_comment":"","space_units":"м²","costs_property_comment":"","costs_rent":""}]},"intro":{"declaration_year":"2014","isnotdeclaration":""}}