{"id":"vulyk_84_154","ft_src":"Chery Beat\n1297 куб. см.\n2011\nChevrolet Aveo\n1497 куб. см., продана за дорученням в 2008 р., але з обліку не знята\n2005\nКіровоградська область\nКіровоград\n45.67\n250\nКіровоград кооператив\n15\nКіровоградська область\nКіровоградська область\n6204\nКіровоград\n97\n2014\n44924\n230941\n44924\n230941\n1297 куб. см.\nChery Beat\n2011\nChevrolet Aveo\n1497 куб. см., продана за дорученням в 2008 р., але з обліку не знята\n2005\n2014\nСолопов Юрій Олексійович\nЮрій Олексійович Солопов\nЮрій Солопов\nСолопов Юрій Олексійович\nЮрій\nПодружжя\nПетрова Н. В., 21. 05. 1971\nДитина\nСолопова В. Ю., 30. 07. 2005\nСолопов Юрій Олексійович\nОлексійович\nсуддя кіровського районного суд м. кіровограда\nЗагальний місцевий суд\nКіровоградська область\nСолопов\nКіровоград\nКіровоградська область\n6204\n230941\n44924\n230941\n44924\nКіровоград кооператив\n250\n15\nКіровоградська область\nКіровоград\nКіровоградська область\n45.67\n97\nКіровоградська область\n6204\nКіровоград\n6204\nПетрова Н. В., 21. 05. 1971\nПодружжя\nСолопова В. Ю., 30. 07. 2005\nДитина\nОлексійович\nСолопов\nЮрій\nСолопов Юрій Олексійович\nЮрій Олексійович Солопов\nЮрій Солопов\nСолопов Юрій Олексійович\nКіровоградська область\nКіровоград\nКіровоградська область\nсуддя кіровського районного суд м. кіровограда\nЗагальний місцевий суд\nСолопов Юрій Олексійович","estate":{"25":[{"address":"Кіровоград","space_units":"м²","space_hidden":false,"space_comment":"","region_hidden":false,"costs_comment":"","address_hidden":true,"costs":"","address_unclear":false,"costs_rent_comment_unclear":false,"costs_comment_unclear":false,"costs_rent_comment":"","space":"97","region_unclear":false,"region":"Кіровоградська область","costs_rent":"6204"}],"27":[{"costs":"","address":"Кіровоград кооператив","space_units":"м²","costs_rent_comment":"","space":"15","space_comment":"","region_hidden":false,"costs_comment":"","region":"Кіровоградська область","address_hidden":true,"costs_rent":"250"}],"31":[{"costs_property_comment":"","address":"Кіровоград","space_units":"м²","space_unclear":false,"region_hidden":false,"costs_property":"","space_comment":"","address_hidden":true,"address_unclear":false,"costs_rent_comment":"","space":"45.67","region":"Кіровоградська область","costs_rent":""}]},"vehicle":{"35":[{"year_hidden":false,"brand_info":"1297 куб. см.","sum_rent_comment":"","brand_unclear":false,"brand_hidden":false,"year":"2011","brand":"Chery Beat","brand_info_hidden":false,"sum_rent":"","year_unclear":false,"sum_comment":"","sum_hidden":false,"brand_info_unclear":false,"sum":""}],"40":[{"sum_comment":"","brand_info_hidden":false,"brand_info":"1497 куб. см., продана за дорученням в 2008 р., але з обліку не знята","sum":"","brand_unclear":false,"brand_hidden":false,"brand":"Chevrolet Aveo","sum_rent":"","sum_rent_comment":"","year":"2005","year_unclear":false}]},"source":"VULYK","income":{"5":{"family_comment":"","family":"44924","comment":"","value_unclear":false,"family_unclear":false,"comment_unclear":false,"value":"230941"},"6":{"family_comment":"","comment_unclear":false,"value":"230941","family":"44924","comment":""},"7":{"family":"","family_comment":"","value":"","comment":"","source_name":""},"8":{"family_comment":"","value":"","family":"","comment":""},"9":{"family_comment":"","value":"","family":"","comment":"","value_unclear":false},"10":{"family_comment":"","value":"","family":"","comment":"","value_unclear":false},"11":{"family_comment":"","value":"","family":"","comment":""},"12":{"family_comment":"","value":"","family":"","comment":""},"13":{"family_comment":"","value":"","family":"","comment":""},"14":{"family_comment":"","value":"","family":"","comment":""},"15":{"family_comment":"","value":"","family":"","comment":""},"16":{"family_comment":"","value":"","family":"","comment":""},"17":{"family_comment":"","value":"","family":"","comment":"","value_unclear":false},"18":{"family_comment":"","value":"","family":"","comment":"","value_unclear":false},"19":{"family_comment":"","value":"","family":"","comment":""},"20":{"family_comment":"","family":"","comment":"","value_unclear":false,"family_unclear":false,"comment_unclear":false,"value":""}},"general":{"family_raw":"","name":"Юрій","full_name_suggest":{"input":["Солопов Юрій Олексійович","Юрій Олексійович Солопов","Юрій Солопов"],"output":"Солопов Юрій Олексійович"},"patronymic":"Олексійович","inn_hidden":true,"addresses":[{"place_city_type_hidden":false,"place_district_hidden":false,"place_address_unclear":false,"place":"Кіровоградська область","place_city":"Кіровоград","place_unclear":false,"place_city_type_unclear":false,"place_city_type":"Місто","place_city_hidden":false,"place_city_unclear":false,"place_district":"","place_district_unclear":false,"place_address":"","place_address_hidden":true,"place_hidden":false}],"inn":"","inn_unclear":false,"last_name":"Солопов","full_name":"Солопов Юрій Олексійович","family":[{"inn":"","inn_unclear":false,"family_name":"Петрова Н. В., 21. 05. 1971","relations_other":"","relations_hidden":false,"name_unclear":false,"inn_hidden":true,"name_hidden":false,"relations":"Подружжя"},{"inn":"","family_name":"Солопова В. Ю., 30. 07. 2005","relations_other":"","name_unclear":false,"inn_hidden":false,"name_hidden":false,"relations":"Дитина"}],"post":{"post_hidden":false,"office":"Загальний місцевий суд","region_hidden":false,"post":"суддя кіровського районного суд м. кіровограда","candidate":"","region_unclear":false,"region":"Кіровоградська область","office_hidden":false,"post_unclear":false,"office_unclear":false}},"liabilities":{"54":{"sum_comment":"","sum_foreign_comment":"","sum_foreign":"","sum":"","sum_comment_hidden":false},"55":{"sum_comment":"","sum_foreign_comment":"","sum_foreign":"","sum":""},"56":{"sum_comment":"","sum_foreign_comment":"","sum_foreign":"","sum":"6204"},"57":{"sum_comment":"","sum_foreign_comment":"","sum_foreign":"","sum":"","sum_comment_hidden":false},"58":{"sum_comment":"","sum_foreign_comment":"","sum_foreign":"","sum":"","sum_comment_hidden":false},"59":{"sum_comment":"","sum_foreign_comment":"","sum_foreign":"","sum":""},"60":{"sum_comment":"","sum_foreign_comment":"","sum_foreign":"","sum":""},"61":{"sum_comment":"","sum_foreign_comment":"","sum_foreign":"","sum":""},"62":{"sum_comment":"","sum_foreign_comment":"","sum_foreign":"","sum":""},"63":{"sum_comment":"","sum_foreign_comment":"","sum_foreign":"","sum":"","sum_comment_hidden":false},"64":{"sum_comment":"","sum_foreign_comment":"","sum_foreign":"","sum":"","sum_comment_hidden":false}},"declaration":{"notfull_lostpages":"","additional_info_text":"","additional_info":"","date":"2015-03-18T00:00:00","notfull":"","url":"http://static.declarations.com.ua/declarations/chosen_ones/judges_batch/2568_solopov_iurii_oleksiiovych.pdf"},"intro":{"isnotdeclaration":"","declaration_year_unclear":false,"declaration_year":"2014"}}