{"income":{"5":{"value":"231608.81","value_unclear":false,"value_hidden":false,"family_comment":"","family":"","comment":""},"6":{"value":"231016.82","family_comment":"","value_unclear":false,"family_unclear":false,"family":"","comment":""},"7":{"source_name_unclear":false,"value":"506.95","family_hidden":false,"family_comment":"","source_name":"Національна школа суддів України","family":"","comment":""},"8":{"family_comment":"","value":"","family":"","comment":""},"9":{"family_comment":"","value":"","family":"","comment":""},"10":{"family_comment":"","value":"","family":"","comment":""},"11":{"family_comment":"","value":"","family":"","comment":""},"12":{"family_comment":"","value":"","family":"","comment":""},"13":{"family_comment":"","value":"","family":"","comment":""},"14":{"family_comment":"","value":"","family":"","comment":""},"15":{"family_comment":"","value":"","family":"","comment":""},"16":{"family_comment":"","value":"","comment_unclear":false,"family":"","comment":""},"17":{"family_comment":"","family_unclear":false,"value":"","family":"","comment":""},"18":{"family_comment":"","value":"","family":"","comment":""},"19":{"value":"","family_hidden":false,"value_hidden":false,"family_comment":"","family":"","comment":""},"20":{"family_comment":"","value":"85.04","comment_unclear":false,"family":"","comment":""}},"id":"vulyk_67_62","declaration":{"additional_info_text":"","notfull_lostpages":"","date":"2015-03-30T00:00:00","notfull":"","additional_info":"","url":"http://static.declarations.com.ua/declarations/chosen_ones/mega_batch/ahafonov_serhii_anatoliiovych.pdf"},"liabilities":{"54":{"sum_foreign_comment":"","sum_foreign_hidden":false,"sum_comment":"","sum_comment_unclear":false,"sum_hidden":false,"sum":"","sum_unclear":false,"sum_foreign":""},"55":{"sum_foreign_comment":"","sum":"","sum_comment":"","sum_foreign":""},"56":{"sum_foreign_comment":"","sum_foreign_hidden":false,"sum_comment":"","sum_hidden":false,"sum":"17500","sum_unclear":false,"sum_foreign":""},"57":{"sum_foreign_comment":"","sum_foreign_hidden":false,"sum_comment":"","sum_comment_unclear":false,"sum_hidden":false,"sum_comment_hidden":false,"sum_unclear":false,"sum":"","sum_foreign":""},"58":{"sum_foreign_comment":"","sum_foreign_hidden":false,"sum_comment":"","sum_comment_unclear":false,"sum_hidden":false,"sum_comment_hidden":false,"sum_unclear":false,"sum":"","sum_foreign":""},"59":{"sum_foreign_comment":"","sum":"","sum_hidden":false,"sum_comment":"","sum_foreign":""},"60":{"sum_foreign_comment":"","sum":"","sum_comment":"","sum_foreign":""},"61":{"sum_foreign_comment":"","sum_foreign_hidden":false,"sum_comment":"","sum_hidden":false,"sum":"","sum_foreign":""},"62":{"sum_foreign_comment":"","sum":"","sum_hidden":false,"sum_comment":"","sum_foreign":""},"63":{"sum_foreign_comment":"","sum":"","sum_comment":"","sum_comment_unclear":false,"sum_hidden":false,"sum_unclear":false,"sum_foreign":""},"64":{"sum_foreign_comment":"","sum":"","sum_comment":"","sum_hidden":false,"sum_unclear":false,"sum_foreign":""}},"ft_src":"17500\nсуддя солом'янського районного суду міста києва\nм. Київ\nЗагальний місцевий суд\nСергій\nАгафонов Я. С. 18. 05. 2009\nДитина\nАнатолійович\nАгафонов Сергій Анатолійович\nАгафонов\nАгафонов Сергій Анатолійович\nСергій Анатолійович Агафонов\nСергій Агафонов\nАгафонов Сергій Анатолійович\n85.04\n231608.81\n506.95\nНаціональна школа суддів України\n231016.82\n94.1\n2014\n231016.82\nНаціональна школа суддів України\n506.95\n231608.81\n85.04\n94.1\nЗагальний місцевий суд\nсуддя солом'янського районного суду міста києва\nм. Київ\nДитина\nАгафонов Я. С. 18. 05. 2009\nАгафонов Сергій Анатолійович\nСергій Анатолійович Агафонов\nСергій Агафонов\nАгафонов Сергій Анатолійович\nАгафонов Сергій Анатолійович\nСергій\nАгафонов\nАнатолійович\n17500\n506.95\nНаціональна школа суддів України\n231016.82\n85.04\n231608.81\n2014\n17500\nДитина\nАгафонов Я. С. 18. 05. 2009\nАнатолійович\nАгафонов\nСергій\nАгафонов Сергій Анатолійович\nСергій Анатолійович Агафонов\nСергій Агафонов\nАгафонов Сергій Анатолійович\nм. Київ\nсуддя солом'янського районного суду міста києва\nЗагальний місцевий суд\nАгафонов Сергій Анатолійович\n94.1\n2014","general":{"inn":"","name":"Сергій","patronymic_unclear":false,"last_name_hidden":false,"family":[{"inn":"","inn_hidden":false,"relations_unclear":false,"relations_hidden":false,"relations_other":"","relations":"Дитина","name_hidden":false,"inn_unclear":false,"family_name":"Агафонов Я. С. 18. 05. 2009","name_unclear":false}],"patronymic":"Анатолійович","inn_hidden":true,"family_raw":"","inn_unclear":false,"post":{"post_unclear":false,"post":"суддя солом'янського районного суду міста києва","post_hidden":false,"region":"м. Київ","region_hidden":false,"office":"Загальний місцевий суд","office_hidden":false,"office_unclear":false},"last_name_unclear":false,"full_name":"Агафонов Сергій Анатолійович","addresses":[{"place_city_type_hidden":false,"place_district_hidden":false,"place_city_type":"","place_city_hidden":true,"place_address_unclear":false,"place_address":"","place":"","place_district":"","place_unclear":false,"place_city":"","place_city_unclear":false,"place_hidden":false,"place_address_hidden":true,"place_district_unclear":false}],"last_name":"Агафонов","full_name_suggest":{"output":"Агафонов Сергій Анатолійович","input":["Агафонов Сергій Анатолійович","Сергій Анатолійович Агафонов","Сергій Агафонов"]},"name_unclear":false},"source":"VULYK","estate":{"25":[{"space_unclear":false,"costs":"","costs_comment":"","costs_hidden":false,"address_hidden":false,"region_hidden":true,"space_comment":"","space":"94.1","address":"","region":"","address_unclear":false,"space_units_unclear":false,"space_comment_unclear":false,"space_units":"м²","costs_rent":"","costs_rent_comment":""}]},"intro":{"declaration_year":"2014","isnotdeclaration":"","declaration_year_hidden":false}}