{"id":"vulyk_86_61","ft_src":"1800 кВт\nVolkswagen Sharan\n1999\n0,2367 га\n2367\n0,12 га\n1200\n297\n58\n2014\n90447\n235531\n90447\n235531\n1800 кВт\n1999\nVolkswagen Sharan\n2014\nАндрусів Ігор Михайлович\nІгор Михайлович Андрусів\nІгор Андрусів\nАндрусів Ігор Михайлович\nАндрусів Ігор Михайлович\nПодружжя\nАндрусів Лариса Петрівна, 26. 03. 1968 року\nДитина\nАндрусів Оксана Ігорівна, 13. 04. 1991 року\nАндрусів Наталія Ігорівна, 17. 01. 1996 року\nДитина\nІгор\nАндрусів\nЗагальний місцевий суд\nІвано-Франківська область\nзаступник голови долинського районного суду\nМихайлович\n235531\n90447\n235531\n90447\n2367\n0,2367 га\n0,12 га\n1200\n297\n58\nАндрусів Лариса Петрівна, 26. 03. 1968 року\nПодружжя\nАндрусів Оксана Ігорівна, 13. 04. 1991 року\nДитина\nДитина\nАндрусів Наталія Ігорівна, 17. 01. 1996 року\nМихайлович\nАндрусів\nІгор\nАндрусів Ігор Михайлович\nІгор Михайлович Андрусів\nІгор Андрусів\nАндрусів Ігор Михайлович\nІвано-Франківська область\nЗагальний місцевий суд\nзаступник голови долинського районного суду\nАндрусів Ігор Михайлович","estate":{"23":[{"address":"","space_units":"м²","costs_comment":"","region_hidden":true,"space_comment":"0,2367 га","address_hidden":true,"costs":"","address_unclear":false,"costs_rent_comment":"","space":"2367","region":"","costs_rent":""}],"24":[{"address":"","space_units":"м²","costs_comment":"","space_comment":"","region_hidden":true,"region":"","address_hidden":true,"space":"297","address_unclear":false,"costs_rent_comment":"","costs":"","costs_rent":""}],"28":[{"address":"","space_units":"м²","costs_comment":"","space_comment":"","region_hidden":true,"region":"","address_hidden":true,"space":"58","address_unclear":false,"costs_rent_comment":"","costs":"","costs_rent":""}],"29":[{"costs_property_comment":"","address":"","space_units":"м²","space_unclear":false,"region_hidden":true,"costs_property":"","space_comment":"0,12 га","address_hidden":true,"costs_rent_comment":"","space":"1200","region":"","costs_rent":""}]},"vehicle":{"35":[{"sum_comment":"","brand_info":"1800 кВт","brand_unclear":false,"sum_rent_comment":"","year":"1999","brand":"Volkswagen Sharan","sum_rent":"","brand_info_unclear":false,"year_unclear":false,"sum":""}]},"source":"VULYK","income":{"5":{"family_comment":"","value":"235531","family":"90447","comment":""},"6":{"family_comment":"","value":"235531","family":"90447","comment":"","family_comment_unclear":false},"7":{"source_name_hidden":false,"family_comment":"","comment":"","family":"","comment_hidden":false,"value":"","source_name":""},"8":{"family_comment":"","value":"","family":"","comment":""},"9":{"family_comment":"","value":"","family":"","comment":""},"10":{"family":"","family_comment":"","comment":"","value_hidden":false,"value_unclear":false,"value":""},"11":{"family_comment":"","value":"","family":"","comment":""},"12":{"family_comment":"","value":"","family":"","comment":""},"13":{"family_comment":"","value":"","family":"","comment":""},"14":{"family_comment":"","value":"","family":"","comment":""},"15":{"family_comment":"","value":"","family":"","comment":""},"16":{"family_comment":"","value":"","family":"","comment":""},"17":{"family_comment":"","value":"","family":"","comment":""},"18":{"family_comment":"","value":"","family":"","comment":""},"19":{"family_comment":"","value":"","family":"","comment":""},"20":{"family_comment":"","comment_unclear":false,"value":"","family":"","comment":""}},"general":{"family_raw":"","name":"Ігор","full_name_suggest":{"input":["Андрусів Ігор Михайлович","Ігор Михайлович Андрусів","Ігор Андрусів"],"output":"Андрусів Ігор Михайлович"},"patronymic":"Михайлович","inn_hidden":true,"patronymic_unclear":false,"inn":"","inn_unclear":false,"last_name":"Андрусів","full_name":"Андрусів Ігор Михайлович","family":[{"inn":"","family_name":"Андрусів Лариса Петрівна, 26. 03. 1968 року","relations_other":"","relations_hidden":false,"name_unclear":false,"inn_hidden":true,"name_hidden":false,"relations":"Подружжя"},{"inn":"","family_name":"Андрусів Оксана Ігорівна, 13. 04. 1991 року","relations_other":"","name_unclear":false,"inn_hidden":true,"name_hidden":false,"relations":"Дитина"},{"inn":"","name_unclear":false,"family_name":"Андрусів Наталія Ігорівна, 17. 01. 1996 року","inn_hidden":true,"relations":"Дитина"}],"post":{"office":"Загальний місцевий суд","post":"заступник голови долинського районного суду","candidate":"","region_hidden":false,"region":"Івано-Франківська область","office_hidden":false,"post_unclear":false,"office_unclear":false},"addresses":[{"place_city_type":"","place_city_type_hidden":true,"place_district_hidden":true,"place_city_hidden":true,"place_district":"","place_hidden":true,"place_address":"","place":"","place_city":"","place_address_hidden":true,"place_unclear":false}]},"liabilities":{"54":{"sum_comment":"","sum_foreign_comment":"","sum_foreign":"","sum_unclear":false,"sum":""},"55":{"sum_comment":"","sum_foreign_comment":"","sum_foreign":"","sum":""},"56":{"sum_comment":"","sum_foreign_comment":"","sum_foreign":"","sum_hidden":false,"sum":""},"57":{"sum_comment":"","sum_foreign_comment":"","sum_foreign":"","sum_unclear":false,"sum":""},"58":{"sum_comment":"","sum_foreign_comment":"","sum_foreign":"","sum_unclear":false,"sum":""},"59":{"sum_comment":"","sum_foreign_comment":"","sum_foreign":"","sum":""},"60":{"sum_comment":"","sum_foreign_comment":"","sum_foreign":"","sum":"","sum_comment_hidden":false},"61":{"sum_comment":"","sum_foreign_comment":"","sum_foreign":"","sum":""},"62":{"sum_comment":"","sum_foreign_comment":"","sum_foreign":"","sum":""},"63":{"sum_comment":"","sum_foreign_comment":"","sum_foreign":"","sum":""},"64":{"sum_comment":"","sum_foreign_comment":"","sum_foreign":"","sum":""}},"declaration":{"notfull_lostpages":"","additional_info_text":"","additional_info":"","date":"2015-03-20T00:00:00","notfull":"","url":"http://static.declarations.com.ua/declarations/chosen_ones/judges_batch/2764_andrusiv_ihor_mykhailovych.pdf"},"intro":{"declaration_year_unclear":false,"declaration_year":"2014"}}