{"income":{"5":{"family_comment":"","family_unclear":false,"value":"180778","family":"7800","comment":""},"6":{"family_comment":"","family_unclear":false,"value":"168598","family":"7800","comment":""},"7":{"value":"","comment_hidden":false,"family_comment":"","source_name":"","family":"","comment":""},"8":{"family_comment":"","value":"","family":"","comment":""},"9":{"family_comment":"","value":"","family":"","comment":""},"10":{"family_comment":"","value":"12180","family":"","comment":""},"11":{"family_comment":"","value":"","value_unclear":false,"family":"","comment":""},"12":{"family_comment":"","value":"","family":"","comment":""},"13":{"family_comment":"","value":"","family":"","comment":""},"14":{"family_comment":"","value":"","family":"","comment":""},"15":{"family_comment":"","value":"","value_unclear":false,"family":"","comment":""},"16":{"family_comment":"","family_unclear":false,"value":"","family":"","comment":""},"17":{"family_comment":"","value":"","family":"","comment":""},"18":{"family_comment":"","value":"","family_hidden":false,"comment":"","family":""},"19":{"family_comment":"","value":"","family":"","comment":""},"20":{"value":"","comment_unclear":false,"comment_hidden":false,"family_comment":"","family":"","comment":"","family_comment_hidden":false}},"id":"vulyk_68_28","banks":{"47":[{"sum_foreign_comment":"","sum_units":"UAH","sum_comment":"","sum_foreign_units":"UAH","sum":"100","sum_units_hidden":false,"sum_foreign":""}]},"declaration":{"additional_info_text":"","notfull_lostpages":"","date":"2014-03-30T00:00:00","notfull":"","additional_info":"","url":"http://static.declarations.com.ua/declarations/chosen_ones/mega_batch/kornieieva_vladlena_viktorivna.pdf"},"liabilities":{"54":{"sum_foreign_comment":"","sum":"","sum_comment":"","sum_comment_unclear":false,"sum_hidden":false,"sum_comment_hidden":false,"sum_unclear":false,"sum_foreign":""},"55":{"sum_foreign_comment":"","sum":"","sum_hidden":false,"sum_comment":"","sum_foreign":""},"56":{"sum_foreign_comment":"","sum_foreign_hidden":false,"sum_comment":"","sum":"","sum_unclear":false,"sum_foreign":""},"57":{"sum_foreign_comment":"","sum":"22190","sum_comment":"","sum_comment_unclear":false,"sum_hidden":false,"sum_comment_hidden":false,"sum_unclear":false,"sum_foreign":""},"58":{"sum_foreign_comment":"","sum":"859","sum_comment":"","sum_hidden":false,"sum_comment_hidden":false,"sum_unclear":false,"sum_foreign":""},"59":{"sum_foreign_comment":"","sum":"","sum_comment":"","sum_foreign":""},"60":{"sum_foreign_comment":"","sum":"","sum_comment":"","sum_comment_unclear":false,"sum_hidden":false,"sum_comment_hidden":false,"sum_unclear":false,"sum_foreign":""},"61":{"sum_foreign_comment":"","sum":"","sum_hidden":false,"sum_comment":"","sum_foreign":""},"62":{"sum_foreign_comment":"","sum":"","sum_comment":"","sum_unclear":false,"sum_foreign":""},"63":{"sum_foreign_comment":"","sum":"5083","sum_comment":"","sum_hidden":false,"sum_comment_hidden":false,"sum_unclear":false,"sum_foreign":""},"64":{"sum_foreign_comment":"","sum":"245","sum_comment":"","sum_hidden":false,"sum_comment_hidden":false,"sum_foreign":""}},"ft_src":"22190\n245\n859\n5083\nсуддя добропільського міськрайонного суду донецької області\nДонецька область\nЗагальний місцевий суд\nВладлена\nВікторівна\nКорнєєва Владлена Вікторівна\nВладлена Вікторівна Корнєєва\nВладлена Корнєєва\nКорнєєва Владлена Вікторівна\nКорнєєва Владлена Вікторівна\nКорнєєва\n12180\n7800\n180778\n7800\n168598\n100\n494\n603\n23.7\n2014\n7800\n168598\n12180\n7800\n180778\n100\n2014\nКорнєєва Владлена Вікторівна\nВладлена Вікторівна Корнєєва\nВладлена Корнєєва\nКорнєєва Владлена Вікторівна\nКорнєєва Владлена Вікторівна\nВладлена\nВікторівна\nЗагальний місцевий суд\nДонецька область\nсуддя добропільського міськрайонного суду донецької області\nКорнєєва\n5083\n245\n22190\n859\n168598\n7800\n180778\n7800\n12180\n494\n603\n23.7\n859\n22190\n245\n5083\nВікторівна\nКорнєєва\nВладлена\nКорнєєва Владлена Вікторівна\nВладлена Вікторівна Корнєєва\nВладлена Корнєєва\nКорнєєва Владлена Вікторівна\nДонецька область\nЗагальний місцевий суд\nсуддя добропільського міськрайонного суду донецької області\nКорнєєва Владлена Вікторівна\n494\n603\n23.7\n100\n2014","general":{"inn":"","name":"Владлена","inn_unclear":false,"family":[{"inn":"","inn_hidden":true,"relations_unclear":false,"relations_hidden":true,"relations_other":"","relations":"","name_hidden":true,"inn_unclear":false,"family_name":"","name_unclear":false}],"inn_hidden":true,"family_raw":"","last_name":"Корнєєва","post":{"post_unclear":false,"region_unclear":false,"post":"суддя добропільського міськрайонного суду донецької області","office":"Загальний місцевий суд","region":"Донецька область","post_hidden":false,"office_hidden":false,"office_unclear":false,"region_hidden":false},"full_name_suggest":{"output":"Корнєєва Владлена Вікторівна","input":["Корнєєва Владлена Вікторівна","Владлена Вікторівна Корнєєва","Владлена Корнєєва"]},"full_name":"Корнєєва Владлена Вікторівна","addresses":[{"place_city_type_hidden":true,"place_district_hidden":true,"place_city_type":"","place_city_hidden":true,"place_address_unclear":false,"place_address":"","place_hidden":true,"place":"","place_district":"","place_unclear":false,"place_city":"","place_address_hidden":true}],"patronymic":"Вікторівна","last_name_unclear":false,"name_unclear":false},"source":"VULYK","estate":{"23":[{"costs":"","costs_comment":"","address_hidden":true,"region_hidden":true,"space_comment":"","space":"494","address":"","region":"","costs_rent_comment":"","space_comment_hidden":false,"space_units":"м²","costs_rent":""},{"costs_rent":"","region":"","costs":"","costs_rent_comment":"","costs_comment":"","address_hidden":false,"region_hidden":true,"space_comment":"","space_units":"м²","space":"603","address":""}],"24":[{"region_unclear":false,"space_unclear":false,"costs":"","costs_comment":"","address_hidden":false,"region_hidden":true,"space_comment":"","space":"23.7","address":"","region":"","costs_rent_comment":"","space_units":"м²","costs_rent":""}]},"intro":{"declaration_year":"2014","isnotdeclaration":""}}