{"income":{"5":{"value":"261513","family_comment":"","value_unclear":false,"comment_hidden":false,"family_hidden":false,"family":"","value_hidden":false,"family_unclear":false,"comment_unclear":false,"comment":"","family_comment_unclear":false},"6":{"value":"249993","family_unclear":false,"family_hidden":false,"family_comment":"","family":"","comment":""},"7":{"family_comment":"","value":"","source_name":"","family":"","comment":""},"8":{"family_comment":"","value":"","value_unclear":false,"family":"","comment":""},"9":{"value":"","family_unclear":false,"family_hidden":false,"family_comment":"","family":"","comment":""},"10":{"family_comment":"","value":"","value_unclear":false,"family":"","comment":""},"11":{"value":"","value_unclear":false,"family_hidden":false,"value_hidden":false,"family_comment":"","family":"","comment":""},"12":{"family_comment":"","value":"","family":"","comment":""},"13":{"family_comment":"","value":"","value_unclear":false,"family":"","comment":""},"14":{"family_comment":"","value":"","family":"","comment":""},"15":{"family_comment":"","value":"","value_unclear":false,"family":"","comment":""},"16":{"family_comment":"","value":"","family":"","comment":""},"17":{"family_comment":"","value":"","family":"","comment":""},"18":{"family_comment":"","value":"","family":"","comment":""},"19":{"family_comment":"","value":"","family":"","comment":""},"20":{"family_comment":"","value":"11520","value_unclear":false,"family":"","comment":""}},"vehicle":{"35":[{"brand_info":"2000","sum_rent_comment":"","brand_info_unclear":false,"year":"2005","sum_hidden":false,"sum_rent_comment_unclear":false,"sum_rent":"","sum":"","brand":"Hyundai Santa FE","sum_comment":"","brand_unclear":false,"brand_hidden":false,"sum_unclear":false}],"44":[{"brand_info":"","sum_rent_comment":"","brand":"Автопричеп 'Камаз 8125'","sum_comment":"","year":"1992","sum":"","sum_rent":""}]},"id":"vulyk_54_34","banks":{"45":[{"sum_foreign_comment":"","sum_units":"UAH","sum_comment":"","sum_comment_unclear":false,"sum_hidden":false,"sum_foreign_units":"UAH","sum_units_unclear":false,"sum_comment_hidden":false,"sum_unclear":false,"sum":"","sum_foreign":""},{"sum_foreign_comment":"","sum_units":"","sum_comment":"","sum_comment_unclear":false,"sum_foreign_units":"","sum":"","sum_foreign":""},{"sum_foreign_comment":"","sum_units":"","sum_comment":"","sum_foreign_units":"","sum":"","sum_foreign":""}],"46":[{"sum_foreign_comment":"","sum_units":"UAH","sum_comment":"","sum_comment_unclear":false,"sum_foreign_units":"UAH","sum":"","sum_foreign":""},{"sum_foreign_comment":"","sum_units":"","sum_comment":"","sum_foreign_units":"","sum":"","sum_foreign":""}],"47":[{"sum_foreign_comment":"","sum_units":"UAH","sum_comment":"","sum_comment_unclear":false,"sum_foreign_units":"UAH","sum":"","sum_foreign":""},{"sum_foreign_comment":"","sum_units":"","sum_comment":"","sum":"","sum_foreign":""}],"48":[{"sum_foreign_comment":"","sum_units":"UAH","sum_comment":"","sum_foreign_units":"UAH","sum":"","sum_foreign":""}],"49":[{"sum_foreign_comment":"","sum_units":"UAH","sum_comment":"","sum_comment_unclear":false,"sum_foreign_units":"UAH","sum":"","sum_foreign":""}],"50":[{"sum_foreign_comment":"","sum_units":"UAH","sum_comment":"","sum_foreign_units":"UAH","sum":"","sum_foreign":""}],"51":[{"sum_foreign_comment":"","sum_units":"UAH","sum_comment":"","sum_comment_unclear":false,"sum_hidden":false,"sum_foreign_units":"UAH","sum_comment_hidden":false,"sum":"","sum_foreign":""},{"sum_foreign_comment":"","sum_units":"","sum_comment":"","sum_foreign_units":"","sum":"","sum_foreign":""},{"sum_foreign_comment":"","sum_units":"","sum_comment":"","sum_foreign_units":"","sum":"","sum_foreign":""}],"52":[{"sum_foreign_comment":"","sum_units":"UAH","sum_comment":"","sum_comment_unclear":false,"sum_foreign_units":"UAH","sum":"","sum_foreign":""}],"53":[{"sum_foreign_comment":"","sum_units":"UAH","sum_comment":"","sum_foreign_units":"UAH","sum":"","sum_unclear":false,"sum_foreign":""}]},"declaration":{"additional_info_text":"","notfull_lostpages":"","date":"2015-03-24T00:00:00","notfull":"","additional_info":"","url":"http://static.declarations.com.ua/declarations/chosen_ones/mega_batch/vodop’yanov_serhii_mykolaiovych.pdf"},"liabilities":{"54":{"sum_foreign_comment":"","sum":"","sum_comment":"","sum_comment_unclear":false,"sum_hidden":false,"sum_comment_hidden":false,"sum_unclear":false,"sum_foreign":""},"55":{"sum_foreign_comment":"","sum":"","sum_comment":"","sum_foreign":""},"56":{"sum_foreign_comment":"","sum":"","sum_comment":"","sum_foreign":""},"57":{"sum_foreign_comment":"","sum":"","sum_comment":"","sum_comment_unclear":false,"sum_comment_hidden":false,"sum_unclear":false,"sum_foreign":""},"58":{"sum_foreign_comment":"","sum":"","sum_comment":"","sum_comment_unclear":false,"sum_comment_hidden":false,"sum_unclear":false,"sum_foreign":""},"59":{"sum_foreign_comment":"","sum_foreign_hidden":false,"sum_comment":"","sum_hidden":false,"sum_comment_hidden":false,"sum":"","sum_foreign":""},"60":{"sum_foreign_comment":"","sum":"","sum_comment":"","sum_foreign":""},"61":{"sum_foreign_comment":"","sum":"","sum_comment":"","sum_foreign":""},"62":{"sum_foreign_comment":"","sum":"","sum_comment":"","sum_foreign":""},"63":{"sum_foreign_comment":"","sum_comment_hidden":false,"sum":"","sum_comment":"","sum_foreign":""},"64":{"sum_foreign_comment":"","sum":"","sum_comment":"","sum_foreign":""}},"ft_src":"суддя жовтневого районного суду м. кривого рогу\nДніпропетровська область\nЗагальний місцевий суд\nСергій\nВодоп'янова І. В\nПодружжя\nМиколайович\nВодоп'янов Сергій Миколайович\nСергій Миколайович Водоп'янов\nСергій Водоп'янов\nВодоп'янов Сергій Миколайович\nВодоп'янов Сергій Миколайович\nВодоп'янов\n2000\nHyundai Santa FE\n2005\n1992\nАвтопричеп 'Камаз 8125'\n2014\n2000\nHyundai Santa FE\n2005\nАвтопричеп 'Камаз 8125'\n1992\n32\nДніпропетровська область\nм. Кривий Ріг,\n21\nВінницька область\n24\nДніпропетровська область\nм. Кривий Ріг,\n924\nДніпропетровська область\nм. Кривий Ріг,\n505\nм. Кривий Ріг,\nДніпропетровська область\n200\nВінницька область\n190\nм. Кривий Ріг,\nДніпропетровська область\nПодружжя\nВодоп'янова І. В\nВодоп'янов Сергій Миколайович\nСергій Миколайович Водоп'янов\nСергій Водоп'янов\nВодоп'янов Сергій Миколайович\nВодоп'янов Сергій Миколайович\nСергій\nМиколайович\nЗагальний місцевий суд\nДніпропетровська область\nсуддя жовтневого районного суду м. кривого рогу\nВодоп'янов\n249993\n11520\n261513\n2014\nДніпропетровська область\nм. Кривий Ріг,\n32\nВінницька область\n200\nм. Кривий Ріг,\n190\nДніпропетровська область\nм. Кривий Ріг,\nДніпропетровська область\n24\nм. Кривий Ріг,\n924\nДніпропетровська область\nм. Кривий Ріг,\n505\nДніпропетровська область\nВінницька область\n21\nПодружжя\nВодоп'янова І. В\nМиколайович\nВодоп'янов\nСергій\nВодоп'янов Сергій Миколайович\nСергій Миколайович Водоп'янов\nСергій Водоп'янов\nВодоп'янов Сергій Миколайович\nДніпропетровська область\nЗагальний місцевий суд\nсуддя жовтневого районного суду м. кривого рогу\nВодоп'янов Сергій Миколайович\n249993\n261513\n11520\nАвтопричеп 'Камаз 8125'\n1992\n2005\nHyundai Santa FE\n2000\n11520\n261513\n249993\nм. Кривий Ріг,\nДніпропетровська область\n924\nм. Кривий Ріг,\nДніпропетровська область\n505\nм. Кривий Ріг,\nДніпропетровська область\n190\nм. Кривий Ріг,\nДніпропетровська область\n32\nВінницька область\n21\nм. Кривий Ріг,\nДніпропетровська область\n24\nВінницька область\n200\n2014","general":{"inn":"","name":"Сергій","patronymic_unclear":false,"family":[{"inn":"","inn_hidden":true,"relations_unclear":false,"relations_hidden":false,"relations_other":"","relations":"Подружжя","name_hidden":false,"inn_unclear":false,"family_name":"Водоп'янова І. В","name_unclear":false}],"patronymic":"Миколайович","inn_hidden":true,"family_raw":"","inn_unclear":false,"post":{"post_unclear":false,"region_unclear":false,"post":"суддя жовтневого районного суду м. кривого рогу","office":"Загальний місцевий суд","region":"Дніпропетровська область","post_hidden":false,"office_hidden":false,"office_unclear":false,"region_hidden":false},"full_name_suggest":{"output":"Водоп'янов Сергій Миколайович","input":["Водоп'янов Сергій Миколайович","Сергій Миколайович Водоп'янов","Сергій Водоп'янов"]},"full_name":"Водоп'янов Сергій Миколайович","addresses":[{"place_district":"","place_city_hidden":true,"place_city":"","place_city_unclear":false,"place_district_hidden":true,"place_city_type":"","place_address_hidden":true,"place_city_type_hidden":true,"place_address":"","place_hidden":true,"place":""}],"last_name":"Водоп'янов","last_name_unclear":false,"name_unclear":false},"source":"VULYK","estate":{"23":[{"space_unclear":false,"costs":"","costs_comment":"","costs_hidden":false,"address_hidden":true,"region_hidden":false,"space_comment":"","space":"924","address":"м. Кривий Ріг,","region":"Дніпропетровська область","address_unclear":false,"costs_rent_comment":"","space_units":"м²","costs_rent":""},{"space":"505","region":"Дніпропетровська область","costs":"","costs_rent_comment":"","costs_comment":"","region_hidden":true,"address_unclear":false,"space_comment":"","space_units":"м²","costs_rent":"","address":"м. Кривий Ріг,"},{"costs_rent":"","region":"","costs":"","costs_rent_comment":"","costs_comment":"","space_comment":"","space_units":"","space":"","address":""},{"costs_rent":"","costs":"","costs_rent_comment":"","costs_comment":"","space_comment":"","space_units":"","space":"","address":""}],"24":[{"space_hidden":false,"costs":"","costs_comment":"","address_hidden":true,"region_hidden":false,"space_comment":"","space":"190","address":"м. Кривий Ріг,","region":"Дніпропетровська область","costs_rent_comment":"","space_units":"м²","costs_rent":""}],"27":[{"costs":"","costs_comment":"","address_hidden":true,"region_hidden":false,"space_comment":"","space":"32","address":"м. Кривий Ріг,","costs_comment_unclear":false,"region":"Дніпропетровська область","address_unclear":false,"costs_rent_comment":"","space_units":"м²","costs_rent":""}],"29":[{"space_unclear":false,"costs_property_hidden":false,"address_hidden":true,"region_hidden":false,"space_comment":"","space":"200","address":"","region":"Вінницька область","costs_property":"","costs_rent_comment":"","space_units":"м²","costs_property_comment":"","costs_rent":""}],"30":[{"region_unclear":false,"space_unclear":false,"address_hidden":true,"region_hidden":false,"space_comment":"","space":"21","address":"","region":"Вінницька область","costs_property":"","costs_rent_comment":"","space_units":"м²","costs_property_comment":"","costs_rent":""}],"33":[{"region_unclear":false,"address_hidden":true,"region_hidden":false,"space_comment":"","space":"24","address":"м. Кривий Ріг,","region":"Дніпропетровська область","costs_property":"","costs_rent_comment":"","address_unclear":false,"space_units":"м²","costs_property_comment":"","costs_rent":""}]},"intro":{"declaration_year":"2014","declaration_year_unclear":false}}