{"id":"vulyk_104_105","ft_src":"2011\nSsangYong Rexton\nRX 270 XVT\nFord Focus\n1596 куб. см.\n2011\n69.1\n2015\n80674.85\n255393.33\n80674.85\n255393.33\n47481.81\nRX 270 XVT\nSsangYong Rexton\n2011\nFord Focus\n1596 куб. см.\n2011\n2015\nПодружжя\nДимарецька В. В. 17. 02. 1967\nДитина\nДимарецький І. В. 14. 09. 1986\nДимарецький\nДимарецький Віктор Михайлович\nВіктор Михайлович Димарецький\nВіктор Димарецький\nДимарецький Віктор Михайлович\nДимарецький Віктор Михайлович\nВіктор\nМихайлович\nЗагальний апеляційний суд\nсуддя апеляційного суду київської області\nКиївська область\n17598.76\n1036.8\n80000\n255393.33\n80674.85\n47481.81\n255393.33\n80674.85\n69.1\n80000\n17598.76\n1036.8\nПодружжя\nДимарецька В. В. 17. 02. 1967\nДитина\nДимарецький І. В. 14. 09. 1986\nМихайлович\nДимарецький\nсуддя апеляційного суду київської області\nЗагальний апеляційний суд\nКиївська область\nДимарецький Віктор Михайлович\nДимарецький Віктор Михайлович\nВіктор Михайлович Димарецький\nВіктор Димарецький\nДимарецький Віктор Михайлович\nВіктор","estate":{"25":[{"costs_unclear":false,"address":"","space_units":"м²","space_comment":"","region_hidden":true,"costs_comment":"","address_hidden":false,"space":"69.1","space_comment_unclear":false,"costs_rent_comment":"","costs":"","region":"","costs_rent":""}]},"vehicle":{"35":[{"sum_comment":"","brand_info":"RX 270 XVT","sum":"","sum_rent_comment":"","year":"2011","brand":"SsangYong Rexton","sum_rent":"","brand_info_unclear":false,"brand_hidden":false}],"40":[{"sum_comment":"","brand_info_hidden":false,"brand_info":"1596 куб. см.","sum":"","sum_rent_comment":"","brand_hidden":false,"brand":"Ford Focus","sum_rent":"","brand_info_unclear":false,"year":"2011"}]},"source":"VULYK","income":{"5":{"family_comment":"","value":"255393.33","family":"80674.85","comment":""},"6":{"family_comment":"","value":"255393.33","family":"80674.85","comment":"","value_unclear":false},"7":{"source_name_hidden":false,"family_comment":"","comment":"","family":"","value":"","source_name":""},"8":{"family_comment":"","value":"","family":"","comment":""},"9":{"family_comment":"","value":"","family":"","comment":""},"10":{"family_comment":"","value":"","family":"","comment":""},"11":{"family_comment":"","value":"","family":"","comment":"","comment_hidden":false},"12":{"family_comment":"","value":"","family":"","comment":""},"13":{"family_comment":"","value":"","family":"","comment":""},"14":{"family_comment":"","value":"","family":"","comment":""},"15":{"family_comment":"","family":"","comment":"","value_unclear":false,"family_unclear":false,"value":""},"16":{"family_comment":"","value":"","family":"","comment":""},"17":{"family_comment":"","value":"","family":"","comment":""},"18":{"family_comment":"","value":"","family":"","comment":""},"19":{"family_comment":"","value":"","family":"","comment":""},"20":{"family_comment":"","comment_unclear":false,"value":"47481.81","family":"","comment":""}},"general":{"inn":"","addresses":[{"place_city_type_hidden":false,"place_city_type":"","place_city_hidden":true,"place_hidden":true,"place_district":"","place_district_hidden":false,"place":"","place_address":"","place_address_hidden":true,"place_city":""}],"last_name":"Димарецький","full_name":"Димарецький Віктор Михайлович","family":[{"inn":"","family_name":"Димарецька В. В. 17. 02. 1967","relations_other":"","name_unclear":false,"inn_hidden":true,"name_hidden":false,"relations":"Подружжя"},{"inn":"","family_name":"Димарецький І. В. 14. 09. 1986","relations_other":"","name_unclear":false,"inn_hidden":false,"name_hidden":false,"relations":"Дитина"}],"patronymic":"Михайлович","inn_hidden":true,"name":"Віктор","post":{"office":"Загальний апеляційний суд","region_unclear":false,"post":"суддя апеляційного суду київської області","region":"Київська область","office_unclear":false},"family_raw":"","full_name_suggest":{"input":["Димарецький Віктор Михайлович","Віктор Михайлович Димарецький","Віктор Димарецький"],"output":"Димарецький Віктор Михайлович"}},"liabilities":{"54":{"sum_comment":"","sum_hidden":false,"sum":"17598.76","sum_foreign_comment":"","sum_foreign":"","sum_unclear":false,"sum_foreign_hidden":false,"sum_comment_hidden":false},"55":{"sum_comment":"","sum_foreign_comment":"","sum_foreign":"","sum":""},"56":{"sum_comment":"","sum_foreign_comment":"","sum_foreign":"","sum_unclear":false,"sum":""},"57":{"sum_comment_unclear":false,"sum_comment":"","sum":"80000","sum_foreign_comment":"","sum_foreign":"","sum_foreign_hidden":false,"sum_comment_hidden":false},"58":{"sum_comment":"","sum_foreign_comment":"","sum_foreign":"","sum_unclear":false,"sum":""},"59":{"sum_comment":"","sum_foreign_comment":"","sum_foreign":"","sum":""},"60":{"sum_comment":"","sum":"1036.8","sum_foreign_comment":"","sum_foreign":"","sum_foreign_hidden":false,"sum_comment_hidden":false},"61":{"sum_comment":"","sum_foreign_comment":"","sum_foreign":"","sum":""},"62":{"sum_comment":"","sum_foreign_comment":"","sum_foreign":"","sum":""},"63":{"sum_comment":"","sum_foreign_comment":"","sum_foreign":"","sum":""},"64":{"sum_comment":"","sum_foreign_comment":"","sum_foreign":"","sum":""}},"declaration":{"additional_info_text":"","additional_info":"","date":"2016-03-28T00:00:00","url":"http://static.declarations.com.ua/declarations/chosen_ones/judges_batch/1903_dymaretskyi_viktor_mykhailovych_2015.pdf"},"intro":{"isnotdeclaration":"","declaration_year":"2015"}}