{"income":{"5":{"value":"207002","family_comment":"","value_unclear":false,"family_unclear":false,"comment_unclear":false,"comment":"","family":"166929"},"6":{"family_comment":"","value":"194822","comment_unclear":false,"family":"","comment":""},"7":{"family_comment":"","value":"","source_name":"","family":"","comment":""},"8":{"family_comment":"","value":"","family":"","comment":""},"9":{"family_comment":"","value":"","value_unclear":false,"family":"","comment":""},"10":{"family_comment":"","value":"12180","value_unclear":false,"family":"","comment":""},"11":{"family_comment":"","value":"","family":"","comment":""},"12":{"family_comment":"","value":"","family":"","comment":""},"13":{"family_comment":"","value":"","family":"","comment":""},"14":{"family_comment":"","value":"","family":"","comment":""},"15":{"family_comment":"","value":"","family":"","comment":""},"16":{"family_comment":"","value":"","family":"","comment":""},"17":{"family_comment":"","value":"","value_unclear":false,"family":"","comment":""},"18":{"family_comment":"","value":"","value_unclear":false,"family":"","comment":""},"19":{"family_comment":"","value":"","family":"","comment":""},"20":{"value":"","family_comment":"","value_unclear":false,"family_unclear":false,"comment_unclear":false,"comment":"","family":""}},"id":"vulyk_84_162","declaration":{"additional_info_text":"","notfull_lostpages":"","date":"2015-03-23T00:00:00","notfull":"","additional_info":"","url":"http://static.declarations.com.ua/declarations/chosen_ones/judges_batch/2576_varakina_nataliia_borysivna.pdf"},"liabilities":{"54":{"sum_foreign_comment":"","sum_comment_hidden":false,"sum":"","sum_comment":"","sum_foreign":""},"55":{"sum_foreign_comment":"","sum":"","sum_comment":"","sum_foreign":""},"56":{"sum_foreign_comment":"","sum":"","sum_comment":"","sum_foreign":""},"57":{"sum_foreign_comment":"","sum_comment_hidden":false,"sum":"","sum_comment":"","sum_foreign":""},"58":{"sum_foreign_comment":"","sum_comment_hidden":false,"sum":"","sum_comment":"","sum_foreign":""},"59":{"sum_foreign_comment":"","sum":"","sum_comment":"","sum_foreign":""},"60":{"sum_foreign_comment":"","sum":"","sum_comment":"","sum_foreign":""},"61":{"sum_foreign_comment":"","sum":"","sum_comment":"","sum_foreign":""},"62":{"sum_foreign_comment":"","sum":"","sum_comment":"","sum_foreign":""},"63":{"sum_foreign_comment":"","sum_comment_hidden":false,"sum":"","sum_comment":"","sum_foreign":""},"64":{"sum_foreign_comment":"","sum_comment_hidden":false,"sum":"","sum_comment":"","sum_foreign":""}},"ft_src":"Кіровоград\n25005\nКіровоградська область\nсуддя кіровського районного суд м. кіровограда\nКіровоградська область\nЗагальний місцевий суд\nНаталія\nВаракін О. В., 18. 03. 1978\nПодружжя\nВаракіна С. О., 02. 10. 2007\nДитина\nБорисівна\nВаракіна Наталія Борисівна\nНаталія Борисівна Варакіна\nНаталія Варакіна\nВаракіна Наталія Борисівна\nВаракіна Наталія Борисівна\nВаракіна\n12180\n207002\n166929\n194822\n2014\n194822\n12180\n166929\n207002\n194822\n207002\n166929\n12180\nВаракіна Наталія Борисівна\nНаталія Борисівна Варакіна\nНаталія Варакіна\nВаракіна Наталія Борисівна\nНаталія\nПодружжя\nВаракін О. В., 18. 03. 1978\nДитина\nВаракіна С. О., 02. 10. 2007\nВаракіна Наталія Борисівна\nБорисівна\nсуддя кіровського районного суд м. кіровограда\nЗагальний місцевий суд\nКіровоградська область\nВаракіна\nКіровоград\n25005\nКіровоградська область\n2014\nВаракін О. В., 18. 03. 1978\nПодружжя\nВаракіна С. О., 02. 10. 2007\nДитина\nБорисівна\nВаракіна\nНаталія\nВаракіна Наталія Борисівна\nНаталія Борисівна Варакіна\nНаталія Варакіна\nВаракіна Наталія Борисівна\nКіровоградська область\nКіровоград\n25005\nКіровоградська область\nсуддя кіровського районного суд м. кіровограда\nЗагальний місцевий суд\nВаракіна Наталія Борисівна\n2014","general":{"inn":"","name":"Наталія","inn_unclear":false,"family":[{"inn":"","inn_hidden":true,"inn_unclear":false,"relations_hidden":false,"relations_other":"","relations":"Подружжя","name_hidden":false,"family_name":"Варакін О. В., 18. 03. 1978","name_unclear":false},{"inn":"","relations":"Дитина","relations_other":"","inn_hidden":false,"family_name":"Варакіна С. О., 02. 10. 2007","name_hidden":false,"name_unclear":false}],"inn_hidden":true,"family_raw":"","last_name":"Варакіна","post":{"post_unclear":false,"region_unclear":false,"post":"суддя кіровського районного суд м. кіровограда","candidate":"","office_hidden":false,"region":"Кіровоградська область","post_hidden":false,"office":"Загальний місцевий суд","office_unclear":false,"region_hidden":false},"full_name":"Варакіна Наталія Борисівна","addresses":[{"place_city_type_unclear":false,"place_address":"25005","place_district_hidden":false,"place_city_type":"Місто","place_address_hidden":true,"place_address_unclear":false,"place_city_type_hidden":false,"place":"Кіровоградська область","place_district":"","place_unclear":false,"place_city":"Кіровоград","place_city_unclear":false,"place_hidden":false,"place_city_hidden":false,"place_district_unclear":false}],"patronymic":"Борисівна","full_name_suggest":{"output":"Варакіна Наталія Борисівна","input":["Варакіна Наталія Борисівна","Наталія Борисівна Варакіна","Наталія Варакіна"]}},"source":"VULYK","intro":{"declaration_year":"2014","isnotdeclaration":"","declaration_year_unclear":false}}