{"income":{"5":{"family_comment":"","family_unclear":false,"value":"172718","family":"207182","comment":""},"6":{"value":"172718","family_comment":"","value_unclear":false,"family_unclear":false,"family":"195170","comment":""},"7":{"value":"","family_comment":"","value_unclear":false,"family_unclear":false,"source_name":"","family":"","comment":"","source_name_hidden":false},"8":{"family_comment":"","value":"","family":"","comment":""},"9":{"family_comment":"","value":"","family":"","comment":""},"10":{"family_comment":"","value":"","value_unclear":false,"family":"","comment":""},"11":{"family_comment":"","value":"","family":"","comment":""},"12":{"family_comment":"","value":"","family":"","comment":""},"13":{"family_comment":"","value":"","family":"","comment":""},"14":{"family_comment":"","value":"","family":"","comment":""},"15":{"family_comment":"","value":"","family":"","comment":""},"16":{"family_comment":"","value":"","family":"","comment":""},"17":{"family_comment":"","value":"","family":"","comment":""},"18":{"family_comment":"","value":"","family":"","comment":""},"19":{"family_comment":"","value":"","family":"","comment":""},"20":{"value":"","value_unclear":false,"comment_hidden":false,"family_comment":"","comment_unclear":false,"comment":"","family":"12012.48"}},"vehicle":{"35":[{"year_hidden":false,"brand_info":"1.3 л","sum_rent_comment":"","year":"2006","brand_info_hidden":false,"year_unclear":false,"sum_rent":"","sum":"","brand":"Daewoo Sens","sum_comment":"","brand_unclear":false,"brand_hidden":false,"sum_unclear":false}],"40":[{"brand_info":"2.0 л","sum_rent_comment":"","brand":"Kia Sportage","sum_comment":"","year":"2009","brand_info_hidden":false,"year_unclear":false,"sum":"","sum_rent":""}]},"id":"vulyk_96_78","declaration":{"additional_info_text":"","notfull_lostpages":"","date":"2016-03-12T00:00:00","notfull":"","additional_info":"","url":"http://static.declarations.com.ua/declarations/chosen_ones/judges_batch/292_bondarchuk_volodymyr_volodymyrovych_2015.pdf"},"liabilities":{"54":{"sum_foreign_comment":"","sum":"","sum_comment":"","sum_hidden":false,"sum_comment_hidden":false,"sum_foreign":""},"55":{"sum_foreign_comment":"","sum":"","sum_comment":"","sum_foreign":""},"56":{"sum_foreign_comment":"","sum":"","sum_comment":"","sum_unclear":false,"sum_foreign":""},"57":{"sum_foreign_comment":"","sum_comment_hidden":false,"sum":"","sum_comment":"","sum_foreign":""},"58":{"sum_foreign_comment":"","sum":"","sum_comment":"","sum_comment_hidden":false,"sum_unclear":false,"sum_foreign":""},"59":{"sum_foreign_comment":"","sum":"","sum_comment":"","sum_foreign":""},"60":{"sum_foreign_comment":"","sum_comment_hidden":false,"sum":"","sum_comment":"","sum_foreign":""},"61":{"sum_foreign_comment":"","sum":"","sum_comment":"","sum_foreign":""},"62":{"sum_foreign_comment":"","sum":"","sum_comment":"","sum_foreign":""},"63":{"sum_foreign_comment":"","sum_comment_hidden":false,"sum":"45167.22","sum_comment":"","sum_foreign":""},"64":{"sum_foreign_comment":"","sum_comment_hidden":false,"sum":"3190.75","sum_comment":"","sum_foreign":""}},"ft_src":"45167.22\n3190.75\nсуддя хмельницького міськрайонного суду хмельницької області\nХмельницька область\nЗагальний місцевий суд\nВолодимир\nБондарчук Л. А. 07. 06. 1980\nПодружжя\nБондарчук В. В. 31. 12. 2012\nДитина\nБондарчук О. В. 31. 12. 2012\nДитина\nВолодимирович\nБондарчук Володимир Володимирович\nБондарчук\nБондарчук Володимир Володимирович\nВолодимир Володимирович Бондарчук\nВолодимир Бондарчук\nБондарчук Володимир Володимирович\n1.3 л\nDaewoo Sens\n2006\n2009\n2.0 л\nKia Sportage\n1200\n800\n2015\n195170\n172718\n207182\n172718\n12012.48\n1.3 л\nDaewoo Sens\n2006\nKia Sportage\n2.0 л\n2009\n2015\nБондарчук Володимир Володимирович\nВолодимир Володимирович Бондарчук\nВолодимир Бондарчук\nБондарчук Володимир Володимирович\nБондарчук Володимир Володимирович\nВолодимир\nБондарчук\nХмельницька область\nсуддя хмельницького міськрайонного суду хмельницької області\nЗагальний місцевий суд\nВолодимирович\nПодружжя\nБондарчук Л. А. 07. 06. 1980\nДитина\nБондарчук В. В. 31. 12. 2012\nДитина\nБондарчук О. В. 31. 12. 2012\n45167.22\n3190.75\n195170\n172718\n12012.48\n172718\n207182\n1200\n800\n45167.22\n3190.75\nБондарчук Л. А. 07. 06. 1980\nПодружжя\nДитина\nБондарчук В. В. 31. 12. 2012\nДитина\nБондарчук О. В. 31. 12. 2012\nВолодимир\nВолодимирович\nБондарчук\nБондарчук Володимир Володимирович\nВолодимир Володимирович Бондарчук\nВолодимир Бондарчук\nБондарчук Володимир Володимирович\nсуддя хмельницького міськрайонного суду хмельницької області\nХмельницька область\nЗагальний місцевий суд\nБондарчук Володимир Володимирович\nDaewoo Sens\n1.3 л\n2006\n2009\n2.0 л\nKia Sportage\n12012.48\n207182\n172718\n172718\n195170\n1200\n800\n2015","general":{"inn":"","name":"Володимир","family":[{"inn":"","inn_hidden":true,"inn_unclear":false,"relations_hidden":false,"relations_other":"","relations":"Подружжя","name_hidden":false,"family_name":"Бондарчук Л. А. 07. 06. 1980","name_unclear":false},{"inn":"","relations":"Дитина","relations_other":"","inn_hidden":false,"family_name":"Бондарчук В. В. 31. 12. 2012","name_hidden":false,"name_unclear":false},{"inn":"","relations":"Дитина","relations_other":"","inn_hidden":false,"family_name":"Бондарчук О. В. 31. 12. 2012","name_unclear":false}],"patronymic":"Володимирович","inn_hidden":true,"family_raw":"","last_name":"Бондарчук","post":{"office":"Загальний місцевий суд","region":"Хмельницька область","office_unclear":false,"post":"суддя хмельницького міськрайонного суду хмельницької області"},"full_name":"Бондарчук Володимир Володимирович","addresses":[{"place_district":"","place_city_hidden":true,"place_city":"","place_city_type_hidden":false,"place_district_hidden":false,"place_city_type":"","place_address_hidden":false,"place_address":"","place_hidden":true,"place":""}],"patronymic_hidden":false,"full_name_suggest":{"output":"Бондарчук Володимир Володимирович","input":["Бондарчук Володимир Володимирович","Володимир Володимирович Бондарчук","Володимир Бондарчук"]}},"source":"VULYK","estate":{"23":[{"region_unclear":false,"space_unclear":false,"costs":"","costs_rent_unclear":false,"costs_comment":"","address_hidden":false,"region_hidden":true,"space_comment":"","space_hidden":false,"space_units_unclear":false,"address":"","region":"","address_unclear":false,"space":"1200","space_comment_unclear":false,"space_units":"м²","costs_rent":"","costs_rent_comment":""}],"29":[{"region_unclear":false,"space_unclear":false,"address_hidden":false,"region_hidden":true,"space_comment":"","space":"800","address":"","region":"","costs_property":"","costs_rent_comment":"","address_unclear":false,"space_units":"м²","costs_property_comment":"","costs_rent":""}]},"intro":{"declaration_year":"2015","isnotdeclaration":""}}