{"income":{"5":{"family_comment":"","family_unclear":false,"value":"159831.26","family":"24275.76","comment":""},"6":{"value":"159831.26","family_comment":"","value_unclear":false,"family_unclear":false,"family":"12493.48","comment":""},"7":{"source_name_unclear":false,"value":"","family_comment":"","source_name":"","family":"","comment":"","source_name_hidden":false},"8":{"family_comment":"","value":"","family":"","comment":""},"9":{"family_comment":"","family_unclear":false,"value":"","family":"","comment":""},"10":{"family_comment":"","value":"","family":"","comment":""},"11":{"family_comment":"","value":"","family":"","comment":""},"12":{"family_comment":"","value":"","family":"","comment":""},"13":{"family_comment":"","value":"","family":"","comment":""},"14":{"family_comment":"","value":"","family":"","comment":""},"15":{"family_comment":"","value":"","family":"","comment":""},"16":{"family_comment":"","family_unclear":false,"value":"","family":"","comment":""},"17":{"family_comment":"","family_unclear":false,"value":"","family":"","comment":""},"18":{"family_comment":"","value":"","family":"","comment":""},"19":{"family_comment":"","value":"","family":"","comment":""},"20":{"family_comment":"","value":"","comment_unclear":false,"family":"11782.28","comment":""}},"vehicle":{"35":[{"brand_info":"1781 куб. см. 438 см","sum":"","brand":"Volkswagen Vento","sum_comment":"","brand_unclear":false,"year":"1994","brand_hidden":false,"brand_info_hidden":false,"brand_info_unclear":true,"sum_rent_comment":"","sum_rent":""}],"36":[{"brand_info":"55.2 кВт 436 см","sum":"","brand":"УАЗ 452 Д","sum_comment":"","brand_unclear":true,"year":"1978","sum_rent_comment":"","sum_rent":""}],"40":[{"brand_info":"1997 куб. см.","sum":"","brand":"Mitsubishi Outlander","sum_comment":"","brand_unclear":false,"year":"2003","brand_hidden":false,"brand_info_hidden":false,"brand_info_unclear":false,"sum_rent_comment":"","sum_rent":""}]},"id":"vulyk_95_27","declaration":{"additional_info_text":"","notfull_lostpages":"","date":"2016-03-14T00:00:00","notfull":"","additional_info":"","url":"http://static.declarations.com.ua/declarations/chosen_ones/judges_batch/28_bilenskyi_oleh_oleksiiovych.pdf"},"liabilities":{"54":{"sum_foreign_comment":"","sum":"","sum_comment":"","sum_hidden":false,"sum_comment_hidden":false,"sum_unclear":false,"sum_foreign":""},"55":{"sum_foreign_comment":"","sum":"","sum_comment":"","sum_foreign":""},"56":{"sum_foreign_comment":"","sum":"","sum_comment":"","sum_foreign":""},"57":{"sum_foreign_comment":"","sum":"","sum_comment":"","sum_hidden":false,"sum_comment_hidden":false,"sum_unclear":false,"sum_foreign":""},"58":{"sum_foreign_comment":"","sum":"","sum_comment":"","sum_hidden":false,"sum_comment_hidden":false,"sum_unclear":false,"sum_foreign":""},"59":{"sum_foreign_comment":"","sum":"","sum_comment":"","sum_foreign":""},"60":{"sum_foreign_comment":"","sum":"","sum_comment":"","sum_hidden":false,"sum_comment_hidden":false,"sum_foreign":""},"61":{"sum_foreign_comment":"","sum":"","sum_comment":"","sum_foreign":""},"62":{"sum_foreign_comment":"","sum":"","sum_comment":"","sum_unclear":false,"sum_foreign":""},"63":{"sum_foreign_comment":"","sum":"","sum_comment":"","sum_unclear":false,"sum_foreign":""},"64":{"sum_foreign_comment":"","sum":"","sum_comment":"","sum_foreign":""}},"ft_src":"1978\n55.2 кВт 436 см\nУАЗ 452 Д\nVolkswagen Vento\n1781 куб. см. 438 см\n1994\nMitsubishi Outlander\n1997 куб. см.\n2003\nм. Південне\n1554\nХарківська область\n45.65\nХарківська область\nХарківська область\nм. Харків\n68.7\nХарківська область\nм. Харків\n66.4\nХарківська область\nХарківська область\nм. Південне\n41.3\nХарківська область\nм. Південне\n45.65\n2015\n12493.48\n159831.26\n24275.76\n159831.26\n11782.28\nVolkswagen Vento\n1781 куб. см. 438 см\n1994\nMitsubishi Outlander\n1997 куб. см.\n2003\n55.2 кВт 436 см\nУАЗ 452 Д\n1978\n1554\nм. Південне\nХарківська область\n45.65\nХарківська область\n41.3\nм. Південне\nХарківська область\n45.65\nм. Південне\nХарківська область\nм. Харків\nХарківська область\n68.7\nм. Харків\nХарківська область\n66.4\nХарківська область\nОлексійович\nПодружжя\nКононова Юлія В'ячеславівна\nДитина\nБіленська Єлизавета Олегівна\nДитина\nБіленська Евеліна Олегівна\nБіленський Олег Олексійович\nОлег Олексійович Біленський\nОлег Біленський\nБіленський Олег Олексійович\nОлег\nПівденне\nХарківська область\nБіленський Олег Олексійович\nБіленський\nАдміністративний місцевий суд\nсуддя харківського окружного адміністративного суду\nХарківська область\n159831.26\n12493.48\n11782.28\n159831.26\n24275.76\n2015\nКононова Юлія В'ячеславівна\nПодружжя\nБіленська Єлизавета Олегівна\nДитина\nБіленська Евеліна Олегівна\nДитина\nХарківська область\nПівденне\nОлексійович\nБіленський\nХарківська область\nАдміністративний місцевий суд\nсуддя харківського окружного адміністративного суду\nБіленський Олег Олексійович\nБіленський Олег Олексійович\nОлег Олексійович Біленський\nОлег Біленський\nБіленський Олег Олексійович\nОлег","general":{"inn":"","inn_hidden":true,"last_name":"Біленський","post":{"post":"суддя харківського окружного адміністративного суду","region":"Харківська область","candidate":"","office_hidden":false,"office":"Адміністративний місцевий суд","office_unclear":false},"name":"Олег","full_name":"Біленський Олег Олексійович","family_raw":"","addresses":[{"place_address":"","place_district_hidden":false,"place_city_type":"","place_city_hidden":false,"place_address_unclear":false,"place_city_type_hidden":false,"place_city":"Південне","place":"Харківська область","place_district":"","place_address_hidden":false,"place_hidden":true,"place_city_unclear":true}],"family":[{"inn":"","inn_hidden":true,"inn_unclear":false,"relations_hidden":false,"relations_other":"","relations":"Подружжя","name_hidden":false,"family_name":"Кононова Юлія В'ячеславівна","name_unclear":true},{"inn":"","inn_hidden":false,"inn_unclear":false,"relations_hidden":false,"relations_other":"","relations":"Дитина","name_hidden":false,"family_name":"Біленська Єлизавета Олегівна","name_unclear":false},{"inn":"","inn_hidden":false,"inn_unclear":false,"relations_hidden":false,"relations_other":"","relations":"Дитина","name_hidden":false,"family_name":"Біленська Евеліна Олегівна","name_unclear":false}],"full_name_suggest":{"output":"Біленський Олег Олексійович","input":["Біленський Олег Олексійович","Олег Олексійович Біленський","Олег Біленський"]},"patronymic":"Олексійович"},"source":"VULYK","estate":{"23":[{"region_unclear":false,"space_unclear":false,"costs_comment_hidden":false,"costs_comment":"","address_hidden":true,"region_hidden":false,"space_comment":"","space":"1554","address":"м. Південне","region":"Харківська область","address_unclear":true,"costs_rent_comment":"","costs":"","space_units":"м²","costs_rent":""},{"costs":"","space_units_unclear":false,"costs_comment":"","address_hidden":false,"region_hidden":false,"space_comment":"","space":"45.65","address":"","region":"Харківська область","costs_rent_comment":"","space_units":"м²","space_units_hidden":false,"costs_rent":""}],"24":[{"costs":"","costs_comment":"","address_hidden":true,"region_hidden":false,"space_comment":"","space":"41.3","address":"м. Південне","region":"Харківська область","address_unclear":true,"costs_rent_comment":"","space_units":"м²","costs_rent":""},{"costs":"","costs_comment":"","address_hidden":false,"region_hidden":false,"space_comment":"","space":"45.65","address":"м. Південне","region":"Харківська область","address_unclear":true,"costs_rent_comment":"","space_units":"м²","costs_rent":""}],"31":[{"space_unclear":false,"address_hidden":true,"region_hidden":false,"space_comment":"","space":"68.7","address":"м. Харків","region":"Харківська область","costs_property":"","costs_rent_comment":"","space_comment_unclear":false,"space_units":"м²","costs_property_comment":"","costs_rent":""},{"address_hidden":false,"region_hidden":false,"space_comment":"","space":"66.4","address":"м. Харків","region":"Харківська область","costs_property":"","costs_rent_comment":"","space_comment_unclear":false,"space_units":"м²","costs_property_comment":"","costs_rent":""}],"32":[{"address_hidden":false,"region_hidden":false,"space_comment":"","space":"","address":"","region":"Харківська область","costs_property":"","costs_rent_comment":"","address_unclear":false,"space_units":"м²","costs_property_comment":"","costs_rent":""}]},"intro":{"declaration_year":"2015","isnotdeclaration":""}}