{"income":{"5":{"family_comment":"відомості не надано","value":"205423","family":"","comment":""},"6":{"family_comment":"","value":"192806","family":"","comment":"","family_hidden":false},"7":{"family_comment":"","value":"","source_name":"","family":"","comment":""},"8":{"family_comment":"","value":"","family":"","comment":""},"9":{"value":"","value_unclear":false,"family_hidden":false,"family_comment":"","family":"","comment":""},"10":{"value":"12617","family_comment":"","family_hidden":false,"value_hidden":false,"family_unclear":false,"family":"","comment":""},"11":{"family_comment":"","value":"","family":"","comment":""},"12":{"family_comment":"","value":"","family":"","comment":""},"13":{"family_comment":"","value":"","family":"","comment":""},"14":{"family_comment":"","value":"","family":"","comment":""},"15":{"family_comment":"","value":"","family":"","comment":""},"16":{"family_comment":"","value":"","family":"","comment":""},"17":{"family_comment":"","value":"","family":"","comment":""},"18":{"family_comment":"","value":"","family":"","comment":""},"19":{"family_comment":"","value":"","family":"","comment":""},"20":{"value":"","comment_unclear":false,"family_comment":"","family":"","comment":"","family_comment_unclear":false}},"vehicle":{"35":[{"brand_info":"","sum":"","brand":"Москвич / АЗЛК 412","sum_comment":"","brand_unclear":false,"year":"1977","brand_hidden":false,"brand_info_unclear":false,"sum_rent_comment":"","sum_rent":"","sum_unclear":false},{"brand_info":"2979 куб. см.","sum":"","brand":"BMW","sum_comment":"","sum_comment_unclear":false,"year":"2010","sum_rent_comment":"","sum_rent":""}],"40":[{"brand_info":"відомості не надано","sum_rent_comment":"","brand":"","sum_comment":"","year":"","brand_info_unclear":false,"sum":"","sum_rent":""}]},"id":"vulyk_75_137","declaration":{"additional_info_text":"У п. 4. Члени сім'ї декларанта під прізвищем дружини Парінова М. В. зазначено 'не надала інформацію' Уздовж стор. 2 (паперової) пп. 6-11 справа вертикальний напис 'Відомостей не надано' Уздовж стор. 3 (паперової) п. 22 справа вертикальний напис 'Відомостей не надано'","notfull_lostpages":"","date":"2014-03-20T00:00:00","notfull":"","additional_info":"1","url":"http://static.declarations.com.ua/declarations/chosen_ones/judges_batch/1798_parinov_andrii_borysovych.pdf"},"liabilities":{"54":{"sum_foreign_comment":"","sum":"","sum_comment":"","sum_foreign":""},"55":{"sum_foreign_comment":"","sum":"","sum_comment":"","sum_foreign":""},"56":{"sum_foreign_comment":"","sum":"","sum_comment":"","sum_foreign":""},"57":{"sum_foreign_comment":"","sum":"","sum_comment":"","sum_foreign":""},"58":{"sum_foreign_comment":"","sum":"","sum_comment":"","sum_foreign":""},"59":{"sum_foreign_comment":"","sum":"","sum_comment":"","sum_comment_unclear":false,"sum_unclear":false,"sum_foreign":""},"60":{"sum_foreign_comment":"","sum":"","sum_comment":"","sum_foreign":""},"61":{"sum_foreign_comment":"","sum":"","sum_comment":"","sum_foreign":""},"62":{"sum_foreign_comment":"","sum":"","sum_comment":"","sum_unclear":false,"sum_foreign":""},"63":{"sum_foreign_comment":"","sum":"","sum_comment":"","sum_foreign":""},"64":{"sum_foreign_comment":"","sum":"","sum_comment":"","sum_foreign":""}},"ft_src":"Москвич / АЗЛК 412\n1977\n2979 куб. см.\nBMW\n2010\nвідомості не надано\nвідомості не надано\nвідомості не надано\n850\n400\nвідомості не надано\nвідомості не надано\n2000\n33\n30\n1\nУ п. 4. Члени сім'ї декларанта під прізвищем дружини Парінова М. В. зазначено 'не надала інформацію' Уздовж стор. 2 (паперової) пп. 6-11 справа вертикальний напис 'Відомостей не надано' Уздовж стор. 3 (паперової) п. 22 справа вертикальний напис 'Відомостей не надано'\n2013\n192806\n12617\nвідомості не надано\n205423\n1977\nМосквич / АЗЛК 412\n2979 куб. см.\nBMW\n2010\nвідомості не надано\nУ п. 4. Члени сім'ї декларанта під прізвищем дружини Парінова М. В. зазначено 'не надала інформацію' Уздовж стор. 2 (паперової) пп. 6-11 справа вертикальний напис 'Відомостей не надано' Уздовж стор. 3 (паперової) п. 22 справа вертикальний напис 'Відомостей не надано'\n1\n2013\nПарінов\nБорисович\nПодружжя\nПарінова М. В\nІнше\nпасинок\nГайдай Я. О\nПарінов Андрій Борисович\nАндрій Борисович Парінов\nАндрій Парінов\nПарінов Андрій Борисович\nАндрій\nПарінов Андрій Борисович\nАпеляційний адміністративний суд\nсуддя київського апеляційного адміністративного суду\nм. Київ\n192806\n205423\nвідомості не надано\n12617\n30\n33\n2000\n400\n850\nвідомості не надано\nвідомості не надано\nвідомості не надано\nвідомості не надано\nПарінова М. В\nПодружжя\nпасинок\nГайдай Я. О\nІнше\nПарінов\nБорисович\nсуддя київського апеляційного адміністративного суду\nм. Київ\nАпеляційний адміністративний суд\nПарінов Андрій Борисович\nПарінов Андрій Борисович\nАндрій Борисович Парінов\nАндрій Парінов\nПарінов Андрій Борисович\nАндрій","general":{"inn_hidden":true,"inn":"","last_name":"Парінов","post":{"office":"Апеляційний адміністративний суд","region":"м. Київ","post":"суддя київського апеляційного адміністративного суду"},"name":"Андрій","full_name":"Парінов Андрій Борисович","family_raw":"","addresses":[{"place_district":"","place_address_hidden":true,"place_hidden":true,"place_address":"","place_district_hidden":true,"place_city_type":"","place_city_hidden":true,"place_city_type_hidden":false,"place_city":"","place":""}],"family":[{"inn":"","inn_hidden":true,"relations_hidden":false,"family_name":"Парінова М. В","relations_other":"","relations":"Подружжя","name_hidden":false,"name_unclear":false},{"inn":"","inn_hidden":true,"family_name":"Гайдай Я. О","relations_other":"пасинок","relations":"Інше","name_hidden":false,"name_unclear":false}],"full_name_suggest":{"output":"Парінов Андрій Борисович","input":["Парінов Андрій Борисович","Андрій Борисович Парінов","Андрій Парінов"]},"patronymic":"Борисович"},"source":"VULYK","estate":{"23":[{"costs":"","costs_comment":"","address_hidden":false,"region_hidden":true,"space_comment":"","space":"400","address":"","region":"","costs_rent_comment":"","space_units":"м²","space_units_hidden":false,"costs_rent":"850"}],"24":[{"costs_rent":"","region":"","costs":"","costs_rent_comment":"","costs_comment":"","region_hidden":true,"space_comment":"","space_units":"м²","space":"","address":""}],"25":[{"space_unclear":false,"costs":"","costs_comment":"","address_hidden":false,"region_hidden":true,"space_comment":"","space_hidden":false,"space":"33","address":"","region":"","costs_rent_comment":"","space_units":"м²","costs_rent":"2000"}],"26":[{"costs_rent":"","region":"","costs":"","costs_rent_comment":"","costs_comment":"","address_hidden":false,"region_hidden":true,"space_comment":"","space_units":"м²","space":"30","address":""}],"29":[{"space_units_unclear":false,"address_hidden":false,"region_hidden":false,"space_comment":"відомості не надано","space":"","address":"відомості не надано","region":"","costs_property":"","costs_rent_comment":"","space_units":"м²","costs_property_comment":"","costs_rent":""}],"31":[{"space_unclear":false,"address_hidden":false,"region_hidden":false,"space_comment":"відомості не надано","space":"","address":"відомості не надано","region":"","costs_property":"","costs_rent_comment":"","space_units":"м²","costs_property_comment":"","costs_rent":""}]},"intro":{"declaration_year":"2013","isnotdeclaration":""}}