{"income":{"5":{"family_comment":"","family_unclear":false,"value":"256334","family":"5057","comment":""},"6":{"value":"252167","family_comment":"","comment_unclear":false,"family_unclear":false,"family":"","comment":""},"7":{"source_name_unclear":false,"value":"","family_comment":"","source_name":"","family":"","comment":"","source_name_hidden":false},"8":{"family_comment":"","value":"","family":"","comment":""},"9":{"family_comment":"","value":"","family":"","comment":""},"10":{"family_comment":"","value":"","comment_unclear":false,"family":"","comment":""},"11":{"family_comment":"","value":"","family":"","comment":""},"12":{"family_comment":"","value":"","family":"5057","comment":""},"13":{"family_comment":"","value":"","family":"","comment":""},"14":{"family_comment":"","value":"","family":"","comment":""},"15":{"family_comment":"","value":"","family":"","comment":""},"16":{"value":"","comment_hidden":false,"value_hidden":false,"family_comment":"","family":"","comment":"","family_comment_unclear":false},"17":{"family_comment":"","value":"","family":"","comment":""},"18":{"family_comment":"","value":"","family":"","comment":""},"19":{"family_comment":"","value":"4167","family":"","comment":""},"20":{"value":"","family_comment":"","value_unclear":false,"family":"","family_unclear":false,"comment_unclear":false,"comment":"","family_comment_unclear":false}},"vehicle":{"35":[{"brand_info":"1500 куб. см.","sum_rent_comment":"","year":"1998","sum_rent_unclear":false,"brand_info_hidden":false,"brand_info_unclear":false,"sum_rent":"","sum":"","brand":"ВАЗ-21093","sum_comment":"","sum_comment_unclear":false,"brand_hidden":false,"sum_unclear":false,"brand_unclear":false}]},"id":"vulyk_58_70","banks":{"45":[{"sum_foreign_comment":"","sum_units":"UAH","sum_comment":"","sum_comment_unclear":false,"sum_hidden":false,"sum_foreign_units":"UAH","sum_comment_hidden":false,"sum_units_hidden":false,"sum":"","sum_foreign":""},{"sum_foreign_comment":"","sum_units":"","sum_comment":"","sum_foreign_units":"","sum":"","sum_foreign":""}],"46":[{"sum_foreign_comment":"","sum_units":"UAH","sum_comment":"","sum_foreign_units":"UAH","sum_comment_hidden":false,"sum":"","sum_foreign":""}],"47":[{"sum_foreign_comment":"","sum_units":"UAH","sum_comment":"","sum_foreign_units":"UAH","sum_comment_hidden":false,"sum":"","sum_foreign":""}],"48":[{"sum_foreign_comment":"","sum_units":"UAH","sum_comment":"","sum_foreign_units":"UAH","sum":"","sum_foreign":""}],"49":[{"sum_foreign_comment":"","sum_units":"UAH","sum_comment":"","sum_foreign_units":"UAH","sum":"","sum_foreign":""}],"50":[{"sum_foreign_comment":"","sum_units":"UAH","sum_comment":"","sum_foreign_units":"UAH","sum":"","sum_foreign":""}],"51":[{"sum_foreign_comment":"","sum_units":"UAH","sum_comment":"","sum_foreign_units":"UAH","sum_comment_hidden":false,"sum":"","sum_foreign":""},{"sum_foreign_comment":"","sum_units":"","sum_comment":"","sum_comment_hidden":false,"sum":"","sum_foreign":""}],"52":[{"sum_foreign_comment":"","sum_units":"UAH","sum_comment":"","sum_foreign_units":"UAH","sum":"","sum_foreign":""}],"53":[{"sum_foreign_comment":"","sum_units":"UAH","sum_comment":"","sum_foreign_units":"UAH","sum":"","sum_foreign":""}]},"declaration":{"additional_info_text":"","notfull_lostpages":"","date":"2015-03-30T00:00:00","notfull":"","additional_info":"","url":"http://static.declarations.com.ua/declarations/chosen_ones/mega_batch/shydlovskyi_viktor_bronislavovych.pdf"},"liabilities":{"54":{"sum_foreign_comment":"","sum":"","sum_hidden":false,"sum_comment":"","sum_foreign":""},"55":{"sum_foreign_comment":"","sum":"","sum_hidden":false,"sum_comment":"","sum_foreign":""},"56":{"sum_foreign_comment":"","sum":"","sum_comment":"","sum_unclear":false,"sum_foreign":""},"57":{"sum_foreign_comment":"","sum":"","sum_comment":"","sum_comment_unclear":false,"sum_comment_hidden":false,"sum_unclear":false,"sum_foreign":""},"58":{"sum_foreign_comment":"","sum":"","sum_comment":"","sum_comment_unclear":false,"sum_comment_hidden":false,"sum_unclear":false,"sum_foreign":""},"59":{"sum_foreign_comment":"","sum":"","sum_comment":"","sum_foreign":""},"60":{"sum_foreign_comment":"","sum":"","sum_comment":"","sum_comment_unclear":false,"sum_unclear":false,"sum_foreign":""},"61":{"sum_foreign_comment":"","sum":"","sum_comment":"","sum_foreign":""},"62":{"sum_foreign_comment":"","sum":"","sum_comment":"","sum_foreign":""},"63":{"sum_foreign_comment":"","sum":"","sum_comment":"","sum_comment_unclear":false,"sum_comment_hidden":false,"sum_unclear":false,"sum_foreign":""},"64":{"sum_foreign_comment":"","sum":"","sum_comment":"","sum_comment_unclear":false,"sum_comment_hidden":false,"sum_unclear":false,"sum_foreign":""}},"ft_src":"Любар\nЛюбарський\nСМТ\nЖитомирська область\nсуддя житомирського апеляційного адміністративного суду\nЖитомирська область\nАпеляційний адміністративний суд\nВіктор\nШидловська Є. Г\nПодружжя\nБроніславович\nШидловський Віктор Броніславович\nВіктор Броніславович Шидловський\nВіктор Шидловський\nШидловський Віктор Броніславович\nШидловський Віктор Броніславович\nШидловський\n1500 куб. см.\nВАЗ-21093\n1998\n2014\n1500 куб. см.\nВАЗ-21093\n1998\n30865\nЖитомирська область\nЛюбарський р-н\n20\nсмт. Любар\nЖитомирська область\n28.5\nсмт. Любар\nЖитомирська область\nПодружжя\nШидловська Є. Г\nШидловський Віктор Броніславович\nВіктор Броніславович Шидловський\nВіктор Шидловський\nШидловський Віктор Броніславович\nШидловський Віктор Броніславович\nВіктор\nБроніславович\nАпеляційний адміністративний суд\nсуддя житомирського апеляційного адміністративного суду\nЖитомирська область\nШидловський\nСМТ\nЛюбар\nЖитомирська область\nЛюбарський\n252167\n5057\n256334\n5057\n4167\n2014\nЛюбарський р-н\n30865\nЖитомирська область\nсмт. Любар\n20\nЖитомирська область\nсмт. Любар\n28.5\nЖитомирська область\nШидловська Є. Г\nПодружжя\nБроніславович\nШидловський\nВіктор\nШидловський Віктор Броніславович\nВіктор Броніславович Шидловський\nВіктор Шидловський\nШидловський Віктор Броніславович\nЖитомирська область\nЛюбар\nЛюбарський\nСМТ\nЖитомирська область\nсуддя житомирського апеляційного адміністративного суду\nАпеляційний адміністративний суд\nШидловський Віктор Броніславович\n252167\n5057\n256334\n4167\n5057\n1998\nВАЗ-21093\n1500 куб. см.\n4167\n5057\n256334\n5057\n252167\nсмт. Любар\nЖитомирська область\n28.5\nЛюбарський р-н\nЖитомирська область\n30865\nсмт. Любар\nЖитомирська область\n20\n2014","general":{"inn":"","name":"Віктор","inn_unclear":false,"family":[{"inn":"","inn_hidden":false,"relations_hidden":false,"family_name":"Шидловська Є. Г","relations_other":"","relations":"Подружжя","name_hidden":false,"name_unclear":false}],"inn_hidden":true,"family_raw":"","last_name":"Шидловський","post":{"post_unclear":false,"post":"суддя житомирського апеляційного адміністративного суду","post_hidden":false,"region":"Житомирська область","region_hidden":false,"office":"Апеляційний адміністративний суд","office_hidden":false,"office_unclear":false},"full_name_suggest":{"output":"Шидловський Віктор Броніславович","input":["Шидловський Віктор Броніславович","Віктор Броніславович Шидловський","Віктор Шидловський"]},"full_name":"Шидловський Віктор Броніславович","addresses":[{"place_city_type_hidden":false,"place_district_hidden":false,"place_city_type":"СМТ","place_city_hidden":false,"place_address_unclear":false,"place_address":"","place_hidden":false,"place":"Житомирська область","place_district":"Любарський","place_unclear":false,"place_city":"Любар","place_address_hidden":true,"place_district_unclear":false}],"patronymic":"Броніславович","last_name_unclear":false},"source":"VULYK","estate":{"23":[{"space_unclear":false,"costs":"","costs_comment":"","address_hidden":false,"region_hidden":false,"space_comment":"","space_hidden":false,"space":"30865","address":"Любарський р-н","costs_comment_unclear":false,"costs_rent_comment_unclear":false,"region":"Житомирська область","address_unclear":false,"costs_rent_comment":"","costs_unclear":false,"space_units":"м²","costs_rent":""},{"costs":"","costs_comment":"","address_hidden":false,"region_hidden":false,"space_comment":"","space":"","address":"","region":"","address_unclear":false,"costs_rent_comment":"","space_units":"","costs_rent":""},{"costs":"","costs_comment":"","address_hidden":false,"region_hidden":false,"space_comment":"","space":"","address":"","region":"","address_unclear":false,"costs_rent_comment":"","space_units":"","costs_rent":""},{"costs_rent":"","region":"","costs":"","costs_rent_comment":"","costs_comment":"","space_comment":"","space_units":"","space":"","address":""},{"costs_rent":"","costs":"","costs_rent_comment":"","costs_comment":"","space_comment":"","space_units":"","space":"","address":""}],"25":[{"region_unclear":false,"space_hidden":false,"costs":"","costs_comment":"","address_hidden":false,"region_hidden":false,"space_comment":"","space":"28.5","address":"смт. Любар","region":"Житомирська область","costs_rent_comment":"","space_comment_unclear":false,"space_units":"м²","costs_rent":""}],"27":[{"space_hidden":false,"costs":"","costs_comment":"","address_hidden":false,"region_hidden":false,"space_comment":"","space":"20","address":"смт. Любар","region":"Житомирська область","costs_rent_comment":"","space_units":"м²","costs_rent":""}]},"intro":{"declaration_year":"2014","isnotdeclaration":"","declaration_year_hidden":false}}