{"income":{"5":{"value":"61397.21","family_comment":"","value_unclear":false,"family":"194375","family_unclear":false,"comment_unclear":false,"comment":"","family_comment_unclear":false},"6":{"value":"49217.21","family_comment":"","value_unclear":false,"family_unclear":false,"family":"194375","comment":""},"7":{"source_name_unclear":false,"value":"","value_unclear":false,"family_comment":"","source_name":"","family":"","comment":"","source_name_hidden":true},"8":{"family_comment":"","value":"","family":"","comment":""},"9":{"family_comment":"","value":"","family":"","comment":""},"10":{"family_comment":"","value":"12180","value_unclear":false,"family":"","comment":""},"11":{"value":"","value_unclear":false,"value_hidden":false,"family_comment":"","family":"","comment":""},"12":{"family_comment":"","value":"","family":"","comment":"","value_hidden":false},"13":{"family_comment":"","value":"","family":"","comment":""},"14":{"family_comment":"","value":"","family":"","comment":""},"15":{"family_comment":"","value":"","family":"","comment":""},"16":{"family_comment":"","value":"","family":"","comment":""},"17":{"family_comment":"","value":"","family":"","comment":""},"18":{"family_comment":"","value":"","family":"","comment":""},"19":{"family_comment":"","family_unclear":false,"value":"","family":"","comment":""},"20":{"family_comment":"","family_unclear":false,"value":"","family":"","comment":""}},"id":"vulyk_61_105","declaration":{"additional_info_text":"","notfull_lostpages":"","date":"2015-03-31T00:00:00","notfull":"","additional_info":"","url":"http://static.declarations.com.ua/declarations/chosen_ones/mega_batch/podus_hanna_serhiivna.pdf"},"liabilities":{"54":{"sum_foreign_comment":"","sum":"","sum_comment":"","sum_comment_unclear":false,"sum_unclear":false,"sum_foreign":""},"55":{"sum_foreign_comment":"","sum":"","sum_comment":"","sum_foreign":""},"56":{"sum_foreign_comment":"","sum":"","sum_comment":"","sum_unclear":false,"sum_foreign":""},"57":{"sum_foreign_comment":"","sum":"","sum_comment":"","sum_comment_hidden":false,"sum_unclear":false,"sum_foreign":""},"58":{"sum_foreign_comment":"","sum":"","sum_comment":"","sum_unclear":false,"sum_foreign":""},"59":{"sum_foreign_comment":"","sum":"","sum_comment":"","sum_foreign":""},"60":{"sum_foreign_comment":"","sum_foreign_hidden":false,"sum_comment":"","sum_hidden":false,"sum":"","sum_foreign":""},"61":{"sum_foreign_comment":"","sum":"","sum_comment":"","sum_foreign":""},"62":{"sum_foreign_comment":"","sum":"","sum_comment":"","sum_unclear":false,"sum_foreign":""},"63":{"sum_foreign_comment":"","sum":"","sum_comment":"","sum_hidden":false,"sum_unclear":false,"sum_foreign":""},"64":{"sum_foreign_comment":"","sum":"","sum_hidden":false,"sum_comment":"","sum_foreign":""}},"ft_src":"суддя дзержинського районного суду м. харкова\nХарківська область\nЗагальний місцевий суд\nГанна\nПодус М. О\nПодружжя\nПодус К. М\nДитина\nПодус В. М\nДитина\nСергіївна\nПодус\nПодус Ганна Сергіївна\nПодус Ганна Сергіївна\nГанна Сергіївна Подус\nГанна Подус\nПодус Ганна Сергіївна\n12180\n61397.21\n194375\n49217.21\n194375\n90.3\n2014\n194375\n49217.21\n12180\n194375\n61397.21\n90.3\nПодружжя\nПодус М. О\nДитина\nПодус К. М\nДитина\nПодус В. М\nПодус Ганна Сергіївна\nГанна Сергіївна Подус\nГанна Подус\nПодус Ганна Сергіївна\nГанна\nПодус Ганна Сергіївна\nПодус\nХарківська область\nЗагальний місцевий суд\nсуддя дзержинського районного суду м. харкова\nСергіївна\n194375\n49217.21\n61397.21\n194375\n12180\n2014\nПодус М. О\nПодружжя\nПодус К. М\nДитина\nПодус В. М\nДитина\nСергіївна\nПодус\nПодус Ганна Сергіївна\nГанна Сергіївна Подус\nГанна Подус\nПодус Ганна Сергіївна\nХарківська область\nсуддя дзержинського районного суду м. харкова\nЗагальний місцевий суд\nПодус Ганна Сергіївна\nГанна\n90.3\n2014","general":{"inn":"","name":"Ганна","patronymic_unclear":false,"family":[{"inn":"","inn_hidden":true,"relations_unclear":false,"relations_hidden":false,"relations_other":"","relations":"Подружжя","name_hidden":false,"family_name":"Подус М. О","name_unclear":false},{"inn":"","relations":"Дитина","relations_other":"","inn_hidden":false,"family_name":"Подус К. М","name_hidden":false,"name_unclear":false},{"inn":"","relations":"Дитина","relations_other":"","inn_hidden":false,"family_name":"Подус В. М","name_hidden":false,"name_unclear":false}],"patronymic":"Сергіївна","inn_hidden":true,"family_raw":"","inn_unclear":false,"post":{"post_unclear":false,"region_unclear":false,"post":"суддя дзержинського районного суду м. харкова","office":"Загальний місцевий суд","region":"Харківська область","post_hidden":false,"office_hidden":false,"region_hidden":false},"last_name_unclear":false,"full_name":"Подус Ганна Сергіївна","addresses":[{"place_address":"","place_district_hidden":true,"place_city_type":"","place_city_hidden":true,"place_address_unclear":false,"place_city_type_hidden":true,"place_hidden":true,"place":"","place_district":"","place_address_hidden":true,"place_city":"","place_district_unclear":false}],"last_name":"Подус","patronymic_hidden":false,"full_name_suggest":{"output":"Подус Ганна Сергіївна","input":["Подус Ганна Сергіївна","Ганна Сергіївна Подус","Ганна Подус"]},"name_unclear":false},"source":"VULYK","estate":{"31":[{"space_unclear":false,"address_hidden":false,"region_hidden":true,"space_comment":"","space_hidden":false,"space":"90.3","address":"","region":"","costs_property":"","costs_rent_comment":"","space_comment_unclear":false,"space_units":"м²","costs_property_comment":"","costs_rent":""}]},"intro":{"declaration_year":"2014","isnotdeclaration":"","declaration_year_hidden":false}}