{"income":{"5":{"family_comment":"","value":"599397","family":"16787","comment":""},"6":{"family_comment":"","value":"244700","family":"16787","comment":""},"7":{"family_comment":"","value":"4073","source_name":"Донецький Національний Університет","family":"","comment":""},"8":{"family_comment":"","value":"","family":"","comment":""},"9":{"value":"504","comment_unclear":false,"family_comment":"","family":"","comment":"","family_comment_unclear":false},"10":{"family_comment":"","value":"","family":"","comment":""},"11":{"family_comment":"","value":"","family":"","comment":""},"12":{"family_comment":"","value":"","family":"","comment":""},"13":{"family_comment":"","value":"","family":"","comment":""},"14":{"family_comment":"","value":"","family":"","comment":""},"15":{"family_comment":"","value":"","family":"","comment":""},"16":{"family_comment":"","value":"350000","family":"","comment":""},"17":{"family_comment":"","value":"","family":"","comment":""},"18":{"family_comment":"","value":"","family":"","comment":""},"19":{"value":"","family_comment":"","value_unclear":false,"family_unclear":false,"family":"","comment":""},"20":{"value":"120","family_comment":"","comment_unclear":false,"comment_hidden":false,"family_unclear":false,"value_unclear":false,"family_comment_unclear":false,"family_comment_hidden":false,"comment":"","family":""}},"vehicle":{"40":[{"year_hidden":false,"brand_info":"1598","sum":"","brand":"Nissan Juke","sum_comment":"","year":"2014","brand_hidden":false,"brand_info_hidden":false,"brand_info_unclear":false,"sum_rent_comment":"","sum_rent":""}]},"id":"vulyk_106_90","declaration":{"additional_info_text":"","notfull_lostpages":"","date":"2016-03-30T00:00:00","notfull":"","additional_info":"","url":"http://static.declarations.com.ua/declarations/chosen_ones/judges_batch/2229_zahorodniuk_andrii_hryhorovych.pdf"},"liabilities":{"54":{"sum_foreign_comment":"","sum":"","sum_comment":"","sum_comment_unclear":false,"sum_hidden":false,"sum_comment_hidden":false,"sum_foreign":""},"55":{"sum_foreign_comment":"","sum":"","sum_foreign":"","sum_comment":"","sum_hidden":false},"56":{"sum_foreign_comment":"","sum":"","sum_comment":"","sum_hidden":false,"sum_comment_hidden":false,"sum_unclear":false,"sum_foreign":""},"57":{"sum_foreign_comment":"","sum":"26335","sum_comment":"Приватбанк","sum_hidden":false,"sum_comment_hidden":false,"sum_foreign":""},"58":{"sum_foreign_comment":"","sum":"","sum_comment":"","sum_hidden":false,"sum_comment_hidden":false,"sum_foreign":""},"59":{"sum_foreign_comment":"","sum":"","sum_comment":"","sum_foreign":""},"60":{"sum_foreign_comment":"","sum":"","sum_comment":"","sum_hidden":false,"sum_comment_hidden":false,"sum_foreign":""},"61":{"sum_foreign_comment":"","sum":"","sum_comment":"","sum_foreign":""},"62":{"sum_foreign_comment":"","sum":"","sum_comment":"","sum_comment_hidden":false,"sum_unclear":false,"sum_foreign":""},"63":{"sum_foreign_comment":"","sum":"142542","sum_comment":"Креді Агріколь Банк індекс Банк","sum_foreign":""},"64":{"sum_foreign_comment":"","sum":"3582","sum_comment":"","sum_foreign":""}},"ft_src":"1598\nNissan Juke\n2014\n2500\n900\n101.1\n2015\n16787\n244700\n504\n4073\nДонецький Національний Університет\n16787\n599397\n350000\n120\n1598\n2014\nNissan Juke\n2500\n900\n101.1\nЗагороднюк Андрій Григорович\nАндрій Григорович Загороднюк\nАндрій Загороднюк\nЗагороднюк Андрій Григорович\nЗагороднюк Андрій Григорович\nПодружжя\nЗагороднюк О. А\nДитина\nЗагороднюк Д. А\nДитина\nЗагороднюк І. А\nАндрій\nЗагороднюк\nВінницька область\nАпеляційний адміністративний суд\nсуддя вінницького апеляційного адміністративного суду\nГригорович\nПриватбанк\n26335\nКреді Агріколь Банк індекс Банк\n142542\n3582\n4073\nДонецький Національний Університет\n244700\n16787\n120\n599397\n16787\n350000\n504\n2015\nПриватбанк\n26335\nКреді Агріколь Банк індекс Банк\n142542\n3582\nЗагороднюк О. А\nПодружжя\nЗагороднюк Д. А\nДитина\nЗагороднюк І. А\nДитина\nГригорович\nЗагороднюк\nАндрій\nЗагороднюк Андрій Григорович\nАндрій Григорович Загороднюк\nАндрій Загороднюк\nЗагороднюк Андрій Григорович\nВінницька область\nАпеляційний адміністративний суд\nсуддя вінницького апеляційного адміністративного суду\nЗагороднюк Андрій Григорович","general":{"inn":"","name":"Андрій","last_name":"Загороднюк","family":[{"inn":"","inn_hidden":true,"relations_unclear":false,"relations_hidden":false,"relations_other":"","relations":"Подружжя","name_hidden":true,"family_name":"Загороднюк О. А","name_unclear":false},{"inn":"","inn_hidden":false,"relations_unclear":false,"family_name":"Загороднюк Д. А","relations_other":"","relations":"Дитина","name_hidden":false,"name_unclear":false},{"inn":"","relations":"Дитина","name_hidden":false,"inn_hidden":false,"family_name":"Загороднюк І. А","name_unclear":false}],"inn_hidden":true,"family_raw":"","inn_unclear":false,"post":{"region_unclear":false,"post":"суддя вінницького апеляційного адміністративного суду","post_hidden":false,"region":"Вінницька область","office":"Апеляційний адміністративний суд","office_unclear":false},"full_name":"Загороднюк Андрій Григорович","addresses":[{"place_district":"","place_address_hidden":true,"place_city":"","place_address":"","place_district_hidden":true,"place_city_type":"","place_city_hidden":true,"place_city_type_hidden":false,"place_hidden":true,"place":""}],"patronymic":"Григорович","full_name_suggest":{"output":"Загороднюк Андрій Григорович","input":["Загороднюк Андрій Григорович","Андрій Григорович Загороднюк","Андрій Загороднюк"]},"name_unclear":false},"source":"VULYK","estate":{"23":[{"region_unclear":false,"space_hidden":false,"costs":"","costs_comment":"","address_hidden":true,"region_hidden":true,"space_comment":"","space_unclear":false,"space":"2500","address":"","costs_comment_unclear":false,"costs_rent_comment_unclear":false,"region":"","address_unclear":false,"costs_rent_comment":"","space_comment_unclear":false,"space_comment_hidden":false,"space_units":"м²","costs_rent":""}],"25":[{"costs":"","costs_comment":"","address_hidden":false,"region_hidden":true,"space_comment":"","space":"101.1","address":"","region":"","costs_rent_comment":"","space_comment_unclear":false,"space_units":"м²","costs_rent":""}],"29":[{"region_unclear":false,"costs_property_comment":"","address_hidden":true,"region_hidden":true,"space_comment":"","space":"900","address":"","costs_rent_comment_unclear":false,"region":"","costs_property":"","costs_rent_comment":"","space_comment_unclear":false,"address_unclear":false,"space_units":"м²","space_units_unclear":false,"costs_rent":""}]},"intro":{"declaration_year":"2015","isnotdeclaration":""}}