{"income":{"5":{"family_comment":"","value":"301965","family":"276085","comment":"","family_hidden":false},"6":{"family_comment":"","value":"244033","family":"262274","comment":"","family_hidden":false},"7":{"family_comment":"","value":"14986","source_name":"ТОВ Академія адвокатури України (01032, м. Київ, бул. Тараса Шевченка,27, код 22928626) Національна школа суддів України (код 37451388","family":"","comment":""},"8":{"family_comment":"","value":"","family":"","comment":""},"9":{"family_comment":"","value":"9664","family":"8040","comment":""},"10":{"family_comment":"","value":"13398","family":"","comment":""},"11":{"family_comment":"","value":"","family":"","comment":""},"12":{"family_comment":"","value":"","family":"","comment":""},"13":{"family_comment":"","value":"","family":"","comment":""},"14":{"family_comment":"","value":"","family":"","comment":""},"15":{"family_comment":"","value":"","family":"","comment":""},"16":{"family_comment":"","value":"","family":"","comment":""},"17":{"family_comment":"","value":"","family":"","comment":""},"18":{"family_comment":"","value":"5771","family":"5771","comment":""},"19":{"family_comment":"","value":"3700","family":"","comment":""},"20":{"family_comment":"","value":"10413","family":"","comment":""}},"vehicle":{"40":[{"year_hidden":false,"brand_info":"3.0","sum":"","brand":"Mitsubishi Pajero","sum_comment":"","year":"2007","brand_hidden":false,"brand_info_hidden":false,"sum_rent_comment":"","sum_rent":""}]},"id":"vulyk_105_17","banks":{"45":[{"sum_foreign_comment":"","sum":"2","sum_comment":"","sum_foreign_units":"UAH","sum_comment_hidden":false,"sum_units":"UAH","sum_foreign":""}],"47":[{"sum_foreign_comment":"","sum":"25","sum_comment":"","sum_foreign_units":"UAH","sum_units":"UAH","sum_foreign":""}],"51":[{"sum_foreign_comment":"","sum":"305","sum_comment":"","sum_foreign_units":"UAH","sum_units":"UAH","sum_foreign":""}],"52":[{"sum_foreign_comment":"","sum":"106677","sum_comment":"","sum_foreign_units":"UAH","sum_units":"UAH","sum_foreign":""}]},"declaration":{"date":"2015-03-31T00:00:00","additional_info_text":"","additional_info":"","url":"http://static.declarations.com.ua/declarations/chosen_ones/judges_batch/4592_korotun_olena_mykolaivna.pdf"},"liabilities":{"54":{"sum_foreign_comment":"","sum_comment":"","sum":"","sum_comment_hidden":false,"sum_foreign":""},"55":{"sum_foreign_comment":"","sum":"","sum_comment":"","sum_foreign":""},"56":{"sum_foreign_comment":"","sum":"","sum_comment":"","sum_foreign":""},"57":{"sum_foreign_comment":"","sum":"","sum_comment":"","sum_comment_unclear":false,"sum_comment_hidden":false,"sum_foreign":""},"58":{"sum_foreign_comment":"","sum":"","sum_comment":"","sum_foreign":""},"59":{"sum_foreign_comment":"","sum":"","sum_comment":"","sum_foreign":""},"60":{"sum_foreign_comment":"","sum":"963","sum_comment":"","sum_foreign":""},"61":{"sum_foreign_comment":"","sum":"","sum_comment":"","sum_foreign":""},"62":{"sum_foreign_comment":"","sum":"","sum_foreign":"","sum_comment":"","sum_hidden":false},"63":{"sum_foreign_comment":"","sum":"167400","sum_comment":"","sum_foreign":""},"64":{"sum_foreign_comment":"","sum":"","sum_comment":"","sum_foreign":""}},"ft_src":"3.0\nMitsubishi Pajero\n2007\n25\n106677\n305\n2\n2014\n3.0\n2007\nMitsubishi Pajero\n2\n25\n305\n106677\n2014\nсуддя київського апеляційного господарського суду\nАпеляційний господарський суд\nм. Київ\nКоротун\nКоротун Олена Миколаївна\nОлена Миколаївна Коротун\nОлена Коротун\nКоротун Олена Миколаївна\nКоротун Олена Миколаївна\nОлена\nМиколаївна\nПодружжя\nКоротун В. М\nДитина\nКоротун М. В\nДитина\nКоротун В. В\n963\n167400\n14986\nТОВ Академія адвокатури України (01032, м. Київ, бул. Тараса Шевченка,27, код 22928626) Національна школа суддів України (код 37451388\n244033\n262274\n10413\n5771\n5771\n301965\n276085\n13398\n9664\n8040\n3700\n13.1\nмашиномісце, у власності\nКТП 10/0. 4 кв, у власності\n17.85\n1/2, у власності\n40.95\n1/2, у власності\n2001\nу власності\n2000\nу власності\n1200\nу власності\nнезавершене будівництво (одноповерхова дерев. коробка без вікон і без дверей, у власності\n123\nу власності\n40.95\n1/2, у власності\n963\n167400\nу власності\n2000\nу власності\n1200\nнезавершене будівництво (одноповерхова дерев. коробка без вікон і без дверей, у власності\nмашиномісце, у власності\n13.1\nКТП 10/0. 4 кв, у власності\nу власності\n2001\nу власності\n123\n1/2, у власності\n40.95\n1/2, у власності\n17.85\n1/2, у власності\n40.95\nКоротун В. М\nПодружжя\nКоротун М. В\nДитина\nКоротун В. В\nДитина\nМиколаївна\nКоротун\nм. Київ\nсуддя київського апеляційного господарського суду\nАпеляційний господарський суд\nКоротун Олена Миколаївна\nКоротун Олена Миколаївна\nОлена Миколаївна Коротун\nОлена Коротун\nКоротун Олена Миколаївна\nОлена\n262274\n244033\n13398\n5771\n5771\n14986\nТОВ Академія адвокатури України (01032, м. Київ, бул. Тараса Шевченка,27, код 22928626) Національна школа суддів України (код 37451388\n276085\n301965\n3700\n8040\n9664\n10413","general":{"inn":"","inn_hidden":true,"last_name":"Коротун","post":{"post_unclear":false,"region_unclear":false,"post":"суддя київського апеляційного господарського суду","office_hidden":false,"region":"м. Київ","office":"Апеляційний господарський суд","office_unclear":false},"name":"Олена","full_name":"Коротун Олена Миколаївна","family_raw":"","addresses":[{"place_district":"","place_address_hidden":false,"place_city":"","place_address":"","place_district_hidden":false,"place_city_type":"","place_city_hidden":false,"place_city_type_hidden":false,"place_hidden":true,"place":""}],"family":[{"inn":"","inn_hidden":true,"relations_hidden":false,"family_name":"Коротун В. М","relations_other":"","relations":"Подружжя","name_hidden":false,"name_unclear":false},{"inn":"","inn_hidden":false,"family_name":"Коротун М. В","relations_other":"","relations":"Дитина","name_hidden":false,"name_unclear":false},{"inn":"","inn_hidden":false,"family_name":"Коротун В. В","relations_other":"","relations":"Дитина","name_hidden":false,"name_unclear":false}],"full_name_suggest":{"output":"Коротун Олена Миколаївна","input":["Коротун Олена Миколаївна","Олена Миколаївна Коротун","Олена Коротун"]},"patronymic":"Миколаївна"},"source":"VULYK","estate":{"23":[{"costs_rent":"","region":"","costs":"","costs_rent_comment":"","costs_comment":"","address_hidden":false,"region_hidden":true,"space_comment":"у власності","space_units":"м²","space":"2001","address":""}],"24":[{"space_hidden":true,"costs":"","costs_comment":"","address_hidden":false,"region_hidden":true,"space_comment":"незавершене будівництво (одноповерхова дерев. коробка без вікон і без дверей, у власності","space":"","address":"","region":"","costs_rent_comment":"","space_units":"м²","costs_rent":""}],"25":[{"space_hidden":false,"costs":"","costs_comment":"","address_hidden":false,"region_hidden":true,"space_comment":"1/2, у власності","space":"17.85","address":"","region":"","costs_rent_comment":"","space_units":"м²","costs_rent":""},{"costs_rent":"","space_unclear":false,"region":"","costs":"","costs_rent_comment":"","costs_comment":"","region_hidden":false,"space_comment":"1/2, у власності","space_units":"м²","space":"40.95","address":""}],"27":[{"costs_rent":"","region":"","costs":"","costs_rent_comment":"","costs_comment":"","address_hidden":false,"region_hidden":true,"space_comment":"","space_units":"м²","space":"","address":""}],"28":[{"space_hidden":false,"costs":"","costs_comment":"","address_hidden":false,"region_hidden":true,"space_comment":"машиномісце, у власності","space":"13.1","address":"","region":"","costs_rent_comment":"","space_units":"м²","costs_rent":""},{"costs_rent":"","space_hidden":true,"region":"","costs":"","costs_rent_comment":"","costs_comment":"","space_comment":"КТП 10/0. 4 кв, у власності","space_units":"м²","space":"","address":""}],"29":[{"costs_rent":"","space_hidden":false,"costs_property":"","costs_rent_comment":"","address_hidden":true,"region_hidden":true,"space_comment":"у власності","costs_property_comment":"","space_units":"м²","space":"2000","address":""},{"costs_rent":"","costs_property":"","costs_rent_comment":"","space_comment":"у власності","costs_property_comment":"","space_units":"м²","space":"1200","address":""}],"31":[{"space_hidden":false,"address_hidden":true,"region_hidden":false,"space_comment":"у власності","space":"123","address":"","region":"","costs_property":"","costs_rent_comment":"","space_units":"м²","costs_property_comment":"","costs_rent":""},{"costs_rent":"","costs_property":"","costs_rent_comment":"","region_hidden":false,"space_comment":"1/2, у власності","costs_property_comment":"","space_units":"м²","space":"40.95","address":""}]},"intro":{"declaration_year":"2014"}}