{"income":{"5":{"value":"240183","family_comment":"","value_unclear":false,"value_hidden":false,"family_unclear":false,"family":"120875","comment":""},"6":{"value":"240183","family_comment":"","value_unclear":false,"family_hidden":false,"value_hidden":false,"family_unclear":false,"family":"116443","comment":""},"7":{"value":"","family_hidden":false,"value_hidden":false,"family_comment":"","source_name":"","family":"","comment":"","source_name_hidden":false},"8":{"family_comment":"","value":"","family":"","comment":""},"9":{"family_comment":"","value":"","comment_unclear":false,"family":"","comment":""},"10":{"value":"","value_unclear":false,"comment_hidden":false,"family_comment":"","family":"","comment":""},"11":{"family_comment":"","value":"","family":"","comment":""},"12":{"family_comment":"","value":"","family":"","comment":""},"13":{"family_comment":"","value":"","comment_hidden":false,"family":"","comment":""},"14":{"family_comment":"","value":"","comment_unclear":false,"family":"","comment":""},"15":{"family_comment":"","value":"","family":"","comment":""},"16":{"family_comment":"","value":"","family":"","comment":"","value_hidden":false},"17":{"family_comment":"","value":"","family":"","comment":"","value_hidden":false},"18":{"family_comment":"","value":"","family":"","comment":"","value_hidden":false},"19":{"family_comment":"","value":"","family":"","comment":"","value_hidden":false},"20":{"value":"","family_comment":"","value_unclear":false,"family_hidden":false,"family":"4432","value_hidden":false,"family_unclear":false,"comment_unclear":false,"comment":"","family_comment_unclear":false}},"id":"vulyk_43_32","banks":{"45":[{"sum_foreign_comment":"","sum_units":"UAH","sum_comment":"","sum_comment_unclear":false,"sum_hidden":false,"sum_foreign_units":"UAH","sum_units_unclear":false,"sum":"","sum_unclear":false,"sum_foreign":""}],"46":[{"sum_foreign_comment":"","sum_units":"UAH","sum_comment":"","sum_hidden":false,"sum_foreign_units":"UAH","sum":"","sum_foreign":""}],"47":[{"sum_foreign_comment":"","sum_units":"UAH","sum_comment":"","sum_hidden":false,"sum_foreign_units":"UAH","sum":"","sum_foreign":""},{"sum_foreign_comment":"","sum_units":"","sum_comment":"","sum_foreign_units":"","sum":"","sum_foreign":""}],"48":[{"sum_foreign_comment":"","sum_units":"UAH","sum_comment":"","sum_hidden":false,"sum_foreign_units":"UAH","sum":"","sum_foreign":""}],"49":[{"sum_foreign_comment":"","sum_units":"UAH","sum_comment":"","sum_hidden":false,"sum_foreign_units":"UAH","sum":"","sum_foreign":""}],"50":[{"sum_foreign_comment":"","sum_units":"UAH","sum_comment":"","sum_hidden":false,"sum_foreign_units":"UAH","sum_foreign_hidden":false,"sum_units_unclear":false,"sum":"","sum_unclear":false,"sum_foreign":""}],"51":[{"sum_foreign_comment":"","sum_units":"UAH","sum_comment":"","sum_hidden":false,"sum_foreign_units":"UAH","sum":"","sum_unclear":false,"sum_foreign":""}],"52":[{"sum_foreign_comment":"","sum_units":"UAH","sum_comment":"","sum_hidden":false,"sum_foreign_units":"UAH","sum":"","sum_foreign":""}],"53":[{"sum_foreign_comment":"","sum_units":"UAH","sum_comment":"","sum_hidden":false,"sum_foreign_units":"UAH","sum":"","sum_foreign":""}]},"declaration":{"additional_info_text":"","notfull_lostpages":"","date":"2015-03-30T00:00:00","notfull":"","additional_info":"","url":"http://static.declarations.com.ua/declarations/chosen_ones/mega_batch/khomyk_iryna_ivanivna.pdf"},"liabilities":{"54":{"sum_foreign_comment":"","sum":"","sum_comment":"","sum_hidden":false,"sum_comment_hidden":false,"sum_unclear":false,"sum_foreign":""},"55":{"sum_foreign_comment":"","sum":"","sum_hidden":false,"sum_comment":"","sum_foreign":""},"56":{"sum_foreign_comment":"","sum":"","sum_comment":"","sum_hidden":false,"sum_unclear":false,"sum_foreign":""},"57":{"sum_foreign_comment":"","sum":"","sum_comment":"","sum_hidden":false,"sum_comment_hidden":false,"sum_unclear":false,"sum_foreign":""},"58":{"sum_foreign_comment":"","sum":"","sum_comment":"","sum_hidden":false,"sum_comment_hidden":false,"sum_foreign":""},"59":{"sum_foreign_comment":"","sum":"","sum_hidden":false,"sum_comment":"","sum_foreign":""},"60":{"sum_foreign_comment":"","sum":"","sum_comment":"","sum_comment_unclear":false,"sum_hidden":false,"sum_unclear":false,"sum_foreign":""},"61":{"sum_foreign_comment":"","sum":"","sum_hidden":false,"sum_comment":"","sum_foreign":""},"62":{"sum_foreign_comment":"","sum":"","sum_comment":"","sum_hidden":false,"sum_unclear":false,"sum_foreign":""},"63":{"sum_foreign_comment":"","sum":"","sum_hidden":false,"sum_comment":"","sum_foreign":""},"64":{"sum_foreign_comment":"","sum":"","sum_comment":"","sum_hidden":false,"sum_unclear":false,"sum_foreign":""}},"ft_src":"суддя великоолександрівського районного суду херсонської області\nХерсонська область\nЗагальний місцевий суд\nІрина\nХомік В. М., 13. 02. 1960\nПодружжя\nХомік Є. В., 13. 06. 1990\nДитина\nІванівна\nХомик\nХомик Ірина Іванівна\nХомик Ірина Іванівна\nІрина Іванівна Хомик\nІрина Хомик\nХомик Ірина Іванівна\nВелика Олександрівка\n74100\nХерсонська область\nСМТ\n4432\n240183\n120875\n240183\n116443\n75\nХерсонська область\nсмт Велика Олександрівка\nс. Мала Олександрівка Великоолександрівського району\nХерсонська область\n5.91\nХерсонська область\nсмт Велика Олександрівка\n.14\nХерсонська область\nсмт. Велика Олександрівка\n75\n2014\n116443\n240183\n120875\n240183\n4432\n2014\nПодружжя\nХомік В. М., 13. 02. 1960\nДитина\nХомік Є. В., 13. 06. 1990\nХомик Ірина Іванівна\nІрина Іванівна Хомик\nІрина Хомик\nХомик Ірина Іванівна\nІрина\nХомик Ірина Іванівна\nХомик\nЗагальний місцевий суд\nсуддя великоолександрівського районного суду херсонської області\nХерсонська область\nІванівна\nСМТ\n74100\nХерсонська область\nВелика Олександрівка\n240183\n116443\n4432\n120875\n240183\n5.91\nХерсонська область\nс. Мала Олександрівка Великоолександрівського району\n.14\nсмт Велика Олександрівка\nХерсонська область\n75\nХерсонська область\nсмт. Велика Олександрівка\n75\nХерсонська область\nсмт Велика Олександрівка\nПодружжя\nХомік В. М., 13. 02. 1960\nХомік Є. В., 13. 06. 1990\nДитина\nХомик Ірина Іванівна\nІрина Іванівна Хомик\nІрина Хомик\nХомик Ірина Іванівна\nІванівна\nХомик\nСМТ\n74100\nВелика Олександрівка\nХерсонська область\nХерсонська область\nЗагальний місцевий суд\nсуддя великоолександрівського районного суду херсонської області\nХомик Ірина Іванівна\nІрина\nсмт Велика Олександрівка\nХерсонська область\n75\nсмт. Велика Олександрівка\nХерсонська область\n75\nс. Мала Олександрівка Великоолександрівського району\nХерсонська область\n5.91\nсмт Велика Олександрівка\nХерсонська область\n.14\n2014","general":{"name_hidden":false,"name":"Ірина","patronymic_unclear":false,"inn":"","family":[{"inn":"","inn_hidden":true,"relations_unclear":false,"relations_hidden":false,"relations_other":"","relations":"Подружжя","name_hidden":false,"inn_unclear":false,"family_name":"Хомік В. М., 13. 02. 1960","name_unclear":false},{"inn":"","relations":"Дитина","relations_unclear":false,"family_name":"Хомік Є. В., 13. 06. 1990","inn_hidden":true,"relations_other":"","name_hidden":false,"name_unclear":false}],"patronymic":"Іванівна","inn_hidden":true,"family_raw":"","inn_unclear":false,"post":{"post_unclear":false,"post":"суддя великоолександрівського районного суду херсонської області","candidate":"","office_hidden":false,"region":"Херсонська область","post_hidden":false,"office":"Загальний місцевий суд","office_unclear":false,"region_hidden":false},"last_name_unclear":false,"full_name":"Хомик Ірина Іванівна","addresses":[{"place_district":"","place_city_hidden":false,"place_city":"Велика Олександрівка","place_city_type_hidden":false,"place_district_hidden":false,"place_city_type":"СМТ","place_hidden":false,"place_address_hidden":true,"place_address":"74100","place":"Херсонська область","place_district_unclear":false}],"last_name":"Хомик","full_name_suggest":{"output":"Хомик Ірина Іванівна","input":["Хомик Ірина Іванівна","Ірина Іванівна Хомик","Ірина Хомик"]}},"source":"VULYK","estate":{"23":[{"region_unclear":false,"space_hidden":false,"costs":"","costs_comment":"","costs_hidden":false,"address_hidden":false,"region_hidden":false,"space_comment":"","space_unclear":false,"space":"","address":"","region":"","address_unclear":false,"costs_rent_comment":"","costs_rent_hidden":false,"costs_unclear":false,"space_units":"м²","costs_rent":""},{"costs_rent":"","region":"","costs":"","costs_rent_comment":"","costs_comment":"","address_hidden":false,"region_hidden":false,"space_comment":"","space_units":"","space":"","address":""},{"costs_rent":"","region":"","costs":"","costs_rent_comment":"","costs_comment":"","region_hidden":false,"space_comment":"","space_units":"","space":"","address":""},{"costs_rent":"","region":"","costs":"","costs_rent_comment":"","costs_comment":"","region_hidden":false,"space_comment":"","space_units":"","space":"","address":""},{"costs_rent":"","region":"","costs":"","costs_rent_comment":"","costs_comment":"","region_hidden":false,"space_comment":"","space_units":"","space":"","address":""}],"24":[{"space_hidden":false,"costs":"","costs_rent_unclear":false,"costs_comment":"","costs_hidden":false,"address_hidden":true,"region_hidden":false,"space_comment":"","space_unclear":false,"space":"75","address":"смт. Велика Олександрівка","costs_comment_unclear":false,"region":"Херсонська область","costs_rent_comment":"","costs_rent_hidden":false,"space_comment_unclear":false,"space_units":"м²","costs_rent":""}],"29":[{"space_unclear":false,"address_hidden":false,"region_hidden":false,"space_comment":"","space":"5.91","address":"с. Мала Олександрівка Великоолександрівського району","region":"Херсонська область","costs_property":"","costs_rent_comment":"","space_units":"га","costs_property_comment":"","costs_rent":""},{"costs_rent":"","region":"Херсонська область","costs_property":"","costs_rent_comment":"","space_comment":"","costs_property_comment":"","space_units":"га","space":".14","address":"смт Велика Олександрівка"}],"30":[{"address_hidden":false,"region_hidden":false,"space_comment":"","space":"75","address":"смт Велика Олександрівка","region":"Херсонська область","costs_property":"","costs_rent_comment":"","space_comment_hidden":false,"space_units":"м²","costs_property_comment":"","costs_rent":""}]},"intro":{"declaration_year":"2014","isnotdeclaration":"","declaration_year_unclear":false,"declaration_year_hidden":false}}