{"id":"vulyk_98_66","ft_src":"2008\nToyota Avensis\n1987 куб. см.\n147000\n1/2 від 52 кв. м\n52\n196\n2014\n1987 куб. см.\n2008\n147000\nToyota Avensis\n2014\nГосподарський місцевий суд\nсуддя господарського суду запорізької області\nЗапорізька область\nСмірнов Олександр Геннадійович\nОлександр Геннадійович Смірнов\nОлександр Смірнов\nСмірнов Олександр Геннадійович\nСмірнов Олександр Геннадійович\nОлександр\nСмірнов\nГеннадійович\n8000\n47000\n5000\n5929\n182813\n90000\n273075\n262\n52\n1/2 від 52 кв. м\n196\n5929\n47000\n5000\n8000\n182813\n262\n273075\n90000\nГеннадійович\nСмірнов\nОлександр\nСмірнов Олександр Геннадійович\nОлександр Геннадійович Смірнов\nОлександр Смірнов\nСмірнов Олександр Геннадійович\nсуддя господарського суду запорізької області\nЗапорізька область\nГосподарський місцевий суд\nСмірнов Олександр Геннадійович","estate":{"25":[{"address":"","space_units":"м²","costs_comment":"","space_unclear":false,"region_hidden":true,"space_comment":"1/2 від 52 кв. м","address_hidden":false,"costs":"","address_unclear":false,"costs_rent_comment":"","space":"52","region":"","costs_rent":""}]},"vehicle":{"35":[{"sum_comment":"","brand_info":"1987 куб. см.","brand_unclear":false,"sum_rent_comment":"","year":"2008","brand":"Toyota Avensis","sum_rent":"","brand_info_unclear":false,"sum":"147000"}]},"source":"VULYK","income":{"5":{"family_comment":"","family":"","comment":"","value_unclear":false,"family_unclear":false,"value":"273075"},"6":{"family_comment":"","value":"182813","family":"","comment":"","value_unclear":false},"7":{"family":"","family_comment":"","value":"","comment":"","source_name":""},"8":{"family_comment":"","value":"","family":"","comment":""},"9":{"family_comment":"","value":"262","family":"","comment":"","value_unclear":false},"10":{"family_comment":"","value":"","family":"","comment":""},"11":{"family_comment":"","value":"","family":"","comment":""},"12":{"family_comment":"","value":"","family":"","comment":""},"13":{"family_comment":"","value":"","family":"","comment":""},"14":{"family_comment":"","value":"","family":"","comment":""},"15":{"family_comment":"","value":"","family":"","comment":""},"16":{"family_comment":"","value":"","family":"","comment":""},"17":{"family_comment":"","value":"","family":"","comment":""},"18":{"family_comment":"","value":"","family":"","comment":""},"19":{"family_comment":"","value":"","family":"","comment":""},"20":{"family_comment":"","value":"90000","family":"","comment":"","value_unclear":false}},"banks":{"45":[{"sum_units":"UAH","sum_comment":"","sum_foreign_units":"UAH","sum_hidden":false,"sum":"196","sum_foreign_comment":"","sum_foreign":"","sum_unclear":false,"sum_comment_hidden":true}]},"declaration":{"date":"2015-03-30T00:00:00","url":"http://static.declarations.com.ua/declarations/chosen_ones/judges_batch/4563_smirnov_oleksandr_henadiiovych.pdf"},"general":{"family_raw":"","name":"Олександр","full_name_suggest":{"input":["Смірнов Олександр Геннадійович","Олександр Геннадійович Смірнов","Олександр Смірнов"],"output":"Смірнов Олександр Геннадійович"},"patronymic":"Геннадійович","inn_hidden":true,"addresses":[{"place_city_type_hidden":false,"place_city_type":"","place_city_hidden":true,"place_hidden":true,"place_district":"","place_district_hidden":false,"place":"","place_address":"","place_address_hidden":true,"place_city":""}],"last_name_hidden":false,"patronymic_hidden":false,"inn":"","inn_unclear":false,"last_name":"Смірнов","full_name":"Смірнов Олександр Геннадійович","post":{"office":"Господарський місцевий суд","region":"Запорізька область","post_unclear":false,"post":"суддя господарського суду запорізької області"},"last_name_unclear":false},"liabilities":{"54":{"sum_comment_unclear":false,"sum_comment":"","sum_hidden":false,"sum":"8000","sum_foreign_comment":"","sum_foreign":"","sum_unclear":false,"sum_comment_hidden":false},"55":{"sum_comment":"","sum_foreign_comment":"","sum_foreign":"","sum":""},"56":{"sum_comment":"","sum_foreign_comment":"","sum_foreign":"","sum_unclear":false,"sum":"5000"},"57":{"sum_comment_unclear":false,"sum_comment":"","sum_hidden":false,"sum":"47000","sum_foreign_comment":"","sum_foreign":"","sum_unclear":false,"sum_comment_hidden":false},"58":{"sum_comment":"","sum_hidden":false,"sum":"5929","sum_foreign_comment":"","sum_foreign":"","sum_unclear":false,"sum_comment_hidden":false},"59":{"sum_comment":"","sum_comment_unclear":false,"sum_foreign_comment":"","sum":"","sum_foreign":""},"60":{"sum_comment":"","sum_hidden":false,"sum":"","sum_foreign_comment":"","sum_foreign":"","sum_comment_hidden":false},"61":{"sum_comment":"","sum_foreign_comment":"","sum_foreign":"","sum":""},"62":{"sum_comment":"","sum":"","sum_foreign_comment":"","sum_foreign":"","sum_unclear":false,"sum_comment_hidden":false},"63":{"sum_comment_unclear":false,"sum_comment":"","sum":"","sum_foreign_comment":"","sum_foreign":"","sum_comment_hidden":false},"64":{"sum_comment":"","sum_foreign_comment":"","sum_foreign":"","sum":"","sum_comment_hidden":false}},"intro":{"declaration_year":"2014"}}