{"income":{"5":{"value":"437194.97","family_comment":"","value_unclear":false,"family":"","family_unclear":false,"comment_unclear":false,"comment":"","family_comment_unclear":false},"6":{"value":"235194.97","family_comment":"","value_unclear":false,"family_unclear":false,"family":"","comment":""},"7":{"source_name_unclear":false,"value":"","value_unclear":false,"family_comment":"","source_name":"","family":"","comment":"","source_name_hidden":false},"8":{"family_comment":"","value":"","family":"","comment":""},"9":{"family_comment":"","value":"","family":"","comment":""},"10":{"family_comment":"","value":"","value_unclear":false,"family":"","comment":""},"11":{"value":"","value_unclear":false,"value_hidden":false,"family_comment":"","family":"","comment":""},"12":{"family_comment":"","value":"","family":"","comment":"","value_hidden":false},"13":{"family_comment":"","value":"","family":"","comment":""},"14":{"family_comment":"","value":"","family":"","comment":""},"15":{"family_comment":"","value":"","family":"","comment":""},"16":{"family_comment":"","value":"","family":"","comment":""},"17":{"family_comment":"","value":"","family":"","comment":""},"18":{"family_comment":"","value":"","family":"","comment":""},"19":{"family_comment":"","family_unclear":false,"value":"","family":"","comment":""},"20":{"family_comment":"","family_unclear":false,"value":"202000","family":"","comment":""}},"id":"vulyk_61_95","declaration":{"additional_info_text":"","notfull_lostpages":"","date":"2015-02-20T00:00:00","notfull":"","additional_info":"","url":"http://static.declarations.com.ua/declarations/chosen_ones/mega_batch/starynshchuk_olha_vasylivna.pdf"},"liabilities":{"54":{"sum_foreign_comment":"","sum":"","sum_comment":"","sum_comment_unclear":false,"sum_unclear":false,"sum_foreign":""},"55":{"sum_foreign_comment":"","sum":"","sum_comment":"","sum_foreign":""},"56":{"sum_foreign_comment":"","sum":"","sum_comment":"","sum_unclear":false,"sum_foreign":""},"57":{"sum_foreign_comment":"","sum":"","sum_comment":"","sum_comment_hidden":false,"sum_unclear":false,"sum_foreign":""},"58":{"sum_foreign_comment":"","sum":"","sum_comment":"","sum_unclear":false,"sum_foreign":""},"59":{"sum_foreign_comment":"","sum":"","sum_comment":"","sum_foreign":""},"60":{"sum_foreign_comment":"","sum_foreign_hidden":false,"sum_comment":"","sum_hidden":false,"sum":"","sum_foreign":""},"61":{"sum_foreign_comment":"","sum":"","sum_comment":"","sum_foreign":""},"62":{"sum_foreign_comment":"","sum":"","sum_comment":"","sum_unclear":false,"sum_foreign":""},"63":{"sum_foreign_comment":"","sum":"","sum_comment":"","sum_hidden":false,"sum_unclear":false,"sum_foreign":""},"64":{"sum_foreign_comment":"","sum":"","sum_hidden":false,"sum_comment":"","sum_foreign":""}},"ft_src":"суддя вінницького міського суду вінницької області\nВінницька область\nЗагальний місцевий суд\nОльга\nВасилівна\nСтаринщук Ольга Василівна\nОльга Василівна Старинщук\nОльга Старинщук\nСтаринщук Ольга Василівна\nСтаринщук Ольга Василівна\nСтаринщук\n202000\n437194.97\n235194.97\n51.3\n2014\n235194.97\n437194.97\n202000\n51.3\nСтаринщук Ольга Василівна\nОльга Василівна Старинщук\nОльга Старинщук\nСтаринщук Ольга Василівна\nСтаринщук Ольга Василівна\nОльга\nВасилівна\nВінницька область\nЗагальний місцевий суд\nсуддя вінницького міського суду вінницької області\nСтаринщук\n235194.97\n202000\n437194.97\n2014\nВасилівна\nСтаринщук\nОльга\nСтаринщук Ольга Василівна\nОльга Василівна Старинщук\nОльга Старинщук\nСтаринщук Ольга Василівна\nВінницька область\nсуддя вінницького міського суду вінницької області\nЗагальний місцевий суд\nСтаринщук Ольга Василівна\n51.3\n2014","general":{"inn":"","name":"Ольга","patronymic_unclear":false,"inn_unclear":false,"patronymic":"Василівна","inn_hidden":true,"family_raw":"","last_name":"Старинщук","post":{"post_unclear":false,"region_unclear":false,"post":"суддя вінницького міського суду вінницької області","office":"Загальний місцевий суд","region":"Вінницька область","post_hidden":false,"office_hidden":false,"region_hidden":false},"full_name_suggest":{"output":"Старинщук Ольга Василівна","input":["Старинщук Ольга Василівна","Ольга Василівна Старинщук","Ольга Старинщук"]},"full_name":"Старинщук Ольга Василівна","addresses":[{"place_address":"","place_district_hidden":false,"place_city_type":"","place_city_hidden":false,"place_address_unclear":false,"place_city_type_hidden":false,"place_hidden":true,"place":"","place_district":"","place_address_hidden":false,"place_city":"","place_district_unclear":false}],"patronymic_hidden":false,"last_name_unclear":false,"name_unclear":false},"source":"VULYK","estate":{"31":[{"space_unclear":false,"address_hidden":true,"region_hidden":true,"space_comment":"","space_hidden":false,"space":"51.3","address":"","region":"","costs_property":"","costs_rent_comment":"","space_comment_unclear":false,"space_units":"м²","costs_property_comment":"","costs_rent":""}]},"intro":{"declaration_year":"2014","isnotdeclaration":"","declaration_year_hidden":false}}