{"income":{"5":{"value":"237566","family_comment":"","value_unclear":false,"family_unclear":false,"family":"69493","comment":""},"6":{"family_comment":"","family_unclear":false,"value":"237508","family":"69493","comment":""},"7":{"source_name_unclear":false,"value":"","family_comment":"","source_name":"","family":"","comment":""},"8":{"family_comment":"","value":"","family":"","comment":""},"9":{"value":"","family_comment":"","comment_hidden":false,"family_unclear":false,"family":"","comment":"","family_comment_hidden":false},"10":{"family_comment":"","value":"","family":"","comment":""},"11":{"family_comment":"","value":"","family":"","comment":""},"12":{"family_comment":"","value":"","family":"","comment":""},"13":{"family_comment":"","value":"","family":"","comment":""},"14":{"family_comment":"","value":"","family":"","comment":""},"15":{"family_comment":"","value":"","family":"","comment":""},"16":{"family_comment":"","value":"","family":"","comment":""},"17":{"family_comment":"","value":"","family":"","comment":""},"18":{"family_comment":"","value":"","family":"","comment":""},"19":{"family_comment":"","value":"","family":"","comment":""},"20":{"value":"58","value_unclear":false,"comment_hidden":false,"family_comment":"","comment_unclear":false,"comment":"","family":""}},"vehicle":{"35":[{"brand_info":"1591 куб. см., 130 к.с., 453 см","sum_rent_comment":"","brand":"Hyundai Elantra","sum_comment":"","year":"2012","brand_info_unclear":false,"sum":"","sum_rent":""}]},"id":"vulyk_108_88","declaration":{"additional_info_text":"","notfull_lostpages":"","date":"2016-03-25T00:00:00","notfull":"","additional_info":"","url":"http://static.declarations.com.ua/declarations/chosen_ones/judges_batch/2387_kyslyi_mykola_mykolaiovych_2015.pdf"},"liabilities":{"54":{"sum_foreign_comment":"","sum":"","sum_hidden":false,"sum_comment":"","sum_foreign":""},"55":{"sum_foreign_comment":"","sum":"","sum_comment":"","sum_foreign":""},"56":{"sum_foreign_comment":"","sum":"","sum_comment":"","sum_unclear":false,"sum_foreign":""},"57":{"sum_foreign_comment":"","sum":"37041","sum_comment":"","sum_hidden":false,"sum_comment_hidden":false,"sum_foreign":""},"58":{"sum_foreign_comment":"","sum_comment_hidden":false,"sum":"3136","sum_comment":"","sum_foreign":""},"59":{"sum_foreign_comment":"","sum":"","sum_comment":"","sum_unclear":false,"sum_foreign":""},"60":{"sum_foreign_comment":"","sum_comment_hidden":false,"sum":"","sum_comment":"","sum_foreign":""},"61":{"sum_foreign_comment":"","sum_comment_hidden":false,"sum":"","sum_comment":"","sum_foreign":""},"62":{"sum_foreign_comment":"","sum":"","sum_comment":"","sum_foreign":""},"63":{"sum_foreign_comment":"","sum":"","sum_comment":"","sum_hidden":false,"sum_comment_hidden":false,"sum_unclear":false,"sum_foreign":""},"64":{"sum_foreign_comment":"","sum":"","sum_comment":"","sum_comment_hidden":false,"sum_unclear":false,"sum_foreign":""}},"ft_src":"37041\n3136\nсуддя апеляційного суду дніпропетровської області\nДніпропетровська область\nЗагальний апеляційний суд\nМикола\nКисла Н. М\nПодружжя\nМиколайович\nКислий Микола Миколайович\nМикола Миколайович Кислий\nМикола Кислий\nКислий Микола Миколайович\nКислий Микола Миколайович\nКислий\n1591 куб. см., 130 к.с., 453 см\n2012\nHyundai Elantra\n760\n47.2\n2015\n69493\n237508\n69493\n237566\n58\n1591 куб. см., 130 к.с., 453 см\n2012\nHyundai Elantra\n2015\nКислий Микола Миколайович\nМикола Миколайович Кислий\nМикола Кислий\nКислий Микола Миколайович\nМикола\nПодружжя\nКисла Н. М\nКислий Микола Миколайович\nМиколайович\nЗагальний апеляційний суд\nДніпропетровська область\nсуддя апеляційного суду дніпропетровської області\nКислий\n37041\n3136\n237508\n69493\n58\n237566\n69493\n760\n47.2\n3136\n37041\nПодружжя\nКисла Н. М\nМиколайович\nКислий\nМикола\nКислий Микола Миколайович\nМикола Миколайович Кислий\nМикола Кислий\nКислий Микола Миколайович\nДніпропетровська область\nсуддя апеляційного суду дніпропетровської області\nЗагальний апеляційний суд\nКислий Микола Миколайович\n2012\n1591 куб. см., 130 к.с., 453 см\nHyundai Elantra\n58\n237566\n69493\n69493\n237508\n47.2\n760\n2015","general":{"inn":"","name":"Микола","inn_unclear":false,"family":[{"inn":"","relations":"Подружжя","inn_unclear":false,"relations_hidden":false,"inn_hidden":true,"relations_other":"","name_hidden":false,"family_name":"Кисла Н. М","name_unclear":false}],"inn_hidden":true,"family_raw":"","last_name":"Кислий","post":{"post_unclear":false,"post":"суддя апеляційного суду дніпропетровської області","office_hidden":false,"region":"Дніпропетровська область","office":"Загальний апеляційний суд","office_unclear":false},"full_name":"Кислий Микола Миколайович","addresses":[{"place_city_type_hidden":false,"place_district_hidden":false,"place_city_type":"","place_city_hidden":true,"place_address_unclear":false,"place_address":"","place_hidden":true,"place":"","place_district":"","place_unclear":false,"place_city":"","place_address_hidden":false}],"patronymic":"Миколайович","full_name_suggest":{"output":"Кислий Микола Миколайович","input":["Кислий Микола Миколайович","Микола Миколайович Кислий","Микола Кислий"]}},"source":"VULYK","estate":{"23":[{"region_unclear":false,"space_unclear":false,"costs":"","costs_comment":"","address_hidden":false,"region_hidden":true,"space_comment":"","space":"760","address":"","region":"","address_unclear":false,"space_units_unclear":false,"space_units":"м²","space_units_hidden":false,"costs_rent":"","costs_rent_comment":""}],"25":[{"space_unclear":false,"costs":"","costs_comment":"","address_hidden":false,"region_hidden":true,"space_comment":"","space":"47.2","address":"","region":"","costs_rent_comment":"","space_comment_unclear":false,"space_units":"м²","space_units_unclear":false,"costs_rent":""}]},"intro":{"declaration_year":"2015","isnotdeclaration":"","declaration_year_hidden":false}}