{"id":"vulyk_65_55","ft_src":"48351\n139931\n14.2\n1\n54. 2) ПрАТ СК 'Кардіф' - 36 3) ПрАТ СК 'Уніка' - 99 57. 2) ПАТ 'Банк Форвард' - 3694 3) ПАТ 'Креді Агріколь Банк' - 22206 58. 2) ПАТ 'Креді Агріколь Банк' - 8894 3) ПАТ 'Банк Форвард' - 906\n2014\n223669\n228169\n4500\n54. 2) ПрАТ СК 'Кардіф' - 36 3) ПрАТ СК 'Уніка' - 99 57. 2) ПАТ 'Банк Форвард' - 3694 3) ПАТ 'Креді Агріколь Банк' - 22206 58. 2) ПАТ 'Креді Агріколь Банк' - 8894 3) ПАТ 'Банк Форвард' - 906\n1\n48351\n139931\n2014\nЛоктіонова Оксана Віталіївна\nОксана Віталіївна Локтіонова\nОксана Локтіонова\nЛоктіонова Оксана Віталіївна\nЛоктіонова Оксана Віталіївна\nОксана\nЛоктіонова\nЗагальний апеляційний суд\nМиколаївська область\nсуддя апеляційного суду миколаївської області\nВіталіївна\n44188\n12573\n452\n223669\n228169\n4500\n14.2\n12573\n44188\n452\nВіталіївна\nЛоктіонова\nОксана\nЛоктіонова Оксана Віталіївна\nОксана Віталіївна Локтіонова\nОксана Локтіонова\nЛоктіонова Оксана Віталіївна\nМиколаївська область\nЗагальний апеляційний суд\nсуддя апеляційного суду миколаївської області\nЛоктіонова Оксана Віталіївна","estate":{"28":[{"address":"","space_units":"м²","space_comment":"","region_hidden":true,"space_units_unclear":false,"costs_comment":"","address_hidden":false,"costs":"","address_unclear":false,"space_comment_unclear":false,"costs_rent_comment":"","space":"14.2","region":"","costs_rent":""}]},"source":"VULYK","income":{"5":{"family":"","family_comment":"","comment":"","value_hidden":false,"value_unclear":false,"value":"228169","family_hidden":false,"family_unclear":false},"6":{"family_comment":"","family":"","value_hidden":false,"comment":"","comment_unclear":false,"value_unclear":false,"value":"223669","family_hidden":false},"7":{"source_name_hidden":false,"family_comment":"","family":"","value_hidden":false,"comment":"","value":"","source_name":""},"8":{"family_comment":"","value":"","family":"","comment":""},"9":{"family_comment":"","comment_unclear":false,"value":"4500","family":"","comment":""},"10":{"family_comment":"","value":"","family":"","comment":"","value_unclear":false},"11":{"family_comment":"","value":"","family":"","comment":""},"12":{"family_comment":"","value":"","family":"","comment":""},"13":{"family_comment":"","value":"","family":"","comment":""},"14":{"family_comment":"","value":"","family":"","comment":""},"15":{"family_comment":"","value":"","family":"","comment":""},"16":{"family_comment":"","value":"","family":"","comment":""},"17":{"family_comment":"","value":"","family":"","comment":""},"18":{"family_comment":"","value":"","family":"","comment":""},"19":{"family":"","family_comment":"","comment":"","value_hidden":false,"value_unclear":false,"comment_hidden":false,"family_hidden":false,"value":"","family_comment_hidden":false},"20":{"family_comment":"","family":"","value_hidden":false,"comment":"","value":"","comment_unclear":false,"value_unclear":false,"family_unclear":false,"family_hidden":false}},"banks":{"45":[{"sum_comment_unclear":false,"sum_comment":"","sum_foreign_units":"UAH","sum_hidden":false,"sum":"48351","sum_foreign_comment":"","sum_units_unclear":false,"sum_unclear":false,"sum_foreign":"","sum_units":"UAH"},{"sum_units":"UAH","sum_comment":"","sum_foreign_units":"UAH","sum":"139931","sum_foreign_comment":"","sum_foreign":"","sum_unclear":false}]},"declaration":{"notfull_lostpages":"","additional_info_text":"54. 2) ПрАТ СК 'Кардіф' - 36 3) ПрАТ СК 'Уніка' - 99 57. 2) ПАТ 'Банк Форвард' - 3694 3) ПАТ 'Креді Агріколь Банк' - 22206 58. 2) ПАТ 'Креді Агріколь Банк' - 8894 3) ПАТ 'Банк Форвард' - 906","additional_info":"1","date":"2015-03-27T00:00:00","notfull":"","url":"http://static.declarations.com.ua/declarations/chosen_ones/mega_batch/loktionova_oksana_vitaliivna.pdf"},"general":{"family_raw":"","name":"Оксана","full_name_suggest":{"input":["Локтіонова Оксана Віталіївна","Оксана Віталіївна Локтіонова","Оксана Локтіонова"],"output":"Локтіонова Оксана Віталіївна"},"name_unclear":false,"patronymic":"Віталіївна","inn_hidden":true,"addresses":[{"place_city_type":"","place_address_unclear":false,"place_city_type_hidden":true,"place_hidden":true,"place_city_hidden":true,"place_district":"","place_district_hidden":true,"place":"","place_city":"","place_address_hidden":true,"place_address":""}],"last_name_hidden":false,"patronymic_hidden":false,"inn":"","inn_unclear":false,"last_name":"Локтіонова","full_name":"Локтіонова Оксана Віталіївна","post":{"post_hidden":false,"office":"Загальний апеляційний суд","post":"суддя апеляційного суду миколаївської області","region":"Миколаївська область","region_hidden":false,"office_unclear":false,"office_hidden":false,"post_unclear":false,"region_unclear":false},"name_hidden":false,"last_name_unclear":false},"liabilities":{"54":{"sum_comment_unclear":false,"sum_comment":"","sum_hidden":false,"sum":"452","sum_foreign_comment":"","sum_foreign":"","sum_comment_hidden":false},"55":{"sum_comment":"","sum_foreign_comment":"","sum_foreign":"","sum":""},"56":{"sum_comment":"","sum_foreign_comment":"","sum_foreign":"","sum_unclear":false,"sum":""},"57":{"sum_comment_unclear":false,"sum_comment":"","sum":"44188","sum_foreign_comment":"","sum_foreign":"","sum_unclear":true},"58":{"sum_comment_unclear":false,"sum_comment":"","sum":"12573","sum_foreign_comment":"","sum_foreign":"","sum_unclear":true},"59":{"sum_comment":"","sum_foreign_comment":"","sum_foreign":"","sum":""},"60":{"sum_comment":"","sum_comment_unclear":false,"sum_foreign_comment":"","sum":"","sum_foreign":""},"61":{"sum_comment":"","sum_foreign_comment":"","sum_foreign":"","sum":""},"62":{"sum_comment":"","sum_foreign_comment":"","sum_foreign":"","sum":""},"63":{"sum_comment":"","sum_foreign_comment":"","sum_foreign":"","sum":""},"64":{"sum_comment":"","sum_foreign_comment":"","sum_foreign":"","sum_unclear":false,"sum":""}},"intro":{"declaration_year_hidden":false,"isnotdeclaration":"","declaration_year":"2014"}}