{"income":{"5":{"value":"305580.48","value_unclear":false,"family_hidden":false,"family_comment":"","family":"","comment":""},"6":{"family_comment":"","value":"305580.48","family":"","comment":""},"7":{"family_comment":"","value":"","source_name":"","family":"","comment":""},"8":{"family_comment":"","value":"","family":"","comment":""},"9":{"family_comment":"","value":"","family":"","comment":""},"10":{"family_comment":"","value":"","family":"","comment":""},"11":{"family_comment":"","value":"","family_hidden":false,"comment":"","family":""},"12":{"family_comment":"","value":"","family":"","comment":""},"13":{"family_comment":"","value":"","family":"","comment":""},"14":{"family_comment":"","value":"","family":"","comment":""},"15":{"family_comment":"","value":"","family":"","comment":""},"16":{"family_comment":"","value":"","family":"","comment":""},"17":{"family_comment":"","value":"","family":"","comment":"","family_comment_unclear":false},"18":{"family_comment":"","value":"","family":"","comment":""},"19":{"family_comment":"","value":"","family":"","comment":""},"20":{"value":"","family_unclear":false,"family_hidden":false,"family_comment":"","family":"","comment":""}},"id":"vulyk_103_77","banks":{"45":[{"sum_foreign_comment":"","sum_units":"UAH","sum_comment":"","sum_hidden":false,"sum_foreign_units":"UAH","sum_comment_hidden":true,"sum_unclear":false,"sum":"20000","sum_foreign":""}]},"declaration":{"date":"2016-03-30T00:00:00","additional_info_text":"","additional_info":"","url":"http://static.declarations.com.ua/declarations/chosen_ones/judges_batch/1301_lahniuk_mykola_mykhailovych.pdf"},"liabilities":{"54":{"sum_foreign_comment":"","sum_foreign_hidden":false,"sum_comment":"","sum_foreign_comment_hidden":false,"sum_hidden":false,"sum_foreign_comment_unclear":false,"sum_comment_hidden":false,"sum_unclear":false,"sum":"","sum_foreign":""},"55":{"sum_foreign_comment":"","sum":"","sum_comment":"","sum_foreign":""},"56":{"sum_foreign_comment":"","sum":"","sum_comment":"","sum_foreign":""},"57":{"sum_foreign_comment":"","sum_foreign_hidden":false,"sum_comment":"","sum_foreign_comment_hidden":false,"sum_hidden":false,"sum_comment_hidden":false,"sum":"","sum_foreign":""},"58":{"sum_foreign_comment":"","sum_foreign_hidden":false,"sum_comment":"","sum_foreign_comment_hidden":false,"sum_hidden":false,"sum_comment_hidden":false,"sum":"","sum_foreign":""},"59":{"sum_foreign_comment":"","sum_foreign_hidden":false,"sum_comment":"","sum_foreign_comment_hidden":false,"sum_hidden":false,"sum_comment_hidden":false,"sum":"","sum_foreign":""},"60":{"sum_foreign_comment":"","sum":"","sum_comment":"","sum_hidden":false,"sum_comment_hidden":false,"sum_foreign":""},"61":{"sum_foreign_comment":"","sum":"","sum_comment":"","sum_foreign":""},"62":{"sum_foreign_comment":"","sum_comment_hidden":false,"sum":"","sum_comment":"","sum_foreign":""},"63":{"sum_foreign_comment":"","sum":"","sum_comment":"","sum_foreign":""},"64":{"sum_foreign_comment":"","sum":"","sum_comment":"","sum_foreign":""}},"ft_src":"Лагнюк Микола Михайлович\nсуддя вищого спецiалiзованого суду україни з розгляду цивiльних і кримiнальних справ\nЗагальнодержавний регіон\nВищий спеціалізований суд з розгляду цивільних і кримінальних справ\nМикола\nЛагнюк Микола Михайлович\nМикола Михайлович Лагнюк\nМикола Лагнюк\nЛагнюк Микола Михайлович\nЛагнюк\nМихайлович\nу власності\n2800\nлітня кухня, лазня  тощо (незавершене будівництво\nу користуванні\n92\nу користуванні\n324\n61.59\nу користуванні\n20000\n2015\nу власності\n2800\n324\nу користуванні\n92\nлітня кухня, лазня  тощо (незавершене будівництво\nу користуванні\n61.59\nу користуванні\nЛагнюк Микола Михайлович\nМикола Михайлович Лагнюк\nМикола Лагнюк\nЛагнюк Микола Михайлович\nЛагнюк Микола Михайлович\nМихайлович\nМикола\nЛагнюк\nВищий спеціалізований суд з розгляду цивільних і кримінальних справ\nсуддя вищого спецiалiзованого суду україни з розгляду цивiльних і кримiнальних справ\nЗагальнодержавний регіон\n305580.48\n305580.48\n20000\n2015\n305580.48\n305580.48\nЛагнюк\nМихайлович\nсуддя вищого спецiалiзованого суду україни з розгляду цивiльних і кримiнальних справ\nВищий спеціалізований суд з розгляду цивільних і кримінальних справ\nЗагальнодержавний регіон\nЛагнюк Микола Михайлович\nЛагнюк Микола Михайлович\nМикола Михайлович Лагнюк\nМикола Лагнюк\nЛагнюк Микола Михайлович\nМикола\n305580.48\n305580.48\nу користуванні\n61.59\n2800\nу власності\nу користуванні\n324\nлітня кухня, лазня  тощо (незавершене будівництво\nу користуванні\n92\n20000\n2015","general":{"inn":"","inn_hidden":true,"last_name":"Лагнюк","post":{"region":"Загальнодержавний регіон","region_unclear":false,"post":"суддя вищого спецiалiзованого суду україни з розгляду цивiльних і кримiнальних справ","office_unclear":false,"office":"Вищий спеціалізований суд з розгляду цивільних і кримінальних справ"},"name":"Микола","full_name":"Лагнюк Микола Михайлович","family_raw":"","addresses":[{"place_district":"","place_city_hidden":true,"place_city":"","place_city_type_hidden":false,"place_district_hidden":false,"place_city_type":"","place_address_hidden":true,"place_address":"","place_hidden":true,"place":""}],"full_name_suggest":{"output":"Лагнюк Микола Михайлович","input":["Лагнюк Микола Михайлович","Микола Михайлович Лагнюк","Микола Лагнюк"]},"patronymic":"Михайлович"},"source":"VULYK","estate":{"23":[{"costs_rent":"","region":"","costs":"","costs_rent_comment":"","costs_comment":"у власності","address_hidden":false,"region_hidden":true,"space_comment":"","space_units":"м²","space":"2800","address":""}],"24":[{"space_hidden":false,"costs":"","costs_comment":"","address_hidden":false,"region_hidden":true,"space_comment":"","space_unclear":false,"space":"324","address":"","region":"","costs_rent_comment":"у користуванні","space_units":"м²","costs_rent":""}],"25":[{"costs":"","costs_comment":"","address_hidden":false,"region_hidden":true,"space_comment":"","space":"61.59","address":"","region":"","costs_rent_comment":"у користуванні","space_comment_unclear":false,"space_comment_hidden":false,"space_units":"м²","costs_rent":""}],"28":[{"space_hidden":false,"costs":"","costs_comment":"","address_hidden":false,"region_hidden":true,"space_comment":"літня кухня, лазня  тощо (незавершене будівництво","space_unclear":false,"space":"92","address":"","region":"","costs_rent_comment":"у користуванні","space_units":"м²","costs_rent":""}]},"intro":{"declaration_year":"2015"}}