{"income":{"5":{"family_comment":"","value":"250616","family":"","comment":""},"6":{"family_comment":"","value":"250616","family":"","comment":""},"7":{"value":"","comment_hidden":false,"value_hidden":false,"family_comment":"","source_name":"","family":"","comment":"","source_name_hidden":false},"8":{"family_comment":"","value":"","family":"","comment":""},"9":{"value":"","comment_hidden":false,"family_comment":"","family":"","comment":"","family_comment_unclear":false},"10":{"family_comment":"","value":"","family":"","comment":""},"11":{"family_comment":"","value":"","comment_hidden":false,"family":"","comment":""},"12":{"family_comment":"","value":"","family":"","comment":""},"13":{"family_comment":"","value":"","family":"","comment":""},"14":{"family_comment":"","value":"","family":"","comment":""},"15":{"family_comment":"","value":"","family":"","comment":""},"16":{"family_comment":"","value":"","family":"","comment":""},"17":{"family_comment":"","value":"","family":"","comment":""},"18":{"family_comment":"","value":"","family":"","comment":""},"19":{"family_comment":"","value":"","family":"","comment":""},"20":{"family_comment":"","value":"","comment_hidden":false,"family":"","comment":""}},"vehicle":{"35":[{"brand_info":"3456","sum_rent_comment":"безоплатне користування","brand":"Lexus RX 350","sum_comment":"","year":"2009","brand_info_unclear":false,"year_unclear":false,"sum":"","sum_rent":""}]},"id":"vulyk_102_124","banks":{"45":[{"sum_foreign_comment":"","sum_units":"USD","sum_comment":"","sum_comment_unclear":false,"sum_hidden":false,"sum_foreign_units":"UAH","sum_comment_hidden":false,"sum_unclear":false,"sum":"850","sum_foreign":""}]},"declaration":{"date":"2016-03-30T00:00:00","additional_info_text":"","additional_info":"","url":"http://static.declarations.com.ua/declarations/chosen_ones/judges_batch/1198_iatsenko_olena_vasylivna.pdf"},"liabilities":{"54":{"sum_foreign_comment":"","sum":"","sum_comment":"","sum_hidden":false,"sum_comment_hidden":false,"sum_foreign":""},"55":{"sum_foreign_comment":"","sum":"","sum_comment":"","sum_foreign":""},"56":{"sum_foreign_comment":"","sum":"","sum_comment":"","sum_foreign":""},"57":{"sum_foreign_comment":"","sum_comment_hidden":false,"sum":"","sum_comment":"","sum_foreign":""},"58":{"sum_foreign_comment":"","sum_comment_hidden":false,"sum":"","sum_comment":"","sum_foreign":""},"59":{"sum_foreign_comment":"","sum_comment_hidden":false,"sum":"","sum_comment":"","sum_foreign":""},"60":{"sum_foreign_comment":"","sum":"","sum_comment":"","sum_hidden":false,"sum_comment_hidden":false,"sum_foreign":""},"61":{"sum_foreign_comment":"","sum":"","sum_comment":"","sum_foreign":""},"62":{"sum_foreign_comment":"","sum":"","sum_comment":"","sum_unclear":false,"sum_foreign":""},"63":{"sum_foreign_comment":"","sum":"","sum_comment":"","sum_hidden":false,"sum_comment_hidden":false,"sum_foreign":""},"64":{"sum_foreign_comment":"","sum_comment_hidden":false,"sum":"","sum_comment":"","sum_foreign":""}},"ft_src":"Яценко Олена Василівна\nВасилівна\nЯценко Олена Василівна\nОлена Василівна Яценко\nОлена Яценко\nЯценко Олена Василівна\nОлена\nсуддя\nЗагальнодержавний регіон\nВищий господарський суд\nЯценко\n2009\n3456\nLexus RX 350\nбезоплатне користування\nмашиномісце\nбезоплатне користування\n13.4\nбезоплатне користування\nбезоплатне користування\n143\n850\n2015\n3456\nбезоплатне користування\nLexus RX 350\n2009\n2015\nЯценко Олена Василівна\nОлена Василівна Яценко\nОлена Яценко\nЯценко Олена Василівна\nОлена\nВасилівна\nЯценко Олена Василівна\nЯценко\nсуддя\nЗагальнодержавний регіон\nВищий господарський суд\n250616\n250616\n13.4\nмашиномісце\nбезоплатне користування\n143\nбезоплатне користування\nбезоплатне користування\n850\n250616\n250616\nВасилівна\nЯценко\nсуддя\nЗагальнодержавний регіон\nВищий господарський суд\nЯценко Олена Василівна\nЯценко Олена Василівна\nОлена Василівна Яценко\nОлена Яценко\nЯценко Олена Василівна\nОлена\nбезоплатне користування\n2009\n3456\nLexus RX 350\n250616\n250616\nбезоплатне користування\nбезоплатне користування\n143\nбезоплатне користування\nмашиномісце\n13.4\n850\n2015","general":{"inn":"","inn_hidden":true,"last_name":"Яценко","post":{"region":"Загальнодержавний регіон","region_unclear":false,"post":"суддя","office_unclear":false,"office":"Вищий господарський суд"},"name":"Олена","full_name":"Яценко Олена Василівна","family_raw":"","addresses":[{"place_district":"","place_city_hidden":true,"place_city":"","place_city_type_hidden":false,"place_district_hidden":false,"place_city_type":"","place_address_hidden":true,"place_address":"","place_hidden":true,"place":""}],"patronymic_hidden":false,"full_name_suggest":{"output":"Яценко Олена Василівна","input":["Яценко Олена Василівна","Олена Василівна Яценко","Олена Яценко"]},"patronymic":"Василівна"},"source":"VULYK","estate":{"25":[{"costs":"","costs_comment":"","address_hidden":false,"region_hidden":true,"space_comment":"безоплатне користування","space":"143","address":"","region":"","address_unclear":false,"costs_rent_comment":"безоплатне користування","space_units":"м²","costs_rent":""}],"28":[{"space_unclear":false,"costs":"","costs_comment":"","address_hidden":false,"region_hidden":true,"space_comment":"машиномісце","space":"13.4","address":"","region":"","costs_rent_comment":"безоплатне користування","space_units":"м²","costs_rent":""}]},"intro":{"declaration_year":"2015"}}