{"income":{"5":{"value":"280843.95","family_comment":"","value_unclear":false,"family_hidden":false,"value_hidden":false,"family_unclear":false,"family":"97209.39","comment":"","family_comment_unclear":false},"6":{"value":"259266.16","family_comment":"","value_unclear":false,"comment_hidden":false,"family_hidden":false,"value_hidden":false,"family_unclear":false,"family":"97209.39","comment":""},"7":{"value":"","value_hidden":false,"family_comment":"","source_name":"","family":"","comment":"","source_name_hidden":false},"8":{"family_comment":"","value":"","family":"","comment":""},"9":{"value":"21577.79","comment_hidden":false,"value_hidden":false,"family_comment":"","family":"","comment":""},"10":{"value":"","value_unclear":false,"value_hidden":false,"family_comment":"","family":"","comment":""},"11":{"family_comment":"","value":"","family":"","comment":""},"12":{"family_comment":"","value":"","family":"","comment":""},"13":{"family_comment":"","value":"","family_hidden":false,"comment":"","family":""},"14":{"family_comment":"","value":"","family":"","comment":""},"15":{"family_comment":"","family_unclear":false,"value":"","family":"","comment":""},"16":{"family_comment":"","value":"","value_unclear":false,"family":"","comment":""},"17":{"family_comment":"","value":"","family":"","comment":""},"18":{"family_comment":"","value":"","family":"","comment":""},"19":{"family_comment":"","value":"","comment_unclear":false,"family":"","comment":""},"20":{"value":"","comment_unclear":false,"family_hidden":false,"value_hidden":false,"family_comment":"","family":"","comment":""}},"vehicle":{"40":[{"year_hidden":false,"brand_info":"","sum_rent_comment":"","year":"2007","brand_info_hidden":false,"brand_info_unclear":false,"sum_rent":"","sum":"","brand":"Lexus RX 350","sum_comment":"","brand_unclear":false,"brand_hidden":false}]},"id":"vulyk_64_6","banks":{"45":[{"sum_foreign_comment":"","sum_units":"USD","sum_comment":"","sum_comment_unclear":false,"sum_foreign_units":"UAH","sum_comment_hidden":true,"sum_unclear":false,"sum":"10000","sum_foreign":""}]},"declaration":{"additional_info_text":"","notfull_lostpages":"","date":"2015-03-24T00:00:00","notfull":"","additional_info":"","url":"http://static.declarations.com.ua/declarations/chosen_ones/mega_batch/cherniavska_larysa_mykolaivna.pdf"},"liabilities":{"54":{"sum_foreign_comment":"","sum":"","sum_comment":"","sum_foreign_comment_hidden":false,"sum_hidden":false,"sum_comment_hidden":false,"sum_unclear":false,"sum_foreign":""},"55":{"sum_foreign_comment":"","sum":"","sum_comment":"","sum_comment_unclear":false,"sum_foreign":""},"56":{"sum_foreign_comment":"","sum":"","sum_comment":"","sum_unclear":false,"sum_foreign":""},"57":{"sum_foreign_comment":"","sum":"","sum_comment":"","sum_hidden":false,"sum_unclear":false,"sum_foreign":""},"58":{"sum_foreign_comment":"","sum":"","sum_comment":"","sum_unclear":false,"sum_foreign":""},"59":{"sum_foreign_comment":"","sum":"","sum_comment":"","sum_comment_unclear":false,"sum_comment_hidden":false,"sum_unclear":false,"sum_foreign":""},"60":{"sum_foreign_comment":"","sum":"","sum_comment":"","sum_foreign":""},"61":{"sum_foreign_comment":"","sum":"","sum_comment":"","sum_foreign":""},"62":{"sum_foreign_comment":"","sum":"","sum_comment":"","sum_unclear":false,"sum_foreign":""},"63":{"sum_foreign_comment":"","sum":"","sum_comment":"","sum_unclear":false,"sum_foreign":""},"64":{"sum_foreign_comment":"","sum":"","sum_comment":"","sum_comment_unclear":false,"sum_unclear":false,"sum_foreign":""}},"ft_src":"суддя приморського районного суду м. одеси\nОдеська область\nЗагальний місцевий суд\nЛариса\nМацей А. О\nПодружжя\nЧернявська О. А\nДитина\nМиколаївна\nЧернявська Лариса Миколаївна\nЧернявська\nЧернявська Лариса Миколаївна\nЛариса Миколаївна Чернявська\nЛариса Чернявська\nЧернявська Лариса Миколаївна\nLexus RX 350\n2007\n10000\n2014\nLexus RX 350\n2007\n10000\n21.7\n65.8\n1/3 квартири\n196.6\nЗагальний місцевий суд\nОдеська область\nсуддя приморського районного суду м. одеси\nПодружжя\nМацей А. О\nДитина\nЧернявська О. А\nЧернявська Лариса Миколаївна\nЛариса Миколаївна Чернявська\nЛариса Чернявська\nЧернявська Лариса Миколаївна\nЧернявська Лариса Миколаївна\nЛариса\nЧернявська\nМиколаївна\n97209.39\n259266.16\n280843.95\n97209.39\n21577.79\n2014\n1/3 квартири\n65.8\n21.7\n196.6\nПодружжя\nМацей А. О\nДитина\nЧернявська О. А\nМиколаївна\nЧернявська\nЛариса\nЧернявська Лариса Миколаївна\nЛариса Миколаївна Чернявська\nЛариса Чернявська\nЧернявська Лариса Миколаївна\nОдеська область\nЗагальний місцевий суд\nсуддя приморського районного суду м. одеси\nЧернявська Лариса Миколаївна\n97209.39\n259266.16\n97209.39\n280843.95\n21577.79\n2007\nLexus RX 350\n280843.95\n97209.39\n21577.79\n259266.16\n97209.39\n1/3 квартири\n65.8\n196.6\n21.7\n10000\n2014","general":{"inn":"","name":"Лариса","last_name_hidden":false,"family":[{"inn":"","inn_hidden":true,"relations_unclear":false,"relations_hidden":false,"relations_other":"","relations":"Подружжя","name_hidden":true,"inn_unclear":false,"family_name":"Мацей А. О","name_unclear":false},{"inn":"","inn_hidden":true,"relations_unclear":false,"relations_hidden":false,"relations_other":"","relations":"Дитина","name_hidden":false,"family_name":"Чернявська О. А","name_unclear":false}],"patronymic":"Миколаївна","inn_hidden":true,"family_raw":"","inn_unclear":false,"post":{"post_unclear":false,"post":"суддя приморського районного суду м. одеси","candidate":"","office_hidden":false,"region":"Одеська область","post_hidden":false,"office":"Загальний місцевий суд","office_unclear":false,"region_hidden":false},"last_name_unclear":false,"full_name":"Чернявська Лариса Миколаївна","addresses":[{"place_city_type_unclear":false,"place_address":"","place_district_hidden":true,"place_city_type":"","place_city_hidden":true,"place_city_type_hidden":true,"place":"","place_district":"","place_unclear":false,"place_city":"","place_city_unclear":false,"place_hidden":true,"place_address_hidden":true}],"last_name":"Чернявська","patronymic_hidden":false,"full_name_suggest":{"output":"Чернявська Лариса Миколаївна","input":["Чернявська Лариса Миколаївна","Лариса Миколаївна Чернявська","Лариса Чернявська"]},"name_unclear":false},"source":"VULYK","estate":{"25":[{"region_unclear":false,"space_unclear":false,"costs":"","costs_rent_unclear":false,"costs_comment":"","costs_hidden":false,"address_hidden":true,"region_hidden":true,"space_comment":"","space_hidden":false,"space":"196.6","space_units_hidden":false,"costs_rent_comment_unclear":false,"region":"","costs_rent_comment":"","costs_rent_hidden":false,"space_comment_unclear":false,"space_units":"м²","address":"","costs_rent":"","costs_unclear":false}],"27":[{"space_unclear":false,"costs":"","costs_comment":"","costs_hidden":false,"address_hidden":true,"region_hidden":true,"space_comment":"","space_hidden":false,"space":"21.7","address":"","region":"","address_unclear":false,"costs_rent_comment":"","costs_rent_hidden":false,"space_units":"м²","costs_rent":""}],"31":[{"region_unclear":false,"address_hidden":true,"region_hidden":true,"space_comment":"1/3 квартири","space":"65.8","address":"","region":"","costs_property":"","costs_rent_comment":"","space_comment_hidden":false,"space_units":"м²","costs_property_comment":"","costs_rent":""}]},"intro":{"declaration_year":"2014","isnotdeclaration":"","declaration_year_unclear":false,"declaration_year_hidden":false}}