{"income":{"5":{"family_comment":"","value":"355905","family":"89667","comment":""},"6":{"family_comment":"","value":"276573","value_unclear":false,"family":"35784","comment":""},"7":{"value":"","family_comment":"","source_name":"","family":"","comment":"","source_name_hidden":false},"8":{"family_comment":"","value":"","family":"","comment":""},"9":{"family_comment":"","value":"39348","family":"1251","comment":""},"10":{"family_comment":"","value":"13398","family":"","comment":""},"11":{"family_comment":"","value":"","comment_hidden":false,"family":"","comment":""},"12":{"family_comment":"","value":"","family":"","comment":""},"13":{"family_comment":"","value":"","family":"","comment":""},"14":{"family_comment":"","value":"","family":"","comment":""},"15":{"value":"","family_comment":"","value_unclear":false,"family_unclear":false,"family":"","comment":""},"16":{"family_comment":"","value":"","family":"","comment":""},"17":{"family_comment":"","value":"","family":"","comment":""},"18":{"family_comment":"","value":"","family":"","comment":""},"19":{"family_comment":"","value":"","family":"","comment":""},"20":{"family_comment":"","value":"26586","comment_unclear":false,"family":"52632","comment":""}},"id":"vulyk_104_140","banks":{"45":[{"sum_foreign_comment":"","sum_units":"UAH","sum_comment":"","sum_hidden":false,"sum_foreign_units":"UAH","sum_foreign_hidden":false,"sum_comment_hidden":true,"sum_unclear":true,"sum":"132417","sum_foreign":""}],"46":[{"sum_foreign_comment":"","sum_units":"UAH","sum_comment":"","sum_hidden":false,"sum_foreign_units":"UAH","sum_comment_hidden":false,"sum":"2004","sum_foreign":""}]},"declaration":{"date":"2016-03-30T00:00:00","additional_info_text":"","additional_info":"","url":"http://static.declarations.com.ua/declarations/chosen_ones/judges_batch/1938_fidria_oleksandr_mykolaiovych-2015.pdf"},"liabilities":{"54":{"sum_foreign_comment":"","sum_foreign_hidden":false,"sum_comment":"","sum_hidden":false,"sum_comment_hidden":true,"sum_unclear":true,"sum":"120","sum_foreign":""},"55":{"sum_foreign_comment":"","sum":"","sum_comment":"","sum_foreign":""},"56":{"sum_foreign_comment":"","sum":"","sum_comment":"","sum_unclear":false,"sum_foreign":""},"57":{"sum_foreign_comment":"","sum_foreign_hidden":false,"sum_comment":"","sum_comment_unclear":false,"sum_comment_hidden":false,"sum":"","sum_foreign":""},"58":{"sum_foreign_comment":"","sum":"","sum_comment":"","sum_unclear":false,"sum_foreign":""},"59":{"sum_foreign_comment":"","sum":"","sum_comment":"","sum_foreign":""},"60":{"sum_foreign_comment":"","sum_foreign_hidden":false,"sum_comment":"","sum_comment_hidden":false,"sum":"","sum_foreign":""},"61":{"sum_foreign_comment":"","sum":"","sum_comment":"","sum_foreign":""},"62":{"sum_foreign_comment":"","sum":"","sum_comment":"","sum_foreign":""},"63":{"sum_foreign_comment":"","sum":"","sum_comment":"","sum_foreign":""},"64":{"sum_foreign_comment":"","sum":"","sum_comment":"","sum_foreign":""}},"ft_src":"120\nФідря Олександр Миколайович\nсуддя, заступник голови апеляційного суду волинської області\nВолинська область\nЗагальний апеляційний суд\nОлександр\nФідря Ганна Дмитрівна\nПодружжя\nЛізунева Олександра Олексіївна\nмати дружини\nІнше\nФідря Олександр Миколайович\nОлександр Миколайович Фідря\nОлександр Фідря\nФідря Олександр Миколайович\nФідря\nМиколайович\n1251\n39348\n13398\n52632\n26586\n89667\n355905\n35784\n276573\n2004\n132417\n600\n48.5\n38\n66.5\n2015\n35784\n276573\n1251\n39348\n13398\n89667\n355905\n52632\n26586\n132417\n2004\n2015\nПодружжя\nФідря Ганна Дмитрівна\nІнше\nЛізунева Олександра Олексіївна\nмати дружини\nФідря\nФідря Олександр Миколайович\nОлександр Миколайович Фідря\nОлександр Фідря\nФідря Олександр Миколайович\nФідря Олександр Миколайович\nОлександр\nМиколайович\nЗагальний апеляційний суд\nсуддя, заступник голови апеляційного суду волинської області\nВолинська область\n120\n276573\n35784\n26586\n52632\n355905\n89667\n39348\n1251\n13398\n600\n38\n48.5\n66.5\n120\nПодружжя\nФідря Ганна Дмитрівна\nІнше\nЛізунева Олександра Олексіївна\nмати дружини\nМиколайович\nФідря\nсуддя, заступник голови апеляційного суду волинської області\nЗагальний апеляційний суд\nВолинська область\nФідря Олександр Миколайович\nФідря Олександр Миколайович\nОлександр Миколайович Фідря\nОлександр Фідря\nФідря Олександр Миколайович\nОлександр\n48.5\n600\n38\n66.5\n132417\n2004\n2015","general":{"inn":"","inn_hidden":true,"last_name":"Фідря","post":{"region":"Волинська область","region_unclear":false,"post":"суддя, заступник голови апеляційного суду волинської області","office_unclear":false,"office":"Загальний апеляційний суд"},"name":"Олександр","full_name":"Фідря Олександр Миколайович","family_raw":"","addresses":[{"place_district":"","place_city_hidden":true,"place_city":"","place_city_type_hidden":false,"place_district_hidden":false,"place_city_type":"","place_address_hidden":true,"place_address":"","place_hidden":false,"place":""}],"family":[{"inn":"","relations":"Подружжя","relations_other":"","inn_hidden":true,"family_name":"Фідря Ганна Дмитрівна","name_hidden":true,"name_unclear":false},{"inn":"","relations":"Інше","relations_other":"мати дружини","inn_hidden":false,"family_name":"Лізунева Олександра Олексіївна","name_hidden":false,"name_unclear":false}],"full_name_suggest":{"output":"Фідря Олександр Миколайович","input":["Фідря Олександр Миколайович","Олександр Миколайович Фідря","Олександр Фідря"]},"patronymic":"Миколайович"},"source":"VULYK","estate":{"23":[{"space_hidden":false,"costs":"","costs_comment":"","address_hidden":false,"region_hidden":true,"space_comment":"","space":"600","address":"","region":"","costs_rent_comment":"","space_comment_unclear":false,"space_units":"м²","costs_rent":""}],"25":[{"costs":"","costs_comment":"","address_hidden":false,"region_hidden":true,"space_comment":"","space":"66.5","address":"","costs_unclear":false,"region":"","costs_rent_comment":"","space_comment_unclear":false,"space_units":"м²","costs_rent":""}],"26":[{"costs_rent":"","region":"","costs":"","costs_rent_comment":"","costs_comment":"","address_hidden":false,"region_hidden":true,"space_comment":"","space_units":"м²","space":"38","address":""}],"31":[{"space_unclear":false,"address_hidden":true,"region_hidden":true,"space_comment":"","space_hidden":false,"space":"48.5","address":"","region":"","costs_property":"","costs_rent_comment":"","space_units":"м²","costs_property_comment":"","costs_rent":""}]},"intro":{"declaration_year":"2015","isnotdeclaration":""}}