{"income":{"5":{"family_comment":"","value":"383044","family":"50900","comment":""},"6":{"family_comment":"","value":"250427","family_hidden":false,"comment":"","family":""},"7":{"family_comment":"","value":"","source_name":"","family":"","comment":""},"8":{"family_comment":"","value":"","family":"","comment":""},"9":{"value":"","value_unclear":false,"family_hidden":false,"family_comment":"","family":"","comment":""},"10":{"value":"12617","family_comment":"","family_hidden":false,"value_hidden":false,"family_unclear":false,"family":"","comment":""},"11":{"family_comment":"","value":"","family":"","comment":""},"12":{"family_comment":"","value":"","family":"","comment":""},"13":{"family_comment":"","value":"","family":"","comment":""},"14":{"family_comment":"","value":"","family":"","comment":""},"15":{"family_comment":"","value":"","family":"","comment":""},"16":{"family_comment":"","value":"120000","family":"","comment":""},"17":{"family_comment":"","value":"","family":"","comment":""},"18":{"family_comment":"","value":"","family":"","comment":""},"19":{"family_comment":"","value":"","family":"","comment":""},"20":{"value":"","comment_unclear":false,"family_comment":"","family":"50900","comment":"","family_comment_unclear":false}},"vehicle":{"35":[{"brand_info":"","sum_rent_comment":"","brand":"Toyota Land Cruiser Prado","sum_comment":"","brand_unclear":false,"year":"2012","brand_hidden":false,"brand_info_unclear":false,"sum":"543599","sum_rent":"","sum_unclear":false}]},"id":"vulyk_75_127","declaration":{"additional_info_text":"","notfull_lostpages":"","date":"2014-03-15T00:00:00","notfull":"","additional_info":"","url":"http://static.declarations.com.ua/declarations/chosen_ones/judges_batch/1808_faidiuk_vitalii_vasylovych.pdf"},"liabilities":{"54":{"sum_foreign_comment":"","sum":"","sum_comment":"","sum_foreign":""},"55":{"sum_foreign_comment":"","sum":"","sum_comment":"","sum_foreign":""},"56":{"sum_foreign_comment":"","sum":"5803","sum_comment":"","sum_foreign":""},"57":{"sum_foreign_comment":"","sum":"","sum_comment":"","sum_foreign":""},"58":{"sum_foreign_comment":"","sum":"","sum_comment":"","sum_foreign":""},"59":{"sum_foreign_comment":"","sum":"","sum_comment":"","sum_comment_unclear":false,"sum_unclear":false,"sum_foreign":""},"60":{"sum_foreign_comment":"","sum":"","sum_comment":"","sum_foreign":""},"61":{"sum_foreign_comment":"","sum":"","sum_comment":"","sum_foreign":""},"62":{"sum_foreign_comment":"","sum":"","sum_comment":"","sum_unclear":false,"sum_foreign":""},"63":{"sum_foreign_comment":"","sum":"","sum_comment":"","sum_foreign":""},"64":{"sum_foreign_comment":"","sum":"","sum_comment":"","sum_foreign":""}},"ft_src":"5803\nФайдюк Віталій Васильович\nсуддя київського апеляційного адміністративного суду\nм. Київ\nАпеляційний адміністративний суд\nВіталій\nФайдюк Н. І\nПодружжя\nФайдюк О. Н\nБатьки\nМарушан К. І\nІнше\nмати дружини\nФайдюк Віталій Васильович\nВіталій Васильович Файдюк\nВіталій Файдюк\nФайдюк Віталій Васильович\nФайдюк\nВасильович\nToyota Land Cruiser Prado\n543599\n2012\n.04\n2.5\n2.3\n2.1\n86.4\n2013\n250427\n12617\n50900\n383044\n120000\n50900\n543599\n2012\nToyota Land Cruiser Prado\n2013\nФайдюк\nВасильович\nПодружжя\nФайдюк Н. І\nБатьки\nФайдюк О. Н\nІнше\nмати дружини\nМарушан К. І\nФайдюк Віталій Васильович\nВіталій Васильович Файдюк\nВіталій Файдюк\nФайдюк Віталій Васильович\nВіталій\nФайдюк Віталій Васильович\nАпеляційний адміністративний суд\nсуддя київського апеляційного адміністративного суду\nм. Київ\n5803\n250427\n50900\n383044\n50900\n120000\n12617\n.04\n2.5\n2.3\n2.1\n86.4\n5803\nФайдюк Н. І\nПодружжя\nФайдюк О. Н\nБатьки\nмати дружини\nМарушан К. І\nІнше\nФайдюк\nВасильович\nсуддя київського апеляційного адміністративного суду\nм. Київ\nАпеляційний адміністративний суд\nФайдюк Віталій Васильович\nФайдюк Віталій Васильович\nВіталій Васильович Файдюк\nВіталій Файдюк\nФайдюк Віталій Васильович\nВіталій\n543599\n2012\nToyota Land Cruiser Prado\n12617\n50900\n50900\n383044\n120000\n250427\n.04\n86.4\n2.5\n2.3\n2.1\n2013","general":{"inn":"","inn_hidden":true,"last_name":"Файдюк","post":{"office":"Апеляційний адміністративний суд","region":"м. Київ","post":"суддя київського апеляційного адміністративного суду"},"name":"Віталій","full_name":"Файдюк Віталій Васильович","family_raw":"","addresses":[{"place_district":"","place_address_hidden":true,"place_city":"","place_city_type_hidden":false,"place_district_hidden":false,"place_city_type":"","place_city_hidden":false,"place_address":"","place_hidden":true,"place":""}],"family":[{"inn":"","inn_hidden":true,"relations_hidden":false,"family_name":"Файдюк Н. І","relations_other":"","relations":"Подружжя","name_hidden":false,"name_unclear":false},{"inn":"","relations":"Батьки","relations_other":"","inn_hidden":false,"family_name":"Файдюк О. Н","name_hidden":false,"name_unclear":false},{"inn":"","relations":"Інше","relations_other":"мати дружини","inn_hidden":false,"family_name":"Марушан К. І","name_hidden":false,"name_unclear":true}],"full_name_suggest":{"output":"Файдюк Віталій Васильович","input":["Файдюк Віталій Васильович","Віталій Васильович Файдюк","Віталій Файдюк"]},"patronymic":"Васильович"},"source":"VULYK","estate":{"23":[{"costs":"","costs_comment":"","address_hidden":false,"region_hidden":true,"space_comment":"","space":".04","address":"","region":"","costs_rent_comment":"","space_units":"га","space_units_hidden":false,"costs_rent":""}],"24":[{"costs_rent":"","region":"","costs":"","costs_rent_comment":"","costs_comment":"","region_hidden":true,"space_comment":"","space_units":"м²","space":"86.4","address":""}],"29":[{"space_units_unclear":false,"address_hidden":false,"region_hidden":true,"space_comment":"","space":"2.5","address":"","region":"","costs_property":"","costs_rent_comment":"","space_units":"га","costs_property_comment":"","costs_rent":""},{"costs_rent":"","region":"","costs_property":"","costs_rent_comment":"","region_hidden":false,"space_comment":"","costs_property_comment":"","space_units":"га","space":"2.3","address":""},{"costs_rent":"","costs_property":"","costs_rent_comment":"","space_comment":"","costs_property_comment":"","space_units":"га","space":"2.1","address":""}]},"intro":{"declaration_year":"2013","isnotdeclaration":""}}