{"income":{"5":{"family_comment":"","value":"243402.93","family":"","comment":""},"6":{"family_comment":"","value":"243402.93","family":"","comment":""},"7":{"family_comment":"","value":"","source_name":"","family":"","comment":""},"8":{"family_comment":"","value":"","family":"","comment":""},"9":{"value":"","comment_unclear":false,"family_comment":"","family":"","comment":"","family_comment_unclear":false},"10":{"family_comment":"","value":"","family":"","comment":""},"11":{"family_comment":"","value":"","family":"","comment":""},"12":{"family_comment":"","value":"","family":"","comment":""},"13":{"family_comment":"","value":"","family":"","comment":""},"14":{"family_comment":"","value":"","family":"","comment":""},"15":{"family_comment":"","value":"","family":"","comment":""},"16":{"family_comment":"","value":"","family":"","comment":""},"17":{"family_comment":"","value":"","family":"","comment":""},"18":{"family_comment":"","value":"","family":"","comment":""},"19":{"value":"","family_comment":"","value_unclear":false,"family_unclear":false,"family":"","comment":""},"20":{"value":"","family_comment":"","value_unclear":false,"comment_hidden":false,"family_comment_hidden":false,"family_unclear":false,"family_comment_unclear":false,"comment_unclear":false,"comment":"","family":""}},"id":"vulyk_106_121","declaration":{"additional_info_text":"","notfull_lostpages":"","date":"2016-03-31T00:00:00","notfull":"","additional_info":"","url":"http://static.declarations.com.ua/declarations/chosen_ones/judges_batch/2260_prokopchuk_tamara_stepanivna.pdf"},"liabilities":{"54":{"sum_foreign_comment":"","sum":"","sum_comment":"","sum_comment_unclear":false,"sum_hidden":false,"sum_comment_hidden":false,"sum_foreign":""},"55":{"sum_foreign_comment":"","sum":"","sum_hidden":false,"sum_comment":"","sum_foreign":""},"56":{"sum_foreign_comment":"","sum":"","sum_comment":"","sum_hidden":false,"sum_comment_hidden":false,"sum_unclear":false,"sum_foreign":""},"57":{"sum_foreign_comment":"","sum":"","sum_comment":"","sum_hidden":false,"sum_comment_hidden":false,"sum_foreign":""},"58":{"sum_foreign_comment":"","sum":"","sum_comment":"","sum_hidden":false,"sum_comment_hidden":false,"sum_foreign":""},"59":{"sum_foreign_comment":"","sum":"","sum_comment":"","sum_foreign":""},"60":{"sum_foreign_comment":"","sum":"","sum_comment":"","sum_hidden":false,"sum_comment_hidden":false,"sum_foreign":""},"61":{"sum_foreign_comment":"","sum":"","sum_comment":"","sum_foreign":""},"62":{"sum_foreign_comment":"","sum":"","sum_comment":"","sum_comment_hidden":false,"sum_unclear":false,"sum_foreign":""},"63":{"sum_foreign_comment":"","sum":"","sum_comment":"","sum_foreign":""},"64":{"sum_foreign_comment":"","sum":"","sum_comment":"","sum_foreign":""}},"ft_src":"суддя дніпропетровського апеляційного адміністративного суду\nДніпропетровська область\nАпеляційний адміністративний суд\nТамара\nКубрак О. О\nДитина\nСтепанівна\nПрокопчук Тамара Степанівна\nТамара Степанівна Прокопчук\nТамара Прокопчук\nПрокопчук Тамара Степанівна\nПрокопчук Тамара Степанівна\nПрокопчук\n243402.93\n243402.93\n33.92\n33.92\n2015\n243402.93\n243402.93\n33.92\n33.92\nПрокопчук Тамара Степанівна\nТамара Степанівна Прокопчук\nТамара Прокопчук\nПрокопчук Тамара Степанівна\nПрокопчук Тамара Степанівна\nДитина\nКубрак О. О\nТамара\nПрокопчук\nДніпропетровська область\nАпеляційний адміністративний суд\nсуддя дніпропетровського апеляційного адміністративного суду\nСтепанівна\n243402.93\n243402.93\n2015\nКубрак О. О\nДитина\nСтепанівна\nПрокопчук\nТамара\nПрокопчук Тамара Степанівна\nТамара Степанівна Прокопчук\nТамара Прокопчук\nПрокопчук Тамара Степанівна\nДніпропетровська область\nАпеляційний адміністративний суд\nсуддя дніпропетровського апеляційного адміністративного суду\nПрокопчук Тамара Степанівна\n33.92\n33.92\n2015","general":{"inn":"","name":"Тамара","inn_unclear":false,"family":[{"inn":"","inn_hidden":false,"relations_unclear":false,"relations_hidden":false,"relations_other":"","relations":"Дитина","name_hidden":false,"family_name":"Кубрак О. О","name_unclear":false}],"inn_hidden":true,"family_raw":"","last_name":"Прокопчук","post":{"region_unclear":false,"region":"Дніпропетровська область","post":"суддя дніпропетровського апеляційного адміністративного суду","office":"Апеляційний адміністративний суд","office_unclear":false,"post_hidden":false},"full_name":"Прокопчук Тамара Степанівна","addresses":[{"place_district":"","place_city_hidden":false,"place_city":"","place_city_type_hidden":false,"place_district_hidden":false,"place_city_type":"","place_address_hidden":false,"place_address":"","place_hidden":true,"place":""}],"patronymic":"Степанівна","full_name_suggest":{"output":"Прокопчук Тамара Степанівна","input":["Прокопчук Тамара Степанівна","Тамара Степанівна Прокопчук","Тамара Прокопчук"]},"name_unclear":false},"source":"VULYK","estate":{"25":[{"costs":"","costs_comment":"","address_hidden":false,"region_hidden":true,"space_comment":"","space":"33.92","address":"","region":"","costs_rent_comment":"","space_comment_unclear":false,"space_units":"м²","costs_rent":""}],"31":[{"space_unclear":false,"address_hidden":true,"region_hidden":true,"space_comment":"","space_hidden":false,"space":"33.92","address":"","region":"","costs_property":"","costs_rent_comment":"","space_comment_unclear":false,"space_units":"м²","costs_property_comment":"","costs_rent":""}]},"intro":{"declaration_year":"2015","isnotdeclaration":""}}