{"income":{"5":{"value":"232370.73","family_unclear":false,"family_hidden":false,"family_comment":"","family":"38961.51","comment":""},"6":{"value":"232370.73","family_comment":"","value_unclear":false,"family_hidden":false,"family_unclear":false,"family":"38961.51","comment":""},"7":{"value":"","family_hidden":false,"value_hidden":false,"family_comment":"","source_name":"","family":"","comment":"","source_name_hidden":false},"8":{"family_comment":"","value":"","family":"","comment":""},"9":{"family_comment":"","value":"","family":"","comment":""},"10":{"family_comment":"","value":"","value_unclear":false,"family":"","comment":""},"11":{"family_comment":"","value":"","family":"","comment":""},"12":{"family_comment":"","value":"","family":"","comment":""},"13":{"family_comment":"","value":"","family":"","comment":""},"14":{"family_comment":"","value":"","family":"","comment":""},"15":{"family_comment":"","value":"","family":"","comment":""},"16":{"family_comment":"","value":"","family":"","comment":""},"17":{"family_comment":"","value":"","family":"","comment":""},"18":{"family_comment":"","value":"","family":"","comment":""},"19":{"family_comment":"","value":"","family":"","comment":""},"20":{"value":"","family_comment":"","value_unclear":false,"family_unclear":false,"comment_unclear":false,"comment":"","family":""}},"id":"vulyk_74_126","banks":{"45":[{"sum_foreign_comment":"","sum":"4478.65","sum_comment":"","sum_comment_unclear":false,"sum_hidden":false,"sum_foreign_units":"UAH","sum_foreign_hidden":false,"sum_units":"UAH","sum_comment_hidden":false,"sum_unclear":false,"sum_foreign":""}]},"declaration":{"additional_info_text":"","notfull_lostpages":"","date":"2014-03-18T00:00:00","notfull":"","additional_info":"","url":"http://static.declarations.com.ua/declarations/chosen_ones/judges_batch/1567_tsiliuryk_viktor_petrovych.pdf"},"liabilities":{"54":{"sum_foreign_comment":"","sum":"","sum_comment":"","sum_comment_unclear":false,"sum_comment_hidden":false,"sum_foreign":""},"55":{"sum_foreign_comment":"","sum":"","sum_comment":"","sum_hidden":false,"sum_unclear":false,"sum_foreign":""},"56":{"sum_foreign_comment":"","sum":"","sum_comment":"","sum_hidden":false,"sum_unclear":false,"sum_foreign":""},"57":{"sum_foreign_comment":"","sum":"","sum_comment":"","sum_comment_unclear":false,"sum_comment_hidden":false,"sum_foreign":""},"58":{"sum_foreign_comment":"","sum_comment_hidden":false,"sum":"","sum_comment":"","sum_foreign":""},"59":{"sum_foreign_comment":"","sum":"","sum_comment":"","sum_foreign":""},"60":{"sum_foreign_comment":"","sum":"","sum_hidden":false,"sum_comment":"","sum_foreign":""},"61":{"sum_foreign_comment":"","sum":"","sum_comment":"","sum_foreign":""},"62":{"sum_foreign_comment":"","sum":"","sum_comment":"","sum_foreign":""},"63":{"sum_foreign_comment":"","sum":"","sum_comment":"","sum_comment_unclear":false,"sum_unclear":false,"sum_foreign":""},"64":{"sum_foreign_comment":"","sum":"","sum_comment":"","sum_comment_unclear":false,"sum_unclear":false,"sum_foreign":""}},"ft_src":"Харків\nХарківська область\nЦілюрик Віктор Петрович\nсуддя жовтневого районного суду м. харкова, суддя апеляційного суду харківської області\nХарківська область\nЗагальний апеляційний суд\nВіктор\nПересіченська Ольга Михайлівна, 19. 07. 1980 р. н\nПодружжя\nЦілюрик Віктор Петрович\nВіктор Петрович Цілюрик\nВіктор Цілюрик\nЦілюрик Віктор Петрович\nЦілюрик\nПетрович\n26.5\n64.5\n255766\n31.8\n4478.65\n2013\n2013\nЗагальний апеляційний суд\nХарківська область\nсуддя жовтневого районного суду м. харкова, суддя апеляційного суду харківської області\nПетрович\nЦілюрик Віктор Петрович\nВіктор Петрович Цілюрик\nВіктор Цілюрик\nЦілюрик Віктор Петрович\nВіктор\nХарківська область\nХарків\nЦілюрик Віктор Петрович\nЦілюрик\nПодружжя\nПересіченська Ольга Михайлівна, 19. 07. 1980 р. н\n38961.51\n232370.73\n232370.73\n38961.51\n26.5\n64.5\n255766\n31.8\n4478.65\n38961.51\n232370.73\n38961.51\n232370.73\nПодружжя\nПересіченська Ольга Михайлівна, 19. 07. 1980 р. н\nХарківська область\nХарків\nПетрович\nЦілюрик\nХарківська область\nЗагальний апеляційний суд\nсуддя жовтневого районного суду м. харкова, суддя апеляційного суду харківської області\nЦілюрик Віктор Петрович\nЦілюрик Віктор Петрович\nВіктор Петрович Цілюрик\nВіктор Цілюрик\nЦілюрик Віктор Петрович\nВіктор\n232370.73\n38961.51\n232370.73\n38961.51\n64.5\n255766\n31.8\n26.5\n4478.65\n2013","general":{"inn":"","inn_hidden":true,"last_name":"Цілюрик","post":{"region_unclear":false,"region":"Харківська область","post":"суддя жовтневого районного суду м. харкова, суддя апеляційного суду харківської області","office":"Загальний апеляційний суд","office_unclear":false,"post_hidden":false},"name":"Віктор","full_name":"Цілюрик Віктор Петрович","family_raw":"","addresses":[{"place_district":"","place_city_hidden":false,"place_city":"Харків","place_city_type_hidden":false,"place_district_hidden":true,"place_city_type":"Місто","place_address_hidden":true,"place_address":"","place_hidden":false,"place":"Харківська область"}],"family":[{"inn":"","relations":"Подружжя","relations_other":"","inn_hidden":true,"family_name":"Пересіченська Ольга Михайлівна, 19. 07. 1980 р. н","name_hidden":false,"name_unclear":false}],"full_name_suggest":{"output":"Цілюрик Віктор Петрович","input":["Цілюрик Віктор Петрович","Віктор Петрович Цілюрик","Віктор Цілюрик"]},"patronymic":"Петрович"},"source":"VULYK","estate":{"25":[{"space_hidden":false,"costs":"","costs_comment":"","address_hidden":false,"region_hidden":true,"space_comment":"","space_unclear":false,"space":"64.5","address":"","region":"","costs_rent_comment":"","space_units":"м²","costs_rent":""},{"costs_rent":"","region":"","costs":"255766","costs_rent_comment":"","costs_comment":"грн","region_hidden":false,"space_comment":"","space_units":"м²","space":"31.8","address":""}],"27":[{"costs":"","costs_comment":"","address_hidden":false,"region_hidden":true,"space_comment":"","space":"26.5","address":"","region":"","address_unclear":false,"costs_rent_comment":"","space_units":"м²","costs_rent":""}]},"intro":{"declaration_year":"2013","isnotdeclaration":"","declaration_year_unclear":false}}