{"income":{"5":{"family_comment":"","family_unclear":false,"value":"291633","family":"553678","comment":""},"6":{"value":"242460","family_comment":"","comment_unclear":false,"family_unclear":false,"family":"251373","comment":""},"7":{"source_name_unclear":false,"value":"","family_comment":"","source_name":"","family":"","comment":"","source_name_hidden":false},"8":{"family_comment":"","value":"","family":"","comment":""},"9":{"family_comment":"","value":"","family":"","comment":""},"10":{"family_comment":"","value":"13398","comment_unclear":false,"family":"13398","comment":""},"11":{"family_comment":"","value":"","family":"","comment":""},"12":{"family_comment":"","value":"","family":"","comment":""},"13":{"family_comment":"","value":"","family":"","comment":""},"14":{"family_comment":"","value":"","family":"","comment":""},"15":{"family_comment":"","value":"2371","family":"","comment":""},"16":{"value":"","comment_hidden":false,"value_hidden":false,"family_comment":"","family":"","comment":"","family_comment_unclear":false},"17":{"family_comment":"","value":"","family":"","comment":""},"18":{"family_comment":"","value":"","family":"","comment":""},"19":{"family_comment":"","value":"","family":"","comment":""},"20":{"value":"33404","family_comment":"","comment_unclear":false,"family_unclear":false,"value_unclear":false,"family":"288897","comment":"","family_comment_unclear":false}},"vehicle":{"35":[{"brand_info":"2494 куб. см., 170 к. с","sum_rent_comment":"","year":"2013","sum_rent_unclear":false,"brand_info_hidden":false,"brand_info_unclear":false,"sum_rent":"","sum":"","brand":"Toyota Rav 4","sum_comment":"","brand_unclear":false,"brand_hidden":false,"sum_unclear":false,"sum_comment_unclear":false}],"40":[{"year_hidden":false,"brand_info":"2982 куб. см., 127 кВт","sum_rent_comment":"","year":"2010","brand_info_hidden":false,"brand_info_unclear":false,"sum_rent":"","sum":"","brand":"Toyota Land Cruiser-150","sum_comment":"","brand_hidden":false,"sum_unclear":false},{"brand_info":"1240 куб. см., 102 к. с","sum":"","brand":"Nissan Micra","sum_comment":"","year":"2008","sum_rent_comment":"","sum_rent":""},{"brand_info":"2.5 LSE, 2494 куб. см., 170 к. с","sum":"","brand":"Toyota Camry","sum_comment":"","year":"2012","sum_rent_comment":"","sum_rent":""}]},"id":"vulyk_58_47","banks":{"45":[{"sum_foreign_comment":"","sum_units":"UAH","sum_comment":"","sum_comment_unclear":false,"sum_hidden":false,"sum_foreign_units":"UAH","sum_comment_hidden":false,"sum_units_hidden":false,"sum":"","sum_foreign":""},{"sum_foreign_comment":"","sum":"","sum_comment":"","sum_foreign_units":"","sum_units":"","sum_foreign":""}],"46":[{"sum_foreign_comment":"","sum":"","sum_comment":"","sum_foreign_units":"UAH","sum_comment_hidden":false,"sum_units":"UAH","sum_foreign":""}],"47":[{"sum_foreign_comment":"","sum":"","sum_comment":"","sum_foreign_units":"UAH","sum_comment_hidden":false,"sum_units":"UAH","sum_foreign":""}],"48":[{"sum_foreign_comment":"","sum":"","sum_comment":"","sum_foreign_units":"UAH","sum_units":"UAH","sum_foreign":""}],"49":[{"sum_foreign_comment":"","sum":"","sum_comment":"","sum_foreign_units":"UAH","sum_units":"UAH","sum_foreign":""}],"50":[{"sum_foreign_comment":"","sum":"","sum_comment":"","sum_foreign_units":"UAH","sum_units":"UAH","sum_foreign":""}],"51":[{"sum_foreign_comment":"","sum":"","sum_comment":"","sum_foreign_units":"UAH","sum_comment_hidden":false,"sum_units":"UAH","sum_foreign":""},{"sum_foreign_comment":"","sum":"","sum_comment":"","sum_comment_hidden":false,"sum_units":"","sum_foreign":""}],"52":[{"sum_foreign_comment":"","sum":"","sum_comment":"","sum_foreign_units":"UAH","sum_units":"UAH","sum_foreign":""}],"53":[{"sum_foreign_comment":"","sum":"","sum_comment":"","sum_foreign_units":"UAH","sum_units":"UAH","sum_foreign":""}]},"declaration":{"additional_info_text":"","notfull_lostpages":"","date":"2015-03-26T00:00:00","notfull":"","additional_info":"","url":"http://static.declarations.com.ua/declarations/chosen_ones/mega_batch/zhyznevska_anzhela_vladyslavivna.pdf"},"liabilities":{"54":{"sum_foreign_comment":"","sum":"","sum_foreign":"","sum_comment":"","sum_hidden":false},"55":{"sum_foreign_comment":"","sum":"","sum_foreign":"","sum_comment":"","sum_hidden":false},"56":{"sum_foreign_comment":"","sum":"16300","sum_comment":"","sum_unclear":false,"sum_foreign":"2950"},"57":{"sum_foreign_comment":"","sum":"","sum_comment":"","sum_comment_unclear":false,"sum_comment_hidden":false,"sum_unclear":false,"sum_foreign":""},"58":{"sum_foreign_comment":"","sum":"","sum_comment":"","sum_comment_unclear":false,"sum_comment_hidden":false,"sum_unclear":false,"sum_foreign":""},"59":{"sum_foreign_comment":"","sum":"","sum_comment":"","sum_foreign":""},"60":{"sum_foreign_comment":"","sum":"","sum_comment":"","sum_comment_unclear":false,"sum_unclear":false,"sum_foreign":""},"61":{"sum_foreign_comment":"","sum":"","sum_comment":"","sum_foreign":""},"62":{"sum_foreign_comment":"","sum":"33800","sum_comment":"","sum_foreign":"2950"},"63":{"sum_foreign_comment":"","sum":"95001","sum_comment":"","sum_comment_unclear":true,"sum_comment_hidden":false,"sum_unclear":true,"sum_foreign":""},"64":{"sum_foreign_comment":"","sum":"2431","sum_comment":"","sum_comment_unclear":true,"sum_comment_hidden":false,"sum_unclear":true,"sum_foreign":""}},"ft_src":"2494 куб. см., 170 к. с\nToyota Rav 4\n2013\n2982 куб. см., 127 кВт\nToyota Land Cruiser-150\n2010\n1240 куб. см., 102 к. с\n2008\nNissan Micra\n2.5 LSE, 2494 куб. см., 170 к. с\n2012\nToyota Camry\n2014\n2494 куб. см., 170 к. с\nToyota Rav 4\n2013\n2982 куб. см., 127 кВт\nToyota Land Cruiser-150\n2010\n1240 куб. см., 102 к. с\nNissan Micra\n2008\n2.5 LSE, 2494 куб. см., 170 к. с\nToyota Camry\n2012\n384.1\nЖитомирська область\nсмт Гуйва, Житомирського р-ну\n74.26\nм. Полонне\nХмельницька область\n92\nм. Хмельницький\nХмельницька область\nБолгарія, м. Варна, КК Золоті піски\n21.9\n164\nсмт Гуйва, Житомирського р-ну\nЖитомирська область\n2100\nЖитомирська область\nсмт Гуйва, Житомирського р-ну\n1564\nХмельницька область\nм. Полонне\nм. Житомир\nЖитомирська область\n141.28\n21.9\nБолгарія, м. Варна, КК Золоті піски, 1/2 частина\nПодружжя\nЖизнєвський Юрій Васильович\nЖизневська Анжела Владиславівна\nАнжела Владиславівна Жизневська\nАнжела Жизневська\nЖизневська Анжела Владиславівна\nЖизневська Анжела Владиславівна\nАнжела\nВладиславівна\nАпеляційний адміністративний суд\nсуддя житомирського апеляційного адміністративного суду\nЖитомирська область\nЖизневська\nЖитомир\nЖитомирська область\n95001\n2431\n2950\n16300\n2950\n33800\n242460\n251373\n33404\n288897\n2371\n291633\n553678\n13398\n13398\n2014\n2431\n2950\n16300\n2950\n33800\n95001\nсмт Гуйва, Житомирського р-ну\nЖитомирська область\n2100\nХмельницька область\nм. Полонне\n1564\nсмт Гуйва, Житомирського р-ну\nЖитомирська область\n164\nсмт Гуйва, Житомирського р-ну\nЖитомирська область\n384.1\nХмельницька область\nм. Полонне\n74.26\nм. Житомир\nЖитомирська область\n141.28\nБолгарія, м. Варна, КК Золоті піски, 1/2 частина\n21.9\nм. Хмельницький\n92\nХмельницька область\nБолгарія, м. Варна, КК Золоті піски\n21.9\nЖизнєвський Юрій Васильович\nПодружжя\nВладиславівна\nЖизневська\nАнжела\nЖизневська Анжела Владиславівна\nАнжела Владиславівна Жизневська\nАнжела Жизневська\nЖизневська Анжела Владиславівна\nЖитомирська область\nЖитомир\nЖитомирська область\nсуддя житомирського апеляційного адміністративного суду\nАпеляційний адміністративний суд\nЖизневська Анжела Владиславівна\n251373\n242460\n2371\n13398\n13398\n553678\n291633\n288897\n33404","general":{"inn":"","name":"Анжела","last_name":"Жизневська","family":[{"inn":"","inn_hidden":true,"relations_hidden":false,"family_name":"Жизнєвський Юрій Васильович","relations_other":"","relations":"Подружжя","name_hidden":false,"name_unclear":true}],"inn_hidden":true,"family_raw":"","inn_unclear":false,"post":{"post_unclear":false,"post":"суддя житомирського апеляційного адміністративного суду","office_hidden":false,"region":"Житомирська область","post_hidden":false,"office":"Апеляційний адміністративний суд","office_unclear":false,"region_hidden":false},"full_name_suggest":{"output":"Жизневська Анжела Владиславівна","input":["Жизневська Анжела Владиславівна","Анжела Владиславівна Жизневська","Анжела Жизневська"]},"full_name":"Жизневська Анжела Владиславівна","addresses":[{"place_address":"","place_district_hidden":false,"place_city_type":"Місто","place_address_hidden":true,"place_address_unclear":false,"place_city_type_hidden":false,"place":"Житомирська область","place_district":"","place_unclear":false,"place_hidden":false,"place_city_hidden":false,"place_city":"Житомир","place_district_unclear":false}],"patronymic":"Владиславівна","last_name_unclear":false},"source":"VULYK","estate":{"23":[{"space_unclear":false,"costs":"","costs_comment":"","address_hidden":false,"region_hidden":false,"space_comment":"","space_hidden":false,"space":"","address":"","costs_comment_unclear":false,"costs_rent_comment_unclear":false,"region":"","address_unclear":false,"costs_rent_comment":"","costs_unclear":false,"space_units":"м²","costs_rent":""},{"costs":"","costs_comment":"","address_hidden":false,"region_hidden":false,"space_comment":"","space":"","address":"","region":"","address_unclear":false,"costs_rent_comment":"","space_units":"","costs_rent":""},{"costs":"","costs_comment":"","address_hidden":false,"region_hidden":false,"space_comment":"","space":"","address":"","region":"","address_unclear":false,"costs_rent_comment":"","space_units":"","costs_rent":""},{"costs_rent":"","region":"","costs":"","costs_rent_comment":"","costs_comment":"","space_comment":"","space_units":"","space":"","address":""},{"costs_rent":"","costs":"","costs_rent_comment":"","costs_comment":"","space_comment":"","space_units":"","space":"","address":""}],"25":[{"region_unclear":false,"space_hidden":false,"costs":"","costs_comment":"","address_hidden":true,"region_hidden":false,"space_comment":"","space":"92","address":"м. Хмельницький","region":"Хмельницька область","costs_rent_comment":"","space_comment_unclear":false,"space_units":"м²","costs_rent":""},{"costs_rent":"","region":"","costs":"","costs_rent_comment":"","costs_comment":"","address_hidden":false,"region_hidden":false,"space_comment":"","space_units":"м²","space":"21.9","address":"Болгарія, м. Варна, КК Золоті піски"}],"29":[{"space_unclear":false,"address_hidden":true,"region_hidden":false,"space_comment":"","space_hidden":false,"space":"2100","address":"смт Гуйва, Житомирського р-ну","region":"Житомирська область","costs_property":"","costs_rent_comment":"","address_unclear":false,"space_units":"м²","costs_property_comment":"","costs_rent":""},{"costs_rent":"","region":"Хмельницька область","costs_property":"","costs_rent_comment":"","address_hidden":true,"region_hidden":false,"space_comment":"","costs_property_comment":"","space_units":"м²","space":"1564","address":"м. Полонне"}],"30":[{"space_hidden":false,"address_hidden":true,"region_hidden":false,"space_comment":"","space":"384.1","address":"смт Гуйва, Житомирського р-ну","region":"Житомирська область","costs_property":"","costs_rent_comment":"","address_unclear":false,"space_units":"м²","costs_property_comment":"","costs_rent":""},{"costs_rent":"","region":"Хмельницька область","costs_property":"","costs_rent_comment":"","space_comment":"","costs_property_comment":"","space_units":"м²","space":"74.26","address":"м. Полонне"}],"31":[{"space_hidden":false,"costs_property_hidden":false,"address_hidden":true,"region_hidden":false,"space_comment":"","space_unclear":false,"space":"141.28","address":"м. Житомир","region":"Житомирська область","costs_property":"","costs_rent_comment":"","costs_rent_hidden":false,"space_comment_unclear":false,"space_units":"м²","costs_property_comment":"","costs_rent":""},{"space_unclear":false,"address_hidden":false,"region_hidden":false,"space_comment":"","space":"21.9","address":"Болгарія, м. Варна, КК Золоті піски, 1/2 частина","region":"","costs_property":"","costs_rent_comment":"","space_comment_unclear":false,"space_units":"м²","costs_property_comment":"","costs_rent":""}],"33":[{"space_unclear":false,"address_hidden":true,"region_hidden":false,"space_comment":"","space":"164","address":"смт Гуйва, Житомирського р-ну","region":"Житомирська область","costs_property":"","costs_rent_comment":"","address_unclear":false,"space_units":"м²","costs_property_comment":"","costs_rent":""}]},"intro":{"declaration_year":"2014","isnotdeclaration":"","declaration_year_hidden":false}}