{"income":{"5":{"value":"244370.95","value_unclear":false,"value_hidden":false,"family_comment":"","family":"","comment":""},"6":{"value":"230490.95","family_comment":"","value_unclear":false,"family_unclear":false,"family":"","comment":""},"7":{"source_name_unclear":false,"value":"","family_hidden":false,"family_comment":"","source_name":"","family":"","comment":""},"8":{"family_comment":"","value":"","family":"","comment":""},"9":{"family_comment":"","value":"","family":"","comment":""},"10":{"family_comment":"","value":"12180","family":"","comment":""},"11":{"family_comment":"","value":"","family":"","comment":""},"12":{"family_comment":"","value":"","family":"","comment":""},"13":{"family_comment":"","value":"","family":"","comment":""},"14":{"family_comment":"","value":"","family":"","comment":""},"15":{"family_comment":"","value":"1700","family":"","comment":""},"16":{"family_comment":"","value":"","comment_unclear":false,"family":"","comment":""},"17":{"family_comment":"","family_unclear":false,"value":"","family":"","comment":""},"18":{"family_comment":"","value":"","family":"","comment":""},"19":{"value":"","family_hidden":false,"value_hidden":false,"family_comment":"","family":"","comment":""},"20":{"family_comment":"","value":"","comment_unclear":false,"family":"","comment":""}},"vehicle":{"35":[{"brand_info":"1.6","sum_rent_comment":"","year":"2013","sum_rent_unclear":false,"brand_info_hidden":false,"brand_info_unclear":false,"year_unclear":false,"sum_rent":"","sum":"100000","brand":"Skoda Rapid","sum_comment":"кредит","sum_comment_unclear":false,"brand_hidden":false,"sum_unclear":false,"brand_unclear":false}]},"id":"vulyk_67_151","declaration":{"additional_info_text":"","notfull_lostpages":"","date":"2015-03-31T00:00:00","notfull":"","additional_info":"","url":"http://static.declarations.com.ua/declarations/chosen_ones/mega_batch/boholiubova_larysa_mykhailivna.pdf"},"liabilities":{"54":{"sum_foreign_comment":"","sum_foreign_hidden":false,"sum_comment":"","sum_comment_unclear":false,"sum_hidden":false,"sum":"","sum_unclear":false,"sum_foreign":""},"55":{"sum_foreign_comment":"","sum":"","sum_comment":"","sum_foreign":""},"56":{"sum_foreign_comment":"","sum_foreign_hidden":false,"sum_comment":"","sum_hidden":false,"sum":"","sum_unclear":false,"sum_foreign":""},"57":{"sum_foreign_comment":"","sum_foreign_hidden":false,"sum_comment":"","sum_comment_unclear":false,"sum_hidden":false,"sum_comment_hidden":false,"sum_unclear":false,"sum":"","sum_foreign":""},"58":{"sum_foreign_comment":"","sum_foreign_hidden":false,"sum_comment":"","sum_comment_unclear":false,"sum_hidden":false,"sum_comment_hidden":false,"sum_unclear":false,"sum":"","sum_foreign":""},"59":{"sum_foreign_comment":"","sum":"","sum_hidden":false,"sum_comment":"","sum_foreign":""},"60":{"sum_foreign_comment":"","sum":"","sum_comment":"","sum_foreign":""},"61":{"sum_foreign_comment":"","sum_foreign_hidden":false,"sum_comment":"","sum_hidden":false,"sum":"","sum_foreign":""},"62":{"sum_foreign_comment":"","sum":"","sum_hidden":false,"sum_comment":"","sum_foreign":""},"63":{"sum_foreign_comment":"","sum":"","sum_comment":"","sum_comment_unclear":false,"sum_hidden":false,"sum_unclear":false,"sum_foreign":""},"64":{"sum_foreign_comment":"","sum":"","sum_comment":"","sum_hidden":false,"sum_unclear":false,"sum_foreign":""}},"ft_src":"суддя красилівського районного суду хмельницької області\nХмельницька область\nЗагальний місцевий суд\nЛариса\nМихайлівна\nБоголюбова\nБоголюбова Лариса Михайлівна\nБоголюбова Лариса Михайлівна\nЛариса Михайлівна Боголюбова\nЛариса Боголюбова\nБоголюбова Лариса Михайлівна\nкредит\n1.6\nSkoda Rapid\n2013\n100000\nм. Хмельницький\n4000\nХмельницька область\nм. Хмельницький\n600\nХмельницька область\n2010р\n32326\n31.5\nХмельницька область\n1/3 частина\nм. Хмельницький\n14.1\nХмельницька область\n2014\n230490.95\n1700\n12180\n244370.95\n1.6\nкредит\nSkoda Rapid\n2013\n100000\n4000\nХмельницька область\nм. Хмельницький\n600\nм. Хмельницький\nХмельницька область\n32326\n31.5\n2010р\nХмельницька область\n14.1\n1/3 частина\nХмельницька область\nм. Хмельницький\nЗагальний місцевий суд\nсуддя красилівського районного суду хмельницької області\nХмельницька область\nБоголюбова Лариса Михайлівна\nЛариса Михайлівна Боголюбова\nЛариса Боголюбова\nБоголюбова Лариса Михайлівна\nЛариса\nБоголюбова Лариса Михайлівна\nБоголюбова\nМихайлівна\n230490.95\n1700\n244370.95\n12180\n2014\nБоголюбова Лариса Михайлівна\nЛариса Михайлівна Боголюбова\nЛариса Боголюбова\nБоголюбова Лариса Михайлівна\nМихайлівна\nБоголюбова\nХмельницька область\nсуддя красилівського районного суду хмельницької області\nЗагальний місцевий суд\nБоголюбова Лариса Михайлівна\nЛариса\n2013\nSkoda Rapid\n100000\nкредит\n1.6\n1700\n12180\n244370.95\n230490.95\n1/3 частина\nм. Хмельницький\nХмельницька область\n14.1\nм. Хмельницький\nХмельницька область\n4000\nм. Хмельницький\nХмельницька область\n600\n32326\nХмельницька область\n31.5\n2010р\n2014","general":{"inn":"","name":"Лариса","patronymic_unclear":false,"last_name_hidden":false,"inn_unclear":false,"patronymic":"Михайлівна","inn_hidden":true,"family_raw":"","last_name":"Боголюбова","post":{"post_unclear":false,"post":"суддя красилівського районного суду хмельницької області","post_hidden":false,"region":"Хмельницька область","region_hidden":false,"office":"Загальний місцевий суд","office_hidden":false,"office_unclear":false},"last_name_unclear":false,"full_name":"Боголюбова Лариса Михайлівна","addresses":[{"place_city_type_hidden":true,"place_district_hidden":true,"place_city_type":"","place_city_hidden":true,"place_address_unclear":false,"place_address":"","place":"","place_district":"","place_unclear":false,"place_city":"","place_city_unclear":false,"place_hidden":true,"place_address_hidden":true,"place_district_unclear":false}],"full_name_suggest":{"output":"Боголюбова Лариса Михайлівна","input":["Боголюбова Лариса Михайлівна","Лариса Михайлівна Боголюбова","Лариса Боголюбова"]},"name_unclear":false},"source":"VULYK","estate":{"23":[{"space_hidden":false,"costs":"","costs_comment":"","costs_hidden":false,"address_hidden":true,"region_hidden":false,"space_comment":"","space_unclear":false,"space":"4000","address":"м. Хмельницький","region":"Хмельницька область","address_unclear":false,"space_units_unclear":false,"costs_rent_hidden":false,"space_comment_unclear":false,"space_units":"м²","costs_rent":"","costs_rent_comment":""},{"space_unclear":false,"costs":"","costs_comment":"","address_hidden":false,"region_hidden":false,"space_comment":"","space":"600","address":"м. Хмельницький","region":"Хмельницька область","costs_rent_comment":"","space_comment_unclear":false,"space_units":"м²","space_units_unclear":false,"costs_rent":""}],"24":[{"space_hidden":false,"costs":"32326","costs_comment":"2010р","costs_hidden":false,"address_hidden":true,"region_hidden":false,"space_comment":"","space":"31.5","address":"","region":"Хмельницька область","costs_rent_comment":"","space_comment_unclear":false,"space_units":"м²","costs_rent":""}],"25":[{"space_unclear":false,"costs":"","costs_comment":"","costs_hidden":false,"address_hidden":false,"region_hidden":false,"space_comment":"1/3 частина","space":"14.1","address":"м. Хмельницький","region":"Хмельницька область","address_unclear":false,"space_units_unclear":false,"space_comment_unclear":false,"space_units":"м²","costs_rent":"","costs_rent_comment":""}]},"intro":{"declaration_year":"2014","isnotdeclaration":"","declaration_year_hidden":false}}