{"income":{"5":{"family_comment":"","value":"203443.18","family":"","comment":""},"6":{"value":"203443.18","family_comment":"","value_unclear":false,"comment_hidden":true,"family_unclear":false,"family":"","comment":""},"7":{"family_comment":"","value":"","source_name":"","family":"","comment":""},"8":{"family_comment":"","value":"","family":"","comment":""},"9":{"family_comment":"","family_unclear":false,"value":"","family":"","comment":""},"10":{"family_comment":"","value":"","value_unclear":false,"family":"","comment":""},"11":{"family_comment":"","value":"","family":"","comment":""},"12":{"family_comment":"","value":"","family":"","comment":""},"13":{"family_comment":"","value":"","family":"","comment":""},"14":{"family_comment":"","value":"","family":"","comment":""},"15":{"family_comment":"","value":"","family":"","comment":""},"16":{"family_comment":"","value":"","family":"","comment":""},"17":{"family_comment":"","value":"","family":"","comment":""},"18":{"family_comment":"","value":"","family":"","comment":""},"19":{"family_comment":"","value":"","family":"","comment":""},"20":{"value":"","family":"","value_unclear":false,"family_hidden":false,"family_comment":"","comment_unclear":false,"comment":"","family_comment_unclear":false}},"id":"vulyk_97_90","declaration":{"additional_info_text":"","notfull_lostpages":"","date":"2015-03-24T00:00:00","notfull":"","additional_info":"","url":"http://static.declarations.com.ua/declarations/chosen_ones/judges_batch/3991_slidenko_andrii_viktorovych.pdf"},"liabilities":{"54":{"sum_foreign_comment":"","sum":"","sum_comment":"","sum_comment_unclear":false,"sum_hidden":false,"sum_comment_hidden":false,"sum_unclear":false,"sum_foreign":""},"55":{"sum_foreign_comment":"","sum":"","sum_comment":"","sum_foreign":""},"56":{"sum_foreign_comment":"","sum":"","sum_comment":"","sum_foreign":""},"57":{"sum_foreign_comment":"","sum":"","sum_comment":"","sum_comment_unclear":false,"sum_hidden":false,"sum_comment_hidden":false,"sum_unclear":false,"sum_foreign":""},"58":{"sum_foreign_comment":"","sum":"","sum_comment":"","sum_comment_unclear":false,"sum_hidden":false,"sum_comment_hidden":false,"sum_unclear":false,"sum_foreign":""},"59":{"sum_foreign_comment":"","sum":"","sum_comment":"","sum_foreign":""},"60":{"sum_foreign_comment":"","sum":"","sum_comment":"","sum_comment_unclear":false,"sum_hidden":false,"sum_comment_hidden":false,"sum_foreign":""},"61":{"sum_foreign_comment":"","sum":"","sum_comment":"","sum_foreign":""},"62":{"sum_foreign_comment":"","sum":"","sum_comment":"","sum_unclear":false,"sum_foreign":""},"63":{"sum_foreign_comment":"","sum":"","sum_hidden":false,"sum_comment":"","sum_foreign":""},"64":{"sum_foreign_comment":"","sum":"","sum_comment":"","sum_foreign":""}},"ft_src":"Харків\n61000\nХарківська область\nсуддя харківського окружного адміністративного суду\nХарківська область\nАдміністративний місцевий суд\nАндрій\nСліденко Д. А\nДитина\nВікторович\nСліденко Андрій Вікторович\nАндрій Вікторович Сліденко\nАндрій Сліденко\nСліденко Андрій Вікторович\nСліденко Андрій Вікторович\nСліденко\n203443.18\n203443.18\nспільна сумісна власність\n87.5\nХарківська область\nм. Харків\nспільна сумісна власність\nНововодолазький район, с. Стара Водолага\n70.1\nХарківська область\nспільна сумісна власність\n87.5\nм. Харків\nХарківська область\n2014\n203443.18\n203443.18\n70.1\nспільна сумісна власність\nХарківська область\nНововодолазький район, с. Стара Водолага\n87.5\nспільна сумісна власність\nХарківська область\nм. Харків\n87.5\nспільна сумісна власність\nм. Харків\nХарківська область\nСліденко Андрій Вікторович\nАндрій Вікторович Сліденко\nАндрій Сліденко\nСліденко Андрій Вікторович\nАндрій\nДитина\nСліденко Д. А\nСліденко Андрій Вікторович\nСліденко\nАдміністративний місцевий суд\nХарківська область\nсуддя харківського окружного адміністративного суду\nВікторович\nХарківська область\n61000\nХарків\n203443.18\n203443.18\n2014\nДитина\nСліденко Д. А\nВікторович\nСліденко\nАндрій\nСліденко Андрій Вікторович\nАндрій Вікторович Сліденко\nАндрій Сліденко\nСліденко Андрій Вікторович\n61000\nХарків\nХарківська область\nХарківська область\nАдміністративний місцевий суд\nсуддя харківського окружного адміністративного суду\nСліденко Андрій Вікторович\nспільна сумісна власність\nм. Харків\nХарківська область\n87.5\nспільна сумісна власність\nм. Харків\nХарківська область\n87.5\nспільна сумісна власність\nНововодолазький район, с. Стара Водолага\nХарківська область\n70.1\n2014","general":{"name_hidden":false,"name":"Андрій","last_name_hidden":false,"inn":"","family":[{"inn":"","relations":"Дитина","relations_other":"","inn_hidden":true,"family_name":"Сліденко Д. А","name_hidden":true,"name_unclear":false}],"patronymic":"Вікторович","inn_hidden":true,"family_raw":"","inn_unclear":false,"post":{"region_unclear":false,"region":"Харківська область","post":"суддя харківського окружного адміністративного суду","office":"Адміністративний місцевий суд","office_unclear":false,"post_hidden":false},"full_name":"Сліденко Андрій Вікторович","addresses":[{"place_district":"","place_city_hidden":false,"place_city":"Харків","place_city_unclear":false,"place_district_hidden":false,"place_city_type":"Місто","place_address_hidden":true,"place_city_type_hidden":false,"place_address":"61000","place_hidden":false,"place":"Харківська область"}],"last_name":"Сліденко","patronymic_hidden":false,"full_name_suggest":{"output":"Сліденко Андрій Вікторович","input":["Сліденко Андрій Вікторович","Андрій Вікторович Сліденко","Андрій Сліденко"]}},"source":"VULYK","estate":{"24":[{"region_unclear":false,"space_unclear":false,"costs":"","costs_comment":"","address_hidden":true,"region_hidden":false,"space_comment":"спільна сумісна власність","space_hidden":false,"space":"70.1","address":"Нововодолазький район, с. Стара Водолага","region":"Харківська область","address_unclear":true,"costs_rent_comment":"","space_comment_unclear":false,"space_units":"м²","costs_rent":""}],"25":[{"region_unclear":false,"space_unclear":false,"costs":"","costs_comment":"","address_hidden":true,"region_hidden":false,"space_comment":"спільна сумісна власність","space_hidden":false,"space":"87.5","address":"м. Харків","region":"Харківська область","costs_rent_comment":"","space_comment_unclear":false,"space_comment_hidden":false,"space_units":"м²","costs_rent":""}],"31":[{"space_unclear":false,"address_hidden":true,"region_hidden":false,"space_comment":"спільна сумісна власність","space_hidden":false,"space":"87.5","address":"м. Харків","region":"Харківська область","costs_property":"","costs_rent_comment":"","space_comment_hidden":false,"space_units":"м²","costs_property_comment":"","costs_rent":""}]},"intro":{"declaration_year":"2014","isnotdeclaration":""}}