{"income":{"5":{"value":"227404","family_comment":"","value_unclear":false,"family_unclear":false,"family":"124215","comment":""},"6":{"family_comment":"","value":"205787","value_unclear":false,"family":"44328","comment":""},"7":{"value":"","value_unclear":false,"family_comment":"","source_name":"","family":"","comment":""},"8":{"family_comment":"","value":"","family":"","comment":""},"9":{"value":"","family_comment":"","value_unclear":false,"family_unclear":false,"family":"5","comment":""},"10":{"family_comment":"","value":"","comment_unclear":false,"family":"","comment":""},"11":{"family_comment":"","value":"","family":"","comment":""},"12":{"family_comment":"","value":"","family":"","comment":""},"13":{"family_comment":"","value":"","value_unclear":false,"family":"","comment":""},"14":{"family_comment":"","value":"","family":"","comment":""},"15":{"family_comment":"","value":"","family":"","comment":""},"16":{"family_comment":"","family_unclear":false,"value":"","family":"","comment":""},"17":{"family_comment":"","family_unclear":false,"value":"","family":"74564","comment":""},"18":{"family_comment":"","value":"","family":"","comment":""},"19":{"family_comment":"","value":"","family":"","comment":""},"20":{"value":"21617","family_comment":"","comment_unclear":false,"family_hidden":false,"value_hidden":false,"family_unclear":false,"value_unclear":false,"comment":"","family":"5318"}},"vehicle":{"35":[{"brand_info":"1389, 90, 66.2 , 425,2","sum_rent_comment":"","sum_rent_comment_unclear":false,"year":"2006","brand_info_hidden":false,"brand_info_unclear":false,"sum_rent":"","sum":"","brand":"Opel Astra","sum_comment":"","brand_unclear":false,"brand_hidden":false}],"39":[{"brand_info":"причіп легковий-В","sum_rent_comment":"","brand":"ПА 004","sum_comment":"","brand_unclear":false,"year":"2013","brand_hidden":false,"sum":"","sum_rent":""}]},"id":"vulyk_100_24","banks":{"45":[{"sum_foreign_comment":"","sum_units":"UAH","sum_comment":"","sum_comment_unclear":false,"sum_foreign_units":"UAH","sum_units_unclear":false,"sum_comment_hidden":false,"sum_unclear":false,"sum":"4","sum_foreign":""}]},"declaration":{"additional_info_text":"","notfull_lostpages":"","date":"2015-03-31T00:00:00","notfull":"","additional_info":"","url":"http://static.declarations.com.ua/declarations/chosen_ones/judges_batch/4151_pcholkin_serhii_anatoliiovych.pdf"},"liabilities":{"54":{"sum_foreign_comment":"","sum":"","sum_comment":"","sum_comment_hidden":false,"sum_unclear":false,"sum_foreign":""},"55":{"sum_foreign_comment":"","sum":"","sum_comment":"","sum_foreign":""},"56":{"sum_foreign_comment":"","sum":"","sum_comment":"","sum_unclear":false,"sum_foreign":""},"57":{"sum_foreign_comment":"","sum":"8973","sum_comment":"","sum_comment_unclear":false,"sum_comment_hidden":false,"sum_unclear":false,"sum_foreign":""},"58":{"sum_foreign_comment":"","sum":"4326","sum_comment":"","sum_comment_hidden":false,"sum_unclear":false,"sum_foreign":""},"59":{"sum_foreign_comment":"","sum":"","sum_comment":"","sum_foreign":""},"60":{"sum_foreign_comment":"","sum_comment":"","sum":"","sum_comment_hidden":false,"sum_foreign":""},"61":{"sum_foreign_comment":"","sum":"","sum_comment":"","sum_foreign":""},"62":{"sum_foreign_comment":"","sum":"","sum_comment":"","sum_unclear":false,"sum_foreign":""},"63":{"sum_foreign_comment":"","sum_comment":"","sum":"5318","sum_comment_hidden":false,"sum_foreign":""},"64":{"sum_foreign_comment":"","sum_comment":"","sum":"","sum_comment_hidden":false,"sum_foreign":""}},"ft_src":"ПА 004\nпричіп легковий-В\n2013\n1389, 90, 66.2 , 425,2\nOpel Astra\n2006\n4\n2014\n1389, 90, 66.2 , 425,2\nOpel Astra\n2006\nпричіп легковий-В\n2013\nПА 004\n4\n28.3\nЛуганська область\nм. Сватове, вул. Ново-Старобільська, 359\n25.06\nЛуганська область\nм. Сватове, пров. Промисловий, 13 кв. 11\nЛуганська область\nм. Сватове, пров. Промисловий, 4Г\n41.1\n.681\nЛуганська область\nм. Сватове, пр. Забурдаєва, 36\nЛуганська область\n.0028\nм. Сватове, вул. Ново-Старобільська, 359\nм. Сватове, пров. Промисловий, 4Г\n.0035\nЛуганська область\n50.14\nЛуганська область\nм. Сватове, пров. Промисловий, 13/11\nм. Сватове, пл. Привокзальна, 11/12\n10.1\nЛуганська область\nПодружжя\nПчолкіна В. А. 28. 06. 1968\nДитина\nПчолкін М. С. 09. 03. 1987\nАнатолійович\nПчолкін\nПчолкін Сергій Анатолійович\nСергій Анатолійович Пчолкін\nСергій Пчолкін\nПчолкін Сергій Анатолійович\nПчолкін Сергій Анатолійович\nСергій\nЗагальний місцевий суд\nЛуганська область\nсуддя сватівського районного суду луганської області\n5318\n8973\n4326\n205787\n44328\n74564\n21617\n5318\n227404\n124215\n5\n2014\n4326\n8973\n5318\nм. Сватове, вул. Ново-Старобільська, 359\n28.3\nЛуганська область\nЛуганська область\nм. Сватове, пров. Промисловий, 4Г\n.0035\nЛуганська область\nм. Сватове, пров. Промисловий, 4Г\n41.1\nм. Сватове, пр. Забурдаєва, 36\n.681\nЛуганська область\nм. Сватове, вул. Ново-Старобільська, 359\n.0028\nЛуганська область\nЛуганська область\nм. Сватове, пров. Промисловий, 13/11\n50.14\nЛуганська область\nм. Сватове, пл. Привокзальна, 11/12\n10.1\nм. Сватове, пров. Промисловий, 13 кв. 11\n25.06\nЛуганська область\nПчолкіна В. А. 28. 06. 1968\nПодружжя\nДитина\nПчолкін М. С. 09. 03. 1987\nАнатолійович\nПчолкін\nЛуганська область\nЗагальний місцевий суд\nсуддя сватівського районного суду луганської області\nПчолкін Сергій Анатолійович\nПчолкін Сергій Анатолійович\nСергій Анатолійович Пчолкін\nСергій Пчолкін\nПчолкін Сергій Анатолійович\nСергій\n44328\n205787\n124215\n227404\n74564\n5\n5318\n21617","general":{"inn":"","inn_hidden":true,"last_name":"Пчолкін","post":{"post_unclear":false,"region_unclear":false,"post":"суддя сватівського районного суду луганської області","post_hidden":false,"region":"Луганська область","office":"Загальний місцевий суд","office_unclear":false},"name":"Сергій","full_name":"Пчолкін Сергій Анатолійович","family_raw":"","addresses":[{"place_district":"","place_address_hidden":true,"place_city":"","place_city_unclear":false,"place_district_hidden":false,"place_city_type":"","place_city_hidden":true,"place_city_type_hidden":false,"place_address":"","place_hidden":true,"place":""}],"family":[{"inn":"","relations":"Подружжя","name_hidden":false,"inn_hidden":true,"family_name":"Пчолкіна В. А. 28. 06. 1968","name_unclear":false},{"inn":"","relations":"Дитина","relations_other":"","inn_hidden":false,"family_name":"Пчолкін М. С. 09. 03. 1987","name_hidden":false,"name_unclear":false}],"full_name_suggest":{"output":"Пчолкін Сергій Анатолійович","input":["Пчолкін Сергій Анатолійович","Сергій Анатолійович Пчолкін","Сергій Пчолкін"]},"patronymic":"Анатолійович"},"source":"VULYK","estate":{"23":[{"space_unclear":false,"costs":"","costs_comment":"","address_hidden":false,"region_hidden":false,"space_comment":"","space":".681","address":"м. Сватове, пр. Забурдаєва, 36","costs_comment_unclear":false,"region":"Луганська область","address_unclear":false,"costs_rent_comment":"","space_comment_unclear":false,"space_units":"га","costs_rent":""},{"costs_rent":"","space_unclear":false,"region":"Луганська область","costs":"","costs_rent_comment":"","costs_comment":"","space_comment":"","space_units":"га","space":".0028","address":"м. Сватове, вул. Ново-Старобільська, 359"}],"25":[{"space_unclear":false,"costs":"","costs_comment":"","address_hidden":false,"region_hidden":false,"space_comment":"","space":"25.06","address":"м. Сватове, пров. Промисловий, 13 кв. 11","costs_comment_unclear":false,"region":"Луганська область","address_unclear":false,"costs_rent_comment":"","space_comment_unclear":false,"space_units":"м²","costs_rent":""}],"27":[{"space_unclear":false,"costs":"","costs_comment":"","address_hidden":false,"region_hidden":false,"space_comment":"","space":"28.3","address":"м. Сватове, вул. Ново-Старобільська, 359","region":"Луганська область","address_unclear":false,"costs_rent_comment":"","space_units":"м²","costs_rent":""}],"29":[{"region_unclear":false,"space_unclear":false,"address_hidden":false,"region_hidden":false,"space_comment":"","space":".0035","address":"м. Сватове, пров. Промисловий, 4Г","region":"Луганська область","costs_property":"","costs_rent_comment":"","address_unclear":false,"space_units":"га","costs_property_comment":"","costs_rent":""}],"31":[{"region_unclear":false,"space_unclear":false,"costs_property_comment_unclear":false,"address_hidden":false,"region_hidden":false,"space_comment":"","space":"50.14","address":"м. Сватове, пров. Промисловий, 13/11","region":"Луганська область","costs_property":"","costs_rent_comment":"","space_comment_unclear":false,"address_unclear":false,"space_units":"м²","costs_property_comment":"","costs_rent":""},{"costs_rent":"","region_unclear":false,"region":"Луганська область","costs_property":"","costs_rent_comment":"","region_hidden":false,"space_comment":"","costs_property_comment":"","space_units":"м²","space":"10.1","address":"м. Сватове, пл. Привокзальна, 11/12"}],"33":[{"space_unclear":false,"address_hidden":false,"region_hidden":false,"space_comment":"","space":"41.1","address":"м. Сватове, пров. Промисловий, 4Г","region":"Луганська область","costs_property":"","costs_rent_comment":"","address_unclear":false,"space_units":"м²","costs_property_comment":"","costs_rent":""}]},"intro":{"declaration_year":"2014"}}