{"income":{"5":{"value":"198429","family_unclear":false,"family_hidden":false,"family_comment":"","family":"911874","comment":""},"6":{"family_comment":"","value":"198407","family_hidden":false,"comment":"","family":""},"7":{"family_comment":"","value":"","source_name":"","family":"","comment":""},"8":{"family_comment":"","value":"","family":"","comment":""},"9":{"value":"","comment_unclear":false,"family_hidden":false,"family_comment":"","family":"","comment":""},"10":{"family_comment":"","value":"","family":"","comment":""},"11":{"family_comment":"","value":"22","family":"","comment":""},"12":{"family_comment":"","value":"","family":"","comment":""},"13":{"family_comment":"","value":"","family":"","comment":""},"14":{"family_comment":"","value":"","family":"","comment":""},"15":{"family_comment":"","value":"","value_unclear":false,"family":"","comment":""},"16":{"family_comment":"","value":"","family":"","comment":""},"17":{"family_comment":"","value":"","family":"911874","comment":""},"18":{"family_comment":"","value":"","family":"","comment":""},"19":{"family_comment":"","value":"","family":"","comment":""},"20":{"value":"","comment_unclear":false,"comment_hidden":false,"family_hidden":false,"value_hidden":false,"family_comment":"","value_unclear":false,"family":"","comment":"","family_comment_hidden":false}},"vehicle":{"35":[{"brand_info":"об'єм двигуна 2261","sum_rent_comment":"право користування","brand":"Mazda CX-7","sum_comment":"","year":"2009","brand_info_hidden":false,"sum":"","sum_rent":""}],"40":[{"brand_info":"об'єм двигуна 1781","sum_rent_comment":"","brand":"Skoda Octavia Tour","sum_comment":"","year":"2008","brand_info_hidden":false,"sum":"","sum_rent":""},{"brand_info":"об'єм двигуна 1781","sum_rent_comment":"","brand":"Skoda Octavia Tour","sum_comment":"","year":"2008","sum":"","sum_rent":""}]},"id":"vulyk_41_69","banks":{"45":[{"sum_foreign_comment":"","sum_units":"UAH","sum_comment":"","sum_foreign_unclear":false,"sum_foreign_units":"UAH","sum_hidden":false,"sum_comment_hidden":false,"sum":"","sum_foreign":""},{"sum_foreign_comment":"","sum_units":"","sum_comment":"","sum_foreign_unclear":false,"sum_foreign_units":"","sum":"","sum_foreign":""}],"46":[{"sum_foreign_comment":"","sum_units":"UAH","sum_comment":"","sum_foreign_units":"UAH","sum_comment_hidden":false,"sum_unclear":false,"sum":"","sum_foreign":""},{"sum_foreign_comment":"","sum_units":"","sum_comment":"","sum_foreign_units":"","sum":"","sum_unclear":false,"sum_foreign":""}],"47":[{"sum_foreign_comment":"","sum_units":"UAH","sum_comment":"","sum_foreign_units":"UAH","sum":"","sum_foreign":""},{"sum_foreign_comment":"","sum_units":"","sum_comment":"","sum_foreign_units":"","sum":"","sum_foreign":""}],"48":[{"sum_foreign_comment":"","sum_units":"UAH","sum_comment":"","sum_foreign_units":"UAH","sum":"","sum_foreign":""}],"49":[{"sum_foreign_comment":"","sum_units":"UAH","sum_comment":"","sum_foreign_units":"UAH","sum":"","sum_foreign":""}],"50":[{"sum_foreign_comment":"","sum_units":"UAH","sum_comment":"","sum_foreign_units":"UAH","sum":"","sum_foreign":""}],"51":[{"sum_foreign_comment":"","sum_units":"UAH","sum_comment":"","sum_hidden":false,"sum_foreign_units":"UAH","sum_comment_hidden":false,"sum_unclear":false,"sum":"","sum_foreign":""},{"sum_foreign_comment":"","sum_units":"","sum_comment":"","sum_foreign_units":"","sum":"","sum_foreign":""}],"52":[{"sum_foreign_comment":"","sum_units":"UAH","sum_comment":"","sum_foreign_units":"UAH","sum_comment_hidden":false,"sum_unclear":false,"sum":"","sum_foreign":""}],"53":[{"sum_foreign_comment":"","sum_units":"UAH","sum_comment":"","sum_foreign_units":"UAH","sum_comment_hidden":false,"sum":"","sum_foreign":""},{"sum_foreign_comment":"","sum_units":"","sum_comment":"","sum_foreign_units":"","sum":"","sum_foreign":""},{"sum_foreign_comment":"","sum_units":"","sum_comment":"","sum_foreign_units":"","sum":"","sum_foreign":""}]},"declaration":{"date":"2015-03-30T00:00:00","additional_info_text":"","additional_info":"","url":"http://static.declarations.com.ua/declarations/chosen_ones/mega_batch/kudelko_nadiia_ievhenivna.pdf"},"liabilities":{"54":{"sum_foreign_comment":"","sum_comment_hidden":false,"sum":"","sum_comment":"","sum_foreign":""},"55":{"sum_foreign_comment":"","sum":"","sum_comment":"","sum_foreign":""},"56":{"sum_foreign_comment":"","sum":"","sum_hidden":false,"sum_comment":"","sum_foreign":""},"57":{"sum_foreign_comment":"","sum":"","sum_comment":"","sum_comment_hidden":false,"sum_unclear":false,"sum_foreign":""},"58":{"sum_foreign_comment":"","sum_comment_hidden":false,"sum":"","sum_comment":"","sum_foreign":""},"59":{"sum_foreign_comment":"","sum":"","sum_comment":"","sum_foreign":""},"60":{"sum_foreign_comment":"","sum_comment_hidden":false,"sum":"","sum_comment":"","sum_foreign":""},"61":{"sum_foreign_comment":"","sum":"","sum_comment":"","sum_foreign":""},"62":{"sum_foreign_comment":"","sum":"","sum_comment":"","sum_foreign":""},"63":{"sum_foreign_comment":"","sum":"","sum_comment":"","sum_comment_hidden":false,"sum_unclear":false,"sum_foreign":""},"64":{"sum_foreign_comment":"","sum_comment_hidden":false,"sum":"","sum_comment":"","sum_foreign":""}},"ft_src":"суддя дніпропетровського окружного адміністративного суду\nДніпропетровська область\nАдміністративний місцевий суд\nНадія\nСліпець\nПодружжя\nКуделько\nДитина\nЄвгенівна\nКуделько Надія Євгенівна\nНадія Євгенівна Куделько\nНадія Куделько\nКуделько Надія Євгенівна\nКуделько\nКуделько Надія Євгенівна\nДніпропетровськ\n49000\nДніпропетровська область\nоб'єм двигуна 2261\n2009\nMazda CX-7\nправо користування\nоб'єм двигуна 1781\n2008\nSkoda Octavia Tour\nоб'єм двигуна 1781\n2008\nSkoda Octavia Tour\n2014\nMazda CX-7\nоб'єм двигуна 2261\nправо користування\n2009\nSkoda Octavia Tour\nоб'єм двигуна 1781\n2008\nоб'єм двигуна 1781\nSkoda Octavia Tour\n2008\n30.3\nм. Дніпропетровськ\nДніпропетровська область\nПодружжя\nСліпець\nДитина\nКуделько\nКуделько Надія Євгенівна\nНадія Євгенівна Куделько\nНадія Куделько\nКуделько Надія Євгенівна\nКуделько Надія Євгенівна\nНадія\nЄвгенівна\nАдміністративний місцевий суд\nсуддя дніпропетровського окружного адміністративного суду\nДніпропетровська область\nКуделько\n49000\nДніпропетровська область\nДніпропетровськ\n198407\n911874\n198429\n911874\n22\n2014\nм. Дніпропетровськ\n30.3\nДніпропетровська область\nСліпець\nПодружжя\nКуделько\nДитина\nЄвгенівна\nКуделько\nНадія\nКуделько Надія Євгенівна\nНадія Євгенівна Куделько\nНадія Куделько\nКуделько Надія Євгенівна\nДніпропетровська область\nДніпропетровськ\n49000\nДніпропетровська область\nсуддя дніпропетровського окружного адміністративного суду\nАдміністративний місцевий суд\nКуделько Надія Євгенівна\n198407\n22\n911874\n198429\n911874\nправо користування\nMazda CX-7\nоб'єм двигуна 2261\n2009\nSkoda Octavia Tour\nоб'єм двигуна 1781\n2008\nSkoda Octavia Tour\nоб'єм двигуна 1781\n2008\n22\n198429\n911874\n911874\n198407\nм. Дніпропетровськ\nДніпропетровська область\n30.3\n2014","general":{"inn":"","name":"Надія","family":[{"inn":"","relations":"Подружжя","relations_hidden":false,"inn_hidden":true,"family_name":"Сліпець","name_hidden":true,"name_unclear":false},{"inn":"","relations":"Дитина","relations_other":"","inn_hidden":false,"family_name":"Куделько","name_hidden":false,"name_unclear":false}],"patronymic":"Євгенівна","inn_hidden":true,"family_raw":"","last_name":"Куделько","post":{"post_unclear":false,"post":"суддя дніпропетровського окружного адміністративного суду","post_hidden":false,"region":"Дніпропетровська область","region_hidden":false,"office":"Адміністративний місцевий суд","office_hidden":false},"last_name_unclear":true,"full_name":"Куделько Надія Євгенівна","addresses":[{"place_district":"","place_city_hidden":false,"place_city":"Дніпропетровськ","place_city_type_hidden":false,"place_district_hidden":false,"place_city_type":"Місто","place_address_hidden":true,"place_address":"49000","place_hidden":false,"place":"Дніпропетровська область"}],"patronymic_hidden":false,"full_name_suggest":{"output":"Куделько Надія Євгенівна","input":["Куделько Надія Євгенівна","Надія Євгенівна Куделько","Надія Куделько"]},"name_unclear":false},"source":"VULYK","estate":{"23":[{"region_unclear":false,"space_unclear":false,"costs":"","costs_comment":"","address_hidden":false,"region_hidden":false,"space_comment":"","space":"","address":"","costs_comment_unclear":false,"region":"","space_units_unclear":false,"space_comment_hidden":false,"space_units":"м²","costs_rent":"","costs_rent_comment":""},{"costs_rent":"","space_unclear":false,"region":"","costs":"","costs_rent_comment":"","costs_comment":"","space_comment":"","space_units":"","space":"","address":""},{"costs_rent":"","region":"","costs":"","costs_rent_comment":"","costs_comment":"","space_comment":"","space_units":"","space":"","address":""}],"25":[{"region_unclear":false,"space_hidden":false,"costs":"","costs_comment":"","address_hidden":true,"region_hidden":false,"space_comment":"","space_unclear":false,"space":"30.3","address":"м. Дніпропетровськ","costs_comment_unclear":false,"region":"Дніпропетровська область","costs_rent_comment":"","costs_unclear":false,"space_units":"м²","costs_rent":""}]},"intro":{"declaration_year":"2014"}}