{"income":{"5":{"value":"309032","value_unclear":false,"family_hidden":false,"value_hidden":false,"family_comment":"","family":"27360","comment":""},"6":{"value":"232601","value_unclear":false,"family_hidden":false,"family_comment":"","family":"16709","comment":""},"7":{"value":"","comment_hidden":false,"family_comment":"","source_name":"","family":"","comment":"","source_name_hidden":false},"8":{"family_comment":"","value":"","family":"","comment":""},"9":{"family_comment":"","value":"2693","family":"2651","comment":""},"10":{"family_comment":"","family_unclear":false,"value":"","family":"","comment":""},"11":{"family_comment":"","value":"","family":"","comment":""},"12":{"family_comment":"","value":"","family":"","comment":""},"13":{"family_comment":"","value":"","family":"","comment":""},"14":{"family_comment":"","value":"","family":"","comment":""},"15":{"family_comment":"","value":"","family":"","comment":""},"16":{"family_comment":"","value":"","family":"","comment":""},"17":{"family_comment":"","value":"","family":"","comment":""},"18":{"family_comment":"","value":"","family":"","comment":""},"19":{"family_comment":"","value":"","family":"","comment":""},"20":{"value":"73738","family_comment":"","family_hidden":false,"family_unclear":false,"family":"8000","comment":"","family_comment_unclear":false}},"vehicle":{"40":[{"brand_info":"1240 куб. см.","sum_rent_comment":"","brand":"Nissan Micra","sum_comment":"","year":"2008","brand_hidden":false,"brand_info_hidden":false,"brand_info_unclear":false,"year_unclear":false,"sum":"","sum_rent":""}]},"id":"vulyk_45_159","banks":{"45":[{"sum_foreign_comment":"","sum_units":"UAH","sum_comment":"","sum_comment_unclear":false,"sum_foreign_units":"UAH","sum_comment_hidden":false,"sum_unclear":false,"sum":"36978","sum_foreign":""},{"sum_foreign_comment":"","sum_units":"","sum_comment":"","sum_foreign_units":"","sum":"","sum_foreign":""}],"46":[{"sum_foreign_comment":"","sum_units":"UAH","sum_comment":"","sum_comment_unclear":false,"sum_foreign_units":"UAH","sum":"","sum_unclear":false,"sum_foreign":""}],"47":[{"sum_foreign_comment":"","sum_units":"UAH","sum_comment":"","sum_foreign_units":"UAH","sum":"","sum_foreign":""}],"48":[{"sum_foreign_comment":"","sum_units":"UAH","sum_comment":"","sum_foreign_units":"UAH","sum":"","sum_foreign":""}],"49":[{"sum_foreign_comment":"","sum_units":"UAH","sum_comment":"","sum_foreign_units":"UAH","sum":"","sum_foreign":""}],"50":[{"sum_foreign_comment":"","sum_units":"UAH","sum_comment":"","sum_foreign_units":"UAH","sum":"","sum_foreign":""}],"51":[{"sum_foreign_comment":"","sum_units":"UAH","sum_comment":"","sum_foreign_units":"UAH","sum_comment_hidden":false,"sum":"34379","sum_foreign":""},{"sum_foreign_comment":"","sum_units":"","sum_comment":"","sum_foreign_units":"","sum":"","sum_foreign":""}],"52":[{"sum_foreign_comment":"","sum_units":"UAH","sum_comment":"","sum_comment_unclear":false,"sum_foreign_units":"UAH","sum":"","sum_unclear":false,"sum_foreign":""}],"53":[{"sum_foreign_comment":"","sum_units":"UAH","sum_comment":"","sum_foreign_comment_hidden":false,"sum_hidden":false,"sum_foreign_units":"UAH","sum_comment_hidden":false,"sum_foreign_hidden":false,"sum":"","sum_foreign":""}]},"declaration":{"additional_info_text":"","notfull_lostpages":"","date":"2015-03-18T00:00:00","notfull":"","additional_info":"","url":"http://static.declarations.com.ua/declarations/chosen_ones/mega_batch/makarov_vitalii_oleksandrovych.pdf"},"liabilities":{"54":{"sum_foreign_comment":"","sum":"510","sum_comment":"","sum_comment_unclear":false,"sum_comment_hidden":false,"sum_unclear":false,"sum_foreign":""},"55":{"sum_foreign_comment":"","sum":"","sum_comment":"","sum_foreign":""},"56":{"sum_foreign_comment":"","sum":"1691","sum_comment":"","sum_comment_unclear":false,"sum_unclear":false,"sum_foreign":""},"57":{"sum_foreign_comment":"","sum":"","sum_comment":"","sum_comment_unclear":false,"sum_hidden":false,"sum_comment_hidden":false,"sum_foreign":""},"58":{"sum_foreign_comment":"","sum":"","sum_comment":"","sum_comment_unclear":false,"sum_hidden":false,"sum_comment_hidden":false,"sum_foreign":""},"59":{"sum_foreign_comment":"","sum":"95883","sum_comment":"","sum_foreign":""},"60":{"sum_foreign_comment":"","sum":"2227","sum_comment":"","sum_comment_unclear":false,"sum_comment_hidden":false,"sum_foreign":""},"61":{"sum_foreign_comment":"","sum":"","sum_comment":"","sum_foreign":""},"62":{"sum_foreign_comment":"","sum":"15478","sum_comment":"","sum_foreign":""},"63":{"sum_foreign_comment":"","sum":"","sum_comment":"","sum_comment_unclear":false,"sum_comment_hidden":false,"sum_unclear":false,"sum_foreign":""},"64":{"sum_foreign_comment":"","sum":"","sum_comment":"","sum_comment_unclear":false,"sum_comment_hidden":false,"sum_unclear":false,"sum_foreign":""}},"ft_src":"95883\n15478\n510\n1691\n2227\nЗапоріжжя\nЗапорізька область\nсуддя орджонікідзевського районного суду м. запоріжжя\nЗапорізька область\nЗагальний місцевий суд\nВіталій\nМакарова О. І\nПодружжя\nМакарова Т. В\nДитина\nКармазіна М. Є\nІнше\nдонька дружини\nОлександрович\nМакаров Віталій Олександрович\nВіталій Олександрович Макаров\nВіталій Макаров\nМакаров Віталій Олександрович\nМакаров Віталій Олександрович\nМакаров\n1240 куб. см.\nNissan Micra\n2008\n34379\n36978\n2014\n1240 куб. см.\n2008\nNissan Micra\n36978\n34379\n6000\nс. Новоукраїнка\n130000\nКримська Автономна Республіка\nс. Вознесенка\n805\nс. м. т. Щебетовка\n39.1\nЗапорізька область\nм. Мелітополь\n71.93\nЗапорізька область\nм. Запоріжжя\n65.6\nм. Мелітополь\nЗапорізька область\nПодружжя\nМакарова О. І\nДитина\nМакарова Т. В\nІнше\nдонька дружини\nКармазіна М. Є\nМакаров Віталій Олександрович\nВіталій Олександрович Макаров\nВіталій Макаров\nМакаров Віталій Олександрович\nМакаров Віталій Олександрович\nВіталій\nМакаров\nЗагальний місцевий суд\nсуддя орджонікідзевського районного суду м. запоріжжя\nЗапорізька область\nОлександрович\nЗапорізька область\nЗапоріжжя\n95883\n2227\n1691\n15478\n510\n232601\n16709\n73738\n8000\n309032\n27360\n2693\n2651\n2014\n1691\n15478\n510\n95883\n2227\nс. Новоукраїнка\n6000\nс. Вознесенка\nКримська Автономна Республіка\n130000\nс. м. т. Щебетовка\n805\nм. Мелітополь\nЗапорізька область\n39.1\nЗапорізька область\nм. Запоріжжя\n71.93\nм. Мелітополь\n65.6\nЗапорізька область\nМакарова О. І\nПодружжя\nМакарова Т. В\nДитина\nдонька дружини\nКармазіна М. Є\nІнше\nОлександрович\nМакаров\nВіталій\nМакаров Віталій Олександрович\nВіталій Олександрович Макаров\nВіталій Макаров\nМакаров Віталій Олександрович\nЗапорізька область\nЗапоріжжя\nЗапорізька область\nсуддя орджонікідзевського районного суду м. запоріжжя\nЗагальний місцевий суд\nМакаров Віталій Олександрович\n16709\n232601\n27360\n309032\n2651\n2693\n8000\n73738\nNissan Micra\n1240 куб. см.\n2008\n73738\n8000\n309032\n27360\n2651\n2693\n232601\n16709\nм. Мелітополь\nЗапорізька область\n39.1\nм. Запоріжжя\nЗапорізька область\n71.93\nс. Новоукраїнка\n6000\nЗапорізька область\nм. Мелітополь\n65.6\nс. Вознесенка\nКримська Автономна Республіка\n130000\nс. м. т. Щебетовка\n805\n36978\n34379\n2014","general":{"inn":"","name":"Віталій","last_name_hidden":false,"family":[{"inn":"","inn_hidden":false,"relations_unclear":false,"relations_hidden":false,"relations_other":"","relations":"Подружжя","name_hidden":false,"family_name":"Макарова О. І","name_unclear":false},{"inn":"","relations":"Дитина","relations_other":"","inn_hidden":true,"family_name":"Макарова Т. В","name_hidden":false,"name_unclear":false},{"inn":"","relations":"Інше","relations_other":"донька дружини","inn_hidden":true,"family_name":"Кармазіна М. Є","name_unclear":false}],"patronymic":"Олександрович","inn_hidden":true,"family_raw":"","inn_unclear":false,"post":{"post_unclear":false,"post":"суддя орджонікідзевського районного суду м. запоріжжя","post_hidden":false,"region":"Запорізька область","region_hidden":false,"office":"Загальний місцевий суд","office_hidden":false,"office_unclear":false},"full_name":"Макаров Віталій Олександрович","addresses":[{"place_district":"","place_city_hidden":false,"place_city":"Запоріжжя","place_city_type_hidden":true,"place_district_hidden":false,"place_city_type":"Місто","place_address_hidden":true,"place_address":"","place_hidden":false,"place":"Запорізька область"}],"last_name":"Макаров","full_name_suggest":{"output":"Макаров Віталій Олександрович","input":["Макаров Віталій Олександрович","Віталій Олександрович Макаров","Віталій Макаров"]}},"source":"VULYK","estate":{"23":[{"space_unclear":false,"costs":"","costs_comment":"","costs_hidden":false,"address_hidden":false,"region_hidden":false,"space_comment":"","space":"6000","address":"с. Новоукраїнка","region":"","space_units_unclear":false,"space_units":"м²","costs_rent":"","costs_rent_comment":""},{"costs":"","costs_comment":"","costs_hidden":false,"address_hidden":false,"region_hidden":false,"space_comment":"","space":"","address":"","region":"","costs_rent_comment":"","space_units":"","costs_rent":""},{"costs_rent":"","space_unclear":false,"region":"","costs":"","costs_rent_comment":"","costs_comment":"","address_hidden":false,"space_comment":"","space_units":"","space":"","address":""},{"costs_rent":"","region":"","costs":"","costs_rent_comment":"","costs_comment":"","space_comment":"","space_units":"","space":"","address":""},{"costs_rent":"","region":"","costs":"","costs_rent_comment":"","costs_comment":"","space_comment":"","space_units":"","space":"","address":""},{"costs_rent":"","region":"","costs":"","costs_rent_comment":"","costs_comment":"","space_comment":"","space_units":"","space":"","address":""}],"25":[{"space_unclear":false,"costs":"","costs_comment":"","address_hidden":false,"region_hidden":false,"space_comment":"","space_hidden":false,"space":"65.6","address":"м. Мелітополь","region":"Запорізька область","address_unclear":false,"costs_rent_comment":"","costs_rent_hidden":false,"space_comment_hidden":false,"space_units":"м²","space_units_hidden":false,"costs_rent":""}],"29":[{"space_hidden":false,"costs_property_comment":"","address_hidden":false,"region_hidden":false,"space_comment":"","space":"130000","address":"с. Вознесенка","region":"Кримська Автономна Республіка","costs_property":"","costs_rent_comment":"","space_units":"м²","space_units_hidden":false,"costs_rent":""},{"space_unclear":false,"costs_property_comment":"","address_hidden":false,"region_hidden":false,"space_comment":"","space":"805","address":"с. м. т. Щебетовка","region":"","costs_property":"","costs_rent_comment":"","space_units":"м²","space_units_unclear":false,"costs_rent":""}],"31":[{"space_unclear":false,"address_hidden":false,"region_hidden":false,"space_comment":"","space_hidden":false,"space":"39.1","address":"м. Мелітополь","region":"Запорізька область","costs_property":"","costs_rent_comment":"","space_units":"м²","costs_property_comment":"","costs_rent":""},{"costs_rent":"","region":"Запорізька область","costs_property":"","costs_rent_comment":"","space_comment_unclear":false,"region_hidden":false,"space_comment":"","costs_property_comment":"","space_units":"м²","space":"71.93","address":"м. Запоріжжя"}]},"intro":{"declaration_year":"2014","isnotdeclaration":""}}