{"income":{"5":{"value":"306578","family_comment":"","value_unclear":false,"family_hidden":false,"value_hidden":false,"family_unclear":false,"comment_unclear":false,"comment":"","family":"73590"},"6":{"value":"306236","family_unclear":false,"family_hidden":false,"family_comment":"","family":"57343","comment":""},"7":{"value":"","family_hidden":false,"value_hidden":false,"family_comment":"","source_name":"","family":"","comment":""},"8":{"family_comment":"","value":"","family":"","comment":""},"9":{"family_comment":"","value":"342","value_unclear":false,"family":"4953","comment":""},"10":{"family_comment":"","family_unclear":false,"value":"","family":"","comment":""},"11":{"family_comment":"","value":"","family":"","comment":""},"12":{"family_comment":"","value":"","family":"","comment":""},"13":{"family_comment":"","value":"","family":"","comment":""},"14":{"family_comment":"","value":"","family":"","comment":""},"15":{"family_comment":"","value":"","family":"","comment":""},"16":{"family_comment":"","value":"","family":"","comment":""},"17":{"family_comment":"","value":"","family":"","comment":""},"18":{"family_comment":"","value":"","family":"","comment":""},"19":{"family_comment":"","value":"","family":"","comment":""},"20":{"value":"","value_unclear":false,"family_comment":"","comment_unclear":false,"comment":"","family":"11294"}},"vehicle":{"40":[{"brand_info":"4398 куб. см.","sum":"","brand":"BMW X5","sum_comment":"","brand_unclear":false,"year":"2001","brand_info_hidden":false,"brand_info_unclear":false,"sum_rent_comment":"","sum_rent":""}]},"id":"vulyk_71_114","banks":{"45":[{"sum_foreign_comment":"","sum_units":"UAH","sum_comment":"","sum_comment_unclear":false,"sum_foreign_units":"UAH","sum_comment_hidden":false,"sum":"4870","sum_foreign":""}],"51":[{"sum_foreign_comment":"","sum_units":"UAH","sum_comment":"","sum_comment_unclear":false,"sum_foreign_units":"UAH","sum_comment_hidden":false,"sum_unclear":false,"sum":"50888","sum_foreign":""}]},"declaration":{"additional_info_text":"","notfull_lostpages":"","date":"2014-03-31T00:00:00","notfull":"","additional_info":"","url":"http://static.declarations.com.ua/declarations/chosen_ones/judges_batch/488_koval_liubov_anatoliivna.pdf"},"liabilities":{"54":{"sum_foreign_comment":"","sum":"","sum_comment":"","sum_comment_unclear":false,"sum_comment_hidden":false,"sum_unclear":false,"sum_foreign":""},"55":{"sum_foreign_comment":"","sum":"","sum_comment":"","sum_foreign":""},"56":{"sum_foreign_comment":"","sum":"","sum_comment":"","sum_comment_unclear":false,"sum_unclear":false,"sum_foreign":""},"57":{"sum_foreign_comment":"","sum":"","sum_comment":"","sum_comment_hidden":false,"sum_unclear":false,"sum_foreign":""},"58":{"sum_foreign_comment":"","sum":"","sum_comment":"","sum_comment_hidden":false,"sum_unclear":false,"sum_foreign":""},"59":{"sum_foreign_comment":"","sum_comment_hidden":false,"sum":"","sum_comment":"","sum_foreign":""},"60":{"sum_foreign_comment":"","sum_comment_hidden":false,"sum":"","sum_comment":"","sum_foreign":""},"61":{"sum_foreign_comment":"","sum":"","sum_comment":"","sum_foreign":""},"62":{"sum_foreign_comment":"","sum":"","sum_comment":"","sum_foreign":""},"63":{"sum_foreign_comment":"","sum":"","sum_comment":"","sum_unclear":false,"sum_foreign":""},"64":{"sum_foreign_comment":"","sum":"","sum_comment":"","sum_unclear":false,"sum_foreign":""}},"ft_src":"суддя дніпропетровського апеляційного господарського суду\nДніпропетровська область\nАпеляційний господарський суд\nЛюбов\nКоваль О. М\nПодружжя\nКоваль І. О\nДитина\nАнатоліївна\nКоваль Любов Анатоліївна\nЛюбов Анатоліївна Коваль\nЛюбов Коваль\nКоваль Любов Анатоліївна\nКоваль Любов Анатоліївна\nКоваль\n4398 куб. см.\nBMW X5\n2001\n63.6\n651.5\n45.3\n50888\n4870\n2013\n4398 куб. см.\n2001\nBMW X5\n63.6\n651.5\n45.3\nПодружжя\nКоваль О. М\nДитина\nКоваль І. О\nКоваль Любов Анатоліївна\nЛюбов Анатоліївна Коваль\nЛюбов Коваль\nКоваль Любов Анатоліївна\nКоваль Любов Анатоліївна\nЛюбов\nАнатоліївна\nАпеляційний господарський суд\nДніпропетровська область\nсуддя дніпропетровського апеляційного господарського суду\nКоваль\n306236\n57343\n11294\n306578\n73590\n342\n4953\n4870\n50888\n2013\n57343\n306236\n4953\n342\n73590\n306578\n11294\nКоваль О. М\nПодружжя\nКоваль І. О\nДитина\nАнатоліївна\nКоваль\nЛюбов\nКоваль Любов Анатоліївна\nЛюбов Анатоліївна Коваль\nЛюбов Коваль\nКоваль Любов Анатоліївна\nДніпропетровська область\nАпеляційний господарський суд\nсуддя дніпропетровського апеляційного господарського суду\nКоваль Любов Анатоліївна\nBMW X5\n4398 куб. см.\n2001\n4953\n342\n11294\n306578\n73590\n306236\n57343\n63.6\n45.3\n651.5\n4870\n50888\n2013","general":{"inn":"","name":"Любов","family":[{"inn":"","inn_hidden":true,"relations_hidden":false,"family_name":"Коваль О. М","relations_other":"","relations":"Подружжя","name_hidden":true,"name_unclear":false},{"inn":"","inn_hidden":true,"relations_hidden":false,"family_name":"Коваль І. О","relations_other":"","relations":"Дитина","name_hidden":false,"name_unclear":false}],"patronymic":"Анатоліївна","inn_hidden":true,"family_raw":"","inn_unclear":false,"post":{"post_unclear":false,"region_unclear":false,"post":"суддя дніпропетровського апеляційного господарського суду","office":"Апеляційний господарський суд","region":"Дніпропетровська область","post_hidden":false,"office_unclear":false},"full_name_suggest":{"output":"Коваль Любов Анатоліївна","input":["Коваль Любов Анатоліївна","Любов Анатоліївна Коваль","Любов Коваль"]},"full_name":"Коваль Любов Анатоліївна","addresses":[{"place_district":"","place_unclear":false,"place_city":"","place_city_type_hidden":true,"place_district_hidden":true,"place_city_type":"","place_city_hidden":true,"place_address_hidden":true,"place_address":"","place_hidden":true,"place":""}],"last_name":"Коваль","patronymic_hidden":false,"last_name_unclear":false,"name_unclear":false},"source":"VULYK","estate":{"25":[{"region_unclear":false,"space_unclear":false,"costs":"","costs_rent_unclear":false,"costs_comment":"","costs_hidden":false,"address_hidden":true,"region_hidden":true,"space_comment":"","space_hidden":false,"space":"45.3","address":"","costs_unclear":false,"region":"","address_unclear":false,"costs_rent_comment":"","costs_rent_hidden":false,"space_comment_unclear":false,"space_units":"м²","costs_rent":""}],"31":[{"space_hidden":false,"costs_property_comment":"","address_hidden":true,"region_hidden":true,"space_comment":"","space":"63.6","address":"","region":"","costs_property":"","costs_rent_comment":"","space_comment_unclear":false,"space_units":"м²","space_units_hidden":false,"costs_rent":""}],"34":[{"region_unclear":false,"space_hidden":false,"address_hidden":true,"region_hidden":true,"space_comment":"","space":"651.5","address":"","region":"","costs_property":"","costs_rent_comment":"","space_comment_hidden":false,"space_units":"м²","costs_property_comment":"","costs_rent":""}]},"intro":{"declaration_year":"2013","isnotdeclaration":""}}