{"id":"vulyk_86_19","ft_src":"2013, у спадщину\n1600 куб. см., 100 кінських сил\nMitsubishi Carisma\n2003\n38900\n1500\n40.5\n2014\n247918.56\n354628.09\n105386\n1023.53\n1600 куб. см., 100 кінських сил\n2013, у спадщину\n2003\nMitsubishi Carisma\n2014\nГапонов Андрій В'ячеславович\nАндрій В'ячеславович Гапонов\nАндрій Гапонов\nГапонов Андрій В'ячеславович\nГапонов Андрій В'ячеславович\nПодружжя\nГапонова О. І\nДитина\nГапонова В. А\nАндрій\nГапонов\nЗагальний апеляційний суд\nДонецька область\nсуддя апеляційного суду донецької області\nВ'ячеславович\n4000\n247918.56\n354628.09\n105386\n1023.53\n38900\n1500\n40.5\n4000\nГапонова О. І\nПодружжя\nГапонова В. А\nДитина\nВ'ячеславович\nГапонов\nАндрій\nГапонов Андрій В'ячеславович\nАндрій В'ячеславович Гапонов\nАндрій Гапонов\nГапонов Андрій В'ячеславович\nДонецька область\nЗагальний апеляційний суд\nсуддя апеляційного суду донецької області\nГапонов Андрій В'ячеславович","estate":{"23":[{"address":"","space_units":"м²","costs_comment":"","region_hidden":true,"space_comment":"","address_hidden":false,"costs":"","address_unclear":false,"costs_rent_comment":"","space":"38900","region":"","costs_rent":""},{"costs":"","address":"","space_units":"м²","costs_rent_comment":"","space":"1500","space_comment":"","costs_comment":"","region":"","costs_rent":""}],"24":[{"address":"","space_units":"м²","costs_comment":"","space_comment":"","region_hidden":true,"region":"","address_hidden":false,"space":"40.5","address_unclear":false,"costs_rent_comment":"","costs":"","costs_rent":""}]},"vehicle":{"35":[{"sum_comment":"2013, у спадщину","brand_info":"1600 куб. см., 100 кінських сил","brand_unclear":false,"sum_rent_comment":"","year":"2003","brand":"Mitsubishi Carisma","sum_rent":"","brand_info_unclear":false,"year_unclear":false,"sum":""}]},"source":"VULYK","income":{"5":{"family_comment":"","value":"354628.09","family":"","comment":""},"6":{"family_comment":"","value":"247918.56","family":"","comment":"","family_comment_unclear":false},"7":{"source_name_hidden":false,"family_comment":"","comment":"","family":"","comment_hidden":false,"value":"","source_name":""},"8":{"family_comment":"","value":"","family":"","comment":""},"9":{"family_comment":"","value":"","family":"","comment":""},"10":{"family":"","family_comment":"","comment":"","value_hidden":false,"value_unclear":false,"value":""},"11":{"family_comment":"","value":"","family":"","comment":""},"12":{"family_comment":"","value":"","family":"","comment":""},"13":{"family_comment":"","value":"","family":"","comment":""},"14":{"family_comment":"","value":"","family":"","comment":""},"15":{"family_comment":"","value":"","family":"","comment":""},"16":{"family_comment":"","value":"105386","family":"","comment":""},"17":{"family_comment":"","value":"","family":"","comment":""},"18":{"family_comment":"","value":"","family":"","comment":""},"19":{"family_comment":"","value":"1023.53","family":"","comment":""},"20":{"family_comment":"","comment_unclear":false,"value":"","family":"","comment":""}},"general":{"family_raw":"","name":"Андрій","full_name_suggest":{"input":["Гапонов Андрій В'ячеславович","Андрій В'ячеславович Гапонов","Андрій Гапонов"],"output":"Гапонов Андрій В'ячеславович"},"patronymic":"В'ячеславович","inn_hidden":true,"patronymic_unclear":false,"inn":"","inn_unclear":false,"last_name":"Гапонов","full_name":"Гапонов Андрій В'ячеславович","family":[{"inn":"","family_name":"Гапонова О. І","relations_other":"","relations_hidden":false,"name_unclear":false,"inn_hidden":true,"name_hidden":false,"relations":"Подружжя"},{"inn":"","family_name":"Гапонова В. А","relations_other":"","name_unclear":false,"inn_hidden":false,"name_hidden":false,"relations":"Дитина"}],"post":{"office":"Загальний апеляційний суд","post":"суддя апеляційного суду донецької області","candidate":"","region_hidden":false,"region":"Донецька область","office_hidden":false,"post_unclear":false,"office_unclear":false},"addresses":[{"place_city_type":"","place_city_type_hidden":false,"place_district_hidden":false,"place_city_hidden":false,"place_district":"","place_hidden":true,"place_address":"","place":"","place_city":"","place_address_hidden":true,"place_unclear":false}]},"liabilities":{"54":{"sum_comment":"","sum_foreign_comment":"","sum_foreign":"","sum_unclear":false,"sum":""},"55":{"sum_comment":"","sum_foreign_comment":"","sum_foreign":"","sum":""},"56":{"sum_comment":"","sum_foreign_comment":"","sum_foreign":"","sum_hidden":false,"sum":"4000"},"57":{"sum_comment":"","sum_foreign_comment":"","sum_foreign":"","sum_unclear":false,"sum":""},"58":{"sum_comment":"","sum_foreign_comment":"","sum_foreign":"","sum_unclear":false,"sum":""},"59":{"sum_comment":"","sum_foreign_comment":"","sum_foreign":"","sum":""},"60":{"sum_comment":"","sum_foreign_comment":"","sum_foreign":"","sum":"","sum_comment_hidden":false},"61":{"sum_comment":"","sum_foreign_comment":"","sum_foreign":"","sum":""},"62":{"sum_comment":"","sum_foreign_comment":"","sum_foreign":"","sum":""},"63":{"sum_comment":"","sum_foreign_comment":"","sum_foreign":"","sum":""},"64":{"sum_comment":"","sum_foreign_comment":"","sum_foreign":"","sum":""}},"declaration":{"notfull_lostpages":"","additional_info_text":"","additional_info":"","date":"2015-03-03T00:00:00","notfull":"","url":"http://static.declarations.com.ua/declarations/chosen_ones/judges_batch/2722_haponov_andrii__v’yacheslavovych.pdf"},"intro":{"declaration_year_unclear":false,"declaration_year":"2014"}}