{"income":{"5":{"value":"305308","family_comment":"","value_unclear":false,"family_hidden":false,"value_hidden":false,"family_unclear":false,"family":"56235","comment":"","family_comment_unclear":false},"6":{"family_comment":"","family_unclear":false,"value":"253283","family":"","comment":""},"7":{"source_name_unclear":false,"value":"","family_comment":"","source_name":"","family":"","comment":"","source_name_hidden":false},"8":{"family_comment":"","value":"","family":"","comment":""},"9":{"family_comment":"","family_unclear":false,"value":"2025","family":"1235","comment":""},"10":{"family_comment":"","value":"","family":"","comment":""},"11":{"family_comment":"дарунки","value":"50000","family":"55000","comment":"дарунки"},"12":{"family_comment":"","value":"","family":"","comment":""},"13":{"family_comment":"","value":"","family":"","comment":""},"14":{"family_comment":"","value":"","family":"","comment":""},"15":{"family_comment":"","value":"","family":"","comment":""},"16":{"value":"","value_unclear":false,"value_hidden":false,"family_comment":"","family":"","comment":""},"17":{"family_comment":"","value":"","family":"","comment":""},"18":{"family_comment":"","value":"","family":"","comment":""},"19":{"family_comment":"","value":"","family":"","comment":""},"20":{"value":"","family_comment":"","value_unclear":false,"comment_hidden":false,"family_hidden":false,"family":"","value_hidden":false,"family_unclear":false,"comment_unclear":false,"comment":"","family_comment_unclear":false}},"vehicle":{"40":[{"brand_info":"ML300 CDI, 2987 куб.см, інше право користування","sum":"","brand":"Mercedes-Benz ML-Class","sum_comment":"","brand_unclear":false,"year":"2011","brand_hidden":false,"brand_info_hidden":false,"brand_info_unclear":false,"sum_rent_comment":"","sum_rent":""}]},"id":"vulyk_62_6","banks":{"45":[{"sum_units":"UAH","sum_hidden":true,"sum_foreign_units_hidden":false,"sum":"646","sum_foreign":"","sum_foreign_comment":"","sum_foreign_hidden":false,"sum_comment":"","sum_comment_unclear":false,"sum_foreign_units":"UAH","sum_comment_hidden":true,"sum_unclear":false}],"46":[{"sum_units":"UAH","sum_hidden":false,"sum_foreign_units_hidden":false,"sum":"646","sum_foreign":"","sum_foreign_comment":"","sum_foreign_hidden":false,"sum_comment":"","sum_comment_unclear":false,"sum_foreign_units":"UAH","sum_comment_hidden":false,"sum_unclear":false}]},"declaration":{"additional_info_text":"","notfull_lostpages":"","date":"2015-03-27T00:00:00","notfull":"","additional_info":"","url":"http://static.declarations.com.ua/declarations/chosen_ones/mega_batch/osipov_iurii_volodymyrovych.pdf"},"liabilities":{"54":{"sum_foreign_comment":"","sum":"","sum_comment":"","sum_hidden":false,"sum_comment_hidden":false,"sum_foreign":""},"55":{"sum_foreign_comment":"","sum":"","sum_comment":"","sum_hidden":false,"sum_comment_hidden":false,"sum_unclear":false,"sum_foreign":""},"56":{"sum_foreign_comment":"","sum":"","sum_comment":"","sum_hidden":false,"sum_unclear":false,"sum_foreign":""},"57":{"sum_foreign_comment":"","sum":"","sum_comment":"","sum_hidden":false,"sum_comment_hidden":false,"sum_unclear":false,"sum_foreign":""},"58":{"sum_foreign_comment":"","sum_foreign_hidden":false,"sum_comment":"","sum_hidden":false,"sum_comment_hidden":false,"sum_unclear":false,"sum":"","sum_foreign":""},"59":{"sum_foreign_comment":"","sum":"","sum_comment":"","sum_foreign":""},"60":{"sum_foreign_comment":"","sum_foreign_hidden":false,"sum_comment":"","sum_hidden":false,"sum_comment_hidden":false,"sum_unclear":false,"sum":"","sum_foreign":""},"61":{"sum_foreign_comment":"","sum_foreign_hidden":false,"sum_comment":"","sum_hidden":false,"sum":"","sum_foreign":""},"62":{"sum_foreign_comment":"","sum":"","sum_comment":"","sum_unclear":false,"sum_foreign":""},"63":{"sum_foreign_comment":"","sum":"","sum_comment":"","sum_hidden":false,"sum_comment_hidden":false,"sum_unclear":false,"sum_foreign":""},"64":{"sum_foreign_comment":"","sum":"","sum_comment":"","sum_comment_unclear":false,"sum_hidden":false,"sum_comment_hidden":false,"sum_foreign":""}},"ft_src":"суддя\nОдеська область\nАпеляційний адміністративний суд\nЮрій\nОсіпова О. А\nПодружжя\nОсіпов М. Ю\nДитина\nОсіпов К. Ю\nДитина\nВолодимирович\nОсіпов Юрій Володимирович\nЮрій Володимирович Осіпов\nЮрій Осіпов\nОсіпов Юрій Володимирович\nОсіпов Юрій Володимирович\nОсіпов\nMercedes-Benz ML-Class\nML300 CDI, 2987 куб.см, інше право користування\n2011\n646\n646\n2014\nML300 CDI, 2987 куб.см, інше право користування\n2011\nMercedes-Benz ML-Class\n646\n646\n108\nПодружжя\nОсіпова О. А\nДитина\nОсіпов М. Ю\nДитина\nОсіпов К. Ю\nОсіпов Юрій Володимирович\nЮрій Володимирович Осіпов\nЮрій Осіпов\nОсіпов Юрій Володимирович\nОсіпов Юрій Володимирович\nЮрій\nВолодимирович\nАпеляційний адміністративний суд\nсуддя\nОдеська область\nОсіпов\n253283\n305308\n56235\nдарунки\n50000\n55000\nдарунки\n2025\n1235\n2014\n108\nПодружжя\nОсіпова О. А\nОсіпов М. Ю\nДитина\nОсіпов К. Ю\nДитина\nВолодимирович\nОсіпов\nЮрій\nОсіпов Юрій Володимирович\nЮрій Володимирович Осіпов\nЮрій Осіпов\nОсіпов Юрій Володимирович\nОдеська область\nсуддя\nАпеляційний адміністративний суд\nОсіпов Юрій Володимирович\n253283\n55000\nдарунки\nдарунки\n50000\n56235\n305308\n1235\n2025\nMercedes-Benz ML-Class\nML300 CDI, 2987 куб.см, інше право користування\n2011\n55000\nдарунки\nдарунки\n50000\n305308\n56235\n1235\n2025\n253283\n108\n646\n646\n2014","general":{"inn":"","name":"Юрій","inn_unclear":false,"family":[{"inn":"","inn_hidden":true,"relations_unclear":false,"relations_hidden":false,"relations_other":"","relations":"Подружжя","name_hidden":true,"inn_unclear":false,"family_name":"Осіпова О. А","name_unclear":false},{"inn":"","inn_hidden":false,"relations_hidden":false,"family_name":"Осіпов М. Ю","relations_other":"","relations":"Дитина","name_hidden":false,"name_unclear":false},{"inn":"","relations":"Дитина","relations_other":"","inn_hidden":false,"family_name":"Осіпов К. Ю","name_hidden":false,"name_unclear":false}],"inn_hidden":true,"family_raw":"","last_name":"Осіпов","post":{"post_unclear":false,"post":"суддя","post_hidden":false,"region":"Одеська область","region_hidden":false,"office":"Апеляційний адміністративний суд","office_hidden":false,"office_unclear":false},"full_name_suggest":{"output":"Осіпов Юрій Володимирович","input":["Осіпов Юрій Володимирович","Юрій Володимирович Осіпов","Юрій Осіпов"]},"full_name":"Осіпов Юрій Володимирович","addresses":[{"place_city_type_unclear":false,"place_address":"","place_district_hidden":true,"place_city_type":"","place_address_hidden":true,"place_address_unclear":false,"place_city_type_hidden":true,"place":"","place_district":"","place_unclear":false,"place_city":"","place_city_unclear":false,"place_hidden":true,"place_city_hidden":true,"place_district_unclear":false}],"patronymic":"Володимирович","last_name_unclear":false,"name_unclear":false},"source":"VULYK","estate":{"25":[{"region_unclear":false,"space_hidden":false,"costs":"","costs_comment":"","costs_hidden":false,"address_hidden":true,"region_hidden":true,"space_comment":"","space_unclear":false,"space":"108","address":"","region":"","costs_rent_comment":"","space_units":"м²","costs_rent":""}],"26":[{"space_hidden":false,"costs":"","costs_comment":"","address_hidden":true,"region_hidden":true,"space_comment":"","space_unclear":false,"space":"","address":"","region":"","costs_rent_comment":"","space_units":"м²","costs_rent":""}]},"intro":{"declaration_year":"2014","isnotdeclaration":"","declaration_year_unclear":false,"declaration_year_hidden":false}}