{"income":{"5":{"value":"182711.3","family_comment":"","value_unclear":false,"family_hidden":false,"value_hidden":false,"family_unclear":false,"family":"","comment":"","family_comment_unclear":false},"6":{"family_comment":"","family_unclear":false,"value":"182655","family":"","comment":""},"7":{"source_name_unclear":false,"value":"","family_comment":"","source_name":"","family":"","comment":"","source_name_hidden":false},"8":{"family_comment":"","value":"","family":"","comment":""},"9":{"family_comment":"","family_unclear":false,"value":"56.3","family":"","comment":""},"10":{"family_comment":"","value":"","family":"","comment":""},"11":{"family_comment":"","value":"","family":"","comment":""},"12":{"family_comment":"","value":"","family":"","comment":""},"13":{"family_comment":"","value":"","family":"","comment":""},"14":{"family_comment":"","value":"","family":"","comment":""},"15":{"family_comment":"","value":"","family":"","comment":""},"16":{"value":"","value_unclear":false,"value_hidden":false,"family_comment":"","family":"","comment":""},"17":{"family_comment":"","value":"","family":"","comment":""},"18":{"family_comment":"","value":"","family":"","comment":""},"19":{"family_comment":"","value":"","family":"","comment":""},"20":{"value":"","family_comment":"","value_unclear":false,"comment_hidden":false,"family_hidden":false,"family":"","value_hidden":false,"family_unclear":false,"comment_unclear":false,"comment":"","family_comment_unclear":false}},"vehicle":{"35":[{"year_hidden":false,"brand_info":"1998 куб. см.","sum_rent_comment":"","sum_rent_hidden":false,"year":"2007","sum_hidden":false,"brand_info_hidden":false,"brand_info_unclear":false,"year_unclear":false,"sum_rent":"","sum":"","brand":"Toyota Rav 4","sum_comment":"","brand_unclear":false,"brand_hidden":false}]},"id":"vulyk_62_135","banks":{"45":[{"sum_units":"UAH","sum_hidden":false,"sum_foreign_units_hidden":false,"sum":"1576.86","sum_foreign":"","sum_foreign_comment":"","sum_foreign_hidden":false,"sum_comment":"","sum_comment_unclear":false,"sum_foreign_units":"UAH","sum_comment_hidden":false,"sum_unclear":false}],"46":[{"sum_units":"UAH","sum_hidden":false,"sum_foreign_units_hidden":false,"sum":"6503.6","sum_foreign":"","sum_foreign_comment":"","sum_foreign_hidden":false,"sum_comment":"","sum_comment_unclear":false,"sum_foreign_units":"UAH","sum_comment_hidden":false,"sum_unclear":false}]},"declaration":{"additional_info_text":"","notfull_lostpages":"","date":"2015-03-12T00:00:00","notfull":"","additional_info":"","url":"http://static.declarations.com.ua/declarations/chosen_ones/mega_batch/hudzenko_iaroslava_oleksandrivna.pdf"},"liabilities":{"54":{"sum_foreign_comment":"","sum":"","sum_comment":"","sum_hidden":false,"sum_comment_hidden":false,"sum_foreign":""},"55":{"sum_foreign_comment":"","sum":"","sum_comment":"","sum_hidden":false,"sum_comment_hidden":false,"sum_unclear":false,"sum_foreign":""},"56":{"sum_foreign_comment":"","sum":"9198.38","sum_comment":"","sum_hidden":false,"sum_unclear":false,"sum_foreign":""},"57":{"sum_foreign_comment":"","sum":"","sum_comment":"","sum_hidden":false,"sum_comment_hidden":false,"sum_unclear":false,"sum_foreign":""},"58":{"sum_foreign_comment":"","sum_foreign_hidden":false,"sum_comment":"","sum_hidden":false,"sum_comment_hidden":false,"sum_unclear":false,"sum":"","sum_foreign":""},"59":{"sum_foreign_comment":"","sum":"","sum_comment":"","sum_foreign":""},"60":{"sum_foreign_comment":"","sum_foreign_hidden":false,"sum_comment":"","sum_hidden":false,"sum_comment_hidden":false,"sum_unclear":false,"sum":"","sum_foreign":""},"61":{"sum_foreign_comment":"","sum_foreign_hidden":false,"sum_comment":"","sum_hidden":false,"sum":"","sum_foreign":""},"62":{"sum_foreign_comment":"","sum":"","sum_comment":"","sum_unclear":false,"sum_foreign":""},"63":{"sum_foreign_comment":"","sum":"","sum_comment":"","sum_hidden":false,"sum_comment_hidden":false,"sum_unclear":false,"sum_foreign":""},"64":{"sum_foreign_comment":"","sum":"","sum_comment":"","sum_comment_unclear":false,"sum_hidden":false,"sum_comment_hidden":false,"sum_foreign":""}},"ft_src":"9198.38\nсуддя господарського суду рівненської області\nРівненська область\nГосподарський місцевий суд\nЯрослава\nОлександрівна\nГудзенко\nГудзенко Ярослава Олександрівна\nГудзенко Ярослава Олександрівна\nЯрослава Олександрівна Гудзенко\nЯрослава Гудзенко\nГудзенко Ярослава Олександрівна\n1998 куб. см.\nToyota Rav 4\n2007\n6503.6\n1576.86\n2014\n1998 куб. см.\nToyota Rav 4\n2007\n1576.86\n6503.6\n17.1\n68.8\n66.9\nГудзенко Ярослава Олександрівна\nЯрослава Олександрівна Гудзенко\nЯрослава Гудзенко\nГудзенко Ярослава Олександрівна\nЯрослава\nГудзенко Ярослава Олександрівна\nОлександрівна\nГосподарський місцевий суд\nсуддя господарського суду рівненської області\nРівненська область\nГудзенко\n9198.38\n182655\n182711.3\n56.3\n2014\n9198.38\n17.1\n68.8\n66.9\nЯрослава\nОлександрівна\nГудзенко\nГудзенко Ярослава Олександрівна\nЯрослава Олександрівна Гудзенко\nЯрослава Гудзенко\nГудзенко Ярослава Олександрівна\nРівненська область\nсуддя господарського суду рівненської області\nГосподарський місцевий суд\nГудзенко Ярослава Олександрівна\n182655\n182711.3\n56.3\nToyota Rav 4\n1998 куб. см.\n2007\n182711.3\n56.3\n182655\n68.8\n66.9\n17.1\n1576.86\n6503.6\n2014","general":{"inn":"","name":"Ярослава","inn_unclear":false,"patronymic":"Олександрівна","inn_hidden":true,"family_raw":"","last_name":"Гудзенко","post":{"post_unclear":false,"post":"суддя господарського суду рівненської області","post_hidden":false,"region":"Рівненська область","region_hidden":false,"office":"Господарський місцевий суд","office_hidden":false,"office_unclear":false},"last_name_unclear":false,"full_name":"Гудзенко Ярослава Олександрівна","addresses":[{"place_city_type_unclear":false,"place_address":"","place_district_hidden":true,"place_city_type":"","place_address_hidden":true,"place_address_unclear":false,"place_city_type_hidden":true,"place":"","place_district":"","place_unclear":false,"place_city":"","place_city_unclear":false,"place_hidden":true,"place_city_hidden":true,"place_district_unclear":false}],"full_name_suggest":{"output":"Гудзенко Ярослава Олександрівна","input":["Гудзенко Ярослава Олександрівна","Ярослава Олександрівна Гудзенко","Ярослава Гудзенко"]},"name_unclear":false},"source":"VULYK","estate":{"25":[{"region_unclear":false,"space_hidden":false,"costs":"","costs_comment":"","costs_hidden":false,"address_hidden":true,"region_hidden":true,"space_comment":"","space_unclear":false,"space":"68.8","address":"","region":"","costs_rent_comment":"","space_units":"м²","costs_rent":""},{"costs":"","costs_comment":"","costs_hidden":false,"address_hidden":false,"region_hidden":false,"space_comment":"","space":"66.9","address":"","region":"","costs_rent_comment":"","space_comment_unclear":false,"space_units":"м²","costs_rent":""}],"27":[{"space_hidden":false,"costs":"","costs_comment":"","address_hidden":true,"region_hidden":true,"space_comment":"","space_unclear":false,"space":"17.1","address":"","region":"","costs_rent_comment":"","space_units":"м²","costs_rent":""}]},"intro":{"declaration_year":"2014","isnotdeclaration":"","declaration_year_unclear":false,"declaration_year_hidden":false}}