{"income":{"5":{"family_comment":"","value":"53880","family_hidden":false,"comment":"","family":"10788"},"6":{"value":"34618","value_unclear":false,"family_hidden":false,"family_comment":"","family":"","comment":""},"7":{"value":"","value_unclear":false,"family_comment":"","source_name":"","family":"","comment":""},"8":{"family_comment":"","value":"","family":"","comment":""},"9":{"family_comment":"","value":"1575","family":"10788","comment":""},"10":{"value":"","family_comment":"","comment_unclear":false,"family_unclear":false,"family":"","comment":"","family_comment_unclear":false},"11":{"family_comment":"","value":"","value_unclear":false,"family":"","comment":""},"12":{"family_comment":"","value":"","family":"","comment":""},"13":{"family_comment":"","value":"","family":"","comment":""},"14":{"family_comment":"","value":"","family":"","comment":""},"15":{"value":"","family_comment":"","comment_unclear":false,"family_unclear":false,"family":"","comment":""},"16":{"family_comment":"","value":"","family":"","comment":""},"17":{"family_comment":"","value":"","family":"","comment":""},"18":{"family_comment":"","family_unclear":false,"value":"","family":"","comment":""},"19":{"family_comment":"","value":"","family":"","comment":""},"20":{"family_comment":"","family_unclear":false,"value":"17687","family":"","comment":""}},"vehicle":{"40":[{"year_hidden":false,"brand_info":"1600","sum_rent_comment":"","year":"1985","brand_info_hidden":false,"year_unclear":false,"sum_rent":"","sum":"","brand":"Volkswagen Jetta","sum_comment":"","sum_comment_unclear":false,"brand_hidden":false},{"brand_info":"2000","sum_rent_comment":"","brand":"Citroen C5","sum_comment":"","year":"2005","sum":"","sum_rent":""}]},"id":"vulyk_92_178","banks":{"51":[{"sum_foreign_comment":"","sum_units":"UAH","sum_comment":"","sum_hidden":false,"sum_foreign_units":"UAH","sum_foreign_units_hidden":false,"sum_foreign_hidden":false,"sum_foreign_units_unclear":false,"sum":"100000","sum_unclear":true,"sum_foreign":""},{"sum_foreign_comment":"","sum_units":"","sum_comment":"","sum":"105940","sum_foreign":""}]},"declaration":{"additional_info_text":"","notfull_lostpages":"","date":"2015-03-30T00:00:00","notfull":"","additional_info":"","url":"http://static.declarations.com.ua/declarations/chosen_ones/judges_batch/3424_kovalyshyn_nataliia_ivanivna.pdf"},"liabilities":{"54":{"sum_foreign_comment":"","sum":"","sum_comment":"","sum_hidden":false,"sum_unclear":false,"sum_foreign":""},"55":{"sum_foreign_comment":"","sum":"","sum_comment":"","sum_unclear":false,"sum_foreign":""},"56":{"sum_foreign_comment":"","sum":"5500","sum_comment":"","sum_comment_unclear":false,"sum_hidden":false,"sum_unclear":false,"sum_foreign":""},"57":{"sum_foreign_comment":"","sum":"","sum_comment":"","sum_hidden":false,"sum_comment_hidden":false,"sum_foreign":""},"58":{"sum_foreign_comment":"","sum":"","sum_comment":"","sum_foreign":""},"59":{"sum_foreign_comment":"","sum":"","sum_comment":"","sum_comment_unclear":false,"sum_foreign":""},"60":{"sum_foreign_comment":"","sum":"","sum_comment":"","sum_foreign":""},"61":{"sum_foreign_comment":"","sum":"","sum_comment":"","sum_foreign":""},"62":{"sum_foreign_comment":"","sum":"","sum_comment":"","sum_comment_unclear":false,"sum_hidden":false,"sum_unclear":false,"sum_foreign":""},"63":{"sum_foreign_comment":"","sum":"","sum_comment":"","sum_foreign":""},"64":{"sum_foreign_comment":"","sum":"","sum_comment":"","sum_foreign":""}},"ft_src":"5500\nЛьвівська область\nСтрийський\nсуддя стрийського міськрайонного суду львівської області\nЛьвівська область\nЗагальний місцевий суд\nНаталія\nКовалишин А. З\nПодружжя\nКовалишин А. А\nДитина\nКовалишин С. А\nДитина\nКовалишин Д. А\nДитина\nІванівна\nКовалишин Наталія Іванівна\nНаталія Іванівна Ковалишин\nНаталія Ковалишин\nКовалишин Наталія Іванівна\nКовалишин Наталія Іванівна\nКовалишин\n1600\nVolkswagen Jetta\n1985\n2000\n2005\nCitroen C5\nСтрийський р-н\nЛьвівська область\n414.5\nСтрийський р-н\n3355\nЛьвівська область\nСколівський р-н\n788\nЛьвівська область\nм. Стрий\n49.3\nЛьвівська область\nЛьвівська область\nм. Стрий\n22.83\nСколівський р-н\n43.2\nЛьвівська область\n100000\n105940\n2014\n1600\nVolkswagen Jetta\n1985\n2000\nCitroen C5\n2005\n3355\nЛьвівська область\nСтрийський р-н\n788\nСколівський р-н\nЛьвівська область\n414.5\nСтрийський р-н\nЛьвівська область\nЛьвівська область\n43.2\nСколівський р-н\nЛьвівська область\nм. Стрий\n22.83\n49.3\nЛьвівська область\nм. Стрий\nПодружжя\nКовалишин А. З\nДитина\nКовалишин А. А\nДитина\nКовалишин С. А\nДитина\nКовалишин Д. А\nКовалишин Наталія Іванівна\nНаталія Іванівна Ковалишин\nНаталія Ковалишин\nКовалишин Наталія Іванівна\nКовалишин Наталія Іванівна\nНаталія\nКовалишин\nЗагальний місцевий суд\nсуддя стрийського міськрайонного суду львівської області\nЛьвівська область\nІванівна\nЛьвівська область\nСтрийський\n5500\n34618\n17687\n53880\n10788\n1575\n10788\n100000\n105940\n2014\n5500\n34618\n10788\n1575\n10788\n53880\n17687\nПодружжя\nКовалишин А. З\nДитина\nКовалишин А. А\nДитина\nКовалишин С. А\nДитина\nКовалишин Д. А\nІванівна\nКовалишин\nНаталія\nКовалишин Наталія Іванівна\nНаталія Іванівна Ковалишин\nНаталія Ковалишин\nКовалишин Наталія Іванівна\nЛьвівська область\nСтрийський\nЛьвівська область\nЗагальний місцевий суд\nсуддя стрийського міськрайонного суду львівської області\nКовалишин Наталія Іванівна\nVolkswagen Jetta\n1600\n1985\nCitroen C5\n2000\n2005\n10788\n1575\n17687\n10788\n53880\n34618\nм. Стрий\nЛьвівська область\n22.83\nСтрийський р-н\nЛьвівська область\n3355\nСколівський р-н\nЛьвівська область\n788\nСтрийський р-н\nЛьвівська область\n414.5\nЛьвівська область\nСколівський р-н\n43.2\nм. Стрий\nЛьвівська область\n49.3\n100000\n105940\n2014","general":{"inn":"","name":"Наталія","patronymic_unclear":false,"family":[{"inn":"","relations":"Подружжя","inn_unclear":false,"relations_hidden":false,"inn_hidden":true,"relations_other":"","name_hidden":false,"family_name":"Ковалишин А. З","name_unclear":false},{"inn":"","relations":"Дитина","inn_unclear":false,"relations_hidden":false,"inn_hidden":false,"relations_other":"","name_hidden":false,"family_name":"Ковалишин А. А","name_unclear":false},{"inn":"","relations":"Дитина","relations_other":"","inn_hidden":false,"family_name":"Ковалишин С. А","name_unclear":false},{"inn":"","relations":"Дитина","relations_other":"","inn_hidden":false,"family_name":"Ковалишин Д. А","name_unclear":false}],"patronymic":"Іванівна","inn_hidden":true,"family_raw":"","inn_unclear":false,"post":{"post_unclear":false,"post":"суддя стрийського міськрайонного суду львівської області","office_hidden":false,"region":"Львівська область","office":"Загальний місцевий суд","office_unclear":false,"region_hidden":false},"full_name":"Ковалишин Наталія Іванівна","addresses":[{"place_district":"Стрийський","place_address_hidden":true,"place_city":"","place_city_type_hidden":false,"place_district_hidden":false,"place_city_type":"","place_city_hidden":true,"place_address_unclear":false,"place_address":"","place_hidden":false,"place":"Львівська область"}],"last_name":"Ковалишин","full_name_suggest":{"output":"Ковалишин Наталія Іванівна","input":["Ковалишин Наталія Іванівна","Наталія Іванівна Ковалишин","Наталія Ковалишин"]}},"source":"VULYK","estate":{"23":[{"region_unclear":false,"space_unclear":false,"costs":"","costs_comment":"","address_hidden":true,"region_hidden":false,"space_comment":"","space":"3355","address":"Стрийський р-н","region":"Львівська область","costs_rent_comment":"","space_units":"м²","costs_rent":""},{"space_hidden":false,"costs":"","costs_comment":"","region_hidden":false,"space_comment":"","space_unclear":false,"space":"788","address":"Сколівський р-н","region":"Львівська область","address_unclear":false,"costs_rent_comment":"","space_units":"","costs_rent":""}],"24":[{"space_unclear":false,"costs":"","costs_comment":"","address_hidden":true,"region_hidden":false,"space_comment":"","space_hidden":false,"space":"414.5","address":"Стрийський р-н","region":"Львівська область","space_units_unclear":false,"space_units":"м²","space_units_hidden":false,"costs_rent":"","costs_rent_comment":""}],"26":[{"costs_rent":"","region":"Львівська область","costs":"","costs_rent_comment":"","costs_comment":"","address_hidden":true,"region_hidden":false,"space_comment":"","space_units":"м²","space":"43.2","address":"Сколівський р-н"}],"27":[{"space_unclear":false,"costs":"","costs_comment":"","address_hidden":true,"region_hidden":false,"space_comment":"","space_hidden":false,"space":"49.3","address":"м. Стрий","region":"Львівська область","address_unclear":false,"costs_rent_comment":"","space_units":"м²","costs_rent":""}],"31":[{"space_unclear":false,"address_hidden":true,"region_hidden":false,"space_comment":"","space_hidden":false,"space":"22.83","address":"м. Стрий","region":"Львівська область","costs_property":"","costs_rent_comment":"","address_unclear":false,"space_units":"м²","costs_property_comment":"","costs_rent":""}]},"intro":{"declaration_year":"2014","isnotdeclaration":""}}