{"income":{"5":{"family_comment":"","value":"234455","family":"14481","comment":""},"6":{"family_comment":"","value":"229846","family":"","comment":""},"7":{"family_comment":"","value":"","source_name":"","family":"","comment":""},"8":{"family_comment":"","value":"","family":"","comment":""},"9":{"value":"","comment_unclear":false,"family_comment":"","family":"","comment":"","family_comment_unclear":false},"10":{"family_comment":"","value":"","family":"6380","comment":""},"11":{"family_comment":"","value":"","family":"","comment":""},"12":{"family_comment":"","value":"","family":"4801","comment":""},"13":{"family_comment":"","value":"","family":"","comment":""},"14":{"family_comment":"","value":"","family":"","comment":""},"15":{"family_comment":"","value":"3872","family":"","comment":""},"16":{"family_comment":"","value":"","family":"","comment":""},"17":{"family_comment":"","value":"","family":"","comment":""},"18":{"family_comment":"","value":"","family":"","comment":""},"19":{"value":"","family_comment":"","value_unclear":false,"family_unclear":false,"family":"","comment":""},"20":{"value":"737","family_comment":"","value_unclear":false,"comment_hidden":false,"family_comment_hidden":false,"family_unclear":false,"family_comment_unclear":false,"comment_unclear":false,"comment":"","family":"3300"},"21":[{"cur":"800","cur_units":"OTHER","uah_equal":"4625","country":"Польща","cur_units_other":"злоті","country_comment":"Страхове відшкодування"}]},"id":"vulyk_106_108","banks":{"45":[{"sum_foreign_comment":"","sum_units":"UAH","sum_comment":"","sum_foreign_comment_hidden":false,"sum_hidden":false,"sum_foreign_units":"UAH","sum_comment_hidden":false,"sum":"3210","sum_foreign":""}],"51":[{"sum_foreign_comment":"","sum_units":"UAH","sum_comment":"","sum_comment_unclear":false,"sum_foreign_comment_hidden":false,"sum_foreign_units":"UAH","sum_comment_hidden":false,"sum":"4993","sum_foreign":""}]},"declaration":{"additional_info_text":"","notfull_lostpages":"","date":"2016-03-30T00:00:00","notfull":"","additional_info":"","url":"http://static.declarations.com.ua/declarations/chosen_ones/judges_batch/2247_himon_mykola_mykhailovych.pdf"},"liabilities":{"54":{"sum_foreign_comment":"","sum":"","sum_comment":"","sum_comment_unclear":false,"sum_hidden":false,"sum_comment_hidden":false,"sum_foreign":""},"55":{"sum_foreign_comment":"","sum":"","sum_hidden":false,"sum_comment":"","sum_foreign":""},"56":{"sum_foreign_comment":"","sum":"","sum_comment":"","sum_hidden":false,"sum_comment_hidden":false,"sum_unclear":false,"sum_foreign":""},"57":{"sum_foreign_comment":"","sum":"","sum_comment":"","sum_hidden":false,"sum_comment_hidden":false,"sum_foreign":""},"58":{"sum_foreign_comment":"","sum":"","sum_comment":"","sum_hidden":false,"sum_comment_hidden":false,"sum_foreign":""},"59":{"sum_foreign_comment":"","sum":"","sum_comment":"","sum_foreign":""},"60":{"sum_foreign_comment":"","sum":"","sum_comment":"","sum_hidden":false,"sum_comment_hidden":false,"sum_foreign":""},"61":{"sum_foreign_comment":"","sum":"","sum_comment":"","sum_foreign":""},"62":{"sum_foreign_comment":"","sum":"","sum_comment":"","sum_comment_hidden":false,"sum_unclear":false,"sum_foreign":""},"63":{"sum_foreign_comment":"","sum":"","sum_comment":"","sum_foreign":""},"64":{"sum_foreign_comment":"","sum":"","sum_comment":"","sum_foreign":""}},"ft_src":"суддя дніпропетровського апеляційного адміністративного суду\nДніпропетровська область\nАпеляційний адміністративний суд\nМикола\nГімон О. В\nПодружжя\nГімон М. М\nДитина\nГімон К. М\nДитина\nМихайлович\nГімон Микола Михайлович\nМикола Михайлович Гімон\nМикола Гімон\nГімон Микола Михайлович\nГімон Микола Михайлович\nГімон\n3872\n6380\n737\n3300\nзлоті\nПольща\nOTHER\n4625\n800\nСтрахове відшкодування\n14481\n234455\n4801\n229846\n4993\n3210\n997\n61\n47.1\n2015\n229846\n3872\n4801\nПольща\n800\nOTHER\n4625\nзлоті\nСтрахове відшкодування\n6380\n14481\n234455\n3300\n737\n3210\n4993\n997\n47.1\n61\nГімон Микола Михайлович\nМикола Михайлович Гімон\nМикола Гімон\nГімон Микола Михайлович\nГімон Микола Михайлович\nПодружжя\nГімон О. В\nДитина\nГімон М. М\nДитина\nГімон К. М\nМикола\nГімон\nДніпропетровська область\nАпеляційний адміністративний суд\nсуддя дніпропетровського апеляційного адміністративного суду\nМихайлович\n229846\n800\nПольща\n4625\nСтрахове відшкодування\nзлоті\nOTHER\n4801\n3872\n3300\n737\n234455\n14481\n6380\n2015\nГімон О. В\nПодружжя\nГімон М. М\nДитина\nГімон К. М\nДитина\nМихайлович\nГімон\nМикола\nГімон Микола Михайлович\nМикола Михайлович Гімон\nМикола Гімон\nГімон Микола Михайлович\nДніпропетровська область\nАпеляційний адміністративний суд\nсуддя дніпропетровського апеляційного адміністративного суду\nГімон Микола Михайлович\n61\n997\n47.1\n3210\n4993\n2015","general":{"inn":"","name":"Микола","inn_unclear":false,"family":[{"inn":"","inn_hidden":false,"relations_unclear":false,"relations_hidden":false,"relations_other":"","relations":"Подружжя","name_hidden":false,"family_name":"Гімон О. В","name_unclear":false},{"inn":"","relations":"Дитина","relations_unclear":false,"family_name":"Гімон М. М","inn_hidden":false,"relations_other":"","name_hidden":false,"name_unclear":false},{"inn_hidden":false,"inn":"","name_hidden":false,"family_name":"Гімон К. М","relations":"Дитина","name_unclear":false}],"inn_hidden":true,"family_raw":"","last_name":"Гімон","post":{"region_unclear":false,"region":"Дніпропетровська область","post":"суддя дніпропетровського апеляційного адміністративного суду","office":"Апеляційний адміністративний суд","office_unclear":false,"post_hidden":false},"full_name":"Гімон Микола Михайлович","addresses":[{"place_district":"","place_city_hidden":false,"place_city":"","place_city_type_hidden":false,"place_district_hidden":false,"place_city_type":"","place_address_hidden":false,"place_address":"","place_hidden":true,"place":""}],"patronymic":"Михайлович","full_name_suggest":{"output":"Гімон Микола Михайлович","input":["Гімон Микола Михайлович","Микола Михайлович Гімон","Микола Гімон"]},"name_unclear":false},"source":"VULYK","estate":{"23":[{"region_unclear":false,"space_hidden":false,"costs":"","costs_comment":"","address_hidden":false,"region_hidden":true,"space_comment":"","space_unclear":false,"space":"997","address":"","costs_comment_unclear":false,"costs_rent_comment_unclear":false,"region":"","address_unclear":false,"costs_rent_comment":"","space_comment_unclear":false,"space_comment_hidden":false,"space_units":"м²","costs_rent":""}],"24":[{"space_unclear":false,"costs":"","costs_comment":"","address_hidden":false,"region_hidden":true,"space_comment":"","space_hidden":false,"space":"47.1","address":"","region":"","costs_rent_comment":"","space_comment_unclear":false,"space_comment_hidden":false,"space_units":"м²","costs_rent":""}],"31":[{"space_unclear":false,"address_hidden":true,"region_hidden":true,"space_comment":"","space_hidden":false,"space":"61","address":"","region":"","costs_property":"","costs_rent_comment":"","space_comment_unclear":false,"space_units":"м²","costs_property_comment":"","costs_rent":""}]},"intro":{"declaration_year":"2015","isnotdeclaration":""}}