{"income":{"5":{"family_comment":"","value":"210154","family":"508656","comment":""},"6":{"family_comment":"","value":"210112","family":"508656","comment":""},"7":{"family_comment":"","value":"","source_name":"","family":"","comment":""},"8":{"family_comment":"","value":"","family":"","comment":""},"9":{"value":"42","comment_unclear":false,"family_comment":"","family":"","comment":"","family_comment_unclear":false},"10":{"family_comment":"","value":"","family":"","comment":""},"11":{"family_comment":"","value":"","family":"","comment":""},"12":{"family_comment":"","value":"","family":"","comment":""},"13":{"family_comment":"","value":"","family":"","comment":""},"14":{"family_comment":"","value":"","family":"","comment":""},"15":{"family_comment":"","value":"","family":"","comment":""},"16":{"family_comment":"","value":"","family":"","comment":""},"17":{"family_comment":"","value":"","family":"","comment":""},"18":{"family_comment":"","value":"","family":"","comment":""},"19":{"value":"","family_comment":"","value_unclear":false,"family_unclear":false,"family":"","comment":""},"20":{"value":"","family_comment":"","value_unclear":false,"comment_hidden":false,"family_comment_hidden":false,"family_unclear":false,"family_comment_unclear":false,"comment_unclear":false,"comment":"","family":""}},"vehicle":{"35":[{"brand_info":"1998 куб. см., 112 кВт","sum_rent_comment":"","brand":"Toyota Rav 4","sum_comment":"","year":"2006","sum_hidden":false,"brand_info_hidden":false,"brand_info_unclear":false,"year_unclear":false,"sum":"","sum_rent":""}]},"id":"vulyk_106_35","banks":{"51":[{"sum_foreign_comment":"","sum_units":"UAH","sum_comment":"Приватбанк","sum_comment_unclear":false,"sum_foreign_comment_hidden":false,"sum_foreign_units":"UAH","sum_comment_hidden":false,"sum":"2874","sum_foreign":""}]},"declaration":{"additional_info_text":"","notfull_lostpages":"","date":"2016-03-25T00:00:00","notfull":"","additional_info":"","url":"http://static.declarations.com.ua/declarations/chosen_ones/judges_batch/2174_koshcheiev_ihor_mykhailovych.pdf"},"liabilities":{"54":{"sum_foreign_comment":"","sum":"","sum_comment":"","sum_comment_unclear":false,"sum_hidden":false,"sum_comment_hidden":false,"sum_foreign":""},"55":{"sum_foreign_comment":"","sum":"","sum_hidden":false,"sum_comment":"","sum_foreign":""},"56":{"sum_foreign_comment":"","sum":"","sum_comment":"","sum_hidden":false,"sum_comment_hidden":false,"sum_unclear":false,"sum_foreign":""},"57":{"sum_foreign_comment":"","sum":"","sum_comment":"","sum_hidden":false,"sum_comment_hidden":false,"sum_foreign":""},"58":{"sum_foreign_comment":"","sum":"","sum_comment":"","sum_hidden":false,"sum_comment_hidden":false,"sum_foreign":""},"59":{"sum_foreign_comment":"","sum":"","sum_comment":"","sum_foreign":""},"60":{"sum_foreign_comment":"","sum":"","sum_comment":"","sum_hidden":false,"sum_comment_hidden":false,"sum_foreign":""},"61":{"sum_foreign_comment":"","sum":"","sum_comment":"","sum_foreign":""},"62":{"sum_foreign_comment":"","sum":"","sum_comment":"","sum_comment_hidden":false,"sum_unclear":false,"sum_foreign":""},"63":{"sum_foreign_comment":"","sum":"","sum_comment":"","sum_foreign":""},"64":{"sum_foreign_comment":"","sum":"","sum_comment":"","sum_foreign":""}},"ft_src":"суддя дніпропетровського апеляційного господарського суду\nДніпропетровська область\nАпеляційний господарський суд\nІгор\nКощеєва Анжеліка Віталіївна\nПодружжя\nКощеєва Вероніка Ігорівна\nДитина\nМихайлович\nКощеєв Ігор Михайлович\nІгор Михайлович Кощеєв\nІгор Кощеєв\nКощеєв Ігор Михайлович\nКощеєв Ігор Михайлович\nКощеєв\nToyota Rav 4\n1998 куб. см., 112 кВт\n2006\nПриватбанк\n2874\n2015\n1998 куб. см., 112 кВт\n2006\nToyota Rav 4\n2874\nПриватбанк\n.1999\n174.5\n132\n16.7\nКощеєв Ігор Михайлович\nІгор Михайлович Кощеєв\nІгор Кощеєв\nКощеєв Ігор Михайлович\nКощеєв Ігор Михайлович\nПодружжя\nКощеєва Анжеліка Віталіївна\nДитина\nКощеєва Вероніка Ігорівна\nІгор\nКощеєв\nДніпропетровська область\nАпеляційний господарський суд\nсуддя дніпропетровського апеляційного господарського суду\nМихайлович\n210112\n508656\n210154\n508656\n42\n2015\n.1999\n132\n174.5\n16.7\nКощеєва Анжеліка Віталіївна\nПодружжя\nКощеєва Вероніка Ігорівна\nДитина\nМихайлович\nКощеєв\nІгор\nКощеєв Ігор Михайлович\nІгор Михайлович Кощеєв\nІгор Кощеєв\nКощеєв Ігор Михайлович\nДніпропетровська область\nАпеляційний господарський суд\nсуддя дніпропетровського апеляційного господарського суду\nКощеєв Ігор Михайлович\n508656\n210112\n42\n508656\n210154\n2006\nToyota Rav 4\n1998 куб. см., 112 кВт\n42\n508656\n210154\n508656\n210112\n132\n174.5\n16.7\n.1999\nПриватбанк\n2874\n2015","general":{"inn":"","name":"Ігор","inn_unclear":false,"family":[{"inn":"","inn_hidden":true,"relations_unclear":false,"relations_hidden":false,"relations_other":"","relations":"Подружжя","name_hidden":true,"family_name":"Кощеєва Анжеліка Віталіївна","name_unclear":false},{"inn":"","relations":"Дитина","relations_unclear":false,"family_name":"Кощеєва Вероніка Ігорівна","inn_hidden":false,"relations_other":"","name_hidden":false,"name_unclear":false}],"inn_hidden":true,"family_raw":"","last_name":"Кощеєв","post":{"region_unclear":false,"region":"Дніпропетровська область","post":"суддя дніпропетровського апеляційного господарського суду","office":"Апеляційний господарський суд","office_unclear":false,"post_hidden":false},"full_name":"Кощеєв Ігор Михайлович","addresses":[{"place_district":"","place_city_hidden":true,"place_city":"","place_city_type_hidden":true,"place_district_hidden":true,"place_city_type":"","place_address_hidden":true,"place_address":"","place_hidden":true,"place":""}],"patronymic":"Михайлович","full_name_suggest":{"output":"Кощеєв Ігор Михайлович","input":["Кощеєв Ігор Михайлович","Ігор Михайлович Кощеєв","Ігор Кощеєв"]},"name_unclear":false},"source":"VULYK","estate":{"29":[{"region_unclear":false,"costs_property_comment":"","address_hidden":true,"region_hidden":true,"space_comment":"","space":".1999","address":"","costs_rent_comment_unclear":false,"region":"","costs_property":"","costs_rent_comment":"","space_comment_unclear":false,"address_unclear":false,"space_units":"га","space_units_unclear":false,"costs_rent":""}],"30":[{"space_unclear":false,"address_hidden":true,"region_hidden":true,"space_comment":"","space_hidden":false,"space":"174.5","address":"","region":"","costs_property":"","costs_rent_comment":"","space_comment_unclear":false,"space_units":"м²","costs_property_comment":"","costs_rent":""}],"31":[{"space_unclear":false,"address_hidden":true,"region_hidden":true,"space_comment":"","space_hidden":false,"space":"132","address":"","region":"","costs_property":"","costs_rent_comment":"","space_comment_unclear":false,"space_units":"м²","costs_property_comment":"","costs_rent":""}],"34":[{"costs_rent":"","costs_property":"","costs_rent_comment":"","address_hidden":true,"region_hidden":true,"space_comment":"","costs_property_comment":"","space_units":"м²","space":"16.7","address":""}]},"intro":{"declaration_year":"2015","isnotdeclaration":""}}