{"income":{"5":{"family_comment":"","value":"256493","family":"14400","comment":""},"6":{"family_comment":"","value":"254978","family":"","comment":""},"7":{"family_comment":"","value":"869","source_name":"Приватний вищій навчальний заклад Дніпропетровський університет ім. Альфреда Нобеля","family":"","comment":""},"8":{"family_comment":"","value":"","family":"","comment":""},"9":{"value":"646","comment_unclear":false,"family_comment":"","family":"","comment":"","family_comment_unclear":false},"10":{"family_comment":"","value":"","family":"","comment":""},"11":{"family_comment":"","value":"","family":"","comment":""},"12":{"family_comment":"","value":"","family":"","comment":""},"13":{"family_comment":"","value":"","family":"","comment":""},"14":{"family_comment":"","value":"","family":"","comment":""},"15":{"family_comment":"","value":"","family":"","comment":""},"16":{"family_comment":"","value":"","family":"","comment":""},"17":{"family_comment":"","value":"","family":"","comment":""},"18":{"family_comment":"","value":"","family":"","comment":""},"19":{"value":"","family_comment":"","value_unclear":false,"family_unclear":false,"family":"","comment":""},"20":{"value":"","family_comment":"пенсія","value_unclear":false,"comment_hidden":false,"family_comment_hidden":false,"family_unclear":false,"family_comment_unclear":false,"comment_unclear":false,"comment":"","family":"14400"}},"vehicle":{"35":[{"brand_info":"1390 куб. см.","sum_rent_comment":"","brand":"Volkswagen Golf V","sum_comment":"","year":"2004","sum_hidden":false,"brand_info_hidden":false,"brand_info_unclear":false,"year_unclear":false,"sum":"","sum_rent":""}]},"id":"vulyk_106_27","banks":{"45":[{"sum_foreign_comment":"","sum_units":"UAH","sum_comment":"","sum_foreign_comment_hidden":false,"sum_hidden":false,"sum_foreign_units":"UAH","sum_comment_hidden":false,"sum":"2622","sum_foreign":""}]},"declaration":{"additional_info_text":"","notfull_lostpages":"","date":"2016-03-29T00:00:00","notfull":"","additional_info":"","url":"http://static.declarations.com.ua/declarations/chosen_ones/judges_batch/2166_vechirko_ihor_oleksandrovych.pdf"},"liabilities":{"54":{"sum_foreign_comment":"","sum":"","sum_comment":"","sum_comment_unclear":false,"sum_hidden":false,"sum_comment_hidden":false,"sum_foreign":""},"55":{"sum_foreign_comment":"","sum":"","sum_hidden":false,"sum_comment":"","sum_foreign":""},"56":{"sum_foreign_comment":"","sum":"","sum_comment":"","sum_hidden":false,"sum_comment_hidden":false,"sum_unclear":false,"sum_foreign":""},"57":{"sum_foreign_comment":"","sum":"","sum_comment":"","sum_hidden":false,"sum_comment_hidden":false,"sum_foreign":""},"58":{"sum_foreign_comment":"","sum":"","sum_comment":"","sum_hidden":false,"sum_comment_hidden":false,"sum_foreign":""},"59":{"sum_foreign_comment":"","sum":"","sum_comment":"","sum_foreign":""},"60":{"sum_foreign_comment":"","sum":"","sum_comment":"","sum_hidden":false,"sum_comment_hidden":false,"sum_foreign":""},"61":{"sum_foreign_comment":"","sum":"","sum_comment":"","sum_foreign":""},"62":{"sum_foreign_comment":"","sum":"","sum_comment":"","sum_comment_hidden":false,"sum_unclear":false,"sum_foreign":""},"63":{"sum_foreign_comment":"","sum":"","sum_comment":"","sum_foreign":""},"64":{"sum_foreign_comment":"","sum":"","sum_comment":"","sum_foreign":""}},"ft_src":"суддя дніпропетровського апеляційного господарського суду\nДніпропетровська область\nАпеляційний господарський суд\nІгор\nВечірко Т. В\nПодружжя\nВечірко А. І\nДитина\nОлександрович\nВечірко Ігор Олександрович\nІгор Олександрович Вечірко\nІгор Вечірко\nВечірко Ігор Олександрович\nВечірко Ігор Олександрович\nВечірко\nVolkswagen Golf V\n1390 куб. см.\n2004\n2622\n2015\n1390 куб. см.\n2004\nVolkswagen Golf V\n2622\n71.34\n37.1\n3100\n71.34\n37.1\n61\nВечірко Ігор Олександрович\nІгор Олександрович Вечірко\nІгор Вечірко\nВечірко Ігор Олександрович\nВечірко Ігор Олександрович\nПодружжя\nВечірко Т. В\nДитина\nВечірко А. І\nІгор\nВечірко\nДніпропетровська область\nАпеляційний господарський суд\nсуддя дніпропетровського апеляційного господарського суду\nОлександрович\n869\nПриватний вищій навчальний заклад Дніпропетровський університет ім. Альфреда Нобеля\n254978\n14400\nпенсія\n256493\n14400\n646\n2015\n3100\n61\n71.34\n37.1\n71.34\n37.1\nВечірко Т. В\nПодружжя\nВечірко А. І\nДитина\nОлександрович\nВечірко\nІгор\nВечірко Ігор Олександрович\nІгор Олександрович Вечірко\nІгор Вечірко\nВечірко Ігор Олександрович\nДніпропетровська область\nАпеляційний господарський суд\nсуддя дніпропетровського апеляційного господарського суду\nВечірко Ігор Олександрович\n254978\n646\n869\nПриватний вищій навчальний заклад Дніпропетровський університет ім. Альфреда Нобеля\n14400\n256493\n14400\nпенсія\n2004\nVolkswagen Golf V\n1390 куб. см.\n646\nпенсія\n14400\n14400\n256493\nПриватний вищій навчальний заклад Дніпропетровський університет ім. Альфреда Нобеля\n869\n254978\n71.34\n37.1\n71.34\n37.1\n61\n3100\n2622\n2015","general":{"inn":"","name":"Ігор","inn_unclear":false,"family":[{"inn":"","inn_hidden":true,"relations_unclear":false,"relations_hidden":false,"relations_other":"","relations":"Подружжя","name_hidden":true,"family_name":"Вечірко Т. В","name_unclear":false},{"inn":"","relations":"Дитина","relations_unclear":false,"family_name":"Вечірко А. І","inn_hidden":false,"relations_other":"","name_hidden":false,"name_unclear":false}],"inn_hidden":true,"family_raw":"","last_name":"Вечірко","post":{"region_unclear":false,"region":"Дніпропетровська область","post":"суддя дніпропетровського апеляційного господарського суду","office":"Апеляційний господарський суд","office_unclear":false,"post_hidden":false},"full_name":"Вечірко Ігор Олександрович","addresses":[{"place_district":"","place_city_hidden":true,"place_city":"","place_city_type_hidden":true,"place_district_hidden":true,"place_city_type":"","place_address_hidden":true,"place_address":"","place_hidden":true,"place":""}],"patronymic":"Олександрович","full_name_suggest":{"output":"Вечірко Ігор Олександрович","input":["Вечірко Ігор Олександрович","Ігор Олександрович Вечірко","Ігор Вечірко"]},"name_unclear":false},"source":"VULYK","estate":{"25":[{"costs":"","costs_comment":"","address_hidden":true,"region_hidden":true,"space_comment":"","space":"71.34","address":"","region":"","costs_rent_comment":"","space_comment_unclear":false,"space_units":"м²","costs_rent":""},{"space_unclear":false,"costs":"","costs_comment":"","address_hidden":false,"region_hidden":false,"space_comment":"","space":"37.1","address":"","region":"","costs_rent_comment":"","space_comment_unclear":false,"space_units":"м²","costs_rent":""}],"26":[{"costs_rent":"","region":"","costs":"","costs_rent_comment":"","costs_comment":"","address_hidden":true,"region_hidden":true,"space_comment":"","space_units":"м²","space":"","address":""}],"27":[{"space_hidden":false,"costs":"","costs_comment":"","address_hidden":true,"region_hidden":true,"space_comment":"","space":"","address":"","region":"","costs_rent_comment":"","space_units":"м²","costs_rent":""}],"29":[{"region_unclear":false,"costs_property_comment":"","address_hidden":true,"region_hidden":true,"space_comment":"","space":"3100","address":"","costs_rent_comment_unclear":false,"region":"","costs_property":"","costs_rent_comment":"","space_comment_unclear":false,"address_unclear":false,"space_units":"м²","space_units_unclear":false,"costs_rent":""}],"31":[{"space_unclear":false,"address_hidden":true,"region_hidden":true,"space_comment":"","space_hidden":false,"space":"71.34","address":"","region":"","costs_property":"","costs_rent_comment":"","space_comment_unclear":false,"space_units":"м²","costs_property_comment":"","costs_rent":""},{"costs_rent":"","region":"","costs_property":"","costs_rent_comment":"","space_comment_unclear":false,"region_hidden":false,"space_comment":"","costs_property_comment":"","space_units":"м²","space":"37.1","address":""}],"32":[{"costs_rent":"","costs_property":"","costs_rent_comment":"","address_hidden":true,"region_hidden":true,"space_comment":"","costs_property_comment":"","space_units":"м²","space":"61","address":""}]},"intro":{"declaration_year":"2015","isnotdeclaration":""}}