{"income":{"5":{"value":"256113","family_comment":"","value_unclear":false,"family_hidden":false,"value_hidden":false,"family_unclear":false,"family":"35","comment":""},"6":{"value":"243890","value_unclear":false,"family_hidden":false,"value_hidden":false,"family_comment":"","comment_unclear":false,"comment":"","family":""},"7":{"value":"","value_hidden":false,"family_comment":"","source_name":"","family":"","comment":"","source_name_hidden":false},"8":{"family_comment":"","value":"","family":"","comment":""},"9":{"family_comment":"","value":"43","comment_unclear":false,"family":"35","comment":""},"10":{"family_comment":"","value":"12180","value_unclear":false,"family":"","comment":""},"11":{"family_comment":"","value":"","family":"","comment":""},"12":{"family_comment":"","value":"","family":"","comment":""},"13":{"family_comment":"","value":"","family":"","comment":""},"14":{"family_comment":"","value":"","family":"","comment":""},"15":{"family_comment":"","value":"","family":"","comment":""},"16":{"family_comment":"","value":"","family":"","comment":""},"17":{"family_comment":"","value":"","family":"","comment":""},"18":{"family_comment":"","value":"","family":"","comment":""},"19":{"value":"","value_unclear":false,"comment_hidden":false,"family_hidden":false,"value_hidden":false,"family_comment":"","family_comment_hidden":false,"comment":"","family":""},"20":{"value":"","family_comment":"","value_unclear":false,"family_hidden":false,"value_hidden":false,"family_unclear":false,"comment_unclear":false,"comment":"","family":""}},"vehicle":{"35":[{"brand_info":"1988 куб. см. (150 к. с.) 4555 мм","sum_rent_comment":"","year":"2004","brand_info_hidden":false,"brand_info_unclear":false,"year_unclear":false,"sum_rent":"","sum":"","brand":"Honda CR-V","sum_comment":"","brand_unclear":false,"brand_hidden":false}],"40":[{"brand_info":"1999 куб. см., 147 к. с., 4690 мм","sum_rent_comment":"","brand":"Mazda 6","sum_comment":"","brand_unclear":false,"year":"2006","brand_hidden":false,"brand_info_unclear":false,"year_unclear":false,"sum":"","sum_rent":""}]},"id":"vulyk_65_82","banks":{"45":[{"sum_foreign_comment":"","sum_units":"USD","sum_comment":"","sum_comment_unclear":false,"sum_hidden":false,"sum_foreign_units":"UAH","sum_units_unclear":false,"sum":"391.23","sum_unclear":false,"sum_foreign":""},{"sum_foreign_comment":"","sum_units":"UAH","sum_comment":"","sum_foreign_units":"UAH","sum":"13929","sum_unclear":false,"sum_foreign":""}],"51":[{"sum_foreign_comment":"","sum_units":"EUR","sum_comment":"","sum_comment_unclear":false,"sum_foreign_units":"UAH","sum":"1165.59","sum_foreign":""},{"sum_foreign_comment":"","sum_units":"UAH","sum_comment":"","sum_foreign_units":"UAH","sum":"2279","sum_foreign":""},{"sum_foreign_comment":"","sum_units":"UAH","sum_comment":"","sum_foreign_units":"UAH","sum":"3828","sum_foreign":""},{"sum_foreign_comment":"","sum_units":"USD","sum_comment":"","sum_foreign_units":"UAH","sum":"55.3","sum_foreign":""}]},"declaration":{"additional_info_text":"","notfull_lostpages":"","date":"2015-03-27T00:00:00","notfull":"","additional_info":"","url":"http://static.declarations.com.ua/declarations/chosen_ones/mega_batch/kniazkov_valerii_volodymyrovych.pdf"},"liabilities":{"54":{"sum_foreign_comment":"","sum":"","sum_comment":"","sum_comment_unclear":false,"sum_hidden":false,"sum_comment_hidden":false,"sum_foreign":""},"55":{"sum_foreign_comment":"","sum":"","sum_comment":"","sum_foreign":""},"56":{"sum_foreign_comment":"","sum":"","sum_comment":"","sum_unclear":false,"sum_foreign":""},"57":{"sum_foreign_comment":"","sum":"","sum_comment":"","sum_comment_unclear":false,"sum_unclear":false,"sum_foreign":""},"58":{"sum_foreign_comment":"","sum":"","sum_comment":"","sum_comment_unclear":false,"sum_unclear":false,"sum_foreign":""},"59":{"sum_foreign_comment":"","sum":"","sum_comment":"","sum_foreign":""},"60":{"sum_foreign_comment":"","sum":"","sum_comment":"","sum_comment_unclear":false,"sum_foreign":""},"61":{"sum_foreign_comment":"","sum":"","sum_comment":"","sum_foreign":""},"62":{"sum_foreign_comment":"","sum":"","sum_comment":"","sum_foreign":""},"63":{"sum_foreign_comment":"","sum":"","sum_comment":"","sum_foreign":""},"64":{"sum_foreign_comment":"","sum":"","sum_comment":"","sum_unclear":false,"sum_foreign":""}},"ft_src":"Мешкає Київ, Зареєстрований М. Донецьк\nгосподарський суд м. києва, суддя\nм. Київ\nГосподарський місцевий суд\nВалерій\nКнязькова Т. В\nПодружжя\nВолодимирович\nКнязьков\nКнязьков Валерій Володимирович\nКнязьков Валерій Володимирович\nВалерій Володимирович Князьков\nВалерій Князьков\nКнязьков Валерій Володимирович\n1988 куб. см. (150 к. с.) 4555 мм\nHonda CR-V\n2004\nMazda 6\n1999 куб. см., 147 к. с., 4690 мм\n2006\n1165.59\n2279\n3828\n55.3\n391.23\n13929\n2014\n1988 куб. см. (150 к. с.) 4555 мм\nHonda CR-V\n2004\n1999 куб. см., 147 к. с., 4690 мм\n2006\nMazda 6\n391.23\n13929\n1165.59\n2279\n3828\n55.3\nвласність\n36.4\nДонецька область\nДонецьк\nвласність\n21.9\nДонецька область\nДонецьк\nвласність\n49\nДонецька область\nДонецьк\n21.9\nвласність\nДонецька область\nДонецьк\n125.2\nкористування\nм. Київ\nГосподарський місцевий суд\nм. Київ\nгосподарський суд м. києва, суддя\nКнязьков Валерій Володимирович\nВалерій Володимирович Князьков\nВалерій Князьков\nКнязьков Валерій Володимирович\nВалерій\nПодружжя\nКнязькова Т. В\nКнязьков Валерій Володимирович\nКнязьков\nВолодимирович\nМешкає Київ, Зареєстрований М. Донецьк\n243890\n256113\n35\n12180\n43\n35\n2014\nвласність\nДонецьк\nДонецька область\n36.4\nвласність\nДонецьк\nДонецька область\n21.9\nвласність\nДонецька область\nДонецьк\n49\nвласність\nДонецька область\nДонецьк\n21.9\nкористування\nм. Київ\n125.2\nКнязькова Т. В\nПодружжя\nВолодимирович\nКнязьков\nВалерій\nКнязьков Валерій Володимирович\nВалерій Володимирович Князьков\nВалерій Князьков\nКнязьков Валерій Володимирович\nМешкає Київ, Зареєстрований М. Донецьк\nм. Київ\nГосподарський місцевий суд\nгосподарський суд м. києва, суддя\nКнязьков Валерій Володимирович\n243890\n12180\n35\n256113\n35\n43\n2004\nHonda CR-V\n1988 куб. см. (150 к. с.) 4555 мм\n2006\nMazda 6\n1999 куб. см., 147 к. с., 4690 мм\n12180\n256113\n35\n35\n43\n243890\nДонецьк\nДонецька область\nвласність\n36.4\nДонецьк\nДонецька область\nвласність\n21.9\nДонецьк\nДонецька область\nвласність\n49\n21.9\nДонецька область\nДонецьк\nвласність\nм. Київ\n125.2\nкористування\n391.23\n13929\n1165.59\n2279\n3828\n55.3\n2014","general":{"name_hidden":false,"name":"Валерій","last_name_hidden":false,"inn":"","family":[{"inn":"","inn_hidden":true,"inn_unclear":false,"relations_hidden":false,"relations_other":"","relations":"Подружжя","name_hidden":false,"family_name":"Князькова Т. В","name_unclear":false}],"patronymic":"Володимирович","inn_hidden":true,"family_raw":"","inn_unclear":false,"post":{"post_unclear":false,"region_unclear":false,"post":"господарський суд м. києва, суддя","office":"Господарський місцевий суд","region":"м. Київ","post_hidden":false,"office_hidden":false,"office_unclear":false,"region_hidden":false},"last_name_unclear":false,"full_name":"Князьков Валерій Володимирович","addresses":[{"place_district":"","place_address_hidden":true,"place_city":"Мешкає Київ, Зареєстрований М. Донецьк","place_city_type_hidden":true,"place_district_hidden":true,"place_city_type":"","place_city_hidden":true,"place_address_unclear":false,"place_address":"","place_hidden":true,"place":""}],"last_name":"Князьков","patronymic_hidden":false,"full_name_suggest":{"output":"Князьков Валерій Володимирович","input":["Князьков Валерій Володимирович","Валерій Володимирович Князьков","Валерій Князьков"]},"name_unclear":false},"source":"VULYK","estate":{"25":[{"space_unclear":false,"costs":"","costs_comment":"власність","address_hidden":false,"region_hidden":false,"space_comment":"","space_hidden":false,"space":"21.9","address":"Донецьк","costs_rent_comment_unclear":false,"region":"Донецька область","address_unclear":false,"costs_rent_comment":"","space_comment_unclear":false,"space_units":"м²","space_units_hidden":false,"costs_rent":""},{"space_hidden":false,"costs":"","costs_comment":"користування","address_hidden":false,"region_hidden":false,"space_comment":"","space_unclear":false,"space":"125.2","address":"","region":"м. Київ","costs_rent_comment":"","space_units":"м²","costs_rent":""}],"31":[{"space_unclear":false,"address_hidden":false,"region_hidden":false,"space_comment":"","space":"36.4","address":"Донецьк","region":"Донецька область","costs_property":"","costs_rent_comment":"","space_comment_unclear":false,"space_units":"м²","costs_property_comment":"власність","costs_rent":""},{"space_unclear":false,"address_hidden":false,"region_hidden":false,"space_comment":"","space":"21.9","address":"Донецьк","region":"Донецька область","costs_property":"","costs_rent_comment":"","space_units":"м²","costs_property_comment":"власність","costs_rent":""},{"costs_rent":"","space_unclear":false,"region":"Донецька область","costs_property":"","costs_rent_comment":"","address_hidden":false,"space_comment":"","costs_property_comment":"власність","space_units":"м²","space":"49","address":"Донецьк"}]},"intro":{"declaration_year":"2014","isnotdeclaration":"","declaration_year_hidden":false}}