{"income":{"5":{"value":"270935","family_comment":"","comment_unclear":false,"family_unclear":false,"family":"1421356","comment":""},"6":{"family_comment":"","value":"268949","family":"","comment":""},"7":{"source_name_unclear":false,"value":"","comment_unclear":false,"family_comment":"","source_name":"","family":"","comment":""},"8":{"family_comment":"","value":"","family":"","comment":""},"9":{"family_comment":"","value":"1810","family":"","comment":""},"10":{"family_comment":"","value":"","family":"","comment":""},"11":{"family_comment":"","value":"","family":"","comment":""},"12":{"family_comment":"","value":"","family":"","comment":""},"13":{"family_comment":"","value":"","family":"","comment":""},"14":{"family_comment":"","value":"","family":"","comment":""},"15":{"family_comment":"","value":"","family":"","comment":""},"16":{"family_comment":"","family_unclear":false,"value":"","family":"","comment":""},"17":{"family_comment":"","value":"","family":"1421356","comment":""},"18":{"family_comment":"","value":"","family":"","comment":""},"19":{"family_comment":"","value":"","family":"","comment":""},"20":{"value":"31336","family_comment":"","comment_unclear":false,"family_unclear":false,"family":"","comment":"Сума кредитного ліміту: 15060, 16100","family_comment_unclear":false}},"vehicle":{"35":[{"brand_info":"2362 куб. см.","sum_rent_comment":"","brand":"Toyota Rav 4","sum_comment":"","brand_unclear":false,"year":"2006","brand_info_unclear":false,"sum":"","sum_rent":""},{"brand_info":"1999 куб. см.","sum":"","brand":"Mazda 6","sum_comment":"","brand_unclear":false,"year":"2005","brand_hidden":false,"sum_rent_comment":"","sum_rent":""}]},"id":"vulyk_107_63","declaration":{"additional_info_text":"","notfull_lostpages":"","date":"2016-03-28T00:00:00","notfull":"","additional_info":"","url":"http://static.declarations.com.ua/declarations/chosen_ones/judges_batch/2042_rybalka_volodymyr_hryhorovych.pdf"},"liabilities":{"54":{"sum_foreign_comment":"","sum":"","sum_comment":"","sum_comment_unclear":false,"sum_comment_hidden":false,"sum_foreign":""},"55":{"sum_foreign_comment":"","sum":"","sum_comment":"","sum_foreign":""},"56":{"sum_foreign_comment":"","sum":"","sum_comment":"","sum_unclear":false,"sum_foreign":""},"57":{"sum_foreign_comment":"","sum":"","sum_comment":"","sum_comment_unclear":false,"sum_foreign":""},"58":{"sum_foreign_comment":"","sum":"","sum_comment":"","sum_comment_unclear":false,"sum_unclear":false,"sum_foreign":""},"59":{"sum_foreign_comment":"","sum":"","sum_comment":"","sum_unclear":false,"sum_foreign":""},"60":{"sum_foreign_comment":"","sum":"","sum_comment":"","sum_comment_unclear":false,"sum_comment_hidden":false,"sum_foreign":""},"61":{"sum_foreign_comment":"","sum":"","sum_comment":"","sum_foreign":""},"62":{"sum_foreign_comment":"","sum":"","sum_comment":"","sum_foreign":""},"63":{"sum_foreign_comment":"","sum":"","sum_comment":"","sum_foreign":""},"64":{"sum_foreign_comment":"","sum":"","sum_comment":"","sum_foreign":""}},"ft_src":"Рибалка Володимир Григорович\nзаступник голови апеляційного суду сумської області\nСумська область\nЗагальний апеляційний суд\nВолодимир\nРибалка К. Д\nПодружжя\nРибалка Володимир Григорович\nВолодимир Григорович Рибалка\nВолодимир Рибалка\nРибалка Володимир Григорович\nРибалка\nГригорович\n2006\nToyota Rav 4\n2362 куб. см.\nMazda 6\n1999 куб. см.\n2005\n600\n341\n41\n47\n354\n26\n7\n54\n2015\n268949\n1810\n1421356\n270935\n1421356\nСума кредитного ліміту: 15060, 16100\n31336\n2362 куб. см.\n2006\nToyota Rav 4\n1999 куб. см.\nMazda 6\n2005\n2015\nРибалка\nПодружжя\nРибалка К. Д\nРибалка Володимир Григорович\nВолодимир Григорович Рибалка\nВолодимир Рибалка\nРибалка Володимир Григорович\nВолодимир\nГригорович\nРибалка Володимир Григорович\nЗагальний апеляційний суд\nзаступник голови апеляційного суду сумської області\nСумська область\n268949\n31336\nСума кредитного ліміту: 15060, 16100\n1421356\n270935\n1421356\n1810\n600\n341\n354\n41\n47\n26\n7\n54\nРибалка К. Д\nПодружжя\nРибалка\nГригорович\nзаступник голови апеляційного суду сумської області\nСумська область\nЗагальний апеляційний суд\nРибалка Володимир Григорович\nРибалка Володимир Григорович\nВолодимир Григорович Рибалка\nВолодимир Рибалка\nРибалка Володимир Григорович\nВолодимир\n2006\n2362 куб. см.\nToyota Rav 4\nMazda 6\n1999 куб. см.\n2005\n1810\nСума кредитного ліміту: 15060, 16100\n31336\n270935\n1421356\n1421356\n268949\n41\n47\n354\n600\n341\n26\n7\n54\n2015","general":{"inn":"","inn_hidden":true,"last_name":"Рибалка","post":{"post_unclear":false,"office":"Загальний апеляційний суд","post":"заступник голови апеляційного суду сумської області","region":"Сумська область"},"name":"Володимир","full_name":"Рибалка Володимир Григорович","family_raw":"","addresses":[{"place_district":"","place_city_hidden":true,"place_city":"","place_city_type_hidden":true,"place_district_hidden":true,"place_city_type":"","place_address_hidden":true,"place_address":"","place_hidden":true,"place":""}],"family":[{"inn":"","relations":"Подружжя","relations_other":"","inn_hidden":true,"family_name":"Рибалка К. Д","name_hidden":true,"name_unclear":false}],"full_name_suggest":{"output":"Рибалка Володимир Григорович","input":["Рибалка Володимир Григорович","Володимир Григорович Рибалка","Володимир Рибалка"]},"patronymic":"Григорович"},"source":"VULYK","estate":{"29":[{"address_hidden":true,"region_hidden":true,"space_comment":"","space":"600","address":"","region":"","costs_property":"","costs_rent_comment":"","costs_rent_hidden":false,"space_units":"м²","costs_property_comment":"","costs_rent":""},{"costs_rent":"","region":"","costs_property":"","costs_rent_comment":"","costs_rent_hidden":false,"region_hidden":false,"space_comment":"","costs_property_comment":"","space_units":"м²","space":"341","address":""}],"30":[{"address_hidden":true,"region_hidden":true,"space_comment":"","space":"354","address":"","region":"","costs_property":"","costs_rent_comment":"","space_comment_unclear":false,"space_units":"м²","costs_property_comment":"","costs_rent":""}],"31":[{"space_unclear":false,"address_hidden":true,"region_hidden":true,"space_comment":"","space_hidden":false,"space":"41","address":"","region":"","costs_property":"","costs_rent_comment":"","space_comment_unclear":false,"space_units":"м²","costs_property_comment":"","costs_rent":""},{"costs_rent":"","costs_property":"","costs_rent_comment":"","region_hidden":false,"space_comment":"","costs_property_comment":"","space_units":"м²","space":"47","address":""}],"32":[{"costs_rent":"","space_hidden":false,"costs_property":"","costs_rent_comment":"","address_hidden":true,"region_hidden":true,"space_comment":"","costs_property_comment":"","space_units":"м²","space":"54","address":""}],"34":[{"costs_rent":"","costs_property":"","costs_rent_comment":"","address_hidden":true,"region_hidden":true,"space_comment":"","costs_property_comment":"","space_units":"м²","space":"26","address":""},{"costs_rent":"","costs_property":"","costs_rent_comment":"","space_comment":"","costs_property_comment":"","space_units":"м²","space":"7","address":""}]},"intro":{"declaration_year":"2015","isnotdeclaration":""}}