{"income":{"5":{"value":"225432.01","comment_hidden":false,"family_comment":"","family":"","comment":"","family_comment_hidden":false},"6":{"value":"225164.93","family_comment":"","comment_hidden":false,"family_hidden":false,"family_unclear":false,"family_comment_hidden":false,"comment":"","family":""},"7":{"value":"","comment_hidden":false,"family_comment_hidden":false,"family_comment":"","source_name":"","family":"","comment":"","source_name_hidden":false},"8":{"family_comment":"","value":"","family":"","comment":""},"9":{"value":"219.14","family_comment":"","value_unclear":false,"family_unclear":false,"comment_unclear":false,"comment":"","family":""},"10":{"family_comment":"","family_unclear":false,"value":"","family":"","comment":""},"11":{"family_comment":"","value":"47.94","family":"","comment":""},"12":{"family_comment":"","value":"","family":"","comment":""},"13":{"family_comment":"","value":"","family":"","comment":""},"14":{"family_comment":"","value":"","family":"","comment":""},"15":{"family_comment":"","value":"","comment_unclear":false,"family":"","comment":""},"16":{"family_comment":"","value":"","comment_unclear":false,"family":"","comment":""},"17":{"family_comment":"","value":"","family":"","comment":""},"18":{"family_comment":"","value":"","family":"","comment":""},"19":{"family_comment":"","value":"","family":"","comment":""},"20":{"value":"","family_comment":"","value_unclear":false,"family_unclear":false,"family_comment_unclear":false,"family_comment_hidden":false,"comment":"","family":""}},"vehicle":{"35":[{"brand_info":"1600 куб. см., 102 к.с.","sum_rent_comment":"","brand":"Seat Toledo","sum_comment":"","brand_unclear":false,"year":"2008","sum_hidden":false,"brand_info_unclear":false,"sum":"","sum_rent":""}]},"id":"vulyk_73_43","banks":{"45":[{"sum_foreign_comment":"","sum_units":"UAH","sum_comment":"","sum_comment_unclear":false,"sum_hidden":false,"sum_foreign_units":"UAH","sum_comment_hidden":false,"sum_unclear":false,"sum":"3888.93","sum_foreign":""}]},"declaration":{"additional_info_text":"","notfull_lostpages":"","date":"2014-03-31T00:00:00","notfull":"","additional_info":"","url":"http://static.declarations.com.ua/declarations/chosen_ones/judges_batch/1396_hriaznov_vasyl_volodymyrovych.pdf"},"liabilities":{"54":{"sum_foreign_comment":"","sum_foreign_hidden":false,"sum_comment":"","sum_comment_unclear":false,"sum_hidden":false,"sum_comment_hidden":false,"sum_unclear":false,"sum":"298.71","sum_foreign":""},"55":{"sum_foreign_comment":"","sum_comment_hidden":false,"sum":"","sum_comment":"","sum_foreign":""},"56":{"sum_foreign_comment":"","sum":"16000","sum_comment":"","sum_comment_unclear":false,"sum_foreign":""},"57":{"sum_foreign_comment":"","sum":"","sum_comment":"","sum_hidden":false,"sum_comment_hidden":false,"sum_unclear":false,"sum_foreign":""},"58":{"sum_foreign_comment":"","sum":"","sum_comment":"","sum_hidden":false,"sum_comment_hidden":false,"sum_foreign":""},"59":{"sum_foreign_comment":"","sum":"","sum_comment":"","sum_comment_unclear":false,"sum_unclear":false,"sum_foreign":""},"60":{"sum_foreign_comment":"","sum":"","sum_comment":"","sum_hidden":false,"sum_comment_hidden":false,"sum_unclear":false,"sum_foreign":""},"61":{"sum_foreign_comment":"","sum":"","sum_comment":"","sum_foreign":""},"62":{"sum_foreign_comment":"","sum":"","sum_comment":"","sum_foreign":""},"63":{"sum_foreign_comment":"","sum":"","sum_comment":"","sum_hidden":false,"sum_comment_hidden":false,"sum_foreign":""},"64":{"sum_foreign_comment":"","sum":"","sum_comment":"","sum_foreign":""}},"ft_src":"298.71\n16000\nсуддя рівненського апеляційного господарського суду\nРівненська область\nАпеляційний господарський суд\nВасиль\nПодружжя\nДитина\nДитина\nВолодимирович\nГрязнов Василь Володимирович\nВасиль Володимирович Грязнов\nВасиль Грязнов\nГрязнов Василь Володимирович\nГрязнов\nГрязнов Василь Володимирович\nSeat Toledo\n1600 куб. см., 102 к.с.\n2008\n20\n58.5\n3888.93\n2013\n1600 куб. см., 102 к.с.\nSeat Toledo\n2008\n2013\nГрязнов Василь Володимирович\nВасиль Володимирович Грязнов\nВасиль Грязнов\nГрязнов Василь Володимирович\nВасиль\nПодружжя\nДитина\nДитина\nГрязнов Василь Володимирович\nВолодимирович\nАпеляційний господарський суд\nРівненська область\nсуддя рівненського апеляційного господарського суду\nГрязнов\n298.71\n16000\n225164.93\n225432.01\n219.14\n47.94\n20\n58.5\n3888.93\n16000\n298.71\n225164.93\n219.14\n47.94\n225432.01\nПодружжя\nДитина\nДитина\nВолодимирович\nГрязнов\nВасиль\nГрязнов Василь Володимирович\nВасиль Володимирович Грязнов\nВасиль Грязнов\nГрязнов Василь Володимирович\nРівненська область\nАпеляційний господарський суд\nсуддя рівненського апеляційного господарського суду\nГрязнов Василь Володимирович\n2008\n1600 куб. см., 102 к.с.\nSeat Toledo\n47.94\n219.14\n225432.01\n225164.93\n58.5\n20\n3888.93\n2013","general":{"inn":"","name":"Василь","family":[{"inn":"","relations":"Подружжя","inn_unclear":false,"relations_hidden":false,"inn_hidden":true,"relations_other":"","name_hidden":true,"family_name":"","name_unclear":false},{"inn":"","relations":"Дитина","inn_unclear":false,"family_name":"","inn_hidden":false,"relations_other":"","name_hidden":true,"name_unclear":false},{"inn":"","relations":"Дитина","relations_other":"","inn_hidden":false,"family_name":"","name_hidden":true,"name_unclear":false}],"patronymic":"Володимирович","inn_hidden":true,"family_raw":"","last_name":"Грязнов","post":{"post_unclear":false,"region_unclear":false,"post":"суддя рівненського апеляційного господарського суду","office":"Апеляційний господарський суд","region":"Рівненська область","post_hidden":false,"office_hidden":false,"office_unclear":false,"region_hidden":false},"last_name_unclear":false,"full_name":"Грязнов Василь Володимирович","addresses":[{"place_district":"","place_city_hidden":true,"place_city":"","place_city_type_hidden":false,"place_district_hidden":true,"place_city_type":"","place_address_hidden":true,"place_address":"","place_hidden":false,"place":""}],"full_name_suggest":{"output":"Грязнов Василь Володимирович","input":["Грязнов Василь Володимирович","Василь Володимирович Грязнов","Василь Грязнов"]},"name_unclear":false},"source":"VULYK","estate":{"25":[{"space_unclear":false,"costs":"","costs_comment":"","costs_hidden":false,"address_hidden":true,"region_hidden":false,"space_comment":"","space_hidden":false,"space":"58.5","address":"","region":"","costs_rent_comment":"","space_comment_hidden":false,"space_units":"м²","costs_rent":""}],"27":[{"space_unclear":false,"costs":"","costs_comment":"","costs_hidden":false,"address_hidden":true,"region_hidden":false,"space_comment":"","space":"20","address":"","region":"","costs_rent_comment":"","space_units":"м²","costs_rent":""}]},"intro":{"declaration_year":"2013"}}