{"income":{"5":{"value":"225278","family_comment":"","value_unclear":false,"family_unclear":false,"family":"","comment":""},"6":{"family_comment":"","value":"217712","value_unclear":false,"family":"","comment":""},"7":{"value":"","value_unclear":false,"family_comment":"","source_name":"","family":"","comment":""},"8":{"family_comment":"","value":"","family":"","comment":""},"9":{"value":"7564","family_comment":"","value_unclear":false,"family_unclear":false,"family":"","comment":""},"10":{"family_comment":"","value":"","comment_unclear":false,"family":"","comment":""},"11":{"family_comment":"","value":"","family":"","comment":""},"12":{"family_comment":"","value":"","family":"","comment":""},"13":{"family_comment":"","value":"","value_unclear":false,"family":"","comment":""},"14":{"family_comment":"","value":"","family":"","comment":""},"15":{"family_comment":"","value":"","family":"","comment":""},"16":{"family_comment":"","family_unclear":false,"value":"","family":"","comment":""},"17":{"family_comment":"","family_unclear":false,"value":"","family":"","comment":""},"18":{"family_comment":"","value":"","family":"","comment":""},"19":{"family_comment":"","value":"","family":"","comment":""},"20":{"value":"","family_comment":"","value_unclear":false,"family_hidden":false,"value_hidden":false,"family_unclear":false,"comment_unclear":false,"comment":"","family":""}},"vehicle":{"35":[{"brand_info":"1892 куб. см.","sum_rent_comment":"","brand_info_unclear":false,"year":"2008","brand_info_hidden":false,"sum_rent_comment_unclear":false,"sum_rent":"","sum":"","brand":"Volkswagen Caddy","sum_comment":"","brand_unclear":false,"brand_hidden":false}]},"id":"vulyk_100_59","banks":{"45":[{"sum_foreign_comment":"","sum_units":"UAH","sum_comment":"","sum_comment_unclear":false,"sum_foreign_units":"UAH","sum_units_unclear":false,"sum_comment_hidden":true,"sum_unclear":false,"sum":"110894","sum_foreign":""}],"46":[{"sum_foreign_comment":"","sum_units":"UAH","sum_comment":"","sum_comment_unclear":false,"sum_foreign_units":"UAH","sum":"88894","sum_unclear":false,"sum_foreign":""}]},"declaration":{"additional_info_text":"","notfull_lostpages":"","date":"2015-03-30T00:00:00","notfull":"","additional_info":"","url":"http://static.declarations.com.ua/declarations/chosen_ones/judges_batch/4227_krupinska_svitlana_stepanivna.pdf"},"liabilities":{"54":{"sum_foreign_comment":"","sum":"","sum_comment":"","sum_comment_hidden":false,"sum_unclear":false,"sum_foreign":""},"55":{"sum_foreign_comment":"","sum":"","sum_comment":"","sum_foreign":""},"56":{"sum_foreign_comment":"","sum":"","sum_comment":"","sum_unclear":false,"sum_foreign":""},"57":{"sum_foreign_comment":"","sum":"","sum_comment":"","sum_comment_unclear":false,"sum_comment_hidden":false,"sum_unclear":false,"sum_foreign":""},"58":{"sum_foreign_comment":"","sum":"","sum_comment":"","sum_comment_hidden":false,"sum_unclear":false,"sum_foreign":""},"59":{"sum_foreign_comment":"","sum":"","sum_comment":"","sum_foreign":""},"60":{"sum_foreign_comment":"","sum_comment_hidden":false,"sum":"","sum_comment":"","sum_foreign":""},"61":{"sum_foreign_comment":"","sum":"","sum_comment":"","sum_foreign":""},"62":{"sum_foreign_comment":"","sum":"","sum_comment":"","sum_unclear":false,"sum_foreign":""},"63":{"sum_foreign_comment":"","sum_comment_hidden":false,"sum":"","sum_comment":"","sum_foreign":""},"64":{"sum_foreign_comment":"","sum_comment_hidden":false,"sum":"","sum_comment":"","sum_foreign":""}},"ft_src":"Степанівна\nКрупінська Світлана Степанівна\nсуддя луцького міськрайонного суду волинської області\nВолинська область\nЗагальний місцевий суд\nСвітлана\nКрупінська Світлана Степанівна\nСвітлана Степанівна Крупінська\nСвітлана Крупінська\nКрупінська Світлана Степанівна\nКрупінська\n1892 куб. см.\nVolkswagen Caddy\n2008\n88894\n110894\n2014\n1892 куб. см.\nVolkswagen Caddy\n2008\n110894\n88894\n2.4775\n43.2\n33.51\n35.8\nЗагальний місцевий суд\nВолинська область\nсуддя луцького міськрайонного суду волинської області\nСтепанівна\nКрупінська Світлана Степанівна\nСвітлана Степанівна Крупінська\nСвітлана Крупінська\nКрупінська Світлана Степанівна\nКрупінська Світлана Степанівна\nСвітлана\nКрупінська\n217712\n225278\n7564\n2014\n2.4775\n33.51\n43.2\n35.8\nСтепанівна\nКрупінська\nВолинська область\nЗагальний місцевий суд\nсуддя луцького міськрайонного суду волинської області\nКрупінська Світлана Степанівна\nКрупінська Світлана Степанівна\nСвітлана Степанівна Крупінська\nСвітлана Крупінська\nКрупінська Світлана Степанівна\nСвітлана\n217712\n225278\n7564\n2008\nVolkswagen Caddy\n1892 куб. см.\n225278\n7564\n217712\n35.8\n2.4775\n43.2\n33.51\n110894\n88894\n2014","general":{"inn":"","inn_hidden":true,"last_name":"Крупінська","post":{"post_unclear":false,"region_unclear":false,"post":"суддя луцького міськрайонного суду волинської області","office":"Загальний місцевий суд","region":"Волинська область","post_hidden":false,"office_unclear":false},"name":"Світлана","full_name":"Крупінська Світлана Степанівна","family_raw":"","addresses":[{"place_district":"","place_city_hidden":true,"place_city":"","place_city_unclear":false,"place_district_hidden":false,"place_city_type":"","place_address_hidden":true,"place_city_type_hidden":false,"place_address":"","place_hidden":true,"place":""}],"full_name_suggest":{"output":"Крупінська Світлана Степанівна","input":["Крупінська Світлана Степанівна","Світлана Степанівна Крупінська","Світлана Крупінська"]},"patronymic":"Степанівна"},"source":"VULYK","estate":{"23":[{"space_unclear":false,"costs":"","costs_comment":"","address_hidden":false,"region_hidden":true,"space_comment":"","space":"2.4775","address":"","costs_comment_unclear":false,"region":"","address_unclear":false,"costs_rent_comment":"","space_comment_unclear":false,"space_units":"га","costs_rent":""}],"24":[{"space_unclear":false,"costs":"","costs_comment":"","address_hidden":false,"region_hidden":true,"space_comment":"","space":"43.2","address":"","region":"","costs_rent_comment":"","space_comment_unclear":false,"space_units":"м²","costs_rent":""}],"25":[{"space_unclear":false,"costs":"","costs_comment":"","address_hidden":false,"region_hidden":true,"space_comment":"","space":"35.8","address":"","costs_comment_unclear":false,"region":"","address_unclear":false,"costs_rent_comment":"","space_comment_unclear":false,"space_units":"м²","costs_rent":""}],"28":[{"costs_rent":"","region":"","costs":"","costs_rent_comment":"","costs_comment":"","address_hidden":false,"region_hidden":true,"space_comment":"","space_units":"м²","space":"33.51","address":""}]},"intro":{"declaration_year":"2014"}}