{"income":{"5":{"value":"168392","family_comment":"","comment_unclear":false,"family_unclear":false,"value_unclear":false,"comment":"","family":"705829"},"6":{"family_comment":"","value":"168392","comment_unclear":false,"family":"","comment":""},"7":{"family_comment":"","value":"","source_name":"","family":"","comment":""},"8":{"family_comment":"","value":"","family":"","comment":""},"9":{"family_comment":"","value":"","value_unclear":false,"family":"2","comment":""},"10":{"family_comment":"","value":"","value_unclear":false,"family":"","comment":""},"11":{"family_comment":"","value":"","family":"","comment":""},"12":{"family_comment":"","value":"","family":"","comment":""},"13":{"family_comment":"","value":"","family":"","comment":""},"14":{"family_comment":"","value":"","family":"","comment":""},"15":{"family_comment":"","value":"","family":"","comment":""},"16":{"family_comment":"","value":"","family":"130000","comment":""},"17":{"family_comment":"","value":"","value_unclear":false,"family":"562853","comment":""},"18":{"family_comment":"","value":"","value_unclear":false,"family":"","comment":""},"19":{"family_comment":"","value":"","family":"","comment":""},"20":{"value":"","family_comment":"","comment_unclear":false,"family_unclear":false,"value_unclear":false,"comment":"","family":"12974"}},"vehicle":{"40":[{"brand_info":"2694 куб. см. 120 кВт 472 см","sum":"","brand":"Toyota Land Cruiser Prado","sum_comment":"","brand_unclear":false,"year":"2006","brand_hidden":false,"brand_info_hidden":false,"year_unclear":false,"sum_rent_comment":"","sum_rent":""}]},"id":"vulyk_84_166","banks":{"51":[{"sum_foreign_comment":"","sum":"52","sum_comment":"","sum_foreign_units":"UAH","sum_units":"UAH","sum_foreign":""}]},"declaration":{"additional_info_text":"","notfull_lostpages":"","date":"2015-03-20T00:00:00","notfull":"","additional_info":"","url":"http://static.declarations.com.ua/declarations/chosen_ones/judges_batch/2580_samoilenko_dmytro_oleksandrovych.pdf"},"liabilities":{"54":{"sum_foreign_comment":"","sum_comment":"","sum":"","sum_comment_hidden":false,"sum_foreign":""},"55":{"sum_foreign_comment":"","sum":"","sum_comment":"","sum_foreign":""},"56":{"sum_foreign_comment":"","sum":"","sum_comment":"","sum_foreign":""},"57":{"sum_foreign_comment":"","sum_comment":"","sum":"","sum_comment_hidden":false,"sum_foreign":""},"58":{"sum_foreign_comment":"","sum_comment":"","sum":"","sum_comment_hidden":false,"sum_foreign":""},"59":{"sum_foreign_comment":"","sum":"","sum_comment":"","sum_foreign":""},"60":{"sum_foreign_comment":"","sum":"","sum_comment":"","sum_foreign":""},"61":{"sum_foreign_comment":"","sum":"","sum_comment":"","sum_foreign":""},"62":{"sum_foreign_comment":"","sum":"","sum_comment":"","sum_foreign":""},"63":{"sum_foreign_comment":"","sum_comment":"","sum":"","sum_comment_hidden":false,"sum_foreign":""},"64":{"sum_foreign_comment":"","sum_comment":"","sum":"","sum_comment_hidden":false,"sum_foreign":""}},"ft_src":"Toyota Land Cruiser Prado\n2694 куб. см. 120 кВт 472 см\n2006\nОдеська область\nБілгород-Дністровський р-н с. Старокозаче\n48.96\nОдеська область\nБілгород-Дністровський р-н с. Старокозаче\n18\nОдеська область\nБілгород-Дністровський р-н с. Удобне\n29.7\n52\n2014\nToyota Land Cruiser Prado\n2694 куб. см. 120 кВт 472 см\n2006\n2014\nСамойленко Дмитро Олександрович\nДмитро Олександрович Самойленко\nДмитро Самойленко\nСамойленко Дмитро Олександрович\nДмитро\nПодружжя\nСамойленко Ю. О\nДитина\nСамойленко О. Д\nДитина\nСамойленко А. Д\nСамойленко Дмитро Олександрович\nОлександрович\nсуддя кіровського районного суд м. кіровограда\nЗагальний місцевий суд\nКіровоградська область\nСамойленко\nОдеса\nОдеська область\n168392\n12974\n562853\n168392\n705829\n130000\n2\nБілгород-Дністровський р-н с. Старокозаче\nОдеська область\n48.96\nБілгород-Дністровський р-н с. Старокозаче\n18\nОдеська область\nБілгород-Дністровський р-н с. Удобне\n29.7\nОдеська область\n52\n168392\n2\n705829\n168392\n130000\n562853\n12974\nСамойленко Ю. О\nПодружжя\nСамойленко О. Д\nДитина\nСамойленко А. Д\nДитина\nОлександрович\nСамойленко\nДмитро\nСамойленко Дмитро Олександрович\nДмитро Олександрович Самойленко\nДмитро Самойленко\nСамойленко Дмитро Олександрович\nОдеська область\nОдеса\nКіровоградська область\nсуддя кіровського районного суд м. кіровограда\nЗагальний місцевий суд\nСамойленко Дмитро Олександрович","general":{"inn":"","name":"Дмитро","last_name":"Самойленко","family":[{"inn":"","inn_hidden":true,"inn_unclear":false,"relations_hidden":false,"relations_other":"","relations":"Подружжя","name_hidden":false,"family_name":"Самойленко Ю. О","name_unclear":false},{"inn":"","inn_hidden":false,"family_name":"Самойленко О. Д","relations_other":"","relations":"Дитина","name_hidden":false,"name_unclear":false},{"inn":"","inn_hidden":false,"family_name":"Самойленко А. Д","relations_other":"","relations":"Дитина","name_hidden":false,"name_unclear":false}],"inn_hidden":true,"family_raw":"","inn_unclear":false,"post":{"post_unclear":false,"region_unclear":false,"post":"суддя кіровського районного суд м. кіровограда","candidate":"","office_hidden":false,"region":"Кіровоградська область","post_hidden":false,"office":"Загальний місцевий суд","office_unclear":false,"region_hidden":false},"full_name":"Самойленко Дмитро Олександрович","addresses":[{"place_city_type_unclear":false,"place_city_type_hidden":false,"place_district_hidden":false,"place_city_type":"Місто","place_address_hidden":true,"place_address_unclear":false,"place_address":"","place":"Одеська область","place_district":"","place_unclear":false,"place_hidden":false,"place_city_unclear":false,"place_city_hidden":false,"place_city":"Одеса","place_district_unclear":false}],"patronymic":"Олександрович","full_name_suggest":{"output":"Самойленко Дмитро Олександрович","input":["Самойленко Дмитро Олександрович","Дмитро Олександрович Самойленко","Дмитро Самойленко"]}},"source":"VULYK","estate":{"34":[{"space_unclear":false,"address_hidden":true,"region_hidden":false,"space_comment":"","space":"48.96","address":"Білгород-Дністровський р-н с. Старокозаче","region":"Одеська область","costs_property":"","costs_rent_comment":"","space_comment_hidden":false,"space_units":"м²","costs_property_comment":"","costs_rent":""},{"region_unclear":false,"address_hidden":true,"space_comment":"","space":"18","address":"Білгород-Дністровський р-н с. Старокозаче","region":"Одеська область","costs_property":"","costs_rent_comment":"","address_unclear":false,"space_units":"м²","costs_property_comment":"","costs_rent":""},{"region_unclear":false,"address_hidden":false,"space_comment":"","space":"29.7","address":"Білгород-Дністровський р-н с. Удобне","region":"Одеська область","costs_property":"","costs_rent_comment":"","address_unclear":false,"space_units":"м²","costs_property_comment":"","costs_rent":""}]},"intro":{"declaration_year":"2014","isnotdeclaration":"","declaration_year_unclear":false}}