{"income":{"5":{"family_comment":"","value":"224388","value_unclear":false,"family":"88290","comment":""},"6":{"value":"224388","value_unclear":false,"family_hidden":false,"family_comment":"","family":"86879","comment":""},"7":{"source_name_unclear":false,"value":"","family_comment":"","source_name":"","family":"","comment":""},"8":{"family_comment":"","value":"","family":"","comment":""},"9":{"family_comment":"","value":"","family":"1411","comment":""},"10":{"family_comment":"","value":"","family":"","comment":""},"11":{"family_comment":"","value":"","comment_unclear":false,"family":"","comment":""},"12":{"family_comment":"","value":"","family":"","comment":""},"13":{"family_comment":"","value":"","family":"","comment":""},"14":{"family_comment":"","value":"","family":"","comment":""},"15":{"family_comment":"","value":"","family":"","comment":""},"16":{"family_comment":"","value":"","family":"","comment":""},"17":{"family_comment":"","value":"","family":"","comment":""},"18":{"family_comment":"","value":"","family":"","comment":""},"19":{"family_comment":"","value":"","family":"","comment":""},"20":{"value":"","family_comment":"","value_unclear":false,"family_unclear":false,"comment_unclear":false,"comment":"","family":""}},"vehicle":{"35":[{"brand_info":"1598","sum_rent_comment":"","brand":"Chevrolet Lacetti","sum_comment":"","brand_unclear":false,"year":"2007","sum_rent_unclear":false,"brand_info_hidden":false,"brand_info_unclear":false,"sum":"","sum_rent":""}]},"id":"vulyk_101_172","banks":{"51":[{"sum_foreign_comment":"","sum_units":"UAH","sum_comment":"","sum_hidden":true,"sum_foreign_units":"UAH","sum_comment_hidden":true,"sum_unclear":false,"sum":"77991","sum_foreign":""}]},"declaration":{"additional_info_text":"","notfull_lostpages":"","date":"2016-03-31T00:00:00","notfull":"","additional_info":"","url":"http://static.declarations.com.ua/declarations/chosen_ones/judges_batch/887_korsun_vitalii_leonidovych_2015.pdf"},"liabilities":{"54":{"sum_foreign_comment":"","sum":"775","sum_comment":"","sum_comment_unclear":false,"sum_hidden":false,"sum_comment_hidden":true,"sum_unclear":true,"sum_foreign":""},"55":{"sum_foreign_comment":"","sum":"","sum_comment":"","sum_foreign":""},"56":{"sum_foreign_comment":"","sum":"","sum_comment":"","sum_comment_hidden":false,"sum_unclear":false,"sum_foreign":""},"57":{"sum_foreign_comment":"","sum":"","sum_comment":"","sum_hidden":false,"sum_comment_hidden":false,"sum_unclear":false,"sum_foreign":""},"58":{"sum_foreign_comment":"","sum":"","sum_comment":"","sum_comment_unclear":false,"sum_hidden":false,"sum_comment_hidden":false,"sum_unclear":false,"sum_foreign":""},"59":{"sum_foreign_comment":"","sum":"","sum_comment":"","sum_foreign":""},"60":{"sum_foreign_comment":"","sum":"","sum_comment":"","sum_hidden":false,"sum_comment_hidden":false,"sum_unclear":false,"sum_foreign":""},"61":{"sum_foreign_comment":"","sum":"","sum_comment":"","sum_foreign":""},"62":{"sum_foreign_comment":"","sum":"","sum_comment":"","sum_comment_unclear":false,"sum_foreign":""},"63":{"sum_foreign_comment":"","sum_comment_hidden":false,"sum":"","sum_comment":"","sum_foreign":""},"64":{"sum_foreign_comment":"","sum_comment_hidden":false,"sum":"","sum_comment":"","sum_foreign":""}},"ft_src":"775\nсуддя господарського суду запорізької області\nЗапорізька область\nГосподарський місцевий суд\nВіталій\nКорсун П. А\nПодружжя\nЛеонідович\nКорсун Віталій Леонідович\nКорсун\nКорсун Віталій Леонідович\nВіталій Леонідович Корсун\nВіталій Корсун\nКорсун Віталій Леонідович\nChevrolet Lacetti\n1598\n2007\n77991\n2015\n1598\n2007\nChevrolet Lacetti\n77991\n38.4\n1/2\n26.995\n66.4\n26.995\nКорсун Віталій Леонідович\nВіталій Леонідович Корсун\nВіталій Корсун\nКорсун Віталій Леонідович\nВіталій\nКорсун Віталій Леонідович\nЛеонідович\nсуддя господарського суду запорізької області\nЗапорізька область\nГосподарський місцевий суд\nКорсун\nПодружжя\nКорсун П. А\n775\n224388\n86879\n224388\n88290\n1411\n2015\n775\n26.995\n66.4\n1/2\n38.4\n26.995\nКорсун П. А\nПодружжя\nВіталій\nЛеонідович\nКорсун\nКорсун Віталій Леонідович\nВіталій Леонідович Корсун\nВіталій Корсун\nКорсун Віталій Леонідович\nсуддя господарського суду запорізької області\nЗапорізька область\nГосподарський місцевий суд\nКорсун Віталій Леонідович\n86879\n224388\n1411\n88290\n224388\n2007\nChevrolet Lacetti\n1598\n1411\n88290\n224388\n224388\n86879\n26.995\n66.4\n26.995\n1/2\n38.4\n77991\n2015","general":{"inn":"","name":"Віталій","inn_unclear":false,"family":[{"inn":"","relations":"Подружжя","relations_other":"","inn_hidden":true,"family_name":"Корсун П. А","name_hidden":true,"name_unclear":false}],"inn_hidden":true,"family_raw":"","last_name":"Корсун","post":{"region":"Запорізька область","region_unclear":false,"post":"суддя господарського суду запорізької області","office_unclear":false,"office":"Господарський місцевий суд"},"full_name":"Корсун Віталій Леонідович","addresses":[{"place_district":"","place_address_hidden":true,"place_city":"","place_city_type_hidden":false,"place_district_hidden":true,"place_city_type":"","place_city_hidden":true,"place_address":"","place_hidden":true,"place":""}],"patronymic":"Леонідович","patronymic_hidden":false,"full_name_suggest":{"output":"Корсун Віталій Леонідович","input":["Корсун Віталій Леонідович","Віталій Леонідович Корсун","Віталій Корсун"]}},"source":"VULYK","estate":{"24":[{"space_unclear":true,"costs":"","costs_comment":"","address_hidden":true,"region_hidden":true,"space_comment":"1/2","space":"38.4","address":"","region":"","costs_rent_comment":"","space_units":"м²","costs_rent":""}],"25":[{"space_unclear":false,"costs":"","costs_comment":"","address_hidden":true,"region_hidden":true,"space_comment":"","space_hidden":false,"space":"26.995","address":"","region":"","costs_rent_comment":"","space_comment_unclear":false,"space_units":"м²","costs_rent":""}],"31":[{"space_unclear":false,"address_hidden":true,"region_hidden":true,"space_comment":"","space_hidden":false,"space":"26.995","address":"","costs_rent_comment_unclear":false,"region":"","costs_property":"","costs_rent_comment":"","space_units":"м²","costs_property_comment":"","costs_rent":""},{"costs_rent":"","region":"","costs_property":"","costs_rent_comment":"","space_comment":"","costs_property_comment":"","space_units":"м²","space":"66.4","address":""}]},"intro":{"declaration_year":"2015"}}