{"income":{"5":{"value":"270591","family_unclear":false,"family_hidden":false,"family_comment":"","family":"12000","comment":""},"6":{"value":"270591","family_comment":"","value_unclear":false,"family_hidden":false,"family_unclear":false,"family":"","comment":""},"7":{"value":"","family_hidden":false,"value_hidden":false,"family_comment":"","source_name":"","family":"","comment":"","source_name_hidden":false},"8":{"family_comment":"","value":"","family":"","comment":""},"9":{"family_comment":"","value":"","family":"","comment":""},"10":{"family_comment":"","value":"","value_unclear":false,"family":"","comment":""},"11":{"family_comment":"","value":"","family":"","comment":""},"12":{"family_comment":"","value":"","family":"","comment":""},"13":{"family_comment":"","value":"","family":"","comment":""},"14":{"family_comment":"","value":"","family":"","comment":""},"15":{"family_comment":"","value":"","family":"","comment":""},"16":{"family_comment":"","value":"","family":"","comment":""},"17":{"family_comment":"","value":"","family":"","comment":""},"18":{"family_comment":"","value":"","family":"","comment":""},"19":{"family_comment":"","value":"","family":"","comment":""},"20":{"value":"","family_comment":"","value_unclear":false,"family_unclear":false,"comment_unclear":false,"comment":"","family":"12000"}},"vehicle":{"35":[{"brand_info":"4608 куб. см.","sum_rent_comment":"","year":"2008","brand_info_hidden":false,"brand_info_unclear":false,"year_unclear":false,"sum_rent":"","sum":"","brand":"Lexus","sum_comment":"","brand_unclear":false,"brand_hidden":false},{"brand_info":"2410 куб. см.","sum_rent_comment":"","brand":"ГАЗ 2410","sum_comment":"","year":"1990","brand_info_unclear":false,"sum":"","sum_rent":""},{"brand_info":"2400 куб. см.","sum_rent_comment":"","brand":"УАЗ 315123","sum_comment":"","year":"1990","sum":"","sum_rent":""}],"40":[{"brand_info":"2400 куб. см.","sum_rent_comment":"","brand":"Toyota Rav 4","sum_comment":"","brand_unclear":false,"year":"2008","brand_info_unclear":false,"year_unclear":false,"sum":"","sum_rent":""}]},"id":"vulyk_74_133","banks":{"45":[{"sum_foreign_comment":"","sum":"200000","sum_comment":"","sum_comment_unclear":false,"sum_hidden":false,"sum_foreign_units":"UAH","sum_foreign_hidden":false,"sum_units":"UAH","sum_comment_hidden":false,"sum_unclear":false,"sum_foreign":""}],"53":[{"sum_foreign_comment":"","sum_units":"UAH","sum_comment":"","sum_foreign_units":"UAH","sum_comment_hidden":false,"sum":"300000","sum_foreign":""}]},"declaration":{"additional_info_text":"","notfull_lostpages":"","date":"2014-03-03T00:00:00","notfull":"","additional_info":"","url":"http://static.declarations.com.ua/declarations/chosen_ones/judges_batch/1560_pletnov_volodymyr_vasylovych.pdf"},"liabilities":{"54":{"sum_foreign_comment":"","sum":"","sum_comment":"","sum_comment_unclear":false,"sum_comment_hidden":false,"sum_foreign":""},"55":{"sum_foreign_comment":"","sum":"","sum_comment":"","sum_hidden":false,"sum_unclear":false,"sum_foreign":""},"56":{"sum_foreign_comment":"","sum":"20000","sum_comment":"","sum_hidden":false,"sum_unclear":false,"sum_foreign":""},"57":{"sum_foreign_comment":"","sum":"","sum_comment":"","sum_comment_unclear":false,"sum_comment_hidden":false,"sum_foreign":""},"58":{"sum_foreign_comment":"","sum_comment_hidden":false,"sum":"","sum_comment":"","sum_foreign":""},"59":{"sum_foreign_comment":"","sum":"","sum_comment":"","sum_foreign":""},"60":{"sum_foreign_comment":"","sum":"","sum_hidden":false,"sum_comment":"","sum_foreign":""},"61":{"sum_foreign_comment":"","sum":"","sum_comment":"","sum_foreign":""},"62":{"sum_foreign_comment":"","sum":"10000","sum_comment":"","sum_foreign":""},"63":{"sum_foreign_comment":"","sum":"","sum_comment":"","sum_comment_unclear":false,"sum_unclear":false,"sum_foreign":""},"64":{"sum_foreign_comment":"","sum":"","sum_comment":"","sum_comment_unclear":false,"sum_unclear":false,"sum_foreign":""}},"ft_src":"10000\n20000\nХарків\nПлетньов Володимир Васильович\nсуддя апеляційного суду харківської області\nХарківська область\nЗагальний апеляційний суд\nВолодимир\nПлетньова А. А., 09. 12. 1986\nПодружжя\nПлетньова Є. В., 25. 09. 2010\nДитина\nПлетньова А. В., 25. 07. 2012\nДитина\nПлетньов Володимир Васильович\nВолодимир Васильович Плетньов\nВолодимир Плетньов\nПлетньов Володимир Васильович\nПлетньов\nВасильович\n4608 куб. см.\nLexus\n2008\n2410 куб. см.\n1990\nГАЗ 2410\n2400 куб. см.\n1990\nУАЗ 315123\nToyota Rav 4\n2400 куб. см.\n2008\nХарківська область\nм. Харків\n80.71\nХарківська область\nм. Харків\n2200\nм. Харків\nХарківська область\n2130\nм. Харків\n328.8\nХарківська область\n300000\n200000\n2013\n4608 куб. см.\nLexus\n2008\n2410 куб. см.\nГАЗ 2410\n1990\n2400 куб. см.\n1990\nУАЗ 315123\n2400 куб. см.\nToyota Rav 4\n2008\n2013\nЗагальний апеляційний суд\nХарківська область\nсуддя апеляційного суду харківської області\nВасильович\nПлетньов Володимир Васильович\nВолодимир Васильович Плетньов\nВолодимир Плетньов\nПлетньов Володимир Васильович\nВолодимир\nХарків\nПлетньов Володимир Васильович\nПлетньов\nПодружжя\nПлетньова А. А., 09. 12. 1986\nДитина\nПлетньова Є. В., 25. 09. 2010\nДитина\nПлетньова А. В., 25. 07. 2012\n20000\n10000\n270591\n12000\n270591\n12000\n2130\nХарківська область\nм. Харків\n2200\nм. Харків\nХарківська область\n328.8\nХарківська область\nм. Харків\nХарківська область\nм. Харків\n80.71\n300000\n200000\n20000\n10000\n270591\n12000\n270591\n12000\nПодружжя\nПлетньова А. А., 09. 12. 1986\nДитина\nПлетньова Є. В., 25. 09. 2010\nДитина\nПлетньова А. В., 25. 07. 2012\nХарків\nВасильович\nПлетньов\nХарківська область\nЗагальний апеляційний суд\nсуддя апеляційного суду харківської області\nПлетньов Володимир Васильович\nПлетньов Володимир Васильович\nВолодимир Васильович Плетньов\nВолодимир Плетньов\nПлетньов Володимир Васильович\nВолодимир\nLexus\n4608 куб. см.\n2008\n1990\n2410 куб. см.\nГАЗ 2410\nУАЗ 315123\n2400 куб. см.\n1990\n2008\n2400 куб. см.\nToyota Rav 4\n12000\n270591\n12000\n270591\nм. Харків\nХарківська область\n80.71\nм. Харків\nХарківська область\n2130\nм. Харків\nХарківська область\n328.8\nм. Харків\nХарківська область\n2200\n200000\n300000\n2013","general":{"inn":"","inn_hidden":false,"last_name":"Плетньов","post":{"region_unclear":false,"region":"Харківська область","post":"суддя апеляційного суду харківської області","office":"Загальний апеляційний суд","office_unclear":false,"post_hidden":false},"name":"Володимир","full_name":"Плетньов Володимир Васильович","family_raw":"","addresses":[{"place_district":"","place_city_hidden":false,"place_city":"Харків","place_city_type_hidden":false,"place_district_hidden":false,"place_city_type":"Місто","place_address_hidden":false,"place_address":"","place_hidden":false,"place":""}],"family":[{"inn":"","relations":"Подружжя","relations_other":"","inn_hidden":false,"family_name":"Плетньова А. А., 09. 12. 1986","name_hidden":false,"name_unclear":false},{"inn":"","relations":"Дитина","relations_other":"","inn_hidden":false,"family_name":"Плетньова Є. В., 25. 09. 2010","name_hidden":false,"name_unclear":false},{"inn":"","relations":"Дитина","relations_other":"","inn_hidden":false,"family_name":"Плетньова А. В., 25. 07. 2012","name_hidden":false,"name_unclear":false}],"full_name_suggest":{"output":"Плетньов Володимир Васильович","input":["Плетньов Володимир Васильович","Володимир Васильович Плетньов","Володимир Плетньов"]},"patronymic":"Васильович"},"source":"VULYK","estate":{"23":[{"space_hidden":false,"costs":"","costs_comment":"","address_hidden":false,"region_hidden":false,"space_comment":"","space_unclear":false,"space":"2130","address":"м. Харків","region":"Харківська область","space_units_unclear":false,"space_comment_unclear":false,"space_units":"м²","costs_rent":"","costs_rent_comment":""}],"26":[{"costs":"","costs_comment":"","address_hidden":false,"region_hidden":false,"space_comment":"","space":"328.8","address":"м. Харків","region":"Харківська область","address_unclear":false,"costs_rent_comment":"","space_units":"м²","costs_rent":""}],"29":[{"costs_rent":"","region":"Харківська область","costs_property":"","costs_rent_comment":"","address_hidden":false,"region_hidden":false,"space_comment":"","costs_property_comment":"","space_units":"м²","space":"2200","address":"м. Харків"}],"31":[{"space_unclear":false,"address_hidden":false,"region_hidden":false,"space_comment":"","space":"80.71","address":"м. Харків","region":"Харківська область","costs_property":"","costs_rent_comment":"","address_unclear":false,"space_units":"м²","costs_property_comment":"","costs_rent":""}]},"intro":{"declaration_year":"2013","isnotdeclaration":"","declaration_year_unclear":false}}