{"income":{"5":{"family_comment":"","value":"206911.35","family":"","comment":""},"6":{"family_comment":"","value":"193513.35","family":"","comment":"","family_comment_unclear":false},"7":{"value":"","comment_hidden":false,"family_comment":"","source_name":"","family":"","comment":"","source_name_hidden":false},"8":{"family_comment":"","value":"","family":"","comment":""},"9":{"family_comment":"","value":"","family":"","comment":""},"10":{"value":"13398","value_unclear":false,"value_hidden":false,"family_comment":"","family":"","comment":""},"11":{"family_comment":"","value":"","family":"","comment":""},"12":{"family_comment":"","value":"","family":"","comment":""},"13":{"family_comment":"","value":"","family":"","comment":""},"14":{"family_comment":"","value":"","family":"","comment":""},"15":{"family_comment":"","value":"","family":"","comment":""},"16":{"family_comment":"","value":"","family":"","comment":""},"17":{"family_comment":"","value":"","family":"","comment":""},"18":{"family_comment":"","value":"","family":"","comment":""},"19":{"family_comment":"","value":"","family":"","comment":""},"20":{"family_comment":"","value":"","comment_unclear":false,"family":"","comment":""}},"vehicle":{"40":[{"brand_info":"2500 куб. см.","sum_rent_comment":"","brand":"Ford Kuga","sum_comment":"","brand_unclear":false,"year":"2011","sum":"","sum_rent":""}]},"id":"vulyk_86_7","declaration":{"additional_info_text":"","notfull_lostpages":"","date":"2015-03-12T00:00:00","notfull":"","additional_info":"","url":"http://static.declarations.com.ua/declarations/chosen_ones/judges_batch/2710_topchii_tetiana_v’yacheslavivna.pdf"},"liabilities":{"54":{"sum_foreign_comment":"","sum":"","sum_comment":"","sum_unclear":false,"sum_foreign":""},"55":{"sum_foreign_comment":"","sum":"","sum_comment":"","sum_foreign":""},"56":{"sum_foreign_comment":"","sum":"3340","sum_hidden":false,"sum_comment":"","sum_foreign":""},"57":{"sum_foreign_comment":"","sum":"","sum_comment":"","sum_unclear":false,"sum_foreign":""},"58":{"sum_foreign_comment":"","sum":"","sum_comment":"","sum_unclear":false,"sum_foreign":""},"59":{"sum_foreign_comment":"","sum":"","sum_comment":"","sum_foreign":""},"60":{"sum_foreign_comment":"","sum_comment_hidden":false,"sum":"","sum_comment":"","sum_foreign":""},"61":{"sum_foreign_comment":"","sum":"","sum_comment":"","sum_foreign":""},"62":{"sum_foreign_comment":"","sum":"3110","sum_comment":"","sum_foreign":""},"63":{"sum_foreign_comment":"","sum":"","sum_comment":"","sum_foreign":""},"64":{"sum_foreign_comment":"","sum":"","sum_comment":"","sum_foreign":""}},"ft_src":"3110\n3340\nсуддя апеляційного суду донецької області\nДонецька область\nЗагальний апеляційний суд\nТетяна\nТопчій О. О\nПодружжя\nТопчій А. О\nДитина\nВ'ячеславівна\nТопчій Тетяна В'ячеславівна\nТетяна В'ячеславівна Топчій\nТетяна Топчій\nТопчій Тетяна В'ячеславівна\nТопчій Тетяна В'ячеславівна\nТопчій\n2011\n2500 куб. см.\nFord Kuga\n44.2\n70\n2014\n193513.35\n13398\n206911.35\n2500 куб. см.\nFord Kuga\n2011\n2014\nТопчій Тетяна В'ячеславівна\nТетяна В'ячеславівна Топчій\nТетяна Топчій\nТопчій Тетяна В'ячеславівна\nТопчій Тетяна В'ячеславівна\nПодружжя\nТопчій О. О\nДитина\nТопчій А. О\nТетяна\nТопчій\nЗагальний апеляційний суд\nДонецька область\nсуддя апеляційного суду донецької області\nВ'ячеславівна\n3340\n3110\n193513.35\n206911.35\n13398\n44.2\n70\n3110\n3340\nТопчій О. О\nПодружжя\nТопчій А. О\nДитина\nВ'ячеславівна\nТопчій\nТетяна\nТопчій Тетяна В'ячеславівна\nТетяна В'ячеславівна Топчій\nТетяна Топчій\nТопчій Тетяна В'ячеславівна\nДонецька область\nЗагальний апеляційний суд\nсуддя апеляційного суду донецької області\nТопчій Тетяна В'ячеславівна\n2011\n2500 куб. см.\nFord Kuga\n13398\n206911.35\n193513.35\n44.2\n70\n2014","general":{"inn":"","name":"Тетяна","patronymic_unclear":false,"family":[{"inn":"","inn_hidden":true,"relations_hidden":false,"family_name":"Топчій О. О","relations_other":"","relations":"Подружжя","name_hidden":false,"name_unclear":false},{"inn":"","relations":"Дитина","relations_other":"","inn_hidden":true,"family_name":"Топчій А. О","name_hidden":false,"name_unclear":false}],"patronymic":"В'ячеславівна","inn_hidden":true,"family_raw":"","inn_unclear":false,"post":{"post_unclear":false,"post":"суддя апеляційного суду донецької області","candidate":"","office_hidden":false,"region":"Донецька область","office":"Загальний апеляційний суд","office_unclear":false,"region_hidden":false},"full_name":"Топчій Тетяна В'ячеславівна","addresses":[{"place_district":"","place_unclear":false,"place_city":"","place_city_type_hidden":false,"place_district_hidden":false,"place_city_type":"","place_city_hidden":false,"place_address_hidden":true,"place_address":"","place_hidden":false,"place":""}],"last_name":"Топчій","full_name_suggest":{"output":"Топчій Тетяна В'ячеславівна","input":["Топчій Тетяна В'ячеславівна","Тетяна В'ячеславівна Топчій","Тетяна Топчій"]}},"source":"VULYK","estate":{"25":[{"space_unclear":false,"costs":"","costs_comment":"","address_hidden":false,"region_hidden":true,"space_comment":"","space_hidden":false,"space":"70","address":"","region":"","address_unclear":false,"costs_rent_comment":"","space_units":"м²","costs_rent":""}],"31":[{"space_unclear":false,"address_hidden":false,"region_hidden":true,"space_comment":"","space_hidden":false,"space":"44.2","address":"","region":"","costs_property":"","costs_rent_comment":"","space_units":"м²","costs_property_comment":"","costs_rent":""}]},"intro":{"declaration_year":"2014","declaration_year_unclear":false}}