{"id":"vulyk_108_125","ft_src":"24600\n73.3\n2015\n228075\n166\n13398\nНаціональна школа суддів України, Дніпропетровське регіональне відділення\n2167\n247131\n1600\nпенсія за віком\n17215\n24600\n73.3\nЗагальний апеляційний суд\nДніпропетровська область\nсуддя апеляційного суду дніпропетровської області\nСтуковенкова\nСтуковенкова Тетяна Григорівна\nТетяна Григорівна Стуковенкова\nТетяна Стуковенкова\nСтуковенкова Тетяна Григорівна\nТетяна\nСтуковенкова Тетяна Григорівна\nГригорівна\n7359\n2167\nНаціональна школа суддів України, Дніпропетровське регіональне відділення\n228075\n17215\nпенсія за віком\n247131\n166\n13398\n1600\n2015\n7359\nСтуковенкова\nГригорівна\nДніпропетровська область\nсуддя апеляційного суду дніпропетровської області\nЗагальний апеляційний суд\nСтуковенкова Тетяна Григорівна\nСтуковенкова Тетяна Григорівна\nТетяна Григорівна Стуковенкова\nТетяна Стуковенкова\nСтуковенкова Тетяна Григорівна\nТетяна","estate":{"23":[{"address":"","space_units":"м²","costs_comment":"","space_unclear":false,"region_hidden":true,"space_units_unclear":false,"space_comment":"","address_hidden":true,"costs":"","address_unclear":false,"costs_rent_comment":"","space":"24600","region_unclear":false,"region":"","space_units_hidden":false,"costs_rent":""}],"25":[{"address":"","space_units":"м²","costs_comment":"","space_unclear":false,"region_hidden":true,"space_units_unclear":false,"space_comment":"","address_hidden":true,"costs":"","space_comment_unclear":false,"costs_rent_comment":"","space":"73.3","region":"","costs_rent":""}]},"source":"VULYK","income":{"5":{"family_comment":"","family":"","comment":"","value_unclear":false,"family_unclear":false,"value":"247131"},"6":{"family_comment":"","value":"228075","family_unclear":false,"family":"","comment":""},"7":{"family_comment":"","comment":"","family":"","source_name_unclear":false,"value":"2167","source_name":"Національна школа суддів України, Дніпропетровське регіональне відділення"},"8":{"family_comment":"","value":"","family":"","comment":""},"9":{"family_comment":"","family":"","comment":"","family_unclear":false,"comment_hidden":false,"value":"166","family_comment_hidden":false},"10":{"family_comment":"","value":"13398","family":"","comment":""},"11":{"family_comment":"","value":"","family":"","comment":""},"12":{"family_comment":"","value":"","family":"","comment":""},"13":{"family_comment":"","value":"","family":"","comment":""},"14":{"family_comment":"","value":"","family":"","comment":""},"15":{"family_comment":"","value":"","family":"","comment":""},"16":{"family_comment":"","value":"","family":"","comment":""},"17":{"family_comment":"","value":"","family":"","comment":""},"18":{"family_comment":"","value":"","family":"","comment":""},"19":{"family_comment":"","value":"1600","family":"","comment":""},"20":{"family_comment":"","comment":"пенсія за віком","family":"","value_unclear":false,"comment_hidden":false,"comment_unclear":false,"value":"17215"}},"general":{"inn":"","inn_unclear":false,"last_name":"Стуковенкова","full_name_suggest":{"input":["Стуковенкова Тетяна Григорівна","Тетяна Григорівна Стуковенкова","Тетяна Стуковенкова"],"output":"Стуковенкова Тетяна Григорівна"},"full_name":"Стуковенкова Тетяна Григорівна","patronymic":"Григорівна","inn_hidden":true,"name":"Тетяна","post":{"office":"Загальний апеляційний суд","post":"суддя апеляційного суду дніпропетровської області","office_unclear":false,"office_hidden":false,"region":"Дніпропетровська область","post_unclear":false},"family_raw":"","addresses":[{"place_city_type_hidden":true,"place_hidden":true,"place_address_unclear":false,"place":"","place_city":"","place_unclear":false,"place_city_type":"","place_city_hidden":true,"place_district":"","place_district_hidden":true,"place_address":"","place_address_hidden":true}]},"liabilities":{"54":{"sum_comment":"","sum_foreign_comment":"","sum_foreign":"","sum_hidden":false,"sum":""},"55":{"sum_comment":"","sum_foreign_comment":"","sum_foreign":"","sum":""},"56":{"sum_comment":"","sum_foreign_comment":"","sum_foreign":"","sum_unclear":false,"sum":""},"57":{"sum_comment":"","sum_hidden":false,"sum":"7359","sum_foreign_comment":"","sum_foreign":"","sum_comment_hidden":false},"58":{"sum_comment":"","sum_foreign_comment":"","sum_foreign":"","sum":"","sum_comment_hidden":false},"59":{"sum_comment":"","sum_foreign_comment":"","sum_foreign":"","sum_unclear":false,"sum":""},"60":{"sum_comment":"","sum_foreign_comment":"","sum_foreign":"","sum":"","sum_comment_hidden":false},"61":{"sum_comment":"","sum_foreign_comment":"","sum_foreign":"","sum":"","sum_comment_hidden":false},"62":{"sum_comment":"","sum_foreign_comment":"","sum_foreign":"","sum":""},"63":{"sum_comment":"","sum_hidden":false,"sum":"","sum_foreign_comment":"","sum_foreign":"","sum_unclear":false,"sum_comment_hidden":false},"64":{"sum_comment":"","sum":"","sum_foreign_comment":"","sum_foreign":"","sum_unclear":false,"sum_comment_hidden":false}},"declaration":{"notfull_lostpages":"","additional_info_text":"","additional_info":"","date":"2016-03-29T00:00:00","notfull":"","url":"http://static.declarations.com.ua/declarations/chosen_ones/judges_batch/2424_stukovenkova_tetiana_hryhorivna_2015.pdf"},"intro":{"declaration_year_hidden":false,"isnotdeclaration":"","declaration_year":"2015"}}