{"income":{"5":{"value":"762033","value_unclear":false,"family_hidden":false,"family_comment":"","family":"1162500","comment":""},"6":{"family_comment":"","value":"305743","family":"","comment":""},"7":{"family_comment":"","value":"","source_name":"","family":"","comment":""},"8":{"family_comment":"","value":"","family":"","comment":""},"9":{"family_comment":"","value":"","family":"","comment":""},"10":{"family_comment":"","value":"","family":"","comment":""},"11":{"family_comment":"","value":"","family_hidden":false,"comment":"","family":""},"12":{"family_comment":"","value":"","family":"","comment":""},"13":{"family_comment":"","value":"","family":"","comment":""},"14":{"family_comment":"","value":"","family":"","comment":""},"15":{"family_comment":"","value":"","family":"","comment":""},"16":{"family_comment":"","value":"","family":"1162500","comment":""},"17":{"family_comment":"","value":"","family":"","comment":"","family_comment_unclear":false},"18":{"family_comment":"","value":"","family":"","comment":""},"19":{"family_comment":"","value":"","family":"","comment":""},"20":{"value":"367","family_unclear":false,"family_hidden":false,"family_comment":"","family":"","comment":"бонус плюс"}},"vehicle":{"35":[{"brand_info":"2.5","sum":"870000","brand":"Nissan X-Trail","sum_comment":"","brand_unclear":false,"year":"2014","brand_hidden":false,"brand_info_hidden":false,"brand_info_unclear":false,"sum_rent_comment":"","sum_rent":""}]},"id":"vulyk_103_92","declaration":{"date":"2016-03-20T00:00:00","additional_info_text":"","additional_info":"","url":"http://static.declarations.com.ua/declarations/chosen_ones/judges_batch/1316_surzhok_anatolii_vasylovych.pdf"},"liabilities":{"54":{"sum_foreign_comment":"","sum_foreign_hidden":true,"sum_comment":"","sum_foreign_comment_hidden":true,"sum_hidden":true,"sum_foreign_comment_unclear":false,"sum_comment_hidden":true,"sum_unclear":false,"sum":"55180","sum_foreign":""},"55":{"sum_foreign_comment":"","sum":"","sum_comment":"","sum_foreign":""},"56":{"sum_foreign_comment":"","sum":"","sum_comment":"","sum_foreign":""},"57":{"sum_foreign_comment":"","sum_foreign_hidden":true,"sum_comment":"","sum_foreign_comment_hidden":true,"sum_hidden":true,"sum_comment_hidden":true,"sum":"42522","sum_foreign":""},"58":{"sum_foreign_comment":"","sum_foreign_hidden":true,"sum_comment":"","sum_foreign_comment_hidden":true,"sum_hidden":true,"sum_comment_hidden":true,"sum":"18977","sum_foreign":""},"59":{"sum_foreign_comment":"","sum_foreign_hidden":true,"sum_comment":"комісія банку по кредитному договору","sum_foreign_comment_hidden":true,"sum_hidden":true,"sum_comment_hidden":true,"sum":"11398","sum_foreign":""},"60":{"sum_foreign_comment":"","sum":"","sum_comment":"","sum_hidden":false,"sum_comment_hidden":false,"sum_foreign":""},"61":{"sum_foreign_comment":"","sum":"","sum_comment":"","sum_foreign":""},"62":{"sum_foreign_comment":"","sum_comment_hidden":false,"sum":"","sum_comment":"","sum_foreign":""},"63":{"sum_foreign_comment":"","sum":"","sum_comment":"","sum_foreign":""},"64":{"sum_foreign_comment":"","sum":"","sum_comment":"","sum_foreign":""}},"ft_src":"комісія банку по кредитному договору\n11398\n42522\n55180\n18977\nСуржок Анатолій Васильович\nсуддя вссу\nЗагальнодержавний регіон\nВищий спеціалізований суд з розгляду цивільних і кримінальних справ\nАнатолій\nСуржок Тетяна Петрівна\nПодружжя\nСуржок Анатолій Васильович\nАнатолій Васильович Суржок\nАнатолій Суржок\nСуржок Анатолій Васильович\nСуржок\nВасильович\nNissan X-Trail\n870000\n2.5\n2014\nчлен товариства з 1990\n28\n400\nсвідоцтво про право на спадщину за законом з 29.09.2000\n54\n138.5\nсвідоцтво про право на спадщину за законом з 29.09.2000\n3600\n230\n2015\n305743\n1162500\n762033\n1162500\nбонус плюс\n367\n2.5\n2014\n870000\nNissan X-Trail\nчлен товариства з 1990\n28\n230\nсвідоцтво про право на спадщину за законом з 29.09.2000\n3600\n400\n54\nсвідоцтво про право на спадщину за законом з 29.09.2000\n138.5\nСуржок\nСуржок Анатолій Васильович\nАнатолій Васильович Суржок\nАнатолій Суржок\nСуржок Анатолій Васильович\nСуржок Анатолій Васильович\nВасильович\nПодружжя\nСуржок Тетяна Петрівна\nАнатолій\nВищий спеціалізований суд з розгляду цивільних і кримінальних справ\nсуддя вссу\nЗагальнодержавний регіон\n11398\nкомісія банку по кредитному договору\n18977\n42522\n55180\n305743\nбонус плюс\n367\n762033\n1162500\n1162500\n2015\n18977\n42522\n55180\nкомісія банку по кредитному договору\n11398\nПодружжя\nСуржок Тетяна Петрівна\nСуржок\nВасильович\nсуддя вссу\nВищий спеціалізований суд з розгляду цивільних і кримінальних справ\nЗагальнодержавний регіон\nСуржок Анатолій Васильович\nСуржок Анатолій Васильович\nАнатолій Васильович Суржок\nАнатолій Суржок\nСуржок Анатолій Васильович\nАнатолій\n870000\nNissan X-Trail\n2.5\n2014\n367\nбонус плюс\n762033\n1162500\n1162500\n305743\n3600\nсвідоцтво про право на спадщину за законом з 29.09.2000\nсвідоцтво про право на спадщину за законом з 29.09.2000\n54\n28\nчлен товариства з 1990\n230\n138.5\n400\n2015","general":{"inn":"","inn_hidden":true,"last_name":"Суржок","post":{"region":"Загальнодержавний регіон","region_unclear":false,"post":"суддя вссу","office_unclear":false,"office":"Вищий спеціалізований суд з розгляду цивільних і кримінальних справ"},"name":"Анатолій","full_name":"Суржок Анатолій Васильович","family_raw":"","addresses":[{"place_district":"","place_city_hidden":true,"place_city":"","place_city_type_hidden":true,"place_district_hidden":true,"place_city_type":"","place_address_hidden":true,"place_address":"","place_hidden":true,"place":""}],"family":[{"inn":"","relations":"Подружжя","relations_hidden":false,"inn_hidden":true,"relations_other":"","name_hidden":true,"family_name":"Суржок Тетяна Петрівна","name_unclear":false}],"full_name_suggest":{"output":"Суржок Анатолій Васильович","input":["Суржок Анатолій Васильович","Анатолій Васильович Суржок","Анатолій Суржок"]},"patronymic":"Васильович"},"source":"VULYK","estate":{"23":[{"costs_rent":"","region":"","costs":"","costs_rent_comment":"свідоцтво про право на спадщину за законом з 29.09.2000","costs_comment":"","address_hidden":true,"region_hidden":true,"space_comment":"","space_units":"м²","space":"3600","address":""}],"24":[{"space_hidden":false,"costs":"","costs_comment":"","address_hidden":true,"region_hidden":true,"space_comment":"свідоцтво про право на спадщину за законом з 29.09.2000","space_unclear":false,"space":"54","address":"","region":"","costs_rent_comment":"","space_units":"м²","costs_rent":""}],"27":[{"costs_rent":"","region":"","costs":"","costs_rent_comment":"член товариства з 1990","costs_comment":"","address_hidden":true,"region_hidden":true,"space_comment":"","space_units":"м²","space":"28","address":""}],"29":[{"space_hidden":false,"address_hidden":true,"region_hidden":true,"space_comment":"","space":"400","address":"","region":"","costs_property":"","costs_rent_comment":"","space_units":"м²","costs_property_comment":"","costs_rent":""}],"30":[{"space_unclear":false,"address_hidden":true,"region_hidden":true,"space_comment":"","space_hidden":false,"space":"230","address":"","costs_property":"","costs_rent_comment":"","space_units":"м²","costs_property_comment":"","costs_rent":""}],"32":[{"costs_rent":"","costs_property":"","costs_rent_comment":"","address_hidden":true,"region_hidden":true,"space_comment":"","costs_property_comment":"","space_units":"м²","space":"138.5","address":""}]},"intro":{"declaration_year":"2015"}}