{"income":{"5":{"value":"249227","family_comment":"","value_unclear":false,"comment_hidden":false,"family_hidden":false,"value_hidden":false,"family_unclear":false,"family_comment_unclear":false,"family":"217183","comment":"","family_comment_hidden":false},"6":{"value":"245651","family_comment":"","value_unclear":false,"family_hidden":false,"value_hidden":false,"family_unclear":false,"family":"165136","comment":""},"7":{"source_name_unclear":false,"value":"","family_hidden":false,"value_hidden":false,"family_comment":"","source_name":"","family":"","comment":"","source_name_hidden":false},"8":{"value":"","family_comment":"","value_unclear":false,"family_hidden":false,"value_hidden":false,"family_unclear":false,"family":"","comment":""},"9":{"value":"59","family_comment":"","value_unclear":false,"family_hidden":false,"value_hidden":false,"family_unclear":false,"comment_unclear":false,"comment":"","family":"121"},"10":{"value":"","value_unclear":false,"family_hidden":false,"value_hidden":false,"family_comment":"","family":"","comment":""},"11":{"value":"","family_hidden":false,"value_hidden":false,"family_comment":"","family":"","comment":""},"12":{"value":"","family_comment":"","family_hidden":false,"value_hidden":false,"family_unclear":false,"family":"","comment":""},"13":{"value":"","family_hidden":false,"value_hidden":false,"family_comment":"","family":"","comment":""},"14":{"value":"","family_hidden":false,"value_hidden":false,"family_comment":"","family":"","comment":""},"15":{"value":"3442","family_hidden":false,"value_hidden":false,"family_comment":"","family":"","comment":""},"16":{"value":"","value_unclear":false,"family_hidden":false,"value_hidden":false,"family_comment":"","family":"","comment":""},"17":{"value":"","family_hidden":false,"value_hidden":false,"family_comment":"","family":"","comment":""},"18":{"value":"","family_hidden":false,"value_hidden":false,"family_comment":"","family":"","comment":""},"19":{"value":"","comment_unclear":false,"family_hidden":false,"value_hidden":false,"family_comment":"","family":"","comment":""},"20":{"value":"75","family_comment":"","comment_unclear":false,"comment_hidden":false,"family_hidden":false,"value_hidden":false,"family_unclear":false,"family_comment_unclear":false,"family_comment_hidden":false,"comment":"","family":"51926"}},"vehicle":{"35":[{"year_hidden":false,"brand_info":"об'єм двигуна 2658","sum_rent_comment":"","sum_rent_comment_unclear":false,"sum_rent_hidden":false,"year":"2008","sum_hidden":false,"brand_info_hidden":false,"brand_info_unclear":false,"year_unclear":false,"sum_rent":"","sum_rent_unclear":false,"sum":"","brand":"Hyundai Tucson","sum_comment":"","brand_unclear":false,"brand_hidden":false,"sum_unclear":false}],"39":[{"brand_info":"мотоцикл, об'єм двигуна 175","sum_rent_comment":"","brand":"ЗДК 4. 105 'Сова'","sum_comment":"","year":"1994","brand_hidden":false,"brand_info_hidden":false,"sum_hidden":false,"sum":"","sum_rent":"","sum_unclear":false}],"40":[{"year_hidden":false,"brand_info":"об'єм двигуна 1997","sum_rent_comment":"","year":"2007","sum_hidden":false,"brand_info_hidden":false,"brand_info_unclear":false,"year_unclear":false,"sum_rent":"","sum":"","brand":"Peugeot 407 ST 2,0 E","sum_comment":"","brand_unclear":false,"brand_hidden":false}]},"id":"vulyk_69_208","banks":{"45":[{"sum_foreign_comment":"","sum":"2692","sum_comment":"","sum_hidden":false,"sum_foreign_units":"UAH","sum_foreign_hidden":false,"sum_units":"UAH","sum_comment_hidden":false,"sum_unclear":false,"sum_foreign":"","sum_units_hidden":false}],"46":[{"sum_foreign_comment":"","sum_units":"UAH","sum_comment":"","sum_hidden":false,"sum_foreign_units":"UAH","sum_foreign_hidden":false,"sum":"600","sum_unclear":false,"sum_foreign":""}],"51":[{"sum_foreign_comment":"","sum_units":"UAH","sum_comment":"","sum_comment_unclear":false,"sum_hidden":false,"sum_foreign_units":"UAH","sum_comment_hidden":false,"sum_unclear":false,"sum":"3473","sum_foreign":""}]},"declaration":{"additional_info_text":"","notfull_lostpages":"","date":"2015-03-30T00:00:00","notfull":"","additional_info":"","url":"http://static.declarations.com.ua/declarations/chosen_ones/epic_batch/dev_iatko_vladyslav_volodymyrovych.pdf"},"liabilities":{"54":{"sum_foreign_comment":"","sum":"11320","sum_comment":"","sum_hidden":false,"sum_comment_hidden":false,"sum_unclear":false,"sum_foreign":""},"55":{"sum_foreign_comment":"","sum":"","sum_hidden":false,"sum_comment":"","sum_foreign":""},"56":{"sum_foreign_comment":"","sum":"","sum_comment":"","sum_comment_unclear":false,"sum_hidden":false,"sum_unclear":false,"sum_foreign":""},"57":{"sum_foreign_comment":"","sum":"","sum_comment":"","sum_comment_unclear":false,"sum_hidden":false,"sum_comment_hidden":false,"sum_foreign":""},"58":{"sum_foreign_comment":"","sum":"","sum_comment":"","sum_comment_unclear":false,"sum_hidden":false,"sum_comment_hidden":false,"sum_unclear":false,"sum_foreign":""},"59":{"sum_foreign_comment":"","sum":"","sum_hidden":false,"sum_comment":"","sum_foreign":""},"60":{"sum_foreign_comment":"","sum":"","sum_comment":"","sum_hidden":false,"sum_comment_hidden":false,"sum_foreign":""},"61":{"sum_foreign_comment":"","sum":"","sum_hidden":false,"sum_comment":"","sum_foreign":""},"62":{"sum_foreign_comment":"","sum":"","sum_comment":"","sum_comment_unclear":false,"sum_hidden":false,"sum_unclear":false,"sum_foreign":""},"63":{"sum_foreign_comment":"","sum":"25554","sum_comment":"","sum_hidden":false,"sum_comment_hidden":false,"sum_unclear":false,"sum_foreign":""},"64":{"sum_foreign_comment":"","sum":"346","sum_comment":"","sum_hidden":false,"sum_comment_hidden":false,"sum_foreign":""}},"ft_src":"11320\n25554\n346\nголова оболонського районного суду м. києва\nм. Київ\nЗагальний місцевий суд\nВладислав\nДев'ятко О. В\nПодружжя\nДев'ятко Я. В\nДитина\nДев'ятко П. В\nДитина\nДев'ятко О. В\nБрат/Сестра\nВолодимирович\nДев'ятко Владислав Володимирович\nВладислав Володимирович Дев'ятко\nВладислав Дев'ятко\nДев'ятко Владислав Володимирович\nДев'ятко Владислав Володимирович\nДев'ятко\nЗДК 4. 105 'Сова'\nмотоцикл, об'єм двигуна 175\n1994\nоб'єм двигуна 2658\nHyundai Tucson\n2008\nPeugeot 407 ST 2,0 E\nоб'єм двигуна 1997\n2007\n600\n3473\n2692\n2014\nоб'єм двигуна 2658\nHyundai Tucson\n2008\nоб'єм двигуна 1997\nPeugeot 407 ST 2,0 E\n2007\nЗДК 4. 105 'Сова'\nмотоцикл, об'єм двигуна 175\n1994\n2692\n3473\n600\n10000\n12100\n70.1\n40.24\nкомунальна власність\nкомун. власність\nслужбова\nслужбова\n79.78\n40.24\nкомунальна власність\nкомун. власність\n79.78\nслужбова\nслужбова\nДев'ятко Владислав Володимирович\nВладислав Володимирович Дев'ятко\nВладислав Дев'ятко\nДев'ятко Владислав Володимирович\nДев'ятко Владислав Володимирович\nПодружжя\nДев'ятко О. В\nДитина\nДев'ятко Я. В\nДитина\nДев'ятко П. В\nБрат/Сестра\nДев'ятко О. В\nВладислав\nДев'ятко\nЗагальний місцевий суд\nголова оболонського районного суду м. києва\nм. Київ\nВолодимирович\n11320\n25554\n346\n165136\n245651\n75\n51926\n3442\n249227\n217183\n121\n59\n2014\n11320\n25554\n346\n10000\n70.1\n12100\nкомунальна власність\nкомун. власність\n40.24\nслужбова\nслужбова\n79.78\nкомунальна власність\nкомун. власність\n40.24\nслужбова\nслужбова\n79.78\nДев'ятко О. В\nПодружжя\nДев'ятко Я. В\nДитина\nДев'ятко П. В\nДитина\nДев'ятко О. В\nБрат/Сестра\nВолодимирович\nДев'ятко\nВладислав\nДев'ятко Владислав Володимирович\nВладислав Володимирович Дев'ятко\nВладислав Дев'ятко\nДев'ятко Владислав Володимирович\nм. Київ\nголова оболонського районного суду м. києва\nЗагальний місцевий суд\nДев'ятко Владислав Володимирович\n165136\n245651\n3442\n121\n59\n217183\n249227\n51926\n75\n1994\nЗДК 4. 105 'Сова'\nмотоцикл, об'єм двигуна 175\nHyundai Tucson\nоб'єм двигуна 2658\n2008\nPeugeot 407 ST 2,0 E\nоб'єм двигуна 1997\n2007\n3442\n59\n121\n75\n51926\n249227\n217183\n245651\n165136\nкомунальна власність\nкомун. власність\n40.24\nслужбова\nслужбова\n79.78\n70.1\n12100\nкомунальна власність\nкомун. власність\n40.24\nслужбова\nслужбова\n79.78\n10000\n2692\n3473\n600\n2014","general":{"inn":"","name":"Владислав","patronymic_unclear":false,"family":[{"inn":"","inn_hidden":true,"relations_unclear":false,"relations_hidden":false,"relations_other":"","relations":"Подружжя","name_hidden":false,"inn_unclear":false,"family_name":"Дев'ятко О. В","name_unclear":false},{"inn":"","inn_hidden":true,"relations_unclear":false,"relations_hidden":false,"relations_other":"","relations":"Дитина","name_hidden":false,"inn_unclear":false,"family_name":"Дев'ятко Я. В","name_unclear":false},{"inn":"","inn_hidden":true,"relations_unclear":false,"relations_hidden":false,"relations_other":"","relations":"Дитина","name_hidden":false,"family_name":"Дев'ятко П. В","name_unclear":false},{"inn":"","relations":"Брат/Сестра","relations_other":"","inn_hidden":false,"family_name":"Дев'ятко О. В","name_hidden":false,"name_unclear":false}],"patronymic":"Володимирович","inn_hidden":true,"family_raw":"","inn_unclear":false,"post":{"post_unclear":false,"region_unclear":false,"post":"голова оболонського районного суду м. києва","candidate":"","office_hidden":false,"region":"м. Київ","post_hidden":false,"office":"Загальний місцевий суд","office_unclear":false,"region_hidden":false},"full_name_suggest":{"output":"Дев'ятко Владислав Володимирович","input":["Дев'ятко Владислав Володимирович","Владислав Володимирович Дев'ятко","Владислав Дев'ятко"]},"full_name":"Дев'ятко Владислав Володимирович","addresses":[{"place_city_type_unclear":false,"place_address":"","place_district_hidden":true,"place_city_type":"","place_address_hidden":true,"place_address_unclear":false,"place_city_type_hidden":true,"place":"","place_district":"","place_unclear":false,"place_city":"","place_city_unclear":false,"place_hidden":true,"place_city_hidden":true,"place_district_unclear":false}],"last_name":"Дев'ятко","last_name_unclear":false,"name_unclear":false},"source":"VULYK","estate":{"23":[{"space_unclear":false,"costs":"","costs_rent_unclear":false,"costs_comment":"","costs_hidden":false,"space_hidden":false,"space_units_unclear":false,"space_units_hidden":false,"costs_comment_unclear":false,"region":"","costs_unclear":false,"space_comment_hidden":false,"costs_rent":"","region_unclear":false,"address_hidden":true,"region_hidden":true,"space_comment":"","space":"10000","address":"","address_unclear":false,"costs_rent_comment":"","costs_rent_hidden":false,"space_units":"м²"}],"25":[{"region_unclear":false,"space_unclear":false,"costs":"","costs_comment":"","costs_hidden":false,"address_hidden":true,"region_hidden":true,"space_comment":"комунальна власність","space_hidden":false,"space":"40.24","space_units_hidden":false,"region":"","address_unclear":false,"costs_rent_comment":"","costs_rent_hidden":false,"space_comment_unclear":false,"space_comment_hidden":false,"space_units":"м²","address":"комун. власність","costs_rent":""},{"space_unclear":false,"costs":"","costs_comment":"","address_hidden":false,"region_hidden":false,"space_comment":"службова","space":"79.78","address":"службова","region":"","address_unclear":true,"costs_rent_comment":"","space_comment_unclear":false,"space_units":"м²","costs_rent":""}],"29":[{"region_unclear":false,"space_unclear":false,"costs_property_hidden":false,"costs_property":"","address_hidden":true,"region_hidden":true,"space_comment":"","space_units_hidden":false,"space_hidden":false,"space":"12100","address":"","region":"","address_unclear":false,"space_units_unclear":false,"space_comment_hidden":false,"space_units":"м²","costs_property_comment":"","costs_rent":"","costs_rent_comment":""}],"30":[{"space_unclear":false,"costs_property_hidden":false,"address_hidden":true,"region_hidden":true,"space_comment":"","space_units_hidden":false,"space_hidden":false,"space":"70.1","address":"","region":"","costs_property":"","space_units_unclear":false,"space_comment_hidden":false,"space_units":"м²","costs_property_comment":"","costs_rent":"","costs_rent_comment":""}],"31":[{"region_unclear":false,"space_unclear":false,"space_hidden":false,"costs_rent_unclear":false,"space_units_unclear":false,"address_hidden":true,"region_hidden":true,"space_comment":"комунальна власність","costs_property_unclear":false,"space":"40.24","space_units_hidden":false,"region":"","address_unclear":false,"costs_rent_comment":"","space_comment_hidden":false,"costs_property":"","space_units":"м²","costs_property_comment":"","costs_rent":"","address":"комун. власність"},{"space_unclear":false,"address_hidden":false,"region_hidden":true,"space_comment":"службова","space":"79.78","address":"службова","region":"","costs_property":"","costs_rent_comment":"","space_comment_unclear":false,"space_units":"м²","costs_property_comment":"","costs_rent":""}]},"intro":{"declaration_year":"2014","isnotdeclaration":"","declaration_year_unclear":false,"declaration_year_hidden":false}}