{"income":{"5":{"value":"187757","family_comment":"","value_unclear":false,"family_hidden":false,"value_hidden":false,"family_unclear":false,"family":"","comment":""},"6":{"value":"187757","family_comment":"","value_unclear":false,"family_unclear":false,"family":"","comment":""},"7":{"source_name_unclear":false,"value":"","comment_hidden":false,"family_comment":"","source_name":"","family":"","comment":"","source_name_hidden":false},"8":{"family_comment":"","value":"","family":"","comment":""},"9":{"value":"","family_comment":"","value_unclear":false,"family_hidden":false,"family_unclear":false,"family":"","comment":"","family_comment_unclear":false},"10":{"family_comment":"","value":"","family":"","comment":""},"11":{"family_comment":"","value":"","family":"","comment":""},"12":{"family_comment":"","value":"","family":"","comment":""},"13":{"family_comment":"","value":"","family":"","comment":""},"14":{"family_comment":"","value":"","family":"","comment":""},"15":{"family_comment":"","value":"","family":"","comment":""},"16":{"family_comment":"","value":"","family":"","comment":""},"17":{"family_comment":"","value":"","family":"","comment":""},"18":{"family_comment":"","value":"","family":"","comment":""},"19":{"family_comment":"","value":"","family":"","comment":""},"20":{"value":"","family_comment":"","value_unclear":false,"family_comment_hidden":false,"family_unclear":false,"family_comment_unclear":false,"comment_unclear":false,"comment":"","family":""}},"vehicle":{"35":[{"year_hidden":false,"brand_info":"2445 куб. см.","sum_rent_comment":"","year":"1985","brand_info_hidden":false,"brand_info_unclear":false,"sum_rent":"","sum":"","brand":"УАЗ 3151","sum_comment":"","brand_unclear":false,"brand_hidden":false}]},"id":"vulyk_93_38","banks":{"47":[{"sum_foreign_comment":"","sum_units":"UAH","sum_comment":"","sum_foreign_units":"UAH","sum":"300","sum_foreign":""}]},"declaration":{"additional_info_text":"","notfull_lostpages":"","date":"2015-03-31T00:00:00","notfull":"","additional_info":"","url":"http://static.declarations.com.ua/declarations/chosen_ones/judges_batch/3484_hulyk_andrii_hryhorovych.pdf"},"liabilities":{"54":{"sum_foreign_comment":"","sum":"","sum_hidden":false,"sum_comment":"","sum_foreign":""},"55":{"sum_foreign_comment":"","sum":"","sum_comment":"","sum_foreign":""},"56":{"sum_foreign_comment":"","sum":"","sum_comment":"","sum_foreign":""},"57":{"sum_foreign_comment":"","sum":"","sum_comment":"","sum_hidden":false,"sum_comment_hidden":false,"sum_unclear":false,"sum_foreign":""},"58":{"sum_foreign_comment":"","sum":"","sum_comment":"","sum_comment_unclear":false,"sum_hidden":false,"sum_unclear":false,"sum_foreign":""},"59":{"sum_foreign_comment":"","sum":"","sum_comment":"","sum_foreign":""},"60":{"sum_foreign_comment":"","sum":"","sum_hidden":false,"sum_comment":"","sum_foreign":""},"61":{"sum_foreign_comment":"","sum":"","sum_comment":"","sum_foreign":""},"62":{"sum_foreign_comment":"","sum":"","sum_comment":"","sum_foreign":""},"63":{"sum_foreign_comment":"","sum":"","sum_comment":"","sum_foreign":""},"64":{"sum_foreign_comment":"","sum":"","sum_comment":"","sum_foreign":""}},"ft_src":"Гулик Андрій Григорович\nсуддя львівського окружного адміністративного суду\nЛьвівська область\nАдміністративний місцевий суд\nАндрій\nГулик Андрій Григорович\nАндрій Григорович Гулик\nАндрій Гулик\nГулик Андрій Григорович\nГулик\nГригорович\n2445 куб. см.\nУАЗ 3151\n1985\n2040\n17.6\n1/4\n82.6\n300\n2014\n2445 куб. см.\nУАЗ 3151\n1985\n17.6\n2040\n1/4\n82.6\nГулик\nГулик Андрій Григорович\nАндрій Григорович Гулик\nАндрій Гулик\nГулик Андрій Григорович\nГулик Андрій Григорович\nГригорович\nАндрій\nЛьвівська область\nАдміністративний місцевий суд\nсуддя львівського окружного адміністративного суду\n187757\n187757\n300\n2014\n187757\n187757\nГулик\nГригорович\nЛьвівська область\nАдміністративний місцевий суд\nсуддя львівського окружного адміністративного суду\nГулик Андрій Григорович\nГулик Андрій Григорович\nАндрій Григорович Гулик\nАндрій Гулик\nГулик Андрій Григорович\nАндрій\nУАЗ 3151\n2445 куб. см.\n1985\n187757\n187757\n1/4\n82.6\n2040\n17.6\n300\n2014","general":{"inn":"","inn_hidden":true,"last_name":"Гулик","post":{"post_unclear":false,"region_unclear":false,"region":"Львівська область","candidate":"","post":"суддя львівського окружного адміністративного суду","office":"Адміністративний місцевий суд","office_unclear":false},"name":"Андрій","full_name":"Гулик Андрій Григорович","family_raw":"","addresses":[{"place_district":"","place_city_hidden":false,"place_city":"","place_city_type_hidden":false,"place_district_hidden":false,"place_city_type":"","place_address_hidden":false,"place_address":"","place_hidden":true,"place":""}],"full_name_suggest":{"output":"Гулик Андрій Григорович","input":["Гулик Андрій Григорович","Андрій Григорович Гулик","Андрій Гулик"]},"patronymic":"Григорович"},"source":"VULYK","estate":{"25":[{"space_hidden":false,"costs":"","costs_comment":"","address_hidden":false,"region_hidden":true,"space_comment":"1/4","space_unclear":false,"space":"82.6","address":"","costs_rent_comment_unclear":false,"region":"","costs_rent_comment":"","space_units":"м²","costs_rent":""}],"28":[{"space_unclear":false,"costs":"","costs_comment":"","address_hidden":false,"region_hidden":true,"space_comment":"","space":"17.6","address":"","region":"","costs_rent_comment":"","space_units":"м²","costs_rent":"2040"}]},"intro":{"declaration_year":"2014","isnotdeclaration":""}}