{"income":{"5":{"family_comment":"","family_unclear":false,"value":"368010","family":"","comment":""},"6":{"family_comment":"","family_unclear":false,"value":"264011","family":"","comment":""},"7":{"value":"","comment_hidden":false,"family_comment":"","source_name":"","family":"","comment":""},"8":{"family_comment":"","value":"","family":"","comment":""},"9":{"family_comment":"","value":"58063","family":"","comment":""},"10":{"family_comment":"","value":"13398","family":"","comment":""},"11":{"family_comment":"","value":"382","value_unclear":false,"family":"","comment":""},"12":{"family_comment":"","value":"","family":"","comment":""},"13":{"family_comment":"","value":"","family":"","comment":""},"14":{"family_comment":"","value":"","family":"","comment":""},"15":{"family_comment":"","value":"","value_unclear":false,"family":"","comment":""},"16":{"family_comment":"","family_unclear":false,"value":"","family":"","comment":""},"17":{"family_comment":"","value":"","family":"","comment":""},"18":{"family_comment":"","value":"","family_hidden":false,"comment":"","family":""},"19":{"family_comment":"","value":"","family":"","comment":""},"20":{"value":"32156","comment_unclear":false,"comment_hidden":false,"family_comment":"","family":"","comment":"","family_comment_hidden":false}},"vehicle":{"40":[{"brand_info":"180 CGI, 1796 куб. см.","sum_rent_comment":"","brand":"Mercedes-Benz C-Class","sum_comment":"","year":"2011","brand_hidden":false,"brand_info_hidden":false,"brand_info_unclear":false,"year_unclear":false,"sum":"","sum_rent":""}]},"id":"vulyk_68_182","banks":{"45":[{"sum_foreign_comment":"","sum_units":"UAH","sum_units_hidden":false,"sum_comment":"","sum_comment_unclear":false,"sum_hidden":false,"sum_foreign_units":"UAH","sum_comment_hidden":false,"sum_unclear":false,"sum":"898540","sum_foreign":""},{"sum_foreign_comment":"","sum_units":"UAH","sum_comment":"","sum_foreign_units":"UAH","sum_comment_hidden":false,"sum":"3920","sum_foreign":""}],"46":[{"sum_foreign_comment":"","sum_units":"UAH","sum_comment":"","sum_foreign_units":"UAH","sum":"3920","sum_foreign":""}]},"declaration":{"additional_info_text":"","notfull_lostpages":"","date":"2015-03-27T00:00:00","notfull":"","additional_info":"","url":"http://static.declarations.com.ua/declarations/chosen_ones/mega_batch/diakovych_viktor_petrovych.pdf"},"liabilities":{"54":{"sum_foreign_comment":"","sum":"","sum_comment":"","sum_comment_unclear":false,"sum_hidden":false,"sum_comment_hidden":false,"sum_unclear":false,"sum_foreign":""},"55":{"sum_foreign_comment":"","sum":"","sum_hidden":false,"sum_comment":"","sum_foreign":""},"56":{"sum_foreign_comment":"","sum_foreign_hidden":false,"sum_comment":"","sum":"","sum_unclear":false,"sum_foreign":""},"57":{"sum_foreign_comment":"","sum":"","sum_comment":"","sum_comment_unclear":false,"sum_hidden":false,"sum_comment_hidden":false,"sum_unclear":false,"sum_foreign":""},"58":{"sum_foreign_comment":"","sum":"","sum_comment":"","sum_hidden":false,"sum_comment_hidden":false,"sum_unclear":false,"sum_foreign":""},"59":{"sum_foreign_comment":"","sum":"","sum_comment":"","sum_foreign":""},"60":{"sum_foreign_comment":"","sum":"","sum_comment":"","sum_comment_unclear":false,"sum_hidden":false,"sum_comment_hidden":false,"sum_unclear":false,"sum_foreign":""},"61":{"sum_foreign_comment":"","sum":"","sum_hidden":false,"sum_comment":"","sum_foreign":""},"62":{"sum_foreign_comment":"","sum":"","sum_comment":"","sum_unclear":false,"sum_foreign":""},"63":{"sum_foreign_comment":"","sum":"","sum_comment":"","sum_hidden":false,"sum_comment_hidden":false,"sum_unclear":false,"sum_foreign":""},"64":{"sum_foreign_comment":"","sum":"","sum_comment":"","sum_hidden":false,"sum_comment_hidden":false,"sum_foreign":""}},"ft_src":"суддя львівського апеляційного адміністративного суду\nЛьвівська область\nАпеляційний адміністративний суд\nВіктор\nДякович М. М\nПодружжя\nПетрович\nДякович Віктор Петрович\nВіктор Петрович Дякович\nВіктор Дякович\nДякович Віктор Петрович\nДякович Віктор Петрович\nДякович\n180 CGI, 1796 куб. см.\nMercedes-Benz C-Class\n2011\n3920\n898540\n3920\n2014\n180 CGI, 1796 куб. см.\n2011\nMercedes-Benz C-Class\n898540\n3920\n3920\n13480\n4.9924\nСпадщина\n950\n288.6\nДякович Віктор Петрович\nВіктор Петрович Дякович\nВіктор Дякович\nДякович Віктор Петрович\nДякович Віктор Петрович\nПодружжя\nДякович М. М\nВіктор\nПетрович\nАпеляційний адміністративний суд\nЛьвівська область\nсуддя львівського апеляційного адміністративного суду\nДякович\n264011\n32156\n368010\n382\n13398\n58063\n2014\n13480\nСпадщина\n4.9924\n288.6\n950\nПодружжя\nДякович М. М\nПетрович\nДякович\nВіктор\nДякович Віктор Петрович\nВіктор Петрович Дякович\nВіктор Дякович\nДякович Віктор Петрович\nЛьвівська область\nАпеляційний адміністративний суд\nсуддя львівського апеляційного адміністративного суду\nДякович Віктор Петрович\n264011\n382\n13398\n368010\n58063\n32156\nMercedes-Benz C-Class\n180 CGI, 1796 куб. см.\n2011\n382\n13398\n32156\n368010\n58063\n264011\n288.6\n13480\nСпадщина\n4.9924\n950\n898540\n3920\n3920\n2014","general":{"inn":"","name":"Віктор","inn_unclear":false,"family":[{"inn":"","inn_hidden":false,"relations_unclear":false,"relations_hidden":false,"relations_other":"","relations":"Подружжя","name_hidden":false,"inn_unclear":false,"family_name":"Дякович М. М","name_unclear":false}],"inn_hidden":false,"family_raw":"","last_name":"Дякович","post":{"post_unclear":false,"region_unclear":false,"post":"суддя львівського апеляційного адміністративного суду","office":"Апеляційний адміністративний суд","region":"Львівська область","post_hidden":false,"office_hidden":false,"office_unclear":false,"region_hidden":false},"full_name_suggest":{"output":"Дякович Віктор Петрович","input":["Дякович Віктор Петрович","Віктор Петрович Дякович","Віктор Дякович"]},"full_name":"Дякович Віктор Петрович","patronymic":"Петрович","last_name_unclear":false,"name_unclear":false},"source":"VULYK","estate":{"23":[{"costs":"","costs_comment":"","address_hidden":false,"region_hidden":true,"space_comment":"","space":"13480","address":"","region":"","costs_rent_comment":"","space_comment_hidden":false,"space_units":"м²","costs_rent":""},{"costs_rent":"","region":"","costs":"","costs_rent_comment":"","costs_comment":"","address_hidden":false,"region_hidden":false,"space_comment":"Спадщина","space_units":"га","space":"4.9924","address":""}],"29":[{"space_unclear":false,"address_hidden":false,"region_hidden":true,"space_comment":"","space_units_hidden":false,"space_hidden":false,"space":"950","address":"","region":"","costs_property":"","space_units_unclear":false,"space_units":"м²","costs_property_comment":"","costs_rent":"","costs_rent_comment":""}],"30":[{"space_unclear":false,"address_hidden":false,"region_hidden":true,"space_comment":"","space_hidden":false,"space":"288.6","address":"","region":"","costs_property":"","costs_rent_comment":"","space_units":"м²","costs_property_comment":"","costs_rent":""}]},"intro":{"declaration_year":"2014","isnotdeclaration":""}}