{"id":"vulyk_109_27","ft_src":"2.2\n2003\nOpel Vectra\n600\n386\n80\n1000\n103\nприватизаційні сертифікати\n500\nприватизаційні сертифікати\n17\nСпадщина\n9219\n2015\n2.2\n2003\nOpel Vectra\n2015\nДем'як Валентина Миколаївна\nВалентина Миколаївна Дем'як\nВалентина Дем'як\nДем'як Валентина Миколаївна\nВалентина\nДитина\nДем'як П. Ю\nДем'як Валентина Миколаївна\nМиколаївна\nГосподарський місцевий суд\nВолинська область\nсуддя господарського суду волинської області\nДем'як\n57688\n118521\n100\nНаціональнашкола суддів України Львівське регіоеальне відділення\n362\nНаціональна школа суддів України, Львівське регіональне відділення\n229353\n8877\nКредит овердрафт\n79659\n309368\n8877\n600\n386\n1000\n80\n103\n9219\nСпадщина\nприватизаційні сертифікати\n17\n500\nприватизаційні сертифікати\n57688\n118521\n100\n8877\n229353\nНаціональна школа суддів України, Львівське регіональне відділення\nНаціональнашкола суддів України Львівське регіоеальне відділення\n362\n8877\n309368\nКредит овердрафт\n79659\nДитина\nДем'як П. Ю\nМиколаївна\nДем'як\nВалентина\nДем'як Валентина Миколаївна\nВалентина Миколаївна Дем'як\nВалентина Дем'як\nДем'як Валентина Миколаївна\nВолинська область\nГосподарський місцевий суд\nсуддя господарського суду волинської області\nДем'як Валентина Миколаївна","estate":{"23":[{"address":"","space_units":"м²","costs_rent_unclear":false,"costs_comment":"","space_unclear":false,"region_hidden":true,"space_comment":"","address_hidden":true,"costs":"","costs_rent_comment":"","space":"600","region":"","costs_rent":""},{"address":"","space_units":"м²","costs_rent_unclear":false,"space_hidden":false,"space_comment":"","region_hidden":false,"costs_comment":"","address_hidden":false,"space":"386","costs_rent_comment":"","costs":"","region":"","costs_rent":""}],"25":[{"address":"","space_units":"м²","space_hidden":false,"space_unclear":false,"region_hidden":true,"costs_comment":"","space_comment":"","address_hidden":true,"space":"103","costs_rent_comment":"","costs":"","region":"","space_units_hidden":false,"costs_rent":""}],"29":[{"costs_property_comment":"","address":"","space_units":"м²","space_unclear":false,"region_hidden":true,"costs_property":"","space_comment":"","address_hidden":true,"costs_rent_comment":"","space":"1000","region":"","costs_rent":""}],"30":[{"costs_property_comment":"","address":"","space_units":"м²","costs_rent_comment":"","space_hidden":false,"region_hidden":true,"costs_property":"","space_comment":"","space":"80","address_hidden":true,"costs_rent":""}]},"vehicle":{"40":[{"sum_comment":"","brand_info":"2.2","sum":"","sum_rent_comment":"","year":"2003","brand":"Opel Vectra","sum_rent":"","brand_info_unclear":false}]},"source":"VULYK","income":{"5":{"family_comment":"","value":"309368","family":"8877","comment":""},"6":{"family_comment":"","value":"229353","family":"8877","comment":""},"7":{"source_name_hidden":false,"family_comment":"","comment":"Національнашкола суддів України Львівське регіоеальне відділення","family":"","comment_hidden":false,"value":"362","source_name":"Національна школа суддів України, Львівське регіональне відділення"},"8":{"family_comment":"","family_hidden":false,"value":"","family":"","comment":""},"9":{"family_comment":"","family":"","comment":"","value_unclear":false,"family_unclear":false,"value":""},"10":{"family_comment":"","value":"","family":"","comment":""},"11":{"family_comment":"","value":"","family":"","comment":""},"12":{"family_comment":"","value":"","family":"","comment":""},"13":{"family_comment":"","value":"","family":"","comment":""},"14":{"family_comment":"","value":"","family":"","comment":""},"15":{"family_comment":"","value":"","family":"","comment":""},"16":{"family_comment":"","value":"","family":"","comment":""},"17":{"family_comment":"","value":"","family":"","comment":""},"18":{"family_comment":"","value":"","family":"","comment":""},"19":{"family_comment":"","value":"","family":"","comment":""},"20":{"family_comment":"","family":"","comment":"Кредит овердрафт","value_unclear":false,"family_hidden":false,"value":"79659"}},"banks":{"45":[{"sum_units":"UAH","sum_comment":"Спадщина","sum_foreign_units":"UAH","sum":"9219","sum_units_hidden":false,"sum_foreign_comment":"","sum_foreign":"","sum_unclear":false,"sum_comment_hidden":false}],"47":[{"sum_comment_unclear":true,"sum_comment":"приватизаційні сертифікати","sum_foreign_units":"UAH","sum":"500","sum_foreign_comment":"","sum_foreign":"","sum_units":"UAH"}],"52":[{"sum_comment_unclear":true,"sum_comment":"приватизаційні сертифікати","sum_foreign_units_hidden":false,"sum_foreign_units":"UAH","sum":"17","sum_foreign_comment":"","sum_foreign":"","sum_foreign_hidden":false,"sum_units":"UAH"}]},"declaration":{"notfull_lostpages":"","additional_info_text":"","additional_info":"","date":"2016-03-30T00:00:00","notfull":"","url":"http://static.declarations.com.ua/declarations/chosen_ones/judges_batch/2484_dem_iak_valentyna_mykolaivna_2015.pdf"},"general":{"family_raw":"","name":"Валентина","full_name_suggest":{"input":["Дем'як Валентина Миколаївна","Валентина Миколаївна Дем'як","Валентина Дем'як"],"output":"Дем'як Валентина Миколаївна"},"patronymic":"Миколаївна","inn_hidden":true,"addresses":[{"place_city_type_hidden":false,"place_city_type":"","place_city_hidden":true,"place_hidden":true,"place_district":"","place_district_hidden":true,"place":"","place_address":"","place_address_hidden":true,"place_city":""}],"inn":"","inn_unclear":false,"last_name":"Дем'як","full_name":"Дем'як Валентина Миколаївна","family":[{"inn":"","family_name":"Дем'як П. Ю","relations_hidden":false,"name_unclear":false,"relations":"Дитина","inn_hidden":true,"name_hidden":false,"relations_other":""}],"post":{"office":"Господарський місцевий суд","post":"суддя господарського суду волинської області","office_unclear":false,"region_hidden":false,"region":"Волинська область","office_hidden":false,"region_unclear":false},"name_hidden":false},"liabilities":{"54":{"sum_comment":"","sum_hidden":false,"sum":"100","sum_foreign_comment":"","sum_foreign":"","sum_unclear":false,"sum_comment_hidden":false},"55":{"sum_comment":"","sum_comment_unclear":false,"sum_foreign_comment":"","sum":"","sum_foreign":""},"56":{"sum_comment":"","sum_foreign_comment":"","sum_foreign":"","sum":""},"57":{"sum_comment":"","sum_foreign_comment":"","sum_foreign":"","sum":"118521","sum_comment_hidden":false},"58":{"sum_comment":"","sum_foreign_comment":"","sum_foreign":"","sum":"57688","sum_comment_hidden":false},"59":{"sum_comment":"","sum_foreign_comment":"","sum_foreign":"","sum":""},"60":{"sum_comment":"","sum_foreign_comment":"","sum_foreign":"","sum":""},"61":{"sum_comment":"","sum_foreign_comment":"","sum_foreign":"","sum":""},"62":{"sum_comment":"","sum_foreign_comment":"","sum_foreign":"","sum":""},"63":{"sum_comment":"","sum_foreign_comment":"","sum_foreign":"","sum":""},"64":{"sum_comment":"","sum_foreign_comment":"","sum_foreign":"","sum":""}},"intro":{"isnotdeclaration":"","declaration_year":"2015"}}