{"id":"vulyk_75_12","ft_src":"1796 куб.см., 140 к. с., 446 см\n2007\nOpel Zafira\n81\n600\n15\n68.11\n3, 6, 8\n1\n2014\n36000\n255682\n11000\n36000\n347150\n80468\n1796 куб.см., 140 к. с., 446 см\n2007\nOpel Zafira\n3, 6, 8\n1\n2014\nЛіпчанська\nВолодимирівна\nПодружжя\nЛіпчанський Олександр Миколайович\nЛіпчанська Надія Володимирівна\nНадія Володимирівна Ліпчанська\nНадія Ліпчанська\nЛіпчанська Надія Володимирівна\nНадія\nЛіпчанська Надія Володимирівна\nАпеляційний господарський суд\nсуддя одеського апеляційного господарського суду\nОдеська область\n255682\n36000\n80468\n347150\n36000\n11000\n600\n81\n68.11\n15\nЛіпчанський Олександр Миколайович\nПодружжя\nЛіпчанська\nВолодимирівна\nсуддя одеського апеляційного господарського суду\nОдеська область\nАпеляційний господарський суд\nЛіпчанська Надія Володимирівна\nЛіпчанська Надія Володимирівна\nНадія Володимирівна Ліпчанська\nНадія Ліпчанська\nЛіпчанська Надія Володимирівна\nНадія","estate":{"25":[{"address":"","space_units":"м²","space_hidden":false,"space_unclear":false,"region_hidden":true,"costs_comment":"","space_comment":"","address_hidden":true,"space":"68.11","costs_rent_comment":"","costs":"","region":"","costs_rent":""}],"29":[{"costs_property_comment":"","costs_property":"","address":"","space_units":"м²","space_comment":"","region_hidden":true,"space_units_unclear":false,"region":"","address_hidden":true,"costs_rent_comment":"","space":"600","costs_rent":""}],"31":[{"costs_property_comment":"","address":"","space_units":"м²","space_unclear":false,"region_hidden":true,"costs_property":"","space_comment":"","address_hidden":true,"costs_rent_comment":"","space":"81","region":"","costs_rent":""}],"32":[{"costs_property_comment":"","address":"","space_units":"м²","costs_rent_comment":"","space":"15","region":"","region_hidden":true,"costs_property":"","space_comment":"","address_hidden":true,"costs_rent":""}]},"vehicle":{"40":[{"sum_comment":"","brand_info":"1796 куб.см., 140 к. с., 446 см","sum":"","sum_rent_comment":"","year":"2007","brand":"Opel Zafira","sum_rent":"","brand_info_unclear":false}]},"source":"VULYK","income":{"5":{"family_comment":"","value":"347150","family":"36000","comment":""},"6":{"family_comment":"","family_hidden":false,"value":"255682","family":"36000","comment":""},"7":{"family":"","family_comment":"","value":"","comment":"","source_name":""},"8":{"family_comment":"","value":"","family":"","comment":""},"9":{"family_comment":"","family":"","comment":"","value_unclear":false,"family_hidden":false,"value":"11000"},"10":{"family":"","family_comment":"","comment":"","value_hidden":false,"value":"","family_hidden":false,"family_unclear":false},"11":{"family_comment":"","value":"","family":"","comment":""},"12":{"family_comment":"","value":"","family":"","comment":""},"13":{"family_comment":"","value":"","family":"","comment":""},"14":{"family_comment":"","value":"","family":"","comment":""},"15":{"family_comment":"","value":"","family":"","comment":""},"16":{"family_comment":"","value":"","family":"","comment":""},"17":{"family_comment":"","value":"","family":"","comment":""},"18":{"family_comment":"","value":"","family":"","comment":""},"19":{"family_comment":"","value":"","family":"","comment":""},"20":{"family_comment":"","comment":"","family":"","comment_unclear":false,"value":"80468","family_comment_unclear":false}},"general":{"inn":"","addresses":[{"place_city_type_hidden":true,"place_city_type":"","place_city_hidden":true,"place_hidden":true,"place_district":"","place_district_hidden":true,"place":"","place_city":"","place_address_hidden":true,"place_address":""}],"last_name":"Ліпчанська","full_name":"Ліпчанська Надія Володимирівна","family":[{"inn":"","family_name":"Ліпчанський Олександр Миколайович","relations_other":"","relations_hidden":false,"name_unclear":false,"inn_hidden":true,"name_hidden":true,"relations":"Подружжя"}],"patronymic":"Володимирівна","inn_hidden":true,"name":"Надія","post":{"office":"Апеляційний господарський суд","region":"Одеська область","post":"суддя одеського апеляційного господарського суду"},"family_raw":"","full_name_suggest":{"input":["Ліпчанська Надія Володимирівна","Надія Володимирівна Ліпчанська","Надія Ліпчанська"],"output":"Ліпчанська Надія Володимирівна"}},"liabilities":{"54":{"sum_comment":"","sum_foreign_comment":"","sum_foreign":"","sum":""},"55":{"sum_comment":"","sum_foreign_comment":"","sum_foreign":"","sum":""},"56":{"sum_comment":"","sum_foreign_comment":"","sum_foreign":"","sum":""},"57":{"sum_comment":"","sum_foreign_comment":"","sum_foreign":"","sum":""},"58":{"sum_comment":"","sum_foreign_comment":"","sum_foreign":"","sum":""},"59":{"sum_comment_unclear":false,"sum_comment":"","sum":"","sum_foreign_comment":"","sum_foreign":"","sum_unclear":false},"60":{"sum_comment":"","sum_foreign_comment":"","sum_foreign":"","sum":""},"61":{"sum_comment":"","sum_foreign_comment":"","sum_foreign":"","sum":""},"62":{"sum_comment":"","sum_foreign_comment":"","sum_foreign":"","sum_unclear":false,"sum":""},"63":{"sum_comment":"","sum_foreign_comment":"","sum_foreign":"","sum":""},"64":{"sum_comment":"","sum_foreign_comment":"","sum_foreign":"","sum":""}},"declaration":{"notfull_lostpages":"3, 6, 8","additional_info_text":"","additional_info":"","date":"2015-03-30T00:00:00","notfull":"1","url":"http://static.declarations.com.ua/declarations/chosen_ones/judges_batch/1923_lipchanska_nadiia_volodymyrivna.pdf"},"intro":{"isnotdeclaration":"","declaration_year":"2014"}}