{"income":{"5":{"value":"190250.67","family_comment":"","value_unclear":false,"family_unclear":false,"family":"","comment":""},"6":{"value":"190250.67","family_comment":"","value_unclear":false,"family_unclear":false,"family":"","comment":""},"7":{"family_comment":"","value":"","source_name":"","family":"","comment":""},"8":{"family_comment":"","value":"","family":"","comment":""},"9":{"family_comment":"","value":"1.83","family":"","comment":""},"10":{"family_comment":"","value":"","family":"","comment":""},"11":{"family_comment":"","value":"","family":"","comment":""},"12":{"family_comment":"","value":"","family":"","comment":""},"13":{"family_comment":"","value":"","family":"","comment":""},"14":{"family_comment":"","value":"","family":"","comment":""},"15":{"family_comment":"","value":"","value_unclear":false,"family":"","comment":""},"16":{"family_comment":"","value":"","family":"","comment":""},"17":{"family_comment":"","value":"","family":"","comment":""},"18":{"family_comment":"","value":"","family":"","comment":""},"19":{"family_comment":"","value":"","family":"","comment":""},"20":{"value":"","family_comment":"","value_unclear":false,"family_unclear":false,"family":"","comment":"","family_comment_unclear":false}},"id":"vulyk_99_46","banks":{"45":[{"sum_foreign_comment":"","sum_units":"UAH","sum_comment":"Ощадбанк України","sum_foreign_units":"UAH","sum_comment_hidden":false,"sum":"1000","sum_foreign":""}]},"declaration":{"date":"2016-03-17T00:00:00","notfull":"","url":"http://static.declarations.com.ua/declarations/chosen_ones/judges_batch/595_zhytniak_larysa_oleksandrivna_2015.pdf","notfull_lostpages":""},"liabilities":{"54":{"sum_foreign_comment":"","sum":"","sum_comment":"","sum_comment_unclear":false,"sum_comment_hidden":false,"sum_foreign":""},"55":{"sum_foreign_comment":"","sum":"","sum_comment":"","sum_foreign":""},"56":{"sum_foreign_comment":"","sum":"11958.52","sum_comment":"","sum_foreign":""},"57":{"sum_foreign_comment":"","sum_comment_hidden":false,"sum":"","sum_comment":"","sum_foreign":""},"58":{"sum_foreign_comment":"","sum_comment_hidden":false,"sum":"","sum_comment":"","sum_foreign":""},"59":{"sum_foreign_comment":"","sum":"","sum_comment":"","sum_comment_hidden":false,"sum_unclear":false,"sum_foreign":""},"60":{"sum_foreign_comment":"","sum_comment_hidden":false,"sum":"","sum_comment":"","sum_foreign":""},"61":{"sum_foreign_comment":"","sum":"","sum_comment":"","sum_foreign":""},"62":{"sum_foreign_comment":"","sum":"","sum_comment":"","sum_foreign":""},"63":{"sum_foreign_comment":"","sum_comment_hidden":false,"sum":"","sum_comment":"","sum_foreign":""},"64":{"sum_foreign_comment":"","sum_comment_hidden":false,"sum":"","sum_comment":"","sum_foreign":""}},"ft_src":"11958.52\nЖитняк Лариса Олександрівна\nсуддя чернігівського окружного адміністративного суду\nЧернігівська область\nАдміністративний місцевий суд\nЛариса\nЖитняк Лариса Олександрівна\nЛариса Олександрівна Житняк\nЛариса Житняк\nЖитняк Лариса Олександрівна\nЖитняк\nОлександрівна\n1.83\n190250.67\n190250.67\nОщадбанк України\n1000\n55.03\n2015\n190250.67\n1.83\n190250.67\nОщадбанк України\n1000\n2015\nЖитняк\nЖитняк Лариса Олександрівна\nЛариса Олександрівна Житняк\nЛариса Житняк\nЖитняк Лариса Олександрівна\nЛариса\nОлександрівна\nЖитняк Лариса Олександрівна\nАдміністративний місцевий суд\nсуддя чернігівського окружного адміністративного суду\nЧернігівська область\n11958.52\n190250.67\n190250.67\n1.83\n55.03\n11958.52\nЖитняк\nОлександрівна\nсуддя чернігівського окружного адміністративного суду\nЧернігівська область\nАдміністративний місцевий суд\nЖитняк Лариса Олександрівна\nЖитняк Лариса Олександрівна\nЛариса Олександрівна Житняк\nЛариса Житняк\nЖитняк Лариса Олександрівна\nЛариса\n55.03\nОщадбанк України\n1000\n2015","general":{"inn":"","inn_hidden":true,"last_name":"Житняк","post":{"post_unclear":false,"office":"Адміністративний місцевий суд","post":"суддя чернігівського окружного адміністративного суду","region":"Чернігівська область"},"name":"Лариса","full_name":"Житняк Лариса Олександрівна","family_raw":"","addresses":[{"place_district":"","place_city_hidden":true,"place_city":"","place_city_type_hidden":false,"place_district_hidden":false,"place_city_type":"","place_address_hidden":true,"place_address":"","place_hidden":true,"place":""}],"full_name_suggest":{"output":"Житняк Лариса Олександрівна","input":["Житняк Лариса Олександрівна","Лариса Олександрівна Житняк","Лариса Житняк"]},"patronymic":"Олександрівна"},"source":"VULYK","estate":{"25":[{"space_hidden":false,"costs":"","costs_comment":"","address_hidden":false,"region_hidden":true,"space_comment":"","space_unclear":false,"space":"55.03","address":"","region":"","costs_rent_comment":"","space_units":"м²","costs_rent":""}]},"intro":{"declaration_year":"2015"}}