{"income":{"5":{"value":"181888.98","family_comment":"","value_unclear":false,"family_hidden":false,"value_hidden":false,"family_unclear":false,"family":"52532.09","comment":""},"6":{"value":"181888.98","family_comment":"","value_unclear":false,"family_unclear":false,"family":"52532.09","comment":""},"7":{"source_name_unclear":false,"value":"","comment_hidden":false,"family_comment":"","source_name":"","family":"","comment":"","source_name_hidden":false},"8":{"family_comment":"","value":"","family":"","comment":""},"9":{"value":"","family_comment":"","value_unclear":false,"family_hidden":false,"family_unclear":false,"family":"","comment":"","family_comment_unclear":false},"10":{"family_comment":"","value":"","family":"","comment":""},"11":{"family_comment":"","value":"","family":"","comment":""},"12":{"family_comment":"","value":"","family":"","comment":""},"13":{"family_comment":"","value":"","family":"","comment":""},"14":{"family_comment":"","value":"","family":"","comment":""},"15":{"family_comment":"","value":"","family":"","comment":""},"16":{"family_comment":"","value":"","family":"","comment":""},"17":{"family_comment":"","value":"","family":"","comment":""},"18":{"family_comment":"","value":"","family":"","comment":""},"19":{"family_comment":"","value":"","family":"","comment":""},"20":{"value":"","family_comment":"","value_unclear":false,"family_comment_hidden":false,"family_unclear":false,"family_comment_unclear":false,"comment_unclear":false,"comment":"","family":""}},"vehicle":{"35":[{"year_hidden":false,"brand_info":"1200 куб. см.","sum_rent_comment":"","year":"2006","brand_info_hidden":false,"brand_info_unclear":false,"sum_rent":"","sum":"30100","brand":"Skoda Fabia","sum_comment":"","brand_unclear":false,"brand_hidden":false}]},"id":"vulyk_93_69","declaration":{"additional_info_text":"","notfull_lostpages":"","date":"2015-03-27T00:00:00","notfull":"","additional_info":"","url":"http://static.declarations.com.ua/declarations/chosen_ones/judges_batch/3515_kos_ihor_bohdanovych.pdf"},"liabilities":{"54":{"sum_foreign_comment":"","sum":"","sum_hidden":false,"sum_comment":"","sum_foreign":""},"55":{"sum_foreign_comment":"","sum":"","sum_comment":"","sum_foreign":""},"56":{"sum_foreign_comment":"","sum":"10250","sum_comment":"","sum_foreign":""},"57":{"sum_foreign_comment":"","sum":"","sum_comment":"","sum_hidden":false,"sum_comment_hidden":false,"sum_unclear":false,"sum_foreign":""},"58":{"sum_foreign_comment":"","sum":"","sum_comment":"","sum_comment_unclear":false,"sum_hidden":false,"sum_unclear":false,"sum_foreign":""},"59":{"sum_foreign_comment":"","sum":"","sum_comment":"","sum_foreign":""},"60":{"sum_foreign_comment":"","sum":"","sum_hidden":false,"sum_comment":"","sum_foreign":""},"61":{"sum_foreign_comment":"","sum":"","sum_comment":"","sum_foreign":""},"62":{"sum_foreign_comment":"","sum":"17200","sum_comment":"","sum_foreign":""},"63":{"sum_foreign_comment":"","sum":"","sum_comment":"","sum_foreign":""},"64":{"sum_foreign_comment":"","sum":"","sum_comment":"","sum_foreign":""}},"ft_src":"17200\n10250\nКос Ігор Богданович\nсуддя буського районного суду львівської області\nЛьвівська область\nЗагальний місцевий суд\nІгор\nПодружжя\nДитина\nКос Ігор Богданович\nІгор Богданович Кос\nІгор Кос\nКос Ігор Богданович\nКос\nБогданович\n1200 куб. см.\n30100\nSkoda Fabia\n2006\n106\n2014\n52532.09\n181888.98\n52532.09\n181888.98\n1200 куб. см.\n30100\nSkoda Fabia\n2006\n106\nКос\nПодружжя\nДитина\nКос Ігор Богданович\nІгор Богданович Кос\nІгор Кос\nКос Ігор Богданович\nКос Ігор Богданович\nІгор\nБогданович\nЛьвівська область\nЗагальний місцевий суд\nсуддя буського районного суду львівської області\n10250\n17200\n52532.09\n181888.98\n181888.98\n52532.09\n2014\n10250\n17200\nПодружжя\nДитина\nКос\nБогданович\nЛьвівська область\nЗагальний місцевий суд\nсуддя буського районного суду львівської області\nКос Ігор Богданович\nКос Ігор Богданович\nІгор Богданович Кос\nІгор Кос\nКос Ігор Богданович\nІгор\nSkoda Fabia\n30100\n1200 куб. см.\n2006\n181888.98\n52532.09\n181888.98\n52532.09\n106\n2014","general":{"inn":"","inn_hidden":true,"last_name":"Кос","post":{"post_unclear":false,"region_unclear":false,"region":"Львівська область","candidate":"","post":"суддя буського районного суду львівської області","office":"Загальний місцевий суд","office_unclear":false},"name":"Ігор","full_name":"Кос Ігор Богданович","family_raw":"","addresses":[{"place_district":"","place_city_hidden":true,"place_city":"","place_city_type_hidden":true,"place_district_hidden":true,"place_city_type":"","place_address_hidden":true,"place_address":"","place_hidden":true,"place":""}],"family":[{"inn":"","relations":"Подружжя","relations_hidden":false,"inn_hidden":true,"relations_other":"","name_hidden":true,"family_name":"","name_unclear":false},{"inn":"","relations":"Дитина","relations_other":"","inn_hidden":false,"family_name":"","name_hidden":true,"name_unclear":false}],"full_name_suggest":{"output":"Кос Ігор Богданович","input":["Кос Ігор Богданович","Ігор Богданович Кос","Ігор Кос"]},"patronymic":"Богданович"},"source":"VULYK","estate":{"31":[{"space_hidden":false,"address_hidden":true,"region_hidden":true,"space_comment":"","space":"106","address":"","region":"","costs_property":"","costs_rent_comment":"","space_comment_unclear":false,"space_units":"м²","costs_property_comment":"","costs_rent":""}]},"intro":{"declaration_year":"2014","isnotdeclaration":""}}