{"income":{"5":{"value":"246601.04","family_comment":"","value_unclear":false,"comment_hidden":false,"family_hidden":false,"value_hidden":false,"family_unclear":false,"family":"","comment":""},"6":{"value":"246601.04","family_comment":"","value_unclear":false,"family_hidden":false,"family_unclear":false,"comment_unclear":false,"comment":"","family":""},"7":{"source_name_unclear":false,"value":"","value_hidden":false,"family_comment":"","source_name":"","family":"","comment":"","source_name_hidden":false},"8":{"value":"","family_hidden":false,"value_hidden":false,"family_comment":"","family":"","comment":""},"9":{"value":"","family_comment":"","value_unclear":false,"family_hidden":false,"value_hidden":false,"family_unclear":false,"family":"","comment":""},"10":{"family_comment":"","value":"","family":"","comment":""},"11":{"family_comment":"","value":"","family":"","comment":""},"12":{"family_comment":"","value":"","family":"","comment":""},"13":{"family_comment":"","value":"","family":"","comment":""},"14":{"family_comment":"","value":"","family":"","comment":""},"15":{"family_comment":"","value":"","family":"","comment":""},"16":{"value":"","family_comment":"","value_unclear":false,"family_unclear":false,"family":"","comment":""},"17":{"family_comment":"","value":"","family":"","comment":""},"18":{"family_comment":"","value":"","family":"","comment":""},"19":{"family_comment":"","value":"","comment_unclear":false,"family":"","comment":""},"20":{"value":"","family_comment":"","value_unclear":false,"comment_hidden":false,"family_hidden":false,"family":"12001","value_hidden":false,"family_unclear":false,"comment_unclear":false,"comment":"","family_comment_unclear":false}},"vehicle":{"35":[{"brand_info":"1591 куб. см.","sum_rent_comment":"","brand":"Hyundai Accent","sum_comment":"","brand_unclear":false,"year":"2012","brand_info_unclear":false,"sum":"","sum_rent":""}]},"id":"vulyk_63_6","declaration":{"additional_info_text":"","notfull_lostpages":"","date":"2015-03-23T00:00:00","notfull":"","additional_info":"","url":"http://static.declarations.com.ua/declarations/chosen_ones/mega_batch/koblova_olha_dmytrivna.pdf"},"liabilities":{"54":{"sum_foreign_comment":"","sum":"","sum_comment":"","sum_unclear":false,"sum_foreign":""},"55":{"sum_foreign_comment":"","sum":"","sum_comment":"","sum_foreign":""},"56":{"sum_foreign_comment":"","sum":"63600","sum_comment":"","sum_unclear":false,"sum_foreign":""},"57":{"sum_foreign_comment":"","sum":"51739","sum_comment":"","sum_comment_hidden":false,"sum_unclear":false,"sum_foreign":""},"58":{"sum_foreign_comment":"","sum_comment_hidden":false,"sum":"11861","sum_comment":"","sum_foreign":""},"59":{"sum_foreign_comment":"","sum":"","sum_comment":"","sum_foreign":""},"60":{"sum_foreign_comment":"","sum":"","sum_comment":"","sum_comment_unclear":false,"sum_foreign":""},"61":{"sum_foreign_comment":"","sum":"","sum_comment":"","sum_unclear":false,"sum_foreign":""},"62":{"sum_foreign_comment":"","sum":"","sum_comment":"","sum_unclear":false,"sum_foreign":""},"63":{"sum_foreign_comment":"","sum":"","sum_comment":"","sum_hidden":false,"sum_comment_hidden":false,"sum_unclear":false,"sum_foreign":""},"64":{"sum_foreign_comment":"","sum_comment_hidden":false,"sum":"","sum_comment":"","sum_foreign":""}},"ft_src":"51739\n11861\n63600\nсуддя малиновського районного суду м. одеси\nОдеська область\nЗагальний місцевий суд\nОльга\nКоблов Артем Олександрович\nДитина\nДмитрівна\nКоблова\nКоблова Ольга Дмитрівна\nКоблова Ольга Дмитрівна\nОльга Дмитрівна Коблова\nОльга Коблова\nКоблова Ольга Дмитрівна\n12001\n246601.04\n246601.04\n2012\n1591 куб. см.\nHyundai Accent\n2012\nHyundai Accent\n1591 куб. см.\n2014\n246601.04\n246601.04\n12001\n1591 куб. см.\n2012\nHyundai Accent\n246601.04\n12001\n246601.04\nКоблова Ольга Дмитрівна\nОльга Дмитрівна Коблова\nОльга Коблова\nКоблова Ольга Дмитрівна\nОльга\nДитина\nКоблов Артем Олександрович\nКоблова Ольга Дмитрівна\nКоблова\nЗагальний місцевий суд\nОдеська область\nсуддя малиновського районного суду м. одеси\nДмитрівна\n51739\n63600\n11861\n2014\n11861\n51739\n63600\nДитина\nКоблов Артем Олександрович\nДмитрівна\nКоблова\nКоблова Ольга Дмитрівна\nОльга Дмитрівна Коблова\nОльга Коблова\nКоблова Ольга Дмитрівна\nОльга\nОдеська область\nсуддя малиновського районного суду м. одеси\nЗагальний місцевий суд\nКоблова Ольга Дмитрівна\n2014","general":{"name_hidden":false,"name":"Ольга","patronymic_unclear":false,"last_name_hidden":false,"inn":"","family":[{"inn":"","inn_hidden":false,"relations_unclear":false,"relations_hidden":false,"relations_other":"","relations":"Дитина","name_hidden":false,"inn_unclear":false,"family_name":"Коблов Артем Олександрович","name_unclear":false}],"patronymic":"Дмитрівна","inn_hidden":false,"family_raw":"","inn_unclear":false,"post":{"post_unclear":false,"region_unclear":false,"region":"Одеська область","office_hidden":false,"region_hidden":false,"post":"суддя малиновського районного суду м. одеси","office_unclear":false,"office":"Загальний місцевий суд"},"last_name_unclear":false,"full_name":"Коблова Ольга Дмитрівна","last_name":"Коблова","full_name_suggest":{"output":"Коблова Ольга Дмитрівна","input":["Коблова Ольга Дмитрівна","Ольга Дмитрівна Коблова","Ольга Коблова"]},"name_unclear":false},"source":"VULYK","intro":{"declaration_year":"2014","isnotdeclaration":"","declaration_year_unclear":false}}