{"id":"vulyk_106_136","ft_src":"Volkswagen Touareg\nспільна власність\n2967 куб. см., 176 кВт , 479.5 см\n2010\n1600 куб. см., 77 кВт , 412.2 см\n2012\nVolkswagen Golf\nспільна власність\n2967 куб. см., 176 кВт , 479.5 см\nVolkswagen Touareg\n2010\n1600 куб. см., 77 кВт , 412.2 см\n2012\nVolkswagen Golf\n51.59\n65.6\n45\n1500\n51.59\n2015\n71730\n258119\n128\n71730\n258247\n2967 куб. см., 176 кВт , 479.5 см\nспільна власність\n2010\nVolkswagen Touareg\n1600 куб. см., 77 кВт , 412.2 см\nспільна власність\nVolkswagen Golf\n2012\n2967 куб. см., 176 кВт , 479.5 см\n2010\nVolkswagen Touareg\nVolkswagen Golf\n1600 куб. см., 77 кВт , 412.2 см\n2012\n1500\n45\n51.59\n65.6\n51.59\nЮхименко Олександр Васильович\nОлександр Васильович Юхименко\nОлександр Юхименко\nЮхименко Олександр Васильович\nЮхименко Олександр Васильович\nПодружжя\nЮхименко Л. М\nДитина\nЮхименко О. О\nОлександр\nЮхименко\nДніпропетровська область\nАпеляційний адміністративний суд\nсуддя дніпропетровського апеляційного адміністративного суду\nВасильович\n62076\n258119\n71730\n258247\n71730\n128\n2015\n62076\nЮхименко Л. М\nПодружжя\nЮхименко О. О\nДитина\nВасильович\nЮхименко\nОлександр\nЮхименко Олександр Васильович\nОлександр Васильович Юхименко\nОлександр Юхименко\nЮхименко Олександр Васильович\nДніпропетровська область\nАпеляційний адміністративний суд\nсуддя дніпропетровського апеляційного адміністративного суду\nЮхименко Олександр Васильович","estate":{"25":[{"address":"","space_units":"м²","costs_comment":"","region_hidden":true,"space_comment":"","address_hidden":false,"costs":"","space_comment_unclear":false,"costs_rent_comment":"","space":"51.59","region":"","costs_rent":""}],"27":[{"address":"","space_units":"м²","space_hidden":false,"space_comment":"","region_hidden":true,"costs_comment":"","address_hidden":false,"space":"45","costs_rent_comment":"","costs":"","region":"","costs_rent":""}],"29":[{"costs_property_comment":"","address":"","space_units":"м²","space_comment":"","region_hidden":true,"costs_property":"","region":"","address_hidden":true,"space_units_unclear":false,"address_unclear":false,"costs_rent_comment_unclear":false,"costs_rent_comment":"","space":"1500","region_unclear":false,"space_comment_unclear":false,"costs_rent":""}],"31":[{"costs_property_comment":"","address":"","space_units":"м²","space_hidden":false,"space_unclear":false,"region_hidden":true,"costs_property":"","space_comment":"","address_hidden":true,"space_comment_unclear":false,"costs_rent_comment":"","space":"51.59","region":"","costs_rent":""},{"costs_property_comment":"","address":"","space_units":"м²","costs_rent_comment":"","space":"65.6","region":"","region_hidden":false,"costs_property":"","space_comment":"","space_comment_unclear":false,"costs_rent":""}]},"vehicle":{"35":[{"sum_comment":"","brand_info_hidden":false,"sum_rent":"","sum":"","sum_rent_comment":"спільна власність","year":"2010","brand":"Volkswagen Touareg","brand_info":"2967 куб. см., 176 кВт , 479.5 см","brand_info_unclear":false,"year_unclear":false,"sum_hidden":false},{"sum_comment":"","brand_info":"1600 куб. см., 77 кВт , 412.2 см","sum":"","sum_rent_comment":"спільна власність","year":"2012","brand":"Volkswagen Golf","sum_rent":""}],"40":[{"year_hidden":false,"brand_info_hidden":false,"brand_info":"2967 куб. см., 176 кВт , 479.5 см","sum":"","sum_rent_comment":"","brand_hidden":false,"sum_comment":"","sum_rent":"","brand":"Volkswagen Touareg","year":"2010","brand_info_unclear":false},{"sum_comment":"","brand_info_hidden":false,"brand_info":"1600 куб. см., 77 кВт , 412.2 см","sum":"","sum_rent_comment":"","year":"2012","brand":"Volkswagen Golf","sum_rent":""}]},"source":"VULYK","income":{"5":{"family_comment":"","value":"258247","family":"71730","comment":""},"6":{"family_comment":"","value":"258119","family":"71730","comment":""},"7":{"family":"","family_comment":"","value":"","comment":"","source_name":""},"8":{"family_comment":"","value":"","family":"","comment":""},"9":{"family_comment":"","comment":"","family":"","comment_unclear":false,"value":"128","family_comment_unclear":false},"10":{"family_comment":"","value":"","family":"","comment":""},"11":{"family_comment":"","value":"","family":"","comment":""},"12":{"family_comment":"","value":"","family":"","comment":""},"13":{"family_comment":"","value":"","family":"","comment":""},"14":{"family_comment":"","value":"","family":"","comment":""},"15":{"family_comment":"","value":"","family":"","comment":""},"16":{"family_comment":"","value":"","family":"","comment":""},"17":{"family_comment":"","value":"","family":"","comment":""},"18":{"family_comment":"","value":"","family":"","comment":""},"19":{"family_comment":"","family":"","comment":"","value_unclear":false,"family_unclear":false,"value":""},"20":{"family_comment":"","family":"","comment":"","value_unclear":false,"value":"","comment_hidden":false,"comment_unclear":false,"family_unclear":false,"family_comment_hidden":false,"family_comment_unclear":false}},"general":{"family":[{"inn":"","family_name":"Юхименко Л. М","relations_other":"","relations_hidden":false,"relations_unclear":false,"name_unclear":false,"inn_hidden":true,"name_hidden":false,"relations":"Подружжя"},{"inn":"","family_name":"Юхименко О. О","relations_other":"","relations_unclear":false,"name_unclear":false,"inn_hidden":false,"name_hidden":false,"relations":"Дитина"}],"family_raw":"","name":"Олександр","full_name_suggest":{"input":["Юхименко Олександр Васильович","Олександр Васильович Юхименко","Олександр Юхименко"],"output":"Юхименко Олександр Васильович"},"name_unclear":false,"patronymic":"Васильович","inn_hidden":true,"addresses":[{"place_city_type_hidden":true,"place_city_type":"","place_city_hidden":true,"place_hidden":true,"place_district":"","place_district_hidden":false,"place":"","place_city":"","place_address_hidden":true,"place_address":""}],"inn":"","inn_unclear":false,"last_name":"Юхименко","full_name":"Юхименко Олександр Васильович","post":{"post_hidden":false,"office":"Апеляційний адміністративний суд","post":"суддя дніпропетровського апеляційного адміністративного суду","office_unclear":false,"region_unclear":false,"region":"Дніпропетровська область"}},"liabilities":{"54":{"sum_comment_unclear":false,"sum_comment":"","sum_hidden":false,"sum":"","sum_foreign_comment":"","sum_foreign":"","sum_comment_hidden":false},"55":{"sum_comment":"","sum_foreign_comment":"","sum_foreign":"","sum_hidden":false,"sum":""},"56":{"sum_comment":"","sum_hidden":false,"sum":"","sum_foreign_comment":"","sum_foreign":"","sum_unclear":false,"sum_comment_hidden":false},"57":{"sum_comment":"","sum_hidden":false,"sum":"62076","sum_foreign_comment":"","sum_foreign":"","sum_comment_hidden":false},"58":{"sum_comment":"","sum_hidden":false,"sum":"","sum_foreign_comment":"","sum_foreign":"","sum_comment_hidden":false},"59":{"sum_comment":"","sum_foreign_comment":"","sum_foreign":"","sum":""},"60":{"sum_comment":"","sum_hidden":false,"sum":"","sum_foreign_comment":"","sum_foreign":"","sum_comment_hidden":false},"61":{"sum_comment":"","sum_foreign_comment":"","sum_foreign":"","sum":""},"62":{"sum_comment":"","sum":"","sum_foreign_comment":"","sum_foreign":"","sum_unclear":false,"sum_comment_hidden":false},"63":{"sum_comment":"","sum_foreign_comment":"","sum_foreign":"","sum":""},"64":{"sum_comment":"","sum_foreign_comment":"","sum_foreign":"","sum":""}},"declaration":{"notfull_lostpages":"","additional_info_text":"","additional_info":"","date":"2016-03-30T00:00:00","notfull":"","url":"http://static.declarations.com.ua/declarations/chosen_ones/judges_batch/2275_iukhymenko_oleksandr_vasylovych.pdf"},"intro":{"isnotdeclaration":"","declaration_year":"2015"}}