{"income":{"5":{"value":"292017","value_unclear":false,"family_hidden":false,"family_comment":"","family":"","comment":""},"6":{"family_comment":"","value":"292017","family":"","comment":""},"7":{"family_comment":"","value":"","source_name":"","family":"","comment":""},"8":{"family_comment":"","value":"","family":"","comment":""},"9":{"family_comment":"","value":"","family":"","comment":""},"10":{"family_comment":"","value":"","family":"","comment":""},"11":{"family_comment":"","value":"","family_hidden":false,"comment":"","family":""},"12":{"family_comment":"","value":"","family":"","comment":""},"13":{"family_comment":"","value":"","family":"","comment":""},"14":{"family_comment":"","value":"","family":"","comment":""},"15":{"family_comment":"","value":"","family":"","comment":""},"16":{"family_comment":"","value":"","family":"","comment":""},"17":{"family_comment":"","value":"","family":"","comment":"","family_comment_unclear":false},"18":{"family_comment":"","value":"","family":"","comment":""},"19":{"family_comment":"","value":"","family":"","comment":""},"20":{"value":"","family_unclear":false,"family_hidden":false,"family_comment":"","family":"","comment":""}},"vehicle":{"35":[{"brand_info":"1984","sum":"","brand":"Volkswagen Tiguan","sum_comment":"","brand_unclear":false,"year":"2011","brand_hidden":false,"brand_info_hidden":false,"brand_info_unclear":false,"sum_rent_comment":"","sum_rent":""}]},"id":"vulyk_103_39","declaration":{"date":"2016-03-31T00:00:00","additional_info_text":"","additional_info":"","url":"http://static.declarations.com.ua/declarations/chosen_ones/judges_batch/1263_lesko_alla_oleksiivna.pdf"},"liabilities":{"54":{"sum_foreign_comment":"","sum_foreign_hidden":false,"sum_comment":"","sum_foreign_comment_hidden":false,"sum_hidden":false,"sum_foreign_comment_unclear":false,"sum_comment_hidden":false,"sum_unclear":false,"sum":"","sum_foreign":""},"55":{"sum_foreign_comment":"","sum":"","sum_comment":"","sum_foreign":""},"56":{"sum_foreign_comment":"","sum":"","sum_comment":"","sum_foreign":""},"57":{"sum_foreign_comment":"","sum_foreign_hidden":false,"sum_comment":"","sum_foreign_comment_hidden":false,"sum_hidden":false,"sum_comment_hidden":false,"sum":"","sum_foreign":""},"58":{"sum_foreign_comment":"","sum_foreign_hidden":false,"sum_comment":"","sum_foreign_comment_hidden":false,"sum_hidden":false,"sum_comment_hidden":false,"sum":"","sum_foreign":""},"59":{"sum_foreign_comment":"","sum_foreign_hidden":false,"sum_comment":"","sum_foreign_comment_hidden":false,"sum_hidden":false,"sum_comment_hidden":false,"sum":"","sum_foreign":""},"60":{"sum_foreign_comment":"","sum":"","sum_comment":"","sum_hidden":false,"sum_comment_hidden":false,"sum_foreign":""},"61":{"sum_foreign_comment":"","sum":"","sum_comment":"","sum_foreign":""},"62":{"sum_foreign_comment":"","sum_comment_hidden":false,"sum":"","sum_comment":"","sum_foreign":""},"63":{"sum_foreign_comment":"","sum":"","sum_comment":"","sum_foreign":""},"64":{"sum_foreign_comment":"","sum":"","sum_comment":"","sum_foreign":""}},"ft_src":"Лесько Алла Олексіївна\nсуддя вссу, секретар дисциплінарної секції врю\nЗагальнодержавний регіон\nВищий спеціалізований суд з розгляду цивільних і кримінальних справ\nАлла\nРозман П. В\nДитина\nЛесько Алла Олексіївна\nАлла Олексіївна Лесько\nАлла Лесько\nЛесько Алла Олексіївна\nЛесько\nОлексіївна\nVolkswagen Tiguan\n1984\n2011\n1/3 частина квартири\n63.6\nмашиномісце\n13.9\n78.6\n1/3 частина квартири, право користування\n63.6\n2015\n292017\n292017\n1984\n2011\nVolkswagen Tiguan\n1/3 частина квартири\n63.6\n13.9\nмашиномісце\n78.6\n63.6\n1/3 частина квартири, право користування\nЛесько\nЛесько Алла Олексіївна\nАлла Олексіївна Лесько\nАлла Лесько\nЛесько Алла Олексіївна\nЛесько Алла Олексіївна\nОлексіївна\nДитина\nРозман П. В\nАлла\nВищий спеціалізований суд з розгляду цивільних і кримінальних справ\nсуддя вссу, секретар дисциплінарної секції врю\nЗагальнодержавний регіон\n292017\n292017\n2015\nДитина\nРозман П. В\nЛесько\nОлексіївна\nсуддя вссу, секретар дисциплінарної секції врю\nВищий спеціалізований суд з розгляду цивільних і кримінальних справ\nЗагальнодержавний регіон\nЛесько Алла Олексіївна\nЛесько Алла Олексіївна\nАлла Олексіївна Лесько\nАлла Лесько\nЛесько Алла Олексіївна\nАлла\nVolkswagen Tiguan\n1984\n2011\n292017\n292017\n1/3 частина квартири\n63.6\n78.6\n1/3 частина квартири, право користування\n63.6\nмашиномісце\n13.9\n2015","general":{"inn":"","inn_hidden":true,"last_name":"Лесько","post":{"region":"Загальнодержавний регіон","region_unclear":false,"post":"суддя вссу, секретар дисциплінарної секції врю","office_unclear":false,"office":"Вищий спеціалізований суд з розгляду цивільних і кримінальних справ"},"name":"Алла","full_name":"Лесько Алла Олексіївна","family_raw":"","addresses":[{"place_district":"","place_city_hidden":true,"place_city":"","place_city_type_hidden":false,"place_district_hidden":false,"place_city_type":"","place_address_hidden":true,"place_address":"","place_hidden":true,"place":""}],"family":[{"inn":"","relations":"Дитина","relations_hidden":false,"inn_hidden":true,"relations_other":"","name_hidden":true,"family_name":"Розман П. В","name_unclear":false}],"full_name_suggest":{"output":"Лесько Алла Олексіївна","input":["Лесько Алла Олексіївна","Алла Олексіївна Лесько","Алла Лесько"]},"patronymic":"Олексіївна"},"source":"VULYK","estate":{"25":[{"costs":"","costs_comment":"","address_hidden":false,"region_hidden":true,"space_comment":"","space":"78.6","address":"","region":"","costs_rent_comment":"","space_comment_unclear":false,"space_comment_hidden":false,"space_units":"м²","costs_rent":""},{"costs_rent":"","region":"","costs":"","costs_rent_comment":"","costs_comment":"","region_hidden":false,"space_comment":"1/3 частина квартири, право користування","space_units":"м²","space":"63.6","address":""}],"28":[{"space_hidden":false,"costs":"","costs_comment":"","address_hidden":false,"region_hidden":true,"space_comment":"машиномісце","space_unclear":false,"space":"13.9","address":"","region":"","costs_rent_comment":"","space_units":"м²","costs_rent":""}],"31":[{"space_hidden":false,"address_hidden":false,"region_hidden":true,"space_comment":"1/3 частина квартири","space":"63.6","address":"","costs_property":"","costs_rent_comment":"","address_unclear":false,"space_units":"м²","costs_property_comment":"","costs_rent":""}]},"intro":{"declaration_year":"2015"}}