{"id":"vulyk_109_128","ft_src":"75 кВт , 102 к.с.\n2006\nSkoda Octavia A5\n1/4 частина квартири\n48.8\nоренда офіса нотаріуса\n31.7\n118.4\n295\n2015\n75 кВт , 102 к.с.\n2006\nSkoda Octavia A5\n2015\nПодружжя\nЯроцька Т. В\nДитина\nЯроцька М. А\nДитина\nЯроцька В. А\nЯроцький Андрій Миколайович\nАндрій Миколайович Яроцький\nАндрій Яроцький\nЯроцький Андрій Миколайович\nАндрій\nЯроцький Андрій Миколайович\nЯроцький\nГосподарський місцевий суд\nХмельницька область\nсуддя господарського суду хмельницької області\nМиколайович\n97\n185228\n53040\n28\n185353\n65953\n12900\n13\n118.4\n1/4 частина квартири\n48.8\n31.7\nоренда офіса нотаріуса\n295\n185228\n12900\n97\n65953\n185353\n53040\n13\n28\nПодружжя\nЯроцька Т. В\nДитина\nЯроцька М. А\nДитина\nЯроцька В. А\nАндрій\nМиколайович\nЯроцький\nЯроцький Андрій Миколайович\nАндрій Миколайович Яроцький\nАндрій Яроцький\nЯроцький Андрій Миколайович\nХмельницька область\nГосподарський місцевий суд\nсуддя господарського суду хмельницької області\nЯроцький Андрій Миколайович","estate":{"24":[{"costs":"","address":"","space_units":"м²","costs_rent_comment":"","space":"118.4","space_comment":"","region_hidden":true,"costs_comment":"","region":"","address_hidden":false,"costs_rent":""}],"31":[{"costs_property_comment":"","address":"","space_units":"м²","space_hidden":false,"space_comment":"1/4 частина квартири","region_hidden":true,"costs_property":"","region":"","address_hidden":true,"costs_rent_comment":"","space":"48.8","space_units_hidden":false,"costs_rent":""}],"34":[{"costs_property_comment":"","address":"","space_units":"м²","costs_rent_comment":"","space":"31.7","region_hidden":true,"costs_property":"","space_comment":"оренда офіса нотаріуса","address_hidden":true,"costs_rent":""}]},"vehicle":{"40":[{"sum_comment":"","brand_info":"75 кВт , 102 к.с.","sum":"","sum_rent_comment":"","year":"2006","brand":"Skoda Octavia A5","sum_rent":"","brand_info_unclear":false}]},"source":"VULYK","income":{"5":{"family_comment":"","value":"185353","family":"65953","comment":""},"6":{"family_comment":"","value":"185228","family":"","comment":""},"7":{"source_name_hidden":true,"family_comment":"","comment":"","family":"","comment_hidden":false,"value":"97","source_name":""},"8":{"family_comment":"","family_hidden":true,"value":"","family":"","comment":""},"9":{"family_comment":"","family":"13","comment":"","value_unclear":false,"family_unclear":false,"value":""},"10":{"family_comment":"","value":"","family":"12900","comment":""},"11":{"family_comment":"","value":"","family":"","comment":""},"12":{"family_comment":"","value":"","family":"","comment":""},"13":{"family_comment":"","value":"","family":"","comment":""},"14":{"family_comment":"","value":"","family":"","comment":""},"15":{"family_comment":"","value":"","family":"","comment":""},"16":{"family_comment":"","value":"","family":"","comment":""},"17":{"family_comment":"","value":"","family":"53040","comment":""},"18":{"family_comment":"","value":"","family":"","comment":""},"19":{"family_comment":"","value":"","family":"","comment":""},"20":{"family_comment":"","family":"","comment":"","value_unclear":false,"family_hidden":true,"value":"28"}},"banks":{"51":[{"sum_units":"UAH","sum_comment":"","sum_foreign_units":"UAH","sum":"295","sum_units_hidden":false,"sum_foreign_comment":"","sum_foreign":"","sum_unclear":false,"sum_comment_hidden":false}]},"declaration":{"notfull_lostpages":"","additional_info_text":"","additional_info":"","date":"2016-03-30T00:00:00","notfull":"","url":"http://static.declarations.com.ua/declarations/chosen_ones/judges_batch/2585_iarotskyi_andrii_mykolaiovych_2015.pdf"},"general":{"family_raw":"","name":"Андрій","full_name_suggest":{"input":["Яроцький Андрій Миколайович","Андрій Миколайович Яроцький","Андрій Яроцький"],"output":"Яроцький Андрій Миколайович"},"patronymic":"Миколайович","inn_hidden":true,"inn":"","inn_unclear":false,"last_name":"Яроцький","full_name":"Яроцький Андрій Миколайович","family":[{"inn":"","family_name":"Яроцька Т. В","relations_hidden":false,"name_unclear":true,"relations":"Подружжя","inn_hidden":true,"name_hidden":true,"relations_other":""},{"inn":"","family_name":"Яроцька М. А","relations_other":"","name_unclear":true,"inn_hidden":true,"name_hidden":true,"relations":"Дитина"},{"inn":"","family_name":"Яроцька В. А","relations_other":"","name_unclear":true,"inn_hidden":true,"name_hidden":true,"relations":"Дитина"}],"post":{"office":"Господарський місцевий суд","post":"суддя господарського суду хмельницької області","office_unclear":false,"region_hidden":false,"region":"Хмельницька область","office_hidden":false,"region_unclear":false},"name_hidden":false},"liabilities":{"54":{"sum_comment":"","sum_hidden":false,"sum":"","sum_foreign_comment":"","sum_foreign":"","sum_unclear":false,"sum_comment_hidden":false},"55":{"sum_comment":"","sum_comment_unclear":false,"sum_foreign_comment":"","sum":"","sum_foreign":""},"56":{"sum_comment":"","sum_foreign_comment":"","sum_foreign":"","sum":""},"57":{"sum_comment":"","sum_foreign_comment":"","sum_foreign":"","sum":"","sum_comment_hidden":false},"58":{"sum_comment":"","sum_foreign_comment":"","sum_foreign":"","sum":"","sum_comment_hidden":false},"59":{"sum_comment":"","sum_foreign_comment":"","sum_foreign":"","sum":""},"60":{"sum_comment":"","sum_foreign_comment":"","sum_foreign":"","sum":""},"61":{"sum_comment":"","sum_foreign_comment":"","sum_foreign":"","sum":""},"62":{"sum_comment":"","sum_foreign_comment":"","sum_foreign":"","sum":""},"63":{"sum_comment":"","sum_foreign_comment":"","sum_foreign":"","sum":""},"64":{"sum_comment":"","sum_foreign_comment":"","sum_foreign":"","sum":""}},"intro":{"isnotdeclaration":"","declaration_year":"2015"}}