{"income":{"5":{"value":"189465.87","family_comment":"","value_unclear":false,"family_hidden":false,"value_hidden":false,"family_unclear":false,"comment_unclear":false,"comment":"","family":""},"6":{"value":"189465.87","family_comment":"","value_unclear":false,"family_hidden":false,"value_hidden":false,"family_unclear":false,"comment_unclear":false,"comment":"","family":""},"7":{"source_name_unclear":false,"value":"","family_comment":"","source_name":"","family":"","comment":""},"8":{"family_comment":"","value":"","family":"","comment":""},"9":{"value":"","value_unclear":false,"comment_hidden":false,"family_comment":"","comment_unclear":false,"comment":"","family":""},"10":{"value":"","comment_unclear":false,"value_hidden":false,"family_comment":"","family":"","comment":""},"11":{"family_comment":"","value":"","family":"","comment":""},"12":{"family_comment":"","value":"","family":"","comment":""},"13":{"family_comment":"","value":"","family":"","comment":""},"14":{"family_comment":"","value":"","family":"","comment":""},"15":{"family_comment":"","value":"","family":"","comment":""},"16":{"family_comment":"","value":"","family":"","comment":""},"17":{"family_comment":"","value":"","family":"","comment":""},"18":{"value":"","family_hidden":false,"value_hidden":false,"family_comment":"","family":"","comment":""},"19":{"family_comment":"","value":"","family":"","comment":""},"20":{"value":"","family_comment":"","value_unclear":false,"family_hidden":false,"value_hidden":false,"family_unclear":false,"family":"","comment":""}},"vehicle":{"35":[{"year_hidden":true,"brand_info":"","sum_rent_comment":"","year":"","brand_info_unclear":false,"year_unclear":true,"sum_rent":"","sum":"","brand":"","sum_comment":"","brand_unclear":false,"brand_hidden":false}],"40":[{"brand_info":"1598 куб. см.","sum_rent_comment":"","brand":"Citroen C4","sum_comment":"","brand_unclear":false,"year":"2012","brand_info_unclear":false,"year_unclear":false,"sum":"","sum_rent":""}]},"id":"vulyk_66_178","declaration":{"additional_info_text":"","notfull_lostpages":"","date":"2015-03-31T00:00:00","notfull":"","additional_info":"","url":"http://static.declarations.com.ua/declarations/chosen_ones/mega_batch/nozdriakov_stanislav_viktorovych.pdf"},"liabilities":{"54":{"sum_foreign_comment":"","sum":"","sum_comment":"","sum_comment_unclear":false,"sum_comment_hidden":false,"sum_unclear":false,"sum_foreign":""},"55":{"sum_foreign_comment":"","sum":"","sum_comment":"","sum_foreign":""},"56":{"sum_foreign_comment":"","sum_foreign_hidden":false,"sum_comment":"","sum_hidden":false,"sum_comment_hidden":false,"sum":"","sum_foreign":""},"57":{"sum_foreign_comment":"","sum":"","sum_comment":"","sum_comment_unclear":false,"sum_hidden":false,"sum_comment_hidden":false,"sum_unclear":false,"sum_foreign":""},"58":{"sum_foreign_comment":"","sum":"","sum_comment":"","sum_comment_unclear":false,"sum_unclear":false,"sum_foreign":""},"59":{"sum_foreign_comment":"","sum_foreign_hidden":false,"sum_comment":"","sum_comment_unclear":false,"sum_hidden":false,"sum":"","sum_foreign":""},"60":{"sum_foreign_comment":"","sum":"","sum_comment":"","sum_comment_unclear":false,"sum_foreign":""},"61":{"sum_foreign_comment":"","sum":"","sum_comment":"","sum_foreign":""},"62":{"sum_foreign_comment":"","sum_foreign_hidden":false,"sum_comment":"","sum_hidden":false,"sum":"","sum_unclear":false,"sum_foreign":""},"63":{"sum_foreign_comment":"","sum":"","sum_comment":"","sum_comment_unclear":false,"sum_comment_hidden":false,"sum_unclear":false,"sum_foreign":""},"64":{"sum_foreign_comment":"","sum":"","sum_comment":"","sum_comment_unclear":false,"sum_foreign":""}},"ft_src":"суддя подільського районного суду м. києва\nм. Київ\nЗагальний місцевий суд\nСтаніслав\nПарінцева Лілія Юріївна, 30. 05. 1973\nПодружжя\nНоздряков Георгій Станіславович 03. 12. 1996\nДитина\nНоздряков Федір Станіславович, 13. 02. 2006\nДитина\nНоздрякова Ева Станіславівна, 26. 10. 2012\nДитина\nВікторович\nНоздряков\nНоздряков Станіслав Вікторович\nНоздряков Станіслав Вікторович\nСтаніслав Вікторович Ноздряков\nСтаніслав Ноздряков\nНоздряков Станіслав Вікторович\n1598 куб. см.\nCitroen C4\n2012\n.071\nДарування\n58.1\n200\n195\nДарування\n.1442\nДарування\n.3227\nПостійне користування\n100\n2014\n189465.87\n189465.87\n1598 куб. см.\n2012\nCitroen C4\n100\nПостійне користування\n.1442\nДарування\n.3227\nДарування\n.071\n58.1\nДарування\n200\n195\nНоздряков Станіслав Вікторович\nСтаніслав Вікторович Ноздряков\nСтаніслав Ноздряков\nНоздряков Станіслав Вікторович\nНоздряков Станіслав Вікторович\nПодружжя\nПарінцева Лілія Юріївна, 30. 05. 1973\nДитина\nНоздряков Георгій Станіславович 03. 12. 1996\nДитина\nНоздряков Федір Станіславович, 13. 02. 2006\nДитина\nНоздрякова Ева Станіславівна, 26. 10. 2012\nСтаніслав\nНоздряков\nЗагальний місцевий суд\nсуддя подільського районного суду м. києва\nм. Київ\nВікторович\n189465.87\n189465.87\n2014\nПарінцева Лілія Юріївна, 30. 05. 1973\nПодружжя\nНоздряков Георгій Станіславович 03. 12. 1996\nДитина\nНоздряков Федір Станіславович, 13. 02. 2006\nДитина\nНоздрякова Ева Станіславівна, 26. 10. 2012\nДитина\nВікторович\nНоздряков\nСтаніслав\nНоздряков Станіслав Вікторович\nСтаніслав Вікторович Ноздряков\nСтаніслав Ноздряков\nНоздряков Станіслав Вікторович\nм. Київ\nсуддя подільського районного суду м. києва\nЗагальний місцевий суд\nНоздряков Станіслав Вікторович\n2012\n1598 куб. см.\nCitroen C4\n189465.87\n189465.87\n200\nДарування\n.1442\nДарування\n.3227\nДарування\n58.1\n100\nПостійне користування\n195\n.071\n2014","general":{"inn":"","name":"Станіслав","last_name_hidden":false,"family":[{"inn":"","inn_hidden":false,"relations_hidden":false,"family_name":"Парінцева Лілія Юріївна, 30. 05. 1973","relations_other":"","relations":"Подружжя","name_hidden":false,"name_unclear":false},{"inn":"","inn_hidden":false,"relations_unclear":false,"relations_hidden":false,"relations_other":"","relations":"Дитина","name_hidden":false,"family_name":"Ноздряков Георгій Станіславович 03. 12. 1996","name_unclear":false},{"inn":"","inn_hidden":false,"relations_hidden":false,"family_name":"Ноздряков Федір Станіславович, 13. 02. 2006","relations_other":"","relations":"Дитина","name_hidden":false,"name_unclear":false},{"inn":"","relations":"Дитина","relations_other":"","inn_hidden":false,"family_name":"Ноздрякова Ева Станіславівна, 26. 10. 2012","name_hidden":false,"name_unclear":false}],"patronymic":"Вікторович","inn_hidden":false,"family_raw":"","inn_unclear":false,"post":{"post_unclear":false,"post":"суддя подільського районного суду м. києва","candidate":"","office_hidden":false,"region":"м. Київ","office":"Загальний місцевий суд","office_unclear":false},"last_name_unclear":false,"full_name":"Ноздряков Станіслав Вікторович","last_name":"Ноздряков","full_name_suggest":{"output":"Ноздряков Станіслав Вікторович","input":["Ноздряков Станіслав Вікторович","Станіслав Вікторович Ноздряков","Станіслав Ноздряков"]}},"source":"VULYK","estate":{"23":[{"space_unclear":false,"costs":"","costs_comment":"","costs_hidden":false,"address_hidden":false,"region_hidden":false,"space_comment":"Дарування","space_hidden":false,"space":".1442","space_units_hidden":false,"region":"","address_unclear":false,"space_units_unclear":false,"space_units":"га","address":"","costs_rent":"","costs_rent_comment":""},{"costs_rent":"","region":"","costs":"","costs_rent_comment":"","costs_comment":"","address_hidden":false,"space_comment":"Дарування","space_units":"га","space":".3227","address":""}],"24":[{"space_unclear":false,"costs":"","costs_comment":"","costs_hidden":false,"address_hidden":false,"region_hidden":false,"space_comment":"Дарування","space_hidden":false,"space":"58.1","address":"","region":"","address_unclear":false,"costs_rent_comment":"","costs_rent_hidden":false,"space_comment_unclear":false,"space_units":"м²","costs_rent":""}],"25":[{"region_unclear":false,"space_hidden":false,"costs":"","costs_comment":"","costs_hidden":false,"address_hidden":false,"region_hidden":false,"space_comment":"Постійне користування","space_unclear":false,"space":"100","space_units_hidden":false,"region":"","address_unclear":false,"costs_rent_comment":"","space_comment_unclear":false,"space_units":"м²","address":"","costs_rent":""}],"29":[{"space_unclear":false,"address_hidden":false,"region_hidden":false,"space_comment":"","space_hidden":false,"space":".071","address":"","region":"","costs_property":"","costs_rent_comment":"","space_units":"га","costs_property_comment":"","costs_rent":""}],"31":[{"space_unclear":false,"address_hidden":false,"region_hidden":false,"space_comment":"","space_hidden":false,"space":"200","address":"","region":"","costs_property":"","costs_rent_comment":"","space_comment_unclear":false,"space_comment_hidden":false,"space_units":"м²","costs_property_comment":"","costs_rent":""}],"34":[{"space_unclear":false,"address_hidden":false,"region_hidden":false,"space_comment":"","space_hidden":false,"space":"195","address":"","region":"","costs_property":"","costs_rent_comment":"","space_comment_unclear":false,"space_units":"м²","costs_property_comment":"","costs_rent":""}]},"intro":{"declaration_year":"2014","isnotdeclaration":"","declaration_year_unclear":false}}