{"income":{"5":{"value":"186949","family_comment":"","value_unclear":false,"family_hidden":false,"value_hidden":false,"family_unclear":false,"family":"242646","comment":""},"6":{"value":"186949","family_comment":"","value_unclear":false,"family_unclear":false,"family":"","comment":""},"7":{"source_name_unclear":false,"value":"","comment_hidden":false,"family_comment":"","source_name":"","family":"","comment":"","source_name_hidden":false},"8":{"family_comment":"","value":"","family":"","comment":""},"9":{"value":"","family_comment":"","value_unclear":false,"family_hidden":false,"family_unclear":false,"family":"","comment":"","family_comment_unclear":false},"10":{"family_comment":"","value":"","family":"","comment":""},"11":{"family_comment":"","value":"","family":"","comment":""},"12":{"family_comment":"","value":"","family":"","comment":""},"13":{"family_comment":"","value":"","family":"","comment":""},"14":{"family_comment":"","value":"","family":"","comment":""},"15":{"family_comment":"","value":"","family":"","comment":""},"16":{"family_comment":"","value":"","family":"57700","comment":""},"17":{"family_comment":"","value":"","family":"184946","comment":""},"18":{"family_comment":"","value":"","family":"","comment":""},"19":{"family_comment":"","value":"","family":"","comment":""},"20":{"value":"","family_comment":"","value_unclear":false,"family_comment_hidden":false,"family_unclear":false,"family_comment_unclear":false,"comment_unclear":false,"comment":"","family":""}},"vehicle":{"35":[{"year_hidden":false,"brand_info":"1995 куб. см.","sum_rent_comment":"","year":"2007","brand_info_hidden":false,"brand_info_unclear":false,"sum_rent":"","sum":"","brand":"BMW","sum_comment":"","brand_unclear":false,"brand_hidden":false}]},"id":"vulyk_93_41","declaration":{"additional_info_text":"","notfull_lostpages":"","date":"2015-03-31T00:00:00","notfull":"","additional_info":"","url":"http://static.declarations.com.ua/declarations/chosen_ones/judges_batch/3487_leiko-zhuromska_maiia_viktorivna.pdf"},"liabilities":{"54":{"sum_foreign_comment":"","sum":"8347","sum_hidden":false,"sum_comment":"","sum_foreign":""},"55":{"sum_foreign_comment":"","sum":"","sum_comment":"","sum_foreign":""},"56":{"sum_foreign_comment":"","sum":"","sum_comment":"","sum_foreign":""},"57":{"sum_foreign_comment":"","sum":"","sum_comment":"","sum_hidden":false,"sum_comment_hidden":false,"sum_unclear":false,"sum_foreign":""},"58":{"sum_foreign_comment":"","sum":"","sum_comment":"","sum_comment_unclear":false,"sum_hidden":false,"sum_unclear":false,"sum_foreign":""},"59":{"sum_foreign_comment":"","sum":"","sum_comment":"","sum_foreign":""},"60":{"sum_foreign_comment":"","sum":"","sum_hidden":false,"sum_comment":"","sum_foreign":""},"61":{"sum_foreign_comment":"","sum":"","sum_comment":"","sum_foreign":""},"62":{"sum_foreign_comment":"","sum":"","sum_comment":"","sum_foreign":""},"63":{"sum_foreign_comment":"","sum":"","sum_comment":"","sum_foreign":""},"64":{"sum_foreign_comment":"","sum":"","sum_comment":"","sum_foreign":""}},"ft_src":"8347\nЛейко-Журомська Майя Вікторівна\nсуддя львівського окружного адміністративного суду\nЛьвівська область\nАдміністративний місцевий суд\nМайя\nЖуромський В. І\nПодружжя\nГелик Ю. В\nДитина\nЛейко-Журомська Майя Вікторівна\nМайя Вікторівна Лейко-Журомська\nМайя Лейко-Журомська\nЛейко-Журомська Майя Вікторівна\nЛейко-Журомська\nВікторівна\n1995 куб. см.\nBMW\n2007\n18.1\n34.9\n1/2\n411\n117\n1200\n244.9\n41.3\n1/2\n411\n117\n121\n2014\n186949\n242646\n186949\n57700\n184946\n1995 куб. см.\nBMW\n2007\n18.1\n34.9\n121\n411\n1/2\n117\n411\n1/2\n117\n1200\n244.9\n41.3\nЛейко-Журомська\nПодружжя\nЖуромський В. І\nДитина\nГелик Ю. В\nЛейко-Журомська Майя Вікторівна\nМайя Вікторівна Лейко-Журомська\nМайя Лейко-Журомська\nЛейко-Журомська Майя Вікторівна\nЛейко-Журомська Майя Вікторівна\nМайя\nВікторівна\nЛьвівська область\nАдміністративний місцевий суд\nсуддя львівського окружного адміністративного суду\n8347\n186949\n184946\n186949\n242646\n57700\n2014\n8347\nПодружжя\nЖуромський В. І\nДитина\nГелик Ю. В\nЛейко-Журомська\nВікторівна\nЛьвівська область\nАдміністративний місцевий суд\nсуддя львівського окружного адміністративного суду\nЛейко-Журомська Майя Вікторівна\nЛейко-Журомська Майя Вікторівна\nМайя Вікторівна Лейко-Журомська\nМайя Лейко-Журомська\nЛейко-Журомська Майя Вікторівна\nМайя\nBMW\n1995 куб. см.\n2007\n186949\n242646\n57700\n184946\n186949\n41.3\n1/2\n411\n117\n244.9\n18.1\n34.9\n121\n1/2\n411\n117\n1200\n2014","general":{"inn":"","inn_hidden":true,"last_name":"Лейко-Журомська","post":{"post_unclear":false,"region_unclear":false,"region":"Львівська область","candidate":"","post":"суддя львівського окружного адміністративного суду","office":"Адміністративний місцевий суд","office_unclear":false},"name":"Майя","full_name":"Лейко-Журомська Майя Вікторівна","family_raw":"","addresses":[{"place_district":"","place_city_hidden":true,"place_city":"","place_city_type_hidden":true,"place_district_hidden":false,"place_city_type":"","place_address_hidden":true,"place_address":"","place_hidden":true,"place":""}],"family":[{"inn":"","relations":"Подружжя","relations_hidden":false,"inn_hidden":true,"relations_other":"","name_hidden":false,"family_name":"Журомський В. І","name_unclear":false},{"inn":"","relations":"Дитина","relations_other":"","inn_hidden":false,"family_name":"Гелик Ю. В","name_hidden":false,"name_unclear":false}],"full_name_suggest":{"output":"Лейко-Журомська Майя Вікторівна","input":["Лейко-Журомська Майя Вікторівна","Майя Вікторівна Лейко-Журомська","Майя Лейко-Журомська"]},"patronymic":"Вікторівна"},"source":"VULYK","estate":{"23":[{"space_unclear":true,"costs":"","costs_comment":"","address_hidden":false,"region_hidden":true,"space_comment":"1/2","space":"411","address":"","region":"","costs_rent_comment":"","space_comment_unclear":true,"space_units":"м²","costs_rent":""},{"costs_rent":"","region":"","costs":"","costs_rent_comment":"","costs_comment":"","region_hidden":false,"space_comment":"","space_units":"м²","space":"117","address":""}],"24":[{"space_unclear":false,"costs":"","costs_comment":"","address_hidden":false,"region_hidden":true,"space_comment":"","space":"244.9","address":"","region":"","costs_rent_comment":"","space_comment_unclear":false,"space_units":"м²","costs_rent":""}],"25":[{"space_hidden":false,"costs":"","costs_comment":"","address_hidden":false,"region_hidden":true,"space_comment":"","space_unclear":false,"space":"121","address":"","costs_rent_comment_unclear":false,"region":"","costs_rent_comment":"","space_units":"м²","costs_rent":""}],"27":[{"costs_rent":"","region":"","costs":"","costs_rent_comment":"","costs_comment":"","address_hidden":true,"region_hidden":true,"space_comment":"","space_units":"м²","space":"18.1","address":""},{"costs_rent":"","region":"","costs":"","costs_rent_comment":"","costs_comment":"","region_hidden":false,"space_comment":"","space_units":"м²","space":"34.9","address":""}],"29":[{"space_unclear":true,"address_hidden":true,"region_hidden":true,"space_comment":"1/2","space":"411","address":"","region":"","costs_property":"","costs_rent_comment":"","space_comment_unclear":true,"space_units":"м²","costs_property_comment":"","costs_rent":""},{"costs_rent":"","region":"","costs_property":"","costs_rent_comment":"","region_hidden":false,"space_comment":"","costs_property_comment":"","space_units":"м²","space":"117","address":""},{"costs_rent":"","space_unclear":false,"costs_property":"","costs_rent_comment":"","space_comment_unclear":false,"space_comment":"","costs_property_comment":"","space_units":"м²","space":"1200","address":""}],"31":[{"space_hidden":false,"address_hidden":true,"region_hidden":true,"space_comment":"","space":"41.3","address":"","region":"","costs_property":"","costs_rent_comment":"","space_comment_unclear":false,"space_units":"м²","costs_property_comment":"","costs_rent":""}]},"intro":{"declaration_year":"2014","isnotdeclaration":""}}