{"income":{"5":{"family_comment":"","family_unclear":false,"value":"311224","family":"195659","comment":""},"6":{"value":"215959","family_comment":"","value_unclear":false,"family_unclear":false,"family":"98168","comment":""},"7":{"value":"","family_comment":"","value_unclear":false,"family_unclear":false,"source_name":"","family":"","comment":"","source_name_hidden":false},"8":{"family_comment":"","value":"","family":"","comment":""},"9":{"family_comment":"","value":"","family":"","comment":""},"10":{"family_comment":"","value":"","value_unclear":false,"family":"","comment":""},"11":{"family_comment":"","value":"","family":"","comment":""},"12":{"family_comment":"","value":"","family":"18955","comment":""},"13":{"family_comment":"","value":"","family":"","comment":""},"14":{"family_comment":"","value":"","family":"","comment":""},"15":{"family_comment":"","value":"80225","family":"78536","comment":""},"16":{"family_comment":"","value":"","family":"","comment":""},"17":{"family_comment":"","value":"","family":"","comment":""},"18":{"family_comment":"","value":"","family":"","comment":""},"19":{"family_comment":"","value":"","family":"","comment":""},"20":{"value":"15040","value_unclear":false,"comment_hidden":false,"family_comment":"","comment_unclear":false,"comment":"","family":""}},"vehicle":{"40":[{"brand_info":"2987 куб. см.","sum":"","brand":"Mercedes-Benz E 280","sum_comment":"","year":"2005","brand_info_hidden":false,"year_unclear":false,"sum_rent_comment":"","sum_rent":""}]},"id":"vulyk_96_47","declaration":{"additional_info_text":"","notfull_lostpages":"","date":"2016-03-30T00:00:00","notfull":"","additional_info":"","url":"http://static.declarations.com.ua/declarations/chosen_ones/judges_batch/261_pushkarchuk_valentyna_petrivna_2015.pdf"},"liabilities":{"54":{"sum_foreign_comment":"","sum":"","sum_comment":"","sum_hidden":false,"sum_comment_hidden":false,"sum_foreign":""},"55":{"sum_foreign_comment":"","sum":"","sum_comment":"","sum_foreign":""},"56":{"sum_foreign_comment":"","sum":"","sum_comment":"","sum_unclear":false,"sum_foreign":""},"57":{"sum_foreign_comment":"","sum_comment":"","sum":"","sum_comment_hidden":false,"sum_foreign":""},"58":{"sum_foreign_comment":"","sum":"","sum_comment":"","sum_comment_hidden":false,"sum_unclear":false,"sum_foreign":""},"59":{"sum_foreign_comment":"","sum":"","sum_comment":"","sum_foreign":""},"60":{"sum_foreign_comment":"","sum_comment":"","sum":"","sum_comment_hidden":false,"sum_foreign":""},"61":{"sum_foreign_comment":"","sum":"","sum_comment":"","sum_foreign":""},"62":{"sum_foreign_comment":"","sum":"","sum_comment":"","sum_foreign":""},"63":{"sum_foreign_comment":"","sum_comment":"","sum":"","sum_comment_hidden":false,"sum_foreign":""},"64":{"sum_foreign_comment":"","sum_comment":"","sum":"","sum_comment_hidden":false,"sum_foreign":""}},"ft_src":"2005\n2987 куб. см.\nMercedes-Benz E 280\nспільна сумісна власність\n85\nспільна сумісна\n85\n2015\n98168\n215959\n78536\n80225\n195659\n311224\n15040\n18955\nMercedes-Benz E 280\n2987 куб. см.\n2005\n2015\nПушкарчук Валентина Петрівна\nВалентина Петрівна Пушкарчук\nВалентина Пушкарчук\nПушкарчук Валентина Петрівна\nПушкарчук Валентина Петрівна\nВалентина\nПушкарчук\nВолинська область\nсуддя луцького міськрайонного суду волинської області\nЗагальний місцевий суд\nПетрівна\nДитина\nПушкарчук О. В\nДитина\nПушкарчук С. В\n98168\n215959\n18955\n15040\n80225\n78536\n311224\n195659\nспільна сумісна власність\n85\nспільна сумісна\n85\nПушкарчук О. В\nДитина\nДитина\nПушкарчук С. В\nВалентина\nПетрівна\nПушкарчук\nПушкарчук Валентина Петрівна\nВалентина Петрівна Пушкарчук\nВалентина Пушкарчук\nПушкарчук Валентина Петрівна\nсуддя луцького міськрайонного суду волинської області\nВолинська область\nЗагальний місцевий суд\nПушкарчук Валентина Петрівна","general":{"inn":"","name":"Валентина","family":[{"inn":"","inn_hidden":true,"inn_unclear":false,"relations_hidden":false,"relations_other":"","relations":"Дитина","name_hidden":true,"family_name":"Пушкарчук О. В","name_unclear":false},{"inn":"","relations":"Дитина","relations_other":"","inn_hidden":false,"family_name":"Пушкарчук С. В","name_hidden":true,"name_unclear":false}],"patronymic":"Петрівна","inn_hidden":true,"family_raw":"","last_name":"Пушкарчук","post":{"office":"Загальний місцевий суд","region":"Волинська область","office_unclear":false,"post":"суддя луцького міськрайонного суду волинської області"},"full_name":"Пушкарчук Валентина Петрівна","addresses":[{"place_district":"","place_address_hidden":true,"place_city":"","place_address":"","place_district_hidden":false,"place_city_type":"","place_city_hidden":false,"place_city_type_hidden":false,"place_hidden":true,"place":""}],"patronymic_hidden":false,"full_name_suggest":{"output":"Пушкарчук Валентина Петрівна","input":["Пушкарчук Валентина Петрівна","Валентина Петрівна Пушкарчук","Валентина Пушкарчук"]}},"source":"VULYK","estate":{"25":[{"space_comment_unclear":false,"space_unclear":false,"costs":"","costs_comment":"","address_hidden":false,"region_hidden":true,"space_comment":"спільна сумісна","space_hidden":false,"space":"85","address":"","costs_rent_comment_unclear":false,"region":"","address_unclear":false,"costs_rent_comment":"","costs_unclear":false,"space_comment_hidden":false,"space_units":"м²","costs_rent":""}],"31":[{"space_unclear":false,"address_hidden":true,"region_hidden":true,"space_comment":"спільна сумісна власність","space_hidden":false,"space":"85","address":"","region":"","costs_property":"","costs_rent_comment":"","address_unclear":false,"space_units":"м²","costs_property_comment":"","costs_rent":""}]},"intro":{"declaration_year":"2015","isnotdeclaration":""}}