{"id":"vulyk_101_86","ft_src":"Audi A4\n1781 куб. см.\n1999\n1399 куб. см.\nHyundai Getz\n2007\n64.2\n84.7\n2015\n79433.84\n249085.33\nПриватбанк\n33.59\n79433.84\n343246.32\n94127.4\n1781 куб. см.\n1999\nAudi A4\n1399 куб. см.\n2007\nHyundai Getz\n64.2\n84.7\nВолинець Михайло Михайлович\nМихайло Михайлович Волинець\nМихайло Волинець\nВолинець Михайло Михайлович\nМихайло\nВолинець Михайло Михайлович\nМихайлович\nсуддя апеляційного суду львівської області\nЛьвівська область\nЗагальний апеляційний суд\nВолинець\nПодружжя\nВолинець Т. В\nДитина\nВолинець Р. М\nДитина\nВолинець С. М\n240\nПАТ Страхова компанія Інгострах\n249085.33\n79433.84\n94127.4\n343246.32\n79433.84\n33.59\nПриватбанк\n2015\nПАТ Страхова компанія Інгострах\n240\nВолинець Т. В\nПодружжя\nВолинець Р. М\nДитина\nВолинець С. М\nДитина\nМихайло\nМихайлович\nВолинець\nВолинець Михайло Михайлович\nМихайло Михайлович Волинець\nМихайло Волинець\nВолинець Михайло Михайлович\nсуддя апеляційного суду львівської області\nЛьвівська область\nЗагальний апеляційний суд\nВолинець Михайло Михайлович","estate":{"25":[{"address":"","space_units":"м²","space_hidden":false,"space_unclear":false,"region_hidden":true,"costs_comment":"","space_comment":"","address_hidden":false,"space":"84.7","space_comment_unclear":false,"costs_rent_comment":"","costs":"","region":"","costs_rent":""}],"31":[{"costs_property_comment":"","address":"","space_units":"м²","space_hidden":false,"space_unclear":false,"region_hidden":true,"costs_property":"","space_comment":"","address_hidden":false,"costs_rent_comment_unclear":false,"costs_rent_comment":"","space":"64.2","region":"","costs_rent":""}]},"vehicle":{"35":[{"sum_comment":"","brand_info_hidden":false,"sum_rent":"","sum":"","brand_unclear":false,"year":"1999","brand":"Audi A4","brand_info":"1781 куб. см.","sum_rent_comment":"","brand_info_unclear":false,"sum_rent_unclear":false}],"40":[{"sum_comment":"","brand_info_hidden":false,"brand_info":"1399 куб. см.","sum":"","sum_rent_comment":"","brand_hidden":false,"brand":"Hyundai Getz","sum_rent":"","brand_info_unclear":false,"year":"2007"}]},"source":"VULYK","income":{"5":{"family_comment":"","value":"343246.32","family":"79433.84","comment":"","value_unclear":false},"6":{"family_comment":"","family":"79433.84","comment":"","value_unclear":false,"family_hidden":false,"value":"249085.33"},"7":{"family_comment":"","comment":"","family":"","source_name_unclear":false,"value":"","source_name":""},"8":{"family_comment":"","value":"","family":"","comment":""},"9":{"family_comment":"","value":"33.59","family":"","comment":"Приватбанк"},"10":{"family_comment":"","value":"","family":"","comment":""},"11":{"family_comment":"","comment_unclear":false,"value":"","family":"","comment":""},"12":{"family_comment":"","value":"","family":"","comment":""},"13":{"family_comment":"","value":"","family":"","comment":""},"14":{"family_comment":"","value":"","family":"","comment":""},"15":{"family_comment":"","value":"","family":"","comment":""},"16":{"family_comment":"","value":"","family":"","comment":""},"17":{"family_comment":"","value":"","family":"","comment":""},"18":{"family_comment":"","value":"","family":"","comment":""},"19":{"family_comment":"","value":"","family":"","comment":""},"20":{"family_comment":"","comment":"","family":"","value_unclear":false,"family_unclear":false,"comment_unclear":false,"value":"94127.4"}},"general":{"family":[{"inn":"","family_name":"Волинець Т. В","relations_other":"","name_unclear":false,"inn_hidden":true,"name_hidden":true,"relations":"Подружжя"},{"inn":"","family_name":"Волинець Р. М","relations_other":"","relations_unclear":false,"name_unclear":false,"inn_hidden":true,"name_hidden":false,"relations":"Дитина"},{"inn":"","family_name":"Волинець С. М","relations_other":"","name_unclear":false,"inn_hidden":false,"name_hidden":false,"relations":"Дитина"}],"family_raw":"","name":"Михайло","full_name_suggest":{"input":["Волинець Михайло Михайлович","Михайло Михайлович Волинець","Михайло Волинець"],"output":"Волинець Михайло Михайлович"},"patronymic":"Михайлович","inn_hidden":true,"addresses":[{"place_city_type_hidden":false,"place_city_type":"","place_city_hidden":true,"place_hidden":true,"place_district":"","place_district_hidden":false,"place":"","place_city":"","place_address_hidden":true,"place_address":""}],"patronymic_hidden":false,"inn":"","inn_unclear":false,"last_name":"Волинець","full_name":"Волинець Михайло Михайлович","post":{"office_unclear":false,"region_unclear":false,"post":"суддя апеляційного суду львівської області","region":"Львівська область","office":"Загальний апеляційний суд"}},"liabilities":{"54":{"sum_comment_unclear":false,"sum_comment":"ПАТ Страхова компанія Інгострах","sum_hidden":false,"sum":"240","sum_foreign_comment":"","sum_foreign":"","sum_unclear":false,"sum_comment_hidden":false},"55":{"sum_comment":"","sum_foreign_comment":"","sum_foreign":"","sum":""},"56":{"sum_comment":"","sum":"","sum_foreign_comment":"","sum_foreign":"","sum_unclear":false,"sum_comment_hidden":false},"57":{"sum_comment":"","sum_hidden":false,"sum":"","sum_foreign_comment":"","sum_foreign":"","sum_unclear":false,"sum_comment_hidden":false},"58":{"sum_comment_unclear":false,"sum_comment":"","sum_hidden":false,"sum":"","sum_foreign_comment":"","sum_foreign":"","sum_unclear":false,"sum_comment_hidden":false},"59":{"sum_comment":"","sum_foreign_comment":"","sum_foreign":"","sum":""},"60":{"sum_comment":"","sum_hidden":false,"sum":"","sum_foreign_comment":"","sum_foreign":"","sum_unclear":false,"sum_comment_hidden":false},"61":{"sum_comment":"","sum_foreign_comment":"","sum_foreign":"","sum":""},"62":{"sum_comment":"","sum_comment_unclear":false,"sum_foreign_comment":"","sum":"","sum_foreign":""},"63":{"sum_comment":"","sum_foreign_comment":"","sum_foreign":"","sum":"","sum_comment_hidden":false},"64":{"sum_comment":"","sum_foreign_comment":"","sum_foreign":"","sum":"","sum_comment_hidden":false}},"declaration":{"notfull_lostpages":"","additional_info_text":"","additional_info":"","date":"2016-03-30T00:00:00","notfull":"","url":"http://static.declarations.com.ua/declarations/chosen_ones/judges_batch/758_volynets_mykhailo_mykhailovych_2015.pdf"},"intro":{"declaration_year":"2015"}}