{"income":{"5":{"family_comment":"","value":"276061","family":"","comment":""},"6":{"family_comment":"","value":"270889","family":"","comment":""},"7":{"family_comment":"","value":"","source_name":"","family":"","comment":""},"8":{"family_comment":"","value":"","family":"","comment":""},"9":{"value":"5172","comment_unclear":false,"family_comment":"","family":"","comment":"","family_comment_unclear":false},"10":{"family_comment":"","value":"","family":"","comment":""},"11":{"family_comment":"","value":"","family":"","comment":""},"12":{"family_comment":"","value":"","family":"","comment":""},"13":{"family_comment":"","value":"","family":"","comment":""},"14":{"family_comment":"","value":"","family":"","comment":""},"15":{"family_comment":"","value":"","family":"","comment":""},"16":{"family_comment":"","value":"","family":"","comment":""},"17":{"family_comment":"","value":"","family":"","comment":""},"18":{"family_comment":"","value":"","family":"","comment":""},"19":{"value":"","family_comment":"","value_unclear":false,"family_unclear":false,"family":"","comment":""},"20":{"value":"","family_comment":"","value_unclear":false,"comment_hidden":false,"family_comment_hidden":false,"family_unclear":false,"family_comment_unclear":false,"comment_unclear":false,"comment":"","family":""}},"id":"vulyk_106_32","declaration":{"additional_info_text":"","notfull_lostpages":"","date":"2016-03-31T00:00:00","notfull":"","additional_info":"","url":"http://static.declarations.com.ua/declarations/chosen_ones/judges_batch/2171_dmytrenko_hanna_kostiantynivna.pdf"},"liabilities":{"54":{"sum_foreign_comment":"","sum":"","sum_comment":"","sum_comment_unclear":false,"sum_hidden":false,"sum_comment_hidden":false,"sum_foreign":""},"55":{"sum_foreign_comment":"","sum":"","sum_hidden":false,"sum_comment":"","sum_foreign":""},"56":{"sum_foreign_comment":"","sum":"","sum_comment":"","sum_hidden":false,"sum_comment_hidden":false,"sum_unclear":false,"sum_foreign":""},"57":{"sum_foreign_comment":"","sum":"","sum_comment":"","sum_hidden":false,"sum_comment_hidden":false,"sum_foreign":""},"58":{"sum_foreign_comment":"","sum":"","sum_comment":"","sum_hidden":false,"sum_comment_hidden":false,"sum_foreign":""},"59":{"sum_foreign_comment":"","sum":"","sum_comment":"","sum_foreign":""},"60":{"sum_foreign_comment":"","sum":"","sum_comment":"","sum_hidden":false,"sum_comment_hidden":false,"sum_foreign":""},"61":{"sum_foreign_comment":"","sum":"","sum_comment":"","sum_foreign":""},"62":{"sum_foreign_comment":"","sum":"","sum_comment":"","sum_comment_hidden":false,"sum_unclear":false,"sum_foreign":""},"63":{"sum_foreign_comment":"","sum":"","sum_comment":"","sum_foreign":""},"64":{"sum_foreign_comment":"","sum":"","sum_comment":"","sum_foreign":""}},"ft_src":"суддя дніпропетровського апеляційного господарського суду\nДніпропетровська область\nАпеляційний господарський суд\nГанна\nДмитренко Дмитро Юрійович\nДитина\nКостянтинівна\nДмитренко Ганна Костянтинівна\nГанна Костянтинівна Дмитренко\nГанна Дмитренко\nДмитренко Ганна Костянтинівна\nДмитренко Ганна Костянтинівна\nДмитренко\n5172\n276061\n270889\nспадщина\n43.4\n75.4\n74.6\n2015\n270889\n5172\n276061\n43.4\nспадщина\n75.4\n74.6\nДмитренко Ганна Костянтинівна\nГанна Костянтинівна Дмитренко\nГанна Дмитренко\nДмитренко Ганна Костянтинівна\nДмитренко Ганна Костянтинівна\nДитина\nДмитренко Дмитро Юрійович\nГанна\nДмитренко\nДніпропетровська область\nАпеляційний господарський суд\nсуддя дніпропетровського апеляційного господарського суду\nКостянтинівна\n270889\n276061\n5172\n2015\nДмитренко Дмитро Юрійович\nДитина\nКостянтинівна\nДмитренко\nГанна\nДмитренко Ганна Костянтинівна\nГанна Костянтинівна Дмитренко\nГанна Дмитренко\nДмитренко Ганна Костянтинівна\nДніпропетровська область\nАпеляційний господарський суд\nсуддя дніпропетровського апеляційного господарського суду\nДмитренко Ганна Костянтинівна\nспадщина\n43.4\n75.4\n74.6\n2015","general":{"inn":"","name":"Ганна","inn_unclear":false,"family":[{"inn":"","inn_hidden":true,"relations_unclear":false,"relations_hidden":false,"relations_other":"","relations":"Дитина","name_hidden":true,"family_name":"Дмитренко Дмитро Юрійович","name_unclear":false}],"inn_hidden":true,"family_raw":"","last_name":"Дмитренко","post":{"region_unclear":false,"region":"Дніпропетровська область","post":"суддя дніпропетровського апеляційного господарського суду","office":"Апеляційний господарський суд","office_unclear":false,"post_hidden":false},"full_name":"Дмитренко Ганна Костянтинівна","addresses":[{"place_district":"","place_city_hidden":true,"place_city":"","place_city_type_hidden":true,"place_district_hidden":true,"place_city_type":"","place_address_hidden":true,"place_address":"","place_hidden":true,"place":""}],"patronymic":"Костянтинівна","full_name_suggest":{"output":"Дмитренко Ганна Костянтинівна","input":["Дмитренко Ганна Костянтинівна","Ганна Костянтинівна Дмитренко","Ганна Дмитренко"]},"name_unclear":false},"source":"VULYK","estate":{"25":[{"costs":"","costs_comment":"","address_hidden":true,"region_hidden":true,"space_comment":"спадщина","space":"43.4","address":"","region":"","costs_rent_comment":"","space_comment_unclear":false,"space_units":"м²","costs_rent":""},{"space_unclear":false,"costs":"","costs_comment":"","address_hidden":false,"region_hidden":false,"space_comment":"","space":"75.4","address":"","region":"","costs_rent_comment":"","space_comment_unclear":false,"space_units":"м²","costs_rent":""},{"costs":"","costs_comment":"","address_hidden":false,"space_comment":"","space":"74.6","address":"","costs_unclear":false,"region":"","costs_rent_comment":"","space_comment_unclear":false,"space_units":"м²","costs_rent":""}]},"intro":{"declaration_year":"2015","isnotdeclaration":""}}