{"income":{"5":{"value":"237747","family_comment":"","value_unclear":false,"family_unclear":false,"family":"276546","comment":""},"6":{"value":"225567","family_comment":"","value_unclear":false,"value_hidden":false,"family_unclear":false,"family":"184862","comment":""},"7":{"family_comment":"","value":"","source_name":"","family":"","comment":""},"8":{"family_comment":"","value":"","family":"","comment":""},"9":{"value":"","family_comment":"","value_unclear":false,"family_unclear":false,"family":"","comment":""},"10":{"value":"12180","family_comment":"","value_unclear":false,"family_unclear":false,"family":"1684","comment":""},"11":{"family_comment":"","value":"","family":"","comment":""},"12":{"family_comment":"","value":"","family":"","comment":""},"13":{"family_comment":"","value":"","family":"","comment":""},"14":{"family_comment":"","value":"","family":"","comment":""},"15":{"family_comment":"","value":"","family":"","comment":""},"16":{"family_comment":"","value":"","family":"90000","comment":""},"17":{"family_comment":"","family_unclear":false,"value":"","family":"","comment":""},"18":{"family_comment":"","value":"","family":"","comment":""},"19":{"family_comment":"","value":"","family":"","comment":""},"20":{"value":"","comment_unclear":false,"family_comment":"","family":"","comment":"","family_comment_unclear":false}},"vehicle":{"40":[{"year_hidden":false,"brand_info":"1999 куб. см.","sum_rent_comment":"","brand":"Ford Focus","sum_comment":"","brand_unclear":false,"year":"2011","brand_hidden":false,"brand_info_unclear":false,"sum":"","sum_rent":""},{"brand_info":"3000 куб. см.","sum_rent_comment":"","brand":"Mitsubishi Outlander","sum_comment":"","year":"2008","sum":"","sum_rent":""}],"44":[{"brand_info":"мотоцикл 149 куб. см.","sum_rent_comment":"","brand":"Lifan","sum_comment":"","year":"2014","sum":"","sum_rent":""}]},"id":"vulyk_37_54","banks":{"45":[{"sum_foreign_comment":"","sum_units":"UAH","sum_units_hidden":false,"sum_comment":"","sum_comment_unclear":false,"sum_hidden":false,"sum_foreign_units":"UAH","sum_comment_hidden":false,"sum_unclear":false,"sum":"861","sum_foreign":""},{"sum_foreign_comment":"","sum_units":"","sum_comment":"","sum_foreign_units":"","sum":"","sum_foreign":""},{"sum_foreign_comment":"","sum_units":"","sum_comment":"","sum_foreign_units":"","sum":"","sum_foreign":""}],"46":[{"sum_foreign_comment":"","sum_units":"UAH","sum_comment":"","sum_foreign_units":"UAH","sum":"","sum_foreign":""},{"sum_foreign_comment":"","sum_units":"","sum_comment":"","sum_foreign_units":"","sum":"","sum_foreign":""}],"47":[{"sum_foreign_comment":"","sum_units":"UAH","sum_comment":"","sum_foreign_units":"UAH","sum_comment_hidden":false,"sum":"","sum_foreign":""}],"48":[{"sum_foreign_comment":"","sum_units":"UAH","sum_comment":"","sum_foreign_units":"UAH","sum":"","sum_foreign":""}],"49":[{"sum_foreign_comment":"","sum_units":"UAH","sum_comment":"","sum_foreign_units":"UAH","sum":"","sum_foreign":""}],"50":[{"sum_foreign_comment":"","sum_units":"UAH","sum_comment":"","sum_foreign_units":"UAH","sum":"","sum_foreign":""}],"51":[{"sum_foreign_comment":"","sum_units":"UAH","sum_comment":"","sum_hidden":false,"sum_foreign_units":"UAH","sum_comment_hidden":false,"sum_unclear":false,"sum":"","sum_foreign":""}],"52":[{"sum_foreign_comment":"","sum_units":"UAH","sum_comment":"","sum_foreign_units":"UAH","sum_comment_hidden":false,"sum":"","sum_foreign":""}],"53":[{"sum_foreign_comment":"","sum_units":"UAH","sum_comment":"","sum_comment_unclear":false,"sum_foreign_units":"UAH","sum":"","sum_foreign":""}]},"declaration":{"additional_info_text":"","notfull_lostpages":"","date":"2015-03-25T00:00:00","notfull":"","additional_info":"","url":"http://static.declarations.com.ua/declarations/chosen_ones/mega_batch/nezhentseva_olena_volodymyrivna.pdf"},"liabilities":{"54":{"sum_foreign_comment":"","sum_comment_hidden":false,"sum":"","sum_comment":"","sum_foreign":""},"55":{"sum_foreign_comment":"","sum":"","sum_comment":"","sum_foreign":""},"56":{"sum_foreign_comment":"","sum":"10900","sum_comment":"","sum_unclear":false,"sum_foreign":""},"57":{"sum_foreign_comment":"","sum":"","sum_comment":"","sum_hidden":false,"sum_comment_hidden":false,"sum_unclear":false,"sum_foreign":""},"58":{"sum_foreign_comment":"","sum":"","sum_comment":"","sum_hidden":false,"sum_comment_hidden":false,"sum_foreign":""},"59":{"sum_foreign_comment":"","sum":"","sum_hidden":false,"sum_comment":"","sum_foreign":""},"60":{"sum_foreign_comment":"","sum_comment_hidden":false,"sum":"","sum_comment":"","sum_foreign":""},"61":{"sum_foreign_comment":"","sum":"","sum_comment":"","sum_foreign":""},"62":{"sum_foreign_comment":"","sum":"47175","sum_comment":"","sum_unclear":false,"sum_foreign":""},"63":{"sum_foreign_comment":"","sum_comment_hidden":false,"sum":"","sum_comment":"","sum_foreign":""},"64":{"sum_foreign_comment":"","sum_comment_hidden":false,"sum":"","sum_comment":"","sum_foreign":""}},"ft_src":"47175\n10900\nсуддя центрально-міського райсуду м. макіївки, з 25 лютого 2015 р. - суддя слов'янського міськрайонного суду донецької області\nДонецька область\nЗагальний місцевий суд\nОлена\nНеженцев В. А\nПодружжя\nНеженцев М. В\nДитина\nШирокорад Є. А\nБатьки\nВолодимирівна\nНеженцева Олена Володимирівна\nОлена Володимирівна Неженцева\nОлена Неженцева\nНеженцева Олена Володимирівна\nНеженцева\nНеженцева Олена Володимирівна\nFord Focus\n1999 куб. см.\n2011\n3000 куб. см.\n2008\nMitsubishi Outlander\nмотоцикл 149 куб. см.\n2014\nLifan\n861\n2014\n1999 куб. см.\n2011\nFord Focus\n3000 куб. см.\nMitsubishi Outlander\n2008\nмотоцикл 149 куб. см.\nLifan\n2014\n861\n620\n26.8\n26.1\n33.47\n64.9\n16.73\nПодружжя\nНеженцев В. А\nДитина\nНеженцев М. В\nБатьки\nШирокорад Є. А\nНеженцева Олена Володимирівна\nОлена Володимирівна Неженцева\nОлена Неженцева\nНеженцева Олена Володимирівна\nНеженцева Олена Володимирівна\nОлена\nВолодимирівна\nЗагальний місцевий суд\nсуддя центрально-міського райсуду м. макіївки, з 25 лютого 2015 р. - суддя слов'янського міськрайонного суду донецької області\nДонецька область\nНеженцева\n10900\n47175\n184862\n225567\n237747\n276546\n90000\n12180\n1684\n2014\n10900\n47175\n620\n26.8\n26.1\n33.47\n64.9\n16.73\nНеженцев В. А\nПодружжя\nНеженцев М. В\nДитина\nШирокорад Є. А\nБатьки\nВолодимирівна\nНеженцева\nОлена\nНеженцева Олена Володимирівна\nОлена Володимирівна Неженцева\nОлена Неженцева\nНеженцева Олена Володимирівна\nДонецька область\nсуддя центрально-міського райсуду м. макіївки, з 25 лютого 2015 р. - суддя слов'янського міськрайонного суду донецької області\nЗагальний місцевий суд\nНеженцева Олена Володимирівна\n184862\n225567\n1684\n12180\n276546\n237747\n90000\nLifan\nмотоцикл 149 куб. см.\n2014\n2011\nFord Focus\n1999 куб. см.\nMitsubishi Outlander\n3000 куб. см.\n2008\n12180\n1684\n237747\n276546\n90000\n225567\n184862\n33.47\n64.9\n620\n26.8\n26.1\n16.73\n861\n2014","general":{"inn":"","name":"Олена","patronymic_unclear":false,"family":[{"inn":"","inn_hidden":true,"relations_unclear":false,"relations_hidden":false,"relations_other":"","relations":"Подружжя","name_hidden":true,"family_name":"Неженцев В. А","name_unclear":false},{"inn":"","relations":"Дитина","relations_unclear":false,"family_name":"Неженцев М. В","inn_hidden":false,"relations_other":"","name_hidden":false,"name_unclear":false},{"inn":"","relations":"Батьки","relations_unclear":false,"family_name":"Широкорад Є. А","inn_hidden":false,"relations_other":"","name_hidden":false,"name_unclear":false}],"patronymic":"Володимирівна","inn_hidden":true,"family_raw":"","last_name":"Неженцева","post":{"post_unclear":false,"post":"суддя центрально-міського райсуду м. макіївки, з 25 лютого 2015 р. - суддя слов'янського міськрайонного суду донецької області","post_hidden":false,"region":"Донецька область","region_hidden":false,"office":"Загальний місцевий суд","office_hidden":false,"office_unclear":false},"last_name_unclear":false,"full_name":"Неженцева Олена Володимирівна","addresses":[{"place_district":"","place_city_hidden":true,"place_city":"","place_city_type_hidden":false,"place_district_hidden":false,"place_city_type":"","place_address_hidden":true,"place_address":"","place_hidden":true,"place":""}],"full_name_suggest":{"output":"Неженцева Олена Володимирівна","input":["Неженцева Олена Володимирівна","Олена Володимирівна Неженцева","Олена Неженцева"]},"name_unclear":false},"source":"VULYK","estate":{"23":[{"space_unclear":false,"costs":"","costs_comment":"","address_hidden":true,"region_hidden":true,"space_comment":"","space_hidden":false,"space":"620","address":"","region":"","space_units_unclear":false,"space_units":"м²","costs_rent":"","costs_rent_comment":""},{"costs_rent":"","space_unclear":false,"region":"","costs":"","costs_rent_comment":"","costs_comment":"","space_comment":"","space_units":"","space":"","address":""},{"costs_rent":"","region":"","costs":"","costs_rent_comment":"","costs_comment":"","space_comment":"","space_units":"","space":"","address":""},{"costs_rent":"","region":"","costs":"","costs_rent_comment":"","costs_comment":"","space_comment":"","space_units":"","space":"","address":""},{"costs_rent":"","region":"","costs":"","costs_rent_comment":"","costs_comment":"","space_comment":"","space_units":"","space":"","address":""},{"costs_rent":"","region":"","costs":"","costs_rent_comment":"","costs_comment":"","space_comment":"","space_units":"","space":"","address":""},{"costs_rent":"","region":"","costs":"","costs_rent_comment":"","costs_comment":"","space_comment":"","space_units":"","space":"","address":""},{"costs_rent":"","region":"","costs":"","costs_rent_comment":"","costs_comment":"","space_comment":"","space_units":"","space":"","address":""}],"25":[{"region_unclear":false,"space_hidden":false,"costs":"","costs_rent_unclear":false,"costs_comment":"","address_hidden":true,"region_hidden":true,"space_comment":"","space_unclear":false,"space":"16.73","address":"","region":"","address_unclear":false,"costs_rent_comment":"","space_comment_unclear":false,"space_units":"м²","costs_rent":""}],"31":[{"region_unclear":false,"space_hidden":false,"address_hidden":true,"region_hidden":true,"space_comment":"","space_unclear":false,"space":"33.47","address":"","region":"","costs_property":"","costs_rent_comment":"","address_unclear":false,"space_units":"м²","costs_property_comment":"","costs_rent":""},{"costs_rent":"","region":"","costs_property":"","costs_rent_comment":"","space_comment":"","costs_property_comment":"","space_units":"м²","space":"64.9","address":""}],"33":[{"costs_rent":"","region":"","costs_property":"","costs_rent_comment":"","address_hidden":true,"region_hidden":true,"space_comment":"","costs_property_comment":"","space_units":"м²","space":"26.8","address":""},{"costs_rent":"","costs_property":"","costs_rent_comment":"","space_comment":"","costs_property_comment":"","space_units":"м²","space":"26.1","address":""}]},"intro":{"declaration_year":"2014","isnotdeclaration":"","declaration_year_unclear":false}}