{"income":{"5":{"family_comment":"","value":"230222","family_hidden":false,"comment":"","family":"175024"},"6":{"value":"230222","value_unclear":false,"family_hidden":false,"family_comment":"","family":"","comment":""},"7":{"family_comment":"","value":"","source_name":"","family":"","comment":""},"8":{"family_comment":"","value":"","family":"","comment":""},"9":{"family_comment":"","value":"","value_unclear":false,"family":"","comment":""},"10":{"family_comment":"","value":"","value_unclear":false,"family":"","comment":""},"11":{"family_comment":"","value":"","family":"","comment":""},"12":{"family_comment":"","value":"","family":"","comment":""},"13":{"family_comment":"","value":"","family":"","comment":""},"14":{"family_comment":"","value":"","family":"","comment":""},"15":{"family_comment":"","value":"","family":"","comment":""},"16":{"family_comment":"","value":"","family":"","comment":"","family_comment_hidden":false},"17":{"family_comment":"","value":"","family_hidden":false,"comment":"","family":"149480"},"18":{"family_comment":"","value":"","family":"","comment":""},"19":{"family_comment":"","value":"","family":"","comment":""},"20":{"value":"","value_unclear":false,"family_comment_hidden":false,"family_comment":"","comment_unclear":false,"comment":"","family":"25544"}},"vehicle":{"35":[{"year_hidden":false,"brand_info":"1600 куб. см., 91.94 KW","sum_rent_comment":"","year":"2011","brand_info_hidden":false,"brand_info_unclear":false,"year_unclear":false,"sum_rent":"","sum":"","brand":"Ford Focus","sum_comment":"інше правове користування","brand_unclear":false,"brand_hidden":false,"sum_unclear":false}],"40":[{"year_hidden":false,"brand_info":"1600 куб. см., 91.94 KW","sum_rent_comment":"","year":"2011","brand_info_hidden":false,"brand_info_unclear":false,"sum_rent":"","sum":"","brand":"Ford Focus","sum_comment":"","brand_unclear":false,"brand_hidden":false}]},"id":"vulyk_42_76","banks":{"45":[{"sum_foreign_comment":"","sum_units":"UAH","sum_comment":"","sum_foreign_comment_hidden":false,"sum_hidden":false,"sum_foreign_units":"UAH","sum_foreign_hidden":false,"sum_comment_hidden":false,"sum_unclear":false,"sum":"","sum_foreign":""},{"sum_foreign_comment":"","sum_units":"","sum_comment":"","sum_foreign_units":"","sum":"","sum_foreign":""}],"46":[{"sum_foreign_comment":"","sum_units":"UAH","sum_comment":"","sum_hidden":false,"sum_foreign_units":"UAH","sum_comment_hidden":false,"sum_unclear":false,"sum":"","sum_foreign":""}],"47":[{"sum_foreign_comment":"","sum_units":"UAH","sum_comment":"","sum_comment_unclear":false,"sum_hidden":false,"sum_foreign_units":"UAH","sum":"","sum_foreign":""},{"sum_foreign_comment":"","sum":"","sum_comment":"","sum_foreign":""}],"48":[{"sum_foreign_comment":"","sum_units":"UAH","sum_comment":"","sum_foreign_units":"UAH","sum":"","sum_foreign":""}],"49":[{"sum_foreign_comment":"","sum_units":"UAH","sum_comment":"","sum_foreign_units":"UAH","sum":"","sum_foreign":""}],"50":[{"sum_foreign_comment":"","sum_units":"UAH","sum_comment":"","sum_foreign_units":"UAH","sum":"","sum_foreign":""}],"51":[{"sum_foreign_comment":"","sum_units":"UAH","sum_comment":"","sum_comment_unclear":false,"sum_hidden":false,"sum_foreign_units":"UAH","sum_comment_hidden":false,"sum":"","sum_foreign":""},{"sum_foreign_comment":"","sum_units":"","sum_comment":"","sum_hidden":false,"sum_foreign_units":"","sum":"","sum_units_hidden":false,"sum_foreign":""}],"52":[{"sum_foreign_comment":"","sum_units":"UAH","sum_comment":"","sum_comment_unclear":false,"sum_hidden":false,"sum_foreign_units":"UAH","sum":"","sum_units_hidden":false,"sum_foreign":""}],"53":[{"sum_foreign_comment":"","sum_units":"UAH","sum_comment":"","sum_foreign_units":"UAH","sum":"","sum_foreign":""}]},"declaration":{"additional_info_text":"","notfull_lostpages":"","date":"2015-03-30T00:00:00","notfull":"","additional_info":"","url":"http://static.declarations.com.ua/declarations/chosen_ones/mega_batch/boiko_v_iacheslav_petrovych.pdf"},"liabilities":{"54":{"sum_foreign_comment":"","sum":"","sum_comment":"","sum_foreign_comment_hidden":false,"sum_comment_hidden":false,"sum_foreign":""},"55":{"sum_foreign_comment":"","sum":"","sum_comment":"","sum_foreign":""},"56":{"sum_foreign_comment":"","sum":"","sum_comment":"","sum_foreign":""},"57":{"sum_foreign_comment":"","sum":"","sum_comment":"","sum_comment_unclear":false,"sum_comment_hidden":false,"sum_unclear":false,"sum_foreign":""},"58":{"sum_foreign_comment":"","sum":"","sum_comment":"","sum_foreign_unclear":false,"sum_comment_hidden":false,"sum_unclear":false,"sum_foreign":""},"59":{"sum_foreign_comment":"","sum":"","sum_comment":"","sum_foreign":""},"60":{"sum_foreign_comment":"","sum":"","sum_comment":"","sum_comment_unclear":false,"sum_hidden":false,"sum_comment_hidden":false,"sum_foreign":""},"61":{"sum_foreign_comment":"","sum":"","sum_comment":"","sum_foreign":""},"62":{"sum_foreign_comment":"","sum":"","sum_comment":"","sum_hidden":false,"sum_comment_hidden":false,"sum_foreign":""},"63":{"sum_foreign_comment":"","sum":"","sum_comment":"","sum_comment_hidden":false,"sum_unclear":false,"sum_foreign":""},"64":{"sum_foreign_comment":"","sum":"","sum_comment":"","sum_hidden":false,"sum_comment_hidden":false,"sum_foreign":""}},"ft_src":"голова суду, суддя цюрупинського районного суду херсонської області\nХерсонська область\nЗагальний місцевий суд\nВ'ячеслав\nЯновська А. О\nдружина без реєстрації шлюбу\nІнше\nБойко М. В\nДитина\nБойко М. В\nДитина\nБойко О. В\nДитина\nПетрович\nБойко В'ячеслав Петрович\nВ'ячеслав Петрович Бойко\nВ'ячеслав Бойко\nБойко В'ячеслав Петрович\nБойко\nБойко В'ячеслав Петрович\nінше правове користування\n1600 куб. см., 91.94 KW\nFord Focus\n2011\n1600 куб. см., 91.94 KW\nFord Focus\n2011\n2014\n1600 куб. см., 91.94 KW\nінше правове користування\nFord Focus\n2011\n1600 куб. см., 91.94 KW\nFord Focus\n2011\n68\n15.5\n101.2\nІнше\nдружина без реєстрації шлюбу\nЯновська А. О\nДитина\nБойко М. В\nДитина\nБойко М. В\nБойко О. В\nДитина\nБойко В'ячеслав Петрович\nВ'ячеслав Петрович Бойко\nВ'ячеслав Бойко\nБойко В'ячеслав Петрович\nБойко В'ячеслав Петрович\nВ'ячеслав\nБойко\nголова суду, суддя цюрупинського районного суду херсонської області\nЗагальний місцевий суд\nХерсонська область\nПетрович\n230222\n149480\n25544\n230222\n175024\n2014\n15.5\n68\n101.2\nдружина без реєстрації шлюбу\nЯновська А. О\nІнше\nБойко М. В\nДитина\nБойко М. В\nДитина\nДитина\nБойко О. В\nПетрович\nБойко\nВ'ячеслав\nБойко В'ячеслав Петрович\nВ'ячеслав Петрович Бойко\nВ'ячеслав Бойко\nБойко В'ячеслав Петрович\nХерсонська область\nголова суду, суддя цюрупинського районного суду херсонської області\nЗагальний місцевий суд\nБойко В'ячеслав Петрович\n230222\n175024\n230222\n149480\n25544\nFord Focus\nінше правове користування\n1600 куб. см., 91.94 KW\n2011\n2011\nFord Focus\n1600 куб. см., 91.94 KW\n25544\n175024\n230222\n149480\n230222\n68\n15.5\n101.2\n2014","general":{"inn":"","name":"В'ячеслав","patronymic_unclear":false,"last_name_hidden":false,"family":[{"inn":"","inn_hidden":true,"relations_hidden":false,"family_name":"Яновська А. О","relations_other":"дружина без реєстрації шлюбу","relations":"Інше","name_hidden":false,"name_unclear":true},{"inn":"","relations":"Дитина","relations_other":"","inn_hidden":false,"family_name":"Бойко М. В","name_hidden":false,"name_unclear":false},{"inn":"","relations":"Дитина","relations_other":"","inn_hidden":false,"family_name":"Бойко М. В","name_hidden":false,"name_unclear":false},{"inn":"","family_name":"Бойко О. В","relations":"Дитина","relations_other":"","name_unclear":false}],"patronymic":"Петрович","inn_hidden":true,"family_raw":"","last_name":"Бойко","post":{"region_unclear":false,"region":"Херсонська область","post":"голова суду, суддя цюрупинського районного суду херсонської області","office":"Загальний місцевий суд","office_hidden":false,"region_hidden":false},"last_name_unclear":false,"full_name":"Бойко В'ячеслав Петрович","addresses":[{"place_district":"","place_city_hidden":true,"place_city":"","place_city_type_hidden":true,"place_district_hidden":true,"place_city_type":"","place_address_hidden":true,"place_address":"","place_hidden":true,"place":""}],"full_name_suggest":{"output":"Бойко В'ячеслав Петрович","input":["Бойко В'ячеслав Петрович","В'ячеслав Петрович Бойко","В'ячеслав Бойко"]}},"source":"VULYK","estate":{"23":[{"space_unclear":false,"costs":"","costs_comment":"","address_hidden":false,"region_hidden":false,"space_comment":"","space_hidden":false,"space":"","address":"","region":"","address_unclear":false,"space_units_unclear":false,"space_comment_unclear":false,"space_units":"м²","costs_rent":"","costs_rent_comment":""},{"costs":"","costs_comment":"","address_hidden":false,"region_hidden":false,"space_comment":"","space_units_unclear":false,"address":"","space":"","region":"","costs_rent_comment":"","space_units":"","costs_rent":""},{"costs_rent":"","region":"","costs":"","costs_rent_comment":"","costs_comment":"","space_comment":"","space_units":"","space":"","address":""},{"costs_rent":"","region":"","costs":"","costs_rent_comment":"","costs_comment":"","space_comment":"","space_units":"","space":"","address":""},{"costs_rent":"","region":"","costs":"","costs_rent_comment":"","costs_comment":"","space_comment":"","space_units":"","space":"","address":""},{"costs_rent":"","costs":"","costs_rent_comment":"","costs_comment":"","space_comment":"","space_units":"","space":"","address":""}],"25":[{"space_unclear":false,"costs":"","costs_comment":"","address_hidden":true,"region_hidden":true,"space_comment":"","space_hidden":false,"space":"101.2","address":"","region":"","costs_rent_comment":"","space_comment_unclear":false,"space_units":"м²","costs_rent":""}],"31":[{"space_hidden":false,"address_hidden":false,"region_hidden":true,"space_comment":"","space":"68","address":"","region":"","costs_property":"","costs_rent_comment":"","space_units":"м²","costs_property_comment":"","costs_rent":""}],"34":[{"costs_rent":"","region":"","costs_property":"","costs_rent_comment":"","address_hidden":true,"region_hidden":true,"space_comment":"","costs_property_comment":"","space_units":"м²","space":"15.5","address":""}]},"intro":{"declaration_year":"2014","isnotdeclaration":""}}