{"income":{"5":{"value":"208360","family_comment":"","value_unclear":false,"family_unclear":false,"family":"","comment":""},"6":{"family_comment":"","value":"202855","value_unclear":false,"family":"","comment":""},"7":{"family_comment":"","value":"5505","source_name":"Дніпропетровський державний університет внутрішніх справ","family":"","comment":""},"8":{"family_comment":"","value":"","family":"","comment":""},"9":{"family_comment":"","value":"","value_unclear":false,"family":"","comment":""},"10":{"family_comment":"","value":"","family":"","comment":""},"11":{"family_comment":"","value":"","family":"","comment":""},"12":{"family_comment":"","value":"","family":"","comment":""},"13":{"family_comment":"","value":"","family":"","comment":""},"14":{"family_comment":"","value":"","family":"","comment":""},"15":{"family_comment":"","value":"","family":"","comment":""},"16":{"family_comment":"","value":"","family":"","comment":""},"17":{"family_comment":"","value":"","family":"","comment":""},"18":{"family_comment":"","value":"","family":"","comment":""},"19":{"family_comment":"","value":"","family":"","comment":""},"20":{"family_comment":"","value":"","value_unclear":false,"family":"","comment":""}},"vehicle":{"35":[{"brand_info":"1199 куб. см.","sum_rent_comment":"","brand":"Citroen C-Elysee","sum_comment":"","brand_unclear":false,"year":"2013","brand_info_unclear":false,"sum":"","sum_rent":""}]},"id":"vulyk_98_47","declaration":{"date":"2015-03-30T00:00:00","url":"http://static.declarations.com.ua/declarations/chosen_ones/judges_batch/4544_boieva_olena_serhiivna.pdf"},"liabilities":{"54":{"sum_foreign_comment":"","sum":"24748","sum_comment":"","sum_comment_unclear":false,"sum_hidden":false,"sum_comment_hidden":true,"sum_unclear":true,"sum_foreign":""},"55":{"sum_foreign_comment":"","sum":"","sum_comment":"","sum_foreign":""},"56":{"sum_foreign_comment":"","sum":"","sum_comment":"","sum_unclear":false,"sum_foreign":""},"57":{"sum_foreign_comment":"","sum":"25641","sum_comment":"","sum_comment_unclear":false,"sum_hidden":false,"sum_comment_hidden":true,"sum_unclear":true,"sum_foreign":""},"58":{"sum_foreign_comment":"","sum":"","sum_comment":"","sum_hidden":false,"sum_comment_hidden":false,"sum_unclear":false,"sum_foreign":""},"59":{"sum_foreign_comment":"","sum":"","sum_comment":"","sum_comment_unclear":false,"sum_foreign":""},"60":{"sum_foreign_comment":"","sum":"","sum_comment":"","sum_hidden":false,"sum_comment_hidden":false,"sum_foreign":""},"61":{"sum_foreign_comment":"","sum":"","sum_comment":"","sum_foreign":""},"62":{"sum_foreign_comment":"","sum":"","sum_comment":"","sum_comment_hidden":false,"sum_unclear":false,"sum_foreign":""},"63":{"sum_foreign_comment":"","sum":"","sum_comment":"","sum_comment_unclear":false,"sum_comment_hidden":false,"sum_foreign":""},"64":{"sum_foreign_comment":"","sum_comment_hidden":false,"sum":"","sum_comment":"","sum_foreign":""}},"ft_src":"25641\n24748\nсуддя господарського суду запорізької області\nЗапорізька область\nГосподарський місцевий суд\nОлена\nФіліна П. О\nДитина\nСергіївна\nБоєва Олена Сергіївна\nОлена Сергіївна Боєва\nОлена Боєва\nБоєва Олена Сергіївна\nБоєва Олена Сергіївна\nБоєва\n208360\nДніпропетровський державний університет внутрішніх справ\n5505\n202855\n2013\n1199 куб. см.\nCitroen C-Elysee\n2013\nCitroen C-Elysee\n1199 куб. см.\n2014\n202855\n5505\nДніпропетровський державний університет внутрішніх справ\n208360\n1199 куб. см.\n2013\nCitroen C-Elysee\nДніпропетровський державний університет внутрішніх справ\n5505\n202855\n208360\nГосподарський місцевий суд\nсуддя господарського суду запорізької області\nЗапорізька область\nБоєва Олена Сергіївна\nОлена Сергіївна Боєва\nОлена Боєва\nБоєва Олена Сергіївна\nБоєва Олена Сергіївна\nДитина\nФіліна П. О\nОлена\nБоєва\nСергіївна\n24748\n25641\n2014\n25641\n24748\nДитина\nФіліна П. О\nСергіївна\nБоєва\nОлена\nБоєва Олена Сергіївна\nОлена Сергіївна Боєва\nОлена Боєва\nБоєва Олена Сергіївна\nсуддя господарського суду запорізької області\nЗапорізька область\nГосподарський місцевий суд\nБоєва Олена Сергіївна\n2014","general":{"inn":"","name":"Олена","last_name_hidden":false,"family":[{"inn":"","relations":"Дитина","relations_other":"","inn_hidden":true,"family_name":"Філіна П. О","name_hidden":true,"name_unclear":true}],"patronymic":"Сергіївна","inn_hidden":true,"family_raw":"","inn_unclear":false,"post":{"post_unclear":false,"office":"Господарський місцевий суд","post":"суддя господарського суду запорізької області","region":"Запорізька область"},"full_name_suggest":{"output":"Боєва Олена Сергіївна","input":["Боєва Олена Сергіївна","Олена Сергіївна Боєва","Олена Боєва"]},"full_name":"Боєва Олена Сергіївна","addresses":[{"place_district":"","place_city_hidden":true,"place_city":"","place_city_type_hidden":false,"place_district_hidden":false,"place_city_type":"","place_address_hidden":true,"place_address":"","place_hidden":true,"place":""}],"last_name":"Боєва","patronymic_hidden":false,"last_name_unclear":false},"source":"VULYK","intro":{"declaration_year":"2014"}}