{"income":{"5":{"family_comment":"","value":"245375","family":"77570","comment":""},"6":{"family_comment":"","value":"225051","family":"77570","comment":""},"7":{"value":"","comment_hidden":false,"family_comment":"","source_name":"","family":"","comment":"","source_name_hidden":false},"8":{"family_comment":"","value":"","family_hidden":false,"comment":"","family":""},"9":{"value":"1167","family_comment":"","value_unclear":false,"family_unclear":false,"family":"","comment":""},"10":{"family_comment":"","value":"","family":"","comment":""},"11":{"family_comment":"","value":"","family":"","comment":""},"12":{"family_comment":"","value":"","family":"","comment":""},"13":{"family_comment":"","value":"","family":"","comment":""},"14":{"family_comment":"","value":"","family":"","comment":""},"15":{"family_comment":"","value":"","family":"","comment":""},"16":{"family_comment":"","value":"","family":"","comment":""},"17":{"family_comment":"","value":"","family":"","comment":""},"18":{"family_comment":"","value":"","family":"","comment":""},"19":{"family_comment":"","value":"","family":"","comment":""},"20":{"value":"19157","value_unclear":false,"family_hidden":false,"family_comment":"","family":"","comment":""}},"id":"vulyk_109_12","banks":{"45":[{"sum_foreign_comment":"","sum_unclear":false,"sum_units":"UAH","sum_comment":"ПАТ «Укрсоцбанк»","sum_foreign_units":"UAH","sum_comment_hidden":false,"sum_units_hidden":false,"sum":"2995","sum_foreign":""}]},"declaration":{"additional_info_text":"","notfull_lostpages":"","date":"2016-03-25T00:00:00","notfull":"","additional_info":"","url":"http://static.declarations.com.ua/declarations/chosen_ones/judges_batch/2469_kozhukhar_mariia_serhiivna_2015.pdf"},"liabilities":{"54":{"sum_foreign_comment":"","sum":"","sum_comment":"","sum_hidden":false,"sum_comment_hidden":false,"sum_unclear":false,"sum_foreign":""},"55":{"sum_foreign_comment":"","sum":"","sum_comment":"","sum_comment_unclear":false,"sum_foreign":""},"56":{"sum_foreign_comment":"","sum":"","sum_comment":"","sum_foreign":""},"57":{"sum_foreign_comment":"","sum_comment_hidden":false,"sum":"","sum_comment":"","sum_foreign":""},"58":{"sum_foreign_comment":"","sum_comment_hidden":false,"sum":"","sum_comment":"","sum_foreign":""},"59":{"sum_foreign_comment":"","sum":"","sum_comment":"","sum_foreign":""},"60":{"sum_foreign_comment":"","sum":"","sum_comment":"","sum_foreign":""},"61":{"sum_foreign_comment":"","sum":"","sum_comment":"","sum_foreign":""},"62":{"sum_foreign_comment":"","sum":"","sum_comment":"","sum_foreign":""},"63":{"sum_foreign_comment":"","sum":"","sum_comment":"","sum_foreign":""},"64":{"sum_foreign_comment":"","sum":"","sum_comment":"","sum_foreign":""}},"ft_src":"суддя господарського суду вінницької області\nВінницька область\nГосподарський місцевий суд\nМарія\nКожухар В. В\nДитина\nСергіївна\nКожухар Марія Сергіївна\nКожухар\nКожухар Марія Сергіївна\nМарія Сергіївна Кожухар\nМарія Кожухар\nКожухар Марія Сергіївна\n1000\n85.3\n66.9\n551\n41.2\nПАТ «Укрсоцбанк»\n2995\n2015\n2015\nДитина\nКожухар В. В\nКожухар Марія Сергіївна\nМарія Сергіївна Кожухар\nМарія Кожухар\nКожухар Марія Сергіївна\nМарія\nКожухар Марія Сергіївна\nКожухар\nГосподарський місцевий суд\nВінницька область\nсуддя господарського суду вінницької області\nСергіївна\n225051\n77570\n19157\n245375\n77570\n1167\n41.2\n551\n1000\n85.3\n66.9\n2995\nПАТ «Укрсоцбанк»\n77570\n225051\n77570\n245375\n1167\n19157\nДитина\nКожухар В. В\nМарія\nСергіївна\nКожухар\nКожухар Марія Сергіївна\nМарія Сергіївна Кожухар\nМарія Кожухар\nКожухар Марія Сергіївна\nВінницька область\nГосподарський місцевий суд\nсуддя господарського суду вінницької області\nКожухар Марія Сергіївна\n19157\n77570\n245375\n1167\n77570\n225051\n66.9\n551\n85.3\n41.2\n1000\nПАТ «Укрсоцбанк»\n2995\n2015","general":{"name_hidden":false,"name":"Марія","inn":"","inn_unclear":false,"family":[{"inn":"","relations":"Дитина","relations_hidden":false,"inn_hidden":true,"relations_other":"","name_hidden":false,"family_name":"Кожухар В. В","name_unclear":false}],"inn_hidden":true,"family_raw":"","last_name":"Кожухар","post":{"region_unclear":false,"region":"Вінницька область","post":"суддя господарського суду вінницької області","region_hidden":false,"office":"Господарський місцевий суд","office_hidden":false,"office_unclear":false},"full_name":"Кожухар Марія Сергіївна","patronymic":"Сергіївна","full_name_suggest":{"output":"Кожухар Марія Сергіївна","input":["Кожухар Марія Сергіївна","Марія Сергіївна Кожухар","Марія Кожухар"]}},"source":"VULYK","estate":{"23":[{"space_unclear":false,"costs":"","costs_rent_unclear":false,"costs_comment":"","address_hidden":false,"region_hidden":true,"space_comment":"","space":"551","address":"","region":"","costs_rent_comment":"","space_units":"м²","costs_rent":""}],"24":[{"costs_rent":"","region":"","costs":"","costs_rent_comment":"","costs_comment":"","address_hidden":false,"region_hidden":true,"space_comment":"","space_units":"м²","space":"85.3","address":""}],"25":[{"space_unclear":false,"costs":"","costs_comment":"","address_hidden":false,"region_hidden":true,"space_comment":"","space_hidden":false,"space":"41.2","address":"","region":"","costs_rent_comment":"","space_units":"м²","space_units_hidden":false,"costs_rent":""}],"29":[{"space_unclear":false,"address_hidden":true,"region_hidden":true,"space_comment":"","space":"1000","address":"","region":"","costs_property":"","costs_rent_comment":"","space_units":"м²","costs_property_comment":"","costs_rent":""}],"30":[{"costs_rent":"","space_hidden":false,"costs_property":"","costs_rent_comment":"","address_hidden":false,"region_hidden":true,"space_comment":"","costs_property_comment":"","space_units":"м²","space":"","address":""}],"31":[{"space_hidden":false,"costs_property_comment":"","address_hidden":true,"region_hidden":true,"space_comment":"","space":"66.9","address":"","region":"","costs_property":"","costs_rent_comment":"","space_units":"м²","space_units_hidden":false,"costs_rent":""}]},"intro":{"declaration_year":"2015","isnotdeclaration":""}}