{"income":{"5":{"value":"227052","family_comment":"","value_unclear":false,"family_unclear":false,"family":"6124","comment":""},"6":{"family_comment":"","value":"227052","value_unclear":false,"family":"3364","comment":""},"7":{"value":"","value_unclear":false,"family_comment":"","source_name":"","family":"","comment":""},"8":{"family_comment":"","value":"","family":"","comment":""},"9":{"value":"","family_comment":"","value_unclear":false,"family_unclear":false,"family":"","comment":""},"10":{"family_comment":"","value":"","comment_unclear":false,"family":"","comment":""},"11":{"family_comment":"","value":"","family":"60","comment":""},"12":{"family_comment":"","value":"","family":"","comment":""},"13":{"family_comment":"","value":"","value_unclear":false,"family":"","comment":""},"14":{"family_comment":"","value":"","family":"","comment":""},"15":{"family_comment":"","value":"","family":"","comment":""},"16":{"family_comment":"","family_unclear":false,"value":"","family":"","comment":""},"17":{"family_comment":"","family_unclear":false,"value":"","family":"2500","comment":""},"18":{"family_comment":"","value":"","family":"","comment":""},"19":{"family_comment":"","value":"","family":"","comment":""},"20":{"value":"","family_comment":"","value_unclear":false,"family_hidden":false,"value_hidden":false,"family_unclear":false,"comment_unclear":false,"comment":"","family":"200"}},"vehicle":{"35":[{"brand_info":"3956 куб. см. у користуванні","sum_rent_comment":"","brand_info_unclear":false,"year":"2007","brand_info_hidden":false,"sum_rent_comment_unclear":false,"sum_rent":"","sum":"","brand":"Toyota Prado","sum_comment":"","brand_unclear":false,"brand_hidden":false}],"40":[{"brand_info":"1792 куб. см. у власності","sum_rent_comment":"","brand":"Geely Emgrand 7","sum_comment":"","year":"2014","brand_info_hidden":false,"brand_info_unclear":false,"sum":"","sum_rent":""}]},"id":"vulyk_100_14","declaration":{"additional_info_text":"","notfull_lostpages":"","date":"2015-03-31T00:00:00","notfull":"","additional_info":"","url":"http://static.declarations.com.ua/declarations/chosen_ones/judges_batch/4132_serdynskyi_volodymyr_stepanovych.pdf"},"liabilities":{"54":{"sum_foreign_comment":"","sum":"","sum_comment":"","sum_comment_hidden":false,"sum_unclear":false,"sum_foreign":""},"55":{"sum_foreign_comment":"","sum":"","sum_comment":"","sum_foreign":""},"56":{"sum_foreign_comment":"","sum":"25000","sum_comment":"","sum_unclear":false,"sum_foreign":""},"57":{"sum_foreign_comment":"","sum":"","sum_comment":"","sum_comment_unclear":false,"sum_comment_hidden":false,"sum_unclear":false,"sum_foreign":""},"58":{"sum_foreign_comment":"","sum":"","sum_comment":"","sum_comment_hidden":false,"sum_unclear":false,"sum_foreign":""},"59":{"sum_foreign_comment":"","sum":"","sum_comment":"","sum_foreign":""},"60":{"sum_foreign_comment":"","sum_comment_hidden":false,"sum":"","sum_comment":"","sum_foreign":""},"61":{"sum_foreign_comment":"","sum":"","sum_comment":"","sum_foreign":""},"62":{"sum_foreign_comment":"","sum":"","sum_comment":"","sum_unclear":true,"sum_foreign":""},"63":{"sum_foreign_comment":"","sum_comment_hidden":false,"sum":"","sum_comment":"","sum_foreign":""},"64":{"sum_foreign_comment":"","sum_comment_hidden":false,"sum":"","sum_comment":"","sum_foreign":""}},"ft_src":"25000\nСердинський Володимир Степанович\nсуддя броварського міськрайонного суду київської області\nКиївська область\nЗагальний місцевий суд\nВолодимир\nСердинська Наталія Володимирівна 18. 01. 1985\nПодружжя\nСердинська Юлія Володимирівна 25. 08. 2006\nДитина\nСердинський Володимир Степанович\nВолодимир Степанович Сердинський\nВолодимир Сердинський\nСердинський Володимир Степанович\nСердинський\nСтепанович\n3956 куб. см. у користуванні\nToyota Prado\n2007\n2014\n1792 куб. см. у власності\nGeely Emgrand 7\n1000\n1200\n297.7\n10.7\n44.9\n105\n46.9\n2014\n3364\n227052\n60\n6124\n227052\n2500\n200\n3956 куб. см. у користуванні\nToyota Prado\n2007\nGeely Emgrand 7\n1792 куб. см. у власності\n2014\n297.7\n105\n46.9\n1200\n1000\n44.9\n10.7\nПодружжя\nСердинська Наталія Володимирівна 18. 01. 1985\nДитина\nСердинська Юлія Володимирівна 25. 08. 2006\nСтепанович\nСердинський\nСердинський Володимир Степанович\nВолодимир Степанович Сердинський\nВолодимир Сердинський\nСердинський Володимир Степанович\nСердинський Володимир Степанович\nВолодимир\nЗагальний місцевий суд\nКиївська область\nсуддя броварського міськрайонного суду київської області\n25000\n227052\n3364\n2500\n200\n227052\n6124\n60\n2014\n25000\nСердинська Наталія Володимирівна 18. 01. 1985\nПодружжя\nДитина\nСердинська Юлія Володимирівна 25. 08. 2006\nСтепанович\nСердинський\nКиївська область\nЗагальний місцевий суд\nсуддя броварського міськрайонного суду київської області\nСердинський Володимир Степанович\nСердинський Володимир Степанович\nВолодимир Степанович Сердинський\nВолодимир Сердинський\nСердинський Володимир Степанович\nВолодимир\n2007\nToyota Prado\n3956 куб. см. у користуванні\n2014\n1792 куб. см. у власності\nGeely Emgrand 7\n60\n200\n227052\n6124\n2500\n3364\n227052\n44.9\n1200\n105\n46.9\n297.7\n10.7\n1000\n2014","general":{"inn":"","inn_hidden":true,"last_name":"Сердинський","post":{"post_unclear":false,"region_unclear":false,"post":"суддя броварського міськрайонного суду київської області","office":"Загальний місцевий суд","region":"Київська область","post_hidden":false,"office_unclear":false},"name":"Володимир","full_name":"Сердинський Володимир Степанович","family_raw":"","addresses":[{"place_district":"","place_city_hidden":true,"place_city":"","place_city_unclear":false,"place_district_hidden":false,"place_city_type":"","place_address_hidden":true,"place_city_type_hidden":false,"place_address":"","place_hidden":true,"place":""}],"family":[{"inn_hidden":true,"inn":"","name_hidden":false,"family_name":"Сердинська Наталія Володимирівна 18. 01. 1985","relations":"Подружжя","name_unclear":false},{"inn":"","relations":"Дитина","relations_other":"","inn_hidden":true,"family_name":"Сердинська Юлія Володимирівна 25. 08. 2006","name_hidden":false,"name_unclear":false}],"full_name_suggest":{"output":"Сердинський Володимир Степанович","input":["Сердинський Володимир Степанович","Володимир Степанович Сердинський","Володимир Сердинський"]},"patronymic":"Степанович"},"source":"VULYK","estate":{"23":[{"space_unclear":false,"costs":"","costs_comment":"","address_hidden":false,"region_hidden":true,"space_comment":"","space":"1200","address":"","costs_comment_unclear":false,"region":"","address_unclear":false,"costs_rent_comment":"","space_comment_unclear":false,"space_units":"м²","costs_rent":""}],"25":[{"space_unclear":false,"costs":"","costs_comment":"","address_hidden":false,"region_hidden":true,"space_comment":"","space":"105","address":"","costs_comment_unclear":false,"region":"","address_unclear":false,"costs_rent_comment":"","space_comment_unclear":false,"space_units":"м²","costs_rent":""},{"costs_rent":"","region":"","costs":"","costs_rent_comment":"","costs_comment":"","region_hidden":false,"space_comment":"","space_units":"м²","space":"46.9","address":""}],"29":[{"region_unclear":false,"space_unclear":false,"address_hidden":true,"region_hidden":true,"space_comment":"","space":"1000","address":"","region":"","costs_property":"","costs_rent_comment":"","address_unclear":false,"space_units":"м²","costs_property_comment":"","costs_rent":""}],"30":[{"costs_rent":"","region":"","costs_property":"","costs_rent_comment":"","address_hidden":true,"region_hidden":true,"space_comment":"","costs_property_comment":"","space_units":"м²","space":"297.7","address":""}],"31":[{"region_unclear":false,"space_unclear":false,"costs_property_comment_unclear":false,"address_hidden":true,"region_hidden":true,"space_comment":"","space":"44.9","address":"","region":"","costs_property":"","costs_rent_comment":"","space_comment_unclear":false,"address_unclear":false,"space_units":"м²","costs_property_comment":"","costs_rent":""}],"34":[{"costs_rent":"","region":"","costs_property":"","costs_rent_comment":"","address_hidden":true,"region_hidden":true,"space_comment":"","costs_property_comment":"","space_units":"м²","space":"10.7","address":""}]},"intro":{"declaration_year":"2014"}}