{"income":{"5":{"value":"202486.86","family_comment":"","value_unclear":false,"family_unclear":false,"family":"","comment":""},"6":{"value":"202486.86","family_comment":"","value_unclear":false,"family_unclear":false,"family":"","comment":""},"7":{"source_name_unclear":false,"value":"","family_comment":"","source_name":"","family":"","comment":""},"8":{"family_comment":"","value":"","family":"","comment":""},"9":{"family_comment":"","value":"","comment_unclear":false,"family":"","comment":""},"10":{"family_comment":"","value":"","family":"","comment":""},"11":{"family_comment":"","value":"","family":"","comment":""},"12":{"family_comment":"","value":"","family":"","comment":""},"13":{"family_comment":"","value":"","family":"","comment":""},"14":{"family_comment":"","value":"","family":"","comment":""},"15":{"family_comment":"","value":"","family":"","comment":""},"16":{"family_comment":"","value":"","family":"","comment":""},"17":{"family_comment":"","value":"","family":"","comment":""},"18":{"family_comment":"","value":"","family":"","comment":""},"19":{"family_comment":"","value":"","family":"","comment":""},"20":{"family_comment":"","value":"","comment_unclear":false,"family":"","comment":""}},"vehicle":{"35":[{"year_hidden":false,"brand_info":"1100 куб. см., за генеральним дорученням перебуває у володінні, користуванні, розпорядженні іншої особи","sum_rent_comment":"","year":"1989","brand_info_unclear":false,"year_unclear":false,"sum_rent":"","sum":"","brand":"ЗАЗ 1102 Таврия","sum_comment":"","brand_unclear":false,"brand_hidden":false}],"40":[{"brand_info":"1600 куб. см., за генеральним дорученням перебуває у володінні, користуванні, розпорядженні іншої особи","sum_rent_comment":"","year":"1995","sum_hidden":false,"brand_info_unclear":false,"year_unclear":false,"sum_rent":"","sum":"","brand":"ВАЗ 21099","sum_comment":"","brand_unclear":false,"brand_hidden":false},{"brand_info":"2200 куб. см.","sum_rent_comment":"","brand":"Mercedes-Benz Vito","sum_comment":"","brand_unclear":false,"year":"2003","brand_info_unclear":false,"sum":"","sum_rent":""}],"44":[{"brand_info":"причіп за генеральним дорученням перебуває у володінні, користуванні, розпорядженні іншої особи","sum":"","brand":"КРКЗ 100","sum_comment":"","year":"","brand_hidden":false,"sum_rent_comment":"","sum_rent":""}]},"id":"vulyk_17_55","banks":{"45":[{"sum_foreign_comment":"","sum_units":"UAH","sum_comment":"","sum_comment_unclear":false,"sum_hidden":false,"sum_foreign_units":"UAH","sum_units_unclear":false,"sum_comment_hidden":false,"sum_unclear":false,"sum":"1316.3","sum_foreign":""},{"sum_foreign_comment":"","sum":"1","sum_comment":"","sum_foreign_units":"UAH","sum_comment_hidden":false,"sum_units":"UAH","sum_foreign":""},{"sum_foreign_comment":"","sum":"","sum_comment":"","sum_foreign_units":"","sum_units":"","sum_foreign":""},{"sum_foreign_comment":"","sum":"","sum_comment":"","sum_foreign_units":"","sum_units":"","sum_foreign":""}],"46":[{"sum_foreign_comment":"","sum_units":"UAH","sum_comment":"","sum_comment_unclear":false,"sum_hidden":false,"sum_foreign_units":"UAH","sum_comment_hidden":false,"sum":"","sum_foreign":""},{"sum_foreign_comment":"","sum":"","sum_comment":"","sum_foreign_units":"","sum_units":"","sum_foreign":""},{"sum_foreign_comment":"","sum":"","sum_comment":"","sum_foreign_units":"","sum_units":"","sum_foreign":""}],"47":[{"sum_foreign_comment":"","sum":"","sum_comment":"","sum_comment_unclear":false,"sum_foreign_units":"UAH","sum_units":"UAH","sum_foreign":""}],"48":[{"sum_foreign_comment":"","sum":"","sum_comment":"","sum_foreign_units":"UAH","sum_units":"UAH","sum_foreign":""}],"49":[{"sum_foreign_comment":"","sum":"","sum_comment":"","sum_foreign_units":"UAH","sum_units":"UAH","sum_foreign":""}],"50":[{"sum_foreign_comment":"","sum":"","sum_comment":"","sum_foreign_units":"UAH","sum_units":"UAH","sum_foreign":""}],"51":[{"sum_foreign_comment":"","sum_units":"UAH","sum_comment":"","sum_hidden":false,"sum_foreign_units":"UAH","sum_units_unclear":false,"sum_comment_hidden":false,"sum_unclear":false,"sum":"1","sum_foreign":""},{"sum_foreign_comment":"","sum_unclear":false,"sum":"1","sum_comment":"","sum_comment_unclear":false,"sum_foreign_units":"UAH","sum_units":"UAH","sum_foreign":""},{"sum_foreign_comment":"","sum":"","sum_comment":"","sum_foreign_units":"","sum_units":"","sum_foreign":""},{"sum_foreign_comment":"","sum":"","sum_comment":"","sum_foreign_units":"","sum_units":"","sum_foreign":""}],"52":[{"sum_foreign_comment":"","sum":"","sum_comment":"","sum_comment_unclear":false,"sum_foreign_units":"UAH","sum_units":"UAH","sum_foreign":""}],"53":[{"sum_foreign_comment":"","sum":"","sum_comment":"","sum_foreign_units":"UAH","sum_comment_hidden":false,"sum_units":"UAH","sum_foreign":""}]},"declaration":{"additional_info_text":"","notfull_lostpages":"","date":"2015-03-30T00:00:00","notfull":"","additional_info":"","url":"http://static.declarations.com.ua/declarations/chosen_ones/mega_batch/yurlahina_tamara_volodymyrivna.pdf"},"liabilities":{"54":{"sum_foreign_comment":"","sum":"","sum_comment":"","sum_comment_unclear":false,"sum_comment_hidden":false,"sum_unclear":false,"sum_foreign":""},"55":{"sum_foreign_comment":"","sum":"","sum_comment":"","sum_foreign":""},"56":{"sum_foreign_comment":"","sum":"","sum_comment":"","sum_unclear":false,"sum_foreign":""},"57":{"sum_foreign_comment":"","sum":"","sum_comment":"","sum_comment_unclear":false,"sum_hidden":false,"sum_comment_hidden":false,"sum_unclear":false,"sum_foreign":""},"58":{"sum_foreign_comment":"","sum":"","sum_comment":"","sum_comment_unclear":false,"sum_hidden":false,"sum_comment_hidden":false,"sum_unclear":false,"sum_foreign":""},"59":{"sum_foreign_comment":"","sum":"","sum_comment":"","sum_comment_unclear":false,"sum_foreign":""},"60":{"sum_foreign_comment":"","sum":"","sum_comment":"","sum_comment_unclear":false,"sum_hidden":false,"sum_comment_hidden":false,"sum_foreign":""},"61":{"sum_foreign_comment":"","sum":"","sum_comment":"","sum_foreign":""},"62":{"sum_foreign_comment":"","sum":"","sum_comment":"","sum_foreign":""},"63":{"sum_foreign_comment":"","sum":"","sum_comment":"","sum_comment_unclear":false,"sum_hidden":false,"sum_comment_hidden":false,"sum_unclear":false,"sum_foreign":""},"64":{"sum_foreign_comment":"","sum":"","sum_comment":"","sum_comment_unclear":false,"sum_hidden":false,"sum_comment_hidden":false,"sum_foreign":""}},"ft_src":"1100 куб. см., за генеральним дорученням перебуває у володінні, користуванні, розпорядженні іншої особи\nЗАЗ 1102 Таврия\n1989\nВАЗ 21099\n1600 куб. см., за генеральним дорученням перебуває у володінні, користуванні, розпорядженні іншої особи\n1995\n2003\nMercedes-Benz Vito\n2200 куб. см.\nКРКЗ 100\nпричіп за генеральним дорученням перебуває у володінні, користуванні, розпорядженні іншої особи\n1\n1\n1316.3\n1\n2014\n1100 куб. см., за генеральним дорученням перебуває у володінні, користуванні, розпорядженні іншої особи\nЗАЗ 1102 Таврия\n1989\n1600 куб. см., за генеральним дорученням перебуває у володінні, користуванні, розпорядженні іншої особи\nВАЗ 21099\n1995\n2200 куб. см.\n2003\nMercedes-Benz Vito\nпричіп за генеральним дорученням перебуває у володінні, користуванні, розпорядженні іншої особи\nКРКЗ 100\n1316.3\n1\n1\n1\n.49\nперебуває у володінні та користуванні іншої особи, договір завдатку\n181.3\nу користуванні, місце проживання, зареєстрована\n91\nперебуває у володінні та користуванні іншої особи, договір завдатку\n181.3\n49\n1/3 частина\nЮрлагіна Тамара Володимирівна\nТамара Володимирівна Юрлагіна\nТамара Юрлагіна\nЮрлагіна Тамара Володимирівна\nТамара\nПодружжя\nТесленко І. М\nДитина\nТесленко О. І\nЮрлагіна Тамара Володимирівна\nЮрлагіна\nЗагальний місцевий суд\nЗапорізька область\nсуддя мелітопольського міськрайонного суду запорізької області\nВолодимирівна\n202486.86\n202486.86\n2014\nперебуває у володінні та користуванні іншої особи, договір завдатку\n91\n181.3\nперебуває у володінні та користуванні іншої особи, договір завдатку\n.49\nу користуванні, місце проживання, зареєстрована\n181.3\n1/3 частина\n49\nПодружжя\nТесленко І. М\nТесленко О. І\nДитина\nВолодимирівна\nЮрлагіна\nТамара\nЮрлагіна Тамара Володимирівна\nТамара Володимирівна Юрлагіна\nТамара Юрлагіна\nЮрлагіна Тамара Володимирівна\nЗапорізька область\nЗагальний місцевий суд\nсуддя мелітопольського міськрайонного суду запорізької області\nЮрлагіна Тамара Володимирівна\n202486.86\n202486.86","general":{"name_hidden":false,"name":"Тамара","patronymic_unclear":false,"inn":"","last_name":"Юрлагіна","family":[{"inn":"","inn_hidden":true,"relations_unclear":false,"relations_hidden":false,"relations_other":"","relations":"Подружжя","name_hidden":true,"inn_unclear":false,"family_name":"Тесленко І. М","name_unclear":false},{"inn":"","inn_hidden":false,"inn_unclear":false,"family_name":"Тесленко О. І","relations_other":"","relations":"Дитина","name_hidden":false,"name_unclear":false}],"inn_hidden":true,"family_raw":"","inn_unclear":false,"post":{"post_unclear":false,"region_unclear":false,"post":"суддя мелітопольського міськрайонного суду запорізької області","candidate":"","post_hidden":false,"region":"Запорізька область","office":"Загальний місцевий суд","office_hidden":false,"office_unclear":false,"region_hidden":false},"full_name_suggest":{"output":"Юрлагіна Тамара Володимирівна","input":["Юрлагіна Тамара Володимирівна","Тамара Володимирівна Юрлагіна","Тамара Юрлагіна"]},"full_name":"Юрлагіна Тамара Володимирівна","addresses":[{"place_address":"","place_district_hidden":true,"place_city_type":"","place_address_hidden":true,"place_city_type_hidden":true,"place_city":"","place":"","place_district":"","place_unclear":false,"place_hidden":true,"place_city_unclear":false,"place_city_hidden":true,"place_district_unclear":false}],"patronymic":"Володимирівна","patronymic_hidden":false,"last_name_unclear":false,"name_unclear":false},"source":"VULYK","estate":{"23":[{"space_hidden":false,"costs":"","costs_comment":"","address_hidden":false,"region_hidden":false,"space_comment":"","space":"","address":"","region":"","costs_rent_comment":"","space_units":"м²","costs_rent":""},{"costs_rent":"","region":"","costs":"","costs_rent_comment":"","costs_comment":"","region_hidden":false,"space_comment":"","space_units":"","space":"","address":""},{"costs_rent":"","costs":"","costs_rent_comment":"","costs_comment":"","space_comment":"","space_units":"","space":"","address":""}],"24":[{"costs_rent":"","region":"","costs":"","costs_rent_comment":"","costs_comment":"","address_hidden":true,"region_hidden":true,"space_comment":"у користуванні, місце проживання, зареєстрована","space_units":"м²","space":"181.3","address":""}],"25":[{"space_unclear":false,"costs":"","costs_comment":"","address_hidden":true,"region_hidden":true,"space_comment":"1/3 частина","space_hidden":false,"space":"49","address":"","region":"","costs_rent_comment":"","space_comment_unclear":false,"space_units":"м²","space_units_hidden":false,"costs_rent":""}],"29":[{"region_unclear":false,"space_unclear":false,"address_hidden":true,"region_hidden":true,"space_comment":"перебуває у володінні та користуванні іншої особи, договір завдатку","space_hidden":false,"space":".49","address":"","region":"","costs_property":"","costs_rent_comment":"","space_units":"м²","costs_property_comment":"","costs_rent":""}],"30":[{"region_unclear":false,"space_unclear":false,"address_hidden":true,"region_hidden":true,"space_comment":"перебуває у володінні та користуванні іншої особи, договір завдатку","space":"91","address":"","region":"","costs_property":"","costs_rent_comment":"","space_units":"м²","costs_property_comment":"","costs_rent":""},{"costs_rent":"","region":"","costs_property":"","costs_rent_comment":"","region_hidden":false,"space_comment":"","costs_property_comment":"","space_units":"м²","space":"181.3","address":""}]},"intro":{"declaration_year":"2014","isnotdeclaration":"","declaration_year_hidden":false}}