{"income":{"5":{"value":"179309","family_comment":"","value_unclear":false,"family_hidden":false,"value_hidden":false,"family_unclear":false,"family":"","comment":"","family_comment_unclear":false},"6":{"family_comment":"","family_unclear":false,"value":"179309","family":"","comment":""},"7":{"source_name_unclear":false,"value":"","family_comment":"","source_name":"","family":"","comment":"","source_name_hidden":false},"8":{"family_comment":"","value":"","family":"","comment":""},"9":{"family_comment":"","family_unclear":false,"value":"","family":"","comment":""},"10":{"family_comment":"","value":"","family":"","comment":""},"11":{"family_comment":"","value":"","family":"","comment":""},"12":{"family_comment":"","value":"","family":"","comment":""},"13":{"family_comment":"","value":"","family":"","comment":""},"14":{"family_comment":"","value":"","family":"","comment":""},"15":{"family_comment":"","value":"","family":"","comment":""},"16":{"value":"","value_unclear":false,"value_hidden":false,"family_comment":"","family":"","comment":""},"17":{"family_comment":"","value":"","family":"","comment":""},"18":{"family_comment":"","value":"","family":"","comment":""},"19":{"family_comment":"","value":"","family":"","comment":""},"20":{"value":"","family_comment":"","value_unclear":false,"comment_hidden":false,"family_hidden":false,"family":"","value_hidden":false,"family_unclear":false,"comment_unclear":false,"comment":"","family_comment_unclear":false}},"vehicle":{"35":[{"year_hidden":false,"brand_info":"об'єм двигуна 4999","sum_rent_comment":"","sum_rent_hidden":false,"year":"2011","sum_hidden":false,"brand_info_hidden":false,"brand_info_unclear":false,"year_unclear":false,"sum_rent":"","sum":"","brand":"Land Rover Range Rover","sum_comment":"","brand_unclear":false,"brand_hidden":false}]},"id":"vulyk_62_65","declaration":{"additional_info_text":"","notfull_lostpages":"","date":"2015-03-26T00:00:00","notfull":"","additional_info":"","url":"http://static.declarations.com.ua/declarations/chosen_ones/mega_batch/kravchuk_tetiana_oleksandrivna.pdf"},"liabilities":{"54":{"sum_foreign_comment":"","sum":"","sum_comment":"","sum_hidden":false,"sum_comment_hidden":false,"sum_foreign":""},"55":{"sum_foreign_comment":"","sum":"","sum_comment":"","sum_hidden":false,"sum_comment_hidden":false,"sum_unclear":false,"sum_foreign":""},"56":{"sum_foreign_comment":"","sum":"","sum_comment":"","sum_hidden":false,"sum_unclear":false,"sum_foreign":""},"57":{"sum_foreign_comment":"","sum":"","sum_comment":"","sum_hidden":false,"sum_comment_hidden":false,"sum_unclear":false,"sum_foreign":""},"58":{"sum_foreign_comment":"","sum_foreign_hidden":false,"sum_comment":"","sum_hidden":false,"sum_comment_hidden":false,"sum_unclear":false,"sum":"","sum_foreign":""},"59":{"sum_foreign_comment":"","sum":"","sum_comment":"","sum_foreign":""},"60":{"sum_foreign_comment":"","sum_foreign_hidden":false,"sum_comment":"","sum_hidden":false,"sum_comment_hidden":false,"sum_unclear":false,"sum":"","sum_foreign":""},"61":{"sum_foreign_comment":"","sum_foreign_hidden":false,"sum_comment":"","sum_hidden":false,"sum":"","sum_foreign":""},"62":{"sum_foreign_comment":"","sum":"","sum_comment":"","sum_unclear":false,"sum_foreign":""},"63":{"sum_foreign_comment":"","sum":"","sum_comment":"","sum_hidden":false,"sum_comment_hidden":false,"sum_unclear":false,"sum_foreign":""},"64":{"sum_foreign_comment":"","sum":"","sum_comment":"","sum_comment_unclear":false,"sum_hidden":false,"sum_comment_hidden":false,"sum_foreign":""}},"ft_src":"суддя рівненського окружного адміністративного суду\nРівненська область\nАдміністративний місцевий суд\nТетяна\nОлександрівна\nКравчук\nКравчук Тетяна Олександрівна\nКравчук Тетяна Олександрівна\nТетяна Олександрівна Кравчук\nТетяна Кравчук\nКравчук Тетяна Олександрівна\nоб'єм двигуна 4999\nLand Rover Range Rover\n2011\nна іншому праві користування\n2014\n179309\n179309\nоб'єм двигуна 4999\nLand Rover Range Rover\n2011\nна іншому праві користування\nКравчук Тетяна Олександрівна\nТетяна Олександрівна Кравчук\nТетяна Кравчук\nКравчук Тетяна Олександрівна\nТетяна\nКравчук Тетяна Олександрівна\nОлександрівна\nАдміністративний місцевий суд\nсуддя рівненського окружного адміністративного суду\nРівненська область\nКравчук\n179309\n179309\n2014\nТетяна\nОлександрівна\nКравчук\nКравчук Тетяна Олександрівна\nТетяна Олександрівна Кравчук\nТетяна Кравчук\nКравчук Тетяна Олександрівна\nРівненська область\nсуддя рівненського окружного адміністративного суду\nАдміністративний місцевий суд\nКравчук Тетяна Олександрівна\nLand Rover Range Rover\nоб'єм двигуна 4999\n2011\n179309\n179309\nна іншому праві користування\n2014","general":{"inn":"","name":"Тетяна","inn_unclear":false,"patronymic":"Олександрівна","inn_hidden":true,"family_raw":"","last_name":"Кравчук","post":{"post_unclear":false,"post":"суддя рівненського окружного адміністративного суду","post_hidden":false,"region":"Рівненська область","region_hidden":false,"office":"Адміністративний місцевий суд","office_hidden":false,"office_unclear":false},"last_name_unclear":false,"full_name":"Кравчук Тетяна Олександрівна","addresses":[{"place_city_type_unclear":false,"place_address":"","place_district_hidden":true,"place_city_type":"","place_address_hidden":true,"place_address_unclear":false,"place_city_type_hidden":true,"place":"","place_district":"","place_unclear":false,"place_city":"","place_city_unclear":false,"place_hidden":true,"place_city_hidden":true,"place_district_unclear":false}],"full_name_suggest":{"output":"Кравчук Тетяна Олександрівна","input":["Кравчук Тетяна Олександрівна","Тетяна Олександрівна Кравчук","Тетяна Кравчук"]},"name_unclear":false},"source":"VULYK","estate":{"25":[{"region_unclear":false,"space_hidden":true,"costs":"","costs_comment":"","costs_hidden":false,"address_hidden":true,"region_hidden":true,"space_comment":"на іншому праві користування","space_unclear":false,"space":"","address":"","region":"","costs_rent_comment":"","space_units":"м²","costs_rent":""}]},"intro":{"declaration_year":"2014","isnotdeclaration":"","declaration_year_unclear":false,"declaration_year_hidden":false}}