{"id":"vulyk_74_10","ft_src":"1.5 л, 78.752 кВт , 107 к. с., 434 см\nRenault Scenic\n2007\nне надала відомостей\nне надала відомостей\nне надала відомостей\n44.8\n5520\n26835\n45\n350\n5560\n26835\n2013\n1.5 л, 78.752 кВт , 107 к. с., 434 см\nRenault Scenic\n2007\nне надала відомостей\n2013\nАпеляційний адміністративний суд\nм. Київ\nсуддя київського апеляційного адміністративного суду\nОлександрівна\nГрибан Інна Олександрівна\nІнна Олександрівна Грибан\nІнна Грибан\nГрибан Інна Олександрівна\nІнна\nГрибан Інна Олександрівна\nГрибан\nБатьки\nГрибан Р. С\nне надала відомостей\n251798\nне надала відомостей\nне надала відомостей\n257018\n5220\nне надала відомостей\nне надала відомості\nне надала відомостей\nне надала відомостей\n44.8\n45\n350\n5560\n26835\n5520\n26835\nне надала відомостей\n251798\nне надала відомостей\n5220\nне надала відомості\nне надала відомостей\n257018\nне надала відомостей\nБатьки\nГрибан Р. С\nОлександрівна\nГрибан\nм. Київ\nАпеляційний адміністративний суд\nсуддя київського апеляційного адміністративного суду\nГрибан Інна Олександрівна\nГрибан Інна Олександрівна\nІнна Олександрівна Грибан\nІнна Грибан\nГрибан Інна Олександрівна\nІнна","estate":{"25":[{"address":"","space_units":"м²","space_hidden":false,"space_unclear":false,"region_hidden":true,"costs_comment":"","space_comment":"","address_hidden":true,"space":"44.8","costs_rent_comment":"","costs":"","region":"","costs_rent":""}],"29":[{"costs_property_comment":"","address":"не надала відомостей","space_units":"м²","costs_rent_comment":"","space":"","region":"","region_hidden":false,"costs_property":"","space_comment":"не надала відомостей","address_hidden":false,"costs_rent":""}]},"vehicle":{"35":[{"brand_info":"1.5 л, 78.752 кВт , 107 к. с., 434 см","sum_rent_comment":"","brand_unclear":false,"year":"2007","brand_hidden":false,"sum_comment":"","brand_info_hidden":false,"sum_rent":"","brand":"Renault Scenic","year_unclear":false,"brand_info_unclear":false,"sum":""}],"40":[{"sum_comment":"","brand_info":"не надала відомостей","brand_unclear":false,"sum_rent_comment":"","year":"","brand":"","sum_rent":"","brand_info_unclear":false,"year_unclear":false,"sum":""}]},"source":"VULYK","income":{"5":{"family_comment":"не надала відомостей","family":"","comment":"","family_unclear":false,"family_hidden":false,"value":"257018"},"6":{"family_comment":"","family":"не надала відомостей","comment":"","value_unclear":false,"family_unclear":false,"family_hidden":false,"value":"251798"},"7":{"source_name_hidden":false,"family_comment":"","family":"","value_hidden":false,"comment":"","family_hidden":false,"value":"","source_name":""},"8":{"family_comment":"не надала відомості","value":"","family":"","comment":""},"9":{"family_comment":"не надала відомостей","value":"5220","family":"","comment":""},"10":{"family_comment":"","value":"","family":"","comment":"","value_unclear":false},"11":{"family_comment":"","value":"","family":"","comment":""},"12":{"family_comment":"","value":"","family":"","comment":""},"13":{"family_comment":"","value":"","family":"","comment":""},"14":{"family_comment":"","value":"","family":"","comment":""},"15":{"family_comment":"","value":"","family":"","comment":""},"16":{"family_comment":"","value":"","family":"","comment":""},"17":{"family_comment":"","value":"","family":"","comment":""},"18":{"family_comment":"","value":"","family":"","comment":""},"19":{"family_comment":"","value":"","family":"","comment":""},"20":{"family_comment":"","comment":"","family":"","value_unclear":false,"family_unclear":false,"comment_unclear":false,"value":""},"22":[{"country_comment":"не надала відомостей","uah_equal":"","cur":"","country":"","cur_units":"USD"}]},"banks":{"45":[{"sum_comment_unclear":false,"sum_units":"UAH","sum_foreign_units":"UAH","sum_hidden":false,"sum":"45","sum_foreign_comment":"","sum_comment":"","sum_unclear":false,"sum_foreign":"","sum_comment_hidden":false,"sum_foreign_hidden":false},{"sum_comment_unclear":false,"sum_comment":"","sum_foreign_units":"UAH","sum":"350","sum_foreign_comment":"","sum_foreign":"","sum_units":"UAH"},{"sum_units":"UAH","sum_comment":"","sum_foreign_units":"UAH","sum":"5560","sum_foreign_comment":"","sum_foreign":""},{"sum_units":"UAH","sum_comment":"","sum_foreign_units":"UAH","sum":"26835","sum_foreign_comment":"","sum_foreign":""}],"46":[{"sum_units":"UAH","sum_comment":"","sum_foreign_units":"UAH","sum":"5520","sum_foreign_comment":"","sum_foreign":"","sum_foreign_hidden":false},{"sum_units":"UAH","sum_comment":"","sum_foreign_units":"UAH","sum":"26835","sum_foreign_comment":"","sum_foreign":""}]},"declaration":{"notfull_lostpages":"","additional_info_text":"","additional_info":"","date":"2014-03-19T00:00:00","notfull":"","url":"http://static.declarations.com.ua/declarations/chosen_ones/judges_batch/1774_hryban_inna_oleksandrivna.pdf"},"general":{"inn":"","addresses":[{"place_city_type_hidden":true,"place_city_type":"","place_city_hidden":true,"place_hidden":true,"place_district":"","place_district_hidden":true,"place":"","place_address":"","place_address_hidden":true,"place_city":""}],"last_name":"Грибан","full_name":"Грибан Інна Олександрівна","family":[{"inn":"","family_name":"Грибан Р. С","relations_other":"","name_unclear":false,"inn_hidden":true,"name_hidden":true,"relations":"Батьки"}],"patronymic":"Олександрівна","inn_hidden":true,"name":"Інна","post":{"post_hidden":false,"office":"Апеляційний адміністративний суд","post":"суддя київського апеляційного адміністративного суду","office_unclear":false,"region_unclear":false,"region":"м. Київ"},"family_raw":"","full_name_suggest":{"input":["Грибан Інна Олександрівна","Інна Олександрівна Грибан","Інна Грибан"],"output":"Грибан Інна Олександрівна"}},"liabilities":{"54":{"sum_comment_unclear":false,"sum_comment":"","sum":"","sum_foreign_comment":"","sum_foreign":"","sum_comment_hidden":false},"55":{"sum_comment":"","sum_hidden":false,"sum":"","sum_foreign_comment":"","sum_foreign":"","sum_unclear":false},"56":{"sum_comment":"","sum_hidden":false,"sum":"","sum_foreign_comment":"","sum_foreign":"","sum_unclear":false},"57":{"sum_comment_unclear":false,"sum_comment":"","sum":"","sum_foreign_comment":"","sum_foreign":"","sum_comment_hidden":false},"58":{"sum_comment":"","sum_foreign_comment":"","sum_foreign":"","sum":"","sum_comment_hidden":false},"59":{"sum_comment":"","sum_foreign_comment":"","sum_foreign":"","sum":""},"60":{"sum_comment":"","sum_foreign_comment":"","sum_foreign":"","sum_hidden":false,"sum":""},"61":{"sum_comment":"","sum_foreign_comment":"","sum_foreign":"","sum":""},"62":{"sum_comment":"","sum_foreign_comment":"","sum_foreign":"","sum":""},"63":{"sum_comment_unclear":false,"sum_comment":"","sum":"","sum_foreign_comment":"","sum_foreign":"","sum_unclear":false},"64":{"sum_comment_unclear":false,"sum_comment":"","sum":"","sum_foreign_comment":"","sum_foreign":"","sum_unclear":false}},"intro":{"isnotdeclaration":"","declaration_year_unclear":false,"declaration_year":"2013"}}