{"income":{"5":{"family_comment":"","value":"238496","family":"","comment":""},"6":{"family_comment":"","value":"238496","family":"","comment":""},"7":{"value":"","comment_hidden":false,"family_comment":"","source_name":"","family":"","comment":"","source_name_hidden":false},"8":{"family_comment":"","value":"","family":"","comment":"","family_hidden":false},"9":{"value":"49","family_comment":"","value_unclear":false,"family_unclear":false,"family":"","comment":""},"10":{"family_comment":"","value":"","family":"","comment":""},"11":{"family_comment":"","value":"","family":"","comment":""},"12":{"family_comment":"","value":"","family":"","comment":""},"13":{"family_comment":"","value":"","family":"","comment":""},"14":{"family_comment":"","value":"","family":"","comment":""},"15":{"family_comment":"","value":"","family":"","comment":""},"16":{"family_comment":"","value":"","family":"","comment":""},"17":{"family_comment":"","value":"","family":"","comment":""},"18":{"family_comment":"","value":"","family":"","comment":""},"19":{"family_comment":"","value":"","family":"","comment":""},"20":{"value":"","value_unclear":false,"family_hidden":false,"family_comment":"","family":"","comment":""}},"vehicle":{"40":[{"brand_info":"1987","sum_rent_comment":"","brand":"Toyota Rav 4","sum_comment":"","year":"2010","brand_info_unclear":false,"sum":"","sum_rent":""}]},"id":"vulyk_109_44","banks":{"45":[{"sum_foreign_comment":"","sum_unclear":false,"sum":"55328","sum_comment":"Приватбанк","sum_foreign_units":"UAH","sum_units":"UAH","sum_comment_hidden":false,"sum_units_hidden":false,"sum_foreign":""}],"46":[{"sum_foreign_comment":"","sum":"42000","sum_comment":"","sum_foreign_units":"UAH","sum_units":"UAH","sum_foreign":""}]},"declaration":{"additional_info_text":"","notfull_lostpages":"","date":"2016-03-31T00:00:00","notfull":"","additional_info":"","url":"http://static.declarations.com.ua/declarations/chosen_ones/judges_batch/2501_kalynychenko_liudmyla_mykhailivna_2015.pdf"},"liabilities":{"54":{"sum_foreign_comment":"","sum":"13200","sum_comment":"","sum_hidden":true,"sum_comment_hidden":false,"sum_unclear":true,"sum_foreign":""},"55":{"sum_foreign_comment":"","sum":"","sum_comment":"","sum_comment_unclear":false,"sum_foreign":""},"56":{"sum_foreign_comment":"","sum":"","sum_comment":"","sum_foreign":""},"57":{"sum_foreign_comment":"","sum_comment":"","sum":"","sum_comment_hidden":false,"sum_foreign":""},"58":{"sum_foreign_comment":"","sum_comment":"","sum":"","sum_comment_hidden":false,"sum_foreign":""},"59":{"sum_foreign_comment":"","sum":"","sum_comment":"","sum_foreign":""},"60":{"sum_foreign_comment":"","sum":"","sum_comment":"","sum_foreign":""},"61":{"sum_foreign_comment":"","sum":"","sum_comment":"","sum_foreign":""},"62":{"sum_foreign_comment":"","sum":"","sum_comment":"","sum_foreign":""},"63":{"sum_foreign_comment":"","sum":"","sum_comment":"","sum_foreign":""},"64":{"sum_foreign_comment":"","sum":"","sum_comment":"","sum_foreign":""}},"ft_src":"1987\n2010\nToyota Rav 4\n42000\nПриватбанк\n55328\n2015\n1987\n2010\nToyota Rav 4\n2015\nКалиниченко Людмила Михайлівна\nЛюдмила Михайлівна Калиниченко\nЛюдмила Калиниченко\nКалиниченко Людмила Михайлівна\nКалиниченко Людмила Михайлівна\nЛюдмила\nКалиниченко\nГосподарський місцевий суд\nДніпропетровська область\nсуддя господарського суду дніпропетровської області\nМихайлівна\n13200\n238496\n238496\n49\n55328\nПриватбанк\n42000\n13200\n238496\n238496\n49\nМихайлівна\nКалиниченко\nЛюдмила\nКалиниченко Людмила Михайлівна\nЛюдмила Михайлівна Калиниченко\nЛюдмила Калиниченко\nКалиниченко Людмила Михайлівна\nДніпропетровська область\nГосподарський місцевий суд\nсуддя господарського суду дніпропетровської області\nКалиниченко Людмила Михайлівна","general":{"name_hidden":false,"name":"Людмила","inn":"","last_name":"Калиниченко","patronymic":"Михайлівна","inn_hidden":true,"family_raw":"","inn_unclear":false,"post":{"region_unclear":false,"region":"Дніпропетровська область","post":"суддя господарського суду дніпропетровської області","region_hidden":false,"office":"Господарський місцевий суд","office_hidden":false,"office_unclear":false},"full_name":"Калиниченко Людмила Михайлівна","addresses":[{"place_district":"","place_address_hidden":true,"place_city":"","place_address":"","place_district_hidden":true,"place_city_type":"","place_city_hidden":true,"place_city_type_hidden":true,"place_hidden":true,"place":""}],"full_name_suggest":{"output":"Калиниченко Людмила Михайлівна","input":["Калиниченко Людмила Михайлівна","Людмила Михайлівна Калиниченко","Людмила Калиниченко"]}},"source":"VULYK","intro":{"declaration_year":"2015","isnotdeclaration":""}}