{"id":"vulyk_102_53","ft_src":"придбана у 2011 р\n2007\nоб'єм 4.7 куб. дм.\nLexus GX 470\n.1175\n82,8 кв. м-житлова площа\n181.7\n.12\nприватизована 1/2 частина квартири\n1/2\n50.3\n1/2 частина квартири\n50.3\n47.89\n2015\n329215.73\n47544\n329215.73\n47544\nпенсія\nоб'єм 4.7 куб. дм.\nLexus GX 470\n2007\nпридбана у 2011 р\n2015\nЛіпський Дмитро Володимирович\nДмитро Володимирович Ліпський\nДмитро Ліпський\nЛіпський Дмитро Володимирович\nЛіпський Дмитро Володимирович\nДмитро\nВолодимирович\nсуддя вищого адміністративного суду україни – секретар 3-ї судової палати\nЗагальнодержавний регіон\nВищий адміністративний суд\nЛіпський\nПодружжя\n16190\n7200\n329215.73\n47544\nпенсія\n329215.73\n47544\n.1175\n.12\n181.7\n82,8 кв. м-житлова площа\nприватизована 1/2 частина квартири\n50.3\n1/2\n50.3\n1/2 частина квартири\n47.89\n7200\n16190\nПодружжя\nДмитро\nВолодимирович\nЛіпський\nЛіпський Дмитро Володимирович\nДмитро Володимирович Ліпський\nДмитро Ліпський\nЛіпський Дмитро Володимирович\nсуддя вищого адміністративного суду україни – секретар 3-ї судової палати\nЗагальнодержавний регіон\nВищий адміністративний суд\nЛіпський Дмитро Володимирович","estate":{"23":[{"address":"","space_units":"га","space_comment":"","region_hidden":true,"space_units_unclear":false,"costs_comment":"","address_hidden":false,"space":".1175","space_comment_unclear":false,"costs_rent_comment":"","costs":"","region":"","costs_rent":""}],"25":[{"address":"","space_units":"м²","costs_comment":"","space_comment":"1/2 частина квартири","region_hidden":true,"region":"","address_hidden":false,"space":"50.3","address_unclear":false,"costs_rent_comment":"","costs":"","costs_rent":""},{"costs":"","address":"","space_units":"м²","costs_rent_comment":"","space":"47.89","space_comment":"","region_hidden":false,"costs_comment":"","region":"","costs_rent":""}],"29":[{"costs_property_comment":"","address":"","space_units":"га","space_comment":"","region_hidden":true,"costs_property":"","region":"","address_hidden":false,"space_comment_hidden":false,"costs_rent_comment":"","space":".12","costs_rent":""}],"30":[{"costs_property_comment":"","address":"","space_units":"м²","costs_rent_comment":"","space":"181.7","region":"","region_hidden":true,"costs_property":"","space_comment":"82,8 кв. м-житлова площа","address_hidden":false,"costs_rent":""}],"31":[{"costs_property_comment":"приватизована 1/2 частина квартири","address":"","space_units":"м²","costs_rent_comment":"","space":"50.3","region":"","region_hidden":true,"costs_property":"","space_comment":"1/2","address_hidden":false,"costs_rent":""}]},"vehicle":{"35":[{"sum_comment":"придбана у 2011 р","brand_info":"об'єм 4.7 куб. дм.","sum":"","sum_rent_comment":"","year":"2007","brand":"Lexus GX 470","sum_rent":"","brand_info_unclear":false,"year_unclear":false}]},"source":"VULYK","income":{"5":{"family_comment":"","value":"329215.73","family":"47544","comment":""},"6":{"family_comment":"","value":"329215.73","family":"","comment":""},"7":{"source_name_hidden":false,"family_comment":"","family":"","value_hidden":false,"comment":"","comment_hidden":false,"value":"","source_name":""},"8":{"family_comment":"","value":"","family":"","comment":""},"9":{"family_comment":"","family":"","comment":"","comment_hidden":false,"value":"","family_comment_unclear":false},"10":{"family_comment":"","value":"","family":"","comment":""},"11":{"family_comment":"","value":"","family":"","comment":"","comment_hidden":false},"12":{"family_comment":"","value":"","family":"","comment":""},"13":{"family_comment":"","value":"","family":"","comment":""},"14":{"family_comment":"","value":"","family":"","comment":""},"15":{"family_comment":"","value":"","family":"","comment":""},"16":{"family_comment":"","value":"","family":"","comment":""},"17":{"family_comment":"","value":"","family":"","comment":""},"18":{"family_comment":"","value":"","family":"","comment":""},"19":{"family_comment":"","value":"","family":"","comment":""},"20":{"family_comment":"пенсія","value":"","family":"47544","comment":"","comment_hidden":false}},"general":{"family":[{"inn":"","family_name":"","name_unclear":false,"inn_hidden":true,"name_hidden":true,"relations":"Подружжя"}],"family_raw":"","name":"Дмитро","full_name_suggest":{"input":["Ліпський Дмитро Володимирович","Дмитро Володимирович Ліпський","Дмитро Ліпський"],"output":"Ліпський Дмитро Володимирович"},"patronymic":"Володимирович","inn_hidden":true,"patronymic_hidden":false,"inn":"","addresses":[{"place_city_type_hidden":false,"place_city_type":"","place_city_hidden":true,"place_hidden":true,"place_district":"","place_district_hidden":false,"place":"","place_address":"","place_address_hidden":true,"place_city":""}],"last_name":"Ліпський","full_name":"Ліпський Дмитро Володимирович","post":{"office_unclear":false,"region_unclear":false,"post":"суддя вищого адміністративного суду україни – секретар 3-ї судової палати","region":"Загальнодержавний регіон","office":"Вищий адміністративний суд"}},"liabilities":{"54":{"sum_comment":"","sum_hidden":false,"sum":"","sum_foreign_comment":"","sum_foreign":"","sum_comment_hidden":false},"55":{"sum_comment":"","sum_foreign_comment":"","sum_foreign":"","sum":""},"56":{"sum_comment":"","sum_foreign_comment":"","sum_foreign":"","sum":"16190"},"57":{"sum_comment":"","sum_foreign_comment":"","sum_foreign":"","sum":"","sum_comment_hidden":false},"58":{"sum_comment":"","sum_foreign_comment":"","sum_foreign":"","sum":"","sum_comment_hidden":false},"59":{"sum_comment":"","sum_foreign_comment":"","sum_foreign":"","sum":"","sum_comment_hidden":false},"60":{"sum_comment":"","sum_hidden":false,"sum":"","sum_foreign_comment":"","sum_foreign":"","sum_comment_hidden":false},"61":{"sum_comment":"","sum_foreign_comment":"","sum_foreign":"","sum":""},"62":{"sum_comment":"","sum_foreign_comment":"","sum_foreign":"","sum_unclear":false,"sum":"7200"},"63":{"sum_comment":"","sum_hidden":false,"sum":"","sum_foreign_comment":"","sum_foreign":"","sum_comment_hidden":false},"64":{"sum_comment":"","sum_foreign_comment":"","sum_foreign":"","sum":"","sum_comment_hidden":false}},"declaration":{"additional_info_text":"","additional_info":"","date":"2016-03-24T00:00:00","url":"http://static.declarations.com.ua/declarations/chosen_ones/judges_batch/1127_lipskyi_dmytro_volodymyrovych.pdf"},"intro":{"declaration_year":"2015"}}