{"income":{"5":{"value":"21870","family_comment":"","value_unclear":false,"comment_hidden":false,"family_hidden":true,"value_hidden":false,"family_unclear":false,"family_comment_hidden":false,"comment":"","family":""},"6":{"value":"","family_comment":"","value_unclear":false,"family_hidden":false,"family_unclear":false,"family":"","comment":""},"7":{"source_name_unclear":false,"value":"","family_hidden":false,"family_comment":"","source_name":"","family":"","comment":"","source_name_hidden":false},"8":{"family_comment":"","value":"","family":"","comment":""},"9":{"value":"","value_unclear":false,"family_hidden":false,"family_comment":"","family":"","comment":""},"10":{"value":"","value_unclear":false,"family_hidden":false,"value_hidden":false,"family_comment":"","comment_unclear":false,"comment":"","family":""},"11":{"family_comment":"","value":"","family":"","comment":""},"12":{"family_comment":"","value":"","family":"","comment":""},"13":{"family_comment":"","value":"","family":"","comment":""},"14":{"family_comment":"","value":"","family":"","comment":""},"15":{"family_comment":"","value":"","family_hidden":false,"comment":"","family":""},"16":{"value":"","value_unclear":false,"family_hidden":false,"family_comment":"","family":"","comment":""},"17":{"family_comment":"","value":"","family_hidden":false,"comment":"","family":""},"18":{"family_comment":"","value":"","value_unclear":false,"family":"","comment":""},"19":{"family_comment":"","value":"","family":"","comment":""},"20":{"value":"21870","family_comment":"","value_unclear":false,"family_hidden":false,"family_unclear":false,"comment_unclear":false,"comment":"","family":""}},"vehicle":{"40":[{"year_hidden":true,"brand_info":"","sum_rent_comment":"","year":"","brand_info_hidden":false,"brand_info_unclear":false,"year_unclear":false,"sum_rent":"","sum":"","brand":"","sum_comment":"","brand_unclear":false,"brand_hidden":true}]},"id":"vulyk_72_270","declaration":{"additional_info_text":"","notfull_lostpages":"","date":"2015-03-25T00:00:00","notfull":"","additional_info":"","url":"http://static.declarations.com.ua/declarations/chosen_ones/epic_batch/starovoitova_svitlana_mykolaivna.pdf"},"liabilities":{"54":{"sum_foreign_comment":"","sum":"","sum_comment":"","sum_comment_hidden":false,"sum_unclear":false,"sum_foreign":""},"55":{"sum_foreign_comment":"","sum":"","sum_comment":"","sum_foreign":""},"56":{"sum_foreign_comment":"","sum":"","sum_hidden":false,"sum_comment":"","sum_foreign":""},"57":{"sum_foreign_comment":"","sum":"","sum_comment":"","sum_comment_unclear":false,"sum_hidden":false,"sum_comment_hidden":false,"sum_unclear":false,"sum_foreign":""},"58":{"sum_foreign_comment":"","sum":"","sum_comment":"","sum_comment_unclear":false,"sum_hidden":false,"sum_comment_hidden":false,"sum_unclear":false,"sum_foreign":""},"59":{"sum_foreign_comment":"","sum_foreign_hidden":false,"sum_comment":"","sum_foreign_unclear":false,"sum_comment_hidden":false,"sum":"","sum_foreign":""},"60":{"sum_foreign_comment":"","sum_foreign_hidden":false,"sum_comment":"","sum_hidden":false,"sum":"","sum_foreign":""},"61":{"sum_foreign_comment":"","sum_foreign_hidden":false,"sum_comment":"","sum_hidden":false,"sum":"","sum_foreign":""},"62":{"sum_foreign_comment":"","sum_foreign_hidden":false,"sum_comment":"","sum_hidden":false,"sum":"","sum_foreign":""},"63":{"sum_foreign_comment":"","sum_foreign_hidden":false,"sum_comment":"","sum_comment_unclear":false,"sum_hidden":false,"sum_comment_hidden":false,"sum_unclear":false,"sum":"","sum_foreign":""},"64":{"sum_foreign_comment":"","sum_foreign_hidden":false,"sum_comment":"","sum_hidden":false,"sum":"","sum_foreign":""}},"ft_src":"Київ\nсуддя дніпровського районного суду міста києва\nм. Київ\nЗагальний місцевий суд\nСвітлана\nМиколаївна\nСтаровойтова\nСтаровойтова Світлана Миколаївна\nСтаровойтова Світлана Миколаївна\nСвітлана Миколаївна Старовойтова\nСвітлана Старовойтова\nСтаровойтова Світлана Миколаївна\nкiмната у гуртожитку\nм. Київ\n9.8\n2014\n21870\n21870\nкiмната у гуртожитку\nм. Київ\n9.8\nСтаровойтова Світлана Миколаївна\nСвітлана Миколаївна Старовойтова\nСвітлана Старовойтова\nСтаровойтова Світлана Миколаївна\nСвітлана\nСтаровойтова Світлана Миколаївна\nСтаровойтова\nм. Київ\nЗагальний місцевий суд\nсуддя дніпровського районного суду міста києва\nМиколаївна\nКиїв\n21870\n21870\n2014\nМиколаївна\nСтаровойтова\nСтаровойтова Світлана Миколаївна\nСвітлана Миколаївна Старовойтова\nСвітлана Старовойтова\nСтаровойтова Світлана Миколаївна\nКиїв\nм. Київ\nЗагальний місцевий суд\nсуддя дніпровського районного суду міста києва\nСтаровойтова Світлана Миколаївна\nСвітлана\n21870\n21870\nкiмната у гуртожитку\nм. Київ\n9.8\n2014","general":{"inn":"","name":"Світлана","patronymic_unclear":false,"family":[{"inn":"","inn_hidden":false,"relations_unclear":false,"relations_hidden":true,"relations_other":"","relations":"","name_hidden":true,"inn_unclear":false,"family_name":"","name_unclear":false}],"patronymic":"Миколаївна","inn_hidden":true,"family_raw":"","inn_unclear":false,"post":{"post_unclear":false,"region_unclear":false,"post":"суддя дніпровського районного суду міста києва","candidate":"","office_hidden":false,"region":"м. Київ","post_hidden":false,"office":"Загальний місцевий суд","office_unclear":false,"region_hidden":false},"last_name_unclear":false,"full_name":"Старовойтова Світлана Миколаївна","addresses":[{"place_city_type_hidden":false,"place_district_hidden":false,"place_city_type":"Місто","place_city_hidden":false,"place_address_unclear":false,"place_address":"","place":"","place_district":"","place_unclear":false,"place_city":"Київ","place_city_unclear":false,"place_hidden":false,"place_address_hidden":true,"place_district_unclear":false}],"last_name":"Старовойтова","patronymic_hidden":false,"full_name_suggest":{"output":"Старовойтова Світлана Миколаївна","input":["Старовойтова Світлана Миколаївна","Світлана Миколаївна Старовойтова","Світлана Старовойтова"]},"name_unclear":false},"source":"VULYK","estate":{"34":[{"space_hidden":false,"address_hidden":false,"region_hidden":true,"space_comment":"кiмната у гуртожитку","space":"9.8","address":"","region":"м. Київ","costs_property":"","costs_rent_comment":"","space_units":"м²","costs_property_comment":"","costs_rent":""}]},"intro":{"declaration_year":"2014","isnotdeclaration":"","declaration_year_unclear":false}}