{"income":{"5":{"value":"186259","family_comment":"","value_unclear":false,"family_hidden":false,"value_hidden":false,"family_unclear":false,"family":"","comment":""},"6":{"value":"186259","value_unclear":false,"family_hidden":false,"value_hidden":false,"family_comment":"","comment_unclear":false,"comment":"","family":""},"7":{"value":"","value_hidden":false,"family_comment":"","source_name":"","family":"","comment":"","source_name_hidden":false},"8":{"family_comment":"","value":"","family":"","comment":""},"9":{"family_comment":"","value":"3031","comment_unclear":false,"family":"","comment":""},"10":{"family_comment":"","value":"","value_unclear":false,"family":"","comment":""},"11":{"family_comment":"","value":"","family":"","comment":""},"12":{"family_comment":"","value":"","family":"","comment":""},"13":{"family_comment":"","value":"","family":"","comment":""},"14":{"family_comment":"","value":"","family":"","comment":""},"15":{"family_comment":"","value":"","family":"","comment":""},"16":{"family_comment":"","value":"","family":"","comment":""},"17":{"family_comment":"","value":"","family":"","comment":""},"18":{"family_comment":"","value":"","family":"","comment":""},"19":{"value":"","value_unclear":false,"comment_hidden":false,"family_hidden":false,"value_hidden":false,"family_comment":"","family_comment_hidden":false,"comment":"","family":""},"20":{"value":"","family_comment":"","value_unclear":false,"family_hidden":false,"value_hidden":false,"family_unclear":false,"comment_unclear":false,"comment":"","family":""}},"id":"vulyk_65_160","declaration":{"additional_info_text":"","notfull_lostpages":"","date":"2015-03-25T00:00:00","notfull":"","additional_info":"","url":"http://static.declarations.com.ua/declarations/chosen_ones/mega_batch/plokhotnichenko_leonid_ivanovych.pdf"},"liabilities":{"54":{"sum_foreign_comment":"","sum":"","sum_comment":"","sum_comment_unclear":false,"sum_hidden":false,"sum_comment_hidden":false,"sum_foreign":""},"55":{"sum_foreign_comment":"","sum":"","sum_comment":"","sum_foreign":""},"56":{"sum_foreign_comment":"","sum":"","sum_comment":"","sum_unclear":false,"sum_foreign":""},"57":{"sum_foreign_comment":"","sum":"","sum_comment":"","sum_comment_unclear":false,"sum_unclear":false,"sum_foreign":""},"58":{"sum_foreign_comment":"","sum":"","sum_comment":"","sum_comment_unclear":false,"sum_unclear":false,"sum_foreign":""},"59":{"sum_foreign_comment":"","sum":"","sum_comment":"","sum_foreign":""},"60":{"sum_foreign_comment":"","sum":"","sum_comment":"","sum_comment_unclear":false,"sum_foreign":""},"61":{"sum_foreign_comment":"","sum":"","sum_comment":"","sum_foreign":""},"62":{"sum_foreign_comment":"","sum":"","sum_comment":"","sum_foreign":""},"63":{"sum_foreign_comment":"","sum":"","sum_comment":"","sum_foreign":""},"64":{"sum_foreign_comment":"","sum":"","sum_comment":"","sum_unclear":false,"sum_foreign":""}},"ft_src":"Кіровоград\n25000\nКіровоградська область\nсуддя ленінського районного суду м. кіровограда\nКіровоградська область\nЗагальний місцевий суд\nЛеонід\nПлохотніченко С. Л\nДитина\nПлохотніченко М. Л\nДитина\nІванович\nПлохотніченко\nПлохотніченко Леонід Іванович\nПлохотніченко Леонід Іванович\nЛеонід Іванович Плохотніченко\nЛеонід Плохотніченко\nПлохотніченко Леонід Іванович\n186259\n3031\n186259\n160\n2430\nХерсонська область\n81.9\nХерсонська область\n2014\n186259\n186259\n3031\n2430\nХерсонська область\n160\n81.9\nХерсонська область\nЗагальний місцевий суд\nКіровоградська область\nсуддя ленінського районного суду м. кіровограда\nПлохотніченко Леонід Іванович\nЛеонід Іванович Плохотніченко\nЛеонід Плохотніченко\nПлохотніченко Леонід Іванович\nЛеонід\nДитина\nПлохотніченко С. Л\nДитина\nПлохотніченко М. Л\nПлохотніченко Леонід Іванович\nПлохотніченко\nІванович\n25000\nКіровоградська область\nКіровоград\n186259\n186259\n3031\n2014\nПлохотніченко С. Л\nДитина\nДитина\nПлохотніченко М. Л\nІванович\nПлохотніченко\nЛеонід\nПлохотніченко Леонід Іванович\nЛеонід Іванович Плохотніченко\nЛеонід Плохотніченко\nПлохотніченко Леонід Іванович\n25000\nКіровоград\nКіровоградська область\nКіровоградська область\nЗагальний місцевий суд\nсуддя ленінського районного суду м. кіровограда\nПлохотніченко Леонід Іванович\n160\nХерсонська область\n2430\nХерсонська область\n81.9\n2014","general":{"name_hidden":false,"name":"Леонід","last_name_hidden":false,"inn":"","family":[{"inn":"","inn_hidden":false,"inn_unclear":false,"relations_hidden":false,"relations_other":"","relations":"Дитина","name_hidden":false,"family_name":"Плохотніченко С. Л","name_unclear":false},{"inn":"","inn_hidden":false,"relations_unclear":false,"relations_hidden":false,"relations_other":"","relations":"Дитина","name_hidden":false,"inn_unclear":false,"family_name":"Плохотніченко М. Л","name_unclear":false}],"patronymic":"Іванович","inn_hidden":false,"family_raw":"","inn_unclear":false,"post":{"post_unclear":false,"region_unclear":false,"post":"суддя ленінського районного суду м. кіровограда","office":"Загальний місцевий суд","region":"Кіровоградська область","post_hidden":false,"office_hidden":false,"office_unclear":false,"region_hidden":false},"last_name_unclear":false,"full_name":"Плохотніченко Леонід Іванович","addresses":[{"place_district":"","place_address_hidden":false,"place_city":"Кіровоград","place_city_type_hidden":false,"place_district_hidden":false,"place_city_type":"Місто","place_city_hidden":false,"place_address_unclear":false,"place_address":"25000","place_hidden":false,"place":"Кіровоградська область"}],"last_name":"Плохотніченко","patronymic_hidden":false,"full_name_suggest":{"output":"Плохотніченко Леонід Іванович","input":["Плохотніченко Леонід Іванович","Леонід Іванович Плохотніченко","Леонід Плохотніченко"]},"name_unclear":false},"source":"VULYK","estate":{"23":[{"space_unclear":false,"costs":"","costs_comment":"","address_hidden":false,"region_hidden":false,"space_comment":"","space_hidden":false,"space":"2430","address":"","region":"Херсонська область","address_unclear":false,"costs_rent_comment":"","space_units":"м²","costs_rent":"160"}],"24":[{"space_unclear":false,"costs":"","costs_comment":"","address_hidden":false,"region_hidden":false,"space_comment":"","space_hidden":false,"space":"81.9","address":"","region":"Херсонська область","address_unclear":false,"costs_rent_comment":"","space_units":"м²","costs_rent":""}]},"intro":{"declaration_year":"2014","isnotdeclaration":"","declaration_year_hidden":false}}