{"id":"vulyk_84_24","ft_src":"Дніпропетровська область\nсмт Магдалинівка\n28\n.15\nДніпропетровська область\nм. Дніпропетровськ\n9.8\nДніпропетровська область\nм. Дніпропетровськ\n75.9\n2014\n31345\n198443\n12180\n50112\n210623\n4629\n14138\n198443\n31345\n4629\n14138\n210623\n50112\n12180\nЖивоглядов Андрій Миколайович\nАндрій Миколайович Живоглядов\nАндрій Живоглядов\nЖивоглядов Андрій Миколайович\nАндрій\nПодружжя\nЖивоглядова У. С\nДитина\nТурченко В. В\nДитина\nЖивоглядов Д. А\nЖивоглядов Андрій Миколайович\nМиколайович\nсуддя магдалинівського районного суду дніпропетровської області\nЗагальний місцевий суд\nДніпропетровська область\nЖивоглядов\nСМТ\nМагдалинівка\n51100\nДніпропетровська область\nМагдалинівський\n40641\n6615\n.15\n28\nДніпропетровська область\nсмт Магдалинівка\nм. Дніпропетровськ\nДніпропетровська область\n9.8\n75.9\nДніпропетровська область\nм. Дніпропетровськ\n2014\n40641\n6615\nЖивоглядова У. С\nПодружжя\nТурченко В. В\nДитина\nЖивоглядов Д. А\nДитина\nМиколайович\nЖивоглядов\nАндрій\nЖивоглядов Андрій Миколайович\nАндрій Миколайович Живоглядов\nАндрій Живоглядов\nЖивоглядов Андрій Миколайович\nДніпропетровська область\nМагдалинівка\nМагдалинівський\nСМТ\n51100\nДніпропетровська область\nсуддя магдалинівського районного суду дніпропетровської області\nЗагальний місцевий суд\nЖивоглядов Андрій Миколайович","estate":{"23":[{"address":"смт Магдалинівка","space_units":"га","costs_comment":"","space_comment":"","region_hidden":false,"region":"Дніпропетровська область","address_hidden":false,"costs":"","address_unclear":false,"space_comment_unclear":false,"costs_rent_comment":"","space":".15","region_unclear":false,"costs_rent":"28"}],"25":[{"address":"м. Дніпропетровськ","space_units":"м²","space_hidden":false,"space_comment":"","region_hidden":false,"costs_comment":"","address_hidden":false,"costs":"","address_unclear":false,"costs_rent_comment_unclear":false,"costs_comment_unclear":false,"costs_rent_comment":"","space":"75.9","region_unclear":false,"region":"Дніпропетровська область","costs_rent":""}],"31":[{"costs_property_comment":"","address":"м. Дніпропетровськ","space_units":"м²","space_unclear":false,"region_hidden":false,"costs_property":"","space_comment":"","address_hidden":false,"address_unclear":false,"costs_rent_comment":"","space":"9.8","region":"Дніпропетровська область","costs_rent":""}]},"source":"VULYK","income":{"5":{"family_comment":"","family":"50112","comment":"","value_unclear":false,"family_unclear":false,"comment_unclear":false,"value":"210623"},"6":{"family_comment":"","comment_unclear":false,"value":"198443","family":"31345","comment":""},"7":{"family":"","family_comment":"","value":"","comment":"","source_name":""},"8":{"family_comment":"","value":"","family":"","comment":""},"9":{"family_comment":"","value":"","family":"","comment":"","value_unclear":false},"10":{"family_comment":"","value":"12180","family":"","comment":"","value_unclear":false},"11":{"family_comment":"","value":"","family":"","comment":""},"12":{"family_comment":"","value":"","family":"14138","comment":""},"13":{"family_comment":"","value":"","family":"","comment":""},"14":{"family_comment":"","value":"","family":"","comment":""},"15":{"family_comment":"","value":"","family":"","comment":""},"16":{"family_comment":"","value":"","family":"","comment":""},"17":{"family_comment":"","value":"","family":"","comment":"","value_unclear":false},"18":{"family_comment":"","value":"","family":"","comment":"","value_unclear":false},"19":{"family_comment":"","value":"","family":"","comment":""},"20":{"family_comment":"","family":"4629","comment":"","value_unclear":false,"family_unclear":false,"comment_unclear":false,"value":""}},"general":{"family_raw":"","name":"Андрій","full_name_suggest":{"input":["Живоглядов Андрій Миколайович","Андрій Миколайович Живоглядов","Андрій Живоглядов"],"output":"Живоглядов Андрій Миколайович"},"patronymic":"Миколайович","inn_hidden":true,"addresses":[{"place_city_type_hidden":false,"place_district_hidden":false,"place_address_unclear":false,"place":"Дніпропетровська область","place_city":"Магдалинівка","place_unclear":false,"place_city_type_unclear":false,"place_city_type":"СМТ","place_city_hidden":false,"place_city_unclear":false,"place_district":"Магдалинівський","place_district_unclear":false,"place_address":"51100","place_address_hidden":false,"place_hidden":false}],"inn":"","inn_unclear":false,"last_name":"Живоглядов","full_name":"Живоглядов Андрій Миколайович","family":[{"inn":"","inn_unclear":false,"family_name":"Живоглядова У. С","relations_other":"","relations_hidden":false,"name_unclear":false,"inn_hidden":true,"name_hidden":false,"relations":"Подружжя"},{"inn":"","family_name":"Турченко В. В","relations_other":"","name_unclear":false,"inn_hidden":false,"name_hidden":false,"relations":"Дитина"},{"inn":"","family_name":"Живоглядов Д. А","relations_other":"","name_unclear":false,"inn_hidden":false,"name_hidden":false,"relations":"Дитина"}],"post":{"post_hidden":false,"office":"Загальний місцевий суд","region_hidden":false,"post":"суддя магдалинівського районного суду дніпропетровської області","candidate":"","region_unclear":false,"region":"Дніпропетровська область","office_hidden":false,"post_unclear":false,"office_unclear":false}},"liabilities":{"54":{"sum_comment":"","sum_foreign_comment":"","sum_foreign":"","sum":"","sum_comment_hidden":false},"55":{"sum_comment":"","sum_foreign_comment":"","sum_foreign":"","sum":""},"56":{"sum_comment":"","sum_foreign_comment":"","sum_foreign":"","sum":""},"57":{"sum_comment":"","sum_foreign_comment":"","sum_foreign":"","sum":"6615","sum_comment_hidden":false},"58":{"sum_comment":"","sum_foreign_comment":"","sum_foreign":"","sum":"40641","sum_comment_hidden":false},"59":{"sum_comment":"","sum_foreign_comment":"","sum_foreign":"","sum":""},"60":{"sum_comment":"","sum_foreign_comment":"","sum_foreign":"","sum":""},"61":{"sum_comment":"","sum_foreign_comment":"","sum_foreign":"","sum":""},"62":{"sum_comment":"","sum_foreign_comment":"","sum_foreign":"","sum":""},"63":{"sum_comment":"","sum_foreign_comment":"","sum_foreign":"","sum":"","sum_comment_hidden":false},"64":{"sum_comment":"","sum_foreign_comment":"","sum_foreign":"","sum":"","sum_comment_hidden":false}},"declaration":{"notfull_lostpages":"","additional_info_text":"","additional_info":"","date":"2015-03-26T00:00:00","notfull":"","url":"http://static.declarations.com.ua/declarations/chosen_ones/judges_batch/2438_zhyvohliadov_andrii_mykolaiovych.pdf"},"intro":{"isnotdeclaration":"","declaration_year_unclear":false,"declaration_year":"2014"}}