{"income":{"5":{"value":"186930.6","family_comment":"","value_unclear":false,"comment_hidden":false,"family_hidden":false,"value_hidden":false,"family_unclear":false,"family_comment_hidden":false,"comment":"","family":"21428.41"},"6":{"value":"170294.85","family_comment":"","value_unclear":false,"family_hidden":false,"family_unclear":false,"family":"17635.9","comment":""},"7":{"source_name_unclear":false,"value":"","family_hidden":false,"family_comment":"","source_name":"","family":"","comment":"","source_name_hidden":false},"8":{"family_comment":"","value":"","family":"","comment":""},"9":{"value":"855.75","value_unclear":false,"family_hidden":false,"family_comment":"","family":"","comment":""},"10":{"value":"12180","value_unclear":false,"family_hidden":false,"value_hidden":false,"family_comment":"","comment_unclear":false,"comment":"","family":""},"11":{"family_comment":"","value":"","family":"","comment":""},"12":{"family_comment":"","value":"","family":"","comment":""},"13":{"family_comment":"","value":"","family":"","comment":""},"14":{"family_comment":"","value":"","family":"","comment":""},"15":{"family_comment":"","value":"","family_hidden":false,"comment":"","family":""},"16":{"value":"","value_unclear":false,"family_hidden":false,"family_comment":"","family":"","comment":""},"17":{"family_comment":"","value":"","family_hidden":false,"comment":"","family":""},"18":{"family_comment":"","value":"","value_unclear":false,"family":"","comment":""},"19":{"family_comment":"","value":"3600","family":"","comment":""},"20":{"value":"","family_comment":"2232,31 грн. - одноразова допомога при народженні дитини 1560 грн. - дпомога по догляду за дитиною до 3-х років","value_unclear":false,"family_hidden":false,"family_unclear":false,"comment_unclear":false,"comment":"","family":"3792.54"}},"vehicle":{"40":[{"year_hidden":false,"brand_info":"1.0 куб. дм., 90 к. с","sum_rent_comment":"","year":"2013","brand_info_hidden":false,"brand_info_unclear":false,"year_unclear":false,"sum_rent":"","sum":"","brand":"Ford Focus","sum_comment":"","brand_unclear":false,"brand_hidden":false}]},"id":"vulyk_72_310","banks":{"46":[{"sum_foreign_comment":"","sum_units":"UAH","sum_comment":"","sum_hidden":false,"sum_foreign_units":"UAH","sum_comment_hidden":false,"sum_unclear":false,"sum":"3668.27","sum_foreign":""}]},"declaration":{"additional_info_text":"","notfull_lostpages":"","date":"2015-03-27T00:00:00","notfull":"","additional_info":"","url":"http://static.declarations.com.ua/declarations/chosen_ones/epic_batch/kushnirchuk_roman_oleksiiovych.pdf"},"liabilities":{"54":{"sum_foreign_comment":"","sum":"","sum_comment":"","sum_comment_hidden":false,"sum_unclear":false,"sum_foreign":""},"55":{"sum_foreign_comment":"","sum":"","sum_comment":"","sum_foreign":""},"56":{"sum_foreign_comment":"","sum":"","sum_hidden":false,"sum_comment":"","sum_foreign":""},"57":{"sum_foreign_comment":"","sum":"","sum_comment":"","sum_comment_unclear":false,"sum_hidden":false,"sum_comment_hidden":false,"sum_unclear":false,"sum_foreign":""},"58":{"sum_foreign_comment":"","sum":"","sum_comment":"","sum_comment_unclear":false,"sum_hidden":false,"sum_comment_hidden":false,"sum_unclear":false,"sum_foreign":""},"59":{"sum_foreign_comment":"","sum_foreign_hidden":false,"sum_comment":"","sum_foreign_unclear":false,"sum_comment_hidden":false,"sum":"","sum_foreign":""},"60":{"sum_foreign_comment":"","sum_foreign_hidden":false,"sum_comment":"","sum_hidden":false,"sum":"","sum_foreign":""},"61":{"sum_foreign_comment":"","sum_foreign_hidden":false,"sum_comment":"","sum_hidden":false,"sum":"","sum_foreign":""},"62":{"sum_foreign_comment":"","sum_foreign_hidden":false,"sum_comment":"","sum_hidden":false,"sum":"","sum_foreign":""},"63":{"sum_foreign_comment":"","sum_foreign_hidden":false,"sum_comment":"","sum_comment_unclear":false,"sum_hidden":false,"sum_comment_hidden":false,"sum_unclear":false,"sum":"","sum_foreign":""},"64":{"sum_foreign_comment":"","sum_foreign_hidden":false,"sum_comment":"","sum_hidden":false,"sum":"","sum_foreign":""}},"ft_src":"Дніпропетровськ\nДніпропетровськ\nДніпропетровська область\nсуддя самарського районного суду м. дніпропетровська\nДніпропетровська область\nЗагальний місцевий суд\nРоман\nКушнірчук Наталія Василівна\nПодружжя\nКушнірчук Софія Романівна\nДитина\nОлексійович\nКушнірчук\nКушнірчук Роман Олексійович\nКушнірчук Роман Олексійович\nРоман Олексійович Кушнірчук\nРоман Кушнірчук\nКушнірчук Роман Олексійович\n1.0 куб. дм., 90 к. с\nFord Focus\n2013\n1/2 частина\n5.8663\n79.9\n3668.27\n2014\n1.0 куб. дм., 90 к. с\nFord Focus\n2013\n5.8663\n1/2 частина\n79.9\nПодружжя\nКушнірчук Наталія Василівна\nДитина\nКушнірчук Софія Романівна\nКушнірчук Роман Олексійович\nРоман Олексійович Кушнірчук\nРоман Кушнірчук\nКушнірчук Роман Олексійович\nРоман\nКушнірчук Роман Олексійович\nКушнірчук\nДніпропетровська область\nЗагальний місцевий суд\nсуддя самарського районного суду м. дніпропетровська\nОлексійович\nДніпропетровськ\nДніпропетровська область\nДніпропетровськ\n170294.85\n17635.9\n2232,31 грн. - одноразова допомога при народженні дитини 1560 грн. - дпомога по догляду за дитиною до 3-х років\n3792.54\n186930.6\n21428.41\n855.75\n12180\n3600\n3668.27\n2014\n17635.9\n170294.85\n855.75\n12180\n21428.41\n186930.6\n3600\n2232,31 грн. - одноразова допомога при народженні дитини 1560 грн. - дпомога по догляду за дитиною до 3-х років\n3792.54\nКушнірчук Наталія Василівна\nПодружжя\nКушнірчук Софія Романівна\nДитина\nОлексійович\nКушнірчук\nКушнірчук Роман Олексійович\nРоман Олексійович Кушнірчук\nРоман Кушнірчук\nКушнірчук Роман Олексійович\nДніпропетровська область\nДніпропетровськ\nДніпропетровськ\nДніпропетровська область\nЗагальний місцевий суд\nсуддя самарського районного суду м. дніпропетровська\nКушнірчук Роман Олексійович\nРоман\nFord Focus\n1.0 куб. дм., 90 к. с\n2013\n3600\n855.75\n12180\n2232,31 грн. - одноразова допомога при народженні дитини 1560 грн. - дпомога по догляду за дитиною до 3-х років\n3792.54\n186930.6\n21428.41\n170294.85\n17635.9\n79.9\n1/2 частина\n5.8663\n3668.27\n2014","general":{"inn":"","name":"Роман","patronymic_unclear":false,"family":[{"inn":"","inn_hidden":false,"relations_unclear":false,"relations_hidden":false,"relations_other":"","relations":"Подружжя","name_hidden":false,"inn_unclear":false,"family_name":"Кушнірчук Наталія Василівна","name_unclear":false},{"inn":"","inn_hidden":false,"relations_hidden":false,"family_name":"Кушнірчук Софія Романівна","relations_other":"","relations":"Дитина","name_hidden":false,"name_unclear":false}],"patronymic":"Олексійович","inn_hidden":false,"family_raw":"","inn_unclear":false,"post":{"post_unclear":false,"region_unclear":false,"post":"суддя самарського районного суду м. дніпропетровська","candidate":"","office_hidden":false,"region":"Дніпропетровська область","post_hidden":false,"office":"Загальний місцевий суд","office_unclear":false,"region_hidden":false},"last_name_unclear":false,"full_name":"Кушнірчук Роман Олексійович","addresses":[{"place_city_type_hidden":false,"place_district_hidden":false,"place_city_type":"Місто","place_city_hidden":false,"place_address_unclear":false,"place_address":"","place":"Дніпропетровська область","place_district":"Дніпропетровськ","place_unclear":false,"place_city":"Дніпропетровськ","place_city_unclear":false,"place_hidden":false,"place_address_hidden":false,"place_district_unclear":false}],"last_name":"Кушнірчук","patronymic_hidden":false,"full_name_suggest":{"output":"Кушнірчук Роман Олексійович","input":["Кушнірчук Роман Олексійович","Роман Олексійович Кушнірчук","Роман Кушнірчук"]},"name_unclear":false},"source":"VULYK","estate":{"23":[{"space_hidden":false,"costs":"","costs_rent_unclear":false,"costs_comment":"","costs_hidden":false,"address_hidden":false,"region_hidden":false,"space_comment":"1/2 частина","space_unclear":false,"space":"5.8663","address":"","region":"","address_unclear":false,"costs_rent_comment":"","costs_rent_hidden":false,"space_units":"га","space_units_hidden":false,"costs_rent":""}],"31":[{"space_unclear":false,"address_hidden":false,"region_hidden":true,"space_comment":"","space_units_hidden":false,"space_hidden":false,"space":"79.9","address":"","region":"","address_unclear":false,"costs_rent_comment":"","costs_property":"","space_units":"м²","costs_property_comment":"","costs_rent":""}]},"intro":{"declaration_year":"2014","isnotdeclaration":"","declaration_year_unclear":false}}