{"income":{"5":{"value":"303020","family_comment":"","value_unclear":false,"family_hidden":false,"family_unclear":false,"family":"80045","comment":""},"6":{"value":"240678","family_comment":"","value_unclear":false,"family_hidden":false,"family_unclear":false,"family":"","comment":""},"7":{"value":"","family_comment":"","source_name":"","family":"","comment":"","source_name_hidden":false},"8":{"family_comment":"","value":"","family":"","comment":""},"9":{"family_comment":"","value":"","family":"","comment":""},"10":{"value":"","family_comment":"","value_unclear":false,"family_unclear":false,"family":"","comment":""},"11":{"family_comment":"","value":"","family":"","comment":""},"12":{"family_comment":"","value":"","family":"","comment":""},"13":{"family_comment":"","value":"","family":"","comment":""},"14":{"family_comment":"","value":"","family":"","comment":""},"15":{"value":"17424","value_unclear":false,"value_hidden":false,"family_comment":"","family":"","comment":""},"16":{"family_comment":"","value":"","family":"","comment":""},"17":{"family_comment":"","value":"","family":"77845","comment":"","family_comment_hidden":false},"18":{"family_comment":"","value":"","family":"","comment":""},"19":{"family_comment":"","value":"","family":"2200","comment":""},"20":{"value":"44918","family_comment":"","comment_unclear":false,"family_unclear":false,"family_comment_unclear":false,"family_comment_hidden":false,"comment":"","family":""}},"vehicle":{"35":[{"brand_info":"1800 куб см, 120 кВт , 483.3 см","sum_rent_comment":"","year":"2008","brand_info_hidden":false,"brand_info_unclear":false,"sum_rent":"","sum":"","brand":"Skoda Superb Classic","sum_comment":"","brand_unclear":false,"brand_hidden":false,"sum_rent_comment_hidden":false},{"brand_info":"2477 куб. см., 131 кВт , 469.5 см","sum":"","brand":"Mitsubishi Pajero Sport","sum_comment":"","brand_unclear":false,"year":"2013","brand_hidden":false,"brand_info_hidden":false,"brand_info_unclear":false,"sum_rent_comment":"","sum_rent":""}]},"id":"vulyk_28_15","banks":{"45":[{"sum_units":"UAH","sum_hidden":false,"sum_units_hidden":false,"sum_foreign":"","sum_foreign_comment":"","sum":"","sum_comment":"","sum_comment_unclear":false,"sum_foreign_units":"UAH","sum_units_unclear":false,"sum_comment_hidden":false,"sum_unclear":false},{"sum_foreign_comment":"","sum_units":"","sum_comment":"","sum_foreign_units":"","sum_units_unclear":false,"sum_comment_hidden":false,"sum_unclear":false,"sum":"","sum_foreign":""},{"sum_foreign_comment":"","sum_units":"","sum_comment":"","sum_foreign_units":"","sum":"","sum_foreign":""}],"46":[{"sum_foreign_comment":"","sum_units":"UAH","sum_comment":"","sum_hidden":false,"sum_foreign_units":"UAH","sum_units_unclear":false,"sum_comment_hidden":false,"sum_unclear":false,"sum":"","sum_foreign":""},{"sum_foreign_comment":"","sum_units":"","sum_comment":"","sum_comment_hidden":false,"sum":"","sum_foreign":""}],"47":[{"sum_units":"UAH","sum_foreign_comment_hidden":false,"sum_hidden":false,"sum_foreign":"","sum_foreign_comment":"","sum":"","sum_comment":"","sum_comment_unclear":false,"sum_foreign_units":"UAH","sum_units_unclear":false,"sum_comment_hidden":false,"sum_unclear":false},{"sum_foreign_comment":"","sum_units":"","sum_comment":"","sum":"","sum_foreign":""}],"48":[{"sum_foreign_comment":"","sum_units":"UAH","sum_comment":"","sum_foreign_units":"UAH","sum":"","sum_foreign":""},{"sum_foreign_comment":"","sum_units":"","sum_comment":"","sum_foreign_units":"","sum":"","sum_foreign":""}],"49":[{"sum_foreign_comment":"","sum_units":"UAH","sum_comment":"","sum_foreign_units":"UAH","sum":"","sum_foreign":""}],"50":[{"sum_foreign_comment":"","sum_units":"UAH","sum_comment":"","sum_foreign_units":"UAH","sum":"","sum_foreign":""}],"51":[{"sum_units":"UAH","sum_foreign_units_unclear":false,"sum_foreign_unclear":false,"sum_hidden":false,"sum_units_hidden":false,"sum_foreign":"","sum_foreign_comment":"","sum":"","sum_comment":"","sum_foreign_units":"UAH","sum_units_unclear":false,"sum_comment_hidden":false,"sum_unclear":false},{"sum_foreign_comment":"","sum_units":"","sum_comment":"","sum_foreign_units":"","sum_comment_hidden":false,"sum":"","sum_foreign":""}],"52":[{"sum_foreign_comment":"","sum_units":"UAH","sum_comment":"","sum_comment_unclear":false,"sum_foreign_units":"UAH","sum_units_unclear":false,"sum_comment_hidden":false,"sum_unclear":false,"sum":"","sum_foreign":""}],"53":[{"sum_foreign_comment":"","sum_units":"UAH","sum_comment":"","sum_foreign_units":"UAH","sum":"","sum_foreign":""}]},"declaration":{"additional_info_text":"","notfull_lostpages":"","date":"2015-03-30T00:00:00","notfull":"","additional_info":"","url":"http://static.declarations.com.ua/declarations/chosen_ones/mega_batch/feskov_petro_vasylvych.pdf"},"liabilities":{"54":{"sum_foreign_comment":"","sum":"","sum_comment":"","sum_comment_unclear":false,"sum_hidden":false,"sum_comment_hidden":false,"sum_unclear":false,"sum_foreign":""},"55":{"sum_foreign_comment":"","sum":"","sum_comment":"","sum_foreign":""},"56":{"sum_foreign_comment":"","sum":"","sum_comment":"","sum_unclear":false,"sum_foreign":""},"57":{"sum_foreign_comment":"","sum":"85649","sum_comment":"","sum_hidden":false,"sum_comment_hidden":false,"sum_unclear":false,"sum_foreign":""},"58":{"sum_foreign_comment":"","sum_comment_hidden":false,"sum":"34351","sum_comment":"","sum_foreign":""},"59":{"sum_foreign_comment":"","sum":"","sum_comment":"","sum_comment_unclear":false,"sum_unclear":false,"sum_foreign":""},"60":{"sum_foreign_comment":"","sum":"","sum_comment":"","sum_comment_unclear":false,"sum_hidden":false,"sum_comment_hidden":false,"sum_unclear":false,"sum_foreign":""},"61":{"sum_foreign_comment":"","sum":"","sum_hidden":false,"sum_comment":"","sum_foreign":""},"62":{"sum_foreign_comment":"","sum":"","sum_comment":"","sum_unclear":false,"sum_foreign":""},"63":{"sum_foreign_comment":"","sum":"","sum_comment":"","sum_hidden":false,"sum_comment_hidden":false,"sum_foreign":""},"64":{"sum_foreign_comment":"","sum":"","sum_comment":"","sum_hidden":false,"sum_comment_hidden":false,"sum_foreign":""}},"ft_src":"85649\n34351\nМалі Дорогостаї\nСело\n35100\nРівненська область\nМлинівський\nголова млинівського районного суду рівненської області\nРівненська область\nЗагальний місцевий суд\nПетро\nПодружжя\nВасильович\nФеськов\nФеськов Петро Васильович\nФеськов Петро Васильович\nПетро Васильович Феськов\nПетро Феськов\nФеськов Петро Васильович\n1800 куб см, 120 кВт , 483.3 см\nSkoda Superb Classic\n2008\nMitsubishi Pajero Sport\n2477 куб. см., 131 кВт , 469.5 см\n2013\n2014\n1800 куб см, 120 кВт , 483.3 см\nSkoda Superb Classic\n2008\n2477 куб. см., 131 кВт , 469.5 см\n2013\nMitsubishi Pajero Sport\n3700\nРівненська область\nсело Малі Дорогостаї Млинівського району\n30100\nРівненська область\nВладиславівська сільська рада, село Гончариха Млинівського району\n37.4\nРівненська область\nсело Малі Дорогостаї Млинівського району\n37.4\nРівненська область\nсело Малі Дорогостаї Млинівського району\nРівненська область\nм. Рівне\n37.5\nФеськов Петро Васильович\nПетро Васильович Феськов\nПетро Феськов\nФеськов Петро Васильович\nФеськов Петро Васильович\nПодружжя\nПетро\nВасильович\nЗагальний місцевий суд\nголова млинівського районного суду рівненської області\nРівненська область\nФеськов\nСело\n35100\nРівненська область\nМалі Дорогостаї\nМлинівський\n85649\n34351\n240678\n77845\n44918\n17424\n80045\n303020\n2200\n2014\n34351\n85649\nм. Рівне\n37.5\nРівненська область\nсело Малі Дорогостаї Млинівського району\nРівненська область\n37.4\nВладиславівська сільська рада, село Гончариха Млинівського району\nРівненська область\n30100\nсело Малі Дорогостаї Млинівського району\n3700\nРівненська область\nсело Малі Дорогостаї Млинівського району\n37.4\nРівненська область\nПодружжя\nПетро\nВасильович\nФеськов\nФеськов Петро Васильович\nПетро Васильович Феськов\nПетро Феськов\nФеськов Петро Васильович\nСело\nРівненська область\nМалі Дорогостаї\n35100\nМлинівський\nРівненська область\nголова млинівського районного суду рівненської області\nЗагальний місцевий суд\nФеськов Петро Васильович\n240678\n17424\n80045\n303020\n77845\n2200\n44918\nSkoda Superb Classic\n1800 куб см, 120 кВт , 483.3 см\n2008\nMitsubishi Pajero Sport\n2477 куб. см., 131 кВт , 469.5 см\n2013\n2200\n17424\n44918\n303020\n80045\n77845\n240678\nм. Рівне\nРівненська область\n37.5\nсело Малі Дорогостаї Млинівського району\nРівненська область\n37.4\nсело Малі Дорогостаї Млинівського району\nРівненська область\n37.4\nВладиславівська сільська рада, село Гончариха Млинівського району\nРівненська область\n30100\nсело Малі Дорогостаї Млинівського району\nРівненська область\n3700\n2014","general":{"inn":"","name":"Петро","family":[{"inn":"","inn_hidden":true,"inn_unclear":false,"relations_hidden":false,"relations_other":"","relations":"Подружжя","name_hidden":true,"family_name":"","name_unclear":false}],"patronymic":"Васильович","inn_hidden":true,"family_raw":"","last_name":"Феськов","post":{"post_unclear":false,"post":"голова млинівського районного суду рівненської області","post_hidden":false,"region":"Рівненська область","office":"Загальний місцевий суд","office_hidden":false,"office_unclear":false},"last_name_unclear":false,"full_name":"Феськов Петро Васильович","addresses":[{"place_district":"Млинівський","place_city_hidden":false,"place_city":"Малі Дорогостаї","place_city_type_hidden":false,"place_district_hidden":false,"place_city_type":"Село","place_address_hidden":true,"place_address":"35100","place_hidden":false,"place":"Рівненська область"}],"full_name_suggest":{"output":"Феськов Петро Васильович","input":["Феськов Петро Васильович","Петро Васильович Феськов","Петро Феськов"]}},"source":"VULYK","estate":{"23":[{"space_hidden":false,"costs":"","costs_comment":"","costs_hidden":false,"address_hidden":false,"region_hidden":false,"space_comment":"","space_unclear":false,"space":"3700","address":"село Малі Дорогостаї Млинівського району","region":"Рівненська область","address_unclear":false,"costs_rent_comment":"","costs_rent_hidden":false,"costs_unclear":false,"space_units":"м²","costs_rent":""},{"space_unclear":false,"costs":"","costs_comment":"","costs_hidden":false,"region_hidden":false,"space_comment":"","space":"","address":"","costs_comment_unclear":false,"region":"","costs_rent_comment":"","costs_rent_hidden":false,"space_comment_unclear":false,"space_units":"","costs_rent":""},{"costs_rent":"","region":"","costs":"","costs_rent_comment":"","costs_comment":"","space_comment":"","space_units":"","space":"","address":""}],"24":[{"space_hidden":false,"costs":"","costs_comment":"","costs_hidden":false,"address_hidden":false,"region_hidden":false,"space_comment":"","space":"37.4","address":"село Малі Дорогостаї Млинівського району","region":"Рівненська область","costs_rent_comment":"","costs_rent_hidden":false,"space_comment_hidden":false,"costs_rent_comment_hidden":false,"space_units":"м²","costs_rent":""}],"29":[{"space_unclear":false,"address_hidden":false,"region_hidden":false,"space_comment":"","space":"30100","address":"Владиславівська сільська рада, село Гончариха Млинівського району","region":"Рівненська область","costs_property":"","costs_rent_comment":"","address_unclear":false,"space_units":"м²","costs_property_comment":"","costs_rent":""}],"30":[{"space_unclear":false,"address_hidden":false,"region_hidden":false,"space_comment":"","space_hidden":false,"space":"37.4","address":"село Малі Дорогостаї Млинівського району","region":"Рівненська область","costs_property":"","costs_rent_comment":"","space_units":"м²","costs_property_comment":"","costs_rent":""}],"31":[{"space_unclear":false,"address_hidden":false,"region_hidden":false,"space_comment":"","space_hidden":false,"space":"37.5","address":"м. Рівне","region":"Рівненська область","costs_property":"","costs_rent_comment":"","space_comment_unclear":false,"space_comment_hidden":false,"space_units":"м²","costs_property_comment":"","costs_rent":""}]},"intro":{"declaration_year":"2014","isnotdeclaration":"","declaration_year_hidden":false}}