{"id":"vulyk_109_30","ft_src":"1998 куб. см., 112 кВт , 431.5 см\nToyota Rav 4\n2008\nспадщина\n.09\n1/2 від заг. пл\n.15\n1/2 від заг. пл\n.25\n1/2 від заг. пл\n.2766\n1/2 від заг. пл\n2.337\nспадщина\n2.3369\n2.0787\n.8173\n1/2 від заг. пл\n.1226\n1/2 від заг. пл\n.3074\n1/2 від заг.пл.\n.15\nспадкове майно\n83.5\n1/2 частки від заг. пл., спадщина\n62.1\n1/2 частки від заг. пл., спадщина\n57.2\n1/2 частки від заг. пл. спільна частк. вл\n178.9\n9626\n2015\n1998 куб. см., 112 кВт , 431.5 см\nToyota Rav 4\n2008\n2015\nВалентина\nАнатоліївна\nПахолюк Валентина Анатоліївна\nПахолюк Валентина Анатоліївна\nВалентина Анатоліївна Пахолюк\nВалентина Пахолюк\nПахолюк Валентина Анатоліївна\nПахолюк\nГосподарський місцевий суд\nВолинська область\nсуддя господарського суду волинської області\n239787.06\n20131.74\n265448.72\n3.86\n5526.06\n.09\nспадщина\n.15\n1/2 від заг. пл\n.25\n1/2 від заг. пл\n.2766\n1/2 від заг. пл\n2.337\n1/2 від заг. пл\n2.3369\nспадщина\n2.0787\n.8173\n.1226\n1/2 від заг. пл\n.3074\n1/2 від заг. пл\n.15\n1/2 від заг.пл.\n62.1\n1/2 частки від заг. пл., спадщина\n57.2\n1/2 частки від заг. пл., спадщина\n83.5\nспадкове майно\n178.9\n1/2 частки від заг. пл. спільна частк. вл\n9626\n239787.06\n265448.72\n5526.06\n3.86\n20131.74\nАнатоліївна\nПахолюк\nВолинська область\nГосподарський місцевий суд\nсуддя господарського суду волинської області\nПахолюк Валентина Анатоліївна\nПахолюк Валентина Анатоліївна\nВалентина Анатоліївна Пахолюк\nВалентина Пахолюк\nПахолюк Валентина Анатоліївна\nВалентина","estate":{"23":[{"address":"","space_units":"га","costs_rent_unclear":false,"costs_comment":"","space_unclear":false,"region_hidden":false,"space_comment":"спадщина","address_hidden":false,"costs":"","costs_rent_comment":"","space":".09","region":"","costs_rent":""},{"address":"","space_units":"га","costs_rent_unclear":false,"space_hidden":false,"space_comment":"1/2 від заг. пл","region_hidden":false,"costs_comment":"","address_hidden":false,"space":".15","costs_rent_comment":"","costs":"","region":"","costs_rent":""},{"costs":"","address":"","space_units":"га","costs_rent_comment":"","space":".25","space_comment":"1/2 від заг. пл","region_hidden":false,"costs_comment":"","region":"","costs_rent":""},{"costs":"","address":"","space_units":"га","costs_rent_comment":"","space":".2766","space_comment":"1/2 від заг. пл","costs_comment":"","region":"","costs_rent":""},{"costs":"","address":"","space_units":"га","costs_rent_comment":"","space":"2.337","space_comment":"1/2 від заг. пл","costs_comment":"","costs_rent":""},{"costs":"","address":"","space_units":"га","costs_rent_comment":"","space":"2.3369","space_comment":"спадщина","costs_comment":"","costs_rent":""},{"costs":"","address":"","space_units":"га","costs_rent_comment":"","space":"2.0787","space_comment":"","costs_comment":"","costs_rent":""},{"costs":"","address":"","space_units":"га","costs_rent_comment":"","space":".8173","space_comment":"","costs_comment":"","costs_rent":""},{"costs":"","address":"","space_units":"га","costs_rent_comment":"","space":".1226","space_comment":"1/2 від заг. пл","costs_comment":"","costs_rent":""},{"costs":"","address":"","space_units":"га","costs_rent_comment":"","space":".3074","space_comment":"1/2 від заг. пл","costs_comment":"","costs_rent":""},{"costs":"","address":"","space_units":"га","costs_rent_comment":"","space":".15","space_comment":"1/2 від заг.пл.","costs_comment":"","costs_rent":""}],"24":[{"costs":"","address":"","space_units":"м²","costs_rent_comment":"","space":"62.1","space_comment":"1/2 частки від заг. пл., спадщина","region_hidden":false,"costs_comment":"","region":"","address_hidden":false,"costs_rent":""},{"costs":"","address":"","space_units":"м²","costs_rent_comment":"","space":"57.2","space_comment":"1/2 частки від заг. пл., спадщина","costs_comment":"","region":"","costs_rent":""}],"25":[{"address":"","space_units":"м²","space_hidden":false,"space_unclear":false,"region_hidden":false,"costs_comment":"","space_comment":"1/2 частки від заг. пл. спільна частк. вл","address_hidden":false,"space":"178.9","costs_rent_comment":"","costs":"","region":"","space_units_hidden":false,"costs_rent":""}],"28":[{"costs":"","address":"","space_units":"м²","costs_rent_comment":"","space":"83.5","space_comment":"спадкове майно","region_hidden":false,"costs_comment":"","region":"","address_hidden":false,"costs_rent":""}]},"vehicle":{"35":[{"sum_comment_unclear":false,"brand_info":"1998 куб. см., 112 кВт , 431.5 см","sum_rent_comment":"","brand_unclear":false,"brand_hidden":false,"year":"2008","sum_comment":"","brand_info_hidden":false,"sum_rent":"","brand":"Toyota Rav 4","year_unclear":false,"brand_info_unclear":false,"sum":""}]},"source":"VULYK","income":{"5":{"family_comment":"","value":"265448.72","family":"","comment":""},"6":{"family_comment":"","value":"239787.06","family":"","comment":""},"7":{"source_name_hidden":false,"family_comment":"","comment":"","family":"","comment_hidden":false,"value":"","source_name":""},"8":{"family_comment":"","family_hidden":false,"value":"","family":"","comment":""},"9":{"family_comment":"","family":"","comment":"","value_unclear":false,"family_unclear":false,"value":"3.86"},"10":{"family_comment":"","value":"","family":"","comment":""},"11":{"family_comment":"","value":"","family":"","comment":""},"12":{"family_comment":"","value":"","family":"","comment":""},"13":{"family_comment":"","value":"","family":"","comment":""},"14":{"family_comment":"","value":"","family":"","comment":""},"15":{"family_comment":"","value":"","family":"","comment":""},"16":{"family_comment":"","value":"","family":"","comment":""},"17":{"family_comment":"","value":"","family":"","comment":""},"18":{"family_comment":"","value":"","family":"","comment":""},"19":{"family_comment":"","value":"5526.06","family":"","comment":""},"20":{"family_comment":"","family":"","comment":"","value_unclear":false,"family_hidden":false,"value":"20131.74"}},"banks":{"45":[{"sum_units":"UAH","sum_comment":"","sum_foreign_units":"UAH","sum":"9626","sum_units_hidden":false,"sum_foreign_comment":"","sum_foreign":"","sum_unclear":false,"sum_comment_hidden":false}]},"declaration":{"notfull_lostpages":"","additional_info_text":"","additional_info":"","date":"2016-03-30T00:00:00","notfull":"","url":"http://static.declarations.com.ua/declarations/chosen_ones/judges_batch/2487_pakholiuk_valentyna_anatoliiivna_2015.pdf"},"general":{"inn":"","inn_unclear":false,"last_name":"Пахолюк","full_name_suggest":{"input":["Пахолюк Валентина Анатоліївна","Валентина Анатоліївна Пахолюк","Валентина Пахолюк"],"output":"Пахолюк Валентина Анатоліївна"},"full_name":"Пахолюк Валентина Анатоліївна","patronymic":"Анатоліївна","family_raw":"","name":"Валентина","name_hidden":false,"post":{"office":"Господарський місцевий суд","post":"суддя господарського суду волинської області","office_unclear":false,"region_hidden":false,"region":"Волинська область","office_hidden":false,"region_unclear":false},"inn_hidden":false},"liabilities":{"54":{"sum_comment":"","sum_hidden":false,"sum":"","sum_foreign_comment":"","sum_foreign":"","sum_unclear":false,"sum_comment_hidden":false},"55":{"sum_comment":"","sum_comment_unclear":false,"sum_foreign_comment":"","sum":"","sum_foreign":""},"56":{"sum_comment":"","sum_foreign_comment":"","sum_foreign":"","sum":""},"57":{"sum_comment":"","sum_foreign_comment":"","sum_foreign":"","sum":"","sum_comment_hidden":false},"58":{"sum_comment":"","sum_foreign_comment":"","sum_foreign":"","sum":"","sum_comment_hidden":false},"59":{"sum_comment":"","sum_foreign_comment":"","sum_foreign":"","sum":""},"60":{"sum_comment":"","sum_foreign_comment":"","sum_foreign":"","sum":""},"61":{"sum_comment":"","sum_foreign_comment":"","sum_foreign":"","sum":""},"62":{"sum_comment":"","sum_foreign_comment":"","sum_foreign":"","sum":""},"63":{"sum_comment":"","sum_foreign_comment":"","sum_foreign":"","sum":""},"64":{"sum_comment":"","sum_foreign_comment":"","sum_foreign":"","sum":""}},"intro":{"isnotdeclaration":"","declaration_year":"2015"}}