{"income":{"5":{"family_comment":"","value":"259927","value_unclear":false,"family":"934","comment":""},"6":{"value":"246556","value_unclear":false,"family_hidden":false,"family_comment":"","family":"934","comment":""},"7":{"source_name_unclear":false,"value":"","family_comment":"","source_name":"","family":"","comment":""},"8":{"family_comment":"","value":"","family":"","comment":""},"9":{"family_comment":"","value":"1970","family":"","comment":"Приватбанк, Ощадбанк"},"10":{"family_comment":"","value":"","family":"","comment":""},"11":{"family_comment":"","value":"","comment_unclear":false,"family":"","comment":""},"12":{"family_comment":"","value":"","family":"","comment":""},"13":{"family_comment":"","value":"","family":"","comment":""},"14":{"family_comment":"","value":"","family":"","comment":""},"15":{"family_comment":"","value":"","family":"","comment":""},"16":{"family_comment":"","value":"","family":"","comment":""},"17":{"family_comment":"","value":"","family":"","comment":""},"18":{"family_comment":"","value":"","family":"","comment":""},"19":{"family_comment":"","value":"","family":"","comment":""},"20":{"value":"11401","family_comment":"","value_unclear":false,"family_unclear":false,"comment_unclear":false,"comment":"військова пенсія","family":""}},"vehicle":{"35":[{"brand_info":"V - 1796 куб.см","sum_rent_comment":"","brand":"Opel Zafira","sum_comment":"","brand_unclear":false,"year":"2012","sum_rent_unclear":false,"brand_info_hidden":false,"brand_info_unclear":false,"sum":"","sum_rent":""}]},"id":"vulyk_101_82","banks":{"45":[{"sum_foreign_comment":"","sum_units":"UAH","sum_comment":"","sum_comment_unclear":false,"sum_hidden":false,"sum_foreign_units":"UAH","sum_comment_hidden":false,"sum_unclear":false,"sum":"10699","sum_foreign":""}],"46":[{"sum_foreign_comment":"","sum_units":"UAH","sum_comment":"","sum_hidden":false,"sum_foreign_units":"UAH","sum_comment_hidden":false,"sum":"8005","sum_foreign":""}]},"declaration":{"additional_info_text":"","notfull_lostpages":"","date":"2016-03-28T00:00:00","notfull":"","additional_info":"","url":"http://static.declarations.com.ua/declarations/chosen_ones/judges_batch/754_belena_albert_viktorovych_2015.pdf"},"liabilities":{"54":{"sum_foreign_comment":"","sum":"","sum_comment":"","sum_comment_unclear":false,"sum_hidden":false,"sum_comment_hidden":false,"sum_unclear":false,"sum_foreign":""},"55":{"sum_foreign_comment":"","sum":"","sum_comment":"","sum_foreign":""},"56":{"sum_foreign_comment":"","sum":"","sum_comment":"","sum_comment_hidden":false,"sum_unclear":false,"sum_foreign":""},"57":{"sum_foreign_comment":"","sum":"","sum_comment":"","sum_hidden":false,"sum_comment_hidden":false,"sum_unclear":false,"sum_foreign":""},"58":{"sum_foreign_comment":"","sum":"","sum_comment":"","sum_comment_unclear":false,"sum_hidden":false,"sum_comment_hidden":false,"sum_unclear":false,"sum_foreign":""},"59":{"sum_foreign_comment":"","sum":"","sum_comment":"","sum_foreign":""},"60":{"sum_foreign_comment":"","sum":"","sum_comment":"","sum_hidden":false,"sum_comment_hidden":false,"sum_unclear":false,"sum_foreign":""},"61":{"sum_foreign_comment":"","sum":"","sum_comment":"","sum_foreign":""},"62":{"sum_foreign_comment":"","sum":"","sum_comment":"","sum_comment_unclear":false,"sum_foreign":""},"63":{"sum_foreign_comment":"","sum_comment_hidden":false,"sum":"","sum_comment":"","sum_foreign":""},"64":{"sum_foreign_comment":"","sum_comment_hidden":false,"sum":"","sum_comment":"","sum_foreign":""}},"ft_src":"суддя апеляційного суду львівської області\nЛьвівська область\nЗагальний апеляційний суд\nАльберт\nБелена Олена Вікторівна\nПодружжя\nБелена Дмитро Альбертович\nДитина\nБелена Катерина Альбертівна\nДитина\nВікторович\nБелена Альберт Вікторович\nБелена\nБелена Альберт Вікторович\nАльберт Вікторович Белена\nАльберт Белена\nБелена Альберт Вікторович\nOpel Zafira\nV - 1796 куб.см\n2012\n8005\n10699\n2015\nOpel Zafira\nV - 1796 куб.см\n2012\n10699\n8005\n2015\nПодружжя\nБелена Олена Вікторівна\nДитина\nБелена Дмитро Альбертович\nДитина\nБелена Катерина Альбертівна\nБелена Альберт Вікторович\nАльберт Вікторович Белена\nАльберт Белена\nБелена Альберт Вікторович\nАльберт\nБелена Альберт Вікторович\nВікторович\nЗагальний апеляційний суд\nсуддя апеляційного суду львівської області\nЛьвівська область\nБелена\n246556\n934\nвійськова пенсія\n11401\n259927\n934\nПриватбанк, Ощадбанк\n1970\n100.1\n100.1\nБелена Олена Вікторівна\nПодружжя\nБелена Дмитро Альбертович\nДитина\nБелена Катерина Альбертівна\nДитина\nАльберт\nВікторович\nБелена\nБелена Альберт Вікторович\nАльберт Вікторович Белена\nАльберт Белена\nБелена Альберт Вікторович\nсуддя апеляційного суду львівської області\nЗагальний апеляційний суд\nЛьвівська область\nБелена Альберт Вікторович\n934\n246556\nПриватбанк, Ощадбанк\n1970\n934\n259927\nвійськова пенсія\n11401\n2012\nOpel Zafira\nV - 1796 куб.см\nПриватбанк, Ощадбанк\n1970\nвійськова пенсія\n11401\n934\n259927\n246556\n934\n100.1\n10699\n8005\n2015","general":{"inn":"","name":"Альберт","inn_unclear":false,"family":[{"inn":"","relations":"Подружжя","relations_other":"","inn_hidden":true,"family_name":"Белена Олена Вікторівна","name_hidden":true,"name_unclear":false},{"inn":"","relations":"Дитина","relations_unclear":false,"family_name":"Белена Дмитро Альбертович","inn_hidden":true,"relations_other":"","name_hidden":false,"name_unclear":false},{"inn":"","relations":"Дитина","relations_other":"","inn_hidden":true,"family_name":"Белена Катерина Альбертівна","name_hidden":false,"name_unclear":false}],"inn_hidden":true,"family_raw":"","last_name":"Белена","post":{"region":"Львівська область","region_unclear":false,"post":"суддя апеляційного суду львівської області","office_unclear":false,"office":"Загальний апеляційний суд"},"full_name":"Белена Альберт Вікторович","addresses":[{"place_district":"","place_city_hidden":true,"place_city":"","place_city_type_hidden":false,"place_district_hidden":false,"place_city_type":"","place_address_hidden":true,"place_address":"","place_hidden":true,"place":""}],"patronymic":"Вікторович","patronymic_hidden":false,"full_name_suggest":{"output":"Белена Альберт Вікторович","input":["Белена Альберт Вікторович","Альберт Вікторович Белена","Альберт Белена"]}},"source":"VULYK","estate":{"25":[{"space_unclear":false,"costs":"","costs_comment":"","address_hidden":false,"region_hidden":true,"space_comment":"","space_hidden":false,"space":"100.1","address":"","region":"","costs_rent_comment":"","space_comment_unclear":false,"space_units":"м²","costs_rent":""}],"26":[{"costs_rent":"","region":"","costs":"","costs_rent_comment":"","costs_comment":"","address_hidden":false,"region_hidden":true,"space_comment":"","space_units":"м²","space":"","address":""}]},"intro":{"declaration_year":"2015"}}