{"income":{"5":{"value":"224485","family_comment":"","value_unclear":false,"comment_hidden":false,"family_hidden":false,"value_hidden":false,"family_unclear":false,"family_comment_unclear":false,"family_comment_hidden":false,"comment":"","family":"42067"},"6":{"value":"202660","family_comment":"","value_unclear":false,"family_hidden":false,"value_hidden":false,"family_unclear":false,"family":"42067","comment":""},"7":{"source_name_unclear":false,"value":"","family_hidden":false,"value_hidden":false,"family_comment":"","source_name":"","family":"","comment":"","source_name_hidden":false},"8":{"value":"","family_comment":"","value_unclear":false,"family_hidden":false,"value_hidden":false,"family_unclear":false,"family":"","comment":""},"9":{"value":"4643","family_comment":"","value_unclear":false,"family_hidden":false,"value_hidden":false,"family_unclear":false,"comment_unclear":false,"comment":"","family":""},"10":{"value":"","value_unclear":false,"family_hidden":false,"value_hidden":false,"family_comment":"","family":"","comment":""},"11":{"value":"","family_hidden":false,"value_hidden":false,"family_comment":"","family":"","comment":""},"12":{"value":"","family_comment":"","family_hidden":false,"value_hidden":false,"family_unclear":false,"family":"","comment":""},"13":{"value":"","family_hidden":false,"value_hidden":false,"family_comment":"","family":"","comment":"Нараховані Надати відомості не маю можливості у звязку з АТО"},"14":{"value":"","family_hidden":false,"value_hidden":false,"family_comment":"","family":"","comment":""},"15":{"value":"","family_hidden":false,"value_hidden":false,"family_comment":"","family":"","comment":""},"16":{"value":"","value_unclear":false,"family_hidden":false,"value_hidden":false,"family_comment":"","family":"","comment":""},"17":{"value":"","family_hidden":false,"value_hidden":false,"family_comment":"","family":"","comment":""},"18":{"value":"","family_hidden":false,"value_hidden":false,"family_comment":"","family":"","comment":""},"19":{"value":"","comment_unclear":false,"family_hidden":false,"value_hidden":false,"family_comment":"","family":"","comment":""},"20":{"value":"16170","family_comment":"","comment_unclear":false,"comment_hidden":false,"family_hidden":false,"value_hidden":false,"family_unclear":false,"family_comment_unclear":false,"family_comment_hidden":false,"comment":"Допомога при народженні дитини: нараховано - 12150, одержано 11138 Щомісячна адресна допомога переселенцям 5032","family":""}},"vehicle":{"35":[{"year_hidden":false,"brand_info":"1498 куб. см., (на підставі довіреності","sum_rent_comment":"","sum_rent_comment_unclear":false,"sum_rent_hidden":false,"year":"2008","sum_hidden":false,"brand_info_hidden":false,"brand_info_unclear":false,"year_unclear":false,"sum_rent":"","sum_rent_unclear":false,"sum":"","brand":"Daewoo Lanos","sum_comment":"","brand_unclear":false,"brand_hidden":false,"sum_unclear":false}],"40":[{"year_hidden":false,"brand_info":"1690 куб. см.","sum_rent_comment":"","year":"2004","sum_hidden":false,"brand_info_hidden":false,"brand_info_unclear":false,"year_unclear":false,"sum_rent":"","sum":"","brand":"ВАЗ 21213","sum_comment":"","brand_unclear":false,"brand_hidden":false},{"brand_info":"1498 куб. см., (на підставі довіреності","sum_rent_comment":"","brand":"Daewoo Lanos","sum_comment":"","year":"2008","brand_info_unclear":false,"sum":"","sum_rent":""}]},"id":"vulyk_69_6","banks":{"45":[{"sum_foreign_comment":"","sum":"80024","sum_comment":"","sum_hidden":false,"sum_foreign_units":"UAH","sum_foreign_hidden":false,"sum_units":"UAH","sum_comment_hidden":false,"sum_unclear":false,"sum_foreign":"","sum_units_hidden":false}]},"declaration":{"additional_info_text":"","notfull_lostpages":"","date":"2015-03-31T00:00:00","notfull":"","additional_info":"","url":"http://static.declarations.com.ua/declarations/chosen_ones/mega_batch/kosenko_tetiana_valeriivna.pdf"},"liabilities":{"54":{"sum_foreign_comment":"","sum":"","sum_comment":"","sum_hidden":false,"sum_comment_hidden":false,"sum_unclear":false,"sum_foreign":""},"55":{"sum_foreign_comment":"","sum":"","sum_hidden":false,"sum_comment":"","sum_foreign":""},"56":{"sum_foreign_comment":"","sum":"","sum_comment":"","sum_comment_unclear":false,"sum_hidden":false,"sum_unclear":false,"sum_foreign":""},"57":{"sum_foreign_comment":"","sum":"","sum_comment":"","sum_comment_unclear":false,"sum_hidden":false,"sum_comment_hidden":false,"sum_foreign":""},"58":{"sum_foreign_comment":"","sum":"","sum_comment":"","sum_comment_unclear":false,"sum_hidden":false,"sum_comment_hidden":false,"sum_unclear":false,"sum_foreign":""},"59":{"sum_foreign_comment":"","sum":"","sum_hidden":false,"sum_comment":"","sum_foreign":""},"60":{"sum_foreign_comment":"","sum":"","sum_comment":"","sum_hidden":false,"sum_comment_hidden":false,"sum_foreign":""},"61":{"sum_foreign_comment":"","sum":"","sum_hidden":false,"sum_comment":"","sum_foreign":""},"62":{"sum_foreign_comment":"","sum":"","sum_comment":"","sum_comment_unclear":false,"sum_hidden":false,"sum_unclear":false,"sum_foreign":""},"63":{"sum_foreign_comment":"","sum":"","sum_comment":"","sum_hidden":false,"sum_comment_hidden":false,"sum_unclear":false,"sum_foreign":""},"64":{"sum_foreign_comment":"","sum":"","sum_comment":"","sum_hidden":false,"sum_comment_hidden":false,"sum_foreign":""}},"ft_src":"суддя господарського суду луганської області\nЛуганська область\nГосподарський місцевий суд\nТетяна\nЗаєць С. І., 31. 03. 1982\nЦивільний чоловік\nІнше\nКосенко С. Д., 29. 09. 2001\nДитина\nЗаєць К. С., 16. 02. 2013\nДитина\nВалеріївна\nКосенко Тетяна Валеріївна\nТетяна Валеріївна Косенко\nТетяна Косенко\nКосенко Тетяна Валеріївна\nКосенко Тетяна Валеріївна\nКосенко\n1498 куб. см., (на підставі довіреності\nDaewoo Lanos\n2008\n1690 куб. см.\nВАЗ 21213\n2004\n1498 куб. см., (на підставі довіреності\n2008\nDaewoo Lanos\n80024\n2014\n1498 куб. см., (на підставі довіреності\nDaewoo Lanos\n2008\n1690 куб. см.\nВАЗ 21213\n2004\n1498 куб. см., (на підставі довіреності\nDaewoo Lanos\n2008\n80024\n42.3\n44.2\n618\n127.8\n90.9\n44.2\nІнше\nЗаєць С. І., 31. 03. 1982\nЦивільний чоловік\nДитина\nКосенко С. Д., 29. 09. 2001\nДитина\nЗаєць К. С., 16. 02. 2013\nКосенко Тетяна Валеріївна\nТетяна Валеріївна Косенко\nТетяна Косенко\nКосенко Тетяна Валеріївна\nКосенко Тетяна Валеріївна\nТетяна\nВалеріївна\nГосподарський місцевий суд\nЛуганська область\nсуддя господарського суду луганської області\nКосенко\n42067\n202660\nНараховані Надати відомості не маю можливості у звязку з АТО\nДопомога при народженні дитини: нараховано - 12150, одержано 11138 Щомісячна адресна допомога переселенцям 5032\n16170\n42067\n224485\n4643\n2014\n127.8\n90.9\n44.2\n42.3\n618\n44.2\nІнше\nЗаєць С. І., 31. 03. 1982\nЦивільний чоловік\nДитина\nКосенко С. Д., 29. 09. 2001\nЗаєць К. С., 16. 02. 2013\nДитина\nВалеріївна\nКосенко\nТетяна\nКосенко Тетяна Валеріївна\nТетяна Валеріївна Косенко\nТетяна Косенко\nКосенко Тетяна Валеріївна\nЛуганська область\nГосподарський місцевий суд\nсуддя господарського суду луганської області\nКосенко Тетяна Валеріївна\n42067\n202660\nНараховані Надати відомості не маю можливості у звязку з АТО\n42067\n224485\n4643\nДопомога при народженні дитини: нараховано - 12150, одержано 11138 Щомісячна адресна допомога переселенцям 5032\n16170\nDaewoo Lanos\n1498 куб. см., (на підставі довіреності\n2008\nВАЗ 21213\n1690 куб. см.\n2004\n2008\n1498 куб. см., (на підставі довіреності\nDaewoo Lanos\n16170\nДопомога при народженні дитини: нараховано - 12150, одержано 11138 Щомісячна адресна допомога переселенцям 5032\n224485\n42067\n4643\n202660\n42067\nНараховані Надати відомості не маю можливості у звязку з АТО\n44.2\n618\n90.9\n42.3\n44.2\n127.8\n80024\n2014","general":{"inn":"","name":"Тетяна","patronymic_unclear":false,"family":[{"inn":"","inn_hidden":false,"relations_unclear":false,"relations_hidden":false,"relations_other":"Цивільний чоловік","relations":"Інше","name_hidden":false,"inn_unclear":false,"family_name":"Заєць С. І., 31. 03. 1982","name_unclear":false},{"inn":"","inn_hidden":false,"relations_unclear":true,"relations_hidden":false,"relations_other":"","relations":"Дитина","name_hidden":false,"inn_unclear":false,"family_name":"Косенко С. Д., 29. 09. 2001","name_unclear":false},{"inn":"","inn_hidden":false,"relations_unclear":false,"relations_hidden":false,"relations_other":"","relations":"Дитина","name_hidden":false,"family_name":"Заєць К. С., 16. 02. 2013","name_unclear":false}],"patronymic":"Валеріївна","inn_hidden":true,"family_raw":"","inn_unclear":false,"post":{"post_unclear":false,"region_unclear":false,"post":"суддя господарського суду луганської області","candidate":"","office_hidden":false,"region":"Луганська область","post_hidden":false,"office":"Господарський місцевий суд","office_unclear":false,"region_hidden":false},"full_name_suggest":{"output":"Косенко Тетяна Валеріївна","input":["Косенко Тетяна Валеріївна","Тетяна Валеріївна Косенко","Тетяна Косенко"]},"full_name":"Косенко Тетяна Валеріївна","addresses":[{"place_city_type_unclear":false,"place_address":"","place_district_hidden":false,"place_city_type":"","place_address_hidden":false,"place_address_unclear":false,"place_city_type_hidden":false,"place":"","place_district":"","place_unclear":false,"place_city":"","place_city_unclear":false,"place_hidden":true,"place_city_hidden":false,"place_district_unclear":false}],"last_name":"Косенко","last_name_unclear":false,"name_unclear":false},"source":"VULYK","estate":{"23":[{"space_unclear":false,"costs":"","costs_rent_unclear":false,"costs_comment":"","costs_hidden":false,"space_hidden":false,"space_units_unclear":false,"space_units_hidden":false,"costs_comment_unclear":false,"region":"","costs_unclear":false,"space_comment_hidden":false,"costs_rent":"","region_unclear":false,"address_hidden":false,"region_hidden":true,"space_comment":"","space":"618","address":"","address_unclear":false,"costs_rent_comment":"","costs_rent_hidden":false,"space_units":"м²"}],"24":[{"region_unclear":false,"space_hidden":false,"costs":"","costs_comment":"","costs_hidden":false,"address_hidden":false,"region_hidden":true,"space_comment":"","space_unclear":false,"space":"90.9","address":"","region":"","address_unclear":false,"costs_rent_comment":"","costs_rent_hidden":false,"space_units":"м²","space_units_hidden":false,"costs_rent":""}],"25":[{"region_unclear":false,"space_unclear":false,"costs":"","costs_comment":"","costs_hidden":false,"address_hidden":false,"region_hidden":true,"space_comment":"","space_hidden":false,"space":"44.2","space_units_hidden":false,"region":"","address_unclear":false,"costs_rent_comment":"","costs_rent_hidden":false,"space_comment_unclear":false,"space_comment_hidden":false,"space_units":"м²","address":"","costs_rent":""}],"29":[{"region_unclear":false,"space_hidden":false,"costs_property_hidden":false,"costs_property":"","address_hidden":false,"region_hidden":true,"space_comment":"","space_units_hidden":false,"space_unclear":false,"space":"127.8","address":"","region":"","address_unclear":false,"space_units_unclear":false,"space_comment_hidden":false,"space_units":"м²","costs_property_comment":"","costs_rent":"","costs_rent_comment":""}],"30":[{"space_unclear":false,"costs_property_hidden":false,"address_hidden":false,"region_hidden":true,"space_comment":"","costs_rent_comment":"","space_hidden":false,"space":"42.3","space_units_hidden":false,"region":"","costs_property":"","space_units_unclear":false,"space_comment_hidden":false,"space_units":"м²","costs_property_comment":"","costs_rent":"","address":""}],"31":[{"region_unclear":false,"space_unclear":false,"space_hidden":false,"costs_rent_unclear":false,"space_units_unclear":false,"address_hidden":false,"region_hidden":true,"space_comment":"","costs_property_unclear":false,"space":"44.2","space_units_hidden":false,"region":"","address_unclear":false,"costs_rent_comment":"","space_comment_hidden":false,"costs_property":"","space_units":"м²","costs_property_comment":"","costs_rent":"","address":""}]},"intro":{"declaration_year":"2014","isnotdeclaration":"","declaration_year_unclear":false,"declaration_year_hidden":false}}