{"income":{"5":{"value":"198680","family_comment":"","value_unclear":false,"family":"339674","family_unclear":false,"comment_unclear":false,"comment":"","family_comment_unclear":false},"6":{"value":"198680","family_comment":"","value_unclear":false,"family_unclear":false,"family":"256823","comment":""},"7":{"source_name_unclear":false,"value":"","value_unclear":false,"family_comment":"","source_name":"","family":"","comment":"","source_name_hidden":true},"8":{"family_comment":"","value":"","family":"","comment":""},"9":{"family_comment":"","value":"","family":"","comment":""},"10":{"family_comment":"","value":"","value_unclear":false,"family":"","comment":""},"11":{"value":"","value_unclear":false,"value_hidden":false,"family_comment":"","family":"","comment":""},"12":{"family_comment":"","value":"","family":"","comment":"","value_hidden":false},"13":{"family_comment":"","value":"","family":"","comment":""},"14":{"family_comment":"","value":"","family":"","comment":""},"15":{"family_comment":"","value":"","family":"","comment":""},"16":{"family_comment":"","value":"","family":"","comment":""},"17":{"family_comment":"","value":"","family":"","comment":""},"18":{"family_comment":"","value":"","family":"","comment":""},"19":{"family_comment":"","family_unclear":false,"value":"","family":"","comment":""},"20":{"family_comment":"","family_unclear":false,"value":"","family":"82851","comment":""}},"vehicle":{"40":[{"brand_info":"1596 куб. см.","sum":"","brand":"ВАЗ 21144","sum_comment":"","brand_unclear":false,"year":"2007","brand_hidden":false,"brand_info_hidden":false,"brand_info_unclear":true,"sum_rent_comment":"","sum_rent":""},{"brand_info":"1998 куб. см.","sum_rent_comment":"","brand":"Toyota Rav 4","sum_comment":"","brand_unclear":false,"year":"2008","brand_info_unclear":true,"sum":"","sum_rent":""}],"44":[{"brand_info":"причіп до л/а модель ПП-2.8 , марка ПР","sum_rent_comment":"","brand":"причіп легковий","sum_comment":"","brand_unclear":true,"year":"2008","brand_info_unclear":true,"sum":"","sum_rent":""}]},"id":"vulyk_61_43","declaration":{"additional_info_text":"","notfull_lostpages":"","date":"2015-03-30T00:00:00","notfull":"","additional_info":"","url":"http://static.declarations.com.ua/declarations/chosen_ones/mega_batch/mediana_iuliia_valeriivna.pdf"},"liabilities":{"54":{"sum_foreign_comment":"","sum":"","sum_comment":"","sum_comment_unclear":false,"sum_unclear":false,"sum_foreign":""},"55":{"sum_foreign_comment":"","sum":"","sum_comment":"","sum_foreign":""},"56":{"sum_foreign_comment":"","sum":"","sum_comment":"","sum_unclear":false,"sum_foreign":""},"57":{"sum_foreign_comment":"","sum":"","sum_comment":"","sum_comment_hidden":false,"sum_unclear":false,"sum_foreign":""},"58":{"sum_foreign_comment":"","sum":"","sum_comment":"","sum_unclear":false,"sum_foreign":""},"59":{"sum_foreign_comment":"","sum":"","sum_comment":"","sum_foreign":""},"60":{"sum_foreign_comment":"","sum_foreign_hidden":false,"sum_comment":"","sum_hidden":false,"sum":"","sum_foreign":""},"61":{"sum_foreign_comment":"","sum":"","sum_comment":"","sum_foreign":""},"62":{"sum_foreign_comment":"","sum":"235","sum_comment":"","sum_unclear":false,"sum_foreign":""},"63":{"sum_foreign_comment":"","sum":"","sum_comment":"","sum_hidden":false,"sum_unclear":false,"sum_foreign":""},"64":{"sum_foreign_comment":"","sum":"","sum_hidden":false,"sum_comment":"","sum_foreign":""}},"ft_src":"235\nсуддя вінницького міського суду вінницької області\nВінницька область\nЗагальний місцевий суд\nЮлія\nМедяний В. М\nПодружжя\nМедяна В. В\nДитина\nВалеріївна\nМедяна\nМедяна Юлія Валеріївна\nМедяна Юлія Валеріївна\nЮлія Валеріївна Медяна\nЮлія Медяна\nМедяна Юлія Валеріївна\nВАЗ 21144\n1596 куб. см.\n2007\n2008\nToyota Rav 4\n1998 куб. см.\n2008\nпричіп легковий\nпричіп до л/а модель ПП-2.8 , марка ПР\n95.7\n95.7\n2014\n256823\n198680\n339674\n198680\n82851\n1596 куб. см.\n2007\nВАЗ 21144\n1998 куб. см.\n2008\nToyota Rav 4\nпричіп до л/а модель ПП-2.8 , марка ПР\n2008\nпричіп легковий\n95.7\n95.7\nПодружжя\nМедяний В. М\nДитина\nМедяна В. В\nМедяна Юлія Валеріївна\nЮлія Валеріївна Медяна\nЮлія Медяна\nМедяна Юлія Валеріївна\nЮлія\nМедяна Юлія Валеріївна\nМедяна\nВінницька область\nЗагальний місцевий суд\nсуддя вінницького міського суду вінницької області\nВалеріївна\n235\n256823\n198680\n82851\n198680\n339674\n2014\n235\nМедяний В. М\nПодружжя\nМедяна В. В\nДитина\nВалеріївна\nМедяна\nМедяна Юлія Валеріївна\nЮлія Валеріївна Медяна\nЮлія Медяна\nМедяна Юлія Валеріївна\nВінницька область\nсуддя вінницького міського суду вінницької області\nЗагальний місцевий суд\nМедяна Юлія Валеріївна\nЮлія\n2008\nпричіп до л/а модель ПП-2.8 , марка ПР\nпричіп легковий\nВАЗ 21144\n1596 куб. см.\n2007\n2008\n1998 куб. см.\nToyota Rav 4\n82851\n198680\n339674\n198680\n256823\n95.7\n95.7\n2014","general":{"inn":"","name":"Юлія","patronymic_unclear":false,"family":[{"inn":"","inn_hidden":true,"relations_unclear":false,"relations_hidden":false,"relations_other":"","relations":"Подружжя","name_hidden":false,"family_name":"Медяний В. М","name_unclear":false},{"inn":"","relations":"Дитина","relations_other":"","inn_hidden":false,"family_name":"Медяна В. В","name_hidden":false,"name_unclear":false}],"patronymic":"Валеріївна","inn_hidden":true,"family_raw":"","inn_unclear":false,"post":{"post_unclear":false,"region_unclear":false,"post":"суддя вінницького міського суду вінницької області","office":"Загальний місцевий суд","region":"Вінницька область","post_hidden":false,"office_hidden":false,"region_hidden":false},"last_name_unclear":false,"full_name":"Медяна Юлія Валеріївна","addresses":[{"place_address":"","place_district_hidden":true,"place_city_type":"","place_city_hidden":true,"place_address_unclear":false,"place_city_type_hidden":true,"place_hidden":true,"place":"","place_district":"","place_address_hidden":true,"place_city":"","place_district_unclear":false}],"last_name":"Медяна","patronymic_hidden":false,"full_name_suggest":{"output":"Медяна Юлія Валеріївна","input":["Медяна Юлія Валеріївна","Юлія Валеріївна Медяна","Юлія Медяна"]},"name_unclear":false},"source":"VULYK","estate":{"25":[{"region_unclear":false,"space_hidden":false,"costs":"","costs_comment":"","address_hidden":false,"region_hidden":true,"space_comment":"","space_unclear":false,"space":"95.7","address":"","costs_comment_unclear":false,"costs_unclear":false,"region":"","address_unclear":false,"costs_rent_comment":"","space_comment_unclear":false,"space_units":"м²","costs_rent":""}],"31":[{"space_unclear":false,"address_hidden":false,"region_hidden":true,"space_comment":"","space_hidden":false,"space":"95.7","address":"","region":"","costs_property":"","costs_rent_comment":"","space_comment_unclear":false,"space_units":"м²","costs_property_comment":"","costs_rent":""}]},"intro":{"declaration_year":"2014","isnotdeclaration":"","declaration_year_hidden":false}}