{"income":{"5":{"family_comment":"","value":"341017","family":"","comment":""},"6":{"family_comment":"","value":"265411","family":"","comment":"","family_comment_unclear":false},"7":{"value":"","comment_hidden":false,"family_comment":"","source_name":"","family":"","comment":"","source_name_hidden":false},"8":{"family_comment":"","value":"","family":"","comment":""},"9":{"family_comment":"","value":"16217","family":"","comment":""},"10":{"value":"","value_unclear":false,"value_hidden":false,"family_comment":"","family":"","comment":""},"11":{"family_comment":"","value":"","family":"","comment":""},"12":{"family_comment":"","value":"","family":"","comment":""},"13":{"family_comment":"","value":"","family":"","comment":""},"14":{"family_comment":"","value":"","family":"","comment":""},"15":{"family_comment":"","value":"","family":"","comment":""},"16":{"family_comment":"","value":"","family":"","comment":""},"17":{"family_comment":"","value":"","family":"","comment":""},"18":{"family_comment":"","value":"","family":"","comment":""},"19":{"family_comment":"","value":"","family":"","comment":""},"20":{"family_comment":"","value":"59389","comment_unclear":false,"family":"","comment":"пенсія"}},"vehicle":{"35":[{"brand_info":"NF-193, об'єм 1799, потужність 90 кВт","sum_rent_comment":"","brand":"Chevrolet Lacetti","sum_comment":"","brand_unclear":false,"year":"2006","brand_info_unclear":false,"year_unclear":false,"sum":"","sum_rent":""}]},"id":"vulyk_86_51","banks":{"45":[{"sum_foreign_comment":"","sum_units":"UAH","sum_comment":"","sum_foreign_units":"UAH","sum_comment_hidden":false,"sum_unclear":false,"sum":"144440","sum_foreign":""}],"47":[{"sum_foreign_comment":"","sum_units":"UAH","sum_comment":"","sum_foreign_units":"UAH","sum":"16494","sum_foreign":""}]},"declaration":{"additional_info_text":"","notfull_lostpages":"","date":"2015-03-18T00:00:00","notfull":"","additional_info":"","url":"http://static.declarations.com.ua/declarations/chosen_ones/judges_batch/2754_soroka_halyna_pylypivna.pdf"},"liabilities":{"54":{"sum_foreign_comment":"","sum":"","sum_comment":"","sum_unclear":false,"sum_foreign":""},"55":{"sum_foreign_comment":"","sum":"","sum_comment":"","sum_foreign":""},"56":{"sum_foreign_comment":"","sum":"10176","sum_hidden":false,"sum_comment":"","sum_foreign":""},"57":{"sum_foreign_comment":"","sum":"","sum_comment":"","sum_unclear":false,"sum_foreign":""},"58":{"sum_foreign_comment":"","sum":"","sum_comment":"","sum_unclear":false,"sum_foreign":""},"59":{"sum_foreign_comment":"","sum":"","sum_comment":"","sum_foreign":""},"60":{"sum_foreign_comment":"","sum_comment_hidden":false,"sum":"","sum_comment":"","sum_foreign":""},"61":{"sum_foreign_comment":"","sum":"","sum_comment":"","sum_foreign":""},"62":{"sum_foreign_comment":"","sum":"","sum_comment":"","sum_foreign":""},"63":{"sum_foreign_comment":"","sum":"","sum_comment":"","sum_foreign":""},"64":{"sum_foreign_comment":"","sum":"","sum_comment":"","sum_foreign":""}},"ft_src":"10176\nсуддя апеляційного суду донецької області\nДонецька область\nЗагальний апеляційний суд\nГалина\nПилипівна\nСорока Галина Пилипівна\nГалина Пилипівна Сорока\nГалина Сорока\nСорока Галина Пилипівна\nСорока Галина Пилипівна\nСорока\nNF-193, об'єм 1799, потужність 90 кВт\nChevrolet Lacetti\n2006\n600\n28\n20.5\n65.14\n16494\n144440\n2014\nNF-193, об'єм 1799, потужність 90 кВт\n2006\nChevrolet Lacetti\n2014\nСорока Галина Пилипівна\nГалина Пилипівна Сорока\nГалина Сорока\nСорока Галина Пилипівна\nСорока Галина Пилипівна\nГалина\nСорока\nЗагальний апеляційний суд\nДонецька область\nсуддя апеляційного суду донецької області\nПилипівна\n10176\n265411\n59389\nпенсія\n341017\n16217\n600\n28\n20.5\n65.14\n144440\n16494\n10176\n265411\n16217\n341017\nпенсія\n59389\nСорока Галина Пилипівна\nГалина Пилипівна Сорока\nГалина Сорока\nСорока Галина Пилипівна\nПилипівна\nСорока\nГалина\nДонецька область\nЗагальний апеляційний суд\nсуддя апеляційного суду донецької області\nСорока Галина Пилипівна\n2006\nNF-193, об'єм 1799, потужність 90 кВт\nChevrolet Lacetti\n16217\nпенсія\n59389\n341017\n265411\n20.5\n65.14\n600\n28\n16494\n144440\n2014","general":{"inn":"","name":"Галина","patronymic_unclear":false,"inn_unclear":false,"patronymic":"Пилипівна","inn_hidden":true,"family_raw":"","last_name":"Сорока","post":{"post_unclear":false,"post":"суддя апеляційного суду донецької області","candidate":"","office_hidden":false,"region":"Донецька область","office":"Загальний апеляційний суд","office_unclear":false,"region_hidden":false},"full_name":"Сорока Галина Пилипівна","addresses":[{"place_district":"","place_unclear":false,"place_city":"","place_city_type_hidden":false,"place_district_hidden":false,"place_city_type":"","place_city_hidden":false,"place_address_hidden":false,"place_address":"","place_hidden":true,"place":""}],"full_name_suggest":{"output":"Сорока Галина Пилипівна","input":["Сорока Галина Пилипівна","Галина Пилипівна Сорока","Галина Сорока"]}},"source":"VULYK","estate":{"23":[{"costs":"","costs_comment":"","address_hidden":false,"region_hidden":true,"space_comment":"","space":"600","address":"","region":"","address_unclear":false,"costs_rent_comment":"","space_units":"м²","costs_rent":""}],"25":[{"space_unclear":false,"costs":"","costs_comment":"","address_hidden":false,"region_hidden":true,"space_comment":"","space_hidden":false,"space":"20.5","address":"","region":"","address_unclear":false,"costs_rent_comment":"","space_units":"м²","costs_rent":""},{"costs_rent":"","region":"","costs":"","costs_rent_comment":"","costs_comment":"","region_hidden":false,"space_comment":"","space_units":"м²","space":"65.14","address":""}],"27":[{"costs_rent":"","region":"","costs":"","costs_rent_comment":"","costs_comment":"","address_hidden":false,"region_hidden":true,"space_comment":"","space_units":"м²","space":"28","address":""}]},"intro":{"declaration_year":"2014","declaration_year_unclear":false}}