{"income":{"5":{"value":"218630.71","family_unclear":false,"family_hidden":false,"family_comment":"","family":"40904.19","comment":""},"6":{"value":"217855.11","family_comment":"","value_unclear":false,"family_hidden":false,"family_unclear":false,"family":"","comment":""},"7":{"value":"","family_comment":"","source_name":"","family":"","comment":"","source_name_hidden":false},"8":{"family_comment":"","value":"","family":"","comment":""},"9":{"family_comment":"","value":"","family":"","comment":""},"10":{"family_comment":"","value":"","family":"","comment":""},"11":{"family_comment":"","value":"","family":"","comment":""},"12":{"family_comment":"","value":"","family":"","comment":""},"13":{"family_comment":"","value":"","family":"","comment":""},"14":{"family_comment":"","value":"","family":"","comment":""},"15":{"family_comment":"","value":"","family":"","comment":""},"16":{"family_comment":"","value":"","family":"","comment":"","value_hidden":false},"17":{"family_comment":"","value":"","family_hidden":false,"comment":"","family":""},"18":{"family_comment":"","value":"","family":"","comment":""},"19":{"family_comment":"","value":"","family":"","comment":""},"20":{"value":"775.6","family_comment":"","value_unclear":false,"family_hidden":false,"family_unclear":false,"family":"40904.19","comment":""}},"id":"vulyk_16_32","banks":{"45":[{"sum_foreign_comment":"","sum_units":"UAH","sum_comment":"","sum_comment_unclear":false,"sum_foreign_units":"UAH","sum_comment_hidden":false,"sum_unclear":false,"sum":"","sum_foreign":""},{"sum_foreign_comment":"","sum_units":"","sum_comment":"","sum_foreign_units":"","sum_comment_hidden":false,"sum":"","sum_foreign":""},{"sum_foreign_comment":"","sum_units":"","sum_comment":"","sum_foreign_units":"","sum":"","sum_unclear":false,"sum_foreign":""}],"46":[{"sum_foreign_comment":"","sum_units":"UAH","sum_comment":"","sum_foreign_units":"UAH","sum_comment_hidden":false,"sum_unclear":false,"sum":"","sum_foreign":""}],"47":[{"sum_foreign_comment":"","sum_units":"UAH","sum_comment":"","sum_comment_unclear":false,"sum_foreign_units":"UAH","sum":"","sum_foreign":""}],"48":[{"sum_foreign_comment":"","sum_units":"UAH","sum_comment":"","sum_foreign_units":"UAH","sum":"","sum_foreign":""}],"49":[{"sum_foreign_comment":"","sum_units":"UAH","sum_comment":"","sum_foreign_units":"UAH","sum":"","sum_foreign":""}],"50":[{"sum_foreign_comment":"","sum_units":"UAH","sum_comment":"","sum_foreign_units":"UAH","sum":"","sum_foreign":""}],"51":[{"sum_foreign_comment":"","sum_units":"UAH","sum_comment":"","sum_hidden":false,"sum_foreign_units":"UAH","sum_comment_hidden":false,"sum_unclear":false,"sum":"","sum_foreign":""},{"sum_foreign_comment":"","sum_units":"","sum_comment":"","sum_foreign_units":"","sum_comment_hidden":false,"sum":"","sum_foreign":""}],"52":[{"sum_foreign_comment":"","sum_units":"UAH","sum_comment":"","sum_foreign_units":"UAH","sum":"","sum_foreign":""},{"sum_foreign_comment":"","sum_units":"","sum_comment":"","sum_foreign_units":"","sum":"","sum_foreign":""}],"53":[{"sum_foreign_comment":"","sum_units":"UAH","sum_comment":"","sum_hidden":false,"sum_foreign_units":"UAH","sum_comment_hidden":false,"sum":"","sum_foreign":""}]},"declaration":{"additional_info_text":"паспорт ВК 583199 паспорт чоловіка ВЕ 293229 паспорт дочки ВК 950495","notfull_lostpages":"","date":"2015-03-25T00:00:00","notfull":"","additional_info":"1","url":"http://static.declarations.com.ua/declarations/chosen_ones/mega_batch/arynycheva_svitlana_anatoliiovna.pdf"},"liabilities":{"54":{"sum_foreign_comment":"","sum":"","sum_comment":"","sum_comment_unclear":false,"sum_hidden":false,"sum_comment_hidden":false,"sum_unclear":false,"sum_foreign":""},"55":{"sum_foreign_comment":"","sum":"","sum_comment":"","sum_foreign":""},"56":{"sum_foreign_comment":"","sum":"","sum_comment":"","sum_unclear":false,"sum_foreign":""},"57":{"sum_foreign_comment":"","sum":"","sum_comment":"","sum_comment_unclear":false,"sum_hidden":false,"sum_comment_hidden":false,"sum_unclear":false,"sum_foreign":""},"58":{"sum_foreign_comment":"","sum":"","sum_comment":"","sum_comment_unclear":false,"sum_hidden":false,"sum_comment_hidden":false,"sum_foreign":""},"59":{"sum_foreign_comment":"","sum":"","sum_comment":"","sum_foreign":""},"60":{"sum_foreign_comment":"","sum":"","sum_comment":"","sum_comment_unclear":false,"sum_hidden":false,"sum_comment_hidden":false,"sum_foreign":""},"61":{"sum_foreign_comment":"","sum_comment_hidden":false,"sum":"","sum_comment":"","sum_foreign":""},"62":{"sum_foreign_comment":"","sum":"","sum_comment":"","sum_foreign":""},"63":{"sum_foreign_comment":"","sum_comment_hidden":false,"sum":"","sum_comment":"","sum_foreign":""},"64":{"sum_foreign_comment":"","sum_comment_hidden":false,"sum":"","sum_comment":"","sum_foreign":""}},"ft_src":"паспорт ВК 583199 паспорт чоловіка ВЕ 293229 паспорт дочки ВК 950495\n1\n2755020520\nАриничева Світлана Анатоліївна\nголова - суддя єнакієвського міського суду донецької області\nДонецька область\nЗагальний місцевий суд\nСвітлана\n2497814756\nАриничев І. О. 21. 05. 1968\nПодружжя\n3536903588\nПолякова А. В. 01. 11. 1996\nДитина\nАриничева Світлана Анатоліївна\nСвітлана Анатоліївна Ариничева\nСвітлана Ариничева\nАриничева Світлана Анатоліївна\nАриничева\nАнатоліївна\n775.6\n40904.19\n218630.71\n40904.19\n217855.11\nм. Харцизськ, вул. Краснознаменська, б. 148\nДонецька область\n34\nм. Єнакієве вул. Комуністична 41-А\n48.8\nДонецька область\n1\nпаспорт ВК 583199 паспорт чоловіка ВЕ 293229 паспорт дочки ВК 950495\n2014\n217855.11\n40904.19\n218630.71\n40904.19\n775.6\nпаспорт ВК 583199 паспорт чоловіка ВЕ 293229 паспорт дочки ВК 950495\n1\n2014\nАриничева\n2755020520\nАриничева Світлана Анатоліївна\nСвітлана Анатоліївна Ариничева\nСвітлана Ариничева\nАриничева Світлана Анатоліївна\nСвітлана\nАнатоліївна\nАриничева Світлана Анатоліївна\nголова - суддя єнакієвського міського суду донецької області\nДонецька область\nЗагальний місцевий суд\nПодружжя\nАриничев І. О. 21. 05. 1968\n2497814756\nДитина\nПолякова А. В. 01. 11. 1996\n3536903588\n217855.11\n40904.19\n775.6\n218630.71\n40904.19\n34\nДонецька область\nм. Харцизськ, вул. Краснознаменська, б. 148\n48.8\nм. Єнакієве вул. Комуністична 41-А\nДонецька область\n2497814756\nАриничев І. О. 21. 05. 1968\nПодружжя\n3536903588\nПолякова А. В. 01. 11. 1996\nДитина\n2755020520\nАнатоліївна\nАриничева\nголова - суддя єнакієвського міського суду донецької області\nДонецька область\nЗагальний місцевий суд\nАриничева Світлана Анатоліївна\nАриничева Світлана Анатоліївна\nСвітлана Анатоліївна Ариничева\nСвітлана Ариничева\nАриничева Світлана Анатоліївна\nСвітлана\nм. Харцизськ, вул. Краснознаменська, б. 148\nДонецька область\n34\nм. Єнакієве вул. Комуністична 41-А\nДонецька область\n48.8\n2014","general":{"inn":"2755020520","inn_hidden":false,"last_name":"Ариничева","post":{"post_unclear":false,"post_hidden":false,"post":"голова - суддя єнакієвського міського суду донецької області","region":"Донецька область","office":"Загальний місцевий суд"},"name":"Світлана","full_name":"Ариничева Світлана Анатоліївна","family_raw":"","addresses":[{"place_district":"","place_city_hidden":true,"place_city":"","place_city_type_hidden":true,"place_district_hidden":true,"place_city_type":"","place_address_hidden":true,"place_address":"","place_hidden":true,"place":""}],"family":[{"inn":"2497814756","inn_hidden":false,"relations_hidden":false,"family_name":"Ариничев І. О. 21. 05. 1968","relations_other":"","relations":"Подружжя","name_hidden":false,"name_unclear":false},{"inn":"3536903588","relations":"Дитина","inn_unclear":true,"family_name":"Полякова А. В. 01. 11. 1996","inn_hidden":false,"relations_other":"","name_hidden":false,"name_unclear":false}],"full_name_suggest":{"output":"Ариничева Світлана Анатоліївна","input":["Ариничева Світлана Анатоліївна","Світлана Анатоліївна Ариничева","Світлана Ариничева"]},"patronymic":"Анатоліївна"},"source":"VULYK","estate":{"23":[{"space_unclear":false,"costs":"","costs_comment":"","address_hidden":false,"region_hidden":false,"space_comment":"","space":"","address":"","region":"","costs_rent_comment":"","space_units":"м²","space_units_unclear":false,"costs_rent":""},{"costs_rent":"","region":"","costs":"","costs_rent_comment":"","costs_comment":"","address_hidden":false,"region_hidden":false,"space_comment":"","space_units":"","space":"","address":""},{"costs_rent":"","region":"","costs":"","costs_rent_comment":"","costs_comment":"","address_hidden":false,"region_hidden":false,"space_comment":"","space_units":"","space":"","address":""},{"costs_rent":"","region":"","costs":"","costs_rent_comment":"","costs_comment":"","space_comment":"","space_units":"","space":"","address":""}],"25":[{"space_unclear":false,"costs":"","costs_comment":"","address_hidden":false,"region_hidden":false,"space_comment":"","space":"48.8","address":"м. Єнакієве вул. Комуністична 41-А","region":"Донецька область","costs_rent_comment":"","space_comment_hidden":false,"space_units":"м²","costs_rent":""}],"30":[{"space_hidden":false,"address_hidden":false,"region_hidden":false,"space_comment":"","space":"34","address":"м. Харцизськ, вул. Краснознаменська, б. 148","region":"Донецька область","costs_property":"","costs_rent_comment":"","space_units":"м²","costs_property_comment":"","costs_rent":""}]},"intro":{"declaration_year":"2014","isnotdeclaration":"","declaration_year_unclear":false}}