{"income":{"5":{"value":"327412.77","family_comment":"","value_unclear":false,"comment_hidden":false,"family_hidden":false,"value_hidden":false,"family_unclear":false,"family_comment_hidden":false,"comment":"","family":"7405.85"},"6":{"value":"236619.93","family_comment":"","value_unclear":false,"family_hidden":false,"family_unclear":false,"family":"","comment":""},"7":{"source_name_unclear":false,"value":"","family_hidden":false,"family_comment":"","source_name":"","family":"","comment":"","source_name_hidden":false},"8":{"family_comment":"","value":"","family":"","comment":""},"9":{"value":"","value_unclear":false,"family_hidden":false,"family_comment":"","family":"","comment":""},"10":{"value":"","value_unclear":false,"family_hidden":false,"value_hidden":false,"family_comment":"","comment_unclear":false,"comment":"","family":""},"11":{"family_comment":"","value":"","family":"","comment":""},"12":{"family_comment":"","value":"","family":"","comment":""},"13":{"family_comment":"","value":"","family":"","comment":""},"14":{"family_comment":"","value":"","family":"","comment":""},"15":{"family_comment":"","value":"","family_hidden":false,"comment":"","family":""},"16":{"value":"","value_unclear":false,"family_hidden":false,"family_comment":"","family":"","comment":""},"17":{"family_comment":"","value":"","family_hidden":false,"comment":"","family":""},"18":{"family_comment":"","value":"","value_unclear":false,"family":"","comment":""},"19":{"family_comment":"","value":"","family":"","comment":""},"20":{"value":"90792.84","family_comment":"стипендія","value_unclear":true,"family_hidden":false,"family_unclear":true,"comment_unclear":false,"comment":"","family":"7405.85"}},"vehicle":{"40":[{"year_hidden":false,"brand_info":"2000 куб. см.","sum_rent_comment":"","year":"2010","brand_info_hidden":false,"brand_info_unclear":false,"year_unclear":false,"sum_rent":"","sum":"","brand":"Subaru Forester","sum_comment":"","brand_unclear":false,"brand_hidden":false},{"brand_info":"1900 куб. см.","sum_rent_comment":"","brand":"Skoda","sum_comment":"","year":"2002","sum":"","sum_rent":""}]},"id":"vulyk_72_134","declaration":{"additional_info_text":"","notfull_lostpages":"","date":"2015-03-30T00:00:00","notfull":"","additional_info":"","url":"http://static.declarations.com.ua/declarations/chosen_ones/epic_batch/didyk_mykola_volodymyrovych.pdf"},"liabilities":{"54":{"sum_foreign_comment":"","sum":"","sum_comment":"","sum_comment_hidden":false,"sum_unclear":false,"sum_foreign":""},"55":{"sum_foreign_comment":"","sum":"","sum_comment":"","sum_foreign":""},"56":{"sum_foreign_comment":"","sum":"","sum_hidden":false,"sum_comment":"","sum_foreign":""},"57":{"sum_foreign_comment":"","sum":"","sum_comment":"","sum_comment_unclear":false,"sum_hidden":false,"sum_comment_hidden":false,"sum_unclear":false,"sum_foreign":""},"58":{"sum_foreign_comment":"","sum":"","sum_comment":"","sum_comment_unclear":false,"sum_hidden":false,"sum_comment_hidden":false,"sum_unclear":false,"sum_foreign":""},"59":{"sum_foreign_comment":"","sum_foreign_hidden":false,"sum_comment":"","sum_foreign_unclear":false,"sum_comment_hidden":false,"sum":"","sum_foreign":""},"60":{"sum_foreign_comment":"","sum_foreign_hidden":false,"sum_comment":"","sum_hidden":false,"sum":"","sum_foreign":""},"61":{"sum_foreign_comment":"","sum_foreign_hidden":false,"sum_comment":"","sum_hidden":false,"sum":"","sum_foreign":""},"62":{"sum_foreign_comment":"","sum_foreign_hidden":false,"sum_comment":"","sum_hidden":false,"sum":"","sum_foreign":""},"63":{"sum_foreign_comment":"","sum_foreign_hidden":false,"sum_comment":"","sum_comment_unclear":false,"sum_hidden":false,"sum_comment_hidden":false,"sum_unclear":false,"sum":"","sum_foreign":""},"64":{"sum_foreign_comment":"","sum_foreign_hidden":false,"sum_comment":"","sum_hidden":false,"sum":"","sum_foreign":""}},"ft_src":"Київ\nм. Київ\nсуддя голосіївського районного суду міста києва\nм. Київ\nЗагальний місцевий суд\nМикола\nДідик Н. А\nПодружжя\nДідик Ю. М\nДитина\nДідик І. М\nДитина\nВолодимирович\nДідик\nДідик Микола Володимирович\nДідик Микола Володимирович\nМикола Володимирович Дідик\nМикола Дідик\nДідик Микола Володимирович\n2000 куб. см.\nSubaru Forester\n2010\n1900 куб. см.\n2002\nSkoda\nХмельницька область\nм. Хмельницький\n21\nХмельницька область\nЧемеровецький р-н, с. Чорна\n0.25\nм. Київ\n97.6\n106.5\nм. Хмельницький\nХмельницька область\n2014\n236619.93\n7405.85\n327412.77\nстипендія\n7405.85\n90792.84\n2000 куб. см.\nSubaru Forester\n2010\n1900 куб. см.\nSkoda\n2002\n21\nм. Хмельницький\nХмельницька область\n0.25\nЧемеровецький р-н, с. Чорна\nХмельницька область\nм. Київ\n97.6\nм. Хмельницький\n106.5\nХмельницька область\nПодружжя\nДідик Н. А\nДитина\nДідик Ю. М\nДитина\nДідик І. М\nДідик Микола Володимирович\nМикола Володимирович Дідик\nМикола Дідик\nДідик Микола Володимирович\nМикола\nДідик Микола Володимирович\nДідик\nм. Київ\nЗагальний місцевий суд\nсуддя голосіївського районного суду міста києва\nВолодимирович\nКиїв\nм. Київ\n236619.93\n90792.84\nстипендія\n7405.85\n327412.77\n7405.85\n2014\nДідик Н. А\nПодружжя\nДідик Ю. М\nДитина\nДідик І. М\nДитина\nВолодимирович\nДідик\nДідик Микола Володимирович\nМикола Володимирович Дідик\nМикола Дідик\nДідик Микола Володимирович\nм. Київ\nКиїв\nм. Київ\nЗагальний місцевий суд\nсуддя голосіївського районного суду міста києва\nДідик Микола Володимирович\nМикола\nSubaru Forester\n2000 куб. см.\n2010\nSkoda\n1900 куб. см.\n2002\nстипендія\n90792.84\n7405.85\n327412.77\n7405.85\n236619.93\nм. Київ\n97.6\nХмельницька область\nм. Хмельницький\n21\nЧемеровецький р-н, с. Чорна\nХмельницька область\n0.25\n106.5\nм. Хмельницький\nХмельницька область\n2014","general":{"inn":"","name":"Микола","patronymic_unclear":false,"family":[{"inn":"","inn_hidden":true,"relations_unclear":false,"relations_hidden":false,"relations_other":"","relations":"Подружжя","name_hidden":false,"inn_unclear":false,"family_name":"Дідик Н. А","name_unclear":false},{"inn":"","inn_hidden":false,"relations_hidden":false,"family_name":"Дідик Ю. М","relations_other":"","relations":"Дитина","name_hidden":false,"name_unclear":false},{"inn":"","inn_hidden":false,"relations_hidden":false,"family_name":"Дідик І. М","relations_other":"","relations":"Дитина","name_hidden":false,"name_unclear":false}],"patronymic":"Володимирович","inn_hidden":true,"family_raw":"","inn_unclear":false,"post":{"post_unclear":false,"region_unclear":false,"post":"суддя голосіївського районного суду міста києва","candidate":"","office_hidden":false,"region":"м. Київ","post_hidden":false,"office":"Загальний місцевий суд","office_unclear":false,"region_hidden":false},"last_name_unclear":false,"full_name":"Дідик Микола Володимирович","addresses":[{"place_city_type_hidden":false,"place_district_hidden":false,"place_city_type":"Місто","place_city_hidden":false,"place_address_unclear":false,"place_address":"","place":"м. Київ","place_district":"","place_unclear":false,"place_city":"Київ","place_city_unclear":false,"place_hidden":true,"place_address_hidden":true,"place_district_unclear":false}],"last_name":"Дідик","patronymic_hidden":false,"full_name_suggest":{"output":"Дідик Микола Володимирович","input":["Дідик Микола Володимирович","Микола Володимирович Дідик","Микола Дідик"]},"name_unclear":false},"source":"VULYK","estate":{"23":[{"space_hidden":false,"costs":"","costs_rent_unclear":false,"costs_comment":"","costs_hidden":false,"address_hidden":false,"region_hidden":false,"space_comment":"","space_unclear":false,"space":"21","address":"м. Хмельницький","region":"Хмельницька область","address_unclear":false,"costs_rent_comment":"","costs_rent_hidden":false,"space_units":"м²","space_units_hidden":false,"costs_rent":""},{"costs":"","costs_comment":"","address_hidden":false,"region_hidden":false,"space_comment":"","space":"0.25","address":"Чемеровецький р-н, с. Чорна","region":"Хмельницька область","address_unclear":false,"costs_rent_comment":"","space_units":"га","costs_rent":""}],"25":[{"space_unclear":false,"costs":"","costs_rent_unclear":false,"costs_comment":"","costs_hidden":false,"space_hidden":false,"costs_comment_unclear":false,"costs_rent_comment_unclear":false,"region":"Хмельницька область","space_comment_hidden":false,"space_comment_unclear":false,"costs_rent_comment_hidden":false,"costs_rent":"","costs_comment_hidden":false,"address_hidden":false,"region_hidden":false,"space_comment":"","space":"106.5","address":"м. Хмельницький","address_unclear":false,"costs_rent_comment":"","costs_rent_hidden":false,"space_units":"м²"}],"31":[{"space_unclear":false,"address_hidden":false,"region_hidden":false,"space_comment":"","space_units_hidden":false,"space_hidden":false,"space":"97.6","address":"","region":"м. Київ","address_unclear":false,"costs_rent_comment":"","costs_property":"","space_units":"м²","costs_property_comment":"","costs_rent":""}]},"intro":{"declaration_year":"2014","isnotdeclaration":"","declaration_year_unclear":false}}