{"income":{"5":{"value":"263316","family_comment":"","value_unclear":false,"family_unclear":false,"family":"14124","comment":""},"6":{"family_comment":"","value":"258271","family":"","comment":""},"7":{"source_name_unclear":false,"value":"1250","family_hidden":false,"value_hidden":false,"family_comment":"","source_name":"Чернівецька філія Приватного акціонерного товариства 'Вищий навчальний заклад 'Міжрегіональна академія управління персоналом''","family":"","comment":"","source_name_hidden":false},"8":{"value":"","family_hidden":false,"value_hidden":false,"family_comment":"","family":"","comment":""},"9":{"value":"","comment_hidden":false,"family_hidden":false,"value_hidden":false,"family_comment":"","family":"","comment":""},"10":{"family_comment":"","value":"","family":"","comment":""},"11":{"value":"","family_hidden":false,"value_hidden":false,"family_comment":"","family":"","comment":""},"12":{"family_comment":"","value":"","family":"","comment":"","value_hidden":false},"13":{"family_comment":"","value":"","family":"","comment":"","value_hidden":false},"14":{"family_comment":"","value":"","family":"","comment":"","value_hidden":false},"15":{"family_comment":"","value":"","family":"","comment":"","value_hidden":false},"16":{"family_comment":"","value":"","family":"","comment":"","value_hidden":false},"17":{"family_comment":"","value":"","family":"","comment":"","value_hidden":false},"18":{"family_comment":"","value":"","family":"","comment":"","value_hidden":false},"19":{"family_comment":"","value":"","family":"","comment":"","value_hidden":false},"20":{"value":"3795","family_comment":"","value_unclear":false,"family":"14124","family_unclear":false,"comment_unclear":false,"comment":"","family_comment_unclear":false}},"id":"vulyk_33_131","banks":{"45":[{"sum_foreign_comment":"","sum_units":"UAH","sum_comment":"","sum_hidden":false,"sum_foreign_units":"UAH","sum_comment_hidden":false,"sum":"","sum_foreign":""},{"sum_foreign_comment":"","sum_units":"","sum_comment":"","sum_foreign_units":"","sum":"","sum_foreign":""},{"sum_foreign_comment":"","sum_units":"","sum_comment":"","sum_foreign_units":"","sum":"","sum_foreign":""}],"46":[{"sum_foreign_comment":"","sum_units":"UAH","sum_comment":"","sum_foreign_units":"UAH","sum_comment_hidden":false,"sum":"","sum_foreign":""}],"47":[{"sum_foreign_comment":"","sum_units":"UAH","sum_comment":"","sum_comment_unclear":false,"sum_foreign_units":"UAH","sum":"","sum_foreign":""}],"48":[{"sum_foreign_comment":"","sum_units":"UAH","sum_comment":"","sum_foreign_units":"UAH","sum":"","sum_foreign":""}],"49":[{"sum_foreign_comment":"","sum_units":"UAH","sum_comment":"","sum_foreign_units":"UAH","sum":"","sum_foreign":""}],"50":[{"sum_foreign_comment":"","sum_units":"UAH","sum_comment":"","sum_foreign_units":"UAH","sum":"","sum_foreign":""}],"51":[{"sum_foreign_comment":"","sum_units":"UAH","sum_comment":"","sum_hidden":false,"sum_foreign_units":"UAH","sum_comment_hidden":false,"sum":"","sum_foreign":""},{"sum_foreign_comment":"","sum_units":"","sum_comment":"","sum_foreign_units":"","sum":"","sum_foreign":""},{"sum_foreign_comment":"","sum":"","sum_comment":"","sum_foreign":""}],"52":[{"sum_foreign_comment":"","sum_units":"UAH","sum_comment":"","sum_foreign_units":"UAH","sum_comment_hidden":false,"sum":"","sum_foreign":""}],"53":[{"sum_foreign_comment":"","sum_units":"UAH","sum_comment":"","sum_comment_unclear":false,"sum_foreign_units":"UAH","sum":"","sum_foreign":""}]},"declaration":{"additional_info_text":"","notfull_lostpages":"","date":"2015-03-26T00:00:00","notfull":"","additional_info":"","url":"http://static.declarations.com.ua/declarations/chosen_ones/mega_batch/marchuk_valerii_trokhymovych.pdf"},"liabilities":{"54":{"sum_foreign_comment":"","sum":"","sum_hidden":false,"sum_comment":"","sum_foreign":""},"55":{"sum_foreign_comment":"","sum":"","sum_comment":"","sum_foreign":""},"56":{"sum_foreign_comment":"","sum":"","sum_comment":"","sum_foreign":""},"57":{"sum_foreign_comment":"","sum_foreign_hidden":false,"sum_comment":"","sum_hidden":false,"sum_comment_hidden":false,"sum":"","sum_foreign":""},"58":{"sum_foreign_comment":"","sum_foreign_hidden":false,"sum_comment":"","sum_hidden":false,"sum_comment_hidden":false,"sum":"","sum_foreign":""},"59":{"sum_foreign_comment":"","sum":"","sum_comment":"","sum_unclear":false,"sum_foreign":""},"60":{"sum_foreign_comment":"","sum":"","sum_comment":"","sum_foreign":""},"61":{"sum_foreign_comment":"","sum":"","sum_comment":"","sum_foreign":""},"62":{"sum_foreign_comment":"","sum":"","sum_comment":"","sum_unclear":false,"sum_foreign":""},"63":{"sum_foreign_comment":"","sum":"","sum_comment":"","sum_foreign":""},"64":{"sum_foreign_comment":"","sum":"","sum_comment":"","sum_foreign":""}},"ft_src":"заступник голови апеляційного суду чернівецької області\nЧернівецька область\nЗагальний апеляційний суд\nМарчук Валерій Трохимович\nВалерій\nМарчук Валерій Трохимович\nВалерій Трохимович Марчук\nВалерій Марчук\nМарчук Валерій Трохимович\nМарчук\nТрохимович\n3795\n14124\n263316\n14124\n1250\nЧернівецька філія Приватного акціонерного товариства 'Вищий навчальний заклад 'Міжрегіональна академія управління персоналом''\n258271\n.0941\n278.9\n.0941\n278.9\n2014\n258271\nЧернівецька філія Приватного акціонерного товариства 'Вищий навчальний заклад 'Міжрегіональна академія управління персоналом''\n1250\n14124\n263316\n14124\n3795\n2014\nЗагальний апеляційний суд\nзаступник голови апеляційного суду чернівецької області\nЧернівецька область\nМарчук\nМарчук Валерій Трохимович\nВалерій Трохимович Марчук\nВалерій Марчук\nМарчук Валерій Трохимович\nВалерій\nМарчук Валерій Трохимович\nТрохимович\n1250\nЧернівецька філія Приватного акціонерного товариства 'Вищий навчальний заклад 'Міжрегіональна академія управління персоналом''\n258271\n3795\n14124\n263316\n14124\n.0941\n.0941\n278.9\n278.9\nМарчук\nТрохимович\nЧернівецька область\nзаступник голови апеляційного суду чернівецької області\nЗагальний апеляційний суд\nМарчук Валерій Трохимович\nМарчук Валерій Трохимович\nВалерій Трохимович Марчук\nВалерій Марчук\nМарчук Валерій Трохимович\nВалерій\n278.9\n.0941\n278.9\n.0941\n2014","general":{"inn":"","inn_hidden":false,"last_name":"Марчук","post":{"post_unclear":false,"post":"заступник голови апеляційного суду чернівецької області","candidate":"","office_hidden":false,"region":"Чернівецька область","post_hidden":false,"office":"Загальний апеляційний суд","region_hidden":false},"name":"Валерій","full_name":"Марчук Валерій Трохимович","family_raw":"","last_name_unclear":false,"full_name_suggest":{"output":"Марчук Валерій Трохимович","input":["Марчук Валерій Трохимович","Валерій Трохимович Марчук","Валерій Марчук"]},"patronymic":"Трохимович"},"source":"VULYK","estate":{"23":[{"space_unclear":false,"costs":"","costs_comment":"","address_hidden":false,"region_hidden":false,"space_comment":"","space_hidden":false,"space":".0941","address":"","region":"","space_units_unclear":false,"space_units":"га","costs_rent":"","costs_rent_comment":""},{"costs":"","costs_rent_unclear":false,"costs_comment":"","address_hidden":false,"region_hidden":false,"space_comment":"","space":"","address":"","region":"","address_unclear":false,"space_units_unclear":false,"space_units":"","costs_rent":"","costs_rent_comment":""},{"region_unclear":false,"costs":"","costs_comment":"","address_hidden":false,"region_hidden":false,"space_comment":"","space":"","address":"","region":"","address_unclear":false,"costs_rent_comment":"","space_units":"","costs_rent":""},{"costs_rent":"","region":"","costs":"","costs_rent_comment":"","costs_comment":"","address_hidden":false,"region_hidden":false,"space_comment":"","space_units":"","space":"","address":""},{"costs_rent":"","region":"","costs":"","costs_rent_comment":"","costs_comment":"","space_comment":"","space_units":"","space":"","address":""}],"24":[{"space_hidden":false,"costs":"","costs_comment":"","address_hidden":false,"region_hidden":false,"space_comment":"","space_unclear":false,"space":"278.9","address":"","region":"","costs_rent_comment":"","space_units":"м²","costs_rent":""}],"29":[{"region_unclear":false,"space_hidden":false,"address_hidden":false,"region_hidden":false,"space_comment":"","space_unclear":false,"space":".0941","address":"","region":"","costs_property":"","space_units_unclear":false,"space_units":"га","costs_property_comment":"","costs_rent":"","costs_rent_comment":""}],"30":[{"region_unclear":false,"space_hidden":false,"address_hidden":false,"region_hidden":false,"space_comment":"","space":"278.9","address":"","region":"","costs_property":"","costs_rent_comment":"","space_units":"м²","costs_property_comment":"","costs_rent":""}]},"intro":{"declaration_year":"2014"}}