{"income":{"5":{"value":"276604.52","family_unclear":false,"family_hidden":false,"family_comment":"","family":"","comment":""},"6":{"value":"276604.52","family_comment":"","value_unclear":false,"family_hidden":false,"family_unclear":false,"family":"","comment":""},"7":{"value":"","family_hidden":false,"value_hidden":false,"family_comment":"","source_name":"","family":"","comment":"","source_name_hidden":false},"8":{"family_comment":"","value":"","family":"","comment":""},"9":{"family_comment":"","value":"","family":"","comment":""},"10":{"family_comment":"","value":"","value_unclear":false,"family":"","comment":""},"11":{"family_comment":"","value":"","family":"","comment":""},"12":{"family_comment":"","value":"","family":"","comment":""},"13":{"family_comment":"","value":"","family":"","comment":""},"14":{"family_comment":"","value":"","family":"","comment":""},"15":{"family_comment":"","value":"","family":"","comment":""},"16":{"family_comment":"","value":"","family":"","comment":""},"17":{"family_comment":"","value":"","family":"","comment":""},"18":{"family_comment":"","value":"","family":"","comment":""},"19":{"family_comment":"","value":"","family":"","comment":""},"20":{"value":"","family_comment":"","value_unclear":false,"family_unclear":false,"comment_unclear":false,"comment":"","family":""}},"vehicle":{"40":[{"brand_info":"2 л","sum_rent_comment":"","brand":"Nissan Maxima","sum_comment":"","brand_unclear":false,"year":"1998","brand_info_unclear":false,"year_unclear":false,"sum":"","sum_rent":""}]},"id":"vulyk_74_89","declaration":{"additional_info_text":"","notfull_lostpages":"","date":"2014-03-17T00:00:00","notfull":"","additional_info":"","url":"http://static.declarations.com.ua/declarations/chosen_ones/judges_batch/1604_starostin_volodymyr_vadymovych.pdf"},"liabilities":{"54":{"sum_foreign_comment":"","sum":"","sum_comment":"","sum_comment_unclear":false,"sum_comment_hidden":false,"sum_foreign":""},"55":{"sum_foreign_comment":"","sum":"","sum_comment":"","sum_hidden":false,"sum_unclear":false,"sum_foreign":""},"56":{"sum_foreign_comment":"","sum":"","sum_comment":"","sum_hidden":false,"sum_unclear":false,"sum_foreign":""},"57":{"sum_foreign_comment":"","sum":"","sum_comment":"","sum_comment_unclear":false,"sum_comment_hidden":false,"sum_foreign":""},"58":{"sum_foreign_comment":"","sum_comment_hidden":false,"sum":"","sum_comment":"","sum_foreign":""},"59":{"sum_foreign_comment":"","sum":"","sum_comment":"","sum_foreign":""},"60":{"sum_foreign_comment":"","sum":"","sum_hidden":false,"sum_comment":"","sum_foreign":""},"61":{"sum_foreign_comment":"","sum":"","sum_comment":"","sum_foreign":""},"62":{"sum_foreign_comment":"","sum":"","sum_comment":"","sum_foreign":""},"63":{"sum_foreign_comment":"","sum":"","sum_comment":"","sum_comment_unclear":false,"sum_unclear":false,"sum_foreign":""},"64":{"sum_foreign_comment":"","sum":"","sum_comment":"","sum_comment_unclear":false,"sum_unclear":false,"sum_foreign":""}},"ft_src":"Старостін Володимир Вадимович\nсуддя харківського апеляційного адміністративного суду\nХарківська область\nАпеляційний адміністративний суд\nВолодимир\nДитина\nСтаростін Володимир Вадимович\nВолодимир Вадимович Старостін\nВолодимир Старостін\nСтаростін Володимир Вадимович\nСтаростін\nВадимович\nNissan Maxima\n2 л\n1998\n94\nспадщина\n26.15\nспадщина\n64\n2013\n276604.52\n276604.52\n2 л\nNissan Maxima\n1998\n2013\nАпеляційний адміністративний суд\nХарківська область\nсуддя харківського апеляційного адміністративного суду\nВадимович\nСтаростін Володимир Вадимович\nВолодимир Вадимович Старостін\nВолодимир Старостін\nСтаростін Володимир Вадимович\nВолодимир\nСтаростін Володимир Вадимович\nСтаростін\nДитина\n276604.52\n276604.52\n26.15\nспадщина\n94\n64\nспадщина\nДитина\nВадимович\nСтаростін\nХарківська область\nАпеляційний адміністративний суд\nсуддя харківського апеляційного адміністративного суду\nСтаростін Володимир Вадимович\nСтаростін Володимир Вадимович\nВолодимир Вадимович Старостін\nВолодимир Старостін\nСтаростін Володимир Вадимович\nВолодимир\n1998\n2 л\nNissan Maxima\n276604.52\n276604.52\n94\n64\nспадщина\n26.15\nспадщина\n2013","general":{"inn":"","inn_hidden":true,"last_name":"Старостін","post":{"region_unclear":false,"region":"Харківська область","post":"суддя харківського апеляційного адміністративного суду","office":"Апеляційний адміністративний суд","office_unclear":false,"post_hidden":false},"name":"Володимир","full_name":"Старостін Володимир Вадимович","family_raw":"","addresses":[{"place_district":"","place_city_hidden":true,"place_city":"","place_city_type_hidden":true,"place_district_hidden":true,"place_city_type":"","place_address_hidden":true,"place_address":"","place_hidden":true,"place":""}],"family":[{"inn":"","relations":"Дитина","relations_other":"","inn_hidden":true,"family_name":"","name_hidden":true,"name_unclear":false}],"full_name_suggest":{"output":"Старостін Володимир Вадимович","input":["Старостін Володимир Вадимович","Володимир Вадимович Старостін","Володимир Старостін"]},"patronymic":"Вадимович"},"source":"VULYK","estate":{"25":[{"space_hidden":false,"costs":"","costs_comment":"спадщина","address_hidden":true,"region_hidden":true,"space_comment":"","space_unclear":false,"space":"64","address":"","region":"","costs_rent_comment":"","space_units":"м²","costs_rent":""}],"27":[{"costs":"","costs_comment":"спадщина","address_hidden":true,"region_hidden":true,"space_comment":"","space":"26.15","address":"","region":"","address_unclear":false,"costs_rent_comment":"","space_units":"м²","costs_rent":""}],"31":[{"space_unclear":false,"address_hidden":true,"region_hidden":true,"space_comment":"","space":"94","address":"","region":"","costs_property":"","costs_rent_comment":"","address_unclear":false,"space_units":"м²","costs_property_comment":"","costs_rent":""}]},"intro":{"declaration_year":"2013","isnotdeclaration":"","declaration_year_unclear":false}}