{"income":{"5":{"family_comment":"","value":"326975.98","family":"","comment":""},"6":{"family_comment":"","value":"292243.33","value_unclear":false,"family":"","comment":""},"7":{"value":"5000","family_comment":"","source_name":"Рада адвокатів Київської області, м. Київ, вул. Фрунзе, 15","family":"","comment":"","source_name_hidden":false},"8":{"family_comment":"","value":"","family":"","comment":""},"9":{"family_comment":"","value":"","family":"","comment":""},"10":{"family_comment":"","value":"","family":"","comment":""},"11":{"family_comment":"","value":"","comment_hidden":false,"family":"","comment":""},"12":{"family_comment":"","value":"","family":"","comment":""},"13":{"family_comment":"","value":"","family":"","comment":""},"14":{"family_comment":"","value":"","family":"","comment":""},"15":{"value":"","family_comment":"","value_unclear":false,"family_unclear":false,"family":"","comment":""},"16":{"family_comment":"","value":"","family":"","comment":""},"17":{"family_comment":"","value":"","family":"","comment":""},"18":{"family_comment":"","value":"","family":"","comment":""},"19":{"family_comment":"","value":"","family":"","comment":""},"20":{"family_comment":"","value":"29732.65","comment_unclear":false,"family":"","comment":""}},"vehicle":{"35":[{"brand_info":"об'єм двигуна 1596 куб. см.","sum_rent_comment":"","brand":"ВАЗ 212","sum_comment":"","year":"1991","brand_hidden":false,"brand_info_unclear":false,"sum":"","sum_rent":""}],"39":[{"brand_info":"загальний причіп, легковий, маса без навантаження 150 кг, максим. маса 500 кг","sum_rent_comment":"","brand":"","sum_comment":"","brand_unclear":false,"year":"1992","brand_hidden":true,"brand_info_unclear":true,"sum":"","sum_rent":""}]},"id":"vulyk_104_68","declaration":{"date":"2016-03-31T00:00:00","additional_info_text":"","additional_info":"","url":"http://static.declarations.com.ua/declarations/chosen_ones/judges_batch/1866_danilov_oleksii_mykolaiovych_2015.pdf"},"liabilities":{"54":{"sum_foreign_comment":"","sum_unclear":false,"sum":"","sum_comment":"","sum_hidden":false,"sum_comment_hidden":false,"sum_foreign_hidden":false,"sum_foreign":""},"55":{"sum_foreign_comment":"","sum":"","sum_comment":"","sum_foreign":""},"56":{"sum_foreign_comment":"","sum":"","sum_comment":"","sum_unclear":false,"sum_foreign":""},"57":{"sum_foreign_comment":"","sum":"","sum_comment":"","sum_comment_unclear":false,"sum_comment_hidden":false,"sum_foreign_hidden":false,"sum_foreign":""},"58":{"sum_foreign_comment":"","sum":"","sum_comment":"","sum_unclear":false,"sum_foreign":""},"59":{"sum_foreign_comment":"","sum":"","sum_comment":"","sum_foreign":""},"60":{"sum_foreign_comment":"","sum":"","sum_comment":"","sum_comment_hidden":false,"sum_foreign_hidden":false,"sum_foreign":""},"61":{"sum_foreign_comment":"","sum":"","sum_comment":"","sum_foreign":""},"62":{"sum_foreign_comment":"","sum":"","sum_comment":"","sum_foreign":""},"63":{"sum_foreign_comment":"","sum":"","sum_comment":"","sum_foreign":""},"64":{"sum_foreign_comment":"","sum":"","sum_comment":"","sum_foreign":""}},"ft_src":"загальний причіп, легковий, маса без навантаження 150 кг, максим. маса 500 кг\n1992\n1991\nВАЗ 212\nоб'єм двигуна 1596 куб. см.\n64\n800\n1200\n116/2\n1000\n2/3 частини в користуванні сина Андрія 1988 р. н. та бувшої дружини Данілової Л. П\n64\nв користуванні 1/3 частини\n55.25\n2015\n292243.33\nРада адвокатів Київської області, м. Київ, вул. Фрунзе, 15\n5000\n326975.98\n29732.65\nоб'єм двигуна 1596 куб. см.\nВАЗ 212\n1991\nзагальний причіп, легковий, маса без навантаження 150 кг, максим. маса 500 кг\n1992\n2015\nДитина\nДанілов Віталій Олексійович 11. 07. 2001\nДанілов\nДанілов Олексій Миколайович\nОлексій Миколайович Данілов\nОлексій Данілов\nДанілов Олексій Миколайович\nДанілов Олексій Миколайович\nОлексій\nМиколайович\nЗагальний апеляційний суд\nголова апеляційного суду київської області\nКиївська область\n5000\nРада адвокатів Київської області, м. Київ, вул. Фрунзе, 15\n292243.33\n29732.65\n326975.98\n800\n1200\n1000\n116/2\n64\n64\n2/3 частини в користуванні сина Андрія 1988 р. н. та бувшої дружини Данілової Л. П\n55.25\nв користуванні 1/3 частини\nДитина\nДанілов Віталій Олексійович 11. 07. 2001\nМиколайович\nДанілов\nголова апеляційного суду київської області\nЗагальний апеляційний суд\nКиївська область\nДанілов Олексій Миколайович\nДанілов Олексій Миколайович\nОлексій Миколайович Данілов\nОлексій Данілов\nДанілов Олексій Миколайович\nОлексій","general":{"inn":"","inn_hidden":true,"last_name":"Данілов","post":{"region":"Київська область","office":"Загальний апеляційний суд","post":"голова апеляційного суду київської області","office_unclear":false,"region_unclear":false},"name":"Олексій","full_name":"Данілов Олексій Миколайович","family_raw":"","addresses":[{"place_district":"","place_address_hidden":true,"place_city":"","place_address":"","place_district_hidden":false,"place_city_type":"","place_city_hidden":true,"place_city_type_hidden":false,"place_hidden":true,"place":""}],"family":[{"inn":"","relations":"Дитина","relations_other":"","inn_hidden":true,"family_name":"Данілов Віталій Олексійович 11. 07. 2001","name_hidden":false,"name_unclear":false}],"full_name_suggest":{"output":"Данілов Олексій Миколайович","input":["Данілов Олексій Миколайович","Олексій Миколайович Данілов","Олексій Данілов"]},"patronymic":"Миколайович"},"source":"VULYK","estate":{"23":[{"space_hidden":false,"costs":"","costs_comment":"","address_hidden":false,"region_hidden":true,"space_comment":"","space":"800","address":"","region":"","costs_rent_comment":"","space_comment_unclear":false,"space_units":"м²","costs_rent":""}],"24":[{"space_hidden":false,"costs":"","costs_comment":"","address_hidden":false,"region_hidden":true,"space_comment":"","space":"1200","address":"","region":"","costs_rent_comment":"","space_comment_unclear":false,"space_units":"м²","costs_rent":""},{"costs_rent":"","region":"","costs":"","costs_rent_comment":"","costs_comment":"","space_comment":"116/2","space_units":"м²","space":"1000","address":""}],"25":[{"costs":"","costs_comment":"","address_hidden":false,"region_hidden":true,"space_comment":"в користуванні 1/3 частини","space":"55.25","address":"","costs_unclear":false,"region":"","costs_rent_comment":"","space_comment_unclear":false,"space_units":"м²","costs_rent":""}],"26":[{"costs_rent":"","region":"","costs":"","costs_rent_comment":"","costs_comment":"","address_hidden":false,"region_hidden":true,"space_comment":"","space_units":"м²","space":"64","address":""}],"31":[{"space_unclear":false,"address_hidden":false,"region_hidden":true,"space_comment":"2/3 частини в користуванні сина Андрія 1988 р. н. та бувшої дружини Данілової Л. П","space_hidden":false,"space":"64","address":"","region":"","costs_property":"","costs_rent_comment":"","space_units":"м²","costs_property_comment":"","costs_rent":""}]},"intro":{"declaration_year":"2015","isnotdeclaration":""}}