{"income":{"5":{"value":"202513.57","family_comment":"","value_unclear":true,"family_hidden":false,"family_unclear":false,"family":"","comment":""},"6":{"value":"202513.57","family_comment":"","value_unclear":true,"family_unclear":false,"family":"","comment":""},"7":{"value":"","family_comment":"","source_name":"","family":"","comment":"","source_name_hidden":false},"8":{"family_comment":"","value":"","family":"","comment":""},"9":{"family_comment":"","value":"","family":"","comment":""},"10":{"value":"","family_hidden":false,"value_hidden":false,"family_comment":"","family":"","comment":""},"11":{"family_comment":"","value":"","family":"","comment":""},"12":{"family_comment":"","value":"","family":"","comment":""},"13":{"family_comment":"","value":"","family":"","comment":""},"14":{"family_comment":"","value":"","family":"","comment":""},"15":{"family_comment":"","value":"","family":"","comment":""},"16":{"family_comment":"","value":"","value_unclear":false,"family":"","comment":""},"17":{"family_comment":"","value":"","family":"","comment":""},"18":{"family_comment":"","value":"","family":"","comment":""},"19":{"family_comment":"","value":"","family":"","comment":""},"20":{"value":"","family_comment":"","family_unclear":false,"family":"","comment":"","family_comment_unclear":false}},"id":"vulyk_27_191","banks":{"45":[{"sum_foreign_comment":"","sum":"","sum_comment":"","sum_hidden":false,"sum_foreign_units":"UAH","sum_foreign_hidden":false,"sum_units":"UAH","sum_comment_hidden":false,"sum_units_hidden":false,"sum_foreign":""},{"sum_foreign_comment":"","sum_units":"","sum_comment":"","sum_foreign_units":"","sum_comment_hidden":false,"sum":"","sum_foreign":""}],"46":[{"sum_foreign_comment":"","sum_units":"UAH","sum_comment":"","sum_comment_unclear":false,"sum_hidden":false,"sum_foreign_units":"UAH","sum_comment_hidden":false,"sum":"","sum_foreign":""},{"sum_foreign_comment":"","sum_units":"","sum_comment":"","sum_comment_unclear":false,"sum_foreign_units":"","sum":"","sum_foreign":""}],"47":[{"sum_foreign_comment":"","sum":"","sum_comment":"","sum_hidden":false,"sum_foreign_units":"UAH","sum_foreign_hidden":false,"sum_units":"UAH","sum_comment_hidden":false,"sum_unclear":false,"sum_foreign":"","sum_units_hidden":false}],"48":[{"sum_foreign_comment":"","sum_units":"UAH","sum_comment":"","sum_foreign_units":"UAH","sum":"","sum_foreign":""}],"49":[{"sum_foreign_comment":"","sum_units":"UAH","sum_comment":"","sum_foreign_units":"UAH","sum":"","sum_foreign":""}],"50":[{"sum_foreign_comment":"","sum_units":"UAH","sum_comment":"","sum_foreign_units":"UAH","sum":"","sum_foreign":""}],"51":[{"sum_foreign_comment":"","sum_units":"UAH","sum_units_hidden":false,"sum_comment":"","sum_comment_unclear":false,"sum_hidden":false,"sum_foreign_units":"UAH","sum_comment_hidden":false,"sum_unclear":false,"sum":"","sum_foreign":""},{"sum_foreign_comment":"","sum_units":"","sum_comment":"","sum_foreign_units":"","sum_comment_hidden":false,"sum":"","sum_foreign":""}],"52":[{"sum_foreign_comment":"","sum_units":"UAH","sum_comment":"","sum_comment_unclear":false,"sum_units_hidden":false,"sum_foreign_units":"UAH","sum_comment_hidden":false,"sum_unclear":false,"sum":"","sum_foreign":""}],"53":[{"sum_foreign_comment":"","sum_units":"UAH","sum_comment":"","sum_foreign_units":"UAH","sum":"","sum_foreign":""}]},"declaration":{"additional_info_text":"","notfull_lostpages":"","date":"2015-03-23T00:00:00","notfull":"","additional_info":"","url":"http://static.declarations.com.ua/declarations/chosen_ones/mega_batch/porovskyi_vitalii_anatoliiovych.pdf"},"liabilities":{"54":{"sum_foreign_comment":"","sum_foreign_hidden":false,"sum_comment":"","sum_comment_hidden":false,"sum":"","sum_foreign":""},"55":{"sum_foreign_comment":"","sum":"","sum_comment":"","sum_foreign":""},"56":{"sum_foreign_comment":"","sum":"","sum_comment":"","sum_hidden":false,"sum_unclear":false,"sum_foreign":""},"57":{"sum_foreign_comment":"","sum":"","sum_comment":"","sum_hidden":false,"sum_comment_hidden":false,"sum_unclear":false,"sum_foreign":""},"58":{"sum_foreign_comment":"","sum":"","sum_comment":"","sum_hidden":false,"sum_comment_hidden":false,"sum_unclear":false,"sum_foreign":""},"59":{"sum_foreign_comment":"","sum":"1800","sum_comment":"","sum_foreign":""},"60":{"sum_foreign_comment":"","sum":"","sum_comment":"","sum_hidden":false,"sum_comment_hidden":false,"sum_foreign":""},"61":{"sum_foreign_comment":"","sum":"","sum_comment":"","sum_foreign":""},"62":{"sum_foreign_comment":"","sum":"","sum_comment":"","sum_foreign":""},"63":{"sum_foreign_comment":"","sum":"","sum_comment":"","sum_hidden":false,"sum_comment_hidden":false,"sum_foreign":""},"64":{"sum_foreign_comment":"","sum":"","sum_comment":"","sum_hidden":false,"sum_comment_hidden":false,"sum_foreign":""}},"ft_src":"1800\nсуддя володимирецького районного суду рівненської області\nРівненська область\nЗагальний місцевий суд\nВіталій\nАнатолійович\nПоровський\nПоровський Віталій Анатолійович\nПоровський Віталій Анатолійович\nВіталій Анатолійович Поровський\nВіталій Поровський\nПоровський Віталій Анатолійович\nВолодимирець\n34300\nРівненська область\nВолодимирецький\nСМТ\n202513.57\n202513.57\nнадане в користування\nм. Рівне\nсоток\n3\nРівненська область\nАвтору належить 1/4 житлового будинку, що був придбаний у 1983 році\n1983 рік\nм. Рівне\n18.6\nРівненська область\n1/2 сарая\nм. Рівне\n1983\nРівненська область\n2014\n202513.57\n202513.57\n2014\nПоровський Віталій Анатолійович\nВіталій Анатолійович Поровський\nВіталій Поровський\nПоровський Віталій Анатолійович\nВіталій\nПоровський Віталій Анатолійович\nПоровський\nЗагальний місцевий суд\nРівненська область\nсуддя володимирецького районного суду рівненської області\nАнатолійович\n34300\nСМТ\nРівненська область\nВолодимирець\nВолодимирецький\n1800\n202513.57\n202513.57\n3\nнадане в користування\nРівненська область\nсоток\nм. Рівне\n1983 рік\n18.6\nАвтору належить 1/4 житлового будинку, що був придбаний у 1983 році\nРівненська область\nм. Рівне\n1983\n1/2 сарая\nм. Рівне\nРівненська область\n1800\nПоровський Віталій Анатолійович\nВіталій Анатолійович Поровський\nВіталій Поровський\nПоровський Віталій Анатолійович\nАнатолійович\nПоровський\nСМТ\n34300\nВолодимирець\nРівненська область\nВолодимирецький\nРівненська область\nЗагальний місцевий суд\nсуддя володимирецького районного суду рівненської області\nПоровський Віталій Анатолійович\nВіталій\nсоток\nнадане в користування\nм. Рівне\nРівненська область\n3\n1983 рік\nАвтору належить 1/4 житлового будинку, що був придбаний у 1983 році\nм. Рівне\nРівненська область\n18.6\n1983\n1/2 сарая\nм. Рівне\nРівненська область\n2014","general":{"name_hidden":false,"name":"Віталій","patronymic_unclear":false,"inn":"","inn_unclear":false,"patronymic":"Анатолійович","inn_hidden":true,"family_raw":"","last_name":"Поровський","post":{"post_unclear":false,"region_unclear":false,"post":"суддя володимирецького районного суду рівненської області","office":"Загальний місцевий суд","region":"Рівненська область","post_hidden":false,"office_unclear":false},"last_name_unclear":false,"full_name":"Поровський Віталій Анатолійович","addresses":[{"place_district":"Володимирецький","place_address_hidden":true,"place_city":"Володимирець","place_city_type_hidden":false,"place_district_hidden":false,"place_city_type":"СМТ","place_city_hidden":false,"place_address_unclear":false,"place_address":"34300","place_hidden":false,"place":"Рівненська область"}],"full_name_suggest":{"output":"Поровський Віталій Анатолійович","input":["Поровський Віталій Анатолійович","Віталій Анатолійович Поровський","Віталій Поровський"]},"name_unclear":false},"source":"VULYK","estate":{"23":[{"costs":"","costs_comment":"","address_hidden":true,"region_hidden":false,"space_comment":"надане в користування","space":"3","address":"м. Рівне","region":"Рівненська область","address_unclear":false,"costs_rent_comment":"","costs_rent_comment_hidden":false,"space_units":"соток","space_units_unclear":false,"costs_rent":""},{"costs":"","costs_comment":"","address_hidden":false,"region_hidden":false,"space_comment":"","space":"","address":"","costs_comment_unclear":false,"region":"","costs_rent_comment":"","space_units":"","costs_rent":""},{"costs_rent":"","region":"","costs":"","costs_rent_comment":"","costs_comment":"","space_comment":"","space_units":"","space":"","address":""},{"costs_rent":"","region":"","costs":"","costs_rent_comment":"","costs_comment":"","space_comment":"","space_units":"","space":"","address":""}],"24":[{"space_unclear":false,"costs":"1983 рік","costs_comment":"","address_hidden":true,"region_hidden":false,"space_comment":"Автору належить 1/4 житлового будинку, що був придбаний у 1983 році","space":"18.6","address":"м. Рівне","region":"Рівненська область","costs_rent_comment":"","space_units":"м²","costs_rent":""}],"28":[{"space_unclear":true,"costs":"1983","costs_comment":"","address_hidden":true,"region_hidden":false,"space_comment":"1/2 сарая","space":"","address":"м. Рівне","region":"Рівненська область","costs_rent_comment":"","space_units":"м²","costs_rent":""}]},"intro":{"declaration_year":"2014","isnotdeclaration":"","declaration_year_hidden":false}}