{"income":{"5":{"family_comment":"","value":"224294.69","family":"108400","comment":""},"6":{"family_comment":"","value":"224183.38","family":"","comment":""},"7":{"value":"","comment_hidden":false,"family_comment":"","source_name":"","family":"","comment":"","source_name_hidden":false},"8":{"family_comment":"","value":"","family_hidden":false,"comment":"","family":""},"9":{"value":"111.31","family_comment":"","value_unclear":false,"family_unclear":false,"family":"","comment":""},"10":{"family_comment":"","value":"","family":"","comment":""},"11":{"family_comment":"","value":"","family":"","comment":""},"12":{"family_comment":"","value":"","family":"","comment":""},"13":{"family_comment":"","value":"","family":"","comment":""},"14":{"family_comment":"","value":"","family":"","comment":""},"15":{"family_comment":"","value":"","family":"","comment":""},"16":{"family_comment":"","value":"","family":"","comment":""},"17":{"family_comment":"","value":"","family":"","comment":""},"18":{"family_comment":"","value":"","family":"","comment":""},"19":{"family_comment":"","value":"","family":"","comment":""},"20":{"value":"","value_unclear":false,"family_hidden":false,"family_comment":"пенсія","family":"108400","comment":""}},"vehicle":{"35":[{"brand_info":"2.2","sum_rent_comment":"","year":"2014","brand_info_hidden":false,"brand_info_unclear":false,"year_unclear":false,"sum_rent":"","sum":"","brand":"Toyota Rav 4","sum_comment":"","sum_comment_unclear":false,"brand_hidden":false,"brand_unclear":false}],"40":[{"brand_info":"3.5","sum_rent_comment":"","brand":"Toyota Highlander","sum_comment":"","year":"2011","brand_info_unclear":false,"sum":"","sum_rent":""}]},"id":"vulyk_109_63","declaration":{"additional_info_text":"","notfull_lostpages":"","date":"2016-03-29T00:00:00","notfull":"","additional_info":"","url":"http://static.declarations.com.ua/declarations/chosen_ones/judges_batch/2520_petrova_valentyna_ivanivna_2015.pdf"},"liabilities":{"54":{"sum_foreign_comment":"","sum":"","sum_comment":"","sum_hidden":false,"sum_comment_hidden":false,"sum_unclear":false,"sum_foreign":""},"55":{"sum_foreign_comment":"","sum":"","sum_comment":"","sum_comment_unclear":false,"sum_foreign":""},"56":{"sum_foreign_comment":"","sum":"","sum_comment":"","sum_foreign":""},"57":{"sum_foreign_comment":"","sum_comment_hidden":false,"sum":"","sum_comment":"","sum_foreign":""},"58":{"sum_foreign_comment":"","sum_comment_hidden":false,"sum":"","sum_comment":"","sum_foreign":""},"59":{"sum_foreign_comment":"","sum":"","sum_comment":"","sum_foreign":""},"60":{"sum_foreign_comment":"","sum":"","sum_comment":"","sum_foreign":""},"61":{"sum_foreign_comment":"","sum":"","sum_comment":"","sum_foreign":""},"62":{"sum_foreign_comment":"","sum":"","sum_comment":"","sum_foreign":""},"63":{"sum_foreign_comment":"","sum":"","sum_comment":"","sum_foreign":""},"64":{"sum_foreign_comment":"","sum":"","sum_comment":"","sum_foreign":""}},"ft_src":"суддя господарського суду дніпропетровської області\nДніпропетровська область\nГосподарський місцевий суд\nВалентина\nПетров В. Г\nПодружжя\nІванівна\nПетрова Валентина Іванівна\nПетрова\nПетрова Валентина Іванівна\nВалентина Іванівна Петрова\nВалентина Петрова\nПетрова Валентина Іванівна\n2.2\nToyota Rav 4\n2014\n3.5\n2011\nToyota Highlander\n37.1\n337.3\n28\n40\n57.1\n106.7\n60.6\n530\n140\n2015\n224183.38\n108400\n224294.69\n111.31\nпенсія\n108400\n2.2\nToyota Rav 4\n2014\n3.5\n2011\nToyota Highlander\n2015\nПодружжя\nПетров В. Г\nПетрова Валентина Іванівна\nВалентина Іванівна Петрова\nВалентина Петрова\nПетрова Валентина Іванівна\nВалентина\nПетрова Валентина Іванівна\nПетрова\nГосподарський місцевий суд\nДніпропетровська область\nсуддя господарського суду дніпропетровської області\nІванівна\n224183.38\nпенсія\n108400\n224294.69\n108400\n111.31\n37.1\n337.3\n60.6\n140\n530\n28\n57.1\n106.7\n40\nПодружжя\nПетров В. Г\nВалентина\nІванівна\nПетрова\nПетрова Валентина Іванівна\nВалентина Іванівна Петрова\nВалентина Петрова\nПетрова Валентина Іванівна\nДніпропетровська область\nГосподарський місцевий суд\nсуддя господарського суду дніпропетровської області\nПетрова Валентина Іванівна\n2014\nToyota Rav 4\n2.2\n2011\n3.5\nToyota Highlander\nпенсія\n108400\n108400\n224294.69\n111.31\n224183.38\n57.1\n106.7\n530\n28\n60.6\n40\n37.1\n337.3\n140\n2015","general":{"name_hidden":false,"name":"Валентина","inn":"","inn_unclear":false,"family":[{"inn":"","relations":"Подружжя","relations_hidden":false,"inn_hidden":true,"relations_other":"","name_hidden":false,"family_name":"Петров В. Г","name_unclear":false}],"inn_hidden":true,"family_raw":"","last_name":"Петрова","post":{"region_unclear":false,"region":"Дніпропетровська область","post":"суддя господарського суду дніпропетровської області","region_hidden":false,"office":"Господарський місцевий суд","office_hidden":false,"office_unclear":false},"full_name":"Петрова Валентина Іванівна","patronymic":"Іванівна","full_name_suggest":{"output":"Петрова Валентина Іванівна","input":["Петрова Валентина Іванівна","Валентина Іванівна Петрова","Валентина Петрова"]}},"source":"VULYK","estate":{"23":[{"space_unclear":true,"costs":"","costs_rent_unclear":false,"costs_comment":"","address_hidden":false,"region_hidden":true,"space_comment":"","space":"530","address":"","region":"","costs_rent_comment":"","space_units":"м²","costs_rent":""}],"24":[{"costs_rent":"","region":"","costs":"","costs_rent_comment":"","costs_comment":"","address_hidden":false,"region_hidden":true,"space_comment":"","space_units":"м²","space":"","address":""}],"25":[{"space_unclear":true,"costs":"","costs_comment":"","address_hidden":false,"region_hidden":true,"space_comment":"","space_hidden":false,"space":"140","address":"","region":"","costs_rent_comment":"","space_units":"м²","space_units_hidden":false,"costs_rent":""}],"26":[{"space_unclear":true,"costs":"","costs_comment":"","address_hidden":false,"region_hidden":true,"space_comment":"","space":"60.6","address":"","region":"","costs_rent_comment":"","space_units":"м²","costs_rent":""}],"27":[{"space_unclear":true,"costs":"","costs_rent_unclear":false,"costs_comment":"","address_hidden":false,"region_hidden":true,"space_comment":"","space":"37.1","address":"","region":"","costs_rent_comment":"","space_units":"м²","costs_rent":""},{"costs_rent":"","space_unclear":false,"region":"","costs":"","costs_rent_comment":"","costs_comment":"","region_hidden":true,"space_comment":"","space_units":"м²","space":"337.3","address":""}],"31":[{"space_hidden":false,"costs_property_comment":"","address_hidden":false,"region_hidden":true,"space_comment":"","space":"57.1","address":"","region":"","costs_property":"","costs_rent_comment":"","space_units":"м²","space_units_hidden":false,"costs_rent":""},{"costs_rent":"","region":"","costs_property":"","costs_rent_comment":"","space_comment":"","costs_property_comment":"","space_units":"м²","space":"106.7","address":""}],"32":[{"costs_rent":"","region":"","costs_property":"","costs_rent_comment":"","address_hidden":false,"region_hidden":true,"space_comment":"","costs_property_comment":"","space_units":"м²","space":"40","address":""}],"33":[{"costs_rent":"","costs_property":"","costs_rent_comment":"","address_hidden":false,"region_hidden":true,"space_comment":"","costs_property_comment":"","space_units":"м²","space":"28","address":""}]},"intro":{"declaration_year":"2015","isnotdeclaration":""}}