{"id":"vulyk_109_9","ft_src":"2000 куб. см.\n2007\nVolkswagen Passat B6\nвикрадений у розшуку\n1988\nВАЗ 2104\n1600 куб. см.\n2012\nKia Rio\n37\n20\n23\n2434.5\n18.5\n26.8\nАдвок. бюро 'Говор'\n1000\nКреді Агріколь Банк індекс Банк\n37450\nПриватбанк\n1370\nПАТ Банк Кредит Дніпро\n77\nПАТ Платинум Банк\n2021\nд/р ПАТ Платинум Банк\n91000\nкомп/р Ощадбанк СРСР\n122\nкомп. р. Ощадбанку СРСР\n2026\n2015\n2000 куб. см.\n2007\nVolkswagen Passat B6\nвикрадений у розшуку\n1988\nВАЗ 2104\n1600 куб. см.\nKia Rio\n2012\n2015\nГовор Надія Дмитрівна\nНадія Дмитрівна Говор\nНадія Говор\nГовор Надія Дмитрівна\nНадія\nПодружжя\nГовор І. К\nДитина\nГовор Д. І\nГовор Надія Дмитрівна\nДмитрівна\nГосподарський місцевий суд\nВінницька область\nсуддя господарського суду вінницької області\nГовор\n226072\n48004\n20332\n226727\n146222\n655\n77886\n2434.5\n20\n23\n37\n18.5\n26.8\n1000\nАдвок. бюро 'Говор'\n2026\nкомп. р. Ощадбанку СРСР\n37450\nКреді Агріколь Банк індекс Банк\nПриватбанк\n1370\nПАТ Банк Кредит Дніпро\n77\nПАТ Платинум Банк\n2021\nд/р ПАТ Платинум Банк\n91000\nкомп/р Ощадбанк СРСР\n122\n48004\n226072\n146222\n226727\n77886\n655\n20332\nПодружжя\nГовор І. К\nДитина\nГовор Д. І\nДмитрівна\nГовор\nНадія\nГовор Надія Дмитрівна\nНадія Дмитрівна Говор\nНадія Говор\nГовор Надія Дмитрівна\nВінницька область\nГосподарський місцевий суд\nсуддя господарського суду вінницької області\nГовор Надія Дмитрівна","estate":{"23":[{"address":"","space_units":"м²","costs_rent_unclear":false,"costs_comment":"","space_unclear":false,"region_hidden":true,"space_comment":"","address_hidden":true,"costs":"","costs_rent_comment":"","space":"2434.5","region":"","costs_rent":""}],"24":[{"costs":"","address":"","space_units":"м²","costs_rent_comment":"","space":"23","space_comment":"","region_hidden":true,"costs_comment":"","region":"","address_hidden":true,"costs_rent":""}],"25":[{"address":"","space_units":"м²","space_hidden":false,"space_unclear":false,"region_hidden":true,"costs_comment":"","space_comment":"","address_hidden":true,"space":"18.5","costs_rent_comment":"","costs":"","region":"","space_units_hidden":false,"costs_rent":""},{"costs":"","address":"","space_units":"м²","costs_rent_comment":"","space":"26.8","space_comment":"","region_hidden":true,"costs_comment":"","region":"","address_hidden":false,"costs_rent":""}],"31":[{"costs_property_comment":"","address":"","space_units":"м²","space_hidden":false,"space_comment":"","region_hidden":true,"costs_property":"","region":"","address_hidden":true,"costs_rent_comment":"","space":"37","space_units_hidden":false,"costs_rent":""}],"33":[{"costs_property_comment":"","address":"","space_units":"м²","costs_rent_comment":"","space":"20","region_hidden":true,"costs_property":"","space_comment":"","address_hidden":true,"costs_rent":""}]},"vehicle":{"40":[{"sum_comment":"","brand_info":"2000 куб. см.","sum":"","sum_rent_comment":"","year":"2007","brand":"Volkswagen Passat B6","sum_rent":"","brand_info_unclear":false},{"sum_comment":"","brand_info":"викрадений у розшуку","sum":"","sum_rent_comment":"","year":"1988","brand":"ВАЗ 2104","sum_rent":""},{"sum_comment":"","brand_info":"1600 куб. см.","sum":"","sum_rent_comment":"","year":"2012","brand":"Kia Rio","sum_rent":""}]},"source":"VULYK","income":{"5":{"family_comment":"","value":"226727","family":"146222","comment":""},"6":{"family_comment":"","value":"226072","family":"48004","comment":""},"7":{"source_name_hidden":false,"family_comment":"","comment":"","family":"","comment_hidden":false,"value":"","source_name":""},"8":{"family_comment":"","family_hidden":false,"value":"","family":"","comment":""},"9":{"family_comment":"","family":"77886","comment":"","value_unclear":false,"family_unclear":false,"value":"655"},"10":{"family_comment":"","value":"","family":"","comment":""},"11":{"family_comment":"","value":"","family":"","comment":""},"12":{"family_comment":"","value":"","family":"","comment":""},"13":{"family_comment":"","value":"","family":"","comment":""},"14":{"family_comment":"","value":"","family":"","comment":""},"15":{"family_comment":"","value":"","family":"","comment":""},"16":{"family_comment":"","value":"","family":"","comment":""},"17":{"family_comment":"","value":"","family":"","comment":""},"18":{"family_comment":"","value":"","family":"","comment":""},"19":{"family_comment":"","value":"","family":"","comment":""},"20":{"family_comment":"","family":"20332","comment":"","value_unclear":false,"family_hidden":false,"value":""}},"banks":{"45":[{"sum_units":"UAH","sum_comment":"комп. р. Ощадбанку СРСР","sum_foreign_units":"UAH","sum":"2026","sum_units_hidden":false,"sum_foreign_comment":"","sum_foreign":"","sum_unclear":false,"sum_comment_hidden":false}],"51":[{"sum_units":"UAH","sum_comment":"Креді Агріколь Банк індекс Банк","sum_foreign_units":"UAH","sum":"37450","sum_units_hidden":false,"sum_foreign_comment":"","sum_foreign":"","sum_unclear":false,"sum_comment_hidden":false},{"sum_units":"UAH","sum_comment":"Приватбанк","sum":"1370","sum_foreign_comment":"","sum_foreign":"","sum_unclear":false},{"sum_comment":"ПАТ Банк Кредит Дніпро","sum_units":"UAH","sum_foreign":"","sum":"77","sum_foreign_comment":""},{"sum_comment":"ПАТ Платинум Банк","sum_units":"UAH","sum_foreign":"","sum":"2021","sum_foreign_comment":""},{"sum_comment":"д/р ПАТ Платинум Банк","sum_units":"UAH","sum_foreign":"","sum":"91000","sum_foreign_comment":""},{"sum_comment":"комп/р Ощадбанк СРСР","sum_units":"UAH","sum_foreign":"","sum":"122","sum_foreign_comment":""}],"53":[{"sum_comment_unclear":false,"sum_units":"UAH","sum_foreign_units_hidden":false,"sum_foreign_units":"UAH","sum":"1000","sum_foreign_comment":"","sum_comment":"Адвок. бюро 'Говор'","sum_foreign":"","sum_comment_hidden":false,"sum_foreign_hidden":false}]},"declaration":{"notfull_lostpages":"","additional_info_text":"","additional_info":"","date":"2016-03-28T00:00:00","notfull":"","url":"http://static.declarations.com.ua/declarations/chosen_ones/judges_batch/2466_hovor_nadiia_dmytrivna_2015.pdf"},"general":{"family_raw":"","name":"Надія","full_name_suggest":{"input":["Говор Надія Дмитрівна","Надія Дмитрівна Говор","Надія Говор"],"output":"Говор Надія Дмитрівна"},"patronymic":"Дмитрівна","inn_hidden":true,"addresses":[{"place_city_type_hidden":true,"place_city_type":"","place_city_hidden":true,"place_hidden":true,"place_district":"","place_district_hidden":true,"place":"","place_address":"","place_address_hidden":true,"place_city":""}],"inn":"","inn_unclear":true,"last_name":"Говор","full_name":"Говор Надія Дмитрівна","family":[{"inn":"","family_name":"Говор І. К","relations_hidden":false,"name_unclear":false,"relations":"Подружжя","inn_hidden":true,"name_hidden":true,"relations_other":""},{"inn":"","family_name":"Говор Д. І","relations_other":"","name_unclear":false,"inn_hidden":false,"name_hidden":false,"relations":"Дитина"}],"post":{"office":"Господарський місцевий суд","post":"суддя господарського суду вінницької області","office_unclear":false,"region_hidden":false,"region":"Вінницька область","office_hidden":false,"region_unclear":false},"name_hidden":false},"liabilities":{"54":{"sum_comment":"","sum_hidden":false,"sum":"","sum_foreign_comment":"","sum_foreign":"","sum_unclear":false,"sum_comment_hidden":false},"55":{"sum_comment":"","sum_comment_unclear":false,"sum_foreign_comment":"","sum":"","sum_foreign":""},"56":{"sum_comment":"","sum_foreign_comment":"","sum_foreign":"","sum":""},"57":{"sum_comment":"","sum_foreign_comment":"","sum_foreign":"","sum":"","sum_comment_hidden":false},"58":{"sum_comment":"","sum_foreign_comment":"","sum_foreign":"","sum":"","sum_comment_hidden":false},"59":{"sum_comment":"","sum_foreign_comment":"","sum_foreign":"","sum":""},"60":{"sum_comment":"","sum_foreign_comment":"","sum_foreign":"","sum":""},"61":{"sum_comment":"","sum_foreign_comment":"","sum_foreign":"","sum":""},"62":{"sum_comment":"","sum_foreign_comment":"","sum_foreign":"","sum":""},"63":{"sum_comment":"","sum_foreign_comment":"","sum_foreign":"","sum":""},"64":{"sum_comment":"","sum_foreign_comment":"","sum_foreign":"","sum":""}},"intro":{"isnotdeclaration":"","declaration_year":"2015"}}