{"income":{"5":{"value":"297808","value_unclear":false,"family_hidden":false,"family_comment":"","family":"358107","comment":""},"6":{"family_comment":"","value":"297808","family":"","comment":""},"7":{"family_comment":"","value":"","source_name":"","family":"","comment":""},"8":{"family_comment":"","value":"","family":"","comment":""},"9":{"family_comment":"","value":"","family":"","comment":""},"10":{"family_comment":"","value":"","family":"","comment":""},"11":{"family_comment":"","value":"","family_hidden":false,"comment":"","family":""},"12":{"family_comment":"","value":"","family":"","comment":""},"13":{"family_comment":"","value":"","family":"","comment":""},"14":{"family_comment":"","value":"","family":"","comment":""},"15":{"family_comment":"","value":"","family":"","comment":""},"16":{"family_comment":"","value":"","family":"","comment":""},"17":{"family_comment":"","value":"","family":"","comment":"","family_comment_unclear":false},"18":{"family_comment":"","value":"","family":"","comment":""},"19":{"family_comment":"","value":"","family":"","comment":""},"20":{"value":"","family_unclear":false,"family_hidden":false,"family_comment":"","family":"358107","comment":""}},"vehicle":{"35":[{"brand_info":"1994 куб. см.","sum":"260000","brand":"Subaru Forester","sum_comment":"","brand_unclear":false,"year":"2010","brand_hidden":false,"brand_info_hidden":false,"brand_info_unclear":false,"sum_rent_comment":"","sum_rent":""}]},"id":"vulyk_103_88","declaration":{"date":"2016-03-11T00:00:00","additional_info_text":"","additional_info":"","url":"http://static.declarations.com.ua/declarations/chosen_ones/judges_batch/1312_romanets_lolita_anatoliivna.pdf"},"liabilities":{"54":{"sum_foreign_comment":"","sum_foreign_hidden":false,"sum_comment":"дві суми 13920 та 21988,50","sum_foreign_comment_hidden":false,"sum_hidden":false,"sum_foreign_comment_unclear":true,"sum_comment_hidden":true,"sum_unclear":true,"sum":"35908.5","sum_foreign":""},"55":{"sum_foreign_comment":"","sum":"","sum_comment":"","sum_foreign":""},"56":{"sum_foreign_comment":"","sum":"","sum_comment":"","sum_foreign":""},"57":{"sum_foreign_comment":"","sum_foreign_hidden":false,"sum_comment":"","sum_foreign_comment_hidden":false,"sum_hidden":false,"sum_comment_hidden":false,"sum":"","sum_foreign":""},"58":{"sum_foreign_comment":"","sum_foreign_hidden":false,"sum_comment":"","sum_foreign_comment_hidden":false,"sum_hidden":false,"sum_comment_hidden":false,"sum":"","sum_foreign":""},"59":{"sum_foreign_comment":"","sum_foreign_hidden":false,"sum_comment":"","sum_foreign_comment_hidden":false,"sum_hidden":false,"sum_comment_hidden":false,"sum":"","sum_foreign":""},"60":{"sum_foreign_comment":"","sum":"","sum_comment":"","sum_hidden":false,"sum_comment_hidden":false,"sum_foreign":""},"61":{"sum_foreign_comment":"","sum":"","sum_comment":"","sum_foreign":""},"62":{"sum_foreign_comment":"","sum_comment_hidden":false,"sum":"","sum_comment":"","sum_foreign":""},"63":{"sum_foreign_comment":"","sum":"","sum_comment":"","sum_foreign":""},"64":{"sum_foreign_comment":"","sum":"","sum_comment":"","sum_foreign":""}},"ft_src":"дві суми 13920 та 21988,50\n35908.5\nРоманець Лоліта Анатоліївна\nсуддя вищого спецiалiзованого суду україни з розгляду цивiльних і кримiнальних справ\nЗагальнодержавний регіон\nВищий спеціалізований суд з розгляду цивільних і кримінальних справ\nЛоліта\nКоновалов В. М\nПодружжя\nКоновалова М. В\nДитина\nРоманець Лоліта Анатоліївна\nЛоліта Анатоліївна Романець\nЛоліта Романець\nРоманець Лоліта Анатоліївна\nРоманець\nАнатоліївна\nSubaru Forester\n260000\n1994 куб. см.\n2010\n63.4\n.1\n31.7\n58.6\n2015\n297808\n358107\n297808\n358107\n1994 куб. см.\n2010\n260000\nSubaru Forester\n.1\n63.4\n31.7\n58.6\nРоманець\nРоманець Лоліта Анатоліївна\nЛоліта Анатоліївна Романець\nЛоліта Романець\nРоманець Лоліта Анатоліївна\nРоманець Лоліта Анатоліївна\nАнатоліївна\nПодружжя\nКоновалов В. М\nКоновалова М. В\nДитина\nЛоліта\nВищий спеціалізований суд з розгляду цивільних і кримінальних справ\nсуддя вищого спецiалiзованого суду україни з розгляду цивiльних і кримiнальних справ\nЗагальнодержавний регіон\n35908.5\nдві суми 13920 та 21988,50\n297808\n358107\n297808\n358107\n2015\nдві суми 13920 та 21988,50\n35908.5\nПодружжя\nКоновалов В. М\nДитина\nКоновалова М. В\nРоманець\nАнатоліївна\nсуддя вищого спецiалiзованого суду україни з розгляду цивiльних і кримiнальних справ\nВищий спеціалізований суд з розгляду цивільних і кримінальних справ\nЗагальнодержавний регіон\nРоманець Лоліта Анатоліївна\nРоманець Лоліта Анатоліївна\nЛоліта Анатоліївна Романець\nЛоліта Романець\nРоманець Лоліта Анатоліївна\nЛоліта\n260000\nSubaru Forester\n1994 куб. см.\n2010\n358107\n297808\n358107\n297808\n63.4\n31.7\n58.6\n.1\n2015","general":{"inn":"","inn_hidden":true,"last_name":"Романець","post":{"region":"Загальнодержавний регіон","region_unclear":false,"post":"суддя вищого спецiалiзованого суду україни з розгляду цивiльних і кримiнальних справ","office_unclear":false,"office":"Вищий спеціалізований суд з розгляду цивільних і кримінальних справ"},"name":"Лоліта","full_name":"Романець Лоліта Анатоліївна","family_raw":"","addresses":[{"place_district":"","place_city_hidden":true,"place_city":"","place_city_type_hidden":true,"place_district_hidden":true,"place_city_type":"","place_address_hidden":true,"place_address":"","place_hidden":true,"place":""}],"family":[{"inn":"","relations":"Подружжя","relations_hidden":false,"inn_hidden":true,"relations_other":"","name_hidden":true,"family_name":"Коновалов В. М","name_unclear":false},{"inn":"","family_name":"Коновалова М. В","relations":"Дитина","inn_hidden":false,"relations_other":""}],"full_name_suggest":{"output":"Романець Лоліта Анатоліївна","input":["Романець Лоліта Анатоліївна","Лоліта Анатоліївна Романець","Лоліта Романець"]},"patronymic":"Анатоліївна"},"source":"VULYK","estate":{"25":[{"costs":"","costs_comment":"","address_hidden":true,"region_hidden":true,"space_comment":"","space":"31.7","address":"","region":"","costs_rent_comment":"","space_comment_unclear":false,"space_comment_hidden":false,"space_units":"м²","costs_rent":""},{"costs_rent":"","region":"","costs":"","costs_rent_comment":"","costs_comment":"","region_hidden":false,"space_comment":"","space_units":"м²","space":"58.6","address":""}],"29":[{"space_hidden":false,"address_hidden":true,"region_hidden":true,"space_comment":"","space":".1","address":"","region":"","costs_property":"","costs_rent_comment":"","space_units":"га","costs_property_comment":"","costs_rent":""}],"31":[{"space_hidden":false,"address_hidden":true,"region_hidden":true,"space_comment":"","space":"63.4","address":"","costs_property":"","costs_rent_comment":"","address_unclear":false,"space_units":"м²","costs_property_comment":"","costs_rent":""}]},"intro":{"declaration_year":"2015"}}