{"income":{"5":{"value":"271332","family_comment":"","value_unclear":false,"family_unclear":false,"comment_unclear":false,"comment":"","family":"11738"},"6":{"family_comment":"","value":"258715","comment_unclear":false,"family":"","comment":""},"7":{"family_comment":"","value":"","source_name":"","family":"","comment":""},"8":{"family_comment":"","value":"","family":"","comment":""},"9":{"family_comment":"","value":"","value_unclear":false,"family":"","comment":""},"10":{"family_comment":"","value":"12617","value_unclear":false,"family":"","comment":""},"11":{"family_comment":"","value":"","family":"","comment":""},"12":{"family_comment":"","value":"","family":"","comment":""},"13":{"family_comment":"","value":"","family":"","comment":""},"14":{"family_comment":"","value":"","family":"","comment":""},"15":{"family_comment":"","value":"","family":"","comment":""},"16":{"family_comment":"","value":"","family":"","comment":""},"17":{"family_comment":"","value":"","value_unclear":false,"family":"","comment":""},"18":{"family_comment":"","value":"","value_unclear":false,"family":"","comment":""},"19":{"family_comment":"","value":"","family":"","comment":""},"20":{"value":"","family_comment":"","value_unclear":false,"family_unclear":false,"comment_unclear":false,"comment":"","family":""}},"vehicle":{"35":[{"year_hidden":false,"brand_info":"1.6 куб. см.","sum_rent_comment":"","year":"2008","sum_hidden":false,"brand_info_hidden":false,"brand_info_unclear":false,"year_unclear":false,"sum_rent":"","sum":"","brand":"Hyundai Elantra","sum_comment":"","brand_unclear":false,"brand_hidden":false}]},"id":"vulyk_84_41","declaration":{"additional_info_text":"","notfull_lostpages":"","date":"2014-03-25T00:00:00","notfull":"","additional_info":"","url":"http://static.declarations.com.ua/declarations/chosen_ones/judges_batch/2455_kovaliumnus_ella_leonidivna.pdf"},"liabilities":{"54":{"sum_foreign_comment":"","sum_comment_hidden":false,"sum":"7129","sum_comment":"","sum_foreign":""},"55":{"sum_foreign_comment":"","sum":"","sum_comment":"","sum_foreign":""},"56":{"sum_foreign_comment":"","sum":"7681","sum_comment":"","sum_foreign":""},"57":{"sum_foreign_comment":"","sum_comment_hidden":false,"sum":"","sum_comment":"","sum_foreign":""},"58":{"sum_foreign_comment":"","sum_comment_hidden":false,"sum":"","sum_comment":"","sum_foreign":""},"59":{"sum_foreign_comment":"","sum":"","sum_comment":"","sum_foreign":""},"60":{"sum_foreign_comment":"","sum":"","sum_comment":"","sum_foreign":""},"61":{"sum_foreign_comment":"","sum":"","sum_comment":"","sum_foreign":""},"62":{"sum_foreign_comment":"","sum":"","sum_comment":"","sum_foreign":""},"63":{"sum_foreign_comment":"","sum_comment_hidden":false,"sum":"","sum_comment":"","sum_foreign":""},"64":{"sum_foreign_comment":"","sum_comment_hidden":false,"sum":"","sum_comment":"","sum_foreign":""}},"ft_src":"7129\n7681\nсуддя апеляційного суду донецької області\nДонецька область\nЗагальний апеляційний суд\nЕлла\nКовалюмнус В. С. (померла 18. 11. 2013\nБатьки\nЛеонідівна\nКовалюмнус Елла Леонідівна\nЕлла Леонідівна Ковалюмнус\nЕлла Ковалюмнус\nКовалюмнус Елла Леонідівна\nКовалюмнус Елла Леонідівна\nКовалюмнус\nHyundai Elantra\n1.6 куб. см.\n2008\n56\n2013\n258715\n12617\n11738\n271332\n1.6 куб. см.\nHyundai Elantra\n2008\n2013\nКовалюмнус Елла Леонідівна\nЕлла Леонідівна Ковалюмнус\nЕлла Ковалюмнус\nКовалюмнус Елла Леонідівна\nЕлла\nБатьки\nКовалюмнус В. С. (померла 18. 11. 2013\nКовалюмнус Елла Леонідівна\nЛеонідівна\nсуддя апеляційного суду донецької області\nЗагальний апеляційний суд\nДонецька область\nКовалюмнус\n7681\n7129\n258715\n271332\n11738\n12617\n56\n7681\n7129\nКовалюмнус В. С. (померла 18. 11. 2013\nБатьки\nЛеонідівна\nКовалюмнус\nЕлла\nКовалюмнус Елла Леонідівна\nЕлла Леонідівна Ковалюмнус\nЕлла Ковалюмнус\nКовалюмнус Елла Леонідівна\nДонецька область\nсуддя апеляційного суду донецької області\nЗагальний апеляційний суд\nКовалюмнус Елла Леонідівна\nHyundai Elantra\n1.6 куб. см.\n2008\n12617\n271332\n11738\n258715\n56\n2013","general":{"inn":"","name":"Елла","inn_unclear":false,"family":[{"inn":"","inn_hidden":true,"inn_unclear":false,"relations_hidden":false,"relations_other":"","relations":"Батьки","name_hidden":false,"family_name":"Ковалюмнус В. С. (померла 18. 11. 2013","name_unclear":false}],"inn_hidden":true,"family_raw":"","last_name":"Ковалюмнус","post":{"post_unclear":false,"region_unclear":false,"post":"суддя апеляційного суду донецької області","candidate":"","office_hidden":false,"region":"Донецька область","post_hidden":false,"office":"Загальний апеляційний суд","office_unclear":false,"region_hidden":false},"full_name":"Ковалюмнус Елла Леонідівна","addresses":[{"place_city_type_unclear":false,"place_address":"","place_district_hidden":true,"place_city_type":"","place_address_hidden":true,"place_address_unclear":false,"place_city_type_hidden":true,"place":"","place_district":"","place_unclear":false,"place_city":"","place_city_unclear":false,"place_hidden":true,"place_city_hidden":true,"place_district_unclear":false}],"patronymic":"Леонідівна","full_name_suggest":{"output":"Ковалюмнус Елла Леонідівна","input":["Ковалюмнус Елла Леонідівна","Елла Леонідівна Ковалюмнус","Елла Ковалюмнус"]}},"source":"VULYK","estate":{"24":[{"region_unclear":false,"space_unclear":false,"costs":"","costs_comment":"","address_hidden":false,"region_hidden":true,"space_comment":"","space_hidden":false,"space":"","address":"","region":"","address_unclear":false,"costs_rent_comment":"","space_units":"м²","costs_rent":""}],"25":[{"region_unclear":false,"space_hidden":false,"costs":"","costs_comment":"","address_hidden":false,"region_hidden":true,"space_comment":"","space":"56","address":"","costs_comment_unclear":false,"costs_rent_comment_unclear":false,"region":"","address_unclear":false,"costs_rent_comment":"","space_units":"м²","costs_rent":""}]},"intro":{"declaration_year":"2013","isnotdeclaration":"","declaration_year_unclear":false}}