{"income":{"5":{"value":"182965.8","family_comment":"","value_unclear":false,"family_hidden":false,"value_hidden":false,"family_unclear":false,"family":"1957.61","comment":""},"6":{"value":"181050.61","family_comment":"","value_unclear":false,"family_unclear":false,"family":"","comment":""},"7":{"source_name_unclear":false,"value":"","comment_hidden":false,"family_comment":"","source_name":"","family":"","comment":"","source_name_hidden":false},"8":{"family_comment":"","value":"","family":"","comment":""},"9":{"value":"1467.08","family_comment":"","value_unclear":false,"family_hidden":false,"family_unclear":false,"family":"","comment":"","family_comment_unclear":false},"10":{"family_comment":"","value":"","family":"","comment":""},"11":{"family_comment":"","value":"","family":"","comment":""},"12":{"family_comment":"","value":"","family":"","comment":""},"13":{"family_comment":"","value":"","family":"","comment":""},"14":{"family_comment":"","value":"","family":"","comment":""},"15":{"family_comment":"","value":"","family":"","comment":""},"16":{"family_comment":"","value":"","family":"","comment":""},"17":{"family_comment":"","value":"","family":"","comment":""},"18":{"family_comment":"","value":"","family":"","comment":""},"19":{"family_comment":"","value":"","family":"","comment":""},"20":{"value":"448.11","family_comment":"","value_unclear":false,"family_comment_hidden":false,"family_unclear":false,"family_comment_unclear":false,"comment_unclear":false,"comment":"","family":"1957.61"}},"vehicle":{"35":[{"year_hidden":false,"brand_info":"1997 куб. см., 140 к.с.","sum_rent_comment":"","year":"2008","brand_info_hidden":false,"brand_info_unclear":false,"sum_rent":"","sum":"","brand":"Nissan Qashqai","sum_comment":"","brand_unclear":false,"brand_hidden":false}],"40":[{"brand_info":"1997 куб. см., 150 к.с.","sum_rent_comment":"","brand":"Honda CR-V","sum_comment":"","year":"2008","brand_info_unclear":false,"sum":"","sum_rent":""}]},"id":"vulyk_93_49","banks":{"45":[{"sum_units":"UAH","sum_foreign":"","sum_hidden":false,"sum":"87516.11","sum_units_hidden":false,"sum_foreign_comment":"","sum_foreign_hidden":false,"sum_comment":"Приватбанк","sum_comment_unclear":false,"sum_foreign_units":"UAH","sum_units_unclear":false,"sum_comment_hidden":false,"sum_unclear":false}]},"declaration":{"additional_info_text":"","notfull_lostpages":"","date":"2015-03-31T00:00:00","notfull":"","additional_info":"","url":"http://static.declarations.com.ua/declarations/chosen_ones/judges_batch/3495_kravtsiv_oleh_romanovych.pdf"},"liabilities":{"54":{"sum_foreign_comment":"","sum":"","sum_hidden":false,"sum_comment":"","sum_foreign":""},"55":{"sum_foreign_comment":"","sum":"","sum_comment":"","sum_foreign":""},"56":{"sum_foreign_comment":"","sum":"","sum_comment":"","sum_foreign":""},"57":{"sum_foreign_comment":"","sum":"","sum_comment":"","sum_hidden":false,"sum_comment_hidden":false,"sum_unclear":false,"sum_foreign":""},"58":{"sum_foreign_comment":"","sum":"","sum_comment":"","sum_comment_unclear":false,"sum_hidden":false,"sum_unclear":false,"sum_foreign":""},"59":{"sum_foreign_comment":"","sum":"","sum_comment":"","sum_foreign":""},"60":{"sum_foreign_comment":"","sum":"","sum_hidden":false,"sum_comment":"","sum_foreign":""},"61":{"sum_foreign_comment":"","sum":"","sum_comment":"","sum_foreign":""},"62":{"sum_foreign_comment":"","sum":"","sum_comment":"","sum_foreign":""},"63":{"sum_foreign_comment":"","sum":"","sum_comment":"","sum_foreign":""},"64":{"sum_foreign_comment":"","sum":"","sum_comment":"","sum_foreign":""}},"ft_src":"Кравців Олег Романович\nсуддя львівського окружного адміністративного суду\nЛьвівська область\nАдміністративний місцевий суд\nОлег\nПронь О. Р\nПодружжя\nКравців І. О\nДитина\nКравців Д. О\nДитина\nКравців Я. О\nДитина\nКравців С. О\nДитина\nКравців Олег Романович\nОлег Романович Кравців\nОлег Кравців\nКравців Олег Романович\nКравців\nРоманович\n1997 куб. см., 140 к.с.\nNissan Qashqai\n2008\n1997 куб. см., 150 к.с.\n2008\nHonda CR-V\n46.6\n800\n281.1\n521\n291.3\n119.2\n92\nПриватбанк\n87516.11\n2014\n1997 куб. см., 140 к.с.\nNissan Qashqai\n2008\n1997 куб. см., 150 к.с.\nHonda CR-V\n2008\n46.6\n291.3\n92\n521\n800\n281.1\n119.2\nКравців\nПодружжя\nПронь О. Р\nДитина\nКравців І. О\nДитина\nКравців Д. О\nДитина\nКравців Я. О\nКравців С. О\nДитина\nКравців Олег Романович\nОлег Романович Кравців\nОлег Кравців\nКравців Олег Романович\nКравців Олег Романович\nОлег\nРоманович\nЛьвівська область\nАдміністративний місцевий суд\nсуддя львівського окружного адміністративного суду\n181050.61\n1957.61\n448.11\n182965.8\n1957.61\n1467.08\nПриватбанк\n87516.11\n2014\n181050.61\n1467.08\n1957.61\n182965.8\n1957.61\n448.11\nПодружжя\nПронь О. Р\nДитина\nКравців І. О\nДитина\nКравців Д. О\nКравців Я. О\nДитина\nДитина\nКравців С. О\nКравців\nРоманович\nЛьвівська область\nАдміністративний місцевий суд\nсуддя львівського окружного адміністративного суду\nКравців Олег Романович\nКравців Олег Романович\nОлег Романович Кравців\nОлег Кравців\nКравців Олег Романович\nОлег\nNissan Qashqai\n1997 куб. см., 140 к.с.\n2008\n2008\n1997 куб. см., 150 к.с.\nHonda CR-V\n1467.08\n448.11\n1957.61\n182965.8\n1957.61\n181050.61\n119.2\n521\n281.1\n46.6\n291.3\n92\n800\n87516.11\nПриватбанк\n2014","general":{"inn":"","inn_hidden":true,"last_name":"Кравців","post":{"post_unclear":false,"region_unclear":false,"region":"Львівська область","candidate":"","post":"суддя львівського окружного адміністративного суду","office":"Адміністративний місцевий суд","office_unclear":false},"name":"Олег","full_name":"Кравців Олег Романович","family_raw":"","addresses":[{"place_district":"","place_city_hidden":true,"place_city":"","place_city_type_hidden":true,"place_district_hidden":true,"place_city_type":"","place_address_hidden":true,"place_address":"","place_hidden":true,"place":""}],"family":[{"inn":"","relations":"Подружжя","relations_hidden":false,"inn_hidden":true,"relations_other":"","name_hidden":true,"family_name":"Пронь О. Р","name_unclear":false},{"inn":"","relations":"Дитина","relations_other":"","inn_hidden":false,"family_name":"Кравців І. О","name_hidden":false,"name_unclear":false},{"inn":"","relations":"Дитина","relations_other":"","inn_hidden":false,"family_name":"Кравців Д. О","name_hidden":false,"name_unclear":false},{"inn":"","relations":"Дитина","relations_other":"","inn_hidden":false,"family_name":"Кравців Я. О","name_hidden":false},{"inn":"","family_name":"Кравців С. О","relations":"Дитина","relations_other":""}],"full_name_suggest":{"output":"Кравців Олег Романович","input":["Кравців Олег Романович","Олег Романович Кравців","Олег Кравців"]},"patronymic":"Романович"},"source":"VULYK","estate":{"23":[{"space_unclear":false,"costs":"","costs_comment":"","address_hidden":true,"region_hidden":true,"space_comment":"","space":"521","address":"","region":"","costs_rent_comment":"","space_comment_unclear":false,"space_units":"м²","costs_rent":""}],"24":[{"space_unclear":false,"costs":"","costs_comment":"","address_hidden":true,"region_hidden":true,"space_comment":"","space":"281.1","address":"","region":"","costs_rent_comment":"","space_comment_unclear":false,"space_units":"м²","costs_rent":""}],"25":[{"space_hidden":false,"costs":"","costs_comment":"","address_hidden":true,"region_hidden":true,"space_comment":"","space_unclear":false,"space":"92","address":"","costs_rent_comment_unclear":false,"region":"","costs_rent_comment":"","space_units":"м²","costs_rent":""}],"27":[{"costs_rent":"","region":"","costs":"","costs_rent_comment":"","costs_comment":"","address_hidden":true,"region_hidden":true,"space_comment":"","space_units":"м²","space":"46.6","address":""}],"29":[{"space_unclear":false,"address_hidden":true,"region_hidden":true,"space_comment":"","space":"800","address":"","region":"","costs_property":"","costs_rent_comment":"","space_comment_unclear":false,"space_units":"м²","costs_property_comment":"","costs_rent":""}],"30":[{"space_unclear":false,"address_hidden":true,"region_hidden":true,"space_comment":"","space":"291.3","address":"","region":"","costs_property":"","costs_rent_comment":"","space_units":"м²","costs_property_comment":"","costs_rent":""}],"31":[{"space_hidden":false,"address_hidden":true,"region_hidden":true,"space_comment":"","space":"119.2","address":"","region":"","costs_property":"","costs_rent_comment":"","space_comment_unclear":false,"space_units":"м²","costs_property_comment":"","costs_rent":""}]},"intro":{"declaration_year":"2014","isnotdeclaration":""}}