{"income":{"5":{"value":"242535.94","family_comment":"","value_unclear":false,"family_hidden":false,"value_hidden":false,"family_unclear":false,"family":"11376","comment":"","family_comment_unclear":false},"6":{"family_comment":"","family_unclear":false,"value":"229137.94","family":"","comment":""},"7":{"source_name_unclear":false,"value":"","family_comment":"","source_name":"","family":"","comment":"","source_name_hidden":false},"8":{"family_comment":"","value":"","family":"","comment":""},"9":{"family_comment":"","family_unclear":false,"value":"","family":"","comment":""},"10":{"family_comment":"","value":"13398","family":"","comment":""},"11":{"family_comment":"","value":"","family":"","comment":""},"12":{"family_comment":"","value":"","family":"","comment":""},"13":{"family_comment":"","value":"","family":"","comment":""},"14":{"family_comment":"","value":"","family":"","comment":""},"15":{"family_comment":"","value":"","family":"","comment":""},"16":{"value":"","value_unclear":false,"value_hidden":false,"family_comment":"","family":"","comment":""},"17":{"family_comment":"","value":"","family":"","comment":""},"18":{"family_comment":"","value":"","family":"","comment":""},"19":{"family_comment":"","value":"","family":"","comment":""},"20":{"value":"","family_comment":"","value_unclear":false,"comment_hidden":false,"family_hidden":false,"family":"11376","value_hidden":false,"family_unclear":false,"comment_unclear":false,"comment":"","family_comment_unclear":false}},"vehicle":{"40":[{"brand_info":"2354 куб см, 457.5 см","sum":"","brand":"Honda CR-V","sum_comment":"","brand_unclear":false,"year":"2010","brand_hidden":false,"brand_info_hidden":false,"brand_info_unclear":false,"sum_rent_comment":"","sum_rent":""}]},"id":"vulyk_62_33","banks":{"45":[{"sum_units":"UAH","sum_hidden":false,"sum_foreign_units_hidden":false,"sum":"200000","sum_foreign":"","sum_foreign_comment":"","sum_foreign_hidden":false,"sum_comment":"","sum_comment_unclear":false,"sum_foreign_units":"UAH","sum_comment_hidden":false,"sum_unclear":false}],"46":[{"sum_units":"UAH","sum_hidden":false,"sum_foreign_units_hidden":false,"sum":"200000","sum_foreign":"","sum_foreign_comment":"","sum_foreign_hidden":false,"sum_comment":"","sum_comment_unclear":false,"sum_foreign_units":"UAH","sum_comment_hidden":false,"sum_unclear":false}],"51":[{"sum_units":"UAH","sum_hidden":false,"sum_foreign_units_hidden":false,"sum":"200000","sum_foreign":"","sum_foreign_comment":"","sum_foreign_hidden":false,"sum_comment":"","sum_comment_unclear":false,"sum_foreign_units":"UAH","sum_comment_hidden":false,"sum_unclear":false}]},"declaration":{"additional_info_text":"","notfull_lostpages":"","date":"2015-03-27T00:00:00","notfull":"","additional_info":"","url":"http://static.declarations.com.ua/declarations/chosen_ones/mega_batch/hul_v’yacheslav_volodymyrovych.pdf"},"liabilities":{"54":{"sum_foreign_comment":"","sum":"","sum_comment":"","sum_hidden":false,"sum_comment_hidden":false,"sum_foreign":""},"55":{"sum_foreign_comment":"","sum":"","sum_comment":"","sum_hidden":false,"sum_comment_hidden":false,"sum_unclear":false,"sum_foreign":""},"56":{"sum_foreign_comment":"","sum":"2900","sum_comment":"","sum_hidden":false,"sum_unclear":false,"sum_foreign":""},"57":{"sum_foreign_comment":"","sum":"","sum_comment":"","sum_hidden":false,"sum_comment_hidden":false,"sum_unclear":false,"sum_foreign":""},"58":{"sum_foreign_comment":"","sum_foreign_hidden":false,"sum_comment":"","sum_hidden":false,"sum_comment_hidden":false,"sum_unclear":false,"sum":"","sum_foreign":""},"59":{"sum_foreign_comment":"","sum":"","sum_comment":"","sum_foreign":""},"60":{"sum_foreign_comment":"","sum_foreign_hidden":false,"sum_comment":"","sum_hidden":false,"sum_comment_hidden":false,"sum_unclear":false,"sum":"","sum_foreign":""},"61":{"sum_foreign_comment":"","sum_foreign_hidden":false,"sum_comment":"","sum_hidden":false,"sum":"","sum_foreign":""},"62":{"sum_foreign_comment":"","sum":"","sum_comment":"","sum_unclear":false,"sum_foreign":""},"63":{"sum_foreign_comment":"","sum":"","sum_comment":"","sum_hidden":false,"sum_comment_hidden":false,"sum_unclear":false,"sum_foreign":""},"64":{"sum_foreign_comment":"","sum":"","sum_comment":"","sum_comment_unclear":false,"sum_hidden":false,"sum_comment_hidden":false,"sum_foreign":""}},"ft_src":"2900\nсуддя апеляційного суду київської області\nКиївська область\nЗагальний апеляційний суд\nВ'ячеслав\nГуль Л. О\nПодружжя\nГуль Т. В\nДитина\nГуль А. В\nДитина\nВолодимирович\nГуль В'ячеслав Володимирович\nВ'ячеслав Володимирович Гуль\nВ'ячеслав Гуль\nГуль В'ячеслав Володимирович\nГуль В'ячеслав Володимирович\nГуль\nHonda CR-V\n2354 куб см, 457.5 см\n2010\n200000\n200000\n200000\n2014\n2354 куб см, 457.5 см\n2010\nHonda CR-V\n200000\n200000\n200000\n1200\nприватизація\nГуль В'ячеслав Володимирович\nВ'ячеслав Володимирович Гуль\nВ'ячеслав Гуль\nГуль В'ячеслав Володимирович\nГуль В'ячеслав Володимирович\nПодружжя\nГуль Л. О\nДитина\nГуль Т. В\nДитина\nГуль А. В\nВ'ячеслав\nВолодимирович\nЗагальний апеляційний суд\nсуддя апеляційного суду київської області\nКиївська область\nГуль\n2900\n229137.94\n11376\n242535.94\n11376\n13398\n2014\n2900\nприватизація\n1200\nПодружжя\nГуль Л. О\nГуль Т. В\nДитина\nГуль А. В\nДитина\nВолодимирович\nГуль\nВ'ячеслав\nГуль В'ячеслав Володимирович\nВ'ячеслав Володимирович Гуль\nВ'ячеслав Гуль\nГуль В'ячеслав Володимирович\nКиївська область\nсуддя апеляційного суду київської області\nЗагальний апеляційний суд\nГуль В'ячеслав Володимирович\n229137.94\n13398\n11376\n242535.94\n11376\nHonda CR-V\n2354 куб см, 457.5 см\n2010\n13398\n11376\n242535.94\n11376\n229137.94\nприватизація\n1200\n200000\n200000\n200000\n2014","general":{"inn":"","name":"В'ячеслав","inn_unclear":false,"family":[{"inn":"","inn_hidden":false,"relations_unclear":false,"relations_hidden":false,"relations_other":"","relations":"Подружжя","name_hidden":false,"inn_unclear":false,"family_name":"Гуль Л. О","name_unclear":false},{"inn":"","inn_hidden":false,"relations_hidden":false,"family_name":"Гуль Т. В","relations_other":"","relations":"Дитина","name_hidden":false,"name_unclear":false},{"inn":"","relations":"Дитина","relations_other":"","inn_hidden":false,"family_name":"Гуль А. В","name_hidden":false,"name_unclear":false}],"inn_hidden":false,"family_raw":"","last_name":"Гуль","post":{"post_unclear":false,"post":"суддя апеляційного суду київської області","post_hidden":false,"region":"Київська область","region_hidden":false,"office":"Загальний апеляційний суд","office_hidden":false,"office_unclear":false},"full_name_suggest":{"output":"Гуль В'ячеслав Володимирович","input":["Гуль В'ячеслав Володимирович","В'ячеслав Володимирович Гуль","В'ячеслав Гуль"]},"full_name":"Гуль В'ячеслав Володимирович","patronymic":"Володимирович","last_name_unclear":false,"name_unclear":false},"source":"VULYK","estate":{"23":[{"region_unclear":false,"space_unclear":false,"costs":"","costs_comment":"","costs_hidden":false,"address_hidden":false,"region_hidden":false,"space_comment":"приватизація","space":"1200","address":"","region":"","address_unclear":false,"space_units_unclear":false,"space_comment_unclear":false,"space_units":"м²","space_units_hidden":false,"costs_rent":"","costs_rent_comment":""}]},"intro":{"declaration_year":"2014","isnotdeclaration":"","declaration_year_unclear":false,"declaration_year_hidden":false}}