{"income":{"5":{"family_comment":"","value":"","family":"","comment":""},"6":{"value":"258502.48","family_comment":"","value_unclear":false,"comment_hidden":false,"family_unclear":false,"family":"26557.55","comment":"дві суми: 258382,89 та 119,59"},"7":{"family_comment":"","value":"","source_name":"","family":"","comment":""},"8":{"family_comment":"","value":"","family":"","comment":""},"9":{"family_comment":"","family_unclear":false,"value":"","family":"","comment":""},"10":{"family_comment":"","value":"","value_unclear":false,"family":"","comment":""},"11":{"family_comment":"","value":"","family":"","comment":""},"12":{"family_comment":"","value":"","family":"","comment":""},"13":{"family_comment":"","value":"","family":"","comment":""},"14":{"family_comment":"","value":"","family":"","comment":""},"15":{"family_comment":"","value":"","family":"","comment":""},"16":{"family_comment":"","value":"","family":"","comment":""},"17":{"family_comment":"","value":"","family":"","comment":""},"18":{"family_comment":"","value":"","family":"","comment":""},"19":{"family_comment":"","value":"","family":"","comment":""},"20":{"value":"","family":"","value_unclear":false,"family_hidden":false,"family_comment":"","comment_unclear":false,"comment":"","family_comment_unclear":false}},"vehicle":{"35":[{"year_hidden":false,"brand_info":"1.9 куб. дм","sum_rent_comment":"","year":"2008","brand_info_hidden":false,"brand_info_unclear":false,"sum_rent":"","sum":"","brand":"Skoda Octavia","sum_comment":"","brand_unclear":false,"brand_hidden":false},{"brand_info":"1.5 куб. дм","sum_rent_comment":"","brand":"ВАЗ 2103","sum_comment":"","brand_unclear":false,"year":"1980","brand_info_hidden":false,"brand_info_unclear":false,"year_unclear":false,"sum":"","sum_rent":""}],"44":[{"brand_info":"мотоцикл","sum_rent_comment":"","brand":"Viper 125","sum_comment":"","year":"2006","brand_hidden":false,"sum":"","sum_rent":""}]},"id":"vulyk_97_38","declaration":{"additional_info_text":"","notfull_lostpages":"","date":"2015-03-30T00:00:00","notfull":"","additional_info":"","url":"http://static.declarations.com.ua/declarations/chosen_ones/judges_batch/3866_melnychenko_iurii_volodymyrovych.pdf"},"liabilities":{"54":{"sum_foreign_comment":"","sum":"","sum_comment":"","sum_comment_unclear":false,"sum_hidden":false,"sum_comment_hidden":false,"sum_unclear":false,"sum_foreign":""},"55":{"sum_foreign_comment":"","sum":"","sum_comment":"","sum_foreign":""},"56":{"sum_foreign_comment":"","sum":"","sum_comment":"","sum_foreign":""},"57":{"sum_foreign_comment":"","sum":"","sum_comment":"","sum_comment_unclear":false,"sum_hidden":false,"sum_comment_hidden":false,"sum_unclear":false,"sum_foreign":""},"58":{"sum_foreign_comment":"","sum":"","sum_comment":"","sum_comment_unclear":false,"sum_hidden":false,"sum_comment_hidden":false,"sum_unclear":false,"sum_foreign":""},"59":{"sum_foreign_comment":"","sum":"","sum_comment":"","sum_foreign":""},"60":{"sum_foreign_comment":"","sum":"","sum_comment":"","sum_comment_unclear":false,"sum_hidden":false,"sum_comment_hidden":false,"sum_foreign":""},"61":{"sum_foreign_comment":"","sum":"","sum_comment":"","sum_foreign":""},"62":{"sum_foreign_comment":"","sum":"","sum_comment":"","sum_unclear":false,"sum_foreign":""},"63":{"sum_foreign_comment":"","sum":"","sum_hidden":false,"sum_comment":"","sum_foreign":""},"64":{"sum_foreign_comment":"","sum":"","sum_comment":"","sum_foreign":""}},"ft_src":"суддя апеляційного суду чернігівської області\nЧернігівська область\nЗагальний апеляційний суд\nЮрій\nМельниченко Тамара Іванівна\nПодружжя\nВолодимирович\nМельниченко Юрій Володимирович\nЮрій Володимирович Мельниченко\nЮрій Мельниченко\nМельниченко Юрій Володимирович\nМельниченко Юрій Володимирович\nМельниченко\n1.9 куб. дм\nSkoda Octavia\n2008\nВАЗ 2103\n1.5 куб. дм\n1980\n2006\nмотоцикл\nViper 125\n1000\n53\n53\n2014\n26557.55\nдві суми: 258382,89 та 119,59\n258502.48\n1.9 куб. дм\nSkoda Octavia\n2008\nВАЗ 2103\n1.5 куб. дм\n1980\nмотоцикл\n2006\nViper 125\n2014\nМельниченко Юрій Володимирович\nЮрій Володимирович Мельниченко\nЮрій Мельниченко\nМельниченко Юрій Володимирович\nЮрій\nПодружжя\nМельниченко Тамара Іванівна\nМельниченко Юрій Володимирович\nМельниченко\nЗагальний апеляційний суд\nЧернігівська область\nсуддя апеляційного суду чернігівської області\nВолодимирович\nдві суми: 258382,89 та 119,59\n258502.48\n26557.55\n1000\n53\n53\nПодружжя\nМельниченко Тамара Іванівна\nВолодимирович\nМельниченко\nЮрій\nМельниченко Юрій Володимирович\nЮрій Володимирович Мельниченко\nЮрій Мельниченко\nМельниченко Юрій Володимирович\nЧернігівська область\nЗагальний апеляційний суд\nсуддя апеляційного суду чернігівської області\nМельниченко Юрій Володимирович\n2006\nмотоцикл\nViper 125\n2008\nSkoda Octavia\n1.9 куб. дм\n1980\nВАЗ 2103\n1.5 куб. дм\nдві суми: 258382,89 та 119,59\n258502.48\n26557.55\n53\n1000\n53\n2014","general":{"name_hidden":false,"name":"Юрій","last_name_hidden":false,"inn":"","family":[{"inn":"","relations":"Подружжя","relations_other":"","inn_hidden":true,"family_name":"Мельниченко Тамара Іванівна","name_hidden":true,"name_unclear":false}],"patronymic":"Володимирович","inn_hidden":true,"family_raw":"","inn_unclear":false,"post":{"region_unclear":false,"region":"Чернігівська область","post":"суддя апеляційного суду чернігівської області","office":"Загальний апеляційний суд","office_unclear":false,"post_hidden":false},"full_name":"Мельниченко Юрій Володимирович","addresses":[{"place_district":"","place_city_hidden":true,"place_city":"","place_city_unclear":false,"place_district_hidden":false,"place_city_type":"","place_address_hidden":true,"place_city_type_hidden":false,"place_address":"","place_hidden":true,"place":""}],"last_name":"Мельниченко","patronymic_hidden":false,"full_name_suggest":{"output":"Мельниченко Юрій Володимирович","input":["Мельниченко Юрій Володимирович","Юрій Володимирович Мельниченко","Юрій Мельниченко"]}},"source":"VULYK","estate":{"23":[{"region_unclear":false,"space_unclear":false,"costs":"","costs_rent_unclear":false,"costs_comment":"","address_hidden":false,"region_hidden":true,"space_comment":"","space":"1000","address":"","region":"","address_unclear":false,"costs_rent_comment":"","space_units":"м²","costs_rent":""}],"25":[{"region_unclear":false,"space_unclear":false,"costs":"","costs_comment":"","address_hidden":false,"region_hidden":true,"space_comment":"","space_hidden":false,"space":"53","address":"","region":"","costs_rent_comment":"","space_comment_unclear":false,"space_comment_hidden":false,"space_units":"м²","costs_rent":""}],"31":[{"space_unclear":false,"address_hidden":false,"region_hidden":true,"space_comment":"","space_hidden":false,"space":"53","address":"","region":"","costs_property":"","costs_rent_comment":"","space_comment_hidden":false,"space_units":"м²","costs_property_comment":"","costs_rent":""}]},"intro":{"declaration_year":"2014","isnotdeclaration":""}}