{"income":{"5":{"value":"254057.18","family_comment":"","family_hidden":false,"value_hidden":false,"family_unclear":false,"family":"","comment":""},"6":{"value":"220109.4","comment_unclear":false,"family_comment":"","family":"","comment":"","family_comment_unclear":false},"7":{"family_comment":"","value":"","source_name":"","family":"","comment":""},"8":{"family_comment":"","value":"","family":"","comment":""},"9":{"family_comment":"","value":"","family":"","comment":""},"10":{"family_comment":"","value":"12180","family":"","comment":""},"11":{"family_comment":"","value":"","family":"","comment":"","family_comment_unclear":false},"12":{"family_comment":"","value":"","family":"","comment":""},"13":{"family_comment":"","value":"","family":"","comment":""},"14":{"family_comment":"","value":"","family":"","comment":""},"15":{"family_comment":"","value":"","family":"","comment":""},"16":{"family_comment":"","value":"","family":"","comment":""},"17":{"family_comment":"","value":"","family":"","comment":""},"18":{"family_comment":"","value":"","family":"","comment":""},"19":{"family_comment":"","value":"","family":"","comment":"","value_hidden":false},"20":{"family_comment":"","value":"21767.78","comment_unclear":false,"family":"","comment":""}},"vehicle":{"35":[{"brand_info":"1998 куб. см.","sum_rent_comment":"","brand":"Chevrolet","sum_comment":"","sum_rent_hidden":false,"year":"2005","sum_hidden":false,"brand_info_hidden":false,"brand_info_unclear":false,"sum":"","sum_rent":""}]},"id":"vulyk_51_183","banks":{"45":[{"sum_foreign_comment":"","sum_units":"UAH","sum_comment":"","sum_comment_unclear":false,"sum_hidden":false,"sum_foreign_units":"UAH","sum_comment_hidden":false,"sum":"49454.37","sum_foreign":""},{"sum_foreign_comment":"","sum_units":"","sum_comment":"","sum_foreign_units":"","sum":"","sum_foreign":""},{"sum_foreign_comment":"","sum_units":"","sum_comment":"","sum_foreign_units":"","sum":"","sum_foreign":""},{"sum_foreign_comment":"","sum_units":"","sum_comment":"","sum_foreign_units":"","sum":"","sum_foreign":""},{"sum_foreign_comment":"","sum_units":"","sum_comment":"","sum_foreign_units":"","sum":"","sum_unclear":false,"sum_foreign":""}],"46":[{"sum_foreign_comment":"","sum_units":"UAH","sum_comment":"","sum_foreign_units":"UAH","sum":"","sum_foreign":""}],"47":[{"sum_foreign_comment":"","sum_units":"UAH","sum_comment":"","sum_foreign_units":"UAH","sum":"","sum_foreign":""}],"48":[{"sum_foreign_comment":"","sum_units":"UAH","sum_comment":"","sum_foreign_units":"UAH","sum":"","sum_foreign":""}],"49":[{"sum_foreign_comment":"","sum_units":"UAH","sum_comment":"","sum_foreign_units":"UAH","sum":"","sum_foreign":""}],"50":[{"sum_foreign_comment":"","sum_units":"UAH","sum_comment":"","sum_foreign_units":"UAH","sum":"","sum_foreign":""}],"51":[{"sum_foreign_comment":"","sum_units":"UAH","sum_comment":"","sum_foreign_units":"UAH","sum_comment_hidden":false,"sum":"","sum_foreign":""},{"sum_foreign_comment":"","sum_units":"","sum_comment":"","sum_foreign_units":"","sum":"","sum_foreign":""},{"sum_foreign_comment":"","sum_units":"","sum_comment":"","sum_foreign_units":"","sum":"","sum_foreign":""}],"52":[{"sum_foreign_comment":"","sum_units":"UAH","sum_comment":"","sum_foreign_units":"UAH","sum_comment_hidden":false,"sum":"","sum_foreign":""}],"53":[{"sum_foreign_comment":"","sum_units":"UAH","sum_comment":"","sum_foreign_units":"UAH","sum":"","sum_foreign":""}]},"declaration":{"additional_info_text":"","notfull_lostpages":"","date":"2015-03-27T00:00:00","notfull":"","additional_info":"","url":"http://static.declarations.com.ua/declarations/chosen_ones/mega_batch/kolupaiev_valerii_viktorovych.pdf"},"liabilities":{"54":{"sum_foreign_comment":"","sum_comment_hidden":false,"sum":"","sum_comment":"","sum_foreign":""},"55":{"sum_foreign_comment":"","sum":"","sum_comment":"","sum_foreign":""},"56":{"sum_foreign_comment":"","sum":"","sum_comment":"","sum_foreign":""},"57":{"sum_foreign_comment":"","sum":"","sum_comment":"","sum_hidden":false,"sum_comment_hidden":false,"sum_foreign":""},"58":{"sum_foreign_comment":"","sum_comment_hidden":false,"sum":"","sum_comment":"","sum_foreign":""},"59":{"sum_foreign_comment":"","sum":"","sum_comment":"","sum_foreign":""},"60":{"sum_foreign_comment":"","sum":"","sum_comment":"","sum_foreign":""},"61":{"sum_foreign_comment":"","sum":"","sum_comment":"","sum_foreign":""},"62":{"sum_foreign_comment":"","sum":"","sum_comment":"","sum_foreign":""},"63":{"sum_foreign_comment":"","sum_comment_hidden":false,"sum":"","sum_comment":"","sum_foreign":""},"64":{"sum_foreign_comment":"","sum":"","sum_comment":"","sum_foreign":""}},"ft_src":"Житомир\n10014\nЖитомирська область\nКолупаєв Валерій Вікторович\nсуддя корольовського районного суду м. житомира\nЖитомирська область\nЗагальний місцевий суд\nВалерій\nКолупаєва Анастасія Валерієвна, 24. 03. 2000 р/н\nДитина\nКолупаєв Валерій Вікторович\nВалерій Вікторович Колупаєв\nВалерій Колупаєв\nКолупаєв Валерій Вікторович\nКолупаєв\nВікторович\nChevrolet\n1998 куб. см.\n2005\n49454.37\n2014\n1998 куб. см.\n2005\nChevrolet\n49454.37\n.15\nЖитомирська область\nсмт Гуйва, Житомирський р-н\nЖитомирська область\nм. Житомир\n49.5\n49.5\nЖитомирська область\nм. Житомир\nКолупаєв\nКолупаєв Валерій Вікторович\nВалерій Вікторович Колупаєв\nВалерій Колупаєв\nКолупаєв Валерій Вікторович\nВалерій\nВікторович\n10014\nЖитомирська область\nЖитомир\nКолупаєв Валерій Вікторович\nЗагальний місцевий суд\nсуддя корольовського районного суду м. житомира\nЖитомирська область\nДитина\nКолупаєва Анастасія Валерієвна, 24. 03. 2000 р/н\n220109.4\n21767.78\n254057.18\n12180\n2014\nсмт Гуйва, Житомирський р-н\n.15\nЖитомирська область\nЖитомирська область\nм. Житомир\n49.5\nм. Житомир\n49.5\nЖитомирська область\nКолупаєва Анастасія Валерієвна, 24. 03. 2000 р/н\nДитина\nВікторович\nЖитомирська область\nЖитомир\n10014\nКолупаєв\nЖитомирська область\nЗагальний місцевий суд\nсуддя корольовського районного суду м. житомира\nКолупаєв Валерій Вікторович\nКолупаєв Валерій Вікторович\nВалерій Вікторович Колупаєв\nВалерій Колупаєв\nКолупаєв Валерій Вікторович\nВалерій\n220109.4\n12180\n254057.18\n21767.78\n2005\nChevrolet\n1998 куб. см.\n12180\n21767.78\n254057.18\n220109.4\nЖитомирська область\nм. Житомир\n49.5\nсмт Гуйва, Житомирський р-н\nЖитомирська область\n.15\nм. Житомир\nЖитомирська область\n49.5\n49454.37\n2014","general":{"inn":"","inn_hidden":true,"last_name":"Колупаєв","post":{"post":"суддя корольовського районного суду м. житомира","region":"Житомирська область","office_hidden":false,"office":"Загальний місцевий суд","office_unclear":false,"region_hidden":false},"name":"Валерій","full_name":"Колупаєв Валерій Вікторович","family_raw":"","addresses":[{"place_district":"","place_city_hidden":false,"place_city":"Житомир","place_city_type_hidden":false,"place_district_hidden":false,"place_city_type":"Місто","place_address_hidden":true,"place_address":"10014","place_hidden":false,"place":"Житомирська область"}],"family":[{"inn":"","relations":"Дитина","relations_other":"","inn_hidden":true,"family_name":"Колупаєва Анастасія Валерієвна, 24. 03. 2000 р/н","name_hidden":false,"name_unclear":false}],"full_name_suggest":{"output":"Колупаєв Валерій Вікторович","input":["Колупаєв Валерій Вікторович","Валерій Вікторович Колупаєв","Валерій Колупаєв"]},"patronymic":"Вікторович"},"source":"VULYK","estate":{"23":[{"costs":"","costs_comment":"","costs_hidden":false,"address_hidden":false,"region_hidden":false,"space_comment":"","space":".15","address":"смт Гуйва, Житомирський р-н","region":"Житомирська область","address_unclear":false,"costs_rent_comment":"","costs_rent_hidden":false,"space_units":"га","costs_rent":""},{"costs":"","costs_comment":"","costs_hidden":false,"region_hidden":false,"space_comment":"","space":"","address":"","region":"","costs_rent_comment":"","costs_rent_hidden":false,"space_units":"","costs_rent":""},{"space":"","region":"","costs":"","costs_rent_comment":"","costs_comment":"","address_unclear":false,"space_comment":"","space_units":"","costs_rent":"","address":""},{"costs_rent":"","region":"","costs":"","costs_rent_comment":"","costs_comment":"","space_comment":"","space_units":"","space":"","address":""}],"25":[{"space_unclear":false,"costs":"","costs_comment":"","costs_hidden":false,"address_hidden":true,"region_hidden":false,"space_comment":"","space_hidden":false,"space":"49.5","address":"м. Житомир","region":"Житомирська область","address_unclear":false,"costs_rent_comment":"","space_units":"м²","costs_rent":""}],"31":[{"space_hidden":false,"costs_property_hidden":false,"address_hidden":true,"region_hidden":false,"space_comment":"","space_unclear":false,"space":"49.5","address":"м. Житомир","region":"Житомирська область","address_unclear":false,"costs_rent_comment":"","costs_rent_hidden":false,"costs_property":"","space_units":"м²","costs_property_comment":"","costs_rent":""}]},"intro":{"declaration_year":"2014","isnotdeclaration":""}}