{"income":{"5":{"family_comment":"","value":"12930","family":"23953","comment":""},"6":{"family_comment":"","value":"","family_hidden":false,"comment":"","family":""},"7":{"family_comment":"","value":"","source_name":"","family":"","comment":""},"8":{"family_comment":"","value":"","family":"","comment":""},"9":{"value":"","value_unclear":false,"family_hidden":false,"family_comment":"","family":"","comment":""},"10":{"value":"","family_comment":"","family_hidden":false,"value_hidden":false,"family_unclear":false,"family":"","comment":""},"11":{"family_comment":"","value":"","family":"","comment":""},"12":{"family_comment":"","value":"","family":"","comment":""},"13":{"family_comment":"","value":"","family":"","comment":""},"14":{"family_comment":"","value":"","family":"","comment":""},"15":{"family_comment":"","value":"","family":"","comment":""},"16":{"family_comment":"","value":"","family":"","comment":""},"17":{"family_comment":"","value":"","family":"","comment":""},"18":{"family_comment":"","value":"","family":"","comment":""},"19":{"family_comment":"","value":"","family":"","comment":""},"20":{"value":"12930","comment_unclear":false,"family_comment":"","family":"","comment":"допомога при народженні дитини","family_comment_unclear":false},"22":[{"cur":"1883","cur_units":"USD","country":"США","uah_equal":"23953","country_comment":""}]},"vehicle":{"40":[{"brand_info":"2400 куб. см.","sum_rent_comment":"","brand":"Toyota Avensis","sum_comment":"","year":"2005","brand_info_unclear":false,"sum":"","sum_rent":""},{"brand_info":"1250 куб. см.","sum_rent_comment":"","brand":"Ford Fiesta","sum_comment":"","brand_unclear":false,"year":"2007","sum":"","sum_rent":""}]},"id":"vulyk_75_90","declaration":{"additional_info_text":"","notfull_lostpages":"","date":"2015-03-26T00:00:00","notfull":"","additional_info":"","url":"http://static.declarations.com.ua/declarations/chosen_ones/judges_batch/1845_dvirna_iuliia_heorhiivna.pdf"},"liabilities":{"54":{"sum_foreign_comment":"","sum":"","sum_comment":"","sum_foreign":""},"55":{"sum_foreign_comment":"","sum":"","sum_comment":"","sum_foreign":""},"56":{"sum_foreign_comment":"","sum":"","sum_comment":"","sum_foreign":""},"57":{"sum_foreign_comment":"","sum":"","sum_comment":"","sum_foreign":""},"58":{"sum_foreign_comment":"","sum":"","sum_comment":"","sum_foreign":""},"59":{"sum_foreign_comment":"","sum":"","sum_comment":"","sum_comment_unclear":false,"sum_unclear":false,"sum_foreign":""},"60":{"sum_foreign_comment":"","sum":"","sum_comment":"","sum_foreign":""},"61":{"sum_foreign_comment":"","sum":"","sum_comment":"","sum_foreign":""},"62":{"sum_foreign_comment":"","sum":"2000","sum_comment":"","sum_unclear":false,"sum_foreign":""},"63":{"sum_foreign_comment":"","sum":"","sum_comment":"","sum_foreign":""},"64":{"sum_foreign_comment":"","sum":"","sum_comment":"","sum_foreign":""}},"ft_src":"2000\nДвірна Юлія Георгіївна\nсуддя апеляційного суду запорізької області\nЗапорізька область\nЗагальний апеляційний суд\nЮлія\nДвірний А. В\nПодружжя\nДвірний Д. А\nДитина\nДвірна А. А\nДитина\nДвірна Юлія Георгіївна\nЮлія Георгіївна Двірна\nЮлія Двірна\nДвірна Юлія Георгіївна\nДвірна\nГеоргіївна\n2400 куб. см.\n2005\nToyota Avensis\n2007\n1250 куб. см.\nFord Fiesta\n24\n66.08\n69.4\n.0503\n2014\n23953\n12930\nдопомога при народженні дитини\n12930\n23953\nСША\n1883\n2400 куб. см.\n2005\nToyota Avensis\n1250 куб. см.\nFord Fiesta\n2007\n2014\nДвірна\nГеоргіївна\nПодружжя\nДвірний А. В\nДитина\nДвірний Д. А\nДитина\nДвірна А. А\nДвірна Юлія Георгіївна\nЮлія Георгіївна Двірна\nЮлія Двірна\nДвірна Юлія Георгіївна\nЮлія\nДвірна Юлія Георгіївна\nЗагальний апеляційний суд\nсуддя апеляційного суду запорізької області\nЗапорізька область\n2000\n23953\n1883\nСША\n12930\nдопомога при народженні дитини\n12930\n23953\n24\n69.4\n66.08\n.0503\n2000\nДвірний А. В\nПодружжя\nДвірний Д. А\nДитина\nДвірна А. А\nДитина\nДвірна\nГеоргіївна\nсуддя апеляційного суду запорізької області\nЗапорізька область\nЗагальний апеляційний суд\nДвірна Юлія Георгіївна\nДвірна Юлія Георгіївна\nЮлія Георгіївна Двірна\nЮлія Двірна\nДвірна Юлія Георгіївна\nЮлія\n2005\n2400 куб. см.\nToyota Avensis\n2007\n1250 куб. см.\nFord Fiesta\n12930\nдопомога при народженні дитини\n23953\n12930\n23953\nСША\n1883\n66.08\n69.4\n24\n.0503\n2014","general":{"inn":"","inn_hidden":true,"last_name":"Двірна","post":{"office":"Загальний апеляційний суд","region":"Запорізька область","post":"суддя апеляційного суду запорізької області"},"name":"Юлія","full_name":"Двірна Юлія Георгіївна","family_raw":"","addresses":[{"place_district":"","place_address_hidden":false,"place_city":"","place_city_type_hidden":false,"place_district_hidden":false,"place_city_type":"","place_city_hidden":false,"place_address":"","place_hidden":true,"place":""}],"family":[{"inn":"","inn_hidden":false,"relations_hidden":false,"family_name":"Двірний А. В","relations_other":"","relations":"Подружжя","name_hidden":false,"name_unclear":false},{"inn":"","relations":"Дитина","relations_other":"","inn_hidden":false,"family_name":"Двірний Д. А","name_hidden":false,"name_unclear":false},{"inn":"","relations":"Дитина","relations_other":"","inn_hidden":false,"family_name":"Двірна А. А","name_hidden":false,"name_unclear":false}],"full_name_suggest":{"output":"Двірна Юлія Георгіївна","input":["Двірна Юлія Георгіївна","Юлія Георгіївна Двірна","Юлія Двірна"]},"patronymic":"Георгіївна"},"source":"VULYK","estate":{"29":[{"space_units_unclear":false,"address_hidden":true,"region_hidden":true,"space_comment":"","space":".0503","address":"","region":"","costs_property":"","costs_rent_comment":"","space_units":"га","costs_property_comment":"","costs_rent":""}],"30":[{"costs_rent":"","region":"","costs_property":"","costs_rent_comment":"","region_hidden":true,"space_comment":"","costs_property_comment":"","space_units":"м²","space":"69.4","address":""}],"31":[{"space_unclear":false,"address_hidden":true,"region_hidden":true,"space_comment":"","space":"66.08","address":"","region":"","costs_property":"","costs_rent_comment":"","space_units":"м²","costs_property_comment":"","costs_rent":""}],"33":[{"costs_rent":"","region":"","costs_property":"","costs_rent_comment":"","region_hidden":true,"space_comment":"","costs_property_comment":"","space_units":"м²","space":"24","address":""}]},"intro":{"declaration_year":"2014","isnotdeclaration":""}}