{"income":{"5":{"value":"440166","comment_hidden":false,"family_comment":"","family":"","comment":"","family_comment_hidden":false},"6":{"value":"240166","family_comment":"","comment_hidden":false,"family_hidden":false,"family_unclear":false,"family_comment_hidden":false,"comment":"","family":""},"7":{"value":"","comment_hidden":false,"family_comment_hidden":false,"family_comment":"","source_name":"","family":"","comment":"","source_name_hidden":false},"8":{"family_comment":"","value":"","family":"","comment":""},"9":{"value":"","family_comment":"","value_unclear":false,"family_unclear":false,"comment_unclear":false,"comment":"","family":""},"10":{"family_comment":"","family_unclear":false,"value":"","family":"","comment":""},"11":{"family_comment":"","value":"","family":"","comment":""},"12":{"family_comment":"","value":"","family":"","comment":""},"13":{"family_comment":"","value":"","family":"","comment":""},"14":{"family_comment":"","value":"","family":"","comment":""},"15":{"family_comment":"","value":"","comment_unclear":false,"family":"","comment":""},"16":{"family_comment":"","value":"","comment_unclear":false,"family":"","comment":""},"17":{"family_comment":"","value":"","family":"","comment":""},"18":{"family_comment":"","value":"","family":"","comment":""},"19":{"family_comment":"","value":"","family":"","comment":""},"20":{"value":"200000","family_comment":"","value_unclear":false,"family_unclear":false,"family_comment_unclear":false,"family_comment_hidden":false,"comment":"","family":""}},"vehicle":{"35":[{"brand_info":"1598 куб.см.","sum_rent_comment":"","brand":"Nissan Note","sum_comment":"","brand_unclear":false,"year":"2008","sum_hidden":false,"brand_info_unclear":false,"sum":"","sum_rent":""}]},"id":"vulyk_73_12","declaration":{"additional_info_text":"","notfull_lostpages":"","date":"2014-03-21T00:00:00","notfull":"","additional_info":"","url":"http://static.declarations.com.ua/declarations/chosen_ones/judges_batch/1475_khrapak_nataliia_mykolaivna.pdf"},"liabilities":{"54":{"sum_foreign_comment":"","sum_foreign_hidden":false,"sum_comment":"","sum_comment_unclear":false,"sum_hidden":false,"sum_comment_hidden":false,"sum_unclear":false,"sum":"","sum_foreign":""},"55":{"sum_foreign_comment":"","sum_comment_hidden":false,"sum":"","sum_comment":"","sum_foreign":""},"56":{"sum_foreign_comment":"","sum":"","sum_comment":"","sum_comment_unclear":false,"sum_foreign":""},"57":{"sum_foreign_comment":"","sum":"200000","sum_comment":"","sum_hidden":false,"sum_comment_hidden":false,"sum_unclear":false,"sum_foreign":""},"58":{"sum_foreign_comment":"","sum":"538","sum_comment":"","sum_hidden":false,"sum_comment_hidden":false,"sum_foreign":""},"59":{"sum_foreign_comment":"","sum":"","sum_comment":"","sum_comment_unclear":false,"sum_unclear":false,"sum_foreign":""},"60":{"sum_foreign_comment":"","sum":"","sum_comment":"","sum_hidden":false,"sum_comment_hidden":false,"sum_unclear":false,"sum_foreign":""},"61":{"sum_foreign_comment":"","sum":"","sum_comment":"","sum_foreign":""},"62":{"sum_foreign_comment":"","sum":"","sum_comment":"","sum_foreign":""},"63":{"sum_foreign_comment":"","sum":"","sum_comment":"","sum_hidden":false,"sum_comment_hidden":false,"sum_foreign":""},"64":{"sum_foreign_comment":"","sum":"","sum_comment":"","sum_foreign":""}},"ft_src":"200000\n538\nсуддя апеляційного суду тернопільської області\nТернопільська область\nЗагальний апеляційний суд\nНаталія\nЖебелюк В. В\nДитина\nМиколаївна\nХрапак Наталія Миколаївна\nНаталія Миколаївна Храпак\nНаталія Храпак\nХрапак Наталія Миколаївна\nХрапак\nХрапак Наталія Миколаївна\nNissan Note\n1598 куб.см.\n2008\n17\n22\n98\n2013\n240166\n440166\n200000\n1598 куб.см.\nNissan Note\n2008\n2013\nХрапак Наталія Миколаївна\nНаталія Миколаївна Храпак\nНаталія Храпак\nХрапак Наталія Миколаївна\nНаталія\nДитина\nЖебелюк В. В\nХрапак Наталія Миколаївна\nМиколаївна\nЗагальний апеляційний суд\nТернопільська область\nсуддя апеляційного суду тернопільської області\nХрапак\n538\n200000\n240166\n200000\n440166\n17\n22\n98\n538\n200000\nДитина\nЖебелюк В. В\nМиколаївна\nХрапак\nНаталія\nХрапак Наталія Миколаївна\nНаталія Миколаївна Храпак\nНаталія Храпак\nХрапак Наталія Миколаївна\nТернопільська область\nЗагальний апеляційний суд\nсуддя апеляційного суду тернопільської області\nХрапак Наталія Миколаївна\n2008\n1598 куб.см.\nNissan Note\n200000\n440166\n240166\n98\n17\n22\n2013","general":{"inn":"","name":"Наталія","family":[{"inn":"","relations":"Дитина","inn_unclear":false,"relations_hidden":false,"inn_hidden":true,"relations_other":"","name_hidden":false,"family_name":"Жебелюк В. В","name_unclear":false}],"patronymic":"Миколаївна","inn_hidden":true,"family_raw":"","last_name":"Храпак","post":{"post_unclear":false,"region_unclear":false,"post":"суддя апеляційного суду тернопільської області","office":"Загальний апеляційний суд","region":"Тернопільська область","post_hidden":false,"office_hidden":false,"office_unclear":false,"region_hidden":false},"last_name_unclear":false,"full_name":"Храпак Наталія Миколаївна","addresses":[{"place_district":"","place_city_hidden":true,"place_city":"","place_city_type_hidden":false,"place_district_hidden":false,"place_city_type":"","place_address_hidden":true,"place_address":"","place_hidden":false,"place":""}],"full_name_suggest":{"output":"Храпак Наталія Миколаївна","input":["Храпак Наталія Миколаївна","Наталія Миколаївна Храпак","Наталія Храпак"]},"name_unclear":false},"source":"VULYK","estate":{"25":[{"space_unclear":false,"costs":"","costs_comment":"","costs_hidden":false,"address_hidden":true,"region_hidden":false,"space_comment":"","space_hidden":false,"space":"98","address":"","region":"","costs_rent_comment":"","space_comment_hidden":false,"space_units":"м²","costs_rent":""}],"27":[{"space_unclear":false,"costs":"","costs_comment":"","costs_hidden":false,"address_hidden":true,"region_hidden":false,"space_comment":"","space":"17","address":"","region":"","costs_rent_comment":"","space_units":"м²","costs_rent":""},{"costs_rent":"","region":"","costs":"","costs_rent_comment":"","costs_comment":"","space_comment":"","space_units":"м²","space":"22","address":""}]},"intro":{"declaration_year":"2013"}}