{"income":{"5":{"value":"234554","value_unclear":false,"comment_hidden":false,"family_hidden":false,"value_hidden":false,"family_comment":"","family":"145500","comment":""},"6":{"value":"223204","value_unclear":false,"comment_hidden":false,"family_hidden":false,"value_hidden":false,"family_comment":"","family_comment_hidden":false,"comment":"","family":""},"7":{"family_comment":"","value":"","source_name":"","family":"","comment":""},"8":{"family_comment":"","value":"","family":"","comment":""},"9":{"family_comment":"","value":"11350","family":"","comment":""},"10":{"value":"","value_unclear":false,"family_hidden":false,"family_comment":"","family":"","comment":""},"11":{"family_comment":"","value":"","family":"","comment":""},"12":{"family_comment":"","value":"","family":"","comment":""},"13":{"family_comment":"","value":"","family":"","comment":""},"14":{"family_comment":"","value":"","family":"","comment":""},"15":{"family_comment":"","value":"","comment_unclear":false,"family":"","comment":""},"16":{"family_comment":"","value":"","family":"145500","comment":""},"17":{"family_comment":"","value":"","family":"","comment":""},"18":{"family_comment":"","value":"","family":"","comment":""},"19":{"family_comment":"","value":"","family":"","comment":""},"20":{"family_comment":"","value":"","family":"","comment":"","family_comment_hidden":false}},"vehicle":{"35":[{"brand_info":"об'єм двигуна 2477 куб. см., потужність 100 кВт","sum":"","brand":"Mitsubishi L 200 invite","sum_comment":"","brand_unclear":false,"year":"2008","brand_info_hidden":false,"sum_rent_comment":"","sum_rent":""}],"37":[{"brand_info":"Судно. Довжина - 3.1 м, двигун Tohatsu 9.8 , потужність 7.2 кВт , об'єм 169 куб см","sum_rent_comment":"","brand":"Шельф-310к","sum_comment":"","year":"2011","sum":"","sum_rent":""}]},"id":"vulyk_79_54","banks":{"45":[{"sum_foreign_comment":"","sum_units":"UAH","sum_comment":"","sum_foreign_comment_hidden":false,"sum_foreign_units":"UAH","sum_comment_hidden":true,"sum_foreign_hidden":false,"sum":"240019","sum_foreign":""},{"sum_foreign_comment":"","sum_units":"UAH","sum_comment":"","sum_foreign_units":"","sum_comment_hidden":true,"sum":"20000","sum_foreign":""}],"46":[{"sum_foreign_comment":"","sum_units":"UAH","sum_comment":"","sum_foreign_comment_hidden":false,"sum_foreign_units":"UAH","sum_comment_hidden":true,"sum_foreign_hidden":false,"sum":"240019","sum_foreign":""},{"sum_foreign_comment":"","sum_units":"UAH","sum_comment":"","sum_foreign_units":"","sum_comment_hidden":true,"sum":"20000","sum_foreign":""}],"51":[{"sum_foreign_comment":"","sum_units":"UAH","sum_comment":"","sum_foreign_comment_hidden":false,"sum_foreign_units":"UAH","sum_comment_hidden":true,"sum_foreign_hidden":false,"sum":"30433","sum_foreign":""}]},"declaration":{"date":"2015-03-31T00:00:00","additional_info_text":"","additional_info":"","url":"http://static.declarations.com.ua/declarations/chosen_ones/judges_batch/2059_cherednychenko_vladyslav_ievheniiovych.pdf"},"liabilities":{"54":{"sum_foreign_comment":"","sum_comment_hidden":false,"sum":"","sum_comment":"","sum_foreign":""},"55":{"sum_foreign_comment":"","sum":"","sum_comment":"","sum_foreign":""},"56":{"sum_foreign_comment":"","sum":"","sum_hidden":false,"sum_comment":"","sum_foreign":""},"57":{"sum_foreign_comment":"","sum":"","sum_comment":"","sum_comment_unclear":false,"sum_hidden":false,"sum_comment_hidden":false,"sum_foreign":""},"58":{"sum_foreign_comment":"","sum":"","sum_comment":"","sum_comment_unclear":false,"sum_hidden":false,"sum_comment_hidden":false,"sum_unclear":false,"sum_foreign":""},"59":{"sum_foreign_comment":"","sum":"","sum_comment":"","sum_foreign":""},"60":{"sum_foreign_comment":"","sum_comment_hidden":false,"sum":"","sum_comment":"","sum_foreign":""},"61":{"sum_foreign_comment":"","sum":"","sum_comment":"","sum_foreign":""},"62":{"sum_foreign_comment":"","sum":"","sum_comment":"","sum_foreign":""},"63":{"sum_foreign_comment":"","sum":"","sum_comment":"","sum_unclear":false,"sum_foreign":""},"64":{"sum_foreign_comment":"","sum":"","sum_comment":"","sum_unclear":false,"sum_foreign":""}},"ft_src":"суддя дніпропетровського апеляційного адміністративного суду\nДніпропетровська область\nАпеляційний адміністративний суд\nВладислав\nПодружжя\nДитина\nДитина\nЄвгенійович\nЧередниченко Владислав Євгенійович\nВладислав Євгенійович Чередниченко\nВладислав Чередниченко\nЧередниченко Владислав Євгенійович\nЧередниченко Владислав Євгенійович\nЧередниченко\n2008\nMitsubishi L 200 invite\nоб'єм двигуна 2477 куб. см., потужність 100 кВт\nСудно. Довжина - 3.1 м, двигун Tohatsu 9.8 , потужність 7.2 кВт , об'єм 169 куб см\n2011\nШельф-310к\n240019\n20000\n30433\n240019\n20000\n2014\nСудно. Довжина - 3.1 м, двигун Tohatsu 9.8 , потужність 7.2 кВт , об'єм 169 куб см\nШельф-310к\n2011\nMitsubishi L 200 invite\nоб'єм двигуна 2477 куб. см., потужність 100 кВт\n2008\n240019\n20000\n30433\n240019\n20000\n24\n70.5\n44.7\nПодружжя\nДитина\nДитина\nЧередниченко Владислав Євгенійович\nВладислав Євгенійович Чередниченко\nВладислав Чередниченко\nЧередниченко Владислав Євгенійович\nЧередниченко Владислав Євгенійович\nВладислав\nЧередниченко\nАпеляційний адміністративний суд\nДніпропетровська область\nсуддя дніпропетровського апеляційного адміністративного суду\nЄвгенійович\n223204\n234554\n145500\n145500\n11350\n2014\n70.5\n24\n44.7\nПодружжя\nДитина\nДитина\nЄвгенійович\nЧередниченко\nВладислав\nЧередниченко Владислав Євгенійович\nВладислав Євгенійович Чередниченко\nВладислав Чередниченко\nЧередниченко Владислав Євгенійович\nДніпропетровська область\nАпеляційний адміністративний суд\nсуддя дніпропетровського апеляційного адміністративного суду\nЧередниченко Владислав Євгенійович\n223204\n11350\n145500\n234554\n145500\n2008\nMitsubishi L 200 invite\nоб'єм двигуна 2477 куб. см., потужність 100 кВт\nШельф-310к\nСудно. Довжина - 3.1 м, двигун Tohatsu 9.8 , потужність 7.2 кВт , об'єм 169 куб см\n2011\n11350\n234554\n145500\n145500\n223204\n70.5\n44.7\n24\n240019\n20000\n30433\n240019\n20000\n2014","general":{"inn":"","name":"Владислав","last_name_hidden":false,"family":[{"inn":"","inn_hidden":true,"relations_hidden":false,"family_name":"","relations_other":"","relations":"Подружжя","name_hidden":true,"name_unclear":false},{"inn_hidden":true,"inn":"","name_hidden":false,"family_name":"","relations":"Дитина","name_unclear":false},{"inn":"","family_name":"","relations":"Дитина","inn_hidden":false}],"patronymic":"Євгенійович","inn_hidden":true,"family_raw":"","inn_unclear":false,"post":{"post_unclear":false,"post":"суддя дніпропетровського апеляційного адміністративного суду","post_hidden":false,"region":"Дніпропетровська область","region_hidden":false,"office":"Апеляційний адміністративний суд","office_hidden":false,"office_unclear":false},"full_name":"Чередниченко Владислав Євгенійович","addresses":[{"place_district":"","place_city_hidden":true,"place_city":"","place_city_type_hidden":true,"place_district_hidden":true,"place_city_type":"","place_address_hidden":true,"place_address":"","place_hidden":true,"place":""}],"last_name":"Чередниченко","full_name_suggest":{"output":"Чередниченко Владислав Євгенійович","input":["Чередниченко Владислав Євгенійович","Владислав Євгенійович Чередниченко","Владислав Чередниченко"]}},"source":"VULYK","estate":{"25":[{"space_unclear":false,"costs":"","costs_rent_unclear":false,"costs_comment":"","address_hidden":true,"region_hidden":true,"space_comment":"","space_hidden":false,"space":"44.7","address":"","costs_rent_comment_unclear":false,"region":"","costs_rent_comment":"","costs_unclear":false,"space_units":"м²","costs_rent":""}],"31":[{"space_unclear":false,"address_hidden":true,"region_hidden":true,"space_comment":"","space_hidden":false,"space":"70.5","address":"","region":"","costs_property":"","costs_rent_comment":"","space_units":"м²","costs_property_comment":"","costs_rent":""}],"33":[{"costs_rent":"","region":"","costs_property":"","costs_rent_comment":"","address_hidden":true,"region_hidden":true,"space_comment":"","costs_property_comment":"","space_units":"м²","space":"24","address":""}]},"intro":{"declaration_year":"2014"}}