{"income":{"5":{"family_comment":"","value":"179819.02","family":"","comment":""},"6":{"value":"167639.02","family_comment":"","value_unclear":false,"comment_hidden":false,"family_unclear":false,"family":"","comment":""},"7":{"family_comment":"","value":"","source_name":"","family":"","comment":""},"8":{"family_comment":"","value":"","family":"","comment":""},"9":{"family_comment":"","family_unclear":false,"value":"","family":"","comment":""},"10":{"family_comment":"","value":"12180","value_unclear":false,"family":"","comment":""},"11":{"family_comment":"","value":"","family":"","comment":""},"12":{"family_comment":"","value":"","family":"","comment":""},"13":{"family_comment":"","value":"","family":"","comment":""},"14":{"family_comment":"","value":"","family":"","comment":""},"15":{"family_comment":"","value":"","family":"","comment":""},"16":{"family_comment":"","value":"","family":"","comment":""},"17":{"family_comment":"","value":"","family":"","comment":""},"18":{"family_comment":"","value":"","family":"","comment":""},"19":{"family_comment":"","value":"","family":"","comment":""},"20":{"value":"","family":"","value_unclear":false,"family_hidden":false,"family_comment":"","comment_unclear":false,"comment":"","family_comment_unclear":false}},"id":"vulyk_97_180","declaration":{"additional_info_text":"","notfull_lostpages":"","date":"2015-03-30T00:00:00","notfull":"","additional_info":"","url":"http://static.declarations.com.ua/declarations/chosen_ones/judges_batch/4095_nelha_dina_viacheslavivna.pdf"},"liabilities":{"54":{"sum_foreign_comment":"","sum":"","sum_comment":"","sum_comment_unclear":false,"sum_hidden":false,"sum_comment_hidden":false,"sum_unclear":false,"sum_foreign":""},"55":{"sum_foreign_comment":"","sum":"","sum_comment":"","sum_foreign":""},"56":{"sum_foreign_comment":"","sum":"1160","sum_comment":"","sum_foreign":""},"57":{"sum_foreign_comment":"","sum":"","sum_comment":"","sum_comment_unclear":false,"sum_hidden":false,"sum_comment_hidden":false,"sum_unclear":false,"sum_foreign":""},"58":{"sum_foreign_comment":"","sum":"","sum_comment":"","sum_comment_unclear":false,"sum_hidden":false,"sum_comment_hidden":false,"sum_unclear":false,"sum_foreign":""},"59":{"sum_foreign_comment":"","sum":"","sum_comment":"","sum_foreign":""},"60":{"sum_foreign_comment":"","sum":"","sum_comment":"","sum_comment_unclear":false,"sum_hidden":false,"sum_comment_hidden":false,"sum_foreign":""},"61":{"sum_foreign_comment":"","sum":"","sum_comment":"","sum_foreign":""},"62":{"sum_foreign_comment":"","sum":"","sum_comment":"","sum_unclear":false,"sum_foreign":""},"63":{"sum_foreign_comment":"","sum":"","sum_hidden":false,"sum_comment":"","sum_foreign":""},"64":{"sum_foreign_comment":"","sum":"","sum_comment":"","sum_foreign":""}},"ft_src":"1160\nДніпродзержинськ\n51900\nДніпропетровська область\nсуддя\nДніпропетровська область\nЗагальний місцевий суд\nДіна\nВячеславівна\nНельга Діна Вячеславівна\nДіна Вячеславівна Нельга\nДіна Нельга\nНельга Діна Вячеславівна\nНельга Діна Вячеславівна\nНельга\n12180\n179819.02\n167639.02\n44.2\n113351\nУкраїна\n2014\n167639.02\n12180\n179819.02\n113351\n44.2\nУкраїна\nЗагальний місцевий суд\nДніпропетровська область\nсуддя\nНельга Діна Вячеславівна\nДіна Вячеславівна Нельга\nДіна Нельга\nНельга Діна Вячеславівна\nНельга Діна Вячеславівна\nДіна\nНельга\nВячеславівна\nДніпропетровська область\n51900\nДніпродзержинськ\n1160\n167639.02\n179819.02\n12180\n2014\n1160\nВячеславівна\nНельга\nДіна\nНельга Діна Вячеславівна\nДіна Вячеславівна Нельга\nДіна Нельга\nНельга Діна Вячеславівна\n51900\nДніпродзержинськ\nДніпропетровська область\nДніпропетровська область\nЗагальний місцевий суд\nсуддя\nНельга Діна Вячеславівна\n113351\nУкраїна\n44.2\n2014","general":{"name_hidden":false,"name":"Діна","last_name_hidden":false,"inn":"","last_name":"Нельга","patronymic":"Вячеславівна","inn_hidden":true,"family_raw":"","inn_unclear":false,"post":{"region_unclear":true,"region":"Дніпропетровська область","post":"суддя","office":"Загальний місцевий суд","office_unclear":true,"post_hidden":false},"full_name":"Нельга Діна Вячеславівна","addresses":[{"place_district":"","place_city_hidden":false,"place_city":"Дніпродзержинськ","place_city_unclear":false,"place_district_hidden":false,"place_city_type":"Місто","place_address_hidden":true,"place_city_type_hidden":false,"place_address":"51900","place_hidden":false,"place":"Дніпропетровська область"}],"patronymic_hidden":false,"full_name_suggest":{"output":"Нельга Діна Вячеславівна","input":["Нельга Діна Вячеславівна","Діна Вячеславівна Нельга","Діна Нельга"]}},"source":"VULYK","estate":{"25":[{"region_unclear":false,"space_unclear":false,"costs":"113351","costs_comment":"","address_hidden":false,"region_hidden":true,"space_comment":"","space_hidden":false,"space":"44.2","address":"Україна","region":"","costs_rent_comment":"","space_comment_unclear":false,"space_comment_hidden":false,"space_units":"м²","costs_rent":""}]},"intro":{"declaration_year":"2014","isnotdeclaration":""}}