{"income":{"5":{"value":"179429.09","family_comment":"","value_unclear":false,"family_unclear":false,"family":"57709.34","comment":""},"6":{"value":"179429.09","family_comment":"","value_unclear":false,"value_hidden":false,"family_unclear":false,"family":"31805.5","comment":""},"7":{"family_comment":"","value":"","source_name":"","family":"","comment":""},"8":{"family_comment":"","value":"","family":"","comment":""},"9":{"value":"","family_comment":"","value_unclear":false,"family_unclear":false,"family":"","comment":""},"10":{"value":"","family_comment":"","value_unclear":false,"family_unclear":false,"family":"","comment":""},"11":{"family_comment":"","value":"","family":"","comment":""},"12":{"family_comment":"","value":"","family":"","comment":""},"13":{"family_comment":"","value":"","family":"","comment":""},"14":{"family_comment":"","value":"","family":"","comment":""},"15":{"family_comment":"","value":"","family":"","comment":""},"16":{"family_comment":"","value":"","family":"","comment":""},"17":{"family_comment":"","family_unclear":false,"value":"","family":"","comment":""},"18":{"family_comment":"","value":"","family":"","comment":""},"19":{"family_comment":"","value":"","family":"","comment":""},"20":{"value":"","comment_unclear":false,"family_comment":"","family":"25903.84","comment":"","family_comment_unclear":false}},"vehicle":{"35":[{"year_hidden":false,"brand_info":"1600 куб. см.","sum_rent_comment":"","brand":"Chevrolet Lacetti","sum_comment":"","brand_unclear":false,"year":"2007","brand_info_unclear":false,"year_unclear":false,"sum":"","sum_rent":""}],"40":[{"year_hidden":false,"brand_info":"1100 куб. см.","sum_rent_comment":"","brand":"ЗАЗ 11028 Таврия","sum_comment":"","brand_unclear":false,"year":"1995","brand_hidden":false,"brand_info_unclear":false,"sum":"","sum_rent":""}],"44":[{"brand_info":"причіп","sum_rent_comment":"","brand":"ГТБ 8160","sum_comment":"","year":"2006","sum":"","sum_rent":""}]},"id":"vulyk_37_49","banks":{"45":[{"sum_foreign_comment":"","sum_units":"UAH","sum_units_hidden":false,"sum_comment":"","sum_comment_unclear":false,"sum_hidden":false,"sum_foreign_units":"UAH","sum_comment_hidden":false,"sum_unclear":true,"sum":"8","sum_foreign":""},{"sum_foreign_comment":"","sum_units":"","sum_comment":"","sum_foreign_units":"","sum":"","sum_foreign":""},{"sum_foreign_comment":"","sum_units":"","sum_comment":"","sum_foreign_units":"","sum":"","sum_foreign":""}],"46":[{"sum_foreign_comment":"","sum_units":"UAH","sum_comment":"","sum_foreign_units":"UAH","sum":"","sum_foreign":""},{"sum_foreign_comment":"","sum_units":"","sum_comment":"","sum_foreign_units":"","sum":"","sum_foreign":""}],"47":[{"sum_foreign_comment":"","sum_units":"UAH","sum_comment":"","sum_foreign_units":"UAH","sum_comment_hidden":false,"sum":"","sum_foreign":""}],"48":[{"sum_foreign_comment":"","sum_units":"UAH","sum_comment":"","sum_foreign_units":"UAH","sum":"","sum_foreign":""}],"49":[{"sum_foreign_comment":"","sum_units":"UAH","sum_comment":"","sum_foreign_units":"UAH","sum":"","sum_foreign":""}],"50":[{"sum_foreign_comment":"","sum_units":"UAH","sum_comment":"","sum_foreign_units":"UAH","sum":"","sum_foreign":""}],"51":[{"sum_foreign_comment":"","sum_units":"UAH","sum_comment":"","sum_hidden":false,"sum_foreign_units":"UAH","sum_comment_hidden":false,"sum_unclear":false,"sum":"","sum_foreign":""}],"52":[{"sum_foreign_comment":"","sum_units":"UAH","sum_comment":"","sum_foreign_units":"UAH","sum_comment_hidden":false,"sum":"1500","sum_foreign":""}],"53":[{"sum_foreign_comment":"","sum_units":"UAH","sum_comment":"","sum_comment_unclear":false,"sum_foreign_units":"UAH","sum":"","sum_foreign":""}]},"declaration":{"additional_info_text":"","notfull_lostpages":"","date":"2015-03-26T00:00:00","notfull":"","additional_info":"","url":"http://static.declarations.com.ua/declarations/chosen_ones/mega_batch/starovetskyi_volodymyr_ivanovych.pdf"},"liabilities":{"54":{"sum_foreign_comment":"","sum_comment_hidden":false,"sum":"","sum_comment":"","sum_foreign":""},"55":{"sum_foreign_comment":"","sum":"","sum_comment":"","sum_foreign":""},"56":{"sum_foreign_comment":"","sum":"","sum_comment":"","sum_unclear":false,"sum_foreign":""},"57":{"sum_foreign_comment":"","sum":"","sum_comment":"","sum_hidden":false,"sum_comment_hidden":false,"sum_unclear":false,"sum_foreign":""},"58":{"sum_foreign_comment":"","sum":"","sum_comment":"","sum_hidden":false,"sum_comment_hidden":false,"sum_foreign":""},"59":{"sum_foreign_comment":"","sum":"","sum_hidden":false,"sum_comment":"","sum_foreign":""},"60":{"sum_foreign_comment":"","sum_comment_hidden":false,"sum":"","sum_comment":"","sum_foreign":""},"61":{"sum_foreign_comment":"","sum":"","sum_comment":"","sum_foreign":""},"62":{"sum_foreign_comment":"","sum":"","sum_comment":"","sum_unclear":false,"sum_foreign":""},"63":{"sum_foreign_comment":"","sum_comment_hidden":false,"sum":"","sum_comment":"","sum_foreign":""},"64":{"sum_foreign_comment":"","sum_comment_hidden":false,"sum":"","sum_comment":"","sum_foreign":""}},"ft_src":"суддя слов'янського міськрайонного суду донецької області\nДонецька область\nЗагальний місцевий суд\nВолодимир\nСтаровецька А. В\nПодружжя\nСтаровецька Е. В\nДитина\nСтаровецький Д. В\nДитина\nПоляченко І. П\nІнше\nмати дружини\nПоляченко В. І\nІнше\nбатько дружини\nІванович\nСтаровецький Володимир Іванович\nВолодимир Іванович Старовецький\nВолодимир Старовецький\nСтаровецький Володимир Іванович\nСтаровецький\nСтаровецький Володимир Іванович\n1600 куб. см.\nChevrolet Lacetti\n2007\nЗАЗ 11028 Таврия\n1100 куб. см.\n1995\nпричіп\n2006\nГТБ 8160\n8\n1500\n2014\n1600 куб. см.\n2007\nChevrolet Lacetti\n1100 куб. см.\n1995\nЗАЗ 11028 Таврия\nпричіп\nГТБ 8160\n2006\n8\n1500\n.11\n.06\n48.6\nПодружжя\nСтаровецька А. В\nДитина\nСтаровецька Е. В\nДитина\nСтаровецький Д. В\nІнше\nмати дружини\nПоляченко І. П\nПоляченко В. І\nІнше\nбатько дружини\nСтаровецький Володимир Іванович\nВолодимир Іванович Старовецький\nВолодимир Старовецький\nСтаровецький Володимир Іванович\nСтаровецький Володимир Іванович\nВолодимир\nІванович\nЗагальний місцевий суд\nсуддя слов'янського міськрайонного суду донецької області\nДонецька область\nСтаровецький\n31805.5\n179429.09\n25903.84\n179429.09\n57709.34\n2014\n48.6\n.11\n.06\nСтаровецька А. В\nПодружжя\nСтаровецька Е. В\nДитина\nСтаровецький Д. В\nДитина\nмати дружини\nПоляченко І. П\nІнше\nІнше\nбатько дружини\nПоляченко В. І\nІванович\nСтаровецький\nВолодимир\nСтаровецький Володимир Іванович\nВолодимир Іванович Старовецький\nВолодимир Старовецький\nСтаровецький Володимир Іванович\nДонецька область\nсуддя слов'янського міськрайонного суду донецької області\nЗагальний місцевий суд\nСтаровецький Володимир Іванович\n31805.5\n179429.09\n57709.34\n179429.09\n25903.84\nГТБ 8160\nпричіп\n2006\n2007\nChevrolet Lacetti\n1600 куб. см.\n1995\nЗАЗ 11028 Таврия\n1100 куб. см.\n25903.84\n179429.09\n57709.34\n179429.09\n31805.5\n48.6\n.11\n.06\n8\n1500\n2014","general":{"inn":"","name":"Володимир","patronymic_unclear":false,"family":[{"inn":"","inn_hidden":true,"relations_unclear":false,"relations_hidden":false,"relations_other":"","relations":"Подружжя","name_hidden":true,"family_name":"Старовецька А. В","name_unclear":false},{"inn":"","relations":"Дитина","relations_unclear":false,"family_name":"Старовецька Е. В","inn_hidden":false,"relations_other":"","name_hidden":false,"name_unclear":true},{"inn":"","relations":"Дитина","relations_unclear":false,"family_name":"Старовецький Д. В","inn_hidden":false,"relations_other":"","name_hidden":false,"name_unclear":true},{"inn":"","relations":"Інше","relations_other":"мати дружини","inn_hidden":false,"family_name":"Поляченко І. П","name_hidden":false,"name_unclear":false},{"inn":"","family_name":"Поляченко В. І","relations":"Інше","relations_other":"батько дружини"}],"patronymic":"Іванович","inn_hidden":true,"family_raw":"","last_name":"Старовецький","post":{"post_unclear":false,"post":"суддя слов'янського міськрайонного суду донецької області","post_hidden":false,"region":"Донецька область","region_hidden":false,"office":"Загальний місцевий суд","office_hidden":false,"office_unclear":false},"last_name_unclear":false,"full_name":"Старовецький Володимир Іванович","addresses":[{"place_district":"","place_city_hidden":false,"place_city":"","place_city_type_hidden":false,"place_district_hidden":false,"place_city_type":"","place_address_hidden":true,"place_address":"","place_hidden":true,"place":""}],"full_name_suggest":{"output":"Старовецький Володимир Іванович","input":["Старовецький Володимир Іванович","Володимир Іванович Старовецький","Володимир Старовецький"]},"name_unclear":false},"source":"VULYK","estate":{"23":[{"space_unclear":false,"costs":"","costs_comment":"","address_hidden":false,"region_hidden":false,"space_comment":"","space_hidden":false,"space":"","address":"","region":"","space_units_unclear":false,"space_units":"м²","costs_rent":"","costs_rent_comment":""},{"costs_rent":"","space_unclear":false,"region":"","costs":"","costs_rent_comment":"","costs_comment":"","space_comment":"","space_units":"","space":"","address":""},{"costs_rent":"","region":"","costs":"","costs_rent_comment":"","costs_comment":"","space_comment":"","space_units":"","space":"","address":""},{"costs_rent":"","region":"","costs":"","costs_rent_comment":"","costs_comment":"","space_comment":"","space_units":"","space":"","address":""},{"costs_rent":"","region":"","costs":"","costs_rent_comment":"","costs_comment":"","space_comment":"","space_units":"","space":"","address":""},{"costs_rent":"","region":"","costs":"","costs_rent_comment":"","costs_comment":"","space_comment":"","space_units":"","space":"","address":""},{"costs_rent":"","region":"","costs":"","costs_rent_comment":"","costs_comment":"","space_comment":"","space_units":"","space":"","address":""},{"costs_rent":"","region":"","costs":"","costs_rent_comment":"","costs_comment":"","space_comment":"","space_units":"","space":"","address":""}],"29":[{"space_hidden":false,"address_hidden":true,"region_hidden":true,"space_comment":"","space":".11","address":"","region":"","costs_property":"","costs_rent_comment":"","space_units":"га","costs_property_comment":"","costs_rent":""},{"space_unclear":false,"region_hidden":false,"space_comment":"","space":".06","address":"","region":"","costs_property":"","costs_rent_comment":"","space_comment_unclear":false,"space_units":"га","costs_property_comment":"","costs_rent":""}],"30":[{"space_unclear":false,"address_hidden":true,"region_hidden":true,"space_comment":"","space_hidden":false,"space":"48.6","address":"","region":"","costs_property":"","costs_rent_comment":"","space_units":"м²","costs_property_comment":"","costs_rent":""}]},"intro":{"declaration_year":"2014","isnotdeclaration":"","declaration_year_unclear":false}}