{"income":{"5":{"value":"310326.51","family_comment":"","value_unclear":false,"family_unclear":false,"family":"128400","comment":""},"6":{"value":"256031.95","family_comment":"","value_unclear":false,"family_unclear":false,"family":"","comment":""},"7":{"family_comment":"","value":"","source_name":"","family":"","comment":""},"8":{"family_comment":"","value":"","family":"","comment":""},"9":{"family_comment":"","value":"","value_unclear":false,"family":"","comment":""},"10":{"family_comment":"","value":"","value_unclear":false,"family":"","comment":""},"11":{"family_comment":"","value":"","family":"","comment":""},"12":{"family_comment":"","value":"","family":"","comment":""},"13":{"family_comment":"","value":"","value_unclear":false,"family":"","comment":""},"14":{"family_comment":"","value":"","family":"","comment":""},"15":{"family_comment":"","value":"19567.56","family":"32400","comment":""},"16":{"family_comment":"","value":"","family":"","comment":""},"17":{"family_comment":"","value":"","family":"96000","comment":""},"18":{"family_comment":"","value":"","family":"","comment":""},"19":{"family_comment":"","value":"","family":"","comment":""},"20":{"family_comment":"","family_unclear":false,"value":"34727","family":"","comment":""}},"vehicle":{"35":[{"year_hidden":false,"brand_info":"1799 куб. см.","sum_rent_comment":"","year":"2006","brand_info_unclear":false,"sum_rent":"","sum":"","brand":"Honda Civic","sum_comment":"","brand_unclear":false,"brand_hidden":false,"sum_comment_unclear":false}],"40":[{"brand_info":"2260 куб. см.","sum":"","brand":"Mazda CX-7","sum_comment":"","brand_unclear":false,"year":"2007","brand_info_hidden":false,"brand_info_unclear":true,"year_unclear":false,"sum_rent_comment":"","sum_rent":""}]},"id":"vulyk_85_73","declaration":{"additional_info_text":"","notfull_lostpages":"","date":"2015-03-25T00:00:00","notfull":"","additional_info":"","url":"http://static.declarations.com.ua/declarations/chosen_ones/judges_batch/2676_medintseva_nina_mykhailivna.pdf"},"liabilities":{"54":{"sum_foreign_comment":"","sum":"","sum_comment":"","sum_comment_unclear":false,"sum_foreign":""},"55":{"sum_foreign_comment":"","sum":"","sum_comment":"","sum_foreign":""},"56":{"sum_foreign_comment":"","sum":"","sum_comment":"","sum_unclear":false,"sum_foreign":""},"57":{"sum_foreign_comment":"","sum":"","sum_comment":"","sum_foreign":""},"58":{"sum_foreign_comment":"","sum_comment":"","sum":"","sum_comment_hidden":false,"sum_foreign":""},"59":{"sum_foreign_comment":"","sum":"","sum_comment":"","sum_foreign":""},"60":{"sum_foreign_comment":"","sum":"","sum_comment":"","sum_foreign":""},"61":{"sum_foreign_comment":"","sum":"","sum_comment":"","sum_foreign":""},"62":{"sum_foreign_comment":"","sum":"","sum_comment":"","sum_unclear":false,"sum_foreign":""},"63":{"sum_foreign_comment":"","sum":"32214.9","sum_comment":"","sum_unclear":false,"sum_foreign":""},"64":{"sum_foreign_comment":"","sum":"","sum_comment":"","sum_foreign":""}},"ft_src":"1799 куб. см.\nHonda Civic\n2006\nMazda CX-7\n2260 куб. см.\n2007\nм. Артемівськ\nДонецька область\n.1077\nДонецька область\nм. Артемівськ\n.0054\nДонецька область\nм. Артемівськ\n44.6\n1/3 вiд 86,05\n28.68\nм. Артемівськ\nДонецька область\n235.1\nДонецька область\nм. Артемівськ\n44.56\nДонецька область\nм. Артемівськ\n41.28\n47.2\n1/3 вiд 86,05\n28.68\n2014\n256031.95\n32400\n19567.56\n128400\n310326.51\n96000\n34727\n1799 куб. см.\nHonda Civic\n2006\n2260 куб. см.\n2007\nMazda CX-7\n235.1\nДонецька область\nм. Артемівськ\n44.56\nм. Артемівськ\nДонецька область\n47.2\n28.68\n1/3 вiд 86,05\n.1077\nДонецька область\nм. Артемівськ\n.0054\nм. Артемівськ\nДонецька область\n44.6\nм. Артемівськ\nДонецька область\n28.68\n1/3 вiд 86,05\n41.28\nм. Артемівськ\nДонецька область\nМедінцева Ніна Михайлівна\nНіна Михайлівна Медінцева\nНіна Медінцева\nМедінцева Ніна Михайлівна\nНіна\nПодружжя\nТопузян Р. Х\nМедінцева Ніна Михайлівна\nМедінцева\nЗагальний місцевий суд\nзаступник голови артемівського міськрайонного суду донецької області\nДонецька область\nМихайлівна\nДонецька область\n32214.9\n256031.95\n96000\n34727\n19567.56\n32400\n310326.51\n128400\n2014\n32214.9\nТопузян Р. Х\nПодружжя\nМихайлівна\nМедінцева\nНіна\nМедінцева Ніна Михайлівна\nНіна Михайлівна Медінцева\nНіна Медінцева\nМедінцева Ніна Михайлівна\nДонецька область\nзаступник голови артемівського міськрайонного суду донецької області\nДонецька область\nЗагальний місцевий суд\nМедінцева Ніна Михайлівна","general":{"inn":"","name":"Ніна","last_name_hidden":false,"family":[{"inn":"","inn_hidden":true,"relations_unclear":false,"relations_hidden":false,"relations_other":"","relations":"Подружжя","name_hidden":true,"family_name":"Топузян Р. Х","name_unclear":false}],"patronymic":"Михайлівна","inn_hidden":true,"family_raw":"","last_name":"Медінцева","post":{"post_unclear":false,"post_hidden":false,"post":"заступник голови артемівського міськрайонного суду донецької області","region":"Донецька область","office":"Загальний місцевий суд"},"full_name_suggest":{"output":"Медінцева Ніна Михайлівна","input":["Медінцева Ніна Михайлівна","Ніна Михайлівна Медінцева","Ніна Медінцева"]},"full_name":"Медінцева Ніна Михайлівна","addresses":[{"place_district":"","place_address_hidden":true,"place_city":"","place_address":"","place_district_hidden":false,"place_city_type":"","place_city_hidden":true,"place_city_type_hidden":false,"place_hidden":false,"place":"Донецька область"}],"last_name_unclear":false},"source":"VULYK","estate":{"25":[{"space_unclear":false,"costs":"","costs_comment":"","address_hidden":false,"region_hidden":true,"space_comment":"","space_hidden":false,"space":"47.2","address":"","costs_comment_unclear":false,"region":"","costs_rent_comment":"","space_comment_unclear":false,"space_units":"м²","costs_rent":""},{"space_hidden":false,"costs":"","costs_comment":"","address_hidden":false,"region_hidden":false,"space_comment":"1/3 вiд 86,05","space":"28.68","address":"","region":"","costs_rent_comment":"","space_units":"м²","costs_rent":""}],"29":[{"space_unclear":false,"address_hidden":true,"region_hidden":true,"space_comment":"","space":".1077","address":"м. Артемівськ","region":"Донецька область","costs_property":"","costs_rent_comment":"","space_units":"га","costs_property_comment":"","costs_rent":""},{"costs_rent":"","region":"Донецька область","costs_property":"","costs_rent_comment":"","address_hidden":true,"region_hidden":true,"space_comment":"","costs_property_comment":"","space_units":"га","space":".0054","address":"м. Артемівськ"}],"30":[{"space_unclear":false,"address_hidden":true,"region_hidden":true,"space_comment":"","space":"235.1","address":"м. Артемівськ","region":"Донецька область","costs_property":"","costs_rent_comment":"","space_units":"м²","costs_property_comment":"","costs_rent":""},{"costs_rent":"","region":"Донецька область","costs_property":"","costs_rent_comment":"","space_comment":"","costs_property_comment":"","space_units":"м²","space":"44.56","address":"м. Артемівськ"}],"31":[{"space_unclear":false,"address_hidden":true,"region_hidden":true,"space_comment":"1/3 вiд 86,05","space":"28.68","address":"","region":"","costs_property":"","costs_rent_comment":"","space_units":"м²","costs_property_comment":"","costs_rent":""}],"33":[{"costs_rent":"","region":"Донецька область","costs_property":"","costs_rent_comment":"","address_hidden":true,"region_hidden":false,"space_comment":"","costs_property_comment":"","space_units":"м²","space":"44.6","address":"м. Артемівськ"}],"34":[{"costs_rent":"","region":"Донецька область","costs_property":"","costs_rent_comment":"","address_hidden":true,"region_hidden":false,"space_comment":"","costs_property_comment":"","space_units":"м²","space":"41.28","address":"м. Артемівськ"}]},"intro":{"declaration_year":"2014","isnotdeclaration":""}}