{"id":"vulyk_84_159","ft_src":"Кіровоградська область\nм. Кіровоград\n47.9\nКіровоградська область\nм. Кіровоград\n47.9\n204257\n2014\n2014\nКулінка Людмила Дмитріївна\nЛюдмила Дмитріївна Кулінка\nЛюдмила Кулінка\nКулінка Людмила Дмитріївна\nЛюдмила\nДитина\nБалабан К. С., 20. 02. 1998\nКулінка Людмила Дмитріївна\nДмитріївна\nсуддя кіровського районного суд м. кіровограда\nЗагальний місцевий суд\nКіровоградська область\nКулінка\nКіровоград\n25030\nКіровоградська область\n168864\n191319\n10275\n12180\nм. Кіровоград\nКіровоградська область\n47.9\n47.9\nКіровоградська область\nм. Кіровоград\n204257\n168864\n10275\n12180\n191319\nБалабан К. С., 20. 02. 1998\nДитина\nДмитріївна\nКулінка\nЛюдмила\nКулінка Людмила Дмитріївна\nЛюдмила Дмитріївна Кулінка\nЛюдмила Кулінка\nКулінка Людмила Дмитріївна\nКіровоградська область\nКіровоград\n25030\nКіровоградська область\nсуддя кіровського районного суд м. кіровограда\nЗагальний місцевий суд\nКулінка Людмила Дмитріївна","estate":{"25":[{"address":"м. Кіровоград","space_units":"м²","space_hidden":false,"space_comment":"","region_hidden":false,"costs_comment":"","address_hidden":true,"costs":"","address_unclear":false,"costs_rent_comment_unclear":false,"costs_comment_unclear":false,"costs_rent_comment":"","space":"47.9","region_unclear":false,"region":"Кіровоградська область","costs_rent":""}],"31":[{"costs_property_comment":"","address":"м. Кіровоград","space_units":"м²","space_unclear":false,"region_hidden":false,"costs_property":"","space_comment":"","address_hidden":true,"address_unclear":false,"costs_rent_comment":"","space":"47.9","region":"Кіровоградська область","costs_rent":""}]},"source":"VULYK","income":{"5":{"family_comment":"","family":"","comment":"","value_unclear":false,"family_unclear":false,"comment_unclear":false,"value":"191319"},"6":{"family_comment":"","comment_unclear":false,"value":"168864","family":"","comment":""},"7":{"family":"","family_comment":"","value":"","comment":"","source_name":""},"8":{"family_comment":"","value":"","family":"","comment":""},"9":{"family_comment":"","value":"10275","family":"","comment":"","value_unclear":false},"10":{"family_comment":"","value":"12180","family":"","comment":"","value_unclear":false},"11":{"family_comment":"","value":"","family":"","comment":""},"12":{"family_comment":"","value":"","family":"","comment":""},"13":{"family_comment":"","value":"","family":"","comment":""},"14":{"family_comment":"","value":"","family":"","comment":""},"15":{"family_comment":"","value":"","family":"","comment":""},"16":{"family_comment":"","value":"","family":"","comment":""},"17":{"family_comment":"","value":"","family":"","comment":"","value_unclear":false},"18":{"family_comment":"","value":"","family":"","comment":"","value_unclear":false},"19":{"family_comment":"","value":"","family":"","comment":""},"20":{"family_comment":"","family":"","comment":"","value_unclear":false,"family_unclear":false,"comment_unclear":false,"value":""}},"banks":{"45":[{"sum_comment_unclear":false,"sum_comment":"","sum_foreign_units":"UAH","sum":"204257","sum_foreign_comment":"","sum_foreign":"","sum_unclear":false,"sum_units":"UAH"}]},"declaration":{"notfull_lostpages":"","additional_info_text":"","additional_info":"","date":"2015-03-23T00:00:00","notfull":"","url":"http://static.declarations.com.ua/declarations/chosen_ones/judges_batch/2573_kulinka_liudmyla_dmytriivna.pdf"},"general":{"family_raw":"","name":"Людмила","full_name_suggest":{"input":["Кулінка Людмила Дмитріївна","Людмила Дмитріївна Кулінка","Людмила Кулінка"],"output":"Кулінка Людмила Дмитріївна"},"patronymic":"Дмитріївна","inn_hidden":true,"addresses":[{"place_city_type_hidden":false,"place_district_hidden":false,"place_address_unclear":false,"place":"Кіровоградська область","place_city":"Кіровоград","place_unclear":false,"place_city_type_unclear":false,"place_city_type":"Місто","place_city_hidden":false,"place_city_unclear":false,"place_district":"","place_district_unclear":false,"place_address":"25030","place_address_hidden":true,"place_hidden":false}],"inn":"","inn_unclear":false,"last_name":"Кулінка","full_name":"Кулінка Людмила Дмитріївна","family":[{"inn":"","inn_unclear":false,"family_name":"Балабан К. С., 20. 02. 1998","relations_other":"","relations_hidden":false,"name_unclear":true,"inn_hidden":true,"name_hidden":false,"relations":"Дитина"}],"post":{"post_hidden":false,"office":"Загальний місцевий суд","region_hidden":false,"post":"суддя кіровського районного суд м. кіровограда","candidate":"","region_unclear":false,"region":"Кіровоградська область","office_hidden":false,"post_unclear":false,"office_unclear":false}},"liabilities":{"54":{"sum_comment":"","sum_foreign_comment":"","sum_foreign":"","sum":"","sum_comment_hidden":false},"55":{"sum_comment":"","sum_foreign_comment":"","sum_foreign":"","sum":""},"56":{"sum_comment":"","sum_foreign_comment":"","sum_foreign":"","sum":""},"57":{"sum_comment":"","sum_foreign_comment":"","sum_foreign":"","sum":"","sum_comment_hidden":false},"58":{"sum_comment":"","sum_foreign_comment":"","sum_foreign":"","sum":"","sum_comment_hidden":false},"59":{"sum_comment":"","sum_foreign_comment":"","sum_foreign":"","sum":""},"60":{"sum_comment":"","sum_foreign_comment":"","sum_foreign":"","sum":""},"61":{"sum_comment":"","sum_foreign_comment":"","sum_foreign":"","sum":""},"62":{"sum_comment":"","sum_foreign_comment":"","sum_foreign":"","sum":""},"63":{"sum_comment":"","sum_foreign_comment":"","sum_foreign":"","sum":"","sum_comment_hidden":false},"64":{"sum_comment":"","sum_foreign_comment":"","sum_foreign":"","sum":"","sum_comment_hidden":false}},"intro":{"isnotdeclaration":"","declaration_year_unclear":false,"declaration_year":"2014"}}