{"income":{"5":{"family_comment":"","family_unclear":false,"value":"813587","family":"1560314","comment":""},"6":{"value":"233287","family_comment":"","comment_unclear":false,"family_unclear":false,"family":"","comment":""},"7":{"source_name_unclear":false,"value":"","family_comment":"","source_name":"","family":"","comment":"","source_name_hidden":false},"8":{"family_comment":"","value":"","family":"","comment":""},"9":{"family_comment":"","value":"","family":"","comment":""},"10":{"family_comment":"","value":"","comment_unclear":false,"family":"","comment":""},"11":{"family_comment":"","value":"300","family":"","comment":""},"12":{"family_comment":"","value":"","family":"","comment":""},"13":{"family_comment":"","value":"","family":"","comment":""},"14":{"family_comment":"","value":"","family":"","comment":""},"15":{"family_comment":"","value":"","family":"","comment":""},"16":{"value":"580000","comment_hidden":false,"value_hidden":false,"family_comment":"","family":"1126431","comment":"","family_comment_unclear":false},"17":{"family_comment":"","value":"","family":"433883","comment":""},"18":{"family_comment":"","value":"","family":"","comment":""},"19":{"family_comment":"","value":"","family":"","comment":""},"20":{"value":"","family_comment":"","value_unclear":false,"family":"","family_unclear":false,"comment_unclear":false,"comment":"","family_comment_unclear":false}},"vehicle":{"35":[{"brand_info":"2993 куб. см.","sum_rent_comment":"","year":"2013","sum_rent_unclear":false,"brand_info_hidden":false,"brand_info_unclear":false,"sum_rent":"","sum":"520000","brand":"BMW","sum_comment":"","sum_comment_unclear":false,"brand_hidden":false,"sum_unclear":false,"brand_unclear":false}],"39":[{"year_hidden":true,"brand_info":"1170 куб.см., 92 кВт","sum_rent_comment":"","brand":"BMW","sum_comment":"","year":"","brand_hidden":false,"sum":"","sum_rent":""}],"40":[{"year_hidden":false,"brand_info":"2986 куб. см. 166 кВт","sum_rent_comment":"","year":"2011","brand_info_hidden":false,"brand_info_unclear":false,"sum_rent":"","sum":"","brand":"Mercedes-Benz","sum_comment":"","brand_hidden":false,"sum_unclear":false}]},"id":"vulyk_58_176","banks":{"45":[{"sum_foreign_comment":"","sum_units":"UAH","sum_comment":"","sum_comment_unclear":false,"sum_hidden":false,"sum_foreign_units":"UAH","sum_comment_hidden":false,"sum_units_hidden":false,"sum":"","sum_foreign":""},{"sum_foreign_comment":"","sum_units":"","sum_comment":"","sum_foreign_units":"","sum":"","sum_foreign":""}],"46":[{"sum_foreign_comment":"","sum_units":"UAH","sum_comment":"","sum_foreign_units":"UAH","sum_comment_hidden":false,"sum":"","sum_foreign":""}],"47":[{"sum_foreign_comment":"","sum_units":"UAH","sum_comment":"","sum_foreign_units":"UAH","sum_comment_hidden":false,"sum":"","sum_foreign":""}],"48":[{"sum_foreign_comment":"","sum_units":"UAH","sum_comment":"","sum_foreign_units":"UAH","sum":"","sum_foreign":""}],"49":[{"sum_foreign_comment":"","sum_units":"UAH","sum_comment":"","sum_foreign_units":"UAH","sum":"","sum_foreign":""}],"50":[{"sum_foreign_comment":"","sum_units":"UAH","sum_comment":"","sum_foreign_units":"UAH","sum":"","sum_foreign":""}],"51":[{"sum_foreign_comment":"","sum_units":"UAH","sum_comment":"","sum_foreign_units":"UAH","sum_comment_hidden":false,"sum":"","sum_foreign":""},{"sum_foreign_comment":"","sum_units":"","sum_comment":"","sum_comment_hidden":false,"sum":"","sum_foreign":""}],"52":[{"sum_foreign_comment":"","sum_units":"UAH","sum_comment":"","sum_foreign_units":"UAH","sum":"","sum_foreign":""}],"53":[{"sum_foreign_comment":"","sum_units":"UAH","sum_comment":"","sum_foreign_units":"UAH","sum":"","sum_foreign":""}]},"declaration":{"additional_info_text":"","notfull_lostpages":"","date":"2015-03-27T00:00:00","notfull":"","additional_info":"","url":"http://static.declarations.com.ua/declarations/chosen_ones/mega_batch/kuzmyshyn_vitalii_mykolaiovych.pdf"},"liabilities":{"54":{"sum_foreign_comment":"","sum":"","sum_hidden":false,"sum_comment":"","sum_foreign":""},"55":{"sum_foreign_comment":"","sum":"","sum_hidden":false,"sum_comment":"","sum_foreign":""},"56":{"sum_foreign_comment":"","sum":"9117","sum_comment":"","sum_unclear":false,"sum_foreign":""},"57":{"sum_foreign_comment":"","sum":"","sum_comment":"","sum_comment_unclear":false,"sum_comment_hidden":false,"sum_unclear":false,"sum_foreign":""},"58":{"sum_foreign_comment":"","sum":"","sum_comment":"","sum_comment_unclear":false,"sum_comment_hidden":false,"sum_unclear":false,"sum_foreign":""},"59":{"sum_foreign_comment":"","sum":"","sum_comment":"","sum_foreign":""},"60":{"sum_foreign_comment":"","sum":"","sum_comment":"","sum_comment_unclear":false,"sum_unclear":false,"sum_foreign":""},"61":{"sum_foreign_comment":"","sum":"","sum_comment":"","sum_foreign":""},"62":{"sum_foreign_comment":"","sum":"47741","sum_comment":"","sum_foreign":""},"63":{"sum_foreign_comment":"","sum":"","sum_comment":"","sum_comment_unclear":false,"sum_comment_hidden":false,"sum_unclear":false,"sum_foreign":""},"64":{"sum_foreign_comment":"","sum":"","sum_comment":"","sum_comment_unclear":false,"sum_comment_hidden":false,"sum_unclear":false,"sum_foreign":""}},"ft_src":"47741\n9117\nВінницька область\nголова вінницького апеляційного адміністративного суду\nВінницька область\nАпеляційний адміністративний суд\nВіталій\nКузьмишина А. Л\nПодружжя\nКузьмишина А. В\nДитина\nКузьмишин В. В\nДитина\nКузьмишина С. В\nДитина\nМиколайович\nКузьмишин Віталій Миколайович\nВіталій Миколайович Кузьмишин\nВіталій Кузьмишин\nКузьмишин Віталій Миколайович\nКузьмишин Віталій Миколайович\nКузьмишин\nBMW\n1170 куб.см., 92 кВт\n2993 куб. см.\nBMW\n2013\n520000\n2986 куб. см. 166 кВт\nMercedes-Benz\n2011\n2014\n2993 куб. см.\nBMW\n2013\n520000\n2986 куб. см. 166 кВт\nMercedes-Benz\n2011\n1170 куб.см., 92 кВт\nBMW\n88\n1/4\n91.7\n48.8\n116.6\n91.7\nПодружжя\nКузьмишина А. Л\nДитина\nКузьмишина А. В\nДитина\nКузьмишин В. В\nДитина\nКузьмишина С. В\nКузьмишин Віталій Миколайович\nВіталій Миколайович Кузьмишин\nВіталій Кузьмишин\nКузьмишин Віталій Миколайович\nКузьмишин Віталій Миколайович\nВіталій\nМиколайович\nАпеляційний адміністративний суд\nголова вінницького апеляційного адміністративного суду\nВінницька область\nКузьмишин\nВінницька область\n9117\n47741\n233287\n433883\n813587\n1560314\n580000\n1126431\n300\n2014\n9117\n47741\n91.7\n48.8\n116.6\n1/4\n88\n91.7\nКузьмишина А. Л\nПодружжя\nКузьмишина А. В\nДитина\nКузьмишин В. В\nДитина\nКузьмишина С. В\nДитина\nМиколайович\nКузьмишин\nВіталій\nКузьмишин Віталій Миколайович\nВіталій Миколайович Кузьмишин\nВіталій Кузьмишин\nКузьмишин Віталій Миколайович\nВінницька область\nВінницька область\nголова вінницького апеляційного адміністративного суду\nАпеляційний адміністративний суд\nКузьмишин Віталій Миколайович\n233287\n300\n1560314\n813587\n1126431\n580000\n433883\nBMW\n1170 куб.см., 92 кВт\n2013\nBMW\n520000\n2993 куб. см.\nMercedes-Benz\n2986 куб. см. 166 кВт\n2011\n300\n1560314\n813587\n580000\n1126431\n433883\n233287\n91.7\n48.8\n1/4\n88\n116.6\n91.7\n2014","general":{"inn":"","name":"Віталій","inn_unclear":false,"family":[{"inn":"","inn_hidden":false,"relations_hidden":false,"family_name":"Кузьмишина А. Л","relations_other":"","relations":"Подружжя","name_hidden":false,"name_unclear":false},{"inn":"","inn_hidden":false,"relations_hidden":false,"family_name":"Кузьмишина А. В","relations_other":"","relations":"Дитина","name_hidden":false,"name_unclear":false},{"inn":"","relations":"Дитина","inn_unclear":false,"family_name":"Кузьмишин В. В","inn_hidden":false,"relations_other":"","name_hidden":false,"name_unclear":false},{"inn":"","relations":"Дитина","relations_other":"","inn_hidden":false,"family_name":"Кузьмишина С. В","name_unclear":false}],"inn_hidden":true,"family_raw":"","last_name":"Кузьмишин","post":{"post_unclear":false,"post":"голова вінницького апеляційного адміністративного суду","post_hidden":false,"region":"Вінницька область","region_hidden":false,"office":"Апеляційний адміністративний суд","office_hidden":false,"office_unclear":false},"full_name_suggest":{"output":"Кузьмишин Віталій Миколайович","input":["Кузьмишин Віталій Миколайович","Віталій Миколайович Кузьмишин","Віталій Кузьмишин"]},"full_name":"Кузьмишин Віталій Миколайович","addresses":[{"place_city_type_hidden":false,"place_district_hidden":false,"place_city_type":"","place_city_hidden":false,"place_address_unclear":false,"place_address":"","place_hidden":false,"place":"Вінницька область","place_district":"","place_unclear":false,"place_city":"","place_address_hidden":true,"place_district_unclear":false}],"patronymic":"Миколайович","last_name_unclear":false},"source":"VULYK","estate":{"23":[{"space_unclear":false,"costs":"","costs_comment":"","address_hidden":false,"region_hidden":false,"space_comment":"","space_hidden":false,"space":"","address":"","costs_comment_unclear":false,"costs_rent_comment_unclear":false,"region":"","address_unclear":false,"costs_rent_comment":"","costs_unclear":false,"space_units":"м²","costs_rent":""},{"costs":"","costs_comment":"","address_hidden":false,"region_hidden":false,"space_comment":"","space":"","address":"","region":"","address_unclear":false,"costs_rent_comment":"","space_units":"","costs_rent":""},{"costs":"","costs_comment":"","address_hidden":false,"region_hidden":false,"space_comment":"","space":"","address":"","region":"","address_unclear":false,"costs_rent_comment":"","space_units":"","costs_rent":""},{"costs_rent":"","region":"","costs":"","costs_rent_comment":"","costs_comment":"","space_comment":"","space_units":"","space":"","address":""},{"costs_rent":"","costs":"","costs_rent_comment":"","costs_comment":"","space_comment":"","space_units":"","space":"","address":""}],"24":[{"space_unclear":true,"costs":"","costs_comment":"","address_hidden":false,"region_hidden":true,"space_comment":"1/4","space_hidden":false,"space":"88","address":"","costs_comment_unclear":false,"costs_unclear":false,"region":"","address_unclear":false,"costs_rent_comment":"","space_comment_unclear":true,"space_units":"м²","costs_rent":""}],"25":[{"region_unclear":false,"space_hidden":false,"costs":"","costs_comment":"","address_hidden":false,"region_hidden":true,"space_comment":"","space":"91.7","address":"","region":"","costs_rent_comment":"","space_comment_unclear":false,"space_units":"м²","costs_rent":""}],"31":[{"space_unclear":false,"costs_property_hidden":false,"address_hidden":false,"region_hidden":true,"space_comment":"","space_hidden":false,"space":"91.7","address":"","region":"","costs_property":"","costs_rent_comment":"","costs_rent_hidden":false,"space_comment_unclear":false,"space_units":"м²","costs_property_comment":"","costs_rent":""},{"space_unclear":false,"address_hidden":false,"region_hidden":false,"space_comment":"","space":"48.8","address":"","region":"","costs_property":"","costs_rent_comment":"","space_comment_unclear":false,"space_units":"м²","costs_property_comment":"","costs_rent":""}],"34":[{"region_unclear":false,"address_hidden":false,"region_hidden":true,"space_comment":"","space":"116.6","address":"","region":"","costs_property":"","costs_rent_comment":"","space_units":"м²","costs_property_comment":"","costs_rent":""}]},"intro":{"declaration_year":"2014","isnotdeclaration":"","declaration_year_hidden":false}}