{"income":{"5":{"value":"231876.51","family_comment":"","value_unclear":false,"family_hidden":false,"value_hidden":false,"family_unclear":false,"comment_unclear":false,"comment":"","family":""},"6":{"value":"219696.51","family_comment":"","value_unclear":false,"family_hidden":false,"value_hidden":false,"family_unclear":false,"comment_unclear":false,"comment":"","family":""},"7":{"source_name_unclear":false,"value":"","family_comment":"","source_name":"","family":"","comment":""},"8":{"family_comment":"","value":"","family":"","comment":""},"9":{"value":"","value_unclear":false,"comment_hidden":false,"family_comment":"","comment_unclear":false,"comment":"","family":""},"10":{"value":"12180","comment_unclear":false,"value_hidden":false,"family_comment":"","family":"","comment":""},"11":{"family_comment":"","value":"","family":"","comment":""},"12":{"family_comment":"","value":"","family":"","comment":""},"13":{"family_comment":"","value":"","family":"","comment":""},"14":{"family_comment":"","value":"","family":"","comment":""},"15":{"family_comment":"","value":"","family":"","comment":""},"16":{"family_comment":"","value":"","family":"","comment":""},"17":{"family_comment":"","value":"","family":"","comment":""},"18":{"value":"","family_hidden":false,"value_hidden":false,"family_comment":"","family":"","comment":""},"19":{"family_comment":"","value":"","family":"","comment":""},"20":{"value":"","family_comment":"","value_unclear":false,"family_hidden":false,"value_hidden":false,"family_unclear":false,"family":"","comment":""}},"id":"vulyk_66_147","declaration":{"additional_info_text":"","notfull_lostpages":"","date":"2015-03-02T00:00:00","notfull":"","additional_info":"","url":"http://static.declarations.com.ua/declarations/chosen_ones/mega_batch/karikova_larysa_vitaliivna.pdf"},"liabilities":{"54":{"sum_foreign_comment":"","sum":"","sum_comment":"","sum_comment_unclear":false,"sum_comment_hidden":false,"sum_unclear":false,"sum_foreign":""},"55":{"sum_foreign_comment":"","sum":"","sum_comment":"","sum_foreign":""},"56":{"sum_foreign_comment":"","sum_foreign_hidden":false,"sum_comment":"","sum_hidden":false,"sum_comment_hidden":false,"sum":"","sum_foreign":""},"57":{"sum_foreign_comment":"","sum":"690.94","sum_comment":"","sum_comment_unclear":false,"sum_hidden":false,"sum_comment_hidden":false,"sum_unclear":false,"sum_foreign":""},"58":{"sum_foreign_comment":"","sum":"291.31","sum_comment":"","sum_comment_unclear":false,"sum_unclear":false,"sum_foreign":""},"59":{"sum_foreign_comment":"","sum_foreign_hidden":false,"sum_comment":"","sum_comment_unclear":false,"sum_hidden":false,"sum":"","sum_foreign":""},"60":{"sum_foreign_comment":"","sum":"","sum_comment":"","sum_comment_unclear":false,"sum_foreign":""},"61":{"sum_foreign_comment":"","sum":"","sum_comment":"","sum_foreign":""},"62":{"sum_foreign_comment":"","sum_foreign_hidden":false,"sum_comment":"","sum_hidden":false,"sum":"","sum_unclear":false,"sum_foreign":""},"63":{"sum_foreign_comment":"","sum":"","sum_comment":"","sum_comment_unclear":false,"sum_comment_hidden":false,"sum_unclear":false,"sum_foreign":""},"64":{"sum_foreign_comment":"","sum":"","sum_comment":"","sum_comment_unclear":false,"sum_foreign":""}},"ft_src":"690.94\n291.31\nсуддя миколаївського районного суду миколаївської області\nМиколаївська область\nЗагальний місцевий суд\nЛариса\nІвченко В. О. 26. 09. 2000 р. н\nДитина\nВіталіївна\nКарікова Лариса Віталіївна\nЛариса Віталіївна Карікова\nЛариса Карікова\nКарікова Лариса Віталіївна\nКарікова Лариса Віталіївна\nКарікова\n12180\n231876.51\n219696.51\n1/2 частина\n30\n1/2 частина\n30\n2014\n219696.51\n12180\n231876.51\n30\n1/2 частина\n30\n1/2 частина\nЗагальний місцевий суд\nсуддя миколаївського районного суду миколаївської області\nМиколаївська область\nДитина\nІвченко В. О. 26. 09. 2000 р. н\nКарікова Лариса Віталіївна\nЛариса Віталіївна Карікова\nЛариса Карікова\nКарікова Лариса Віталіївна\nКарікова Лариса Віталіївна\nЛариса\nКарікова\nВіталіївна\n690.94\n291.31\n219696.51\n231876.51\n12180\n2014\n291.31\n690.94\nІвченко В. О. 26. 09. 2000 р. н\nДитина\nВіталіївна\nКарікова\nЛариса\nКарікова Лариса Віталіївна\nЛариса Віталіївна Карікова\nЛариса Карікова\nКарікова Лариса Віталіївна\nМиколаївська область\nсуддя миколаївського районного суду миколаївської області\nЗагальний місцевий суд\nКарікова Лариса Віталіївна\n1/2 частина\n30\n30\n1/2 частина\n2014","general":{"inn":"","name":"Лариса","last_name_hidden":false,"family":[{"inn":"","inn_hidden":false,"relations_hidden":false,"family_name":"Івченко В. О. 26. 09. 2000 р. н","relations_other":"","relations":"Дитина","name_hidden":false,"name_unclear":true}],"patronymic":"Віталіївна","inn_hidden":true,"family_raw":"","inn_unclear":false,"post":{"post_unclear":false,"post":"суддя миколаївського районного суду миколаївської області","candidate":"","office_hidden":false,"region":"Миколаївська область","office":"Загальний місцевий суд","office_unclear":false},"full_name_suggest":{"output":"Карікова Лариса Віталіївна","input":["Карікова Лариса Віталіївна","Лариса Віталіївна Карікова","Лариса Карікова"]},"full_name":"Карікова Лариса Віталіївна","addresses":[{"place_city_type_unclear":false,"place_address":"","place_district_hidden":true,"place_city_type":"","place_address_hidden":true,"place_address_unclear":false,"place_city_type_hidden":true,"place":"","place_district":"","place_unclear":false,"place_city":"","place_city_unclear":false,"place_hidden":true,"place_city_hidden":true,"place_district_unclear":false}],"last_name":"Карікова","last_name_unclear":false},"source":"VULYK","estate":{"24":[{"space_unclear":false,"costs":"","costs_comment":"","costs_hidden":true,"address_hidden":false,"region_hidden":false,"space_comment":"","space_hidden":true,"space":"","address":"","region":"","address_unclear":false,"costs_rent_comment":"","costs_rent_hidden":true,"space_comment_unclear":false,"space_units":"м²","costs_rent":""}],"25":[{"region_unclear":false,"space_hidden":false,"costs":"","costs_comment":"","costs_hidden":false,"address_hidden":true,"region_hidden":true,"space_comment":"1/2 частина","space_unclear":false,"space":"30","space_units_hidden":false,"region":"","address_unclear":false,"costs_rent_comment":"","space_comment_unclear":false,"space_units":"м²","address":"","costs_rent":""}],"31":[{"space_unclear":false,"address_hidden":true,"region_hidden":true,"space_comment":"1/2 частина","space_hidden":false,"space":"30","address":"","region":"","costs_property":"","costs_rent_comment":"","space_comment_unclear":false,"space_comment_hidden":false,"space_units":"м²","costs_property_comment":"","costs_rent":""}]},"intro":{"declaration_year":"2014","isnotdeclaration":"","declaration_year_unclear":false}}