{"income":{"5":{"family_comment":"","family_unclear":false,"value":"245092","family":"50615","comment":""},"6":{"family_comment":"","family_unclear":false,"value":"245092","family":"50615","comment":""},"7":{"value":"","comment_hidden":false,"family_comment":"","source_name":"","family":"","comment":""},"8":{"family_comment":"","value":"","family":"","comment":""},"9":{"family_comment":"","value":"","family":"","comment":""},"10":{"family_comment":"","value":"","family":"","comment":""},"11":{"family_comment":"","value":"","value_unclear":false,"family":"","comment":""},"12":{"family_comment":"","value":"","family":"","comment":""},"13":{"family_comment":"","value":"","family":"","comment":""},"14":{"family_comment":"","value":"","family":"","comment":""},"15":{"family_comment":"","value":"","value_unclear":false,"family":"","comment":""},"16":{"family_comment":"","family_unclear":false,"value":"","family":"","comment":""},"17":{"family_comment":"","value":"","family":"","comment":""},"18":{"family_comment":"","value":"","family_hidden":false,"comment":"","family":""},"19":{"family_comment":"","value":"","family":"","comment":""},"20":{"value":"","comment_unclear":false,"comment_hidden":false,"family_comment":"","family":"","comment":"","family_comment_hidden":false}},"vehicle":{"35":[{"brand_info":"1400 куб. см.","sum_rent_comment":"","year":"2009","brand_info_hidden":false,"brand_info_unclear":true,"year_unclear":false,"sum_rent":"","sum":"89700","brand":"Hyundai Accent","sum_comment":"","brand_unclear":false,"brand_hidden":false}]},"id":"vulyk_68_64","declaration":{"additional_info_text":"","notfull_lostpages":"","date":"2015-03-27T00:00:00","notfull":"","additional_info":"","url":"http://static.declarations.com.ua/declarations/chosen_ones/mega_batch/strashnyi_oleksandr_mykolaiovych.pdf"},"liabilities":{"54":{"sum_foreign_comment":"","sum":"","sum_comment":"","sum_comment_unclear":false,"sum_hidden":false,"sum_comment_hidden":false,"sum_unclear":false,"sum_foreign":""},"55":{"sum_foreign_comment":"","sum":"","sum_hidden":false,"sum_comment":"","sum_foreign":""},"56":{"sum_foreign_comment":"","sum_foreign_hidden":false,"sum_comment":"","sum":"","sum_unclear":false,"sum_foreign":""},"57":{"sum_foreign_comment":"","sum":"","sum_comment":"","sum_comment_unclear":false,"sum_hidden":false,"sum_comment_hidden":false,"sum_unclear":false,"sum_foreign":""},"58":{"sum_foreign_comment":"","sum":"","sum_comment":"","sum_hidden":false,"sum_comment_hidden":false,"sum_unclear":false,"sum_foreign":""},"59":{"sum_foreign_comment":"","sum":"","sum_comment":"","sum_foreign":""},"60":{"sum_foreign_comment":"","sum":"","sum_comment":"","sum_comment_unclear":false,"sum_hidden":false,"sum_comment_hidden":false,"sum_unclear":false,"sum_foreign":""},"61":{"sum_foreign_comment":"","sum":"","sum_hidden":false,"sum_comment":"","sum_foreign":""},"62":{"sum_foreign_comment":"","sum":"","sum_comment":"","sum_unclear":false,"sum_foreign":""},"63":{"sum_foreign_comment":"","sum":"","sum_comment":"","sum_hidden":false,"sum_comment_hidden":false,"sum_unclear":false,"sum_foreign":""},"64":{"sum_foreign_comment":"","sum":"","sum_comment":"","sum_hidden":false,"sum_comment_hidden":false,"sum_foreign":""}},"ft_src":"заступник голови борзнянського районного суду чернігівської області\nЧернігівська область\nЗагальний місцевий суд\nОлександр\nСтрашна Тетяна Миколаївна 24. 11. 1962\nПодружжя\nМиколайович\nСтрашний Олександр Миколайович\nОлександр Миколайович Страшний\nОлександр Страшний\nСтрашний Олександр Миколайович\nСтрашний Олександр Миколайович\nСтрашний\n1400 куб. см.\nHyundai Accent\n2009\n89700\n.12\n.12\n1/4\n25\n1/4\n25\n2014\n50615\n245092\n50615\n245092\n1400 куб. см.\nHyundai Accent\n2009\n89700\n.12\n.12\n25\n1/4\n25\n1/4\nСтрашний Олександр Миколайович\nОлександр Миколайович Страшний\nОлександр Страшний\nСтрашний Олександр Миколайович\nСтрашний Олександр Миколайович\nПодружжя\nСтрашна Тетяна Миколаївна 24. 11. 1962\nОлександр\nМиколайович\nЗагальний місцевий суд\nЧернігівська область\nзаступник голови борзнянського районного суду чернігівської області\nСтрашний\n245092\n50615\n245092\n50615\n2014\nПодружжя\nСтрашна Тетяна Миколаївна 24. 11. 1962\nМиколайович\nСтрашний\nОлександр\nСтрашний Олександр Миколайович\nОлександр Миколайович Страшний\nОлександр Страшний\nСтрашний Олександр Миколайович\nЧернігівська область\nЗагальний місцевий суд\nзаступник голови борзнянського районного суду чернігівської області\nСтрашний Олександр Миколайович\n2009\nHyundai Accent\n89700\n1400 куб. см.\n50615\n245092\n50615\n245092\n1/4\n25\n.12\n.12\n25\n1/4\n2014","general":{"inn":"","name":"Олександр","inn_unclear":false,"family":[{"inn":"","inn_hidden":false,"relations_unclear":true,"relations_hidden":false,"relations_other":"","relations":"Подружжя","name_hidden":false,"inn_unclear":false,"family_name":"Страшна Тетяна Миколаївна 24. 11. 1962","name_unclear":false}],"inn_hidden":true,"family_raw":"","last_name":"Страшний","post":{"post_unclear":false,"region_unclear":false,"post":"заступник голови борзнянського районного суду чернігівської області","office":"Загальний місцевий суд","region":"Чернігівська область","post_hidden":false,"office_hidden":true,"office_unclear":true,"region_hidden":false},"full_name_suggest":{"output":"Страшний Олександр Миколайович","input":["Страшний Олександр Миколайович","Олександр Миколайович Страшний","Олександр Страшний"]},"full_name":"Страшний Олександр Миколайович","patronymic":"Миколайович","last_name_unclear":false,"name_unclear":false},"source":"VULYK","estate":{"23":[{"costs":"","costs_comment":"","address_hidden":false,"region_hidden":true,"space_comment":"","space":".12","address":"","region":"","costs_rent_comment":"","space_comment_hidden":false,"space_units":"га","costs_rent":""},{"costs_rent":"","region":"","costs":"","costs_rent_comment":"","costs_comment":"","address_hidden":false,"region_hidden":false,"space_comment":"","space_units":"га","space":".12","address":""}],"25":[{"space_unclear":false,"costs":"","costs_comment":"","address_hidden":false,"region_hidden":true,"space_comment":"1/4","space_hidden":false,"space":"25","address":"","space_comment_unclear":false,"region":"","address_unclear":false,"costs_rent_comment":"","costs_unclear":false,"space_units":"м²","space_units_hidden":false,"costs_rent":""}],"31":[{"space_unclear":false,"address_hidden":false,"region_hidden":true,"space_comment":"1/4","space_hidden":false,"space":"25","address":"","region":"","costs_property":"","costs_rent_comment":"","space_units":"м²","costs_property_comment":"","costs_rent":""}]},"intro":{"declaration_year":"2014","isnotdeclaration":""}}