{"income":{"5":{"family_comment":"","value":"193630.68","family":"10500","comment":""},"6":{"value":"193630.68","family_comment":"","value_unclear":false,"comment_hidden":false,"family_unclear":false,"family":"","comment":""},"7":{"family_comment":"","value":"","source_name":"","family":"","comment":""},"8":{"family_comment":"","value":"","family":"","comment":""},"9":{"family_comment":"","family_unclear":false,"value":"","family":"","comment":""},"10":{"family_comment":"","value":"","value_unclear":false,"family":"","comment":""},"11":{"family_comment":"","value":"","family":"","comment":""},"12":{"family_comment":"","value":"","family":"","comment":""},"13":{"family_comment":"","value":"","family":"","comment":""},"14":{"family_comment":"","value":"","family":"","comment":""},"15":{"family_comment":"","value":"","family":"","comment":""},"16":{"family_comment":"","value":"","family":"","comment":""},"17":{"family_comment":"","value":"","family":"","comment":""},"18":{"family_comment":"","value":"","family":"","comment":""},"19":{"family_comment":"","value":"","family":"","comment":""},"20":{"value":"","family":"10500","value_unclear":false,"family_hidden":false,"family_comment":"","comment_unclear":false,"comment":"","family_comment_unclear":false}},"vehicle":{"35":[{"year_hidden":false,"brand_info":"1992 куб. см., 150 к. с., 429.5 см","sum_rent_comment":"","year":"2010","brand_info_hidden":false,"brand_info_unclear":false,"sum_rent":"","sum":"","brand":"Mitsubishi ASX","sum_comment":"","brand_unclear":false,"brand_hidden":false}]},"id":"vulyk_97_95","declaration":{"additional_info_text":"","notfull_lostpages":"","date":"2015-03-30T00:00:00","notfull":"","additional_info":"","url":"http://static.declarations.com.ua/declarations/chosen_ones/judges_batch/3996_shevchenko_oleksandr_volodymyrovych.pdf"},"liabilities":{"54":{"sum_foreign_comment":"","sum":"","sum_comment":"","sum_comment_unclear":false,"sum_hidden":false,"sum_comment_hidden":false,"sum_unclear":false,"sum_foreign":""},"55":{"sum_foreign_comment":"","sum":"","sum_comment":"","sum_foreign":""},"56":{"sum_foreign_comment":"","sum":"","sum_comment":"","sum_foreign":""},"57":{"sum_foreign_comment":"","sum":"","sum_comment":"","sum_comment_unclear":false,"sum_hidden":false,"sum_comment_hidden":false,"sum_unclear":false,"sum_foreign":""},"58":{"sum_foreign_comment":"","sum":"","sum_comment":"","sum_comment_unclear":false,"sum_hidden":false,"sum_comment_hidden":false,"sum_unclear":false,"sum_foreign":""},"59":{"sum_foreign_comment":"","sum":"","sum_comment":"","sum_foreign":""},"60":{"sum_foreign_comment":"","sum":"","sum_comment":"","sum_comment_unclear":false,"sum_hidden":false,"sum_comment_hidden":false,"sum_foreign":""},"61":{"sum_foreign_comment":"","sum":"","sum_comment":"","sum_foreign":""},"62":{"sum_foreign_comment":"","sum":"","sum_comment":"","sum_unclear":false,"sum_foreign":""},"63":{"sum_foreign_comment":"","sum":"","sum_hidden":false,"sum_comment":"","sum_foreign":""},"64":{"sum_foreign_comment":"","sum":"","sum_comment":"","sum_foreign":""}},"ft_src":"Харків\n61000\nХарківська область\nсуддя харківського окружного адміністративного суду\nХарківська область\nАдміністративний місцевий суд\nОлександр\nШевченко Г. П\nПодружжя\nШевченко А. О\nДитина\nВолодимирович\nШевченко Олександр Володимирович\nОлександр Володимирович Шевченко\nОлександр Шевченко\nШевченко Олександр Володимирович\nШевченко Олександр Володимирович\nШевченко\n1992 куб. см., 150 к. с., 429.5 см\nMitsubishi ASX\n2010\n113.5\nм. Харків\nХарківська область\n2014\n193630.68\n10500\n193630.68\n10500\n1992 куб. см., 150 к. с., 429.5 см\nMitsubishi ASX\n2010\n2014\nШевченко Олександр Володимирович\nОлександр Володимирович Шевченко\nОлександр Шевченко\nШевченко Олександр Володимирович\nОлександр\nПодружжя\nШевченко Г. П\nДитина\nШевченко А. О\nШевченко Олександр Володимирович\nШевченко\nАдміністративний місцевий суд\nХарківська область\nсуддя харківського окружного адміністративного суду\nВолодимирович\nХарківська область\n61000\nХарків\n193630.68\n10500\n193630.68\n10500\n113.5\nм. Харків\nХарківська область\nПодружжя\nШевченко Г. П\nШевченко А. О\nДитина\nВолодимирович\nШевченко\nОлександр\nШевченко Олександр Володимирович\nОлександр Володимирович Шевченко\nОлександр Шевченко\nШевченко Олександр Володимирович\n61000\nХарків\nХарківська область\nХарківська область\nАдміністративний місцевий суд\nсуддя харківського окружного адміністративного суду\nШевченко Олександр Володимирович\n2010\nMitsubishi ASX\n1992 куб. см., 150 к. с., 429.5 см\n10500\n10500\n193630.68\n193630.68\nм. Харків\nХарківська область\n113.5\n2014","general":{"name_hidden":false,"name":"Олександр","last_name_hidden":false,"inn":"","family":[{"inn":"","relations":"Подружжя","relations_other":"","inn_hidden":true,"family_name":"Шевченко Г. П","name_hidden":true,"name_unclear":false},{"inn_hidden":true,"inn":"","name_hidden":false,"family_name":"Шевченко А. О","relations":"Дитина","name_unclear":false}],"patronymic":"Володимирович","inn_hidden":true,"family_raw":"","inn_unclear":false,"post":{"region_unclear":false,"region":"Харківська область","post":"суддя харківського окружного адміністративного суду","office":"Адміністративний місцевий суд","office_unclear":false,"post_hidden":false},"full_name":"Шевченко Олександр Володимирович","addresses":[{"place_district":"","place_city_hidden":false,"place_city":"Харків","place_city_unclear":false,"place_district_hidden":false,"place_city_type":"Місто","place_address_hidden":true,"place_city_type_hidden":false,"place_address":"61000","place_hidden":false,"place":"Харківська область"}],"last_name":"Шевченко","patronymic_hidden":false,"full_name_suggest":{"output":"Шевченко Олександр Володимирович","input":["Шевченко Олександр Володимирович","Олександр Володимирович Шевченко","Олександр Шевченко"]}},"source":"VULYK","estate":{"25":[{"region_unclear":false,"space_unclear":false,"costs":"","costs_comment":"","address_hidden":true,"region_hidden":false,"space_comment":"","space_hidden":false,"space":"113.5","address":"м. Харків","region":"Харківська область","costs_rent_comment":"","space_comment_unclear":false,"space_comment_hidden":false,"space_units":"м²","costs_rent":""}]},"intro":{"declaration_year":"2014","isnotdeclaration":""}}