{"income":{"5":{"value":"278461","value_unclear":false,"comment_hidden":false,"family_hidden":false,"value_hidden":false,"family_comment":"","family":"56035","comment":""},"6":{"value":"222801","value_unclear":false,"comment_hidden":false,"family_hidden":false,"value_hidden":false,"family_comment":"","family_comment_hidden":false,"comment":"","family":"49795"},"7":{"family_comment":"","value":"","source_name":"","family":"","comment":""},"8":{"family_comment":"","value":"","family":"","comment":""},"9":{"family_comment":"","value":"7495","family":"1097","comment":""},"10":{"value":"","value_unclear":false,"family_hidden":false,"family_comment":"","family":"4893","comment":""},"11":{"family_comment":"","value":"","family":"250","comment":""},"12":{"family_comment":"","value":"","family":"","comment":""},"13":{"family_comment":"","value":"","family":"","comment":""},"14":{"family_comment":"","value":"","family":"","comment":""},"15":{"family_comment":"","value":"","comment_unclear":false,"family":"","comment":""},"16":{"family_comment":"","value":"","family":"","comment":""},"17":{"family_comment":"","value":"","family":"","comment":""},"18":{"family_comment":"","value":"","family":"","comment":""},"19":{"family_comment":"","value":"","family":"","comment":""},"20":{"family_comment":"","value":"48165","family":"","comment":"","family_comment_hidden":false}},"vehicle":{"35":[{"brand_info":"2500 куб. см.","sum":"","brand":"Mercedes-Benz 250","sum_comment":"","brand_unclear":false,"year":"1995","brand_info_hidden":false,"sum_rent_comment":"","sum_rent":""}]},"id":"vulyk_79_21","declaration":{"date":"2015-03-27T00:00:00","additional_info_text":"","additional_info":"","url":"http://static.declarations.com.ua/declarations/chosen_ones/judges_batch/2026_horodivskyi_anatolii_andriiovych.pdf"},"liabilities":{"54":{"sum_foreign_comment":"","sum_comment_hidden":false,"sum":"","sum_comment":"","sum_foreign":""},"55":{"sum_foreign_comment":"","sum":"","sum_comment":"","sum_foreign":""},"56":{"sum_foreign_comment":"","sum":"","sum_hidden":false,"sum_comment":"","sum_foreign":""},"57":{"sum_foreign_comment":"","sum":"","sum_comment":"","sum_comment_unclear":false,"sum_hidden":false,"sum_comment_hidden":false,"sum_foreign":""},"58":{"sum_foreign_comment":"","sum":"","sum_comment":"","sum_comment_unclear":false,"sum_hidden":false,"sum_comment_hidden":false,"sum_unclear":false,"sum_foreign":""},"59":{"sum_foreign_comment":"","sum":"","sum_comment":"","sum_foreign":""},"60":{"sum_foreign_comment":"","sum_comment_hidden":false,"sum":"","sum_comment":"","sum_foreign":""},"61":{"sum_foreign_comment":"","sum":"","sum_comment":"","sum_foreign":""},"62":{"sum_foreign_comment":"","sum":"","sum_comment":"","sum_foreign":""},"63":{"sum_foreign_comment":"","sum":"","sum_comment":"","sum_unclear":false,"sum_foreign":""},"64":{"sum_foreign_comment":"","sum":"","sum_comment":"","sum_unclear":false,"sum_foreign":""}},"ft_src":"суддя козятинського міськрайонного суду вінницької області\nВінницька область\nЗагальний місцевий суд\nАнатолій\nГородівська Ганна Георгівна\nПодружжя\nГородівський Владислав Анатолійович\nДитина\nГородівська Юлія Анатоліївна\nДитина\nАндрійович\nГородівський Анатолій Андрійович\nАнатолій Андрійович Городівський\nАнатолій Городівський\nГородівський Анатолій Андрійович\nГородівський Анатолій Андрійович\nГородівський\n1995\nMercedes-Benz 250\n2500 куб. см.\n69.2\n433.4\n22.3\n2014\n49795\n222801\n1097\n7495\n250\n4893\n56035\n278461\n48165\nMercedes-Benz 250\n2500 куб. см.\n1995\n433.4\n69.2\n22.3\nПодружжя\nГородівська Ганна Георгівна\nДитина\nГородівський Владислав Анатолійович\nГородівська Юлія Анатоліївна\nДитина\nГородівський Анатолій Андрійович\nАнатолій Андрійович Городівський\nАнатолій Городівський\nГородівський Анатолій Андрійович\nГородівський Анатолій Андрійович\nАнатолій\nГородівський\nЗагальний місцевий суд\nВінницька область\nсуддя козятинського міськрайонного суду вінницької області\nАндрійович\n222801\n49795\n48165\n278461\n56035\n7495\n1097\n4893\n250\n2014\nГородівська Ганна Георгівна\nПодружжя\nГородівський Владислав Анатолійович\nДитина\nГородівська Юлія Анатоліївна\nДитина\nАндрійович\nГородівський\nАнатолій\nГородівський Анатолій Андрійович\nАнатолій Андрійович Городівський\nАнатолій Городівський\nГородівський Анатолій Андрійович\nВінницька область\nЗагальний місцевий суд\nсуддя козятинського міськрайонного суду вінницької області\nГородівський Анатолій Андрійович\n1995\nMercedes-Benz 250\n2500 куб. см.\n250\n1097\n7495\n4893\n48165\n278461\n56035\n222801\n49795\n69.2\n22.3\n433.4\n2014","general":{"inn":"","name":"Анатолій","last_name_hidden":false,"family":[{"inn":"","inn_hidden":true,"relations_hidden":false,"family_name":"Городівська Ганна Георгівна","relations_other":"","relations":"Подружжя","name_hidden":true,"name_unclear":false},{"inn_hidden":true,"inn":"","name_hidden":true,"family_name":"Городівський Владислав Анатолійович","relations":"Дитина","name_unclear":false},{"inn":"","family_name":"Городівська Юлія Анатоліївна","relations":"Дитина","inn_hidden":false}],"patronymic":"Андрійович","inn_hidden":true,"family_raw":"","inn_unclear":false,"post":{"post_unclear":false,"post":"суддя козятинського міськрайонного суду вінницької області","post_hidden":false,"region":"Вінницька область","region_hidden":false,"office":"Загальний місцевий суд","office_hidden":false,"office_unclear":false},"full_name":"Городівський Анатолій Андрійович","addresses":[{"place_district":"","place_city_hidden":true,"place_city":"","place_city_type_hidden":false,"place_district_hidden":false,"place_city_type":"","place_address_hidden":false,"place_address":"","place_hidden":true,"place":""}],"last_name":"Городівський","full_name_suggest":{"output":"Городівський Анатолій Андрійович","input":["Городівський Анатолій Андрійович","Анатолій Андрійович Городівський","Анатолій Городівський"]}},"source":"VULYK","estate":{"25":[{"space_unclear":false,"costs":"","costs_rent_unclear":false,"costs_comment":"","address_hidden":false,"region_hidden":true,"space_comment":"","space_hidden":false,"space":"22.3","address":"","costs_rent_comment_unclear":false,"region":"","costs_rent_comment":"","costs_unclear":false,"space_units":"м²","costs_rent":""}],"29":[{"costs_rent":"","region":"","costs_property":"","costs_rent_comment":"","address_hidden":false,"region_hidden":true,"space_comment":"","costs_property_comment":"","space_units":"м²","space":"433.4","address":""}],"30":[{"costs_rent":"","costs_property":"","costs_rent_comment":"","address_hidden":false,"region_hidden":true,"space_comment":"","costs_property_comment":"","space_units":"м²","space":"69.2","address":""}],"31":[{"space_unclear":false,"address_hidden":false,"region_hidden":true,"space_comment":"","space_hidden":true,"space":"","address":"","region":"","costs_property":"","costs_rent_comment":"","space_units":"м²","costs_property_comment":"","costs_rent":""}]},"intro":{"declaration_year":"2014"}}