{"income":{"5":{"value":"332087.3","family_comment":"","value_unclear":false,"family":"24308.78","family_unclear":false,"comment_unclear":false,"comment":"","family_comment_unclear":false},"6":{"value":"242087.3","family_comment":"","value_unclear":false,"family_unclear":false,"family":"","comment":""},"7":{"source_name_unclear":false,"value":"","value_unclear":false,"family_comment":"","source_name":"","family":"","comment":"","source_name_hidden":false},"8":{"family_comment":"","value":"","family":"","comment":""},"9":{"family_comment":"","value":"","family":"","comment":""},"10":{"family_comment":"","value":"","value_unclear":false,"family":"","comment":""},"11":{"value":"","value_unclear":false,"value_hidden":false,"family_comment":"","family":"","comment":""},"12":{"family_comment":"","value":"","family":"","comment":"","value_hidden":false},"13":{"family_comment":"","value":"","family":"","comment":""},"14":{"family_comment":"","value":"","family":"","comment":""},"15":{"family_comment":"","value":"","family":"","comment":""},"16":{"family_comment":"","value":"90000","family":"","comment":""},"17":{"family_comment":"","value":"","family":"","comment":""},"18":{"family_comment":"","value":"","family":"","comment":""},"19":{"family_comment":"","family_unclear":false,"value":"","family":"","comment":""},"20":{"family_comment":"","family_unclear":false,"value":"","family":"12588","comment":""}},"vehicle":{"35":[{"year_hidden":false,"brand_info":"","sum_rent_comment":"","year":"2013","sum_hidden":false,"brand_info_hidden":true,"brand_info_unclear":false,"year_unclear":false,"sum_rent":"","sum":"","brand":"Subaru Forester","sum_comment":"","brand_unclear":false,"brand_hidden":false}]},"id":"vulyk_61_9","declaration":{"additional_info_text":"","notfull_lostpages":"","date":"2015-03-17T00:00:00","notfull":"","additional_info":"","url":"http://static.declarations.com.ua/declarations/chosen_ones/mega_batch/yelizarov_ihor_ievhenovych.pdf"},"liabilities":{"54":{"sum_foreign_comment":"","sum":"","sum_comment":"","sum_comment_unclear":false,"sum_unclear":false,"sum_foreign":""},"55":{"sum_foreign_comment":"","sum":"","sum_comment":"","sum_foreign":""},"56":{"sum_foreign_comment":"","sum":"4700","sum_comment":"","sum_unclear":false,"sum_foreign":""},"57":{"sum_foreign_comment":"","sum":"90489.49","sum_comment":"","sum_comment_hidden":false,"sum_unclear":false,"sum_foreign":""},"58":{"sum_foreign_comment":"","sum":"10143.48","sum_comment":"","sum_unclear":false,"sum_foreign":""},"59":{"sum_foreign_comment":"","sum":"","sum_comment":"","sum_foreign":""},"60":{"sum_foreign_comment":"","sum_foreign_hidden":false,"sum_comment":"","sum_hidden":false,"sum":"","sum_foreign":""},"61":{"sum_foreign_comment":"","sum":"","sum_comment":"","sum_foreign":""},"62":{"sum_foreign_comment":"","sum":"","sum_comment":"","sum_unclear":false,"sum_foreign":""},"63":{"sum_foreign_comment":"","sum":"","sum_comment":"","sum_hidden":false,"sum_unclear":false,"sum_foreign":""},"64":{"sum_foreign_comment":"","sum":"","sum_hidden":false,"sum_comment":"","sum_foreign":""}},"ft_src":"90489.49\n10143.48\n4700\nХарків\nХарківська область\nсуддя московського районного суду м. харкова\nХарківська область\nЗагальний місцевий суд\nІгор\nЄлізарова Тетяна Іванівна\nПодружжя\nЄлізарова Катерина Ігорівна\nДитина\nЄвгенович\nЄлізаров\nЄлізаров Ігор Євгенович\nЄлізаров Ігор Євгенович\nІгор Євгенович Єлізаров\nІгор Єлізаров\nЄлізаров Ігор Євгенович\nSubaru Forester\n2013\nм. Харків\nХарківська область\n49.7\nм. Харків\n320.5\nХарківська область\nХарківський район\n57.1\nХарківська область\n2014\n242087.3\n24308.78\n332087.3\n90000\n12588\nSubaru Forester\n2013\n320.5\nХарківська область\nм. Харків\n57.1\nХарківський район\nХарківська область\n49.7\nм. Харків\nХарківська область\nПодружжя\nЄлізарова Тетяна Іванівна\nДитина\nЄлізарова Катерина Ігорівна\nЄлізаров Ігор Євгенович\nІгор Євгенович Єлізаров\nІгор Єлізаров\nЄлізаров Ігор Євгенович\nІгор\nЄлізаров Ігор Євгенович\nЄлізаров\nХарківська область\nЗагальний місцевий суд\nсуддя московського районного суду м. харкова\nЄвгенович\nХарків\nХарківська область\n90489.49\n4700\n10143.48\n242087.3\n12588\n332087.3\n24308.78\n90000\n2014\n10143.48\n90489.49\n4700\nЄлізарова Тетяна Іванівна\nПодружжя\nЄлізарова Катерина Ігорівна\nДитина\nЄвгенович\nЄлізаров\nЄлізаров Ігор Євгенович\nІгор Євгенович Єлізаров\nІгор Єлізаров\nЄлізаров Ігор Євгенович\nХарківська область\nХарків\nХарківська область\nсуддя московського районного суду м. харкова\nЗагальний місцевий суд\nЄлізаров Ігор Євгенович\nІгор\nSubaru Forester\n2013\n12588\n332087.3\n24308.78\n90000\n242087.3\nм. Харків\nХарківська область\n49.7\nм. Харків\nХарківська область\n320.5\nХарківський район\nХарківська область\n57.1\n2014","general":{"inn":"","name":"Ігор","patronymic_unclear":false,"family":[{"inn":"","inn_hidden":true,"relations_unclear":false,"relations_hidden":false,"relations_other":"","relations":"Подружжя","name_hidden":false,"family_name":"Єлізарова Тетяна Іванівна","name_unclear":false},{"inn":"","relations":"Дитина","relations_other":"","inn_hidden":false,"family_name":"Єлізарова Катерина Ігорівна","name_hidden":false,"name_unclear":false}],"patronymic":"Євгенович","inn_hidden":true,"family_raw":"","inn_unclear":false,"post":{"post_unclear":false,"region_unclear":false,"post":"суддя московського районного суду м. харкова","office":"Загальний місцевий суд","region":"Харківська область","post_hidden":false,"office_hidden":false,"region_hidden":false},"last_name_unclear":false,"full_name":"Єлізаров Ігор Євгенович","addresses":[{"place_address":"","place_district_hidden":true,"place_city_type":"Місто","place_city_hidden":false,"place_address_unclear":false,"place_city_type_hidden":false,"place_hidden":false,"place":"Харківська область","place_district":"","place_address_hidden":true,"place_city":"Харків","place_district_unclear":false}],"last_name":"Єлізаров","patronymic_hidden":false,"full_name_suggest":{"output":"Єлізаров Ігор Євгенович","input":["Єлізаров Ігор Євгенович","Ігор Євгенович Єлізаров","Ігор Єлізаров"]},"name_unclear":false},"source":"VULYK","estate":{"24":[{"region_unclear":false,"space_unclear":false,"costs":"","costs_comment":"","address_hidden":false,"region_hidden":true,"space_comment":"","space_hidden":false,"space":"320.5","address":"м. Харків","region":"Харківська область","address_unclear":false,"costs_rent_comment":"","space_comment_unclear":false,"space_units":"м²","costs_rent":""}],"26":[{"space_hidden":false,"costs":"","costs_comment":"","address_hidden":false,"region_hidden":true,"space_comment":"","space":"57.1","address":"Харківський район","region":"Харківська область","costs_rent_comment":"","space_units":"м²","costs_rent":""}],"31":[{"space_unclear":false,"address_hidden":false,"region_hidden":true,"space_comment":"","space_hidden":false,"space":"49.7","address":"м. Харків","region":"Харківська область","costs_property":"","costs_rent_comment":"","space_comment_unclear":false,"space_units":"м²","costs_property_comment":"","costs_rent":""}]},"intro":{"declaration_year":"2014","isnotdeclaration":"","declaration_year_hidden":false}}