{"income":{"5":{"value":"185147","family_comment":"","value_unclear":false,"comment_hidden":false,"family_hidden":false,"value_hidden":false,"family_unclear":false,"family_comment_hidden":false,"comment":"","family":"12593"},"6":{"value":"180961","family_comment":"","value_unclear":false,"family_hidden":false,"family_unclear":false,"family":"12593","comment":""},"7":{"source_name_unclear":false,"value":"4186","family_hidden":false,"family_comment":"","source_name":"Національний університет 'Одеська юридична академія'","family":"","comment":"","source_name_hidden":false},"8":{"family_comment":"","value":"","family":"","comment":""},"9":{"value":"","value_unclear":false,"family_hidden":false,"family_comment":"","family":"","comment":""},"10":{"value":"","value_unclear":false,"family_hidden":false,"value_hidden":false,"family_comment":"","comment_unclear":false,"comment":"","family":""},"11":{"family_comment":"","value":"","family":"","comment":""},"12":{"family_comment":"","value":"","family":"","comment":""},"13":{"family_comment":"","value":"","family":"","comment":""},"14":{"family_comment":"","value":"","family":"","comment":""},"15":{"family_comment":"","value":"","family_hidden":false,"comment":"","family":""},"16":{"value":"","value_unclear":false,"family_hidden":false,"family_comment":"","family":"","comment":""},"17":{"family_comment":"","value":"","family_hidden":false,"comment":"","family":""},"18":{"family_comment":"","value":"","value_unclear":false,"family":"","comment":""},"19":{"family_comment":"","value":"","family":"","comment":""},"20":{"value":"","family_comment":"","value_unclear":false,"family_hidden":false,"family_unclear":false,"comment_unclear":false,"comment":"","family":""}},"id":"vulyk_72_326","declaration":{"additional_info_text":"","notfull_lostpages":"","date":"2015-03-20T00:00:00","notfull":"","additional_info":"","url":"http://static.declarations.com.ua/declarations/chosen_ones/epic_batch/rymar_ihor_anatoliiovych.pdf"},"liabilities":{"54":{"sum_foreign_comment":"","sum":"","sum_comment":"","sum_comment_hidden":false,"sum_unclear":false,"sum_foreign":""},"55":{"sum_foreign_comment":"","sum":"","sum_comment":"","sum_foreign":""},"56":{"sum_foreign_comment":"","sum":"","sum_hidden":false,"sum_comment":"","sum_foreign":""},"57":{"sum_foreign_comment":"","sum":"","sum_comment":"","sum_comment_unclear":false,"sum_hidden":false,"sum_comment_hidden":false,"sum_unclear":false,"sum_foreign":""},"58":{"sum_foreign_comment":"","sum":"","sum_comment":"","sum_comment_unclear":false,"sum_hidden":false,"sum_comment_hidden":false,"sum_unclear":false,"sum_foreign":""},"59":{"sum_foreign_comment":"","sum_foreign_hidden":false,"sum_comment":"","sum_foreign_unclear":false,"sum_comment_hidden":false,"sum":"","sum_foreign":""},"60":{"sum_foreign_comment":"","sum_foreign_hidden":false,"sum_comment":"","sum_hidden":false,"sum":"","sum_foreign":""},"61":{"sum_foreign_comment":"","sum_foreign_hidden":false,"sum_comment":"","sum_hidden":false,"sum":"","sum_foreign":""},"62":{"sum_foreign_comment":"","sum_foreign_hidden":false,"sum_comment":"","sum_hidden":false,"sum":"","sum_foreign":""},"63":{"sum_foreign_comment":"","sum_foreign_hidden":false,"sum_comment":"","sum_comment_unclear":false,"sum_hidden":false,"sum_comment_hidden":false,"sum_unclear":false,"sum":"","sum_foreign":""},"64":{"sum_foreign_comment":"","sum_foreign_hidden":false,"sum_comment":"","sum_hidden":false,"sum":"","sum_foreign":""}},"ft_src":"суддя березівського районного суду одеської області\nОдеська область\nЗагальний місцевий суд\nІгор\nРимар (Курбатова) Дар'я Володимирівна, 12. 08. 1992\nПодружжя\nАнатолійович\nРимар\nРимар Ігор Анатолійович\nРимар Ігор Анатолійович\nІгор Анатолійович Римар\nІгор Римар\nРимар Ігор Анатолійович\n185147\n12593\n4186\nНаціональний університет 'Одеська юридична академія'\n180961\n12593\n.089\nволодіє 2/3 частинами\n65\n2014\n12593\n180961\nНаціональний університет 'Одеська юридична академія'\n4186\n12593\n185147\n4186\nНаціональний університет 'Одеська юридична академія'\n180961\n12593\n185147\n12593\nПодружжя\nРимар (Курбатова) Дар'я Володимирівна, 12. 08. 1992\nРимар Ігор Анатолійович\nІгор Анатолійович Римар\nІгор Римар\nРимар Ігор Анатолійович\nІгор\nРимар Ігор Анатолійович\nРимар\nОдеська область\nЗагальний місцевий суд\nсуддя березівського районного суду одеської області\nАнатолійович\n.089\nволодіє 2/3 частинами\n65\n2014\nРимар (Курбатова) Дар'я Володимирівна, 12. 08. 1992\nПодружжя\nАнатолійович\nРимар\nРимар Ігор Анатолійович\nІгор Анатолійович Римар\nІгор Римар\nРимар Ігор Анатолійович\nОдеська область\nЗагальний місцевий суд\nсуддя березівського районного суду одеської області\nРимар Ігор Анатолійович\nІгор\nволодіє 2/3 частинами\n65\n.089\n2014","general":{"inn":"","name":"Ігор","patronymic_unclear":false,"family":[{"inn":"","inn_hidden":true,"relations_unclear":false,"relations_hidden":false,"relations_other":"","relations":"Подружжя","name_hidden":false,"inn_unclear":false,"family_name":"Римар (Курбатова) Дар'я Володимирівна, 12. 08. 1992","name_unclear":false}],"patronymic":"Анатолійович","inn_hidden":true,"family_raw":"","inn_unclear":false,"post":{"post_unclear":false,"region_unclear":false,"post":"суддя березівського районного суду одеської області","candidate":"","office_hidden":false,"region":"Одеська область","post_hidden":false,"office":"Загальний місцевий суд","office_unclear":false,"region_hidden":false},"last_name_unclear":false,"full_name":"Римар Ігор Анатолійович","addresses":[{"place_city_type_hidden":true,"place_district_hidden":true,"place_city_type":"","place_city_hidden":true,"place_address_unclear":false,"place_address":"","place":"","place_district":"","place_unclear":false,"place_city":"","place_city_unclear":false,"place_hidden":true,"place_address_hidden":true,"place_district_unclear":false}],"last_name":"Римар","patronymic_hidden":false,"full_name_suggest":{"output":"Римар Ігор Анатолійович","input":["Римар Ігор Анатолійович","Ігор Анатолійович Римар","Ігор Римар"]},"name_unclear":false},"source":"VULYK","estate":{"23":[{"space_hidden":false,"costs":"","costs_rent_unclear":false,"costs_comment":"","costs_hidden":false,"address_hidden":true,"region_hidden":true,"space_comment":"","space_unclear":false,"space":".089","address":"","region":"","address_unclear":false,"costs_rent_comment":"","costs_rent_hidden":false,"space_units":"га","space_units_hidden":false,"costs_rent":""}],"31":[{"space_unclear":false,"address_hidden":true,"region_hidden":true,"space_comment":"володіє 2/3 частинами","space_units_hidden":false,"space_hidden":false,"space":"65","address":"","region":"","address_unclear":false,"costs_rent_comment":"","costs_property":"","space_units":"м²","costs_property_comment":"","costs_rent":""}]},"intro":{"declaration_year":"2014","isnotdeclaration":"","declaration_year_unclear":false}}