{"income":{"5":{"family_comment":"","value":"2195495","family":"","comment":""},"6":{"family_comment":"","value":"289538","family":"","comment":""},"7":{"value":"","comment_hidden":false,"value_hidden":false,"family_comment":"","source_name":"","family":"","comment":"","source_name_hidden":false},"8":{"family_comment":"","value":"","family":"","comment":""},"9":{"value":"65428","comment_hidden":false,"family_comment":"","family":"","comment":"","family_comment_unclear":false},"10":{"family_comment":"","value":"","family":"","comment":""},"11":{"family_comment":"","value":"1822529","comment_hidden":false,"family":"","comment":""},"12":{"family_comment":"","value":"","family":"","comment":""},"13":{"family_comment":"","value":"","family":"","comment":""},"14":{"family_comment":"","value":"","family":"","comment":""},"15":{"family_comment":"","value":"","family":"","comment":""},"16":{"family_comment":"","value":"18000","family":"","comment":""},"17":{"family_comment":"","value":"","family":"","comment":""},"18":{"family_comment":"","value":"","family":"","comment":""},"19":{"family_comment":"","value":"","family":"","comment":""},"20":{"family_comment":"","value":"","comment_hidden":false,"family":"","comment":""}},"vehicle":{"35":[{"brand_info":"2400","sum_rent_comment":"","brand":"Volvo S80","sum_comment":"","year":"2006","brand_info_unclear":false,"year_unclear":false,"sum":"","sum_rent":""}]},"id":"vulyk_102_113","banks":{"45":[{"sum_foreign_comment":"","sum_units":"UAH","sum_comment":"","sum_comment_unclear":false,"sum_hidden":false,"sum_foreign_units":"UAH","sum_comment_hidden":true,"sum_unclear":false,"sum":"483893","sum_foreign":""}]},"declaration":{"date":"2016-03-16T00:00:00","additional_info_text":"","additional_info":"","url":"http://static.declarations.com.ua/declarations/chosen_ones/judges_batch/1187_korobenko_hennadii_petrovych.pdf"},"liabilities":{"54":{"sum_foreign_comment":"","sum":"","sum_comment":"","sum_hidden":false,"sum_comment_hidden":false,"sum_foreign":""},"55":{"sum_foreign_comment":"","sum":"","sum_comment":"","sum_foreign":""},"56":{"sum_foreign_comment":"","sum":"","sum_comment":"","sum_foreign":""},"57":{"sum_foreign_comment":"","sum_comment_hidden":false,"sum":"","sum_comment":"","sum_foreign":""},"58":{"sum_foreign_comment":"","sum_comment_hidden":false,"sum":"","sum_comment":"","sum_foreign":""},"59":{"sum_foreign_comment":"","sum_comment_hidden":false,"sum":"","sum_comment":"","sum_foreign":""},"60":{"sum_foreign_comment":"","sum":"","sum_comment":"","sum_hidden":false,"sum_comment_hidden":false,"sum_foreign":""},"61":{"sum_foreign_comment":"","sum":"","sum_comment":"","sum_foreign":""},"62":{"sum_foreign_comment":"","sum":"","sum_comment":"","sum_unclear":false,"sum_foreign":""},"63":{"sum_foreign_comment":"","sum":"","sum_comment":"","sum_hidden":false,"sum_comment_hidden":false,"sum_foreign":""},"64":{"sum_foreign_comment":"","sum_comment_hidden":false,"sum":"","sum_comment":"","sum_foreign":""}},"ft_src":"Коробенко Геннадій Петрович\nПетрович\nКоробенко Геннадій Петрович\nГеннадій Петрович Коробенко\nГеннадій Коробенко\nКоробенко Геннадій Петрович\nГеннадій\nсуддя\nЗагальнодержавний регіон\nВищий господарський суд\nКоробенко\n2006\n2400\nVolvo S80\nмашиномісце\n13.9\n88.8\n483893\n2015\n2400\nVolvo S80\n2006\n2015\nКоробенко Геннадій Петрович\nГеннадій Петрович Коробенко\nГеннадій Коробенко\nКоробенко Геннадій Петрович\nГеннадій\nПетрович\nКоробенко Геннадій Петрович\nКоробенко\nсуддя\nЗагальнодержавний регіон\nВищий господарський суд\n289538\n2195495\n18000\n1822529\n65428\n13.9\nмашиномісце\n88.8\n483893\n289538\n1822529\n2195495\n18000\n65428\nПетрович\nКоробенко\nсуддя\nЗагальнодержавний регіон\nВищий господарський суд\nКоробенко Геннадій Петрович\nКоробенко Геннадій Петрович\nГеннадій Петрович Коробенко\nГеннадій Коробенко\nКоробенко Геннадій Петрович\nГеннадій\n2006\n2400\nVolvo S80\n1822529\n2195495\n18000\n65428\n289538\n88.8\nмашиномісце\n13.9\n483893\n2015","general":{"inn":"","inn_hidden":true,"last_name":"Коробенко","post":{"region":"Загальнодержавний регіон","region_unclear":false,"post":"суддя","office_unclear":false,"office":"Вищий господарський суд"},"name":"Геннадій","full_name":"Коробенко Геннадій Петрович","family_raw":"","addresses":[{"place_district":"","place_city_hidden":true,"place_city":"","place_city_type_hidden":false,"place_district_hidden":false,"place_city_type":"","place_address_hidden":true,"place_address":"","place_hidden":true,"place":""}],"patronymic_hidden":false,"full_name_suggest":{"output":"Коробенко Геннадій Петрович","input":["Коробенко Геннадій Петрович","Геннадій Петрович Коробенко","Геннадій Коробенко"]},"patronymic":"Петрович"},"source":"VULYK","estate":{"25":[{"costs":"","costs_comment":"","address_hidden":false,"region_hidden":true,"space_comment":"","space":"88.8","address":"","region":"","address_unclear":false,"costs_rent_comment":"","space_units":"м²","costs_rent":""}],"28":[{"space_unclear":false,"costs":"","costs_comment":"","address_hidden":false,"region_hidden":true,"space_comment":"машиномісце","space":"13.9","address":"","region":"","costs_rent_comment":"","space_units":"м²","costs_rent":""}]},"intro":{"declaration_year":"2015"}}