{"income":{"5":{"value":"245778","family_comment":"","value_unclear":false,"comment_hidden":false,"family_hidden":false,"value_hidden":false,"family_unclear":false,"family_comment_unclear":false,"family":"27602","comment":"","family_comment_hidden":false},"6":{"value":"233598","family_comment":"","value_unclear":false,"family_hidden":false,"value_hidden":false,"family_unclear":false,"family":"1602","comment":""},"7":{"source_name_unclear":false,"value":"","family_hidden":false,"value_hidden":false,"family_comment":"","source_name":"","family":"","comment":"","source_name_hidden":false},"8":{"value":"","family_comment":"","value_unclear":false,"family_hidden":false,"value_hidden":false,"family_unclear":false,"family":"","comment":""},"9":{"value":"","family_comment":"","value_unclear":false,"family_hidden":false,"value_hidden":false,"family_unclear":false,"comment_unclear":false,"comment":"","family":""},"10":{"value":"12180","value_unclear":false,"family_hidden":false,"value_hidden":false,"family_comment":"","family":"","comment":""},"11":{"value":"","family_hidden":false,"value_hidden":false,"family_comment":"","family":"","comment":""},"12":{"value":"","family_comment":"","family_hidden":false,"value_hidden":false,"family_unclear":false,"family":"","comment":""},"13":{"value":"","family_hidden":false,"value_hidden":false,"family_comment":"","family":"","comment":""},"14":{"value":"","family_hidden":false,"value_hidden":false,"family_comment":"","family":"","comment":""},"15":{"value":"","family_hidden":false,"value_hidden":false,"family_comment":"","family":"","comment":""},"16":{"value":"","value_unclear":false,"family_hidden":false,"value_hidden":false,"family_comment":"","family":"","comment":""},"17":{"value":"","family_hidden":false,"value_hidden":false,"family_comment":"","family":"","comment":""},"18":{"value":"","family_hidden":false,"value_hidden":false,"family_comment":"","family":"","comment":""},"19":{"value":"","comment_unclear":false,"family_hidden":false,"value_hidden":false,"family_comment":"","family":"","comment":""},"20":{"value":"","family_comment":"","comment_unclear":false,"comment_hidden":false,"family_hidden":false,"value_hidden":false,"family_unclear":false,"family_comment_unclear":false,"family_comment_hidden":false,"comment":"","family":"26000"}},"vehicle":{"35":[{"year_hidden":false,"brand_info":"2000 куб. см.","sum_rent_comment":"","sum_rent_comment_unclear":false,"sum_rent_hidden":false,"year":"2002","sum_hidden":false,"brand_info_hidden":false,"brand_info_unclear":false,"year_unclear":false,"sum_rent":"","sum_rent_unclear":false,"sum":"","brand":"Nissan X-Trail","sum_comment":"","brand_unclear":false,"brand_hidden":false,"sum_unclear":false}],"40":[{"year_hidden":false,"brand_info":"2000 куб. см.","sum_rent_comment":"","year":"2002","sum_hidden":false,"brand_info_hidden":false,"brand_info_unclear":false,"year_unclear":false,"sum_rent":"","sum":"","brand":"Nissan X-Trail","sum_comment":"","brand_unclear":false,"brand_hidden":false}]},"id":"vulyk_69_36","declaration":{"additional_info_text":"","notfull_lostpages":"","date":"2015-03-30T00:00:00","notfull":"","additional_info":"","url":"http://static.declarations.com.ua/declarations/chosen_ones/epic_batch/napolov_mykola_ivanovych.pdf"},"liabilities":{"54":{"sum_foreign_comment":"","sum":"","sum_comment":"","sum_hidden":false,"sum_comment_hidden":false,"sum_unclear":false,"sum_foreign":""},"55":{"sum_foreign_comment":"","sum":"","sum_hidden":false,"sum_comment":"","sum_foreign":""},"56":{"sum_foreign_comment":"","sum":"","sum_comment":"","sum_comment_unclear":false,"sum_hidden":false,"sum_unclear":false,"sum_foreign":""},"57":{"sum_foreign_comment":"","sum":"","sum_comment":"","sum_comment_unclear":false,"sum_hidden":false,"sum_comment_hidden":false,"sum_foreign":""},"58":{"sum_foreign_comment":"","sum":"","sum_comment":"","sum_comment_unclear":false,"sum_hidden":false,"sum_comment_hidden":false,"sum_unclear":false,"sum_foreign":""},"59":{"sum_foreign_comment":"","sum":"","sum_hidden":false,"sum_comment":"","sum_foreign":""},"60":{"sum_foreign_comment":"","sum":"","sum_comment":"","sum_hidden":false,"sum_comment_hidden":false,"sum_foreign":""},"61":{"sum_foreign_comment":"","sum":"","sum_hidden":false,"sum_comment":"","sum_foreign":""},"62":{"sum_foreign_comment":"","sum":"","sum_comment":"","sum_comment_unclear":false,"sum_hidden":false,"sum_unclear":false,"sum_foreign":""},"63":{"sum_foreign_comment":"","sum":"","sum_comment":"","sum_hidden":false,"sum_comment_hidden":false,"sum_unclear":false,"sum_foreign":""},"64":{"sum_foreign_comment":"","sum":"","sum_comment":"","sum_hidden":false,"sum_comment_hidden":false,"sum_foreign":""}},"ft_src":"суддя новгород-сіверського районного суду чернігівської області\nЧернігівська область\nЗагальний місцевий суд\nМикола\nНаполова Наталія Василівна\nПодружжя\nНаполов Сергій Миколайович\nДитина\nНаполов Святослав Миколайович\nДитина\nІванович\nНаполов Микола Іванович\nМикола Іванович Наполов\nМикола Наполов\nНаполов Микола Іванович\nНаполов Микола Іванович\nНаполов\n2000 куб. см.\nNissan X-Trail\n2002\nNissan X-Trail\n2000 куб. см.\n2002\nм. Новгород-Сіверський\n.0116\nЧернігівська область\nм. Новгород-Сіверський\n.1\nЧернігівська область\n85.3\nЧернігівська область\nм. Новгород-Сіверський\nЧернігівська область\nм. Новгород-Сіверський\n116.1\n2014\n1602\n233598\n12180\n27602\n245778\n26000\n2000 куб. см.\nNissan X-Trail\n2002\n2000 куб. см.\nNissan X-Trail\n2002\nм. Новгород-Сіверський\nЧернігівська область\n.1\n.0116\nм. Новгород-Сіверський\nЧернігівська область\n116.1\nЧернігівська область\nм. Новгород-Сіверський\n85.3\nм. Новгород-Сіверський\nЧернігівська область\nНаполов Микола Іванович\nМикола Іванович Наполов\nМикола Наполов\nНаполов Микола Іванович\nНаполов Микола Іванович\nПодружжя\nНаполова Наталія Василівна\nДитина\nНаполов Сергій Миколайович\nДитина\nНаполов Святослав Миколайович\nМикола\nНаполов\nЗагальний місцевий суд\nсуддя новгород-сіверського районного суду чернігівської області\nЧернігівська область\nІванович\n1602\n233598\n26000\n245778\n27602\n12180\n2014\nНаполова Наталія Василівна\nПодружжя\nНаполов Сергій Миколайович\nДитина\nНаполов Святослав Миколайович\nДитина\nІванович\nНаполов\nМикола\nНаполов Микола Іванович\nМикола Іванович Наполов\nМикола Наполов\nНаполов Микола Іванович\nЧернігівська область\nсуддя новгород-сіверського районного суду чернігівської області\nЗагальний місцевий суд\nНаполов Микола Іванович\nNissan X-Trail\n2000 куб. см.\n2002\nNissan X-Trail\n2000 куб. см.\n2002\n12180\n26000\n245778\n27602\n233598\n1602\n.1\nЧернігівська область\nм. Новгород-Сіверський\n116.1\nЧернігівська область\nм. Новгород-Сіверський\nЧернігівська область\nм. Новгород-Сіверський\n85.3\nЧернігівська область\nм. Новгород-Сіверський\n.0116\n2014","general":{"inn":"","name":"Микола","patronymic_unclear":false,"family":[{"inn":"","inn_hidden":true,"relations_unclear":false,"relations_hidden":false,"relations_other":"","relations":"Подружжя","name_hidden":false,"inn_unclear":false,"family_name":"Наполова Наталія Василівна","name_unclear":false},{"inn":"","inn_hidden":false,"relations_unclear":false,"relations_hidden":false,"relations_other":"","relations":"Дитина","name_hidden":false,"inn_unclear":false,"family_name":"Наполов Сергій Миколайович","name_unclear":false},{"inn":"","inn_hidden":true,"relations_unclear":false,"relations_hidden":false,"relations_other":"","relations":"Дитина","name_hidden":false,"family_name":"Наполов Святослав Миколайович","name_unclear":false}],"patronymic":"Іванович","inn_hidden":true,"family_raw":"","inn_unclear":false,"post":{"post_unclear":false,"region_unclear":false,"post":"суддя новгород-сіверського районного суду чернігівської області","candidate":"","office_hidden":false,"region":"Чернігівська область","post_hidden":false,"office":"Загальний місцевий суд","office_unclear":false,"region_hidden":false},"full_name_suggest":{"output":"Наполов Микола Іванович","input":["Наполов Микола Іванович","Микола Іванович Наполов","Микола Наполов"]},"full_name":"Наполов Микола Іванович","addresses":[{"place_city_type_unclear":false,"place_address":"","place_district_hidden":true,"place_city_type":"","place_address_hidden":true,"place_address_unclear":false,"place_city_type_hidden":false,"place":"","place_district":"","place_unclear":false,"place_city":"","place_city_unclear":false,"place_hidden":true,"place_city_hidden":true,"place_district_unclear":false}],"last_name":"Наполов","last_name_unclear":false,"name_unclear":false},"source":"VULYK","estate":{"23":[{"space_unclear":false,"costs":"","costs_rent_unclear":false,"costs_comment":"","costs_hidden":false,"space_hidden":false,"space_units_unclear":false,"space_units_hidden":false,"costs_comment_unclear":false,"region":"Чернігівська область","costs_unclear":false,"space_comment_hidden":false,"costs_rent":"","region_unclear":false,"address_hidden":false,"region_hidden":false,"space_comment":"","space":".1","address":"м. Новгород-Сіверський","address_unclear":false,"costs_rent_comment":"","costs_rent_hidden":false,"space_units":"га"}],"24":[{"region_unclear":false,"space_hidden":false,"costs":"","costs_comment":"","costs_hidden":false,"address_hidden":false,"region_hidden":false,"space_comment":"","space_unclear":false,"space":"116.1","address":"м. Новгород-Сіверський","region":"Чернігівська область","address_unclear":false,"costs_rent_comment":"","costs_rent_hidden":false,"space_units":"м²","space_units_hidden":false,"costs_rent":""}],"29":[{"region_unclear":false,"space_unclear":false,"costs_property_hidden":false,"costs_property":"","address_hidden":true,"region_hidden":false,"space_comment":"","space_units_hidden":false,"space_hidden":false,"space":".0116","address":"м. Новгород-Сіверський","region":"Чернігівська область","address_unclear":false,"space_units_unclear":false,"space_comment_hidden":false,"space_units":"га","costs_property_comment":"","costs_rent":"","costs_rent_comment":""}],"34":[{"space_hidden":false,"costs_property":"","address_hidden":true,"region_hidden":false,"space_comment":"","space_units_hidden":false,"space_unclear":false,"space_units_unclear":false,"address":"м. Новгород-Сіверський","region":"Чернігівська область","address_unclear":false,"space":"85.3","space_comment_hidden":false,"space_units":"м²","costs_property_comment":"","costs_rent":"","costs_rent_comment":""}]},"intro":{"declaration_year":"2014","isnotdeclaration":"","declaration_year_unclear":false,"declaration_year_hidden":false}}