{"income":{"5":{"value":"333391","family_comment":"","value_unclear":false,"family_hidden":false,"value_hidden":false,"family_unclear":false,"comment_unclear":false,"comment":"","family":"14374"},"6":{"value":"271410","family_unclear":false,"family_hidden":false,"family_comment":"","family":"14374","comment":""},"7":{"value":"","family_hidden":false,"value_hidden":false,"family_comment":"","source_name":"","family":"","comment":""},"8":{"family_comment":"","value":"","family":"","comment":""},"9":{"family_comment":"","value":"4","value_unclear":false,"family":"","comment":""},"10":{"family_comment":"","family_unclear":false,"value":"","family":"","comment":""},"11":{"family_comment":"","value":"","family":"","comment":""},"12":{"family_comment":"","value":"","family":"","comment":""},"13":{"family_comment":"","value":"","family":"","comment":""},"14":{"family_comment":"","value":"","family":"","comment":""},"15":{"family_comment":"","value":"","family":"","comment":""},"16":{"family_comment":"","value":"","family":"","comment":""},"17":{"family_comment":"","value":"","family":"","comment":""},"18":{"family_comment":"","value":"","family":"","comment":""},"19":{"family_comment":"","value":"","family":"","comment":""},"20":{"value":"61977","value_unclear":false,"family_comment":"","comment_unclear":false,"comment":"","family":""}},"vehicle":{"40":[{"brand_info":"1994 куб. см., 155 к. с., довжина 462","sum":"","brand":"Subaru Legacy","sum_comment":"","brand_unclear":false,"year":"2006","brand_info_hidden":false,"brand_info_unclear":true,"sum_rent_comment":"","sum_rent":""}]},"id":"vulyk_71_139","banks":{"45":[{"sum_foreign_comment":"","sum_units":"UAH","sum_comment":"","sum_comment_unclear":false,"sum_foreign_units":"UAH","sum_comment_hidden":false,"sum":"250","sum_foreign":""}],"46":[{"sum_foreign_comment":"","sum_units":"UAH","sum_comment":"","sum_comment_unclear":false,"sum_hidden":false,"sum_foreign_units":"UAH","sum_comment_hidden":false,"sum_unclear":false,"sum":"250","sum_foreign":""}]},"declaration":{"additional_info_text":"","notfull_lostpages":"","date":"2014-03-25T00:00:00","notfull":"","additional_info":"","url":"http://static.declarations.com.ua/declarations/chosen_ones/judges_batch/463_hryshchenko_natalia_mykolaivna.pdf"},"liabilities":{"54":{"sum_foreign_comment":"","sum":"2400","sum_comment":"","sum_comment_unclear":false,"sum_comment_hidden":false,"sum_unclear":false,"sum_foreign":""},"55":{"sum_foreign_comment":"","sum":"","sum_comment":"","sum_foreign":""},"56":{"sum_foreign_comment":"","sum":"7469","sum_comment":"","sum_comment_unclear":false,"sum_unclear":false,"sum_foreign":""},"57":{"sum_foreign_comment":"","sum":"","sum_comment":"","sum_comment_hidden":false,"sum_unclear":false,"sum_foreign":""},"58":{"sum_foreign_comment":"","sum":"","sum_comment":"","sum_comment_hidden":false,"sum_unclear":false,"sum_foreign":""},"59":{"sum_foreign_comment":"","sum_comment_hidden":false,"sum":"","sum_comment":"","sum_foreign":""},"60":{"sum_foreign_comment":"","sum_comment_hidden":false,"sum":"","sum_comment":"","sum_foreign":""},"61":{"sum_foreign_comment":"","sum":"","sum_comment":"","sum_foreign":""},"62":{"sum_foreign_comment":"","sum":"400","sum_comment":"","sum_foreign":""},"63":{"sum_foreign_comment":"","sum":"","sum_comment":"","sum_unclear":false,"sum_foreign":""},"64":{"sum_foreign_comment":"","sum":"","sum_comment":"","sum_unclear":false,"sum_foreign":""}},"ft_src":"400\n2400\n7469\nсуддя апеляційного суду дніпропетровської області\nДніпропетровська область\nЗагальний апеляційний суд\nНаталя\nГрищенко Юрій Петрович\nПодружжя\nМиколаївна\nГрищенко Наталя Миколаївна\nНаталя Миколаївна Грищенко\nНаталя Грищенко\nГрищенко Наталя Миколаївна\nГрищенко Наталя Миколаївна\nГрищенко\n1994 куб. см., 155 к. с., довжина 462\nSubaru Legacy\n2006\n1/5 частка\n17.58\n19.6\n88.3\n600\n1/5 частка\n17.58\n250\n250\n2013\n1994 куб. см., 155 к. с., довжина 462\n2006\nSubaru Legacy\n600\n19.6\n88.3\n17.58\n1/5 частка\n17.58\n1/5 частка\nПодружжя\nГрищенко Юрій Петрович\nГрищенко Наталя Миколаївна\nНаталя Миколаївна Грищенко\nНаталя Грищенко\nГрищенко Наталя Миколаївна\nГрищенко Наталя Миколаївна\nНаталя\nМиколаївна\nЗагальний апеляційний суд\nДніпропетровська область\nсуддя апеляційного суду дніпропетровської області\nГрищенко\n2400\n7469\n400\n271410\n14374\n61977\n333391\n14374\n4\n250\n250\n2013\n7469\n400\n2400\n14374\n271410\n4\n14374\n333391\n61977\nГрищенко Юрій Петрович\nПодружжя\nМиколаївна\nГрищенко\nНаталя\nГрищенко Наталя Миколаївна\nНаталя Миколаївна Грищенко\nНаталя Грищенко\nГрищенко Наталя Миколаївна\nДніпропетровська область\nЗагальний апеляційний суд\nсуддя апеляційного суду дніпропетровської області\nГрищенко Наталя Миколаївна\nSubaru Legacy\n1994 куб. см., 155 к. с., довжина 462\n2006\n4\n61977\n333391\n14374\n271410\n14374\n1/5 частка\n17.58\n600\n19.6\n88.3\n17.58\n1/5 частка\n250\n250\n2013","general":{"inn":"","name":"Наталя","family":[{"inn":"","inn_hidden":true,"relations_hidden":false,"family_name":"Грищенко Юрій Петрович","relations_other":"","relations":"Подружжя","name_hidden":false,"name_unclear":false}],"patronymic":"Миколаївна","inn_hidden":true,"family_raw":"","inn_unclear":false,"post":{"post_unclear":false,"region_unclear":false,"post":"суддя апеляційного суду дніпропетровської області","office":"Загальний апеляційний суд","region":"Дніпропетровська область","post_hidden":false,"office_unclear":false},"full_name_suggest":{"output":"Грищенко Наталя Миколаївна","input":["Грищенко Наталя Миколаївна","Наталя Миколаївна Грищенко","Наталя Грищенко"]},"full_name":"Грищенко Наталя Миколаївна","addresses":[{"place_district":"","place_unclear":false,"place_city":"","place_city_type_hidden":false,"place_district_hidden":true,"place_city_type":"","place_city_hidden":true,"place_address_hidden":true,"place_address":"","place_hidden":false,"place":""}],"last_name":"Грищенко","patronymic_hidden":false,"last_name_unclear":false,"name_unclear":false},"source":"VULYK","estate":{"23":[{"space_hidden":false,"costs":"","costs_comment":"","costs_hidden":false,"address_hidden":true,"region_hidden":false,"space_comment":"","space_unclear":false,"space":"600","address":"","costs_comment_unclear":false,"region":"","costs_rent_comment":"","costs_rent_hidden":false,"space_comment_unclear":false,"space_units":"м²","costs_rent":""}],"25":[{"region_unclear":false,"space_unclear":false,"costs":"","costs_rent_unclear":false,"costs_comment":"","costs_hidden":false,"address_hidden":true,"region_hidden":false,"space_comment":"1/5 частка","space_hidden":false,"space":"17.58","address":"","costs_unclear":false,"region":"","address_unclear":false,"costs_rent_comment":"","costs_rent_hidden":false,"space_comment_unclear":false,"space_units":"м²","costs_rent":""}],"26":[{"space_unclear":false,"costs":"","costs_comment":"","address_hidden":true,"region_hidden":false,"space_comment":"","space":"88.3","address":"","region":"","address_unclear":false,"costs_rent_comment":"","space_comment_unclear":false,"space_units":"м²","costs_rent":""}],"31":[{"space_hidden":false,"costs_property_comment":"","address_hidden":true,"region_hidden":false,"space_comment":"1/5 частка","space":"17.58","address":"","region":"","costs_property":"","costs_rent_comment":"","space_comment_unclear":false,"space_units":"м²","space_units_hidden":false,"costs_rent":""}],"33":[{"space_hidden":false,"address_hidden":true,"region_hidden":false,"space_comment":"","space":"19.6","address":"","region":"","costs_property":"","costs_rent_comment":"","space_comment_hidden":false,"space_units":"м²","costs_property_comment":"","costs_rent":""}]},"intro":{"declaration_year":"2013","isnotdeclaration":""}}