{"income":{"5":{"value":"263057","family_comment":"","value_unclear":false,"family_unclear":false,"family":"75148","comment":""},"6":{"family_comment":"","value":"250877","family":"73342","comment":""},"7":{"source_name_unclear":false,"value":"","family_hidden":false,"value_hidden":false,"family_comment":"","source_name":"","family":"","comment":"","source_name_hidden":false},"8":{"value":"","family_hidden":false,"value_hidden":false,"family_comment":"","family":"","comment":""},"9":{"value":"","comment_hidden":false,"family_hidden":false,"value_hidden":false,"family_comment":"","family":"","comment":""},"10":{"family_comment":"","value":"12180","family":"1806","comment":""},"11":{"value":"","family_hidden":false,"value_hidden":false,"family_comment":"","family":"","comment":""},"12":{"family_comment":"","value":"","family":"","comment":"","value_hidden":false},"13":{"family_comment":"","value":"","family":"","comment":"","value_hidden":false},"14":{"family_comment":"","value":"","family":"","comment":"","value_hidden":false},"15":{"family_comment":"","value":"","family":"","comment":"","value_hidden":false},"16":{"family_comment":"","value":"","family":"","comment":"","value_hidden":false},"17":{"family_comment":"","value":"","family":"","comment":"","value_hidden":false},"18":{"family_comment":"","value":"","family":"","comment":"","value_hidden":false},"19":{"family_comment":"","value":"","family":"","comment":"","value_hidden":false},"20":{"value":"","family_comment":"","value_unclear":false,"family":"","family_unclear":false,"comment_unclear":false,"comment":"","family_comment_unclear":false}},"vehicle":{"35":[{"brand_info":"2497 куб. см.","sum_rent_comment":"","brand":"Mercedes-Benz 250 D","sum_comment":"","sum_comment_unclear":false,"year":"1995","brand_hidden":false,"brand_info_unclear":false,"sum":"","sum_rent":"","sum_rent_unclear":false}]},"id":"vulyk_33_165","banks":{"45":[{"sum_foreign_comment":"","sum_units":"UAH","sum_comment":"","sum_hidden":false,"sum_foreign_units":"UAH","sum_comment_hidden":false,"sum":"","sum_foreign":""},{"sum_foreign_comment":"","sum_units":"","sum_comment":"","sum_foreign_units":"","sum":"","sum_foreign":""},{"sum_foreign_comment":"","sum_units":"","sum_comment":"","sum_foreign_units":"","sum":"","sum_foreign":""}],"46":[{"sum_foreign_comment":"","sum_units":"UAH","sum_comment":"","sum_foreign_units":"UAH","sum_comment_hidden":false,"sum":"","sum_foreign":""}],"47":[{"sum_foreign_comment":"","sum_units":"UAH","sum_comment":"","sum_comment_unclear":false,"sum_foreign_units":"UAH","sum":"","sum_foreign":""}],"48":[{"sum_foreign_comment":"","sum_units":"UAH","sum_comment":"","sum_foreign_units":"UAH","sum":"","sum_foreign":""}],"49":[{"sum_foreign_comment":"","sum_units":"UAH","sum_comment":"","sum_foreign_units":"UAH","sum":"","sum_foreign":""}],"50":[{"sum_foreign_comment":"","sum_units":"UAH","sum_comment":"","sum_foreign_units":"UAH","sum":"","sum_foreign":""}],"51":[{"sum_foreign_comment":"","sum_units":"UAH","sum_comment":"","sum_hidden":false,"sum_foreign_units":"UAH","sum_comment_hidden":false,"sum":"","sum_foreign":""},{"sum_foreign_comment":"","sum_units":"","sum_comment":"","sum_foreign_units":"","sum":"","sum_foreign":""},{"sum_foreign_comment":"","sum":"","sum_comment":"","sum_foreign":""}],"52":[{"sum_foreign_comment":"","sum_units":"UAH","sum_comment":"","sum_foreign_units":"UAH","sum_comment_hidden":false,"sum":"","sum_foreign":""}],"53":[{"sum_foreign_comment":"","sum_units":"UAH","sum_comment":"","sum_comment_unclear":false,"sum_foreign_units":"UAH","sum":"","sum_foreign":""}]},"declaration":{"additional_info_text":"","notfull_lostpages":"","date":"2015-02-02T00:00:00","notfull":"","additional_info":"","url":"http://static.declarations.com.ua/declarations/chosen_ones/mega_batch/kruhliuk_volodymyr_hryhorovych.pdf"},"liabilities":{"54":{"sum_foreign_comment":"","sum":"","sum_hidden":false,"sum_comment":"","sum_foreign":""},"55":{"sum_foreign_comment":"","sum":"","sum_comment":"","sum_foreign":""},"56":{"sum_foreign_comment":"","sum":"39970","sum_comment":"","sum_foreign":""},"57":{"sum_foreign_comment":"","sum_foreign_hidden":false,"sum_comment":"","sum_hidden":false,"sum_comment_hidden":false,"sum":"","sum_foreign":""},"58":{"sum_foreign_comment":"","sum_foreign_hidden":false,"sum_comment":"","sum_hidden":false,"sum_comment_hidden":false,"sum":"","sum_foreign":""},"59":{"sum_foreign_comment":"","sum":"17351","sum_comment":"","sum_unclear":false,"sum_foreign":""},"60":{"sum_foreign_comment":"","sum":"","sum_comment":"","sum_foreign":""},"61":{"sum_foreign_comment":"","sum":"","sum_comment":"","sum_foreign":""},"62":{"sum_foreign_comment":"","sum":"15330","sum_comment":"","sum_unclear":false,"sum_foreign":""},"63":{"sum_foreign_comment":"","sum":"","sum_comment":"","sum_foreign":""},"64":{"sum_foreign_comment":"","sum":"","sum_comment":"","sum_foreign":""}},"ft_src":"17351\n15330\n39970\nВижниця\n59200\nЧернівецька область\nВижницький\nголова вижницького районного суду чернівецької області\nЧернівецька область\nЗагальний місцевий суд\nВолодимир\nКруглюк О. І\nПодружжя\nГригорович\nКруглюк\nКруглюк Володимир Григорович\nКруглюк Володимир Григорович\nВолодимир Григорович Круглюк\nВолодимир Круглюк\nКруглюк Володимир Григорович\nMercedes-Benz 250 D\n2497 куб. см.\n1995\n2014\n2497 куб. см.\n1995\nMercedes-Benz 250 D\n780\nЧернівецька область\nм. Вижниця\n600\nЧернівецька область\nм. Вижниця\n2500\nс. Черешенька\nЧернівецька область\nм. Вижниця\n13.6\n1/5 квартири\nЧернівецька область\nм. Вижниця\n25\nЧернівецька область\nм. Вижниця\n13.6\nЧернівецька область\nм. Вижниця\nКруглюк Володимир Григорович\nВолодимир Григорович Круглюк\nВолодимир Круглюк\nКруглюк Володимир Григорович\nКруглюк Володимир Григорович\nПодружжя\nКруглюк О. І\nВолодимир\nГригорович\nЗагальний місцевий суд\nголова вижницького районного суду чернівецької області\nЧернівецька область\nКруглюк\n59200\nЧернівецька область\nВижниця\nВижницький\n17351\n39970\n15330\n250877\n73342\n263057\n75148\n12180\n1806\n2014\n39970\n15330\n17351\nм. Вижниця\nЧернівецька область\n780\nм. Вижниця\n600\nЧернівецька область\nс. Черешенька\n2500\nм. Вижниця\n25\nЧернівецька область\n1/5 квартири\nм. Вижниця\nЧернівецька область\n13.6\nЧернівецька область\nм. Вижниця\nм. Вижниця\nЧернівецька область\n13.6\nКруглюк О. І\nПодружжя\nВолодимир\nГригорович\nКруглюк\nКруглюк Володимир Григорович\nВолодимир Григорович Круглюк\nВолодимир Круглюк\nКруглюк Володимир Григорович\nЧернівецька область\nВижниця\n59200\nВижницький\nЧернівецька область\nголова вижницького районного суду чернівецької області\nЗагальний місцевий суд\nКруглюк Володимир Григорович\n73342\n250877\n1806\n12180\n75148\n263057\n1995\n2497 куб. см.\nMercedes-Benz 250 D\n1806\n12180\n263057\n75148\n73342\n250877\n1/5 квартири\nм. Вижниця\nЧернівецька область\n13.6\nм. Вижниця\nЧернівецька область\n780\nм. Вижниця\nЧернівецька область\n600\nс. Черешенька\n2500\nм. Вижниця\nЧернівецька область\nм. Вижниця\nЧернівецька область\n13.6\nм. Вижниця\nЧернівецька область\n25\n2014","general":{"inn":"","name":"Володимир","family":[{"inn":"","inn_hidden":true,"relations_hidden":false,"family_name":"Круглюк О. І","relations_other":"","relations":"Подружжя","name_hidden":false,"name_unclear":false}],"patronymic":"Григорович","inn_hidden":true,"family_raw":"","last_name":"Круглюк","post":{"post_unclear":false,"post":"голова вижницького районного суду чернівецької області","candidate":"","office_hidden":false,"region":"Чернівецька область","post_hidden":false,"office":"Загальний місцевий суд","region_hidden":false},"last_name_unclear":false,"full_name":"Круглюк Володимир Григорович","addresses":[{"place_district":"Вижницький","place_city_hidden":false,"place_city":"Вижниця","place_city_type_hidden":false,"place_district_hidden":false,"place_city_type":"Місто","place_address_hidden":true,"place_address":"59200","place_hidden":false,"place":"Чернівецька область"}],"full_name_suggest":{"output":"Круглюк Володимир Григорович","input":["Круглюк Володимир Григорович","Володимир Григорович Круглюк","Володимир Круглюк"]}},"source":"VULYK","estate":{"23":[{"space_unclear":false,"costs":"","costs_comment":"","address_hidden":false,"region_hidden":false,"space_comment":"","space_hidden":false,"space":"780","address":"м. Вижниця","region":"Чернівецька область","space_units_unclear":false,"space_units":"м²","costs_rent":"","costs_rent_comment":""},{"costs":"","costs_rent_unclear":false,"costs_comment":"","address_hidden":false,"region_hidden":false,"space_comment":"","space":"600","address":"м. Вижниця","region":"Чернівецька область","address_unclear":false,"space_units_unclear":false,"space_units":"м²","costs_rent":"","costs_rent_comment":""},{"region_unclear":true,"costs":"","costs_comment":"","address_hidden":false,"region_hidden":false,"space_comment":"","space":"2500","address":"с. Черешенька","region":"","address_unclear":true,"costs_rent_comment":"","space_units":"м²","costs_rent":""},{"costs_rent":"","region":"","costs":"","costs_rent_comment":"","costs_comment":"","address_hidden":false,"region_hidden":false,"space_comment":"","space_units":"","space":"","address":""},{"costs_rent":"","region":"","costs":"","costs_rent_comment":"","costs_comment":"","space_comment":"","space_units":"","space":"","address":""}],"24":[{"space_hidden":true,"costs":"","costs_comment":"","address_hidden":false,"region_hidden":false,"space_comment":"","space_unclear":false,"space":"","address":"м. Вижниця","region":"Чернівецька область","costs_rent_comment":"","space_units":"м²","costs_rent":""}],"25":[{"space_unclear":false,"costs":"","costs_comment":"","costs_hidden":false,"address_hidden":false,"region_hidden":false,"space_comment":"","space_hidden":false,"space":"13.6","address":"м. Вижниця","region":"Чернівецька область","costs_rent_comment":"","space_units":"м²","costs_rent":""}],"27":[{"space_unclear":false,"costs":"","costs_comment":"","costs_hidden":false,"address_hidden":false,"region_hidden":false,"space_comment":"","space":"25","address":"м. Вижниця","region":"Чернівецька область","costs_rent_comment":"","space_units":"м²","costs_rent":""}],"31":[{"space_unclear":false,"address_hidden":false,"region_hidden":false,"space_comment":"1/5 квартири","space":"13.6","address":"м. Вижниця","region":"Чернівецька область","costs_property":"","costs_rent_comment":"","space_comment_unclear":false,"space_units":"м²","costs_property_comment":"","costs_rent":""}]},"intro":{"declaration_year":"2014"}}