{"income":{"5":{"value":"217648","family_comment":"","value_unclear":false,"family_unclear":false,"family":"","comment":""},"6":{"value":"217648","family_comment":"","value_unclear":false,"family_unclear":false,"family":"","comment":""},"7":{"family_comment":"","value":"","source_name":"","family":"","comment":""},"8":{"family_comment":"","value":"","family":"","comment":""},"9":{"family_comment":"","value":"","value_unclear":false,"family":"","comment":""},"10":{"family_comment":"","value":"","value_unclear":false,"family":"","comment":""},"11":{"family_comment":"","value":"","family":"","comment":""},"12":{"family_comment":"","value":"","family":"","comment":""},"13":{"family_comment":"","value":"","value_unclear":false,"family":"","comment":""},"14":{"family_comment":"","value":"","family":"","comment":""},"15":{"family_comment":"","value":"","family":"","comment":""},"16":{"family_comment":"","value":"","family":"","comment":""},"17":{"family_comment":"","value":"","family":"","comment":""},"18":{"family_comment":"","value":"","family":"","comment":""},"19":{"family_comment":"","value":"","family":"","comment":""},"20":{"family_comment":"","family_unclear":false,"value":"","family":"","comment":""}},"id":"vulyk_85_75","declaration":{"additional_info_text":"","notfull_lostpages":"","date":"2015-03-30T00:00:00","notfull":"","additional_info":"","url":"http://static.declarations.com.ua/declarations/chosen_ones/judges_batch/2678_radchenko_larysa_anatoliivna.pdf"},"liabilities":{"54":{"sum_foreign_comment":"","sum":"","sum_comment":"","sum_comment_unclear":false,"sum_foreign":""},"55":{"sum_foreign_comment":"","sum":"","sum_comment":"","sum_foreign":""},"56":{"sum_foreign_comment":"","sum":"","sum_comment":"","sum_unclear":false,"sum_foreign":""},"57":{"sum_foreign_comment":"","sum":"","sum_comment":"","sum_foreign":""},"58":{"sum_foreign_comment":"","sum_comment_hidden":false,"sum":"","sum_comment":"","sum_foreign":""},"59":{"sum_foreign_comment":"","sum":"","sum_comment":"","sum_foreign":""},"60":{"sum_foreign_comment":"","sum":"","sum_comment":"","sum_foreign":""},"61":{"sum_foreign_comment":"","sum":"","sum_comment":"","sum_foreign":""},"62":{"sum_foreign_comment":"","sum":"","sum_comment":"","sum_unclear":false,"sum_foreign":""},"63":{"sum_foreign_comment":"","sum":"","sum_comment":"","sum_unclear":false,"sum_foreign":""},"64":{"sum_foreign_comment":"","sum":"","sum_comment":"","sum_foreign":""}},"ft_src":"суддя артемівського міськрайонного суду донецької області\nДонецька область\nЗагальний місцевий суд\nЛариса\nАнатоліївна\nРадченко\nРадченко Лариса Анатоліївна\nРадченко Лариса Анатоліївна\nЛариса Анатоліївна Радченко\nЛариса Радченко\nРадченко Лариса Анатоліївна\nАртемівськ\n84500\nДонецька область\n217648\n217648\nДонецька обл. м. Артемівськ\nДонецька область\n45.4\n2014\n217648\n217648\n217648\n217648\nЗагальний місцевий суд\nсуддя артемівського міськрайонного суду донецької області\nДонецька область\nРадченко Лариса Анатоліївна\nЛариса Анатоліївна Радченко\nЛариса Радченко\nРадченко Лариса Анатоліївна\nЛариса\nРадченко Лариса Анатоліївна\nРадченко\nАнатоліївна\n84500\nДонецька область\nАртемівськ\n45.4\nДонецька область\nДонецька обл. м. Артемівськ\n2014\nАнатоліївна\nРадченко\nЛариса\nРадченко Лариса Анатоліївна\nЛариса Анатоліївна Радченко\nЛариса Радченко\nРадченко Лариса Анатоліївна\n84500\nАртемівськ\nДонецька область\nсуддя артемівського міськрайонного суду донецької області\nДонецька область\nЗагальний місцевий суд\nРадченко Лариса Анатоліївна\nДонецька обл. м. Артемівськ\nДонецька область\n45.4\n2014","general":{"inn":"","name":"Лариса","last_name_hidden":false,"patronymic":"Анатоліївна","inn_hidden":true,"family_raw":"","last_name":"Радченко","post":{"post_unclear":false,"post_hidden":false,"post":"суддя артемівського міськрайонного суду донецької області","region":"Донецька область","office":"Загальний місцевий суд"},"full_name_suggest":{"output":"Радченко Лариса Анатоліївна","input":["Радченко Лариса Анатоліївна","Лариса Анатоліївна Радченко","Лариса Радченко"]},"full_name":"Радченко Лариса Анатоліївна","addresses":[{"place_district":"","place_city_hidden":false,"place_city":"Артемівськ","place_city_type_hidden":false,"place_district_hidden":false,"place_city_type":"Місто","place_address_hidden":true,"place_address":"84500","place_hidden":false,"place":"Донецька область"}],"last_name_unclear":false},"source":"VULYK","estate":{"25":[{"space_hidden":false,"costs":"","costs_comment":"","address_hidden":true,"region_hidden":false,"space_comment":"","space_unclear":false,"space":"45.4","address":"Донецька обл. м. Артемівськ","costs_comment_unclear":false,"region":"Донецька область","costs_rent_comment":"","space_comment_unclear":false,"space_units":"м²","costs_rent":""}]},"intro":{"declaration_year":"2014","isnotdeclaration":""}}