{"income":{"5":{"value":"278749","family_comment":"","value_unclear":false,"family_unclear":false,"family":"","comment":""},"6":{"family_comment":"","value":"259851","value_unclear":false,"family":"","comment":""},"7":{"value":"","value_unclear":false,"family_comment":"","source_name":"","family":"","comment":""},"8":{"family_comment":"","value":"","family":"","comment":""},"9":{"value":"","family_comment":"","value_unclear":false,"family_unclear":false,"family":"","comment":""},"10":{"family_comment":"","value":"","comment_unclear":false,"family":"","comment":""},"11":{"family_comment":"","value":"","family":"","comment":""},"12":{"family_comment":"","value":"","family":"","comment":""},"13":{"family_comment":"","value":"","value_unclear":false,"family":"","comment":""},"14":{"family_comment":"","value":"","family":"","comment":""},"15":{"family_comment":"","value":"","family":"","comment":""},"16":{"family_comment":"","family_unclear":false,"value":"","family":"","comment":""},"17":{"family_comment":"","family_unclear":false,"value":"","family":"","comment":""},"18":{"family_comment":"","value":"","family":"","comment":""},"19":{"family_comment":"","value":"","family":"","comment":""},"20":{"value":"18898","family_comment":"","value_unclear":false,"family_hidden":false,"value_hidden":false,"family_unclear":false,"comment_unclear":false,"comment":"пенсія","family":""}},"id":"vulyk_100_185","banks":{"45":[{"sum_foreign_comment":"","sum_units":"UAH","sum_comment":"Приватбанк","sum_comment_unclear":false,"sum_foreign_units":"UAH","sum_units_unclear":false,"sum_comment_hidden":false,"sum_unclear":false,"sum":"15000","sum_foreign":""}]},"declaration":{"additional_info_text":"","notfull_lostpages":"","date":"2015-03-26T00:00:00","notfull":"","additional_info":"","url":"http://static.declarations.com.ua/declarations/chosen_ones/judges_batch/4455_motsnyi_oleh_stepanovych.pdf"},"liabilities":{"54":{"sum_foreign_comment":"","sum":"","sum_comment":"","sum_comment_hidden":false,"sum_unclear":false,"sum_foreign":""},"55":{"sum_foreign_comment":"","sum":"","sum_comment":"","sum_foreign":""},"56":{"sum_foreign_comment":"","sum":"","sum_comment":"","sum_unclear":false,"sum_foreign":""},"57":{"sum_foreign_comment":"","sum":"","sum_comment":"","sum_comment_unclear":false,"sum_comment_hidden":false,"sum_unclear":false,"sum_foreign":""},"58":{"sum_foreign_comment":"","sum":"","sum_comment":"","sum_comment_hidden":false,"sum_unclear":false,"sum_foreign":""},"59":{"sum_foreign_comment":"","sum":"","sum_comment":"","sum_foreign":""},"60":{"sum_foreign_comment":"","sum_comment_hidden":false,"sum":"","sum_comment":"","sum_foreign":""},"61":{"sum_foreign_comment":"","sum":"","sum_comment":"","sum_foreign":""},"62":{"sum_foreign_comment":"","sum":"","sum_comment":"","sum_unclear":false,"sum_foreign":""},"63":{"sum_foreign_comment":"","sum_comment_hidden":false,"sum":"","sum_comment":"","sum_foreign":""},"64":{"sum_foreign_comment":"","sum_comment_hidden":false,"sum":"","sum_comment":"","sum_foreign":""}},"ft_src":"Степанович\nМоцний Олег Степанович\nсуддя селидівського міського суду донецької області\nДонецька область\nЗагальний місцевий суд\nОлег\nМоцний Олег Степанович\nОлег Степанович Моцний\nОлег Моцний\nМоцний Олег Степанович\nМоцний\n18898\nпенсія\n278749\n259851\nПриватбанк\n15000\n1/2\n54.4\n2014\n259851\n278749\nпенсія\n18898\nПриватбанк\n15000\n54.4\n1/2\nЗагальний місцевий суд\nДонецька область\nсуддя селидівського міського суду донецької області\nСтепанович\nМоцний Олег Степанович\nОлег Степанович Моцний\nОлег Моцний\nМоцний Олег Степанович\nМоцний Олег Степанович\nОлег\nМоцний\n259851\n18898\nпенсія\n278749\n2014\nСтепанович\nМоцний\nДонецька область\nЗагальний місцевий суд\nсуддя селидівського міського суду донецької області\nМоцний Олег Степанович\nМоцний Олег Степанович\nОлег Степанович Моцний\nОлег Моцний\nМоцний Олег Степанович\nОлег\n1/2\n54.4\nПриватбанк\n15000\n2014","general":{"inn":"","inn_hidden":true,"last_name":"Моцний","post":{"post_unclear":false,"region_unclear":false,"post":"суддя селидівського міського суду донецької області","office":"Загальний місцевий суд","region":"Донецька область","post_hidden":false,"office_unclear":false},"name":"Олег","full_name":"Моцний Олег Степанович","family_raw":"","addresses":[{"place_district":"","place_city_hidden":true,"place_city":"","place_city_unclear":false,"place_district_hidden":true,"place_city_type":"","place_address_hidden":true,"place_city_type_hidden":true,"place_address":"","place_hidden":true,"place":""}],"full_name_suggest":{"output":"Моцний Олег Степанович","input":["Моцний Олег Степанович","Олег Степанович Моцний","Олег Моцний"]},"patronymic":"Степанович"},"source":"VULYK","estate":{"24":[{"space_unclear":false,"costs":"","costs_comment":"","address_hidden":true,"region_hidden":true,"space_comment":"1/2","space":"54.4","address":"","region":"","costs_rent_comment":"","space_comment_unclear":false,"space_units":"м²","costs_rent":""}]},"intro":{"declaration_year":"2014"}}