{"income":{"5":{"family_comment":"","value":"214176.65","family":"108715","comment":""},"6":{"family_comment":"","value":"214176.65","family":"18500","comment":""},"7":{"value":"","comment_hidden":false,"family_comment":"","source_name":"","family":"","comment":"","source_name_hidden":false},"8":{"family_comment":"","value":"","family_hidden":false,"comment":"","family":""},"9":{"value":"","family_comment":"","value_unclear":false,"family_unclear":false,"family":"","comment":""},"10":{"family_comment":"","value":"","family":"","comment":""},"11":{"family_comment":"","value":"","family":"","comment":""},"12":{"family_comment":"","value":"","family":"","comment":""},"13":{"family_comment":"","value":"","family":"","comment":""},"14":{"family_comment":"","value":"","family":"","comment":""},"15":{"family_comment":"","value":"","family":"","comment":""},"16":{"family_comment":"","value":"","family":"","comment":""},"17":{"family_comment":"","value":"","family":"67415","comment":""},"18":{"family_comment":"","value":"","family":"","comment":""},"19":{"family_comment":"","value":"","family":"","comment":""},"20":{"value":"","value_unclear":false,"family_hidden":false,"family_comment":"","family":"22800","comment":""}},"vehicle":{"35":[{"brand_info":"","sum_rent_comment":"","year":"2008","brand_info_hidden":false,"brand_info_unclear":false,"year_unclear":false,"sum_rent":"","sum":"","brand":"Geely","sum_comment":"","sum_comment_unclear":false,"brand_hidden":false,"brand_unclear":false},{"brand_info":"","sum_rent_comment":"","brand":"Ford Transit Connect","sum_comment":"","year":"2010","sum":"","sum_rent":""}],"40":[{"brand_info":"2450","sum_rent_comment":"","brand":"ЕРА 3","sum_comment":"","year":"1989","brand_info_unclear":false,"sum":"","sum_rent":""}]},"id":"vulyk_109_80","banks":{"45":[{"sum_foreign_comment":"","sum_unclear":false,"sum_units":"UAH","sum_comment":"ПАТ КБ 'Приватбанк'","sum_foreign_units":"UAH","sum_comment_hidden":false,"sum_units_hidden":false,"sum":"2075.35","sum_foreign":""}],"46":[{"sum_foreign_comment":"","sum_units":"UAH","sum_comment":"ПАТ КБ 'Приватбанк'","sum_foreign_units":"UAH","sum":"2075.35","sum_foreign":""}]},"declaration":{"additional_info_text":"","notfull_lostpages":"","date":"2016-03-31T00:00:00","notfull":"","additional_info":"","url":"http://static.declarations.com.ua/declarations/chosen_ones/judges_batch/2537_kudriashova_iuliia_valeriivna_2015.pdf"},"liabilities":{"54":{"sum_foreign_comment":"","sum":"","sum_comment":"","sum_hidden":false,"sum_comment_hidden":false,"sum_unclear":false,"sum_foreign":""},"55":{"sum_foreign_comment":"","sum":"","sum_comment":"","sum_comment_unclear":false,"sum_foreign":""},"56":{"sum_foreign_comment":"","sum":"","sum_comment":"","sum_foreign":""},"57":{"sum_foreign_comment":"","sum_comment_hidden":false,"sum":"","sum_comment":"","sum_foreign":""},"58":{"sum_foreign_comment":"","sum_comment_hidden":false,"sum":"","sum_comment":"","sum_foreign":""},"59":{"sum_foreign_comment":"","sum":"","sum_comment":"","sum_foreign":""},"60":{"sum_foreign_comment":"","sum":"2491","sum_comment":"","sum_foreign":""},"61":{"sum_foreign_comment":"","sum":"","sum_comment":"","sum_foreign":""},"62":{"sum_foreign_comment":"","sum":"","sum_comment":"","sum_foreign":""},"63":{"sum_foreign_comment":"","sum":"","sum_comment":"","sum_foreign":""},"64":{"sum_foreign_comment":"","sum":"","sum_comment":"","sum_foreign":""}},"ft_src":"2491\nсуддя господарського суду житомирської області\nЖитомирська область\nГосподарський місцевий суд\nЮлія\nКузнєцова Н. М\nБатьки\nКудряшов І. Л\nПодружжя\nКудряшов Д. І\nДитина\nКудряшов І. І\nДитина\nКудряшова А. І\nДитина\nВалеріївна\nКудряшова Юлія Валеріївна\nКудряшова\nКудряшова Юлія Валеріївна\nЮлія Валеріївна Кудряшова\nЮлія Кудряшова\nКудряшова Юлія Валеріївна\nGeely\n2008\n2010\nFord Transit Connect\n2450\n1989\nЕРА 3\n14.96\n103\n8600\n380\n3.74\nПАТ КБ 'Приватбанк'\n2075.35\nПАТ КБ 'Приватбанк'\n2075.35\n2015\nGeely\n2008\nFord Transit Connect\n2010\n2450\n1989\nЕРА 3\n2015\nБатьки\nКузнєцова Н. М\nПодружжя\nКудряшов І. Л\nДитина\nКудряшов Д. І\nДитина\nКудряшов І. І\nКудряшова А. І\nДитина\nКудряшова Юлія Валеріївна\nЮлія Валеріївна Кудряшова\nЮлія Кудряшова\nКудряшова Юлія Валеріївна\nЮлія\nКудряшова Юлія Валеріївна\nКудряшова\nГосподарський місцевий суд\nЖитомирська область\nсуддя господарського суду житомирської області\nВалеріївна\n2491\n214176.65\n18500\n67415\n22800\n214176.65\n108715\n8600\n380\n103\n14.96\n3.74\n2075.35\nПАТ КБ 'Приватбанк'\n2075.35\nПАТ КБ 'Приватбанк'\n2491\n18500\n214176.65\n108715\n214176.65\n67415\n22800\nБатьки\nКузнєцова Н. М\nПодружжя\nКудряшов І. Л\nДитина\nКудряшов Д. І\nДитина\nКудряшов І. І\nДитина\nКудряшова А. І\nЮлія\nВалеріївна\nКудряшова\nКудряшова Юлія Валеріївна\nЮлія Валеріївна Кудряшова\nЮлія Кудряшова\nКудряшова Юлія Валеріївна\nЖитомирська область\nГосподарський місцевий суд\nсуддя господарського суду житомирської області\nКудряшова Юлія Валеріївна\n2008\nGeely\nFord Transit Connect\n2010\n1989\n2450\nЕРА 3\n22800\n108715\n214176.65\n67415\n18500\n214176.65\n14.96\n103\n3.74\n8600\n380\nПАТ КБ 'Приватбанк'\n2075.35\nПАТ КБ 'Приватбанк'\n2075.35\n2015","general":{"name_hidden":false,"name":"Юлія","inn":"","inn_unclear":false,"family":[{"inn":"","relations":"Батьки","relations_hidden":false,"inn_hidden":true,"relations_other":"","name_hidden":false,"family_name":"Кузнєцова Н. М","name_unclear":false},{"inn":"","relations":"Подружжя","relations_other":"","inn_hidden":false,"family_name":"Кудряшов І. Л","name_hidden":false,"name_unclear":false},{"inn":"","relations":"Дитина","relations_other":"","inn_hidden":false,"family_name":"Кудряшов Д. І","name_hidden":false,"name_unclear":false},{"inn":"","relations":"Дитина","inn_unclear":false,"family_name":"Кудряшов І. І","inn_hidden":false,"relations_other":"","name_unclear":false},{"inn":"","family_name":"Кудряшова А. І","relations":"Дитина","relations_other":"","name_unclear":false}],"inn_hidden":true,"family_raw":"","last_name":"Кудряшова","post":{"region_unclear":false,"region":"Житомирська область","post":"суддя господарського суду житомирської області","region_hidden":false,"office":"Господарський місцевий суд","office_hidden":false,"office_unclear":false},"full_name":"Кудряшова Юлія Валеріївна","patronymic":"Валеріївна","full_name_suggest":{"output":"Кудряшова Юлія Валеріївна","input":["Кудряшова Юлія Валеріївна","Юлія Валеріївна Кудряшова","Юлія Кудряшова"]}},"source":"VULYK","estate":{"25":[{"space_unclear":false,"costs":"","costs_comment":"","address_hidden":false,"region_hidden":false,"space_comment":"","space_hidden":false,"space":"3.74","address":"","region":"","costs_rent_comment":"","space_units":"м²","space_units_hidden":false,"costs_rent":""}],"29":[{"space_unclear":false,"address_hidden":false,"region_hidden":false,"space_comment":"","space":"8600","address":"","region":"","costs_property":"","costs_rent_comment":"","space_units":"м²","costs_property_comment":"","costs_rent":""},{"costs_rent":"","costs_property":"","costs_rent_comment":"","space_comment":"","costs_property_comment":"","space_units":"м²","space":"380","address":""}],"30":[{"costs_rent":"","space_hidden":false,"costs_property":"","costs_rent_comment":"","address_hidden":false,"region_hidden":false,"space_comment":"","costs_property_comment":"","space_units":"м²","space":"103","address":""}],"31":[{"space_hidden":false,"costs_property_comment":"","address_hidden":false,"region_hidden":false,"space_comment":"","space":"14.96","address":"","region":"","costs_property":"","costs_rent_comment":"","space_units":"м²","space_units_hidden":false,"costs_rent":""}]},"intro":{"declaration_year":"2015","isnotdeclaration":""}}