{"income":{"5":{"family_comment":"","value":"203228.99","family":"18744","comment":"","family_hidden":false},"6":{"value":"191048.99","value_unclear":false,"family_hidden":false,"family_comment":"","family":"5601","comment":""},"7":{"value":"","value_unclear":false,"family_comment":"","source_name":"","family":"","comment":""},"8":{"family_comment":"","value":"","family":"","comment":""},"9":{"family_comment":"","value":"","family":"","comment":""},"10":{"value":"12180","family_comment":"","comment_unclear":false,"family_unclear":false,"family":"","comment":"","family_comment_unclear":false},"11":{"family_comment":"","value":"","value_unclear":false,"family":"","comment":""},"12":{"family_comment":"","value":"","family":"","comment":""},"13":{"family_comment":"","value":"","family":"","comment":""},"14":{"family_comment":"","value":"","family":"","comment":""},"15":{"value":"","family_comment":"","comment_unclear":false,"family_unclear":false,"family":"1103","comment":""},"16":{"family_comment":"","value":"","family":"","comment":""},"17":{"family_comment":"","value":"","family":"","comment":""},"18":{"family_comment":"","family_unclear":false,"value":"","family":"","comment":""},"19":{"family_comment":"","value":"","family":"","comment":""},"20":{"family_comment":"","family_unclear":false,"value":"","family":"12040","comment":""}},"vehicle":{"35":[{"brand_info":"1998 куб. см., 135 к.с.","sum_rent_comment":"","year":"2009","brand_info_hidden":false,"brand_info_unclear":false,"year_unclear":false,"sum_rent":"","sum":"","brand":"Hyundai Sonata","sum_comment":"","brand_unclear":false,"brand_hidden":false,"sum_comment_unclear":false}]},"id":"vulyk_92_181","declaration":{"additional_info_text":"","notfull_lostpages":"","date":"2015-03-27T00:00:00","notfull":"","additional_info":"","url":"http://static.declarations.com.ua/declarations/chosen_ones/judges_batch/3427_andreikiv_iurii_iaroslavovych.pdf"},"liabilities":{"54":{"sum_foreign_comment":"","sum":"","sum_comment":"","sum_hidden":false,"sum_unclear":false,"sum_foreign":""},"55":{"sum_foreign_comment":"","sum":"","sum_comment":"","sum_unclear":false,"sum_foreign":""},"56":{"sum_foreign_comment":"","sum":"","sum_comment":"","sum_comment_unclear":false,"sum_hidden":false,"sum_unclear":false,"sum_foreign":""},"57":{"sum_foreign_comment":"","sum":"","sum_comment":"","sum_hidden":false,"sum_comment_hidden":false,"sum_foreign":""},"58":{"sum_foreign_comment":"","sum":"","sum_comment":"","sum_foreign":""},"59":{"sum_foreign_comment":"","sum":"","sum_comment":"","sum_comment_unclear":false,"sum_foreign":""},"60":{"sum_foreign_comment":"","sum":"","sum_comment":"","sum_foreign":""},"61":{"sum_foreign_comment":"","sum":"","sum_comment":"","sum_foreign":""},"62":{"sum_foreign_comment":"","sum":"","sum_comment":"","sum_comment_unclear":false,"sum_hidden":false,"sum_unclear":false,"sum_foreign":""},"63":{"sum_foreign_comment":"","sum":"","sum_comment":"","sum_foreign":""},"64":{"sum_foreign_comment":"","sum":"","sum_comment":"","sum_foreign":""}},"ft_src":"1998 куб. см., 135 к.с.\nHyundai Sonata\n2009\nЛьвівська область\nСтрийський р-н\n282.9\nЛьвівська область\nСтрийський р-н\n1000\nм. Стрий\n59\nЛьвівська область\n2014\n5601\n191048.99\n1103\n12180\n18744\n203228.99\n12040\n1998 куб. см., 135 к.с.\nHyundai Sonata\n2009\n1000\nСтрийський р-н\nЛьвівська область\nЛьвівська область\nСтрийський р-н\n282.9\n59\nЛьвівська область\nм. Стрий\nПодружжя\nАндрейків Софія Богданівна\nДитина\nАндрейків Ярослав Юрійович\nДитина\nАндрейків Анастасія Юріївна\nАндрейків Юрій Ярославович\nЮрій Ярославович Андрейків\nЮрій Андрейків\nАндрейків Юрій Ярославович\nАндрейків Юрій Ярославович\nЮрій\nАндрейків\nЗагальний місцевий суд\nсуддя стрийського міськрайонного суду львівської області\nЛьвівська область\nЯрославович\nЛьвівська область\nСтрий\n191048.99\n5601\n12040\n1103\n203228.99\n18744\n12180\n2014\nПодружжя\nАндрейків Софія Богданівна\nДитина\nАндрейків Ярослав Юрійович\nДитина\nАндрейків Анастасія Юріївна\nЯрославович\nАндрейків\nЮрій\nАндрейків Юрій Ярославович\nЮрій Ярославович Андрейків\nЮрій Андрейків\nАндрейків Юрій Ярославович\nСтрий\nЛьвівська область\nЛьвівська область\nЗагальний місцевий суд\nсуддя стрийського міськрайонного суду львівської області\nАндрейків Юрій Ярославович","general":{"inn":"","name":"Юрій","patronymic_unclear":false,"last_name":"Андрейків","family":[{"inn":"","relations":"Подружжя","inn_unclear":false,"relations_hidden":false,"inn_hidden":true,"family_name":"Андрейків Софія Богданівна","relations_other":"","name_hidden":false,"name_unclear":false},{"inn":"","relations":"Дитина","inn_unclear":false,"relations_hidden":false,"inn_hidden":true,"family_name":"Андрейків Ярослав Юрійович","relations_other":"","name_hidden":false,"name_unclear":false},{"inn":"","relations":"Дитина","relations_other":"","inn_hidden":false,"family_name":"Андрейків Анастасія Юріївна","name_unclear":false}],"inn_hidden":true,"family_raw":"","inn_unclear":false,"post":{"post_unclear":false,"post":"суддя стрийського міськрайонного суду львівської області","office_hidden":false,"region":"Львівська область","region_hidden":false,"office":"Загальний місцевий суд","office_unclear":false},"full_name":"Андрейків Юрій Ярославович","addresses":[{"place_district":"","place_address_hidden":true,"place_city":"Стрий","place_address":"","place_district_hidden":true,"place_city_type":"Місто","place_city_hidden":false,"place_address_unclear":false,"place_city_type_hidden":false,"place_hidden":false,"place":"Львівська область"}],"patronymic":"Ярославович","full_name_suggest":{"output":"Андрейків Юрій Ярославович","input":["Андрейків Юрій Ярославович","Юрій Ярославович Андрейків","Юрій Андрейків"]}},"source":"VULYK","estate":{"25":[{"space_hidden":false,"costs":"","costs_comment":"","address_hidden":false,"region_hidden":true,"space_comment":"","space":"59","address":"м. Стрий","region":"Львівська область","address_unclear":false,"costs_rent_comment":"","space_comment_unclear":false,"space_units":"м²","costs_rent":""}],"29":[{"space_unclear":false,"costs_property_comment":"","address_hidden":false,"region_hidden":true,"space_comment":"","space_units_hidden":false,"space":"1000","address":"Стрийський р-н","region":"Львівська область","costs_property":"","costs_rent_comment":"","space_units":"м²","space_units_unclear":false,"costs_rent":""}],"30":[{"space_unclear":false,"address_hidden":false,"region_hidden":true,"space_comment":"","space_hidden":false,"space":"282.9","address":"Стрийський р-н","region":"Львівська область","costs_property":"","costs_rent_comment":"","address_unclear":false,"space_units":"м²","costs_property_comment":"","costs_rent":""}]},"intro":{"declaration_year":"2014","isnotdeclaration":""}}