{"income":{"5":{"family_comment":"","value":"241805","family_hidden":false,"comment":"","family":"118082"},"6":{"value":"236389","value_unclear":false,"family_hidden":false,"family_comment":"","family":"118080","comment":""},"7":{"value":"","value_unclear":false,"family_comment":"","source_name":"","family":"","comment":""},"8":{"family_comment":"","value":"","family":"2","comment":""},"9":{"family_comment":"","value":"","family":"","comment":""},"10":{"value":"","family_comment":"","comment_unclear":false,"family_unclear":false,"family":"","comment":"","family_comment_unclear":false},"11":{"family_comment":"","value":"","value_unclear":false,"family":"","comment":""},"12":{"family_comment":"","value":"","family":"","comment":""},"13":{"family_comment":"","value":"","family":"","comment":""},"14":{"family_comment":"","value":"","family":"","comment":""},"15":{"value":"5416","family_comment":"","comment_unclear":false,"family_unclear":false,"family":"","comment":""},"16":{"family_comment":"","value":"","family":"","comment":""},"17":{"family_comment":"","value":"","family":"","comment":""},"18":{"family_comment":"","family_unclear":false,"value":"","family":"","comment":""},"19":{"family_comment":"","value":"","family":"","comment":""},"20":{"family_comment":"","family_unclear":false,"value":"","family":"","comment":""}},"vehicle":{"35":[{"brand_info":"1600 куб. см.","sum_rent_comment":"","year":"2007","brand_info_hidden":false,"brand_info_unclear":false,"year_unclear":false,"sum_rent":"","sum":"","brand":"Renault Scenic","sum_comment":"","sum_comment_unclear":false,"brand_hidden":false,"brand_unclear":false},{"brand_info":"2500 куб. см.","sum_rent_comment":"","brand":"Nissan Pathfinder","sum_comment":"","brand_unclear":false,"year":"2011","sum":"","sum_rent":""}]},"id":"vulyk_92_141","declaration":{"additional_info_text":"","notfull_lostpages":"","date":"2015-03-20T00:00:00","notfull":"","additional_info":"","url":"http://static.declarations.com.ua/declarations/chosen_ones/judges_batch/3389_danyliv_ievhen_olehovych.pdf"},"liabilities":{"54":{"sum_foreign_comment":"","sum":"470","sum_comment":"","sum_hidden":false,"sum_unclear":false,"sum_foreign":""},"55":{"sum_foreign_comment":"","sum":"","sum_comment":"","sum_unclear":false,"sum_foreign":""},"56":{"sum_foreign_comment":"","sum":"","sum_comment":"","sum_comment_unclear":false,"sum_hidden":false,"sum_unclear":false,"sum_foreign":""},"57":{"sum_foreign_comment":"","sum":"","sum_comment":"","sum_hidden":false,"sum_comment_hidden":false,"sum_foreign":""},"58":{"sum_foreign_comment":"","sum":"","sum_comment":"","sum_foreign":""},"59":{"sum_foreign_comment":"","sum":"","sum_comment":"","sum_comment_unclear":false,"sum_foreign":""},"60":{"sum_foreign_comment":"","sum":"","sum_comment":"","sum_foreign":""},"61":{"sum_foreign_comment":"","sum":"","sum_comment":"","sum_foreign":""},"62":{"sum_foreign_comment":"","sum":"","sum_comment":"","sum_comment_unclear":false,"sum_hidden":false,"sum_unclear":false,"sum_foreign":""},"63":{"sum_foreign_comment":"","sum":"","sum_comment":"","sum_foreign":""},"64":{"sum_foreign_comment":"","sum":"","sum_comment":"","sum_foreign":""}},"ft_src":"470\nсуддя пустомитівського районного суду львівської області\nЛьвівська область\nЗагальний місцевий суд\nЄвген\nДанилів О. М., 11. 11. 1974\nПодружжя\nДанилів А. Є., 27. 12. 1999\nДитина\nДанилів Ю. Є., 26. 11. 2003\nДитина\nДанилів М. Є., 08. 12. 2005\nДитина\nОлегович\nДанилів Євген Олегович\nЄвген Олегович Данилів\nЄвген Данилів\nДанилів Євген Олегович\nДанилів Євген Олегович\nДанилів\n1600 куб. см.\nRenault Scenic\n2007\n2011\n2500 куб. см.\nNissan Pathfinder\n1068\n180\n2014\n118080\n236389\n5416\n2\n118082\n241805\n1600 куб. см.\nRenault Scenic\n2007\n2500 куб. см.\nNissan Pathfinder\n2011\n1068\n180\nПодружжя\nДанилів О. М., 11. 11. 1974\nДитина\nДанилів А. Є., 27. 12. 1999\nДитина\nДанилів Ю. Є., 26. 11. 2003\nДитина\nДанилів М. Є., 08. 12. 2005\nДанилів Євген Олегович\nЄвген Олегович Данилів\nЄвген Данилів\nДанилів Євген Олегович\nДанилів Євген Олегович\nЄвген\nДанилів\nЗагальний місцевий суд\nсуддя пустомитівського районного суду львівської області\nЛьвівська область\nОлегович\n470\n236389\n118080\n5416\n241805\n118082\n2\n2014\n470\nПодружжя\nДанилів О. М., 11. 11. 1974\nДитина\nДанилів А. Є., 27. 12. 1999\nДитина\nДанилів Ю. Є., 26. 11. 2003\nДитина\nДанилів М. Є., 08. 12. 2005\nОлегович\nДанилів\nЄвген\nДанилів Євген Олегович\nЄвген Олегович Данилів\nЄвген Данилів\nДанилів Євген Олегович\nЛьвівська область\nЗагальний місцевий суд\nсуддя пустомитівського районного суду львівської області\nДанилів Євген Олегович\n2007\nRenault Scenic\n1600 куб. см.\n2011\n2500 куб. см.\nNissan Pathfinder\n5416\n118082\n241805\n2\n236389\n118080\n1068\n180\n2014","general":{"inn":"","name":"Євген","patronymic_unclear":false,"family":[{"inn":"","relations":"Подружжя","inn_unclear":false,"relations_hidden":false,"inn_hidden":true,"relations_other":"","name_hidden":false,"family_name":"Данилів О. М., 11. 11. 1974","name_unclear":false},{"inn":"","relations":"Дитина","inn_unclear":false,"relations_hidden":false,"inn_hidden":true,"relations_other":"","name_hidden":false,"family_name":"Данилів А. Є., 27. 12. 1999","name_unclear":false},{"inn":"","relations":"Дитина","relations_other":"","inn_hidden":true,"family_name":"Данилів Ю. Є., 26. 11. 2003","name_unclear":false},{"inn":"","relations":"Дитина","relations_other":"","inn_hidden":true,"family_name":"Данилів М. Є., 08. 12. 2005","name_unclear":false}],"patronymic":"Олегович","inn_hidden":true,"family_raw":"","inn_unclear":false,"post":{"post_unclear":false,"post":"суддя пустомитівського районного суду львівської області","office_hidden":false,"region":"Львівська область","office":"Загальний місцевий суд","office_unclear":false,"region_hidden":false},"full_name":"Данилів Євген Олегович","addresses":[{"place_district":"","place_address_hidden":true,"place_city":"","place_city_type_hidden":true,"place_district_hidden":true,"place_city_type":"","place_city_hidden":true,"place_address_unclear":false,"place_address":"","place_hidden":true,"place":""}],"last_name":"Данилів","full_name_suggest":{"output":"Данилів Євген Олегович","input":["Данилів Євген Олегович","Євген Олегович Данилів","Євген Данилів"]}},"source":"VULYK","estate":{"23":[{"region_unclear":false,"space_unclear":false,"costs":"","costs_comment":"","address_hidden":false,"region_hidden":true,"space_comment":"","space":"1068","address":"","region":"","costs_rent_comment":"","space_units":"м²","costs_rent":""},{"space_hidden":false,"costs":"","costs_comment":"","region_hidden":true,"space_comment":"","space_unclear":false,"space":"180","address":"","region":"","address_unclear":false,"costs_rent_comment":"","space_units":"м²","costs_rent":""}]},"intro":{"declaration_year":"2014","isnotdeclaration":""}}