{"income":{"5":{"value":"283824","family_comment":"","value_unclear":false,"family_hidden":false,"family_unclear":false,"family":"10440","comment":""},"6":{"family_comment":"","value":"238457","family":"","comment":""},"7":{"family_comment":"","value":"","source_name":"","family":"","comment":""},"8":{"family_comment":"","value":"","family":"","comment":""},"9":{"family_comment":"","value":"15823","family":"","comment":""},"10":{"family_comment":"","value":"","value_unclear":false,"family":"","comment":""},"11":{"family_comment":"","value":"","family":"","comment":""},"12":{"family_comment":"","value":"","family":"","comment":""},"13":{"family_comment":"","value":"","family":"","comment":""},"14":{"family_comment":"","value":"","family":"","comment":""},"15":{"family_comment":"","value":"","family":"","comment":""},"16":{"family_comment":"","value":"","family":"","comment":""},"17":{"family_comment":"","value":"","family":"","comment":""},"18":{"family_comment":"","value":"","family":"","comment":""},"19":{"family_comment":"","value":"","family":"","comment":""},"20":{"family_comment":"","value":"29544","family":"10440","comment":""}},"vehicle":{"35":[{"brand_info":"2400 куб. см. 118 кВт","sum_rent_comment":"","brand":"Mitsubishi Outlander","sum_comment":"","brand_unclear":false,"year":"2006","sum":"","sum_rent":""}]},"id":"vulyk_82_70","banks":{"45":[{"sum_foreign_comment":"","sum_units":"UAH","sum_comment":"","sum_foreign_units":"UAH","sum_comment_hidden":false,"sum_unclear":false,"sum":"166565","sum_foreign":""}],"46":[{"sum_foreign_comment":"","sum_units":"UAH","sum_comment":"","sum_hidden":true,"sum_foreign_units":"UAH","sum_comment_hidden":false,"sum":"","sum_foreign":""}]},"declaration":{"date":"2015-03-30T00:00:00","additional_info_text":"","additional_info":"","url":"http://static.declarations.com.ua/declarations/chosen_ones/judges_batch/2265_hrachov_viktor_mykhailovych.pdf"},"liabilities":{"54":{"sum_foreign_comment":"","sum_comment_hidden":false,"sum":"","sum_comment":"","sum_foreign":""},"55":{"sum_foreign_comment":"","sum":"","sum_hidden":false,"sum_comment":"","sum_foreign":""},"56":{"sum_foreign_comment":"","sum":"","sum_comment":"","sum_foreign":""},"57":{"sum_foreign_comment":"","sum":"","sum_comment":"","sum_foreign":""},"58":{"sum_foreign_comment":"","sum":"","sum_comment":"","sum_foreign":""},"59":{"sum_foreign_comment":"","sum":"","sum_comment":"","sum_foreign":""},"60":{"sum_foreign_comment":"","sum":"","sum_comment":"","sum_foreign":""},"61":{"sum_foreign_comment":"","sum":"","sum_comment":"","sum_foreign":""},"62":{"sum_foreign_comment":"","sum":"","sum_comment":"","sum_foreign":""},"63":{"sum_foreign_comment":"","sum":"","sum_comment":"","sum_foreign":""},"64":{"sum_foreign_comment":"","sum":"","sum_comment":"","sum_foreign":""}},"ft_src":"суддя господарського суду черкаської області\nЧеркаська область\nГосподарський місцевий суд\nВіктор\nДитина\nМихайлович\nГрачов Віктор Михайлович\nВіктор Михайлович Грачов\nВіктор Грачов\nГрачов Віктор Михайлович\nГрачов Віктор Михайлович\nГрачов\n2006\n2400 куб. см. 118 кВт\nMitsubishi Outlander\n166565\n2014\n2400 куб. см. 118 кВт\n2006\nMitsubishi Outlander\n166565\n2014\nДитина\nГрачов Віктор Михайлович\nВіктор Михайлович Грачов\nВіктор Грачов\nГрачов Віктор Михайлович\nГрачов Віктор Михайлович\nВіктор\nГрачов\nГосподарський місцевий суд\nЧеркаська область\nсуддя господарського суду черкаської області\nМихайлович\n238457\n29544\n10440\n283824\n10440\n15823\n120\n180\n18\n76\n120\n180\n18\n76\nДитина\nМихайлович\nГрачов\nВіктор\nГрачов Віктор Михайлович\nВіктор Михайлович Грачов\nВіктор Грачов\nГрачов Віктор Михайлович\nЧеркаська область\nГосподарський місцевий суд\nсуддя господарського суду черкаської області\nГрачов Віктор Михайлович\n238457\n15823\n10440\n283824\n10440\n29544\n2006\n2400 куб. см. 118 кВт\nMitsubishi Outlander\n15823\n10440\n29544\n283824\n10440\n238457\n76\n120\n180\n18\n166565\n2014","general":{"inn":"","name":"Віктор","inn_unclear":false,"family":[{"inn":"","inn_hidden":true,"relations_hidden":false,"family_name":"","relations_other":"","relations":"Дитина","name_hidden":true,"name_unclear":false}],"inn_hidden":true,"family_raw":"","last_name":"Грачов","post":{"post":"суддя господарського суду черкаської області","region":"Черкаська область","office_hidden":false,"office":"Господарський місцевий суд","office_unclear":false,"post_hidden":false,"region_hidden":false},"full_name_suggest":{"output":"Грачов Віктор Михайлович","input":["Грачов Віктор Михайлович","Віктор Михайлович Грачов","Віктор Грачов"]},"full_name":"Грачов Віктор Михайлович","addresses":[{"place_district":"","place_city_hidden":true,"place_city":"","place_city_type_hidden":false,"place_district_hidden":false,"place_city_type":"","place_address_hidden":false,"place_address":"","place_hidden":true,"place":""}],"patronymic":"Михайлович","last_name_unclear":false},"source":"VULYK","estate":{"23":[{"costs":"","costs_comment":"","address_hidden":false,"region_hidden":true,"space_comment":"","space_units_unclear":false,"address":"","space":"120","region":"","costs_rent_comment":"","space_units":"м²","costs_rent":""},{"costs_rent":"","region":"","costs":"","costs_rent_comment":"","costs_comment":"","region_hidden":false,"space_comment":"","space_units":"м²","space":"180","address":""}],"25":[{"space_hidden":false,"costs":"","costs_comment":"","costs_hidden":false,"address_hidden":false,"region_hidden":true,"space_comment":"","space_unclear":false,"space":"76","address":"","region":"","costs_rent_comment":"","space_comment_unclear":false,"space_units":"м²","costs_rent":""}],"27":[{"costs_rent":"","region":"","costs":"","costs_rent_comment":"","costs_comment":"","address_hidden":false,"region_hidden":true,"space_comment":"","space_units":"м²","space":"18","address":""}]},"intro":{"declaration_year":"2014"}}