{"income":{"5":{"family_comment":"","value":"285218","family":"31174","comment":""},"6":{"family_comment":"","value":"258845","family":"","comment":""},"7":{"value":"","comment_hidden":false,"family_comment":"","source_name":"","family":"","comment":"","source_name_hidden":false},"8":{"family_comment":"","value":"","family_hidden":false,"comment":"","family":""},"9":{"value":"4226","family_comment":"","value_unclear":false,"family_unclear":false,"family":"9168","comment":""},"10":{"family_comment":"","value":"","family":"","comment":""},"11":{"family_comment":"","value":"","family":"","comment":""},"12":{"family_comment":"","value":"","family":"","comment":""},"13":{"family_comment":"","value":"","family":"","comment":""},"14":{"family_comment":"","value":"","family":"","comment":""},"15":{"family_comment":"","value":"","family":"","comment":""},"16":{"family_comment":"","value":"","family":"","comment":""},"17":{"family_comment":"","value":"","family":"","comment":""},"18":{"family_comment":"","value":"","family":"","comment":""},"19":{"family_comment":"","value":"","family":"","comment":""},"20":{"value":"22147","value_unclear":false,"family_hidden":false,"family_comment":"","family":"22006","comment":""}},"id":"vulyk_109_29","banks":{"45":[{"sum_foreign_comment":"","sum_unclear":false,"sum_units":"UAH","sum_comment":"","sum_foreign_units":"UAH","sum_comment_hidden":false,"sum_units_hidden":false,"sum":"75121","sum_foreign":""}],"51":[{"sum_foreign_comment":"","sum_unclear":false,"sum_units":"UAH","sum_comment":"","sum_foreign_units":"UAH","sum_comment_hidden":false,"sum_units_hidden":false,"sum":"29067","sum_foreign":""}]},"declaration":{"additional_info_text":"","notfull_lostpages":"","date":"2016-03-18T00:00:00","notfull":"","additional_info":"","url":"http://static.declarations.com.ua/declarations/chosen_ones/judges_batch/2486_kravchuk_viktor_oksentiiovych_2015.pdf"},"liabilities":{"54":{"sum_foreign_comment":"","sum":"120","sum_comment":"","sum_hidden":false,"sum_comment_hidden":false,"sum_unclear":true,"sum_foreign":""},"55":{"sum_foreign_comment":"","sum":"","sum_comment":"","sum_comment_unclear":false,"sum_foreign":""},"56":{"sum_foreign_comment":"","sum":"","sum_comment":"","sum_foreign":""},"57":{"sum_foreign_comment":"","sum_comment_hidden":false,"sum":"","sum_comment":"","sum_foreign":""},"58":{"sum_foreign_comment":"","sum_comment_hidden":false,"sum":"","sum_comment":"","sum_foreign":""},"59":{"sum_foreign_comment":"","sum":"","sum_comment":"","sum_foreign":""},"60":{"sum_foreign_comment":"","sum":"","sum_comment":"","sum_foreign":""},"61":{"sum_foreign_comment":"","sum":"","sum_comment":"","sum_foreign":""},"62":{"sum_foreign_comment":"","sum":"","sum_comment":"","sum_foreign":""},"63":{"sum_foreign_comment":"","sum":"","sum_comment":"","sum_foreign":""},"64":{"sum_foreign_comment":"","sum":"","sum_comment":"","sum_foreign":""}},"ft_src":"120\nсуддя господарського суду волинської області\nВолинська область\nГосподарський місцевий суд\nВіктор\nКравчук Валентина Теофілівна\nПодружжя\nОксентійович\nКравчук Віктор Оксентійович\nВіктор Оксентійович Кравчук\nВіктор Кравчук\nКравчук Віктор Оксентійович\nКравчук Віктор Оксентійович\nКравчук\n108\n350\n61\n29067\n75121\n2015\n2015\nКравчук Віктор Оксентійович\nВіктор Оксентійович Кравчук\nВіктор Кравчук\nКравчук Віктор Оксентійович\nВіктор\nПодружжя\nКравчук Валентина Теофілівна\nКравчук Віктор Оксентійович\nОксентійович\nГосподарський місцевий суд\nВолинська область\nсуддя господарського суду волинської області\nКравчук\n120\n258845\n22147\n22006\n285218\n31174\n4226\n9168\n350\n108\n61\n75121\n29067\n120\n258845\n31174\n285218\n9168\n4226\n22006\n22147\nПодружжя\nКравчук Валентина Теофілівна\nОксентійович\nКравчук\nВіктор\nКравчук Віктор Оксентійович\nВіктор Оксентійович Кравчук\nВіктор Кравчук\nКравчук Віктор Оксентійович\nВолинська область\nГосподарський місцевий суд\nсуддя господарського суду волинської області\nКравчук Віктор Оксентійович\n22147\n22006\n31174\n285218\n4226\n9168\n258845\n108\n61\n350\n75121\n29067\n2015","general":{"name_hidden":false,"name":"Віктор","inn":"","family":[{"inn":"","relations":"Подружжя","relations_hidden":false,"inn_hidden":false,"relations_other":"","name_hidden":false,"family_name":"Кравчук Валентина Теофілівна","name_unclear":false}],"patronymic":"Оксентійович","inn_hidden":true,"family_raw":"","inn_unclear":false,"post":{"region_unclear":false,"region":"Волинська область","post":"суддя господарського суду волинської області","region_hidden":false,"office":"Господарський місцевий суд","office_hidden":false,"office_unclear":false},"full_name":"Кравчук Віктор Оксентійович","addresses":[{"place_district":"","place_city_hidden":false,"place_city":"","place_city_type_hidden":false,"place_district_hidden":false,"place_city_type":"","place_address_hidden":false,"place_address":"","place_hidden":true,"place":""}],"last_name":"Кравчук","full_name_suggest":{"output":"Кравчук Віктор Оксентійович","input":["Кравчук Віктор Оксентійович","Віктор Оксентійович Кравчук","Віктор Кравчук"]}},"source":"VULYK","estate":{"25":[{"space_unclear":false,"costs":"","costs_comment":"","address_hidden":false,"region_hidden":true,"space_comment":"","space_hidden":false,"space":"61","address":"","region":"","costs_rent_comment":"","space_units":"м²","space_units_hidden":false,"costs_rent":""}],"29":[{"space_unclear":true,"address_hidden":true,"region_hidden":true,"space_comment":"","space":"350","address":"","region":"","costs_property":"","costs_rent_comment":"","space_units":"м²","costs_property_comment":"","costs_rent":""}],"30":[{"costs_rent":"","space_hidden":false,"costs_property":"","costs_rent_comment":"","address_hidden":true,"region_hidden":true,"space_comment":"","costs_property_comment":"","space_units":"м²","space":"108","address":""}]},"intro":{"declaration_year":"2015","isnotdeclaration":""}}