{"income":{"5":{"value":"273763","value_unclear":false,"family_hidden":false,"family_comment":"","family":"56425","comment":""},"6":{"family_comment":"","value":"258753","value_unclear":false,"family":"","comment":""},"7":{"source_name_unclear":false,"value":"","family_comment":"","source_name":"","family":"","comment":"","source_name_hidden":false},"8":{"family_comment":"","value":"","family":"","comment":""},"9":{"family_comment":"","value":"20","comment_unclear":false,"family":"","comment":""},"10":{"family_comment":"","value":"14616","family":"","comment":""},"11":{"family_comment":"","family_unclear":false,"value":"374","family":"","comment":""},"12":{"family_comment":"","value":"","family":"","comment":""},"13":{"family_comment":"","value":"","family":"","comment":""},"14":{"family_comment":"","value":"","family":"","comment":""},"15":{"family_comment":"","value":"","family":"","comment":""},"16":{"family_comment":"","value":"","family":"","comment":""},"17":{"family_comment":"","value":"","family":"","comment":""},"18":{"family_comment":"","value":"","family":"","comment":""},"19":{"family_comment":"","value":"","family":"884","comment":""},"20":{"value":"","value_unclear":false,"family_comment":"пенсія членів сім'ї","comment_unclear":false,"comment":"","family":"55541"}},"vehicle":{"35":[{"year_hidden":false,"brand_info":"2.0.1998 куб. см.","sum_rent_comment":"","year":"2011","brand_info_hidden":false,"brand_info_unclear":false,"year_unclear":false,"sum_rent":"","sum":"","brand":"Mitsubishi Outlander","sum_comment":"","brand_unclear":false,"brand_hidden":false}],"40":[{"brand_info":"2.0.1997 куб. см.","sum":"","brand":"Mitsubishi Outlander","sum_comment":"","brand_unclear":false,"year":"2007","brand_hidden":false,"brand_info_hidden":false,"brand_info_unclear":false,"sum_rent_comment":"","sum_rent":""}]},"id":"vulyk_94_46","banks":{"45":[{"sum_foreign_comment":"","sum_unclear":false,"sum_units":"UAH","sum_comment":"","sum_hidden":true,"sum_foreign_units":"UAH","sum_units_unclear":false,"sum_comment_hidden":false,"sum_units_hidden":false,"sum":"94","sum_foreign":""}],"51":[{"sum_foreign_comment":"","sum_units":"UAH","sum_comment":"","sum_hidden":true,"sum_foreign_units":"UAH","sum_comment_hidden":false,"sum_unclear":false,"sum":"3117","sum_foreign":""},{"sum_foreign_comment":"","sum_units":"UAH","sum_comment":"","sum_foreign_units":"UAH","sum":"42","sum_unclear":false,"sum_foreign":""}]},"declaration":{"additional_info_text":"","notfull_lostpages":"","date":"2015-03-30T00:00:00","notfull":"","additional_info":"","url":"http://static.declarations.com.ua/declarations/chosen_ones/judges_batch/3692_trakalo_valentyna_volodymyrivna.pdf"},"liabilities":{"54":{"sum_foreign_comment":"","sum":"","sum_comment":"","sum_comment_unclear":false,"sum_comment_hidden":false,"sum_unclear":false,"sum_foreign":""},"55":{"sum_foreign_comment":"","sum":"","sum_comment":"","sum_foreign":""},"56":{"sum_foreign_comment":"","sum":"","sum_comment":"","sum_unclear":false,"sum_foreign":""},"57":{"sum_foreign_comment":"","sum":"","sum_comment":"","sum_hidden":false,"sum_unclear":false,"sum_foreign":""},"58":{"sum_foreign_comment":"","sum":"","sum_comment":"","sum_hidden":false,"sum_unclear":false,"sum_foreign":""},"59":{"sum_foreign_comment":"","sum":"","sum_comment":"","sum_foreign":""},"60":{"sum_foreign_comment":"","sum_comment_hidden":false,"sum":"","sum_comment":"","sum_foreign":""},"61":{"sum_foreign_comment":"","sum":"","sum_comment":"","sum_foreign":""},"62":{"sum_foreign_comment":"","sum":"","sum_hidden":false,"sum_comment":"","sum_foreign":""},"63":{"sum_foreign_comment":"","sum_comment_hidden":false,"sum":"","sum_comment":"","sum_foreign":""},"64":{"sum_foreign_comment":"","sum":"","sum_comment":"","sum_unclear":false,"sum_foreign":""}},"ft_src":"суддя вищого адміністративного суду україни\nЗагальнодержавний регіон\nВищий адміністративний суд України\nВалентина\nПодружжя\nІнше\nМати чоловіка\nВолодимирівна\nТракало Валентина Володимирівна\nВалентина Володимирівна Тракало\nВалентина Тракало\nТракало Валентина Володимирівна\nТракало Валентина Володимирівна\nТракало\n2.0.1998 куб. см.\nMitsubishi Outlander\n2011\nMitsubishi Outlander\n2.0.1997 куб. см.\n2007\n3117\n42\n94\n2014\n2.0.1998 куб. см.\nMitsubishi Outlander\n2011\nMitsubishi Outlander\n2.0.1997 куб. см.\n2007\n94\n3117\n42\n2014\nТракало Валентина Володимирівна\nВалентина Володимирівна Тракало\nВалентина Тракало\nТракало Валентина Володимирівна\nТракало Валентина Володимирівна\nПодружжя\nІнше\nМати чоловіка\nВалентина\nТракало\nВищий адміністративний суд України\nЗагальнодержавний регіон\nсуддя вищого адміністративного суду україни\nВолодимирівна\n258753\nпенсія членів сім'ї\n55541\n273763\n56425\n20\n14616\n374\n884\n.12\n.15\n.221\n1.64\n139.7\n83.5\nкористування\n.12\n.15\n139.7\n.221\n1.64\nкористування\n83.5\nПодружжя\nМати чоловіка\nІнше\nВолодимирівна\nТракало\nВалентина\nТракало Валентина Володимирівна\nВалентина Володимирівна Тракало\nВалентина Тракало\nТракало Валентина Володимирівна\nЗагальнодержавний регіон\nВищий адміністративний суд України\nсуддя вищого адміністративного суду україни\nТракало Валентина Володимирівна\n258753\n20\n374\n14616\n56425\n273763\n884\nпенсія членів сім'ї\n55541\nMitsubishi Outlander\n2.0.1998 куб. см.\n2011\nMitsubishi Outlander\n2.0.1997 куб. см.\n2007\n374\n884\n20\n14616\nпенсія членів сім'ї\n55541\n273763\n56425\n258753\n139.7\n.12\n.15\nкористування\n83.5\n.221\n1.64\n94\n3117\n42\n2014","general":{"inn":"","name":"Валентина","last_name":"Тракало","family":[{"inn":"","relations":"Подружжя","relations_hidden":false,"inn_hidden":true,"family_name":"","name_hidden":true,"name_unclear":false},{"inn":"","relations":"Інше","relations_unclear":false,"family_name":"","inn_hidden":false,"relations_other":"Мати чоловіка","name_hidden":false,"name_unclear":false}],"inn_hidden":true,"family_raw":"","inn_unclear":false,"post":{"post_unclear":false,"region_unclear":false,"post":"суддя вищого адміністративного суду україни","candidate":"","post_hidden":false,"region":"Загальнодержавний регіон","office":"Вищий адміністративний суд України","office_unclear":false},"full_name":"Тракало Валентина Володимирівна","addresses":[{"place_district":"","place_city_hidden":false,"place_city":"","place_city_type_hidden":false,"place_district_hidden":true,"place_city_type":"","place_address_hidden":false,"place_address":"","place_hidden":true,"place":""}],"patronymic":"Володимирівна","patronymic_hidden":false,"full_name_suggest":{"output":"Тракало Валентина Володимирівна","input":["Тракало Валентина Володимирівна","Валентина Володимирівна Тракало","Валентина Тракало"]}},"source":"VULYK","estate":{"23":[{"region_unclear":false,"space_unclear":false,"costs":"","costs_comment":"","address_hidden":false,"region_hidden":true,"space_comment":"","space_hidden":false,"space":".12","address":"","region":"","address_unclear":false,"space_units_unclear":false,"costs_rent_hidden":false,"costs_rent_comment_hidden":false,"space_units":"га","costs_rent":"","costs_rent_comment":""},{"region_unclear":false,"costs":"","costs_comment":"","region_hidden":false,"space_comment":"","space":".15","address":"","region":"","address_unclear":false,"costs_rent_comment":"","costs_rent_hidden":false,"costs_rent_comment_hidden":false,"space_units":"га","costs_rent":""}],"25":[{"region_unclear":false,"space_unclear":false,"costs":"","costs_comment":"","address_hidden":true,"region_hidden":false,"space_comment":"користування","space_hidden":false,"space":"83.5","address":"","region":"","address_unclear":false,"costs_rent_comment":"","costs_rent_hidden":false,"space_comment_unclear":false,"costs_rent_comment_hidden":false,"space_units":"м²","costs_rent":""}],"29":[{"costs_rent":"","region":"","costs_property":"","costs_rent_comment":"","address_hidden":false,"region_hidden":true,"space_comment":"","costs_property_comment":"","space_units":"га","space":".221","address":""},{"costs_rent":"","region":"","costs_property":"","costs_rent_comment":"","address_hidden":false,"region_hidden":false,"space_comment":"","costs_property_comment":"","space_units":"га","space":"1.64","address":""}],"30":[{"space_hidden":false,"address_hidden":false,"region_hidden":true,"space_comment":"","space":"139.7","address":"","region":"","costs_property":"","costs_rent_comment":"","space_units":"м²","costs_property_comment":"","costs_rent":""}]},"intro":{"declaration_year":"2014","isnotdeclaration":""}}