{"income":{"5":{"value":"265063","family_hidden":false,"value_hidden":false,"family_comment":"","family":"37025","comment":""},"6":{"family_comment":"","value":"262044","family":"23628","comment":""},"7":{"family_comment":"","value":"","source_name":"","family":"","comment":""},"8":{"family_comment":"","value":"","family":"","comment":""},"9":{"family_comment":"","value":"3009","family":"","comment":""},"10":{"family_comment":"","value":"","family":"","comment":""},"11":{"family_comment":"","value":"","family":"","comment":""},"12":{"family_comment":"","value":"","family":"13397","comment":""},"13":{"family_comment":"","value":"","family":"","comment":""},"14":{"family_comment":"","value":"","family":"","comment":""},"15":{"family_comment":"","value":"","family":"","comment":""},"16":{"family_comment":"","value":"","family":"","comment":""},"17":{"family_comment":"","value":"","family":"","comment":""},"18":{"family_comment":"","value":"","family":"","comment":""},"19":{"family_comment":"","value":"","family":"","comment":""},"20":{"family_comment":"","value":"","family":"","comment":""}},"vehicle":{"35":[{"brand_info":"1.6","sum_rent_comment":"","brand":"Citroen C3 Picasso","sum_comment":"","year":"2013","sum":"","sum_rent":""}]},"id":"vulyk_89_13","banks":{"45":[{"sum_foreign_comment":"","sum_units":"UAH","sum_comment":"","sum_foreign_units":"UAH","sum_comment_hidden":true,"sum":"23507","sum_foreign":""}],"46":[{"sum_foreign_comment":"","sum_units":"UAH","sum_comment":"","sum_foreign_units":"UAH","sum":"498","sum_foreign":""}]},"declaration":{"date":"2015-03-26T00:00:00","notfull":"","url":"http://static.declarations.com.ua/declarations/chosen_ones/judges_batch/3016_chebanov_oleksandr_olehovych.pdf","notfull_lostpages":""},"liabilities":{"54":{"sum_foreign_comment":"","sum":"","sum_comment":"","sum_foreign":""},"55":{"sum_foreign_comment":"","sum":"","sum_comment":"","sum_foreign":""},"56":{"sum_foreign_comment":"","sum":"","sum_comment":"","sum_unclear":false,"sum_foreign":""},"57":{"sum_foreign_comment":"","sum":"42199","sum_comment":"","sum_foreign":""},"58":{"sum_foreign_comment":"","sum":"1701","sum_comment":"","sum_foreign":""},"59":{"sum_foreign_comment":"","sum":"","sum_comment":"","sum_foreign":""},"60":{"sum_foreign_comment":"","sum":"","sum_comment":"","sum_foreign":""},"61":{"sum_foreign_comment":"","sum":"","sum_comment":"","sum_foreign":""},"62":{"sum_foreign_comment":"","sum":"","sum_comment":"","sum_unclear":false,"sum_foreign":""},"63":{"sum_foreign_comment":"","sum":"21285","sum_comment":"","sum_foreign":""},"64":{"sum_foreign_comment":"","sum":"7864","sum_comment":"","sum_foreign":""}},"ft_src":"42199\n7864\n1701\n21285\nЧебанов Олександр Олегович\nсуддя донецького апеляційного адміністративного суду\nДонецька область\nАпеляційний адміністративний суд\nОлександр\nЧебанова С. І\nПодружжя\nЧебанов О. О\nДитина\nЧебанов Олександр Олегович\nОлександр Олегович Чебанов\nОлександр Чебанов\nЧебанов Олександр Олегович\nЧебанов\nОлегович\n1.6\n2013\nCitroen C3 Picasso\n498\n23507\n2014\n1.6\nCitroen C3 Picasso\n2013\n23507\n498\n2014\nОлегович\nЧебанова С. І\nПодружжя\nДитина\nЧебанов О. О\nЧебанов Олександр Олегович\nОлександр Олегович Чебанов\nОлександр Чебанов\nЧебанов Олександр Олегович\nЧебанов Олександр Олегович\nОлександр\nЧебанов\nДонецька область\nсуддя донецького апеляційного адміністративного суду\nАпеляційний адміністративний суд\n1701\n42199\n7864\n21285\n262044\n23628\n13397\n265063\n37025\n3009\n35\n67.7\n1701\n42199\n7864\n21285\n35\n67.7\nЧебанова С. І\nПодружжя\nЧебанов О. О\nДитина\nОлегович\nЧебанов\nсуддя донецького апеляційного адміністративного суду\nДонецька область\nАпеляційний адміністративний суд\nЧебанов Олександр Олегович\nЧебанов Олександр Олегович\nОлександр Олегович Чебанов\nОлександр Чебанов\nЧебанов Олександр Олегович\nОлександр\n23628\n262044\n37025\n265063\n3009\n13397\nCitroen C3 Picasso\n1.6\n2013\n265063\n37025\n3009\n13397\n23628\n262044\n35\n67.7\n23507\n498\n2014","general":{"inn":"","inn_hidden":true,"last_name":"Чебанов","post":{"office":"Апеляційний адміністративний суд","region":"Донецька область","post":"суддя донецького апеляційного адміністративного суду"},"name":"Олександр","full_name":"Чебанов Олександр Олегович","family_raw":"","addresses":[{"place_district":"","place_city_hidden":true,"place_city":"","place_city_type_hidden":true,"place_district_hidden":true,"place_city_type":"","place_address_hidden":true,"place_address":"","place_hidden":true,"place":""}],"family":[{"inn":"","family_name":"Чебанова С. І","relations":"Подружжя","inn_hidden":true,"name_hidden":true},{"inn":"","relations":"Дитина","relations_other":"","inn_hidden":false,"family_name":"Чебанов О. О","name_hidden":false,"name_unclear":false}],"full_name_suggest":{"output":"Чебанов Олександр Олегович","input":["Чебанов Олександр Олегович","Олександр Олегович Чебанов","Олександр Чебанов"]},"patronymic":"Олегович"},"source":"VULYK","estate":{"25":[{"costs":"","costs_comment":"","address_hidden":true,"region_hidden":true,"space_comment":"","space":"67.7","address":"","region":"","costs_rent_comment":"","space_comment_unclear":false,"space_units":"м²","costs_rent":""}],"31":[{"space_hidden":false,"address_hidden":true,"region_hidden":true,"space_comment":"","space":"35","address":"","region":"","costs_property":"","costs_rent_comment":"","space_units":"м²","costs_property_comment":"","costs_rent":""}]},"intro":{"declaration_year":"2014"}}