{"income":{"5":{"value":"252108.55","family_comment":"","value_unclear":false,"family_hidden":false,"value_hidden":false,"family_unclear":false,"family":"","comment":""},"6":{"value":"239928.55","family_comment":"","value_unclear":false,"family_unclear":false,"family":"","comment":""},"7":{"source_name_unclear":false,"value":"","comment_hidden":false,"family_comment":"","source_name":"","family":"","comment":"","source_name_hidden":false},"8":{"family_comment":"","value":"","family":"","comment":""},"9":{"value":"","family_comment":"","value_unclear":false,"family_hidden":false,"family_unclear":false,"family":"","comment":"","family_comment_unclear":false},"10":{"family_comment":"","value":"12180","family":"","comment":""},"11":{"family_comment":"","value":"","family":"","comment":""},"12":{"family_comment":"","value":"","family":"","comment":""},"13":{"family_comment":"","value":"","family":"","comment":""},"14":{"family_comment":"","value":"","family":"","comment":""},"15":{"family_comment":"","value":"","family":"","comment":""},"16":{"family_comment":"","value":"","family":"","comment":""},"17":{"family_comment":"","value":"","family":"","comment":""},"18":{"family_comment":"","value":"","family":"","comment":""},"19":{"family_comment":"","value":"","family":"","comment":""},"20":{"value":"","family_comment":"","value_unclear":false,"family_comment_hidden":false,"family_unclear":false,"family_comment_unclear":false,"comment_unclear":false,"comment":"","family":""}},"vehicle":{"35":[{"year_hidden":false,"brand_info":"1.3 л","sum_rent_comment":"","year":"2008","brand_info_hidden":false,"brand_info_unclear":false,"sum_rent":"","sum":"","brand":"Suzuki SX4","sum_comment":"","brand_unclear":false,"brand_hidden":false}]},"id":"vulyk_93_87","declaration":{"additional_info_text":"","notfull_lostpages":"","date":"2015-03-13T00:00:00","notfull":"","additional_info":"","url":"http://static.declarations.com.ua/declarations/chosen_ones/judges_batch/3533_bilinska_halyna_bohdanivna.pdf"},"liabilities":{"54":{"sum_foreign_comment":"","sum":"5025.25","sum_hidden":false,"sum_comment":"","sum_foreign":""},"55":{"sum_foreign_comment":"","sum":"","sum_comment":"","sum_foreign":""},"56":{"sum_foreign_comment":"","sum":"6116.17","sum_comment":"","sum_foreign":""},"57":{"sum_foreign_comment":"","sum":"36707.06","sum_comment":"","sum_hidden":false,"sum_comment_hidden":false,"sum_unclear":false,"sum_foreign":""},"58":{"sum_foreign_comment":"","sum":"","sum_comment":"","sum_comment_unclear":false,"sum_hidden":false,"sum_unclear":false,"sum_foreign":""},"59":{"sum_foreign_comment":"","sum":"","sum_comment":"","sum_foreign":""},"60":{"sum_foreign_comment":"","sum":"","sum_hidden":false,"sum_comment":"","sum_foreign":""},"61":{"sum_foreign_comment":"","sum":"","sum_comment":"","sum_foreign":""},"62":{"sum_foreign_comment":"","sum":"","sum_comment":"","sum_foreign":""},"63":{"sum_foreign_comment":"","sum":"","sum_comment":"","sum_foreign":""},"64":{"sum_foreign_comment":"","sum":"","sum_comment":"","sum_foreign":""}},"ft_src":"36707.06\n5025.25\n6116.17\nЛьвів\nЛьвівська область\nБілінська Галина Богданівна\nголова шевченківського районного суду м. львова\nЛьвівська область\nЗагальний місцевий суд\nГалина\nБілінський В. І., 22. 12. 1996\nДитина\nБілінська Галина Богданівна\nГалина Богданівна Білінська\nГалина Білінська\nБілінська Галина Богданівна\nБілінська\nБогданівна\n1.3 л\nSuzuki SX4\n2008\n486\n1000\n60\n2014\n239928.55\n12180\n252108.55\n1.3 л\nSuzuki SX4\n2008\n486\n1000\n60\nБілінська\nДитина\nБілінський В. І., 22. 12. 1996\nБілінська Галина Богданівна\nГалина Богданівна Білінська\nГалина Білінська\nБілінська Галина Богданівна\nБілінська Галина Богданівна\nЛьвівська область\nЛьвів\nГалина\nБогданівна\nЛьвівська область\nЗагальний місцевий суд\nголова шевченківського районного суду м. львова\n36707.06\n5025.25\n6116.17\n239928.55\n252108.55\n12180\n2014\n36707.06\n5025.25\n6116.17\nДитина\nБілінський В. І., 22. 12. 1996\nБілінська\nБогданівна\nЛьвівська область\nЛьвів\nЛьвівська область\nЗагальний місцевий суд\nголова шевченківського районного суду м. львова\nБілінська Галина Богданівна\nБілінська Галина Богданівна\nГалина Богданівна Білінська\nГалина Білінська\nБілінська Галина Богданівна\nГалина\nSuzuki SX4\n1.3 л\n2008\n12180\n252108.55\n239928.55\n60\n486\n1000\n2014","general":{"inn":"","inn_hidden":true,"last_name":"Білінська","post":{"post_unclear":false,"region_unclear":false,"region":"Львівська область","candidate":"","post":"голова шевченківського районного суду м. львова","office":"Загальний місцевий суд","office_unclear":false},"name":"Галина","full_name":"Білінська Галина Богданівна","family_raw":"","addresses":[{"place_district":"","place_city_hidden":false,"place_city":"Львів","place_city_type_hidden":false,"place_district_hidden":false,"place_city_type":"Місто","place_address_hidden":true,"place_address":"","place_hidden":false,"place":"Львівська область"}],"family":[{"inn":"","relations":"Дитина","relations_hidden":false,"inn_hidden":true,"relations_other":"","name_hidden":false,"family_name":"Білінський В. І., 22. 12. 1996","name_unclear":false}],"full_name_suggest":{"output":"Білінська Галина Богданівна","input":["Білінська Галина Богданівна","Галина Богданівна Білінська","Галина Білінська"]},"patronymic":"Богданівна"},"source":"VULYK","estate":{"23":[{"space_unclear":false,"costs":"","costs_comment":"","address_hidden":true,"region_hidden":true,"space_comment":"","space":"486","address":"","region":"","costs_rent_comment":"","space_comment_unclear":false,"space_units":"м²","costs_rent":""},{"costs_rent":"","region":"","costs":"","costs_rent_comment":"","costs_comment":"","region_hidden":true,"space_comment":"","space_units":"м²","space":"1000","address":""}],"25":[{"space_hidden":false,"costs":"","costs_comment":"","address_hidden":true,"region_hidden":true,"space_comment":"","space_unclear":false,"space":"60","address":"","costs_rent_comment_unclear":false,"region":"","costs_rent_comment":"","space_units":"м²","costs_rent":""}]},"intro":{"declaration_year":"2014","isnotdeclaration":""}}