{"income":{"5":{"family_comment":"","value":"223247.04","family":"58195.37","comment":""},"6":{"family_comment":"","value":"209849.04","family":"58195.37","comment":"","family_comment_unclear":false},"7":{"value":"","comment_hidden":false,"family_comment":"","source_name":"","family":"","comment":"","source_name_hidden":false},"8":{"family_comment":"","value":"","family":"","comment":""},"9":{"family_comment":"","value":"","family":"","comment":""},"10":{"value":"13398","value_unclear":false,"value_hidden":false,"family_comment":"","family":"","comment":""},"11":{"family_comment":"","value":"","family":"","comment":""},"12":{"family_comment":"","value":"","family":"","comment":""},"13":{"family_comment":"","value":"","family":"","comment":""},"14":{"family_comment":"","value":"","family":"","comment":""},"15":{"family_comment":"","value":"","family":"","comment":""},"16":{"family_comment":"","value":"","family":"","comment":""},"17":{"family_comment":"","value":"","family":"","comment":""},"18":{"family_comment":"","value":"","family":"","comment":""},"19":{"family_comment":"","value":"","family":"","comment":""},"20":{"family_comment":"","value":"","comment_unclear":false,"family":"","comment":""}},"vehicle":{"35":[{"brand_info":"2500 куб. см.","sum_rent_comment":"","brand":"Mitsubishi Pajero Sport","sum_comment":"","brand_unclear":false,"year":"2011","brand_info_unclear":false,"year_unclear":false,"sum":"","sum_rent":""}]},"id":"vulyk_86_12","declaration":{"additional_info_text":"","notfull_lostpages":"","date":"2015-03-18T00:00:00","notfull":"","additional_info":"","url":"http://static.declarations.com.ua/declarations/chosen_ones/judges_batch/2715_barkov_viktor_mykolaiovych.pdf"},"liabilities":{"54":{"sum_foreign_comment":"","sum":"","sum_comment":"","sum_unclear":false,"sum_foreign":""},"55":{"sum_foreign_comment":"","sum":"","sum_comment":"","sum_foreign":""},"56":{"sum_foreign_comment":"","sum":"","sum_hidden":false,"sum_comment":"","sum_foreign":""},"57":{"sum_foreign_comment":"","sum":"112131.73","sum_comment":"","sum_unclear":false,"sum_foreign":""},"58":{"sum_foreign_comment":"","sum":"16368.27","sum_comment":"","sum_unclear":false,"sum_foreign":""},"59":{"sum_foreign_comment":"","sum":"","sum_comment":"","sum_foreign":""},"60":{"sum_foreign_comment":"","sum_comment_hidden":false,"sum":"","sum_comment":"","sum_foreign":""},"61":{"sum_foreign_comment":"","sum":"","sum_comment":"","sum_foreign":""},"62":{"sum_foreign_comment":"","sum":"","sum_comment":"","sum_foreign":""},"63":{"sum_foreign_comment":"","sum":"","sum_comment":"","sum_foreign":""},"64":{"sum_foreign_comment":"","sum":"","sum_comment":"","sum_foreign":""}},"ft_src":"112131.73\n16368.27\nсуддя апеляційного суду донецької області\nДонецька область\nЗагальний апеляційний суд\nВіктор\nБаркова В. С\nПодружжя\nБарков М. В\nДитина\nБаркова М. В\nДитина\nМиколайович\nБарков Віктор Миколайович\nВіктор Миколайович Барков\nВіктор Барков\nБарков Віктор Миколайович\nБарков Віктор Миколайович\nБарков\n2500 куб. см.\nMitsubishi Pajero Sport\n2011\n500\n45.6\n98\n2014\n58195.37\n209849.04\n13398\n58195.37\n223247.04\n2500 куб. см.\n2011\nMitsubishi Pajero Sport\n2014\nБарков Віктор Миколайович\nВіктор Миколайович Барков\nВіктор Барков\nБарков Віктор Миколайович\nБарков Віктор Миколайович\nПодружжя\nБаркова В. С\nДитина\nБарков М. В\nБаркова М. В\nДитина\nВіктор\nБарков\nЗагальний апеляційний суд\nДонецька область\nсуддя апеляційного суду донецької області\nМиколайович\n16368.27\n112131.73\n209849.04\n58195.37\n223247.04\n58195.37\n13398\n500\n45.6\n98\n16368.27\n112131.73\nБаркова В. С\nПодружжя\nБарков М. В\nДитина\nДитина\nБаркова М. В\nМиколайович\nБарков\nВіктор\nБарков Віктор Миколайович\nВіктор Миколайович Барков\nВіктор Барков\nБарков Віктор Миколайович\nДонецька область\nЗагальний апеляційний суд\nсуддя апеляційного суду донецької області\nБарков Віктор Миколайович\n2011\n2500 куб. см.\nMitsubishi Pajero Sport\n13398\n58195.37\n223247.04\n58195.37\n209849.04\n98\n500\n45.6\n2014","general":{"inn":"","name":"Віктор","patronymic_unclear":false,"family":[{"inn":"","inn_hidden":true,"relations_hidden":false,"family_name":"Баркова В. С","relations_other":"","relations":"Подружжя","name_hidden":false,"name_unclear":false},{"inn":"","relations":"Дитина","relations_other":"","inn_hidden":false,"family_name":"Барков М. В","name_hidden":false,"name_unclear":false},{"inn":"","family_name":"Баркова М. В","relations":"Дитина","inn_hidden":false,"name_unclear":false}],"patronymic":"Миколайович","inn_hidden":true,"family_raw":"","inn_unclear":false,"post":{"post_unclear":false,"post":"суддя апеляційного суду донецької області","candidate":"","office_hidden":false,"region":"Донецька область","office":"Загальний апеляційний суд","office_unclear":false,"region_hidden":false},"full_name":"Барков Віктор Миколайович","addresses":[{"place_district":"","place_unclear":false,"place_city":"","place_city_type_hidden":false,"place_district_hidden":false,"place_city_type":"","place_city_hidden":true,"place_address_hidden":true,"place_address":"","place_hidden":true,"place":""}],"last_name":"Барков","full_name_suggest":{"output":"Барков Віктор Миколайович","input":["Барков Віктор Миколайович","Віктор Миколайович Барков","Віктор Барков"]}},"source":"VULYK","estate":{"23":[{"costs":"","costs_comment":"","address_hidden":false,"region_hidden":true,"space_comment":"","space":"500","address":"","region":"","address_unclear":false,"costs_rent_comment":"","space_units":"м²","costs_rent":""}],"25":[{"space_unclear":false,"costs":"","costs_comment":"","address_hidden":false,"region_hidden":true,"space_comment":"","space_hidden":false,"space":"98","address":"","region":"","address_unclear":false,"costs_rent_comment":"","space_units":"м²","costs_rent":""}],"28":[{"costs":"","costs_comment":"","address_hidden":false,"region_hidden":true,"space_comment":"","space":"45.6","address":"","region":"","address_unclear":false,"costs_rent_comment":"","space_units":"м²","costs_rent":""}]},"intro":{"declaration_year":"2014","declaration_year_unclear":false}}