{"id":"vulyk_104_85","ft_src":"Укрсиббанк\n4628\n1200\nособисті\n20000\n33.4\nна підставі рішення Європейського суду\n1282694\n93.8\n2015\n253987\n329776\nкошти отримані, в кредит та  розстрочку\n75789\n4628\nУкрсиббанк\n2015\nІнше\nБондаренко О. О. 13. 01. 1977\nплемінниця\nКасьяненко\nКасьяненко Лілія Іванівна\nЛілія Іванівна Касьяненко\nЛілія Касьяненко\nКасьяненко Лілія Іванівна\nКасьяненко Лілія Іванівна\nЛілія\nІванівна\nЗагальний апеляційний суд\nсуддя апеляційного суду київської області\nКиївська область\n2961\n37048\n253987\nкошти отримані, в кредит та  розстрочку\n75789\n329776\n1200\n20000\n33.4\nособисті\n1282694\nна підставі рішення Європейського суду\n93.8\n2961\n37048\nІнше\nБондаренко О. О. 13. 01. 1977\nплемінниця\nІванівна\nКасьяненко\nсуддя апеляційного суду київської області\nЗагальний апеляційний суд\nКиївська область\nКасьяненко Лілія Іванівна\nКасьяненко Лілія Іванівна\nЛілія Іванівна Касьяненко\nЛілія Касьяненко\nКасьяненко Лілія Іванівна\nЛілія","estate":{"23":[{"address":"","space_units":"м²","space_hidden":false,"space_comment":"","region_hidden":true,"costs_comment":"","address_hidden":false,"space":"1200","space_comment_unclear":false,"costs_rent_comment":"","costs":"","region":"","costs_rent":""}],"25":[{"costs_unclear":false,"address":"","space_units":"м²","space_comment":"","region_hidden":true,"costs_comment":"особисті","address_hidden":false,"space":"33.4","space_comment_unclear":false,"costs_rent_comment":"","costs":"20000","region":"","costs_rent":""},{"costs":"1282694","costs_unclear":false,"address":"","space_units":"м²","costs_rent_comment":"","space":"93.8","space_comment":"","costs_comment":"на підставі рішення Європейського суду","region":"","space_comment_unclear":false,"costs_rent":""}]},"source":"VULYK","income":{"5":{"family_comment":"","value":"329776","family":"","comment":""},"6":{"family_comment":"","value":"253987","family":"","comment":"","value_unclear":false},"7":{"source_name_hidden":false,"family_comment":"","comment":"","family":"","value":"","source_name":""},"8":{"family_comment":"","value":"","family":"","comment":""},"9":{"family_comment":"","value":"","family":"","comment":""},"10":{"family_comment":"","value":"","family":"","comment":""},"11":{"family_comment":"","value":"","family":"","comment":"","comment_hidden":false},"12":{"family_comment":"","value":"","family":"","comment":""},"13":{"family_comment":"","value":"","family":"","comment":""},"14":{"family_comment":"","value":"","family":"","comment":""},"15":{"family_comment":"","family":"","comment":"","value_unclear":false,"family_unclear":false,"value":""},"16":{"family_comment":"","value":"","family":"","comment":""},"17":{"family_comment":"","value":"","family":"","comment":""},"18":{"family_comment":"","value":"","family":"","comment":""},"19":{"family_comment":"","value":"","family":"","comment":""},"20":{"family_comment":"","comment_unclear":false,"value":"75789","family":"","comment":"кошти отримані, в кредит та  розстрочку"}},"banks":{"45":[{"sum_units":"UAH","sum_comment":"Укрсиббанк","sum_foreign_units":"UAH","sum_hidden":false,"sum":"4628","sum_foreign_comment":"","sum_foreign":"","sum_unclear":false,"sum_foreign_hidden":false,"sum_comment_hidden":false}]},"declaration":{"additional_info_text":"","additional_info":"","date":"2016-03-31T00:00:00","url":"http://static.declarations.com.ua/declarations/chosen_ones/judges_batch/1883_kasianenko_liliia_ivanivna_2015.pdf"},"general":{"inn":"","addresses":[{"place_city_type_hidden":false,"place_city_type":"","place_city_hidden":true,"place_hidden":true,"place_district":"","place_district_hidden":false,"place":"","place_address":"","place_address_hidden":true,"place_city":""}],"last_name":"Касьяненко","full_name":"Касьяненко Лілія Іванівна","family":[{"inn":"","family_name":"Бондаренко О. О. 13. 01. 1977","relations_other":"племінниця","name_unclear":false,"inn_hidden":true,"name_hidden":false,"relations":"Інше"}],"patronymic":"Іванівна","inn_hidden":true,"name":"Лілія","post":{"office":"Загальний апеляційний суд","region_unclear":false,"post":"суддя апеляційного суду київської області","region":"Київська область","office_unclear":false},"family_raw":"","full_name_suggest":{"input":["Касьяненко Лілія Іванівна","Лілія Іванівна Касьяненко","Лілія Касьяненко"],"output":"Касьяненко Лілія Іванівна"}},"liabilities":{"54":{"sum_comment":"","sum_hidden":false,"sum":"","sum_foreign_comment":"","sum_foreign":"","sum_unclear":false,"sum_foreign_hidden":false,"sum_comment_hidden":false},"55":{"sum_comment":"","sum_foreign_comment":"","sum_foreign":"","sum":""},"56":{"sum_comment":"","sum_foreign_comment":"","sum_foreign":"","sum_unclear":false,"sum":""},"57":{"sum_comment_unclear":false,"sum_comment":"","sum":"37048","sum_foreign_comment":"","sum_foreign":"","sum_foreign_hidden":false,"sum_comment_hidden":false},"58":{"sum_comment":"","sum_foreign_comment":"","sum_foreign":"","sum_unclear":false,"sum":"2961"},"59":{"sum_comment":"","sum_foreign_comment":"","sum_foreign":"","sum":""},"60":{"sum_comment":"","sum":"","sum_foreign_comment":"","sum_foreign":"","sum_foreign_hidden":false,"sum_comment_hidden":false},"61":{"sum_comment":"","sum_foreign_comment":"","sum_foreign":"","sum":""},"62":{"sum_comment":"","sum_foreign_comment":"","sum_foreign":"","sum":""},"63":{"sum_comment":"","sum_foreign_comment":"","sum_foreign":"","sum":""},"64":{"sum_comment":"","sum_foreign_comment":"","sum_foreign":"","sum":""}},"intro":{"isnotdeclaration":"","declaration_year":"2015"}}