{"id":"vulyk_109_104","ft_src":"2.0 куб. дм, 149 к. с., 110 кВт , 441.0 см\n2013\nHyundai IX35\nЧовен моторний, 4.92 м\n2013\nFinval 500\nДвигун, 70 к. с\n2013\nYamaha F70\n5500\nНалежить частина у розмірі 17/96\n85.4\n75\n35.8\n55.7\n2015\n176846.13\n50000\n176846.13\n50000\nЧовен моторний, 4.92 м\n2013\nFinval 500\nДвигун, 70 к. с\nYamaha F70\n2013\n2.0 куб. дм, 149 к. с., 110 кВт , 441.0 см\n2013\nHyundai IX35\n2015\nПодружжя\nНікітенко І. О. 09. 03. 1979\nДитина\nНікітенко В. С. 23. 09. 2010\nНікітенко Сергій Валерійович\nСергій Валерійович Нікітенко\nСергій Нікітенко\nНікітенко Сергій Валерійович\nСергій\nНікітенко Сергій Валерійович\nНікітенко\nГосподарський місцевий суд\nХерсонська область\nсуддя господарського суду херсонської області\nВалерійович\n3182.39\n14000\n176846.13\n176846.13\n50000\n50000\n5500\n35.8\n85.4\nНалежить частина у розмірі 17/96\n75\n55.7\n3182.39\n14000\nПодружжя\nНікітенко І. О. 09. 03. 1979\nДитина\nНікітенко В. С. 23. 09. 2010\nСергій\nВалерійович\nНікітенко\nНікітенко Сергій Валерійович\nСергій Валерійович Нікітенко\nСергій Нікітенко\nНікітенко Сергій Валерійович\nХерсонська область\nГосподарський місцевий суд\nсуддя господарського суду херсонської області\nНікітенко Сергій Валерійович","estate":{"23":[{"address":"","space_units":"м²","costs_rent_unclear":false,"costs_comment":"","space_unclear":false,"region_hidden":false,"space_comment":"","address_hidden":false,"costs":"","costs_rent_comment":"","space":"5500","region":"","costs_rent":""}],"24":[{"costs":"","address":"","space_units":"м²","costs_rent_comment":"","space":"35.8","space_comment":"","region_hidden":false,"costs_comment":"","region":"","address_hidden":false,"costs_rent":""}],"25":[{"address":"","space_units":"м²","space_hidden":false,"space_unclear":false,"region_hidden":false,"costs_comment":"","space_comment":"","address_hidden":false,"space":"55.7","costs_rent_comment":"","costs":"","region":"","space_units_hidden":false,"costs_rent":""}],"30":[{"costs_property_comment":"","address":"","space_units":"м²","costs_rent_comment":"","space_hidden":false,"region_hidden":false,"costs_property":"","space_comment":"Належить частина у розмірі 17/96","space":"85.4","address_hidden":false,"costs_rent":""}],"31":[{"costs_property_comment":"","address":"","space_units":"м²","space_hidden":false,"space_comment":"","region_hidden":false,"costs_property":"","region":"","address_hidden":false,"costs_rent_comment":"","space":"75","space_units_hidden":false,"costs_rent":""}]},"vehicle":{"37":[{"sum_comment":"","brand_info":"Човен моторний, 4.92 м","sum":"","sum_rent_comment":"","year":"2013","brand":"Finval 500","sum_rent":""},{"sum_comment":"","brand_info":"Двигун, 70 к. с","sum":"","sum_rent_comment":"","year":"2013","brand":"Yamaha F70","sum_rent":""}],"40":[{"sum_comment":"","brand_info":"2.0 куб. дм, 149 к. с., 110 кВт , 441.0 см","sum":"","sum_rent_comment":"","year":"2013","brand":"Hyundai IX35","sum_rent":"","brand_info_unclear":false}]},"source":"VULYK","income":{"5":{"family_comment":"","value":"176846.13","family":"50000","comment":""},"6":{"family_comment":"","value":"176846.13","family":"","comment":""},"7":{"source_name_hidden":false,"family_comment":"","comment":"","family":"","comment_hidden":false,"value":"","source_name":""},"8":{"family_comment":"","family_hidden":false,"value":"","family":"","comment":""},"9":{"family_comment":"","family":"","comment":"","value_unclear":false,"family_unclear":false,"value":""},"10":{"family_comment":"","value":"","family":"","comment":""},"11":{"family_comment":"","value":"","family":"","comment":""},"12":{"family_comment":"","value":"","family":"","comment":""},"13":{"family_comment":"","value":"","family":"","comment":""},"14":{"family_comment":"","value":"","family":"","comment":""},"15":{"family_comment":"","value":"","family":"","comment":""},"16":{"family_comment":"","value":"","family":"50000","comment":""},"17":{"family_comment":"","value":"","family":"","comment":""},"18":{"family_comment":"","value":"","family":"","comment":""},"19":{"family_comment":"","value":"","family":"","comment":""},"20":{"family_comment":"","family":"","comment":"","value_unclear":false,"family_hidden":false,"value":""}},"general":{"family_raw":"","name":"Сергій","full_name_suggest":{"input":["Нікітенко Сергій Валерійович","Сергій Валерійович Нікітенко","Сергій Нікітенко"],"output":"Нікітенко Сергій Валерійович"},"patronymic":"Валерійович","inn_hidden":true,"inn":"","inn_unclear":false,"last_name":"Нікітенко","full_name":"Нікітенко Сергій Валерійович","family":[{"inn":"","family_name":"Нікітенко І. О. 09. 03. 1979","relations_hidden":false,"name_unclear":false,"relations":"Подружжя","inn_hidden":true,"name_hidden":false,"relations_other":""},{"inn":"","family_name":"Нікітенко В. С. 23. 09. 2010","relations_other":"","name_unclear":false,"inn_hidden":false,"name_hidden":false,"relations":"Дитина"}],"post":{"office":"Господарський місцевий суд","post":"суддя господарського суду херсонської області","office_unclear":false,"region_hidden":false,"region":"Херсонська область","office_hidden":false,"region_unclear":false},"name_hidden":false},"liabilities":{"54":{"sum_comment":"","sum_hidden":false,"sum":"","sum_foreign_comment":"","sum_foreign":"","sum_unclear":false,"sum_comment_hidden":false},"55":{"sum_comment":"","sum_comment_unclear":false,"sum_foreign_comment":"","sum":"","sum_foreign":""},"56":{"sum_comment":"","sum_foreign_comment":"","sum_foreign":"","sum":""},"57":{"sum_comment":"","sum_foreign_comment":"","sum_foreign":"","sum":"14000","sum_comment_hidden":false},"58":{"sum_comment":"","sum_foreign_comment":"","sum_foreign":"","sum":"3182.39","sum_comment_hidden":false},"59":{"sum_comment":"","sum_foreign_comment":"","sum_foreign":"","sum":""},"60":{"sum_comment":"","sum_foreign_comment":"","sum_foreign":"","sum":""},"61":{"sum_comment":"","sum_foreign_comment":"","sum_foreign":"","sum":""},"62":{"sum_comment":"","sum_foreign_comment":"","sum_foreign":"","sum":""},"63":{"sum_comment":"","sum_foreign_comment":"","sum_foreign":"","sum":""},"64":{"sum_comment":"","sum_foreign_comment":"","sum_foreign":"","sum":""}},"declaration":{"notfull_lostpages":"","additional_info_text":"","additional_info":"","date":"2016-03-31T00:00:00","notfull":"","url":"http://static.declarations.com.ua/declarations/chosen_ones/judges_batch/2561_nikitenko_serhii_valeriiovych_2015.pdf"},"intro":{"isnotdeclaration":"","declaration_year":"2015"}}