{"income":{"5":{"family_comment":"","value":"232263","family":"","comment":""},"6":{"family_comment":"","value":"232263","value_unclear":false,"family":"","comment":""},"7":{"value":"","family_comment":"","source_name":"","family":"","comment":"","source_name_hidden":false},"8":{"family_comment":"","value":"","family":"","comment":""},"9":{"family_comment":"","value":"","family":"","comment":""},"10":{"family_comment":"","value":"","family":"","comment":""},"11":{"family_comment":"","value":"","comment_hidden":false,"family":"","comment":""},"12":{"family_comment":"","value":"","family":"","comment":""},"13":{"family_comment":"","value":"","family":"","comment":""},"14":{"family_comment":"","value":"","family":"","comment":""},"15":{"value":"","family_comment":"","value_unclear":false,"family_unclear":false,"family":"","comment":""},"16":{"family_comment":"","value":"","family":"","comment":""},"17":{"family_comment":"","value":"","family":"","comment":""},"18":{"family_comment":"","value":"","family":"","comment":""},"19":{"family_comment":"","value":"","family":"","comment":""},"20":{"family_comment":"","value":"","comment_unclear":false,"family":"","comment":""}},"id":"vulyk_104_10","declaration":{"date":"2016-03-24T00:00:00","additional_info_text":"","additional_info":"","url":"http://static.declarations.com.ua/declarations/chosen_ones/judges_batch/1808_zubets_larysa_petrivna_2015.pdf"},"liabilities":{"54":{"sum_foreign_comment":"","sum_foreign_hidden":false,"sum_comment":"","sum_hidden":false,"sum_comment_hidden":false,"sum_unclear":false,"sum":"","sum_foreign":""},"55":{"sum_foreign_comment":"","sum":"","sum_comment":"","sum_foreign":""},"56":{"sum_foreign_comment":"","sum":"","sum_comment":"","sum_unclear":false,"sum_foreign":""},"57":{"sum_foreign_comment":"","sum_foreign_hidden":false,"sum_comment":"","sum_comment_unclear":false,"sum_comment_hidden":false,"sum":"","sum_foreign":""},"58":{"sum_foreign_comment":"","sum":"","sum_comment":"","sum_unclear":false,"sum_foreign":""},"59":{"sum_foreign_comment":"","sum":"","sum_comment":"","sum_foreign":""},"60":{"sum_foreign_comment":"","sum_foreign_hidden":false,"sum_comment":"","sum_comment_hidden":false,"sum":"","sum_foreign":""},"61":{"sum_foreign_comment":"","sum":"","sum_comment":"","sum_foreign":""},"62":{"sum_foreign_comment":"","sum":"","sum_comment":"","sum_foreign":""},"63":{"sum_foreign_comment":"","sum":"","sum_comment":"","sum_foreign":""},"64":{"sum_foreign_comment":"","sum":"","sum_comment":"","sum_foreign":""}},"ft_src":"Зубець Лариса Петрівна\nсуддя київського апеляційного господарського суду\nм. Київ\nАпеляційний господарський суд\nЛариса\nЗубець Лариса Петрівна\nЛариса Петрівна Зубець\nЛариса Зубець\nЗубець Лариса Петрівна\nЗубець\nПетрівна\n232263\n232263\n.12\n110\n2015\n232263\n232263\n232263\n232263\nЗубець Лариса Петрівна\nЛариса Петрівна Зубець\nЛариса Зубець\nЗубець Лариса Петрівна\nЗубець Лариса Петрівна\nПетрівна\nЛариса\nЗубець\nАпеляційний господарський суд\nсуддя київського апеляційного господарського суду\nм. Київ\n.12\n110\n2015\nЗубець\nПетрівна\nсуддя київського апеляційного господарського суду\nАпеляційний господарський суд\nм. Київ\nЗубець Лариса Петрівна\nЗубець Лариса Петрівна\nЛариса Петрівна Зубець\nЛариса Зубець\nЗубець Лариса Петрівна\nЛариса\n110\n.12\n2015","general":{"inn":"","inn_hidden":true,"last_name":"Зубець","post":{"region":"м. Київ","region_unclear":false,"post":"суддя київського апеляційного господарського суду","office_unclear":false,"office":"Апеляційний господарський суд"},"name":"Лариса","full_name":"Зубець Лариса Петрівна","family_raw":"","addresses":[{"place_district":"","place_city_hidden":true,"place_city":"","place_city_type_hidden":true,"place_district_hidden":true,"place_city_type":"","place_address_hidden":true,"place_address":"","place_hidden":true,"place":""}],"full_name_suggest":{"output":"Зубець Лариса Петрівна","input":["Зубець Лариса Петрівна","Лариса Петрівна Зубець","Лариса Зубець"]},"patronymic":"Петрівна"},"source":"VULYK","estate":{"23":[{"space_hidden":false,"costs":"","costs_comment":"","address_hidden":true,"region_hidden":true,"space_comment":"","space":".12","address":"","region":"","costs_rent_comment":"","space_comment_unclear":false,"space_units":"га","costs_rent":""}],"25":[{"costs":"","costs_comment":"","address_hidden":true,"region_hidden":true,"space_comment":"","space":"110","address":"","costs_unclear":false,"region":"","costs_rent_comment":"","space_comment_unclear":false,"space_units":"м²","costs_rent":""}]},"intro":{"declaration_year":"2015","isnotdeclaration":""}}