{"income":{"5":{"family_comment":"","value":"259385.66","family":"11388","comment":""},"6":{"family_comment":"","value":"245987.66","value_unclear":false,"family":"","comment":""},"7":{"value":"","family_comment":"","source_name":"","family":"","comment":"","source_name_hidden":false},"8":{"family_comment":"","value":"","family":"","comment":""},"9":{"family_comment":"","value":"","family":"","comment":""},"10":{"family_comment":"","value":"13398","family":"","comment":""},"11":{"family_comment":"","value":"","comment_hidden":false,"family":"","comment":""},"12":{"family_comment":"","value":"","family":"","comment":""},"13":{"family_comment":"","value":"","family":"","comment":""},"14":{"family_comment":"","value":"","family":"","comment":""},"15":{"value":"","family_comment":"","value_unclear":false,"family_unclear":false,"family":"","comment":""},"16":{"family_comment":"","value":"","family":"","comment":""},"17":{"family_comment":"","value":"","family":"","comment":""},"18":{"family_comment":"","value":"","family":"","comment":""},"19":{"family_comment":"","value":"","family":"","comment":""},"20":{"family_comment":"","value":"","comment_unclear":false,"family":"11388","comment":""}},"vehicle":{"35":[{"brand_info":"1598 куб. см., 105 кВт","sum_rent_comment":"","brand":"Skoda Octavia Tour","sum_comment":"","year":"2008","brand_hidden":false,"brand_info_unclear":false,"sum":"","sum_rent":""}],"36":[{"brand_info":"СПС 8 С, об'єм двигуна 2148 куб. см.","sum":"","brand":"Mercedes-Benz 313 CDI","sum_comment":"","year":"2003","brand_hidden":false,"sum_rent_comment":"","sum_rent":""}],"39":[{"brand_info":"Причіп легковий","sum_rent_comment":"","brand":"ХТ 81024","sum_comment":"","brand_unclear":false,"year":"1992","brand_hidden":false,"brand_info_unclear":false,"sum":"","sum_rent":""}]},"id":"vulyk_104_168","declaration":{"date":"2016-03-23T00:00:00","additional_info_text":"","additional_info":"","url":"http://static.declarations.com.ua/declarations/chosen_ones/judges_batch/1966_remez_petro_mykolaiovych_2015.pdf"},"liabilities":{"54":{"sum_foreign_comment":"","sum_unclear":false,"sum":"","sum_comment":"","sum_hidden":false,"sum_comment_hidden":false,"sum_foreign_hidden":false,"sum_foreign":""},"55":{"sum_foreign_comment":"","sum":"","sum_comment":"","sum_foreign":""},"56":{"sum_foreign_comment":"","sum":"25000","sum_comment":"","sum_unclear":false,"sum_foreign":""},"57":{"sum_foreign_comment":"","sum":"","sum_comment":"","sum_comment_unclear":false,"sum_comment_hidden":false,"sum_foreign_hidden":false,"sum_foreign":""},"58":{"sum_foreign_comment":"","sum":"","sum_comment":"","sum_unclear":false,"sum_foreign":""},"59":{"sum_foreign_comment":"","sum":"","sum_comment":"","sum_foreign":""},"60":{"sum_foreign_comment":"","sum":"","sum_comment":"","sum_comment_hidden":false,"sum_foreign_hidden":false,"sum_foreign":""},"61":{"sum_foreign_comment":"","sum":"","sum_comment":"","sum_foreign":""},"62":{"sum_foreign_comment":"","sum":"","sum_comment":"","sum_foreign":""},"63":{"sum_foreign_comment":"","sum":"","sum_comment":"","sum_foreign":""},"64":{"sum_foreign_comment":"","sum":"","sum_comment":"","sum_foreign":""}},"ft_src":"ХТ 81024\nПричіп легковий\n1992\n2008\nSkoda Octavia Tour\n1598 куб. см., 105 кВт\nMercedes-Benz 313 CDI\n2003\nСПС 8 С, об'єм двигуна 2148 куб. см.\n403.3\n2889\n64.36\n2015\n245987.66\n13398\n11388\n259385.66\n11388\n1598 куб. см., 105 кВт\nSkoda Octavia Tour\n2008\nПричіп легковий\nХТ 81024\n1992\nСПС 8 С, об'єм двигуна 2148 куб. см.\nMercedes-Benz 313 CDI\n2003\n2015\nПодружжя\nРемез Л. В. 12. 11. 1958\nРемез\nРемез Петро Миколайович\nПетро Миколайович Ремез\nПетро Ремез\nРемез Петро Миколайович\nРемез Петро Миколайович\nКіровоградська область\nКіровоград\nПетро\nМиколайович\nЗагальний апеляційний суд\nсекретар судової палати у кримінальних справах апеляційного суду кіровоградської області\nКіровоградська область\n25000\n245987.66\n11388\n259385.66\n11388\n13398\n2889\n403.3\n64.36\n25000\nПодружжя\nРемез Л. В. 12. 11. 1958\nКіровоградська область\nКіровоград\nМиколайович\nРемез\nсекретар судової палати у кримінальних справах апеляційного суду кіровоградської області\nЗагальний апеляційний суд\nКіровоградська область\nРемез Петро Миколайович\nРемез Петро Миколайович\nПетро Миколайович Ремез\nПетро Ремез\nРемез Петро Миколайович\nПетро","general":{"inn":"","inn_hidden":true,"last_name":"Ремез","post":{"region":"Кіровоградська область","office":"Загальний апеляційний суд","post":"секретар судової палати у кримінальних справах апеляційного суду кіровоградської області","office_unclear":false,"region_unclear":false},"name":"Петро","full_name":"Ремез Петро Миколайович","family_raw":"","addresses":[{"place_district":"","place_address_hidden":true,"place_city":"Кіровоград","place_address":"","place_district_hidden":false,"place_city_type":"Місто","place_city_hidden":false,"place_city_type_hidden":false,"place_hidden":false,"place":"Кіровоградська область"}],"family":[{"inn":"","relations":"Подружжя","relations_other":"","inn_hidden":true,"family_name":"Ремез Л. В. 12. 11. 1958","name_hidden":false,"name_unclear":false}],"full_name_suggest":{"output":"Ремез Петро Миколайович","input":["Ремез Петро Миколайович","Петро Миколайович Ремез","Петро Ремез"]},"patronymic":"Миколайович"},"source":"VULYK","estate":{"25":[{"costs":"","costs_comment":"","address_hidden":false,"region_hidden":true,"space_comment":"","space":"64.36","address":"","costs_unclear":false,"region":"","costs_rent_comment":"","space_comment_unclear":false,"space_units":"м²","costs_rent":""}],"29":[{"space_unclear":false,"address_hidden":false,"region_hidden":true,"space_comment":"","space":"2889","address":"","region":"","costs_property":"","costs_rent_comment":"","space_units":"м²","costs_property_comment":"","costs_rent":""}],"30":[{"space_hidden":false,"address_hidden":false,"region_hidden":true,"space_comment":"","space":"403.3","address":"","region":"","costs_property":"","costs_rent_comment":"","space_comment_unclear":false,"space_units":"м²","costs_property_comment":"","costs_rent":""}]},"intro":{"declaration_year":"2015","isnotdeclaration":""}}