{"income":{"5":{"family_comment":"","value":"259861.77","family":"","comment":""},"6":{"family_comment":"","value":"246226.57","family_hidden":false,"comment":"","family":""},"7":{"family_comment":"","value":"","source_name":"","family":"","comment":""},"8":{"family_comment":"","value":"","family":"","comment":""},"9":{"value":"237.2","value_unclear":false,"family_hidden":false,"family_comment":"","family":"","comment":""},"10":{"value":"13398","family_comment":"","family_hidden":false,"value_hidden":false,"family_unclear":false,"family":"","comment":""},"11":{"family_comment":"","value":"","family":"","comment":""},"12":{"family_comment":"","value":"","family":"","comment":""},"13":{"family_comment":"","value":"","family":"","comment":""},"14":{"family_comment":"","value":"","family":"","comment":""},"15":{"family_comment":"","value":"","family":"","comment":""},"16":{"family_comment":"","value":"","family":"","comment":""},"17":{"family_comment":"","value":"","family":"","comment":""},"18":{"family_comment":"","value":"","family":"","comment":""},"19":{"family_comment":"","value":"","family":"","comment":""},"20":{"value":"","comment_unclear":false,"family_comment":"","family":"","comment":"","family_comment_unclear":false}},"vehicle":{"35":[{"brand_info":"2.4 л","sum_rent_comment":"","brand":"Toyota Camry","sum_comment":"","brand_unclear":false,"year":"2002","brand_hidden":false,"brand_info_unclear":false,"sum":"","sum_rent":"","sum_unclear":false}],"40":[{"brand_info":"2.2 л","sum_rent_comment":"","brand":"Toyota Camry","sum_comment":"","year":"1991","brand_info_unclear":false,"sum":"","sum_rent":""}]},"id":"vulyk_75_18","declaration":{"additional_info_text":"","notfull_lostpages":"3, 8","date":"2015-03-30T00:00:00","notfull":"1","additional_info":"","url":"http://static.declarations.com.ua/declarations/chosen_ones/judges_batch/1917_holovei_viktor_mykolaiovych.pdf"},"liabilities":{"54":{"sum_foreign_comment":"","sum":"","sum_comment":"","sum_foreign":""},"55":{"sum_foreign_comment":"","sum":"","sum_comment":"","sum_foreign":""},"56":{"sum_foreign_comment":"","sum":"","sum_comment":"","sum_foreign":""},"57":{"sum_foreign_comment":"","sum":"","sum_comment":"","sum_foreign":""},"58":{"sum_foreign_comment":"","sum":"","sum_comment":"","sum_foreign":""},"59":{"sum_foreign_comment":"","sum":"","sum_comment":"","sum_comment_unclear":false,"sum_unclear":false,"sum_foreign":""},"60":{"sum_foreign_comment":"","sum":"","sum_comment":"","sum_foreign":""},"61":{"sum_foreign_comment":"","sum":"","sum_comment":"","sum_foreign":""},"62":{"sum_foreign_comment":"","sum":"","sum_comment":"","sum_unclear":false,"sum_foreign":""},"63":{"sum_foreign_comment":"","sum":"","sum_comment":"","sum_foreign":""},"64":{"sum_foreign_comment":"","sum":"","sum_comment":"","sum_foreign":""}},"ft_src":"1\n3, 8\nГоловей Віктор Миколайович\nсуддя одеського апеляційного господарського суду\nОдеська область\nАпеляційний господарський суд\nВіктор\nГоловей Л. А\nПодружжя\nГоловей Віктор Миколайович\nВіктор Миколайович Головей\nВіктор Головей\nГоловей Віктор Миколайович\nГоловей\nМиколайович\nToyota Camry\n2.4 л\n2002\n2.2 л\n1991\nToyota Camry\n.1\n4.64\n54.8\nжитл. площ. 1/2\n62.1\n3, 8\n1\n2014\n246226.57\n237.2\n13398\n259861.77\n2.4 л\n2002\nToyota Camry\n2.2 л\n1991\nToyota Camry\n3, 8\n1\n2014\nГоловей\nМиколайович\nПодружжя\nГоловей Л. А\nГоловей Віктор Миколайович\nВіктор Миколайович Головей\nВіктор Головей\nГоловей Віктор Миколайович\nВіктор\nГоловей Віктор Миколайович\nАпеляційний господарський суд\nсуддя одеського апеляційного господарського суду\nОдеська область\n246226.57\n259861.77\n237.2\n13398\n.1\n4.64\n54.8\n62.1\nжитл. площ. 1/2\nГоловей Л. А\nПодружжя\nГоловей\nМиколайович\nсуддя одеського апеляційного господарського суду\nОдеська область\nАпеляційний господарський суд\nГоловей Віктор Миколайович\nГоловей Віктор Миколайович\nВіктор Миколайович Головей\nВіктор Головей\nГоловей Віктор Миколайович\nВіктор\n2002\nToyota Camry\n2.4 л\n1991\n2.2 л\nToyota Camry\n237.2\n13398\n259861.77\n246226.57\n54.8\n.1\n4.64\nжитл. площ. 1/2\n62.1\n2014","general":{"inn":"","inn_hidden":true,"last_name":"Головей","post":{"office":"Апеляційний господарський суд","region":"Одеська область","post":"суддя одеського апеляційного господарського суду"},"name":"Віктор","full_name":"Головей Віктор Миколайович","family_raw":"","addresses":[{"place_district":"","place_address_hidden":true,"place_city":"","place_city_type_hidden":false,"place_district_hidden":true,"place_city_type":"","place_city_hidden":true,"place_address":"","place_hidden":true,"place":""}],"family":[{"inn":"","inn_hidden":true,"relations_hidden":false,"family_name":"Головей Л. А","relations_other":"","relations":"Подружжя","name_hidden":false,"name_unclear":false}],"full_name_suggest":{"output":"Головей Віктор Миколайович","input":["Головей Віктор Миколайович","Віктор Миколайович Головей","Віктор Головей"]},"patronymic":"Миколайович"},"source":"VULYK","estate":{"23":[{"costs":"","costs_comment":"","address_hidden":false,"region_hidden":true,"space_comment":"","space":".1","address":"","region":"","costs_rent_comment":"","space_units":"га","space_units_hidden":false,"costs_rent":""},{"costs_rent":"","region":"","costs":"","costs_rent_comment":"","costs_comment":"","region_hidden":false,"space_comment":"","space_units":"га","space":"4.64","address":""}],"25":[{"space_hidden":false,"costs":"","costs_comment":"","address_hidden":false,"region_hidden":true,"space_comment":"житл. площ. 1/2","space_unclear":false,"space":"62.1","address":"","region":"","costs_rent_comment":"","space_units":"м²","costs_rent":""}],"31":[{"space_unclear":false,"address_hidden":false,"region_hidden":true,"space_comment":"","space":"54.8","address":"","region":"","costs_property":"","costs_rent_comment":"","space_units":"м²","costs_property_comment":"","costs_rent":""}]},"intro":{"declaration_year":"2014","isnotdeclaration":""}}