{"income":{"5":{"value":"319800","family_comment":"","value_unclear":false,"family_hidden":false,"value_hidden":false,"family_unclear":false,"family_comment_hidden":false,"comment":"","family":"27588"},"6":{"value":"261101","family_comment":"","value_unclear":false,"family_hidden":false,"family_unclear":false,"family":"15000","comment":""},"7":{"family_comment":"","value":"","source_name":"","family":"","comment":""},"8":{"family_comment":"","value":"","family":"","comment":""},"9":{"family_comment":"","value":"","family":"","comment":""},"10":{"family_comment":"","family_unclear":false,"value":"","family":"","comment":""},"11":{"family_comment":"","value":"","family":"","comment":""},"12":{"family_comment":"","value":"","family":"","comment":""},"13":{"family_comment":"","value":"","family":"","comment":""},"14":{"family_comment":"","value":"","comment_unclear":false,"family":"","comment":""},"15":{"family_comment":"","value":"","family":"","comment":""},"16":{"family_comment":"","value":"","family":"","comment":""},"17":{"family_comment":"","value":"","family":"","comment":""},"18":{"family_comment":"","value":"","family":"","comment":""},"19":{"family_comment":"","value":"","family":"","comment":""},"20":{"value":"58699","family_comment":"","value_unclear":false,"family_unclear":false,"comment_unclear":false,"comment":"","family":"12588"}},"vehicle":{"40":[{"brand_info":"1.5","sum_rent_comment":"","brand":"ЗАЗ Vida","sum_comment":"","year":"2012","brand_hidden":false,"brand_info_hidden":false,"year_unclear":false,"sum":"","sum_rent":""}]},"id":"vulyk_35_80","banks":{"45":[{"sum_foreign_comment":"","sum_units":"UAH","sum_comment":"","sum_comment_unclear":false,"sum_hidden":false,"sum_foreign_units":"UAH","sum_comment_hidden":false,"sum_unclear":false,"sum":"","sum_foreign":""},{"sum_foreign_comment":"","sum_units":"","sum_comment":"","sum_foreign_units":"","sum":"","sum_foreign":""},{"sum_foreign_comment":"","sum_units":"","sum_comment":"","sum_foreign_units":"","sum":"","sum_foreign":""}],"46":[{"sum_foreign_comment":"","sum_units":"UAH","sum_comment":"","sum_hidden":false,"sum_foreign_units":"UAH","sum_comment_hidden":false,"sum":"","sum_foreign":""},{"sum_foreign_comment":"","sum_units":"","sum_comment":"","sum_foreign_units":"","sum":"","sum_foreign":""}],"47":[{"sum_foreign_comment":"","sum_units":"UAH","sum_comment":"","sum_foreign_units":"UAH","sum":"","sum_foreign":""}],"48":[{"sum_foreign_comment":"","sum_units":"UAH","sum_comment":"","sum_foreign_units":"UAH","sum":"","sum_foreign":""}],"49":[{"sum_foreign_comment":"","sum_units":"UAH","sum_comment":"","sum_hidden":false,"sum_foreign_units":"UAH","sum":"","sum_foreign":""}],"50":[{"sum_foreign_comment":"","sum_units":"UAH","sum_comment":"","sum_foreign_units":"UAH","sum":"","sum_foreign":""}],"51":[{"sum_foreign_comment":"","sum_units":"UAH","sum_comment":"","sum_comment_unclear":false,"sum_foreign_units":"UAH","sum_comment_hidden":false,"sum":"","sum_foreign":""},{"sum_foreign_comment":"","sum_units":"","sum_comment":"","sum_foreign_units":"","sum":"","sum_foreign":""}],"52":[{"sum_foreign_comment":"","sum_units":"UAH","sum_comment":"","sum_foreign_units":"UAH","sum":"","sum_foreign":""}],"53":[{"sum_foreign_comment":"","sum_units":"UAH","sum_comment":"","sum_foreign_units":"UAH","sum":"","sum_foreign":""}]},"declaration":{"additional_info_text":"","notfull_lostpages":"","date":"2015-03-26T00:00:00","notfull":"","additional_info":"","url":"http://static.declarations.com.ua/declarations/chosen_ones/mega_batch/tomashevskyi_volodymyr_mykolaiovych.pdf"},"liabilities":{"54":{"sum_foreign_comment":"","sum":"","sum_comment":"","sum_comment_unclear":false,"sum_hidden":false,"sum_comment_hidden":false,"sum_unclear":false,"sum_foreign":""},"55":{"sum_foreign_comment":"","sum":"","sum_comment":"","sum_foreign":""},"56":{"sum_foreign_comment":"","sum":"","sum_comment":"","sum_unclear":false,"sum_foreign":""},"57":{"sum_foreign_comment":"","sum":"","sum_comment":"","sum_comment_unclear":false,"sum_hidden":false,"sum_comment_hidden":false,"sum_unclear":false,"sum_foreign":""},"58":{"sum_foreign_comment":"","sum":"","sum_comment":"","sum_hidden":false,"sum_comment_hidden":false,"sum_foreign":""},"59":{"sum_foreign_comment":"","sum":"","sum_comment":"","sum_foreign":""},"60":{"sum_foreign_comment":"","sum_comment_hidden":false,"sum":"","sum_comment":"","sum_foreign":""},"61":{"sum_foreign_comment":"","sum":"","sum_comment":"","sum_foreign":""},"62":{"sum_foreign_comment":"","sum":"","sum_comment":"","sum_foreign":""},"63":{"sum_foreign_comment":"","sum":"","sum_comment":"","sum_hidden":false,"sum_comment_hidden":false,"sum_foreign":""},"64":{"sum_foreign_comment":"","sum":"","sum_comment":"","sum_hidden":false,"sum_comment_hidden":false,"sum_foreign":""}},"ft_src":"суддя жашківського районного суду черкаської області\nЧеркаська область\nЗагальний місцевий суд\nВолодимир\nТомашевська О. П\nПодружжя\nМиколайович\nТомашевський Володимир Миколайович\nВолодимир Миколайович Томашевський\nВолодимир Томашевський\nТомашевський Володимир Миколайович\nТомашевський\nТомашевський Володимир Миколайович\n1.5\nЗАЗ Vida\n2012\n2014\n1.5\n2012\nЗАЗ Vida\n1000\nм. Жашків, садово-огороднє товариство 'Вишенька'\nЧеркаська область\n27\nЧеркаська область\nм. Жашків, вул. Кармелюка 4, кв. 9\nПодружжя\nТомашевська О. П\nТомашевський Володимир Миколайович\nВолодимир Миколайович Томашевський\nВолодимир Томашевський\nТомашевський Володимир Миколайович\nТомашевський Володимир Миколайович\nВолодимир\nТомашевський\nсуддя жашківського районного суду черкаської області\nЗагальний місцевий суд\nЧеркаська область\nМиколайович\n15000\n261101\n12588\n58699\n319800\n27588\n2014\nм. Жашків, садово-огороднє товариство 'Вишенька'\n1000\nЧеркаська область\nм. Жашків, вул. Кармелюка 4, кв. 9\n27\nЧеркаська область\nТомашевська О. П\nПодружжя\nМиколайович\nТомашевський\nВолодимир\nТомашевський Володимир Миколайович\nВолодимир Миколайович Томашевський\nВолодимир Томашевський\nТомашевський Володимир Миколайович\nЧеркаська область\nЗагальний місцевий суд\nсуддя жашківського районного суду черкаської області\nТомашевський Володимир Миколайович\n15000\n261101\n27588\n319800\n12588\n58699\nЗАЗ Vida\n1.5\n2012\n58699\n12588\n319800\n27588\n261101\n15000\nм. Жашків, вул. Кармелюка 4, кв. 9\nЧеркаська область\n27\nм. Жашків, садово-огороднє товариство 'Вишенька'\nЧеркаська область\n1000\n2014","general":{"inn":"","name":"Володимир","patronymic_unclear":false,"last_name_hidden":false,"family":[{"inn":"","inn_hidden":true,"relations_hidden":false,"family_name":"Томашевська О. П","relations_other":"","relations":"Подружжя","name_hidden":true,"name_unclear":false}],"patronymic":"Миколайович","inn_hidden":true,"family_raw":"","last_name":"Томашевський","post":{"post_unclear":false,"region_unclear":false,"post":"суддя жашківського районного суду черкаської області","candidate":"","office_hidden":false,"region":"Черкаська область","post_hidden":true,"office":"Загальний місцевий суд","office_unclear":false},"last_name_unclear":false,"full_name":"Томашевський Володимир Миколайович","addresses":[{"place_district":"","place_city_hidden":true,"place_city":"","place_city_type_hidden":false,"place_district_hidden":true,"place_city_type":"","place_address_hidden":false,"place_address":"","place_hidden":true,"place":""}],"full_name_suggest":{"output":"Томашевський Володимир Миколайович","input":["Томашевський Володимир Миколайович","Володимир Миколайович Томашевський","Володимир Томашевський"]}},"source":"VULYK","estate":{"23":[{"space_unclear":false,"costs":"","costs_comment":"","address_hidden":false,"region_hidden":false,"space_comment":"","space":"1000","address":"м. Жашків, садово-огороднє товариство 'Вишенька'","region":"Черкаська область","address_unclear":false,"costs_rent_comment":"","space_units":"м²","costs_rent":""},{"space_unclear":false,"costs":"","costs_comment":"","address_hidden":false,"region_hidden":false,"space_comment":"","space":"","address":"","region":"","address_unclear":false,"costs_rent_comment":"","space_units":"","costs_rent":""},{"space":"","region":"","costs":"","costs_rent_comment":"","costs_comment":"","address_unclear":false,"space_comment":"","space_units":"","costs_rent":"","address":""},{"costs_rent":"","costs":"","costs_rent_comment":"","costs_comment":"","space_comment":"","space_units":"","space":"","address":""}],"25":[{"space_unclear":false,"costs":"","costs_comment":"","address_hidden":false,"region_hidden":false,"space_comment":"","space_hidden":false,"space":"27","address":"м. Жашків, вул. Кармелюка 4, кв. 9","region":"Черкаська область","address_unclear":false,"costs_rent_comment":"","space_units":"м²","costs_rent":""}]},"intro":{"declaration_year":"2014","isnotdeclaration":"","declaration_year_unclear":false,"declaration_year_hidden":false}}