{"income":{"5":{"family_comment":"","value":"268326","family":"","comment":""},"6":{"family_comment":"","value":"268326","family":"","comment":""},"7":{"value":"","comment_hidden":false,"value_hidden":false,"family_comment":"","source_name":"","family":"","comment":"","source_name_hidden":false},"8":{"family_comment":"","value":"","family":"","comment":""},"9":{"value":"","comment_hidden":false,"family_comment":"","family":"","comment":"","family_comment_unclear":false},"10":{"family_comment":"","value":"","family":"","comment":""},"11":{"family_comment":"","value":"","comment_hidden":false,"family":"","comment":""},"12":{"family_comment":"","value":"","family":"","comment":""},"13":{"family_comment":"","value":"","family":"","comment":""},"14":{"family_comment":"","value":"","family":"","comment":""},"15":{"family_comment":"","value":"","family":"","comment":""},"16":{"family_comment":"","value":"","family":"","comment":""},"17":{"family_comment":"","value":"","family":"","comment":""},"18":{"family_comment":"","value":"","family":"","comment":""},"19":{"family_comment":"","value":"","family":"","comment":""},"20":{"family_comment":"","value":"","comment_hidden":false,"family":"","comment":""}},"id":"vulyk_102_83","banks":{"45":[{"sum_foreign_comment":"","sum_units":"UAH","sum_comment":"","sum_comment_unclear":false,"sum_hidden":false,"sum_foreign_units":"UAH","sum_comment_hidden":true,"sum_unclear":false,"sum":"15582","sum_foreign":""}]},"declaration":{"date":"2016-03-24T00:00:00","additional_info_text":"","additional_info":"","url":"http://static.declarations.com.ua/declarations/chosen_ones/judges_batch/1157_akulova_nina_volodymyrivna.pdf"},"liabilities":{"54":{"sum_foreign_comment":"","sum":"","sum_comment":"","sum_hidden":false,"sum_comment_hidden":false,"sum_foreign":""},"55":{"sum_foreign_comment":"","sum":"","sum_comment":"","sum_foreign":""},"56":{"sum_foreign_comment":"","sum":"","sum_comment":"","sum_foreign":""},"57":{"sum_foreign_comment":"","sum_comment_hidden":false,"sum":"","sum_comment":"","sum_foreign":""},"58":{"sum_foreign_comment":"","sum_comment_hidden":false,"sum":"","sum_comment":"","sum_foreign":""},"59":{"sum_foreign_comment":"","sum_comment_hidden":false,"sum":"","sum_comment":"","sum_foreign":""},"60":{"sum_foreign_comment":"","sum":"","sum_comment":"","sum_hidden":false,"sum_comment_hidden":false,"sum_foreign":""},"61":{"sum_foreign_comment":"","sum":"","sum_comment":"","sum_foreign":""},"62":{"sum_foreign_comment":"","sum":"","sum_comment":"","sum_unclear":false,"sum_foreign":""},"63":{"sum_foreign_comment":"","sum":"","sum_comment":"","sum_hidden":false,"sum_comment_hidden":false,"sum_foreign":""},"64":{"sum_foreign_comment":"","sum_comment_hidden":false,"sum":"","sum_comment":"","sum_foreign":""}},"ft_src":"суддя вищого господарського суду україни\nЗагальнодержавний регіон\nВищий господарський суд\nНіна\nАкулов Юліан Вікторович\nДитина\nВолодимирівна\nАкулова Ніна Володимирівна\nАкулова\nАкулова Ніна Володимирівна\nНіна Володимирівна Акулова\nНіна Акулова\nАкулова Ніна Володимирівна\n34.6\n34.6\n94.7\n15582\n2015\n2015\nАкулова Ніна Володимирівна\nНіна Володимирівна Акулова\nНіна Акулова\nАкулова Ніна Володимирівна\nАкулова Ніна Володимирівна\nНіна\nВолодимирівна\nсуддя вищого господарського суду україни\nЗагальнодержавний регіон\nВищий господарський суд\nАкулова\nДитина\nАкулов Юліан Вікторович\n268326\n268326\n34.6\n34.6\n94.7\n15582\n268326\n268326\nАкулов Юліан Вікторович\nДитина\nНіна\nВолодимирівна\nАкулова\nАкулова Ніна Володимирівна\nНіна Володимирівна Акулова\nНіна Акулова\nАкулова Ніна Володимирівна\nсуддя вищого господарського суду україни\nЗагальнодержавний регіон\nВищий господарський суд\nАкулова Ніна Володимирівна\n268326\n268326\n34.6\n34.6\n94.7\n15582\n2015","general":{"inn":"","name":"Ніна","family":[{"inn_hidden":true,"inn":"","name_hidden":true,"family_name":"Акулов Юліан Вікторович","relations":"Дитина","name_unclear":false}],"patronymic":"Володимирівна","inn_hidden":true,"family_raw":"","last_name":"Акулова","post":{"region":"Загальнодержавний регіон","region_unclear":false,"post":"суддя вищого господарського суду україни","office_unclear":false,"office":"Вищий господарський суд"},"full_name":"Акулова Ніна Володимирівна","addresses":[{"place_district":"","place_city_hidden":true,"place_city":"","place_city_type_hidden":false,"place_district_hidden":false,"place_city_type":"","place_address_hidden":true,"place_address":"","place_hidden":true,"place":""}],"patronymic_hidden":false,"full_name_suggest":{"output":"Акулова Ніна Володимирівна","input":["Акулова Ніна Володимирівна","Ніна Володимирівна Акулова","Ніна Акулова"]}},"source":"VULYK","estate":{"25":[{"costs":"","costs_comment":"","address_hidden":false,"region_hidden":true,"space_comment":"","space":"34.6","address":"","region":"","address_unclear":false,"costs_rent_comment":"","space_units":"м²","costs_rent":""},{"costs_rent":"","region":"","costs":"","costs_rent_comment":"","costs_comment":"","region_hidden":false,"space_comment":"","space_units":"м²","space":"94.7","address":""}],"31":[{"costs_rent":"","region":"","costs_property":"","costs_rent_comment":"","address_hidden":false,"region_hidden":true,"space_comment":"","costs_property_comment":"","space_units":"м²","space":"34.6","address":""}]},"intro":{"declaration_year":"2015"}}