{"income":{"5":{"value":"202826","family_comment":"","value_unclear":false,"family_unclear":false,"family":"15497","comment":""},"6":{"value":"184352","family_comment":"","value_unclear":false,"family_unclear":false,"family":"15497","comment":""},"7":{"family_comment":"","value":"","source_name":"","family":"","comment":""},"8":{"family_comment":"","value":"","family":"","comment":""},"9":{"family_comment":"","value":"5294","value_unclear":false,"family":"","comment":""},"10":{"family_comment":"","value":"12180","value_unclear":false,"family":"","comment":""},"11":{"family_comment":"","value":"","family":"","comment":""},"12":{"family_comment":"","value":"","family":"","comment":""},"13":{"family_comment":"","value":"","value_unclear":false,"family":"","comment":""},"14":{"family_comment":"","value":"","family":"","comment":""},"15":{"family_comment":"","value":"","family":"","comment":""},"16":{"family_comment":"","value":"","family":"","comment":""},"17":{"family_comment":"","value":"","family":"","comment":""},"18":{"family_comment":"","value":"","family":"","comment":""},"19":{"family_comment":"","value":"","family":"","comment":""},"20":{"family_comment":"","family_unclear":false,"value":"","family":"","comment":""}},"id":"vulyk_85_27","declaration":{"additional_info_text":"","notfull_lostpages":"","date":"2015-03-30T00:00:00","notfull":"","additional_info":"","url":"http://static.declarations.com.ua/declarations/chosen_ones/judges_batch/2630_lohoida_tetiana_volodymyrivna.pdf"},"liabilities":{"54":{"sum_foreign_comment":"","sum":"","sum_comment":"","sum_comment_unclear":false,"sum_foreign":""},"55":{"sum_foreign_comment":"","sum":"","sum_comment":"","sum_foreign":""},"56":{"sum_foreign_comment":"","sum":"3200","sum_comment":"","sum_unclear":false,"sum_foreign":""},"57":{"sum_foreign_comment":"","sum":"","sum_comment":"","sum_foreign":""},"58":{"sum_foreign_comment":"","sum_comment_hidden":false,"sum":"","sum_comment":"","sum_foreign":""},"59":{"sum_foreign_comment":"","sum":"","sum_comment":"","sum_foreign":""},"60":{"sum_foreign_comment":"","sum":"","sum_comment":"","sum_foreign":""},"61":{"sum_foreign_comment":"","sum":"","sum_comment":"","sum_foreign":""},"62":{"sum_foreign_comment":"","sum":"","sum_comment":"","sum_unclear":false,"sum_foreign":""},"63":{"sum_foreign_comment":"","sum":"","sum_comment":"","sum_unclear":false,"sum_foreign":""},"64":{"sum_foreign_comment":"","sum":"","sum_comment":"","sum_foreign":""}},"ft_src":"3200\nсуддя донецького окружного адміністративного суду\nДонецька область\nАдміністративний місцевий суд\nТетяна\nПодружжя\nВолодимирівна\nЛогойда\nЛогойда Тетяна Володимирівна\nЛогойда Тетяна Володимирівна\nТетяна Володимирівна Логойда\nТетяна Логойда\nЛогойда Тетяна Володимирівна\n5294\n12180\n202826\n15497\n184352\n15497\n22.3\n2014\n15497\n184352\n5294\n12180\n15497\n202826\n184352\n15497\n202826\n15497\n5294\n12180\nАдміністративний місцевий суд\nсуддя донецького окружного адміністративного суду\nДонецька область\nПодружжя\nЛогойда Тетяна Володимирівна\nТетяна Володимирівна Логойда\nТетяна Логойда\nЛогойда Тетяна Володимирівна\nТетяна\nЛогойда Тетяна Володимирівна\nЛогойда\nВолодимирівна\n3200\n22.3\n2014\n3200\nПодружжя\nТетяна\nВолодимирівна\nЛогойда\nЛогойда Тетяна Володимирівна\nТетяна Володимирівна Логойда\nТетяна Логойда\nЛогойда Тетяна Володимирівна\nсуддя донецького окружного адміністративного суду\nДонецька область\nАдміністративний місцевий суд\nЛогойда Тетяна Володимирівна\n22.3\n2014","general":{"inn":"","name":"Тетяна","last_name_hidden":false,"family":[{"inn":"","inn_hidden":false,"relations_unclear":false,"relations_hidden":false,"relations_other":"","relations":"Подружжя","name_hidden":true,"family_name":"","name_unclear":false}],"patronymic":"Володимирівна","inn_hidden":false,"family_raw":"","last_name":"Логойда","post":{"post_unclear":false,"post_hidden":false,"post":"суддя донецького окружного адміністративного суду","region":"Донецька область","office":"Адміністративний місцевий суд"},"last_name_unclear":false,"full_name":"Логойда Тетяна Володимирівна","full_name_suggest":{"output":"Логойда Тетяна Володимирівна","input":["Логойда Тетяна Володимирівна","Тетяна Володимирівна Логойда","Тетяна Логойда"]}},"source":"VULYK","estate":{"25":[{"space_hidden":false,"costs":"","costs_comment":"","address_hidden":false,"region_hidden":false,"space_comment":"","space_unclear":false,"space":"22.3","address":"","costs_comment_unclear":false,"region":"","costs_rent_comment":"","space_comment_unclear":false,"space_units":"м²","costs_rent":""}]},"intro":{"declaration_year":"2014","isnotdeclaration":""}}