{"income":{"5":{"value":"178351","family_comment":"","value_unclear":false,"family_unclear":false,"family":"","comment":""},"6":{"value":"178351","family_comment":"","value_unclear":false,"family_unclear":false,"family":"","comment":""},"7":{"family_comment":"","value":"","source_name":"","family":"","comment":""},"8":{"family_comment":"","value":"","family":"","comment":""},"9":{"family_comment":"","value":"","value_unclear":false,"family":"","comment":""},"10":{"family_comment":"","value":"","value_unclear":false,"family":"","comment":""},"11":{"family_comment":"","value":"","family":"","comment":""},"12":{"family_comment":"","value":"","family":"","comment":""},"13":{"family_comment":"","value":"","value_unclear":false,"family":"","comment":""},"14":{"family_comment":"","value":"","family":"","comment":""},"15":{"family_comment":"","value":"","family":"","comment":""},"16":{"family_comment":"","value":"","family":"","comment":""},"17":{"family_comment":"","value":"","family":"","comment":""},"18":{"family_comment":"","value":"","family":"","comment":""},"19":{"family_comment":"","value":"","family":"","comment":""},"20":{"family_comment":"","family_unclear":false,"value":"","family":"","comment":""}},"vehicle":{"35":[{"year_hidden":false,"brand_info":"1975 куб. см.","sum_rent_comment":"","year":"2007","brand_info_unclear":false,"sum_rent":"","sum":"","brand":"Kia Ceed","sum_comment":"","brand_unclear":false,"brand_hidden":false,"sum_comment_unclear":false}]},"id":"vulyk_85_49","declaration":{"additional_info_text":"","notfull_lostpages":"","date":"2015-03-31T00:00:00","notfull":"","additional_info":"","url":"http://static.declarations.com.ua/declarations/chosen_ones/judges_batch/2652_volhina_natalia_petrivna.pdf"},"liabilities":{"54":{"sum_foreign_comment":"","sum":"","sum_comment":"","sum_comment_unclear":false,"sum_foreign":""},"55":{"sum_foreign_comment":"","sum":"","sum_comment":"","sum_foreign":""},"56":{"sum_foreign_comment":"","sum":"","sum_comment":"","sum_unclear":false,"sum_foreign":""},"57":{"sum_foreign_comment":"","sum":"","sum_comment":"","sum_foreign":""},"58":{"sum_foreign_comment":"","sum_comment_hidden":false,"sum":"","sum_comment":"","sum_foreign":""},"59":{"sum_foreign_comment":"","sum":"","sum_comment":"","sum_foreign":""},"60":{"sum_foreign_comment":"","sum":"","sum_comment":"","sum_foreign":""},"61":{"sum_foreign_comment":"","sum":"","sum_comment":"","sum_foreign":""},"62":{"sum_foreign_comment":"","sum":"","sum_comment":"","sum_unclear":false,"sum_foreign":""},"63":{"sum_foreign_comment":"","sum":"","sum_comment":"","sum_unclear":false,"sum_foreign":""},"64":{"sum_foreign_comment":"","sum":"","sum_comment":"","sum_foreign":""}},"ft_src":"суддя донецького окружного адміністративного суду\nДонецька область\nАдміністративний місцевий суд\nНаталя\nДитина\nПетрівна\nВолгіна Наталя Петрівна\nНаталя Петрівна Волгіна\nНаталя Волгіна\nВолгіна Наталя Петрівна\nВолгіна\nВолгіна Наталя Петрівна\n1975 куб. см.\nKia Ceed\n2007\n81.7\n2014\n178351\n178351\n1975 куб. см.\nKia Ceed\n2007\n81.7\nВолгіна Наталя Петрівна\nНаталя Петрівна Волгіна\nНаталя Волгіна\nВолгіна Наталя Петрівна\nНаталя\nДитина\nВолгіна Наталя Петрівна\nВолгіна\nАдміністративний місцевий суд\nсуддя донецького окружного адміністративного суду\nДонецька область\nПетрівна\n178351\n178351\n2014\nДитина\nПетрівна\nВолгіна\nНаталя\nВолгіна Наталя Петрівна\nНаталя Петрівна Волгіна\nНаталя Волгіна\nВолгіна Наталя Петрівна\nсуддя донецького окружного адміністративного суду\nДонецька область\nАдміністративний місцевий суд\nВолгіна Наталя Петрівна\nKia Ceed\n1975 куб. см.\n2007\n178351\n178351\n81.7\n2014","general":{"inn":"","name":"Наталя","last_name_hidden":false,"family":[{"inn":"","inn_hidden":true,"relations_unclear":false,"relations_hidden":false,"relations_other":"","relations":"Дитина","name_hidden":true,"family_name":"","name_unclear":false}],"patronymic":"Петрівна","inn_hidden":true,"family_raw":"","last_name":"Волгіна","post":{"post_unclear":false,"post_hidden":false,"post":"суддя донецького окружного адміністративного суду","region":"Донецька область","office":"Адміністративний місцевий суд"},"last_name_unclear":false,"full_name":"Волгіна Наталя Петрівна","addresses":[{"place_district":"","place_city_hidden":true,"place_city":"","place_city_type_hidden":true,"place_district_hidden":true,"place_city_type":"","place_address_hidden":true,"place_address":"","place_hidden":true,"place":""}],"full_name_suggest":{"output":"Волгіна Наталя Петрівна","input":["Волгіна Наталя Петрівна","Наталя Петрівна Волгіна","Наталя Волгіна"]}},"source":"VULYK","estate":{"25":[{"space_hidden":false,"costs":"","costs_comment":"","address_hidden":true,"region_hidden":true,"space_comment":"","space_unclear":false,"space":"81.7","address":"","costs_comment_unclear":false,"region":"","costs_rent_comment":"","space_comment_unclear":false,"space_units":"м²","costs_rent":""}]},"intro":{"declaration_year":"2014","isnotdeclaration":""}}