{"id":"vulyk_106_81","ft_src":"BMW\n2993 куб. см, 190 кВт\n2013\n3456 куб. см.\nLexus\n2010\n1/3\n114\n261.4\n.12\n1\n1/4\n88\nБершадський р-н\nВінницька область\n1/4\nм. Вінниця\n91.7\nВінницька область\n2015\n269054\n250465\n269054\n504633\n250000\n4168\n2993 куб. см, 190 кВт\n2013\nBMW\n3456 куб. см.\n2010\nLexus\n.12\n1\n88\n1/4\nБершадський р-н\nВінницька область\n261.4\n1/3\n114\n91.7\n1/4\nВінницька область\nм. Вінниця\nКузьмишин Віталій Миколайович\nВіталій Миколайович Кузьмишин\nВіталій Кузьмишин\nКузьмишин Віталій Миколайович\nКузьмишин Віталій Миколайович\nПодружжя\nКузьмишина О. М\nДитина\nКузьмишин В. В\nДитина\nКузьмишина С. В\nДитина\nКузьмишина Х. В\nРоманчук Н. В\nІнше\nпасинок\nВіталій\nКузьмишин\nВінницька область\nАпеляційний адміністративний суд\nголова вінницького апеляційного адміністративного суду\nМиколайович\nВінницька область\nВінниця\n2000\n1700\n250465\n269054\n4168\n504633\n269054\n250000\n2015\n2000\n1700\nКузьмишина О. М\nПодружжя\nКузьмишин В. В\nДитина\nКузьмишина С. В\nДитина\nКузьмишина Х. В\nДитина\nІнше\nпасинок\nРоманчук Н. В\nМиколайович\nКузьмишин\nВіталій\nКузьмишин Віталій Миколайович\nВіталій Миколайович Кузьмишин\nВіталій Кузьмишин\nКузьмишин Віталій Миколайович\nВінниця\nВінницька область\nВінницька область\nАпеляційний адміністративний суд\nголова вінницького апеляційного адміністративного суду\nКузьмишин Віталій Миколайович","estate":{"24":[{"address":"Бершадський р-н","space_units":"м²","space_hidden":false,"space_unclear":false,"region_hidden":false,"costs_rent_comment":"","space_comment":"1/4","address_hidden":true,"space_comment_hidden":false,"costs":"","space_comment_unclear":false,"costs_comment":"","space":"88","region":"Вінницька область","costs_rent":""}],"25":[{"address":"м. Вінниця","space_units":"м²","costs_comment":"","region_hidden":false,"space_comment":"1/4","address_hidden":true,"costs":"","space_comment_unclear":false,"costs_rent_comment":"","space":"91.7","region":"Вінницька область","costs_rent":""}],"29":[{"costs_property_comment":"","address":"","space_units":"га","space_comment":"","region_hidden":true,"costs_property":"","region":"","address_hidden":true,"space_units_unclear":false,"address_unclear":false,"costs_rent_comment_unclear":false,"costs_rent_comment":"","space":".12","region_unclear":false,"space_comment_unclear":false,"costs_rent":""},{"costs_property_comment":"","address":"","space_units":"га","costs_rent_comment":"","space":"1","region":"","region_hidden":true,"costs_property":"","space_comment":"","address_hidden":false,"costs_rent":""}],"30":[{"costs_property_comment":"","address":"","space_units":"м²","space_hidden":false,"space_unclear":false,"region_hidden":true,"costs_property":"","space_comment":"","address_hidden":true,"space_comment_unclear":false,"costs_rent_comment":"","space":"261.4","region":"","costs_rent":""}],"31":[{"costs_property_comment":"","address":"","space_units":"м²","space_hidden":false,"space_unclear":false,"region_hidden":true,"costs_property":"","space_comment":"1/3","address_hidden":true,"space_comment_unclear":false,"costs_rent_comment":"","space":"114","region":"","costs_rent":""}]},"vehicle":{"35":[{"sum_comment":"","brand_info_hidden":false,"sum_rent":"","sum":"","sum_rent_comment":"","year":"2013","brand":"BMW","brand_info":"2993 куб. см, 190 кВт","brand_info_unclear":false,"year_unclear":false,"sum_hidden":false}],"40":[{"year_hidden":false,"brand_info_hidden":false,"brand_info":"3456 куб. см.","sum":"","sum_rent_comment":"","brand_hidden":false,"sum_comment":"","sum_rent":"","brand":"Lexus","year":"2010","brand_info_unclear":false}]},"source":"VULYK","income":{"5":{"family_comment":"","value":"504633","family":"269054","comment":""},"6":{"family_comment":"","value":"250465","family":"269054","comment":""},"7":{"family":"","family_comment":"","value":"","comment":"","source_name":""},"8":{"family_comment":"","value":"","family":"","comment":""},"9":{"family_comment":"","comment":"","family":"","comment_unclear":false,"value":"","family_comment_unclear":false},"10":{"family_comment":"","value":"","family":"","comment":""},"11":{"family_comment":"","value":"","family":"","comment":""},"12":{"family_comment":"","value":"","family":"","comment":""},"13":{"family_comment":"","value":"","family":"","comment":""},"14":{"family_comment":"","value":"","family":"","comment":""},"15":{"family_comment":"","value":"","family":"","comment":""},"16":{"family_comment":"","value":"250000","family":"","comment":""},"17":{"family_comment":"","value":"","family":"","comment":""},"18":{"family_comment":"","value":"","family":"","comment":""},"19":{"family_comment":"","family":"","comment":"","value_unclear":false,"family_unclear":false,"value":""},"20":{"family_comment":"","family":"","comment":"","value_unclear":false,"value":"4168","comment_hidden":false,"comment_unclear":false,"family_unclear":false,"family_comment_hidden":false,"family_comment_unclear":false}},"general":{"family":[{"inn":"","family_name":"Кузьмишина О. М","relations_other":"","relations_hidden":false,"relations_unclear":false,"name_unclear":false,"inn_hidden":true,"name_hidden":true,"relations":"Подружжя"},{"inn":"","family_name":"Кузьмишин В. В","relations_other":"","relations_unclear":false,"name_unclear":false,"inn_hidden":false,"name_hidden":false,"relations":"Дитина"},{"inn":"","family_name":"Кузьмишина С. В","name_unclear":false,"inn_hidden":true,"name_hidden":false,"relations":"Дитина"},{"inn":"","family_name":"Кузьмишина Х. В","relations_other":"","name_unclear":false,"inn_hidden":true,"relations":"Дитина"},{"inn":"","family_name":"Романчук Н. В","inn_hidden":true,"relations_other":"пасинок","relations":"Інше"}],"family_raw":"","name":"Віталій","full_name_suggest":{"input":["Кузьмишин Віталій Миколайович","Віталій Миколайович Кузьмишин","Віталій Кузьмишин"],"output":"Кузьмишин Віталій Миколайович"},"name_unclear":false,"patronymic":"Миколайович","inn_hidden":true,"addresses":[{"place_city_type_hidden":false,"place_city_type":"Місто","place_city_hidden":false,"place_hidden":false,"place_district":"","place_district_hidden":false,"place":"Вінницька область","place_city":"Вінниця","place_address_hidden":true,"place_address":""}],"inn":"","inn_unclear":false,"last_name":"Кузьмишин","full_name":"Кузьмишин Віталій Миколайович","post":{"post_hidden":false,"office":"Апеляційний адміністративний суд","post":"голова вінницького апеляційного адміністративного суду","office_unclear":false,"region_unclear":false,"region":"Вінницька область"}},"liabilities":{"54":{"sum_comment_unclear":false,"sum_comment":"","sum_hidden":false,"sum":"2000","sum_foreign_comment":"","sum_foreign":"","sum_comment_hidden":false},"55":{"sum_comment":"","sum_foreign_comment":"","sum_foreign":"","sum_hidden":false,"sum":""},"56":{"sum_comment":"","sum_hidden":false,"sum":"","sum_foreign_comment":"","sum_foreign":"","sum_unclear":false,"sum_comment_hidden":false},"57":{"sum_comment":"","sum_hidden":false,"sum":"","sum_foreign_comment":"","sum_foreign":"","sum_comment_hidden":false},"58":{"sum_comment":"","sum_hidden":false,"sum":"","sum_foreign_comment":"","sum_foreign":"","sum_comment_hidden":false},"59":{"sum_comment":"","sum_foreign_comment":"","sum_foreign":"","sum":""},"60":{"sum_comment":"","sum_hidden":false,"sum":"1700","sum_foreign_comment":"","sum_foreign":"","sum_comment_hidden":false},"61":{"sum_comment":"","sum_foreign_comment":"","sum_foreign":"","sum":""},"62":{"sum_comment":"","sum":"","sum_foreign_comment":"","sum_foreign":"","sum_unclear":false,"sum_comment_hidden":false},"63":{"sum_comment":"","sum_foreign_comment":"","sum_foreign":"","sum":""},"64":{"sum_comment":"","sum_foreign_comment":"","sum_foreign":"","sum":""}},"declaration":{"notfull_lostpages":"","additional_info_text":"","additional_info":"","date":"2016-03-29T00:00:00","notfull":"","url":"http://static.declarations.com.ua/declarations/chosen_ones/judges_batch/2220_kuzmyshyn_vitalii_mykolaiovych.pdf"},"intro":{"isnotdeclaration":"","declaration_year":"2015"}}