{"income":{"5":{"value":"217663","family_comment":"","value_unclear":false,"comment_hidden":false,"family_hidden":false,"value_hidden":false,"family_unclear":false,"family_comment_unclear":false,"family_comment_hidden":false,"comment":"","family":"78211"},"6":{"value":"217663","family_comment":"","value_unclear":false,"family_hidden":false,"value_hidden":false,"family_unclear":false,"family":"","comment":""},"7":{"source_name_unclear":false,"value":"","family_hidden":false,"value_hidden":false,"family_comment":"","source_name":"","family":"","comment":"","source_name_hidden":false},"8":{"value":"","family_comment":"","value_unclear":false,"family_hidden":false,"value_hidden":false,"family_unclear":false,"family":"","comment":""},"9":{"value":"","family_comment":"","value_unclear":false,"family_hidden":false,"value_hidden":false,"family_unclear":false,"comment_unclear":false,"comment":"","family":""},"10":{"value":"","value_unclear":false,"family_hidden":false,"value_hidden":false,"family_comment":"для переселенців із зони АТО","family":"3713","comment":""},"11":{"value":"","family_hidden":false,"value_hidden":false,"family_comment":"","family":"","comment":""},"12":{"value":"","family_comment":"","family_hidden":false,"value_hidden":false,"family_unclear":false,"family":"","comment":""},"13":{"value":"","family_hidden":false,"value_hidden":false,"family_comment":"","family":"","comment":""},"14":{"value":"","family_hidden":false,"value_hidden":false,"family_comment":"","family":"","comment":""},"15":{"value":"","family_hidden":false,"value_hidden":false,"family_comment":"пенсія","family":"71253","comment":""},"16":{"value":"","value_unclear":false,"family_hidden":false,"value_hidden":false,"family_comment":"","family":"","comment":""},"17":{"value":"","family_hidden":false,"value_hidden":false,"family_comment":"","family":"","comment":""},"18":{"value":"","family_hidden":false,"value_hidden":false,"family_comment":"","family":"","comment":""},"19":{"value":"","comment_unclear":false,"family_hidden":false,"value_hidden":false,"family_comment":"пай за заповітом","family":"3245","comment":""},"20":{"value":"","family_comment":"","comment_unclear":false,"comment_hidden":false,"family_hidden":false,"value_hidden":false,"family_unclear":false,"family_comment_unclear":false,"family_comment_hidden":false,"comment":"","family":""}},"vehicle":{"40":[{"year_hidden":false,"brand_info":"1475 куб. см.","sum_rent_comment":"","year":"1985","sum_hidden":false,"brand_info_hidden":false,"brand_info_unclear":false,"year_unclear":false,"sum_rent":"","sum":"","brand":"ВАЗ 2107","sum_comment":"","brand_unclear":false,"brand_hidden":false}]},"id":"vulyk_69_11","declaration":{"additional_info_text":"","notfull_lostpages":"","date":"2015-03-30T00:00:00","notfull":"","additional_info":"","url":"http://static.declarations.com.ua/declarations/chosen_ones/mega_batch/ziubanova_nataliia_mykolaivna.pdf"},"liabilities":{"54":{"sum_foreign_comment":"","sum":"","sum_comment":"","sum_hidden":false,"sum_comment_hidden":false,"sum_unclear":false,"sum_foreign":""},"55":{"sum_foreign_comment":"","sum":"","sum_hidden":false,"sum_comment":"","sum_foreign":""},"56":{"sum_foreign_comment":"","sum":"484","sum_comment":"","sum_comment_unclear":false,"sum_hidden":false,"sum_unclear":false,"sum_foreign":""},"57":{"sum_foreign_comment":"","sum":"","sum_comment":"","sum_comment_unclear":false,"sum_hidden":false,"sum_comment_hidden":false,"sum_foreign":""},"58":{"sum_foreign_comment":"","sum":"","sum_comment":"","sum_comment_unclear":false,"sum_hidden":false,"sum_comment_hidden":false,"sum_unclear":false,"sum_foreign":""},"59":{"sum_foreign_comment":"","sum":"","sum_hidden":false,"sum_comment":"","sum_foreign":""},"60":{"sum_foreign_comment":"","sum":"","sum_comment":"","sum_hidden":false,"sum_comment_hidden":false,"sum_foreign":""},"61":{"sum_foreign_comment":"","sum":"","sum_hidden":false,"sum_comment":"","sum_foreign":""},"62":{"sum_foreign_comment":"","sum":"3185","sum_comment":"","sum_comment_unclear":false,"sum_hidden":false,"sum_unclear":false,"sum_foreign":""},"63":{"sum_foreign_comment":"","sum":"","sum_comment":"","sum_hidden":false,"sum_comment_hidden":false,"sum_unclear":false,"sum_foreign":""},"64":{"sum_foreign_comment":"","sum":"","sum_comment":"","sum_hidden":false,"sum_comment_hidden":false,"sum_foreign":""}},"ft_src":"3185\n484\nсуддя господарського суду луганської області\nЛуганська область\nГосподарський місцевий суд\nНаталія\nЗюбанов М. В\nБатьки\nЗюбанова Т. М\nБатьки\nРябченко М. М\nБабуся\nІнше\nМиколаївна\nЗюбанова Наталія Миколаївна\nНаталія Миколаївна Зюбанова\nНаталія Зюбанова\nЗюбанова Наталія Миколаївна\nЗюбанова Наталія Миколаївна\nЗюбанова\n1475 куб. см.\nВАЗ 2107\n1985\n20.48\n2/3\n49.6\n2/3\n35.73\nпай за заповітом\n54800\nпай за заповітом\n5200\nпай за заповітом\n600\nлітній будинок без опалення с мансардою\n67.5\n1/3\n17.87\n2014\n217663\nпенсія\n71253\nдля переселенців із зони АТО\n3713\n78211\n217663\nпай за заповітом\n3245\n1475 куб. см.\nВАЗ 2107\n1985\n20.48\nлітній будинок без опалення с мансардою\n67.5\n2/3\n49.6\n35.73\n2/3\n17.87\n1/3\n54800\nпай за заповітом\n5200\nпай за заповітом\n600\nпай за заповітом\nЗюбанова Наталія Миколаївна\nНаталія Миколаївна Зюбанова\nНаталія Зюбанова\nЗюбанова Наталія Миколаївна\nЗюбанова Наталія Миколаївна\nБатьки\nЗюбанов М. В\nБатьки\nЗюбанова Т. М\nІнше\nБабуся\nРябченко М. М\nНаталія\nМиколаївна\nГосподарський місцевий суд\nЛуганська область\nсуддя господарського суду луганської області\nЗюбанова\n484\n3185\n217663\nпенсія\n71253\n78211\n217663\nдля переселенців із зони АТО\n3713\nпай за заповітом\n3245\n2014\n484\n3185\nБатьки\nЗюбанов М. В\nБатьки\nЗюбанова Т. М\nБабуся\nРябченко М. М\nІнше\nМиколаївна\nЗюбанова\nНаталія\nЗюбанова Наталія Миколаївна\nНаталія Миколаївна Зюбанова\nНаталія Зюбанова\nЗюбанова Наталія Миколаївна\nЛуганська область\nГосподарський місцевий суд\nсуддя господарського суду луганської області\nЗюбанова Наталія Миколаївна\nВАЗ 2107\n1475 куб. см.\n1985\nпай за заповітом\n3245\nпенсія\n71253\nдля переселенців із зони АТО\n3713\n217663\n78211\n217663\n2/3\n49.6\n2/3\n35.73\n1/3\n17.87\nпай за заповітом\n54800\nпай за заповітом\n5200\nпай за заповітом\n600\n20.48\nлітній будинок без опалення с мансардою\n67.5\n2014","general":{"inn":"","name":"Наталія","patronymic_unclear":false,"family":[{"inn":"","inn_hidden":true,"relations_unclear":false,"relations_hidden":false,"relations_other":"","relations":"Батьки","name_hidden":false,"inn_unclear":false,"family_name":"Зюбанов М. В","name_unclear":false},{"inn":"","inn_hidden":false,"relations_unclear":false,"relations_hidden":false,"relations_other":"","relations":"Батьки","name_hidden":false,"inn_unclear":false,"family_name":"Зюбанова Т. М","name_unclear":false},{"inn":"","inn_hidden":false,"relations_unclear":false,"relations_hidden":false,"relations_other":"Бабуся","relations":"Інше","name_hidden":false,"family_name":"Рябченко М. М","name_unclear":false}],"patronymic":"Миколаївна","inn_hidden":true,"family_raw":"","inn_unclear":false,"post":{"post_unclear":false,"region_unclear":false,"post":"суддя господарського суду луганської області","candidate":"","office_hidden":false,"region":"Луганська область","post_hidden":false,"office":"Господарський місцевий суд","office_unclear":false,"region_hidden":false},"full_name_suggest":{"output":"Зюбанова Наталія Миколаївна","input":["Зюбанова Наталія Миколаївна","Наталія Миколаївна Зюбанова","Наталія Зюбанова"]},"full_name":"Зюбанова Наталія Миколаївна","last_name":"Зюбанова","last_name_unclear":false,"name_unclear":false},"source":"VULYK","estate":{"25":[{"region_unclear":false,"space_unclear":false,"costs":"","costs_comment":"","costs_hidden":false,"address_hidden":true,"region_hidden":false,"space_comment":"1/3","space_hidden":false,"space":"17.87","space_units_hidden":false,"region":"","address_unclear":false,"costs_rent_comment":"","costs_rent_hidden":false,"space_comment_unclear":false,"space_comment_hidden":false,"space_units":"м²","address":"","costs_rent":""}],"29":[{"region_unclear":false,"space_hidden":false,"costs_property_hidden":false,"costs_property":"","address_hidden":true,"region_hidden":false,"space_comment":"пай за заповітом","space_units_hidden":false,"space_unclear":false,"space":"54800","address":"","region":"","address_unclear":false,"space_units_unclear":false,"space_comment_hidden":false,"space_units":"м²","costs_property_comment":"","costs_rent":"","costs_rent_comment":""},{"space_unclear":false,"address_hidden":true,"region_hidden":false,"space_comment":"пай за заповітом","space_hidden":false,"space":"5200","address":"","region":"","costs_property":"","costs_rent_comment":"","space_comment_unclear":false,"space_units":"м²","costs_property_comment":"","costs_rent":""},{"address_hidden":false,"region_hidden":false,"space_comment":"пай за заповітом","space":"600","address":"","region":"","costs_property":"","costs_rent_comment":"","space_comment_unclear":false,"space_units":"м²","costs_property_comment":"","costs_rent":""}],"31":[{"region_unclear":false,"space_unclear":false,"space_hidden":false,"costs_rent_unclear":false,"space_units_unclear":false,"address_hidden":true,"region_hidden":false,"space_comment":"2/3","costs_property_unclear":false,"space":"49.6","space_units_hidden":false,"region":"","address_unclear":false,"costs_rent_comment":"","space_comment_hidden":false,"costs_property":"","space_units":"м²","costs_property_comment":"","costs_rent":"","address":""},{"space_unclear":false,"address_hidden":false,"region_hidden":false,"space_comment":"2/3","space":"35.73","address":"","region":"","costs_property":"","costs_rent_comment":"","space_comment_unclear":false,"space_units":"м²","costs_property_comment":"","costs_rent":""}],"32":[{"space_unclear":false,"address_hidden":true,"region_hidden":false,"space_comment":"літній будинок без опалення с мансардою","space_units_hidden":false,"space_hidden":false,"space":"67.5","address":"","region":"","costs_property":"","space_units_unclear":false,"space_comment_hidden":false,"space_units":"м²","costs_property_comment":"","costs_rent":"","costs_rent_comment":""}],"33":[{"space_hidden":false,"space_units_unclear":false,"address_hidden":true,"region_hidden":false,"space_comment":"","space_units_hidden":false,"space":"20.48","address":"","region":"","address_unclear":false,"costs_rent_comment":"","costs_property":"","space_units":"м²","costs_property_comment":"","costs_rent":""}]},"intro":{"declaration_year":"2014","isnotdeclaration":"","declaration_year_unclear":false,"declaration_year_hidden":false}}