{"income":{"5":{"value":"266609","family_comment":"","value_unclear":false,"family_unclear":false,"family":"364914","comment":""},"6":{"family_comment":"","value":"221133","value_unclear":false,"family":"227055","comment":""},"7":{"family_comment":"","value":"","source_name":"","family":"","comment":""},"8":{"family_comment":"","value":"","family":"","comment":""},"9":{"family_comment":"","value":"","value_unclear":false,"family":"","comment":""},"10":{"family_comment":"","value":"","family":"","comment":""},"11":{"family_comment":"","value":"","family":"","comment":""},"12":{"family_comment":"","value":"","family":"","comment":""},"13":{"family_comment":"","value":"","family":"","comment":""},"14":{"family_comment":"","value":"","family":"","comment":""},"15":{"family_comment":"","value":"","family":"","comment":""},"16":{"family_comment":"","value":"","family":"137859","comment":""},"17":{"family_comment":"","value":"","family":"","comment":""},"18":{"family_comment":"","value":"","family":"","comment":""},"19":{"family_comment":"","value":"","family":"","comment":""},"20":{"family_comment":"","value":"45476","value_unclear":false,"family":"","comment":"пенсія"}},"vehicle":{"40":[{"brand_info":"3456 куб. см.","sum_rent_comment":"","brand":"Lexus RX 350","sum_comment":"","year":"2007","sum":"","sum_rent":""}]},"id":"vulyk_98_13","declaration":{"date":"2015-03-27T00:00:00","url":"http://static.declarations.com.ua/declarations/chosen_ones/judges_batch/4484_cherniuk_alla_iuriivna.pdf"},"liabilities":{"54":{"sum_foreign_comment":"","sum":"","sum_comment":"","sum_comment_unclear":false,"sum_hidden":false,"sum_comment_hidden":false,"sum_unclear":false,"sum_foreign":""},"55":{"sum_foreign_comment":"","sum":"","sum_comment":"","sum_foreign":""},"56":{"sum_foreign_comment":"","sum":"","sum_comment":"","sum_unclear":false,"sum_foreign":""},"57":{"sum_foreign_comment":"","sum":"","sum_comment":"","sum_comment_unclear":false,"sum_hidden":false,"sum_comment_hidden":false,"sum_unclear":false,"sum_foreign":""},"58":{"sum_foreign_comment":"","sum":"","sum_comment":"","sum_hidden":false,"sum_comment_hidden":false,"sum_unclear":false,"sum_foreign":""},"59":{"sum_foreign_comment":"","sum":"","sum_comment":"","sum_comment_unclear":false,"sum_foreign":""},"60":{"sum_foreign_comment":"","sum":"","sum_comment":"","sum_hidden":false,"sum_comment_hidden":false,"sum_foreign":""},"61":{"sum_foreign_comment":"","sum":"","sum_comment":"","sum_foreign":""},"62":{"sum_foreign_comment":"","sum":"","sum_comment":"","sum_comment_hidden":false,"sum_unclear":false,"sum_foreign":""},"63":{"sum_foreign_comment":"","sum":"","sum_comment":"","sum_comment_unclear":false,"sum_comment_hidden":false,"sum_foreign":""},"64":{"sum_foreign_comment":"","sum_comment_hidden":false,"sum":"","sum_comment":"","sum_foreign":""}},"ft_src":"суддя вінницького окружного адміністративного суду\nВінницька область\nАдміністративний місцевий суд\nАлла\nЧернюк І. В\nПодружжя\nЮріївна\nЧернюк Алла Юріївна\nАлла Юріївна Чернюк\nАлла Чернюк\nЧернюк Алла Юріївна\nЧернюк Алла Юріївна\nЧернюк\n3456 куб. см.\n2007\nLexus RX 350\nУкраїна\n.0791\n26\n71.9\n2014\n227055\n221133\n364914\n266609\n137859\nпенсія\n45476\n3456 куб. см.\n2007\nLexus RX 350\n2014\nАдміністративний місцевий суд\nсуддя вінницького окружного адміністративного суду\nВінницька область\nЧернюк Алла Юріївна\nАлла Юріївна Чернюк\nАлла Чернюк\nЧернюк Алла Юріївна\nЧернюк Алла Юріївна\nПодружжя\nЧернюк І. В\nАлла\nЧернюк\nЮріївна\n221133\n227055\n45476\nпенсія\n364914\n266609\n137859\n.0791\nУкраїна\n26\n71.9\nПодружжя\nЧернюк І. В\nЮріївна\nЧернюк\nАлла\nЧернюк Алла Юріївна\nАлла Юріївна Чернюк\nАлла Чернюк\nЧернюк Алла Юріївна\nсуддя вінницького окружного адміністративного суду\nВінницька область\nАдміністративний місцевий суд\nЧернюк Алла Юріївна\nLexus RX 350\n3456 куб. см.\n2007\nпенсія\n45476\n266609\n364914\n137859\n227055\n221133\n71.9\nУкраїна\n.0791\n26\n2014","general":{"inn":"","name":"Алла","last_name_hidden":false,"family":[{"inn":"","relations":"Подружжя","relations_other":"","inn_hidden":true,"family_name":"Чернюк І. В","name_hidden":true,"name_unclear":false}],"patronymic":"Юріївна","inn_hidden":true,"family_raw":"","inn_unclear":true,"post":{"post_unclear":false,"office":"Адміністративний місцевий суд","post":"суддя вінницького окружного адміністративного суду","region":"Вінницька область"},"full_name_suggest":{"output":"Чернюк Алла Юріївна","input":["Чернюк Алла Юріївна","Алла Юріївна Чернюк","Алла Чернюк"]},"full_name":"Чернюк Алла Юріївна","addresses":[{"place_district":"","place_city_hidden":true,"place_city":"","place_city_type_hidden":false,"place_district_hidden":false,"place_city_type":"","place_address_hidden":true,"place_address":"","place_hidden":true,"place":""}],"last_name":"Чернюк","patronymic_hidden":false,"last_name_unclear":false},"source":"VULYK","estate":{"23":[{"space_unclear":false,"costs":"","costs_comment":"","address_hidden":false,"region_hidden":true,"space_comment":"","space":".0791","address":"Україна","region":"","costs_rent_comment":"","space_units":"га","costs_rent":""}],"25":[{"space_unclear":false,"costs":"","costs_comment":"","address_hidden":false,"region_hidden":true,"space_comment":"","space":"71.9","address":"","region":"","address_unclear":false,"costs_rent_comment":"","space_units":"м²","costs_rent":""}],"27":[{"space_unclear":false,"costs":"","costs_comment":"","address_hidden":false,"region_hidden":true,"space_comment":"","space":"26","address":"","region":"","costs_rent_comment":"","space_units":"м²","costs_rent":""}]},"intro":{"declaration_year":"2014"}}