{"income":{"5":{"family_comment":"","value":"226266","family":"49320","comment":""},"6":{"value":"218008","family_comment":"","value_unclear":false,"comment_hidden":false,"family_unclear":false,"family":"49320","comment":""},"7":{"family_comment":"","value":"","source_name":"","family":"","comment":""},"8":{"family_comment":"","value":"","family":"","comment":""},"9":{"family_comment":"","family_unclear":false,"value":"8258","family":"","comment":""},"10":{"family_comment":"","value":"","value_unclear":false,"family":"","comment":""},"11":{"family_comment":"","value":"","family":"","comment":""},"12":{"family_comment":"","value":"","family":"","comment":""},"13":{"family_comment":"","value":"","family":"","comment":""},"14":{"family_comment":"","value":"","family":"","comment":""},"15":{"family_comment":"","value":"","family":"","comment":""},"16":{"family_comment":"","value":"","family":"","comment":""},"17":{"family_comment":"","value":"","family":"","comment":""},"18":{"family_comment":"","value":"","family":"","comment":""},"19":{"family_comment":"","value":"","family":"","comment":""},"20":{"value":"","comment_unclear":false,"family_hidden":false,"family_comment":"","value_unclear":false,"family":"","comment":"","family_comment_unclear":false}},"id":"vulyk_97_14","banks":{"45":[{"sum_foreign_comment":"","sum_units":"UAH","sum_comment":"","sum_comment_unclear":false,"sum_hidden":false,"sum_foreign_units":"UAH","sum_comment_hidden":false,"sum_unclear":false,"sum":"50000","sum_foreign":""}]},"declaration":{"additional_info_text":"","notfull_lostpages":"","date":"2015-03-31T00:00:00","notfull":"","additional_info":"","url":"http://static.declarations.com.ua/declarations/chosen_ones/judges_batch/3842_kutovyi_iurii_stanislavovych.pdf"},"liabilities":{"54":{"sum_foreign_comment":"","sum":"","sum_comment":"","sum_comment_unclear":false,"sum_hidden":false,"sum_comment_hidden":false,"sum_unclear":false,"sum_foreign":""},"55":{"sum_foreign_comment":"","sum":"","sum_comment":"","sum_foreign":""},"56":{"sum_foreign_comment":"","sum":"","sum_comment":"","sum_foreign":""},"57":{"sum_foreign_comment":"","sum":"2864","sum_comment":"","sum_comment_unclear":false,"sum_hidden":false,"sum_comment_hidden":false,"sum_unclear":false,"sum_foreign":""},"58":{"sum_foreign_comment":"","sum":"1","sum_comment":"","sum_comment_unclear":false,"sum_hidden":false,"sum_comment_hidden":false,"sum_unclear":false,"sum_foreign":""},"59":{"sum_foreign_comment":"","sum":"","sum_comment":"","sum_foreign":""},"60":{"sum_foreign_comment":"","sum":"","sum_comment":"","sum_comment_unclear":false,"sum_hidden":false,"sum_comment_hidden":false,"sum_foreign":""},"61":{"sum_foreign_comment":"","sum":"","sum_comment":"","sum_foreign":""},"62":{"sum_foreign_comment":"","sum":"","sum_comment":"","sum_unclear":false,"sum_foreign":""},"63":{"sum_foreign_comment":"","sum":"","sum_foreign":"","sum_comment":"","sum_hidden":false},"64":{"sum_foreign_comment":"","sum":"","sum_comment":"","sum_foreign":""}},"ft_src":"10.75\nЧернігівська область\nм. Чернігів\n260\nм.Чернігів, кооператив\n16\nЧернігівська область\n3036\n35.8\nм. Корюківка\nЧернігівська область\nм. Чернігів\n22.025\nЧернігівська область\n50000\n2014\n2014\nКутовий Юрій Станіславович\nЮрій Станіславович Кутовий\nЮрій Кутовий\nКутовий Юрій Станіславович\nЮрій\nПодружжя\nДрозд І. В\nКутовий Юрій Станіславович\nКутовий\nЗагальний місцевий суд\nЧернігівська область\nголова корюківського районного суду чернігівської області\nСтаніславович\nЧернігівська область\n15300\nКорюківка\n1\n2864\n218008\n49320\n226266\n49320\n8258\n16\n260\nЧернігівська область\nм.Чернігів, кооператив\n10.75\nЧернігівська область\nм. Чернігів\n35.8\nм. Корюківка\n3036\nЧернігівська область\n22.025\nЧернігівська область\nм. Чернігів\n50000\n1\n2864\n49320\n218008\n8258\n49320\n226266\nПодружжя\nДрозд І. В\nСтаніславович\nКутовий\nЮрій\nКутовий Юрій Станіславович\nЮрій Станіславович Кутовий\nЮрій Кутовий\nКутовий Юрій Станіславович\n15300\nКорюківка\nЧернігівська область\nЧернігівська область\nЗагальний місцевий суд\nголова корюківського районного суду чернігівської області\nКутовий Юрій Станіславович","general":{"name_hidden":false,"name":"Юрій","last_name_hidden":false,"inn":"","last_name":"Кутовий","family":[{"inn":"","relations":"Подружжя","relations_other":"","inn_hidden":true,"family_name":"Дрозд І. В","name_hidden":true,"name_unclear":false}],"inn_hidden":true,"family_raw":"","inn_unclear":false,"post":{"region_unclear":false,"post":"голова корюківського районного суду чернігівської області","post_hidden":false,"region":"Чернігівська область","office":"Загальний місцевий суд","office_unclear":false},"full_name":"Кутовий Юрій Станіславович","addresses":[{"place_district":"","place_address_hidden":true,"place_city":"Корюківка","place_city_unclear":false,"place_district_hidden":false,"place_city_type":"Місто","place_city_hidden":false,"place_city_type_hidden":false,"place_address":"15300","place_hidden":false,"place":"Чернігівська область"}],"patronymic":"Станіславович","patronymic_hidden":false,"full_name_suggest":{"output":"Кутовий Юрій Станіславович","input":["Кутовий Юрій Станіславович","Юрій Станіславович Кутовий","Юрій Кутовий"]}},"source":"VULYK","estate":{"25":[{"region_unclear":false,"space_hidden":false,"costs":"","costs_comment":"","address_hidden":true,"region_hidden":false,"space_comment":"","space_unclear":false,"space":"35.8","address":"м. Корюківка","region":"Чернігівська область","costs_rent_comment":"","space_comment_unclear":false,"space_comment_hidden":false,"space_units":"м²","costs_rent":"3036"},{"space_unclear":false,"costs":"","costs_comment":"","address_hidden":false,"space_comment":"","space":"22.025","address":"м. Чернігів","region":"Чернігівська область","costs_rent_comment":"","space_comment_unclear":false,"space_units":"м²","costs_rent":""}],"27":[{"region_unclear":false,"costs":"","costs_comment":"","address_hidden":true,"region_hidden":false,"space_comment":"","space":"16","address":"м.Чернігів, кооператив","region":"Чернігівська область","costs_rent_comment":"","space_units":"м²","costs_rent":"260"}],"31":[{"space_unclear":false,"address_hidden":true,"region_hidden":false,"space_comment":"","space_hidden":false,"space":"10.75","address":"м. Чернігів","region":"Чернігівська область","costs_property":"","costs_rent_comment":"","space_comment_hidden":false,"space_units":"м²","costs_property_comment":"","costs_rent":""}]},"intro":{"declaration_year":"2014","isnotdeclaration":""}}