{"income":{"5":{"value":"248737","family_comment":"","value_unclear":false,"value_hidden":false,"family_unclear":false,"family":"55317","comment":""},"6":{"value":"248737","family_comment":"","value_unclear":false,"family_hidden":false,"value_hidden":false,"family_unclear":false,"family":"55317","comment":""},"7":{"value":"","family_hidden":false,"value_hidden":false,"family_comment":"","source_name":"","family":"","comment":"","source_name_hidden":false},"8":{"family_comment":"","value":"","family":"","comment":""},"9":{"family_comment":"","value":"","comment_unclear":false,"family":"","comment":""},"10":{"value":"","value_unclear":false,"comment_hidden":false,"family_comment":"","family":"","comment":""},"11":{"family_comment":"","value":"","family":"","comment":""},"12":{"family_comment":"","value":"","family":"","comment":""},"13":{"family_comment":"","value":"","comment_hidden":false,"family":"","comment":""},"14":{"family_comment":"","value":"","comment_unclear":false,"family":"","comment":""},"15":{"family_comment":"","value":"","family":"","comment":""},"16":{"family_comment":"","value":"","family":"","comment":"","value_hidden":false},"17":{"family_comment":"","value":"","family":"","comment":"","value_hidden":false},"18":{"family_comment":"","value":"","family":"","comment":"","value_hidden":false},"19":{"family_comment":"","value":"","family":"","comment":"","value_hidden":false},"20":{"value":"","family_comment":"","value_unclear":false,"family_hidden":false,"family":"","value_hidden":false,"family_unclear":false,"comment_unclear":false,"comment":"","family_comment_unclear":false}},"vehicle":{"35":[{"year_hidden":false,"brand_info":"1.6 л 78 к. с","sum_rent_comment":"","brand_info_unclear":false,"sum_rent_hidden":false,"year":"1987","brand_info_hidden":false,"sum_rent_comment_unclear":false,"year_unclear":false,"sum_rent":"","sum":"","brand":"Volkswagen","sum_comment":"","sum_comment_unclear":false,"brand_hidden":false,"sum_unclear":false,"brand_unclear":false}]},"id":"vulyk_43_30","banks":{"45":[{"sum_foreign_comment":"","sum_units":"UAH","sum_comment":"","sum_comment_unclear":false,"sum_hidden":false,"sum_foreign_units":"UAH","sum_units_unclear":false,"sum":"","sum_unclear":false,"sum_foreign":""}],"46":[{"sum_foreign_comment":"","sum_units":"UAH","sum_comment":"","sum_hidden":false,"sum_foreign_units":"UAH","sum":"","sum_foreign":""}],"47":[{"sum_foreign_comment":"","sum_units":"UAH","sum_comment":"","sum_hidden":false,"sum_foreign_units":"UAH","sum":"","sum_foreign":""},{"sum_foreign_comment":"","sum_units":"","sum_comment":"","sum_foreign_units":"","sum":"","sum_foreign":""}],"48":[{"sum_foreign_comment":"","sum_units":"UAH","sum_comment":"","sum_hidden":false,"sum_foreign_units":"UAH","sum":"","sum_foreign":""}],"49":[{"sum_foreign_comment":"","sum_units":"UAH","sum_comment":"","sum_hidden":false,"sum_foreign_units":"UAH","sum":"","sum_foreign":""}],"50":[{"sum_foreign_comment":"","sum_units":"UAH","sum_comment":"","sum_hidden":false,"sum_foreign_units":"UAH","sum_foreign_hidden":false,"sum_units_unclear":false,"sum":"","sum_unclear":false,"sum_foreign":""}],"51":[{"sum_foreign_comment":"","sum_units":"UAH","sum_comment":"","sum_hidden":false,"sum_foreign_units":"UAH","sum":"","sum_unclear":false,"sum_foreign":""}],"52":[{"sum_foreign_comment":"","sum_units":"UAH","sum_comment":"","sum_hidden":false,"sum_foreign_units":"UAH","sum":"","sum_foreign":""}],"53":[{"sum_foreign_comment":"","sum_units":"UAH","sum_comment":"","sum_hidden":false,"sum_foreign_units":"UAH","sum":"","sum_foreign":""}]},"declaration":{"additional_info_text":"","notfull_lostpages":"","date":"2015-03-30T00:00:00","notfull":"","additional_info":"","url":"http://static.declarations.com.ua/declarations/chosen_ones/mega_batch/koval_volodymyr_oleksandrovych.pdf"},"liabilities":{"54":{"sum_foreign_comment":"","sum":"","sum_comment":"","sum_hidden":false,"sum_comment_hidden":false,"sum_unclear":false,"sum_foreign":""},"55":{"sum_foreign_comment":"","sum":"","sum_hidden":false,"sum_comment":"","sum_foreign":""},"56":{"sum_foreign_comment":"","sum":"","sum_comment":"","sum_hidden":false,"sum_unclear":false,"sum_foreign":""},"57":{"sum_foreign_comment":"","sum":"","sum_comment":"","sum_hidden":false,"sum_comment_hidden":false,"sum_unclear":false,"sum_foreign":""},"58":{"sum_foreign_comment":"","sum":"","sum_comment":"","sum_hidden":false,"sum_comment_hidden":false,"sum_foreign":""},"59":{"sum_foreign_comment":"","sum":"","sum_hidden":false,"sum_comment":"","sum_foreign":""},"60":{"sum_foreign_comment":"","sum":"","sum_comment":"","sum_comment_unclear":false,"sum_hidden":false,"sum_unclear":false,"sum_foreign":""},"61":{"sum_foreign_comment":"","sum":"","sum_hidden":false,"sum_comment":"","sum_foreign":""},"62":{"sum_foreign_comment":"","sum":"","sum_comment":"","sum_hidden":false,"sum_unclear":false,"sum_foreign":""},"63":{"sum_foreign_comment":"","sum":"","sum_hidden":false,"sum_comment":"","sum_foreign":""},"64":{"sum_foreign_comment":"","sum":"","sum_comment":"","sum_hidden":false,"sum_unclear":false,"sum_foreign":""}},"ft_src":"голова великоолександрівського районного суду херсонської області\nХерсонська область\nЗагальний місцевий суд\nВолодимир\nКоваль І. М. 21. 04. 1960\nПодружжя\nОлександрович\nКоваль\nКоваль Володимир Олександрович\nКоваль Володимир Олександрович\nВолодимир Олександрович Коваль\nВолодимир Коваль\nКоваль Володимир Олександрович\nВелика Олександрівка\n74100\nХерсонська область\nСМТ\n1.6 л 78 к. с\nVolkswagen\n1987\n2014\n1.6 л 78 к. с\nVolkswagen\n1987\n52\nХерсонська область\nсмт. Велика Олександрівка\nПодружжя\nКоваль І. М. 21. 04. 1960\nКоваль Володимир Олександрович\nВолодимир Олександрович Коваль\nВолодимир Коваль\nКоваль Володимир Олександрович\nВолодимир\nКоваль Володимир Олександрович\nКоваль\nЗагальний місцевий суд\nголова великоолександрівського районного суду херсонської області\nХерсонська область\nОлександрович\nСМТ\n74100\nХерсонська область\nВелика Олександрівка\n248737\n55317\n55317\n248737\n2014\nХерсонська область\nсмт. Велика Олександрівка\n52\nПодружжя\nКоваль І. М. 21. 04. 1960\nКоваль Володимир Олександрович\nВолодимир Олександрович Коваль\nВолодимир Коваль\nКоваль Володимир Олександрович\nОлександрович\nКоваль\nСМТ\n74100\nВелика Олександрівка\nХерсонська область\nХерсонська область\nЗагальний місцевий суд\nголова великоолександрівського районного суду херсонської області\nКоваль Володимир Олександрович\nВолодимир\n55317\n248737\n55317\n248737\nVolkswagen\n1.6 л 78 к. с\n1987\n248737\n55317\n248737\n55317\nХерсонська область\nсмт. Велика Олександрівка\n52\n2014","general":{"name_hidden":false,"name":"Володимир","patronymic_unclear":false,"inn":"","family":[{"inn":"","inn_hidden":true,"relations_unclear":false,"relations_hidden":false,"relations_other":"","relations":"Подружжя","name_hidden":false,"inn_unclear":false,"family_name":"Коваль І. М. 21. 04. 1960","name_unclear":false}],"patronymic":"Олександрович","inn_hidden":true,"family_raw":"","inn_unclear":false,"post":{"post_unclear":false,"post":"голова великоолександрівського районного суду херсонської області","candidate":"","office_hidden":false,"region":"Херсонська область","post_hidden":false,"office":"Загальний місцевий суд","office_unclear":false,"region_hidden":false},"last_name_unclear":false,"full_name":"Коваль Володимир Олександрович","addresses":[{"place_district":"","place_city_hidden":false,"place_city":"Велика Олександрівка","place_city_type_hidden":false,"place_district_hidden":false,"place_city_type":"СМТ","place_hidden":true,"place_address_hidden":true,"place_address":"74100","place":"Херсонська область","place_district_unclear":false}],"last_name":"Коваль","full_name_suggest":{"output":"Коваль Володимир Олександрович","input":["Коваль Володимир Олександрович","Володимир Олександрович Коваль","Володимир Коваль"]}},"source":"VULYK","estate":{"23":[{"region_unclear":false,"space_hidden":false,"costs":"","costs_comment":"","costs_hidden":false,"address_hidden":false,"region_hidden":false,"space_comment":"","space_unclear":false,"space":"","address":"","region":"","address_unclear":false,"costs_rent_comment":"","costs_rent_hidden":false,"costs_unclear":false,"space_units":"м²","costs_rent":""},{"costs_rent":"","region":"","costs":"","costs_rent_comment":"","costs_comment":"","address_hidden":false,"region_hidden":false,"space_comment":"","space_units":"","space":"","address":""},{"costs_rent":"","region":"","costs":"","costs_rent_comment":"","costs_comment":"","region_hidden":false,"space_comment":"","space_units":"","space":"","address":""},{"costs_rent":"","region":"","costs":"","costs_rent_comment":"","costs_comment":"","region_hidden":false,"space_comment":"","space_units":"","space":"","address":""},{"costs_rent":"","region":"","costs":"","costs_rent_comment":"","costs_comment":"","region_hidden":false,"space_comment":"","space_units":"","space":"","address":""}],"25":[{"space_unclear":false,"costs":"","costs_rent_unclear":false,"costs_comment":"","address_hidden":true,"region_hidden":false,"space_comment":"","space_hidden":false,"space":"52","address":"смт. Велика Олександрівка","region":"Херсонська область","address_unclear":false,"costs_rent_comment":"","costs_rent_hidden":false,"space_comment_unclear":false,"space_units":"м²","space_units_hidden":false,"costs_rent":""}]},"intro":{"declaration_year":"2014","isnotdeclaration":"","declaration_year_unclear":false,"declaration_year_hidden":false}}