{"income":{"5":{"family_comment":"","value":"202973","family":"10321","comment":""},"6":{"family_comment":"","value":"202879","family":"","comment":""},"7":{"value":"","comment_hidden":false,"family_comment":"","source_name":"","family":"","comment":"","source_name_hidden":false},"8":{"family_comment":"","value":"","family":"","comment":"","family_hidden":false},"9":{"value":"94","family_comment":"","value_unclear":false,"family_unclear":false,"family":"1","comment":""},"10":{"family_comment":"","value":"","family":"","comment":""},"11":{"family_comment":"","value":"","family":"","comment":""},"12":{"family_comment":"","value":"","family":"","comment":""},"13":{"family_comment":"","value":"","family":"","comment":""},"14":{"family_comment":"","value":"","family":"","comment":""},"15":{"family_comment":"","value":"","family":"","comment":""},"16":{"family_comment":"","value":"","family":"","comment":""},"17":{"family_comment":"","value":"","family":"","comment":""},"18":{"family_comment":"","value":"","family":"","comment":""},"19":{"family_comment":"","value":"","family":"","comment":""},"20":{"value":"","value_unclear":false,"family_hidden":false,"family_comment":"","family":"10320","comment":""}},"vehicle":{"35":[{"brand_info":"1560 куб. см., 68 кВт","sum_rent_comment":"","year":"2014","brand_info_hidden":false,"brand_info_unclear":false,"year_unclear":false,"sum_rent":"","sum":"265000","brand":"Peugeot 301","sum_comment":"","brand_unclear":false,"brand_hidden":false,"sum_comment_unclear":false}]},"id":"vulyk_109_6","declaration":{"additional_info_text":"","notfull_lostpages":"","date":"2016-03-31T00:00:00","notfull":"","additional_info":"","url":"http://static.declarations.com.ua/declarations/chosen_ones/judges_batch/2463_banasko_oleksandr_oleksandrovych_2015.pdf"},"liabilities":{"54":{"sum_foreign_comment":"","sum":"16801","sum_comment":"Приватне акціонерне товариство 'Страхова компанія 'ПЗУ Україна'. Приватне акционерне товариство 'Страхова компанія 'Кардіф'","sum_hidden":false,"sum_comment_hidden":false,"sum_unclear":false,"sum_foreign":""},"55":{"sum_foreign_comment":"","sum":"","sum_comment":"","sum_comment_unclear":false,"sum_foreign":""},"56":{"sum_foreign_comment":"","sum":"","sum_comment":"","sum_foreign":""},"57":{"sum_foreign_comment":"","sum_comment":"Публічне акціонерне товариство 'КредіАгріколь Банк'","sum":"49555","sum_comment_hidden":false,"sum_foreign":""},"58":{"sum_foreign_comment":"","sum_comment":"","sum":"","sum_comment_hidden":false,"sum_foreign":""},"59":{"sum_foreign_comment":"","sum":"","sum_comment":"","sum_foreign":""},"60":{"sum_foreign_comment":"","sum":"","sum_comment":"","sum_foreign":""},"61":{"sum_foreign_comment":"","sum":"","sum_comment":"","sum_foreign":""},"62":{"sum_foreign_comment":"","sum":"","sum_comment":"","sum_foreign":""},"63":{"sum_foreign_comment":"","sum":"","sum_comment":"","sum_foreign":""},"64":{"sum_foreign_comment":"","sum":"","sum_comment":"","sum_foreign":""}},"ft_src":"1560 куб. см., 68 кВт\nPeugeot 301\n2014\n265000\n79.7\nв користуванні\n79.7\n2015\n202879\n10321\n202973\n1\n94\n10320\n1560 куб. см., 68 кВт\nPeugeot 301\n2014\n265000\n2015\nБанасько Олександр Олександрович\nОлександр Олександрович Банасько\nОлександр Банасько\nБанасько Олександр Олександрович\nОлександр\nПодружжя\nБанасько І. М\nДитина\nБанасько А. О\nБанасько Олександр Олександрович\nОлександрович\nГосподарський місцевий суд\nВінницька область\nсуддя господарського суду вінницької області\nБанасько\nПублічне акціонерне товариство 'КредіАгріколь Банк'\n49555\nПриватне акціонерне товариство 'Страхова компанія 'ПЗУ Україна'. Приватне акционерне товариство 'Страхова компанія 'Кардіф'\n16801\n202879\n10320\n202973\n10321\n94\n1\n79.7\n79.7\nв користуванні\nПублічне акціонерне товариство 'КредіАгріколь Банк'\n49555\nПриватне акціонерне товариство 'Страхова компанія 'ПЗУ Україна'. Приватне акционерне товариство 'Страхова компанія 'Кардіф'\n16801\nПодружжя\nБанасько І. М\nДитина\nБанасько А. О\nОлександрович\nБанасько\nОлександр\nБанасько Олександр Олександрович\nОлександр Олександрович Банасько\nОлександр Банасько\nБанасько Олександр Олександрович\nВінницька область\nГосподарський місцевий суд\nсуддя господарського суду вінницької області\nБанасько Олександр Олександрович","general":{"name_hidden":false,"name":"Олександр","inn":"","last_name":"Банасько","family":[{"inn":"","relations":"Подружжя","relations_hidden":false,"inn_hidden":true,"family_name":"Банасько І. М","relations_other":"","name_hidden":false,"name_unclear":true},{"inn":"","relations":"Дитина","relations_other":"","inn_hidden":true,"family_name":"Банасько А. О","name_hidden":false,"name_unclear":false}],"inn_hidden":true,"family_raw":"","inn_unclear":false,"post":{"region_unclear":false,"region":"Вінницька область","post":"суддя господарського суду вінницької області","region_hidden":false,"office":"Господарський місцевий суд","office_hidden":false,"office_unclear":false},"full_name":"Банасько Олександр Олександрович","addresses":[{"place_district":"","place_address_hidden":true,"place_city":"","place_address":"","place_district_hidden":true,"place_city_type":"","place_city_hidden":true,"place_city_type_hidden":true,"place_hidden":true,"place":""}],"patronymic":"Олександрович","full_name_suggest":{"output":"Банасько Олександр Олександрович","input":["Банасько Олександр Олександрович","Олександр Олександрович Банасько","Олександр Банасько"]}},"source":"VULYK","estate":{"25":[{"space_unclear":false,"costs":"","costs_comment":"","address_hidden":false,"region_hidden":true,"space_comment":"","space_hidden":false,"space":"79.7","space_units_hidden":false,"region":"","costs_rent_comment":"в користуванні","space_units":"м²","address":"","costs_rent":""}],"31":[{"space_hidden":false,"address_hidden":false,"region_hidden":true,"space_comment":"","space":"79.7","space_units_hidden":false,"region":"","costs_property":"","costs_rent_comment":"","space_units":"м²","costs_property_comment":"","costs_rent":"","address":""}]},"intro":{"declaration_year":"2015","isnotdeclaration":""}}