{"income":{"5":{"value":"300091","family_comment":"","comment_unclear":false,"family_unclear":false,"family":"29791","comment":""},"6":{"family_comment":"","value":"278454","family":"","comment":""},"7":{"source_name_unclear":false,"value":"","comment_unclear":false,"family_comment":"","source_name":"","family":"","comment":""},"8":{"family_comment":"","value":"","family":"","comment":""},"9":{"family_comment":"","value":"","family":"","comment":""},"10":{"family_comment":"","value":"","family":"","comment":""},"11":{"family_comment":"","value":"","family":"","comment":""},"12":{"family_comment":"","value":"","family":"","comment":""},"13":{"family_comment":"","value":"","family":"","comment":""},"14":{"family_comment":"","value":"","family":"","comment":""},"15":{"family_comment":"","value":"","family":"","comment":""},"16":{"family_comment":"","family_unclear":false,"value":"","family":"","comment":""},"17":{"family_comment":"","value":"","family":"","comment":""},"18":{"family_comment":"","value":"","family":"","comment":""},"19":{"family_comment":"","value":"7093","family":"","comment":""},"20":{"value":"14544","family_comment":"","comment_unclear":false,"family_unclear":false,"family":"29791","comment":"","family_comment_unclear":false}},"vehicle":{"40":[{"brand_info":"1195","sum_rent_comment":"","brand":"Nissan Maxima QX","sum_comment":"","year":"2004","brand_hidden":false,"sum":"","sum_rent":""}],"44":[{"brand_info":"Причіп автомобільний","sum_rent_comment":"","brand":"ХТ 810240","sum_comment":"","year":"1993","brand_info_unclear":false,"sum":"","sum_rent":""}]},"id":"vulyk_107_90","declaration":{"additional_info_text":"","notfull_lostpages":"","date":"2016-03-28T00:00:00","notfull":"","additional_info":"","url":"http://static.declarations.com.ua/declarations/chosen_ones/judges_batch/2069_sybilova_liubov_oleksiivna.pdf"},"liabilities":{"54":{"sum_foreign_comment":"","sum":"","sum_comment":"","sum_comment_unclear":false,"sum_comment_hidden":false,"sum_foreign":""},"55":{"sum_foreign_comment":"","sum":"","sum_comment":"","sum_foreign":""},"56":{"sum_foreign_comment":"","sum":"","sum_comment":"","sum_unclear":false,"sum_foreign":""},"57":{"sum_foreign_comment":"","sum":"","sum_comment":"","sum_comment_unclear":false,"sum_foreign":""},"58":{"sum_foreign_comment":"","sum":"","sum_comment":"","sum_comment_unclear":false,"sum_unclear":false,"sum_foreign":""},"59":{"sum_foreign_comment":"","sum":"","sum_comment":"","sum_unclear":false,"sum_foreign":""},"60":{"sum_foreign_comment":"","sum":"","sum_comment":"","sum_comment_unclear":false,"sum_comment_hidden":false,"sum_foreign":""},"61":{"sum_foreign_comment":"","sum":"","sum_comment":"","sum_foreign":""},"62":{"sum_foreign_comment":"","sum":"","sum_comment":"","sum_foreign":""},"63":{"sum_foreign_comment":"","sum":"","sum_comment":"","sum_foreign":""},"64":{"sum_foreign_comment":"","sum":"","sum_comment":"","sum_foreign":""}},"ft_src":"Сибільова Любов Олексіївна\nсуддя апеляційного суду сумської області\nСумська область\nЗагальний апеляційний суд\nЛюбов\nСибільов В. В\nПодружжя\nСибільова Любов Олексіївна\nЛюбов Олексіївна Сибільова\nЛюбов Сибільова\nСибільова Любов Олексіївна\nСибільова\nОлексіївна\n2004\n1195\nNissan Maxima QX\nПричіп автомобільний\n1993\nХТ 810240\n1204\n1100\n45000\n400\n274.5\nНезавершене будівництво житлового будинку 58%\n274.5\n62.4\n2015\n278454\n29791\n300091\n7093\n29791\n14544\n1195\n2004\nNissan Maxima QX\nПричіп автомобільний\n1993\nХТ 810240\n2015\nСибільова\nПодружжя\nСибільов В. В\nСибільова Любов Олексіївна\nЛюбов Олексіївна Сибільова\nЛюбов Сибільова\nСибільова Любов Олексіївна\nЛюбов\nОлексіївна\nСибільова Любов Олексіївна\nЗагальний апеляційний суд\nсуддя апеляційного суду сумської області\nСумська область\n278454\n29791\n14544\n300091\n29791\n7093\n45000\n400\n1204\n1100\n274.5\n274.5\nНезавершене будівництво житлового будинку 58%\n62.4\nСибільов В. В\nПодружжя\nСибільова\nОлексіївна\nсуддя апеляційного суду сумської області\nСумська область\nЗагальний апеляційний суд\nСибільова Любов Олексіївна\nСибільова Любов Олексіївна\nЛюбов Олексіївна Сибільова\nЛюбов Сибільова\nСибільова Любов Олексіївна\nЛюбов\n1993\nПричіп автомобільний\nХТ 810240\n2004\n1195\nNissan Maxima QX\n7093\n14544\n29791\n300091\n29791\n278454\n274.5\n45000\n400\nНезавершене будівництво житлового будинку 58%\n274.5\n62.4\n1204\n1100\n2015","general":{"inn":"","inn_hidden":true,"last_name":"Сибільова","post":{"post_unclear":false,"office":"Загальний апеляційний суд","post":"суддя апеляційного суду сумської області","region":"Сумська область"},"name":"Любов","full_name":"Сибільова Любов Олексіївна","family_raw":"","addresses":[{"place_district":"","place_city_hidden":false,"place_city":"","place_city_type_hidden":false,"place_district_hidden":false,"place_city_type":"","place_address_hidden":false,"place_address":"","place_hidden":true,"place":""}],"family":[{"inn":"","relations":"Подружжя","relations_other":"","inn_hidden":true,"family_name":"Сибільов В. В","name_hidden":false,"name_unclear":false}],"full_name_suggest":{"output":"Сибільова Любов Олексіївна","input":["Сибільова Любов Олексіївна","Любов Олексіївна Сибільова","Любов Сибільова"]},"patronymic":"Олексіївна"},"source":"VULYK","estate":{"23":[{"costs":"","costs_comment":"","address_hidden":false,"region_hidden":true,"space_comment":"","space":"45000","address":"","region":"","costs_rent_comment":"","space_comment_unclear":false,"space_comment_hidden":false,"space_units":"м²","costs_rent":""},{"costs_rent":"","region":"","costs":"","costs_rent_comment":"","costs_comment":"","address_hidden":false,"region_hidden":false,"space_comment":"","space_units":"м²","space":"400","address":""}],"25":[{"space_hidden":false,"costs":"","costs_comment":"","address_hidden":false,"region_hidden":true,"space_comment":"","space_unclear":false,"space":"62.4","address":"","region":"","costs_rent_comment":"","space_units":"м²","costs_rent":""}],"29":[{"address_hidden":true,"region_hidden":true,"space_comment":"","space":"1204","address":"","region":"","costs_property":"","costs_rent_comment":"","costs_rent_hidden":false,"space_units":"м²","costs_property_comment":"","costs_rent":""},{"costs_rent":"","region":"","costs_property":"","costs_rent_comment":"","costs_rent_hidden":false,"region_hidden":false,"space_comment":"","costs_property_comment":"","space_units":"м²","space":"1100","address":""}],"30":[{"address_hidden":true,"region_hidden":true,"space_comment":"","space":"274.5","address":"","region":"","costs_property":"","costs_rent_comment":"","space_comment_unclear":false,"space_units":"м²","costs_property_comment":"","costs_rent":""}],"34":[{"costs_rent":"","costs_property":"","costs_rent_comment":"","address_hidden":false,"region_hidden":false,"space_comment":"Незавершене будівництво житлового будинку 58%","costs_property_comment":"","space_units":"м²","space":"274.5","address":""}]},"intro":{"declaration_year":"2015","isnotdeclaration":""}}