{"id":"vulyk_105_12","ft_src":"1800 куб. см.\nVolkswagen Passat\n2004\n121.1\n2/3 частини\n69.92\n1200\n1200\n1000\n1500\n1/3 частина\n34.96\n2014\n35362.81\n232884.54\n1218\n13398\n36580.81\n246785.94\n503.4\n1800 куб. см.\n2004\nVolkswagen Passat\n2014\nсуддя київського апеляційного господарського суду\nАпеляційний господарський суд\nм. Київ\nГаврилюк\nГаврилюк Олександр Миколайович\nОлександр Миколайович Гаврилюк\nОлександр Гаврилюк\nГаврилюк Олександр Миколайович\nГаврилюк Олександр Миколайович\nОлександр\nМиколайович\nПодружжя\nГаврилюк Л. А\nДитина\nГаврилюк Д. О\nІнше\nплемінниця дружини\nШляхетко Ю. В\n457.86\n26128.36\n6162.9\n232884.54\n35362.81\n503.4\n246785.94\n36580.81\n13398\n1218\n1000\n1500\n1200\n1200\n34.96\n1/3 частина\n69.92\n2/3 частини\n121.1\n457.86\n26128.36\n6162.9\nГаврилюк Л. А\nПодружжя\nГаврилюк Д. О\nДитина\nплемінниця дружини\nШляхетко Ю. В\nІнше\nМиколайович\nГаврилюк\nм. Київ\nсуддя київського апеляційного господарського суду\nАпеляційний господарський суд\nГаврилюк Олександр Миколайович\nГаврилюк Олександр Миколайович\nОлександр Миколайович Гаврилюк\nОлександр Гаврилюк\nГаврилюк Олександр Миколайович\nОлександр","estate":{"23":[{"costs":"","address":"","space_units":"м²","costs_rent_comment":"","space":"1000","space_comment":"","region_hidden":true,"costs_comment":"","region":"","address_hidden":true,"costs_rent":""},{"costs":"","address":"","space_units":"м²","costs_rent_comment":"","space":"1500","space_comment":"","region_hidden":false,"costs_comment":"","region":"","address_hidden":false,"costs_rent":""}],"24":[{"address":"","space_units":"м²","space_hidden":false,"space_comment":"1/3 частина","region_hidden":true,"costs_comment":"","address_hidden":true,"space":"34.96","costs_rent_comment":"","costs":"","region":"","costs_rent":""}],"29":[{"costs_property_comment":"","address":"","space_units":"м²","costs_rent_comment":"","space_hidden":false,"region_hidden":true,"costs_property":"","space_comment":"","space":"1200","address_hidden":true,"costs_rent":""},{"costs_property_comment":"","address":"","space_units":"м²","costs_rent_comment":"","space":"1200","costs_property":"","space_comment":"","costs_rent":""}],"30":[{"costs_property_comment":"","address":"","space_units":"м²","costs_rent_comment":"","space":"69.92","region_hidden":true,"costs_property":"","space_comment":"2/3 частини","address_hidden":true,"costs_rent":""}],"31":[{"costs_property_comment":"","address":"","space_units":"м²","space_hidden":false,"space_comment":"","region_hidden":true,"costs_property":"","region":"","address_hidden":true,"costs_rent_comment":"","space":"121.1","costs_rent":""}]},"vehicle":{"40":[{"sum_comment":"","brand_info_hidden":false,"sum_rent":"","sum":"","sum_rent_comment":"","brand_hidden":false,"brand":"Volkswagen Passat","brand_info":"1800 куб. см.","year_hidden":false,"year":"2004"}]},"source":"VULYK","income":{"5":{"family_comment":"","family_hidden":false,"value":"246785.94","family":"36580.81","comment":""},"6":{"family_comment":"","family_hidden":false,"value":"232884.54","family":"35362.81","comment":""},"7":{"family":"","family_comment":"","value":"","comment":"","source_name":""},"8":{"family_comment":"","value":"","family":"","comment":""},"9":{"family_comment":"","value":"","family":"","comment":""},"10":{"family_comment":"","value":"13398","family":"1218","comment":""},"11":{"family_comment":"","value":"","family":"","comment":""},"12":{"family_comment":"","value":"","family":"","comment":""},"13":{"family_comment":"","value":"","family":"","comment":""},"14":{"family_comment":"","value":"","family":"","comment":""},"15":{"family_comment":"","value":"","family":"","comment":""},"16":{"family_comment":"","value":"","family":"","comment":""},"17":{"family_comment":"","value":"","family":"","comment":""},"18":{"family_comment":"","value":"","family":"","comment":""},"19":{"family_comment":"","value":"","family":"","comment":""},"20":{"family_comment":"","value":"503.4","family":"","comment":""}},"general":{"inn":"","addresses":[{"place_city_type_hidden":true,"place_city_type":"","place_city_hidden":true,"place_hidden":true,"place_district":"","place_district_hidden":true,"place":"","place_address":"","place_address_hidden":true,"place_city":""}],"last_name":"Гаврилюк","full_name":"Гаврилюк Олександр Миколайович","family":[{"inn":"","family_name":"Гаврилюк Л. А","relations_other":"","relations_hidden":false,"name_unclear":false,"inn_hidden":true,"name_hidden":true,"relations":"Подружжя"},{"inn":"","family_name":"Гаврилюк Д. О","relations_other":"","name_unclear":false,"inn_hidden":false,"name_hidden":false,"relations":"Дитина"},{"inn":"","family_name":"Шляхетко Ю. В","relations_other":"племінниця дружини","name_unclear":false,"inn_hidden":false,"name_hidden":false,"relations":"Інше"}],"patronymic":"Миколайович","inn_hidden":true,"name":"Олександр","post":{"office":"Апеляційний господарський суд","post":"суддя київського апеляційного господарського суду","office_unclear":false,"office_hidden":false,"region":"м. Київ","region_unclear":false,"post_unclear":false},"family_raw":"","full_name_suggest":{"input":["Гаврилюк Олександр Миколайович","Олександр Миколайович Гаврилюк","Олександр Гаврилюк"],"output":"Гаврилюк Олександр Миколайович"}},"liabilities":{"54":{"sum_comment":"","sum_foreign_comment":"","sum_foreign":"","sum":"457.86","sum_comment_hidden":false},"55":{"sum_comment":"","sum_foreign_comment":"","sum_foreign":"","sum":""},"56":{"sum_comment":"","sum_foreign_comment":"","sum_foreign":"","sum":"26128.36"},"57":{"sum_comment_unclear":false,"sum_comment":"","sum":"","sum_foreign_comment":"","sum_foreign":"","sum_comment_hidden":false},"58":{"sum_comment":"","sum_foreign_comment":"","sum_foreign":"","sum":""},"59":{"sum_comment":"","sum_foreign_comment":"","sum_foreign":"","sum":""},"60":{"sum_comment":"","sum_foreign_comment":"","sum_foreign":"","sum":""},"61":{"sum_comment":"","sum_foreign_comment":"","sum_foreign":"","sum":""},"62":{"sum_comment":"","sum_foreign_comment":"","sum_foreign":"","sum_hidden":false,"sum":"6162.9"},"63":{"sum_comment":"","sum_foreign_comment":"","sum_foreign":"","sum":""},"64":{"sum_comment":"","sum_foreign_comment":"","sum_foreign":"","sum":""}},"declaration":{"additional_info_text":"","additional_info":"","date":"2015-03-31T00:00:00","url":"http://static.declarations.com.ua/declarations/chosen_ones/judges_batch/4587_havryliuk_oleksandr_mykolaiovych.pdf"},"intro":{"declaration_year":"2014"}}