{"income":{"5":{"value":"238157","family_comment":"","value_unclear":false,"family_hidden":false,"value_hidden":false,"family_unclear":false,"family":"8276","comment":""},"6":{"value":"238157","value_unclear":false,"family_hidden":false,"value_hidden":false,"family_comment":"","comment_unclear":false,"comment":"","family":""},"7":{"value":"","value_hidden":false,"family_comment":"","source_name":"","family":"","comment":"","source_name_hidden":false},"8":{"family_comment":"","value":"","family":"","comment":""},"9":{"family_comment":"","value":"","comment_unclear":false,"family":"","comment":""},"10":{"family_comment":"","value":"","value_unclear":false,"family":"","comment":""},"11":{"family_comment":"","value":"","family":"","comment":""},"12":{"family_comment":"","value":"","family":"","comment":""},"13":{"family_comment":"","value":"","family":"","comment":""},"14":{"family_comment":"","value":"","family":"","comment":""},"15":{"family_comment":"","value":"","family":"","comment":""},"16":{"family_comment":"","value":"","family":"","comment":""},"17":{"family_comment":"","value":"","family":"","comment":""},"18":{"family_comment":"","value":"","family":"","comment":""},"19":{"value":"","value_unclear":false,"comment_hidden":false,"family_hidden":false,"value_hidden":false,"family_comment":"","family_comment_hidden":false,"comment":"","family":""},"20":{"value":"","family_comment":"","value_unclear":false,"family_hidden":false,"value_hidden":false,"family_unclear":false,"comment_unclear":false,"comment":"","family":"8276"}},"vehicle":{"35":[{"brand_info":"1.8","sum_rent_comment":"","year":"2006","brand_info_hidden":false,"brand_info_unclear":true,"year_unclear":false,"sum_rent":"","sum":"","brand":"Nissan Primera","sum_comment":"","brand_unclear":false,"brand_hidden":false}]},"id":"vulyk_65_132","declaration":{"additional_info_text":"","notfull_lostpages":"","date":"2015-03-05T00:00:00","notfull":"","additional_info":"","url":"http://static.declarations.com.ua/declarations/chosen_ones/mega_batch/kolosovskyi_serhii_iuriiovych.pdf"},"liabilities":{"54":{"sum_foreign_comment":"","sum":"","sum_comment":"","sum_comment_unclear":false,"sum_hidden":false,"sum_comment_hidden":false,"sum_foreign":""},"55":{"sum_foreign_comment":"","sum":"","sum_comment":"","sum_foreign":""},"56":{"sum_foreign_comment":"","sum":"","sum_comment":"","sum_unclear":false,"sum_foreign":""},"57":{"sum_foreign_comment":"","sum":"","sum_comment":"","sum_comment_unclear":false,"sum_unclear":false,"sum_foreign":""},"58":{"sum_foreign_comment":"","sum":"","sum_comment":"","sum_comment_unclear":false,"sum_unclear":false,"sum_foreign":""},"59":{"sum_foreign_comment":"","sum":"","sum_comment":"","sum_foreign":""},"60":{"sum_foreign_comment":"","sum":"","sum_comment":"","sum_comment_unclear":false,"sum_foreign":""},"61":{"sum_foreign_comment":"","sum":"","sum_comment":"","sum_foreign":""},"62":{"sum_foreign_comment":"","sum":"","sum_comment":"","sum_foreign":""},"63":{"sum_foreign_comment":"","sum":"","sum_comment":"","sum_foreign":""},"64":{"sum_foreign_comment":"","sum":"","sum_comment":"","sum_unclear":false,"sum_foreign":""}},"ft_src":"суддя апеляційного суду миколаївської області\nМиколаївська область\nЗагальний апеляційний суд\nСергій\nКолосовська О. В., 17. 03. 1975, шлюб розірвано в вересні 2014\nПодружжя\nЧуркіна К. С., 12. 09. 1940\nтеща\nІнше\nЮрійович\nКолосовський\nКолосовський Сергій Юрійович\nКолосовський Сергій Юрійович\nСергій Юрійович Колосовський\nСергій Колосовський\nКолосовський Сергій Юрійович\n1.8\nNissan Primera\n2006\n211.5\n63.1\n211.5\n63.1\n2014\n238157\n8276\n238157\n8276\n1.8\nNissan Primera\n2006\n211.5\n211.5\n63.1\n63.1\nЗагальний апеляційний суд\nМиколаївська область\nсуддя апеляційного суду миколаївської області\nКолосовський Сергій Юрійович\nСергій Юрійович Колосовський\nСергій Колосовський\nКолосовський Сергій Юрійович\nСергій\nПодружжя\nКолосовська О. В., 17. 03. 1975, шлюб розірвано в вересні 2014\nІнше\nЧуркіна К. С., 12. 09. 1940\nтеща\nКолосовський Сергій Юрійович\nКолосовський\nЮрійович\n238157\n8276\n238157\n8276\n2014\nКолосовська О. В., 17. 03. 1975, шлюб розірвано в вересні 2014\nПодружжя\nІнше\nЧуркіна К. С., 12. 09. 1940\nтеща\nЮрійович\nКолосовський\nСергій\nКолосовський Сергій Юрійович\nСергій Юрійович Колосовський\nСергій Колосовський\nКолосовський Сергій Юрійович\nМиколаївська область\nЗагальний апеляційний суд\nсуддя апеляційного суду миколаївської області\nКолосовський Сергій Юрійович\n2006\nNissan Primera\n1.8\n8276\n238157\n8276\n238157\n63.1\n211.5\n63.1\n211.5\n2014","general":{"name_hidden":false,"name":"Сергій","last_name_hidden":false,"inn":"","family":[{"inn":"","inn_hidden":true,"inn_unclear":false,"relations_hidden":false,"relations_other":"","relations":"Подружжя","name_hidden":false,"family_name":"Колосовська О. В., 17. 03. 1975, шлюб розірвано в вересні 2014","name_unclear":true},{"inn":"","inn_hidden":true,"relations_unclear":true,"relations_hidden":false,"relations_other":"теща","relations":"Інше","name_hidden":false,"inn_unclear":false,"family_name":"Чуркіна К. С., 12. 09. 1940","name_unclear":false}],"patronymic":"Юрійович","inn_hidden":true,"family_raw":"","inn_unclear":false,"post":{"post_unclear":false,"region_unclear":false,"post":"суддя апеляційного суду миколаївської області","office":"Загальний апеляційний суд","region":"Миколаївська область","post_hidden":false,"office_hidden":false,"office_unclear":false,"region_hidden":false},"last_name_unclear":false,"full_name":"Колосовський Сергій Юрійович","addresses":[{"place_district":"","place_address_hidden":true,"place_city":"","place_city_type_hidden":true,"place_district_hidden":true,"place_city_type":"","place_city_hidden":true,"place_address_unclear":false,"place_address":"","place_hidden":true,"place":""}],"last_name":"Колосовський","patronymic_hidden":false,"full_name_suggest":{"output":"Колосовський Сергій Юрійович","input":["Колосовський Сергій Юрійович","Сергій Юрійович Колосовський","Сергій Колосовський"]},"name_unclear":false},"source":"VULYK","estate":{"23":[{"space_unclear":false,"costs":"","costs_comment":"","address_hidden":true,"region_hidden":true,"space_comment":"","space_hidden":false,"space":"211.5","address":"","region":"","address_unclear":false,"costs_rent_comment":"","space_units":"м²","costs_rent":""}],"24":[{"space_unclear":false,"costs":"","costs_comment":"","address_hidden":true,"region_hidden":true,"space_comment":"","space_hidden":false,"space":"63.1","address":"","region":"","address_unclear":false,"costs_rent_comment":"","space_units":"м²","costs_rent":""}],"29":[{"space_unclear":false,"address_hidden":true,"region_hidden":true,"space_comment":"","space_units_hidden":false,"space":"211.5","address":"","region":"","address_unclear":false,"costs_rent_comment":"","costs_property":"","space_units":"м²","costs_property_comment":"","costs_rent":""}],"30":[{"address_hidden":true,"region_hidden":true,"space_comment":"","space":"63.1","address":"","region":"","costs_property":"","costs_rent_comment":"","space_comment_unclear":false,"address_unclear":false,"space_units":"м²","costs_property_comment":"","costs_rent":""}]},"intro":{"declaration_year":"2014","isnotdeclaration":"","declaration_year_hidden":false}}