{"income":{"5":{"family_comment":"","value":"293857.49","value_unclear":false,"family":"25618","comment":""},"6":{"value":"273819","value_unclear":false,"family_hidden":false,"family_comment":"","family":"25618","comment":""},"7":{"source_name_unclear":false,"value":"","family_comment":"","source_name":"","family":"","comment":""},"8":{"family_comment":"","value":"","family":"","comment":""},"9":{"family_comment":"","value":"","family":"","comment":""},"10":{"family_comment":"","value":"","family":"","comment":""},"11":{"family_comment":"","value":"","comment_unclear":false,"family":"","comment":""},"12":{"family_comment":"","value":"","family":"","comment":""},"13":{"family_comment":"","value":"","family":"","comment":""},"14":{"family_comment":"","value":"","family":"","comment":""},"15":{"family_comment":"","value":"","family":"","comment":""},"16":{"family_comment":"","value":"","family":"","comment":""},"17":{"family_comment":"","value":"","family":"","comment":""},"18":{"family_comment":"","value":"","family":"","comment":""},"19":{"family_comment":"","value":"","family":"","comment":""},"20":{"value":"20038.49","family_comment":"","value_unclear":false,"family_unclear":false,"comment_unclear":false,"comment":"","family":""}},"vehicle":{"35":[{"brand_info":"1368 куб. см., 170 к. с","sum_rent_comment":"","brand":"Alfa Romeo Giulietta","sum_comment":"","brand_unclear":false,"year":"2013","sum_rent_unclear":false,"brand_info_hidden":false,"brand_info_unclear":false,"sum":"","sum_rent":""}],"40":[{"brand_info":"2995 куб. см., 183 Квт","sum_rent_comment":"","brand":"Lexus IS 300","sum_comment":"","year":"2007","brand_hidden":false,"brand_info_hidden":false,"brand_info_unclear":false,"sum":"","sum_rent":""}]},"id":"vulyk_101_62","declaration":{"additional_info_text":"","notfull_lostpages":"","date":"2016-03-29T00:00:00","notfull":"","additional_info":"","url":"http://static.declarations.com.ua/declarations/chosen_ones/judges_batch/727_svatanenko_viktor_ivanovych_2015.pdf"},"liabilities":{"54":{"sum_foreign_comment":"","sum":"","sum_comment":"","sum_comment_unclear":false,"sum_hidden":false,"sum_comment_hidden":false,"sum_unclear":false,"sum_foreign":""},"55":{"sum_foreign_comment":"","sum":"","sum_comment":"","sum_foreign":""},"56":{"sum_foreign_comment":"","sum":"16550","sum_comment":"","sum_comment_hidden":false,"sum_unclear":false,"sum_foreign":""},"57":{"sum_foreign_comment":"","sum":"","sum_comment":"","sum_hidden":false,"sum_comment_hidden":false,"sum_unclear":false,"sum_foreign":""},"58":{"sum_foreign_comment":"","sum":"","sum_comment":"","sum_comment_unclear":false,"sum_hidden":false,"sum_comment_hidden":false,"sum_unclear":false,"sum_foreign":""},"59":{"sum_foreign_comment":"","sum":"","sum_comment":"","sum_foreign":""},"60":{"sum_foreign_comment":"","sum":"","sum_comment":"","sum_hidden":false,"sum_comment_hidden":false,"sum_unclear":false,"sum_foreign":""},"61":{"sum_foreign_comment":"","sum":"","sum_comment":"","sum_foreign":""},"62":{"sum_foreign_comment":"","sum":"23050","sum_comment":"","sum_comment_unclear":false,"sum_foreign":""},"63":{"sum_foreign_comment":"","sum_comment_hidden":false,"sum":"","sum_comment":"","sum_foreign":""},"64":{"sum_foreign_comment":"","sum_comment_hidden":false,"sum":"","sum_comment":"","sum_foreign":""}},"ft_src":"23050\n16550\nсуддя апеляційного суду одеської області\nОдеська область\nЗагальний апеляційний суд\nВіктор\nСватаненко Л. П\nПодружжя\nІванович\nСватаненко Віктор Іванович\nСватаненко\nСватаненко Віктор Іванович\nВіктор Іванович Сватаненко\nВіктор Сватаненко\nСватаненко Віктор Іванович\nAlfa Romeo Giulietta\n1368 куб. см., 170 к. с\n2013\n2995 куб. см., 183 Квт\nLexus IS 300\n2007\n190\n473\n2015\n25618\n273819\n25618\n293857.49\n20038.49\nAlfa Romeo Giulietta\n1368 куб. см., 170 к. с\n2013\n2995 куб. см., 183 Квт\n2007\nLexus IS 300\n2015\nПодружжя\nСватаненко Л. П\nСватаненко Віктор Іванович\nВіктор Іванович Сватаненко\nВіктор Сватаненко\nСватаненко Віктор Іванович\nВіктор\nСватаненко Віктор Іванович\nІванович\nЗагальний апеляційний суд\nсуддя апеляційного суду одеської області\nОдеська область\nСватаненко\n16550\n23050\n273819\n25618\n20038.49\n293857.49\n25618\n473\n190\n16550\n23050\nСватаненко Л. П\nПодружжя\nВіктор\nІванович\nСватаненко\nСватаненко Віктор Іванович\nВіктор Іванович Сватаненко\nВіктор Сватаненко\nСватаненко Віктор Іванович\nсуддя апеляційного суду одеської області\nЗагальний апеляційний суд\nОдеська область\nСватаненко Віктор Іванович\n2013\nAlfa Romeo Giulietta\n1368 куб. см., 170 к. с\nLexus IS 300\n2995 куб. см., 183 Квт\n2007\n20038.49\n25618\n293857.49\n273819\n25618\n190\n473\n2015","general":{"inn":"","name":"Віктор","inn_unclear":false,"family":[{"inn":"","relations":"Подружжя","relations_other":"","inn_hidden":true,"family_name":"Сватаненко Л. П","name_hidden":true,"name_unclear":true}],"inn_hidden":true,"family_raw":"","last_name":"Сватаненко","post":{"region":"Одеська область","region_unclear":false,"post":"суддя апеляційного суду одеської області","office_unclear":false,"office":"Загальний апеляційний суд"},"full_name":"Сватаненко Віктор Іванович","addresses":[{"place_district":"","place_city_hidden":true,"place_city":"","place_city_type_hidden":true,"place_district_hidden":true,"place_city_type":"","place_address_hidden":true,"place_address":"","place_hidden":true,"place":""}],"patronymic":"Іванович","patronymic_hidden":false,"full_name_suggest":{"output":"Сватаненко Віктор Іванович","input":["Сватаненко Віктор Іванович","Віктор Іванович Сватаненко","Віктор Сватаненко"]}},"source":"VULYK","estate":{"23":[{"space_unclear":false,"costs":"","costs_comment":"","address_hidden":false,"region_hidden":true,"space_comment":"","space_hidden":false,"space":"","address":"","costs_comment_unclear":false,"region":"","space_units_unclear":false,"space_units":"м²","costs_rent":"","costs_rent_comment":""}],"24":[{"space_unclear":false,"costs":"","costs_comment":"","address_hidden":false,"region_hidden":true,"space_comment":"","space":"","address":"","region":"","costs_rent_comment":"","space_units":"м²","costs_rent":""}],"29":[{"costs_rent":"","region":"","costs_property":"","costs_rent_comment":"","address_hidden":true,"region_hidden":true,"space_comment":"","costs_property_comment":"","space_units":"м²","space":"473","address":""}],"30":[{"costs_rent":"","region":"","costs_property":"","costs_rent_comment":"","address_hidden":true,"region_hidden":true,"space_comment":"","costs_property_comment":"","space_units":"м²","space":"190","address":""}]},"intro":{"declaration_year":"2015"}}