{"income":{"5":{"value":"269219","family_comment":"","comment_unclear":false,"family_unclear":false,"family":"8867","comment":""},"6":{"family_comment":"","value":"255913","family":"","comment":""},"7":{"source_name_unclear":false,"value":"","comment_unclear":false,"family_comment":"","source_name":"","family":"","comment":""},"8":{"family_comment":"","value":"","family":"","comment":""},"9":{"family_comment":"","value":"9306","family":"8867","comment":""},"10":{"family_comment":"","value":"","family":"","comment":""},"11":{"family_comment":"","value":"","family":"","comment":""},"12":{"family_comment":"","value":"","family":"","comment":""},"13":{"family_comment":"","value":"","family":"","comment":""},"14":{"family_comment":"","value":"","family":"","comment":""},"15":{"family_comment":"","value":"","family":"","comment":""},"16":{"family_comment":"","family_unclear":false,"value":"","family":"","comment":""},"17":{"family_comment":"","value":"","family":"","comment":""},"18":{"family_comment":"","value":"","family":"","comment":""},"19":{"family_comment":"","value":"","family":"","comment":""},"20":{"value":"4000","family_comment":"","comment_unclear":false,"family_unclear":false,"family":"","comment":"","family_comment_unclear":false}},"vehicle":{"40":[{"brand_info":"1.6, 84 к.с.","sum":"","brand":"ВАЗ 21104","sum_comment":"","year":"2004","brand_hidden":false,"sum_rent_comment":"","sum_rent":""}]},"id":"vulyk_107_100","banks":{"45":[{"sum_foreign_comment":"","sum_unclear":false,"sum":"45000","sum_comment":"Укрексімбанк","sum_comment_unclear":false,"sum_foreign_units":"UAH","sum_comment_hidden":false,"sum_units":"UAH","sum_foreign":""}],"46":[{"sum_foreign_comment":"","sum":"45000","sum_comment":"","sum_foreign_units":"UAH","sum_units":"UAH","sum_foreign":""}],"51":[{"sum_foreign_comment":"","sum_unclear":false,"sum":"60002","sum_comment":"Ощадбанк України","sum_comment_unclear":false,"sum_foreign_units":"UAH","sum_units":"UAH","sum_foreign":""}]},"declaration":{"additional_info_text":"","notfull_lostpages":"","date":"2016-03-30T00:00:00","notfull":"","additional_info":"","url":"http://static.declarations.com.ua/declarations/chosen_ones/judges_batch/2079_bershadska_halyna_vasylivna.pdf"},"liabilities":{"54":{"sum_foreign_comment":"","sum":"","sum_comment":"","sum_comment_unclear":false,"sum_comment_hidden":false,"sum_foreign":""},"55":{"sum_foreign_comment":"","sum":"","sum_comment":"","sum_foreign":""},"56":{"sum_foreign_comment":"","sum":"","sum_comment":"","sum_unclear":false,"sum_foreign":""},"57":{"sum_foreign_comment":"","sum":"4000","sum_comment":"","sum_comment_unclear":false,"sum_foreign":""},"58":{"sum_foreign_comment":"","sum":"188","sum_comment":"Укрексімбанк","sum_comment_unclear":false,"sum_unclear":false,"sum_foreign":""},"59":{"sum_foreign_comment":"","sum":"","sum_comment":"","sum_unclear":false,"sum_foreign":""},"60":{"sum_foreign_comment":"","sum":"","sum_comment":"","sum_comment_unclear":false,"sum_comment_hidden":false,"sum_foreign":""},"61":{"sum_foreign_comment":"","sum":"","sum_comment":"","sum_foreign":""},"62":{"sum_foreign_comment":"","sum":"","sum_comment":"","sum_foreign":""},"63":{"sum_foreign_comment":"","sum":"","sum_comment":"","sum_foreign":""},"64":{"sum_foreign_comment":"","sum":"","sum_comment":"","sum_foreign":""}},"ft_src":"2004\n1.6, 84 к.с.\nВАЗ 21104\n45000\nОщадбанк України\n60002\nУкрексімбанк\n45000\n2015\n1.6, 84 к.с.\n2004\nВАЗ 21104\n45000\nУкрексімбанк\n60002\nОщадбанк України\n45000\n2015\nБершадська\nПодружжя\nБершадський О. М\nДитина\nБершадський С. О\nБершадська Галина Василівна\nГалина Василівна Бершадська\nГалина Бершадська\nБершадська Галина Василівна\nГалина\nВасилівна\nБершадська Галина Василівна\nЗагальний апеляційний суд\nсуддя апеляційного суду тернопільської області\nТернопільська область\n4000\nУкрексімбанк\n188\n255913\n4000\n269219\n8867\n9306\n8867\n41\nУкрексімбанк\n188\n4000\n41\nБершадський О. М\nПодружжя\nБершадський С. О\nДитина\nБершадська\nВасилівна\nсуддя апеляційного суду тернопільської області\nТернопільська область\nЗагальний апеляційний суд\nБершадська Галина Василівна\nБершадська Галина Василівна\nГалина Василівна Бершадська\nГалина Бершадська\nБершадська Галина Василівна\nГалина\n255913\n8867\n9306\n8867\n269219\n4000","general":{"inn_hidden":true,"inn":"","last_name":"Бершадська","post":{"post_unclear":false,"office":"Загальний апеляційний суд","post":"суддя апеляційного суду тернопільської області","region":"Тернопільська область"},"name":"Галина","full_name":"Бершадська Галина Василівна","family_raw":"","addresses":[{"place_district":"","place_address_hidden":true,"place_city":"","place_address":"","place_district_hidden":true,"place_city_type":"","place_city_hidden":true,"place_city_type_hidden":true,"place_hidden":true,"place":""}],"family":[{"inn":"","inn_hidden":true,"family_name":"Бершадський О. М","relations_other":"","relations":"Подружжя","name_hidden":true,"name_unclear":false},{"inn":"","inn_hidden":false,"family_name":"Бершадський С. О","relations_other":"","relations":"Дитина","name_hidden":false,"name_unclear":false}],"full_name_suggest":{"output":"Бершадська Галина Василівна","input":["Бершадська Галина Василівна","Галина Василівна Бершадська","Галина Бершадська"]},"patronymic":"Василівна"},"source":"VULYK","estate":{"25":[{"space_unclear":false,"costs":"","costs_comment":"","address_hidden":true,"region_hidden":true,"space_comment":"","space_hidden":false,"space":"41","address":"","region":"","costs_rent_comment":"","space_units":"м²","costs_rent":""}]},"intro":{"declaration_year":"2015","isnotdeclaration":""}}