{"income":{"5":{"value":"236107","family_comment":"","value_unclear":false,"family_unclear":false,"comment_unclear":false,"comment":"","family":"15540"},"6":{"family_comment":"","value":"223926","comment_unclear":false,"family":"8540","comment":""},"7":{"family_comment":"","value":"","source_name":"","family":"","comment":""},"8":{"family_comment":"","value":"","family":"","comment":""},"9":{"family_comment":"","value":"","value_unclear":false,"family":"","comment":""},"10":{"family_comment":"","value":"12180","value_unclear":false,"family":"609","comment":""},"11":{"family_comment":"","value":"","family":"","comment":""},"12":{"family_comment":"","value":"","family":"","comment":""},"13":{"family_comment":"","value":"","family":"","comment":""},"14":{"family_comment":"","value":"","family":"","comment":""},"15":{"family_comment":"","value":"","family":"","comment":""},"16":{"family_comment":"","value":"","family":"","comment":""},"17":{"family_comment":"","value":"","value_unclear":false,"family":"","comment":""},"18":{"family_comment":"","value":"","value_unclear":false,"family":"","comment":""},"19":{"family_comment":"","value":"","family":"","comment":""},"20":{"value":"","family_comment":"","value_unclear":false,"family_unclear":false,"comment_unclear":false,"comment":"","family":"7000"}},"vehicle":{"35":[{"year_hidden":false,"brand_info":"","sum_rent_comment":"","year":"2007","sum_hidden":false,"brand_info_hidden":true,"brand_info_unclear":false,"year_unclear":false,"sum_rent":"","sum":"","brand":"Daewoo Nexia","sum_comment":"","brand_unclear":false,"brand_hidden":false}],"41":[{"brand_info":"","sum_rent_comment":"","brand":"ІЖ 2715","sum_comment":"","year":"1984","brand_info_hidden":true,"sum":"","sum_rent":""}]},"id":"vulyk_84_45","declaration":{"additional_info_text":"","notfull_lostpages":"","date":"2015-03-06T00:00:00","notfull":"","additional_info":"","url":"http://static.declarations.com.ua/declarations/chosen_ones/judges_batch/2459_kopeika_tetiana_opanasivna.pdf"},"liabilities":{"54":{"sum_foreign_comment":"","sum_comment_hidden":false,"sum":"","sum_comment":"","sum_foreign":""},"55":{"sum_foreign_comment":"","sum":"","sum_comment":"","sum_foreign":""},"56":{"sum_foreign_comment":"","sum":"","sum_comment":"","sum_foreign":""},"57":{"sum_foreign_comment":"","sum_comment_hidden":false,"sum":"","sum_comment":"","sum_foreign":""},"58":{"sum_foreign_comment":"","sum_comment_hidden":false,"sum":"","sum_comment":"","sum_foreign":""},"59":{"sum_foreign_comment":"","sum":"","sum_comment":"","sum_foreign":""},"60":{"sum_foreign_comment":"","sum":"","sum_comment":"","sum_foreign":""},"61":{"sum_foreign_comment":"","sum":"","sum_comment":"","sum_foreign":""},"62":{"sum_foreign_comment":"","sum":"25000","sum_comment":"","sum_foreign":""},"63":{"sum_foreign_comment":"","sum_comment_hidden":false,"sum":"","sum_comment":"","sum_foreign":""},"64":{"sum_foreign_comment":"","sum_comment_hidden":false,"sum":"","sum_comment":"","sum_foreign":""}},"ft_src":"25000\n56101\nсуддя баштанського районного суду миколаївської області\nМиколаївська область\nЗагальний місцевий суд\nТетяна\nКопейка Л. А\nПодружжя\nКопейка М. Л\nДитина\nОпанасівна\nКопейка Тетяна Опанасівна\nТетяна Опанасівна Копейка\nТетяна Копейка\nКопейка Тетяна Опанасівна\nКопейка Тетяна Опанасівна\nКопейка\n1984\nІЖ 2715\nDaewoo Nexia\n2007\n81.1\n720\n1200\nвласність\n20000\nсуборенда\n318000\n67.3\n2014\n8540\n223926\n609\n12180\n15540\n236107\n7000\nDaewoo Nexia\n2007\nІЖ 2715\n1984\n2014\nКопейка Тетяна Опанасівна\nТетяна Опанасівна Копейка\nТетяна Копейка\nКопейка Тетяна Опанасівна\nТетяна\nПодружжя\nКопейка Л. А\nДитина\nКопейка М. Л\nКопейка Тетяна Опанасівна\nОпанасівна\nсуддя баштанського районного суду миколаївської області\nЗагальний місцевий суд\nМиколаївська область\nКопейка\n56101\n25000\n223926\n8540\n7000\n236107\n15540\n12180\n609\n720\n1200\n20000\nвласність\n318000\nсуборенда\n81.1\n67.3\n25000\nКопейка Л. А\nПодружжя\nКопейка М. Л\nДитина\nОпанасівна\nКопейка\nТетяна\nКопейка Тетяна Опанасівна\nТетяна Опанасівна Копейка\nТетяна Копейка\nКопейка Тетяна Опанасівна\n56101\nМиколаївська область\nсуддя баштанського районного суду миколаївської області\nЗагальний місцевий суд\nКопейка Тетяна Опанасівна\nІЖ 2715\n1984\nDaewoo Nexia\n2007\n609\n12180\n7000\n236107\n15540\n8540\n223926\n81.1\n67.3\n720\n1200\nвласність\n20000\nсуборенда\n318000\n2014","general":{"inn":"","name":"Тетяна","inn_unclear":false,"family":[{"inn":"","inn_hidden":true,"inn_unclear":false,"relations_hidden":false,"relations_other":"","relations":"Подружжя","name_hidden":true,"family_name":"Копейка Л. А","name_unclear":false},{"inn":"","relations":"Дитина","relations_other":"","inn_hidden":false,"family_name":"Копейка М. Л","name_hidden":false,"name_unclear":false}],"inn_hidden":true,"family_raw":"","last_name":"Копейка","post":{"post_unclear":false,"region_unclear":false,"post":"суддя баштанського районного суду миколаївської області","candidate":"","office_hidden":false,"region":"Миколаївська область","post_hidden":false,"office":"Загальний місцевий суд","office_unclear":false,"region_hidden":false},"full_name":"Копейка Тетяна Опанасівна","addresses":[{"place_city_type_unclear":false,"place_address":"56101","place_district_hidden":true,"place_city_type":"","place_address_hidden":true,"place_address_unclear":false,"place_city_type_hidden":true,"place":"","place_district":"","place_unclear":false,"place_city":"","place_city_unclear":false,"place_hidden":true,"place_city_hidden":true,"place_district_unclear":false}],"patronymic":"Опанасівна","full_name_suggest":{"output":"Копейка Тетяна Опанасівна","input":["Копейка Тетяна Опанасівна","Тетяна Опанасівна Копейка","Тетяна Копейка"]}},"source":"VULYK","estate":{"25":[{"region_unclear":false,"space_hidden":false,"costs":"","costs_comment":"","address_hidden":false,"region_hidden":false,"space_comment":"","space":"67.3","address":"","costs_comment_unclear":false,"costs_rent_comment_unclear":false,"region":"","address_unclear":false,"costs_rent_comment":"","space_units":"м²","costs_rent":""}],"26":[{"costs_rent":"","region":"","costs":"","costs_rent_comment":"","costs_comment":"","address_hidden":true,"region_hidden":true,"space_comment":"","space_units":"м²","space":"","address":""}],"29":[{"region_unclear":false,"address_hidden":true,"region_hidden":true,"space_comment":"","space":"720","address":"","region":"","costs_property":"","costs_rent_comment":"","address_unclear":false,"space_units":"м²","costs_property_comment":"","costs_rent":""},{"costs_rent":"","region":"","costs_property":"","costs_rent_comment":"","address_unclear":false,"space_comment":"","costs_property_comment":"","space_units":"м²","space":"1200","address":""},{"costs_rent":"","region":"","costs_property":"","costs_rent_comment":"","space_comment_unclear":true,"space_comment":"власність","costs_property_comment":"","space_units":"м²","space":"20000","address":""},{"costs_rent":"","space_unclear":false,"region":"","costs_property":"","costs_rent_comment":"","space_comment_unclear":true,"space_comment":"суборенда","costs_property_comment":"","space_units":"м²","space":"318000","address":""}],"30":[{"costs_rent":"","region":"","costs_property":"","costs_rent_comment":"","address_hidden":true,"region_hidden":true,"space_comment":"","costs_property_comment":"","space_units":"м²","space":"81.1","address":""}]},"intro":{"declaration_year":"2014","isnotdeclaration":"","declaration_year_unclear":false}}