{"income":{"5":{"value":"486673","family_comment":"","value_unclear":false,"value_hidden":false,"family_unclear":false,"family":"24000","comment":""},"6":{"value":"300964","family_hidden":false,"value_hidden":false,"family_comment":"","family_comment_hidden":false,"comment":"","family":""},"7":{"value":"","value_unclear":false,"family_hidden":false,"value_hidden":false,"family_comment":"","source_name":"","family":"","comment":"","source_name_hidden":false},"8":{"value":"","comment_hidden":false,"family_hidden":false,"value_hidden":false,"family_comment":"","family":"","comment":""},"9":{"value":"","family_comment":"","comment_hidden":false,"family_hidden":false,"value_hidden":false,"family_unclear":false,"family":"","comment":""},"10":{"value":"4956","comment_hidden":false,"family_hidden":false,"value_hidden":false,"family_comment":"","family":"","comment":""},"11":{"value":"","value_unclear":false,"comment_hidden":false,"family_hidden":false,"value_hidden":false,"family_comment":"","family":"","comment":""},"12":{"value":"","comment_hidden":false,"family_hidden":false,"value_hidden":false,"family_comment":"","family":"","comment":""},"13":{"value":"","comment_hidden":false,"family_hidden":false,"value_hidden":false,"family_comment":"","family":"","comment":""},"14":{"value":"139584","comment_hidden":false,"family_hidden":false,"value_hidden":false,"family_comment":"","family":"","comment":""},"15":{"value":"","comment_hidden":false,"family_hidden":false,"value_hidden":false,"family_comment":"","family":"","comment":""},"16":{"value":"","comment_hidden":false,"family_hidden":false,"value_hidden":false,"family_comment":"","family":"","comment":""},"17":{"value":"","comment_hidden":false,"family_hidden":false,"value_hidden":false,"family_comment":"","family":"24000","comment":""},"18":{"value":"","value_unclear":false,"comment_hidden":false,"family_hidden":false,"value_hidden":false,"family_comment":"","family":"","comment":""},"19":{"value":"","comment_hidden":false,"family_hidden":false,"value_hidden":false,"family_comment":"","family":"","comment":""},"20":{"value":"41169","value_unclear":false,"family_comment":"","comment_unclear":false,"comment":"","family":""}},"vehicle":{"35":[{"brand_info":"2987 куб. см.","sum_rent_comment":"","sum_rent_hidden":false,"year":"2010","sum_rent_unclear":false,"brand_info_hidden":false,"brand_info_unclear":false,"year_unclear":false,"sum_hidden":false,"sum_rent":"","sum":"","brand":"Mercedes-Benz GL 350","sum_comment":"","brand_unclear":false,"sum_rent_comment_hidden":false,"sum_comment_hidden":false,"sum_unclear":false}],"40":[{"year_hidden":false,"brand_info":"1400 куб см","sum_rent_comment":"","brand":"Volkswagen Cross Touran","sum_comment":"","brand_unclear":false,"year":"2008","brand_hidden":false,"brand_info_unclear":false,"sum":"","sum_rent":""}]},"id":"vulyk_1_409","declaration":{"additional_info_text":"","notfull_lostpages":"","date":"2014-03-31T00:00:00","notfull":"","additional_info":"","url":"http://static.declarations.com.ua/declarations/chosen_ones/judges_batch/241_dem’yanosov_mykola_vlasovych.pdf"},"liabilities":{"54":{"sum_foreign_comment":"","sum_foreign_hidden":false,"sum_comment":"","sum_hidden":false,"sum_comment_hidden":false,"sum":"","sum_foreign":""},"55":{"sum_foreign_comment":"","sum":"","sum_hidden":false,"sum_comment":"","sum_foreign":""},"56":{"sum_foreign_comment":"","sum":"","sum_comment":"","sum_foreign":""},"57":{"sum_foreign_comment":"","sum_foreign_hidden":false,"sum_comment":"","sum_hidden":false,"sum_comment_hidden":false,"sum_unclear":false,"sum":"","sum_foreign":""},"58":{"sum_foreign_comment":"","sum_foreign_hidden":false,"sum_comment":"","sum_hidden":false,"sum_comment_hidden":false,"sum_unclear":false,"sum":"","sum_foreign":""},"59":{"sum_foreign_comment":"","sum":"","sum_hidden":false,"sum_comment":"","sum_foreign":""},"60":{"sum_foreign_comment":"","sum_foreign_hidden":false,"sum_comment":"","sum_hidden":false,"sum_comment_hidden":false,"sum_unclear":false,"sum":"","sum_foreign":""},"61":{"sum_foreign_comment":"","sum":"","sum_hidden":false,"sum_comment":"","sum_foreign":""},"62":{"sum_foreign_comment":"","sum":"","sum_comment":"","sum_hidden":false,"sum_comment_hidden":false,"sum_foreign":""},"63":{"sum_foreign_comment":"","sum":"","sum_hidden":false,"sum_comment":"","sum_foreign":""},"64":{"sum_foreign_comment":"","sum":"","sum_hidden":false,"sum_comment":"","sum_foreign":""}},"ft_src":"суддя вищого спецiалiзованого суду україни з розгляду цивiльних і кримiнальних справ\nЗагальнодержавний регіон\nВищий спеціалізований суд з розгляду цивільних і кримінальних справ\nМикола\nДем'яносова Г. А\nПодружжя\nДем'яносова Д. М\nДитина\nДем'яносов Д. М\nДитина\nВласович\nДем'яносов Микола Власович\nМикола Власович Дем'яносов\nМикола Дем'яносов\nДем'яносов Микола Власович\nДем'яносов Микола Власович\nДем'яносов\n2987 куб. см.\n2010\nMercedes-Benz GL 350\nVolkswagen Cross Touran\n1400 куб см\n2008\n20\n655\n648\n85.6\n53.3\n19990\n74000\n96\n108.3\n2013\n300964\n139584\n4956\n24000\n486673\n24000\n41169\n2987 куб. см.\nMercedes-Benz GL 350\n2010\n1400 куб см\nVolkswagen Cross Touran\n2008\n20\n96\n108.3\n19990\n74000\n655\n648\n85.6\n53.3\nДем'яносов Микола Власович\nМикола Власович Дем'яносов\nМикола Дем'яносов\nДем'яносов Микола Власович\nДем'яносов Микола Власович\nПодружжя\nДем'яносова Г. А\nДитина\nДем'яносова Д. М\nДитина\nДем'яносов Д. М\nМикола\nВласович\nВищий спеціалізований суд з розгляду цивільних і кримінальних справ\nсуддя вищого спецiалiзованого суду україни з розгляду цивiльних і кримiнальних справ\nЗагальнодержавний регіон\nДем'яносов\n300964\n41169\n24000\n139584\n486673\n24000\n4956\n2013\nДем'яносова Г. А\nПодружжя\nДитина\nДем'яносова Д. М\nДем'яносов Д. М\nДитина\nВласович\nДем'яносов\nМикола\nДем'яносов Микола Власович\nМикола Власович Дем'яносов\nМикола Дем'яносов\nДем'яносов Микола Власович\nЗагальнодержавний регіон\nсуддя вищого спецiалiзованого суду україни з розгляду цивiльних і кримiнальних справ\nВищий спеціалізований суд з розгляду цивільних і кримінальних справ\nДем'яносов Микола Власович\n2010\nMercedes-Benz GL 350\n2987 куб. см.\n2008\nVolkswagen Cross Touran\n1400 куб см\n139584\n4956\n41169\n486673\n24000\n24000\n300964\n53.3\n19990\n74000\n85.6\n20\n96\n108.3\n655\n648\n2013","general":{"inn":"","name":"Микола","inn_unclear":false,"family":[{"inn":"","inn_hidden":true,"relations_unclear":false,"relations_hidden":false,"relations_other":"","relations":"Подружжя","name_hidden":false,"family_name":"Дем'яносова Г. А","name_unclear":true},{"inn":"","inn_hidden":true,"relations_unclear":false,"relations_hidden":false,"relations_other":"","relations":"Дитина","name_hidden":false,"family_name":"Дем'яносова Д. М","name_unclear":false},{"inn":"","relations":"Дитина","relations_other":"","inn_hidden":true,"family_name":"Дем'яносов Д. М","name_hidden":false,"name_unclear":true}],"inn_hidden":false,"family_raw":"","last_name":"Дем'яносов","post":{"post_unclear":false,"post":"суддя вищого спецiалiзованого суду україни з розгляду цивiльних і кримiнальних справ","candidate":"","office_hidden":false,"region":"Загальнодержавний регіон","office":"Вищий спеціалізований суд з розгляду цивільних і кримінальних справ","office_unclear":false,"region_hidden":false},"full_name_suggest":{"output":"Дем'яносов Микола Власович","input":["Дем'яносов Микола Власович","Микола Власович Дем'яносов","Микола Дем'яносов"]},"full_name":"Дем'яносов Микола Власович","addresses":[{"place_city_type_unclear":false,"place_address":"","place_district_hidden":true,"place_city_type":"","place_city_hidden":true,"place_city_type_hidden":true,"place":"","place_district":"","place_unclear":false,"place_city":"","place_city_unclear":false,"place_hidden":true,"place_address_hidden":true}],"patronymic":"Власович","last_name_unclear":false,"name_unclear":false},"source":"VULYK","estate":{"23":[{"space_hidden":false,"costs":"","costs_comment":"","address_hidden":true,"region_hidden":true,"space_comment":"","space_unclear":false,"space":"19990","address":"","space_comment_unclear":false,"region":"","costs_rent_comment":"","costs_unclear":false,"space_comment_hidden":false,"space_units":"м²","costs_rent":""},{"costs_rent":"","region":"","costs":"","costs_rent_comment":"","costs_comment":"","address_hidden":false,"region_hidden":false,"space_comment":"","space_units":"м²","space":"74000","address":""}],"24":[{"costs":"","costs_comment":"","address_hidden":true,"region_hidden":true,"space_comment":"","space":"85.6","address":"","region":"","address_unclear":false,"costs_rent_comment":"","space_comment_unclear":false,"space_units":"м²","costs_rent":""}],"25":[{"space_unclear":true,"costs":"","costs_comment":"","address_hidden":true,"region_hidden":true,"space_comment":"","space_hidden":false,"space":"96","address":"","region":"","costs_rent_comment":"","space_comment_unclear":false,"space_comment_hidden":false,"space_units":"м²","costs_rent":""},{"space_unclear":true,"costs":"","costs_comment":"","address_hidden":true,"region_hidden":true,"space_comment":"","space":"108.3","address":"","region":"","address_unclear":false,"costs_rent_comment":"","space_comment_hidden":false,"space_units":"м²","costs_rent":""}],"27":[{"space_hidden":false,"costs":"","costs_comment":"","costs_hidden":false,"address_hidden":true,"region_hidden":true,"space_comment":"","space":"20","address":"","region":"","address_unclear":false,"costs_rent_comment":"","space_units":"м²","costs_rent":""}],"29":[{"space_unclear":false,"address_hidden":true,"region_hidden":true,"space_comment":"","space_hidden":false,"space":"655","address":"","region":"","costs_property":"","costs_rent_comment":"","space_units":"м²","costs_property_comment":"","costs_rent":""},{"costs_rent":"","region":"","costs_property":"","costs_rent_comment":"","region_hidden":true,"space_comment":"","costs_property_comment":"","space_units":"м²","space":"648","address":""}],"31":[{"space_unclear":false,"address_hidden":true,"region_hidden":true,"space_comment":"","space_hidden":false,"space":"53.3","address":"","region":"","costs_property":"","costs_rent_comment":"","space_comment_unclear":false,"space_units":"м²","costs_property_comment":"","costs_rent":""}]},"intro":{"declaration_year":"2013","isnotdeclaration":"","declaration_year_unclear":false,"declaration_year_hidden":false}}