{"income":{"5":{"value":"247160","comment_hidden":false,"family_comment":"","family":"46094","comment":"","family_comment_hidden":false},"6":{"value":"234543","family_comment":"","comment_hidden":false,"family_hidden":false,"family_unclear":false,"family_comment_hidden":false,"comment":"","family":"46094"},"7":{"value":"","comment_hidden":false,"family_comment_hidden":false,"family_comment":"","source_name":"","family":"","comment":"","source_name_hidden":false},"8":{"family_comment":"","value":"","family":"","comment":""},"9":{"value":"","family_comment":"","value_unclear":false,"family_unclear":false,"comment_unclear":false,"comment":"","family":""},"10":{"family_comment":"","family_unclear":false,"value":"12617","family":"","comment":""},"11":{"family_comment":"","value":"","family":"","comment":""},"12":{"family_comment":"","value":"","family":"","comment":""},"13":{"family_comment":"","value":"","family":"","comment":""},"14":{"family_comment":"","value":"","family":"","comment":""},"15":{"family_comment":"","value":"","comment_unclear":false,"family":"","comment":""},"16":{"family_comment":"","value":"","comment_unclear":false,"family":"","comment":""},"17":{"family_comment":"","value":"","family":"","comment":""},"18":{"family_comment":"","value":"","family":"","comment":""},"19":{"family_comment":"","value":"","family":"","comment":""},"20":{"value":"","family_comment":"","value_unclear":false,"family_unclear":false,"family_comment_unclear":false,"family_comment_hidden":false,"comment":"","family":""}},"vehicle":{"35":[{"brand_info":"2400 куб. см., 122 кВт , 457.4 см","sum_rent_comment":"","brand":"Honda CR-V","sum_comment":"","brand_unclear":false,"year":"2010","sum_hidden":false,"brand_info_unclear":false,"sum":"","sum_rent":""}]},"id":"vulyk_73_132","declaration":{"additional_info_text":"","notfull_lostpages":"","date":"2014-03-31T00:00:00","notfull":"","additional_info":"","url":"http://static.declarations.com.ua/declarations/chosen_ones/judges_batch/1145_iurchenko_iaroslav_oleksandrovych.pdf"},"liabilities":{"54":{"sum_foreign_comment":"","sum_foreign_hidden":false,"sum_comment":"","sum_comment_unclear":false,"sum_hidden":false,"sum_comment_hidden":false,"sum_unclear":false,"sum":"","sum_foreign":""},"55":{"sum_foreign_comment":"","sum_comment_hidden":false,"sum":"","sum_comment":"","sum_foreign":""},"56":{"sum_foreign_comment":"","sum":"","sum_comment":"","sum_comment_unclear":false,"sum_foreign":""},"57":{"sum_foreign_comment":"","sum":"","sum_comment":"","sum_hidden":false,"sum_comment_hidden":false,"sum_unclear":false,"sum_foreign":""},"58":{"sum_foreign_comment":"","sum":"","sum_comment":"","sum_hidden":false,"sum_comment_hidden":false,"sum_foreign":""},"59":{"sum_foreign_comment":"","sum":"","sum_comment":"","sum_comment_unclear":false,"sum_unclear":false,"sum_foreign":""},"60":{"sum_foreign_comment":"","sum":"","sum_comment":"","sum_hidden":false,"sum_comment_hidden":false,"sum_unclear":false,"sum_foreign":""},"61":{"sum_foreign_comment":"","sum":"","sum_comment":"","sum_foreign":""},"62":{"sum_foreign_comment":"","sum":"","sum_comment":"","sum_foreign":""},"63":{"sum_foreign_comment":"","sum":"","sum_comment":"","sum_hidden":false,"sum_comment_hidden":false,"sum_foreign":""},"64":{"sum_foreign_comment":"","sum":"","sum_comment":"","sum_foreign":""}},"ft_src":"суддя львівського апеляційного господарського суду\nЛьвівська область\nАпеляційний господарський суд\nЯрослав\nЮрченко Л. М\nПодружжя\nЮрченко І. Я\nДитина\nОлександрович\nЮрченко Ярослав Олександрович\nЯрослав Олександрович Юрченко\nЯрослав Юрченко\nЮрченко Ярослав Олександрович\nЮрченко\nЮрченко Ярослав Олександрович\nHonda CR-V\n2400 куб. см., 122 кВт , 457.4 см\n2010\nспадщина\n2.98\n119\nспадщина\n208\n2013\n46094\n234543\n12617\n46094\n247160\n2400 куб. см., 122 кВт , 457.4 см\nHonda CR-V\n2010\n2013\nЮрченко Ярослав Олександрович\nЯрослав Олександрович Юрченко\nЯрослав Юрченко\nЮрченко Ярослав Олександрович\nЯрослав\nПодружжя\nЮрченко Л. М\nДитина\nЮрченко І. Я\nЮрченко Ярослав Олександрович\nОлександрович\nАпеляційний господарський суд\nЛьвівська область\nсуддя львівського апеляційного господарського суду\nЮрченко\n46094\n234543\n247160\n46094\n12617\n2.98\nспадщина\n208\nспадщина\n119\nПодружжя\nЮрченко Л. М\nДитина\nЮрченко І. Я\nОлександрович\nЮрченко\nЯрослав\nЮрченко Ярослав Олександрович\nЯрослав Олександрович Юрченко\nЯрослав Юрченко\nЮрченко Ярослав Олександрович\nЛьвівська область\nАпеляційний господарський суд\nсуддя львівського апеляційного господарського суду\nЮрченко Ярослав Олександрович\n2010\n2400 куб. см., 122 кВт , 457.4 см\nHonda CR-V\n12617\n247160\n46094\n234543\n46094\n119\nспадщина\n2.98\nспадщина\n208\n2013","general":{"inn":"","name":"Ярослав","family":[{"inn":"","relations":"Подружжя","inn_unclear":false,"relations_hidden":false,"inn_hidden":true,"relations_other":"","name_hidden":false,"family_name":"Юрченко Л. М","name_unclear":false},{"inn":"","relations":"Дитина","inn_unclear":false,"family_name":"Юрченко І. Я","inn_hidden":false,"relations_other":"","name_hidden":false,"name_unclear":false}],"patronymic":"Олександрович","inn_hidden":true,"family_raw":"","last_name":"Юрченко","post":{"post_unclear":false,"region_unclear":false,"post":"суддя львівського апеляційного господарського суду","office":"Апеляційний господарський суд","region":"Львівська область","post_hidden":false,"office_hidden":false,"office_unclear":false,"region_hidden":false},"last_name_unclear":false,"full_name":"Юрченко Ярослав Олександрович","addresses":[{"place_district":"","place_city_hidden":true,"place_city":"","place_city_type_hidden":false,"place_district_hidden":true,"place_city_type":"","place_address_hidden":true,"place_address":"","place_hidden":true,"place":""}],"full_name_suggest":{"output":"Юрченко Ярослав Олександрович","input":["Юрченко Ярослав Олександрович","Ярослав Олександрович Юрченко","Ярослав Юрченко"]},"name_unclear":false},"source":"VULYK","estate":{"23":[{"space_hidden":true,"costs":"","costs_comment":"","costs_hidden":false,"address_hidden":false,"region_hidden":true,"space_comment":"спадщина","space_unclear":true,"space":"2.98","address":"","region":"","space_units_unclear":false,"costs_unclear":false,"space_units":"га","costs_rent":"","costs_rent_comment":""}],"24":[{"space_unclear":false,"costs":"","costs_comment":"","costs_hidden":false,"address_hidden":false,"region_hidden":true,"space_comment":"спадщина","space":"208","address":"","region":"","space_units_unclear":false,"space_comment_unclear":false,"space_comment_hidden":false,"space_units":"м²","costs_rent":"","costs_rent_comment":""}],"31":[{"space_unclear":false,"address_hidden":true,"region_hidden":true,"space_comment":"","space":"119","address":"","region":"","costs_property":"","costs_rent_comment":"","space_units":"м²","costs_property_comment":"","costs_rent":""}]},"intro":{"declaration_year":"2013"}}