{"income":{"5":{"value":"210891.24","family_comment":"","value_unclear":false,"comment_hidden":false,"family_hidden":false,"value_hidden":false,"family_unclear":false,"family_comment_hidden":false,"comment":"","family":"85855.86"},"6":{"value":"198121.59","family_comment":"","value_unclear":false,"family_hidden":false,"family_unclear":false,"family":"71330.67","comment":""},"7":{"source_name_unclear":false,"value":"12668.21","family_hidden":false,"family_comment":"","source_name":"ЛНМУ ім. Галицького, Національна школа суддів України","family":"","comment":"","source_name_hidden":false},"8":{"family_comment":"","value":"","family":"","comment":""},"9":{"value":"101.44","value_unclear":false,"family_hidden":false,"family_comment":"","family":"5.07","comment":""},"10":{"value":"","value_unclear":false,"family_hidden":false,"value_hidden":false,"family_comment":"","comment_unclear":false,"comment":"","family":""},"11":{"family_comment":"","value":"","family":"","comment":""},"12":{"family_comment":"","value":"","family":"","comment":""},"13":{"family_comment":"","value":"","family":"","comment":""},"14":{"family_comment":"","value":"","family":"","comment":""},"15":{"family_comment":"","value":"","family_hidden":false,"comment":"","family":"14520.12"},"16":{"value":"","value_unclear":false,"family_hidden":false,"family_comment":"","family":"","comment":""},"17":{"family_comment":"","value":"","family_hidden":false,"comment":"","family":""},"18":{"family_comment":"","value":"","value_unclear":false,"family":"","comment":""},"19":{"family_comment":"","value":"","family":"","comment":""},"20":{"value":"","family_comment":"","value_unclear":false,"family_hidden":false,"family_unclear":false,"comment_unclear":false,"comment":"","family":""}},"vehicle":{"41":[{"brand_info":"об'єм двигуна 2.9","sum_rent_comment":"користування","brand":"Mercedes-Benz 410","sum_comment":"","year":"1993","brand_hidden":false,"sum":"","sum_rent":""},{"brand_info":"2.3","sum_rent_comment":"користування","brand":"Fiat Ducato","sum_comment":"","year":"2007","sum":"","sum_rent":""}]},"id":"vulyk_72_83","banks":{"45":[{"sum_foreign_comment":"","sum_units":"UAH","sum_comment":"","sum_comment_unclear":false,"sum_hidden":false,"sum_foreign_units":"UAH","sum_comment_hidden":false,"sum_unclear":false,"sum":"74.14","sum_foreign":""}]},"declaration":{"additional_info_text":"","notfull_lostpages":"","date":"2015-03-31T00:00:00","notfull":"","additional_info":"","url":"http://static.declarations.com.ua/declarations/chosen_ones/epic_batch/buchkivska_viktoriia_leonidivna.pdf"},"liabilities":{"54":{"sum_foreign_comment":"","sum":"","sum_comment":"","sum_comment_hidden":false,"sum_unclear":false,"sum_foreign":""},"55":{"sum_foreign_comment":"","sum":"","sum_comment":"","sum_foreign":""},"56":{"sum_foreign_comment":"","sum":"","sum_hidden":false,"sum_comment":"","sum_foreign":""},"57":{"sum_foreign_comment":"","sum":"4099.35","sum_comment":"","sum_comment_unclear":false,"sum_hidden":false,"sum_comment_hidden":false,"sum_unclear":false,"sum_foreign":""},"58":{"sum_foreign_comment":"","sum":"513.76","sum_comment":"","sum_comment_unclear":false,"sum_hidden":false,"sum_comment_hidden":false,"sum_unclear":false,"sum_foreign":""},"59":{"sum_foreign_comment":"","sum_foreign_hidden":false,"sum_comment":"","sum_foreign_unclear":false,"sum_comment_hidden":false,"sum":"","sum_foreign":""},"60":{"sum_foreign_comment":"","sum_foreign_hidden":false,"sum_comment":"","sum_hidden":false,"sum":"","sum_foreign":""},"61":{"sum_foreign_comment":"","sum_foreign_hidden":false,"sum_comment":"","sum_hidden":false,"sum":"","sum_foreign":""},"62":{"sum_foreign_comment":"","sum_foreign_hidden":false,"sum_comment":"","sum_hidden":false,"sum":"","sum_foreign":""},"63":{"sum_foreign_comment":"","sum_foreign_hidden":false,"sum_comment":"","sum_comment_unclear":false,"sum_hidden":false,"sum_comment_hidden":false,"sum_unclear":false,"sum":"","sum_foreign":""},"64":{"sum_foreign_comment":"","sum_foreign_hidden":false,"sum_comment":"","sum_hidden":false,"sum":"","sum_foreign":""}},"ft_src":"4099.35\n513.76\nЛьвів\nЛьвівська область\nзаступник голови, суддя стрийського міськрайонного суду львівської області\nЛьвівська область\nЗагальний місцевий суд\nВікторія\nБучківський С. П\nПодружжя\nБучківський В. С\nДитина\nВіхвецька М. М\nБатьки\nЛеонідівна\nБучківська\nБучківська Вікторія Леонідівна\nБучківська Вікторія Леонідівна\nВікторія Леонідівна Бучківська\nВікторія Бучківська\nБучківська Вікторія Леонідівна\n1993\nоб'єм двигуна 2.9\nMercedes-Benz 410\nкористування\n2.3\n2007\nFiat Ducato\nкористування\nЛьвівська область\n1001\nЛьвівська область\n665\nЛьвівська область\n36.5\n112\nЛьвівська область\n65.9\nм. Львів\nЛьвівська область\n74.14\n2014\nоб'єм двигуна 2.9\nкористування\n1993\nMercedes-Benz 410\n2.3\nкористування\nFiat Ducato\n2007\n1001\nЛьвівська область\n665\nЛьвівська область\n36.5\nЛьвівська область\n112\nЛьвівська область\nм. Львів\n65.9\nЛьвівська область\nПодружжя\nБучківський С. П\nДитина\nБучківський В. С\nБатьки\nВіхвецька М. М\nБучківська Вікторія Леонідівна\nВікторія Леонідівна Бучківська\nВікторія Бучківська\nБучківська Вікторія Леонідівна\nВікторія\nБучківська Вікторія Леонідівна\nБучківська\nЛьвівська область\nЗагальний місцевий суд\nзаступник голови, суддя стрийського міськрайонного суду львівської області\nЛеонідівна\nЛьвів\nЛьвівська область\n513.76\n4099.35\n12668.21\nЛНМУ ім. Галицького, Національна школа суддів України\n198121.59\n71330.67\n14520.12\n210891.24\n85855.86\n101.44\n5.07\n74.14\n2014\n513.76\n4099.35\n71330.67\n198121.59\n14520.12\n5.07\n101.44\nЛНМУ ім. Галицького, Національна школа суддів України\n12668.21\n85855.86\n210891.24\nБучківський С. П\nПодружжя\nБучківський В. С\nДитина\nВіхвецька М. М\nБатьки\nЛеонідівна\nБучківська\nБучківська Вікторія Леонідівна\nВікторія Леонідівна Бучківська\nВікторія Бучківська\nБучківська Вікторія Леонідівна\nЛьвівська область\nЛьвів\nЛьвівська область\nЗагальний місцевий суд\nзаступник голови, суддя стрийського міськрайонного суду львівської області\nБучківська Вікторія Леонідівна\nВікторія\nкористування\n1993\nоб'єм двигуна 2.9\nMercedes-Benz 410\nкористування\nFiat Ducato\n2.3\n2007\n14520.12\n101.44\n5.07\n210891.24\n85855.86\n12668.21\nЛНМУ ім. Галицького, Національна школа суддів України\n198121.59\n71330.67\n65.9\nм. Львів\nЛьвівська область\nЛьвівська область\n1001\nЛьвівська область\n665\nЛьвівська область\n36.5\nЛьвівська область\n112\n74.14\n2014","general":{"inn":"","name":"Вікторія","patronymic_unclear":false,"family":[{"inn":"","inn_hidden":true,"relations_unclear":false,"relations_hidden":false,"relations_other":"","relations":"Подружжя","name_hidden":false,"inn_unclear":false,"family_name":"Бучківський С. П","name_unclear":false},{"inn":"","inn_hidden":false,"relations_hidden":false,"family_name":"Бучківський В. С","relations_other":"","relations":"Дитина","name_hidden":false,"name_unclear":false},{"inn":"","inn_hidden":false,"relations_hidden":false,"family_name":"Віхвецька М. М","relations_other":"","relations":"Батьки","name_hidden":false,"name_unclear":false}],"patronymic":"Леонідівна","inn_hidden":true,"family_raw":"","inn_unclear":false,"post":{"post_unclear":false,"region_unclear":false,"post":"заступник голови, суддя стрийського міськрайонного суду львівської області","candidate":"","office_hidden":false,"region":"Львівська область","post_hidden":false,"office":"Загальний місцевий суд","office_unclear":false,"region_hidden":false},"last_name_unclear":false,"full_name":"Бучківська Вікторія Леонідівна","addresses":[{"place_city_type_hidden":false,"place_district_hidden":false,"place_city_type":"Місто","place_city_hidden":false,"place_address_unclear":false,"place_address":"","place":"Львівська область","place_district":"","place_unclear":false,"place_city":"Львів","place_city_unclear":false,"place_hidden":false,"place_address_hidden":true,"place_district_unclear":false}],"last_name":"Бучківська","patronymic_hidden":false,"full_name_suggest":{"output":"Бучківська Вікторія Леонідівна","input":["Бучківська Вікторія Леонідівна","Вікторія Леонідівна Бучківська","Вікторія Бучківська"]},"name_unclear":false},"source":"VULYK","estate":{"23":[{"space_hidden":false,"costs":"","costs_rent_unclear":false,"costs_comment":"","costs_hidden":false,"address_hidden":true,"region_hidden":false,"space_comment":"","space_unclear":false,"space":"1001","address":"","region":"Львівська область","address_unclear":true,"costs_rent_comment":"","costs_rent_hidden":false,"space_units":"м²","space_units_hidden":false,"costs_rent":""},{"costs":"","costs_comment":"","address_hidden":true,"region_hidden":false,"space_comment":"","space":"665","address":"","region":"Львівська область","address_unclear":true,"costs_rent_comment":"","space_units":"м²","costs_rent":""}],"24":[{"space_hidden":false,"costs":"","costs_comment":"","address_hidden":true,"region_hidden":false,"space_comment":"","space":"36.5","address":"","region":"Львівська область","address_unclear":true,"costs_rent_comment":"","space_units":"м²","costs_rent":""},{"costs_rent":"","space_unclear":false,"region":"Львівська область","costs":"","costs_rent_comment":"","costs_comment":"","address_hidden":false,"space_comment":"","space_units":"м²","space":"112","address":""}],"25":[{"space_unclear":false,"costs":"","costs_rent_unclear":false,"costs_comment":"","costs_hidden":false,"space_hidden":false,"costs_comment_unclear":false,"costs_rent_comment_unclear":false,"region":"Львівська область","space_comment_hidden":false,"space_comment_unclear":false,"costs_rent_comment_hidden":false,"costs_rent":"","costs_comment_hidden":false,"address_hidden":true,"region_hidden":false,"space_comment":"","space":"65.9","address":"м. Львів","address_unclear":false,"costs_rent_comment":"","costs_rent_hidden":false,"space_units":"м²"}]},"intro":{"declaration_year":"2014","isnotdeclaration":"","declaration_year_unclear":false}}