{"income":{"5":{"value":"203383","value_unclear":false,"family_hidden":false,"family_comment":"","family":"","comment":""},"6":{"family_comment":"","value":"182187","value_unclear":false,"family":"","comment":""},"7":{"source_name_unclear":false,"value":"","family_comment":"","source_name":"","family":"","comment":"","source_name_hidden":false},"8":{"family_comment":"","value":"","family":"","comment":""},"9":{"family_comment":"","value":"21196","comment_unclear":false,"family":"","comment":""},"10":{"family_comment":"","value":"","family":"","comment":""},"11":{"family_comment":"","family_unclear":false,"value":"","family":"","comment":""},"12":{"family_comment":"","value":"","family":"","comment":""},"13":{"family_comment":"","value":"","family":"","comment":""},"14":{"family_comment":"","value":"","family":"","comment":""},"15":{"family_comment":"","value":"","family":"","comment":""},"16":{"family_comment":"","value":"","family":"","comment":""},"17":{"family_comment":"","value":"","family":"","comment":""},"18":{"family_comment":"","value":"","family":"","comment":""},"19":{"family_comment":"","value":"","family":"","comment":""},"20":{"value":"","value_unclear":false,"family_comment":"","comment_unclear":false,"comment":"","family":""}},"id":"vulyk_94_91","banks":{"45":[{"sum_foreign_comment":"","sum_unclear":false,"sum_units":"UAH","sum_comment":"Приватбанк","sum_hidden":false,"sum_foreign_units":"UAH","sum_units_unclear":false,"sum_comment_hidden":false,"sum_units_hidden":false,"sum":"247413","sum_foreign":""},{"sum_foreign_comment":"","sum_units":"UAH","sum_comment":"Ощадбанк України","sum_foreign_units":"","sum":"14196","sum_unclear":false,"sum_foreign":""}]},"declaration":{"additional_info_text":"","notfull_lostpages":"","date":"2015-03-30T00:00:00","notfull":"","additional_info":"","url":"http://static.declarations.com.ua/declarations/chosen_ones/judges_batch/3737_kimstachov_oleh_serhiiovych.pdf"},"liabilities":{"54":{"sum_foreign_comment":"","sum":"","sum_comment":"","sum_comment_unclear":false,"sum_comment_hidden":false,"sum_unclear":false,"sum_foreign":""},"55":{"sum_foreign_comment":"","sum":"","sum_comment":"","sum_foreign":""},"56":{"sum_foreign_comment":"","sum":"","sum_comment":"","sum_unclear":false,"sum_foreign":""},"57":{"sum_foreign_comment":"","sum":"","sum_comment":"","sum_hidden":false,"sum_unclear":false,"sum_foreign":""},"58":{"sum_foreign_comment":"","sum":"","sum_comment":"","sum_hidden":false,"sum_unclear":false,"sum_foreign":""},"59":{"sum_foreign_comment":"","sum":"","sum_comment":"","sum_foreign":""},"60":{"sum_foreign_comment":"","sum_comment_hidden":false,"sum":"","sum_comment":"","sum_foreign":""},"61":{"sum_foreign_comment":"","sum":"","sum_comment":"","sum_foreign":""},"62":{"sum_foreign_comment":"","sum":"","sum_hidden":false,"sum_comment":"","sum_foreign":""},"63":{"sum_foreign_comment":"","sum_comment_hidden":false,"sum":"","sum_comment":"","sum_foreign":""},"64":{"sum_foreign_comment":"","sum":"","sum_comment":"","sum_unclear":false,"sum_foreign":""}},"ft_src":"Черкаська область\nсуддя уманського міськрайонного суду черкаської області\nЧеркаська область\nЗагальний місцевий суд\nОлег\nСергійович\nКімстачов Олег Сергійович\nКімстачов\nКімстачов Олег Сергійович\nОлег Сергійович Кімстачов\nОлег Кімстачов\nКімстачов Олег Сергійович\nЧеркаська область\n42\nПриватбанк\n247413\nОщадбанк України\n14196\n2014\n2014\nЧеркаська область\nКімстачов Олег Сергійович\nОлег Сергійович Кімстачов\nОлег Кімстачов\nКімстачов Олег Сергійович\nКімстачов Олег Сергійович\nОлег\nСергійович\nЗагальний місцевий суд\nЧеркаська область\nсуддя уманського міськрайонного суду черкаської області\nКімстачов\n182187\n203383\n21196\n42\nЧеркаська область\n247413\nПриватбанк\n14196\nОщадбанк України\n182187\n203383\n21196\nСергійович\nКімстачов\nОлег\nКімстачов Олег Сергійович\nОлег Сергійович Кімстачов\nОлег Кімстачов\nКімстачов Олег Сергійович\nЧеркаська область\nЧеркаська область\nЗагальний місцевий суд\nсуддя уманського міськрайонного суду черкаської області\nКімстачов Олег Сергійович\n203383\n21196\n182187\nЧеркаська область\n42\nПриватбанк\n247413\nОщадбанк України\n14196\n2014","general":{"inn":"","name":"Олег","inn_unclear":false,"patronymic":"Сергійович","inn_hidden":true,"family_raw":"","last_name":"Кімстачов","post":{"post_unclear":false,"region_unclear":false,"post":"суддя уманського міськрайонного суду черкаської області","candidate":"","post_hidden":false,"region":"Черкаська область","office":"Загальний місцевий суд","office_unclear":false},"full_name":"Кімстачов Олег Сергійович","addresses":[{"place_district":"","place_address_hidden":true,"place_city":"","place_city_type_hidden":false,"place_district_hidden":false,"place_city_type":"","place_city_hidden":false,"place_address":"","place_hidden":false,"place":"Черкаська область"}],"patronymic_hidden":false,"full_name_suggest":{"output":"Кімстачов Олег Сергійович","input":["Кімстачов Олег Сергійович","Олег Сергійович Кімстачов","Олег Кімстачов"]}},"source":"VULYK","estate":{"24":[{"space_unclear":false,"costs":"","costs_comment":"","address_hidden":false,"region_hidden":false,"space_comment":"","space_hidden":false,"space":"42","address":"","region":"Черкаська область","costs_rent_comment":"","costs_rent_hidden":false,"costs_rent_comment_hidden":false,"space_units":"м²","costs_rent":""}]},"intro":{"declaration_year":"2014","isnotdeclaration":""}}