{"income":{"5":{"family_comment":"","value":"227943","value_unclear":false,"family":"","comment":""},"6":{"value":"178743","value_unclear":false,"family_hidden":false,"family_comment":"","family":"","comment":""},"7":{"source_name_unclear":false,"value":"","family_comment":"","source_name":"","family":"","comment":""},"8":{"family_comment":"","value":"","family":"","comment":""},"9":{"family_comment":"","value":"49200","family":"","comment":""},"10":{"family_comment":"","value":"","family":"","comment":""},"11":{"family_comment":"","value":"","comment_unclear":false,"family":"","comment":""},"12":{"family_comment":"","value":"","family":"","comment":""},"13":{"family_comment":"","value":"","family":"","comment":""},"14":{"family_comment":"","value":"","family":"","comment":""},"15":{"family_comment":"","value":"","family":"","comment":""},"16":{"family_comment":"","value":"","family":"","comment":""},"17":{"family_comment":"","value":"","family":"","comment":""},"18":{"family_comment":"","value":"","family":"","comment":""},"19":{"family_comment":"","value":"","family":"","comment":""},"20":{"value":"","family_comment":"","value_unclear":false,"family_unclear":false,"comment_unclear":false,"comment":"","family":""}},"id":"vulyk_101_151","declaration":{"additional_info_text":"","notfull_lostpages":"","date":"2016-03-31T00:00:00","notfull":"","additional_info":"","url":"http://static.declarations.com.ua/declarations/chosen_ones/judges_batch/866_kimstachov_oleh_serhiiovych_2015.pdf"},"liabilities":{"54":{"sum_foreign_comment":"","sum":"","sum_comment":"","sum_comment_unclear":false,"sum_hidden":false,"sum_comment_hidden":false,"sum_unclear":false,"sum_foreign":""},"55":{"sum_foreign_comment":"","sum":"","sum_comment":"","sum_foreign":""},"56":{"sum_foreign_comment":"","sum":"","sum_comment":"","sum_comment_hidden":false,"sum_unclear":false,"sum_foreign":""},"57":{"sum_foreign_comment":"","sum":"","sum_comment":"","sum_hidden":false,"sum_comment_hidden":false,"sum_unclear":false,"sum_foreign":""},"58":{"sum_foreign_comment":"","sum":"","sum_comment":"","sum_comment_unclear":false,"sum_hidden":false,"sum_comment_hidden":false,"sum_unclear":false,"sum_foreign":""},"59":{"sum_foreign_comment":"","sum":"","sum_comment":"","sum_foreign":""},"60":{"sum_foreign_comment":"","sum":"","sum_comment":"","sum_hidden":false,"sum_comment_hidden":false,"sum_unclear":false,"sum_foreign":""},"61":{"sum_foreign_comment":"","sum":"","sum_comment":"","sum_foreign":""},"62":{"sum_foreign_comment":"","sum":"","sum_comment":"","sum_comment_unclear":false,"sum_foreign":""},"63":{"sum_foreign_comment":"","sum_comment_hidden":false,"sum":"","sum_comment":"","sum_foreign":""},"64":{"sum_foreign_comment":"","sum_comment_hidden":false,"sum":"","sum_comment":"","sum_foreign":""}},"ft_src":"суддя уманського міськрайонного суду черкаської області\nЧеркаська область\nЗагальний місцевий суд\nОлег\nСергійович\nКімстачов Олег Сергійович\nКімстачов\nКімстачов Олег Сергійович\nОлег Сергійович Кімстачов\nОлег Кімстачов\nКімстачов Олег Сергійович\n49200\n227943\n178743\n39\n2015\n178743\n49200\n227943\n39\nКімстачов Олег Сергійович\nОлег Сергійович Кімстачов\nОлег Кімстачов\nКімстачов Олег Сергійович\nОлег\nКімстачов Олег Сергійович\nСергійович\nсуддя уманського міськрайонного суду черкаської області\nЧеркаська область\nЗагальний місцевий суд\nКімстачов\n178743\n227943\n49200\n2015\nСергійович\nКімстачов\nОлег\nКімстачов Олег Сергійович\nОлег Сергійович Кімстачов\nОлег Кімстачов\nКімстачов Олег Сергійович\nсуддя уманського міськрайонного суду черкаської області\nЧеркаська область\nЗагальний місцевий суд\nКімстачов Олег Сергійович\n39\n2015","general":{"inn":"","name":"Олег","inn_unclear":false,"patronymic":"Сергійович","inn_hidden":true,"family_raw":"","last_name":"Кімстачов","post":{"region":"Черкаська область","region_unclear":false,"post":"суддя уманського міськрайонного суду черкаської області","office_unclear":false,"office":"Загальний місцевий суд"},"full_name":"Кімстачов Олег Сергійович","addresses":[{"place_district":"","place_address_hidden":true,"place_city":"","place_city_type_hidden":false,"place_district_hidden":false,"place_city_type":"","place_city_hidden":true,"place_address":"","place_hidden":true,"place":""}],"patronymic_hidden":false,"full_name_suggest":{"output":"Кімстачов Олег Сергійович","input":["Кімстачов Олег Сергійович","Олег Сергійович Кімстачов","Олег Кімстачов"]}},"source":"VULYK","estate":{"24":[{"space_unclear":false,"costs":"","costs_comment":"","address_hidden":false,"region_hidden":true,"space_comment":"","space":"39","address":"","region":"","costs_rent_comment":"","space_units":"м²","costs_rent":""}]},"intro":{"declaration_year":"2015"}}