{"income":{"5":{"value":"325614","family_comment":"","value_unclear":false,"comment_hidden":false,"family_hidden":false,"value_hidden":false,"family_unclear":false,"family_comment_unclear":false,"family_comment_hidden":false,"comment":"","family":"43304"},"6":{"value":"259219","family_comment":"","value_unclear":false,"family_hidden":false,"value_hidden":false,"family_unclear":false,"family":"28424","comment":""},"7":{"source_name_unclear":false,"value":"","family_hidden":false,"value_hidden":false,"family_comment":"","source_name":"","family":"","comment":"","source_name_hidden":false},"8":{"value":"","family_comment":"","value_unclear":false,"family_hidden":false,"value_hidden":false,"family_unclear":false,"family":"","comment":""},"9":{"value":"","family_comment":"","value_unclear":false,"family_hidden":false,"value_hidden":false,"family_unclear":false,"comment_unclear":false,"comment":"","family":""},"10":{"value":"","value_unclear":false,"family_hidden":false,"value_hidden":false,"family_comment":"","family":"","comment":""},"11":{"value":"","family_hidden":false,"value_hidden":false,"family_comment":"","family":"","comment":""},"12":{"value":"","family_comment":"","family_hidden":false,"value_hidden":false,"family_unclear":false,"family":"","comment":""},"13":{"value":"","family_hidden":false,"value_hidden":false,"family_comment":"","family":"","comment":""},"14":{"value":"","family_hidden":false,"value_hidden":false,"family_comment":"","family":"","comment":""},"15":{"value":"","family_hidden":false,"value_hidden":false,"family_comment":"","family":"","comment":""},"16":{"value":"","value_unclear":false,"family_hidden":false,"value_hidden":false,"family_comment":"","family":"","comment":""},"17":{"value":"","family_hidden":false,"value_hidden":false,"family_comment":"","family":"","comment":""},"18":{"value":"","family_hidden":false,"value_hidden":false,"family_comment":"","family":"","comment":""},"19":{"value":"995","comment_unclear":false,"family_hidden":false,"value_hidden":false,"family_comment":"","family":"","comment":""},"20":{"value":"65400","family_comment":"","comment_unclear":false,"comment_hidden":false,"family_hidden":false,"value_hidden":false,"family_unclear":false,"family_comment_unclear":false,"family_comment_hidden":false,"comment":"","family":"14880"}},"vehicle":{"35":[{"year_hidden":false,"brand_info":"2494 куб. см., 180 к. с., 457 см","sum_rent_comment":"","sum_rent_comment_unclear":false,"sum_rent_hidden":false,"year":"2014","sum_hidden":false,"brand_info_hidden":false,"brand_info_unclear":false,"year_unclear":false,"sum_rent":"","sum_rent_unclear":false,"sum":"447000","brand":"Toyota Rav 4","sum_comment":"","brand_unclear":false,"brand_hidden":false,"sum_unclear":false}],"40":[{"year_hidden":false,"brand_info":"1568 куб. см., 73 к. с., 53.7 кВт","sum_rent_comment":"","year":"1980","sum_hidden":false,"brand_info_hidden":false,"brand_info_unclear":false,"year_unclear":false,"sum_rent":"","sum":"","brand":"ВАЗ 2121","sum_comment":"","brand_unclear":false,"brand_hidden":false}]},"id":"vulyk_69_34","declaration":{"additional_info_text":"","notfull_lostpages":"","date":"2015-03-30T00:00:00","notfull":"","additional_info":"","url":"http://static.declarations.com.ua/declarations/chosen_ones/mega_batch/bondarenko_leonid_ivanovych.pdf"},"liabilities":{"54":{"sum_foreign_comment":"","sum":"","sum_comment":"","sum_hidden":false,"sum_comment_hidden":false,"sum_unclear":false,"sum_foreign":""},"55":{"sum_foreign_comment":"","sum":"","sum_hidden":false,"sum_comment":"","sum_foreign":""},"56":{"sum_foreign_comment":"","sum":"","sum_comment":"","sum_comment_unclear":false,"sum_hidden":false,"sum_unclear":false,"sum_foreign":""},"57":{"sum_foreign_comment":"","sum":"","sum_comment":"","sum_comment_unclear":false,"sum_hidden":false,"sum_comment_hidden":false,"sum_foreign":""},"58":{"sum_foreign_comment":"","sum":"","sum_comment":"","sum_comment_unclear":false,"sum_hidden":false,"sum_comment_hidden":false,"sum_unclear":false,"sum_foreign":""},"59":{"sum_foreign_comment":"","sum":"","sum_hidden":false,"sum_comment":"","sum_foreign":""},"60":{"sum_foreign_comment":"","sum":"","sum_comment":"","sum_hidden":false,"sum_comment_hidden":false,"sum_foreign":""},"61":{"sum_foreign_comment":"","sum":"","sum_hidden":false,"sum_comment":"","sum_foreign":""},"62":{"sum_foreign_comment":"","sum":"","sum_comment":"","sum_comment_unclear":false,"sum_hidden":false,"sum_unclear":false,"sum_foreign":""},"63":{"sum_foreign_comment":"","sum":"","sum_comment":"","sum_hidden":false,"sum_comment_hidden":false,"sum_unclear":false,"sum_foreign":""},"64":{"sum_foreign_comment":"","sum":"","sum_comment":"","sum_hidden":false,"sum_comment_hidden":false,"sum_foreign":""}},"ft_src":"заступник голови троїцького районного суду луганської області\nЛуганська область\nЗагальний місцевий суд\nЛеонід\nБондаренко О. В\nПодружжя\nБондаренко Д. А\nДитина\nІванович\nБондаренко Леонід Іванович\nЛеонід Іванович Бондаренко\nЛеонід Бондаренко\nБондаренко Леонід Іванович\nБондаренко Леонід Іванович\nБондаренко\n2494 куб. см., 180 к. с., 457 см\nToyota Rav 4\n2014\n447000\n1568 куб. см., 73 к. с., 53.7 кВт\nВАЗ 2121\n1980\n1.74\n53\n3.2\n89.8\n2014\n28424\n259219\n43304\n325614\n995\n14880\n65400\n2494 куб. см., 180 к. с., 457 см\nToyota Rav 4\n2014\n447000\n1568 куб. см., 73 к. с., 53.7 кВт\nВАЗ 2121\n1980\n1.74\n3.2\n89.8\n53\nПодружжя\nБондаренко О. В\nДитина\nБондаренко Д. А\nБондаренко Леонід Іванович\nЛеонід Іванович Бондаренко\nЛеонід Бондаренко\nБондаренко Леонід Іванович\nБондаренко Леонід Іванович\nЛеонід\nІванович\nЗагальний місцевий суд\nЛуганська область\nзаступник голови троїцького районного суду луганської області\nБондаренко\n28424\n259219\n65400\n14880\n43304\n325614\n995\n2014\nПодружжя\nБондаренко О. В\nДитина\nБондаренко Д. А\nІванович\nБондаренко\nЛеонід\nБондаренко Леонід Іванович\nЛеонід Іванович Бондаренко\nЛеонід Бондаренко\nБондаренко Леонід Іванович\nЛуганська область\nЗагальний місцевий суд\nзаступник голови троїцького районного суду луганської області\nБондаренко Леонід Іванович\nToyota Rav 4\n447000\n2494 куб. см., 180 к. с., 457 см\n2014\nВАЗ 2121\n1568 куб. см., 73 к. с., 53.7 кВт\n1980\n995\n65400\n14880\n325614\n43304\n259219\n28424\n1.74\n89.8\n53\n3.2\n2014","general":{"inn":"","name":"Леонід","patronymic_unclear":false,"family":[{"inn":"","inn_hidden":true,"relations_unclear":false,"relations_hidden":false,"relations_other":"","relations":"Подружжя","name_hidden":true,"inn_unclear":false,"family_name":"Бондаренко О. В","name_unclear":false},{"inn":"","inn_hidden":false,"relations_unclear":false,"relations_hidden":false,"relations_other":"","relations":"Дитина","name_hidden":false,"inn_unclear":false,"family_name":"Бондаренко Д. А","name_unclear":false}],"patronymic":"Іванович","inn_hidden":true,"family_raw":"","inn_unclear":false,"post":{"post_unclear":false,"region_unclear":false,"post":"заступник голови троїцького районного суду луганської області","candidate":"","office_hidden":false,"region":"Луганська область","post_hidden":false,"office":"Загальний місцевий суд","office_unclear":true,"region_hidden":false},"full_name_suggest":{"output":"Бондаренко Леонід Іванович","input":["Бондаренко Леонід Іванович","Леонід Іванович Бондаренко","Леонід Бондаренко"]},"full_name":"Бондаренко Леонід Іванович","addresses":[{"place_city_type_unclear":false,"place_address":"","place_district_hidden":true,"place_city_type":"","place_address_hidden":true,"place_address_unclear":false,"place_city_type_hidden":true,"place":"","place_district":"","place_unclear":false,"place_city":"","place_city_unclear":false,"place_hidden":true,"place_city_hidden":true,"place_district_unclear":false}],"last_name":"Бондаренко","last_name_unclear":false,"name_unclear":false},"source":"VULYK","estate":{"23":[{"space_unclear":false,"costs":"","costs_rent_unclear":false,"costs_comment":"","costs_hidden":false,"space_hidden":false,"space_units_unclear":false,"space_units_hidden":false,"costs_comment_unclear":false,"region":"","costs_unclear":false,"space_comment_hidden":false,"costs_rent":"","region_unclear":false,"address_hidden":true,"region_hidden":true,"space_comment":"","space":"1.74","address":"","address_unclear":false,"costs_rent_comment":"","costs_rent_hidden":false,"space_units":"га"}],"24":[{"region_unclear":false,"space_hidden":false,"costs":"","costs_comment":"","costs_hidden":false,"address_hidden":true,"region_hidden":true,"space_comment":"","space_unclear":false,"space":"89.8","address":"","region":"","address_unclear":false,"costs_rent_comment":"","costs_rent_hidden":false,"space_units":"м²","space_units_hidden":false,"costs_rent":""}],"27":[{"region_unclear":false,"space_hidden":false,"costs":"","costs_comment":"","address_hidden":true,"region_hidden":true,"space_comment":"","space":"53","address":"","region":"","costs_rent_comment":"","space_units":"м²","costs_rent":""}],"29":[{"region_unclear":false,"space_hidden":false,"costs_property_hidden":false,"costs_property":"","address_hidden":true,"region_hidden":true,"space_comment":"","space_units_hidden":false,"space_unclear":false,"space":"3.2","address":"","region":"","address_unclear":false,"space_units_unclear":false,"space_comment_hidden":false,"space_units":"га","costs_property_comment":"","costs_rent":"","costs_rent_comment":""}]},"intro":{"declaration_year":"2014","isnotdeclaration":"","declaration_year_unclear":false,"declaration_year_hidden":false}}