{"income":{"5":{"family_comment":"","value":"211491.65","family":"80724.23","comment":""},"6":{"family_comment":"","value":"211491.65","family":"80723.23","comment":""},"7":{"value":"","comment_hidden":false,"family_comment":"","source_name":"","family":"","comment":"","source_name_hidden":false},"8":{"family_comment":"","value":"","family_hidden":false,"comment":"","family":""},"9":{"value":"","family_comment":"","value_unclear":false,"family_unclear":false,"family":"","comment":""},"10":{"family_comment":"","value":"","family":"","comment":""},"11":{"family_comment":"","value":"","family":"","comment":""},"12":{"family_comment":"","value":"","family":"","comment":""},"13":{"family_comment":"","value":"","family":"","comment":""},"14":{"family_comment":"","value":"","family":"","comment":""},"15":{"family_comment":"","value":"","family":"","comment":""},"16":{"family_comment":"","value":"","family":"","comment":""},"17":{"family_comment":"","value":"","family":"","comment":""},"18":{"family_comment":"","value":"","family":"","comment":""},"19":{"family_comment":"","value":"","family":"","comment":""},"20":{"value":"","value_unclear":false,"family_hidden":false,"family_comment":"","family":"","comment":""},"22":[{"country_hidden":true,"cur":"","cur_units":"USD","uah_equal_hidden":true,"uah_equal":"","cur_hidden":true,"country":"","country_comment":""}]},"vehicle":{"35":[{"brand_info":"1.3","sum_rent_comment":"","year":"2005","brand_info_hidden":false,"brand_info_unclear":false,"year_unclear":false,"sum_rent":"","sum":"","brand":"Daewoo Sens","sum_comment":"","sum_comment_unclear":false,"brand_hidden":false,"brand_unclear":false},{"brand_info":"1.396","sum_rent_comment":"","brand":"Hyundai Accent","sum_comment":"","year":"2012","sum":"","sum_rent":""}]},"id":"vulyk_109_106","banks":{"45":[{"sum_foreign_comment":"","sum_unclear":false,"sum_units":"UAH","sum_comment":"","sum_foreign_units":"UAH","sum_comment_hidden":false,"sum_units_hidden":false,"sum":"40000","sum_foreign":""}],"46":[{"sum_foreign_comment":"","sum_units":"UAH","sum_comment":"","sum_foreign_units":"UAH","sum":"3000","sum_foreign":""}],"51":[{"sum_foreign_comment":"","sum_unclear":false,"sum_units":"UAH","sum_comment":"","sum_foreign_units":"UAH","sum_comment_hidden":false,"sum_units_hidden":false,"sum":"80724.23","sum_foreign":""}],"52":[{"sum_foreign_comment":"","sum_units":"UAH","sum_comment":"","sum_comment_unclear":false,"sum_foreign_units":"UAH","sum_foreign_units_hidden":true,"sum":"","sum_foreign_hidden":true,"sum_foreign":""}],"53":[{"sum_foreign_comment":"","sum_units":"UAH","sum_comment":"","sum_comment_unclear":false,"sum_foreign_units":"UAH","sum_foreign_units_hidden":true,"sum_comment_hidden":false,"sum_foreign_hidden":true,"sum":"","sum_foreign":""}]},"declaration":{"additional_info_text":"","notfull_lostpages":"","date":"2016-03-30T00:00:00","notfull":"","additional_info":"","url":"http://static.declarations.com.ua/declarations/chosen_ones/judges_batch/2563_pintelina_tetiana_heorhiivna_2015.pdf"},"liabilities":{"54":{"sum_foreign_comment":"","sum":"2000","sum_comment":"","sum_hidden":false,"sum_comment_hidden":false,"sum_unclear":false,"sum_foreign":""},"55":{"sum_foreign_comment":"","sum":"","sum_comment":"","sum_comment_unclear":false,"sum_foreign":""},"56":{"sum_foreign_comment":"","sum":"8300","sum_comment":"","sum_foreign":""},"57":{"sum_foreign_comment":"","sum_comment_hidden":false,"sum":"","sum_comment":"","sum_foreign":""},"58":{"sum_foreign_comment":"","sum_comment_hidden":false,"sum":"","sum_comment":"","sum_foreign":""},"59":{"sum_foreign_comment":"","sum":"","sum_comment":"","sum_foreign":""},"60":{"sum_foreign_comment":"","sum":"","sum_comment":"","sum_foreign":""},"61":{"sum_foreign_comment":"","sum":"","sum_comment":"","sum_foreign":""},"62":{"sum_foreign_comment":"","sum":"6700","sum_comment":"","sum_foreign":""},"63":{"sum_foreign_comment":"","sum":"","sum_comment":"","sum_foreign":""},"64":{"sum_foreign_comment":"","sum":"","sum_comment":"","sum_foreign":""}},"ft_src":"6700\n2000\n8300\nсуддя господарського суду херсонської області\nХерсонська область\nГосподарський місцевий суд\nТетяна\nПінтелін Родіон Володимирович\nДитина\nПінтелін Андрій Володимирович\nДитина\nГеоргіївна\nПінтеліна Тетяна Георгіївна\nПінтеліна\nПінтеліна Тетяна Георгіївна\nТетяна Георгіївна Пінтеліна\nТетяна Пінтеліна\nПінтеліна Тетяна Георгіївна\n1.3\nDaewoo Sens\n2005\n1.396\n2012\nHyundai Accent\n.12\n60\n41.2\n100\n60\n3000\n80724.23\n40000\n2015\n1.3\nDaewoo Sens\n2005\n1.396\nHyundai Accent\n2012\n2015\nДитина\nПінтелін Родіон Володимирович\nДитина\nПінтелін Андрій Володимирович\nПінтеліна Тетяна Георгіївна\nТетяна Георгіївна Пінтеліна\nТетяна Пінтеліна\nПінтеліна Тетяна Георгіївна\nТетяна\nПінтеліна Тетяна Георгіївна\nПінтеліна\nГосподарський місцевий суд\nХерсонська область\nсуддя господарського суду херсонської області\nГеоргіївна\n2000\n8300\n6700\n211491.65\n80723.23\n211491.65\n80724.23\n.12\n100\n60\n41.2\n60\n40000\n80724.23\n3000\n2000\n8300\n6700\n80723.23\n211491.65\n80724.23\n211491.65\nДитина\nПінтелін Родіон Володимирович\nДитина\nПінтелін Андрій Володимирович\nТетяна\nГеоргіївна\nПінтеліна\nПінтеліна Тетяна Георгіївна\nТетяна Георгіївна Пінтеліна\nТетяна Пінтеліна\nПінтеліна Тетяна Георгіївна\nХерсонська область\nГосподарський місцевий суд\nсуддя господарського суду херсонської області\nПінтеліна Тетяна Георгіївна\n2005\nDaewoo Sens\n1.3\nHyundai Accent\n1.396\n2012\n80724.23\n211491.65\n80723.23\n211491.65\n60\n41.2\n.12\n100\n60\n40000\n80724.23\n3000\n2015","general":{"name_hidden":false,"name":"Тетяна","inn":"","inn_unclear":false,"family":[{"inn":"","relations":"Дитина","relations_hidden":false,"inn_hidden":true,"relations_other":"","name_hidden":false,"family_name":"Пінтелін Родіон Володимирович","name_unclear":false},{"inn":"","relations":"Дитина","relations_other":"","inn_hidden":true,"family_name":"Пінтелін Андрій Володимирович","name_hidden":false,"name_unclear":false}],"inn_hidden":true,"family_raw":"","last_name":"Пінтеліна","post":{"region_unclear":false,"region":"Херсонська область","post":"суддя господарського суду херсонської області","region_hidden":false,"office":"Господарський місцевий суд","office_hidden":false,"office_unclear":false},"full_name":"Пінтеліна Тетяна Георгіївна","patronymic":"Георгіївна","full_name_suggest":{"output":"Пінтеліна Тетяна Георгіївна","input":["Пінтеліна Тетяна Георгіївна","Тетяна Георгіївна Пінтеліна","Тетяна Пінтеліна"]}},"source":"VULYK","estate":{"23":[{"space_unclear":false,"costs":"","costs_rent_unclear":false,"costs_comment":"","address_hidden":false,"region_hidden":true,"space_comment":"","space":".12","address":"","region":"","costs_rent_comment":"","space_units":"га","costs_rent":""}],"24":[{"costs_rent":"","region":"","costs":"","costs_rent_comment":"","costs_comment":"","address_hidden":false,"region_hidden":true,"space_comment":"","space_units":"м²","space":"100","address":""}],"25":[{"space_unclear":false,"costs":"","costs_comment":"","address_hidden":false,"region_hidden":true,"space_comment":"","space_hidden":false,"space":"60","address":"","region":"","costs_rent_comment":"","space_units":"м²","space_units_hidden":false,"costs_rent":""}],"31":[{"space_hidden":false,"costs_property_comment":"","address_hidden":false,"region_hidden":true,"space_comment":"","space":"60","address":"","region":"","costs_property":"","costs_rent_comment":"","space_units":"м²","space_units_hidden":false,"costs_rent":""},{"costs_rent":"","region":"","costs_property":"","costs_rent_comment":"","space_comment":"","costs_property_comment":"","space_units":"м²","space":"41.2","address":""}]},"intro":{"declaration_year":"2015","isnotdeclaration":""}}