{"income":{"5":{"value":"248208","family_comment":"","value_unclear":false,"comment_hidden":false,"family_hidden":false,"value_hidden":false,"family_unclear":false,"family_comment_hidden":false,"comment":"","family":"31936"},"6":{"value":"248208","family_comment":"","value_unclear":false,"family_hidden":false,"family_unclear":false,"family":"18113","comment":""},"7":{"source_name_unclear":false,"value":"","family_hidden":false,"family_comment":"","source_name":"","family":"","comment":"","source_name_hidden":false},"8":{"family_comment":"","value":"","family":"","comment":""},"9":{"value":"","value_unclear":false,"family_hidden":false,"family_comment":"","family":"","comment":""},"10":{"value":"","value_unclear":false,"family_hidden":false,"value_hidden":false,"family_comment":"","comment_unclear":false,"comment":"","family":"1235"},"11":{"family_comment":"","value":"","family":"","comment":""},"12":{"family_comment":"","value":"","family":"","comment":""},"13":{"family_comment":"","value":"","family":"","comment":""},"14":{"family_comment":"","value":"","family":"","comment":""},"15":{"family_comment":"","value":"","family_hidden":false,"comment":"","family":""},"16":{"value":"","value_unclear":false,"family_hidden":false,"family_comment":"","family":"","comment":""},"17":{"family_comment":"","value":"","family_hidden":false,"comment":"","family":""},"18":{"family_comment":"","value":"","value_unclear":false,"family":"","comment":""},"19":{"family_comment":"","value":"","family":"","comment":""},"20":{"value":"","family_comment":"","value_unclear":false,"family_hidden":false,"family_unclear":false,"comment_unclear":false,"comment":"","family":"12588"}},"vehicle":{"35":[{"brand_info":"2.4 куб. дм.","sum_rent_comment":"","brand_info_unclear":false,"year":"2004","sum_rent_unclear":false,"brand_info_hidden":false,"sum_rent_comment_unclear":false,"sum_hidden":false,"sum_rent":"","sum":"","brand":"Toyota Camry","sum_comment":"","brand_unclear":false,"brand_hidden":false}]},"id":"vulyk_72_105","banks":{"45":[{"sum_foreign_comment":"","sum_units":"UAH","sum_comment":"","sum_comment_unclear":false,"sum_hidden":false,"sum_foreign_units":"UAH","sum_comment_hidden":false,"sum_unclear":false,"sum":"116000","sum_foreign":""}]},"declaration":{"additional_info_text":"","notfull_lostpages":"","date":"2015-03-23T00:00:00","notfull":"","additional_info":"","url":"http://static.declarations.com.ua/declarations/chosen_ones/epic_batch/popovych_viktor_volodymyrovych.pdf"},"liabilities":{"54":{"sum_foreign_comment":"","sum":"","sum_comment":"","sum_comment_hidden":false,"sum_unclear":false,"sum_foreign":""},"55":{"sum_foreign_comment":"","sum":"","sum_comment":"","sum_foreign":""},"56":{"sum_foreign_comment":"","sum":"","sum_hidden":false,"sum_comment":"","sum_foreign":""},"57":{"sum_foreign_comment":"","sum":"","sum_comment":"","sum_comment_unclear":false,"sum_hidden":false,"sum_comment_hidden":false,"sum_unclear":false,"sum_foreign":""},"58":{"sum_foreign_comment":"","sum":"","sum_comment":"","sum_comment_unclear":false,"sum_hidden":false,"sum_comment_hidden":false,"sum_unclear":false,"sum_foreign":""},"59":{"sum_foreign_comment":"","sum_foreign_hidden":false,"sum_comment":"","sum_foreign_unclear":false,"sum_comment_hidden":false,"sum":"","sum_foreign":""},"60":{"sum_foreign_comment":"","sum_foreign_hidden":false,"sum_comment":"","sum_hidden":false,"sum":"","sum_foreign":""},"61":{"sum_foreign_comment":"","sum_foreign_hidden":false,"sum_comment":"","sum_hidden":false,"sum":"","sum_foreign":""},"62":{"sum_foreign_comment":"","sum_foreign_hidden":false,"sum_comment":"","sum_hidden":false,"sum":"","sum_foreign":""},"63":{"sum_foreign_comment":"","sum_foreign_hidden":false,"sum_comment":"","sum_comment_unclear":false,"sum_hidden":false,"sum_comment_hidden":false,"sum_unclear":false,"sum":"","sum_foreign":""},"64":{"sum_foreign_comment":"","sum_foreign_hidden":false,"sum_comment":"","sum_hidden":false,"sum":"","sum_foreign":""}},"ft_src":"голова семенівського районного суду чернігівської області\nЧернігівська область\nЗагальний місцевий суд\nВіктор\nПопович К. Ф\nПодружжя\nВолодимирович\nПопович\nПопович Віктор Володимирович\nПопович Віктор Володимирович\nВіктор Володимирович Попович\nВіктор Попович\nПопович Віктор Володимирович\n2.4 куб. дм.\nToyota Camry\n2004\n70\n105.4\n116000\n2014\n2.4 куб. дм.\nToyota Camry\n2004\n70\n105.4\nПодружжя\nПопович К. Ф\nПопович Віктор Володимирович\nВіктор Володимирович Попович\nВіктор Попович\nПопович Віктор Володимирович\nВіктор\nПопович Віктор Володимирович\nПопович\nЧернігівська область\nЗагальний місцевий суд\nголова семенівського районного суду чернігівської області\nВолодимирович\n248208\n18113\n12588\n248208\n31936\n1235\n116000\n2014\n18113\n248208\n1235\n31936\n248208\n12588\nПопович К. Ф\nПодружжя\nВолодимирович\nПопович\nПопович Віктор Володимирович\nВіктор Володимирович Попович\nВіктор Попович\nПопович Віктор Володимирович\nЧернігівська область\nЗагальний місцевий суд\nголова семенівського районного суду чернігівської області\nПопович Віктор Володимирович\nВіктор\n2004\nToyota Camry\n2.4 куб. дм.\n1235\n12588\n248208\n31936\n248208\n18113\n70\n105.4\n116000\n2014","general":{"inn":"","name":"Віктор","patronymic_unclear":false,"family":[{"inn":"","inn_hidden":true,"relations_unclear":false,"relations_hidden":false,"relations_other":"","relations":"Подружжя","name_hidden":true,"inn_unclear":false,"family_name":"Попович К. Ф","name_unclear":false}],"patronymic":"Володимирович","inn_hidden":true,"family_raw":"","inn_unclear":false,"post":{"post_unclear":false,"region_unclear":false,"post":"голова семенівського районного суду чернігівської області","candidate":"","office_hidden":false,"region":"Чернігівська область","post_hidden":false,"office":"Загальний місцевий суд","office_unclear":false,"region_hidden":false},"last_name_unclear":false,"full_name":"Попович Віктор Володимирович","addresses":[{"place_city_type_hidden":false,"place_district_hidden":true,"place_city_type":"","place_city_hidden":true,"place_address_unclear":false,"place_address":"","place":"","place_district":"","place_unclear":false,"place_city":"","place_city_unclear":false,"place_hidden":false,"place_address_hidden":true,"place_district_unclear":false}],"last_name":"Попович","patronymic_hidden":false,"full_name_suggest":{"output":"Попович Віктор Володимирович","input":["Попович Віктор Володимирович","Віктор Володимирович Попович","Віктор Попович"]},"name_unclear":false},"source":"VULYK","estate":{"23":[{"space_hidden":false,"costs":"","costs_rent_unclear":false,"costs_comment":"","costs_hidden":false,"address_hidden":true,"region_hidden":false,"space_comment":"","space_unclear":false,"space":"70","address":"","region":"","address_unclear":false,"costs_rent_comment":"","costs_rent_hidden":false,"space_units":"м²","space_units_hidden":false,"costs_rent":""}],"24":[{"space_hidden":false,"costs":"","costs_comment":"","address_hidden":true,"region_hidden":false,"space_comment":"","space":"105.4","address":"","region":"","address_unclear":false,"costs_rent_comment":"","space_units":"м²","costs_rent":""}]},"intro":{"declaration_year":"2014","isnotdeclaration":"","declaration_year_unclear":false}}