{"income":{"5":{"value":"214459","family_unclear":false,"family_hidden":false,"family_comment":"","family":"","comment":""},"6":{"value":"201842","family_comment":"","value_unclear":false,"family_hidden":false,"family_unclear":false,"family":"","comment":""},"7":{"value":"","family_hidden":false,"value_hidden":false,"family_comment":"","source_name":"","family":"","comment":"","source_name_hidden":false},"8":{"family_comment":"","value":"","family":"","comment":""},"9":{"family_comment":"","value":"","family":"","comment":""},"10":{"family_comment":"","value":"12617","value_unclear":false,"family":"","comment":""},"11":{"family_comment":"","value":"","family":"","comment":""},"12":{"family_comment":"","value":"","family":"","comment":""},"13":{"family_comment":"","value":"","family":"","comment":""},"14":{"family_comment":"","value":"","family":"","comment":""},"15":{"family_comment":"","value":"","family":"","comment":""},"16":{"family_comment":"","value":"","family":"","comment":""},"17":{"family_comment":"","value":"","family":"","comment":""},"18":{"family_comment":"","value":"","family":"","comment":""},"19":{"family_comment":"","value":"","family":"","comment":""},"20":{"value":"","family_comment":"","value_unclear":false,"family_unclear":false,"comment_unclear":false,"comment":"","family":""}},"id":"vulyk_74_73","banks":{"45":[{"sum_foreign_comment":"","sum":"300","sum_comment":"","sum_comment_unclear":false,"sum_hidden":false,"sum_foreign_units":"UAH","sum_foreign_hidden":false,"sum_units":"UAH","sum_comment_hidden":true,"sum_unclear":false,"sum_foreign":""}]},"declaration":{"additional_info_text":"","notfull_lostpages":"","date":"2014-12-09T00:00:00","notfull":"","additional_info":"","url":"http://static.declarations.com.ua/declarations/chosen_ones/judges_batch/1708_zubets_larysa_petrivna.pdf"},"liabilities":{"54":{"sum_foreign_comment":"","sum":"","sum_comment":"","sum_comment_unclear":false,"sum_comment_hidden":false,"sum_foreign":""},"55":{"sum_foreign_comment":"","sum":"","sum_comment":"","sum_hidden":false,"sum_unclear":false,"sum_foreign":""},"56":{"sum_foreign_comment":"","sum":"","sum_comment":"","sum_hidden":false,"sum_unclear":false,"sum_foreign":""},"57":{"sum_foreign_comment":"","sum":"","sum_comment":"","sum_comment_unclear":false,"sum_comment_hidden":false,"sum_foreign":""},"58":{"sum_foreign_comment":"","sum_comment_hidden":false,"sum":"","sum_comment":"","sum_foreign":""},"59":{"sum_foreign_comment":"","sum":"","sum_comment":"","sum_foreign":""},"60":{"sum_foreign_comment":"","sum":"","sum_hidden":false,"sum_comment":"","sum_foreign":""},"61":{"sum_foreign_comment":"","sum":"","sum_comment":"","sum_foreign":""},"62":{"sum_foreign_comment":"","sum":"","sum_comment":"","sum_foreign":""},"63":{"sum_foreign_comment":"","sum":"","sum_comment":"","sum_comment_unclear":false,"sum_unclear":false,"sum_foreign":""},"64":{"sum_foreign_comment":"","sum":"","sum_comment":"","sum_comment_unclear":false,"sum_unclear":false,"sum_foreign":""}},"ft_src":"Петрівна\nЗубець Лариса Петрівна\nсуддя київського апеляційного господарського суду\nм. Київ\nАпеляційний господарський суд\nЛариса\nЗубець Лариса Петрівна\nЛариса Петрівна Зубець\nЛариса Зубець\nЗубець Лариса Петрівна\nЗубець\n110\n300\n2013\n2013\nАпеляційний господарський суд\nм. Київ\nсуддя київського апеляційного господарського суду\nПетрівна\nЗубець Лариса Петрівна\nЛариса Петрівна Зубець\nЛариса Зубець\nЗубець Лариса Петрівна\nЛариса\nЗубець Лариса Петрівна\nЗубець\n201842\n214459\n12617\n110\n300\n201842\n12617\n214459\nПетрівна\nЗубець\nм. Київ\nАпеляційний господарський суд\nсуддя київського апеляційного господарського суду\nЗубець Лариса Петрівна\nЗубець Лариса Петрівна\nЛариса Петрівна Зубець\nЛариса Зубець\nЗубець Лариса Петрівна\nЛариса\n12617\n214459\n201842\n110\n300\n2013","general":{"inn":"","inn_hidden":true,"last_name":"Зубець","post":{"region_unclear":false,"region":"м. Київ","post":"суддя київського апеляційного господарського суду","office":"Апеляційний господарський суд","office_unclear":false,"post_hidden":false},"name":"Лариса","full_name":"Зубець Лариса Петрівна","family_raw":"","addresses":[{"place_district":"","place_city_hidden":true,"place_city":"","place_city_type_hidden":true,"place_district_hidden":true,"place_city_type":"","place_address_hidden":true,"place_address":"","place_hidden":true,"place":""}],"full_name_suggest":{"output":"Зубець Лариса Петрівна","input":["Зубець Лариса Петрівна","Лариса Петрівна Зубець","Лариса Зубець"]},"patronymic":"Петрівна"},"source":"VULYK","estate":{"25":[{"space_hidden":false,"costs":"","costs_comment":"","address_hidden":true,"region_hidden":true,"space_comment":"","space_unclear":false,"space":"110","address":"","region":"","costs_rent_comment":"","space_units":"м²","costs_rent":""}]},"intro":{"declaration_year":"2013","isnotdeclaration":"","declaration_year_unclear":false}}