{"id":"vulyk_97_179","ft_src":"Skoda Fabia\n2010\n56\nДніпропетровська область\nм. Дніпропетровськ\nм. Дніпропетровськ\nДніпропетровська область\n41.7\nм. Дніпропетровськ\nДніпропетровська область\n1320\n56\nм. Дніпропетровськ\nДніпропетровська область\n2014\n72420.96\n228918.22\n72420.96\n228918.22\nSkoda Fabia\n2010\n2014\nДячков Сергій Васильович\nСергій Васильович Дячков\nСергій Дячков\nДячков Сергій Васильович\nСергій\nПодружжя\nДячкова Н. М\nДитина\nДячков А. С\nДитина\nДячков С. С\nДячков Сергій Васильович\nДячков\nЗагальний місцевий суд\nДніпропетровська область\nсуддя заводського районного суду м. дніпродзержинська дніпропетровської області\nВасильович\nДніпропетровська область\n49054\nДніпропетровськ\n228918.22\n72420.96\n228918.22\n72420.96\n1320\nДніпропетровська область\nм. Дніпропетровськ\n41.7\nДніпропетровська область\nм. Дніпропетровськ\n56\nДніпропетровська область\nм. Дніпропетровськ\n56\nм. Дніпропетровськ\nДніпропетровська область\nПодружжя\nДячкова Н. М\nДячков А. С\nДитина\nДитина\nДячков С. С\nВасильович\nДячков\nСергій\nДячков Сергій Васильович\nСергій Васильович Дячков\nСергій Дячков\nДячков Сергій Васильович\n49054\nДніпропетровськ\nДніпропетровська область\nДніпропетровська область\nЗагальний місцевий суд\nсуддя заводського районного суду м. дніпродзержинська дніпропетровської області\nДячков Сергій Васильович","estate":{"25":[{"address":"м. Дніпропетровськ","space_units":"м²","space_hidden":false,"space_unclear":false,"region_hidden":false,"costs_rent_comment":"","space_comment":"","address_hidden":true,"space_comment_hidden":false,"costs":"","space_comment_unclear":false,"costs_comment":"","space":"56","region_unclear":false,"region":"Дніпропетровська область","costs_rent":""}],"29":[{"costs_property_comment":"","address":"м. Дніпропетровськ","space_units":"м²","space_unclear":false,"region_hidden":false,"costs_property":"","space_comment":"","address_hidden":true,"address_unclear":false,"space_comment_unclear":false,"costs_rent_comment":"","space":"1320","region_unclear":false,"region":"Дніпропетровська область","costs_rent":""}],"30":[{"costs_property_comment":"","address":"м. Дніпропетровськ","space_units":"м²","space_comment":"","region_hidden":false,"costs_property":"","region":"Дніпропетровська область","address_hidden":true,"address_unclear":false,"costs_rent_comment":"","space":"41.7","costs_rent":""}],"31":[{"costs_property_comment":"","address":"м. Дніпропетровськ","space_units":"м²","space_hidden":false,"space_unclear":false,"region_hidden":false,"costs_property":"","space_comment":"","address_hidden":true,"space_comment_hidden":false,"costs_rent_comment":"","space":"56","region":"Дніпропетровська область","costs_rent":""}]},"vehicle":{"40":[{"sum_comment":"","brand_info":"","brand_unclear":false,"sum_rent_comment":"","year":"2010","brand":"Skoda Fabia","sum_rent":"","brand_info_unclear":false,"year_unclear":false,"sum":""}]},"source":"VULYK","income":{"5":{"family_comment":"","value":"228918.22","family":"72420.96","comment":""},"6":{"family_comment":"","family":"72420.96","comment":"","value_unclear":false,"family_unclear":false,"comment_hidden":false,"value":"228918.22"},"7":{"family":"","family_comment":"","value":"","comment":"","source_name":""},"8":{"family_comment":"","value":"","family":"","comment":""},"9":{"family_comment":"","value":"","family_unclear":false,"family":"","comment":""},"10":{"family_comment":"","value":"","family":"","comment":"","value_unclear":false},"11":{"family_comment":"","value":"","family":"","comment":""},"12":{"family_comment":"","value":"","family":"","comment":""},"13":{"family_comment":"","value":"","family":"","comment":""},"14":{"family_comment":"","value":"","family":"","comment":""},"15":{"family_comment":"","value":"","family":"","comment":""},"16":{"family_comment":"","value":"","family":"","comment":""},"17":{"family_comment":"","value":"","family":"","comment":""},"18":{"family_comment":"","value":"","family":"","comment":""},"19":{"family_comment":"","value":"","family":"","comment":""},"20":{"family_comment":"","comment":"","family":"","value_unclear":false,"comment_unclear":false,"value":"","family_hidden":false,"family_comment_unclear":false}},"general":{"family":[{"inn":"","family_name":"Дячкова Н. М","relations_other":"","name_unclear":false,"inn_hidden":true,"name_hidden":true,"relations":"Подружжя"},{"inn":"","family_name":"Дячков А. С","name_unclear":false,"inn_hidden":false,"name_hidden":false,"relations":"Дитина"},{"inn":"","family_name":"Дячков С. С","relations_other":"","name_unclear":false,"inn_hidden":false,"name_hidden":false,"relations":"Дитина"}],"family_raw":"","name":"Сергій","full_name_suggest":{"input":["Дячков Сергій Васильович","Сергій Васильович Дячков","Сергій Дячков"],"output":"Дячков Сергій Васильович"},"patronymic":"Васильович","inn_hidden":true,"addresses":[{"place_city_type":"Місто","place_city_type_hidden":false,"place_hidden":false,"place_city_hidden":false,"place_district_hidden":false,"place_district":"","place_city_unclear":false,"place":"Дніпропетровська область","place_city":"Дніпропетровськ","place_address_hidden":true,"place_address":"49054"}],"last_name_hidden":false,"patronymic_hidden":false,"inn":"","inn_unclear":false,"last_name":"Дячков","full_name":"Дячков Сергій Васильович","post":{"post_hidden":false,"office":"Загальний місцевий суд","post":"суддя заводського районного суду м. дніпродзержинська дніпропетровської області","office_unclear":false,"region_unclear":false,"region":"Дніпропетровська область"},"name_hidden":false},"liabilities":{"54":{"sum_comment_unclear":false,"sum_comment":"","sum_hidden":false,"sum":"","sum_foreign_comment":"","sum_foreign":"","sum_unclear":false,"sum_comment_hidden":false},"55":{"sum_comment":"","sum_foreign_comment":"","sum_foreign":"","sum":""},"56":{"sum_comment":"","sum_foreign_comment":"","sum_foreign":"","sum":""},"57":{"sum_comment_unclear":false,"sum_comment":"","sum_hidden":false,"sum":"","sum_foreign_comment":"","sum_foreign":"","sum_unclear":false,"sum_comment_hidden":false},"58":{"sum_comment_unclear":false,"sum_comment":"","sum_hidden":false,"sum":"","sum_foreign_comment":"","sum_foreign":"","sum_unclear":false,"sum_comment_hidden":false},"59":{"sum_comment":"","sum_foreign_comment":"","sum_foreign":"","sum":""},"60":{"sum_comment_unclear":false,"sum_comment":"","sum_hidden":false,"sum":"","sum_foreign_comment":"","sum_foreign":"","sum_comment_hidden":false},"61":{"sum_comment":"","sum_foreign_comment":"","sum_foreign":"","sum":""},"62":{"sum_comment":"","sum_foreign_comment":"","sum_foreign":"","sum_unclear":false,"sum":""},"63":{"sum_comment":"","sum_foreign_comment":"","sum_foreign":"","sum_hidden":false,"sum":""},"64":{"sum_comment":"","sum_foreign_comment":"","sum_foreign":"","sum":""}},"declaration":{"notfull_lostpages":"","additional_info_text":"","additional_info":"","date":"2015-03-31T00:00:00","notfull":"","url":"http://static.declarations.com.ua/declarations/chosen_ones/judges_batch/4094_diachkov_serhii_vasylovych.pdf"},"intro":{"isnotdeclaration":"","declaration_year":"2014"}}