{"income":{"5":{"value":"241445","family_comment":"","value_unclear":false,"family_unclear":false,"family":"12588","comment":""},"6":{"family_comment":"","value":"229265","value_unclear":false,"family":"","comment":""},"7":{"value":"","value_unclear":false,"family_comment":"","source_name":"","family":"","comment":""},"8":{"family_comment":"","value":"","family":"","comment":""},"9":{"value":"","family_comment":"","value_unclear":false,"family_unclear":false,"family":"","comment":""},"10":{"family_comment":"","value":"12180","comment_unclear":false,"family":"","comment":""},"11":{"family_comment":"","value":"","family":"","comment":""},"12":{"family_comment":"","value":"","family":"","comment":""},"13":{"family_comment":"","value":"","value_unclear":false,"family":"","comment":""},"14":{"family_comment":"","value":"","family":"","comment":""},"15":{"family_comment":"","value":"","family":"","comment":""},"16":{"family_comment":"","family_unclear":false,"value":"","family":"","comment":""},"17":{"family_comment":"","family_unclear":false,"value":"","family":"","comment":""},"18":{"family_comment":"","value":"","family":"","comment":""},"19":{"family_comment":"","value":"","family":"","comment":""},"20":{"value":"","family_comment":"","value_unclear":false,"family_hidden":false,"value_hidden":false,"family_unclear":false,"comment_unclear":false,"comment":"","family":"12588"}},"vehicle":{"35":[{"brand_info":"2.0 , 158 к. с., 110 кВт, у власності","sum_rent_comment":"","brand_info_unclear":false,"year":"2007","brand_info_hidden":false,"sum_rent_comment_unclear":false,"sum_rent":"","sum":"","brand":"Subaru Forester","sum_comment":"","brand_unclear":false,"brand_hidden":false}]},"id":"vulyk_100_21","declaration":{"additional_info_text":"","notfull_lostpages":"","date":"2015-03-31T00:00:00","notfull":"","additional_info":"","url":"http://static.declarations.com.ua/declarations/chosen_ones/judges_batch/4139_rabets_mykola_dmytrovych.pdf"},"liabilities":{"54":{"sum_foreign_comment":"","sum":"","sum_comment":"","sum_comment_hidden":false,"sum_unclear":false,"sum_foreign":""},"55":{"sum_foreign_comment":"","sum":"","sum_comment":"","sum_foreign":""},"56":{"sum_foreign_comment":"","sum":"22600","sum_comment":"","sum_unclear":false,"sum_foreign":""},"57":{"sum_foreign_comment":"","sum":"","sum_comment":"","sum_comment_unclear":false,"sum_comment_hidden":false,"sum_unclear":false,"sum_foreign":""},"58":{"sum_foreign_comment":"","sum":"","sum_comment":"","sum_comment_hidden":false,"sum_unclear":false,"sum_foreign":""},"59":{"sum_foreign_comment":"","sum":"","sum_comment":"","sum_foreign":""},"60":{"sum_foreign_comment":"","sum_comment_hidden":false,"sum":"","sum_comment":"","sum_foreign":""},"61":{"sum_foreign_comment":"","sum":"","sum_comment":"","sum_foreign":""},"62":{"sum_foreign_comment":"","sum":"","sum_comment":"","sum_unclear":false,"sum_foreign":""},"63":{"sum_foreign_comment":"","sum_comment_hidden":false,"sum":"","sum_comment":"","sum_foreign":""},"64":{"sum_foreign_comment":"","sum_comment_hidden":false,"sum":"","sum_comment":"","sum_foreign":""}},"ft_src":"22600\nРабець Микола Дмитрович\nсуддя броварського міськрайонного суду київської області\nКиївська область\nЗагальний місцевий суд\nМикола\nРабець Р. В. 29. 09. 1960\nПодружжя\nРабець Микола Дмитрович\nМикола Дмитрович Рабець\nМикола Рабець\nРабець Микола Дмитрович\nРабець\nДмитрович\n2.0 , 158 к. с., 110 кВт, у власності\nSubaru Forester\n2007\nвласність\n1000\n24\nвласність\n71.5\n2014\n229265\n12180\n12588\n241445\n12588\n2.0 , 158 к. с., 110 кВт, у власності\nSubaru Forester\n2007\n1000\nвласність\n24\n71.5\nвласність\nПодружжя\nРабець Р. В. 29. 09. 1960\nДмитрович\nРабець\nРабець Микола Дмитрович\nМикола Дмитрович Рабець\nМикола Рабець\nРабець Микола Дмитрович\nРабець Микола Дмитрович\nМикола\nЗагальний місцевий суд\nКиївська область\nсуддя броварського міськрайонного суду київської області\n22600\n229265\n12588\n241445\n12588\n12180\n2014\n22600\nРабець Р. В. 29. 09. 1960\nПодружжя\nДмитрович\nРабець\nКиївська область\nЗагальний місцевий суд\nсуддя броварського міськрайонного суду київської області\nРабець Микола Дмитрович\nРабець Микола Дмитрович\nМикола Дмитрович Рабець\nМикола Рабець\nРабець Микола Дмитрович\nМикола\n2007\nSubaru Forester\n2.0 , 158 к. с., 110 кВт, у власності\n12180\n12588\n241445\n12588\n229265\nвласність\n71.5\nвласність\n1000\n24\n2014","general":{"inn":"","inn_hidden":true,"last_name":"Рабець","post":{"post_unclear":false,"region_unclear":false,"post":"суддя броварського міськрайонного суду київської області","office":"Загальний місцевий суд","region":"Київська область","post_hidden":false,"office_unclear":false},"name":"Микола","full_name":"Рабець Микола Дмитрович","family_raw":"","addresses":[{"place_district":"","place_city_hidden":true,"place_city":"","place_city_unclear":false,"place_district_hidden":false,"place_city_type":"","place_address_hidden":true,"place_city_type_hidden":false,"place_address":"","place_hidden":true,"place":""}],"family":[{"inn_hidden":true,"inn":"","name_hidden":false,"family_name":"Рабець Р. В. 29. 09. 1960","relations":"Подружжя","name_unclear":false}],"full_name_suggest":{"output":"Рабець Микола Дмитрович","input":["Рабець Микола Дмитрович","Микола Дмитрович Рабець","Микола Рабець"]},"patronymic":"Дмитрович"},"source":"VULYK","estate":{"23":[{"space_unclear":false,"costs":"","costs_comment":"","address_hidden":false,"region_hidden":true,"space_comment":"власність","space":"1000","address":"","costs_comment_unclear":false,"region":"","address_unclear":false,"costs_rent_comment":"","space_comment_unclear":false,"space_units":"м²","costs_rent":""}],"25":[{"space_unclear":false,"costs":"","costs_comment":"","address_hidden":false,"region_hidden":true,"space_comment":"власність","space":"71.5","address":"","costs_comment_unclear":false,"region":"","address_unclear":false,"costs_rent_comment":"","space_comment_unclear":false,"space_units":"м²","costs_rent":""}],"27":[{"space_unclear":false,"costs":"","costs_comment":"","address_hidden":false,"region_hidden":true,"space_comment":"","space":"24","address":"","region":"","address_unclear":false,"costs_rent_comment":"","space_units":"м²","costs_rent":""}]},"intro":{"declaration_year":"2014"}}