{"income":{"5":{"value":"536991","value_unclear":false,"comment_hidden":false,"family_comment":"","family":"31385","comment":""},"6":{"family_comment":"","value":"233955","family":"29007","comment":"","value_hidden":false},"7":{"family_comment":"","value":"","source_name":"","family":"","comment":""},"8":{"family_comment":"","value":"","family":"","comment":""},"9":{"family_comment":"","value":"","comment_hidden":false,"family":"","comment":""},"10":{"family_comment":"","value":"12180","family":"2378","comment":""},"11":{"family_comment":"","value":"","family":"","comment":""},"12":{"family_comment":"","value":"","family":"","comment":""},"13":{"family_comment":"","value":"","family":"","comment":""},"14":{"family_comment":"","value":"","family":"","comment":""},"15":{"family_comment":"","value":"","family":"","comment":"","family_comment_hidden":false},"16":{"family_comment":"","value":"150801","family":"","comment":""},"17":{"family_comment":"","value":"","family":"","comment":""},"18":{"family_comment":"","value":"","family":"","comment":"","value_hidden":false},"19":{"family_comment":"","value":"","family":"","comment":""},"20":{"family_comment":"","value":"140055","family":"","comment":"","family_comment_unclear":false}},"vehicle":{"35":[{"brand_info":"1995 куб. см.","sum_rent_comment":"","brand":"Suzuki Grand Vitara","sum_comment":"","year":"2006","sum":"","sum_rent":""}]},"id":"vulyk_78_37","banks":{"45":[{"sum_foreign_comment":"","sum_units":"UAH","sum_comment":"","sum_hidden":false,"sum_foreign_units":"UAH","sum":"3700","sum_foreign":""}]},"declaration":{"additional_info_text":"","notfull_lostpages":"","date":"2015-03-30T00:00:00","notfull":"","additional_info":"","url":"http://static.declarations.com.ua/declarations/chosen_ones/judges_batch/2104_ostapchuk_tetiana_volodymyrivna.pdf"},"liabilities":{"54":{"sum_foreign_comment":"","sum_foreign_hidden":false,"sum_comment":"","sum_comment_unclear":false,"sum_hidden":false,"sum_comment_hidden":false,"sum":"2664","sum_foreign":""},"55":{"sum_foreign_comment":"","sum":"","sum_comment":"","sum_foreign":""},"56":{"sum_foreign_comment":"","sum":"","sum_comment":"","sum_foreign":""},"57":{"sum_foreign_comment":"","sum":"10000","sum_comment":"","sum_foreign":""},"58":{"sum_foreign_comment":"","sum":"","sum_comment":"","sum_unclear":false,"sum_foreign":""},"59":{"sum_foreign_comment":"","sum":"","sum_comment":"","sum_foreign":""},"60":{"sum_foreign_comment":"","sum":"","sum_comment":"","sum_comment_unclear":false,"sum_comment_hidden":false,"sum_foreign":""},"61":{"sum_foreign_comment":"","sum":"","sum_comment":"","sum_foreign":""},"62":{"sum_foreign_comment":"","sum":"","sum_hidden":false,"sum_comment":"","sum_foreign":""},"63":{"sum_foreign_comment":"","sum_foreign_hidden":false,"sum_comment":"","sum":"","sum_unclear":false,"sum_foreign":""},"64":{"sum_foreign_comment":"","sum_foreign_hidden":false,"sum_comment":"","sum_hidden":false,"sum":"","sum_foreign":""}},"ft_src":"10000\n2664\nсуддя печерського районного суду міста києва\nм. Київ\nЗагальний місцевий суд\nТетяна\nОстапчук С. А\nДитина\nОстапчук Д. С\nДитина\nВолодимирівна\nОстапчук Тетяна Володимирівна\nТетяна Володимирівна Остапчук\nТетяна Остапчук\nОстапчук Тетяна Володимирівна\nОстапчук\nОстапчук Тетяна Володимирівна\n1995 куб. см.\n2006\nSuzuki Grand Vitara\n21\nсоток\n30\nм. Київ\n50\n335\nм. Київ\n25\nм. Київ\n55\n3700\n2014\n1995 куб. см.\n2006\nSuzuki Grand Vitara\n2014\nДитина\nОстапчук С. А\nДитина\nОстапчук Д. С\nОстапчук Тетяна Володимирівна\nТетяна Володимирівна Остапчук\nТетяна Остапчук\nОстапчук Тетяна Володимирівна\nОстапчук Тетяна Володимирівна\nТетяна\nВолодимирівна\nЗагальний місцевий суд\nсуддя печерського районного суду міста києва\nм. Київ\nОстапчук\n2664\n10000\n233955\n29007\n140055\n536991\n31385\n150801\n12180\n2378\n21\n30\nсоток\n335\nм. Київ\n50\n25\nм. Київ\nм. Київ\n55\n3700\n10000\n2664\n29007\n233955\n2378\n12180\n31385\n536991\n150801\n140055\nДитина\nОстапчук С. А\nДитина\nОстапчук Д. С\nВолодимирівна\nОстапчук\nТетяна\nОстапчук Тетяна Володимирівна\nТетяна Володимирівна Остапчук\nТетяна Остапчук\nОстапчук Тетяна Володимирівна\nм. Київ\nсуддя печерського районного суду міста києва\nЗагальний місцевий суд\nОстапчук Тетяна Володимирівна\nSuzuki Grand Vitara\n1995 куб. см.\n2006\n2378\n12180\n140055\n536991\n31385\n150801\n29007\n233955\nм. Київ\n50\n21\nсоток\n30\n335\nм. Київ\n25\nм. Київ\n55\n3700\n2014","general":{"inn":"","name":"Тетяна","family":[{"inn":"","relations":"Дитина","relations_other":"","inn_hidden":true,"family_name":"Остапчук С. А","name_hidden":false,"name_unclear":false},{"inn":"","relations":"Дитина","relations_other":"","inn_hidden":false,"family_name":"Остапчук Д. С","name_hidden":false,"name_unclear":false}],"patronymic":"Володимирівна","inn_hidden":true,"family_raw":"","last_name":"Остапчук","post":{"post_unclear":false,"post":"суддя печерського районного суду міста києва","post_hidden":false,"region":"м. Київ","region_hidden":false,"office":"Загальний місцевий суд","office_hidden":false},"last_name_unclear":false,"full_name":"Остапчук Тетяна Володимирівна","addresses":[{"place_district":"","place_city_hidden":true,"place_city":"","place_city_type_hidden":false,"place_district_hidden":true,"place_city_type":"","place_address_hidden":true,"place_address":"","place_hidden":true,"place":""}],"full_name_suggest":{"output":"Остапчук Тетяна Володимирівна","input":["Остапчук Тетяна Володимирівна","Тетяна Володимирівна Остапчук","Тетяна Остапчук"]},"name_unclear":false},"source":"VULYK","estate":{"23":[{"costs_rent":"","region":"","costs":"","costs_rent_comment":"","costs_comment":"","address_hidden":false,"region_hidden":true,"space_comment":"","space_units":"м²","space":"21","address":""},{"costs_rent":"","region":"","costs":"","costs_rent_comment":"","costs_comment":"","address_hidden":false,"region_hidden":true,"space_comment":"","space_units":"соток","space":"30","address":""}],"24":[{"costs_rent":"","region":"","costs":"","costs_rent_comment":"","costs_comment":"","address_hidden":false,"region_hidden":true,"space_comment":"","space_units":"м²","space":"335","address":""}],"25":[{"space_hidden":false,"costs":"","costs_comment":"","address_hidden":true,"region_hidden":false,"space_comment":"","space":"25","address":"","region":"м. Київ","address_unclear":false,"costs_rent_comment":"","space_units":"м²","costs_rent":""},{"costs_rent":"","region":"м. Київ","costs":"","costs_rent_comment":"","costs_comment":"","space_comment":"","space_units":"м²","space":"55","address":""}],"31":[{"address_hidden":true,"region_hidden":false,"space_comment":"","space":"50","address":"","region":"м. Київ","costs_property":"","costs_rent_comment":"","address_unclear":false,"space_units":"м²","costs_property_comment":"","costs_rent":""}]},"intro":{"declaration_year":"2014"}}