{"income":{"5":{"value":"265431","family_comment":"","value_unclear":false,"family_hidden":false,"value_hidden":false,"family_unclear":false,"family":"","comment":"","family_comment_unclear":false},"6":{"family_comment":"","family_unclear":false,"value":"218333.96","family":"","comment":""},"7":{"source_name_unclear":false,"value":"","family_comment":"","source_name":"","family":"","comment":"","source_name_hidden":false},"8":{"family_comment":"","value":"","family":"","comment":""},"9":{"family_comment":"","family_unclear":false,"value":"47097","family":"","comment":""},"10":{"family_comment":"","value":"","family":"","comment":""},"11":{"family_comment":"","value":"","family":"","comment":""},"12":{"family_comment":"","value":"","family":"","comment":""},"13":{"family_comment":"","value":"","family":"","comment":""},"14":{"family_comment":"","value":"","family":"","comment":""},"15":{"family_comment":"","value":"","family":"","comment":""},"16":{"value":"","value_unclear":false,"value_hidden":false,"family_comment":"","family":"","comment":""},"17":{"family_comment":"","value":"","family":"","comment":""},"18":{"family_comment":"","value":"","family":"","comment":""},"19":{"family_comment":"","value":"","family":"","comment":""},"20":{"value":"","family_comment":"","value_unclear":false,"comment_hidden":false,"family_hidden":false,"family":"","value_hidden":false,"family_unclear":false,"comment_unclear":false,"comment":"","family_comment_unclear":false}},"id":"vulyk_62_137","banks":{"45":[{"sum_units":"UAH","sum_hidden":false,"sum_foreign_units_hidden":false,"sum":"360000","sum_foreign":"","sum_foreign_comment":"","sum_foreign_hidden":false,"sum_comment":"","sum_comment_unclear":false,"sum_foreign_units":"UAH","sum_comment_hidden":false,"sum_unclear":false}],"46":[{"sum_units":"UAH","sum_hidden":false,"sum_foreign_units_hidden":false,"sum":"135000","sum_foreign":"","sum_foreign_comment":"","sum_foreign_hidden":false,"sum_comment":"","sum_comment_unclear":false,"sum_foreign_units":"UAH","sum_comment_hidden":false,"sum_unclear":false}]},"declaration":{"additional_info_text":"","notfull_lostpages":"","date":"2015-03-30T00:00:00","notfull":"","additional_info":"","url":"http://static.declarations.com.ua/declarations/chosen_ones/mega_batch/ulianich_iryna_volodymyrivna.pdf"},"liabilities":{"54":{"sum_foreign_comment":"","sum":"","sum_comment":"","sum_hidden":false,"sum_comment_hidden":false,"sum_foreign":""},"55":{"sum_foreign_comment":"","sum":"","sum_comment":"","sum_hidden":false,"sum_comment_hidden":false,"sum_unclear":false,"sum_foreign":""},"56":{"sum_foreign_comment":"","sum":"","sum_comment":"","sum_hidden":false,"sum_unclear":false,"sum_foreign":""},"57":{"sum_foreign_comment":"","sum":"","sum_comment":"","sum_hidden":false,"sum_comment_hidden":false,"sum_unclear":false,"sum_foreign":""},"58":{"sum_foreign_comment":"","sum_foreign_hidden":false,"sum_comment":"","sum_hidden":false,"sum_comment_hidden":false,"sum_unclear":false,"sum":"","sum_foreign":""},"59":{"sum_foreign_comment":"","sum":"","sum_comment":"","sum_foreign":""},"60":{"sum_foreign_comment":"","sum_foreign_hidden":false,"sum_comment":"","sum_hidden":false,"sum_comment_hidden":false,"sum_unclear":false,"sum":"","sum_foreign":""},"61":{"sum_foreign_comment":"","sum_foreign_hidden":false,"sum_comment":"","sum_hidden":false,"sum":"","sum_foreign":""},"62":{"sum_foreign_comment":"","sum":"","sum_comment":"","sum_unclear":false,"sum_foreign":""},"63":{"sum_foreign_comment":"","sum":"","sum_comment":"","sum_hidden":false,"sum_comment_hidden":false,"sum_unclear":false,"sum_foreign":""},"64":{"sum_foreign_comment":"","sum":"","sum_comment":"","sum_comment_unclear":false,"sum_hidden":false,"sum_comment_hidden":false,"sum_foreign":""}},"ft_src":"суддя пролетарського районного суду м. донецька\nДонецька область\nЗагальний місцевий суд\nІрина\nВолодимирівна\nУльяніч\nУльяніч Ірина Володимирівна\nУльяніч Ірина Володимирівна\nІрина Володимирівна Ульяніч\nІрина Ульяніч\nУльяніч Ірина Володимирівна\n265431\n47097\n218333.96\n135000\n360000\n2014\n218333.96\n265431\n47097\n360000\n135000\n218333.96\n265431\n47097\nУльяніч Ірина Володимирівна\nІрина Володимирівна Ульяніч\nІрина Ульяніч\nУльяніч Ірина Володимирівна\nІрина\nУльяніч Ірина Володимирівна\nВолодимирівна\nЗагальний місцевий суд\nсуддя пролетарського районного суду м. донецька\nДонецька область\nУльяніч\n2014\nІрина\nВолодимирівна\nУльяніч\nУльяніч Ірина Володимирівна\nІрина Володимирівна Ульяніч\nІрина Ульяніч\nУльяніч Ірина Володимирівна\nДонецька область\nсуддя пролетарського районного суду м. донецька\nЗагальний місцевий суд\nУльяніч Ірина Володимирівна\n360000\n135000\n2014","general":{"inn":"","name":"Ірина","inn_unclear":false,"patronymic":"Володимирівна","inn_hidden":true,"family_raw":"","last_name":"Ульяніч","post":{"post_unclear":false,"post":"суддя пролетарського районного суду м. донецька","post_hidden":false,"region":"Донецька область","region_hidden":false,"office":"Загальний місцевий суд","office_hidden":false,"office_unclear":false},"full_name_suggest":{"output":"Ульяніч Ірина Володимирівна","input":["Ульяніч Ірина Володимирівна","Ірина Володимирівна Ульяніч","Ірина Ульяніч"]},"full_name":"Ульяніч Ірина Володимирівна","last_name_unclear":false,"name_unclear":false},"source":"VULYK","intro":{"declaration_year":"2014","isnotdeclaration":"","declaration_year_unclear":false,"declaration_year_hidden":false}}