{"income":{"5":{"value":"440105","family_comment":"","value_unclear":false,"family_unclear":false,"family":"72348","comment":""},"6":{"family_comment":"","value":"281021","value_unclear":false,"family":"52812","comment":""},"7":{"value":"","value_unclear":false,"family_comment":"","source_name":"","family":"","comment":""},"8":{"family_comment":"","value":"","family":"","comment":""},"9":{"value":"75736","family_comment":"","value_unclear":false,"family_unclear":false,"family":"","comment":""},"10":{"family_comment":"","value":"","comment_unclear":false,"family":"","comment":""},"11":{"family_comment":"","value":"","family":"","comment":""},"12":{"family_comment":"","value":"","family":"","comment":""},"13":{"family_comment":"","value":"","value_unclear":false,"family":"","comment":""},"14":{"family_comment":"","value":"","family":"","comment":""},"15":{"family_comment":"","value":"","family":"","comment":""},"16":{"family_comment":"","family_unclear":false,"value":"","family":"","comment":""},"17":{"family_comment":"","family_unclear":false,"value":"","family":"","comment":""},"18":{"family_comment":"","value":"","family":"","comment":""},"19":{"family_comment":"","value":"","family":"","comment":""},"20":{"value":"83348","family_comment":"","value_unclear":false,"family_hidden":false,"value_hidden":false,"family_unclear":false,"comment_unclear":false,"comment":"","family":"19536"}},"vehicle":{"35":[{"brand_info":"4461 куб. см., 235 кВт , 495.0 см","sum_rent_comment":"","brand_info_unclear":false,"year":"2011","brand_info_hidden":false,"sum_rent_comment_unclear":false,"sum_rent":"","sum":"","brand":"Toyota Land Cruiser 200","sum_comment":"","brand_unclear":false,"brand_hidden":false}]},"id":"vulyk_100_190","banks":{"45":[{"sum_foreign_comment":"","sum_units":"UAH","sum_comment":"","sum_comment_unclear":false,"sum_foreign_units":"UAH","sum_units_unclear":false,"sum_comment_hidden":false,"sum_unclear":false,"sum":"603001","sum_foreign":""}],"47":[{"sum_foreign_comment":"","sum_units":"UAH","sum_comment":"ТОВ КУА ОТП Капітал","sum_comment_unclear":false,"sum_foreign_units":"UAH","sum":"355","sum_unclear":false,"sum_foreign":""}]},"declaration":{"additional_info_text":"","notfull_lostpages":"","date":"2015-03-25T00:00:00","notfull":"","additional_info":"","url":"http://static.declarations.com.ua/declarations/chosen_ones/judges_batch/4460_dobrianskyi_vitalii_vitaliiovych.pdf"},"liabilities":{"54":{"sum_foreign_comment":"","sum":"460","sum_comment":"","sum_comment_hidden":false,"sum_unclear":false,"sum_foreign":""},"55":{"sum_foreign_comment":"","sum":"","sum_comment":"","sum_foreign":""},"56":{"sum_foreign_comment":"","sum":"","sum_comment":"","sum_unclear":false,"sum_foreign":""},"57":{"sum_foreign_comment":"","sum":"","sum_comment":"","sum_comment_unclear":false,"sum_comment_hidden":false,"sum_unclear":false,"sum_foreign":""},"58":{"sum_foreign_comment":"","sum":"","sum_comment":"","sum_comment_hidden":false,"sum_unclear":false,"sum_foreign":""},"59":{"sum_foreign_comment":"","sum":"","sum_comment":"","sum_foreign":""},"60":{"sum_foreign_comment":"","sum_comment_hidden":false,"sum":"","sum_comment":"","sum_foreign":""},"61":{"sum_foreign_comment":"","sum":"","sum_comment":"","sum_foreign":""},"62":{"sum_foreign_comment":"","sum":"","sum_comment":"","sum_unclear":false,"sum_foreign":""},"63":{"sum_foreign_comment":"","sum_comment_hidden":false,"sum":"","sum_comment":"","sum_foreign":""},"64":{"sum_foreign_comment":"","sum_comment_hidden":false,"sum":"","sum_comment":"","sum_foreign":""}},"ft_src":"460\nДобрянський Віталій Віталійович\nголова чернігівського окружного адміністративного суду\nЧернігівська область\nАдміністративний місцевий суд\nВіталій\nДобрянська Галина Андріївна\nПодружжя\nДобрянський Віталій Віталійович\nВіталій Віталійович Добрянський\nВіталій Добрянський\nДобрянський Віталій Віталійович\nДобрянський\nВіталійович\n4461 куб. см., 235 кВт , 495.0 см\nToyota Land Cruiser 200\n2011\nТОВ КУА ОТП Капітал\n355\n603001\n2014\n4461 куб. см., 235 кВт , 495.0 см\nToyota Land Cruiser 200\n2011\n603001\nТОВ КУА ОТП Капітал\n355\n30.6\n68.1\n97.9\nПодружжя\nДобрянська Галина Андріївна\nВіталійович\nДобрянський\nДобрянський Віталій Віталійович\nВіталій Віталійович Добрянський\nВіталій Добрянський\nДобрянський Віталій Віталійович\nДобрянський Віталій Віталійович\nВіталій\nАдміністративний місцевий суд\nЧернігівська область\nголова чернігівського окружного адміністративного суду\n460\n281021\n52812\n83348\n19536\n440105\n72348\n75736\n2014\n460\n68.1\n30.6\n97.9\nДобрянська Галина Андріївна\nПодружжя\nВіталійович\nДобрянський\nЧернігівська область\nАдміністративний місцевий суд\nголова чернігівського окружного адміністративного суду\nДобрянський Віталій Віталійович\nДобрянський Віталій Віталійович\nВіталій Віталійович Добрянський\nВіталій Добрянський\nДобрянський Віталій Віталійович\nВіталій\n52812\n281021\n72348\n440105\n75736\n19536\n83348\n2011\nToyota Land Cruiser 200\n4461 куб. см., 235 кВт , 495.0 см\n83348\n19536\n440105\n72348\n75736\n52812\n281021\n68.1\n97.9\n30.6\nТОВ КУА ОТП Капітал\n355\n603001\n2014","general":{"inn":"","inn_hidden":true,"last_name":"Добрянський","post":{"post_unclear":false,"region_unclear":false,"post":"голова чернігівського окружного адміністративного суду","office":"Адміністративний місцевий суд","region":"Чернігівська область","post_hidden":false,"office_unclear":false},"name":"Віталій","full_name":"Добрянський Віталій Віталійович","family_raw":"","addresses":[{"place_district":"","place_city_hidden":true,"place_city":"","place_city_unclear":false,"place_district_hidden":true,"place_city_type":"","place_address_hidden":true,"place_city_type_hidden":true,"place_address":"","place_hidden":true,"place":""}],"family":[{"inn_hidden":true,"inn":"","name_hidden":true,"family_name":"Добрянська Галина Андріївна","relations":"Подружжя","name_unclear":false}],"full_name_suggest":{"output":"Добрянський Віталій Віталійович","input":["Добрянський Віталій Віталійович","Віталій Віталійович Добрянський","Віталій Добрянський"]},"patronymic":"Віталійович"},"source":"VULYK","estate":{"25":[{"space_unclear":false,"costs":"","costs_comment":"","address_hidden":false,"region_hidden":true,"space_comment":"","space":"97.9","address":"","costs_comment_unclear":false,"region":"","address_unclear":false,"costs_rent_comment":"","space_comment_unclear":false,"space_units":"м²","costs_rent":""}],"27":[{"space_unclear":false,"costs":"","costs_comment":"","address_hidden":false,"region_hidden":true,"space_comment":"","space":"30.6","address":"","region":"","address_unclear":false,"costs_rent_comment":"","space_units":"м²","costs_rent":""}],"31":[{"region_unclear":false,"space_unclear":false,"costs_property_comment_unclear":false,"address_hidden":false,"region_hidden":true,"space_comment":"","space":"68.1","address":"","region":"","costs_property":"","costs_rent_comment":"","space_comment_unclear":false,"address_unclear":false,"space_units":"м²","costs_property_comment":"","costs_rent":""}]},"intro":{"declaration_year":"2014"}}