{"income":{"5":{"value":"291290.79","family_comment":"","value_unclear":false,"family_hidden":false,"value_hidden":false,"family_unclear":false,"family":"418895.4","comment":"","family_comment_unclear":false},"6":{"family_comment":"","family_unclear":false,"value":"277892.79","family":"319478.12","comment":""},"7":{"source_name_unclear":false,"value":"","family_comment":"","source_name":"","family":"","comment":"","source_name_hidden":false},"8":{"family_comment":"","value":"","family":"","comment":""},"9":{"family_comment":"","family_unclear":false,"value":"","family":"","comment":""},"10":{"family_comment":"","value":"13398","family":"15834","comment":""},"11":{"family_comment":"","value":"","family":"","comment":""},"12":{"family_comment":"","value":"","family":"","comment":""},"13":{"family_comment":"","value":"","family":"","comment":""},"14":{"family_comment":"","value":"","family":"","comment":""},"15":{"family_comment":"","value":"","family":"","comment":""},"16":{"value":"","value_unclear":false,"value_hidden":false,"family_comment":"","family":"","comment":""},"17":{"family_comment":"","value":"","family":"","comment":""},"18":{"family_comment":"","value":"","family":"","comment":""},"19":{"family_comment":"","value":"","family":"","comment":""},"20":{"value":"","family_comment":"","value_unclear":false,"comment_hidden":false,"family_hidden":false,"family":"83583.28","value_hidden":false,"family_unclear":false,"comment_unclear":false,"comment":"","family_comment_unclear":false}},"vehicle":{"35":[{"year_hidden":false,"brand_info":"2500 куб. см.","sum_rent_comment":"","sum_rent_hidden":false,"year":"2008","sum_hidden":false,"brand_info_hidden":false,"brand_info_unclear":false,"year_unclear":false,"sum_rent":"","sum":"","brand":"Subaru Forester","sum_comment":"","brand_unclear":false,"brand_hidden":false}]},"id":"vulyk_62_56","declaration":{"additional_info_text":"","notfull_lostpages":"","date":"2015-03-30T00:00:00","notfull":"","additional_info":"","url":"http://static.declarations.com.ua/declarations/chosen_ones/mega_batch/hrynenko_oleksandr_ivanovych.pdf"},"liabilities":{"54":{"sum_foreign_comment":"","sum":"","sum_comment":"","sum_hidden":false,"sum_comment_hidden":false,"sum_foreign":""},"55":{"sum_foreign_comment":"","sum":"","sum_comment":"","sum_hidden":false,"sum_comment_hidden":false,"sum_unclear":false,"sum_foreign":""},"56":{"sum_foreign_comment":"","sum":"","sum_comment":"","sum_hidden":false,"sum_unclear":false,"sum_foreign":""},"57":{"sum_foreign_comment":"","sum":"","sum_comment":"","sum_hidden":false,"sum_comment_hidden":false,"sum_unclear":false,"sum_foreign":""},"58":{"sum_foreign_comment":"","sum_foreign_hidden":false,"sum_comment":"","sum_hidden":false,"sum_comment_hidden":false,"sum_unclear":false,"sum":"","sum_foreign":""},"59":{"sum_foreign_comment":"","sum":"","sum_comment":"","sum_foreign":""},"60":{"sum_foreign_comment":"","sum_foreign_hidden":false,"sum_comment":"","sum_hidden":false,"sum_comment_hidden":false,"sum_unclear":false,"sum":"","sum_foreign":""},"61":{"sum_foreign_comment":"","sum_foreign_hidden":false,"sum_comment":"","sum_hidden":false,"sum":"","sum_foreign":""},"62":{"sum_foreign_comment":"","sum":"","sum_comment":"","sum_unclear":false,"sum_foreign":""},"63":{"sum_foreign_comment":"","sum":"","sum_comment":"","sum_hidden":false,"sum_comment_hidden":false,"sum_unclear":false,"sum_foreign":""},"64":{"sum_foreign_comment":"","sum":"","sum_comment":"","sum_comment_unclear":false,"sum_hidden":false,"sum_comment_hidden":false,"sum_foreign":""}},"ft_src":"суддя апеляційного суду київської області\nКиївська область\nЗагальний апеляційний суд\nОлександр\nЛященко Наталія Павлівна\nПодружжя\nГриненко Наталія Олександрівна\nДитина\nІванович\nГриненко Олександр Іванович\nОлександр Іванович Гриненко\nОлександр Гриненко\nГриненко Олександр Іванович\nГриненко Олександр Іванович\nГриненко\n2500 куб. см.\nSubaru Forester\n2008\n1000\n5900\n38.1\n85.8\n290\n38.1\n2014\n319478.12\n277892.79\n15834\n13398\n418895.4\n291290.79\n83583.28\n2500 куб. см.\nSubaru Forester\n2008\n1000\n5900\n290\n38.1\n85.8\n38.1\nПодружжя\nЛященко Наталія Павлівна\nДитина\nГриненко Наталія Олександрівна\nГриненко Олександр Іванович\nОлександр Іванович Гриненко\nОлександр Гриненко\nГриненко Олександр Іванович\nГриненко Олександр Іванович\nОлександр\nІванович\nЗагальний апеляційний суд\nсуддя апеляційного суду київської області\nКиївська область\nГриненко\n277892.79\n319478.12\n83583.28\n291290.79\n418895.4\n13398\n15834\n2014\nПодружжя\nЛященко Наталія Павлівна\nГриненко Наталія Олександрівна\nДитина\nІванович\nГриненко\nОлександр\nГриненко Олександр Іванович\nОлександр Іванович Гриненко\nОлександр Гриненко\nГриненко Олександр Іванович\nКиївська область\nсуддя апеляційного суду київської області\nЗагальний апеляційний суд\nГриненко Олександр Іванович\nSubaru Forester\n2500 куб. см.\n2008\n15834\n13398\n83583.28\n291290.79\n418895.4\n319478.12\n277892.79\n38.1\n85.8\n1000\n5900\n290\n38.1\n2014","general":{"inn":"","name":"Олександр","inn_unclear":false,"family":[{"inn":"","inn_hidden":true,"relations_unclear":false,"relations_hidden":false,"relations_other":"","relations":"Подружжя","name_hidden":false,"inn_unclear":false,"family_name":"Лященко Наталія Павлівна","name_unclear":false},{"inn":"","inn_hidden":true,"relations_hidden":false,"family_name":"Гриненко Наталія Олександрівна","relations_other":"","relations":"Дитина","name_hidden":false,"name_unclear":false}],"inn_hidden":true,"family_raw":"","last_name":"Гриненко","post":{"post_unclear":false,"post":"суддя апеляційного суду київської області","post_hidden":false,"region":"Київська область","region_hidden":false,"office":"Загальний апеляційний суд","office_hidden":false,"office_unclear":false},"full_name_suggest":{"output":"Гриненко Олександр Іванович","input":["Гриненко Олександр Іванович","Олександр Іванович Гриненко","Олександр Гриненко"]},"full_name":"Гриненко Олександр Іванович","addresses":[{"place_city_type_unclear":false,"place_address":"","place_district_hidden":true,"place_city_type":"","place_address_hidden":true,"place_address_unclear":false,"place_city_type_hidden":true,"place":"","place_district":"","place_unclear":false,"place_city":"","place_city_unclear":false,"place_hidden":true,"place_city_hidden":true,"place_district_unclear":false}],"patronymic":"Іванович","last_name_unclear":false,"name_unclear":false},"source":"VULYK","estate":{"23":[{"region_unclear":false,"space_unclear":false,"costs":"","costs_comment":"","costs_hidden":false,"address_hidden":false,"region_hidden":true,"space_comment":"","space":"1000","address":"","region":"","address_unclear":false,"space_units_unclear":false,"space_comment_unclear":false,"space_units":"м²","space_units_hidden":false,"costs_rent":"","costs_rent_comment":""},{"space_unclear":false,"costs":"","costs_comment":"","costs_hidden":false,"region_hidden":true,"space_comment":"","space_hidden":false,"space":"5900","address":"","region":"","costs_rent_comment":"","space_comment_unclear":false,"space_units":"м²","space_units_hidden":false,"costs_rent":""}],"24":[{"space_unclear":false,"costs":"","costs_comment":"","address_hidden":false,"region_hidden":true,"space_comment":"","space_hidden":false,"space_units_unclear":false,"address":"","region":"","address_unclear":false,"space":"290","space_comment_unclear":false,"space_units":"м²","space_units_hidden":false,"costs_rent":"","costs_rent_comment":""}],"25":[{"region_unclear":false,"space_hidden":false,"costs":"","costs_comment":"","costs_hidden":false,"address_hidden":false,"region_hidden":true,"space_comment":"","space_unclear":false,"space":"38.1","address":"","region":"","costs_rent_comment":"","space_units":"м²","costs_rent":""}],"31":[{"region_unclear":false,"space_hidden":false,"address_hidden":false,"region_hidden":true,"space_comment":"","space_unclear":false,"space":"38.1","costs_property_unclear":false,"region":"","costs_property":"","costs_rent_comment":"","space_comment_unclear":false,"address_unclear":false,"space_units":"м²","costs_property_comment":"","costs_rent":"","address":""},{"region_unclear":false,"space_hidden":false,"address_hidden":false,"region_hidden":false,"space_comment":"","space_units_hidden":false,"space":"85.8","address":"","region":"","address_unclear":false,"costs_rent_comment":"","costs_property":"","space_units":"м²","costs_property_comment":"","costs_rent":""}]},"intro":{"declaration_year":"2014","isnotdeclaration":"","declaration_year_unclear":false,"declaration_year_hidden":false}}