{"id":"vulyk_103_117","ft_src":"Toyota Corolla\n221528\n1 /2 автомобіля, 1600 куб. см.\n2013\n1 /2 автомобіля, 1600 куб. см. (дружина\nToyota Corolla\n2013\n700\n5508\n1983\n557.2\n107.7\n70.8\n128.91\n598.1\n70.8\n300000\n2015\n1 /2 автомобіля, 1600 куб. см.\n2013\n221528\nToyota Corolla\n1 /2 автомобіля, 1600 куб. см. (дружина\n2013\nToyota Corolla\n128.91\n598.1\n70.8\n700\n5508\n1983\n107.7\n557.2\n70.8\nШевчук\nШевчук Станіслав Володимирович\nСтаніслав Володимирович Шевчук\nСтаніслав Шевчук\nШевчук Станіслав Володимирович\nШевчук Станіслав Володимирович\nВолодимирович\nПодружжя\nШевчук Г. З\nШевчук О. С\nДитина\nБрат/Сестра\nОдд Д. В\nСтаніслав\nКонституційний Cуд\nсуддя конституційного суду україни\nЗагальнодержавний регіон\n1070701.6\nНаціональна Академія правових наук України, Національний університет Києво-Могилянська Академія\n71146.68\n257585.48\n1294233.73\n328732.16\n1369196.23\n74962.5\n300000\n2015\n1070701.6\n1294233.73\n257585.48\n74962.5\n71146.68\nНаціональна Академія правових наук України, Національний університет Києво-Могилянська Академія\n1369196.23\n328732.16\nПодружжя\nШевчук Г. З\nДитина\nШевчук О. С\nБрат/Сестра\nОдд Д. В\nШевчук\nВолодимирович\nсуддя конституційного суду україни\nКонституційний Cуд\nЗагальнодержавний регіон\nШевчук Станіслав Володимирович\nШевчук Станіслав Володимирович\nСтаніслав Володимирович Шевчук\nСтаніслав Шевчук\nШевчук Станіслав Володимирович\nСтаніслав","estate":{"24":[{"address":"","space_units":"м²","space_hidden":false,"space_unclear":false,"region_hidden":true,"costs_comment":"","space_comment":"","address_hidden":false,"space":"557.2","costs_rent_comment":"","costs":"","region":"","costs_rent":""}],"25":[{"address":"","space_units":"м²","costs_comment":"","region_hidden":true,"space_comment":"","address_hidden":false,"space_comment_hidden":false,"space":"70.8","space_comment_unclear":false,"costs_rent_comment":"","costs":"","region":"","costs_rent":""}],"29":[{"costs_property_comment":"","address":"","space_units":"м²","space_hidden":false,"space_comment":"","region_hidden":true,"costs_property":"","region":"","address_hidden":false,"costs_rent_comment":"","space":"700","costs_rent":""},{"costs_property_comment":"","address":"","space_units":"м²","costs_rent_comment":"","space":"5508","costs_property":"","space_comment":"","costs_rent":""},{"costs_property_comment":"","address":"","space_units":"м²","costs_rent_comment":"","space":"1983","space_unclear":false,"costs_property":"","space_comment":"","costs_rent":""}],"30":[{"costs_property_comment":"","address":"","space_units":"м²","space_hidden":false,"space_unclear":false,"region_hidden":true,"costs_property":"","space_comment":"","address_hidden":false,"costs_rent_comment":"","space":"128.91","costs_rent":""},{"costs_property_comment":"","address":"","space_units":"м²","costs_rent_comment":"","space":"598.1","costs_property":"","space_comment":"","costs_rent":""}],"31":[{"costs_property_comment":"","address":"","space_units":"м²","space_hidden":false,"region_hidden":true,"costs_property":"","space_comment":"","address_hidden":false,"address_unclear":false,"costs_rent_comment":"","space":"70.8","costs_rent":""}],"33":[{"costs_property_comment":"","address":"","space_units":"м²","costs_rent_comment":"","space_hidden":false,"region_hidden":true,"costs_property":"","space_comment":"","space":"107.7","costs_rent":""}]},"vehicle":{"35":[{"sum_comment":"","brand_info_hidden":false,"brand_info":"1 /2 автомобіля, 1600 куб. см.","sum":"221528","brand_unclear":false,"brand_hidden":false,"brand":"Toyota Corolla","sum_rent":"","brand_info_unclear":false,"sum_rent_comment":"","year":"2013"}],"40":[{"year_hidden":false,"brand_info":"1 /2 автомобіля, 1600 куб. см. (дружина","sum":"","sum_rent_comment":"","brand_hidden":false,"brand":"Toyota Corolla","sum_rent":"","sum_comment":"","year":"2013","brand_info_unclear":false}]},"source":"VULYK","income":{"5":{"family_comment":"","family":"1369196.23","comment":"","value_unclear":false,"family_hidden":false,"value":"328732.16"},"6":{"family_comment":"","value":"257585.48","family":"1294233.73","comment":""},"7":{"family":"","family_comment":"","value":"71146.68","comment":"","source_name":"Національна Академія правових наук України, Національний університет Києво-Могилянська Академія"},"8":{"family_comment":"","value":"","family":"","comment":""},"9":{"family_comment":"","value":"","family":"74962.5","comment":""},"10":{"family_comment":"","value":"","family":"","comment":""},"11":{"family_comment":"","family_hidden":false,"value":"","family":"","comment":""},"12":{"family_comment":"","value":"","family":"","comment":""},"13":{"family_comment":"","value":"","family":"","comment":""},"14":{"family_comment":"","value":"","family":"","comment":""},"15":{"family_comment":"","value":"","family":"","comment":""},"16":{"family_comment":"","value":"","family":"","comment":""},"17":{"family_comment":"","value":"","family":"","comment":"","family_comment_unclear":false},"18":{"family_comment":"","value":"","family":"","comment":""},"19":{"family_comment":"","value":"","family":"","comment":""},"20":{"family_comment":"","family":"","comment":"","family_unclear":false,"family_hidden":false,"value":""}},"banks":{"51":[{"sum_units":"UAH","sum_comment":"","sum_foreign_units":"UAH","sum_hidden":false,"sum":"300000","sum_foreign_comment_hidden":false,"sum_foreign_comment":"","sum_foreign":"","sum_foreign_hidden":false,"sum_comment_hidden":true}]},"declaration":{"additional_info_text":"","additional_info":"","date":"2016-03-24T00:00:00","url":"http://static.declarations.com.ua/declarations/chosen_ones/judges_batch/1072_shevchuk_stanislav_volodymyrovych.pdf"},"general":{"inn":"","addresses":[{"place_city_type_hidden":false,"place_city_type":"","place_city_hidden":true,"place_hidden":true,"place_district":"","place_district_hidden":false,"place":"","place_city":"","place_address_hidden":true,"place_address":""}],"last_name":"Шевчук","full_name":"Шевчук Станіслав Володимирович","family":[{"inn":"","family_name":"Шевчук Г. З","relations_hidden":false,"name_unclear":false,"relations":"Подружжя","inn_hidden":true,"name_hidden":true,"relations_other":""},{"inn":"","family_name":"Шевчук О. С","inn_hidden":true,"relations_other":"","relations":"Дитина"},{"inn":"","family_name":"Одд Д. В","relations_other":"","name_unclear":false,"inn_hidden":false,"relations":"Брат/Сестра"}],"patronymic":"Володимирович","inn_hidden":true,"name":"Станіслав","post":{"office":"Конституційний Cуд","region_unclear":false,"post":"суддя конституційного суду україни","region":"Загальнодержавний регіон","office_unclear":false},"family_raw":"","full_name_suggest":{"input":["Шевчук Станіслав Володимирович","Станіслав Володимирович Шевчук","Станіслав Шевчук"],"output":"Шевчук Станіслав Володимирович"}},"liabilities":{"54":{"sum_foreign_comment_hidden":false,"sum_foreign_comment_unclear":false,"sum_hidden":false,"sum":"","sum_foreign_comment":"","sum_comment":"","sum_unclear":false,"sum_foreign":"","sum_comment_hidden":false,"sum_foreign_hidden":false},"55":{"sum_comment":"","sum_foreign_comment":"","sum_foreign":"","sum":""},"56":{"sum_comment":"","sum_foreign_comment":"","sum_foreign":"","sum":""},"57":{"sum_comment":"","sum_hidden":false,"sum":"","sum_foreign_comment":"","sum_foreign":"","sum_comment_hidden":false,"sum_foreign_hidden":false,"sum_foreign_comment_hidden":false},"58":{"sum_comment":"","sum_hidden":false,"sum":"","sum_foreign_comment":"","sum_foreign":"","sum_comment_hidden":false,"sum_foreign_hidden":false,"sum_foreign_comment_hidden":false},"59":{"sum_comment":"","sum_hidden":false,"sum":"","sum_foreign_comment":"","sum_foreign":"","sum_comment_hidden":false,"sum_foreign_hidden":false,"sum_foreign_comment_hidden":false},"60":{"sum_comment":"","sum_hidden":false,"sum":"","sum_foreign_comment":"","sum_foreign":"","sum_comment_hidden":false},"61":{"sum_comment":"","sum_foreign_comment":"","sum_foreign":"","sum":""},"62":{"sum_comment":"","sum_foreign_comment":"","sum_foreign":"","sum":"1070701.6","sum_comment_hidden":false},"63":{"sum_comment":"","sum_foreign_comment":"","sum_foreign":"","sum":""},"64":{"sum_comment":"","sum_foreign_comment":"","sum_foreign":"","sum":""}},"intro":{"declaration_year":"2015"}}