{"id":"vulyk_62_187","ft_src":"1500\nВАЗ 21099\n1995\nОдеська область\nм. Ананьїв\n890\nОдеська область\nм. Ананьїв\n41.6\nОдеська область\nсмт Ширяєве\n85.3\nОсинівська с/р,Ширяївського р-ну\nОдеська область\n52900\nОсинівська с/р,Ширяївського р-ну\nОдеська область\n1672\nОдеська область\nм. Ананьїв\n346\nДоговір дарування\nОдеська область\nм. Ананьїв\n68.4\n2014\n224660\n13200\n13200\n224660\n2335\n1500\nВАЗ 21099\n1995\n890\nОдеська область\nм. Ананьїв\n52900\nОсинівська с/р,Ширяївського р-ну\nОдеська область\n1672\nОсинівська с/р,Ширяївського р-ну\nОдеська область\nм. Ананьїв\nОдеська область\n346\n68.4\nДоговір дарування\nОдеська область\nм. Ананьїв\n41.6\nОдеська область\nм. Ананьїв\n85.3\nсмт Ширяєве\nОдеська область\nПодружжя\nНиколайчук Г. О. 16. 10. 1955\nНиколайчук Валентин Олександрович\nВалентин Олександрович Николайчук\nВалентин Николайчук\nНиколайчук Валентин Олександрович\nНиколайчук Валентин Олександрович\nВалентин\nОлександрович\nЗагальний місцевий суд\nголова ширяївського районного суду одеської області\nОдеська область\nНиколайчук\n66800\nОдеська область\nШиряївський\n224660\n13200\n224660\n13200\n2335\n2014\nПодружжя\nНиколайчук Г. О. 16. 10. 1955\nОлександрович\nНиколайчук\nВалентин\nНиколайчук Валентин Олександрович\nВалентин Олександрович Николайчук\nВалентин Николайчук\nНиколайчук Валентин Олександрович\nОдеська область\nШиряївський\n66800\nОдеська область\nголова ширяївського районного суду одеської області\nЗагальний місцевий суд\nНиколайчук Валентин Олександрович","estate":{"23":[{"address":"м. Ананьїв","space_units":"м²","costs_hidden":false,"space_unclear":false,"costs_comment":"","space_units_unclear":false,"region":"Одеська область","space_comment_unclear":false,"costs":"","address_unclear":true,"space_comment":"","address_hidden":false,"costs_rent_comment":"","space":"890","region_unclear":false,"region_hidden":false,"space_units_hidden":false,"costs_rent":""}],"24":[{"address":"м. Ананьїв","space_units":"м²","space_hidden":false,"space_unclear":false,"region_hidden":false,"costs_comment":"","space_comment":"Договір дарування","space_comment_unclear":false,"space_units_unclear":false,"costs":"","address_unclear":true,"address_hidden":false,"costs_rent_comment":"","space":"68.4","region":"Одеська область","space_units_hidden":false,"costs_rent":""}],"29":[{"costs_property_comment":"","address":"Осинівська с/р,Ширяївського р-ну","space_units":"м²","space_hidden":false,"space_unclear":false,"region_hidden":false,"costs_property":"","space_comment":"","address_hidden":false,"address_unclear":true,"costs_rent_comment":"","space":"52900","region_unclear":false,"region":"Одеська область","costs_rent":""},{"costs_property_comment":"","address":"Осинівська с/р,Ширяївського р-ну","space_units":"м²","space_unclear":false,"region_hidden":false,"costs_property":"","space_comment":"","address_hidden":true,"costs_rent_comment":"","space":"1672","region_unclear":false,"region":"Одеська область","costs_rent":""},{"costs_property_comment":"","costs_property":"","address":"м. Ананьїв","space_units":"м²","space_comment":"","region_hidden":false,"space_units_unclear":false,"region":"Одеська область","address_hidden":false,"costs_rent_comment":"","space":"346","costs_rent":""}],"30":[{"costs_property_comment":"","address":"м. Ананьїв","space_units":"м²","space_hidden":false,"space_unclear":false,"region_hidden":false,"costs_property":"","space_comment":"","space_comment_unclear":false,"address_unclear":true,"address_hidden":false,"costs_rent_comment":"","space":"41.6","region":"Одеська область","costs_rent":""},{"costs_property_comment":"","address":"смт Ширяєве","space_units":"м²","costs_rent_comment":"","space":"85.3","space_unclear":false,"region_hidden":false,"costs_property":"","space_comment":"","region":"Одеська область","costs_rent":""}]},"vehicle":{"35":[{"year_hidden":false,"brand_info":"1500","sum_rent_comment":"","brand_unclear":false,"brand_hidden":false,"year":"1995","brand":"ВАЗ 21099","sum_rent_hidden":false,"brand_info_hidden":false,"sum_rent":"","year_unclear":false,"sum_comment":"","sum_hidden":false,"brand_info_unclear":false,"sum":""}]},"source":"VULYK","income":{"5":{"family":"13200","family_comment":"","comment":"","value_hidden":false,"value_unclear":false,"value":"224660","family_hidden":false,"family_unclear":false,"family_comment_unclear":false},"6":{"family_comment":"","value":"224660","family_unclear":false,"family":"","comment":""},"7":{"source_name_hidden":false,"family_comment":"","comment":"","family":"","source_name_unclear":false,"value":"","source_name":""},"8":{"family_comment":"","value":"","family":"","comment":""},"9":{"family_comment":"","value":"","family_unclear":false,"family":"","comment":""},"10":{"family_comment":"","value":"","family":"","comment":""},"11":{"family_comment":"","value":"","family":"","comment":""},"12":{"family_comment":"","value":"","family":"","comment":""},"13":{"family_comment":"","value":"","family":"","comment":""},"14":{"family_comment":"","value":"","family":"","comment":""},"15":{"family_comment":"","value":"","family":"13200","comment":""},"16":{"family":"","family_comment":"","comment":"","value_hidden":false,"value_unclear":false,"value":""},"17":{"family_comment":"","value":"","family":"","comment":""},"18":{"family_comment":"","value":"","family":"","comment":""},"19":{"family_comment":"","value":"","family":"2335","comment":""},"20":{"family_unclear":false,"family_comment":"","comment":"","family":"","value_unclear":false,"value_hidden":false,"comment_hidden":false,"comment_unclear":false,"value":"","family_hidden":false,"family_comment_unclear":false}},"general":{"family":[{"inn":"","inn_unclear":false,"family_name":"Николайчук Г. О. 16. 10. 1955","relations_hidden":false,"relations_unclear":false,"name_unclear":false,"relations":"Подружжя","inn_hidden":false,"name_hidden":false,"relations_other":""}],"family_raw":"","name":"Валентин","full_name_suggest":{"input":["Николайчук Валентин Олександрович","Валентин Олександрович Николайчук","Валентин Николайчук"],"output":"Николайчук Валентин Олександрович"},"name_unclear":false,"patronymic":"Олександрович","inn_hidden":false,"addresses":[{"place_city_type_hidden":false,"place_district_hidden":false,"place_address_unclear":false,"place":"Одеська область","place_city":"","place_unclear":false,"place_city_type_unclear":false,"place_city_type":"","place_city_hidden":false,"place_city_unclear":false,"place_district":"Ширяївський","place_district_unclear":false,"place_address":"66800","place_address_hidden":false,"place_hidden":false}],"inn":"","inn_unclear":false,"last_name":"Николайчук","full_name":"Николайчук Валентин Олександрович","post":{"post_hidden":false,"office":"Загальний місцевий суд","post":"голова ширяївського районного суду одеської області","region":"Одеська область","office_hidden":false,"office_unclear":false,"region_hidden":false,"post_unclear":false},"last_name_unclear":false},"liabilities":{"54":{"sum_comment":"","sum_hidden":false,"sum":"","sum_foreign_comment":"","sum_foreign":"","sum_comment_hidden":false},"55":{"sum_comment":"","sum_hidden":false,"sum":"","sum_foreign_comment":"","sum_foreign":"","sum_unclear":false,"sum_comment_hidden":false},"56":{"sum_comment":"","sum_hidden":false,"sum":"","sum_foreign_comment":"","sum_foreign":"","sum_unclear":false},"57":{"sum_comment":"","sum_hidden":false,"sum":"","sum_foreign_comment":"","sum_foreign":"","sum_unclear":false,"sum_comment_hidden":false},"58":{"sum_comment":"","sum_hidden":false,"sum":"","sum_foreign_comment":"","sum_foreign":"","sum_unclear":false,"sum_foreign_hidden":false,"sum_comment_hidden":false},"59":{"sum_comment":"","sum_foreign_comment":"","sum_foreign":"","sum":""},"60":{"sum_comment":"","sum_hidden":false,"sum":"","sum_foreign_comment":"","sum_foreign":"","sum_unclear":false,"sum_foreign_hidden":false,"sum_comment_hidden":false},"61":{"sum_comment":"","sum_hidden":false,"sum":"","sum_foreign_comment":"","sum_foreign":"","sum_foreign_hidden":false},"62":{"sum_comment":"","sum_foreign_comment":"","sum_foreign":"","sum_unclear":false,"sum":""},"63":{"sum_comment":"","sum_hidden":false,"sum":"","sum_foreign_comment":"","sum_foreign":"","sum_unclear":false,"sum_comment_hidden":false},"64":{"sum_comment_unclear":false,"sum_comment":"","sum_hidden":false,"sum":"","sum_foreign_comment":"","sum_foreign":"","sum_comment_hidden":false}},"declaration":{"notfull_lostpages":"","additional_info_text":"","additional_info":"","date":"2015-03-20T00:00:00","notfull":"","url":"http://static.declarations.com.ua/declarations/chosen_ones/mega_batch/nykolaichuk_valentyn_oleksandrovych.pdf"},"intro":{"declaration_year_hidden":false,"isnotdeclaration":"","declaration_year_unclear":false,"declaration_year":"2014"}}