{"income":{"5":{"family_comment":"","value":"232029.69","family_hidden":false,"comment":"","family":"39329.2"},"6":{"value":"232029.69","value_unclear":false,"family_hidden":false,"family_comment":"","family":"17146.46","comment":""},"7":{"family_comment":"","value":"","source_name":"Апеляційний суд Хмельницької області","family":"","comment":""},"8":{"family_comment":"","value":"","family":"","comment":""},"9":{"family_comment":"","value":"","value_unclear":false,"family":"14.39","comment":""},"10":{"family_comment":"","value":"","value_unclear":false,"family":"","comment":""},"11":{"family_comment":"","value":"","family":"","comment":""},"12":{"family_comment":"","value":"","family":"2096.75","comment":""},"13":{"family_comment":"","value":"","family":"","comment":""},"14":{"family_comment":"","value":"","family":"","comment":""},"15":{"family_comment":"","value":"","family":"","comment":""},"16":{"family_comment":"","value":"","family":"","comment":"","family_comment_hidden":false},"17":{"family_comment":"","value":"","family_hidden":false,"comment":"","family":""},"18":{"family_comment":"","value":"","family":"","comment":""},"19":{"family_comment":"","value":"","family":"","comment":""},"20":{"value":"","value_unclear":false,"family_comment_hidden":false,"family_comment":"","comment_unclear":false,"comment":"","family":"20071.6"}},"id":"vulyk_42_102","banks":{"45":[{"sum_foreign_comment":"","sum_units":"UAH","sum_comment":"","sum_foreign_comment_hidden":false,"sum_hidden":false,"sum_foreign_units":"UAH","sum_foreign_hidden":false,"sum_comment_hidden":false,"sum_unclear":false,"sum":"","sum_foreign":""},{"sum_foreign_comment":"","sum_units":"","sum_comment":"","sum_foreign_units":"","sum":"","sum_foreign":""}],"46":[{"sum_foreign_comment":"","sum_units":"UAH","sum_comment":"","sum_hidden":false,"sum_foreign_units":"UAH","sum_comment_hidden":false,"sum_unclear":false,"sum":"","sum_foreign":""}],"47":[{"sum_foreign_comment":"","sum_units":"UAH","sum_comment":"","sum_comment_unclear":false,"sum_hidden":false,"sum_foreign_units":"UAH","sum":"","sum_foreign":""},{"sum_foreign_comment":"","sum":"","sum_comment":"","sum_foreign":""}],"48":[{"sum_foreign_comment":"","sum_units":"UAH","sum_comment":"","sum_foreign_units":"UAH","sum":"","sum_foreign":""}],"49":[{"sum_foreign_comment":"","sum_units":"UAH","sum_comment":"","sum_foreign_units":"UAH","sum":"","sum_foreign":""}],"50":[{"sum_foreign_comment":"","sum_units":"UAH","sum_comment":"","sum_foreign_units":"UAH","sum":"","sum_foreign":""}],"51":[{"sum_foreign_comment":"","sum_units":"UAH","sum_comment":"","sum_comment_unclear":true,"sum_hidden":false,"sum_foreign_units":"UAH","sum_comment_hidden":false,"sum":"94.37","sum_foreign":""},{"sum_foreign_comment":"","sum_units":"","sum_comment":"","sum_hidden":false,"sum_foreign_units":"","sum":"","sum_units_hidden":false,"sum_foreign":""}],"52":[{"sum_foreign_comment":"","sum_units":"UAH","sum_comment":"","sum_comment_unclear":false,"sum_hidden":false,"sum_foreign_units":"UAH","sum":"","sum_units_hidden":false,"sum_foreign":""}],"53":[{"sum_foreign_comment":"","sum_units":"UAH","sum_comment":"","sum_foreign_units":"UAH","sum":"","sum_foreign":""}]},"declaration":{"additional_info_text":"","notfull_lostpages":"","date":"2015-03-18T00:00:00","notfull":"","additional_info":"","url":"http://static.declarations.com.ua/declarations/chosen_ones/mega_batch/bolotin_serhii_mykolaiovych.pdf"},"liabilities":{"54":{"sum_foreign_comment":"","sum":"","sum_comment":"","sum_foreign_comment_hidden":false,"sum_comment_hidden":false,"sum_foreign":""},"55":{"sum_foreign_comment":"","sum":"","sum_comment":"","sum_foreign":""},"56":{"sum_foreign_comment":"","sum":"1478","sum_comment":"","sum_foreign":""},"57":{"sum_foreign_comment":"","sum":"","sum_comment":"","sum_comment_unclear":false,"sum_comment_hidden":false,"sum_unclear":false,"sum_foreign":""},"58":{"sum_foreign_comment":"","sum":"","sum_comment":"","sum_foreign_unclear":false,"sum_comment_hidden":false,"sum_unclear":false,"sum_foreign":""},"59":{"sum_foreign_comment":"","sum":"","sum_comment":"","sum_foreign":""},"60":{"sum_foreign_comment":"","sum":"","sum_comment":"","sum_comment_unclear":false,"sum_hidden":false,"sum_comment_hidden":false,"sum_foreign":""},"61":{"sum_foreign_comment":"","sum":"","sum_comment":"","sum_foreign":""},"62":{"sum_foreign_comment":"","sum":"","sum_comment":"","sum_hidden":false,"sum_comment_hidden":false,"sum_foreign":""},"63":{"sum_foreign_comment":"","sum":"","sum_comment":"","sum_comment_hidden":false,"sum_unclear":false,"sum_foreign":""},"64":{"sum_foreign_comment":"","sum":"","sum_comment":"","sum_hidden":false,"sum_comment_hidden":false,"sum_foreign":""}},"ft_src":"1478\nХмельницький\nХмельницька область\nсуддя апеляційного суду хмельницької області\nХмельницька область\nЗагальний апеляційний суд\nСергій\nБолотіна А. П. 20. 08. 1981\nПодружжя\nМиколайович\nБолотін Сергій Миколайович\nСергій Миколайович Болотін\nСергій Болотін\nБолотін Сергій Миколайович\nБолотін\nБолотін Сергій Миколайович\n20071.6\n39329.2\n232029.69\nАпеляційний суд Хмельницької області\n14.39\n2096.75\n232029.69\n17146.46\n94.37\n.0546\n56.3\n2014\n17146.46\n232029.69\nАпеляційний суд Хмельницької області\n39329.2\n232029.69\n14.39\n20071.6\n2096.75\n94.37\n2014\nПодружжя\nБолотіна А. П. 20. 08. 1981\nБолотін Сергій Миколайович\nСергій Миколайович Болотін\nСергій Болотін\nБолотін Сергій Миколайович\nБолотін Сергій Миколайович\nСергій\nБолотін\nсуддя апеляційного суду хмельницької області\nЗагальний апеляційний суд\nХмельницька область\nМиколайович\nХмельницька область\nХмельницький\n1478\nАпеляційний суд Хмельницької області\n232029.69\n17146.46\n2096.75\n20071.6\n232029.69\n39329.2\n14.39\n.0546\n56.3\n1478\nБолотіна А. П. 20. 08. 1981\nПодружжя\nМиколайович\nБолотін\nСергій\nБолотін Сергій Миколайович\nСергій Миколайович Болотін\nСергій Болотін\nБолотін Сергій Миколайович\nХмельницька область\nХмельницький\nХмельницька область\nсуддя апеляційного суду хмельницької області\nЗагальний апеляційний суд\nБолотін Сергій Миколайович\n56.3\n.0546\n94.37\n2014","general":{"inn":"","name":"Сергій","patronymic_unclear":false,"last_name_hidden":false,"family":[{"inn":"","inn_hidden":true,"relations_hidden":false,"family_name":"Болотіна А. П. 20. 08. 1981","relations_other":"","relations":"Подружжя","name_hidden":false,"name_unclear":false}],"patronymic":"Миколайович","inn_hidden":true,"family_raw":"","last_name":"Болотін","post":{"region_unclear":false,"region":"Хмельницька область","post":"суддя апеляційного суду хмельницької області","office":"Загальний апеляційний суд","office_hidden":false,"region_hidden":false},"last_name_unclear":false,"full_name":"Болотін Сергій Миколайович","addresses":[{"place_district":"","place_city_hidden":false,"place_city":"Хмельницький","place_city_type_hidden":true,"place_district_hidden":false,"place_city_type":"Місто","place_address_hidden":true,"place_address":"","place_hidden":false,"place":"Хмельницька область"}],"full_name_suggest":{"output":"Болотін Сергій Миколайович","input":["Болотін Сергій Миколайович","Сергій Миколайович Болотін","Сергій Болотін"]}},"source":"VULYK","estate":{"23":[{"space_unclear":false,"costs":"","costs_comment":"","address_hidden":false,"region_hidden":true,"space_comment":"","space_hidden":false,"space":".0546","address":"","region":"","address_unclear":false,"space_units_unclear":false,"space_comment_unclear":false,"space_units":"га","costs_rent":"","costs_rent_comment":""},{"costs":"","costs_comment":"","address_hidden":false,"region_hidden":false,"space_comment":"","space_units_unclear":false,"address":"","space":"","region":"","costs_rent_comment":"","space_units":"","costs_rent":""},{"costs_rent":"","region":"","costs":"","costs_rent_comment":"","costs_comment":"","space_comment":"","space_units":"","space":"","address":""},{"costs_rent":"","region":"","costs":"","costs_rent_comment":"","costs_comment":"","space_comment":"","space_units":"","space":"","address":""},{"costs_rent":"","region":"","costs":"","costs_rent_comment":"","costs_comment":"","space_comment":"","space_units":"","space":"","address":""},{"costs_rent":"","costs":"","costs_rent_comment":"","costs_comment":"","space_comment":"","space_units":"","space":"","address":""}],"25":[{"space_unclear":false,"costs":"","costs_comment":"","address_hidden":false,"region_hidden":true,"space_comment":"","space_hidden":false,"space":"56.3","address":"","region":"","costs_rent_comment":"","space_comment_unclear":false,"space_units":"м²","costs_rent":""}]},"intro":{"declaration_year":"2014","isnotdeclaration":""}}