{"income":{"5":{"value":"184552","family_comment":"","value_unclear":false,"family_hidden":false,"value_hidden":false,"family_unclear":false,"comment_unclear":false,"comment":"","family":"2198295"},"6":{"value":"171705","family_comment":"","value_unclear":false,"family_hidden":false,"value_hidden":false,"family_unclear":false,"comment_unclear":false,"comment":"","family":""},"7":{"source_name_unclear":false,"value":"","family_comment":"","source_name":"","family":"","comment":""},"8":{"family_comment":"","value":"","family":"","comment":""},"9":{"value":"","value_unclear":false,"comment_hidden":false,"family_comment":"ПАТ 'Банк Богуслав'","comment_unclear":false,"comment":"","family":"27295"},"10":{"value":"12180","comment_unclear":false,"value_hidden":false,"family_comment":"","family":"","comment":""},"11":{"family_comment":"","value":"","family":"","comment":""},"12":{"family_comment":"","value":"","family":"","comment":""},"13":{"family_comment":"","value":"","family":"","comment":""},"14":{"family_comment":"","value":"","family":"","comment":""},"15":{"family_comment":"","value":"","family":"","comment":""},"16":{"family_comment":"","value":"","family":"","comment":""},"17":{"family_comment":"","value":"","family":"2171000","comment":""},"18":{"value":"","family_hidden":false,"value_hidden":false,"family_comment":"","family":"","comment":""},"19":{"family_comment":"","value":"","family":"","comment":""},"20":{"value":"667","family_comment":"","value_unclear":false,"family_hidden":false,"value_hidden":false,"family_unclear":false,"family":"","comment":""}},"vehicle":{"40":[{"brand_info":"3996 куб. см.","sum_rent_comment":"","brand":"Infiniti FX 37","sum_comment":"","brand_unclear":false,"year":"2011","brand_info_unclear":false,"year_unclear":false,"sum":"","sum_rent":""},{"brand_info":"1390 куб. см.","sum_rent_comment":"","brand":"Seat Ibiza","sum_comment":"","year":"2008","brand_info_unclear":true,"sum":"","sum_rent":""}]},"id":"vulyk_66_88","banks":{"47":[{"sum_foreign_comment":"","sum_units":"UAH","sum_units_hidden":false,"sum_comment":"","sum_comment_unclear":false,"sum_hidden":false,"sum_foreign_units":"UAH","sum_comment_hidden":false,"sum_unclear":false,"sum":"75","sum_foreign":""}],"51":[{"sum_foreign_comment":"","sum_units":"UAH","sum_comment":"","sum_comment_unclear":false,"sum_foreign_units":"UAH","sum_units_unclear":false,"sum_comment_hidden":false,"sum":"412866","sum_foreign":""}],"52":[{"sum_foreign_comment":"","sum_units":"UAH","sum_units_hidden":false,"sum_comment":"","sum_comment_unclear":false,"sum_hidden":false,"sum_foreign_units":"UAH","sum_comment_hidden":false,"sum_unclear":false,"sum":"11","sum_foreign":""}],"53":[{"sum_foreign_comment":"","sum_units":"UAH","sum_comment":"","sum_comment_unclear":false,"sum_foreign_units":"UAH","sum":"26250","sum_foreign":""}]},"declaration":{"additional_info_text":"","notfull_lostpages":"","date":"2015-03-30T00:00:00","notfull":"","additional_info":"","url":"http://static.declarations.com.ua/declarations/chosen_ones/mega_batch/humeha_oksana_valeriivna.pdf"},"liabilities":{"54":{"sum_foreign_comment":"","sum":"","sum_comment":"","sum_comment_unclear":false,"sum_comment_hidden":false,"sum_unclear":false,"sum_foreign":""},"55":{"sum_foreign_comment":"","sum":"","sum_comment":"","sum_foreign":""},"56":{"sum_foreign_comment":"","sum_foreign_hidden":false,"sum_comment":"","sum_hidden":false,"sum_comment_hidden":false,"sum":"2634","sum_foreign":""},"57":{"sum_foreign_comment":"","sum":"","sum_comment":"","sum_comment_unclear":false,"sum_hidden":false,"sum_comment_hidden":false,"sum_unclear":false,"sum_foreign":""},"58":{"sum_foreign_comment":"","sum":"","sum_comment":"","sum_comment_unclear":false,"sum_unclear":false,"sum_foreign":""},"59":{"sum_foreign_comment":"","sum_foreign_hidden":false,"sum_comment":"","sum_comment_unclear":false,"sum_hidden":false,"sum":"","sum_foreign":""},"60":{"sum_foreign_comment":"","sum":"7259","sum_comment":"","sum_comment_unclear":false,"sum_foreign":""},"61":{"sum_foreign_comment":"","sum":"","sum_comment":"","sum_foreign":""},"62":{"sum_foreign_comment":"","sum_foreign_hidden":false,"sum_comment":"","sum_hidden":false,"sum":"15732","sum_unclear":false,"sum_foreign":""},"63":{"sum_foreign_comment":"","sum":"","sum_comment":"","sum_comment_unclear":false,"sum_comment_hidden":false,"sum_unclear":false,"sum_foreign":""},"64":{"sum_foreign_comment":"","sum":"","sum_comment":"","sum_comment_unclear":false,"sum_foreign":""}},"ft_src":"15732\n2634\n7259\nКиїв\nм. Київ\nсуддя господарського суду м. києва\nм. Київ\nГосподарський місцевий суд\nОксана\nГумега А. В\nПодружжя\nГумега С. А\nДитина\nГумега С. А\nДитина\nГумега А. А\nДитина\nВалеріївна\nГумега Оксана Валеріївна\nОксана Валеріївна Гумега\nОксана Гумега\nГумега Оксана Валеріївна\nГумега Оксана Валеріївна\nГумега\n3996 куб. см.\nInfiniti FX 37\n2011\n1390 куб. см.\n2008\nSeat Ibiza\n75\n11\n26250\n412866\n2014\n3996 куб. см.\n2011\nInfiniti FX 37\n1390 куб. см.\nSeat Ibiza\n2008\n26250\n412866\n11\n75\n2103\nКиївська область\n274\nКиївська область\n101.5\nвласність\nм. Київ\n118.1\nу власності 3/4\nм. Київ\n118.1\nвласність 1/4\nм. Київ\nГосподарський місцевий суд\nсуддя господарського суду м. києва\nм. Київ\nПодружжя\nГумега А. В\nДитина\nГумега С. А\nДитина\nГумега С. А\nДитина\nГумега А. А\nГумега Оксана Валеріївна\nОксана Валеріївна Гумега\nОксана Гумега\nГумега Оксана Валеріївна\nГумега Оксана Валеріївна\nОксана\nГумега\nВалеріївна\nКиїв\nм. Київ\n7259\n2634\n15732\n171705\n2171000\n667\n184552\n2198295\n12180\nПАТ 'Банк Богуслав'\n27295\n2014\n2634\n15732\n7259\nвласність\n101.5\nм. Київ\nм. Київ\nу власності 3/4\n118.1\nКиївська область\n2103\nКиївська область\n274\nвласність 1/4\n118.1\nм. Київ\nГумега А. В\nПодружжя\nГумега С. А\nДитина\nГумега С. А\nДитина\nГумега А. А\nДитина\nВалеріївна\nГумега\nОксана\nГумега Оксана Валеріївна\nОксана Валеріївна Гумега\nОксана Гумега\nГумега Оксана Валеріївна\nм. Київ\nКиїв\nм. Київ\nсуддя господарського суду м. києва\nГосподарський місцевий суд\nГумега Оксана Валеріївна\n171705\n12180\n2198295\n184552\n2171000\nПАТ 'Банк Богуслав'\n27295\n667\n2011\n3996 куб. см.\nInfiniti FX 37\n2008\n1390 куб. см.\nSeat Ibiza\n12180\n667\n184552\n2198295\n2171000\nПАТ 'Банк Богуслав'\n27295\n171705\nвласність\nм. Київ\n101.5\nу власності 3/4\nм. Київ\n118.1\n118.1\nвласність 1/4\nм. Київ\nКиївська область\n2103\nКиївська область\n274\n75\n11\n412866\n26250\n2014","general":{"inn":"","name":"Оксана","last_name_hidden":false,"family":[{"inn":"","inn_hidden":true,"relations_hidden":false,"family_name":"Гумега А. В","relations_other":"","relations":"Подружжя","name_hidden":false,"name_unclear":false},{"inn":"","inn_hidden":true,"relations_unclear":false,"relations_hidden":false,"relations_other":"","relations":"Дитина","name_hidden":false,"family_name":"Гумега С. А","name_unclear":false},{"inn":"","inn_hidden":true,"relations_hidden":false,"family_name":"Гумега С. А","relations_other":"","relations":"Дитина","name_hidden":false,"name_unclear":false},{"inn":"","relations":"Дитина","relations_other":"","inn_hidden":true,"family_name":"Гумега А. А","name_hidden":false,"name_unclear":false}],"patronymic":"Валеріївна","inn_hidden":true,"family_raw":"","inn_unclear":false,"post":{"post_unclear":false,"post":"суддя господарського суду м. києва","candidate":"","office_hidden":false,"region":"м. Київ","office":"Господарський місцевий суд","office_unclear":false},"full_name_suggest":{"output":"Гумега Оксана Валеріївна","input":["Гумега Оксана Валеріївна","Оксана Валеріївна Гумега","Оксана Гумега"]},"full_name":"Гумега Оксана Валеріївна","addresses":[{"place_city_type_unclear":false,"place_address":"","place_district_hidden":true,"place_city_type":"Місто","place_address_hidden":true,"place_address_unclear":false,"place_city_type_hidden":true,"place":"м. Київ","place_district":"","place_unclear":false,"place_city":"Київ","place_city_unclear":false,"place_hidden":false,"place_city_hidden":true,"place_district_unclear":false}],"last_name":"Гумега","last_name_unclear":false},"source":"VULYK","estate":{"25":[{"region_unclear":false,"space_hidden":false,"costs":"","costs_comment":"","costs_hidden":false,"address_hidden":true,"region_hidden":false,"space_comment":"власність 1/4","space_unclear":false,"space":"118.1","space_units_hidden":false,"region":"м. Київ","address_unclear":false,"costs_rent_comment":"","space_comment_unclear":false,"space_units":"м²","address":"","costs_rent":""}],"29":[{"space_unclear":false,"address_hidden":true,"region_hidden":false,"space_comment":"","space_hidden":false,"space":"2103","address":"","region":"Київська область","costs_property":"","costs_rent_comment":"","space_units":"м²","costs_property_comment":"","costs_rent":""},{"costs_rent":"","region":"Київська область","costs_property":"","costs_rent_comment":"","address_hidden":true,"region_hidden":false,"space_comment":"","costs_property_comment":"","space_units":"м²","space":"274","address":""}],"31":[{"space_unclear":false,"address_hidden":true,"region_hidden":false,"space_comment":"власність","space_hidden":false,"space":"101.5","address":"","region":"м. Київ","costs_property":"","costs_rent_comment":"","space_comment_unclear":false,"space_comment_hidden":true,"space_units":"м²","costs_property_comment":"","costs_rent":""},{"costs_rent":"","region":"м. Київ","costs_property":"","costs_rent_comment":"","address_hidden":true,"region_hidden":false,"space_comment":"у власності 3/4","costs_property_comment":"","space_units":"м²","space":"118.1","address":""}]},"intro":{"declaration_year":"2014","isnotdeclaration":"","declaration_year_unclear":false}}