{"income":{"5":{"value":"330151.23","family_comment":"","value_unclear":false,"family_hidden":false,"value_hidden":false,"family_unclear":false,"family":"","comment":""},"6":{"value":"181151.23","family_comment":"","value_unclear":false,"family_hidden":false,"value_hidden":false,"family_unclear":false,"family":"","comment":""},"7":{"source_name_unclear":false,"value":"","family_hidden":false,"value_hidden":false,"family_unclear":false,"source_name":"","family_comment":"","family":"","comment":"","source_name_hidden":false},"8":{"value":"","family_hidden":false,"value_hidden":false,"family_comment":"","family":"","comment":""},"9":{"family_comment":"","value":"","family":"","comment":""},"10":{"family_comment":"","value":"","family":"","comment":""},"11":{"family_comment":"","value":"","family":"","comment":"","value_hidden":false},"12":{"value":"","family_hidden":false,"value_hidden":false,"family_comment":"","family":"","comment":""},"13":{"value":"","family_hidden":false,"value_hidden":false,"family_comment":"","family":"","comment":""},"14":{"value":"","family_hidden":false,"value_hidden":false,"family_comment":"","family":"","comment":""},"15":{"value":"","family_hidden":false,"value_hidden":false,"family_comment":"","family":"","comment":""},"16":{"value":"149000","family_hidden":false,"value_hidden":false,"family_comment":"","family":"","comment":""},"17":{"value":"","family_hidden":false,"value_hidden":false,"family_comment":"","family":"","comment":""},"18":{"value":"","family_hidden":false,"value_hidden":false,"family_comment":"","family":"","comment":""},"19":{"value":"","family_hidden":false,"value_hidden":false,"family_comment":"","family":"","comment":""},"20":{"value":"","family_comment":"","value_hidden":false,"family_unclear":false,"family":"","comment":""}},"vehicle":{"35":[{"brand_info":"1198 куб. см., 51 кВт","sum_rent_comment":"","year":"2008","sum_hidden":false,"brand_info_hidden":false,"brand_info_unclear":false,"sum_rent":"","sum":"","brand":"Skoda Fabia Ambiente","sum_comment":"","brand_unclear":false,"brand_hidden":false,"sum_unclear":false}]},"id":"vulyk_32_184","banks":{"45":[{"sum_foreign_comment":"","sum":"","sum_comment":"","sum_comment_unclear":false,"sum_hidden":false,"sum_foreign_units":"UAH","sum_foreign_hidden":false,"sum_units":"UAH","sum_comment_hidden":false,"sum_unclear":false,"sum_foreign":""},{"sum_foreign_comment":"","sum_units":"","sum_comment":"","sum_foreign_units":"","sum":"","sum_foreign":""}],"46":[{"sum_foreign_comment":"","sum_units":"UAH","sum_comment":"","sum_hidden":false,"sum_foreign_units":"UAH","sum_comment_hidden":false,"sum_foreign_hidden":false,"sum":"","sum_foreign":""}],"47":[{"sum_foreign_comment":"","sum_units":"UAH","sum_comment":"","sum_hidden":false,"sum_foreign_units":"UAH","sum":"","sum_foreign_hidden":false,"sum_foreign":""}],"48":[{"sum_foreign_comment":"","sum_units":"UAH","sum_comment":"","sum_hidden":false,"sum_foreign_units":"UAH","sum":"","sum_foreign_hidden":false,"sum_foreign":""}],"49":[{"sum_foreign_comment":"","sum_units":"UAH","sum_comment":"","sum_hidden":false,"sum_foreign_units":"UAH","sum":"","sum_foreign_hidden":false,"sum_foreign":""}],"50":[{"sum_foreign_comment":"","sum_units":"UAH","sum_comment":"","sum_hidden":false,"sum_foreign_units":"UAH","sum":"","sum_foreign_hidden":false,"sum_foreign":""}],"51":[{"sum_foreign_comment":"","sum":"","sum_comment":"","sum_comment_unclear":false,"sum_hidden":false,"sum_foreign_units":"UAH","sum_units":"UAH","sum_comment_hidden":false,"sum_foreign_hidden":false,"sum_foreign":""},{"sum_foreign_comment":"","sum_units":"","sum_comment":"","sum_foreign_units":"","sum":"","sum_foreign":""}],"52":[{"sum_foreign_comment":"","sum_units":"UAH","sum_comment":"","sum_hidden":false,"sum_foreign_units":"UAH","sum_comment_hidden":false,"sum_foreign_hidden":false,"sum":"","sum_foreign":""}],"53":[{"sum_foreign_comment":"","sum_units":"UAH","sum_comment":"","sum_hidden":false,"sum_foreign_units":"UAH","sum":"","sum_foreign_hidden":false,"sum_foreign":""}]},"declaration":{"additional_info_text":"","notfull_lostpages":"","date":"2015-03-24T00:00:00","notfull":"","additional_info":"","url":"http://static.declarations.com.ua/declarations/chosen_ones/mega_batch/holovko_neonila_petrivna.pdf"},"liabilities":{"54":{"sum_foreign_comment":"","sum":"4920.23","sum_comment":"","sum_foreign":""},"55":{"sum_foreign_comment":"","sum":"","sum_hidden":false,"sum_comment":"","sum_foreign":""},"56":{"sum_foreign_comment":"","sum_foreign_hidden":false,"sum_comment":"","sum_hidden":false,"sum":"12000","sum_unclear":false,"sum_foreign":""},"57":{"sum_foreign_comment":"","sum_foreign_hidden":false,"sum_comment":"","sum_hidden":false,"sum_comment_hidden":false,"sum_unclear":false,"sum":"17870.07","sum_foreign":""},"58":{"sum_foreign_comment":"","sum_foreign_hidden":false,"sum_comment":"","sum_hidden":false,"sum_comment_hidden":false,"sum_unclear":false,"sum":"34373.9","sum_foreign":""},"59":{"sum_foreign_comment":"","sum_foreign_hidden":false,"sum_comment":"","sum_comment_unclear":false,"sum_hidden":false,"sum":"","sum_foreign":""},"60":{"sum_foreign_comment":"","sum":"","sum_comment":"","sum_foreign":""},"61":{"sum_foreign_comment":"","sum":"","sum_comment":"","sum_foreign":""},"62":{"sum_foreign_comment":"","sum":"","sum_hidden":false,"sum_comment":"","sum_foreign":""},"63":{"sum_foreign_comment":"","sum":"","sum_comment":"","sum_unclear":false,"sum_foreign":""},"64":{"sum_foreign_comment":"","sum":"","sum_comment":"","sum_foreign":""}},"ft_src":"17870.07\n4920.23\n34373.9\n12000\nвідповідно до даних, внесених до особової картки\nсуддя шепетівського міськрайонного суду хмельницької області\nХмельницька область\nЗагальний місцевий суд\nНеоніла\nПетрівна\nГоловко\nГоловко Неоніла Петрівна\nГоловко Неоніла Петрівна\nНеоніла Петрівна Головко\nНеоніла Головко\nГоловко Неоніла Петрівна\nSkoda Fabia Ambiente\n1198 куб. см., 51 кВт\n2008\n2014\n1198 куб. см., 51 кВт\nSkoda Fabia Ambiente\n2008\n1000\nХмельницька область\nм. Славута\n51.3\nХмельницька область\nм. Славута\n37.4\nм. Шепетівка\nХмельницька область\nПетрівна\nГоловко Неоніла Петрівна\nНеоніла Петрівна Головко\nНеоніла Головко\nГоловко Неоніла Петрівна\nНеоніла\nГоловко Неоніла Петрівна\nЗагальний місцевий суд\nсуддя шепетівського міськрайонного суду хмельницької області\nХмельницька область\nГоловко\nвідповідно до даних, внесених до особової картки\n17870.07\n12000\n34373.9\n4920.23\n181151.23\n330151.23\n149000\n2014\n34373.9\n17870.07\n12000\n4920.23\n1000\nм. Славута\nХмельницька область\nХмельницька область\nм. Славута\n51.3\nм. Шепетівка\n37.4\nХмельницька область\nПетрівна\nГоловко\nГоловко Неоніла Петрівна\nНеоніла Петрівна Головко\nНеоніла Головко\nГоловко Неоніла Петрівна\nвідповідно до даних, внесених до особової картки\nХмельницька область\nЗагальний місцевий суд\nсуддя шепетівського міськрайонного суду хмельницької області\nГоловко Неоніла Петрівна\nНеоніла\n181151.23\n330151.23\n149000\n2008\nSkoda Fabia Ambiente\n1198 куб. см., 51 кВт\n330151.23\n149000\n181151.23\n51.3\nм. Славута\nХмельницька область\nм. Шепетівка\nХмельницька область\n37.4\n1000\nм. Славута\nХмельницька область\n2014","general":{"name_hidden":false,"name":"Неоніла","patronymic_unclear":false,"last_name_hidden":false,"inn":"","patronymic":"Петрівна","inn_hidden":true,"family_raw":"","last_name":"Головко","post":{"post_unclear":false,"post":"суддя шепетівського міськрайонного суду хмельницької області","post_hidden":false,"region":"Хмельницька область","office":"Загальний місцевий суд","office_hidden":false},"last_name_unclear":false,"full_name":"Головко Неоніла Петрівна","addresses":[{"place_district":"","place_city_hidden":true,"place_city":"","place_city_type_hidden":true,"place_district_hidden":true,"place_city_type":"","place_address_hidden":false,"place_address":"відповідно до даних, внесених до особової картки","place_hidden":true,"place":""}],"patronymic_hidden":false,"full_name_suggest":{"output":"Головко Неоніла Петрівна","input":["Головко Неоніла Петрівна","Неоніла Петрівна Головко","Неоніла Головко"]},"name_unclear":false},"source":"VULYK","estate":{"23":[{"space_unclear":false,"costs":"","costs_rent_unclear":false,"costs_comment":"","address_hidden":true,"region_hidden":true,"space_comment":"","space_units_unclear":false,"address":"м. Славута","costs_comment_unclear":false,"region":"Хмельницька область","address_unclear":false,"space":"1000","space_comment_hidden":false,"space_units":"м²","costs_rent":"","costs_rent_comment":""},{"costs_rent":"","space_unclear":false,"region":"","costs":"","costs_rent_comment":"","costs_comment":"","region_hidden":false,"space_comment":"","space_units":"","space":"","address":""},{"space":"","region":"","costs":"","costs_rent_comment":"","costs_comment":"","space_comment":"","space_units_unclear":false,"space_units":"","costs_rent":"","address":""},{"costs_rent":"","region":"","costs":"","costs_rent_comment":"","costs_comment":"","space_comment":"","space_units":"","space":"","address":""}],"25":[{"region_unclear":false,"space_unclear":false,"costs":"","costs_rent_unclear":false,"costs_comment":"","costs_hidden":false,"address_hidden":true,"region_hidden":false,"space_comment":"","space_hidden":false,"space":"51.3","address":"м. Славута","region":"Хмельницька область","address_unclear":false,"costs_rent_comment":"","space_comment_unclear":false,"space_comment_hidden":false,"space_units":"м²","space_units_hidden":false,"costs_rent":""},{"space_unclear":false,"costs":"","costs_rent_unclear":false,"costs_comment":"","address_hidden":true,"region_hidden":false,"space_comment":"","space_hidden":false,"space":"37.4","address":"м. Шепетівка","region":"Хмельницька область","costs_rent_comment":"","space_comment_unclear":false,"space_comment_hidden":false,"space_units":"м²","costs_rent":""}]},"intro":{"declaration_year":"2014","declaration_year_unclear":false}}