{"id":"vulyk_93_77","ft_src":"2000 куб. см.\n2014\nMercedes-Benz GLA 200\n2700 куб. см.\n2011\nMitsubishi Pajero Sport\n300000\n1200\n149\n800\n92\n1000000\n89\n2014\n6805\n1144\n7949\n2000 куб. см.\nMercedes-Benz GLA 200\n2014\n2700 куб. см.\n2011\nMitsubishi Pajero Sport\n300000\n1200\n800\n1000000\n89\n92\n149\nДем'яновський\nПодружжя\nЧугай Ольга Олександрівна 09. 08. 1985\nДитина\nДем'яновська Яна Юліанівна 17. 08. 2004\nДитина\nДем'яновський Марк Юліанович 27. 04. 2006\nДитина\nДем'яновський Олександр Юліанович 01. 12. 2012\nДем'яновський Юліан Галійович\nЮліан Галійович Дем'яновський\nЮліан Дем'яновський\nДем'яновський Юліан Галійович\nДем'яновський Юліан Галійович\nЛьвівська область\nЛьвів\nЮліан\nГалійович\nЛьвівська область\nЗагальний місцевий суд\nсуддя миколаївського районного суду львівської області\n1144\n6805\n7949\n2014\nПодружжя\nЧугай Ольга Олександрівна 09. 08. 1985\nДитина\nДем'яновська Яна Юліанівна 17. 08. 2004\nДитина\nДем'яновський Марк Юліанович 27. 04. 2006\nДем'яновський Олександр Юліанович 01. 12. 2012\nДитина\nДем'яновський\nГалійович\nЛьвівська область\nЛьвів\nЛьвівська область\nЗагальний місцевий суд\nсуддя миколаївського районного суду львівської області\nДем'яновський Юліан Галійович\nДем'яновський Юліан Галійович\nЮліан Галійович Дем'яновський\nЮліан Дем'яновський\nДем'яновський Юліан Галійович\nЮліан","estate":{"23":[{"address":"","space_units":"м²","costs_comment":"","space_unclear":false,"region_hidden":true,"space_comment":"","address_hidden":false,"space":"1200","space_comment_unclear":false,"costs_rent_comment":"","costs":"300000","region":"","costs_rent":""}],"26":[{"costs":"1000000","address":"","space_units":"м²","costs_rent_comment":"","space":"89","space_comment":"","region_hidden":true,"costs_comment":"","region":"","address_hidden":false,"costs_rent":""}],"29":[{"costs_property_comment":"","address":"","space_units":"м²","space_unclear":false,"region_hidden":true,"costs_property":"","space_comment":"","address_hidden":true,"space_comment_unclear":false,"costs_rent_comment":"","space":"800","region":"","costs_rent":""}],"30":[{"costs_property_comment":"","address":"","space_units":"м²","space_unclear":false,"region_hidden":true,"costs_property":"","space_comment":"","address_hidden":true,"costs_rent_comment":"","space":"149","region":"","costs_rent":""}],"31":[{"costs_property_comment":"","address":"","space_units":"м²","space_hidden":false,"space_comment":"","region_hidden":true,"costs_property":"","region":"","address_hidden":true,"space_comment_unclear":false,"costs_rent_comment":"","space":"92","costs_rent":""}]},"vehicle":{"40":[{"sum_comment":"","brand_info":"2000 куб. см.","sum":"","sum_rent_comment":"","year":"2014","brand":"Mercedes-Benz GLA 200","sum_rent":"","brand_info_unclear":false},{"sum_comment":"","brand_info":"2700 куб. см.","sum":"","sum_rent_comment":"","year":"2011","brand":"Mitsubishi Pajero Sport","sum_rent":""}]},"source":"VULYK","income":{"5":{"family":"7949","family_comment":"","comment":"","value_hidden":false,"value_unclear":false,"value":"","family_hidden":false,"family_unclear":false},"6":{"family_comment":"","family":"6805","comment":"","value_unclear":false,"family_unclear":false,"value":""},"7":{"source_name_hidden":false,"family_comment":"","comment":"","family":"1144","comment_hidden":false,"source_name_unclear":false,"value":"","source_name":""},"8":{"family_comment":"","value":"","family":"","comment":""},"9":{"family_comment":"","family":"","comment":"","value_unclear":false,"family_unclear":false,"family_hidden":false,"value":"","family_comment_unclear":false},"10":{"family_comment":"","value":"","family":"","comment":""},"11":{"family_comment":"","value":"","family":"","comment":""},"12":{"family_comment":"","value":"","family":"","comment":""},"13":{"family_comment":"","value":"","family":"","comment":""},"14":{"family_comment":"","value":"","family":"","comment":""},"15":{"family_comment":"","value":"","family":"","comment":""},"16":{"family_comment":"","value":"","family":"","comment":""},"17":{"family_comment":"","value":"","family":"","comment":""},"18":{"family_comment":"","value":"","family":"","comment":""},"19":{"family_comment":"","value":"","family":"","comment":""},"20":{"family_comment":"","family":"","comment":"","value_unclear":false,"value":"","comment_unclear":false,"family_unclear":false,"family_comment_hidden":false,"family_comment_unclear":false}},"general":{"inn":"","addresses":[{"place_city_type_hidden":false,"place_city_type":"Місто","place_city_hidden":false,"place_hidden":false,"place_district":"","place_district_hidden":false,"place":"Львівська область","place_address":"","place_address_hidden":true,"place_city":"Львів"}],"last_name":"Дем'яновський","full_name":"Дем'яновський Юліан Галійович","family":[{"inn":"","family_name":"Чугай Ольга Олександрівна 09. 08. 1985","relations_hidden":false,"name_unclear":false,"relations":"Подружжя","inn_hidden":true,"name_hidden":false,"relations_other":""},{"inn":"","family_name":"Дем'яновська Яна Юліанівна 17. 08. 2004","relations_other":"","name_unclear":false,"inn_hidden":false,"name_hidden":false,"relations":"Дитина"},{"inn":"","family_name":"Дем'яновський Марк Юліанович 27. 04. 2006","relations_other":"","name_unclear":false,"inn_hidden":false,"name_hidden":false,"relations":"Дитина"},{"inn":"","family_name":"Дем'яновський Олександр Юліанович 01. 12. 2012","relations_other":"","name_hidden":false,"inn_hidden":false,"relations":"Дитина"}],"patronymic":"Галійович","inn_hidden":false,"name":"Юліан","post":{"office":"Загальний місцевий суд","post":"суддя миколаївського районного суду львівської області","candidate":"","office_unclear":false,"region":"Львівська область","region_unclear":false,"post_unclear":false},"family_raw":"","full_name_suggest":{"input":["Дем'яновський Юліан Галійович","Юліан Галійович Дем'яновський","Юліан Дем'яновський"],"output":"Дем'яновський Юліан Галійович"}},"liabilities":{"54":{"sum_comment":"","sum_foreign_comment":"","sum_foreign":"","sum_hidden":false,"sum":""},"55":{"sum_comment":"","sum_foreign_comment":"","sum_foreign":"","sum":""},"56":{"sum_comment":"","sum_foreign_comment":"","sum_foreign":"","sum":""},"57":{"sum_comment":"","sum_hidden":false,"sum":"","sum_foreign_comment":"","sum_foreign":"","sum_unclear":false,"sum_comment_hidden":false},"58":{"sum_comment_unclear":false,"sum_comment":"","sum_hidden":false,"sum":"","sum_foreign_comment":"","sum_foreign":"","sum_unclear":false},"59":{"sum_comment":"","sum_foreign_comment":"","sum_foreign":"","sum":""},"60":{"sum_comment":"","sum_foreign_comment":"","sum_foreign":"","sum_hidden":false,"sum":""},"61":{"sum_comment":"","sum_foreign_comment":"","sum_foreign":"","sum":""},"62":{"sum_comment":"","sum_foreign_comment":"","sum_foreign":"","sum":""},"63":{"sum_comment":"","sum_foreign_comment":"","sum_foreign":"","sum":""},"64":{"sum_comment":"","sum_foreign_comment":"","sum_foreign":"","sum":""}},"declaration":{"notfull_lostpages":"","additional_info_text":"","additional_info":"","date":"2015-03-30T00:00:00","notfull":"","url":"http://static.declarations.com.ua/declarations/chosen_ones/judges_batch/3523_dem’yanovskyi_iulian_haliiovych.pdf"},"intro":{"isnotdeclaration":"","declaration_year":"2014"}}