{"income":{"5":{"family_comment":"","value":"271225","family":"174636","comment":""},"6":{"family_comment":"","value":"271225","family":"","comment":""},"7":{"value":"","comment_hidden":false,"value_hidden":false,"family_comment":"","source_name":"","family":"","comment":"","source_name_hidden":false},"8":{"family_comment":"","value":"","family":"","comment":""},"9":{"value":"","comment_hidden":false,"family_comment":"","family":"","comment":"","family_comment_unclear":false},"10":{"family_comment":"","value":"","family":"","comment":""},"11":{"family_comment":"","value":"","comment_hidden":false,"family":"","comment":""},"12":{"family_comment":"","value":"","family":"","comment":""},"13":{"family_comment":"","value":"","family":"","comment":""},"14":{"family_comment":"","value":"","family":"","comment":""},"15":{"family_comment":"","value":"","family":"24636","comment":""},"16":{"family_comment":"","value":"","family":"150000","comment":""},"17":{"family_comment":"","value":"","family":"","comment":""},"18":{"family_comment":"","value":"","family":"","comment":""},"19":{"family_comment":"","value":"","family":"","comment":""},"20":{"family_comment":"","value":"","comment_hidden":false,"family":"","comment":""}},"vehicle":{"35":[{"brand_info":"3.0 , 164 кВт","sum_rent_comment":"","brand":"Mitsubishi Outlander","sum_comment":"","year":"2008","brand_info_unclear":false,"year_unclear":false,"sum":"","sum_rent":""}],"40":[{"brand_info":"2.4 , 140 кВт","sum_rent_comment":"","brand":"Honda Accord","sum_comment":"","year":"2006","brand_info_unclear":false,"sum":"","sum_rent":""}]},"id":"vulyk_102_10","banks":{"45":[{"sum_foreign_comment":"","sum_units":"UAH","sum_comment":"","sum_comment_unclear":false,"sum_hidden":false,"sum_foreign_units":"UAH","sum_comment_hidden":true,"sum_unclear":false,"sum":"7207","sum_foreign":""}]},"declaration":{"date":"2016-03-29T00:00:00","additional_info_text":"","additional_info":"","url":"http://static.declarations.com.ua/declarations/chosen_ones/judges_batch/1084_ieromin_anatolii_vasylovych.pdf"},"liabilities":{"54":{"sum_foreign_comment":"","sum":"","sum_comment":"","sum_hidden":false,"sum_comment_hidden":false,"sum_foreign":""},"55":{"sum_foreign_comment":"","sum":"","sum_comment":"","sum_foreign":""},"56":{"sum_foreign_comment":"","sum":"","sum_comment":"","sum_foreign":""},"57":{"sum_foreign_comment":"","sum_comment_hidden":false,"sum":"","sum_comment":"","sum_foreign":""},"58":{"sum_foreign_comment":"","sum_comment_hidden":false,"sum":"","sum_comment":"","sum_foreign":""},"59":{"sum_foreign_comment":"","sum_comment_hidden":false,"sum":"","sum_comment":"","sum_foreign":""},"60":{"sum_foreign_comment":"","sum":"","sum_comment":"","sum_hidden":false,"sum_comment_hidden":false,"sum_foreign":""},"61":{"sum_foreign_comment":"","sum":"","sum_comment":"","sum_foreign":""},"62":{"sum_foreign_comment":"","sum":"","sum_comment":"","sum_unclear":false,"sum_foreign":""},"63":{"sum_foreign_comment":"","sum":"","sum_comment":"","sum_hidden":false,"sum_comment_hidden":false,"sum_foreign":""},"64":{"sum_foreign_comment":"","sum_comment_hidden":false,"sum":"","sum_comment":"","sum_foreign":""}},"ft_src":"суддя вищого адміністративного суду україни\nЗагальнодержавний регіон\nВищий адміністративний суд\nАнатолій\nПодружжя\nДитина\nВасильович\nЄрьомін Анатолій Васильович\nЄрьомін\nЄрьомін Анатолій Васильович\nАнатолій Васильович Єрьомін\nАнатолій Єрьомін\nЄрьомін Анатолій Васильович\n2008\n3.0 , 164 кВт\nMitsubishi Outlander\n2.4 , 140 кВт\n2006\nHonda Accord\n1120\n72\n36\n7207\n2015\n3.0 , 164 кВт\nMitsubishi Outlander\n2008\n2.4 , 140 кВт\n2006\nHonda Accord\n2015\nЄрьомін Анатолій Васильович\nАнатолій Васильович Єрьомін\nАнатолій Єрьомін\nЄрьомін Анатолій Васильович\nЄрьомін Анатолій Васильович\nАнатолій\nВасильович\nсуддя вищого адміністративного суду україни\nЗагальнодержавний регіон\nВищий адміністративний суд\nЄрьомін\nПодружжя\nДитина\n271225\n24636\n271225\n174636\n150000\n1120\n72\n36\n7207\n271225\n24636\n174636\n271225\n150000\nПодружжя\nДитина\nАнатолій\nВасильович\nЄрьомін\nЄрьомін Анатолій Васильович\nАнатолій Васильович Єрьомін\nАнатолій Єрьомін\nЄрьомін Анатолій Васильович\nсуддя вищого адміністративного суду україни\nЗагальнодержавний регіон\nВищий адміністративний суд\nЄрьомін Анатолій Васильович\n2008\n3.0 , 164 кВт\nMitsubishi Outlander\n2006\n2.4 , 140 кВт\nHonda Accord\n24636\n174636\n271225\n150000\n271225\n72\n1120\n36\n7207\n2015","general":{"inn":"","name":"Анатолій","family":[{"inn_hidden":true,"inn":"","name_hidden":true,"family_name":"","relations":"Подружжя","name_unclear":false},{"inn":"","relations":"Дитина","relations_other":"","inn_hidden":false,"family_name":"","name_hidden":false,"name_unclear":false}],"patronymic":"Васильович","inn_hidden":true,"family_raw":"","last_name":"Єрьомін","post":{"region":"Загальнодержавний регіон","region_unclear":false,"post":"суддя вищого адміністративного суду україни","office_unclear":false,"office":"Вищий адміністративний суд"},"full_name":"Єрьомін Анатолій Васильович","addresses":[{"place_district":"","place_city_hidden":true,"place_city":"","place_city_type_hidden":false,"place_district_hidden":false,"place_city_type":"","place_address_hidden":true,"place_address":"","place_hidden":true,"place":""}],"patronymic_hidden":false,"full_name_suggest":{"output":"Єрьомін Анатолій Васильович","input":["Єрьомін Анатолій Васильович","Анатолій Васильович Єрьомін","Анатолій Єрьомін"]}},"source":"VULYK","estate":{"23":[{"costs":"","costs_comment":"","address_hidden":false,"region_hidden":true,"space_comment":"","space":"1120","address":"","region":"","costs_rent_comment":"","space_comment_unclear":false,"space_units":"м²","space_units_unclear":false,"costs_rent":""}],"25":[{"costs":"","costs_comment":"","address_hidden":false,"region_hidden":true,"space_comment":"","space":"36","address":"","region":"","address_unclear":false,"costs_rent_comment":"","space_units":"м²","costs_rent":""}],"31":[{"costs_rent":"","region":"","costs_property":"","costs_rent_comment":"","address_hidden":false,"region_hidden":true,"space_comment":"","costs_property_comment":"","space_units":"м²","space":"72","address":""}]},"intro":{"declaration_year":"2015"}}