{"income":{"5":{"value":"211635.93","family_comment":"","value_unclear":false,"comment_hidden":false,"family_hidden":false,"value_hidden":false,"family_unclear":false,"family_comment_unclear":false,"family":"","comment":"","family_comment_hidden":false},"6":{"value":"207006.33","family_comment":"","value_unclear":false,"family_hidden":false,"value_hidden":false,"family_unclear":false,"family":"","comment":""},"7":{"source_name_unclear":false,"value":"","family_hidden":false,"value_hidden":false,"family_comment":"","source_name":"","family":"","comment":"","source_name_hidden":false},"8":{"value":"","family_comment":"","value_unclear":false,"family_hidden":false,"value_hidden":false,"family_unclear":false,"family":"","comment":""},"9":{"value":"","family_comment":"","value_unclear":false,"family_hidden":false,"value_hidden":false,"family_unclear":false,"comment_unclear":false,"comment":"","family":""},"10":{"value":"","value_unclear":false,"family_hidden":false,"value_hidden":false,"family_comment":"","family":"","comment":""},"11":{"value":"","family_hidden":false,"value_hidden":false,"family_comment":"","family":"","comment":""},"12":{"value":"","family_comment":"","family_hidden":false,"value_hidden":false,"family_unclear":false,"family":"","comment":""},"13":{"value":"","family_hidden":false,"value_hidden":false,"family_comment":"","family":"","comment":""},"14":{"value":"","family_hidden":false,"value_hidden":false,"family_comment":"","family":"","comment":""},"15":{"value":"","family_hidden":false,"value_hidden":false,"family_comment":"","family":"","comment":""},"16":{"value":"","value_unclear":false,"family_hidden":false,"value_hidden":false,"family_comment":"","family":"","comment":""},"17":{"value":"","family_hidden":false,"value_hidden":false,"family_comment":"","family":"","comment":""},"18":{"value":"","family_hidden":false,"value_hidden":false,"family_comment":"","family":"","comment":""},"19":{"value":"","comment_unclear":false,"family_hidden":false,"value_hidden":false,"family_comment":"","family":"","comment":""},"20":{"value":"4629.6","family_comment":"","comment_unclear":false,"comment_hidden":false,"family_hidden":false,"value_hidden":false,"family_unclear":false,"family_comment_unclear":false,"family_comment_hidden":false,"comment":"Допомога як одинокій матері","family":""}},"vehicle":{"35":[{"year_hidden":false,"brand_info":"1.8 л","sum_rent_comment":"","sum_rent_comment_unclear":false,"sum_rent_hidden":false,"year":"2006","sum_hidden":false,"brand_info_hidden":false,"brand_info_unclear":false,"year_unclear":false,"sum_rent":"","sum_rent_unclear":false,"sum":"","brand":"Chevrolet Lacetti","sum_comment":"","brand_unclear":false,"brand_hidden":false,"sum_unclear":false}]},"id":"vulyk_69_37","declaration":{"additional_info_text":"","notfull_lostpages":"","date":"2015-03-30T00:00:00","notfull":"","additional_info":"","url":"http://static.declarations.com.ua/declarations/chosen_ones/epic_batch/kochura_olena_oleksiivna.pdf"},"liabilities":{"54":{"sum_foreign_comment":"","sum":"1377.15","sum_comment":"","sum_hidden":false,"sum_comment_hidden":false,"sum_unclear":false,"sum_foreign":""},"55":{"sum_foreign_comment":"","sum":"","sum_hidden":false,"sum_comment":"","sum_foreign":""},"56":{"sum_foreign_comment":"","sum":"","sum_comment":"","sum_comment_unclear":false,"sum_hidden":false,"sum_unclear":false,"sum_foreign":""},"57":{"sum_foreign_comment":"","sum":"","sum_comment":"","sum_comment_unclear":false,"sum_hidden":false,"sum_comment_hidden":false,"sum_foreign":""},"58":{"sum_foreign_comment":"","sum":"","sum_comment":"","sum_comment_unclear":false,"sum_hidden":false,"sum_comment_hidden":false,"sum_unclear":false,"sum_foreign":""},"59":{"sum_foreign_comment":"","sum":"","sum_hidden":false,"sum_comment":"","sum_foreign":""},"60":{"sum_foreign_comment":"","sum":"","sum_comment":"","sum_hidden":false,"sum_comment_hidden":false,"sum_foreign":""},"61":{"sum_foreign_comment":"","sum":"","sum_hidden":false,"sum_comment":"","sum_foreign":""},"62":{"sum_foreign_comment":"","sum":"","sum_comment":"","sum_comment_unclear":false,"sum_hidden":false,"sum_unclear":false,"sum_foreign":""},"63":{"sum_foreign_comment":"","sum":"","sum_comment":"","sum_hidden":false,"sum_comment_hidden":false,"sum_unclear":false,"sum_foreign":""},"64":{"sum_foreign_comment":"","sum":"","sum_comment":"","sum_hidden":false,"sum_comment_hidden":false,"sum_foreign":""}},"ft_src":"1377.15\nсуддя новгород-сіверського районного суду чернігівської області\nЧернігівська область\nЗагальний місцевий суд\nОлена\nКочура Андрій Вікторович\nДитина\nОлексіївна\nКочура Олена Олексіївна\nОлена Олексіївна Кочура\nОлена Кочура\nКочура Олена Олексіївна\nКочура Олена Олексіївна\nКочура\n1.8 л\nChevrolet Lacetti\n2006\nм. Новгород-Сіверський\n800\nЧернігівська область\nм. Новгород-Сіверський\n835\nЧернігівська область\nЧернігівська область\nм. Новгород-Сіверський\n100\nжитл. пл. - 98,3\nЧернігівська область\nм. Новгород-Сіверський\n190\n38.2\nм. Київ\n2014\n207006.33\n211635.93\nДопомога як одинокій матері\n4629.6\n1.8 л\nChevrolet Lacetti\n2006\nм. Новгород-Сіверський\nЧернігівська область\n800\n835\nм. Новгород-Сіверський\nЧернігівська область\nм. Новгород-Сіверський\n100\nЧернігівська область\n190\nжитл. пл. - 98,3\nЧернігівська область\nм. Новгород-Сіверський\n38.2\nм. Київ\nКочура Олена Олексіївна\nОлена Олексіївна Кочура\nОлена Кочура\nКочура Олена Олексіївна\nКочура Олена Олексіївна\nДитина\nКочура Андрій Вікторович\nОлена\nКочура\nЗагальний місцевий суд\nсуддя новгород-сіверського районного суду чернігівської області\nЧернігівська область\nОлексіївна\n1377.15\n207006.33\nДопомога як одинокій матері\n4629.6\n211635.93\n2014\n1377.15\nКочура Андрій Вікторович\nДитина\nОлексіївна\nКочура\nОлена\nКочура Олена Олексіївна\nОлена Олексіївна Кочура\nОлена Кочура\nКочура Олена Олексіївна\nЧернігівська область\nсуддя новгород-сіверського районного суду чернігівської області\nЗагальний місцевий суд\nКочура Олена Олексіївна\nChevrolet Lacetti\n1.8 л\n2006\n4629.6\nДопомога як одинокій матері\n211635.93\n207006.33\nм. Київ\n38.2\n800\nЧернігівська область\nм. Новгород-Сіверський\nм. Новгород-Сіверський\nЧернігівська область\n835\nм. Новгород-Сіверський\nЧернігівська область\n100\n190\nЧернігівська область\nжитл. пл. - 98,3\nм. Новгород-Сіверський\n2014","general":{"inn":"","name":"Олена","patronymic_unclear":false,"family":[{"inn":"","inn_hidden":false,"relations_unclear":false,"relations_hidden":false,"relations_other":"","relations":"Дитина","name_hidden":false,"inn_unclear":false,"family_name":"Кочура Андрій Вікторович","name_unclear":false}],"patronymic":"Олексіївна","inn_hidden":true,"family_raw":"","inn_unclear":false,"post":{"post_unclear":false,"region_unclear":false,"post":"суддя новгород-сіверського районного суду чернігівської області","candidate":"","office_hidden":false,"region":"Чернігівська область","post_hidden":false,"office":"Загальний місцевий суд","office_unclear":false,"region_hidden":false},"full_name_suggest":{"output":"Кочура Олена Олексіївна","input":["Кочура Олена Олексіївна","Олена Олексіївна Кочура","Олена Кочура"]},"full_name":"Кочура Олена Олексіївна","last_name":"Кочура","last_name_unclear":false,"name_unclear":false},"source":"VULYK","estate":{"23":[{"space_unclear":false,"costs":"","costs_rent_unclear":false,"costs_comment":"","costs_hidden":false,"space_hidden":false,"space_units_unclear":false,"space_units_hidden":false,"costs_comment_unclear":false,"region":"Чернігівська область","costs_unclear":false,"space_comment_hidden":false,"costs_rent":"","region_unclear":false,"address_hidden":false,"region_hidden":false,"space_comment":"","space":"800","address":"м. Новгород-Сіверський","address_unclear":false,"costs_rent_comment":"","costs_rent_hidden":false,"space_units":"м²"},{"space_unclear":false,"costs":"","costs_rent_unclear":false,"costs_comment":"","address_hidden":false,"region_hidden":true,"space_comment":"","space":"835","address":"м. Новгород-Сіверський","region":"Чернігівська область","address_unclear":false,"costs_rent_comment":"","costs_unclear":false,"space_units":"м²","costs_rent":""},{"costs_rent":"","space_unclear":false,"region":"Чернігівська область","costs":"","costs_rent_comment":"","costs_comment":"","region_hidden":true,"space_comment":"","space_units":"м²","space":"100","address":"м. Новгород-Сіверський"}],"24":[{"region_unclear":false,"space_hidden":false,"costs":"","costs_comment":"","costs_hidden":false,"address_hidden":false,"region_hidden":false,"space_comment":"житл. пл. - 98,3","space_unclear":false,"space":"190","address":"м. Новгород-Сіверський","region":"Чернігівська область","address_unclear":false,"costs_rent_comment":"","costs_rent_hidden":false,"space_units":"м²","space_units_hidden":false,"costs_rent":""}],"25":[{"region_unclear":false,"space_unclear":false,"costs":"","costs_comment":"","costs_hidden":false,"address_hidden":false,"region_hidden":false,"space_comment":"","space_hidden":false,"space":"38.2","space_units_hidden":false,"region":"м. Київ","address_unclear":false,"costs_rent_comment":"","costs_rent_hidden":false,"space_comment_unclear":false,"space_comment_hidden":false,"space_units":"м²","address":"","costs_rent":""}]},"intro":{"declaration_year":"2014","isnotdeclaration":"","declaration_year_unclear":false,"declaration_year_hidden":false}}