{"income":{"5":{"value":"232142","family_comment":"відомості не надано","value_unclear":false,"comment_hidden":false,"family_hidden":false,"family":"","value_hidden":false,"family_unclear":false,"comment_unclear":false,"comment":"","family_comment_unclear":false},"6":{"value":"232142","family_unclear":false,"family_hidden":false,"family_comment":"відомості не надано","family":"","comment":""},"7":{"family_comment":"","value":"","source_name":"","family":"","comment":""},"8":{"family_comment":"","value":"","value_unclear":false,"family":"","comment":""},"9":{"value":"","family_unclear":false,"family_hidden":false,"family_comment":"","family":"","comment":""},"10":{"family_comment":"","value":"","value_unclear":false,"family":"","comment":""},"11":{"value":"","value_unclear":false,"family_hidden":false,"value_hidden":false,"family_comment":"","family":"","comment":""},"12":{"family_comment":"","value":"","family":"","comment":""},"13":{"family_comment":"","value":"","value_unclear":false,"family":"","comment":""},"14":{"family_comment":"","value":"","family":"","comment":""},"15":{"family_comment":"","value":"","value_unclear":false,"family":"","comment":""},"16":{"family_comment":"","value":"","family":"","comment":""},"17":{"family_comment":"","value":"","family":"","comment":""},"18":{"family_comment":"","value":"","family":"","comment":""},"19":{"family_comment":"","value":"","family":"","comment":""},"20":{"family_comment":"","value":"","value_unclear":false,"family":"","comment":""}},"vehicle":{"40":[{"brand_info":"відомості не надано","sum_rent_comment":"","year":"","brand_info_hidden":false,"brand_info_unclear":false,"year_unclear":false,"sum_rent":"","sum":"","brand":"","sum_comment":"","brand_unclear":false,"brand_hidden":false}],"41":[{"brand_info":"відомості не надано","sum_rent_comment":"","brand":"","sum_comment":"","year":"","brand_hidden":false,"sum":"","sum_rent":""}],"42":[{"brand_info":"відомості не надано","sum_rent_comment":"","brand":"","sum_comment":"","year":"","sum":"","sum_rent":""}],"43":[{"brand_info":"відомості не надано","sum_rent_comment":"","brand":"","sum_comment":"","sum":"","sum_rent":""}],"44":[{"brand_info":"відомості не надано","sum_rent_comment":"","brand":"","sum_comment":"","year":"","sum":"","sum_rent":""}]},"id":"vulyk_54_36","banks":{"45":[{"sum_foreign_comment":"","sum_units":"UAH","sum_comment":"","sum_comment_unclear":false,"sum_hidden":false,"sum_foreign_units":"UAH","sum_units_unclear":false,"sum_comment_hidden":false,"sum_unclear":false,"sum":"","sum_foreign":""},{"sum_foreign_comment":"","sum_units":"","sum_comment":"","sum_comment_unclear":false,"sum_foreign_units":"","sum":"","sum_foreign":""},{"sum_foreign_comment":"","sum_units":"","sum_comment":"","sum_foreign_units":"","sum":"","sum_foreign":""}],"46":[{"sum_foreign_comment":"","sum_units":"UAH","sum_comment":"","sum_comment_unclear":false,"sum_foreign_units":"UAH","sum":"","sum_foreign":""},{"sum_foreign_comment":"","sum_units":"","sum_comment":"","sum_foreign_units":"","sum":"","sum_foreign":""}],"47":[{"sum_foreign_comment":"","sum_units":"UAH","sum_comment":"","sum_comment_unclear":false,"sum_foreign_units":"UAH","sum":"","sum_foreign":""},{"sum_foreign_comment":"","sum_units":"","sum_comment":"","sum":"","sum_foreign":""}],"48":[{"sum_foreign_comment":"","sum_units":"UAH","sum_comment":"","sum_foreign_units":"UAH","sum":"","sum_foreign":""}],"49":[{"sum_foreign_comment":"","sum_units":"UAH","sum_comment":"","sum_comment_unclear":false,"sum_foreign_units":"UAH","sum":"","sum_foreign":""}],"50":[{"sum_foreign_comment":"","sum_units":"UAH","sum_comment":"","sum_foreign_units":"UAH","sum":"","sum_foreign":""}],"51":[{"sum_foreign_comment":"","sum_units":"UAH","sum_comment":"","sum_comment_unclear":false,"sum_hidden":false,"sum_foreign_units":"UAH","sum_comment_hidden":false,"sum":"","sum_foreign":""},{"sum_foreign_comment":"","sum_units":"","sum_comment":"","sum_foreign_units":"","sum":"","sum_foreign":""},{"sum_foreign_comment":"","sum_units":"","sum_comment":"","sum_foreign_units":"","sum":"","sum_foreign":""}],"52":[{"sum_foreign_comment":"","sum_units":"UAH","sum_comment":"","sum_comment_unclear":false,"sum_foreign_units":"UAH","sum":"","sum_foreign":""}],"53":[{"sum_foreign_comment":"","sum_units":"UAH","sum_comment":"","sum_foreign_units":"UAH","sum":"","sum_unclear":false,"sum_foreign":""}]},"declaration":{"additional_info_text":"","notfull_lostpages":"","date":"2015-03-30T00:00:00","notfull":"","additional_info":"","url":"http://static.declarations.com.ua/declarations/chosen_ones/mega_batch/pustovit_oleksii_hryhorovych.pdf"},"liabilities":{"54":{"sum_foreign_comment":"","sum":"","sum_comment":"","sum_comment_unclear":false,"sum_hidden":false,"sum_comment_hidden":false,"sum_unclear":false,"sum_foreign":""},"55":{"sum_foreign_comment":"","sum":"","sum_comment":"","sum_foreign":""},"56":{"sum_foreign_comment":"","sum":"","sum_comment":"","sum_foreign":""},"57":{"sum_foreign_comment":"","sum":"","sum_comment":"","sum_comment_unclear":false,"sum_comment_hidden":false,"sum_unclear":false,"sum_foreign":""},"58":{"sum_foreign_comment":"","sum":"","sum_comment":"","sum_comment_unclear":false,"sum_comment_hidden":false,"sum_unclear":false,"sum_foreign":""},"59":{"sum_foreign_comment":"","sum_foreign_hidden":false,"sum_comment":"","sum_hidden":false,"sum_comment_hidden":false,"sum":"","sum_foreign":""},"60":{"sum_foreign_comment":"","sum":"","sum_comment":"","sum_foreign":""},"61":{"sum_foreign_comment":"","sum":"","sum_comment":"","sum_foreign":""},"62":{"sum_foreign_comment":"","sum":"","sum_comment":"","sum_foreign":""},"63":{"sum_foreign_comment":"","sum_comment_hidden":false,"sum":"","sum_comment":"","sum_foreign":""},"64":{"sum_foreign_comment":"","sum":"","sum_comment":"","sum_foreign":""}},"ft_src":"суддя жовтневого районного суду м. кривого рогу\nДніпропетровська область\nЗагальний місцевий суд\nОлексій\nПустовіт Я. В. 10. 08. 1969\nПодружжя\nПустовіт І. О. 09. 02. 2006\nДитина\nГригорович\nПустовіт Олексій Григорович\nОлексій Григорович Пустовіт\nОлексій Пустовіт\nПустовіт Олексій Григорович\nПустовіт Олексій Григорович\nПустовіт\nвідомості не надано\nвідомості не надано\nвідомості не надано\nвідомості не надано\nвідомості не надано\n2014\nвідомості не надано\nвідомості не надано\nвідомості не надано\nвідомості не надано\nвідомості не надано\nвідомості не надано\nвідомості не надано\nвідомості не надано\nвідомості не надано\nвідомості не надано\nвідомості не надано\nвідомості не надано\nвідомості не надано\nвідомості не надано\nвідомості не надано\nвідомості не надано\nвідомості не надано\nПодружжя\nПустовіт Я. В. 10. 08. 1969\nДитина\nПустовіт І. О. 09. 02. 2006\nПустовіт Олексій Григорович\nОлексій Григорович Пустовіт\nОлексій Пустовіт\nПустовіт Олексій Григорович\nПустовіт Олексій Григорович\nОлексій\nГригорович\nЗагальний місцевий суд\nДніпропетровська область\nсуддя жовтневого районного суду м. кривого рогу\nПустовіт\n232142\nвідомості не надано\nвідомості не надано\n232142\n2014\nвідомості не надано\nвідомості не надано\nвідомості не надано\nвідомості не надано\nвідомості не надано\nвідомості не надано\nвідомості не надано\nвідомості не надано\nвідомості не надано\nвідомості не надано\nвідомості не надано\nвідомості не надано\nПодружжя\nПустовіт Я. В. 10. 08. 1969\nПустовіт І. О. 09. 02. 2006\nДитина\nГригорович\nПустовіт\nОлексій\nПустовіт Олексій Григорович\nОлексій Григорович Пустовіт\nОлексій Пустовіт\nПустовіт Олексій Григорович\nДніпропетровська область\nЗагальний місцевий суд\nсуддя жовтневого районного суду м. кривого рогу\nПустовіт Олексій Григорович\nвідомості не надано\n232142\nвідомості не надано\n232142\nвідомості не надано\nвідомості не надано\nвідомості не надано\nвідомості не надано\nвідомості не надано\nвідомості не надано\n232142\nвідомості не надано\n232142\nвідомості не надано\nвідомості не надано\nвідомості не надано\nвідомості не надано\nвідомості не надано\nвідомості не надано\nвідомості не надано\nвідомості не надано\nвідомості не надано\nвідомості не надано\nвідомості не надано\nвідомості не надано\n2014","general":{"inn":"","name":"Олексій","patronymic_unclear":false,"family":[{"inn":"","inn_hidden":false,"relations_unclear":false,"relations_hidden":false,"relations_other":"","relations":"Подружжя","name_hidden":false,"inn_unclear":false,"family_name":"Пустовіт Я. В. 10. 08. 1969","name_unclear":false},{"inn":"","inn_hidden":false,"relations_hidden":false,"family_name":"Пустовіт І. О. 09. 02. 2006","relations_other":"","relations":"Дитина","name_hidden":false,"name_unclear":false}],"patronymic":"Григорович","inn_hidden":true,"family_raw":"","inn_unclear":false,"post":{"post_unclear":false,"region_unclear":false,"post":"суддя жовтневого районного суду м. кривого рогу","office":"Загальний місцевий суд","region":"Дніпропетровська область","post_hidden":false,"office_hidden":false,"office_unclear":false,"region_hidden":false},"full_name_suggest":{"output":"Пустовіт Олексій Григорович","input":["Пустовіт Олексій Григорович","Олексій Григорович Пустовіт","Олексій Пустовіт"]},"full_name":"Пустовіт Олексій Григорович","addresses":[{"place_district":"","place_city_hidden":false,"place_city":"","place_city_unclear":false,"place_district_hidden":false,"place_city_type":"","place_address_hidden":false,"place_city_type_hidden":false,"place_address":"","place_hidden":true,"place":""}],"last_name":"Пустовіт","last_name_unclear":false,"name_unclear":false},"source":"VULYK","estate":{"23":[{"space_unclear":false,"costs":"","costs_comment":"","costs_hidden":false,"address_hidden":false,"region_hidden":false,"space_comment":"","space":"","address":"","region":"","address_unclear":false,"costs_rent_comment":"","space_units":"м²","costs_rent":""},{"space":"","region":"","costs":"","costs_rent_comment":"","costs_comment":"","region_hidden":false,"address_unclear":false,"space_comment":"","space_units":"","costs_rent":"","address":""},{"costs_rent":"","region":"","costs":"","costs_rent_comment":"","costs_comment":"","space_comment":"","space_units":"","space":"","address":""},{"costs_rent":"","costs":"","costs_rent_comment":"","costs_comment":"","space_comment":"","space_units":"","space":"","address":""}],"29":[{"space_unclear":false,"costs_property_hidden":false,"address_hidden":false,"region_hidden":false,"space_comment":"відомості не надано","space":"","address":"відомості не надано","region":"","costs_property":"","costs_rent_comment":"","space_units":"м²","costs_property_comment":"","costs_rent":""}],"30":[{"region_unclear":false,"space_unclear":false,"address_hidden":false,"region_hidden":false,"space_comment":"відомості не надано","space":"","address":"відомості не надано","region":"","costs_property":"","costs_rent_comment":"","space_units":"м²","costs_property_comment":"","costs_rent":""}],"31":[{"space_unclear":false,"address_hidden":false,"region_hidden":false,"space_comment":"відомості не надано","space_hidden":false,"space":"","address":"відомості не надано","region":"","costs_property":"","costs_rent_comment":"","space_units":"м²","costs_property_comment":"","costs_rent":""}],"32":[{"costs_rent":"","region":"","costs_property":"","costs_rent_comment":"","address_hidden":false,"region_hidden":false,"space_comment":"відомості не надано","costs_property_comment":"","space_units":"м²","space":"","address":"відомості не надано"}],"33":[{"region_unclear":false,"address_hidden":false,"region_hidden":false,"space_comment":"відомості не надано","space":"","address":"відомості не надано","region":"","costs_property":"","costs_rent_comment":"","address_unclear":false,"space_units":"м²","costs_property_comment":"","costs_rent":""}],"34":[{"costs_rent":"","region":"","costs_property":"","costs_rent_comment":"","address_hidden":false,"region_hidden":false,"space_comment":"відомості не надано","costs_property_comment":"","space_units":"м²","space":"","address":"відомості не надано"}]},"intro":{"declaration_year":"2014","declaration_year_unclear":false}}