{"income":{"5":{"family_comment":"","value":"175982","family":"41604","comment":""},"6":{"family_comment":"","value":"163802","family":"","comment":""},"7":{"family_comment":"","value":"","source_name":"","family":"","comment":""},"8":{"family_comment":"","value":"","family":"","comment":""},"9":{"family_comment":"","value":"","family":"31104","comment":""},"10":{"family_comment":"","value":"12180","family":"10500","comment":""},"11":{"family_comment":"","value":"","family":"","comment":""},"12":{"family_comment":"","value":"","family":"","comment":""},"13":{"family_comment":"","value":"","family":"","comment":""},"14":{"family_comment":"","value":"","family":"","comment":""},"15":{"family_comment":"","value":"","family":"","comment":""},"16":{"family_comment":"","value":"","family":"","comment":""},"17":{"family_comment":"","value":"","family":"","comment":""},"18":{"family_comment":"","value":"","family":"","comment":""},"19":{"family_comment":"","value":"","family":"","comment":""},"20":{"family_comment":"","value":"","family":"","comment":""}},"vehicle":{"40":[{"brand_info":"2.5 л","sum":"","brand":"Toyota Camry","sum_comment":"","brand_unclear":false,"year":"2011","brand_info_hidden":false,"sum_rent_comment":"","sum_rent":""}]},"id":"vulyk_52_14","banks":{"45":[{"sum_foreign_comment":"","sum_units":"UAH","sum_comment":"","sum_comment_unclear":false,"sum_hidden":false,"sum_foreign_units":"UAH","sum_comment_hidden":false,"sum":"","sum_foreign":""},{"sum_foreign_comment":"","sum_units":"","sum_comment":"","sum_comment_unclear":false,"sum_foreign_units":"","sum":"","sum_unclear":false,"sum_foreign":""}],"46":[{"sum_foreign_comment":"","sum_units":"UAH","sum_comment":"","sum_foreign_units":"UAH","sum_comment_hidden":false,"sum":"","sum_foreign":""}],"47":[{"sum_foreign_comment":"","sum_units":"UAH","sum_comment":"","sum_foreign_units":"UAH","sum_comment_hidden":false,"sum_unclear":false,"sum":"","sum_foreign":""}],"48":[{"sum_foreign_comment":"","sum_units":"UAH","sum_comment":"","sum_foreign_units":"UAH","sum":"","sum_foreign":""}],"49":[{"sum_foreign_comment":"","sum_units":"UAH","sum_comment":"","sum_foreign_units":"UAH","sum":"","sum_foreign":""}],"50":[{"sum_foreign_comment":"","sum_units":"UAH","sum_comment":"","sum_foreign_units":"UAH","sum":"","sum_foreign":""}],"51":[{"sum_foreign_comment":"","sum_units":"UAH","sum_comment":"","sum_foreign_units":"UAH","sum_comment_hidden":false,"sum_unclear":false,"sum":"640000","sum_foreign":""},{"sum_foreign_comment":"","sum_units":"","sum_comment":"","sum_foreign_units":"","sum":"","sum_foreign":""}],"52":[{"sum_foreign_comment":"","sum_units":"UAH","sum_comment":"","sum_foreign_units":"UAH","sum":"","sum_foreign":""}],"53":[{"sum_foreign_comment":"","sum_units":"UAH","sum_comment":"","sum_foreign_units":"UAH","sum":"672000","sum_foreign":""}]},"declaration":{"additional_info_text":"","notfull_lostpages":"","date":"2015-09-21T00:00:00","notfull":"","additional_info":"","url":"http://static.declarations.com.ua/declarations/chosen_ones/mega_batch/bundukov_serhii_vasylovych.pdf"},"liabilities":{"54":{"sum_foreign_comment":"","sum":"","sum_comment":"","sum_foreign":""},"55":{"sum_foreign_comment":"","sum":"","sum_comment":"","sum_foreign":""},"56":{"sum_foreign_comment":"","sum":"","sum_hidden":false,"sum_comment":"","sum_foreign":""},"57":{"sum_foreign_comment":"","sum":"","sum_comment":"","sum_hidden":false,"sum_comment_hidden":false,"sum_foreign":""},"58":{"sum_foreign_comment":"","sum_comment_hidden":false,"sum":"","sum_comment":"","sum_foreign":""},"59":{"sum_foreign_comment":"","sum":"","sum_comment":"","sum_foreign":""},"60":{"sum_foreign_comment":"","sum":"","sum_comment":"","sum_comment_hidden":false,"sum_unclear":false,"sum_foreign":""},"61":{"sum_foreign_comment":"","sum":"","sum_comment":"","sum_foreign":""},"62":{"sum_foreign_comment":"","sum":"","sum_comment":"","sum_foreign":""},"63":{"sum_foreign_comment":"","sum_comment_hidden":false,"sum":"","sum_comment":"","sum_foreign":""},"64":{"sum_foreign_comment":"","sum":"","sum_comment":"","sum_hidden":false,"sum_comment_hidden":false,"sum_foreign":""}},"ft_src":"суддя антрацитівського міськрайонного суду луганської області\nЛуганська область\nЗагальний місцевий суд\nСергій\nБундукова А. Ю\nПодружжя\nБундукова О. С\nДитина\nБундуков С. С\nДитина\nВасильович\nБундуков\nБундуков Сергій Васильович\nБундуков Сергій Васильович\nСергій Васильович Бундуков\nСергій Бундуков\nБундуков Сергій Васильович\n2011\nToyota Camry\n2.5 л\n640000\n672000\n2014\n2.5 л\n2011\nToyota Camry\n640000\n672000\nБундуков Сергій Васильович\nСергій Васильович Бундуков\nСергій Бундуков\nБундуков Сергій Васильович\nБундуков Сергій Васильович\nПодружжя\nБундукова А. Ю\nДитина\nБундукова О. С\nДитина\nБундуков С. С\nСергій\nВасильович\nЗагальний місцевий суд\nсуддя антрацитівського міськрайонного суду луганської області\nЛуганська область\nБундуков\n163802\n175982\n41604\n12180\n10500\n31104\n2014\nБундукова А. Ю\nПодружжя\nБундукова О. С\nДитина\nБундуков С. С\nДитина\nСергій\nВасильович\nБундуков\nБундуков Сергій Васильович\nСергій Васильович Бундуков\nСергій Бундуков\nБундуков Сергій Васильович\nсуддя антрацитівського міськрайонного суду луганської області\nЛуганська область\nЗагальний місцевий суд\nБундуков Сергій Васильович\n163802\n10500\n12180\n41604\n175982\n31104\n2011\nToyota Camry\n2.5 л\n10500\n12180\n41604\n175982\n31104\n163802\n640000\n672000\n2014","general":{"inn":"","name":"Сергій","family":[{"inn":"","relations":"Подружжя","relations_other":"","inn_hidden":true,"family_name":"Бундукова А. Ю","name_hidden":true,"name_unclear":false},{"inn":"","relations":"Дитина","relations_other":"","inn_hidden":true,"family_name":"Бундукова О. С","name_hidden":false},{"inn":"","relations":"Дитина","relations_unclear":false,"family_name":"Бундуков С. С","inn_hidden":false,"relations_other":"","name_unclear":false}],"patronymic":"Васильович","inn_hidden":true,"family_raw":"","last_name":"Бундуков","post":{"office":"Загальний місцевий суд","region":"Луганська область","post":"суддя антрацитівського міськрайонного суду луганської області"},"last_name_unclear":false,"full_name":"Бундуков Сергій Васильович","addresses":[{"place_district":"","place_city_hidden":true,"place_city":"","place_city_type_hidden":true,"place_district_hidden":true,"place_city_type":"","place_address_hidden":true,"place_address":"","place_hidden":true,"place":""}],"full_name_suggest":{"output":"Бундуков Сергій Васильович","input":["Бундуков Сергій Васильович","Сергій Васильович Бундуков","Сергій Бундуков"]}},"source":"VULYK","estate":{"23":[{"costs_rent":"","region":"","costs":"","costs_rent_comment":"","costs_comment":"","address_hidden":false,"region_hidden":false,"space_comment":"","space_units":"м²","space":"","address":""},{"costs_rent":"","region":"","costs":"","costs_rent_comment":"","costs_comment":"","address_hidden":false,"space_comment":"","space_units":"","space":"","address":""},{"costs_rent":"","region":"","costs":"","costs_rent_comment":"","costs_comment":"","address_hidden":false,"space_comment":"","space_units":"","space":"","address":""},{"costs_rent":"","space_unclear":false,"region":"","costs":"","costs_rent_comment":"","costs_comment":"","space_comment":"","space_units":"","space":"","address":""},{"costs_rent":"","region":"","costs":"","costs_rent_comment":"","costs_comment":"","space_comment":"","space_units":"","space":"","address":""},{"costs_rent":"","costs":"","costs_rent_comment":"","costs_comment":"","space_comment":"","space_units":"","space":"","address":""}]},"intro":{"declaration_year":"2014","isnotdeclaration":""}}