{"income":{"5":{"value":"237240","family_comment":"","value_unclear":false,"family_hidden":false,"value_hidden":false,"family_unclear":false,"comment_unclear":false,"comment":"","family":""},"6":{"value":"237240","family_unclear":false,"family_hidden":false,"family_comment":"","family":"","comment":""},"7":{"value":"","family_hidden":false,"value_hidden":false,"family_comment":"","source_name":"","family":"","comment":""},"8":{"family_comment":"","value":"","family":"","comment":""},"9":{"family_comment":"","value":"","value_unclear":false,"family":"","comment":""},"10":{"family_comment":"","family_unclear":false,"value":"","family":"","comment":""},"11":{"family_comment":"","value":"","family":"","comment":""},"12":{"family_comment":"","value":"","family":"","comment":""},"13":{"family_comment":"","value":"","family":"","comment":""},"14":{"family_comment":"","value":"","family":"","comment":""},"15":{"family_comment":"","value":"","family":"","comment":""},"16":{"family_comment":"","value":"","family":"","comment":""},"17":{"family_comment":"","value":"","family":"","comment":""},"18":{"family_comment":"","value":"","family":"","comment":""},"19":{"family_comment":"","value":"","family":"","comment":""},"20":{"value":"","value_unclear":false,"family_comment":"","comment_unclear":false,"comment":"","family":""}},"vehicle":{"35":[{"brand_info":"1493 куб.см.","sum_rent_comment":"","year":"1996","sum_rent_unclear":false,"brand_info_unclear":false,"year_unclear":false,"sum_rent":"","sum":"46000","brand":"Honda Civic","sum_comment":"","brand_unclear":false,"sum_unclear":false}]},"id":"vulyk_71_163","declaration":{"additional_info_text":"","notfull_lostpages":"","date":"2014-12-17T00:00:00","notfull":"","additional_info":"","url":"http://static.declarations.com.ua/declarations/chosen_ones/judges_batch/439_prozorova_maryna_leonidivna.pdf"},"liabilities":{"54":{"sum_foreign_comment":"","sum":"","sum_comment":"","sum_comment_unclear":false,"sum_comment_hidden":false,"sum_unclear":false,"sum_foreign":""},"55":{"sum_foreign_comment":"","sum":"","sum_comment":"","sum_foreign":""},"56":{"sum_foreign_comment":"","sum":"","sum_comment":"","sum_comment_unclear":false,"sum_unclear":false,"sum_foreign":""},"57":{"sum_foreign_comment":"","sum":"","sum_comment":"","sum_comment_hidden":false,"sum_unclear":false,"sum_foreign":""},"58":{"sum_foreign_comment":"","sum":"","sum_comment":"","sum_comment_hidden":false,"sum_unclear":false,"sum_foreign":""},"59":{"sum_foreign_comment":"","sum_comment_hidden":false,"sum":"","sum_comment":"","sum_foreign":""},"60":{"sum_foreign_comment":"","sum_comment_hidden":false,"sum":"","sum_comment":"","sum_foreign":""},"61":{"sum_foreign_comment":"","sum":"","sum_comment":"","sum_foreign":""},"62":{"sum_foreign_comment":"","sum":"","sum_comment":"","sum_foreign":""},"63":{"sum_foreign_comment":"","sum":"","sum_comment":"","sum_unclear":false,"sum_foreign":""},"64":{"sum_foreign_comment":"","sum":"","sum_comment":"","sum_unclear":false,"sum_foreign":""}},"ft_src":"суддя апеляційного суду дніпропетровської області\nДніпропетровська область\nЗагальний апеляційний суд\nМарина\nЛеонідівна\nПрозорова\nПрозорова Марина Леонідівна\nПрозорова Марина Леонідівна\nМарина Леонідівна Прозорова\nМарина Прозорова\nПрозорова Марина Леонідівна\n1493 куб.см.\nHonda Civic\n1996\n46000\n2100\n60\n2013\n237240\n237240\n1493 куб.см.\nHonda Civic\n1996\n46000\n2100\n60\nПрозорова Марина Леонідівна\nМарина Леонідівна Прозорова\nМарина Прозорова\nПрозорова Марина Леонідівна\nМарина\nПрозорова Марина Леонідівна\nПрозорова\nЗагальний апеляційний суд\nДніпропетровська область\nсуддя апеляційного суду дніпропетровської області\nЛеонідівна\n237240\n237240\n2013\nМарина\nЛеонідівна\nПрозорова\nПрозорова Марина Леонідівна\nМарина Леонідівна Прозорова\nМарина Прозорова\nПрозорова Марина Леонідівна\nДніпропетровська область\nЗагальний апеляційний суд\nсуддя апеляційного суду дніпропетровської області\nПрозорова Марина Леонідівна\n1996\nHonda Civic\n46000\n1493 куб.см.\n237240\n237240\n60\n2100\n2013","general":{"inn":"","name":"Марина","inn_unclear":false,"patronymic":"Леонідівна","inn_hidden":false,"family_raw":"","last_name":"Прозорова","post":{"post_unclear":false,"region_unclear":false,"post":"суддя апеляційного суду дніпропетровської області","office":"Загальний апеляційний суд","region":"Дніпропетровська область","post_hidden":false,"office_unclear":false},"last_name_unclear":false,"full_name":"Прозорова Марина Леонідівна","addresses":[{"place_district":"","place_unclear":false,"place_city":"","place_city_type_hidden":true,"place_district_hidden":true,"place_city_type":"","place_city_hidden":true,"place_address_hidden":true,"place_address":"","place_hidden":true,"place":""}],"patronymic_hidden":false,"full_name_suggest":{"output":"Прозорова Марина Леонідівна","input":["Прозорова Марина Леонідівна","Марина Леонідівна Прозорова","Марина Прозорова"]},"name_unclear":false},"source":"VULYK","estate":{"23":[{"space_hidden":false,"costs":"","costs_comment":"","costs_hidden":false,"address_hidden":true,"region_hidden":true,"space_comment":"","space_unclear":false,"space":"2100","address":"","costs_comment_unclear":false,"region":"","costs_rent_comment":"","costs_rent_hidden":false,"space_comment_unclear":false,"space_units":"м²","costs_rent":""}],"25":[{"region_unclear":false,"space_unclear":false,"costs":"","costs_rent_unclear":false,"costs_comment":"","costs_hidden":false,"address_hidden":true,"region_hidden":true,"space_comment":"","space_hidden":false,"space":"60","address":"","costs_unclear":false,"region":"","address_unclear":false,"costs_rent_comment":"","costs_rent_hidden":false,"space_comment_unclear":false,"space_units":"м²","costs_rent":""}]},"intro":{"declaration_year":"2013","isnotdeclaration":""}}