{"income":{"5":{"value":"294902","family_comment":"","value_unclear":false,"family_hidden":false,"value_hidden":false,"family_unclear":false,"family":"95432","comment":""},"6":{"value":"245250","value_unclear":false,"value_hidden":false,"family_comment":"","family":"82543","comment":""},"7":{"family_comment":"","value":"","source_name":"","family":"","comment":""},"8":{"family_comment":"","value":"","family":"","comment":""},"9":{"family_comment":"","value":"","family":"","comment":""},"10":{"value":"13398","family_comment":"","value_unclear":false,"family_unclear":false,"family":"7200","comment":""},"11":{"family_comment":"","value":"","family":"","comment":""},"12":{"family_comment":"","value":"","family":"","comment":""},"13":{"family_comment":"","value":"","family":"","comment":""},"14":{"family_comment":"","value":"","value_unclear":false,"family":"","comment":""},"15":{"family_comment":"","value":"2398","family":"1379","comment":""},"16":{"family_comment":"","value":"","family":"","comment":""},"17":{"family_comment":"","value":"","family":"","comment":""},"18":{"family_comment":"","value":"","family":"","comment":""},"19":{"family_comment":"","value":"","family":"","comment":"","family_comment_unclear":false},"20":{"value":"33856","value_unclear":false,"family_comment":"","comment_unclear":false,"comment":"","family":"4310"}},"vehicle":{"35":[{"year_hidden":false,"brand_info":"1600 куб. см. 91 кВт 4545 мм","sum_rent_comment":"","brand_info_unclear":false,"year":"2011","brand_info_hidden":false,"sum_rent_comment_unclear":false,"sum_rent":"","sum":"","brand":"Toyota Corolla","sum_comment":"","sum_comment_unclear":false,"brand_hidden":false,"sum_rent_comment_hidden":false,"sum_comment_hidden":false,"sum_unclear":false}],"40":[{"brand_info":"1242 куб. см. 67 кВт 3715 мм","sum":"","brand":"Suzuki Splash","sum_comment":"","brand_unclear":false,"year":"2012","brand_hidden":false,"brand_info_hidden":false,"brand_info_unclear":false,"sum_rent_comment":"","sum_rent":""}]},"id":"vulyk_60_101","banks":{"45":[{"sum_foreign_comment":"","sum_units":"UAH","sum_comment":"","sum_comment_unclear":false,"sum_foreign_units":"UAH","sum":"","sum_unclear":false,"sum_foreign":""}],"46":[{"sum_foreign_comment":"","sum_units":"UAH","sum_comment":"","sum_foreign_units":"UAH","sum":"","sum_foreign":""}],"47":[{"sum_foreign_comment":"","sum_units":"UAH","sum_comment":"","sum_foreign_units":"UAH","sum":"871","sum_foreign":""}],"48":[{"sum_foreign_comment":"","sum_units":"UAH","sum_comment":"","sum_foreign_units":"UAH","sum":"","sum_foreign":""}],"49":[{"sum_foreign_comment":"","sum_units":"UAH","sum_comment":"","sum_foreign_units":"UAH","sum":"","sum_foreign":""}],"50":[{"sum_foreign_comment":"","sum_units":"UAH","sum_comment":"","sum_foreign_units":"UAH","sum":"","sum_foreign":""}],"51":[{"sum_foreign_comment":"","sum_units":"UAH","sum_comment":"","sum_foreign_units":"UAH","sum":"352","sum_unclear":false,"sum_foreign":""}],"52":[{"sum_foreign_comment":"","sum_units":"UAH","sum_comment":"","sum_foreign_units":"UAH","sum":"21","sum_foreign":""}],"53":[{"sum_foreign_comment":"","sum_units":"UAH","sum_comment":"","sum_foreign_units":"UAH","sum":"","sum_foreign":""}]},"declaration":{"additional_info_text":"","notfull_lostpages":"","date":"2015-03-23T00:00:00","notfull":"","additional_info":"","url":"http://static.declarations.com.ua/declarations/chosen_ones/mega_batch/matiushenko_ihor_volodymyrovych.pdf"},"liabilities":{"54":{"sum_foreign_comment":"","sum":"9327","sum_comment":"","sum_foreign":""},"55":{"sum_foreign_comment":"","sum":"","sum_comment":"","sum_foreign":""},"56":{"sum_foreign_comment":"","sum":"","sum_comment":"","sum_foreign":""},"57":{"sum_foreign_comment":"","sum":"15799","sum_comment":"","sum_unclear":false,"sum_foreign":""},"58":{"sum_foreign_comment":"","sum":"","sum_comment":"","sum_foreign":""},"59":{"sum_foreign_comment":"","sum":"","sum_comment":"","sum_foreign":""},"60":{"sum_foreign_comment":"","sum":"5048","sum_comment":"","sum_foreign":""},"61":{"sum_foreign_comment":"","sum":"","sum_comment":"","sum_foreign":""},"62":{"sum_foreign_comment":"","sum":"","sum_comment":"","sum_comment_unclear":false,"sum_unclear":false,"sum_foreign":""},"63":{"sum_foreign_comment":"","sum":"","sum_comment":"","sum_foreign":""},"64":{"sum_foreign_comment":"","sum":"","sum_comment":"","sum_foreign":""}},"ft_src":"15799\n9327\n5048\nсуддя апеляційного суду житомирської області\nЖитомирська область\nЗагальний апеляційний суд\nІгор\nПодружжя\nДитина\nВолодимирович\nМатюшенко\nМатюшенко Ігор Володимирович\nМатюшенко Ігор Володимирович\nІгор Володимирович Матюшенко\nІгор Матюшенко\nМатюшенко Ігор Володимирович\n1600 куб. см. 91 кВт 4545 мм\n2011\nToyota Corolla\nSuzuki Splash\n1242 куб. см. 67 кВт 3715 мм\n2012\n871\n352\n21\n2014\n1600 куб. см. 91 кВт 4545 мм\nToyota Corolla\n2011\nSuzuki Splash\n1242 куб. см. 67 кВт 3715 мм\n2012\n352\n21\n871\n48\n2 шт\nм. Житомир\nЖитомирська область\n58.2\nЖитомирський р-н, с. Іванівка\nЖитомирська область\n76.35\n1/3 частина\nм. Житомир\nЖитомирська область\n450\nЖитомирський р-н, с. Іванівка\nЖитомирська область\nЖитомирська область\nЖитомирський р-н, с. Гуйва\n1500\n76.35\n2/3\nЖитомирська область\nм. Житомир\nМатюшенко Ігор Володимирович\nІгор Володимирович Матюшенко\nІгор Матюшенко\nМатюшенко Ігор Володимирович\nМатюшенко Ігор Володимирович\nПодружжя\nДитина\nІгор\nВолодимирович\nсуддя апеляційного суду житомирської області\nЖитомирська область\nЗагальний апеляційний суд\nМатюшенко\n15799\n5048\n9327\n245250\n82543\n33856\n4310\n2398\n1379\n95432\n294902\n13398\n7200\n2014\n15799\n9327\n5048\nЖитомирська область\n2 шт\nм. Житомир\n48\nЖитомирська область\nЖитомирський р-н, с. Гуйва\n1500\nЖитомирський р-н, с. Іванівка\n450\nЖитомирська область\n2/3\nм. Житомир\nЖитомирська область\n76.35\nЖитомирська область\nЖитомирський р-н, с. Іванівка\n58.2\n1/3 частина\nм. Житомир\nЖитомирська область\n76.35\nПодружжя\nДитина\nІгор\nВолодимирович\nМатюшенко\nМатюшенко Ігор Володимирович\nІгор Володимирович Матюшенко\nІгор Матюшенко\nМатюшенко Ігор Володимирович\nсуддя апеляційного суду житомирської області\nЖитомирська область\nЗагальний апеляційний суд\nМатюшенко Ігор Володимирович\n82543\n245250\n1379\n2398\n7200\n13398\n95432\n294902\n4310\n33856\nToyota Corolla\n1600 куб. см. 91 кВт 4545 мм\n2011\nSuzuki Splash\n1242 куб. см. 67 кВт 3715 мм\n2012\n1379\n2398\n13398\n7200\n33856\n4310\n294902\n95432\n245250\n82543\n2/3\nм. Житомир\nЖитомирська область\n76.35\nЖитомирський р-н, с. Іванівка\nЖитомирська область\n450\nЖитомирський р-н, с. Іванівка\nЖитомирська область\n58.2\n2 шт\nм. Житомир\nЖитомирська область\n48\n1/3 частина\nм. Житомир\nЖитомирська область\n76.35\nЖитомирська область\nЖитомирський р-н, с. Гуйва\n1500\n871\n21\n352\n2014","general":{"inn":"","name":"Ігор","family":[{"inn":"","inn_hidden":true,"relations_hidden":false,"family_name":"","relations_other":"","relations":"Подружжя","name_hidden":true,"name_unclear":false},{"inn":"","relations":"Дитина","relations_other":"","inn_hidden":false,"family_name":"","name_hidden":false,"name_unclear":false}],"patronymic":"Володимирович","inn_hidden":true,"family_raw":"","last_name":"Матюшенко","post":{"post_unclear":false,"post_hidden":false,"post":"суддя апеляційного суду житомирської області","region":"Житомирська область","office":"Загальний апеляційний суд"},"last_name_unclear":false,"full_name":"Матюшенко Ігор Володимирович","addresses":[{"place_district":"","place_city_hidden":true,"place_city":"","place_city_type_hidden":true,"place_district_hidden":true,"place_city_type":"","place_address_hidden":true,"place_address":"","place_hidden":true,"place":""}],"full_name_suggest":{"output":"Матюшенко Ігор Володимирович","input":["Матюшенко Ігор Володимирович","Ігор Володимирович Матюшенко","Ігор Матюшенко"]}},"source":"VULYK","estate":{"23":[{"space_unclear":false,"costs":"","costs_comment":"","address_hidden":true,"region_hidden":false,"space_comment":"","space_hidden":false,"space":"450","address":"Житомирський р-н, с. Іванівка","region":"Житомирська область","address_unclear":false,"costs_rent_comment":"","space_units":"м²","costs_rent":""},{"space_unclear":false,"costs":"","costs_comment":"","address_hidden":false,"space_comment":"","space":"","address":"","region":"","address_unclear":false,"costs_rent_comment":"","space_units":"","costs_rent":""},{"costs_rent":"","space_unclear":false,"region":"","costs":"","costs_rent_comment":"","costs_comment":"","space_comment":"","space_units":"","space":"","address":""},{"costs_rent":"","region":"","costs":"","costs_rent_comment":"","costs_comment":"","space_comment":"","space_units":"","space":"","address":""}],"25":[{"space_unclear":false,"costs":"","costs_comment":"","address_hidden":true,"region_hidden":false,"space_comment":"1/3 частина","space_hidden":false,"space":"76.35","address":"м. Житомир","region":"Житомирська область","costs_rent_comment":"","space_comment_unclear":false,"space_units":"м²","costs_rent":""}],"26":[{"space_hidden":false,"costs":"","costs_comment":"","address_hidden":true,"region_hidden":false,"space_comment":"","space":"58.2","address":"Житомирський р-н, с. Іванівка","region":"Житомирська область","address_unclear":false,"costs_rent_comment":"","space_units":"м²","costs_rent":""}],"27":[{"space_hidden":false,"costs":"","costs_comment":"","address_hidden":true,"region_hidden":false,"space_comment":"2 шт","space":"48","address":"м. Житомир","region":"Житомирська область","address_unclear":false,"costs_rent_comment":"","space_units":"м²","costs_rent":""}],"29":[{"space_unclear":false,"address_hidden":true,"region_hidden":false,"space_comment":"","space_units_hidden":false,"space_hidden":false,"space":"1500","address":"Житомирський р-н, с. Гуйва","region":"Житомирська область","address_unclear":false,"space_units_unclear":false,"space_comment_unclear":false,"costs_property":"","space_units":"м²","costs_property_comment":"","costs_rent":"","costs_rent_comment":""}],"31":[{"space_unclear":false,"address_hidden":true,"region_hidden":false,"space_comment":"2/3","space_hidden":false,"space":"76.35","address":"м. Житомир","region":"Житомирська область","costs_property":"","costs_rent_comment":"","address_unclear":false,"space_units":"м²","costs_property_comment":"","costs_rent":""}]},"intro":{"declaration_year":"2014","isnotdeclaration":"","declaration_year_unclear":false}}