{"income":{"5":{"value":"218263","family_comment":"","value_unclear":false,"family_hidden":false,"value_hidden":false,"family_unclear":false,"comment_unclear":true,"comment":"","family":"42075"},"6":{"value":"205814","family_comment":"","value_unclear":false,"family_hidden":false,"value_hidden":false,"family_unclear":false,"comment_unclear":false,"comment":"","family":""},"7":{"source_name_unclear":false,"value":"","family_comment":"","source_name":"","family":"","comment":""},"8":{"family_comment":"","value":"","family":"","comment":""},"9":{"value":"269","value_unclear":false,"comment_hidden":false,"family_comment":"","comment_unclear":false,"comment":"","family":""},"10":{"value":"12180","comment_unclear":false,"value_hidden":false,"family_comment":"","family":"","comment":""},"11":{"family_comment":"","value":"","family":"","comment":""},"12":{"family_comment":"","value":"","family":"","comment":""},"13":{"family_comment":"","value":"","family":"","comment":""},"14":{"family_comment":"","value":"","family":"","comment":""},"15":{"family_comment":"","value":"","family":"","comment":""},"16":{"family_comment":"","value":"","family":"","comment":""},"17":{"family_comment":"","value":"","family":"","comment":""},"18":{"value":"","family_hidden":false,"value_hidden":false,"family_comment":"","family":"","comment":""},"19":{"family_comment":"","value":"","family":"4707","comment":""},"20":{"value":"","family_comment":"пенсія","value_unclear":false,"family_hidden":false,"value_hidden":false,"family_unclear":false,"family":"37368","comment":""}},"vehicle":{"40":[{"brand_info":"двигун 5778301","sum_rent_comment":"","brand":"Москвич 2141","sum_comment":"","brand_unclear":true,"year":"1997","brand_info_unclear":true,"year_unclear":true,"sum":"","sum_rent":""}]},"id":"vulyk_66_38","banks":{"46":[{"sum_foreign_comment":"","sum_units":"UAH","sum_comment":"","sum_foreign_units":"UAH","sum":"12316","sum_foreign":""}]},"declaration":{"additional_info_text":"","notfull_lostpages":"","date":"2015-03-26T00:00:00","notfull":"","additional_info":"","url":"http://static.declarations.com.ua/declarations/chosen_ones/mega_batch/kryvenko_oksana_volodymyrivna.pdf"},"liabilities":{"54":{"sum_foreign_comment":"","sum":"2329","sum_comment":"","sum_comment_unclear":false,"sum_comment_hidden":false,"sum_unclear":false,"sum_foreign":""},"55":{"sum_foreign_comment":"","sum":"","sum_comment":"","sum_foreign":""},"56":{"sum_foreign_comment":"","sum_foreign_hidden":false,"sum_comment":"","sum_hidden":false,"sum_comment_hidden":false,"sum":"","sum_foreign":""},"57":{"sum_foreign_comment":"","sum":"","sum_comment":"","sum_comment_unclear":false,"sum_hidden":false,"sum_comment_hidden":false,"sum_unclear":false,"sum_foreign":""},"58":{"sum_foreign_comment":"","sum":"","sum_comment":"","sum_comment_unclear":false,"sum_unclear":false,"sum_foreign":""},"59":{"sum_foreign_comment":"","sum_foreign_hidden":false,"sum_comment":"","sum_comment_unclear":false,"sum_hidden":false,"sum":"","sum_foreign":""},"60":{"sum_foreign_comment":"","sum":"1600","sum_comment":"","sum_comment_unclear":false,"sum_foreign":""},"61":{"sum_foreign_comment":"","sum":"","sum_comment":"","sum_foreign":""},"62":{"sum_foreign_comment":"","sum_foreign_hidden":false,"sum_comment":"","sum_hidden":false,"sum":"706","sum_unclear":true,"sum_foreign":""},"63":{"sum_foreign_comment":"","sum":"","sum_comment":"","sum_comment_unclear":false,"sum_comment_hidden":false,"sum_unclear":false,"sum_foreign":""},"64":{"sum_foreign_comment":"","sum":"","sum_comment":"","sum_comment_unclear":false,"sum_foreign":""}},"ft_src":"706\n2329\n1600\nсуддя доманівського райсуду миколаївської області\nМиколаївська область\nЗагальний місцевий суд\nОксана\nБатьки\nдід\nІнше\nВолодимирівна\nКривенко Оксана Володимирівна\nОксана Володимирівна Кривенко\nОксана Кривенко\nКривенко Оксана Володимирівна\nКривенко Оксана Володимирівна\nКривенко\nдвигун 5778301\nМосквич 2141\n1997\n12316\n2014\nдвигун 5778301\n1997\nМосквич 2141\n12316\n55100\n31.78\nЗагальний місцевий суд\nсуддя доманівського райсуду миколаївської області\nМиколаївська область\nБатьки\nІнше\nдід\nКривенко Оксана Володимирівна\nОксана Володимирівна Кривенко\nОксана Кривенко\nКривенко Оксана Володимирівна\nКривенко Оксана Володимирівна\nОксана\nКривенко\nВолодимирівна\n1600\n706\n2329\n205814\nпенсія\n37368\n218263\n42075\n12180\n269\n4707\n2014\n706\n2329\n1600\n31.78\n55100\nБатьки\nдід\nІнше\nВолодимирівна\nКривенко\nОксана\nКривенко Оксана Володимирівна\nОксана Володимирівна Кривенко\nОксана Кривенко\nКривенко Оксана Володимирівна\nМиколаївська область\nсуддя доманівського райсуду миколаївської області\nЗагальний місцевий суд\nКривенко Оксана Володимирівна\n205814\n12180\n42075\n218263\n4707\n269\nпенсія\n37368\n1997\nдвигун 5778301\nМосквич 2141\n4707\n12180\nпенсія\n37368\n218263\n42075\n269\n205814\n31.78\n55100\n12316\n2014","general":{"inn":"","name":"Оксана","last_name_hidden":false,"family":[{"inn":"","inn_hidden":true,"relations_hidden":false,"family_name":"","relations_other":"","relations":"Батьки","name_hidden":true,"name_unclear":false},{"inn":"","inn_hidden":false,"relations_unclear":false,"relations_hidden":false,"relations_other":"дід","relations":"Інше","name_hidden":false,"family_name":"","name_unclear":false}],"patronymic":"Володимирівна","inn_hidden":true,"family_raw":"","inn_unclear":false,"post":{"post_unclear":false,"post":"суддя доманівського райсуду миколаївської області","candidate":"","office_hidden":false,"region":"Миколаївська область","office":"Загальний місцевий суд","office_unclear":false},"full_name_suggest":{"output":"Кривенко Оксана Володимирівна","input":["Кривенко Оксана Володимирівна","Оксана Володимирівна Кривенко","Оксана Кривенко"]},"full_name":"Кривенко Оксана Володимирівна","addresses":[{"place_city_type_unclear":false,"place_address":"","place_district_hidden":true,"place_city_type":"","place_address_hidden":true,"place_address_unclear":false,"place_city_type_hidden":true,"place":"","place_district":"","place_unclear":false,"place_city":"","place_city_unclear":false,"place_hidden":true,"place_city_hidden":true,"place_district_unclear":false}],"last_name":"Кривенко","last_name_unclear":false},"source":"VULYK","estate":{"29":[{"space_unclear":false,"address_hidden":true,"region_hidden":true,"space_comment":"","space_hidden":false,"space":"55100","address":"","region":"","costs_property":"","costs_rent_comment":"","space_units":"м²","costs_property_comment":"","costs_rent":""}],"30":[{"space_unclear":false,"address_hidden":true,"region_hidden":true,"space_comment":"","space_hidden":false,"space":"31.78","address":"","region":"","costs_property":"","costs_rent_comment":"","address_unclear":false,"space_units":"м²","costs_property_comment":"","costs_rent":""}]},"intro":{"declaration_year":"2014","isnotdeclaration":"","declaration_year_unclear":false}}