{"income":{"5":{"family_comment":"","value":"264485","family":"","comment":""},"6":{"value":"259425","family_comment":"","value_unclear":false,"comment_hidden":false,"family_unclear":false,"family":"","comment":""},"7":{"family_comment":"","value":"","source_name":"","family":"","comment":""},"8":{"family_comment":"","value":"","family":"","comment":""},"9":{"family_comment":"","family_unclear":false,"value":"430","family":"","comment":""},"10":{"family_comment":"","value":"","value_unclear":false,"family":"","comment":""},"11":{"family_comment":"","value":"","family":"","comment":""},"12":{"family_comment":"","value":"","family":"","comment":""},"13":{"family_comment":"","value":"","family":"","comment":""},"14":{"family_comment":"","value":"","family":"","comment":""},"15":{"family_comment":"","value":"","family":"","comment":""},"16":{"family_comment":"","value":"","family":"","comment":""},"17":{"family_comment":"","value":"","family":"","comment":""},"18":{"family_comment":"","value":"","family":"","comment":""},"19":{"family_comment":"","value":"","family":"","comment":""},"20":{"value":"4629","family":"","value_unclear":false,"family_hidden":false,"family_comment":"","comment_unclear":false,"comment":"","family_comment_unclear":false}},"vehicle":{"35":[{"year_hidden":false,"brand_info":"1399 куб. см., 71.3 кВт","sum_rent_comment":"","year":"2010","brand_info_hidden":false,"brand_info_unclear":false,"sum_rent":"","sum":"","brand":"Kia Rio","sum_comment":"","brand_unclear":false,"brand_hidden":false}]},"id":"vulyk_97_57","declaration":{"additional_info_text":"","notfull_lostpages":"","date":"2015-03-26T00:00:00","notfull":"","additional_info":"","url":"http://static.declarations.com.ua/declarations/chosen_ones/judges_batch/3885_lytvynenko_iryna_vasylivna.pdf"},"liabilities":{"54":{"sum_foreign_comment":"","sum":"","sum_comment":"","sum_comment_unclear":false,"sum_hidden":false,"sum_comment_hidden":false,"sum_unclear":false,"sum_foreign":""},"55":{"sum_foreign_comment":"","sum":"","sum_comment":"","sum_foreign":""},"56":{"sum_foreign_comment":"","sum":"","sum_comment":"","sum_foreign":""},"57":{"sum_foreign_comment":"","sum":"","sum_comment":"","sum_comment_unclear":false,"sum_hidden":false,"sum_comment_hidden":false,"sum_unclear":false,"sum_foreign":""},"58":{"sum_foreign_comment":"","sum":"","sum_comment":"","sum_comment_unclear":false,"sum_hidden":false,"sum_comment_hidden":false,"sum_unclear":false,"sum_foreign":""},"59":{"sum_foreign_comment":"","sum":"","sum_comment":"","sum_foreign":""},"60":{"sum_foreign_comment":"","sum":"","sum_comment":"","sum_comment_unclear":false,"sum_hidden":false,"sum_comment_hidden":false,"sum_foreign":""},"61":{"sum_foreign_comment":"","sum":"","sum_comment":"","sum_foreign":""},"62":{"sum_foreign_comment":"","sum":"","sum_comment":"","sum_unclear":false,"sum_foreign":""},"63":{"sum_foreign_comment":"","sum":"","sum_hidden":false,"sum_comment":"","sum_foreign":""},"64":{"sum_foreign_comment":"","sum":"","sum_comment":"","sum_foreign":""}},"ft_src":"суддя апеляційного суду чернігівської області\nЧернігівська область\nЗагальний апеляційний суд\nІрина\nЛитвиненко К. В. 26. 03. 2003\nДитина\nВасилівна\nЛитвиненко Ірина Василівна\nІрина Василівна Литвиненко\nІрина Литвиненко\nЛитвиненко Ірина Василівна\nЛитвиненко Ірина Василівна\nЛитвиненко\n1399 куб. см., 71.3 кВт\nKia Rio\n2010\nІванівська\n1000\n56.9\n2014\n259425\n430\n264485\n4629\n1399 куб. см., 71.3 кВт\nKia Rio\n2010\n2014\nЛитвиненко Ірина Василівна\nІрина Василівна Литвиненко\nІрина Литвиненко\nЛитвиненко Ірина Василівна\nІрина\nДитина\nЛитвиненко К. В. 26. 03. 2003\nЛитвиненко Ірина Василівна\nЛитвиненко\nЗагальний апеляційний суд\nЧернігівська область\nсуддя апеляційного суду чернігівської області\nВасилівна\n259425\n4629\n264485\n430\n1000\nІванівська\n56.9\nДитина\nЛитвиненко К. В. 26. 03. 2003\nВасилівна\nЛитвиненко\nІрина\nЛитвиненко Ірина Василівна\nІрина Василівна Литвиненко\nІрина Литвиненко\nЛитвиненко Ірина Василівна\nЧернігівська область\nЗагальний апеляційний суд\nсуддя апеляційного суду чернігівської області\nЛитвиненко Ірина Василівна\n2010\nKia Rio\n1399 куб. см., 71.3 кВт\n430\n4629\n264485\n259425\n56.9\nІванівська\n1000\n2014","general":{"name_hidden":false,"name":"Ірина","last_name_hidden":false,"inn":"","family":[{"inn":"","relations":"Дитина","relations_other":"","inn_hidden":true,"family_name":"Литвиненко К. В. 26. 03. 2003","name_hidden":false,"name_unclear":false}],"patronymic":"Василівна","inn_hidden":true,"family_raw":"","inn_unclear":false,"post":{"region_unclear":false,"region":"Чернігівська область","post":"суддя апеляційного суду чернігівської області","office":"Загальний апеляційний суд","office_unclear":false,"post_hidden":false},"full_name":"Литвиненко Ірина Василівна","addresses":[{"place_district":"","place_city_hidden":true,"place_city":"","place_city_unclear":false,"place_district_hidden":false,"place_city_type":"","place_address_hidden":true,"place_city_type_hidden":false,"place_address":"","place_hidden":true,"place":""}],"last_name":"Литвиненко","patronymic_hidden":false,"full_name_suggest":{"output":"Литвиненко Ірина Василівна","input":["Литвиненко Ірина Василівна","Ірина Василівна Литвиненко","Ірина Литвиненко"]}},"source":"VULYK","estate":{"23":[{"region_unclear":false,"space_unclear":false,"costs":"","costs_rent_unclear":false,"costs_comment":"","address_hidden":false,"region_hidden":true,"space_comment":"Іванівська","space":"1000","address":"","region":"","address_unclear":false,"costs_rent_comment":"","space_units":"м²","costs_rent":""}],"31":[{"space_unclear":false,"address_hidden":true,"region_hidden":true,"space_comment":"","space_hidden":false,"space":"56.9","address":"","region":"","costs_property":"","costs_rent_comment":"","space_comment_hidden":false,"space_units":"м²","costs_property_comment":"","costs_rent":""}]},"intro":{"declaration_year":"2014","isnotdeclaration":""}}