{"income":{"5":{"family_comment":"","value":"258519.67","value_unclear":false,"family":"","comment":""},"6":{"value":"246641.54","value_unclear":false,"family_hidden":false,"family_comment":"","family":"","comment":""},"7":{"source_name_unclear":false,"value":"11878.13","family_comment":"","source_name":"","family":"","comment":""},"8":{"family_comment":"","value":"","family":"","comment":""},"9":{"family_comment":"","value":"","family":"","comment":""},"10":{"family_comment":"","value":"","family":"","comment":""},"11":{"family_comment":"","value":"","comment_unclear":false,"family":"","comment":""},"12":{"family_comment":"","value":"","family":"","comment":""},"13":{"family_comment":"","value":"","family":"","comment":""},"14":{"family_comment":"","value":"","family":"","comment":""},"15":{"family_comment":"","value":"","family":"","comment":""},"16":{"family_comment":"","value":"","family":"","comment":""},"17":{"family_comment":"","value":"","family":"","comment":""},"18":{"family_comment":"","value":"","family":"","comment":""},"19":{"family_comment":"","value":"","family":"","comment":""},"20":{"value":"","family_comment":"","value_unclear":false,"family_unclear":false,"comment_unclear":false,"comment":"","family":""}},"vehicle":{"35":[{"brand_info":"270 Х01","sum_rent_comment":"","brand":"SsangYong Rexton RX","sum_comment":"","brand_unclear":false,"year":"2008","sum_rent_unclear":false,"brand_info_hidden":false,"brand_info_unclear":false,"sum":"","sum_rent":""}]},"id":"vulyk_101_64","declaration":{"additional_info_text":"","notfull_lostpages":"","date":"2016-03-30T00:00:00","notfull":"","additional_info":"","url":"http://static.declarations.com.ua/declarations/chosen_ones/judges_batch/729_sievierova_ieliena_stanislavivna_2015.pdf"},"liabilities":{"54":{"sum_foreign_comment":"","sum":"","sum_comment":"","sum_comment_unclear":false,"sum_hidden":false,"sum_comment_hidden":false,"sum_unclear":false,"sum_foreign":""},"55":{"sum_foreign_comment":"","sum":"","sum_comment":"","sum_foreign":""},"56":{"sum_foreign_comment":"","sum":"","sum_comment":"","sum_comment_hidden":false,"sum_unclear":false,"sum_foreign":""},"57":{"sum_foreign_comment":"","sum":"","sum_comment":"","sum_hidden":false,"sum_comment_hidden":false,"sum_unclear":false,"sum_foreign":""},"58":{"sum_foreign_comment":"","sum":"","sum_comment":"","sum_comment_unclear":false,"sum_hidden":false,"sum_comment_hidden":false,"sum_unclear":false,"sum_foreign":""},"59":{"sum_foreign_comment":"","sum":"","sum_comment":"","sum_foreign":""},"60":{"sum_foreign_comment":"","sum":"","sum_comment":"","sum_hidden":false,"sum_comment_hidden":false,"sum_unclear":false,"sum_foreign":""},"61":{"sum_foreign_comment":"","sum":"","sum_comment":"","sum_foreign":""},"62":{"sum_foreign_comment":"","sum":"","sum_comment":"","sum_comment_unclear":false,"sum_foreign":""},"63":{"sum_foreign_comment":"","sum_comment_hidden":false,"sum":"","sum_comment":"","sum_foreign":""},"64":{"sum_foreign_comment":"","sum_comment_hidden":false,"sum":"","sum_comment":"","sum_foreign":""}},"ft_src":"суддя апеляційного суду одеської області\nОдеська область\nЗагальний апеляційний суд\nЄлєна\nРоманенко С. Р\nДитина\nСтаніславівна\nСєвєрова Єлєна Станіславівна\nСєвєрова\nСєвєрова Єлєна Станіславівна\nЄлєна Станіславівна Сєвєрова\nЄлєна Сєвєрова\nСєвєрова Єлєна Станіславівна\nSsangYong Rexton RX\n270 Х01\n2008\n48.7\n2015\n246641.54\n11878.13\n258519.67\n270 Х01\n2008\nSsangYong Rexton RX\n48.7\nСєвєрова Єлєна Станіславівна\nЄлєна Станіславівна Сєвєрова\nЄлєна Сєвєрова\nСєвєрова Єлєна Станіславівна\nЄлєна\nСєвєрова Єлєна Станіславівна\nСтаніславівна\nсуддя апеляційного суду одеської області\nОдеська область\nЗагальний апеляційний суд\nСєвєрова\nДитина\nРоманенко С. Р\n11878.13\n246641.54\n258519.67\n2015\nРоманенко С. Р\nДитина\nЄлєна\nСтаніславівна\nСєвєрова\nСєвєрова Єлєна Станіславівна\nЄлєна Станіславівна Сєвєрова\nЄлєна Сєвєрова\nСєвєрова Єлєна Станіславівна\nсуддя апеляційного суду одеської області\nОдеська область\nЗагальний апеляційний суд\nСєвєрова Єлєна Станіславівна\n2008\nSsangYong Rexton RX\n270 Х01\n258519.67\n11878.13\n246641.54\n48.7\n2015","general":{"inn":"","name":"Єлєна","inn_unclear":false,"family":[{"inn":"","relations":"Дитина","relations_other":"","inn_hidden":false,"family_name":"Романенко С. Р","name_hidden":true,"name_unclear":true}],"inn_hidden":true,"family_raw":"","last_name":"Сєвєрова","post":{"region":"Одеська область","region_unclear":false,"post":"суддя апеляційного суду одеської області","office_unclear":false,"office":"Загальний апеляційний суд"},"full_name":"Сєвєрова Єлєна Станіславівна","addresses":[{"place_district":"","place_address_hidden":true,"place_city":"","place_city_type_hidden":false,"place_district_hidden":false,"place_city_type":"","place_city_hidden":true,"place_address":"","place_hidden":true,"place":""}],"patronymic":"Станіславівна","patronymic_hidden":false,"full_name_suggest":{"output":"Сєвєрова Єлєна Станіславівна","input":["Сєвєрова Єлєна Станіславівна","Єлєна Станіславівна Сєвєрова","Єлєна Сєвєрова"]}},"source":"VULYK","estate":{"25":[{"space_unclear":false,"costs":"","costs_comment":"","address_hidden":false,"region_hidden":true,"space_comment":"","space_hidden":false,"space":"48.7","address":"","region":"","costs_rent_comment":"","space_comment_unclear":false,"space_units":"м²","costs_rent":""}]},"intro":{"declaration_year":"2015"}}