{"income":{"5":{"family_comment":"","value":"467438.55","family":"","comment":""},"6":{"family_comment":"","value":"269318.05","family":"","comment":""},"7":{"family_comment":"","value":"","source_name":"","family":"","comment":""},"8":{"family_comment":"","value":"","family":"","comment":""},"9":{"value":"","comment_unclear":false,"family_comment":"","family":"","comment":"","family_comment_unclear":false},"10":{"family_comment":"","value":"","family":"","comment":""},"11":{"family_comment":"","value":"198120.5","family":"","comment":""},"12":{"family_comment":"","value":"","family":"","comment":""},"13":{"family_comment":"","value":"","family":"","comment":""},"14":{"family_comment":"","value":"","family":"","comment":""},"15":{"family_comment":"","value":"","family":"","comment":""},"16":{"family_comment":"","value":"","family":"","comment":""},"17":{"family_comment":"","value":"","family":"","comment":""},"18":{"family_comment":"","value":"","family":"","comment":""},"19":{"value":"","family_comment":"","value_unclear":false,"family_unclear":false,"family":"","comment":""},"20":{"value":"","family_comment":"","comment_unclear":false,"comment_hidden":false,"family_unclear":false,"value_unclear":false,"family_comment_unclear":false,"family_comment_hidden":false,"comment":"","family":""}},"vehicle":{"35":[{"brand_info":"1329 куб. см.","sum":"182526","brand":"Toyota Yaris","sum_comment":"","year":"2012","sum_hidden":false,"brand_info_hidden":false,"brand_info_unclear":false,"year_unclear":false,"sum_rent_comment":"","sum_rent":""},{"brand_info":"спадщина за законом 2004 року","sum":"","brand":"ВАЗ 2101","sum_comment":"","year":"1971","sum_rent_comment":"","sum_rent":""}]},"id":"vulyk_106_115","declaration":{"additional_info_text":"","notfull_lostpages":"","date":"2016-03-28T00:00:00","notfull":"","additional_info":"","url":"http://static.declarations.com.ua/declarations/chosen_ones/judges_batch/2254_lukmanova_olha_mykolaivna.pdf"},"liabilities":{"54":{"sum_foreign_comment":"","sum":"706.86","sum_comment":"АТ СК АХ Страхування","sum_comment_unclear":true,"sum_hidden":false,"sum_comment_hidden":false,"sum_foreign":""},"55":{"sum_foreign_comment":"","sum":"","sum_foreign":"","sum_comment":"","sum_hidden":false},"56":{"sum_foreign_comment":"","sum":"","sum_comment":"","sum_hidden":false,"sum_comment_hidden":false,"sum_unclear":false,"sum_foreign":""},"57":{"sum_foreign_comment":"","sum":"","sum_comment":"","sum_hidden":false,"sum_comment_hidden":false,"sum_foreign":""},"58":{"sum_foreign_comment":"","sum":"","sum_comment":"","sum_hidden":false,"sum_comment_hidden":false,"sum_foreign":""},"59":{"sum_foreign_comment":"","sum":"","sum_comment":"","sum_foreign":""},"60":{"sum_foreign_comment":"","sum":"","sum_comment":"","sum_hidden":false,"sum_comment_hidden":false,"sum_foreign":""},"61":{"sum_foreign_comment":"","sum":"","sum_comment":"","sum_foreign":""},"62":{"sum_foreign_comment":"","sum":"","sum_comment":"","sum_comment_hidden":false,"sum_unclear":false,"sum_foreign":""},"63":{"sum_foreign_comment":"","sum":"","sum_comment":"","sum_foreign":""},"64":{"sum_foreign_comment":"","sum":"","sum_comment":"","sum_foreign":""}},"ft_src":"Toyota Yaris\n182526\n1329 куб. см.\n2012\nспадщина за законом 2004 року\n1971\nВАЗ 2101\n20.4\nсвідотцтво про право на спадщину за законом 28.12.2004. витяг з Держреєстру 04.07.2014, договір дарування 16.05.2015, витяг з Держреєстру 16.05.2015\n72.3\n72.9\n2015\n269318.05\n198120.5\n467438.55\n1329 куб. см.\n2012\n182526\nToyota Yaris\nспадщина за законом 2004 року\nВАЗ 2101\n1971\n72.3\nсвідотцтво про право на спадщину за законом 28.12.2004. витяг з Держреєстру 04.07.2014, договір дарування 16.05.2015, витяг з Держреєстру 16.05.2015\n20.4\n72.9\nЛукманова Ольга Миколаївна\nОльга Миколаївна Лукманова\nОльга Лукманова\nЛукманова Ольга Миколаївна\nЛукманова Ольга Миколаївна\nОльга\nЛукманова\nДніпропетровська область\nАпеляційний адміністративний суд\nсуддя дніпропетровського апеляційного адміністративного суду\nМиколаївна\nАТ СК АХ Страхування\n706.86\n269318.05\n467438.55\n198120.5\n2015\nАТ СК АХ Страхування\n706.86\nМиколаївна\nЛукманова\nОльга\nЛукманова Ольга Миколаївна\nОльга Миколаївна Лукманова\nОльга Лукманова\nЛукманова Ольга Миколаївна\nДніпропетровська область\nАпеляційний адміністративний суд\nсуддя дніпропетровського апеляційного адміністративного суду\nЛукманова Ольга Миколаївна","general":{"inn":"","name":"Ольга","last_name":"Лукманова","patronymic":"Миколаївна","inn_hidden":true,"family_raw":"","inn_unclear":false,"post":{"region_unclear":false,"post":"суддя дніпропетровського апеляційного адміністративного суду","post_hidden":false,"region":"Дніпропетровська область","office":"Апеляційний адміністративний суд","office_unclear":false},"full_name":"Лукманова Ольга Миколаївна","addresses":[{"place_district":"","place_address_hidden":true,"place_city":"","place_address":"","place_district_hidden":true,"place_city_type":"","place_city_hidden":true,"place_city_type_hidden":true,"place_hidden":true,"place":""}],"full_name_suggest":{"output":"Лукманова Ольга Миколаївна","input":["Лукманова Ольга Миколаївна","Ольга Миколаївна Лукманова","Ольга Лукманова"]},"name_unclear":false},"source":"VULYK","estate":{"24":[{"space_unclear":false,"costs":"","costs_comment":"","address_hidden":true,"region_hidden":true,"space_comment":"свідотцтво про право на спадщину за законом 28.12.2004. витяг з Держреєстру 04.07.2014, договір дарування 16.05.2015, витяг з Держреєстру 16.05.2015","space_hidden":false,"space":"72.3","address":"","region":"","costs_rent_comment":"","space_comment_unclear":false,"space_comment_hidden":false,"space_units":"м²","costs_rent":""}],"25":[{"costs":"","costs_comment":"","address_hidden":true,"region_hidden":true,"space_comment":"","space":"72.9","address":"","region":"","costs_rent_comment":"","space_comment_unclear":false,"space_units":"м²","costs_rent":""}],"27":[{"space_hidden":false,"costs":"","costs_comment":"","address_hidden":true,"region_hidden":true,"space_comment":"","space":"20.4","address":"","region":"","costs_rent_comment":"","space_units":"м²","costs_rent":""}]},"intro":{"declaration_year":"2015","isnotdeclaration":""}}