{"id":"vulyk_84_164","ft_src":"Кіровоградська область\nм. Кіровоград\n65.4\nм. Кіровоград\n64.3\nКіровоградська область\n2014\n205880\n12180\n218060\n205880\n218060\n12180\nсуддя кіровського районного суд м. кіровограда\nЗагальний місцевий суд\nКіровоградська область\nВолодимирівна\nМохонько\nМохонько Віталіна Володимирівна\nВіталіна Володимирівна Мохонько\nВіталіна Мохонько\nМохонько Віталіна Володимирівна\nВіталіна\nКіровоград\nКіровоградська область\nМохонько Віталіна Володимирівна\n8326\n65.4\nКіровоградська область\nм. Кіровоград\nм. Кіровоград\n64.3\nКіровоградська область\n2014\n8326\nВолодимирівна\nКіровоградська область\nКіровоград\nМохонько\nКіровоградська область\nсуддя кіровського районного суд м. кіровограда\nЗагальний місцевий суд\nМохонько Віталіна Володимирівна\nМохонько Віталіна Володимирівна\nВіталіна Володимирівна Мохонько\nВіталіна Мохонько\nМохонько Віталіна Володимирівна\nВіталіна","estate":{"25":[{"address":"м. Кіровоград","space_units":"м²","space_hidden":false,"space_comment":"","region_hidden":false,"costs_comment":"","address_hidden":false,"costs":"","address_unclear":false,"costs_rent_comment_unclear":false,"costs_comment_unclear":false,"costs_rent_comment":"","space":"65.4","region_unclear":false,"region":"Кіровоградська область","costs_rent":""},{"costs":"","address":"м. Кіровоград","space_units":"м²","costs_rent_comment":"","space":"64.3","space_comment":"","region_hidden":false,"costs_comment":"","region":"Кіровоградська область","costs_rent":""}]},"source":"VULYK","income":{"5":{"family_comment":"","family":"","comment":"","value_unclear":false,"family_unclear":false,"comment_unclear":false,"value":"218060"},"6":{"family_comment":"","comment_unclear":false,"value":"205880","family":"","comment":""},"7":{"family":"","family_comment":"","value":"","comment":"","source_name":""},"8":{"family_comment":"","value":"","family":"","comment":""},"9":{"family_comment":"","value":"","family":"","comment":"","value_unclear":false},"10":{"family_comment":"","value":"12180","family":"","comment":"","value_unclear":false},"11":{"family_comment":"","value":"","family":"","comment":""},"12":{"family_comment":"","value":"","family":"","comment":""},"13":{"family_comment":"","value":"","family":"","comment":""},"14":{"family_comment":"","value":"","family":"","comment":""},"15":{"family_comment":"","value":"","family":"","comment":""},"16":{"family_comment":"","value":"","family":"","comment":""},"17":{"family_comment":"","value":"","family":"","comment":"","value_unclear":false},"18":{"family_comment":"","value":"","family":"","comment":"","value_unclear":false},"19":{"family_comment":"","value":"","family":"","comment":""},"20":{"family_comment":"","family":"","comment":"","value_unclear":false,"family_unclear":false,"comment_unclear":false,"value":""}},"general":{"inn":"","inn_unclear":false,"last_name":"Мохонько","full_name_suggest":{"input":["Мохонько Віталіна Володимирівна","Віталіна Володимирівна Мохонько","Віталіна Мохонько"],"output":"Мохонько Віталіна Володимирівна"},"full_name":"Мохонько Віталіна Володимирівна","patronymic":"Володимирівна","inn_hidden":true,"name":"Віталіна","post":{"post_hidden":false,"office":"Загальний місцевий суд","region_hidden":false,"post":"суддя кіровського районного суд м. кіровограда","candidate":"","region_unclear":false,"region":"Кіровоградська область","office_hidden":false,"post_unclear":false,"office_unclear":false},"family_raw":"","addresses":[{"place_city_type_hidden":false,"place_district_hidden":false,"place_address_unclear":false,"place":"Кіровоградська область","place_city":"Кіровоград","place_unclear":false,"place_city_type_unclear":false,"place_city_type":"Місто","place_city_hidden":false,"place_city_unclear":false,"place_district":"","place_district_unclear":false,"place_address":"","place_address_hidden":true,"place_hidden":false}]},"liabilities":{"54":{"sum_comment":"","sum_foreign_comment":"","sum_foreign":"","sum":"","sum_comment_hidden":false},"55":{"sum_comment":"","sum_foreign_comment":"","sum_foreign":"","sum":""},"56":{"sum_comment":"","sum_foreign_comment":"","sum_foreign":"","sum":"8326"},"57":{"sum_comment":"","sum_foreign_comment":"","sum_foreign":"","sum":"","sum_comment_hidden":false},"58":{"sum_comment":"","sum_foreign_comment":"","sum_foreign":"","sum":"","sum_comment_hidden":false},"59":{"sum_comment":"","sum_foreign_comment":"","sum_foreign":"","sum":""},"60":{"sum_comment":"","sum_foreign_comment":"","sum_foreign":"","sum":""},"61":{"sum_comment":"","sum_foreign_comment":"","sum_foreign":"","sum":""},"62":{"sum_comment":"","sum_foreign_comment":"","sum_foreign":"","sum":""},"63":{"sum_comment":"","sum_foreign_comment":"","sum_foreign":"","sum":"","sum_comment_hidden":false},"64":{"sum_comment":"","sum_foreign_comment":"","sum_foreign":"","sum":"","sum_comment_hidden":false}},"declaration":{"notfull_lostpages":"","additional_info_text":"","additional_info":"","date":"2015-03-24T00:00:00","notfull":"","url":"http://static.declarations.com.ua/declarations/chosen_ones/judges_batch/2578_mokhonko_vitalina_volodymyrivna.pdf"},"intro":{"isnotdeclaration":"","declaration_year_unclear":false,"declaration_year":"2014"}}