{"income":{"5":{"value":"169271","family_comment":"","value_unclear":false,"family_unclear":false,"family":"","comment":""},"6":{"family_comment":"","family_unclear":false,"value":"157091","family":"","comment":""},"7":{"source_name_unclear":false,"value":"","family_comment":"","source_name":"","family":"","comment":""},"8":{"family_comment":"","value":"","family":"","comment":""},"9":{"value":"","family_comment":"","comment_hidden":false,"family_unclear":false,"family":"","comment":"","family_comment_hidden":false},"10":{"family_comment":"","value":"12180","family":"","comment":""},"11":{"family_comment":"","value":"","family":"","comment":""},"12":{"family_comment":"","value":"","family":"","comment":""},"13":{"family_comment":"","value":"","family":"","comment":""},"14":{"family_comment":"","value":"","family":"","comment":""},"15":{"family_comment":"","value":"","family":"","comment":""},"16":{"family_comment":"","value":"","family":"","comment":""},"17":{"family_comment":"","value":"","family":"","comment":""},"18":{"family_comment":"","value":"","family":"","comment":""},"19":{"family_comment":"","value":"","family":"","comment":""},"20":{"value":"","value_unclear":false,"comment_hidden":false,"family_comment":"","comment_unclear":false,"comment":"","family":""}},"id":"vulyk_108_147","declaration":{"additional_info_text":"","notfull_lostpages":"","date":"2016-01-26T00:00:00","notfull":"","additional_info":"","url":"http://static.declarations.com.ua/declarations/chosen_ones/judges_batch/2446_bashmakov_ievhen_anatoliiovych_2015.pdf"},"liabilities":{"54":{"sum_foreign_comment":"","sum":"","sum_foreign":"","sum_comment":"","sum_hidden":false},"55":{"sum_foreign_comment":"","sum":"","sum_comment":"","sum_foreign":""},"56":{"sum_foreign_comment":"","sum":"19031","sum_comment":"","sum_unclear":false,"sum_foreign":""},"57":{"sum_foreign_comment":"","sum":"","sum_comment":"","sum_hidden":false,"sum_comment_hidden":false,"sum_foreign":""},"58":{"sum_foreign_comment":"","sum_comment":"","sum":"","sum_comment_hidden":false,"sum_foreign":""},"59":{"sum_foreign_comment":"","sum":"","sum_comment":"","sum_unclear":false,"sum_foreign":""},"60":{"sum_foreign_comment":"","sum_comment":"","sum":"","sum_comment_hidden":false,"sum_foreign":""},"61":{"sum_foreign_comment":"","sum_comment":"","sum":"","sum_comment_hidden":false,"sum_foreign":""},"62":{"sum_foreign_comment":"","sum":"","sum_comment":"","sum_foreign":""},"63":{"sum_foreign_comment":"","sum":"","sum_comment":"","sum_hidden":false,"sum_comment_hidden":false,"sum_unclear":false,"sum_foreign":""},"64":{"sum_foreign_comment":"","sum":"","sum_comment":"","sum_comment_hidden":false,"sum_unclear":false,"sum_foreign":""}},"ft_src":"м. Дніпропетровськ\n817\nДніпропетровська область\nм. Дніпропетровськ\n239.1\nДніпропетровська область\n2015\n157091\n12180\n169271\n817\nДніпропетровська область\nм. Дніпропетровськ\n239.1\nДніпропетровська область\nм. Дніпропетровськ\nЖовтневий районний суд м. Дніпропетровська\nДніпропетровська область\nсуддя жовтневого районного суду м. дніпропетровська\nБашмаков\nДніпропетровськ\nДніпропетровська область\nБашмаков Євген Анатолійович\nЄвген Анатолійович Башмаков\nЄвген Башмаков\nБашмаков Євген Анатолійович\nЄвген\nБашмаков Євген Анатолійович\nАнатолійович\n19031\n157091\n169271\n12180\n2015\n19031\nБашмаков\nАнатолійович\nДніпропетровська область\nДніпропетровськ\nДніпропетровська область\nсуддя жовтневого районного суду м. дніпропетровська\nЖовтневий районний суд м. Дніпропетровська\nБашмаков Євген Анатолійович\nБашмаков Євген Анатолійович\nЄвген Анатолійович Башмаков\nЄвген Башмаков\nБашмаков Євген Анатолійович\nЄвген","general":{"inn_hidden":true,"inn":"","inn_unclear":false,"post":{"post_unclear":false,"post":"суддя жовтневого районного суду м. дніпропетровська","office_hidden":false,"region":"Дніпропетровська область","office":"Жовтневий районний суд м. Дніпропетровська","office_unclear":false},"name":"Євген","full_name":"Башмаков Євген Анатолійович","family_raw":"","addresses":[{"place_address":"","place_district_hidden":false,"place_city_type":"Місто","place_city_hidden":false,"place_address_unclear":false,"place_city_type_hidden":false,"place_city":"Дніпропетровськ","place":"Дніпропетровська область","place_district":"","place_unclear":false,"place_hidden":false,"place_address_hidden":true}],"last_name":"Башмаков","full_name_suggest":{"output":"Башмаков Євген Анатолійович","input":["Башмаков Євген Анатолійович","Євген Анатолійович Башмаков","Євген Башмаков"]},"patronymic":"Анатолійович"},"source":"VULYK","estate":{"23":[{"region_unclear":false,"space_unclear":false,"costs":"","costs_comment":"","address_hidden":false,"region_hidden":false,"space_comment":"","space":"817","address":"м. Дніпропетровськ","region":"Дніпропетровська область","address_unclear":false,"space_units_unclear":false,"space_units":"м²","space_units_hidden":false,"costs_rent":"","costs_rent_comment":""}],"24":[{"space_hidden":false,"costs":"","costs_comment":"","address_hidden":false,"region_hidden":false,"space_comment":"","space":"239.1","address":"м. Дніпропетровськ","region":"Дніпропетровська область","costs_rent_comment":"","space_units":"м²","costs_rent":""}]},"intro":{"declaration_year":"2015","isnotdeclaration":"","declaration_year_hidden":false}}