{"income":{"5":{"value":"218902","family_comment":"","value_unclear":false,"family_hidden":false,"value_hidden":false,"family_unclear":false,"family":"2934","comment":"","family_comment_unclear":false},"6":{"family_comment":"","family_unclear":false,"value":"218902","family":"","comment":""},"7":{"source_name_unclear":false,"value":"","family_comment":"","source_name":"","family":"","comment":"","source_name_hidden":false},"8":{"family_comment":"","value":"","family":"","comment":""},"9":{"family_comment":"","family_unclear":false,"value":"","family":"","comment":""},"10":{"family_comment":"","value":"","family":"","comment":""},"11":{"family_comment":"","value":"","family":"","comment":""},"12":{"family_comment":"","value":"","family":"2934","comment":""},"13":{"family_comment":"","value":"","family":"","comment":""},"14":{"family_comment":"","value":"","family":"","comment":""},"15":{"family_comment":"","value":"","family":"","comment":""},"16":{"value":"","value_unclear":false,"value_hidden":false,"family_comment":"","family":"","comment":""},"17":{"family_comment":"","value":"","family":"","comment":""},"18":{"family_comment":"","value":"","family":"","comment":""},"19":{"family_comment":"","value":"","family":"","comment":""},"20":{"value":"","family_comment":"","value_unclear":false,"comment_hidden":false,"family_hidden":false,"family":"","value_hidden":false,"family_unclear":false,"comment_unclear":false,"comment":"","family_comment_unclear":false}},"vehicle":{"35":[{"year_hidden":false,"brand_info":"","sum_rent_comment":"","sum_rent_hidden":false,"year":"2008","sum_hidden":false,"brand_info_hidden":false,"brand_info_unclear":false,"year_unclear":false,"sum_rent":"","sum":"","brand":"Mitsubishi Outlander","sum_comment":"","brand_unclear":false,"brand_hidden":false}]},"id":"vulyk_62_158","declaration":{"additional_info_text":"","notfull_lostpages":"","date":"2015-03-30T00:00:00","notfull":"","additional_info":"","url":"http://static.declarations.com.ua/declarations/chosen_ones/mega_batch/silantieva_elina_ievheniivna.pdf"},"liabilities":{"54":{"sum_foreign_comment":"","sum":"","sum_comment":"","sum_hidden":false,"sum_comment_hidden":false,"sum_foreign":""},"55":{"sum_foreign_comment":"","sum":"","sum_comment":"","sum_hidden":false,"sum_comment_hidden":false,"sum_unclear":false,"sum_foreign":""},"56":{"sum_foreign_comment":"","sum":"35600","sum_comment":"","sum_hidden":false,"sum_unclear":false,"sum_foreign":""},"57":{"sum_foreign_comment":"","sum":"","sum_comment":"","sum_hidden":false,"sum_comment_hidden":false,"sum_unclear":false,"sum_foreign":""},"58":{"sum_foreign_comment":"","sum_foreign_hidden":false,"sum_comment":"","sum_hidden":false,"sum_comment_hidden":false,"sum_unclear":false,"sum":"","sum_foreign":""},"59":{"sum_foreign_comment":"","sum":"","sum_comment":"","sum_foreign":""},"60":{"sum_foreign_comment":"","sum_foreign_hidden":false,"sum_comment":"","sum_hidden":false,"sum_comment_hidden":false,"sum_unclear":false,"sum":"","sum_foreign":""},"61":{"sum_foreign_comment":"","sum_foreign_hidden":false,"sum_comment":"","sum_hidden":false,"sum":"","sum_foreign":""},"62":{"sum_foreign_comment":"","sum":"","sum_comment":"","sum_unclear":false,"sum_foreign":""},"63":{"sum_foreign_comment":"","sum":"","sum_comment":"","sum_hidden":false,"sum_comment_hidden":false,"sum_unclear":false,"sum_foreign":""},"64":{"sum_foreign_comment":"","sum":"","sum_comment":"","sum_comment_unclear":false,"sum_hidden":false,"sum_comment_hidden":false,"sum_foreign":""}},"ft_src":"35600\nголова фрунзенського районного суду м. харкова\nХарківська область\nЗагальний місцевий суд\nЕліна\nСілантьєва С. Є\nДитина\nОлійник С. О\nПодружжя\nЄвгеніївна\nСілантьєва Еліна Євгеніївна\nЕліна Євгеніївна Сілантьєва\nЕліна Сілантьєва\nСілантьєва Еліна Євгеніївна\nСілантьєва Еліна Євгеніївна\nСілантьєва\nMitsubishi Outlander\n2008\n.1375\n24.5\n100.1\n2014\n218902\n2934\n218902\n2934\nMitsubishi Outlander\n2008\n.1375\n24.5\n100.1\nДитина\nСілантьєва С. Є\nПодружжя\nОлійник С. О\nСілантьєва Еліна Євгеніївна\nЕліна Євгеніївна Сілантьєва\nЕліна Сілантьєва\nСілантьєва Еліна Євгеніївна\nСілантьєва Еліна Євгеніївна\nЕліна\nЄвгеніївна\nЗагальний місцевий суд\nголова фрунзенського районного суду м. харкова\nХарківська область\nСілантьєва\n35600\n218902\n2934\n218902\n2934\n2014\n35600\nДитина\nСілантьєва С. Є\nОлійник С. О\nПодружжя\nЄвгеніївна\nСілантьєва\nЕліна\nСілантьєва Еліна Євгеніївна\nЕліна Євгеніївна Сілантьєва\nЕліна Сілантьєва\nСілантьєва Еліна Євгеніївна\nХарківська область\nголова фрунзенського районного суду м. харкова\nЗагальний місцевий суд\nСілантьєва Еліна Євгеніївна\nMitsubishi Outlander\n2008\n218902\n2934\n2934\n218902\n24.5\n100.1\n.1375\n2014","general":{"inn":"","name":"Еліна","inn_unclear":false,"family":[{"inn":"","inn_hidden":true,"relations_unclear":false,"relations_hidden":false,"relations_other":"","relations":"Дитина","name_hidden":false,"inn_unclear":false,"family_name":"Сілантьєва С. Є","name_unclear":true},{"inn":"","inn_hidden":true,"relations_hidden":false,"family_name":"Олійник С. О","relations_other":"","relations":"Подружжя","name_hidden":false,"name_unclear":true}],"inn_hidden":true,"family_raw":"","last_name":"Сілантьєва","post":{"post_unclear":false,"post":"голова фрунзенського районного суду м. харкова","post_hidden":false,"region":"Харківська область","region_hidden":false,"office":"Загальний місцевий суд","office_hidden":false,"office_unclear":false},"full_name_suggest":{"output":"Сілантьєва Еліна Євгеніївна","input":["Сілантьєва Еліна Євгеніївна","Еліна Євгеніївна Сілантьєва","Еліна Сілантьєва"]},"full_name":"Сілантьєва Еліна Євгеніївна","addresses":[{"place_city_type_unclear":false,"place_address":"","place_district_hidden":false,"place_city_type":"","place_address_hidden":false,"place_address_unclear":false,"place_city_type_hidden":true,"place":"","place_district":"","place_unclear":false,"place_city":"","place_city_unclear":false,"place_hidden":true,"place_city_hidden":true,"place_district_unclear":false}],"patronymic":"Євгеніївна","last_name_unclear":false,"name_unclear":false},"source":"VULYK","estate":{"23":[{"region_unclear":false,"space_unclear":false,"costs":"","costs_comment":"","costs_hidden":false,"address_hidden":false,"region_hidden":true,"space_comment":"","space":".1375","address":"","region":"","address_unclear":false,"space_units_unclear":false,"space_comment_unclear":false,"space_units":"га","space_units_hidden":false,"costs_rent":"","costs_rent_comment":""}],"25":[{"region_unclear":false,"space_hidden":false,"costs":"","costs_comment":"","costs_hidden":false,"address_hidden":false,"region_hidden":true,"space_comment":"","space_unclear":false,"space":"24.5","address":"","region":"","costs_rent_comment":"","space_units":"м²","costs_rent":""},{"costs":"","costs_comment":"","costs_hidden":false,"address_hidden":false,"region_hidden":false,"space_comment":"","space":"100.1","address":"","region":"","costs_rent_comment":"","space_comment_unclear":false,"space_units":"м²","costs_rent":""}]},"intro":{"declaration_year":"2014","isnotdeclaration":"","declaration_year_unclear":false,"declaration_year_hidden":false}}