{"income":{"5":{"family_comment":"","value":"357708.28","family":"","comment":""},"6":{"family_comment":"","value":"270345.31","value_unclear":false,"family":"","comment":""},"7":{"value":"","family_comment":"","source_name":"","family":"","comment":"","source_name_hidden":false},"8":{"family_comment":"","value":"","family":"","comment":""},"9":{"family_comment":"","value":"62226.18","family":"","comment":""},"10":{"family_comment":"","value":"13398","family":"","comment":""},"11":{"family_comment":"","value":"","comment_hidden":false,"family":"","comment":""},"12":{"family_comment":"","value":"","family":"","comment":""},"13":{"family_comment":"","value":"","family":"","comment":""},"14":{"family_comment":"","value":"","family":"","comment":""},"15":{"value":"","family_comment":"","value_unclear":false,"family_unclear":false,"family":"","comment":""},"16":{"family_comment":"","value":"","family":"","comment":""},"17":{"family_comment":"","value":"","family":"","comment":""},"18":{"family_comment":"","value":"","family":"","comment":""},"19":{"family_comment":"","value":"","family":"","comment":""},"20":{"family_comment":"","value":"11738.84","comment_unclear":false,"family":"","comment":"пенсія"}},"id":"vulyk_104_47","banks":{"45":[{"sum_foreign_comment":"","sum_units":"UAH","sum_comment":"","sum_hidden":false,"sum_foreign_units":"UAH","sum_foreign_hidden":false,"sum_comment_hidden":false,"sum_unclear":false,"sum":"969270.7","sum_foreign":""}]},"declaration":{"date":"2016-03-21T00:00:00","additional_info_text":"","additional_info":"","url":"http://static.declarations.com.ua/declarations/chosen_ones/judges_batch/1845_ropii_liudmyla_mykolaivna_2015.pdf"},"liabilities":{"54":{"sum_foreign_comment":"","sum_foreign_hidden":false,"sum_comment":"","sum_hidden":false,"sum_comment_hidden":false,"sum_unclear":false,"sum":"","sum_foreign":""},"55":{"sum_foreign_comment":"","sum":"","sum_comment":"","sum_foreign":""},"56":{"sum_foreign_comment":"","sum":"","sum_comment":"","sum_unclear":false,"sum_foreign":""},"57":{"sum_foreign_comment":"","sum_foreign_hidden":false,"sum_comment":"","sum_comment_unclear":false,"sum_comment_hidden":false,"sum":"","sum_foreign":""},"58":{"sum_foreign_comment":"","sum":"","sum_comment":"","sum_unclear":false,"sum_foreign":""},"59":{"sum_foreign_comment":"","sum":"","sum_comment":"","sum_foreign":""},"60":{"sum_foreign_comment":"","sum_foreign_hidden":false,"sum_comment":"","sum_comment_hidden":false,"sum":"","sum_foreign":""},"61":{"sum_foreign_comment":"","sum":"","sum_comment":"","sum_foreign":""},"62":{"sum_foreign_comment":"","sum":"","sum_comment":"","sum_foreign":""},"63":{"sum_foreign_comment":"","sum":"","sum_comment":"","sum_foreign":""},"64":{"sum_foreign_comment":"","sum":"","sum_comment":"","sum_foreign":""}},"ft_src":"Ропій Людмила Миколаївна\nсуддя\nм. Київ\nАпеляційний господарський суд\nЛюдмила\nРопій Людмила Миколаївна\nЛюдмила Миколаївна Ропій\nЛюдмила Ропій\nРопій Людмила Миколаївна\nРопій\nМиколаївна\n62226.18\n13398\nпенсія\n11738.84\n357708.28\n270345.31\n969270.7\n61.5\n2015\n270345.31\n62226.18\n13398\n357708.28\nпенсія\n11738.84\n969270.7\n2015\nРопій Людмила Миколаївна\nЛюдмила Миколаївна Ропій\nЛюдмила Ропій\nРопій Людмила Миколаївна\nРопій Людмила Миколаївна\nМиколаївна\nЛюдмила\nРопій\nАпеляційний господарський суд\nсуддя\nм. Київ\n270345.31\nпенсія\n11738.84\n357708.28\n62226.18\n13398\n61.5\nРопій\nМиколаївна\nсуддя\nАпеляційний господарський суд\nм. Київ\nРопій Людмила Миколаївна\nРопій Людмила Миколаївна\nЛюдмила Миколаївна Ропій\nЛюдмила Ропій\nРопій Людмила Миколаївна\nЛюдмила\n61.5\n969270.7\n2015","general":{"inn":"","inn_hidden":true,"last_name":"Ропій","post":{"region":"м. Київ","region_unclear":false,"post":"суддя","office_unclear":false,"office":"Апеляційний господарський суд"},"name":"Людмила","full_name":"Ропій Людмила Миколаївна","family_raw":"","addresses":[{"place_district":"","place_city_hidden":true,"place_city":"","place_city_type_hidden":true,"place_district_hidden":true,"place_city_type":"","place_address_hidden":true,"place_address":"","place_hidden":true,"place":""}],"full_name_suggest":{"output":"Ропій Людмила Миколаївна","input":["Ропій Людмила Миколаївна","Людмила Миколаївна Ропій","Людмила Ропій"]},"patronymic":"Миколаївна"},"source":"VULYK","estate":{"25":[{"costs":"","costs_comment":"","address_hidden":false,"region_hidden":true,"space_comment":"","space":"61.5","address":"","costs_unclear":false,"region":"","costs_rent_comment":"","space_comment_unclear":false,"space_units":"м²","costs_rent":""}]},"intro":{"declaration_year":"2015","isnotdeclaration":""}}