{"income":{"5":{"family_comment":"","value":"250123.54","family":"","comment":""},"6":{"family_comment":"","value":"249310.83","family":"","comment":""},"7":{"family_comment":"","value":"","source_name":"","family":"","comment":""},"8":{"family_comment":"","value":"","family":"","comment":""},"9":{"value":"","comment_unclear":false,"family_comment":"","family":"","comment":"","family_comment_unclear":false},"10":{"family_comment":"","value":"","family":"","comment":""},"11":{"family_comment":"","value":"","family":"","comment":""},"12":{"family_comment":"","value":"","family":"","comment":""},"13":{"family_comment":"","value":"","family":"","comment":""},"14":{"family_comment":"","value":"","family":"","comment":""},"15":{"family_comment":"","value":"","family":"","comment":""},"16":{"family_comment":"","value":"","family":"","comment":""},"17":{"family_comment":"","value":"","family":"","comment":""},"18":{"family_comment":"","value":"","family":"","comment":""},"19":{"value":"","family_comment":"","value_unclear":false,"family_unclear":false,"family":"","comment":""},"20":{"value":"812.71","family_comment":"","value_unclear":false,"comment_hidden":false,"family_comment_hidden":false,"family_unclear":false,"family_comment_unclear":false,"comment_unclear":false,"comment":"","family":""}},"vehicle":{"35":[{"brand_info":"","sum_rent_comment":"","brand":"Nissan Teana","sum_comment":"","year":"2008","sum_hidden":false,"brand_info_hidden":true,"brand_info_unclear":false,"year_unclear":false,"sum":"","sum_rent":""}],"37":[{"brand_info":"","sum_rent_comment":"","brand":"Колібрі КМ-400","sum_comment":"","year":"2013","brand_info_hidden":true,"sum":"","sum_rent":""}],"40":[{"year_hidden":false,"brand_info":"","sum_rent_comment":"","brand":"Skoda Fabia","sum_comment":"","year":"2008","brand_hidden":false,"brand_info_hidden":true,"brand_info_unclear":false,"sum":"","sum_rent":""},{"brand_info":"","sum_rent_comment":"","brand":"BMW 315","sum_comment":"","year":"1982","brand_info_hidden":false,"sum":"","sum_rent":""}]},"id":"vulyk_106_139","declaration":{"additional_info_text":"","notfull_lostpages":"","date":"2016-03-25T00:00:00","notfull":"","additional_info":"","url":"http://static.declarations.com.ua/declarations/chosen_ones/judges_batch/2278_herashchenko_ihor_volodymyrovych.pdf"},"liabilities":{"54":{"sum_foreign_comment":"","sum":"","sum_comment":"","sum_comment_unclear":false,"sum_hidden":false,"sum_comment_hidden":false,"sum_foreign":""},"55":{"sum_foreign_comment":"","sum":"","sum_hidden":false,"sum_comment":"","sum_foreign":""},"56":{"sum_foreign_comment":"","sum":"","sum_comment":"","sum_hidden":false,"sum_comment_hidden":false,"sum_unclear":false,"sum_foreign":""},"57":{"sum_foreign_comment":"","sum":"","sum_comment":"","sum_hidden":false,"sum_comment_hidden":false,"sum_foreign":""},"58":{"sum_foreign_comment":"","sum":"","sum_comment":"","sum_hidden":false,"sum_comment_hidden":false,"sum_foreign":""},"59":{"sum_foreign_comment":"","sum":"","sum_comment":"","sum_foreign":""},"60":{"sum_foreign_comment":"","sum":"","sum_comment":"","sum_hidden":false,"sum_comment_hidden":false,"sum_foreign":""},"61":{"sum_foreign_comment":"","sum":"","sum_comment":"","sum_foreign":""},"62":{"sum_foreign_comment":"","sum":"","sum_comment":"","sum_comment_hidden":false,"sum_unclear":false,"sum_foreign":""},"63":{"sum_foreign_comment":"","sum":"","sum_comment":"","sum_foreign":""},"64":{"sum_foreign_comment":"","sum":"","sum_comment":"","sum_foreign":""}},"ft_src":"заступник голови донецького апеляційного адміністративного суду, суддя\nДонецька область\nАпеляційний адміністративний суд\nІгор\nГеращенко І. В\nПодружжя\nГеращенко Р. І\nДитина\nВолодимирович\nГеращенко Ігор Володимирович\nІгор Володимирович Геращенко\nІгор Геращенко\nГеращенко Ігор Володимирович\nГеращенко Ігор Володимирович\nГеращенко\nNissan Teana\n2008\n2013\nКолібрі КМ-400\nSkoda Fabia\n2008\n1982\nBMW 315\n27\n26\n26\n92\n2015\n249310.83\n250123.54\n812.71\nКолібрі КМ-400\n2013\n2008\nSkoda Fabia\nBMW 315\n1982\n2008\nNissan Teana\n26\n26\n27\n92\nГеращенко Ігор Володимирович\nІгор Володимирович Геращенко\nІгор Геращенко\nГеращенко Ігор Володимирович\nГеращенко Ігор Володимирович\nПодружжя\nГеращенко І. В\nДитина\nГеращенко Р. І\nІгор\nГеращенко\nДонецька область\nАпеляційний адміністративний суд\nзаступник голови донецького апеляційного адміністративного суду, суддя\nВолодимирович\n249310.83\n812.71\n250123.54\n2015\nГеращенко І. В\nПодружжя\nГеращенко Р. І\nДитина\nВолодимирович\nГеращенко\nІгор\nГеращенко Ігор Володимирович\nІгор Володимирович Геращенко\nІгор Геращенко\nГеращенко Ігор Володимирович\nДонецька область\nАпеляційний адміністративний суд\nзаступник голови донецького апеляційного адміністративного суду, суддя\nГеращенко Ігор Володимирович\n2008\nNissan Teana\nКолібрі КМ-400\n2013\nSkoda Fabia\n2008\nBMW 315\n1982\n812.71\n250123.54\n249310.83\n27\n92\n26\n26\n2015","general":{"inn":"","name":"Ігор","inn_unclear":false,"family":[{"inn":"","inn_hidden":true,"relations_unclear":false,"relations_hidden":false,"relations_other":"","relations":"Подружжя","name_hidden":true,"family_name":"Геращенко І. В","name_unclear":false},{"inn":"","relations":"Дитина","relations_unclear":false,"family_name":"Геращенко Р. І","inn_hidden":false,"relations_other":"","name_hidden":false,"name_unclear":false}],"inn_hidden":true,"family_raw":"","last_name":"Геращенко","post":{"region_unclear":false,"region":"Донецька область","post":"заступник голови донецького апеляційного адміністративного суду, суддя","office":"Апеляційний адміністративний суд","office_unclear":false,"post_hidden":false},"full_name":"Геращенко Ігор Володимирович","addresses":[{"place_district":"","place_city_hidden":true,"place_city":"","place_city_type_hidden":true,"place_district_hidden":true,"place_city_type":"","place_address_hidden":true,"place_address":"","place_hidden":true,"place":""}],"patronymic":"Володимирович","full_name_suggest":{"output":"Геращенко Ігор Володимирович","input":["Геращенко Ігор Володимирович","Ігор Володимирович Геращенко","Ігор Геращенко"]},"name_unclear":false},"source":"VULYK","estate":{"25":[{"costs":"","costs_comment":"","address_hidden":true,"region_hidden":true,"space_comment":"","space":"92","address":"","region":"","costs_rent_comment":"","space_comment_unclear":false,"space_units":"м²","costs_rent":""}],"27":[{"space_hidden":false,"costs":"","costs_comment":"","address_hidden":true,"region_hidden":true,"space_comment":"","space":"26","address":"","region":"","costs_rent_comment":"","space_units":"м²","costs_rent":""},{"costs_rent":"","region":"","costs":"","costs_rent_comment":"","costs_comment":"","space_comment":"","space_units":"м²","space":"26","address":""}],"31":[{"space_unclear":false,"address_hidden":true,"region_hidden":true,"space_comment":"","space_hidden":false,"space":"27","address":"","region":"","costs_property":"","costs_rent_comment":"","space_comment_unclear":false,"space_units":"м²","costs_property_comment":"","costs_rent":""}]},"intro":{"declaration_year":"2015","isnotdeclaration":""}}