{"income":{"5":{"value":"235710","value_unclear":false,"comment_hidden":false,"family_hidden":false,"value_hidden":false,"family_comment":"","family":"","comment":""},"6":{"value":"218593","value_unclear":false,"comment_hidden":false,"family_hidden":false,"value_hidden":false,"family_comment":"","family_comment_hidden":false,"comment":"","family":""},"7":{"family_comment":"","value":"","source_name":"","family":"","comment":""},"8":{"family_comment":"","value":"","family":"","comment":""},"9":{"family_comment":"","value":"4","family":"","comment":""},"10":{"value":"13398","value_unclear":false,"family_hidden":false,"family_comment":"","family":"","comment":""},"11":{"family_comment":"","value":"","family":"","comment":""},"12":{"family_comment":"","value":"","family":"","comment":""},"13":{"family_comment":"","value":"","family":"","comment":""},"14":{"family_comment":"","value":"","family":"","comment":""},"15":{"family_comment":"","value":"","comment_unclear":false,"family":"","comment":""},"16":{"family_comment":"","value":"","family":"","comment":""},"17":{"family_comment":"","value":"","family":"","comment":""},"18":{"family_comment":"","value":"","family":"","comment":""},"19":{"family_comment":"","value":"","family":"","comment":""},"20":{"family_comment":"","value":"3715","family":"","comment":"","family_comment_hidden":false}},"vehicle":{"35":[{"brand_info":"1586 куб. см., 82/5600 кВт","sum":"","brand":"Suzuki SX4 Classic","sum_comment":"","brand_unclear":false,"year":"2014","brand_info_hidden":false,"sum_rent_comment":"","sum_rent":""}]},"id":"vulyk_79_29","declaration":{"date":"2015-03-30T00:00:00","additional_info_text":"","additional_info":"","url":"http://static.declarations.com.ua/declarations/chosen_ones/judges_batch/2034_barannyk_nataliia_petrivna.pdf"},"liabilities":{"54":{"sum_foreign_comment":"","sum_comment_hidden":false,"sum":"6424","sum_comment":"","sum_foreign":""},"55":{"sum_foreign_comment":"","sum":"","sum_comment":"","sum_foreign":""},"56":{"sum_foreign_comment":"","sum":"24600","sum_hidden":false,"sum_comment":"","sum_foreign":""},"57":{"sum_foreign_comment":"","sum":"300","sum_comment":"","sum_comment_unclear":false,"sum_hidden":false,"sum_comment_hidden":false,"sum_foreign":""},"58":{"sum_foreign_comment":"","sum":"600","sum_comment":"","sum_comment_unclear":false,"sum_hidden":false,"sum_comment_hidden":false,"sum_unclear":false,"sum_foreign":""},"59":{"sum_foreign_comment":"","sum":"","sum_comment":"","sum_foreign":""},"60":{"sum_foreign_comment":"","sum_comment_hidden":false,"sum":"","sum_comment":"","sum_foreign":""},"61":{"sum_foreign_comment":"","sum":"","sum_comment":"","sum_foreign":""},"62":{"sum_foreign_comment":"","sum":"","sum_comment":"","sum_foreign":""},"63":{"sum_foreign_comment":"","sum":"","sum_comment":"","sum_unclear":false,"sum_foreign":""},"64":{"sum_foreign_comment":"","sum":"","sum_comment":"","sum_unclear":false,"sum_foreign":""}},"ft_src":"300\n6424\n600\n24600\nсуддя дніпропетровського апеляційного адміністративного суду\nДніпропетровська область\nАпеляційний адміністративний суд\nНаталія\nДитина\nПетрівна\nБаранник Наталія Петрівна\nНаталія Петрівна Баранник\nНаталія Баранник\nБаранник Наталія Петрівна\nБаранник Наталія Петрівна\nБаранник\n2014\nSuzuki SX4 Classic\n1586 куб. см., 82/5600 кВт\n2\n49.7\n2014\n218593\n4\n13398\n235710\n3715\nSuzuki SX4 Classic\n1586 куб. см., 82/5600 кВт\n2014\n2\n49.7\nДитина\nБаранник Наталія Петрівна\nНаталія Петрівна Баранник\nНаталія Баранник\nБаранник Наталія Петрівна\nБаранник Наталія Петрівна\nНаталія\nБаранник\nАпеляційний адміністративний суд\nДніпропетровська область\nсуддя дніпропетровського апеляційного адміністративного суду\nПетрівна\n600\n6424\n300\n24600\n218593\n3715\n235710\n4\n13398\n2014\n600\n300\n24600\n6424\nДитина\nПетрівна\nБаранник\nНаталія\nБаранник Наталія Петрівна\nНаталія Петрівна Баранник\nНаталія Баранник\nБаранник Наталія Петрівна\nДніпропетровська область\nАпеляційний адміністративний суд\nсуддя дніпропетровського апеляційного адміністративного суду\nБаранник Наталія Петрівна\n2014\nSuzuki SX4 Classic\n1586 куб. см., 82/5600 кВт\n4\n13398\n3715\n235710\n218593\n49.7\n2\n2014","general":{"inn":"","name":"Наталія","last_name_hidden":false,"family":[{"inn":"","inn_hidden":false,"relations_hidden":false,"family_name":"","relations_other":"","relations":"Дитина","name_hidden":true,"name_unclear":false}],"patronymic":"Петрівна","inn_hidden":true,"family_raw":"","inn_unclear":true,"post":{"post_unclear":false,"post":"суддя дніпропетровського апеляційного адміністративного суду","post_hidden":false,"region":"Дніпропетровська область","region_hidden":false,"office":"Апеляційний адміністративний суд","office_hidden":false,"office_unclear":false},"full_name":"Баранник Наталія Петрівна","addresses":[{"place_district":"","place_city_hidden":true,"place_city":"","place_city_type_hidden":false,"place_district_hidden":false,"place_city_type":"","place_address_hidden":false,"place_address":"","place_hidden":true,"place":""}],"last_name":"Баранник","full_name_suggest":{"output":"Баранник Наталія Петрівна","input":["Баранник Наталія Петрівна","Наталія Петрівна Баранник","Наталія Баранник"]}},"source":"VULYK","estate":{"23":[{"costs":"","costs_comment":"","costs_hidden":false,"address_hidden":false,"region_hidden":true,"space_comment":"","space":"2","address":"","region":"","costs_rent_comment":"","costs_rent_hidden":false,"space_comment_hidden":false,"space_comment_unclear":false,"costs_rent_comment_hidden":false,"space_units":"га","costs_comment_hidden":false,"costs_rent":""}],"25":[{"space_unclear":false,"costs":"","costs_rent_unclear":false,"costs_comment":"","address_hidden":false,"region_hidden":true,"space_comment":"","space_hidden":false,"space":"49.7","address":"","costs_rent_comment_unclear":false,"region":"","costs_rent_comment":"","costs_unclear":false,"space_units":"м²","costs_rent":""}]},"intro":{"declaration_year":"2014"}}