{"id":"vulyk_109_107","ft_src":"310 S, надувний човен, 310 см\n2013\nBark BT\n.0535\n17.79\n17.79\n2015\n33958.15\n178048.12\n33958.15\n178048.12\n310 S, надувний човен, 310 см\n2013\nBark BT\n2015\nСоловйов Кирило Володимирович\nКирило Володимирович Соловйов\nКирило Соловйов\nСоловйов Кирило Володимирович\nКирило\nПодружжя\nСоловйова Надія Сергіївна 11. 11. 1974\nДитина\nСоловйов Андрій Кирилович 12. 10. 2002\nСоловйов Кирило Володимирович\nВолодимирович\nГосподарський місцевий суд\nХерсонська область\nсуддя господарського суду херсонської області\nСоловйов\n3468.65\n3468.66\n178048.12\n33958.15\n178048.12\n33958.15\n.0535\n17.79\n17.79\n3468.65\n3468.66\nПодружжя\nСоловйова Надія Сергіївна 11. 11. 1974\nДитина\nСоловйов Андрій Кирилович 12. 10. 2002\nВолодимирович\nСоловйов\nКирило\nСоловйов Кирило Володимирович\nКирило Володимирович Соловйов\nКирило Соловйов\nСоловйов Кирило Володимирович\nХерсонська область\nГосподарський місцевий суд\nсуддя господарського суду херсонської області\nСоловйов Кирило Володимирович","estate":{"23":[{"address":"","space_units":"га","costs_rent_unclear":false,"costs_comment":"","space_unclear":false,"region_hidden":true,"space_comment":"","address_hidden":false,"costs":"","costs_rent_comment":"","space":".0535","region":"","costs_rent":""}],"25":[{"address":"","space_units":"м²","space_hidden":false,"space_unclear":false,"region_hidden":true,"costs_comment":"","space_comment":"","address_hidden":false,"space":"17.79","costs_rent_comment":"","costs":"","region":"","space_units_hidden":false,"costs_rent":""}],"31":[{"costs_property_comment":"","address":"","space_units":"м²","space_hidden":false,"space_comment":"","region_hidden":true,"costs_property":"","region":"","address_hidden":false,"costs_rent_comment":"","space":"17.79","space_units_hidden":false,"costs_rent":""}]},"vehicle":{"37":[{"sum_comment":"","brand_info":"310 S, надувний човен, 310 см","sum":"","sum_rent_comment":"","year":"2013","brand":"Bark BT","sum_rent":""}]},"source":"VULYK","income":{"5":{"family_comment":"","value":"178048.12","family":"33958.15","comment":""},"6":{"family_comment":"","value":"178048.12","family":"33958.15","comment":""},"7":{"source_name_hidden":false,"family_comment":"","comment":"","family":"","comment_hidden":false,"value":"","source_name":""},"8":{"family_comment":"","family_hidden":false,"value":"","family":"","comment":""},"9":{"family_comment":"","family":"","comment":"","value_unclear":false,"family_unclear":false,"value":""},"10":{"family_comment":"","value":"","family":"","comment":""},"11":{"family_comment":"","value":"","family":"","comment":""},"12":{"family_comment":"","value":"","family":"","comment":""},"13":{"family_comment":"","value":"","family":"","comment":""},"14":{"family_comment":"","value":"","family":"","comment":""},"15":{"family_comment":"","value":"","family":"","comment":""},"16":{"family_comment":"","value":"","family":"","comment":""},"17":{"family_comment":"","value":"","family":"","comment":""},"18":{"family_comment":"","value":"","family":"","comment":""},"19":{"family_comment":"","value":"","family":"","comment":""},"20":{"family_comment":"","family":"","comment":"","value_unclear":false,"family_hidden":false,"value":""}},"general":{"family_raw":"","name":"Кирило","full_name_suggest":{"input":["Соловйов Кирило Володимирович","Кирило Володимирович Соловйов","Кирило Соловйов"],"output":"Соловйов Кирило Володимирович"},"patronymic":"Володимирович","inn_hidden":true,"addresses":[{"place_city_type_hidden":true,"place_city_type":"","place_city_hidden":true,"place_hidden":true,"place_district":"","place_district_hidden":true,"place":"","place_address":"","place_address_hidden":false,"place_city":""}],"inn":"","inn_unclear":false,"last_name":"Соловйов","full_name":"Соловйов Кирило Володимирович","family":[{"inn":"","family_name":"Соловйова Надія Сергіївна 11. 11. 1974","relations_hidden":false,"name_unclear":false,"relations":"Подружжя","inn_hidden":true,"name_hidden":false,"relations_other":""},{"inn":"","family_name":"Соловйов Андрій Кирилович 12. 10. 2002","relations_other":"","name_unclear":false,"inn_hidden":false,"name_hidden":false,"relations":"Дитина"}],"post":{"office":"Господарський місцевий суд","post":"суддя господарського суду херсонської області","office_unclear":false,"region_hidden":false,"region":"Херсонська область","office_hidden":false,"region_unclear":false},"name_hidden":false},"liabilities":{"54":{"sum_comment":"","sum_hidden":false,"sum":"","sum_foreign_comment":"","sum_foreign":"","sum_unclear":false,"sum_comment_hidden":false},"55":{"sum_comment":"","sum_comment_unclear":false,"sum_foreign_comment":"","sum":"","sum_foreign":""},"56":{"sum_comment":"","sum_foreign_comment":"","sum_foreign":"","sum":"3468.65"},"57":{"sum_comment":"","sum_foreign_comment":"","sum_foreign":"","sum":"","sum_comment_hidden":false},"58":{"sum_comment":"","sum_foreign_comment":"","sum_foreign":"","sum":"","sum_comment_hidden":false},"59":{"sum_comment":"","sum_foreign_comment":"","sum_foreign":"","sum":""},"60":{"sum_comment":"","sum_foreign_comment":"","sum_foreign":"","sum":""},"61":{"sum_comment":"","sum_foreign_comment":"","sum_foreign":"","sum":""},"62":{"sum_comment":"","sum_foreign_comment":"","sum_foreign":"","sum":"3468.66"},"63":{"sum_comment":"","sum_foreign_comment":"","sum_foreign":"","sum":""},"64":{"sum_comment":"","sum_foreign_comment":"","sum_foreign":"","sum":""}},"declaration":{"notfull_lostpages":"","additional_info_text":"","additional_info":"","date":"2016-03-30T00:00:00","notfull":"","url":"http://static.declarations.com.ua/declarations/chosen_ones/judges_batch/2564_soloviov_kyrylo_volodymyrovych_2015.pdf"},"intro":{"isnotdeclaration":"","declaration_year":"2015"}}