{"income":{"5":{"value":"239663","family_comment":"","value_unclear":false,"family_unclear":false,"family":"19201","comment":""},"6":{"value":"226265","family_comment":"","value_unclear":false,"family_unclear":false,"family":"","comment":""},"7":{"family_comment":"","value":"","source_name":"","family":"","comment":""},"8":{"family_comment":"","value":"","family":"","comment":""},"9":{"family_comment":"","value":"","value_unclear":false,"family":"","comment":""},"10":{"family_comment":"","value":"13398","value_unclear":false,"family":"","comment":""},"11":{"family_comment":"","value":"","family":"","comment":""},"12":{"family_comment":"","value":"","family":"","comment":""},"13":{"family_comment":"","value":"","value_unclear":false,"family":"","comment":""},"14":{"family_comment":"","value":"","family":"","comment":""},"15":{"family_comment":"","value":"","family":"","comment":""},"16":{"family_comment":"","value":"","family":"","comment":""},"17":{"family_comment":"","value":"","family":"","comment":""},"18":{"family_comment":"","value":"","family":"","comment":""},"19":{"family_comment":"","value":"","family":"","comment":""},"20":{"family_comment":"","family_unclear":false,"value":"","family":"","comment":""}},"vehicle":{"35":[{"year_hidden":false,"brand_info":"3.2 л","sum_rent_comment":"","year":"2008","brand_info_unclear":false,"sum_rent":"","sum":"","brand":"Mazda CX-9","sum_comment":"","brand_unclear":false,"brand_hidden":false,"sum_comment_unclear":false}],"40":[{"brand_info":"","sum_rent_comment":"","brand":"BMW 525","sum_comment":"","brand_unclear":false,"year":"2005","brand_info_hidden":false,"brand_info_unclear":false,"year_unclear":false,"sum":"","sum_rent":""}]},"id":"vulyk_85_88","declaration":{"additional_info_text":"","notfull_lostpages":"","date":"2015-03-27T00:00:00","notfull":"","additional_info":"","url":"http://static.declarations.com.ua/declarations/chosen_ones/judges_batch/2691_ahieiev_oleksandr_volodymyrovych.pdf"},"liabilities":{"54":{"sum_foreign_comment":"","sum":"","sum_comment":"","sum_comment_unclear":false,"sum_foreign":""},"55":{"sum_foreign_comment":"","sum":"","sum_comment":"","sum_foreign":""},"56":{"sum_foreign_comment":"","sum":"","sum_comment":"","sum_unclear":false,"sum_foreign":""},"57":{"sum_foreign_comment":"","sum":"","sum_comment":"","sum_foreign":""},"58":{"sum_foreign_comment":"","sum_comment_hidden":false,"sum":"","sum_comment":"","sum_foreign":""},"59":{"sum_foreign_comment":"","sum":"","sum_comment":"","sum_foreign":""},"60":{"sum_foreign_comment":"","sum":"","sum_comment":"","sum_foreign":""},"61":{"sum_foreign_comment":"","sum":"","sum_comment":"","sum_foreign":""},"62":{"sum_foreign_comment":"","sum":"","sum_comment":"","sum_unclear":false,"sum_foreign":""},"63":{"sum_foreign_comment":"","sum":"","sum_comment":"","sum_unclear":false,"sum_foreign":""},"64":{"sum_foreign_comment":"","sum":"","sum_comment":"","sum_foreign":""}},"ft_src":"суддя апеляційного суду донецької області\nДонецька область\nЗагальний апеляційний суд\nОлександр\nАгєєва Н. Г\nПодружжя\nАгєєв Г. О\nДитина\nАгєєва М. О\nДитина\nВолодимирович\nАгєєв Олександр Володимирович\nОлександр Володимирович Агєєв\nОлександр Агєєв\nАгєєв Олександр Володимирович\nАгєєв\nАгєєв Олександр Володимирович\n3.2 л\nMazda CX-9\n2008\nBMW 525\n2005\n.25\n33.2\n40.1\n66.9\n2014\n226265\n13398\n19201\n239663\n3.2 л\nMazda CX-9\n2008\n2005\nBMW 525\n.25\n40.1\n66.9\n33.2\nАгєєв Олександр Володимирович\nОлександр Володимирович Агєєв\nОлександр Агєєв\nАгєєв Олександр Володимирович\nОлександр\nПодружжя\nАгєєва Н. Г\nДитина\nАгєєв Г. О\nДитина\nАгєєва М. О\nАгєєв Олександр Володимирович\nАгєєв\nЗагальний апеляційний суд\nсуддя апеляційного суду донецької області\nДонецька область\nВолодимирович\n226265\n239663\n19201\n13398\n2014\nАгєєва Н. Г\nПодружжя\nАгєєв Г. О\nДитина\nАгєєва М. О\nДитина\nВолодимирович\nАгєєв\nОлександр\nАгєєв Олександр Володимирович\nОлександр Володимирович Агєєв\nОлександр Агєєв\nАгєєв Олександр Володимирович\nсуддя апеляційного суду донецької області\nДонецька область\nЗагальний апеляційний суд\nАгєєв Олександр Володимирович\nMazda CX-9\n3.2 л\n2008\n2005\nBMW 525\n13398\n239663\n19201\n226265\n66.9\n.25\n40.1\n33.2\n2014","general":{"inn":"","name":"Олександр","last_name_hidden":false,"family":[{"inn":"","inn_hidden":false,"relations_unclear":false,"relations_hidden":false,"relations_other":"","relations":"Подружжя","name_hidden":false,"family_name":"Агєєва Н. Г","name_unclear":false},{"inn":"","relations":"Дитина","relations_other":"","inn_hidden":false,"family_name":"Агєєв Г. О","name_hidden":false,"name_unclear":false},{"inn":"","relations":"Дитина","relations_other":"","inn_hidden":false,"family_name":"Агєєва М. О","name_unclear":false}],"patronymic":"Володимирович","inn_hidden":true,"family_raw":"","last_name":"Агєєв","post":{"post_unclear":false,"post_hidden":false,"post":"суддя апеляційного суду донецької області","region":"Донецька область","office":"Загальний апеляційний суд"},"last_name_unclear":false,"full_name":"Агєєв Олександр Володимирович","addresses":[{"place_district":"","place_city_hidden":false,"place_city":"","place_city_type_hidden":false,"place_district_hidden":false,"place_city_type":"","place_address_hidden":false,"place_address":"","place_hidden":true,"place":""}],"full_name_suggest":{"output":"Агєєв Олександр Володимирович","input":["Агєєв Олександр Володимирович","Олександр Володимирович Агєєв","Олександр Агєєв"]}},"source":"VULYK","estate":{"23":[{"space_unclear":false,"costs":"","costs_comment":"","address_hidden":false,"region_hidden":true,"space_comment":"","space":".25","address":"","costs_comment_unclear":false,"costs_rent_comment_unclear":false,"region":"","costs_rent_comment":"","costs_unclear":false,"space_units":"га","costs_rent":""}],"24":[{"space_hidden":false,"costs":"","costs_comment":"","address_hidden":false,"region_hidden":true,"space_comment":"","space_unclear":false,"space":"40.1","address":"","region":"","costs_rent_comment":"","space_units":"м²","costs_rent":""}],"27":[{"costs":"","costs_comment":"","address_hidden":false,"region_hidden":true,"space_comment":"","space":"33.2","address":"","costs_comment_unclear":false,"region":"","costs_rent_comment":"","space_units":"м²","costs_rent":""}],"30":[{"space_unclear":false,"address_hidden":true,"region_hidden":true,"space_comment":"","space":"66.9","address":"","region":"","costs_property":"","costs_rent_comment":"","space_units":"м²","costs_property_comment":"","costs_rent":""}]},"intro":{"declaration_year":"2014","isnotdeclaration":""}}