{"income":{"5":{"value":"","family_comment":"","value_unclear":false,"family_hidden":true,"value_hidden":true,"family_unclear":false,"family":"","comment":"","family_comment_unclear":false},"6":{"family_comment":"","family_unclear":false,"value":"","family":"","comment":""},"7":{"source_name_unclear":false,"value":"","family_comment":"","source_name":"","family":"","comment":"","source_name_hidden":false},"8":{"family_comment":"","value":"","family":"","comment":""},"9":{"family_comment":"","family_unclear":false,"value":"","family":"","comment":""},"10":{"family_comment":"","value":"","family":"","comment":""},"11":{"family_comment":"","value":"","family":"","comment":""},"12":{"family_comment":"","value":"","family":"","comment":""},"13":{"family_comment":"","value":"","family":"","comment":""},"14":{"family_comment":"","value":"","family":"","comment":""},"15":{"family_comment":"","value":"","family":"","comment":""},"16":{"value":"","value_unclear":false,"value_hidden":false,"family_comment":"","family":"","comment":""},"17":{"family_comment":"","value":"","family":"","comment":""},"18":{"family_comment":"","value":"","family":"","comment":""},"19":{"family_comment":"","value":"","family":"","comment":""},"20":{"value":"","family_comment":"","value_unclear":false,"comment_hidden":false,"family_hidden":false,"family":"33705","value_hidden":false,"family_unclear":true,"comment_unclear":false,"comment":"","family_comment_unclear":false}},"vehicle":{"40":[{"brand_info":"1994","sum":"","brand":"Subaru Forester","sum_comment":"","brand_unclear":false,"year":"2008","brand_hidden":false,"brand_info_hidden":false,"brand_info_unclear":false,"sum_rent_comment":"","sum_rent":""},{"brand_info":"1299","sum_rent_comment":"","brand":"ЗАЗ 110558","sum_comment":"","year":"2009","brand_hidden":false,"brand_info_unclear":false,"sum":"","sum_rent":""}]},"id":"vulyk_62_16","declaration":{"additional_info_text":"","notfull_lostpages":"","date":"2015-03-27T00:00:00","notfull":"","additional_info":"","url":"http://static.declarations.com.ua/declarations/chosen_ones/mega_batch/pankeieva_viktoriia_anatoliivna.pdf"},"liabilities":{"54":{"sum_foreign_comment":"","sum":"","sum_comment":"","sum_hidden":false,"sum_comment_hidden":false,"sum_foreign":""},"55":{"sum_foreign_comment":"","sum":"","sum_comment":"","sum_hidden":false,"sum_comment_hidden":false,"sum_unclear":false,"sum_foreign":""},"56":{"sum_foreign_comment":"","sum":"6230","sum_comment":"","sum_hidden":false,"sum_unclear":false,"sum_foreign":""},"57":{"sum_foreign_comment":"","sum":"","sum_comment":"","sum_hidden":false,"sum_comment_hidden":false,"sum_unclear":false,"sum_foreign":""},"58":{"sum_foreign_comment":"","sum_foreign_hidden":false,"sum_comment":"","sum_hidden":false,"sum_comment_hidden":false,"sum_unclear":false,"sum":"","sum_foreign":""},"59":{"sum_foreign_comment":"","sum":"","sum_comment":"","sum_foreign":""},"60":{"sum_foreign_comment":"","sum_foreign_hidden":false,"sum_comment":"","sum_hidden":false,"sum_comment_hidden":false,"sum_unclear":false,"sum":"3968","sum_foreign":""},"61":{"sum_foreign_comment":"","sum_foreign_hidden":false,"sum_comment":"","sum_hidden":false,"sum":"","sum_foreign":""},"62":{"sum_foreign_comment":"","sum":"10000","sum_comment":"","sum_unclear":false,"sum_foreign":""},"63":{"sum_foreign_comment":"","sum":"","sum_comment":"","sum_hidden":false,"sum_comment_hidden":false,"sum_unclear":false,"sum_foreign":""},"64":{"sum_foreign_comment":"","sum":"","sum_comment":"","sum_comment_unclear":false,"sum_hidden":false,"sum_comment_hidden":false,"sum_foreign":""}},"ft_src":"10000\n6230\n3968\nсуддя житомирського окружного адміністративного суду\nЖитомирська область\nАдміністративний місцевий суд\nВікторія\nПанкеєв С. М\nПодружжя\nПанкеєва С. С\nДитина\nАнатоліївна\nПанкеєва Вікторія Анатоліївна\nВікторія Анатоліївна Панкеєва\nВікторія Панкеєва\nПанкеєва Вікторія Анатоліївна\nПанкеєва Вікторія Анатоліївна\nПанкеєва\nSubaru Forester\n1994\n2008\n2009\nЗАЗ 110558\n1299\n949\n47.7\n2014\n33705\n1994\n2008\nSubaru Forester\n1299\n2009\nЗАЗ 110558\n949\n47.7\nПодружжя\nПанкеєв С. М\nДитина\nПанкеєва С. С\nПанкеєва Вікторія Анатоліївна\nВікторія Анатоліївна Панкеєва\nВікторія Панкеєва\nПанкеєва Вікторія Анатоліївна\nПанкеєва Вікторія Анатоліївна\nВікторія\nАнатоліївна\nАдміністративний місцевий суд\nсуддя житомирського окружного адміністративного суду\nЖитомирська область\nПанкеєва\n3968\n6230\n10000\n33705\n2014\n6230\n10000\n3968\nПодружжя\nПанкеєв С. М\nПанкеєва С. С\nДитина\nАнатоліївна\nПанкеєва\nВікторія\nПанкеєва Вікторія Анатоліївна\nВікторія Анатоліївна Панкеєва\nВікторія Панкеєва\nПанкеєва Вікторія Анатоліївна\nЖитомирська область\nсуддя житомирського окружного адміністративного суду\nАдміністративний місцевий суд\nПанкеєва Вікторія Анатоліївна\nSubaru Forester\n1994\n2008\n2009\n1299\nЗАЗ 110558\n33705\n47.7\n949\n2014","general":{"inn":"","name":"Вікторія","inn_unclear":true,"family":[{"inn":"","inn_hidden":true,"relations_unclear":false,"relations_hidden":false,"relations_other":"","relations":"Подружжя","name_hidden":false,"inn_unclear":false,"family_name":"Панкеєв С. М","name_unclear":false},{"inn":"","inn_hidden":true,"relations_hidden":false,"family_name":"Панкеєва С. С","relations_other":"","relations":"Дитина","name_hidden":false,"name_unclear":false}],"inn_hidden":true,"family_raw":"","last_name":"Панкеєва","post":{"post_unclear":false,"post":"суддя житомирського окружного адміністративного суду","post_hidden":false,"region":"Житомирська область","region_hidden":false,"office":"Адміністративний місцевий суд","office_hidden":false,"office_unclear":false},"full_name_suggest":{"output":"Панкеєва Вікторія Анатоліївна","input":["Панкеєва Вікторія Анатоліївна","Вікторія Анатоліївна Панкеєва","Вікторія Панкеєва"]},"full_name":"Панкеєва Вікторія Анатоліївна","addresses":[{"place_city_type_unclear":false,"place_address":"","place_district_hidden":false,"place_city_type":"","place_address_hidden":false,"place_address_unclear":false,"place_city_type_hidden":false,"place":"","place_district":"","place_unclear":false,"place_city":"","place_city_unclear":false,"place_hidden":true,"place_city_hidden":false,"place_district_unclear":false}],"patronymic":"Анатоліївна","last_name_unclear":false,"name_unclear":false},"source":"VULYK","estate":{"23":[{"region_unclear":false,"space_unclear":false,"costs":"","costs_comment":"","costs_hidden":false,"address_hidden":false,"region_hidden":true,"space_comment":"","space":"949","address":"","region":"","address_unclear":false,"space_units_unclear":false,"space_comment_unclear":false,"space_units":"м²","space_units_hidden":false,"costs_rent":"","costs_rent_comment":""}],"25":[{"region_unclear":true,"space_hidden":false,"costs":"","costs_comment":"","costs_hidden":false,"address_hidden":false,"region_hidden":true,"space_comment":"","space_unclear":false,"space":"47.7","address":"","region":"","costs_rent_comment":"","space_units":"м²","costs_rent":""}]},"intro":{"declaration_year":"2014","isnotdeclaration":"","declaration_year_unclear":false,"declaration_year_hidden":false}}