{"id":"vulyk_100_47","ft_src":"Т-25А\nтрактор, об'єм 1500 , потужність 26.6 , довжина 311.0\n1986\nотриманий в якості соціальної допомоги через управління соціального захисту\n2010\n1598 куб. см., 105 к. с., 75 кВт , 477 см\nVolkswagen Passat\nсмт Рокитне, вул. Прорізна, 1\n29\nКиївська область\nКримська Автономна Республіка\nм. Феодосія, смт Приморський, вул. Перемоги, 2\nу користуванні\n600\nсмт Рокитне, вул. Прорізна, 1\n136\nКиївська область\nгосподарська споруда\nсмт Рокитне, вул. Прорізна, 1\n82\nКиївська область\nсмт Рокитне, вул. Прорізна, 1\n1358\nКиївська область\nділянка\nсмт Рокитне, Рокитнянська сільрада\n1000\nКиївська область\n2014\n35172\n232684\n35172\n232684\n19139\nпенсія\nпенсія\n22967\nVolkswagen Passat\n1598 куб. см., 105 к. с., 75 кВт , 477 см\n2010\nотриманий в якості соціальної допомоги через управління соціального захисту\nтрактор, об'єм 1500 , потужність 26.6 , довжина 311.0\n1986\nТ-25А\n29\nКиївська область\nсмт Рокитне, вул. Прорізна, 1\nсмт Рокитне, Рокитнянська сільрада\n1000\nділянка\nКиївська область\nсмт Рокитне, вул. Прорізна, 1\n82\nгосподарська споруда\nКиївська область\n1358\nКиївська область\nсмт Рокитне, вул. Прорізна, 1\nм. Феодосія, смт Приморський, вул. Перемоги, 2\n600\nу користуванні\nКримська Автономна Республіка\n136\nсмт Рокитне, вул. Прорізна, 1\nКиївська область\nПодружжя\nЛитвин А. М. 21. 11. 1959\n2187406186\nВасильович\nКиївська область\nвул. Прорізна, 1, 09600\nСМТ\nРокитне\nЛитвин\nЛитвин Олександр Васильович\nОлександр Васильович Литвин\nОлександр Литвин\nЛитвин Олександр Васильович\nЛитвин Олександр Васильович\n2215600036\nОлександр\nЗагальний місцевий суд\nКиївська область\nголова рокитнянського районного суду київської області\n6451\n232684\n35172\n22967\n19139\nпенсія\nпенсія\n232684\n35172\n2014\n6451\n2187406186\nЛитвин А. М. 21. 11. 1959\nПодружжя\n2215600036\nСМТ\nвул. Прорізна, 1, 09600\nРокитне\nКиївська область\nВасильович\nЛитвин\nКиївська область\nЗагальний місцевий суд\nголова рокитнянського районного суду київської області\nЛитвин Олександр Васильович\nЛитвин Олександр Васильович\nОлександр Васильович Литвин\nОлександр Литвин\nЛитвин Олександр Васильович\nОлександр","estate":{"23":[{"address":"смт Рокитне, вул. Прорізна, 1","space_units":"м²","costs_comment":"","space_unclear":false,"region_hidden":false,"space_comment":"","address_hidden":false,"costs":"","address_unclear":false,"space_comment_unclear":false,"costs_comment_unclear":false,"costs_rent_comment":"","space":"1358","region":"Київська область","costs_rent":""}],"24":[{"address":"смт Рокитне, вул. Прорізна, 1","space_units":"м²","costs_comment":"","space_unclear":false,"region_hidden":false,"space_comment":"","address_hidden":false,"space":"136","space_comment_unclear":false,"costs_rent_comment":"","costs":"","region":"Київська область","costs_rent":""}],"26":[{"costs":"","address":"смт Рокитне, Рокитнянська сільрада","space_units":"м²","costs_rent_comment":"","space":"1000","space_comment":"ділянка","region_hidden":false,"costs_comment":"","region":"Київська область","address_hidden":false,"costs_rent":""}],"27":[{"address":"смт Рокитне, вул. Прорізна, 1","space_units":"м²","costs_comment":"","space_unclear":false,"region_hidden":false,"space_comment":"","address_hidden":false,"costs":"","address_unclear":false,"costs_rent_comment":"","space":"29","region":"Київська область","costs_rent":""}],"28":[{"costs":"","address":"смт Рокитне, вул. Прорізна, 1","space_units":"м²","costs_rent_comment":"","space":"82","space_comment":"господарська споруда","region_hidden":false,"costs_comment":"","region":"Київська область","address_hidden":false,"costs_rent":""}],"29":[{"costs_property_comment":"","address":"м. Феодосія, смт Приморський, вул. Перемоги, 2","space_units":"м²","space_unclear":false,"region_hidden":false,"costs_property":"","space_comment":"","address_hidden":false,"address_unclear":false,"costs_rent_comment":"у користуванні","space":"600","region_unclear":false,"region":"Кримська Автономна Республіка","costs_rent":""}]},"vehicle":{"39":[{"sum_comment":"","brand_unclear":false,"sum_rent":"","sum":"","sum_rent_comment":"","brand_hidden":false,"brand":"Т-25А","brand_info":"трактор, об'єм 1500 , потужність 26.6 , довжина 311.0","year":"1986"}],"40":[{"sum_comment":"отриманий в якості соціальної допомоги через управління соціального захисту","brand_info_hidden":false,"brand_info":"1598 куб. см., 105 к. с., 75 кВт , 477 см","sum":"","sum_rent_comment":"","year":"2010","brand":"Volkswagen Passat","sum_rent":"","brand_info_unclear":false}]},"source":"VULYK","income":{"5":{"family_comment":"","family":"35172","comment":"","value_unclear":false,"family_unclear":false,"value":"232684"},"6":{"family_comment":"","value":"232684","family":"35172","comment":"","value_unclear":false},"7":{"family_comment":"","comment":"","family":"","value_unclear":false,"value":"","source_name":""},"8":{"family_comment":"","value":"","family":"","comment":""},"9":{"family_comment":"","family":"","comment":"","value_unclear":false,"family_unclear":false,"value":""},"10":{"family_comment":"","comment_unclear":false,"value":"","family":"","comment":""},"11":{"family_comment":"","value":"","family":"","comment":""},"12":{"family_comment":"","value":"","family":"","comment":""},"13":{"family_comment":"","value":"","family":"","comment":"","value_unclear":false},"14":{"family_comment":"","value":"","family":"","comment":""},"15":{"family_comment":"","value":"","family":"","comment":""},"16":{"family_comment":"","value":"","family_unclear":false,"family":"","comment":""},"17":{"family_comment":"","value":"","family_unclear":false,"family":"","comment":""},"18":{"family_comment":"","value":"","family":"","comment":""},"19":{"family_comment":"","value":"","family":"","comment":""},"20":{"family":"19139","family_comment":"пенсія","comment":"пенсія","value_hidden":false,"value_unclear":false,"value":"22967","comment_unclear":false,"family_unclear":false,"family_hidden":false}},"general":{"inn":"2215600036","addresses":[{"place_city_type":"СМТ","place_city_type_hidden":false,"place_hidden":false,"place_city_hidden":false,"place_district_hidden":false,"place_district":"","place_city_unclear":false,"place":"Київська область","place_city":"Рокитне","place_address_hidden":false,"place_address":"вул. Прорізна, 1, 09600"}],"last_name":"Литвин","full_name":"Литвин Олександр Васильович","family":[{"inn":"2187406186","family_name":"Литвин А. М. 21. 11. 1959","name_unclear":false,"inn_hidden":false,"name_hidden":false,"relations":"Подружжя"}],"patronymic":"Васильович","inn_hidden":false,"name":"Олександр","post":{"post_hidden":false,"office":"Загальний місцевий суд","post":"голова рокитнянського районного суду київської області","office_unclear":false,"region_unclear":false,"region":"Київська область","post_unclear":false},"family_raw":"","full_name_suggest":{"input":["Литвин Олександр Васильович","Олександр Васильович Литвин","Олександр Литвин"],"output":"Литвин Олександр Васильович"}},"liabilities":{"54":{"sum_comment":"","sum":"","sum_foreign_comment":"","sum_foreign":"","sum_unclear":false,"sum_comment_hidden":false},"55":{"sum_comment":"","sum_foreign_comment":"","sum_foreign":"","sum":""},"56":{"sum_comment":"","sum_foreign_comment":"","sum_foreign":"","sum_unclear":false,"sum":"6451"},"57":{"sum_comment_unclear":false,"sum_comment":"","sum":"","sum_foreign_comment":"","sum_foreign":"","sum_unclear":false,"sum_comment_hidden":false},"58":{"sum_comment":"","sum":"","sum_foreign_comment":"","sum_foreign":"","sum_unclear":false,"sum_comment_hidden":false},"59":{"sum_comment":"","sum_foreign_comment":"","sum_foreign":"","sum":""},"60":{"sum_comment":"","sum_foreign_comment":"","sum_foreign":"","sum":"","sum_comment_hidden":false},"61":{"sum_comment":"","sum_foreign_comment":"","sum_foreign":"","sum":""},"62":{"sum_comment":"","sum_foreign_comment":"","sum_foreign":"","sum_unclear":false,"sum":""},"63":{"sum_comment":"","sum_foreign_comment":"","sum_foreign":"","sum":"","sum_comment_hidden":false},"64":{"sum_comment":"","sum_foreign_comment":"","sum_foreign":"","sum":"","sum_comment_hidden":false}},"declaration":{"notfull_lostpages":"","additional_info_text":"","additional_info":"","date":"2015-03-20T00:00:00","notfull":"","url":"http://static.declarations.com.ua/declarations/chosen_ones/judges_batch/4215_lytvyn_oleksandr_vasylovych.pdf"},"intro":{"declaration_year":"2014"}}