{"income":{"5":{"value":"249452","family_comment":"","comment_unclear":false,"family_unclear":false,"family":"23948","comment":""},"6":{"family_comment":"","value":"246276","family":"20810","comment":""},"7":{"source_name_unclear":false,"value":"","comment_unclear":false,"family_comment":"","source_name":"","family":"","comment":""},"8":{"family_comment":"","value":"","family":"","comment":""},"9":{"family_comment":"","value":"85","family":"","comment":""},"10":{"family_comment":"","value":"","family":"","comment":""},"11":{"family_comment":"","value":"","family":"","comment":""},"12":{"family_comment":"","value":"","family":"","comment":""},"13":{"family_comment":"","value":"","family":"","comment":""},"14":{"family_comment":"","value":"","family":"","comment":""},"15":{"family_comment":"","value":"","family":"","comment":""},"16":{"family_comment":"","family_unclear":false,"value":"","family":"","comment":""},"17":{"family_comment":"","value":"","family":"","comment":""},"18":{"family_comment":"","value":"","family":"","comment":""},"19":{"family_comment":"","value":"3091","family":"3138","comment":""},"20":{"value":"","family_comment":"","comment_unclear":false,"family_unclear":false,"family":"","comment":"","family_comment_unclear":false}},"vehicle":{"35":[{"brand_info":"1994 куб. см.","sum_rent_comment":"","brand":"Subaru Forester","sum_comment":"","brand_unclear":false,"year":"2008","brand_info_unclear":false,"sum":"","sum_rent":""}]},"id":"vulyk_107_76","banks":{"51":[{"sum_foreign_comment":"","sum_units":"UAH","sum_comment":"","sum_comment_unclear":false,"sum_foreign_units":"UAH","sum":"54","sum_unclear":false,"sum_foreign":""}]},"declaration":{"additional_info_text":"","notfull_lostpages":"","date":"2016-03-28T00:00:00","notfull":"","additional_info":"","url":"http://static.declarations.com.ua/declarations/chosen_ones/judges_batch/2055_shunko_hryhorii_oleksiiovych.pdf"},"liabilities":{"54":{"sum_foreign_comment":"","sum":"","sum_comment":"","sum_comment_unclear":false,"sum_comment_hidden":false,"sum_foreign":""},"55":{"sum_foreign_comment":"","sum":"","sum_comment":"","sum_foreign":""},"56":{"sum_foreign_comment":"","sum":"","sum_comment":"","sum_unclear":false,"sum_foreign":""},"57":{"sum_foreign_comment":"","sum":"","sum_comment":"","sum_comment_unclear":false,"sum_foreign":""},"58":{"sum_foreign_comment":"","sum":"","sum_comment":"","sum_comment_unclear":false,"sum_unclear":false,"sum_foreign":""},"59":{"sum_foreign_comment":"","sum":"","sum_comment":"","sum_unclear":false,"sum_foreign":""},"60":{"sum_foreign_comment":"","sum":"","sum_comment":"","sum_comment_unclear":false,"sum_comment_hidden":false,"sum_foreign":""},"61":{"sum_foreign_comment":"","sum":"","sum_comment":"","sum_foreign":""},"62":{"sum_foreign_comment":"","sum":"","sum_comment":"","sum_foreign":""},"63":{"sum_foreign_comment":"","sum":"","sum_comment":"","sum_foreign":""},"64":{"sum_foreign_comment":"","sum":"","sum_comment":"","sum_foreign":""}},"ft_src":"Шунько Григорій Олексійович\nсуддя апеляційного суду сумської області\nСумська область\nЗагальний апеляційний суд\nГригорій\nШунько Світлана Миколаївна\nПодружжя\nШунько Микола Григорович\nДитина\nШунько Григорій Олексійович\nГригорій Олексійович Шунько\nГригорій Шунько\nШунько Григорій Олексійович\nШунько\nОлексійович\n2008\nSubaru Forester\n1994 куб. см.\n54\n2015\n1994 куб. см.\n2008\nSubaru Forester\n54\n2015\nШунько\nПодружжя\nШунько Світлана Миколаївна\nДитина\nШунько Микола Григорович\nШунько Григорій Олексійович\nГригорій Олексійович Шунько\nГригорій Шунько\nШунько Григорій Олексійович\nГригорій\nОлексійович\nШунько Григорій Олексійович\nЗагальний апеляційний суд\nсуддя апеляційного суду сумської області\nСумська область\n246276\n20810\n249452\n23948\n85\n3091\n3138\n140\n18.7\n53.9\n.2195\n.1562\n2\n.2195\n.1562\n2\n140\n18.7\n53.9\n.2195\n.1562\n2\n140\n18.7\n53.9\n140\n18.7\n.2195\n.1562\n2\n53.9\nШунько Світлана Миколаївна\nПодружжя\nШунько Микола Григорович\nДитина\nШунько\nОлексійович\nсуддя апеляційного суду сумської області\nСумська область\nЗагальний апеляційний суд\nШунько Григорій Олексійович\nШунько Григорій Олексійович\nГригорій Олексійович Шунько\nГригорій Шунько\nШунько Григорій Олексійович\nГригорій\n20810\n246276\n85\n23948\n249452\n3138\n3091\n2008\n1994 куб. см.\nSubaru Forester\n3138\n3091\n85\n249452\n23948\n20810\n246276\n53.9\n.2195\n.1562\n2\n140\n18.7\n140\n18.7\n53.9\n.2195\n.1562\n2\n54\n2015","general":{"inn":"","inn_hidden":true,"last_name":"Шунько","post":{"post_unclear":false,"office":"Загальний апеляційний суд","post":"суддя апеляційного суду сумської області","region":"Сумська область"},"name":"Григорій","full_name":"Шунько Григорій Олексійович","family_raw":"","addresses":[{"place_district":"","place_city_hidden":true,"place_city":"","place_city_type_hidden":true,"place_district_hidden":true,"place_city_type":"","place_address_hidden":true,"place_address":"","place_hidden":true,"place":""}],"family":[{"inn":"","relations":"Подружжя","relations_other":"","inn_hidden":true,"family_name":"Шунько Світлана Миколаївна","name_hidden":true,"name_unclear":false},{"inn":"","relations":"Дитина","relations_other":"","inn_hidden":false,"family_name":"Шунько Микола Григорович","name_hidden":false,"name_unclear":false}],"full_name_suggest":{"output":"Шунько Григорій Олексійович","input":["Шунько Григорій Олексійович","Григорій Олексійович Шунько","Григорій Шунько"]},"patronymic":"Олексійович"},"source":"VULYK","estate":{"23":[{"costs":"","costs_comment":"","address_hidden":true,"region_hidden":true,"space_comment":"","space":".2195","address":"","region":"","costs_rent_comment":"","space_comment_unclear":false,"space_comment_hidden":false,"space_units":"га","costs_rent":""},{"costs_rent":"","region":"","costs":"","costs_rent_comment":"","costs_comment":"","address_hidden":false,"region_hidden":false,"space_comment":"","space_units":"га","space":".1562","address":""},{"costs_rent":"","region":"","costs":"","costs_rent_comment":"","costs_comment":"","space_comment":"","space_units":"га","space":"2","address":""}],"24":[{"space_hidden":false,"costs":"","costs_comment":"","address_hidden":true,"region_hidden":true,"space_comment":"","space":"140","address":"","region":"","costs_rent_comment":"","space_units":"м²","costs_rent":""},{"costs_rent":"","region":"","costs":"","costs_rent_comment":"","costs_comment":"","space_comment":"","space_units":"м²","space":"18.7","address":""}],"25":[{"space_hidden":false,"costs":"","costs_comment":"","address_hidden":true,"region_hidden":true,"space_comment":"","space_unclear":false,"space":"53.9","address":"","region":"","costs_rent_comment":"","space_units":"м²","costs_rent":""}],"29":[{"address_hidden":true,"region_hidden":true,"space_comment":"","space":".2195","address":"","region":"","costs_property":"","costs_rent_comment":"","costs_rent_hidden":false,"space_units":"га","costs_property_comment":"","costs_rent":""},{"costs_rent":"","region":"","costs_property":"","costs_rent_comment":"","costs_rent_hidden":false,"region_hidden":false,"space_comment":"","costs_property_comment":"","space_units":"га","space":".1562","address":""},{"costs_rent":"","region":"","costs_property":"","costs_rent_comment":"","space_comment":"","costs_property_comment":"","space_units":"га","space":"2","address":""}],"30":[{"address_hidden":true,"region_hidden":true,"space_comment":"","space":"140","address":"","region":"","costs_property":"","costs_rent_comment":"","space_comment_unclear":false,"space_units":"м²","costs_property_comment":"","costs_rent":""},{"costs_rent":"","costs_property":"","costs_rent_comment":"","space_comment":"","costs_property_comment":"","space_units":"м²","space":"18.7","address":""}],"31":[{"space_unclear":false,"address_hidden":true,"region_hidden":true,"space_comment":"","space_hidden":false,"space":"53.9","address":"","region":"","costs_property":"","costs_rent_comment":"","space_comment_unclear":false,"space_units":"м²","costs_property_comment":"","costs_rent":""}]},"intro":{"declaration_year":"2015","isnotdeclaration":""}}