{"income":{"5":{"value":"212839","family_comment":"","value_unclear":false,"comment_hidden":false,"family_hidden":false,"value_hidden":false,"family_unclear":false,"family_comment_hidden":false,"comment":"","family":"201300"},"6":{"value":"200659","family_comment":"","value_unclear":false,"family_hidden":false,"family_unclear":false,"family":"80000","comment":""},"7":{"source_name_unclear":false,"value":"","family_hidden":false,"family_comment":"","source_name":"","family":"12000","comment":"","source_name_hidden":false},"8":{"family_comment":"","value":"","family":"","comment":""},"9":{"value":"","value_unclear":false,"family_hidden":false,"family_comment":"","family":"","comment":""},"10":{"value":"","value_unclear":false,"family_hidden":false,"value_hidden":false,"family_comment":"","comment_unclear":false,"comment":"","family":"3300"},"11":{"family_comment":"","value":"","family":"100000","comment":""},"12":{"family_comment":"","value":"","family":"","comment":""},"13":{"family_comment":"","value":"","family":"","comment":""},"14":{"family_comment":"","value":"","family":"","comment":""},"15":{"family_comment":"","value":"","family_hidden":false,"comment":"","family":""},"16":{"value":"","value_unclear":false,"family_hidden":false,"family_comment":"","family":"","comment":""},"17":{"family_comment":"","value":"","family_hidden":false,"comment":"","family":""},"18":{"family_comment":"","value":"","value_unclear":false,"family":"","comment":""},"19":{"family_comment":"","value":"","family":"6000","comment":""},"20":{"value":"12180","family_comment":"","value_unclear":false,"family_hidden":false,"family_unclear":false,"comment_unclear":false,"comment":"","family":""}},"vehicle":{"35":[{"brand_info":"2400 куб. см.","sum_rent_comment":"","brand_info_unclear":false,"year":"2007","sum_rent_unclear":false,"brand_info_hidden":false,"sum_rent_comment_unclear":false,"sum_hidden":false,"sum_rent":"","sum":"","brand":"Chevrolet Captiva","sum_comment":"","brand_unclear":false,"brand_hidden":false}]},"id":"vulyk_72_153","declaration":{"additional_info_text":"","notfull_lostpages":"","date":"2015-04-10T00:00:00","notfull":"","additional_info":"","url":"http://static.declarations.com.ua/declarations/chosen_ones/epic_batch/ladychenko_serhii_volodymyrovych.pdf"},"liabilities":{"54":{"sum_foreign_comment":"","sum":"","sum_comment":"","sum_comment_hidden":false,"sum_unclear":false,"sum_foreign":""},"55":{"sum_foreign_comment":"","sum":"","sum_comment":"","sum_foreign":""},"56":{"sum_foreign_comment":"","sum":"","sum_hidden":false,"sum_comment":"","sum_foreign":""},"57":{"sum_foreign_comment":"","sum":"","sum_comment":"","sum_comment_unclear":false,"sum_hidden":false,"sum_comment_hidden":false,"sum_unclear":false,"sum_foreign":""},"58":{"sum_foreign_comment":"","sum":"","sum_comment":"","sum_comment_unclear":false,"sum_hidden":false,"sum_comment_hidden":false,"sum_unclear":false,"sum_foreign":""},"59":{"sum_foreign_comment":"","sum_foreign_hidden":false,"sum_comment":"","sum_foreign_unclear":false,"sum_comment_hidden":false,"sum":"","sum_foreign":""},"60":{"sum_foreign_comment":"","sum_foreign_hidden":false,"sum_comment":"","sum_hidden":false,"sum":"","sum_foreign":""},"61":{"sum_foreign_comment":"","sum_foreign_hidden":false,"sum_comment":"","sum_hidden":false,"sum":"","sum_foreign":""},"62":{"sum_foreign_comment":"","sum_foreign_hidden":false,"sum_comment":"","sum_hidden":false,"sum":"","sum_foreign":""},"63":{"sum_foreign_comment":"","sum_foreign_hidden":false,"sum_comment":"","sum_comment_unclear":false,"sum_hidden":false,"sum_comment_hidden":false,"sum_unclear":false,"sum":"","sum_foreign":""},"64":{"sum_foreign_comment":"","sum_foreign_hidden":false,"sum_comment":"","sum_hidden":false,"sum":"","sum_foreign":""}},"ft_src":"Луганська область\nсуддя голосіївського районного суду міста києва\nм. Київ\nЗагальний місцевий суд\nСергій\nЛадиченко А. В\nПодружжя\nЛадиченко Е. С\nДитина\nЛадиченко Т. С\nДитина\nВолодимирович\nЛадиченко\nЛадиченко Сергій Володимирович\nЛадиченко Сергій Володимирович\nСергій Володимирович Ладиченко\nСергій Ладиченко\nЛадиченко Сергій Володимирович\n2400 куб. см.\nChevrolet Captiva\n2007\nЛуганська область\nм. Антрацит, вул. Петраковського\n50\nм. Ровеньки, вул. Орджонікідзе\nЛуганська область\n100\nЛуганська область\nм. Ровеньки, вул. Орджонікідзе\n100\n2014\n80000\n200659\n100000\n3300\n12000\n201300\n212839\n6000\n12180\n2400 куб. см.\nChevrolet Captiva\n2007\n100\nЛуганська область\nм. Ровеньки, вул. Орджонікідзе\nЛуганська область\n100\nм. Ровеньки, вул. Орджонікідзе\nЛуганська область\nм. Антрацит, вул. Петраковського\n50\nПодружжя\nЛадиченко А. В\nДитина\nЛадиченко Е. С\nДитина\nЛадиченко Т. С\nЛадиченко Сергій Володимирович\nСергій Володимирович Ладиченко\nСергій Ладиченко\nЛадиченко Сергій Володимирович\nСергій\nЛадиченко Сергій Володимирович\nЛадиченко\nм. Київ\nЗагальний місцевий суд\nсуддя голосіївського районного суду міста києва\nВолодимирович\nЛуганська область\n12000\n200659\n80000\n12180\n212839\n201300\n3300\n100000\n6000\n2014\nЛадиченко А. В\nПодружжя\nЛадиченко Е. С\nДитина\nЛадиченко Т. С\nДитина\nВолодимирович\nЛадиченко\nЛадиченко Сергій Володимирович\nСергій Володимирович Ладиченко\nСергій Ладиченко\nЛадиченко Сергій Володимирович\nЛуганська область\nм. Київ\nЗагальний місцевий суд\nсуддя голосіївського районного суду міста києва\nЛадиченко Сергій Володимирович\nСергій\n2007\nChevrolet Captiva\n2400 куб. см.\n100000\n6000\n3300\n12180\n212839\n201300\n12000\n200659\n80000\nЛуганська область\nм. Антрацит, вул. Петраковського\n50\nм. Ровеньки, вул. Орджонікідзе\nЛуганська область\n100\nм. Ровеньки, вул. Орджонікідзе\nЛуганська область\n100\n2014","general":{"inn":"","name":"Сергій","patronymic_unclear":false,"family":[{"inn":"","inn_hidden":true,"relations_unclear":false,"relations_hidden":false,"relations_other":"","relations":"Подружжя","name_hidden":true,"inn_unclear":false,"family_name":"Ладиченко А. В","name_unclear":false},{"inn":"","inn_hidden":false,"relations_hidden":false,"family_name":"Ладиченко Е. С","relations_other":"","relations":"Дитина","name_hidden":false,"name_unclear":false},{"inn":"","inn_hidden":false,"relations_hidden":false,"family_name":"Ладиченко Т. С","relations_other":"","relations":"Дитина","name_hidden":false,"name_unclear":false}],"patronymic":"Володимирович","inn_hidden":true,"family_raw":"","inn_unclear":false,"post":{"post_unclear":false,"region_unclear":false,"post":"суддя голосіївського районного суду міста києва","candidate":"","office_hidden":false,"region":"м. Київ","post_hidden":false,"office":"Загальний місцевий суд","office_unclear":false,"region_hidden":false},"last_name_unclear":false,"full_name":"Ладиченко Сергій Володимирович","addresses":[{"place_city_type_hidden":false,"place_district_hidden":false,"place_city_type":"Місто","place_city_hidden":true,"place_address_unclear":false,"place_address":"","place":"Луганська область","place_district":"","place_unclear":false,"place_city":"","place_city_unclear":false,"place_hidden":false,"place_address_hidden":true,"place_district_unclear":false}],"last_name":"Ладиченко","patronymic_hidden":false,"full_name_suggest":{"output":"Ладиченко Сергій Володимирович","input":["Ладиченко Сергій Володимирович","Сергій Володимирович Ладиченко","Сергій Ладиченко"]},"name_unclear":false},"source":"VULYK","estate":{"24":[{"space_hidden":false,"costs":"","costs_comment":"","address_hidden":true,"region_hidden":false,"space_comment":"","space":"100","address":"м. Ровеньки, вул. Орджонікідзе","region":"Луганська область","address_unclear":false,"costs_rent_comment":"","space_units":"м²","costs_rent":""}],"30":[{"region_unclear":false,"space_unclear":false,"address_hidden":true,"region_hidden":false,"space_comment":"","space_hidden":false,"space":"100","address":"м. Ровеньки, вул. Орджонікідзе","region":"Луганська область","costs_property":"","costs_rent_comment":"","space_units":"м²","costs_property_comment":"","costs_rent":""}],"31":[{"space_unclear":false,"address_hidden":true,"region_hidden":false,"space_comment":"","space_units_hidden":false,"space_hidden":false,"space":"50","address":"м. Антрацит, вул. Петраковського","region":"Луганська область","address_unclear":false,"costs_rent_comment":"","costs_property":"","space_units":"м²","costs_property_comment":"","costs_rent":""}]},"intro":{"declaration_year":"2014","isnotdeclaration":"","declaration_year_unclear":false}}