{"id":"vulyk_109_138","ft_src":"1/2 ч\nЧернівецька область\nм. Чернівці, вул. Комарова, буд. 29-Б, кв. 72\n50\n1/2 ч\n50\n103005.82\n1\nДва аркуша № 5\n2015\nДва аркуша № 5\n1\n2015\nКовальчук Тетяна Іванівна\nТетяна Іванівна Ковальчук\nТетяна Ковальчук\nКовальчук Тетяна Іванівна\nТетяна\nПодружжя\nКовальчук Тетяна Іванівна\nІванівна\nГосподарський місцевий суд\nЧернівецька область\nсуддя господарського суду чернівецької області\nКовальчук\n187002.72\n54744\n2500\n199182.72\n63270\n12180\n6026\n1/2 ч\nм. Чернівці, вул. Комарова, буд. 29-Б, кв. 72\nЧернівецька область\n50\n50\n1/2 ч\n103005.82\n54744\n187002.72\n6026\n12180\n63270\n199182.72\n2500\nПодружжя\nІванівна\nКовальчук\nТетяна\nКовальчук Тетяна Іванівна\nТетяна Іванівна Ковальчук\nТетяна Ковальчук\nКовальчук Тетяна Іванівна\nЧернівецька область\nГосподарський місцевий суд\nсуддя господарського суду чернівецької області\nКовальчук Тетяна Іванівна","estate":{"25":[{"address":"","space_units":"м²","space_hidden":false,"space_unclear":false,"region_hidden":true,"costs_comment":"","space_comment":"1/2 ч","address_hidden":false,"space":"50","costs_rent_comment":"","costs":"","region":"","space_units_hidden":false,"costs_rent":""}],"31":[{"costs_property_comment":"","address":"м. Чернівці, вул. Комарова, буд. 29-Б, кв. 72","space_units":"м²","space_hidden":false,"space_comment":"1/2 ч","region_hidden":false,"costs_property":"","region":"Чернівецька область","address_hidden":false,"costs_rent_comment":"","space":"50","space_units_hidden":false,"costs_rent":""}]},"source":"VULYK","income":{"5":{"family_comment":"","value":"199182.72","family":"63270","comment":""},"6":{"family_comment":"","value":"187002.72","family":"54744","comment":""},"7":{"source_name_hidden":false,"family_comment":"","comment":"","family":"","comment_hidden":false,"value":"","source_name":""},"8":{"family_comment":"","family_hidden":false,"value":"","family":"","comment":""},"9":{"family_comment":"","family":"","comment":"","value_unclear":false,"family_unclear":false,"value":""},"10":{"family_comment":"","value":"12180","family":"6026","comment":""},"11":{"family_comment":"","value":"","family":"","comment":""},"12":{"family_comment":"","value":"","family":"2500","comment":""},"13":{"family_comment":"","value":"","family":"","comment":""},"14":{"family_comment":"","value":"","family":"","comment":""},"15":{"family_comment":"","value":"","family":"","comment":""},"16":{"family_comment":"","value":"","family":"","comment":""},"17":{"family_comment":"","value":"","family":"","comment":""},"18":{"family_comment":"","value":"","family":"","comment":""},"19":{"family_comment":"","value":"","family":"","comment":""},"20":{"family_comment":"","family":"","comment":"","value_unclear":false,"family_hidden":false,"value":""}},"banks":{"45":[{"sum_units":"UAH","sum_comment":"","sum_foreign_units":"UAH","sum":"103005.82","sum_units_hidden":false,"sum_foreign_comment":"","sum_foreign":"","sum_unclear":false,"sum_comment_hidden":false}]},"declaration":{"notfull_lostpages":"","additional_info_text":"Два аркуша № 5","additional_info":"1","date":"2016-03-12T00:00:00","notfull":"","url":"http://static.declarations.com.ua/declarations/chosen_ones/judges_batch/2595_kovalchuk_tetiana_ivanivna_2015.pdf"},"general":{"family_raw":"","name":"Тетяна","full_name_suggest":{"input":["Ковальчук Тетяна Іванівна","Тетяна Іванівна Ковальчук","Тетяна Ковальчук"],"output":"Ковальчук Тетяна Іванівна"},"patronymic":"Іванівна","inn_hidden":true,"addresses":[{"place_city_type_hidden":false,"place_city_type":"","place_city_hidden":false,"place_hidden":true,"place_district":"","place_district_hidden":false,"place":"","place_address":"","place_address_hidden":false,"place_city":""}],"inn":"","inn_unclear":false,"last_name":"Ковальчук","full_name":"Ковальчук Тетяна Іванівна","family":[{"inn":"","family_name":"","relations_hidden":false,"name_unclear":false,"relations":"Подружжя","inn_hidden":true,"name_hidden":true,"relations_other":""}],"post":{"office":"Господарський місцевий суд","post":"суддя господарського суду чернівецької області","office_unclear":false,"region_hidden":false,"region":"Чернівецька область","office_hidden":false,"region_unclear":false},"name_hidden":false},"liabilities":{"54":{"sum_comment":"","sum_hidden":false,"sum":"","sum_foreign_comment":"","sum_foreign":"","sum_unclear":false,"sum_comment_hidden":false},"55":{"sum_comment":"","sum_comment_unclear":false,"sum_foreign_comment":"","sum":"","sum_foreign":""},"56":{"sum_comment":"","sum_foreign_comment":"","sum_foreign":"","sum":""},"57":{"sum_comment":"","sum_foreign_comment":"","sum_foreign":"","sum":"","sum_comment_hidden":false},"58":{"sum_comment":"","sum_foreign_comment":"","sum_foreign":"","sum":"","sum_comment_hidden":false},"59":{"sum_comment":"","sum_foreign_comment":"","sum_foreign":"","sum":""},"60":{"sum_comment":"","sum_foreign_comment":"","sum_foreign":"","sum":""},"61":{"sum_comment":"","sum_foreign_comment":"","sum_foreign":"","sum":""},"62":{"sum_comment":"","sum_foreign_comment":"","sum_foreign":"","sum":""},"63":{"sum_comment":"","sum_foreign_comment":"","sum_foreign":"","sum":""},"64":{"sum_comment":"","sum_foreign_comment":"","sum_foreign":"","sum":""}},"intro":{"isnotdeclaration":"","declaration_year":"2015"}}