{"income":{"5":{"value":"237462","family_comment":"","value_unclear":false,"family_hidden":false,"family_unclear":false,"family":"152207","comment":""},"6":{"value":"237462","value_unclear":false,"comment_hidden":false,"family_hidden":false,"value_hidden":false,"family_comment":"","family":"112644","comment":""},"7":{"value":"","family_comment":"","source_name":"","family":"","comment":"","source_name_hidden":false},"8":{"family_comment":"","value":"","family":"","comment":""},"9":{"family_comment":"","value":"","family":"2414","comment":"","value_hidden":false},"10":{"value":"12180","value_unclear":false,"family_hidden":false,"value_hidden":false,"family_comment":"","family":"","comment":""},"11":{"family_comment":"","value":"","family":"","comment":""},"12":{"family_comment":"","value":"","family":"","comment":""},"13":{"family_comment":"","value":"","comment_hidden":false,"family":"","comment":""},"14":{"value":"","comment_hidden":false,"value_hidden":false,"family_comment":"","family":"","comment":""},"15":{"family_comment":"","value":"","family":"","comment":""},"16":{"family_comment":"","value":"","family":"","comment":"","value_hidden":false},"17":{"family_comment":"","value":"","family":"","comment":""},"18":{"family_comment":"","value":"","family":"","comment":""},"19":{"family_comment":"","value":"","family":"","comment":"","value_hidden":false},"20":{"value":"","family_comment":"","comment_unclear":false,"family_unclear":false,"family":"","comment":""}},"vehicle":{"35":[{"brand_info":"1800 куб. см., 122 кВт , 461.1 см","sum_rent_comment":"","sum_rent_hidden":false,"year":"2006","sum_hidden":false,"brand_info_hidden":false,"brand_info_unclear":false,"sum_rent":"","sum":"","brand":"Opel Vectra","sum_comment":"","sum_rent_comment_hidden":false},{"brand_info":"1300 куб. см., 63 кВт , 423.7 см","sum_rent_comment":"","brand":"Daewoo Sens","sum_comment":"","brand_unclear":false,"year":"2002","year_unclear":false,"sum":"","sum_rent":""}]},"id":"vulyk_12_51","banks":{"45":[{"sum_foreign_comment":"","sum":"652","sum_comment":"","sum_hidden":false,"sum_foreign_units":"UAH","sum_foreign_hidden":false,"sum_units":"UAH","sum_comment_hidden":false,"sum_unclear":false,"sum_foreign":"","sum_units_hidden":false},{"sum_foreign_comment":"","sum_units":"","sum_comment":"","sum_foreign_units":"","sum":"","sum_foreign":""}],"46":[{"sum_foreign_comment":"","sum_units":"UAH","sum_comment":"","sum_hidden":false,"sum_foreign_units":"UAH","sum":"","sum_foreign_hidden":false,"sum_foreign":""}],"47":[{"sum_foreign_comment":"","sum_units":"UAH","sum_comment":"","sum_comment_unclear":false,"sum_foreign_units":"UAH","sum":"","sum_foreign":""},{"sum_foreign_comment":"","sum_units":"","sum_comment":"","sum_foreign_units":"","sum":"","sum_foreign":""}],"48":[{"sum_foreign_comment":"","sum_units":"UAH","sum_comment":"","sum_foreign_units":"UAH","sum":"","sum_foreign":""}],"49":[{"sum_foreign_comment":"","sum_units":"UAH","sum_comment":"","sum_foreign_units":"UAH","sum":"","sum_foreign":""}],"50":[{"sum_foreign_comment":"","sum_units":"UAH","sum_comment":"","sum_foreign_units":"UAH","sum":"","sum_foreign":""}],"51":[{"sum_foreign_comment":"","sum_units":"UAH","sum_comment":"","sum_hidden":false,"sum_foreign_units":"UAH","sum_comment_hidden":false,"sum_units_hidden":false,"sum":"1751","sum_foreign":""}],"52":[{"sum_foreign_comment":"","sum_units":"UAH","sum_comment":"","sum_comment_unclear":false,"sum_foreign_units":"UAH","sum":"","sum_foreign":""},{"sum_foreign_comment":"","sum_units":"","sum_comment":"","sum_foreign_units":"","sum":"","sum_foreign":""},{"sum_foreign_comment":"","sum_units":"","sum_comment":"","sum_foreign_units":"","sum":"","sum_foreign":""},{"sum_foreign_comment":"","sum_units":"","sum_comment":"","sum_foreign_units":"","sum":"","sum_foreign":""}],"53":[{"sum_foreign_comment":"","sum_units":"UAH","sum_comment":"","sum_foreign_units":"UAH","sum":"","sum_foreign":""}]},"declaration":{"additional_info_text":"","notfull_lostpages":"","date":"2015-03-27T00:00:00","notfull":"","additional_info":"","url":"http://static.declarations.com.ua/declarations/chosen_ones/mega_batch/skrypchenko_dmytro_mykolaiovych.pdf"},"liabilities":{"54":{"sum_foreign_comment":"","sum":"376","sum_comment":"","sum_hidden":false,"sum_comment_hidden":false,"sum_foreign":""},"55":{"sum_foreign_comment":"","sum":"","sum_comment":"","sum_foreign":""},"56":{"sum_foreign_comment":"","sum":"","sum_comment":"","sum_foreign":""},"57":{"sum_foreign_comment":"","sum":"","sum_comment":"","sum_comment_unclear":false,"sum_hidden":false,"sum_comment_hidden":false,"sum_unclear":false,"sum_foreign":""},"58":{"sum_foreign_comment":"","sum":"","sum_comment":"","sum_comment_unclear":false,"sum_hidden":false,"sum_foreign":""},"59":{"sum_foreign_comment":"","sum":"","sum_hidden":false,"sum_comment":"","sum_foreign":""},"60":{"sum_foreign_comment":"","sum":"","sum_comment":"","sum_hidden":false,"sum_comment_hidden":false,"sum_foreign":""},"61":{"sum_foreign_comment":"","sum":"","sum_comment":"","sum_foreign":""},"62":{"sum_foreign_comment":"","sum":"","sum_comment":"","sum_comment_unclear":false,"sum_unclear":false,"sum_foreign":""},"63":{"sum_foreign_comment":"","sum":"","sum_comment":"","sum_comment_unclear":false,"sum_foreign":""},"64":{"sum_foreign_comment":"","sum":"","sum_comment":"","sum_comment_unclear":false,"sum_foreign":""}},"ft_src":"376\nголова томаківського районного суду дніпропетровської області\nДніпропетровська область\nЗагальний місцевий суд\nДмитро\nСкрипченко Н. М., 11. 08. 1973 р. н\nПодружжя\nСкрипченко Р. Д., 21. 07. 1993 р. н\nДитина\nМиколайович\nСкрипченко\nСкрипченко Дмитро Миколайович\nСкрипченко Дмитро Миколайович\nДмитро Миколайович Скрипченко\nДмитро Скрипченко\nСкрипченко Дмитро Миколайович\n1800 куб. см., 122 кВт , 461.1 см\nOpel Vectra\n2006\n1300 куб. см., 63 кВт , 423.7 см\nDaewoo Sens\n2002\n1751\n652\n2014\n1800 куб. см., 122 кВт , 461.1 см\nOpel Vectra\n2006\n1300 куб. см., 63 кВт , 423.7 см\n2002\nDaewoo Sens\n652\n1751\n28\nсмт. Томаківка, вул. Середня\nДніпропетровська область\n95.5\nсмт. Томаківка, вул. Р. Люксембург, 3\nДніпропетровська область\n20.8\nДніпропетровська область\nсмт Томаківка, вул. Шосейна, 3а, кв. 14\n1000\nсмт. Томаківка, вул. Р. Люксембург, 3\nДніпропетровська область\nсмт. Томаківка, вул. Шосейна, 3-а, кв. 14\nДніпропетровська область\n20.8\nЗагальний місцевий суд\nголова томаківського районного суду дніпропетровської області\nДніпропетровська область\nПодружжя\nСкрипченко Н. М., 11. 08. 1973 р. н\nДитина\nСкрипченко Р. Д., 21. 07. 1993 р. н\nСкрипченко Дмитро Миколайович\nДмитро Миколайович Скрипченко\nДмитро Скрипченко\nСкрипченко Дмитро Миколайович\nДмитро\nСкрипченко Дмитро Миколайович\nСкрипченко\nМиколайович\n376\n237462\n112644\n152207\n237462\n12180\n2414\n2014\n376\nсмт. Томаківка, вул. Середня\n28\nДніпропетровська область\nДніпропетровська область\nсмт. Томаківка, вул. Р. Люксембург, 3\n1000\nсмт. Томаківка, вул. Р. Люксембург, 3\nДніпропетровська область\n95.5\nДніпропетровська область\nсмт. Томаківка, вул. Шосейна, 3-а, кв. 14\n20.8\nсмт Томаківка, вул. Шосейна, 3а, кв. 14\n20.8\nДніпропетровська область\nПодружжя\nСкрипченко Н. М., 11. 08. 1973 р. н\nСкрипченко Р. Д., 21. 07. 1993 р. н\nДитина\nМиколайович\nСкрипченко\nДмитро\nСкрипченко Дмитро Миколайович\nДмитро Миколайович Скрипченко\nДмитро Скрипченко\nСкрипченко Дмитро Миколайович\nДніпропетровська область\nЗагальний місцевий суд\nголова томаківського районного суду дніпропетровської області\nСкрипченко Дмитро Миколайович\n112644\n237462\n12180\n152207\n237462\n2414\nOpel Vectra\n1800 куб. см., 122 кВт , 461.1 см\n2006\n2002\nDaewoo Sens\n1300 куб. см., 63 кВт , 423.7 см\n12180\n237462\n152207\n2414\n237462\n112644\nсмт. Томаківка, вул. Шосейна, 3-а, кв. 14\nДніпропетровська область\n20.8\nсмт. Томаківка, вул. Середня\nДніпропетровська область\n28\nсмт. Томаківка, вул. Р. Люксембург, 3\nДніпропетровська область\n95.5\nсмт Томаківка, вул. Шосейна, 3а, кв. 14\nДніпропетровська область\n20.8\nсмт. Томаківка, вул. Р. Люксембург, 3\nДніпропетровська область\n1000\n652\n1751\n2014","general":{"inn":"","name":"Дмитро","patronymic_unclear":false,"last_name_hidden":false,"family":[{"inn":"","inn_hidden":true,"relations_unclear":false,"relations_hidden":false,"relations_other":"","relations":"Подружжя","name_hidden":false,"inn_unclear":false,"family_name":"Скрипченко Н. М., 11. 08. 1973 р. н","name_unclear":false},{"inn":"","relations":"Дитина","inn_unclear":false,"family_name":"Скрипченко Р. Д., 21. 07. 1993 р. н","inn_hidden":false,"relations_other":"","name_hidden":false,"name_unclear":false}],"patronymic":"Миколайович","inn_hidden":true,"family_raw":"","inn_unclear":false,"post":{"post_unclear":false,"post":"голова томаківського районного суду дніпропетровської області","candidate":"","office_hidden":false,"region":"Дніпропетровська область","post_hidden":false,"office":"Загальний місцевий суд","office_unclear":false},"last_name_unclear":false,"full_name":"Скрипченко Дмитро Миколайович","addresses":[{"place_district":"","place_city_hidden":true,"place_city":"","place_city_type_hidden":false,"place_district_hidden":true,"place_city_type":"","place_address_hidden":true,"place_address":"","place_hidden":true,"place":""}],"last_name":"Скрипченко","patronymic_hidden":false,"full_name_suggest":{"output":"Скрипченко Дмитро Миколайович","input":["Скрипченко Дмитро Миколайович","Дмитро Миколайович Скрипченко","Дмитро Скрипченко"]}},"source":"VULYK","estate":{"23":[{"space_unclear":false,"costs":"","costs_comment":"","address_hidden":false,"region_hidden":true,"space_comment":"","space_hidden":false,"space":"","address":"","costs_comment_unclear":false,"region":"","address_unclear":false,"costs_rent_comment":"","space_units":"м²","costs_rent":""},{"space_unclear":false,"costs":"","costs_comment":"","address_hidden":false,"region_hidden":false,"space_comment":"","space":"","address":"","region":"","costs_rent_comment":"","space_units":"","costs_rent":""},{"space_hidden":false,"costs":"","costs_comment":"","address_hidden":false,"region_hidden":false,"space_comment":"","space":"","address":"","region":"","costs_rent_comment":"","space_units":"","costs_rent":""},{"costs_rent":"","region":"","costs":"","costs_rent_comment":"","costs_comment":"","space_comment":"","space_units":"","space":"","address":""}],"24":[{"space_unclear":false,"costs":"","costs_comment":"","address_hidden":false,"region_hidden":true,"space_comment":"","space":"","address":"","region":"","costs_rent_comment":"","space_units":"м²","space_units_hidden":false,"costs_rent":""}],"25":[{"region_unclear":false,"space_hidden":false,"costs":"","costs_comment":"","costs_hidden":false,"address_hidden":false,"region_hidden":false,"space_comment":"","space_unclear":false,"space":"20.8","address":"смт Томаківка, вул. Шосейна, 3а, кв. 14","region":"Дніпропетровська область","address_unclear":false,"costs_rent_comment":"","costs_rent_hidden":false,"space_comment_unclear":false,"space_units":"м²","costs_rent":""}],"27":[{"space_hidden":false,"costs":"","costs_comment":"","address_hidden":false,"region_hidden":false,"space_comment":"","space":"28","address":"смт. Томаківка, вул. Середня","region":"Дніпропетровська область","costs_rent_comment":"","space_units":"м²","costs_rent":""}],"29":[{"region_unclear":false,"space_unclear":false,"address_hidden":false,"region_hidden":false,"space_comment":"","space":"1000","address":"смт. Томаківка, вул. Р. Люксембург, 3","region":"Дніпропетровська область","costs_property":"","costs_rent_comment":"","space_comment_unclear":false,"address_unclear":false,"space_units":"м²","costs_property_comment":"","costs_rent":""}],"30":[{"space_hidden":false,"address_hidden":false,"region_hidden":false,"space_comment":"","space":"95.5","address":"смт. Томаківка, вул. Р. Люксембург, 3","region":"Дніпропетровська область","costs_property":"","costs_rent_comment":"","space_comment_unclear":false,"space_units":"м²","costs_property_comment":"","costs_rent":""}],"31":[{"space_hidden":false,"costs_property_hidden":false,"address_hidden":false,"region_hidden":false,"space_comment":"","space":"20.8","address":"смт. Томаківка, вул. Шосейна, 3-а, кв. 14","region":"Дніпропетровська область","costs_property":"","costs_rent_comment":"","costs_rent_hidden":false,"space_units":"м²","costs_property_comment":"","costs_rent":""}]},"intro":{"declaration_year":"2014","isnotdeclaration":""}}