{"income":{"5":{"family_comment":"","value":"282769","family_hidden":false,"comment":"","family":"339548"},"6":{"family_comment":"","value":"223204","family_hidden":false,"comment":"","family":"177605"},"7":{"family_comment":"","value":"","source_name":"ТОВ Видавництво Істина","family":"976","comment":""},"8":{"family_comment":"","value":"","family":"","comment":""},"9":{"family_comment":"","value":"46167","family":"","comment":""},"10":{"family_comment":"","value":"13398","family":"16967","comment":""},"11":{"family_comment":"","value":"","family":"24000","comment":""},"12":{"family_comment":"","value":"","family":"","comment":""},"13":{"family_comment":"","value":"","family":"","comment":""},"14":{"family_comment":"","value":"","family":"120000","comment":""},"15":{"family_comment":"","value":"","family":"","comment":""},"16":{"family_comment":"","value":"","family":"","comment":""},"17":{"family_comment":"","value":"","family":"","comment":""},"18":{"family_comment":"","value":"","family":"","comment":""},"19":{"family_comment":"","value":"","family":"","comment":""},"20":{"family_comment":"","value":"","family":"","comment":""}},"vehicle":{"35":[{"brand_info":"2656","sum_rent_comment":"","brand":"Hyundai Santa FE","sum_comment":"","year":"2008","brand_info_hidden":false,"sum":"","sum_rent":""}]},"id":"vulyk_105_39","banks":{"45":[{"sum_foreign_comment":"","sum_units":"UAH","sum_comment":"","sum_foreign_units":"UAH","sum_comment_hidden":false,"sum":"385978","sum_foreign":""}]},"declaration":{"date":"2015-03-19T00:00:00","additional_info_text":"","additional_info":"","url":"http://static.declarations.com.ua/declarations/chosen_ones/judges_batch/4614_buravlov_serhii_ivanovych.pdf"},"liabilities":{"54":{"sum_foreign_comment":"","sum_comment_hidden":false,"sum":"","sum_comment":"","sum_foreign":""},"55":{"sum_foreign_comment":"","sum":"","sum_comment":"","sum_foreign":""},"56":{"sum_foreign_comment":"","sum":"","sum_comment":"","sum_foreign":""},"57":{"sum_foreign_comment":"","sum":"","sum_comment":"","sum_comment_unclear":false,"sum_comment_hidden":false,"sum_foreign":""},"58":{"sum_foreign_comment":"","sum":"","sum_comment":"","sum_foreign":""},"59":{"sum_foreign_comment":"","sum":"","sum_comment":"","sum_foreign":""},"60":{"sum_foreign_comment":"","sum":"","sum_comment":"","sum_foreign":""},"61":{"sum_foreign_comment":"","sum":"","sum_comment":"","sum_foreign":""},"62":{"sum_foreign_comment":"","sum":"","sum_hidden":false,"sum_comment":"","sum_foreign":""},"63":{"sum_foreign_comment":"","sum":"","sum_comment":"","sum_foreign":""},"64":{"sum_foreign_comment":"","sum":"","sum_comment":"","sum_foreign":""}},"ft_src":"Буравльов Сергій Іванович\nсуддя київського апеляційного господарського суду\nм. Київ\nАпеляційний господарський суд\nСергій\nСидоренко Н. Л\nПодружжя\nБуравльова О. С\nДитина\nБуравльов Сергій Іванович\nСергій Іванович Буравльов\nСергій Буравльов\nБуравльов Сергій Іванович\nБуравльов\nІванович\n2656\n2008\nHyundai Santa FE\n385978\n2014\nHyundai Santa FE\n2656\n2008\n385978\n2014\nсуддя київського апеляційного господарського суду\nАпеляційний господарський суд\nм. Київ\nБуравльов\nБуравльов Сергій Іванович\nСергій Іванович Буравльов\nСергій Буравльов\nБуравльов Сергій Іванович\nБуравльов Сергій Іванович\nСергій\nІванович\nПодружжя\nСидоренко Н. Л\nДитина\nБуравльова О. С\n976\nТОВ Видавництво Істина\n223204\n177605\n120000\n282769\n339548\n24000\n13398\n16967\n46167\n68.7\n36.3\n36.1\n43.2\nправо користування\n68.7\n36.3\n36.1\nправо користування\n43.2\nСидоренко Н. Л\nПодружжя\nБуравльова О. С\nДитина\nІванович\nБуравльов\nм. Київ\nсуддя київського апеляційного господарського суду\nАпеляційний господарський суд\nБуравльов Сергій Іванович\nБуравльов Сергій Іванович\nСергій Іванович Буравльов\nСергій Буравльов\nБуравльов Сергій Іванович\nСергій\n177605\n223204\n120000\n24000\n16967\n13398\n976\nТОВ Видавництво Істина\n339548\n282769\n46167\nHyundai Santa FE\n2656\n2008\n24000\n120000\n16967\n13398\n339548\n282769\n976\nТОВ Видавництво Істина\n46167\n177605\n223204\n68.7\n36.3\n36.1\nправо користування\n43.2\n385978\n2014","general":{"inn":"","inn_hidden":true,"last_name":"Буравльов","post":{"post_unclear":false,"region_unclear":false,"region":"м. Київ","office_hidden":false,"office":"Апеляційний господарський суд","post":"суддя київського апеляційного господарського суду","office_unclear":false},"name":"Сергій","full_name":"Буравльов Сергій Іванович","family_raw":"","addresses":[{"place_district":"","place_city_hidden":false,"place_city":"","place_city_type_hidden":false,"place_district_hidden":false,"place_city_type":"","place_address_hidden":false,"place_address":"","place_hidden":true,"place":""}],"family":[{"inn":"","inn_hidden":true,"relations_hidden":false,"family_name":"Сидоренко Н. Л","relations_other":"","relations":"Подружжя","name_hidden":false,"name_unclear":false},{"inn":"","relations":"Дитина","relations_other":"","inn_hidden":false,"family_name":"Буравльова О. С","name_hidden":false,"name_unclear":false}],"full_name_suggest":{"output":"Буравльов Сергій Іванович","input":["Буравльов Сергій Іванович","Сергій Іванович Буравльов","Сергій Буравльов"]},"patronymic":"Іванович"},"source":"VULYK","estate":{"25":[{"space_hidden":false,"costs":"","costs_comment":"","address_hidden":false,"region_hidden":true,"space_comment":"право користування","space":"43.2","address":"","region":"","costs_rent_comment":"","space_units":"м²","costs_rent":""}],"31":[{"space_hidden":false,"address_hidden":true,"region_hidden":true,"space_comment":"","space":"68.7","address":"","region":"","costs_property":"","costs_rent_comment":"","space_units":"м²","costs_property_comment":"","costs_rent":""},{"costs_rent":"","costs_property":"","costs_rent_comment":"","region_hidden":false,"space_comment":"","costs_property_comment":"","space_units":"м²","space":"36.3","address":""},{"costs_rent":"","costs_property":"","costs_rent_comment":"","space_comment":"","costs_property_comment":"","space_units":"м²","space":"36.1","address":""}]},"intro":{"declaration_year":"2014"}}