[{"id":"vulyk_68_92","ft_src":"довжина 439 см, потужність 150 кВт , 1998 куб. см.\nToyota Rav 4\n2006\n1794 куб. см, потужність 95 кВт , довжина 464 см\nToyota Avensis\n2007\n32.6\n29.4\nу власності 1/2 від 435,8\n435.8\nу власгності 1/2 від 1030\n1030\n15711\n160000\nу власності 1/4 від 81,3\nнежитлове приміщення першого поверху\n81.3\n2014\n532\n222185\n13398\n12682\n235583\nщомісячна одноразова допомога при народженні дитини\n12150\nдовжина 439 см, потужність 150 кВт , 1998 куб. см.\nToyota Rav 4\n2006\n1794 куб. см, потужність 95 кВт , довжина 464 см\n2007\nToyota Avensis\nу власгності 1/2 від 1030\n1030\n15711\n435.8\nу власності 1/2 від 435,8\n32.6\n29.4\n160000\n81.3\nу власності 1/4 від 81,3\nнежитлове приміщення першого поверху\nПодружжя\nІваніцька М. Є\nДитина\nЗапотічний П-І. І\nДитина\nЗапотічний С. І\nЗапотічний Ігор Ігорович\nІгор Ігорович Запотічний\nІгор Запотічний\nЗапотічний Ігор Ігорович\nЗапотічний Ігор Ігорович\nІгор\nІгорович\nАпеляційний адміністративний суд\nЛьвівська область\nсуддя львівського апеляційного адміністративного суду\nЗапотічний\n222185\n532\nщомісячна одноразова допомога при народженні дитини\n12150\n235583\n12682\n13398\n2014\nПодружжя\nІваніцька М. Є\nЗапотічний П-І. І\nДитина\nЗапотічний С. І\nДитина\nІгорович\nЗапотічний\nІгор\nЗапотічний Ігор Ігорович\nІгор Ігорович Запотічний\nІгор Запотічний\nЗапотічний Ігор Ігорович\nЛьвівська область\nАпеляційний адміністративний суд\nсуддя львівського апеляційного адміністративного суду\nЗапотічний Ігор Ігорович","estate":{"28":[{"costs":"160000","address":"нежитлове приміщення першого поверху","space_units":"м²","costs_rent_comment":"","space":"81.3","space_comment":"у власності 1/4 від 81,3","region_hidden":true,"costs_comment":"","region":"","address_hidden":false,"costs_rent":""}],"29":[{"costs_property_comment":"","costs_property":"","address":"","space_units":"м²","space_hidden":false,"space_unclear":false,"region_hidden":true,"costs_rent_comment":"","space_comment":"у власгності 1/2 від 1030","address_hidden":false,"space_units_unclear":false,"space":"1030","region":"","space_units_hidden":false,"costs_rent":""},{"costs_property_comment":"","address":"","space_units":"м²","space_unclear":false,"region_hidden":true,"costs_property":"","space_comment":"","space_comment_hidden":false,"costs_rent_comment":"","space":"15711","region":"","costs_rent":""}],"30":[{"costs_property_comment":"","address":"","space_units":"м²","space_hidden":false,"space_unclear":false,"region_hidden":true,"costs_property":"","space_comment":"у власності 1/2 від 435,8","address_hidden":false,"costs_rent_comment":"","space":"435.8","region":"","costs_rent":""}],"31":[{"costs_property_comment":"","address":"","space_units":"м²","space_hidden":false,"space_unclear":false,"region_hidden":true,"costs_property":"","space_comment":"","address_hidden":false,"costs_rent_comment":"","space":"32.6","region":"","costs_rent":""},{"costs_property_comment":"","address":"","space_units":"м²","costs_rent_comment":"","space":"29.4","region":"","region_hidden":false,"costs_property":"","space_comment":"","address_hidden":false,"costs_rent":""}]},"vehicle":{"35":[{"brand_info":"довжина 439 см, потужність 150 кВт , 1998 куб. см.","sum_rent_comment":"","brand_unclear":false,"year":"2006","brand_hidden":false,"sum_comment":"","brand_info_hidden":false,"sum_rent":"","brand":"Toyota Rav 4","year_unclear":false,"brand_info_unclear":false,"sum":""}],"40":[{"sum_comment":"","brand_info_hidden":false,"brand_info":"1794 куб. см, потужність 95 кВт , довжина 464 см","sum":"","sum_rent_comment":"","brand_hidden":false,"brand":"Toyota Avensis","sum_rent":"","brand_info_unclear":false,"year":"2007","year_unclear":false}]},"source":"VULYK","income":{"5":{"family_comment":"","value":"235583","family_unclear":false,"family":"12682","comment":""},"6":{"family_comment":"","value":"222185","family_unclear":false,"family":"532","comment":""},"7":{"family_comment":"","comment":"","family":"","comment_hidden":false,"value":"","source_name":""},"8":{"family_comment":"","value":"","family":"","comment":""},"9":{"family_comment":"","value":"","family":"","comment":""},"10":{"family_comment":"","value":"13398","family":"","comment":""},"11":{"family_comment":"","value":"","family":"","comment":"","value_unclear":false},"12":{"family_comment":"","value":"","family":"","comment":""},"13":{"family_comment":"","value":"","family":"","comment":""},"14":{"family_comment":"","value":"","family":"","comment":""},"15":{"family_comment":"","value":"","family":"","comment":"","value_unclear":false},"16":{"family_comment":"","value":"","family_unclear":false,"family":"","comment":""},"17":{"family_comment":"","value":"","family":"","comment":""},"18":{"family_comment":"","family_hidden":false,"value":"","family":"","comment":""},"19":{"family_comment":"","value":"","family":"","comment":""},"20":{"family_comment":"щомісячна одноразова допомога при народженні дитини","comment":"","family":"12150","comment_hidden":false,"comment_unclear":false,"value":"","family_comment_hidden":false}},"general":{"family":[{"inn":"","inn_unclear":false,"family_name":"Іваніцька М. Є","relations_hidden":false,"relations_unclear":false,"name_unclear":true,"relations":"Подружжя","inn_hidden":false,"name_hidden":false,"relations_other":""},{"inn":"","inn_unclear":false,"family_name":"Запотічний П-І. І","relations_other":"","relations_hidden":false,"name_unclear":false,"inn_hidden":false,"name_hidden":false,"relations":"Дитина"},{"inn":"","family_name":"Запотічний С. І","relations_other":"","name_unclear":false,"inn_hidden":false,"name_hidden":false,"relations":"Дитина"}],"family_raw":"","name":"Ігор","full_name_suggest":{"input":["Запотічний Ігор Ігорович","Ігор Ігорович Запотічний","Ігор Запотічний"],"output":"Запотічний Ігор Ігорович"},"name_unclear":false,"patronymic":"Ігорович","inn_hidden":true,"addresses":[{"place_city_type_hidden":false,"place_hidden":true,"place_address_unclear":false,"place":"","place_city":"","place_unclear":false,"place_city_type":"","place_city_hidden":false,"place_district":"","place_district_hidden":false,"place_address":"","place_address_hidden":false}],"inn":"","inn_unclear":false,"last_name":"Запотічний","full_name":"Запотічний Ігор Ігорович","post":{"post_hidden":false,"office":"Апеляційний адміністративний суд","post":"суддя львівського апеляційного адміністративного суду","region":"Львівська область","region_hidden":false,"office_unclear":false,"office_hidden":false,"post_unclear":false,"region_unclear":false},"last_name_unclear":false},"liabilities":{"54":{"sum_comment_unclear":false,"sum_comment":"","sum_hidden":false,"sum":"","sum_foreign_comment":"","sum_foreign":"","sum_unclear":false,"sum_comment_hidden":false},"55":{"sum_comment":"","sum_foreign_comment":"","sum_foreign":"","sum_hidden":false,"sum":""},"56":{"sum_comment":"","sum":"","sum_foreign_comment":"","sum_foreign":"","sum_unclear":false,"sum_foreign_hidden":false},"57":{"sum_comment_unclear":false,"sum_comment":"","sum_hidden":false,"sum":"","sum_foreign_comment":"","sum_foreign":"","sum_unclear":false,"sum_comment_hidden":false},"58":{"sum_comment":"","sum_hidden":false,"sum":"","sum_foreign_comment":"","sum_foreign":"","sum_unclear":false,"sum_comment_hidden":false},"59":{"sum_comment":"","sum_foreign_comment":"","sum_foreign":"","sum":""},"60":{"sum_comment_unclear":false,"sum_comment":"","sum_hidden":false,"sum":"","sum_foreign_comment":"","sum_foreign":"","sum_unclear":false,"sum_comment_hidden":false},"61":{"sum_comment":"","sum_foreign_comment":"","sum_foreign":"","sum_hidden":false,"sum":""},"62":{"sum_comment":"","sum_foreign_comment":"","sum_foreign":"","sum_unclear":false,"sum":""},"63":{"sum_comment":"","sum_hidden":false,"sum":"","sum_foreign_comment":"","sum_foreign":"","sum_unclear":false,"sum_comment_hidden":false},"64":{"sum_comment":"","sum_hidden":false,"sum":"","sum_foreign_comment":"","sum_foreign":"","sum_comment_hidden":false}},"declaration":{"notfull_lostpages":"","additional_info_text":"","additional_info":"","date":"2015-03-31T00:00:00","notfull":"","url":"http://static.declarations.com.ua/declarations/chosen_ones/mega_batch/zapotichnyi_ihor_ihorovych.pdf"},"intro":{"isnotdeclaration":"","declaration_year":"2014"}},{"id":"5176","ft_src":"Toyota Rav 4\n1998 куб см, 150 кВт , 439 см\n2006\n2007\nToyota Avensis\n1794 куб см, 95 кВт , 464 см\n500\n15711\n32.6\n29.4\n217.9\n2013\n13892\n196782\n48\n24\n12617\nЛьвівське регіональне відділення Національної школи суддів України\n287\n25685\n209710\n11745\n1998 куб см, 150 кВт , 439 см\nToyota Rav 4\n2006\n1794 куб см, 95 кВт , 464 см\nToyota Avensis\n2007\n2013\nЗапотічний Ігор Ігорович\nІгор Ігорович Запотічний\nІгор Запотічний\nЗапотічний Ігор Ігорович\nІгор\nПодружжя\nІваніцька М. Є\nДитина\nЗапотічний П-І. І\nДитина\nЗапотічний С. І\nЗапотічний Ігор Ігорович\nІгорович\nАпеляційний адміністративний суд\nЛьвівська область\nсуддя львівського апеляційного адміністративного суду\nЗапотічний\n2022\n287\nЛьвівське регіональне відділення Національної школи суддів України\n13892\n196782\n11745\n209710\n25685\n12617\n24\n48\n217.9\n500\n15711\n32.6\n29.4\n2022\nПодружжя\nІваніцька М. Є\nДитина\nЗапотічний П-І. І\nДитина\nЗапотічний С. І\nІгорович\nЗапотічний\nІгор\nЗапотічний Ігор Ігорович\nІгор Ігорович Запотічний\nІгор Запотічний\nЗапотічний Ігор Ігорович\nЛьвівська область\nАпеляційний адміністративний суд\nсуддя львівського апеляційного адміністративного суду\nЗапотічний Ігор Ігорович","estate":{"23":[{"costs_unclear":false,"address":"","space_units":"м²","costs_hidden":false,"space_hidden":false,"space_unclear":false,"region_hidden":true,"space_units_unclear":false,"costs_comment":"","address_hidden":false,"space":"","space_comment":"","costs_rent_comment":"","costs":"","region":"","costs_rent":""}],"24":[{"address":"","space_units":"м²","costs_hidden":false,"costs_comment":"","space_unclear":false,"region_hidden":true,"space_units_unclear":false,"space_comment":"","space_comment_unclear":false,"space_comment_hidden":false,"costs":"","address_hidden":false,"costs_rent_comment":"","space":"","region":"","costs_rent":""}],"25":[{"address":"","space_units":"м²","costs_hidden":false,"space_hidden":false,"space_unclear":false,"region_hidden":true,"costs_rent_comment":"","space_comment":"","address_hidden":false,"space_comment_hidden":false,"costs":"","costs_comment":"","space":"","region":"","costs_rent":""}],"29":[{"costs_property_comment":"","address":"","space_units":"м²","space_unclear":false,"region_hidden":true,"costs_property":"","space_comment":"","address_hidden":true,"costs_rent_comment":"","space":"500","region":"","costs_rent":""},{"costs_property_comment":"","costs_rent":"","address":"","space_units":"м²","costs_rent_comment":"","space":"15711","region":"","region_hidden":false,"costs_property":"","space_comment":"","space_comment_hidden":false}],"30":[{"costs_property_comment":"","address":"","space_units":"м²","space_hidden":false,"space_unclear":false,"region_hidden":true,"costs_property":"","space_comment":"","address_hidden":true,"space_comment_unclear":false,"costs_rent_comment":"","space":"217.9","region":"","costs_rent":""}],"31":[{"costs_property_comment":"","address":"","space_units":"м²","space_unclear":false,"region_hidden":true,"costs_property":"","space_comment":"","address_hidden":true,"costs_rent_comment":"","space":"32.6","region":"","costs_rent":""},{"costs_property_comment":"","address":"","space_units":"м²","costs_rent_comment":"","space":"29.4","space_unclear":false,"region_hidden":false,"costs_property":"","space_comment":"","region":"","costs_rent":""}]},"vehicle":{"35":[{"brand_info":"1998 куб см, 150 кВт , 439 см","sum_comment":"","sum_hidden":false,"brand_unclear":false,"sum_rent_comment":"","year":"2006","brand":"Toyota Rav 4","sum_rent":"","brand_info_unclear":false,"sum":""}],"40":[{"sum_comment":"","brand_info":"1794 куб см, 95 кВт , 464 см","brand_unclear":false,"sum_rent_comment":"","year":"2007","brand":"Toyota Avensis","sum_rent":"","brand_info_unclear":false,"sum":""}]},"source":"VULYK","income":{"5":{"family_comment":"","family":"25685","comment":"","comment_hidden":false,"value":"209710","family_comment_hidden":false},"6":{"family_comment":"","family":"13892","comment":"","comment_hidden":false,"family_hidden":false,"family_unclear":false,"family_comment_hidden":false,"value":"196782"},"7":{"source_name_hidden":false,"family_comment":"","comment":"","family":"","comment_hidden":false,"value":"287","family_comment_hidden":false,"source_name":"Львівське регіональне відділення Національної школи суддів України"},"8":{"family_comment":"","value":"","family":"","comment":""},"9":{"family_comment":"","comment":"","family":"","value_unclear":false,"family_unclear":false,"comment_unclear":false,"value":""},"10":{"family_comment":"","value":"12617","family_unclear":false,"family":"","comment":""},"11":{"family_comment":"","value":"24","family":"48","comment":""},"12":{"family_comment":"","value":"","family":"","comment":""},"13":{"family_comment":"","value":"","family":"","comment":""},"14":{"family_comment":"","value":"","family":"","comment":""},"15":{"family_comment":"","comment_unclear":false,"value":"","family":"","comment":""},"16":{"family_comment":"","comment_unclear":false,"value":"","family":"","comment":""},"17":{"family_comment":"","value":"","family":"","comment":""},"18":{"family_comment":"","value":"","family":"","comment":""},"19":{"family_comment":"","value":"","family":"","comment":""},"20":{"family_comment":"","family":"11745","comment":"","value_unclear":false,"family_unclear":false,"value":"","family_comment_hidden":false,"family_comment_unclear":false}},"general":{"family_raw":"","name":"Ігор","full_name_suggest":{"input":["Запотічний Ігор Ігорович","Ігор Ігорович Запотічний","Ігор Запотічний"],"output":"Запотічний Ігор Ігорович"},"name_unclear":false,"patronymic":"Ігорович","inn_hidden":true,"inn":"","addresses":[{"place_city_type_hidden":true,"place_city_type":"","place_city_hidden":true,"place_hidden":true,"place_district":"","place_district_hidden":true,"place":"","place_city":"","place_address_hidden":true,"place_address":""}],"last_name":"Запотічний","full_name":"Запотічний Ігор Ігорович","family":[{"inn":"","inn_unclear":false,"family_name":"Іваніцька М. Є","relations_hidden":false,"name_unclear":false,"relations":"Подружжя","inn_hidden":true,"name_hidden":false,"relations_other":""},{"inn":"","inn_unclear":false,"family_name":"Запотічний П-І. І","relations_other":"","name_unclear":false,"inn_hidden":true,"name_hidden":false,"relations":"Дитина"},{"inn":"","family_name":"Запотічний С. І","relations_other":"","name_unclear":false,"inn_hidden":false,"name_hidden":false,"relations":"Дитина"}],"post":{"post_hidden":false,"office":"Апеляційний адміністративний суд","post":"суддя львівського апеляційного адміністративного суду","region":"Львівська область","region_hidden":false,"office_unclear":false,"office_hidden":false,"post_unclear":false,"region_unclear":false},"last_name_unclear":false},"liabilities":{"54":{"sum_comment_unclear":false,"sum_comment":"","sum_hidden":true,"sum":"2022","sum_foreign_comment":"","sum_foreign":"","sum_unclear":false,"sum_foreign_hidden":true,"sum_comment_hidden":true},"55":{"sum_comment":"","sum_foreign_comment":"","sum_foreign":"","sum":"","sum_comment_hidden":false},"56":{"sum_comment":"","sum_comment_unclear":false,"sum_foreign_comment":"","sum":"","sum_foreign":""},"57":{"sum_comment":"","sum_hidden":false,"sum":"","sum_foreign_comment":"","sum_foreign":"","sum_unclear":false,"sum_comment_hidden":false},"58":{"sum_comment":"","sum_hidden":false,"sum":"","sum_foreign_comment":"","sum_foreign":"","sum_comment_hidden":false},"59":{"sum_comment_unclear":false,"sum_comment":"","sum":"","sum_foreign_comment":"","sum_foreign":"","sum_unclear":false},"60":{"sum_comment":"","sum_hidden":false,"sum":"","sum_foreign_comment":"","sum_foreign":"","sum_unclear":false,"sum_comment_hidden":false},"61":{"sum_comment":"","sum_foreign_comment":"","sum_foreign":"","sum":""},"62":{"sum_comment":"","sum_foreign_comment":"","sum_foreign":"","sum":""},"63":{"sum_comment":"","sum_hidden":false,"sum":"","sum_foreign_comment":"","sum_foreign":"","sum_comment_hidden":false},"64":{"sum_comment":"","sum_foreign_comment":"","sum_foreign":"","sum":""}},"declaration":{"notfull_lostpages":"","additional_info_text":"","additional_info":"","date":"2014-03-28T00:00:00","notfull":"","url":"http://static.declarations.com.ua/declarations/chosen_ones/judges_batch/1176_zapotichnyi_ihor_ihorovych.pdf"},"intro":{"declaration_year":"2013"}}]