[{"id":"vulyk_84_163","ft_src":"Toyota Corolla\n1.6 л. 124 к. с\n2011\nВАЗ 2106\n1600 куб. см.\n1991\n1100 куб. см.\nТаврія\n2001\nм. Кіровоград\n84\nКіровоградська область\nКіровоградська область\nм. Кіровоград\n84\nм. Кіровоград\n50\nКіровоградська область\nКіровоградська область\n5000\nКіровоградська область\nм. Кіровоград\n84\nКіровоградська область\nм. Кіровоград\n50\nКіровоградська область\nм. Кіровоград\n14\nКіровоградська область\nм. Кіровоград\n80\nКіровоградська область\nм. Кіровоград\n80\n250000\n2014\n1.6 л. 124 к. с\nToyota Corolla\n2011\nВАЗ 2106\n1600 куб. см.\n1991\n1100 куб. см.\n2001\nТаврія\n2014\nЗавгородній Євген Віталійович\nЄвген Віталійович Завгородній\nЄвген Завгородній\nЗавгородній Євген Віталійович\nЄвген\nБатьки\nЗавгородній В. І., 15. 10. 1947\nПодружжя\nЗавгородня В. В., 09. 07. 1977\nДитина\nЗавгородня Є. Є., 27. 04. 2005\nДитина\nЗавгородній З. Є., 23. 04. 2009\nЗавгородній Євген Віталійович\nВіталійович\nсуддя кіровського районного суд м. кіровограда\nЗагальний місцевий суд\nКіровоградська область\nЗавгородній\nКіровоград\n25006\nКіровоградська область\n5000\n20000\n11000\n190895.36\n20000\n3000\n203075.36\n30000\n7000\n12180\n48\nм. Кіровоград\n84\nКіровоградська область\n50\nм. Кіровоград\nКіровоградська область\n80\nКіровоградська область\nм. Кіровоград\n84\nм. Кіровоград\nКіровоградська область\n84\nКіровоградська область\nм. Кіровоград\n5000\nКіровоградська область\n50\nКіровоградська область\nм. Кіровоград\nм. Кіровоград\nКіровоградська область\n80\nм. Кіровоград\nКіровоградська область\n14\n250000\n20000\n11000\n5000\n20000\n190895.36\n7000\n48\n12180\n30000\n203075.36\n3000\nЗавгородній В. І., 15. 10. 1947\nБатьки\nЗавгородня В. В., 09. 07. 1977\nПодружжя\nЗавгородня Є. Є., 27. 04. 2005\nДитина\nЗавгородній З. Є., 23. 04. 2009\nДитина\nВіталійович\nЗавгородній\nЄвген\nЗавгородній Євген Віталійович\nЄвген Віталійович Завгородній\nЄвген Завгородній\nЗавгородній Євген Віталійович\nКіровоградська область\nКіровоград\n25006\nКіровоградська область\nсуддя кіровського районного суд м. кіровограда\nЗагальний місцевий суд\nЗавгородній Євген Віталійович","estate":{"23":[{"address":"м. Кіровоград","space_units":"м²","costs_comment":"","space_comment":"","region_hidden":false,"region":"Кіровоградська область","address_hidden":true,"costs":"","address_unclear":false,"space_comment_unclear":false,"costs_rent_comment":"","space":"84","region_unclear":false,"costs_rent":""}],"24":[{"address":"м. Кіровоград","space_units":"м²","space_hidden":false,"space_unclear":false,"region_hidden":false,"costs_comment":"","space_comment":"","address_hidden":true,"costs":"","address_unclear":false,"costs_rent_comment":"","space":"50","region_unclear":false,"region":"Кіровоградська область","costs_rent":""}],"25":[{"address":"м. Кіровоград","space_units":"м²","space_hidden":false,"space_comment":"","region_hidden":false,"costs_comment":"","address_hidden":true,"costs":"","address_unclear":false,"costs_rent_comment_unclear":false,"costs_comment_unclear":false,"costs_rent_comment":"","space":"80","region_unclear":false,"region":"Кіровоградська область","costs_rent":""}],"27":[{"costs":"","address":"м. Кіровоград","space_units":"м²","costs_rent_comment":"","space":"84","space_comment":"","region_hidden":false,"costs_comment":"","region":"Кіровоградська область","address_hidden":true,"costs_rent":""}],"29":[{"costs_property_comment":"","address":"","space_units":"м²","space_comment":"","region_hidden":false,"costs_property":"","region":"Кіровоградська область","address_hidden":true,"address_unclear":false,"costs_rent_comment":"","space":"5000","region_unclear":false,"costs_rent":""}],"30":[{"costs_property_comment":"","address":"м. Кіровоград","space_units":"м²","costs_rent_comment":"","space":"50","region":"Кіровоградська область","region_hidden":false,"costs_property":"","space_comment":"","address_hidden":true,"costs_rent":""}],"31":[{"costs_property_comment":"","address":"м. Кіровоград","space_units":"м²","space_unclear":false,"region_hidden":false,"costs_property":"","space_comment":"","address_hidden":false,"address_unclear":false,"costs_rent_comment":"","space":"80","region":"Кіровоградська область","costs_rent":""}],"33":[{"costs_property_comment":"","address":"м. Кіровоград","space_units":"м²","costs_rent_comment":"","space":"84","region":"Кіровоградська область","region_hidden":false,"costs_property":"","space_comment":"","address_hidden":true,"costs_rent":""}],"34":[{"costs_property_comment":"","address":"м. Кіровоград","space_units":"м²","space_unclear":false,"region_hidden":false,"costs_property":"","space_comment":"","address_hidden":true,"space_comment_hidden":false,"costs_rent_comment":"","space":"14","region":"Кіровоградська область","costs_rent":""}]},"vehicle":{"35":[{"year_hidden":false,"brand_info":"1.6 л. 124 к. с","sum_rent_comment":"","brand_unclear":false,"brand_hidden":false,"year":"2011","brand":"Toyota Corolla","brand_info_hidden":false,"sum_rent":"","year_unclear":false,"sum_comment":"","sum_hidden":false,"brand_info_unclear":false,"sum":""}],"40":[{"sum_comment":"","brand_info_hidden":false,"brand_info":"1600 куб. см.","sum":"","brand_unclear":false,"brand_hidden":false,"brand":"ВАЗ 2106","sum_rent":"","sum_rent_comment":"","year":"1991","year_unclear":false},{"sum_comment":"","brand_info_hidden":false,"brand_info":"1100 куб. см.","sum":"","sum_rent_comment":"","brand_hidden":false,"brand":"Таврія","sum_rent":"","brand_info_unclear":false,"year":"2001"}]},"source":"VULYK","income":{"5":{"family_comment":"","family":"30000","comment":"","value_unclear":false,"family_unclear":false,"comment_unclear":false,"value":"203075.36"},"6":{"family_comment":"","comment_unclear":false,"value":"190895.36","family":"20000","comment":""},"7":{"family":"","family_comment":"","value":"","comment":"","source_name":""},"8":{"family_comment":"","value":"","family":"","comment":""},"9":{"family_comment":"","value":"","family":"7000","comment":"","value_unclear":false},"10":{"family_comment":"","value":"12180","family":"","comment":"","value_unclear":false},"11":{"family_comment":"","value":"48","family":"","comment":""},"12":{"family_comment":"","value":"","family":"","comment":""},"13":{"family_comment":"","value":"","family":"","comment":""},"14":{"family_comment":"","value":"","family":"","comment":""},"15":{"family_comment":"","value":"","family":"","comment":""},"16":{"family_comment":"","value":"","family":"","comment":""},"17":{"family_comment":"","value":"","family":"3000","comment":"","value_unclear":false},"18":{"family_comment":"","value":"","family":"","comment":"","value_unclear":false},"19":{"family_comment":"","value":"","family":"","comment":""},"20":{"family_comment":"","family":"","comment":"","value_unclear":false,"family_unclear":false,"comment_unclear":false,"value":""}},"banks":{"51":[{"sum_units":"UAH","sum_comment":"","sum_foreign_units":"UAH","sum":"250000","sum_foreign_comment":"","sum_foreign":""}]},"declaration":{"notfull_lostpages":"","additional_info_text":"","additional_info":"","date":"2015-03-20T00:00:00","notfull":"","url":"http://static.declarations.com.ua/declarations/chosen_ones/judges_batch/2577_zavhorodnii_ievhen_vitaliiovych.pdf"},"general":{"family_raw":"","name":"Євген","full_name_suggest":{"input":["Завгородній Євген Віталійович","Євген Віталійович Завгородній","Євген Завгородній"],"output":"Завгородній Євген Віталійович"},"patronymic":"Віталійович","inn_hidden":true,"addresses":[{"place_city_type_hidden":false,"place_district_hidden":false,"place_address_unclear":false,"place":"Кіровоградська область","place_city":"Кіровоград","place_unclear":false,"place_city_type_unclear":false,"place_city_type":"Місто","place_city_hidden":false,"place_city_unclear":false,"place_district":"","place_district_unclear":false,"place_address":"25006","place_address_hidden":true,"place_hidden":false}],"inn":"","inn_unclear":false,"last_name":"Завгородній","full_name":"Завгородній Євген Віталійович","family":[{"inn":"","inn_unclear":false,"family_name":"Завгородній В. І., 15. 10. 1947","relations_other":"","relations_hidden":false,"name_unclear":false,"inn_hidden":true,"name_hidden":false,"relations":"Батьки"},{"inn":"","family_name":"Завгородня В. В., 09. 07. 1977","relations_other":"","name_unclear":false,"inn_hidden":false,"name_hidden":false,"relations":"Подружжя"},{"inn":"","family_name":"Завгородня Є. Є., 27. 04. 2005","relations_other":"","name_unclear":false,"inn_hidden":false,"name_hidden":false,"relations":"Дитина"},{"inn":"","family_name":"Завгородній З. Є., 23. 04. 2009","relations_other":"","name_unclear":false,"inn_hidden":false,"relations":"Дитина"}],"post":{"post_hidden":false,"office":"Загальний місцевий суд","region_hidden":false,"post":"суддя кіровського районного суд м. кіровограда","candidate":"","region_unclear":false,"region":"Кіровоградська область","office_hidden":false,"post_unclear":false,"office_unclear":false}},"liabilities":{"54":{"sum_comment":"","sum_foreign_comment":"","sum_foreign":"","sum":"","sum_comment_hidden":false},"55":{"sum_comment":"","sum_foreign_comment":"","sum_foreign":"","sum":""},"56":{"sum_comment":"","sum_foreign_comment":"","sum_foreign":"","sum":"20000"},"57":{"sum_comment":"","sum_foreign_comment":"","sum_foreign":"","sum":"","sum_comment_hidden":false},"58":{"sum_comment":"","sum_foreign_comment":"","sum_foreign":"","sum":"","sum_comment_hidden":false},"59":{"sum_comment":"","sum_foreign_comment":"","sum_foreign":"","sum":"5000"},"60":{"sum_comment":"","sum_foreign_comment":"","sum_foreign":"","sum":""},"61":{"sum_comment":"","sum_foreign_comment":"","sum_foreign":"","sum":""},"62":{"sum_comment":"","sum_foreign_comment":"","sum_foreign":"","sum":"11000"},"63":{"sum_comment":"","sum_foreign_comment":"","sum_foreign":"","sum":"","sum_comment_hidden":false},"64":{"sum_comment":"","sum_foreign_comment":"","sum_foreign":"","sum":"","sum_comment_hidden":false}},"intro":{"isnotdeclaration":"","declaration_year_unclear":false,"declaration_year":"2014"}}]