[{"id":"vulyk_60_141","declaration":{"notfull_lostpages":"","additional_info_text":"","additional_info":"","date":"2015-03-30T00:00:00","notfull":"","url":"http://static.declarations.com.ua/declarations/chosen_ones/mega_batch/zav_iazun_serhii_mykhailovych.pdf"},"estate":{"23":[{"address":"Радомишльський р-н, с. Кочерів","space_units":"га","space_hidden":false,"space_unclear":false,"region_hidden":false,"costs_comment":"","space_comment":"земельний пай, отриманий у спадщину, але остаточно не оформлений","address_hidden":false,"costs":"","address_unclear":false,"costs_rent_comment":"","space":"2.69","region":"Житомирська область","costs_rent":""},{"address":"","space_units":"","space_unclear":false,"costs_comment":"","space_comment":"","address_hidden":false,"space":"","address_unclear":false,"costs_rent_comment":"","costs":"","region":"","costs_rent":""},{"costs":"","address":"","space_units":"","costs_rent_comment":"","space":"","space_unclear":false,"space_comment":"","costs_comment":"","region":"","costs_rent":""},{"costs":"","address":"","space_units":"","costs_rent_comment":"","space":"","space_comment":"","costs_comment":"","region":"","costs_rent":""}],"25":[{"address":"м. Коростишів","space_units":"м²","space_hidden":false,"space_unclear":false,"region_hidden":false,"costs_comment":"","space_comment":"","address_hidden":false,"space":"13.7","space_comment_unclear":false,"costs_rent_comment":"","costs":"","region":"Житомирська область","costs_rent":""}],"29":[{"costs_property_comment":"","address":"Коростишівський р-н, с. Колодязьки","space_units":"га","space_hidden":false,"space_unclear":false,"region_hidden":false,"costs_property":"","space_comment":"","space_comment_unclear":false,"space_units_unclear":false,"address_unclear":false,"address_hidden":false,"costs_rent_comment":"","space":".2281","region":"Житомирська область","space_units_hidden":false,"costs_rent":""}],"31":[{"costs_property_comment":"","address":"м. Коростишів","space_units":"м²","space_hidden":false,"space_unclear":false,"region_hidden":false,"costs_property":"","space_comment":"","address_hidden":true,"address_unclear":false,"costs_rent_comment":"","space":"27.32","region":"Житомирська область","costs_rent":""},{"costs_property_comment":"","address":"м. Коростишів","space_units":"м²","costs_rent_comment":"","space":"15.96","region":"Житомирська область","costs_property":"","space_comment":"","costs_rent":""}]},"vehicle":{"35":[{"sum_comment_unclear":false,"sum_rent_comment_hidden":false,"brand_info":"2148 куб. см., 170 к. с., 125 кВт","sum":"","sum_rent_comment":"право користування","brand_hidden":false,"year_hidden":false,"sum_rent_comment_unclear":false,"sum_comment":"","brand_info_hidden":false,"sum_rent":"","brand":"Mercedes-Benz E220","brand_info_unclear":false,"sum_unclear":false,"sum_comment_hidden":false,"year":"2007"}]},"source":"VULYK","income":{"5":{"family":"76940","family_comment":"","comment":"","value_hidden":false,"value_unclear":false,"value":"243907","family_hidden":false,"family_unclear":false},"6":{"family":"75648","family_comment":"","comment":"","value_hidden":false,"value_unclear":false,"value":"228446"},"7":{"family":"","family_comment":"","value":"","comment":"","source_name":""},"8":{"family_comment":"","value":"","family":"","comment":""},"9":{"family_comment":"","value":"","family":"1298","comment":""},"10":{"family_comment":"","family":"","comment":"","value_unclear":false,"family_unclear":false,"value":"13398"},"11":{"family_comment":"","value":"","family":"","comment":""},"12":{"family_comment":"","value":"","family":"","comment":""},"13":{"family_comment":"","value":"","family":"","comment":""},"14":{"family_comment":"","value":"","family":"","comment":"","value_unclear":false},"15":{"family_comment":"","value":"","family":"","comment":""},"16":{"family_comment":"","value":"","family":"","comment":""},"17":{"family_comment":"","value":"","family":"","comment":""},"18":{"family_comment":"","value":"","family":"","comment":""},"19":{"family_comment":"","value":"2063","family":"","comment":"","family_comment_unclear":false},"20":{"family_comment":"","comment":"","family":"","value_unclear":false,"comment_unclear":false,"value":""}},"banks":{"45":[{"sum_comment_unclear":false,"sum_comment":"","sum_foreign_units":"UAH","sum":"","sum_foreign_comment":"","sum_foreign":"","sum_unclear":false,"sum_units":"UAH"}],"46":[{"sum_units":"UAH","sum_comment":"","sum_foreign_units":"UAH","sum":"","sum_foreign_comment":"","sum_foreign":""}],"47":[{"sum_units":"UAH","sum_comment":"","sum_foreign_units":"UAH","sum":"","sum_foreign_comment":"","sum_foreign":""}],"48":[{"sum_units":"UAH","sum_comment":"","sum_foreign_units":"UAH","sum":"","sum_foreign_comment":"","sum_foreign":""}],"49":[{"sum_units":"UAH","sum_comment":"","sum_foreign_units":"UAH","sum":"","sum_foreign_comment":"","sum_foreign":""}],"50":[{"sum_units":"UAH","sum_comment":"","sum_foreign_units":"UAH","sum":"","sum_foreign_comment":"","sum_foreign":""}],"51":[{"sum_units":"UAH","sum_comment":"","sum_foreign_units":"UAH","sum":"114415","sum_foreign_comment":"","sum_foreign":"","sum_unclear":false}],"52":[{"sum_units":"UAH","sum_comment":"","sum_foreign_units":"UAH","sum":"","sum_foreign_comment":"","sum_foreign":""}],"53":[{"sum_units":"UAH","sum_comment":"","sum_foreign_units":"UAH","sum":"","sum_foreign_comment":"","sum_foreign":""}]},"ft_src":"2148 куб. см., 170 к. с., 125 кВт\nправо користування\n2007\nMercedes-Benz E220\n114415\n2014\n2148 куб. см., 170 к. с., 125 кВт\nправо користування\nMercedes-Benz E220\n2007\n114415\n2.69\nземельний пай, отриманий у спадщину, але остаточно не оформлений\nРадомишльський р-н, с. Кочерів\nЖитомирська область\nЖитомирська область\nКоростишівський р-н, с. Колодязьки\n.2281\n27.32\nЖитомирська область\nм. Коростишів\n15.96\nм. Коростишів\nЖитомирська область\n13.7\nм. Коростишів\nЖитомирська область\nЗав'язун Сергій Михайлович\nСергій Михайлович Зав'язун\nСергій Зав'язун\nЗав'язун Сергій Михайлович\nЗав'язун Сергій Михайлович\nПодружжя\nДитина\nСергій\nМихайлович\nсуддя апеляційного суду житомирської області\nЖитомирська область\nЗагальний апеляційний суд\nЗав'язун\n228446\n75648\n76940\n243907\n13398\n1298\n2063\n2014\nземельний пай, отриманий у спадщину, але остаточно не оформлений\nРадомишльський р-н, с. Кочерів\n2.69\nЖитомирська область\nЖитомирська область\nКоростишівський р-н, с. Колодязьки\n.2281\nм. Коростишів\nЖитомирська область\n27.32\nЖитомирська область\nм. Коростишів\n15.96\nм. Коростишів\nЖитомирська область\n13.7\nПодружжя\nДитина\nСергій\nМихайлович\nЗав'язун\nЗав'язун Сергій Михайлович\nСергій Михайлович Зав'язун\nСергій Зав'язун\nЗав'язун Сергій Михайлович\nсуддя апеляційного суду житомирської області\nЖитомирська область\nЗагальний апеляційний суд\nЗав'язун Сергій Михайлович\n75648\n228446\n13398\n76940\n243907\n2063\n1298","general":{"family_raw":"","name":"Сергій","full_name_suggest":{"input":["Зав'язун Сергій Михайлович","Сергій Михайлович Зав'язун","Сергій Зав'язун"],"output":"Зав'язун Сергій Михайлович"},"patronymic":"Михайлович","inn_hidden":true,"inn":"","addresses":[{"place_city_type_hidden":false,"place_city_type":"","place_city_hidden":true,"place_hidden":true,"place_district":"","place_district_hidden":false,"place":"","place_address":"","place_address_hidden":true,"place_city":""}],"last_name":"Зав'язун","full_name":"Зав'язун Сергій Михайлович","family":[{"inn":"","family_name":"","relations_other":"","relations_hidden":false,"name_unclear":false,"inn_hidden":true,"name_hidden":true,"relations":"Подружжя"},{"inn":"","family_name":"","relations_other":"","name_unclear":false,"inn_hidden":true,"name_hidden":true,"relations":"Дитина"}],"post":{"post_hidden":false,"office":"Загальний апеляційний суд","region":"Житомирська область","post_unclear":false,"post":"суддя апеляційного суду житомирської області"},"last_name_unclear":false},"liabilities":{"54":{"sum_comment":"","sum_foreign_comment":"","sum_foreign":"","sum":""},"55":{"sum_comment":"","sum_foreign_comment":"","sum_foreign":"","sum":""},"56":{"sum_comment":"","sum_foreign_comment":"","sum_foreign":"","sum":""},"57":{"sum_comment":"","sum_foreign_comment":"","sum_foreign":"","sum_unclear":false,"sum":""},"58":{"sum_comment":"","sum_foreign_comment":"","sum_foreign":"","sum":""},"59":{"sum_comment":"","sum_foreign_comment":"","sum_foreign":"","sum":""},"60":{"sum_comment":"","sum_foreign_comment":"","sum_foreign":"","sum":""},"61":{"sum_comment":"","sum_foreign_comment":"","sum_foreign":"","sum":""},"62":{"sum_comment_unclear":false,"sum_comment":"","sum":"","sum_foreign_comment":"","sum_foreign":"","sum_unclear":false},"63":{"sum_comment":"","sum_foreign_comment":"","sum_foreign":"","sum":""},"64":{"sum_comment":"","sum_foreign_comment":"","sum_foreign":"","sum":""}},"intro":{"isnotdeclaration":"","declaration_year_unclear":false,"declaration_year":"2014"}},{"ft_src":"керування за дорученням\nMercedes-Benz,E-class\n2007\nЖитомирська область, Коростишівський район, с.Колодязьки\n2281\nм. Коростишів\n43,66\nКоростишів, приховано\n13,7\n200000\nTRUE\nПозначку поставив помилково, прибрати її не вдається.\nFALSE\nFALSE\n2013\n61829\n206540\n12659\n12617\n82618\n254711\n8130\n35554\nMercedes-Benz,E-class\n2007\nкерування за дорученням\nПозначку поставив помилково, прибрати її не вдається.\nFALSE\nTRUE\nЖитомирська область, Коростишівський район, с.Колодязьки\n2281\nм. Коростишів\n43,66\nКоростишів, приховано\n13,7\nСуддя апеляційного суду Житомирської області\nДружина - Зав’язун О.М.;дочка - Зав’язун О.С.\nЗав'язун\nЗав’язун Сергій Михайлович\nСергій Михайлович Зав’язун\nСергій Зав’язун\nЗав’язун Сергій Михайлович\nСергій\nЗав'язун Сергій Михайлович\nЗагальний апеляційний суд\nСуддя\nЖитомирська область\nМихайлович\n206540\n61829\n35554\n254711\n82618\n12617\n12659\n8130\n200000\n2013\nFALSE\nЗав'язун\nМихайлович\nДружина - Зав’язун О.М.;дочка - Зав’язун О.С.\nЗав'язун Сергій Михайлович\nСергій Михайлович Зав'язун\nСергій Зав'язун\nЗав'язун Сергій Михайлович\nСергій\nСуддя апеляційного суду Житомирської області\nСуддя\nЖитомирська область\nЗагальний апеляційний суд\nЗав'язун Сергій Михайлович","estate":{"23":[{"costs":"","address":"","space_units":"","costs_rent_comment":"","space":"","costs_comment":"","costs_rent":"","space_comment":"","region":"","location_raw":""},{"costs":"","address":"","space_units":"","costs_rent_comment":"","space":"","costs_comment":"","costs_rent":"","space_comment":"","region":"","location_raw":""},{"costs":"","address":"","space_units":"","costs_rent_comment":"","space":"","costs_comment":"","costs_rent":"","space_comment":"","region":"","location_raw":""}],"25":[{"costs":"","address":"","space_units":"","costs_rent_comment":"","space":"13,7","costs_comment":"","costs_rent":"","space_comment":"","region":"","location_raw":"Коростишів, приховано"}],"29":[{"costs_property_comment":"","address":"","space_units":"","costs_rent_comment":"","space":"2281","space_comment":"","costs_property":"","region":"","location_raw":"Житомирська область, Коростишівський район, с.Колодязьки","costs_rent":""}],"31":[{"costs_property_comment":"","address":"","space_units":"","costs_rent_comment":"","space":"43,66","space_comment":"","costs_property":"","region":"","location_raw":"м. Коростишів","costs_rent":""}]},"vehicle":{"35":[{"sum_comment":"керування за дорученням","brand_info":"","sum":"","sum_rent_comment":"","year":"2007","brand":"Mercedes-Benz,E-class","sum_rent":"","brand_hidden":false}]},"id":"2802","income":{"5":{"family_comment":"","value":"254711","family":"82618","comment":""},"6":{"family_comment":"","value":"206540","family":"61829","comment":""},"7":{"family":"0","family_comment":"","value":"0","comment":"","source_name":"0"},"8":{"family_comment":"","value":"0","family":"0","comment":""},"9":{"family_comment":"","value":"0","family":"8130","comment":""},"10":{"family_comment":"","value":"12617","family":"12659","comment":""},"11":{"family_comment":"","value":"0","family":"0","comment":""},"12":{"family_comment":"","value":"0","family":"0","comment":""},"13":{"family_comment":"","value":"0","family":"0","comment":""},"14":{"family_comment":"","value":"0","family":"0","comment":""},"15":{"family_comment":"","value":"0","family":"0","comment":""},"16":{"family_comment":"","value":"0","family":"0","comment":""},"17":{"family_comment":"","value":"0","family":"0","comment":""},"18":{"family_comment":"","value":"0","family":"0","comment":""},"19":{"family_comment":"","value":"0","family":"0","comment":""},"20":{"family_comment":"","value":"35554","family":"0","comment":""},"21":[{"country_comment":"","uah_equal":"0","country":"0","cur":"0"},{"country_comment":"","uah_equal":"0","country":"0","cur":"0"},{"country_comment":"","uah_equal":"0","country":"0","cur":"0"},{"country_comment":"","uah_equal":"0","country":"0","cur":"0"},{"country_comment":"","uah_equal":"0","country":"0","cur":"0"}],"22":[{"country_comment":"","uah_equal":"0","country":"0","cur":"0"},{"country_comment":"","uah_equal":"0","country":"0","cur":"0"},{"country_comment":"","uah_equal":"0","country":"0","cur":"0"},{"country_comment":"","uah_equal":"0","country":"0","cur":"0"},{"country_comment":"","uah_equal":"0","country":"0","cur":"0"}]},"banks":{"45":[{"sum_units":"UAH","sum_comment":"","sum_foreign_units":"","sum":"","sum_foreign_comment":"","sum_foreign":""},{"sum_units":"USD","sum_comment":"","sum_foreign_units":"","sum":"","sum_foreign_comment":"","sum_foreign":""},{"sum_units":"EUR","sum_comment":"","sum_foreign_units":"","sum":"","sum_foreign_comment":"","sum_foreign":""}],"46":[{"sum_units":"UAH","sum_comment":"","sum_foreign_units":"","sum":"","sum_foreign_comment":"","sum_foreign":""},{"sum_units":"USD","sum_comment":"","sum_foreign_units":"","sum":"","sum_foreign_comment":"","sum_foreign":""},{"sum_units":"EUR","sum_comment":"","sum_foreign_units":"","sum":"","sum_foreign_comment":"","sum_foreign":""}],"47":[{"sum_units":"","sum_comment":"","sum_foreign_units":"","sum":"","sum_foreign_comment":"","sum_foreign":""}],"48":[{"sum_units":"","sum_comment":"","sum_foreign_units":"","sum":"","sum_foreign_comment":"","sum_foreign":""}],"49":[{"sum_units":"","sum_comment":"","sum_foreign_units":"","sum":"","sum_foreign_comment":"","sum_foreign":""}],"50":[{"sum_units":"","sum_comment":"","sum_foreign_units":"","sum":"","sum_foreign_comment":"","sum_foreign":""}],"51":[{"sum_units":"UAH","sum_comment":"","sum_foreign_units":"","sum":"200000","sum_foreign_comment":"","sum_foreign":""},{"sum_units":"USD","sum_comment":"","sum_foreign_units":"","sum":"","sum_foreign_comment":"","sum_foreign":""},{"sum_units":"EUR","sum_comment":"","sum_foreign_units":"","sum":"","sum_foreign_comment":"","sum_foreign":""}],"52":[{"sum_units":"","sum_comment":"","sum_foreign_units":"","sum":"","sum_foreign_comment":"","sum_foreign":""}],"53":[{"sum_units":"","sum_comment":"","sum_foreign_units":"","sum":"","sum_foreign_comment":"","sum_foreign":""}]},"declaration":{"notfull_lostpages":"","additional_info_text":"Позначку поставив помилково, прибрати її не вдається.","additional_info":"TRUE","notfull":"FALSE","url":"http://static.declarations.com.ua/declarations/sudy/apeliatsiini_sudy_oblastei__m.kyieva/zhytomyrska/zavyazun_s_m.pdf","needs_scancopy_check":false},"general":{"family_raw":"Дружина - Зав’язун О.М.;дочка - Зав’язун О.С.","name":"Сергій","full_name_suggest":{"input":["Зав'язун Сергій Михайлович","Сергій Михайлович Зав'язун","Сергій Зав'язун"],"output":"Зав'язун Сергій Михайлович"},"post_raw":"Суддя апеляційного суду Житомирської області","name_unclear":false,"patronymic":"Михайлович","patronymic_unclear":false,"last_name_hidden":false,"patronymic_hidden":false,"inn":"","addresses_raw_hidden":true,"last_name":"Зав'язун","full_name":"Зав'язун Сергій Михайлович","post":{"office":"Загальний апеляційний суд","region":"Житомирська область","post":"Суддя"},"addresses_raw":"приховано","name_hidden":false,"last_name_unclear":false},"liabilities":{"54":{"sum_comment":"","sum_foreign_comment":"","sum_foreign":"","sum":""},"55":{"sum_units":"","sum_comment":"","sum_foreign_units":"","sum":"","sum_foreign_comment":"","sum_foreign":""},"56":{"sum_comment":"","sum_foreign_comment":"","sum_foreign":"","sum":""},"57":{"sum_comment":"","sum_foreign_comment":"","sum_foreign":"","sum":""},"58":{"sum_comment":"","sum_foreign_comment":"","sum_foreign":"","sum":""},"59":{"sum_comment":"","sum_foreign_comment":"","sum_foreign":"","sum":""},"60":{"sum_comment":"","sum_foreign_comment":"","sum_foreign":"","sum":""},"61":{"sum_units":"","sum_comment":"","sum_foreign_units":"","sum":"","sum_foreign_comment":"","sum_foreign":""},"62":{"sum_comment":"","sum_foreign_comment":"","sum_foreign":"","sum":""},"63":{"sum_comment":"","sum_units":"","sum_foreign":"","sum":"","sum_foreign_comment":""},"64":{"sum_comment":"","sum_units":"","sum_foreign":"","sum":"","sum_foreign_comment":""}},"intro":{"isnotdeclaration":"FALSE","declaration_year":"2013"}}]