[{"id":"vulyk_61_161","ft_src":"1.6 л\nKia Soul\n2010\nОсиківська с/р\nБердичівський р-н, с. Дубова\n.25\nЖитомирська область\nгаражний кооператив\n36\nЖитомирська область\nм. Бердичів\n67\n2014\n17400\n241452\n17400\n295470\nпенсія, допомога ЧАЕС\n54017\n1.6 л\nKia Soul\n2010\n.25\nОсиківська с/р\nЖитомирська область\nБердичівський р-н, с. Дубова\n36\nгаражний кооператив\n67\nм. Бердичів\nЖитомирська область\nПодружжя\nДружина\nЗайцев Анатолій Володимирович\nАнатолій Володимирович Зайцев\nАнатолій Зайцев\nЗайцев Анатолій Володимирович\nАнатолій\nЗайцев Анатолій Володимирович\nЗайцев\nЖитомирська область\nЗагальний місцевий суд\nсуддя бердичівського міськрайонного суду житомирської області\nВолодимирович\n250\n17400\n241452\n54017\nпенсія, допомога ЧАЕС\n295470\n17400\n2014\n250\nДружина\nПодружжя\nВолодимирович\nЗайцев\nЗайцев Анатолій Володимирович\nАнатолій Володимирович Зайцев\nАнатолій Зайцев\nЗайцев Анатолій Володимирович\nЖитомирська область\nсуддя бердичівського міськрайонного суду житомирської області\nЗагальний місцевий суд\nЗайцев Анатолій Володимирович\nАнатолій","estate":{"23":[{"address":"Бердичівський р-н, с. Дубова","space_units":"га","costs_comment":"","space_unclear":false,"region_hidden":false,"space_units_unclear":false,"space_comment":"Осиківська с/р","address_hidden":false,"costs":"","address_unclear":false,"space_comment_unclear":false,"costs_rent_comment":"","space":".25","region_unclear":false,"region":"Житомирська область","costs_rent":""}],"25":[{"costs_unclear":false,"address":"м. Бердичів","space_units":"м²","space_hidden":false,"space_unclear":false,"region_hidden":false,"costs_comment":"","space_comment":"","space_comment_unclear":false,"costs":"","address_unclear":false,"address_hidden":false,"costs_comment_unclear":false,"costs_rent_comment":"","space":"67","region_unclear":false,"region":"Житомирська область","costs_rent":""}],"27":[{"address":"","space_units":"м²","costs_rent_unclear":false,"space_comment":"гаражний кооператив","region_hidden":false,"costs_comment":"","address_hidden":false,"space":"36","address_unclear":false,"costs_rent_comment":"","costs":"","region":"","costs_rent":""}]},"vehicle":{"35":[{"year_hidden":false,"brand_info":"1.6 л","sum_rent_comment":"","brand_unclear":false,"brand_hidden":false,"year":"2010","sum_hidden":false,"sum_comment":"","brand_info_hidden":false,"sum_rent":"","brand":"Kia Soul","year_unclear":false,"brand_info_unclear":false,"sum":""}]},"source":"VULYK","income":{"5":{"family_comment":"","comment":"","family":"17400","value_unclear":false,"family_unclear":false,"comment_unclear":false,"value":"295470","family_comment_unclear":false},"6":{"family_comment":"","family":"17400","comment":"","value_unclear":false,"family_unclear":false,"value":"241452"},"7":{"source_name_hidden":false,"family_comment":"","comment":"","family":"","value_unclear":false,"source_name_unclear":false,"value":"","source_name":""},"8":{"family_comment":"","value":"","family":"","comment":""},"9":{"family_comment":"","value":"","family":"","comment":""},"10":{"family_comment":"","value":"","family":"","comment":"","value_unclear":false},"11":{"family":"","family_comment":"","comment":"","value_hidden":false,"value_unclear":false,"value":""},"12":{"family":"","family_comment":"","value":"","comment":"","value_hidden":false},"13":{"family_comment":"","value":"","family":"","comment":""},"14":{"family_comment":"","value":"","family":"","comment":""},"15":{"family_comment":"","value":"","family":"","comment":""},"16":{"family_comment":"","value":"","family":"","comment":""},"17":{"family_comment":"","value":"","family":"","comment":""},"18":{"family_comment":"","value":"","family":"","comment":""},"19":{"family_comment":"","value":"","family_unclear":false,"family":"","comment":""},"20":{"family_comment":"","value":"54017","family_unclear":false,"family":"","comment":"пенсія, допомога ЧАЕС"}},"general":{"family":[{"inn":"","family_name":"Дружина","relations_other":"","relations_hidden":false,"relations_unclear":false,"name_unclear":false,"inn_hidden":false,"name_hidden":true,"relations":"Подружжя"}],"family_raw":"","name":"Анатолій","full_name_suggest":{"input":["Зайцев Анатолій Володимирович","Анатолій Володимирович Зайцев","Анатолій Зайцев"],"output":"Зайцев Анатолій Володимирович"},"name_unclear":false,"patronymic":"Володимирович","inn_hidden":true,"patronymic_unclear":false,"patronymic_hidden":false,"inn":"","inn_unclear":false,"last_name":"Зайцев","full_name":"Зайцев Анатолій Володимирович","post":{"post_hidden":false,"office":"Загальний місцевий суд","post_unclear":false,"post":"суддя бердичівського міськрайонного суду житомирської області","region_hidden":false,"region":"Житомирська область","region_unclear":false,"office_hidden":false},"addresses":[{"place_city_type_hidden":false,"place_district_hidden":false,"place_address_unclear":false,"place":"","place_city":"","place_city_type":"","place_city_hidden":false,"place_district":"","place_district_unclear":false,"place_address":"","place_address_hidden":false,"place_hidden":true}],"last_name_unclear":false},"liabilities":{"54":{"sum_comment_unclear":false,"sum_comment":"","sum":"250","sum_foreign_comment":"","sum_foreign":"","sum_unclear":false},"55":{"sum_comment":"","sum_foreign_comment":"","sum_foreign":"","sum":""},"56":{"sum_comment":"","sum_foreign_comment":"","sum_foreign":"","sum_unclear":false,"sum":""},"57":{"sum_comment":"","sum":"","sum_foreign_comment":"","sum_foreign":"","sum_unclear":false,"sum_comment_hidden":false},"58":{"sum_comment":"","sum_foreign_comment":"","sum_foreign":"","sum_unclear":false,"sum":""},"59":{"sum_comment":"","sum_foreign_comment":"","sum_foreign":"","sum":""},"60":{"sum_comment":"","sum_hidden":false,"sum":"","sum_foreign_comment":"","sum_foreign":"","sum_foreign_hidden":false},"61":{"sum_comment":"","sum_foreign_comment":"","sum_foreign":"","sum":""},"62":{"sum_comment":"","sum_foreign_comment":"","sum_foreign":"","sum_unclear":false,"sum":""},"63":{"sum_comment":"","sum_hidden":false,"sum":"","sum_foreign_comment":"","sum_foreign":"","sum_unclear":false},"64":{"sum_comment":"","sum_foreign_comment":"","sum_foreign":"","sum_hidden":false,"sum":""}},"declaration":{"notfull_lostpages":"","additional_info_text":"","additional_info":"","date":"2015-03-23T00:00:00","notfull":"","url":"http://static.declarations.com.ua/declarations/chosen_ones/mega_batch/zaitsev_anatolii_volodymyrovych.pdf"},"intro":{"declaration_year_hidden":false,"isnotdeclaration":"","declaration_year":"2014"}}]