[{"id":"vulyk_41_61","declaration":{"additional_info_text":"","additional_info":"","date":"2015-02-10T00:00:00","url":"http://static.declarations.com.ua/declarations/chosen_ones/mega_batch/zhukova_ievheniia_oleksiivna.pdf"},"estate":{"23":[{"address":"","space_units":"м²","costs_comment":"","space_unclear":false,"region_hidden":false,"space_units_unclear":false,"space_comment":"","address_hidden":false,"space_comment_hidden":false,"space":"","costs_comment_unclear":false,"costs_rent_comment":"","costs":"","region_unclear":false,"region":"","costs_rent":""},{"costs":"","address":"","space_units":"","costs_rent_comment":"","space":"","space_unclear":false,"space_comment":"","costs_comment":"","region":"","costs_rent":""},{"costs":"","address":"","space_units":"","costs_rent_comment":"","space":"","space_comment":"","costs_comment":"","region":"","costs_rent":""}],"25":[{"costs_unclear":false,"address":"м. Дніпропетровськ","space_units":"м²","space_hidden":false,"space_unclear":false,"region_hidden":false,"costs_rent_comment":"","space_comment":"","address_hidden":true,"costs":"","costs_comment_unclear":false,"costs_comment":"","space":"60.2","region_unclear":false,"region":"Дніпропетровська область","costs_rent":""}],"31":[{"costs_property_comment":"","address":"м. Дніпропетровськ","space_units":"м²","space_hidden":false,"space_comment":"","region_hidden":false,"costs_property":"","region":"Дніпропетровська область","address_hidden":true,"space_comment_unclear":false,"costs_rent_comment":"","space":"148.9","costs_rent":""}],"34":[{"costs_property_comment":"","address":"м. Дніпропетровськ","space_units":"м²","costs_rent_comment":"","space":"87.8","region":"Дніпропетровська область","region_hidden":true,"costs_property":"","space_comment":"офісне приміщення","address_hidden":true,"costs_rent":""},{"costs_property_comment":"","address":"м. Дніпропетровськ","space_units":"м²","costs_rent_comment":"","space":"21.9","region":"Дніпропетровська область","costs_property":"","space_comment":"паркувальне місце","costs_rent":""}]},"vehicle":{"35":[{"sum_comment":"","brand_info_hidden":false,"brand_info":"1595","sum":"","sum_rent_comment":"","year":"2009","brand":"Volkswagen Golf","sum_rent":""}],"40":[{"sum_comment":"","brand_info_hidden":false,"brand_info":"2967","sum":"","sum_rent_comment":"","year":"2012","brand":"Volkswagen Touareg","sum_rent":""}]},"source":"VULYK","income":{"5":{"family_comment":"","family":"119063","comment":"","family_unclear":false,"family_hidden":false,"value":"109425"},"6":{"family_comment":"","family_hidden":false,"value":"95715","family":"24774","comment":""},"7":{"family":"14765","family_comment":"","value":"","comment":"","source_name":"Національна академія держ. управління при Президентові України ДРІДУ Дніпропетровське РВ НШС України"},"8":{"family_comment":"","value":"","family":"","comment":""},"9":{"family_comment":"","comment":"","family":"28240","comment_unclear":false,"value":"","family_hidden":false},"10":{"family_comment":"","value":"","family":"","comment":""},"11":{"family_comment":"","value":"","family":"","comment":""},"12":{"family_comment":"","value":"","family":"","comment":""},"13":{"family_comment":"","value":"","family":"","comment":""},"14":{"family_comment":"","value":"","family":"","comment":""},"15":{"family_comment":"","value":"","family":"","comment":"","value_unclear":false},"16":{"family_comment":"","value":"","family":"","comment":""},"17":{"family_comment":"","value":"","family":"20500","comment":""},"18":{"family_comment":"","value":"","family":"","comment":""},"19":{"family_comment":"","value":"","family":"","comment":""},"20":{"family_comment":"","family":"30784","value_hidden":false,"comment":"","comment_hidden":false,"comment_unclear":false,"value_unclear":false,"value":"13710","family_hidden":false,"family_comment_hidden":false}},"banks":{"45":[{"sum_units":"UAH","sum_comment":"","sum_foreign_units":"UAH","sum_hidden":false,"sum":"","sum_foreign_comment":"","sum_foreign_unclear":false,"sum_foreign":"","sum_comment_hidden":false},{"sum_units":"","sum_comment":"","sum_foreign_units":"","sum":"","sum_foreign_comment":"","sum_foreign_unclear":false,"sum_foreign":""}],"46":[{"sum_units":"UAH","sum_comment":"","sum_foreign_units":"UAH","sum":"","sum_foreign_comment":"","sum_foreign":"","sum_unclear":false,"sum_comment_hidden":false},{"sum_units":"","sum_comment":"","sum_foreign_units":"","sum":"","sum_foreign_comment":"","sum_foreign":"","sum_unclear":false}],"47":[{"sum_units":"UAH","sum_comment":"","sum_foreign_units":"UAH","sum":"","sum_foreign_comment":"","sum_foreign":""},{"sum_units":"","sum_comment":"","sum_foreign_units":"","sum":"","sum_foreign_comment":"","sum_foreign":""}],"48":[{"sum_units":"UAH","sum_comment":"","sum_foreign_units":"UAH","sum":"","sum_foreign_comment":"","sum_foreign":""}],"49":[{"sum_units":"UAH","sum_comment":"","sum_foreign_units":"UAH","sum":"","sum_foreign_comment":"","sum_foreign":""}],"50":[{"sum_units":"UAH","sum_comment":"","sum_foreign_units":"UAH","sum":"","sum_foreign_comment":"","sum_foreign":""}],"51":[{"sum_units":"UAH","sum_comment":"","sum_foreign_units":"UAH","sum_hidden":false,"sum":"","sum_foreign_comment":"","sum_foreign":"","sum_unclear":false,"sum_comment_hidden":false},{"sum_units":"","sum_comment":"","sum_foreign_units":"","sum":"","sum_foreign_comment":"","sum_foreign":""}],"52":[{"sum_units":"UAH","sum_comment":"","sum_foreign_units":"UAH","sum":"","sum_foreign_comment":"","sum_foreign":"","sum_unclear":false,"sum_comment_hidden":false}],"53":[{"sum_units":"UAH","sum_comment":"","sum_foreign_units":"UAH","sum":"135370","sum_foreign_comment":"","sum_foreign":"","sum_comment_hidden":true},{"sum_units":"","sum_comment":"","sum_foreign_units":"","sum":"","sum_foreign_comment":"","sum_foreign":""},{"sum_units":"","sum_comment":"","sum_foreign_units":"","sum":"","sum_foreign_comment":"","sum_foreign":""}]},"ft_src":"1595\n2009\nVolkswagen Golf\n2967\n2012\nVolkswagen Touareg\n135370\n2014\nVolkswagen Golf\n1595\n2009\nVolkswagen Touareg\n2967\n2012\n135370\n148.9\nм. Дніпропетровськ\nДніпропетровська область\n87.8\nофісне приміщення\nм. Дніпропетровськ\nДніпропетровська область\n21.9\nпаркувальне місце\nДніпропетровська область\nм. Дніпропетровськ\n60.2\nм. Дніпропетровськ\nДніпропетровська область\nПодружжя\nЖуков С. В\nДитина\nЖуков С. С\nДитина\nЖукова Д. С\nІванова Л. С\nБатьки\nЖукова Євгенія Олексіївна\nЄвгенія Олексіївна Жукова\nЄвгенія Жукова\nЖукова Євгенія Олексіївна\nЖукова Євгенія Олексіївна\nЄвгенія\nОлексіївна\nАдміністративний місцевий суд\nсуддя дніпропетровського окружного адміністративного суду\nДніпропетровська область\nЖукова\n49000\nДніпропетровська область\nДніпропетровськ\n528\n447\nНаціональна академія держ. управління при Президентові України ДРІДУ Дніпропетровське РВ НШС України\n14765\n95715\n24774\n20500\n13710\n30784\n109425\n119063\n28240\n2014\n447\n528\nДніпропетровська область\nофісне приміщення\nм. Дніпропетровськ\n87.8\nДніпропетровська область\nпаркувальне місце\nм. Дніпропетровськ\n21.9\nм. Дніпропетровськ\nДніпропетровська область\n148.9\nм. Дніпропетровськ\n60.2\nДніпропетровська область\nЖуков С. В\nПодружжя\nЖуков С. С\nДитина\nЖукова Д. С\nДитина\nБатьки\nІванова Л. С\nОлексіївна\nЖукова\nЄвгенія\nЖукова Євгенія Олексіївна\nЄвгенія Олексіївна Жукова\nЄвгенія Жукова\nЖукова Євгенія Олексіївна\nДніпропетровська область\nДніпропетровськ\n49000\nДніпропетровська область\nсуддя дніпропетровського окружного адміністративного суду\nАдміністративний місцевий суд\nЖукова Євгенія Олексіївна\n24774\n95715\n14765\nНаціональна академія держ. управління при Президентові України ДРІДУ Дніпропетровське РВ НШС України\n119063\n109425\n20500\n28240\n30784\n13710","general":{"family":[{"inn":"","family_name":"Жуков С. В","relations_hidden":false,"name_unclear":false,"inn_hidden":true,"name_hidden":true,"relations":"Подружжя"},{"inn":"","family_name":"Жуков С. С","relations_other":"","name_unclear":false,"inn_hidden":false,"name_hidden":false,"relations":"Дитина"},{"inn":"","family_name":"Жукова Д. С","relations_other":"","name_unclear":false,"inn_hidden":false,"name_hidden":false,"relations":"Дитина"},{"inn":"","family_name":"Іванова Л. С","relations_other":"","relations":"Батьки"}],"family_raw":"","name":"Євгенія","full_name_suggest":{"input":["Жукова Євгенія Олексіївна","Євгенія Олексіївна Жукова","Євгенія Жукова"],"output":"Жукова Євгенія Олексіївна"},"name_unclear":false,"patronymic":"Олексіївна","inn_hidden":true,"patronymic_hidden":false,"inn":"","addresses":[{"place_city_type_hidden":false,"place_city_type":"Місто","place_city_hidden":false,"place_hidden":true,"place_district":"","place_district_hidden":false,"place":"Дніпропетровська область","place_address":"49000","place_address_hidden":true,"place_city":"Дніпропетровськ"}],"last_name":"Жукова","full_name":"Жукова Євгенія Олексіївна","post":{"post_hidden":false,"office":"Адміністративний місцевий суд","post":"суддя дніпропетровського окружного адміністративного суду","office_hidden":false,"region":"Дніпропетровська область","region_hidden":false,"post_unclear":false},"last_name_unclear":false},"liabilities":{"54":{"sum_comment":"","sum_foreign_comment":"","sum_foreign":"","sum":"447","sum_comment_hidden":true},"55":{"sum_comment":"","sum_foreign_comment":"","sum_foreign":"","sum":""},"56":{"sum_comment":"","sum_foreign_comment":"","sum_foreign":"","sum_hidden":false,"sum":""},"57":{"sum_comment":"","sum":"","sum_foreign_comment":"","sum_foreign":"","sum_unclear":false,"sum_comment_hidden":false},"58":{"sum_comment":"","sum_foreign_comment":"","sum_foreign":"","sum":"","sum_comment_hidden":false},"59":{"sum_comment":"","sum_foreign_comment":"","sum_foreign":"","sum":""},"60":{"sum_comment":"","sum_foreign_comment":"","sum_foreign":"","sum":"528","sum_comment_hidden":true},"61":{"sum_comment":"","sum_foreign_comment":"","sum_foreign":"","sum":""},"62":{"sum_comment":"","sum_foreign_comment":"","sum_foreign":"","sum":""},"63":{"sum_comment":"","sum":"","sum_foreign_comment":"","sum_foreign":"","sum_unclear":false,"sum_comment_hidden":false},"64":{"sum_comment":"","sum_foreign_comment":"","sum_foreign":"","sum":"","sum_comment_hidden":false}},"intro":{"declaration_year":"2014"}},{"ft_src":"Volkswagen,Golf\n2009\nVolkswagen,Touareg\n2012\nофісне приміщення, м. Дніпропетровськ\n87,8\nпаркувальне місце, м. Дніпропетровськ\n21,9\nм. Дніпропетровськ\n148,9\nм. Дніпропетровськ\n60,2\n27220\nFALSE\nFALSE\nFALSE\n2013\n77929\n72182\n116\n362404\n142489\n82000\n172520\n29839\n70307\nVolkswagen,Golf\n2009\nVolkswagen,Touareg\n2012\nFALSE\nFALSE\nм. Дніпропетровськ\n148,9\nофісне приміщення, м. Дніпропетровськ\n87,8\nпаркувальне місце, м. Дніпропетровськ\n21,9\nм. Дніпропетровськ\n60,2\nСуддя Дніпропетровського окружного адміністративного суду\nЧоловік Жуков С.В.;син Жуков  С.С.;донька Жукова Д.С.;мати Іванова Л.С.\nДніпропетровська\nДніпропетровськ\nЖукова\nЖукова Євгенія Олексіївна\nЄвгенія Олексіївна Жукова\nЄвгенія Жукова\nЖукова Євгенія Олексіївна\nЄвгенія\nЖукова Євгенія Олексіївна\nАдміністративний місцевий суд\nСуддя\nДніпропетровська область\nОлексіївна\nприховано;м Дніпропетровськ, 49000\n116\n72182\n77929\n172520\n70307\n29839\n142489\n362404\n82000\n27220\n2013\nFALSE\nЖукова\nОлексіївна\nЧоловік Жуков С.В.;син Жуков  С.С.;донька Жукова Д.С.;мати Іванова Л.С.\nЖукова Євгенія Олексіївна\nЄвгенія Олексіївна Жукова\nЄвгенія Жукова\nЖукова Євгенія Олексіївна\nЄвгенія\nСуддя Дніпропетровського окружного адміністративного суду\nДніпропетровська\nДніпропетровськ\nСуддя\nДніпропетровська область\nАдміністративний місцевий суд\nЖукова Євгенія Олексіївна\nприховано;м Дніпропетровськ, 49000","estate":{"23":[{"costs":"","address":"","space_units":"","costs_rent_comment":"","space":"","costs_comment":"","costs_rent":"","space_comment":"","region":"","location_raw":""},{"costs":"","address":"","space_units":"","costs_rent_comment":"","space":"","costs_comment":"","costs_rent":"","space_comment":"","region":"","location_raw":""},{"costs":"","address":"","space_units":"","costs_rent_comment":"","space":"","costs_comment":"","costs_rent":"","space_comment":"","region":"","location_raw":""}],"25":[{"costs":"","address":"","space_units":"","costs_rent_comment":"","space":"60,2","costs_comment":"","costs_rent":"","space_comment":"","region":"","location_raw":"м. Дніпропетровськ"}],"31":[{"costs_property_comment":"","address":"","space_units":"","costs_rent_comment":"","space":"148,9","space_comment":"","costs_property":"","region":"","location_raw":"м. Дніпропетровськ","costs_rent":""}],"34":[{"costs_property_comment":"","address":"","space_units":"","costs_rent_comment":"","space":"87,8","space_comment":"","costs_property":"","region":"","location_raw":"офісне приміщення, м. Дніпропетровськ","costs_rent":""},{"costs_property_comment":"","address":"","space_units":"","costs_rent_comment":"","space":"21,9","space_comment":"","costs_property":"","region":"","location_raw":"паркувальне місце, м. Дніпропетровськ","costs_rent":""}]},"vehicle":{"35":[{"sum_comment":"","brand_info":"","sum":"","sum_rent_comment":"","year":"2009","brand":"Volkswagen,Golf","sum_rent":"","brand_hidden":false}],"40":[{"sum_comment":"","brand_info":"","sum":"","sum_rent_comment":"","year":"2012","brand":"Volkswagen,Touareg","sum_rent":"","brand_hidden":false}]},"id":"2862","income":{"5":{"family_comment":"","value":"142489","family":"362404","comment":""},"6":{"family_comment":"","value":"72182","family":"77929","comment":""},"7":{"family":"116","family_comment":"","value":"0","comment":"","source_name":"0"},"8":{"family_comment":"","value":"0","family":"0","comment":""},"9":{"family_comment":"","value":"0","family":"0","comment":""},"10":{"family_comment":"","value":"0","family":"0","comment":""},"11":{"family_comment":"","value":"0","family":"0","comment":""},"12":{"family_comment":"","value":"0","family":"0","comment":""},"13":{"family_comment":"","value":"0","family":"0","comment":""},"14":{"family_comment":"","value":"0","family":"0","comment":""},"15":{"family_comment":"","value":"0","family":"0","comment":""},"16":{"family_comment":"","value":"0","family":"82000","comment":""},"17":{"family_comment":"","value":"0","family":"172520","comment":""},"18":{"family_comment":"","value":"0","family":"0","comment":""},"19":{"family_comment":"","value":"0","family":"0","comment":""},"20":{"family_comment":"","value":"70307","family":"29839","comment":""},"21":[{"country_comment":"","uah_equal":"0","country":"0","cur":"0"},{"country_comment":"","uah_equal":"0","country":"0","cur":"0"},{"country_comment":"","uah_equal":"0","country":"0","cur":"0"},{"country_comment":"","uah_equal":"0","country":"0","cur":"0"},{"country_comment":"","uah_equal":"0","country":"0","cur":"0"}],"22":[{"country_comment":"","uah_equal":"0","country":"0","cur":"0"},{"country_comment":"","uah_equal":"0","country":"0","cur":"0"},{"country_comment":"","uah_equal":"0","country":"0","cur":"0"},{"country_comment":"","uah_equal":"0","country":"0","cur":"0"},{"country_comment":"","uah_equal":"0","country":"0","cur":"0"}]},"banks":{"45":[{"sum_units":"UAH","sum_comment":"","sum_foreign_units":"","sum":"","sum_foreign_comment":"","sum_foreign":""},{"sum_units":"USD","sum_comment":"","sum_foreign_units":"","sum":"","sum_foreign_comment":"","sum_foreign":""},{"sum_units":"EUR","sum_comment":"","sum_foreign_units":"","sum":"","sum_foreign_comment":"","sum_foreign":""}],"46":[{"sum_units":"UAH","sum_comment":"","sum_foreign_units":"","sum":"","sum_foreign_comment":"","sum_foreign":""},{"sum_units":"USD","sum_comment":"","sum_foreign_units":"","sum":"","sum_foreign_comment":"","sum_foreign":""},{"sum_units":"EUR","sum_comment":"","sum_foreign_units":"","sum":"","sum_foreign_comment":"","sum_foreign":""}],"47":[{"sum_units":"","sum_comment":"","sum_foreign_units":"","sum":"","sum_foreign_comment":"","sum_foreign":""}],"48":[{"sum_units":"","sum_comment":"","sum_foreign_units":"","sum":"","sum_foreign_comment":"","sum_foreign":""}],"49":[{"sum_units":"","sum_comment":"","sum_foreign_units":"","sum":"","sum_foreign_comment":"","sum_foreign":""}],"50":[{"sum_units":"","sum_comment":"","sum_foreign_units":"","sum":"","sum_foreign_comment":"","sum_foreign":""}],"51":[{"sum_units":"UAH","sum_comment":"","sum_foreign_units":"","sum":"","sum_foreign_comment":"","sum_foreign":""},{"sum_units":"USD","sum_comment":"","sum_foreign_units":"","sum":"","sum_foreign_comment":"","sum_foreign":""},{"sum_units":"EUR","sum_comment":"","sum_foreign_units":"","sum":"","sum_foreign_comment":"","sum_foreign":""}],"52":[{"sum_units":"","sum_comment":"","sum_foreign_units":"","sum":"","sum_foreign_comment":"","sum_foreign":""}],"53":[{"sum_units":"","sum_comment":"","sum_foreign_units":"","sum":"27220","sum_foreign_comment":"","sum_foreign":""}]},"declaration":{"notfull_lostpages":"","additional_info_text":"","additional_info":"FALSE","notfull":"FALSE","url":"http://static.declarations.com.ua/declarations/sudy/mistsevi_sudy/okruzhni_administratyvni_sudy/dnipropetrovska/zhukova.pdf","needs_scancopy_check":false},"general":{"family_raw":"Чоловік Жуков С.В.;син Жуков  С.С.;донька Жукова Д.С.;мати Іванова Л.С.","name":"Євгенія","full_name_suggest":{"input":["Жукова Євгенія Олексіївна","Євгенія Олексіївна Жукова","Євгенія Жукова"],"output":"Жукова Євгенія Олексіївна"},"post_raw":"Суддя Дніпропетровського окружного адміністративного суду","name_unclear":false,"patronymic":"Олексіївна","patronymic_unclear":false,"last_name_hidden":false,"patronymic_hidden":false,"inn":"","addresses_raw_hidden":true,"last_name":"Жукова","full_name":"Жукова Євгенія Олексіївна","post":{"office":"Адміністративний місцевий суд","region":"Дніпропетровська область","post":"Суддя"},"addresses":[{"place_district":"","place_city_type":"","place_address_type":"","place":"Дніпропетровська","place_address":"","place_city":"Дніпропетровськ"}],"name_hidden":false,"last_name_unclear":false,"addresses_raw":"приховано;м Дніпропетровськ, 49000"},"liabilities":{"54":{"sum_comment":"","sum_foreign_comment":"","sum_foreign":"","sum":""},"55":{"sum_units":"","sum_comment":"","sum_foreign_units":"","sum":"","sum_foreign_comment":"","sum_foreign":""},"56":{"sum_comment":"","sum_foreign_comment":"","sum_foreign":"","sum":""},"57":{"sum_comment":"","sum_foreign_comment":"","sum_foreign":"","sum":""},"58":{"sum_comment":"","sum_foreign_comment":"","sum_foreign":"","sum":""},"59":{"sum_comment":"","sum_foreign_comment":"","sum_foreign":"","sum":""},"60":{"sum_comment":"","sum_foreign_comment":"","sum_foreign":"","sum":""},"61":{"sum_units":"","sum_comment":"","sum_foreign_units":"","sum":"","sum_foreign_comment":"","sum_foreign":""},"62":{"sum_comment":"","sum_foreign_comment":"","sum_foreign":"","sum":""},"63":{"sum_comment":"","sum_units":"","sum_foreign":"","sum":"","sum_foreign_comment":""},"64":{"sum_comment":"","sum_units":"","sum_foreign":"","sum":"","sum_foreign_comment":""}},"intro":{"isnotdeclaration":"FALSE","declaration_year":"2013"}}]