[{"id":"vulyk_95_20","ft_src":"ВАЗ 2115\n1.6 л, КВт-59.5\n2007\nчастка у власності\nХарківська область\nЧугуїв\n20.9\nХарківська область\nХарків\n35\nХарківська область\nчастка у власності\nм. Чугуїв\n20.9\nХарківська область\nХарківська область\nу користуванні\nХарків\n35\n13000\n4811\n2015\nВАЗ 2115\n1.6 л, КВт-59.5\n2007\n2015\nВолодимирівна\nБатьки\nПанаріна Т. Г\nЗоркіна Юлія Володимирівна\nЮлія Володимирівна Зоркіна\nЮлія Зоркіна\nЗоркіна Юлія Володимирівна\nЮлія\nХарків\nХарківська область\nЗоркіна Юлія Володимирівна\nЗоркіна\nАдміністративний місцевий суд\nсуддя харківського окружного адміністративного суду\nХарківська область\n3925\n157452\n48052\n157452\n48052\nчастка у власності\nЧугуїв\nХарківська область\n20.9\nХарків\nХарківська область\n35\n20.9\nчастка у власності\nм. Чугуїв\nХарківська область\n35\nу користуванні\nХарків\nХарківська область\nХарківська область\n4811\n13000\n3925\n157452\n48052\n157452\n48052\nПанаріна Т. Г\nБатьки\nХарківська область\nХарків\nВолодимирівна\nЗоркіна\nХарківська область\nАдміністративний місцевий суд\nсуддя харківського окружного адміністративного суду\nЗоркіна Юлія Володимирівна\nЗоркіна Юлія Володимирівна\nЮлія Володимирівна Зоркіна\nЮлія Зоркіна\nЗоркіна Юлія Володимирівна\nЮлія","estate":{"25":[{"address":"м. Чугуїв","space_units":"м²","space_hidden":false,"space_unclear":false,"region_hidden":false,"costs_rent_comment":"","space_comment":"частка у власності","address_hidden":true,"costs":"","address_unclear":false,"space_comment_unclear":false,"costs_comment":"","space":"20.9","region":"Харківська область","costs_rent":""},{"address":"Харків","space_units":"м²","space_hidden":false,"space_comment":"у користуванні","region_hidden":false,"costs_comment":"","address_hidden":false,"space":"35","address_unclear":false,"costs_rent_comment":"","costs":"","region":"Харківська область","costs_rent":""}],"31":[{"costs_property_comment":"","address":"Чугуїв","space_units":"м²","space_unclear":false,"region_hidden":false,"costs_property":"","space_comment":"частка у власності","address_hidden":true,"space_comment_unclear":false,"costs_rent_comment":"","space":"20.9","region":"Харківська область","costs_rent":""},{"costs_property_comment":"","address":"Харків","space_units":"м²","space_comment":"","region_hidden":false,"costs_property":"","region":"Харківська область","address_hidden":false,"space_comment_unclear":false,"costs_rent_comment":"","space":"35","costs_rent":""}],"32":[{"costs_property_comment":"","address":"","space_units":"м²","space_comment":"","region_hidden":false,"costs_property":"","region":"Харківська область","address_hidden":false,"address_unclear":false,"costs_rent_comment":"","space":"","costs_rent":""}]},"vehicle":{"35":[{"sum_comment":"","brand_info_hidden":false,"brand_info":"1.6 л, КВт-59.5","sum":"","brand_unclear":false,"brand_hidden":false,"brand":"ВАЗ 2115","sum_rent":"","sum_rent_comment":"","year":"2007","brand_info_unclear":false}]},"source":"VULYK","income":{"5":{"family_comment":"","value":"157452","family_unclear":false,"family":"48052","comment":""},"6":{"family_comment":"","family":"","comment":"","value_unclear":false,"family_unclear":false,"value":"157452"},"7":{"source_name_hidden":false,"family_comment":"","comment":"","family":"","source_name_unclear":false,"value":"","source_name":""},"8":{"family_comment":"","value":"","family":"","comment":""},"9":{"family_comment":"","value":"","family_unclear":false,"family":"","comment":""},"10":{"family_comment":"","value":"","family":"","comment":""},"11":{"family_comment":"","value":"","family":"","comment":""},"12":{"family_comment":"","value":"","family":"","comment":""},"13":{"family_comment":"","value":"","family":"","comment":""},"14":{"family_comment":"","value":"","family":"","comment":""},"15":{"family_comment":"","value":"","family":"","comment":""},"16":{"family_comment":"","value":"","family_unclear":false,"family":"","comment":""},"17":{"family_comment":"","value":"","family_unclear":false,"family":"","comment":""},"18":{"family_comment":"","value":"","family":"","comment":""},"19":{"family_comment":"","value":"","family":"","comment":""},"20":{"family_comment":"","comment_unclear":false,"value":"","family":"48052","comment":""}},"banks":{"45":[{"sum_units":"UAH","sum_comment_unclear":false,"sum_foreign_units_hidden":false,"sum_hidden":true,"sum":"4811","sum_foreign":"","sum_foreign_hidden":false,"sum_foreign_comment":"","sum_foreign_units":"UAH","sum_comment_hidden":false,"sum_units_hidden":false,"sum_comment":"","sum_foreign_comment_hidden":false}],"51":[{"sum_units":"UAH","sum_foreign_units_hidden":false,"sum_hidden":true,"sum":"13000","sum_foreign":"","sum_foreign_hidden":false,"sum_comment":"","sum_foreign_units":"UAH","sum_comment_hidden":false,"sum_foreign_comment":"","sum_unclear":false,"sum_foreign_comment_hidden":false}]},"declaration":{"notfull_lostpages":"","additional_info_text":"","additional_info":"","date":"2016-03-23T00:00:00","notfull":"","url":"http://static.declarations.com.ua/declarations/chosen_ones/judges_batch/21_zorkina_iuliia_volodymyrivna.pdf"},"general":{"inn":"","addresses":[{"place_city_type_hidden":false,"place_district_hidden":false,"place_address_unclear":false,"place":"Харківська область","place_city":"Харків","place_city_type":"Місто","place_city_hidden":false,"place_district":"","place_city_unclear":false,"place_address":"","place_address_hidden":true,"place_hidden":false}],"last_name":"Зоркіна","full_name":"Зоркіна Юлія Володимирівна","family":[{"inn":"","inn_unclear":false,"family_name":"Панаріна Т. Г","relations_other":"","relations_hidden":false,"name_unclear":false,"inn_hidden":true,"name_hidden":true,"relations":"Батьки"}],"patronymic":"Володимирівна","inn_hidden":true,"name":"Юлія","post":{"office":"Адміністративний місцевий суд","post":"суддя харківського окружного адміністративного суду","candidate":"","office_unclear":false,"region":"Харківська область","office_hidden":false},"family_raw":"","full_name_suggest":{"input":["Зоркіна Юлія Володимирівна","Юлія Володимирівна Зоркіна","Юлія Зоркіна"],"output":"Зоркіна Юлія Володимирівна"}},"liabilities":{"54":{"sum_comment":"","sum_hidden":true,"sum":"3925","sum_foreign_comment":"","sum_foreign":"","sum_unclear":true,"sum_comment_hidden":false},"55":{"sum_comment":"","sum_foreign_comment":"","sum_foreign":"","sum":""},"56":{"sum_comment":"","sum_foreign_comment":"","sum_foreign":"","sum":""},"57":{"sum_comment":"","sum_hidden":false,"sum":"","sum_foreign_comment":"","sum_foreign":"","sum_unclear":false,"sum_comment_hidden":false},"58":{"sum_comment":"","sum_hidden":false,"sum":"","sum_foreign_comment":"","sum_foreign":"","sum_unclear":false,"sum_comment_hidden":false},"59":{"sum_comment":"","sum_foreign_comment":"","sum_foreign":"","sum":""},"60":{"sum_comment":"","sum_hidden":false,"sum":"","sum_foreign_comment":"","sum_foreign":"","sum_comment_hidden":false},"61":{"sum_comment":"","sum_foreign_comment":"","sum_foreign":"","sum":""},"62":{"sum_comment":"","sum_foreign_comment":"","sum_foreign":"","sum_unclear":false,"sum":""},"63":{"sum_comment":"","sum_foreign_comment":"","sum_foreign":"","sum_unclear":false,"sum":""},"64":{"sum_comment":"","sum_foreign_comment":"","sum_foreign":"","sum":""}},"intro":{"isnotdeclaration":"","declaration_year":"2015"}},{"id":"vulyk_97_82","ft_src":"1.6 куб. дм, ГОСТ 14846 -81 , нетто кВт -59.5\nВАЗ 2115/ВАЗ 11183\n2007\n20.9\nХарківська область\nХарківська область\nм. Харків\n35\nчастка у власності\n20.9\nм. Чугуїв\nХарківська область\nм. Харків\n35\nХарківська область\n13000\n4811\n12081\n2014\n1.6 куб. дм, ГОСТ 14846 -81 , нетто кВт -59.5\nВАЗ 2115/ВАЗ 11183\n2007\n2014\nЗоркіна Юлія Володимирівна\nЮлія Володимирівна Зоркіна\nЮлія Зоркіна\nЗоркіна Юлія Володимирівна\nЮлія\nБатьки\nПанаріна Т. Г\nЗоркіна Юлія Володимирівна\nЗоркіна\nАдміністративний місцевий суд\nХарківська область\nсуддя харківського окружного адміністративного суду\nВолодимирівна\nХарківська область\n61145, прописана: 61166\nХарків\n3689\n206764\n46633\n207242\n46633\n478\n20.9\nХарківська область\n35\nХарківська область\nм. Харків\n20.9\nчастка у власності\nм. Чугуїв\nХарківська область\n35\nХарківська область\nм. Харків\n4811\n12081\n13000\n3689\n206764\n478\n46633\n207242\n46633\nБатьки\nПанаріна Т. Г\nВолодимирівна\nЗоркіна\nЮлія\nЗоркіна Юлія Володимирівна\nЮлія Володимирівна Зоркіна\nЮлія Зоркіна\nЗоркіна Юлія Володимирівна\n61145, прописана: 61166\nХарків\nХарківська область\nХарківська область\nАдміністративний місцевий суд\nсуддя харківського окружного адміністративного суду\nЗоркіна Юлія Володимирівна","estate":{"25":[{"address":"м. Чугуїв","space_units":"м²","space_hidden":false,"space_unclear":false,"region_hidden":false,"costs_rent_comment":"","space_comment":"частка у власності","address_hidden":true,"space_comment_hidden":false,"costs":"","space_comment_unclear":false,"costs_comment":"","space":"20.9","region_unclear":false,"region":"Харківська область","costs_rent":""},{"address":"м. Харків","space_units":"м²","space_unclear":false,"costs_comment":"","space_comment":"","address_hidden":false,"space":"35","space_comment_unclear":false,"costs_rent_comment":"","costs":"","region":"Харківська область","costs_rent":""}],"31":[{"costs_property_comment":"","address":"","space_units":"м²","space_hidden":false,"space_unclear":false,"region_hidden":false,"costs_property":"","space_comment":"","address_hidden":true,"space_comment_hidden":false,"costs_rent_comment":"","space":"20.9","region":"Харківська область","costs_rent":""},{"costs_property_comment":"","address":"м. Харків","space_units":"м²","costs_rent_comment":"","space":"35","region":"Харківська область","costs_property":"","space_comment":"","address_hidden":false,"costs_rent":""}]},"vehicle":{"35":[{"year_hidden":false,"brand_info":"1.6 куб. дм, ГОСТ 14846 -81 , нетто кВт -59.5","brand_unclear":false,"sum_rent_comment":"","brand_hidden":false,"year":"2007","sum_comment":"","brand_info_hidden":false,"sum_rent":"","brand":"ВАЗ 2115/ВАЗ 11183","brand_info_unclear":false,"sum":""}]},"source":"VULYK","income":{"5":{"family_comment":"","value":"207242","family":"46633","comment":""},"6":{"family_comment":"","family":"","comment":"","value_unclear":false,"family_unclear":false,"comment_hidden":false,"value":"206764"},"7":{"family":"","family_comment":"","value":"","comment":"","source_name":""},"8":{"family_comment":"","value":"","family":"","comment":""},"9":{"family_comment":"","value":"478","family_unclear":false,"family":"","comment":""},"10":{"family_comment":"","value":"","family":"","comment":"","value_unclear":false},"11":{"family_comment":"","value":"","family":"","comment":""},"12":{"family_comment":"","value":"","family":"","comment":""},"13":{"family_comment":"","value":"","family":"","comment":""},"14":{"family_comment":"","value":"","family":"","comment":""},"15":{"family_comment":"","value":"","family":"","comment":""},"16":{"family_comment":"","value":"","family":"","comment":""},"17":{"family_comment":"","value":"","family":"","comment":""},"18":{"family_comment":"","value":"","family":"","comment":""},"19":{"family_comment":"","value":"","family":"","comment":""},"20":{"family_comment":"","comment":"","family":"46633","value_unclear":false,"comment_unclear":false,"value":"","family_hidden":false,"family_comment_unclear":false}},"banks":{"45":[{"sum_comment_unclear":false,"sum_units":"UAH","sum_foreign_units":"UAH","sum_hidden":true,"sum":"4811","sum_foreign_comment":"","sum_comment":"","sum_unclear":true,"sum_foreign":"","sum_comment_hidden":true},{"sum_comment_unclear":false,"sum_comment":"","sum":"12081","sum_foreign_comment":"","sum_units_unclear":true,"sum_unclear":true,"sum_foreign":"","sum_units":""}],"51":[{"sum_comment_unclear":false,"sum_units":"UAH","sum_foreign_units":"UAH","sum_hidden":true,"sum":"13000","sum_foreign_comment":"","sum_comment":"","sum_unclear":false,"sum_foreign":"","sum_comment_hidden":true}]},"declaration":{"notfull_lostpages":"","additional_info_text":"","additional_info":"","date":"2015-03-30T00:00:00","notfull":"","url":"http://static.declarations.com.ua/declarations/chosen_ones/judges_batch/3983_zorkina_iuliia_volodymyrivna.pdf"},"general":{"family":[{"inn":"","family_name":"Панаріна Т. Г","relations_other":"","name_unclear":false,"inn_hidden":true,"name_hidden":true,"relations":"Батьки"}],"family_raw":"","name":"Юлія","full_name_suggest":{"input":["Зоркіна Юлія Володимирівна","Юлія Володимирівна Зоркіна","Юлія Зоркіна"],"output":"Зоркіна Юлія Володимирівна"},"patronymic":"Володимирівна","inn_hidden":true,"addresses":[{"place_city_type":"Місто","place_city_type_hidden":false,"place_hidden":false,"place_city_hidden":false,"place_district_hidden":false,"place_district":"","place_city_unclear":false,"place":"Харківська область","place_city":"Харків","place_address_hidden":true,"place_address":"61145, прописана: 61166"}],"last_name_hidden":false,"patronymic_hidden":false,"inn":"","inn_unclear":false,"last_name":"Зоркіна","full_name":"Зоркіна Юлія Володимирівна","post":{"post_hidden":false,"office":"Адміністративний місцевий суд","post":"суддя харківського окружного адміністративного суду","office_unclear":false,"region_unclear":false,"region":"Харківська область"},"name_hidden":false},"liabilities":{"54":{"sum_comment_unclear":false,"sum_comment":"","sum_hidden":true,"sum":"3689","sum_foreign_comment":"","sum_foreign":"","sum_unclear":false,"sum_comment_hidden":true},"55":{"sum_comment":"","sum_foreign_comment":"","sum_foreign":"","sum":""},"56":{"sum_comment":"","sum_foreign_comment":"","sum_foreign":"","sum":""},"57":{"sum_comment_unclear":false,"sum_comment":"","sum_hidden":false,"sum":"","sum_foreign_comment":"","sum_foreign":"","sum_unclear":false,"sum_comment_hidden":false},"58":{"sum_comment_unclear":false,"sum_comment":"","sum_hidden":false,"sum":"","sum_foreign_comment":"","sum_foreign":"","sum_unclear":false,"sum_comment_hidden":false},"59":{"sum_comment":"","sum_foreign_comment":"","sum_foreign":"","sum":""},"60":{"sum_comment_unclear":false,"sum_comment":"","sum_hidden":false,"sum":"","sum_foreign_comment":"","sum_foreign":"","sum_comment_hidden":false},"61":{"sum_comment":"","sum_foreign_comment":"","sum_foreign":"","sum":""},"62":{"sum_comment":"","sum_foreign_comment":"","sum_foreign":"","sum_unclear":false,"sum":""},"63":{"sum_comment":"","sum_foreign_comment":"","sum_foreign":"","sum_hidden":false,"sum":""},"64":{"sum_comment":"","sum_foreign_comment":"","sum_foreign":"","sum":""}},"intro":{"isnotdeclaration":"","declaration_year":"2014"}}]